{
  "type": "Feature",
  "properties": {
    "gn:admin1_code":"2.0",
    "gn:admin2_code":"220.0",
    "gn:admin3_code":"22005.0",
    "gn:asciiname":"Rumoc",
    "gn:country_code":"PE",
    "gn:dem":2727,
    "gn:feature_class":"P",
    "gn:feature_code":"PPL",
    "gn:name":"Rumoc",
    "gn:population":0,
    "gn:timezone":"America/Lima",
    "iso:country":"PE",
    "wof:name":"Rumoc",
    "wof:placetype":"locality"
},
  "geometry": {"coordinates":[-77.96333,-9.36333],"type":"Point"}
}