{
  "type": "Feature",
  "properties": {
    "gn:admin1_code":"15",
    "gn:admin2_code":"1506.0",
    "gn:admin3_code":"150601.0",
    "gn:asciiname":"Fundo Sorpresa",
    "gn:country_code":"PE",
    "gn:dem":154,
    "gn:feature_class":"P",
    "gn:feature_code":"PPL",
    "gn:name":"Fundo Sorpresa",
    "gn:population":0,
    "gn:timezone":"America/Lima",
    "iso:country":"PE",
    "name:spa_x_preferred":[
        "Fundo Sorpresa"
    ],
    "name:spa_x_variant":[
        "Sorpresa"
    ],
    "wof:name":"Fundo Sorpresa",
    "wof:placetype":"locality"
},
  "geometry": {"coordinates":[-77.21935999999999,-11.5091],"type":"Point"}
}