{
  "type": "Feature",
  "properties": {
    "gn:admin1_code":"13",
    "gn:admin2_code":"1310.0",
    "gn:admin3_code":"131006.0",
    "gn:asciiname":"Quiruvilca",
    "gn:country_code":"PE",
    "gn:dem":4071,
    "gn:feature_class":"P",
    "gn:feature_code":"PPL",
    "gn:name":"Quiruvilca",
    "gn:population":0,
    "gn:timezone":"America/Lima",
    "iso:country":"PE",
    "wof:name":"Quiruvilca",
    "wof:placetype":"locality"
},
  "geometry": {"coordinates":[-78.28341999999998,-8.00229],"type":"Point"}
}