{
  "type": "Feature",
  "properties": {
    "gn:admin1_code":"02",
    "gn:admin2_code":"220.0",
    "gn:admin3_code":"22002.0",
    "gn:asciiname":"Cascapara",
    "gn:country_code":"PE",
    "gn:dem":2727,
    "gn:feature_class":"P",
    "gn:feature_code":"PPLA3",
    "gn:name":"Cascapara",
    "gn:population":0,
    "gn:timezone":"America/Lima",
    "iso:country":"PE",
    "name:und_x_variant":[
        "Kascapara",
        "Caskapara",
        "Cascapara"
    ],
    "wof:name":"Cascapara",
    "wof:placetype":"locality"
},
  "geometry": {"coordinates":[-77.71639,-9.22583],"type":"Point"}
}