{
  "type": "Feature",
  "properties": {
    "gn:admin1_code":"13.0",
    "gn:admin2_code":"1308.0",
    "gn:admin3_code":"130801.0",
    "gn:asciiname":"Chaquicocha",
    "gn:country_code":"PE",
    "gn:dem":3415,
    "gn:feature_class":"P",
    "gn:feature_code":"PPL",
    "gn:name":"Chaquicocha",
    "gn:population":0,
    "gn:timezone":"America/Lima",
    "iso:country":"PE",
    "wof:name":"Chaquicocha",
    "wof:placetype":"locality"
},
  "geometry": {"coordinates":[-77.23968000000001,-8.30954],"type":"Point"}
}