{
  "type": "Feature",
  "properties": {
    "gn:admin1_code":"05",
    "gn:admin2_code":"511.0",
    "gn:admin3_code":"51101.0",
    "gn:asciiname":"San Antonio de Pinchi",
    "gn:country_code":"PE",
    "gn:dem":3660,
    "gn:feature_class":"P",
    "gn:feature_code":"PPL",
    "gn:name":"San Antonio de Pinchi",
    "gn:population":0,
    "gn:timezone":"America/Lima",
    "iso:country":"PE",
    "wof:name":"San Antonio de Pinchi",
    "wof:placetype":"locality"
},
  "geometry": {"coordinates":[-73.84898000000003,-13.65831],"type":"Point"}
}