{
  "type": "Feature",
  "properties": {
    "gn:admin1_code":"18",
    "gn:admin2_code":"1801.0",
    "gn:admin3_code":"180101.0",
    "gn:asciiname":"Huaracane Hacienda",
    "gn:country_code":"PE",
    "gn:dem":1427,
    "gn:feature_class":"P",
    "gn:feature_code":"PPL",
    "gn:name":"Huaracane Hacienda",
    "gn:population":0,
    "gn:timezone":"America/Lima",
    "iso:country":"PE",
    "name:und_x_variant":[
        "Huaracane",
        "Huaracane Hacienda"
    ],
    "wof:name":"Huaracane Hacienda",
    "wof:placetype":"locality"
},
  "geometry": {"coordinates":[-70.94308000000002,-17.16694],"type":"Point"}
}