{
  "type": "Feature",
  "properties": {
    "gn:admin1_code":"20",
    "gn:admin2_code":"2003.0",
    "gn:admin3_code":"200304.0",
    "gn:asciiname":"Chirimoyo",
    "gn:country_code":"PE",
    "gn:dem":1370,
    "gn:feature_class":"P",
    "gn:feature_code":"PPL",
    "gn:name":"Chirimoyo",
    "gn:population":0,
    "gn:timezone":"America/Lima",
    "iso:country":"PE",
    "name:und_x_variant":[
        "Chiumoye",
        "Chirimoyo"
    ],
    "wof:name":"Chirimoyo",
    "wof:placetype":"locality"
},
  "geometry": {"coordinates":[-79.50715,-5.9195],"type":"Point"}
}