{
  "type": "Feature",
  "properties": {
    "gn:admin1_code":"5.0",
    "gn:admin2_code":"501.0",
    "gn:admin3_code":"50113.0",
    "gn:asciiname":"Pinaopampa",
    "gn:country_code":"PE",
    "gn:dem":3345,
    "gn:feature_class":"P",
    "gn:feature_code":"PPL",
    "gn:name":"Pinaopampa",
    "gn:population":0,
    "gn:timezone":"America/Lima",
    "iso:country":"PE",
    "wof:name":"Pinaopampa",
    "wof:placetype":"locality"
},
  "geometry": {"coordinates":[-74.10706,-13.22819],"type":"Point"}
}