{
  "type": "Feature",
  "properties": {
    "gn:admin1_code":"04",
    "gn:admin2_code":"401.0",
    "gn:admin3_code":"40119.0",
    "gn:asciiname":"Quimsapuquio",
    "gn:country_code":"PE",
    "gn:dem":4428,
    "gn:feature_class":"P",
    "gn:feature_code":"PPL",
    "gn:name":"Quimsapuquio",
    "gn:population":0,
    "gn:timezone":"America/Lima",
    "iso:country":"PE",
    "wof:name":"Quimsapuquio",
    "wof:placetype":"locality"
},
  "geometry": {"coordinates":[-70.91667,-16.13332999999999],"type":"Point"}
}