{
  "type": "Feature",
  "properties": {
    "gn:admin1_code":"15",
    "gn:admin2_code":"1505.0",
    "gn:admin3_code":"150502.0",
    "gn:asciiname":"Santacruz de Asia",
    "gn:country_code":"PE",
    "gn:dem":8,
    "gn:feature_class":"P",
    "gn:feature_code":"PPL",
    "gn:name":"Santacruz de Asia",
    "gn:population":0,
    "gn:timezone":"America/Lima",
    "iso:country":"PE",
    "wof:name":"Santacruz de Asia",
    "wof:placetype":"locality"
},
  "geometry": {"coordinates":[-76.59988,-12.75958],"type":"Point"}
}