{
  "type": "Feature",
  "properties": {
    "gn:admin1_code":"18",
    "gn:admin2_code":"1802.0",
    "gn:admin3_code":"180203.0",
    "gn:asciiname":"Coalaque",
    "gn:country_code":"PE",
    "gn:dem":2276,
    "gn:feature_class":"P",
    "gn:feature_code":"PPLA3",
    "gn:name":"Coalaque",
    "gn:population":0,
    "gn:timezone":"America/Lima",
    "iso:country":"PE",
    "wof:name":"Coalaque",
    "wof:placetype":"locality"
},
  "geometry": {"coordinates":[-71.02139,-16.65056],"type":"Point"}
}