{
  "type": "Feature",
  "properties": {
    "gn:admin1_code":"8",
    "gn:admin2_code":"808.0",
    "gn:admin3_code":"80803.0",
    "gn:asciiname":"Pumahuasi",
    "gn:country_code":"PE",
    "gn:dem":3945,
    "gn:feature_class":"P",
    "gn:feature_code":"PPL",
    "gn:name":"Pumahuasi",
    "gn:population":0,
    "gn:timezone":"America/Lima",
    "iso:country":"PE",
    "name:ceb_x_preferred":[
        "Pumahuasi"
    ],
    "name:ita_x_preferred":[
        "Pumahuasi"
    ],
    "name:spa_x_preferred":[
        "Pumahuasi"
    ],
    "name:swe_x_preferred":[
        "Pumahuasi"
    ],
    "wof:name":"Pumahuasi",
    "wof:placetype":"locality"
},
  "geometry": {"coordinates":[-71.57719,-14.70996],"type":"Point"}
}