{
  "type": "Feature",
  "properties": {
    "gn:admin1_code":"2.0",
    "gn:admin2_code":"212.0",
    "gn:admin3_code":"21201.0",
    "gn:asciiname":"Culluna",
    "gn:country_code":"PE",
    "gn:dem":2965,
    "gn:feature_class":"P",
    "gn:feature_code":"PPL",
    "gn:name":"Culluna",
    "gn:population":0,
    "gn:timezone":"America/Lima",
    "iso:country":"PE",
    "wof:name":"Culluna",
    "wof:placetype":"locality"
},
  "geometry": {"coordinates":[-77.75055999999999,-9.04694],"type":"Point"}
}