{
  "type": "Feature",
  "properties": {
    "gn:admin1_code":"15",
    "gn:admin2_code":"1506.0",
    "gn:admin3_code":"150608.0",
    "gn:asciiname":"Cequiapata",
    "gn:country_code":"PE",
    "gn:dem":4737,
    "gn:feature_class":"P",
    "gn:feature_code":"PPL",
    "gn:name":"Cequiapata",
    "gn:population":0,
    "gn:timezone":"America/Lima",
    "iso:country":"PE",
    "wof:name":"Cequiapata",
    "wof:placetype":"locality"
},
  "geometry": {"coordinates":[-76.65139000000001,-11.05833],"type":"Point"}
}