{
  "type": "Feature",
  "properties": {
    "gn:admin1_code":"15",
    "gn:admin2_code":"1510.0",
    "gn:admin3_code":"151011.0",
    "gn:asciiname":"Pumacocha",
    "gn:country_code":"PE",
    "gn:dem":4561,
    "gn:feature_class":"P",
    "gn:feature_code":"PPL",
    "gn:name":"Pumacocha",
    "gn:population":0,
    "gn:timezone":"America/Lima",
    "iso:country":"PE",
    "wof:name":"Pumacocha",
    "wof:placetype":"locality"
},
  "geometry": {"coordinates":[-75.81278,-12.61056],"type":"Point"}
}