{
  "type": "Feature",
  "properties": {
    "gn:admin1_code":"19.0",
    "gn:admin2_code":"1901.0",
    "gn:admin3_code":"190104.0",
    "gn:asciiname":"Escalon",
    "gn:country_code":"PE",
    "gn:dem":4336,
    "gn:feature_class":"P",
    "gn:feature_code":"PPL",
    "gn:name":"Escalon",
    "gn:population":0,
    "gn:timezone":"America/Lima",
    "iso:country":"PE",
    "wof:name":"Escalon",
    "wof:placetype":"locality"
},
  "geometry": {"coordinates":[-76.33588,-11.05511],"type":"Point"}
}