{
  "type": "Feature",
  "properties": {
    "gn:admin1_code":"17.0",
    "gn:admin2_code":"1701.0",
    "gn:asciiname":"Puerto Jaem",
    "gn:country_code":"PE",
    "gn:dem":191,
    "gn:feature_class":"P",
    "gn:feature_code":"PPL",
    "gn:name":"Puerto Jaem",
    "gn:population":0,
    "gn:timezone":"America/La_Paz",
    "iso:country":"PE",
    "name:spa_x_preferred":[
        "Puerto Jaem"
    ],
    "wof:name":"Puerto Jaem",
    "wof:placetype":"locality"
},
  "geometry": {"coordinates":[-68.68544,-12.52758],"type":"Point"}
}