{
  "type": "Feature",
  "properties": {
    "gn:admin1_code":"1.0",
    "gn:admin2_code":"104.0",
    "gn:admin3_code":"10402.0",
    "gn:asciiname":"Puesto de Vigilancia Cuatro B",
    "gn:country_code":"PE",
    "gn:dem":1257,
    "gn:feature_class":"P",
    "gn:feature_code":"PPL",
    "gn:name":"Puesto de Vigilancia Cuatro B",
    "gn:population":0,
    "gn:timezone":"America/Lima",
    "iso:country":"PE",
    "name:spa_x_preferred":[
        "Puesto de Vigilancia Cuatro B"
    ],
    "name:spa_x_variant":[
        "P.V. 4 B"
    ],
    "wof:name":"Puesto de Vigilancia Cuatro B",
    "wof:placetype":"locality"
},
  "geometry": {"coordinates":[-78.53585,-4.02222],"type":"Point"}
}