{
  "type": "Feature",
  "properties": {
    "gn:admin1_code":"10",
    "gn:admin2_code":"1001.0",
    "gn:admin3_code":"100105.0",
    "gn:asciiname":"Jurush",
    "gn:country_code":"PE",
    "gn:dem":4142,
    "gn:feature_class":"P",
    "gn:feature_code":"PPL",
    "gn:name":"Jurush",
    "gn:population":0,
    "gn:timezone":"America/Lima",
    "iso:country":"PE",
    "wof:name":"Jurush",
    "wof:placetype":"locality"
},
  "geometry": {"coordinates":[-76.52206,-10.16754],"type":"Point"}
}