{
  "type": "Feature",
  "properties": {
    "gn:admin1_code":"22.0",
    "gn:admin2_code":"2202.0",
    "gn:admin3_code":"220201.0",
    "gn:asciiname":"Dos de Mayo",
    "gn:country_code":"PE",
    "gn:dem":246,
    "gn:feature_class":"P",
    "gn:feature_code":"PPL",
    "gn:name":"Dos de Mayo",
    "gn:population":0,
    "gn:timezone":"America/Lima",
    "iso:country":"PE",
    "name:spa_x_preferred":[
        "Dos de Mayo"
    ],
    "wof:name":"Dos de Mayo",
    "wof:placetype":"locality"
},
  "geometry": {"coordinates":[-76.56088000000003,-7.05314],"type":"Point"}
}