{
  "type": "Feature",
  "properties": {
    "gn:admin1_code":"20",
    "gn:admin2_code":"2005.0",
    "gn:admin3_code":"200504.0",
    "gn:asciiname":"Colan",
    "gn:country_code":"PE",
    "gn:dem":6,
    "gn:feature_class":"P",
    "gn:feature_code":"PPL",
    "gn:name":"Col\u00e1n",
    "gn:population":0,
    "gn:timezone":"America/Lima",
    "iso:country":"PE",
    "wof:name":"Colan",
    "wof:placetype":"locality"
},
  "geometry": {"coordinates":[-81.05864,-5.0061],"type":"Point"}
}