{
  "type": "Feature",
  "properties": {
    "gn:admin1_code":"05",
    "gn:admin2_code":"506.0",
    "gn:admin3_code":"50602.0",
    "gn:asciiname":"Ismayjoto",
    "gn:country_code":"PE",
    "gn:dem":3942,
    "gn:feature_class":"P",
    "gn:feature_code":"PPL",
    "gn:name":"Ismayjoto",
    "gn:population":0,
    "gn:timezone":"America/Lima",
    "iso:country":"PE",
    "wof:name":"Ismayjoto",
    "wof:placetype":"locality"
},
  "geometry": {"coordinates":[-74.42625,-14.18191],"type":"Point"}
}