{
  "type": "Feature",
  "properties": {
    "gn:admin1_code":"05",
    "gn:admin2_code":"505.0",
    "gn:admin3_code":"50501.0",
    "gn:asciiname":"Collpa",
    "gn:country_code":"PE",
    "gn:dem":2957,
    "gn:feature_class":"P",
    "gn:feature_code":"PPL",
    "gn:name":"Collpa",
    "gn:population":0,
    "gn:timezone":"America/Lima",
    "iso:country":"PE",
    "wof:name":"Collpa",
    "wof:placetype":"locality"
},
  "geometry": {"coordinates":[-73.93156,-13.04197],"type":"Point"}
}