{
  "type": "Feature",
  "properties": {
    "gn:admin1_code":"5",
    "gn:admin2_code":"509.0",
    "gn:admin3_code":"50910.0",
    "gn:asciiname":"Sillacha",
    "gn:country_code":"PE",
    "gn:dem":3521,
    "gn:feature_class":"P",
    "gn:feature_code":"PPL",
    "gn:name":"Sillacha",
    "gn:population":0,
    "gn:timezone":"America/Lima",
    "iso:country":"PE",
    "wof:name":"Sillacha",
    "wof:placetype":"locality"
},
  "geometry": {"coordinates":[-73.63916999999999,-14.09167],"type":"Point"}
}