{
  "type": "Feature",
  "properties": {
    "gn:admin1_code":"05",
    "gn:admin2_code":"501.0",
    "gn:admin3_code":"50102.0",
    "gn:asciiname":"Pataramojo",
    "gn:country_code":"PE",
    "gn:dem":3335,
    "gn:feature_class":"P",
    "gn:feature_code":"PPL",
    "gn:name":"Pataramojo",
    "gn:population":0,
    "gn:timezone":"America/Lima",
    "iso:country":"PE",
    "name:und_x_variant":[
        "Pataramocco",
        "Pataramojo"
    ],
    "wof:name":"Pataramojo",
    "wof:placetype":"locality"
},
  "geometry": {"coordinates":[-74.00400999999999,-13.22346],"type":"Point"}
}