{
  "type": "Feature",
  "properties": {
    "gn:admin1_code":"03",
    "gn:admin2_code":"306.0",
    "gn:admin3_code":"30607.0",
    "gn:asciiname":"Pilluto",
    "gn:country_code":"PE",
    "gn:dem":2607,
    "gn:feature_class":"P",
    "gn:feature_code":"PPL",
    "gn:name":"Pilluto",
    "gn:population":0,
    "gn:timezone":"America/Lima",
    "iso:country":"PE",
    "wof:name":"Pilluto",
    "wof:placetype":"locality"
},
  "geometry": {"coordinates":[-73.70259,-13.66743],"type":"Point"}
}