{
  "type": "Feature",
  "properties": {
    "gn:admin1_code":"12.0",
    "gn:admin2_code":"1202.0",
    "gn:admin3_code":"120209.0",
    "gn:asciiname":"Alapampa",
    "gn:country_code":"PE",
    "gn:dem":2373,
    "gn:feature_class":"P",
    "gn:feature_code":"PPL",
    "gn:name":"Alapampa",
    "gn:population":0,
    "gn:timezone":"America/Lima",
    "iso:country":"PE",
    "wof:name":"Alapampa",
    "wof:placetype":"locality"
},
  "geometry": {"coordinates":[-75.09241,-11.59061],"type":"Point"}
}