{
  "type": "Feature",
  "properties": {
    "gn:admin1_code":"4.0",
    "gn:admin2_code":"401.0",
    "gn:admin3_code":"40106.0",
    "gn:asciiname":"Hacienda Cangallo",
    "gn:country_code":"PE",
    "gn:dem":2946,
    "gn:feature_class":"P",
    "gn:feature_code":"PPL",
    "gn:name":"Hacienda Cangallo",
    "gn:population":0,
    "gn:timezone":"America/Lima",
    "iso:country":"PE",
    "name:spa_x_preferred":[
        "Hacienda Cangallo"
    ],
    "wof:name":"Hacienda Cangallo",
    "wof:placetype":"locality"
},
  "geometry": {"coordinates":[-71.41034999999999,-16.39477],"type":"Point"}
}