{
  "type": "Feature",
  "properties": {
    "gn:admin1_code":"2.0",
    "gn:admin2_code":"205.0",
    "gn:admin3_code":"20509.0",
    "gn:asciiname":"Cajon",
    "gn:country_code":"PE",
    "gn:dem":2848,
    "gn:feature_class":"P",
    "gn:feature_code":"PPL",
    "gn:name":"Caj\u00f3n",
    "gn:population":0,
    "gn:timezone":"America/Lima",
    "iso:country":"PE",
    "wof:name":"Cajon",
    "wof:placetype":"locality"
},
  "geometry": {"coordinates":[-77.12025,-10.16747],"type":"Point"}
}