{
  "type": "Feature",
  "properties": {
    "gn:admin1_code":"20",
    "gn:admin2_code":"2005.0",
    "gn:admin3_code":"200507.0",
    "gn:asciiname":"Vista Florida",
    "gn:country_code":"PE",
    "gn:dem":13,
    "gn:feature_class":"P",
    "gn:feature_code":"PPL",
    "gn:name":"Vista Florida",
    "gn:population":0,
    "gn:timezone":"America/Lima",
    "iso:country":"PE",
    "name:und_x_variant":[
        "Vistaflorida Hacienda",
        "Vistaflorida",
        "Vista Florida"
    ],
    "wof:name":"Vista Florida",
    "wof:placetype":"locality"
},
  "geometry": {"coordinates":[-81.04783,-4.85104],"type":"Point"}
}