{
  "type": "Feature",
  "properties": {
    "gn:admin1_code":"8",
    "gn:admin2_code":"802.0",
    "gn:admin3_code":"80204.0",
    "gn:asciiname":"Tactabamba",
    "gn:country_code":"PE",
    "gn:dem":3897,
    "gn:feature_class":"P",
    "gn:feature_code":"PPL",
    "gn:name":"Tactabamba",
    "gn:population":0,
    "gn:timezone":"America/Lima",
    "iso:country":"PE",
    "wof:name":"Tactabamba",
    "wof:placetype":"locality"
},
  "geometry": {"coordinates":[-71.46326999999999,-14.08171],"type":"Point"}
}