{
  "type": "Feature",
  "properties": {
    "gn:admin1_code":"12.0",
    "gn:admin2_code":"1201.0",
    "gn:admin3_code":"120128.0",
    "gn:asciiname":"Siusa",
    "gn:country_code":"PE",
    "gn:dem":4372,
    "gn:feature_class":"P",
    "gn:feature_code":"PPL",
    "gn:name":"Siusa",
    "gn:population":0,
    "gn:timezone":"America/Lima",
    "iso:country":"PE",
    "wof:name":"Siusa",
    "wof:placetype":"locality"
},
  "geometry": {"coordinates":[-75.21661999999998,-11.85679],"type":"Point"}
}