{
  "type": "Feature",
  "properties": {
    "gn:admin1_code":"12.0",
    "gn:admin2_code":"1204.0",
    "gn:admin3_code":"120421.0",
    "gn:asciiname":"Los Andes",
    "gn:country_code":"PE",
    "gn:dem":3925,
    "gn:feature_class":"P",
    "gn:feature_code":"PPL",
    "gn:name":"Los Andes",
    "gn:population":0,
    "gn:timezone":"America/Lima",
    "iso:country":"PE",
    "name:ceb_x_preferred":[
        "Los Andes"
    ],
    "name:deu_x_preferred":[
        "Los Andes"
    ],
    "name:hye_x_preferred":[
        "\u053c\u0578\u057d \u0531\u0576\u0564\u0565\u057d"
    ],
    "name:ita_x_preferred":[
        "Los Andes"
    ],
    "name:nld_x_preferred":[
        "Los Andes"
    ],
    "name:rus_x_preferred":[
        "\u041b\u043e\u0441-\u0410\u043d\u0434\u0435\u0441"
    ],
    "name:sco_x_preferred":[
        "Los Andes"
    ],
    "name:slk_x_preferred":[
        "Los Andes"
    ],
    "name:swe_x_preferred":[
        "Los Andes"
    ],
    "name:war_x_preferred":[
        "Los Andes"
    ],
    "wof:name":"Los Andes",
    "wof:placetype":"locality"
},
  "geometry": {"coordinates":[-75.47145999999999,-11.84681],"type":"Point"}
}