{
  "type": "Feature",
  "properties": {
    "gn:admin1_code":"1.0",
    "gn:admin2_code":"105.0",
    "gn:admin3_code":"10509.0",
    "gn:asciiname":"Oratorio",
    "gn:country_code":"PE",
    "gn:dem":2320,
    "gn:feature_class":"P",
    "gn:feature_code":"PPLL",
    "gn:name":"Oratorio",
    "gn:population":0,
    "gn:timezone":"America/Lima",
    "iso:country":"PE",
    "wof:name":"Oratorio",
    "wof:placetype":"locality"
},
  "geometry": {"coordinates":[-77.93361,-6.16163],"type":"Point"}
}