{
  "type": "Feature",
  "properties": {
    "gn:admin1_code":"20",
    "gn:admin2_code":"2005.0",
    "gn:admin3_code":"200504.0",
    "gn:asciiname":"La Bocana",
    "gn:country_code":"PE",
    "gn:dem":7,
    "gn:feature_class":"P",
    "gn:feature_code":"PPL",
    "gn:name":"La Bocana",
    "gn:population":0,
    "gn:timezone":"America/Lima",
    "iso:country":"PE",
    "wof:name":"La Bocana",
    "wof:placetype":"locality"
},
  "geometry": {"coordinates":[-81.12127,-4.9249],"type":"Point"}
}