{
  "type": "Feature",
  "properties": {
    "gn:admin1_code":"09",
    "gn:admin2_code":"906.0",
    "gn:admin3_code":"90613.0",
    "gn:asciiname":"Huanacuyoc",
    "gn:country_code":"PE",
    "gn:dem":3148,
    "gn:feature_class":"P",
    "gn:feature_code":"PPL",
    "gn:name":"Huanacuyoc",
    "gn:population":0,
    "gn:timezone":"America/Lima",
    "iso:country":"PE",
    "wof:name":"Huanacuyoc",
    "wof:placetype":"locality"
},
  "geometry": {"coordinates":[-75.35420999999999,-13.89826],"type":"Point"}
}