{
  "type": "Feature",
  "properties": {
    "gn:admin1_code":"14",
    "gn:admin2_code":"1401.0",
    "gn:admin3_code":"140109.0",
    "gn:asciiname":"Nueva Arica",
    "gn:country_code":"PE",
    "gn:dem":174,
    "gn:feature_class":"P",
    "gn:feature_code":"PPLA3",
    "gn:name":"Nueva Arica",
    "gn:population":0,
    "gn:timezone":"America/Lima",
    "iso:country":"PE",
    "wof:name":"Nueva Arica",
    "wof:placetype":"locality"
},
  "geometry": {"coordinates":[-79.34278,-6.87278],"type":"Point"}
}