{
  "type": "Feature",
  "properties": {
    "gn:admin1_code":"13",
    "gn:admin2_code":"1301.0",
    "gn:admin3_code":"130110.0",
    "gn:asciiname":"La Capilla",
    "gn:cc2":"PE",
    "gn:country_code":"PE",
    "gn:dem":374,
    "gn:feature_class":"P",
    "gn:feature_code":"PPL",
    "gn:name":"La Capilla",
    "gn:population":0,
    "gn:timezone":"America/Lima",
    "iso:country":"PE",
    "name:und_x_variant":[
        "La Capilla Hacienda",
        "La Capilla"
    ],
    "wof:name":"La Capilla",
    "wof:placetype":"locality"
},
  "geometry": {"coordinates":[-78.81667,-8.01667],"type":"Point"}
}