{
  "type": "Feature",
  "properties": {
    "gn:admin1_code":"23",
    "gn:admin2_code":"2304.0",
    "gn:admin3_code":"230402.0",
    "gn:asciiname":"Putina",
    "gn:country_code":"PE",
    "gn:dem":1932,
    "gn:feature_class":"P",
    "gn:feature_code":"PPL",
    "gn:name":"Putina",
    "gn:population":0,
    "gn:timezone":"America/Lima",
    "iso:country":"PE",
    "name:ceb_x_preferred":[
        "Putina"
    ],
    "name:por_x_preferred":[
        "Putina"
    ],
    "name:rus_x_preferred":[
        "\u041f\u0443\u0442\u0438\u043d\u0430"
    ],
    "name:ukr_x_preferred":[
        "\u041f\u0443\u0442\u0438\u043d\u0430"
    ],
    "name:und_x_variant":[
        "Putina Hacienda",
        "Putina"
    ],
    "wof:name":"Putina",
    "wof:placetype":"locality"
},
  "geometry": {"coordinates":[-70.22756,-17.49501],"type":"Point"}
}