{
  "type": "Feature",
  "properties": {
    "gn:admin1_code":"2.0",
    "gn:admin2_code":"214.0",
    "gn:admin3_code":"21402.0",
    "gn:asciiname":"Huayllampo",
    "gn:country_code":"PE",
    "gn:dem":3188,
    "gn:feature_class":"P",
    "gn:feature_code":"PPL",
    "gn:name":"Huayllampo",
    "gn:population":0,
    "gn:timezone":"America/Lima",
    "iso:country":"PE",
    "wof:name":"Huayllampo",
    "wof:placetype":"locality"
},
  "geometry": {"coordinates":[-77.33629999999999,-10.45053],"type":"Point"}
}