{
  "type": "Feature",
  "properties": {
    "gn:admin1_code":"23",
    "gn:admin2_code":"2304.0",
    "gn:admin3_code":"230408.0",
    "gn:asciiname":"Incamoco",
    "gn:country_code":"PE",
    "gn:dem":4343,
    "gn:feature_class":"P",
    "gn:feature_code":"PPL",
    "gn:name":"Incamoco",
    "gn:population":0,
    "gn:timezone":"America/Lima",
    "iso:country":"PE",
    "wof:name":"Incamoco",
    "wof:placetype":"locality"
},
  "geometry": {"coordinates":[-69.83591,-17.25465],"type":"Point"}
}