{
  "type": "Feature",
  "properties": {
    "gn:admin1_code":"12",
    "gn:admin2_code":"1203.0",
    "gn:admin3_code":"120303.0",
    "gn:asciiname":"Amauta",
    "gn:country_code":"PE",
    "gn:dem":667,
    "gn:feature_class":"P",
    "gn:feature_code":"PPLL",
    "gn:name":"Amauta",
    "gn:population":0,
    "gn:timezone":"America/Lima",
    "iso:country":"PE",
    "name:fra_x_preferred":[
        "Amauta"
    ],
    "name:glg_x_preferred":[
        "Amauta"
    ],
    "name:spa_x_preferred":[
        "Amauta"
    ],
    "wof:name":"Amauta",
    "wof:placetype":"locality"
},
  "geometry": {"coordinates":[-74.78494000000001,-10.99174],"type":"Point"}
}