{
  "type": "Feature",
  "properties": {
    "gn:admin1_code":"05",
    "gn:admin2_code":"511.0",
    "gn:admin3_code":"51104.0",
    "gn:asciiname":"Pichirca",
    "gn:country_code":"PE",
    "gn:dem":2964,
    "gn:feature_class":"P",
    "gn:feature_code":"PPL",
    "gn:name":"Pichirca",
    "gn:population":0,
    "gn:timezone":"America/Lima",
    "iso:country":"PE",
    "wof:name":"Pichirca",
    "wof:placetype":"locality"
},
  "geometry": {"coordinates":[-73.82974,-13.59089],"type":"Point"}
}