{
  "type": "Feature",
  "properties": {
    "gn:admin1_code":"17.0",
    "gn:admin2_code":"1701.0",
    "gn:asciiname":"Florida",
    "gn:country_code":"PE",
    "gn:dem":238,
    "gn:feature_class":"P",
    "gn:feature_code":"PPL",
    "gn:name":"Florida",
    "gn:population":0,
    "gn:timezone":"America/Lima",
    "iso:country":"PE",
    "name:spa_x_preferred":[
        "Florida"
    ],
    "wof:name":"Florida",
    "wof:placetype":"locality"
},
  "geometry": {"coordinates":[-69.27686,-12.23442],"type":"Point"}
}