{
  "type": "Feature",
  "properties": {
    "gn:admin1_code":"8.0",
    "gn:admin2_code":"803.0",
    "gn:admin3_code":"80301.0",
    "gn:asciiname":"Yupana",
    "gn:country_code":"PE",
    "gn:dem":3763,
    "gn:feature_class":"P",
    "gn:feature_code":"PPL",
    "gn:name":"Yupana",
    "gn:population":0,
    "gn:timezone":"America/Lima",
    "iso:country":"PE",
    "wof:name":"Yupana",
    "wof:placetype":"locality"
},
  "geometry": {"coordinates":[-72.16,-13.51639],"type":"Point"}
}