{
  "type": "Feature",
  "properties": {
    "gn:admin1_code":"20",
    "gn:admin2_code":"2003.0",
    "gn:admin3_code":"200302.0",
    "gn:asciiname":"Coyona",
    "gn:country_code":"PE",
    "gn:dem":1153,
    "gn:feature_class":"P",
    "gn:feature_code":"PPL",
    "gn:name":"Coyona",
    "gn:population":0,
    "gn:timezone":"America/Lima",
    "iso:country":"PE",
    "wof:name":"Coyona",
    "wof:placetype":"locality"
},
  "geometry": {"coordinates":[-79.62009999999999,-5.30997],"type":"Point"}
}