{
  "type": "Feature",
  "properties": {
    "gn:admin1_code":"16",
    "gn:admin2_code":"1601.0",
    "gn:admin3_code":"160101.0",
    "gn:asciiname":"Tarapoto",
    "gn:country_code":"PE",
    "gn:dem":94,
    "gn:feature_class":"P",
    "gn:feature_code":"PPL",
    "gn:name":"Tarapoto",
    "gn:population":0,
    "gn:timezone":"America/Lima",
    "iso:country":"PE",
    "name:ara_x_preferred":[
        "\u062a\u0627\u0631\u0627\u0628\u0648\u062a\u0648"
    ],
    "name:bul_x_preferred":[
        "\u0422\u0430\u0440\u0430\u043f\u043e\u0442\u043e"
    ],
    "name:cat_x_preferred":[
        "Tarapoto"
    ],
    "name:ceb_x_preferred":[
        "Tarapoto"
    ],
    "name:deu_x_preferred":[
        "Tarapoto"
    ],
    "name:epo_x_preferred":[
        "Tarapoto"
    ],
    "name:fas_x_preferred":[
        "\u062a\u0627\u0631\u0627\u067e\u0648\u062a\u0648"
    ],
    "name:fin_x_preferred":[
        "Tarapoto"
    ],
    "name:fra_x_preferred":[
        "Tarapoto"
    ],
    "name:ita_x_preferred":[
        "Tarapoto"
    ],
    "name:kat_x_preferred":[
        "\u10e2\u10d0\u10e0\u10d0\u10de\u10dd\u10e2\u10dd"
    ],
    "name:lit_x_preferred":[
        "Tarapotas"
    ],
    "name:nld_x_preferred":[
        "Tarapoto"
    ],
    "name:pol_x_preferred":[
        "Tarapoto"
    ],
    "name:por_x_preferred":[
        "Tarapoto"
    ],
    "name:que_x_preferred":[
        "Taraputu"
    ],
    "name:rus_x_preferred":[
        "\u0422\u0430\u0440\u0430\u043f\u043e\u0442\u043e"
    ],
    "name:spa_x_preferred":[
        "Tarapoto"
    ],
    "name:swe_x_preferred":[
        "Tarapoto"
    ],
    "name:tat_x_preferred":[
        "\u0422\u0430\u0440\u0430\u043f\u043e\u0442\u043e"
    ],
    "name:urd_x_preferred":[
        "\u062a\u0627\u0631\u0627\u067e\u0648\u062a\u0648"
    ],
    "name:vol_x_preferred":[
        "Tarapoto"
    ],
    "name:war_x_preferred":[
        "Tarapoto"
    ],
    "name:zho_x_preferred":[
        "\u5854\u62c9\u6ce2\u6258"
    ],
    "wof:name":"Tarapoto",
    "wof:placetype":"locality"
},
  "geometry": {"coordinates":[-73.40494,-3.80459],"type":"Point"}
}