{
  "type": "Feature",
  "properties": {
    "gn:admin1_code":"21",
    "gn:admin2_code":"2111.0",
    "gn:admin3_code":"211101.0",
    "gn:asciiname":"Corecache",
    "gn:country_code":"PE",
    "gn:dem":3838,
    "gn:feature_class":"P",
    "gn:feature_code":"PPL",
    "gn:name":"Corecache",
    "gn:population":0,
    "gn:timezone":"America/Lima",
    "iso:country":"PE",
    "wof:name":"Corecache",
    "wof:placetype":"locality"
},
  "geometry": {"coordinates":[-70.04626,-15.44227],"type":"Point"}
}