{
  "type": "Feature",
  "properties": {
    "gn:admin1_code":"08",
    "gn:admin2_code":"809.0",
    "gn:admin3_code":"80902.0",
    "gn:asciiname":"La Mision",
    "gn:country_code":"PE",
    "gn:dem":1621,
    "gn:feature_class":"P",
    "gn:feature_code":"PPL",
    "gn:name":"La Misi\u00f3n",
    "gn:population":0,
    "gn:timezone":"America/Lima",
    "iso:country":"PE",
    "wof:name":"La Mision",
    "wof:placetype":"locality"
},
  "geometry": {"coordinates":[-72.75,-12.46667],"type":"Point"}
}