{
  "type": "Feature",
  "properties": {
    "gn:admin1_code":"02",
    "gn:admin2_code":"208.0",
    "gn:admin3_code":"20801.0",
    "gn:asciiname":"Hacienda San Rafael",
    "gn:country_code":"PE",
    "gn:dem":118,
    "gn:feature_class":"P",
    "gn:feature_code":"PPL",
    "gn:name":"Hacienda San Rafael",
    "gn:population":0,
    "gn:timezone":"America/Lima",
    "iso:country":"PE",
    "name:und_x_variant":[
        "San Rafael"
    ],
    "wof:name":"Hacienda San Rafael",
    "wof:placetype":"locality"
},
  "geometry": {"coordinates":[-78.22963,-9.53625],"type":"Point"}
}