{
  "type": "Feature",
  "properties": {
    "gn:admin1_code":"15",
    "gn:admin2_code":"1501.0",
    "gn:admin3_code":"150106.0",
    "gn:asciiname":"Canon",
    "gn:country_code":"PE",
    "gn:dem":264,
    "gn:feature_class":"P",
    "gn:feature_code":"PPL",
    "gn:name":"Ca\u00f1\u00f3n",
    "gn:population":0,
    "gn:timezone":"America/Lima",
    "iso:country":"PE",
    "name:ara_x_preferred":[
        "\u0634\u0631\u064a\u0639\u0629"
    ],
    "name:bul_x_preferred":[
        "\u041a\u0430\u043d\u043e\u043d"
    ],
    "name:cat_x_preferred":[
        "C\u00e0non"
    ],
    "name:ceb_x_preferred":[
        "Canon"
    ],
    "name:cym_x_preferred":[
        "Canon"
    ],
    "name:deu_x_preferred":[
        "Canon"
    ],
    "name:epo_x_preferred":[
        "Kanono"
    ],
    "name:fas_x_preferred":[
        "\u06a9\u0627\u0646\u0646"
    ],
    "name:fra_x_preferred":[
        "Canon"
    ],
    "name:glg_x_preferred":[
        "Canon"
    ],
    "name:heb_x_preferred":[
        "\u05e7\u05d0\u05e0\u05d5\u05df"
    ],
    "name:jpn_x_preferred":[
        "\u30ab\u30ce\u30f3"
    ],
    "name:kir_x_preferred":[
        "\u041a\u0430\u043d\u043e\u043d"
    ],
    "name:lat_x_preferred":[
        "Canon"
    ],
    "name:lav_x_preferred":[
        "Kanons"
    ],
    "name:lim_x_preferred":[
        "Canon"
    ],
    "name:nld_x_preferred":[
        "Canon"
    ],
    "name:pol_x_preferred":[
        "Kanon"
    ],
    "name:por_x_preferred":[
        "Canon"
    ],
    "name:rus_x_preferred":[
        "\u041a\u0430\u043d\u043e\u043d"
    ],
    "name:scn_x_preferred":[
        "C\u00e0nuni"
    ],
    "name:slk_x_preferred":[
        "Canon"
    ],
    "name:spa_x_preferred":[
        "Canon"
    ],
    "name:srp_x_preferred":[
        "\u041a\u0430\u043d\u043e\u043d"
    ],
    "name:swe_x_preferred":[
        "Canon"
    ],
    "name:tam_x_preferred":[
        "\u0b95\u0bc6\u0ba9\u0bbe\u0ba9\u0bcd"
    ],
    "name:tha_x_preferred":[
        "\u0e41\u0e04\u0e19\u0e2d\u0e19"
    ],
    "name:ukr_x_preferred":[
        "\u041a\u0430\u043d\u043e\u043d"
    ],
    "name:wln_x_preferred":[
        "Canon"
    ],
    "name:zho_x_preferred":[
        "Canon"
    ],
    "wof:name":"Canon",
    "wof:placetype":"locality"
},
  "geometry": {"coordinates":[-77.02333,-11.84694],"type":"Point"}
}