{
  "type": "Feature",
  "properties": {
    "gn:admin1_code":"15",
    "gn:admin2_code":"1501.0",
    "gn:admin3_code":"150106.0",
    "gn:asciiname":"Canon",
    "gn:country_code":"PE",
    "gn:dem":264,
    "gn:feature_class":"P",
    "gn:feature_code":"PPL",
    "gn:name":"Ca\u00f1\u00f3n",
    "gn:population":0,
    "gn:timezone":"America/Lima",
    "iso:country":"PE",
    "wof:name":"Canon",
    "wof:placetype":"locality"
},
  "geometry": {"coordinates":[-77.02333,-11.84694],"type":"Point"}
}