{
  "type": "Feature",
  "properties": {
    "gn:admin1_code":"04",
    "gn:admin2_code":"401.0",
    "gn:admin3_code":"40119.0",
    "gn:asciiname":"Yuraccasa",
    "gn:country_code":"PE",
    "gn:dem":4140,
    "gn:feature_class":"P",
    "gn:feature_code":"PPL",
    "gn:name":"Yuraccasa",
    "gn:population":0,
    "gn:timezone":"America/Lima",
    "iso:country":"PE",
    "wof:name":"Yuraccasa",
    "wof:placetype":"locality"
},
  "geometry": {"coordinates":[-71.05594000000001,-16.11758],"type":"Point"}
}