{
  "type": "Feature",
  "properties": {
    "gn:admin1_code":"5.0",
    "gn:admin2_code":"507.0",
    "gn:admin3_code":"50701.0",
    "gn:asciiname":"Quichcaloma",
    "gn:country_code":"PE",
    "gn:dem":3292,
    "gn:feature_class":"P",
    "gn:feature_code":"PPL",
    "gn:name":"Quichcaloma",
    "gn:population":0,
    "gn:timezone":"America/Lima",
    "iso:country":"PE",
    "name:spa_x_preferred":[
        "Quichcaloma"
    ],
    "wof:name":"Quichcaloma",
    "wof:placetype":"locality"
},
  "geometry": {"coordinates":[-73.76734999999999,-15.0455],"type":"Point"}
}