{
  "type": "Feature",
  "properties": {
    "gn:admin1_code":"5.0",
    "gn:admin2_code":"505.0",
    "gn:admin3_code":"50504.0",
    "gn:asciiname":"Cachitarina",
    "gn:country_code":"PE",
    "gn:dem":2791,
    "gn:feature_class":"P",
    "gn:feature_code":"PPL",
    "gn:name":"Cachitarina",
    "gn:population":0,
    "gn:timezone":"America/Lima",
    "iso:country":"PE",
    "wof:name":"Cachitarina",
    "wof:placetype":"locality"
},
  "geometry": {"coordinates":[-73.82643,-13.20124],"type":"Point"}
}