{
  "type": "Feature",
  "properties": {
    "gn:admin1_code":"3",
    "gn:admin2_code":"306.0",
    "gn:admin3_code":"30605.0",
    "gn:asciiname":"Atajara",
    "gn:country_code":"PE",
    "gn:dem":3439,
    "gn:feature_class":"P",
    "gn:feature_code":"PPL",
    "gn:name":"Atajara",
    "gn:population":0,
    "gn:timezone":"America/Lima",
    "iso:country":"PE",
    "wof:name":"Atajara",
    "wof:placetype":"locality"
},
  "geometry": {"coordinates":[-73.49966999999999,-13.57],"type":"Point"}
}