{
  "type": "Feature",
  "properties": {
    "gn:admin1_code":"5",
    "gn:admin2_code":"506.0",
    "gn:admin3_code":"50612.0",
    "gn:asciiname":"Apacheta",
    "gn:country_code":"PE",
    "gn:dem":3103,
    "gn:feature_class":"P",
    "gn:feature_code":"PPL",
    "gn:name":"Apacheta",
    "gn:population":0,
    "gn:timezone":"America/Lima",
    "iso:country":"PE",
    "wof:name":"Apacheta",
    "wof:placetype":"locality"
},
  "geometry": {"coordinates":[-74.76666999999998,-14.38333],"type":"Point"}
}