{
  "type": "Feature",
  "properties": {
    "gn:admin1_code":"9.0",
    "gn:admin2_code":"903.0",
    "gn:admin3_code":"90301.0",
    "gn:asciiname":"Jenhuapata",
    "gn:country_code":"PE",
    "gn:dem":4454,
    "gn:feature_class":"P",
    "gn:feature_code":"PPL",
    "gn:name":"Jenhuapata",
    "gn:population":0,
    "gn:timezone":"America/Lima",
    "iso:country":"PE",
    "wof:name":"Jenhuapata",
    "wof:placetype":"locality"
},
  "geometry": {"coordinates":[-74.69438000000002,-13.20889],"type":"Point"}
}