{
  "type": "Feature",
  "properties": {
    "gn:admin1_code":"21.0",
    "gn:admin2_code":"2112.0",
    "gn:asciiname":"Amoyo",
    "gn:country_code":"PE",
    "gn:dem":2570,
    "gn:feature_class":"P",
    "gn:feature_code":"PPL",
    "gn:name":"Amoyo",
    "gn:population":0,
    "gn:timezone":"America/Lima",
    "iso:country":"PE",
    "name:spa_x_preferred":[
        "Amoyo"
    ],
    "wof:name":"Amoyo",
    "wof:placetype":"locality"
},
  "geometry": {"coordinates":[-69.44232,-14.31737],"type":"Point"}
}