{
  "type": "Feature",
  "properties": {
    "gn:admin1_code":"12",
    "gn:admin2_code":"1208.0",
    "gn:admin3_code":"120806.0",
    "gn:asciiname":"Callpapampa",
    "gn:country_code":"PE",
    "gn:dem":3876,
    "gn:feature_class":"P",
    "gn:feature_code":"PPL",
    "gn:name":"Callpapampa",
    "gn:population":0,
    "gn:timezone":"America/Lima",
    "iso:country":"PE",
    "wof:name":"Callpapampa",
    "wof:placetype":"locality"
},
  "geometry": {"coordinates":[-75.97069999999999,-11.46545],"type":"Point"}
}