{
  "type": "Feature",
  "properties": {
    "gn:admin1_code":"8.0",
    "gn:admin2_code":"813.0",
    "gn:admin3_code":"81302.0",
    "gn:asciiname":"Huajtanamojo",
    "gn:country_code":"PE",
    "gn:dem":3735,
    "gn:feature_class":"P",
    "gn:feature_code":"PPL",
    "gn:name":"Huajtanamojo",
    "gn:population":0,
    "gn:timezone":"America/Lima",
    "iso:country":"PE",
    "wof:name":"Huajtanamojo",
    "wof:placetype":"locality"
},
  "geometry": {"coordinates":[-72.07306,-13.41944],"type":"Point"}
}