{
  "type": "Feature",
  "properties": {
    "gn:admin1_code":"22",
    "gn:admin2_code":"2202.0",
    "gn:admin3_code":"220201.0",
    "gn:asciiname":"Vainillas",
    "gn:country_code":"PE",
    "gn:dem":242,
    "gn:feature_class":"P",
    "gn:feature_code":"PPL",
    "gn:name":"Vainillas",
    "gn:population":0,
    "gn:timezone":"America/Lima",
    "iso:country":"PE",
    "name:spa_x_preferred":[
        "Vainillas"
    ],
    "name:und_x_variant":[
        "Vainilla",
        "Vainilla Trapiche"
    ],
    "wof:name":"Vainillas",
    "wof:placetype":"locality"
},
  "geometry": {"coordinates":[-76.55065,-7.07681],"type":"Point"}
}