{
  "type": "Feature",
  "properties": {
    "gn:admin1_code":"21",
    "gn:admin2_code":"2102.0",
    "gn:admin3_code":"210208.0",
    "gn:asciiname":"Condorire",
    "gn:cc2":"PE",
    "gn:country_code":"PE",
    "gn:dem":4075,
    "gn:feature_class":"P",
    "gn:feature_code":"PPL",
    "gn:name":"Condorire",
    "gn:population":0,
    "gn:timezone":"America/Lima",
    "iso:country":"PE",
    "name:und_x_variant":[
        "Condorire Hacienda",
        "Condoriri",
        "Condorire"
    ],
    "wof:name":"Condorire",
    "wof:placetype":"locality"
},
  "geometry": {"coordinates":[-70.03333000000001,-14.81667],"type":"Point"}
}