{
  "type": "Feature",
  "properties": {
    "gn:admin1_code":"06",
    "gn:admin2_code":"602.0",
    "gn:admin3_code":"60202.0",
    "gn:asciiname":"Portachuelo",
    "gn:country_code":"PE",
    "gn:dem":3514,
    "gn:feature_class":"P",
    "gn:feature_code":"PPL",
    "gn:name":"Portachuelo",
    "gn:population":0,
    "gn:timezone":"America/Lima",
    "iso:country":"PE",
    "name:ceb_x_preferred":[
        "Portachuelo"
    ],
    "name:deu_x_preferred":[
        "Portachuelo"
    ],
    "name:fra_x_preferred":[
        "Portachuelo"
    ],
    "name:ita_x_preferred":[
        "Portachuelo"
    ],
    "name:pol_x_preferred":[
        "Portachuelo"
    ],
    "name:que_x_preferred":[
        "Portachuelo"
    ],
    "name:spa_x_preferred":[
        "Portachuelo"
    ],
    "name:swe_x_preferred":[
        "Portachuelo"
    ],
    "name:war_x_preferred":[
        "Portachuelo"
    ],
    "name:zho_x_preferred":[
        "\u6ce2\u723e\u4e18\u57c3\u6d1b"
    ],
    "wof:name":"Portachuelo",
    "wof:placetype":"locality"
},
  "geometry": {"coordinates":[-78.31614999999999,-7.63578],"type":"Point"}
}