{
  "type": "Feature",
  "properties": {
    "gn:admin1_code":"05",
    "gn:admin2_code":"506.0",
    "gn:admin3_code":"50609.0",
    "gn:asciiname":"El Milagro",
    "gn:country_code":"PE",
    "gn:dem":1650,
    "gn:feature_class":"P",
    "gn:feature_code":"PPL",
    "gn:name":"El Milagro",
    "gn:population":0,
    "gn:timezone":"America/Lima",
    "iso:country":"PE",
    "name:spa_x_preferred":[
        "El Milagro"
    ],
    "wof:name":"El Milagro",
    "wof:placetype":"locality"
},
  "geometry": {"coordinates":[-74.84375,-14.67879],"type":"Point"}
}