{
  "type": "Feature",
  "properties": {
    "gn:admin1_code":"04",
    "gn:admin2_code":"401.0",
    "gn:admin3_code":"40125.0",
    "gn:asciiname":"La Travada",
    "gn:country_code":"PE",
    "gn:dem":1066,
    "gn:feature_class":"P",
    "gn:feature_code":"PPL",
    "gn:name":"La Travada",
    "gn:population":0,
    "gn:timezone":"America/Lima",
    "iso:country":"PE",
    "wof:name":"La Travada",
    "wof:placetype":"locality"
},
  "geometry": {"coordinates":[-71.97389,-16.55222],"type":"Point"}
}