{
  "type": "Feature",
  "properties": {
    "gn:admin1_code":"21",
    "gn:admin2_code":"2112",
    "gn:asciiname":"Palpabamba",
    "gn:country_code":"PE",
    "gn:dem":1353,
    "gn:feature_class":"P",
    "gn:feature_code":"PPL",
    "gn:name":"Palpabamba",
    "gn:population":0,
    "gn:timezone":"America/Lima",
    "iso:country":"PE",
    "name:spa_x_preferred":[
        "Palpabamba"
    ],
    "wof:name":"Palpabamba",
    "wof:placetype":"locality"
},
  "geometry": {"coordinates":[-69.56444999999999,-13.90603],"type":"Point"}
}