{
  "type": "Feature",
  "properties": {
    "gn:admin1_code":"21",
    "gn:admin2_code":"2107.0",
    "gn:admin3_code":"210709.0",
    "gn:asciiname":"Minas Belenguela",
    "gn:country_code":"PE",
    "gn:dem":4231,
    "gn:feature_class":"P",
    "gn:feature_code":"PPL",
    "gn:name":"Minas Belenguela",
    "gn:population":0,
    "gn:timezone":"America/Lima",
    "iso:country":"PE",
    "wof:name":"Minas Belenguela",
    "wof:placetype":"locality"
},
  "geometry": {"coordinates":[-70.56083000000002,-15.65444],"type":"Point"}
}