{
  "type": "Feature",
  "properties": {
    "gn:admin1_code":"21",
    "gn:admin2_code":"2112.0",
    "gn:admin3_code":"211204.0",
    "gn:asciiname":"Punayllu",
    "gn:country_code":"PE",
    "gn:dem":3899,
    "gn:feature_class":"P",
    "gn:feature_code":"PPL",
    "gn:name":"Punayllu",
    "gn:population":0,
    "gn:timezone":"America/Lima",
    "iso:country":"PE",
    "wof:name":"Punayllu",
    "wof:placetype":"locality"
},
  "geometry": {"coordinates":[-69.66421,-14.38111],"type":"Point"}
}