{
  "type": "Feature",
  "properties": {
    "gn:admin1_code":"10",
    "gn:admin2_code":"1002.0",
    "gn:admin3_code":"100203.0",
    "gn:asciiname":"Huampun",
    "gn:country_code":"PE",
    "gn:dem":3891,
    "gn:feature_class":"P",
    "gn:feature_code":"PPL",
    "gn:name":"Huamp\u00fan",
    "gn:population":0,
    "gn:timezone":"America/Lima",
    "iso:country":"PE",
    "wof:name":"Huampun",
    "wof:placetype":"locality"
},
  "geometry": {"coordinates":[-76.4837,-10.26715],"type":"Point"}
}