{
  "type": "Feature",
  "properties": {
    "gn:admin1_code":"20",
    "gn:admin2_code":"2004.0",
    "gn:admin3_code":"200404.0",
    "gn:asciiname":"Pabur",
    "gn:cc2":"PE",
    "gn:country_code":"PE",
    "gn:dem":96,
    "gn:feature_class":"P",
    "gn:feature_code":"PPL",
    "gn:name":"Pabur",
    "gn:population":0,
    "gn:timezone":"America/Lima",
    "iso:country":"PE",
    "name:und_x_variant":[
        "Pabur Hacienda",
        "Pabur"
    ],
    "wof:name":"Pabur",
    "wof:placetype":"locality"
},
  "geometry": {"coordinates":[-80.09999999999999,-5.16667],"type":"Point"}
}