{
  "type": "Feature",
  "properties": {
    "gn:admin1_code":"15.0",
    "gn:admin2_code":"1506.0",
    "gn:admin3_code":"150601.0",
    "gn:asciiname":"Fundo San Francisco",
    "gn:country_code":"PE",
    "gn:dem":166,
    "gn:feature_class":"P",
    "gn:feature_code":"PPL",
    "gn:name":"Fundo San Francisco",
    "gn:population":0,
    "gn:timezone":"America/Lima",
    "iso:country":"PE",
    "name:spa_x_preferred":[
        "Fundo San Francisco"
    ],
    "wof:name":"Fundo San Francisco",
    "wof:placetype":"locality"
},
  "geometry": {"coordinates":[-77.2132,-11.50754],"type":"Point"}
}