{
  "type": "Feature",
  "properties": {
    "gn:admin1_code":"3",
    "gn:admin2_code":"302.0",
    "gn:admin3_code":"30215.0",
    "gn:asciiname":"Jello Pata",
    "gn:country_code":"PE",
    "gn:dem":3390,
    "gn:feature_class":"P",
    "gn:feature_code":"PPL",
    "gn:name":"Jello Pata",
    "gn:population":0,
    "gn:timezone":"America/Lima",
    "iso:country":"PE",
    "wof:name":"Jello Pata",
    "wof:placetype":"locality"
},
  "geometry": {"coordinates":[-73.50416,-13.6491],"type":"Point"}
}