{
  "type": "Feature",
  "properties": {
    "gn:admin1_code":"20",
    "gn:admin2_code":"2002.0",
    "gn:admin3_code":"200201.0",
    "gn:asciiname":"Ambasal",
    "gn:country_code":"PE",
    "gn:dem":1484,
    "gn:feature_class":"P",
    "gn:feature_code":"PPL",
    "gn:name":"Ambasal",
    "gn:population":0,
    "gn:timezone":"America/Lima",
    "iso:country":"PE",
    "name:und_x_variant":[
        "Ambasal Ciudad",
        "Ambasal"
    ],
    "wof:name":"Ambasal",
    "wof:placetype":"locality"
},
  "geometry": {"coordinates":[-79.7461,-4.58231],"type":"Point"}
}