{
  "type": "Feature",
  "properties": {
    "gn:admin1_code":"15.0",
    "gn:admin2_code":"1507.0",
    "gn:admin3_code":"150724.0",
    "gn:asciiname":"Chula",
    "gn:country_code":"PE",
    "gn:dem":3381,
    "gn:feature_class":"P",
    "gn:feature_code":"PPL",
    "gn:name":"Chula",
    "gn:population":0,
    "gn:timezone":"America/Lima",
    "iso:country":"PE",
    "name:ceb_x_preferred":[
        "Chula"
    ],
    "name:deu_x_preferred":[
        "Chula"
    ],
    "name:por_x_preferred":[
        "Chula"
    ],
    "name:spa_x_preferred":[
        "Chula"
    ],
    "name:swe_x_preferred":[
        "Chula"
    ],
    "name:tha_x_preferred":[
        "Chula"
    ],
    "name:ukr_x_preferred":[
        "\u0427\u0443\u043b\u0430"
    ],
    "wof:name":"Chula",
    "wof:placetype":"locality"
},
  "geometry": {"coordinates":[-76.56626,-11.76597],"type":"Point"}
}