{
  "type": "Feature",
  "properties": {
    "gn:admin1_code":"05",
    "gn:admin2_code":"505.0",
    "gn:admin3_code":"50508.0",
    "gn:asciiname":"Tambo",
    "gn:country_code":"PE",
    "gn:dem":3170,
    "gn:feature_class":"P",
    "gn:feature_code":"PPLA3",
    "gn:name":"Tambo",
    "gn:population":0,
    "gn:timezone":"America/Lima",
    "iso:country":"PE",
    "name:ceb_x_preferred":[
        "Tambo"
    ],
    "name:deu_x_preferred":[
        "Tambo"
    ],
    "name:fra_x_preferred":[
        "Tambo"
    ],
    "name:hrv_x_preferred":[
        "Tambo"
    ],
    "name:nor_x_preferred":[
        "Tambo"
    ],
    "name:por_x_preferred":[
        "Tambo"
    ],
    "name:rus_x_preferred":[
        "\u0422\u0430\u043c\u0431\u043e"
    ],
    "name:spa_x_preferred":[
        "Tambo"
    ],
    "name:swe_x_preferred":[
        "Tambo"
    ],
    "wof:name":"Tambo",
    "wof:placetype":"locality"
},
  "geometry": {"coordinates":[-74.01666999999998,-12.93333],"type":"Point"}
}