{
  "type": "Feature",
  "properties": {
    "gn:admin1_code":"12.0",
    "gn:admin2_code":"1202.0",
    "gn:admin3_code":"120206.0",
    "gn:asciiname":"Yerbabuena",
    "gn:country_code":"PE",
    "gn:dem":2995,
    "gn:feature_class":"P",
    "gn:feature_code":"PPL",
    "gn:name":"Yerbabuena",
    "gn:population":0,
    "gn:timezone":"America/Lima",
    "iso:country":"PE",
    "wof:name":"Yerbabuena",
    "wof:placetype":"locality"
},
  "geometry": {"coordinates":[-75.05691,-11.62094],"type":"Point"}
}