{
  "type": "Feature",
  "properties": {
    "gn:admin1_code":"22",
    "gn:admin2_code":"2209.0",
    "gn:admin3_code":"220904.0",
    "gn:asciiname":"Leticia",
    "gn:country_code":"PE",
    "gn:dem":657,
    "gn:feature_class":"P",
    "gn:feature_code":"PPL",
    "gn:name":"Leticia",
    "gn:population":0,
    "gn:timezone":"America/Lima",
    "iso:country":"PE",
    "wof:name":"Leticia",
    "wof:placetype":"locality"
},
  "geometry": {"coordinates":[-75.90000000000001,-6.55],"type":"Point"}
}