{
  "type": "Feature",
  "properties": {
    "gn:admin1_code":"22",
    "gn:admin2_code":"2209.0",
    "gn:admin3_code":"220904.0",
    "gn:asciiname":"Leticia",
    "gn:country_code":"PE",
    "gn:dem":657,
    "gn:feature_class":"P",
    "gn:feature_code":"PPL",
    "gn:name":"Leticia",
    "gn:population":0,
    "gn:timezone":"America/Lima",
    "iso:country":"PE",
    "name:bre_x_preferred":[
        "Leticia"
    ],
    "name:ceb_x_preferred":[
        "Leticia"
    ],
    "name:deu_x_preferred":[
        "Laetitia"
    ],
    "name:fra_x_preferred":[
        "L\u00e6titia"
    ],
    "name:hat_x_preferred":[
        "Laetitia"
    ],
    "name:hun_x_preferred":[
        "Let\u00edcia"
    ],
    "name:ita_x_preferred":[
        "Letizia"
    ],
    "name:nld_x_preferred":[
        "Laetitia"
    ],
    "name:pol_x_preferred":[
        "Letycja"
    ],
    "name:por_x_preferred":[
        "Let\u00edcia"
    ],
    "name:ron_x_preferred":[
        "Leticia"
    ],
    "name:rus_x_preferred":[
        "\u041b\u0435\u0442\u0438\u0441\u0438\u044f"
    ],
    "name:spa_x_preferred":[
        "Leticia"
    ],
    "wof:name":"Leticia",
    "wof:placetype":"locality"
},
  "geometry": {"coordinates":[-75.90000000000001,-6.55],"type":"Point"}
}