{
  "type": "Feature",
  "properties": {
    "gn:admin1_code":"02",
    "gn:admin2_code":"217.0",
    "gn:admin3_code":"21705.0",
    "gn:asciiname":"Huertas",
    "gn:country_code":"PE",
    "gn:dem":1926,
    "gn:feature_class":"P",
    "gn:feature_code":"PPL",
    "gn:name":"Huertas",
    "gn:population":0,
    "gn:timezone":"America/Lima",
    "iso:country":"PE",
    "wof:name":"Huertas",
    "wof:placetype":"locality"
},
  "geometry": {"coordinates":[-77.59148,-10.12321],"type":"Point"}
}