{
  "type": "Feature",
  "properties": {
    "gn:admin1_code":"11.0",
    "gn:admin2_code":"1105.0",
    "gn:admin3_code":"110506.0",
    "gn:asciiname":"Alto La Luna",
    "gn:country_code":"PE",
    "gn:dem":48,
    "gn:feature_class":"P",
    "gn:feature_code":"PPL",
    "gn:name":"Alto La Luna",
    "gn:population":0,
    "gn:timezone":"America/Lima",
    "iso:country":"PE",
    "name:spa_x_preferred":[
        "Alto La Luna"
    ],
    "wof:name":"Alto La Luna",
    "wof:placetype":"locality"
},
  "geometry": {"coordinates":[-76.18334,-13.71238],"type":"Point"}
}