{
  "type": "Feature",
  "properties": {
    "gn:admin1_code":"15",
    "gn:admin2_code":"1508.0",
    "gn:admin3_code":"150812.0",
    "gn:asciiname":"Palca",
    "gn:country_code":"PE",
    "gn:dem":14,
    "gn:feature_class":"P",
    "gn:feature_code":"PPL",
    "gn:name":"Palca",
    "gn:population":0,
    "gn:timezone":"America/Lima",
    "iso:country":"PE",
    "wof:name":"Palca",
    "wof:placetype":"locality"
},
  "geometry": {"coordinates":[-77.64333000000001,-11.03222],"type":"Point"}
}