{
  "type": "Feature",
  "properties": {
    "gn:admin1_code":"9.0",
    "gn:admin2_code":"902.0",
    "gn:asciiname":"Rarunmarca",
    "gn:country_code":"PE",
    "gn:dem":3306,
    "gn:feature_class":"P",
    "gn:feature_code":"PPL",
    "gn:name":"Rarunmarca",
    "gn:population":0,
    "gn:timezone":"America/Lima",
    "iso:country":"PE",
    "wof:name":"Rarunmarca",
    "wof:placetype":"locality"
},
  "geometry": {"coordinates":[-74.48198000000002,-12.8173],"type":"Point"}
}