{
  "type": "Feature",
  "properties": {
    "gn:admin1_code":"9",
    "gn:admin2_code":"906.0",
    "gn:admin3_code":"90601.0",
    "gn:asciiname":"Chinchillcoma",
    "gn:country_code":"PE",
    "gn:dem":3647,
    "gn:feature_class":"P",
    "gn:feature_code":"PPL",
    "gn:name":"Chinchillcoma",
    "gn:population":0,
    "gn:timezone":"America/Lima",
    "iso:country":"PE",
    "wof:name":"Chinchillcoma",
    "wof:placetype":"locality"
},
  "geometry": {"coordinates":[-75.36944,-13.63056],"type":"Point"}
}