{
  "type": "Feature",
  "properties": {
    "gn:admin1_code":"12.0",
    "gn:admin2_code":"1206.0",
    "gn:admin3_code":"120608.0",
    "gn:asciiname":"Majireni",
    "gn:country_code":"PE",
    "gn:dem":279,
    "gn:feature_class":"P",
    "gn:feature_code":"PPLL",
    "gn:name":"Majireni",
    "gn:population":0,
    "gn:timezone":"America/Lima",
    "iso:country":"PE",
    "name:spa_x_preferred":[
        "Majireni"
    ],
    "wof:name":"Majireni",
    "wof:placetype":"locality"
},
  "geometry": {"coordinates":[-73.84751,-11.23627],"type":"Point"}
}