{
  "type": "Feature",
  "properties": {
    "gn:admin1_code":"09",
    "gn:admin2_code":"901.0",
    "gn:admin3_code":"90106.0",
    "gn:asciiname":"Chaupiyacu",
    "gn:country_code":"PE",
    "gn:dem":4670,
    "gn:feature_class":"P",
    "gn:feature_code":"PPL",
    "gn:name":"Chaupiyacu",
    "gn:population":0,
    "gn:timezone":"America/Lima",
    "iso:country":"PE",
    "name:und_x_variant":[
        "Chaupiyaku"
    ],
    "wof:name":"Chaupiyacu",
    "wof:placetype":"locality"
},
  "geometry": {"coordinates":[-74.92645,-13.15407],"type":"Point"}
}