{
  "type": "Feature",
  "properties": {
    "gn:admin1_code":"4",
    "gn:admin2_code":"406.0",
    "gn:admin3_code":"40602.0",
    "gn:asciiname":"Apacheta de Jaisura",
    "gn:country_code":"PE",
    "gn:dem":3943,
    "gn:feature_class":"P",
    "gn:feature_code":"PPL",
    "gn:name":"Apacheta de Jaisura",
    "gn:population":0,
    "gn:timezone":"America/Lima",
    "iso:country":"PE",
    "wof:name":"Apacheta de Jaisura",
    "wof:placetype":"locality"
},
  "geometry": {"coordinates":[-72.76805999999998,-15.76667],"type":"Point"}
}