{
  "type": "Feature",
  "properties": {
    "gn:admin1_code":"16",
    "gn:admin2_code":"1607.0",
    "gn:admin3_code":"160704.0",
    "gn:asciiname":"La Draga",
    "gn:cc2":"PE",
    "gn:country_code":"PE",
    "gn:dem":160,
    "gn:feature_class":"P",
    "gn:feature_code":"PPL",
    "gn:name":"La Draga",
    "gn:population":0,
    "gn:timezone":"America/Lima",
    "iso:country":"PE",
    "name:und_x_variant":[
        "La Braga",
        "La Draga"
    ],
    "wof:name":"La Draga",
    "wof:placetype":"locality"
},
  "geometry": {"coordinates":[-77.31667,-4.55],"type":"Point"}
}