{
  "type": "Feature",
  "properties": {
    "gn:admin1_code":"12.0",
    "gn:admin2_code":"1202.0",
    "gn:admin3_code":"120206.0",
    "gn:asciiname":"Chaca",
    "gn:country_code":"PE",
    "gn:dem":2894,
    "gn:feature_class":"P",
    "gn:feature_code":"PPL",
    "gn:name":"Chaca",
    "gn:population":0,
    "gn:timezone":"America/Lima",
    "iso:country":"PE",
    "name:ceb_x_preferred":[
        "Chaca"
    ],
    "name:kor_x_preferred":[
        "\ucc28\uce74\uc18d"
    ],
    "name:swe_x_preferred":[
        "Chaca"
    ],
    "wof:name":"Chaca",
    "wof:placetype":"locality"
},
  "geometry": {"coordinates":[-75.08584999999999,-11.6973],"type":"Point"}
}