{
  "type": "Feature",
  "properties": {
    "gn:admin1_code":"02",
    "gn:admin2_code":"220.0",
    "gn:admin3_code":"22005.0",
    "gn:asciiname":"La Victoria",
    "gn:country_code":"PE",
    "gn:dem":1640,
    "gn:feature_class":"P",
    "gn:feature_code":"PPLL",
    "gn:name":"La Victoria",
    "gn:population":0,
    "gn:timezone":"America/Lima",
    "iso:country":"PE",
    "name:bre_x_preferred":[
        "La Victoria"
    ],
    "name:ceb_x_preferred":[
        "La Victoria"
    ],
    "name:deu_x_preferred":[
        "La Victoria"
    ],
    "name:fra_x_preferred":[
        "La Victoria"
    ],
    "name:glg_x_preferred":[
        "La Victoria"
    ],
    "name:ita_x_preferred":[
        "La Victoria"
    ],
    "name:msa_x_preferred":[
        "La Victoria"
    ],
    "name:nld_x_preferred":[
        "La Victoria"
    ],
    "name:por_x_preferred":[
        "La Victoria"
    ],
    "name:rus_x_preferred":[
        "\u041b\u0430-\u0412\u0438\u043a\u0442\u043e\u0440\u0438\u044f"
    ],
    "name:swe_x_preferred":[
        "La Victoria"
    ],
    "name:vie_x_preferred":[
        "La Victoria"
    ],
    "name:vol_x_preferred":[
        "La Victoria"
    ],
    "name:war_x_preferred":[
        "La Victoria"
    ],
    "wof:name":"La Victoria",
    "wof:placetype":"locality"
},
  "geometry": {"coordinates":[-78.00778000000003,-9.33083],"type":"Point"}
}