{
  "type": "Feature",
  "properties": {
    "gn:admin1_code":"13.0",
    "gn:admin2_code":"1308.0",
    "gn:admin3_code":"130808.0",
    "gn:asciiname":"Alto del Rayo",
    "gn:country_code":"PE",
    "gn:dem":3689,
    "gn:feature_class":"P",
    "gn:feature_code":"PPL",
    "gn:name":"Alto del Rayo",
    "gn:population":0,
    "gn:timezone":"America/Lima",
    "iso:country":"PE",
    "wof:name":"Alto del Rayo",
    "wof:placetype":"locality"
},
  "geometry": {"coordinates":[-77.46389000000001,-8.06],"type":"Point"}
}