{
  "type": "Feature",
  "properties": {
    "gn:admin1_code":"21",
    "gn:admin2_code":"2111.0",
    "gn:admin3_code":"211103.0",
    "gn:asciiname":"Chachra",
    "gn:country_code":"PE",
    "gn:dem":4193,
    "gn:feature_class":"P",
    "gn:feature_code":"PPL",
    "gn:name":"Chachra",
    "gn:population":0,
    "gn:timezone":"America/Lima",
    "iso:country":"PE",
    "wof:name":"Chachra",
    "wof:placetype":"locality"
},
  "geometry": {"coordinates":[-70.62238000000001,-15.83723],"type":"Point"}
}