{
  "type": "Feature",
  "properties": {
    "gn:admin1_code":"06",
    "gn:admin2_code":"604.0",
    "gn:admin3_code":"60416.0",
    "gn:asciiname":"Llonque",
    "gn:country_code":"PE",
    "gn:dem":914,
    "gn:feature_class":"P",
    "gn:feature_code":"PPL",
    "gn:name":"Llonque",
    "gn:population":0,
    "gn:timezone":"America/Lima",
    "iso:country":"PE",
    "wof:name":"Llonque",
    "wof:placetype":"locality"
},
  "geometry": {"coordinates":[-79.20589,-6.49916],"type":"Point"}
}