{
  "type": "Feature",
  "properties": {
    "gn:admin1_code":"10",
    "gn:admin2_code":"1002.0",
    "gn:admin3_code":"100205.0",
    "gn:asciiname":"Viroy",
    "gn:cc2":"PE",
    "gn:country_code":"PE",
    "gn:dem":2106,
    "gn:feature_class":"P",
    "gn:feature_code":"PPL",
    "gn:name":"Viroy",
    "gn:population":0,
    "gn:timezone":"America/Lima",
    "iso:country":"PE",
    "name:und_x_variant":[
        "Vivay",
        "Virroy",
        "Viray",
        "Viroy"
    ],
    "wof:name":"Viroy",
    "wof:placetype":"locality"
},
  "geometry": {"coordinates":[-76.23333000000002,-10.15],"type":"Point"}
}