{
  "type": "Feature",
  "properties": {
    "gn:admin1_code":"05",
    "gn:admin2_code":"510.0",
    "gn:admin3_code":"51004.0",
    "gn:asciiname":"Tama",
    "gn:country_code":"PE",
    "gn:dem":3518,
    "gn:feature_class":"P",
    "gn:feature_code":"PPL",
    "gn:name":"Tama",
    "gn:population":0,
    "gn:timezone":"America/Lima",
    "iso:country":"PE",
    "wof:name":"Tama",
    "wof:placetype":"locality"
},
  "geometry": {"coordinates":[-73.93611,-14.09083],"type":"Point"}
}