{
  "type": "Feature",
  "properties": {
    "gn:admin1_code":"13",
    "gn:admin2_code":"1309.0",
    "gn:admin3_code":"130908.0",
    "gn:asciiname":"Hualango",
    "gn:country_code":"PE",
    "gn:dem":3085,
    "gn:feature_class":"P",
    "gn:feature_code":"PPL",
    "gn:name":"Hualango",
    "gn:population":0,
    "gn:timezone":"America/Lima",
    "iso:country":"PE",
    "wof:name":"Hualango",
    "wof:placetype":"locality"
},
  "geometry": {"coordinates":[-77.8193,-7.59544],"type":"Point"}
}