{
  "type": "Feature",
  "properties": {
    "gn:admin1_code":"11",
    "gn:admin2_code":"1101.0",
    "gn:admin3_code":"110107.0",
    "gn:asciiname":"Pongo Chico",
    "gn:country_code":"PE",
    "gn:dem":411,
    "gn:feature_class":"P",
    "gn:feature_code":"PPL",
    "gn:name":"Pongo Chico",
    "gn:population":0,
    "gn:timezone":"America/Lima",
    "iso:country":"PE",
    "name:spa_x_preferred":[
        "Pongo Chico"
    ],
    "wof:name":"Pongo Chico",
    "wof:placetype":"locality"
},
  "geometry": {"coordinates":[-75.69242,-14.11675],"type":"Point"}
}