{
  "type": "Feature",
  "properties": {
    "gn:admin1_code":"5.0",
    "gn:admin2_code":"505.0",
    "gn:admin3_code":"50502.0",
    "gn:asciiname":"San Martin",
    "gn:country_code":"PE",
    "gn:dem":683,
    "gn:feature_class":"P",
    "gn:feature_code":"PPL",
    "gn:name":"San Mart\u00edn",
    "gn:population":0,
    "gn:timezone":"America/Lima",
    "iso:country":"PE",
    "wof:name":"San Martin",
    "wof:placetype":"locality"
},
  "geometry": {"coordinates":[-73.58100999999998,-12.86158],"type":"Point"}
}