{
  "type": "Feature",
  "properties": {
    "gn:admin1_code":"16.0",
    "gn:admin2_code":"1606.0",
    "gn:asciiname":"Ramires Hurtado",
    "gn:country_code":"PE",
    "gn:dem":142,
    "gn:feature_class":"P",
    "gn:feature_code":"PPL",
    "gn:name":"Ramires Hurtado",
    "gn:population":0,
    "gn:timezone":"America/Lima",
    "iso:country":"PE",
    "name:spa_x_preferred":[
        "Ramires Hurtado"
    ],
    "wof:name":"Ramires Hurtado",
    "wof:placetype":"locality"
},
  "geometry": {"coordinates":[-75.26414,-7.07095],"type":"Point"}
}