{
  "type": "Feature",
  "properties": {
    "gn:admin1_code":"5.0",
    "gn:admin2_code":"501.0",
    "gn:admin3_code":"50101.0",
    "gn:asciiname":"Capilla Pampa",
    "gn:country_code":"PE",
    "gn:dem":2723,
    "gn:feature_class":"P",
    "gn:feature_code":"PPL",
    "gn:name":"Capilla Pampa",
    "gn:population":0,
    "gn:timezone":"America/Lima",
    "iso:country":"PE",
    "wof:name":"Capilla Pampa",
    "wof:placetype":"locality"
},
  "geometry": {"coordinates":[-74.21658000000002,-13.16432],"type":"Point"}
}