{
  "type": "Feature",
  "properties": {
    "gn:admin1_code":"8",
    "gn:admin2_code":"806.0",
    "gn:admin3_code":"80601.0",
    "gn:asciiname":"Herca",
    "gn:country_code":"PE",
    "gn:dem":3623,
    "gn:feature_class":"P",
    "gn:feature_code":"PPL",
    "gn:name":"Herca",
    "gn:population":0,
    "gn:timezone":"America/Lima",
    "iso:country":"PE",
    "name:und_x_variant":[
        "Hercca",
        "Herca"
    ],
    "wof:name":"Herca",
    "wof:placetype":"locality"
},
  "geometry": {"coordinates":[-71.25255,-14.30818],"type":"Point"}
}