{
  "type": "Feature",
  "properties": {
    "gn:admin1_code":"06",
    "gn:admin2_code":"601.0",
    "gn:admin3_code":"60105.0",
    "gn:asciiname":"Fraile",
    "gn:country_code":"PE",
    "gn:dem":3936,
    "gn:feature_class":"P",
    "gn:feature_code":"PPL",
    "gn:name":"Fraile",
    "gn:population":0,
    "gn:timezone":"America/Lima",
    "iso:country":"PE",
    "wof:name":"Fraile",
    "wof:placetype":"locality"
},
  "geometry": {"coordinates":[-78.49105,-6.92507],"type":"Point"}
}