{
  "type": "Feature",
  "properties": {
    "gn:admin1_code":"8",
    "gn:admin2_code":"808.0",
    "gn:admin3_code":"80803.0",
    "gn:asciiname":"Chuana",
    "gn:country_code":"PE",
    "gn:dem":4275,
    "gn:feature_class":"P",
    "gn:feature_code":"PPL",
    "gn:name":"Chua\u00f1a",
    "gn:population":0,
    "gn:timezone":"America/Lima",
    "iso:country":"PE",
    "wof:name":"Chuana",
    "wof:placetype":"locality"
},
  "geometry": {"coordinates":[-71.71249,-14.72852],"type":"Point"}
}