{
  "type": "Feature",
  "properties": {
    "gn:admin1_code":"08",
    "gn:admin2_code":"809.0",
    "gn:admin3_code":"80901.0",
    "gn:asciiname":"Echarate",
    "gn:country_code":"PE",
    "gn:dem":1005,
    "gn:feature_class":"P",
    "gn:feature_code":"PPL",
    "gn:name":"Echarate",
    "gn:population":0,
    "gn:timezone":"America/Lima",
    "iso:country":"PE",
    "wof:name":"Echarate",
    "wof:placetype":"locality"
},
  "geometry": {"coordinates":[-72.5783,-12.76832],"type":"Point"}
}