{
  "type": "Feature",
  "properties": {
    "gn:admin1_code":"2.0",
    "gn:admin2_code":"201.0",
    "gn:admin3_code":"20106.0",
    "gn:asciiname":"Collpa",
    "gn:country_code":"PE",
    "gn:dem":3370,
    "gn:feature_class":"P",
    "gn:feature_code":"PPL",
    "gn:name":"Collpa",
    "gn:population":0,
    "gn:timezone":"America/Lima",
    "iso:country":"PE",
    "wof:name":"Collpa",
    "wof:placetype":"locality"
},
  "geometry": {"coordinates":[-77.60221999999997,-9.4225],"type":"Point"}
}