{
  "type": "Feature",
  "properties": {
    "gn:admin1_code":"10.0",
    "gn:admin2_code":"1005.0",
    "gn:admin3_code":"100509.0",
    "gn:asciiname":"Ojeragra",
    "gn:country_code":"PE",
    "gn:dem":3760,
    "gn:feature_class":"P",
    "gn:feature_code":"PPL",
    "gn:name":"Ojeragra",
    "gn:population":0,
    "gn:timezone":"America/Lima",
    "iso:country":"PE",
    "wof:name":"Ojeragra",
    "wof:placetype":"locality"
},
  "geometry": {"coordinates":[-76.88630999999999,-9.50628],"type":"Point"}
}