{
  "type": "Feature",
  "properties": {
    "gn:admin1_code":"8.0",
    "gn:admin2_code":"813.0",
    "gn:admin3_code":"81301.0",
    "gn:asciiname":"San Isidro",
    "gn:country_code":"PE",
    "gn:dem":2974,
    "gn:feature_class":"P",
    "gn:feature_code":"PPL",
    "gn:name":"San Isidro",
    "gn:population":0,
    "gn:timezone":"America/Lima",
    "iso:country":"PE",
    "wof:name":"San Isidro",
    "wof:placetype":"locality"
},
  "geometry": {"coordinates":[-72.18666999999998,-13.26722],"type":"Point"}
}