{
  "type": "Feature",
  "properties": {
    "gn:admin1_code":"12",
    "gn:admin2_code":"1207.0",
    "gn:admin3_code":"120702.0",
    "gn:asciiname":"Muruhuay",
    "gn:country_code":"PE",
    "gn:dem":3015,
    "gn:feature_class":"P",
    "gn:feature_code":"PPL",
    "gn:name":"Muruhuay",
    "gn:population":0,
    "gn:timezone":"America/Lima",
    "iso:country":"PE",
    "name:und_x_variant":[
        "Muruhuoy"
    ],
    "wof:name":"Muruhuay",
    "wof:placetype":"locality"
},
  "geometry": {"coordinates":[-75.65516,-11.34629],"type":"Point"}
}