{
  "type": "Feature",
  "properties": {
    "gn:admin1_code":"23",
    "gn:admin2_code":"2301.0",
    "gn:admin3_code":"230107.0",
    "gn:asciiname":"Japichuyo",
    "gn:country_code":"PE",
    "gn:dem":4563,
    "gn:feature_class":"P",
    "gn:feature_code":"PPL",
    "gn:name":"Japichuyo",
    "gn:population":0,
    "gn:timezone":"America/Lima",
    "iso:country":"PE",
    "wof:name":"Japichuyo",
    "wof:placetype":"locality"
},
  "geometry": {"coordinates":[-69.77472,-17.53639],"type":"Point"}
}