{
  "type": "Feature",
  "properties": {
    "gn:admin1_code":"16",
    "gn:admin2_code":"1603.0",
    "gn:admin3_code":"160304.0",
    "gn:asciiname":"San Juan de Trompeteros",
    "gn:country_code":"PE",
    "gn:dem":121,
    "gn:feature_class":"P",
    "gn:feature_code":"PPL",
    "gn:name":"San Juan de Trompeteros",
    "gn:population":0,
    "gn:timezone":"America/Lima",
    "iso:country":"PE",
    "wof:name":"San Juan de Trompeteros",
    "wof:placetype":"locality"
},
  "geometry": {"coordinates":[-75.07525,-3.81043],"type":"Point"}
}