{
  "type": "Feature",
  "properties": {
    "gn:admin1_code":"20",
    "gn:admin2_code":"2002.0",
    "gn:admin3_code":"200210.0",
    "gn:asciiname":"San Joaquin",
    "gn:country_code":"PE",
    "gn:dem":379,
    "gn:feature_class":"P",
    "gn:feature_code":"PPL",
    "gn:name":"San Joaqu\u00edn",
    "gn:population":0,
    "gn:timezone":"America/Lima",
    "iso:country":"PE",
    "name:ceb_x_preferred":[
        "San Joaquin"
    ],
    "name:deu_x_preferred":[
        "San Joaquin"
    ],
    "name:fra_x_preferred":[
        "San Joaquin"
    ],
    "name:ita_x_preferred":[
        "San Joaquin"
    ],
    "name:nds_x_preferred":[
        "San Joaquin"
    ],
    "name:nld_x_preferred":[
        "San Joaquin"
    ],
    "name:pol_x_preferred":[
        "San Joaquin"
    ],
    "name:por_x_preferred":[
        "San Joaquin"
    ],
    "name:swe_x_preferred":[
        "San Joaquin"
    ],
    "name:und_x_variant":[
        "Hacienda San Joaqu\u00edn",
        "San Joaquin Hacienda",
        "Hacienda Joaqu\u00edn",
        "San Joaqu\u00edn"
    ],
    "name:war_x_preferred":[
        "San Joaquin"
    ],
    "wof:name":"San Joaquin",
    "wof:placetype":"locality"
},
  "geometry": {"coordinates":[-80.06924000000002,-4.55972],"type":"Point"}
}