{
  "type": "Feature",
  "properties": {
    "gn:admin1_code":"12.0",
    "gn:admin2_code":"1202.0",
    "gn:admin3_code":"120209.0",
    "gn:asciiname":"Yaurinja",
    "gn:country_code":"PE",
    "gn:dem":2955,
    "gn:feature_class":"P",
    "gn:feature_code":"PPL",
    "gn:name":"Yaurinja",
    "gn:population":0,
    "gn:timezone":"America/Lima",
    "iso:country":"PE",
    "wof:name":"Yaurinja",
    "wof:placetype":"locality"
},
  "geometry": {"coordinates":[-75.07734000000001,-11.65062],"type":"Point"}
}