{
  "type": "Feature",
  "properties": {
    "gn:admin1_code":"12",
    "gn:admin2_code":"1209.0",
    "gn:admin3_code":"120909.0",
    "gn:asciiname":"Hornonniyoc",
    "gn:country_code":"PE",
    "gn:dem":4560,
    "gn:feature_class":"P",
    "gn:feature_code":"PPL",
    "gn:name":"Hornonniyoc",
    "gn:population":0,
    "gn:timezone":"America/Lima",
    "iso:country":"PE",
    "wof:name":"Hornonniyoc",
    "wof:placetype":"locality"
},
  "geometry": {"coordinates":[-75.52528000000002,-12.20111],"type":"Point"}
}