{
  "type": "Feature",
  "properties": {
    "gn:admin1_code":"16.0",
    "gn:admin2_code":"1601.0",
    "gn:admin3_code":"160102.0",
    "gn:asciiname":"Pisco",
    "gn:country_code":"PE",
    "gn:dem":106,
    "gn:feature_class":"P",
    "gn:feature_code":"PPL",
    "gn:name":"Pisco",
    "gn:population":0,
    "gn:timezone":"America/Lima",
    "iso:country":"PE",
    "wof:name":"Pisco",
    "wof:placetype":"locality"
},
  "geometry": {"coordinates":[-73.71456999999999,-3.88963],"type":"Point"}
}