{
  "type": "Feature",
  "properties": {
    "gn:admin1_code":"16.0",
    "gn:admin2_code":"1601.0",
    "gn:admin3_code":"160102.0",
    "gn:asciiname":"Pisco",
    "gn:country_code":"PE",
    "gn:dem":106,
    "gn:feature_class":"P",
    "gn:feature_code":"PPL",
    "gn:name":"Pisco",
    "gn:population":0,
    "gn:timezone":"America/Lima",
    "iso:country":"PE",
    "name:ara_x_preferred":[
        "\u0628\u064a\u0633\u0643\u0648"
    ],
    "name:cat_x_preferred":[
        "Pisco"
    ],
    "name:ces_x_preferred":[
        "Pisco"
    ],
    "name:chv_x_preferred":[
        "\u041f\u0438\u0441\u043a\u043e"
    ],
    "name:deu_x_preferred":[
        "Pisco"
    ],
    "name:epo_x_preferred":[
        "Pisko"
    ],
    "name:fas_x_preferred":[
        "\u067e\u06cc\u0633\u06a9\u0648"
    ],
    "name:fin_x_preferred":[
        "Pisco"
    ],
    "name:fra_x_preferred":[
        "Pisco"
    ],
    "name:glg_x_preferred":[
        "Pisco"
    ],
    "name:hun_x_preferred":[
        "Pisco"
    ],
    "name:ita_x_preferred":[
        "Pisco"
    ],
    "name:jpn_x_preferred":[
        "\u30d4\u30b9\u30b3"
    ],
    "name:nld_x_preferred":[
        "Pisco"
    ],
    "name:nno_x_preferred":[
        "Pisco"
    ],
    "name:pol_x_preferred":[
        "Pisco"
    ],
    "name:por_x_preferred":[
        "Pisco"
    ],
    "name:rus_x_preferred":[
        "\u041f\u0438\u0441\u043a\u043e"
    ],
    "name:slv_x_preferred":[
        "Pisco"
    ],
    "name:spa_x_preferred":[
        "Pisco"
    ],
    "name:swe_x_preferred":[
        "Pisco"
    ],
    "name:tha_x_preferred":[
        "\u0e1b\u0e34\u0e2a\u0e42\u0e01"
    ],
    "name:tur_x_preferred":[
        "Pisco"
    ],
    "name:ukr_x_preferred":[
        "\u041f\u0456\u0441\u043a\u043e"
    ],
    "name:xmf_x_preferred":[
        "\u10de\u10d8\u10e1\u10d9\u10dd"
    ],
    "name:zho_x_preferred":[
        "\u76ae\u65af\u53ef"
    ],
    "wof:name":"Pisco",
    "wof:placetype":"locality"
},
  "geometry": {"coordinates":[-73.71456999999999,-3.88963],"type":"Point"}
}