{
  "type": "Feature",
  "properties": {
    "gn:admin1_code":"21",
    "gn:admin2_code":"2103",
    "gn:asciiname":"Cochacucho",
    "gn:country_code":"PE",
    "gn:dem":3830,
    "gn:feature_class":"P",
    "gn:feature_code":"PPL",
    "gn:name":"Cochacucho",
    "gn:population":0,
    "gn:timezone":"America/Lima",
    "iso:country":"PE",
    "name:spa_x_preferred":[
        "Cochacucho"
    ],
    "name:zho_x_preferred":[
        "\u79d1\u67e5\u5eab\u55ac\u5c71"
    ],
    "wof:name":"Cochacucho",
    "wof:placetype":"locality"
},
  "geometry": {"coordinates":[-69.89241,-13.91641],"type":"Point"}
}