{
  "type": "Feature",
  "properties": {
    "gn:admin1_code":"15",
    "gn:admin2_code":"1510.0",
    "gn:admin3_code":"151027.0",
    "gn:asciiname":"Tamara",
    "gn:country_code":"PE",
    "gn:dem":2857,
    "gn:feature_class":"P",
    "gn:feature_code":"PPL",
    "gn:name":"Tamar\u00e1",
    "gn:population":0,
    "gn:timezone":"America/Lima",
    "iso:country":"PE",
    "wof:name":"Tamara",
    "wof:placetype":"locality"
},
  "geometry": {"coordinates":[-76.22190999999999,-12.44413],"type":"Point"}
}