{
  "type": "Feature",
  "properties": {
    "gn:admin1_code":"15",
    "gn:admin2_code":"1510.0",
    "gn:admin3_code":"151027.0",
    "gn:asciiname":"Tamara",
    "gn:country_code":"PE",
    "gn:dem":2857,
    "gn:feature_class":"P",
    "gn:feature_code":"PPL",
    "gn:name":"Tamar\u00e1",
    "gn:population":0,
    "gn:timezone":"America/Lima",
    "iso:country":"PE",
    "name:ceb_x_preferred":[
        "Tamara"
    ],
    "name:ces_x_preferred":[
        "Tamara"
    ],
    "name:deu_x_preferred":[
        "Tamara"
    ],
    "name:est_x_preferred":[
        "Tamara"
    ],
    "name:fra_x_preferred":[
        "Tamara"
    ],
    "name:hun_x_preferred":[
        "Tamara"
    ],
    "name:ita_x_preferred":[
        "Tamara"
    ],
    "name:jpn_x_preferred":[
        "\u30bf\u30de\u30e9"
    ],
    "name:mal_x_preferred":[
        "\u0d1f\u0d2e\u0d3e\u0d30"
    ],
    "name:pol_x_preferred":[
        "Tamara"
    ],
    "name:por_x_preferred":[
        "Tamara"
    ],
    "name:rus_x_preferred":[
        "\u0422\u0430\u043c\u0430\u0440\u0430"
    ],
    "name:spa_x_preferred":[
        "Tamara"
    ],
    "name:srp_x_preferred":[
        "\u0422\u0430\u043c\u0430\u0440\u0430"
    ],
    "name:swe_x_preferred":[
        "Tamara"
    ],
    "name:ukr_x_preferred":[
        "\u0422\u0430\u043c\u0430\u0440\u0430"
    ],
    "wof:name":"Tamara",
    "wof:placetype":"locality"
},
  "geometry": {"coordinates":[-76.22190999999999,-12.44413],"type":"Point"}
}