{
  "type": "Feature",
  "properties": {
    "gn:admin1_code":"13",
    "gn:admin2_code":"1302.0",
    "gn:admin3_code":"130204.0",
    "gn:asciiname":"Magdalena de Cao",
    "gn:country_code":"PE",
    "gn:dem":27,
    "gn:feature_class":"P",
    "gn:feature_code":"PPL",
    "gn:name":"Magdalena de Cao",
    "gn:population":0,
    "gn:timezone":"America/Lima",
    "iso:country":"PE",
    "wof:name":"Magdalena de Cao",
    "wof:placetype":"locality"
},
  "geometry": {"coordinates":[-79.29458000000002,-7.87778],"type":"Point"}
}