{
  "type": "Feature",
  "properties": {
    "gn:admin1_code":"21",
    "gn:admin2_code":"2104.0",
    "gn:admin3_code":"210407.0",
    "gn:asciiname":"Anufani",
    "gn:country_code":"PE",
    "gn:dem":3847,
    "gn:feature_class":"P",
    "gn:feature_code":"PPL",
    "gn:name":"A\u00f1ufani",
    "gn:population":0,
    "gn:timezone":"America/Lima",
    "iso:country":"PE",
    "wof:name":"Anufani",
    "wof:placetype":"locality"
},
  "geometry": {"coordinates":[-69.16752,-16.61757],"type":"Point"}
}