{
  "type": "Feature",
  "properties": {
    "gn:admin1_code":"12.0",
    "gn:admin2_code":"1205.0",
    "gn:admin3_code":"120501.0",
    "gn:asciiname":"Ranten",
    "gn:country_code":"PE",
    "gn:dem":4165,
    "gn:feature_class":"P",
    "gn:feature_code":"PPL",
    "gn:name":"Ranten",
    "gn:population":0,
    "gn:timezone":"America/Lima",
    "iso:country":"PE",
    "wof:name":"Ranten",
    "wof:placetype":"locality"
},
  "geometry": {"coordinates":[-76.0076,-11.00771],"type":"Point"}
}