{
  "type": "Feature",
  "properties": {
    "gn:admin1_code":"12.0",
    "gn:admin2_code":"1205.0",
    "gn:admin3_code":"120501.0",
    "gn:asciiname":"Ranten",
    "gn:country_code":"PE",
    "gn:dem":4165,
    "gn:feature_class":"P",
    "gn:feature_code":"PPL",
    "gn:name":"Ranten",
    "gn:population":0,
    "gn:timezone":"America/Lima",
    "iso:country":"PE",
    "name:ceb_x_preferred":[
        "Ranten"
    ],
    "name:deu_x_preferred":[
        "Ranten"
    ],
    "name:epo_x_preferred":[
        "Ranten"
    ],
    "name:fas_x_preferred":[
        "\u0631\u0627\u0646\u062a\u0646"
    ],
    "name:fra_x_preferred":[
        "Ranten"
    ],
    "name:hun_x_preferred":[
        "Ranten"
    ],
    "name:ita_x_preferred":[
        "Ranten"
    ],
    "name:kaz_x_preferred":[
        "\u0420\u0430\u043d\u0442\u0435\u043d"
    ],
    "name:nld_x_preferred":[
        "Ranten"
    ],
    "name:pol_x_preferred":[
        "Ranten"
    ],
    "name:rus_x_preferred":[
        "\u0420\u0430\u043d\u0442\u0435\u043d"
    ],
    "name:slk_x_preferred":[
        "Ranten"
    ],
    "name:spa_x_preferred":[
        "Ranten"
    ],
    "name:swe_x_preferred":[
        "Ranten"
    ],
    "name:uzb_x_preferred":[
        "Ranten"
    ],
    "name:vie_x_preferred":[
        "Ranten"
    ],
    "name:vol_x_preferred":[
        "Ranten"
    ],
    "name:war_x_preferred":[
        "Ranten"
    ],
    "wof:name":"Ranten",
    "wof:placetype":"locality"
},
  "geometry": {"coordinates":[-76.0076,-11.00771],"type":"Point"}
}