{
  "type": "Feature",
  "properties": {
    "gn:admin1_code":"17.0",
    "gn:admin2_code":"1701.0",
    "gn:asciiname":"Isla Peru",
    "gn:country_code":"PE",
    "gn:dem":194,
    "gn:feature_class":"P",
    "gn:feature_code":"PPL",
    "gn:name":"Isla Peru",
    "gn:population":0,
    "gn:timezone":"America/Lima",
    "iso:country":"PE",
    "name:spa_x_preferred":[
        "Isla Peru"
    ],
    "wof:name":"Isla Peru",
    "wof:placetype":"locality"
},
  "geometry": {"coordinates":[-69.18375999999999,-12.57651],"type":"Point"}
}