{
  "type": "Feature",
  "properties": {
    "gn:admin1_code":"11.0",
    "gn:admin2_code":"1102.0",
    "gn:admin3_code":"110205.0",
    "gn:asciiname":"Punta La Isla",
    "gn:country_code":"PE",
    "gn:dem":164,
    "gn:feature_class":"P",
    "gn:feature_code":"PPL",
    "gn:name":"Punta La Isla",
    "gn:population":0,
    "gn:timezone":"America/Lima",
    "iso:country":"PE",
    "wof:name":"Punta La Isla",
    "wof:placetype":"locality"
},
  "geometry": {"coordinates":[-76.054,-13.47297],"type":"Point"}
}