{
  "type": "Feature",
  "properties": {
    "gn:admin1_code":"21",
    "gn:admin2_code":"2105.0",
    "gn:asciiname":"Jullani",
    "gn:country_code":"PE",
    "gn:dem":3823,
    "gn:feature_class":"P",
    "gn:feature_code":"PPL",
    "gn:name":"Jullani",
    "gn:population":0,
    "gn:timezone":"America/Lima",
    "iso:country":"PE",
    "name:spa_x_preferred":[
        "Jullani"
    ],
    "wof:name":"Jullani",
    "wof:placetype":"locality"
},
  "geometry": {"coordinates":[-69.45316,-15.99675],"type":"Point"}
}