{
  "type": "Feature",
  "properties": {
    "gn:admin1_code":"24",
    "gn:admin2_code":"2401.0",
    "gn:admin3_code":"240102.0",
    "gn:asciiname":"El Tablazo",
    "gn:country_code":"PE",
    "gn:dem":17,
    "gn:feature_class":"P",
    "gn:feature_code":"PPLL",
    "gn:name":"El Tablazo",
    "gn:population":0,
    "gn:timezone":"America/Lima",
    "iso:country":"PE",
    "wof:name":"El Tablazo",
    "wof:placetype":"locality"
},
  "geometry": {"coordinates":[-80.47223000000002,-3.60823],"type":"Point"}
}