{
  "type": "Feature",
  "properties": {
    "gn:admin1_code":"23.0",
    "gn:admin2_code":"2301.0",
    "gn:admin3_code":"230101.0",
    "gn:asciiname":"Pueblo Libre",
    "gn:country_code":"PE",
    "gn:dem":17,
    "gn:feature_class":"P",
    "gn:feature_code":"PPL",
    "gn:name":"Pueblo Libre",
    "gn:population":0,
    "gn:timezone":"America/Lima",
    "iso:country":"PE",
    "name:cat_x_preferred":[
        "Pueblo Libre"
    ],
    "name:que_x_preferred":[
        "Pueblo Libre distritu"
    ],
    "name:zho_x_preferred":[
        "\u81ea\u7531\u90e8\u843d\u5340"
    ],
    "wof:name":"Pueblo Libre",
    "wof:placetype":"locality"
},
  "geometry": {"coordinates":[-70.43444000000002,-18.3025],"type":"Point"}
}