{
  "type": "Feature",
  "properties": {
    "gn:admin1_code":"20",
    "gn:admin2_code":"2004.0",
    "gn:admin3_code":"200401.0",
    "gn:asciiname":"Huasimal",
    "gn:country_code":"PE",
    "gn:dem":98,
    "gn:feature_class":"P",
    "gn:feature_code":"PPL",
    "gn:name":"Huasimal",
    "gn:population":0,
    "gn:timezone":"America/Lima",
    "iso:country":"PE",
    "name:und_x_variant":[
        "Huasimal Hacienda",
        "Huasimal"
    ],
    "wof:name":"Huasimal",
    "wof:placetype":"locality"
},
  "geometry": {"coordinates":[-80.17437,-5.14116],"type":"Point"}
}