{
  "type": "Feature",
  "properties": {
    "gn:admin1_code":"12.0",
    "gn:admin2_code":"1208.0",
    "gn:admin3_code":"120807.0",
    "gn:asciiname":"Quiulacocha",
    "gn:country_code":"PE",
    "gn:dem":4578,
    "gn:feature_class":"P",
    "gn:feature_code":"PPL",
    "gn:name":"Quiulacocha",
    "gn:population":0,
    "gn:timezone":"America/Lima",
    "iso:country":"PE",
    "wof:name":"Quiulacocha",
    "wof:placetype":"locality"
},
  "geometry": {"coordinates":[-76.43661999999998,-11.31518],"type":"Point"}
}