{
  "type": "Feature",
  "properties": {
    "gn:admin1_code":"12.0",
    "gn:admin2_code":"1201.0",
    "gn:asciiname":"Chuquipirhua",
    "gn:country_code":"PE",
    "gn:dem":2332,
    "gn:feature_class":"P",
    "gn:feature_code":"PPL",
    "gn:name":"Chuquipirhua",
    "gn:population":0,
    "gn:timezone":"America/Lima",
    "iso:country":"PE",
    "wof:name":"Chuquipirhua",
    "wof:placetype":"locality"
},
  "geometry": {"coordinates":[-74.87403,-12.01044],"type":"Point"}
}