{
  "type": "Feature",
  "properties": {
    "gn:admin1_code":"10.0",
    "gn:admin2_code":"1010.0",
    "gn:admin3_code":"101005.0",
    "gn:asciiname":"Marcuyoc",
    "gn:country_code":"PE",
    "gn:dem":3521,
    "gn:feature_class":"P",
    "gn:feature_code":"PPL",
    "gn:name":"Marcuyoc",
    "gn:population":0,
    "gn:timezone":"America/Lima",
    "iso:country":"PE",
    "wof:name":"Marcuyoc",
    "wof:placetype":"locality"
},
  "geometry": {"coordinates":[-76.64775999999998,-9.9356],"type":"Point"}
}