{
  "type": "Feature",
  "properties": {
    "gn:admin1_code":"04",
    "gn:admin2_code":"405.0",
    "gn:admin3_code":"40519.0",
    "gn:asciiname":"Cruce Chalhuanca",
    "gn:country_code":"PE",
    "gn:dem":4309,
    "gn:feature_class":"P",
    "gn:feature_code":"PPL",
    "gn:name":"Cruce Chalhuanca",
    "gn:population":0,
    "gn:timezone":"America/Lima",
    "iso:country":"PE",
    "wof:name":"Cruce Chalhuanca",
    "wof:placetype":"locality"
},
  "geometry": {"coordinates":[-71.38243,-15.78515],"type":"Point"}
}