{
  "type": "Feature",
  "properties": {
    "gn:admin1_code":"9.0",
    "gn:admin2_code":"907.0",
    "gn:admin3_code":"90709.0",
    "gn:asciiname":"Fundo Huaychao",
    "gn:country_code":"PE",
    "gn:dem":2741,
    "gn:feature_class":"P",
    "gn:feature_code":"PPL",
    "gn:name":"Fundo Huaychao",
    "gn:population":0,
    "gn:timezone":"America/Lima",
    "iso:country":"PE",
    "wof:name":"Fundo Huaychao",
    "wof:placetype":"locality"
},
  "geometry": {"coordinates":[-74.92108,-12.23291],"type":"Point"}
}