{
  "type": "Feature",
  "properties": {
    "gn:admin1_code":"21",
    "gn:admin2_code":"2101.0",
    "gn:admin3_code":"210112.0",
    "gn:asciiname":"Pallalla",
    "gn:country_code":"PE",
    "gn:dem":3853,
    "gn:feature_class":"P",
    "gn:feature_code":"PPL",
    "gn:name":"Pallalla",
    "gn:population":0,
    "gn:timezone":"America/Lima",
    "iso:country":"PE",
    "wof:name":"Pallalla",
    "wof:placetype":"locality"
},
  "geometry": {"coordinates":[-69.77603000000001,-15.93672],"type":"Point"}
}