{
  "type": "Feature",
  "properties": {
    "gn:admin1_code":"2.0",
    "gn:admin2_code":"210.0",
    "gn:admin3_code":"21010.0",
    "gn:asciiname":"Garuhuagaga",
    "gn:country_code":"PE",
    "gn:dem":3751,
    "gn:feature_class":"P",
    "gn:feature_code":"PPL",
    "gn:name":"Garuhuagaga",
    "gn:population":0,
    "gn:timezone":"America/Lima",
    "iso:country":"PE",
    "wof:name":"Garuhuagaga",
    "wof:placetype":"locality"
},
  "geometry": {"coordinates":[-76.89482,-9.14584],"type":"Point"}
}