{
  "type": "Feature",
  "properties": {
    "gn:admin1_code":"18",
    "gn:admin2_code":"1801.0",
    "gn:admin3_code":"180105.0",
    "gn:asciiname":"Muilaque",
    "gn:country_code":"PE",
    "gn:dem":3174,
    "gn:feature_class":"P",
    "gn:feature_code":"PPL",
    "gn:name":"Muilaque",
    "gn:population":0,
    "gn:timezone":"America/Lima",
    "iso:country":"PE",
    "wof:name":"Muilaque",
    "wof:placetype":"locality"
},
  "geometry": {"coordinates":[-70.71075999999999,-16.67579],"type":"Point"}
}