{
  "type": "Feature",
  "properties": {
    "gn:admin1_code":"2.0",
    "gn:admin2_code":"210.0",
    "gn:admin3_code":"21011.0",
    "gn:asciiname":"Santa Rosa de Tingo",
    "gn:country_code":"PE",
    "gn:dem":3537,
    "gn:feature_class":"P",
    "gn:feature_code":"PPL",
    "gn:name":"Santa Rosa de Tingo",
    "gn:population":0,
    "gn:timezone":"America/Lima",
    "iso:country":"PE",
    "wof:name":"Santa Rosa de Tingo",
    "wof:placetype":"locality"
},
  "geometry": {"coordinates":[-76.98636999999999,-9.35784],"type":"Point"}
}