{
  "type": "Feature",
  "properties": {
    "gn:admin1_code":"15",
    "gn:admin2_code":"1507.0",
    "gn:admin3_code":"150722.0",
    "gn:asciiname":"Choccna",
    "gn:country_code":"PE",
    "gn:dem":3937,
    "gn:feature_class":"P",
    "gn:feature_code":"PPL",
    "gn:name":"Choccna",
    "gn:population":0,
    "gn:timezone":"America/Lima",
    "iso:country":"PE",
    "wof:name":"Choccna",
    "wof:placetype":"locality"
},
  "geometry": {"coordinates":[-76.24167,-11.78028],"type":"Point"}
}