{
  "type": "Feature",
  "properties": {
    "gn:admin1_code":"02",
    "gn:admin2_code":"218.0",
    "gn:admin3_code":"21801.0",
    "gn:asciiname":"La Rinconada",
    "gn:country_code":"PE",
    "gn:dem":47,
    "gn:feature_class":"P",
    "gn:feature_code":"PPL",
    "gn:name":"La Rinconada",
    "gn:population":0,
    "gn:timezone":"America/Lima",
    "iso:country":"PE",
    "name:ara_x_preferred":[
        "\u0644\u0627 \u0631\u064a\u0646\u0643\u0648\u0646\u0627\u062f\u0627"
    ],
    "name:arg_x_preferred":[
        "La Rinconada"
    ],
    "name:ast_x_preferred":[
        "La Rinconada"
    ],
    "name:ceb_x_preferred":[
        "La Rinconada"
    ],
    "name:epo_x_preferred":[
        "La Rinconada"
    ],
    "name:eus_x_preferred":[
        "La Rinconada"
    ],
    "name:fra_x_preferred":[
        "La Rinconada"
    ],
    "name:glg_x_preferred":[
        "La Rinconada"
    ],
    "name:hye_x_preferred":[
        "\u053c\u0561 \u054c\u056b\u0576\u056f\u0578\u0576\u0561\u0564\u0561"
    ],
    "name:ind_x_preferred":[
        "La Rinconada"
    ],
    "name:ita_x_preferred":[
        "La Rinconada"
    ],
    "name:kaz_x_preferred":[
        "\u041b\u0430-\u0420\u0438\u043d\u043a\u043e\u043d\u0430\u0434\u0430"
    ],
    "name:mlg_x_preferred":[
        "La Rinconada"
    ],
    "name:msa_x_preferred":[
        "La Rinconada"
    ],
    "name:nld_x_preferred":[
        "La Rinconada"
    ],
    "name:oci_x_preferred":[
        "La Rinconada"
    ],
    "name:pol_x_preferred":[
        "La Rinconada"
    ],
    "name:por_x_preferred":[
        "La Rinconada"
    ],
    "name:ron_x_preferred":[
        "La Rinconada"
    ],
    "name:rus_x_preferred":[
        "\u041b\u0430-\u0420\u0438\u043d\u043a\u043e\u043d\u0430\u0434\u0430"
    ],
    "name:sco_x_preferred":[
        "La Rinconada"
    ],
    "name:spa_x_preferred":[
        "La Rinconada"
    ],
    "name:srp_x_preferred":[
        "\u041b\u0430 \u0420\u0438\u043d\u043a\u043e\u043d\u0430\u0434\u0430"
    ],
    "name:tur_x_preferred":[
        "La Rinconada"
    ],
    "name:ukr_x_preferred":[
        "\u041b\u0430-\u0420\u0456\u043d\u043a\u043e\u043d\u0430\u0434\u0430"
    ],
    "name:uzb_x_preferred":[
        "La Rinconada"
    ],
    "name:vie_x_preferred":[
        "La Rinconada"
    ],
    "name:war_x_preferred":[
        "La Rinconada"
    ],
    "name:zho_x_preferred":[
        "\u62c9\u6797\u79d1\u7eb3\u8fbe"
    ],
    "wof:name":"La Rinconada",
    "wof:placetype":"locality"
},
  "geometry": {"coordinates":[-78.54745,-9.03019],"type":"Point"}
}