{
  "type": "Feature",
  "properties": {
    "gn:admin1_code":"03",
    "gn:admin2_code":"305.0",
    "gn:admin3_code":"30503.0",
    "gn:asciiname":"Cielo Orco",
    "gn:country_code":"PE",
    "gn:dem":3950,
    "gn:feature_class":"P",
    "gn:feature_code":"PPL",
    "gn:name":"Cielo Orco",
    "gn:population":0,
    "gn:timezone":"America/Lima",
    "iso:country":"PE",
    "wof:name":"Cielo Orco",
    "wof:placetype":"locality"
},
  "geometry": {"coordinates":[-72.43333,-13.88333],"type":"Point"}
}