{
  "type": "Feature",
  "properties": {
    "gn:country":"PE",
    "gn:fcode":"PPLA3",
    "gn:pop":8799,
    "iso:country":"PE",
    "name:unk_x_variant":[
        "Cocahacra"
    ],
    "qs:name":"Cocachacra",
    "qs:photos_9r":0,
    "qs:photos_sr":0,
    "qs:pop_sr":"5",
    "wd:wordcount":51,
    "wof:name":"Cocachacra",
    "wof:placetype":"locality",
    "wof:population":8799
},
  "geometry": {"coordinates":[-71.75749999999999,-17.08833],"type":"Point"}
}