{
  "type": "Feature",
  "properties": {
    "gn:country":"PE",
    "gn:fcode":"PPLA3",
    "gn:population":8799,
    "iso:country":"PE",
    "name:kat_x_preferred":[
        "\u10e1\u10d0\u10dc\u10e2\u10d0-\u10d9\u10e0\u10e3\u10e1-\u10d3\u10d4-\u10d9\u10dd\u10d9\u10d0\u10e9\u10d0\u10e0\u10d9\u10d8\u10e1 \u10e0\u10d0\u10d8\u10dd\u10dc\u10d8"
    ],
    "name:que_x_preferred":[
        "Kukachakra distritu"
    ],
    "name:und_x_variant":[
        "Cocahacra"
    ],
    "name:zho_x_preferred":[
        "\u8056\u514b\u9b6f\u65af\u5fb7\u79d1\u5361\u67e5\u514b\u62c9\u5340"
    ],
    "qs:name":"Cocachacra",
    "qs:photos_9r":0,
    "qs:photos_sr":0,
    "qs:pop_sr":"5",
    "wd:wordcount":51,
    "wof:name":"Cocachacra",
    "wof:placetype":"locality",
    "wof:population":8799
},
  "geometry": {"coordinates":[-71.75749999999999,-17.08833],"type":"Point"}
}