{
  "type": "Feature",
  "properties": {
    "gn:admin1_code":"21",
    "gn:admin2_code":"2103.0",
    "gn:asciiname":"Chimboya",
    "gn:country_code":"PE",
    "gn:dem":4753,
    "gn:feature_class":"P",
    "gn:feature_code":"PPL",
    "gn:name":"Chimboya",
    "gn:population":0,
    "gn:timezone":"America/Lima",
    "iso:country":"PE",
    "name:nld_x_preferred":[
        "Chimboya"
    ],
    "name:que_x_preferred":[
        "Chimpulla"
    ],
    "name:spa_x_preferred":[
        "Chimboya"
    ],
    "name:zho_x_preferred":[
        "\u6b3d\u666e\u5229\u4e9e\u5c71"
    ],
    "wof:name":"Chimboya",
    "wof:placetype":"locality"
},
  "geometry": {"coordinates":[-70.76476,-13.86287],"type":"Point"}
}