{
  "type": "Feature",
  "properties": {
    "gn:admin1_code":"18",
    "gn:admin2_code":"1802.0",
    "gn:admin3_code":"180210.0",
    "gn:asciiname":"Exchaji",
    "gn:country_code":"PE",
    "gn:dem":3472,
    "gn:feature_class":"P",
    "gn:feature_code":"PPL",
    "gn:name":"Exchaji",
    "gn:population":0,
    "gn:timezone":"America/Lima",
    "iso:country":"PE",
    "wof:name":"Exchaji",
    "wof:placetype":"locality"
},
  "geometry": {"coordinates":[-70.72655999999998,-16.22929],"type":"Point"}
}