{
  "type": "Feature",
  "properties": {
    "gn:admin1_code":"09",
    "gn:admin2_code":"904.0",
    "gn:admin3_code":"90412.0",
    "gn:asciiname":"Ucrococha",
    "gn:country_code":"PE",
    "gn:dem":3538,
    "gn:feature_class":"P",
    "gn:feature_code":"PPL",
    "gn:name":"Ucrococha",
    "gn:population":0,
    "gn:timezone":"America/Lima",
    "iso:country":"PE",
    "wof:name":"Ucrococha",
    "wof:placetype":"locality"
},
  "geometry": {"coordinates":[-75.62233000000001,-13.13768],"type":"Point"}
}