{
  "type": "Feature",
  "properties": {
    "gn:admin1_code":"10.0",
    "gn:admin2_code":"1011.0",
    "gn:admin3_code":"101105.0",
    "gn:asciiname":"Mesapata",
    "gn:country_code":"PE",
    "gn:dem":3477,
    "gn:feature_class":"P",
    "gn:feature_code":"PPL",
    "gn:name":"Mesapata",
    "gn:population":0,
    "gn:timezone":"America/Lima",
    "iso:country":"PE",
    "wof:name":"Mesapata",
    "wof:placetype":"locality"
},
  "geometry": {"coordinates":[-76.4623,-9.8825],"type":"Point"}
}