{
  "type": "Feature",
  "properties": {
    "gn:admin1_code":"25",
    "gn:admin2_code":"2502.0",
    "gn:asciiname":"Pajonal Janteni",
    "gn:country_code":"PE",
    "gn:dem":1374,
    "gn:feature_class":"P",
    "gn:feature_code":"PPL",
    "gn:name":"Pajonal Janteni",
    "gn:population":0,
    "gn:timezone":"America/Lima",
    "iso:country":"PE",
    "name:spa_x_preferred":[
        "Pajonal Janteni"
    ],
    "wof:name":"Pajonal Janteni",
    "wof:placetype":"locality"
},
  "geometry": {"coordinates":[-74.42416999999998,-10.80602],"type":"Point"}
}