{
  "type": "Feature",
  "properties": {
    "gn:admin1_code":"12",
    "gn:admin2_code":"1202.0",
    "gn:admin3_code":"120203.0",
    "gn:asciiname":"Otuto",
    "gn:country_code":"PE",
    "gn:dem":3390,
    "gn:feature_class":"P",
    "gn:feature_code":"PPL",
    "gn:name":"Otuto",
    "gn:population":0,
    "gn:timezone":"America/Lima",
    "iso:country":"PE",
    "wof:name":"Otuto",
    "wof:placetype":"locality"
},
  "geometry": {"coordinates":[-74.92327,-11.80474],"type":"Point"}
}