{
  "type": "Feature",
  "properties": {
    "gn:admin1_code":"08",
    "gn:admin2_code":"812.0",
    "gn:admin3_code":"81209.0",
    "gn:asciiname":"Huallatalloc",
    "gn:cc2":"PE",
    "gn:country_code":"PE",
    "gn:dem":3662,
    "gn:feature_class":"P",
    "gn:feature_code":"PPL",
    "gn:name":"Huallatalloc",
    "gn:population":0,
    "gn:timezone":"America/Lima",
    "iso:country":"PE",
    "name:und_x_variant":[
        "Hualla-Hualla",
        "Huallavoe",
        "Huallatalloc"
    ],
    "wof:name":"Huallatalloc",
    "wof:placetype":"locality"
},
  "geometry": {"coordinates":[-70.95,-13.51667],"type":"Point"}
}