{
  "type": "Feature",
  "properties": {
    "gn:admin1_code":"2.0",
    "gn:admin2_code":"205.0",
    "gn:admin3_code":"20505.0",
    "gn:asciiname":"Alalac Machay",
    "gn:country_code":"PE",
    "gn:dem":4292,
    "gn:feature_class":"P",
    "gn:feature_code":"PPL",
    "gn:name":"Alalac Machay",
    "gn:population":0,
    "gn:timezone":"America/Lima",
    "iso:country":"PE",
    "wof:name":"Alalac Machay",
    "wof:placetype":"locality"
},
  "geometry": {"coordinates":[-77.28433000000003,-10.17538],"type":"Point"}
}