{
  "type": "Feature",
  "properties": {
    "gn:admin1_code":"02",
    "gn:admin2_code":"214.0",
    "gn:admin3_code":"21410.0",
    "gn:asciiname":"Santiago de Chilcas",
    "gn:country_code":"PE",
    "gn:dem":3674,
    "gn:feature_class":"P",
    "gn:feature_code":"PPL",
    "gn:name":"Santiago de Chilcas",
    "gn:population":0,
    "gn:timezone":"America/Lima",
    "iso:country":"PE",
    "wof:name":"Santiago de Chilcas",
    "wof:placetype":"locality"
},
  "geometry": {"coordinates":[-77.36587,-10.43861],"type":"Point"}
}