{
  "type": "Feature",
  "properties": {
    "gn:admin1_code":"06",
    "gn:admin2_code":"604.0",
    "gn:admin3_code":"60411.0",
    "gn:asciiname":"La Planta",
    "gn:country_code":"PE",
    "gn:dem":346,
    "gn:feature_class":"P",
    "gn:feature_code":"PPL",
    "gn:name":"La Planta",
    "gn:population":0,
    "gn:timezone":"America/Lima",
    "iso:country":"PE",
    "wof:name":"La Planta",
    "wof:placetype":"locality"
},
  "geometry": {"coordinates":[-79.2821,-6.61321],"type":"Point"}
}