{
  "type": "Feature",
  "properties": {
    "gn:admin1_code":"9.0",
    "gn:admin2_code":"903.0",
    "gn:admin3_code":"90308.0",
    "gn:asciiname":"Llihuapata",
    "gn:country_code":"PE",
    "gn:dem":4315,
    "gn:feature_class":"P",
    "gn:feature_code":"PPL",
    "gn:name":"Llihuapata",
    "gn:population":0,
    "gn:timezone":"America/Lima",
    "iso:country":"PE",
    "wof:name":"Llihuapata",
    "wof:placetype":"locality"
},
  "geometry": {"coordinates":[-74.66105999999998,-12.9354],"type":"Point"}
}