{
  "type": "Feature",
  "properties": {
    "gn:admin1_code":"14",
    "gn:admin2_code":"1402.0",
    "gn:admin3_code":"140203.0",
    "gn:asciiname":"Lajas",
    "gn:country_code":"PE",
    "gn:dem":604,
    "gn:feature_class":"P",
    "gn:feature_code":"PPL",
    "gn:name":"Lajas",
    "gn:population":0,
    "gn:timezone":"America/Lima",
    "iso:country":"PE",
    "name:ceb_x_preferred":[
        "Lajas"
    ],
    "name:fra_x_preferred":[
        "Lajas"
    ],
    "name:ita_x_preferred":[
        "Lajas"
    ],
    "name:nld_x_preferred":[
        "Lajas"
    ],
    "name:pol_x_preferred":[
        "Lajas"
    ],
    "name:swe_x_preferred":[
        "Lajas"
    ],
    "wof:name":"Lajas",
    "wof:placetype":"locality"
},
  "geometry": {"coordinates":[-79.44688000000002,-6.34851],"type":"Point"}
}