{
  "type": "Feature",
  "properties": {
    "gn:admin1_code":"8.0",
    "gn:admin2_code":"804.0",
    "gn:admin3_code":"80404.0",
    "gn:asciiname":"Collpana",
    "gn:country_code":"PE",
    "gn:dem":3614,
    "gn:feature_class":"P",
    "gn:feature_code":"PPL",
    "gn:name":"Collpana",
    "gn:population":0,
    "gn:timezone":"America/Lima",
    "iso:country":"PE",
    "wof:name":"Collpana",
    "wof:placetype":"locality"
},
  "geometry": {"coordinates":[-72.01611,-13.13778],"type":"Point"}
}