{
  "type": "Feature",
  "properties": {
    "gn:admin1_code":"06",
    "gn:admin2_code":"610.0",
    "gn:admin3_code":"61007.0",
    "gn:asciiname":"Kamish",
    "gn:country_code":"PE",
    "gn:dem":3900,
    "gn:feature_class":"P",
    "gn:feature_code":"PPL",
    "gn:name":"Kamish",
    "gn:population":0,
    "gn:timezone":"America/Lima",
    "iso:country":"PE",
    "wof:name":"Kamish",
    "wof:placetype":"locality"
},
  "geometry": {"coordinates":[-77.98333000000002,-7.25],"type":"Point"}
}