{
  "type": "Feature",
  "properties": {
    "gn:admin1_code":"15",
    "gn:admin2_code":"1501.0",
    "gn:admin3_code":"150103.0",
    "gn:asciiname":"Pariache",
    "gn:cc2":"PE",
    "gn:country_code":"PE",
    "gn:dem":504,
    "gn:feature_class":"P",
    "gn:feature_code":"PPL",
    "gn:name":"Pariache",
    "gn:population":0,
    "gn:timezone":"America/Lima",
    "iso:country":"PE",
    "name:und_x_variant":[
        "Pariache Hacienda",
        "Pariache"
    ],
    "wof:name":"Pariache",
    "wof:placetype":"locality"
},
  "geometry": {"coordinates":[-76.84999999999999,-12.01667],"type":"Point"}
}