{
  "type": "Feature",
  "properties": {
    "gn:admin1_code":"8",
    "gn:admin2_code":"808.0",
    "gn:admin3_code":"80801.0",
    "gn:asciiname":"Chimapaccata",
    "gn:country_code":"PE",
    "gn:dem":4242,
    "gn:feature_class":"P",
    "gn:feature_code":"PPL",
    "gn:name":"Chimapaccata",
    "gn:population":0,
    "gn:timezone":"America/Lima",
    "iso:country":"PE",
    "wof:name":"Chimapaccata",
    "wof:placetype":"locality"
},
  "geometry": {"coordinates":[-71.23999999999999,-15.01556],"type":"Point"}
}