{
  "type": "Feature",
  "properties": {
    "gn:admin1_code":"12.0",
    "gn:admin2_code":"1203.0",
    "gn:admin3_code":"120302.0",
    "gn:asciiname":"Alto Pichanaki",
    "gn:country_code":"PE",
    "gn:dem":895,
    "gn:feature_class":"P",
    "gn:feature_code":"PPL",
    "gn:name":"Alto Pichanaki",
    "gn:population":0,
    "gn:timezone":"America/Lima",
    "iso:country":"PE",
    "name:spa_x_preferred":[
        "Alto Pichanaki"
    ],
    "wof:name":"Alto Pichanaki",
    "wof:placetype":"locality"
},
  "geometry": {"coordinates":[-74.97326,-10.98164],"type":"Point"}
}