{
  "type": "Feature",
  "properties": {
    "gn:admin1_code":"06",
    "gn:admin2_code":"603.0",
    "gn:admin3_code":"60312.0",
    "gn:asciiname":"Hacienda Pallar",
    "gn:country_code":"PE",
    "gn:dem":3027,
    "gn:feature_class":"P",
    "gn:feature_code":"PPL",
    "gn:name":"Hacienda Pallar",
    "gn:population":0,
    "gn:timezone":"America/Lima",
    "iso:country":"PE",
    "wof:name":"Hacienda Pallar",
    "wof:placetype":"locality"
},
  "geometry": {"coordinates":[-78.29338,-6.72816],"type":"Point"}
}