{
  "type": "Feature",
  "properties": {
    "gn:admin1_code":"12",
    "gn:admin2_code":"1207.0",
    "gn:admin3_code":"120701.0",
    "gn:asciiname":"Palcapampa",
    "gn:country_code":"PE",
    "gn:dem":3834,
    "gn:feature_class":"P",
    "gn:feature_code":"PPL",
    "gn:name":"Palcapampa",
    "gn:population":0,
    "gn:timezone":"America/Lima",
    "iso:country":"PE",
    "wof:name":"Palcapampa",
    "wof:placetype":"locality"
},
  "geometry": {"coordinates":[-75.80239,-11.47912],"type":"Point"}
}