{
  "type": "Feature",
  "properties": {
    "gn:admin1_code":"19",
    "gn:admin2_code":"1903.0",
    "gn:admin3_code":"190306.0",
    "gn:asciiname":"Puerto Victoria",
    "gn:country_code":"PE",
    "gn:dem":225,
    "gn:feature_class":"P",
    "gn:feature_code":"PPL",
    "gn:name":"Puerto Victoria",
    "gn:population":0,
    "gn:timezone":"America/Lima",
    "iso:country":"PE",
    "wof:name":"Puerto Victoria",
    "wof:placetype":"locality"
},
  "geometry": {"coordinates":[-74.93377,-9.87663],"type":"Point"}
}