{
  "type": "Feature",
  "properties": {
    "gn:admin1_code":"06",
    "gn:admin2_code":"604.0",
    "gn:admin3_code":"60412.0",
    "gn:asciiname":"Chonta",
    "gn:country_code":"PE",
    "gn:dem":1291,
    "gn:feature_class":"P",
    "gn:feature_code":"PPL",
    "gn:name":"Chonta",
    "gn:population":0,
    "gn:timezone":"America/Lima",
    "iso:country":"PE",
    "wof:name":"Chonta",
    "wof:placetype":"locality"
},
  "geometry": {"coordinates":[-79.35467,-6.36964],"type":"Point"}
}