{
  "type": "Feature",
  "properties": {
    "gn:admin1_code":"11",
    "gn:admin2_code":"1103.0",
    "gn:admin3_code":"110303.0",
    "gn:asciiname":"Hacienda San Pablo",
    "gn:country_code":"PE",
    "gn:dem":417,
    "gn:feature_class":"P",
    "gn:feature_code":"PPL",
    "gn:name":"Hacienda San Pablo",
    "gn:population":0,
    "gn:timezone":"America/Lima",
    "iso:country":"PE",
    "name:und_x_variant":[
        "San Pablo Hacienda",
        "San Pablo",
        "Hacienda San Pablo"
    ],
    "wof:name":"Hacienda San Pablo",
    "wof:placetype":"locality"
},
  "geometry": {"coordinates":[-75.08077,-14.65549],"type":"Point"}
}