{
  "type": "Feature",
  "properties": {
    "gn:admin1_code":"14",
    "gn:admin2_code":"1402.0",
    "gn:admin3_code":"140203.0",
    "gn:asciiname":"Tamboni",
    "gn:country_code":"PE",
    "gn:dem":1340,
    "gn:feature_class":"P",
    "gn:feature_code":"PPL",
    "gn:name":"Tamboni",
    "gn:population":0,
    "gn:timezone":"America/Lima",
    "iso:country":"PE",
    "wof:name":"Tamboni",
    "wof:placetype":"locality"
},
  "geometry": {"coordinates":[-79.44138000000002,-6.28819],"type":"Point"}
}