{
  "type": "Feature",
  "properties": {
    "gn:admin1_code":"09",
    "gn:admin2_code":"901.0",
    "gn:admin3_code":"90102.0",
    "gn:asciiname":"San Antonio",
    "gn:country_code":"PE",
    "gn:dem":3994,
    "gn:feature_class":"P",
    "gn:feature_code":"PPL",
    "gn:name":"San Antonio",
    "gn:population":0,
    "gn:timezone":"America/Lima",
    "iso:country":"PE",
    "wof:name":"San Antonio",
    "wof:placetype":"locality"
},
  "geometry": {"coordinates":[-75.24446999999998,-12.6887],"type":"Point"}
}