{
  "type": "Feature",
  "properties": {
    "gn:admin1_code":"20",
    "gn:admin2_code":"2001.0",
    "gn:admin3_code":"200104.0",
    "gn:asciiname":"San Silvestre",
    "gn:country_code":"PE",
    "gn:dem":45,
    "gn:feature_class":"P",
    "gn:feature_code":"PPL",
    "gn:name":"San Silvestre",
    "gn:population":0,
    "gn:timezone":"America/Lima",
    "iso:country":"PE",
    "wof:name":"San Silvestre",
    "wof:placetype":"locality"
},
  "geometry": {"coordinates":[-80.60401,-5.05446],"type":"Point"}
}