{
  "type": "Feature",
  "properties": {
    "gn:admin1_code":"10.0",
    "gn:admin2_code":"1003.0",
    "gn:admin3_code":"100307.0",
    "gn:asciiname":"Rupapampa",
    "gn:country_code":"PE",
    "gn:dem":3931,
    "gn:feature_class":"P",
    "gn:feature_code":"PPL",
    "gn:name":"Rupapampa",
    "gn:population":0,
    "gn:timezone":"America/Lima",
    "iso:country":"PE",
    "wof:name":"Rupapampa",
    "wof:placetype":"locality"
},
  "geometry": {"coordinates":[-76.62234000000002,-9.65661],"type":"Point"}
}