{
  "type": "Feature",
  "properties": {
    "gn:admin1_code":"12",
    "gn:admin2_code":"1202.0",
    "gn:admin3_code":"120206.0",
    "gn:asciiname":"Limite",
    "gn:country_code":"PE",
    "gn:dem":3975,
    "gn:feature_class":"P",
    "gn:feature_code":"PPL",
    "gn:name":"Limite",
    "gn:population":0,
    "gn:timezone":"America/Lima",
    "iso:country":"PE",
    "wof:name":"Limite",
    "wof:placetype":"locality"
},
  "geometry": {"coordinates":[-74.91511,-11.65819],"type":"Point"}
}