{
  "type": "Feature",
  "properties": {
    "gn:admin1_code":"15",
    "gn:admin2_code":"1505.0",
    "gn:admin3_code":"150505.0",
    "gn:asciiname":"Capto",
    "gn:country_code":"PE",
    "gn:dem":614,
    "gn:feature_class":"P",
    "gn:feature_code":"PPLL",
    "gn:name":"Capto",
    "gn:population":0,
    "gn:timezone":"America/Lima",
    "iso:country":"PE",
    "name:spa_x_preferred":[
        "Capto"
    ],
    "wof:name":"Capto",
    "wof:placetype":"locality"
},
  "geometry": {"coordinates":[-76.56075,-12.39856],"type":"Point"}
}