{
  "type": "Feature",
  "properties": {
    "gn:admin1_code":"25",
    "gn:admin2_code":"2501.0",
    "gn:admin3_code":"250103.0",
    "gn:asciiname":"Venecia",
    "gn:country_code":"PE",
    "gn:dem":179,
    "gn:feature_class":"P",
    "gn:feature_code":"PPL",
    "gn:name":"Venecia",
    "gn:population":0,
    "gn:timezone":"America/Lima",
    "iso:country":"PE",
    "wof:name":"Venecia",
    "wof:placetype":"locality"
},
  "geometry": {"coordinates":[-74.51666999999998,-9.13333],"type":"Point"}
}