{
  "type": "Feature",
  "properties": {
    "gn:admin1_code":"14",
    "gn:admin2_code":"1403.0",
    "gn:admin3_code":"140308.0",
    "gn:asciiname":"San Antonio",
    "gn:cc2":"PE",
    "gn:country_code":"PE",
    "gn:dem":71,
    "gn:feature_class":"P",
    "gn:feature_code":"PPLL",
    "gn:name":"San Antonio",
    "gn:population":0,
    "gn:timezone":"America/Lima",
    "iso:country":"PE",
    "wof:name":"San Antonio",
    "wof:placetype":"locality"
},
  "geometry": {"coordinates":[-80.01666999999998,-6.02778],"type":"Point"}
}