{
  "type": "Feature",
  "properties": {
    "gn:admin1_code":"15",
    "gn:admin2_code":"1510.0",
    "gn:admin3_code":"151021.0",
    "gn:asciiname":"Achucura",
    "gn:country_code":"PE",
    "gn:dem":3921,
    "gn:feature_class":"P",
    "gn:feature_code":"PPL",
    "gn:name":"Achucura",
    "gn:population":0,
    "gn:timezone":"America/Lima",
    "iso:country":"PE",
    "wof:name":"Achucura",
    "wof:placetype":"locality"
},
  "geometry": {"coordinates":[-75.85583000000003,-12.28083],"type":"Point"}
}