{
  "type": "Feature",
  "properties": {
    "gn:admin1_code":"3",
    "gn:admin2_code":"302.0",
    "gn:admin3_code":"30205.0",
    "gn:asciiname":"Pallasona",
    "gn:country_code":"PE",
    "gn:dem":3725,
    "gn:feature_class":"P",
    "gn:feature_code":"PPL",
    "gn:name":"Pallasona",
    "gn:population":0,
    "gn:timezone":"America/Lima",
    "iso:country":"PE",
    "wof:name":"Pallasona",
    "wof:placetype":"locality"
},
  "geometry": {"coordinates":[-73.56716999999998,-13.79565],"type":"Point"}
}