{
  "type": "Feature",
  "properties": {
    "gn:admin1_code":"09",
    "gn:admin2_code":"906.0",
    "gn:admin3_code":"90607.0",
    "gn:asciiname":"Llillinta",
    "gn:country_code":"PE",
    "gn:dem":4481,
    "gn:feature_class":"P",
    "gn:feature_code":"PPL",
    "gn:name":"Llillinta",
    "gn:population":0,
    "gn:timezone":"America/Lima",
    "iso:country":"PE",
    "wof:name":"Llillinta",
    "wof:placetype":"locality"
},
  "geometry": {"coordinates":[-74.75605,-13.21087],"type":"Point"}
}