{
  "type": "Feature",
  "properties": {
    "gn:admin1_code":"21",
    "gn:admin2_code":"2107.0",
    "gn:admin3_code":"210709.0",
    "gn:asciiname":"Lauramicaya Pata",
    "gn:country_code":"PE",
    "gn:dem":4222,
    "gn:feature_class":"P",
    "gn:feature_code":"PPL",
    "gn:name":"Lauramicaya Pata",
    "gn:population":0,
    "gn:timezone":"America/Lima",
    "iso:country":"PE",
    "wof:name":"Lauramicaya Pata",
    "wof:placetype":"locality"
},
  "geometry": {"coordinates":[-70.51006,-15.58941],"type":"Point"}
}