{
  "type": "Feature",
  "properties": {
    "gn:admin1_code":"3.0",
    "gn:admin2_code":"305.0",
    "gn:admin3_code":"30503.0",
    "gn:asciiname":"Huacamis",
    "gn:country_code":"PE",
    "gn:dem":2864,
    "gn:feature_class":"P",
    "gn:feature_code":"PPL",
    "gn:name":"Huacamis",
    "gn:population":0,
    "gn:timezone":"America/Lima",
    "iso:country":"PE",
    "wof:name":"Huacamis",
    "wof:placetype":"locality"
},
  "geometry": {"coordinates":[-72.45806,-13.81889],"type":"Point"}
}