{
  "type": "Feature",
  "properties": {
    "gn:admin1_code":"3",
    "gn:admin2_code":"302.0",
    "gn:admin3_code":"30217.0",
    "gn:asciiname":"Jatun Pucro",
    "gn:country_code":"PE",
    "gn:dem":3596,
    "gn:feature_class":"P",
    "gn:feature_code":"PPL",
    "gn:name":"Jatun Pucro",
    "gn:population":0,
    "gn:timezone":"America/Lima",
    "iso:country":"PE",
    "wof:name":"Jatun Pucro",
    "wof:placetype":"locality"
},
  "geometry": {"coordinates":[-73.515,-14.05667],"type":"Point"}
}