{
  "type": "Feature",
  "properties": {
    "gn:admin1_code":"04",
    "gn:admin2_code":"402.0",
    "gn:admin3_code":"40206.0",
    "gn:asciiname":"Punta Negra",
    "gn:country_code":"PE",
    "gn:dem":40,
    "gn:feature_class":"P",
    "gn:feature_code":"PPL",
    "gn:name":"Punta Negra",
    "gn:population":0,
    "gn:timezone":"America/Lima",
    "iso:country":"PE",
    "name:nds_x_preferred":[
        "Punta Negra"
    ],
    "name:srp_x_preferred":[
        "\u041f\u0443\u043d\u0442\u0430 \u041d\u0435\u0433\u0440\u0430"
    ],
    "name:und_x_variant":[
        "Hacienda Punta Negra",
        "Punta Negra"
    ],
    "wof:name":"Punta Negra",
    "wof:placetype":"locality"
},
  "geometry": {"coordinates":[-73.1204,-16.38652],"type":"Point"}
}