{
  "type": "Feature",
  "properties": {
    "gn:admin1_code":"1.0",
    "gn:admin2_code":"105.0",
    "gn:admin3_code":"10507.0",
    "gn:asciiname":"Choctamal",
    "gn:country_code":"PE",
    "gn:dem":2720,
    "gn:feature_class":"P",
    "gn:feature_code":"PPL",
    "gn:name":"Choctamal",
    "gn:population":0,
    "gn:timezone":"America/Lima",
    "iso:country":"PE",
    "wof:name":"Choctamal",
    "wof:placetype":"locality"
},
  "geometry": {"coordinates":[-77.98599,-6.39458],"type":"Point"}
}