{
  "type": "Feature",
  "properties": {
    "gn:admin1_code":"5.0",
    "gn:admin2_code":"505.0",
    "gn:admin3_code":"50502.0",
    "gn:asciiname":"Liberta",
    "gn:country_code":"PE",
    "gn:dem":890,
    "gn:feature_class":"P",
    "gn:feature_code":"PPL",
    "gn:name":"Liberta",
    "gn:population":0,
    "gn:timezone":"America/Lima",
    "iso:country":"PE",
    "name:jpn_x_preferred":[
        "\u30ea\u30d9\u30eb\u30bf"
    ],
    "wof:name":"Liberta",
    "wof:placetype":"locality"
},
  "geometry": {"coordinates":[-73.53161,-12.96113],"type":"Point"}
}