{
  "type": "Feature",
  "properties": {
    "gn:admin1_code":"9.0",
    "gn:admin2_code":"903.0",
    "gn:admin3_code":"90302.0",
    "gn:asciiname":"Rayusca",
    "gn:country_code":"PE",
    "gn:dem":3737,
    "gn:feature_class":"P",
    "gn:feature_code":"PPL",
    "gn:name":"Rayusca",
    "gn:population":0,
    "gn:timezone":"America/Lima",
    "iso:country":"PE",
    "wof:name":"Rayusca",
    "wof:placetype":"locality"
},
  "geometry": {"coordinates":[-74.7058,-12.85474],"type":"Point"}
}