{
  "type": "Feature",
  "properties": {
    "gn:admin1_code":"10.0",
    "gn:admin2_code":"1007.0",
    "gn:admin3_code":"100702.0",
    "gn:asciiname":"Huamuco",
    "gn:country_code":"PE",
    "gn:dem":529,
    "gn:feature_class":"P",
    "gn:feature_code":"PPL",
    "gn:name":"Huamuco",
    "gn:population":0,
    "gn:timezone":"America/Lima",
    "iso:country":"PE",
    "wof:name":"Huamuco",
    "wof:placetype":"locality"
},
  "geometry": {"coordinates":[-76.27534,-8.66288],"type":"Point"}
}