{
  "type": "Feature",
  "properties": {
    "gn:admin1_code":"5.0",
    "gn:admin2_code":"506.0",
    "gn:admin3_code":"50609.0",
    "gn:asciiname":"Pamparenda",
    "gn:country_code":"PE",
    "gn:dem":3100,
    "gn:feature_class":"P",
    "gn:feature_code":"PPL",
    "gn:name":"Pamparenda",
    "gn:population":0,
    "gn:timezone":"America/Lima",
    "iso:country":"PE",
    "name:spa_x_preferred":[
        "Pamparenda"
    ],
    "wof:name":"Pamparenda",
    "wof:placetype":"locality"
},
  "geometry": {"coordinates":[-74.68743000000001,-14.69351],"type":"Point"}
}