{
  "type": "Feature",
  "properties": {
    "gn:admin1_code":"21.0",
    "gn:admin2_code":"2112.0",
    "gn:asciiname":"Mina Betaspata",
    "gn:country_code":"PE",
    "gn:dem":2677,
    "gn:feature_class":"P",
    "gn:feature_code":"PPL",
    "gn:name":"Mina Betaspata",
    "gn:population":0,
    "gn:timezone":"America/Lima",
    "iso:country":"PE",
    "name:spa_x_preferred":[
        "Mina Betaspata"
    ],
    "wof:name":"Mina Betaspata",
    "wof:placetype":"locality"
},
  "geometry": {"coordinates":[-69.11496,-14.42851],"type":"Point"}
}