{
  "type": "Feature",
  "properties": {
    "gn:admin1_code":"13",
    "gn:admin2_code":"1306.0",
    "gn:admin3_code":"130601.0",
    "gn:asciiname":"Sanchique",
    "gn:country_code":"PE",
    "gn:dem":2945,
    "gn:feature_class":"P",
    "gn:feature_code":"PPL",
    "gn:name":"Sanchique",
    "gn:population":0,
    "gn:timezone":"America/Lima",
    "iso:country":"PE",
    "wof:name":"Sanchique",
    "wof:placetype":"locality"
},
  "geometry": {"coordinates":[-78.61366,-7.9288],"type":"Point"}
}