{
  "type": "Feature",
  "properties": {
    "gn:admin1_code":"19.0",
    "gn:admin2_code":"1902.0",
    "gn:admin3_code":"190205.0",
    "gn:asciiname":"Sharan",
    "gn:country_code":"PE",
    "gn:dem":3949,
    "gn:feature_class":"P",
    "gn:feature_code":"PPL",
    "gn:name":"Sharan",
    "gn:population":0,
    "gn:timezone":"America/Lima",
    "iso:country":"PE",
    "wof:name":"Sharan",
    "wof:placetype":"locality"
},
  "geometry": {"coordinates":[-76.51971999999998,-10.41889],"type":"Point"}
}