{
  "type": "Feature",
  "properties": {
    "gn:admin1_code":"18",
    "gn:admin2_code":"1801.0",
    "gn:admin3_code":"180103.0",
    "gn:asciiname":"Alito",
    "gn:country_code":"PE",
    "gn:dem":2630,
    "gn:feature_class":"P",
    "gn:feature_code":"PPL",
    "gn:name":"Alito",
    "gn:population":0,
    "gn:timezone":"America/Lima",
    "iso:country":"PE",
    "wof:name":"Alito",
    "wof:placetype":"locality"
},
  "geometry": {"coordinates":[-70.71826,-16.77136],"type":"Point"}
}