{
  "type": "Feature",
  "properties": {
    "gn:admin1_code":"5.0",
    "gn:admin2_code":"504.0",
    "gn:admin3_code":"50406.0",
    "gn:asciiname":"Ajopucro",
    "gn:country_code":"PE",
    "gn:dem":4127,
    "gn:feature_class":"P",
    "gn:feature_code":"PPL",
    "gn:name":"Ajopucro",
    "gn:population":0,
    "gn:timezone":"America/Lima",
    "iso:country":"PE",
    "wof:name":"Ajopucro",
    "wof:placetype":"locality"
},
  "geometry": {"coordinates":[-74.23832,-12.71023],"type":"Point"}
}