{
  "type": "Feature",
  "properties": {
    "gn:admin1_code":"12.0",
    "gn:admin2_code":"1204.0",
    "gn:admin3_code":"120427.0",
    "gn:asciiname":"Banadero",
    "gn:country_code":"PE",
    "gn:dem":4522,
    "gn:feature_class":"P",
    "gn:feature_code":"PPL",
    "gn:name":"Ba\u00f1adero",
    "gn:population":0,
    "gn:timezone":"America/Lima",
    "iso:country":"PE",
    "wof:name":"Banadero",
    "wof:placetype":"locality"
},
  "geometry": {"coordinates":[-75.43868000000001,-11.64873],"type":"Point"}
}