{
  "type": "Feature",
  "properties": {
    "gn:admin1_code":"9.0",
    "gn:admin2_code":"902.0",
    "gn:admin3_code":"90208.0",
    "gn:asciiname":"Achocana",
    "gn:country_code":"PE",
    "gn:dem":4103,
    "gn:feature_class":"P",
    "gn:feature_code":"PPL",
    "gn:name":"Achocana",
    "gn:population":0,
    "gn:timezone":"America/Lima",
    "iso:country":"PE",
    "wof:name":"Achocana",
    "wof:placetype":"locality"
},
  "geometry": {"coordinates":[-74.59889,-12.73187],"type":"Point"}
}