{
  "type": "Feature",
  "properties": {
    "gn:admin1_code":"05",
    "gn:admin2_code":"504.0",
    "gn:admin3_code":"50403.0",
    "gn:asciiname":"Teneria",
    "gn:country_code":"PE",
    "gn:dem":3345,
    "gn:feature_class":"P",
    "gn:feature_code":"PPL",
    "gn:name":"Teneria",
    "gn:population":0,
    "gn:timezone":"America/Lima",
    "iso:country":"PE",
    "wof:name":"Teneria",
    "wof:placetype":"locality"
},
  "geometry": {"coordinates":[-74.16968,-12.99664],"type":"Point"}
}