{
  "type": "Feature",
  "properties": {
    "gn:admin1_code":"20",
    "gn:admin2_code":"2002.0",
    "gn:admin3_code":"200204.0",
    "gn:asciiname":"Arrendamientos",
    "gn:country_code":"PE",
    "gn:dem":3017,
    "gn:feature_class":"P",
    "gn:feature_code":"PPL",
    "gn:name":"Arrendamientos",
    "gn:population":0,
    "gn:timezone":"America/Lima",
    "iso:country":"PE",
    "wof:name":"Arrendamientos",
    "wof:placetype":"locality"
},
  "geometry": {"coordinates":[-79.89645,-4.82933],"type":"Point"}
}