{
  "type": "Feature",
  "properties": {
    "gn:admin1_code":"10.0",
    "gn:admin2_code":"1005.0",
    "gn:admin3_code":"100504.0",
    "gn:asciiname":"Saucian Pampa",
    "gn:country_code":"PE",
    "gn:dem":4228,
    "gn:feature_class":"P",
    "gn:feature_code":"PPL",
    "gn:name":"Saucian Pampa",
    "gn:population":0,
    "gn:timezone":"America/Lima",
    "iso:country":"PE",
    "wof:name":"Saucian Pampa",
    "wof:placetype":"locality"
},
  "geometry": {"coordinates":[-76.68162,-9.49],"type":"Point"}
}