{
  "type": "Feature",
  "properties": {
    "gn:admin1_code":"13",
    "gn:admin2_code":"1310.0",
    "gn:admin3_code":"131006.0",
    "gn:asciiname":"Alumbre",
    "gn:country_code":"PE",
    "gn:dem":3761,
    "gn:feature_class":"P",
    "gn:feature_code":"PPL",
    "gn:name":"Alumbre",
    "gn:population":0,
    "gn:timezone":"America/Lima",
    "iso:country":"PE",
    "wof:name":"Alumbre",
    "wof:placetype":"locality"
},
  "geometry": {"coordinates":[-78.24982,-8.1048],"type":"Point"}
}