{
  "type": "Feature",
  "properties": {
    "gn:admin1_code":"10.0",
    "gn:admin2_code":"1008.0",
    "gn:admin3_code":"100804.0",
    "gn:asciiname":"Yunca Shunto",
    "gn:country_code":"PE",
    "gn:dem":2633,
    "gn:feature_class":"P",
    "gn:feature_code":"PPL",
    "gn:name":"Yunca Shunto",
    "gn:population":0,
    "gn:timezone":"America/Lima",
    "iso:country":"PE",
    "wof:name":"Yunca Shunto",
    "wof:placetype":"locality"
},
  "geometry": {"coordinates":[-76.03774,-9.85999],"type":"Point"}
}