{
  "type": "Feature",
  "properties": {
    "gn:admin1_code":"12",
    "gn:admin2_code":"1207.0",
    "gn:admin3_code":"120708.0",
    "gn:asciiname":"Putaca",
    "gn:country_code":"PE",
    "gn:dem":4021,
    "gn:feature_class":"P",
    "gn:feature_code":"PPL",
    "gn:name":"Putaca",
    "gn:population":0,
    "gn:timezone":"America/Lima",
    "iso:country":"PE",
    "wof:name":"Putaca",
    "wof:placetype":"locality"
},
  "geometry": {"coordinates":[-75.85528000000002,-11.285],"type":"Point"}
}