{
  "type": "Feature",
  "properties": {
    "gn:country":"PE",
    "gn:fcode":"PPLA3",
    "gn:population":9197,
    "iso:country":"PE",
    "name:ara_x_preferred":[
        "\u0644\u0627\u062c\u0648\u0646\u0627"
    ],
    "name:ben_x_preferred":[
        "\u09b2\u09be\u0997\u09c1\u09a8\u09be\u09b8"
    ],
    "name:ceb_x_preferred":[
        "Lagunas"
    ],
    "name:deu_x_preferred":[
        "Lagunas"
    ],
    "name:ell_x_preferred":[
        "\u039b\u03b1\u03b3\u03bf\u03cd\u03bd\u03b1\u03c2"
    ],
    "name:eng_x_preferred":[
        "Lagunas"
    ],
    "name:fas_x_preferred":[
        "\u0644\u0627\u06af\u0648\u0646\u0627"
    ],
    "name:fra_x_preferred":[
        "Lagunas"
    ],
    "name:heb_x_preferred":[
        "\u05dc\u05d2\u05d5\u05e0\u05d0\u05e1"
    ],
    "name:hin_x_preferred":[
        "\u0932\u0917\u0942\u0928\u093e\u0938"
    ],
    "name:hun_x_preferred":[
        "Lagunas"
    ],
    "name:ind_x_preferred":[
        "Lagunas"
    ],
    "name:ita_x_preferred":[
        "Lagunas"
    ],
    "name:jpn_x_preferred":[
        "\u30e9\u30b0\u30ca\u30b9"
    ],
    "name:kor_x_preferred":[
        "\ub77c\uad6c\ub098\uc2a4"
    ],
    "name:nld_x_preferred":[
        "Lagunas"
    ],
    "name:pol_x_preferred":[
        "Lagunas"
    ],
    "name:por_x_preferred":[
        "Lagunas"
    ],
    "name:rus_x_preferred":[
        "\u041b\u0430\u0433\u0443\u043d\u0430"
    ],
    "name:spa_x_preferred":[
        "Lagunas"
    ],
    "name:srp_x_preferred":[
        "\u041b\u0430\u0433\u0443\u043d\u0430\u0441"
    ],
    "name:swe_x_preferred":[
        "Lagunas"
    ],
    "name:tur_x_preferred":[
        "Lagunas"
    ],
    "name:ukr_x_preferred":[
        "\u041b\u0430\u0433\u0443\u043d\u0430\u0441"
    ],
    "name:und_x_variant":[
        "San Antonio de la Laguna"
    ],
    "name:urd_x_preferred":[
        "\u0644\u0627\u06af\u0648\u0646\u0627\u0632"
    ],
    "name:vie_x_preferred":[
        "Lagunas"
    ],
    "name:zho_cn_x_preferred":[
        "\u62c9\u53e4\u7eb3\u65af"
    ],
    "name:zho_tw_x_preferred":[
        "\u62c9\u53e4\u7d0d\u65af"
    ],
    "qs:name":"Lagunas",
    "qs:photos_9r":0,
    "qs:photos_sr":0,
    "qs:pop_sr":"5",
    "wd:wordcount":49,
    "wof:name":"Lagunas",
    "wof:placetype":"locality",
    "wof:population":9197
},
  "geometry": {"coordinates":[-75.67528,-5.22694],"type":"Point"}
}