{
  "type": "Feature",
  "properties": {
    "gn:country":"PE",
    "gn:fcode":"PPLA3",
    "gn:population":9197,
    "iso:country":"PE",
    "name:ceb_x_preferred":[
        "Lagunas"
    ],
    "name:deu_x_preferred":[
        "Lagunas"
    ],
    "name:por_x_preferred":[
        "Lagunas"
    ],
    "name:spa_x_preferred":[
        "Lagunas"
    ],
    "name:srp_x_preferred":[
        "\u041b\u0430\u0433\u0443\u043d\u0430\u0441"
    ],
    "name:swe_x_preferred":[
        "Lagunas"
    ],
    "name:und_x_variant":[
        "San Antonio de la Laguna"
    ],
    "qs:name":"Lagunas",
    "qs:photos_9r":0,
    "qs:photos_sr":0,
    "qs:pop_sr":"5",
    "wd:wordcount":49,
    "wof:name":"Lagunas",
    "wof:placetype":"locality",
    "wof:population":9197
},
  "geometry": {"coordinates":[-75.67528,-5.22694],"type":"Point"}
}