{
  "type": "Feature",
  "properties": {
    "gn:country":"PE",
    "gn:fcode":"PPLA3",
    "gn:pop":9197,
    "iso:country":"PE",
    "name:unk_x_variant":[
        "San Antonio de la Laguna"
    ],
    "qs:name":"Lagunas",
    "qs:photos_9r":0,
    "qs:photos_sr":0,
    "qs:pop_sr":"5",
    "wd:wordcount":49,
    "wof:name":"Lagunas",
    "wof:placetype":"locality",
    "wof:population":9197
},
  "geometry": {"coordinates":[-75.67528,-5.22694],"type":"Point"}
}