{
  "type": "Feature",
  "properties": {
    "gn:admin1_code":"12.0",
    "gn:admin2_code":"1204.0",
    "gn:admin3_code":"120402.0",
    "gn:asciiname":"Chuquishuari",
    "gn:country_code":"PE",
    "gn:dem":3660,
    "gn:feature_class":"P",
    "gn:feature_code":"PPL",
    "gn:name":"Chuquishuari",
    "gn:population":0,
    "gn:timezone":"America/Lima",
    "iso:country":"PE",
    "wof:name":"Chuquishuari",
    "wof:placetype":"locality"
},
  "geometry": {"coordinates":[-75.56276,-11.63386],"type":"Point"}
}