{
  "type": "Feature",
  "properties": {
    "gn:admin1_code":"15",
    "gn:admin2_code":"1510.0",
    "gn:admin3_code":"151018.0",
    "gn:asciiname":"Lancaque",
    "gn:country_code":"PE",
    "gn:dem":3569,
    "gn:feature_class":"P",
    "gn:feature_code":"PPL",
    "gn:name":"Lancaque",
    "gn:population":0,
    "gn:timezone":"America/Lima",
    "iso:country":"PE",
    "wof:name":"Lancaque",
    "wof:placetype":"locality"
},
  "geometry": {"coordinates":[-75.77167,-12.35833],"type":"Point"}
}