{
  "type": "Feature",
  "properties": {
    "gn:admin1_code":"8.0",
    "gn:admin2_code":"803.0",
    "gn:admin3_code":"80308.0",
    "gn:asciiname":"Rosasjasa",
    "gn:country_code":"PE",
    "gn:dem":3485,
    "gn:feature_class":"P",
    "gn:feature_code":"PPLL",
    "gn:name":"Rosasjasa",
    "gn:population":0,
    "gn:timezone":"America/Lima",
    "iso:country":"PE",
    "wof:name":"Rosasjasa",
    "wof:placetype":"locality"
},
  "geometry": {"coordinates":[-72.09611,-13.48111],"type":"Point"}
}