{
  "type": "Feature",
  "properties": {
    "gn:admin1_code":"9.0",
    "gn:admin2_code":"907.0",
    "gn:admin3_code":"90706.0",
    "gn:asciiname":"Marcupata",
    "gn:country_code":"PE",
    "gn:dem":3323,
    "gn:feature_class":"P",
    "gn:feature_code":"PPL",
    "gn:name":"Marcupata",
    "gn:population":0,
    "gn:timezone":"America/Lima",
    "iso:country":"PE",
    "wof:name":"Marcupata",
    "wof:placetype":"locality"
},
  "geometry": {"coordinates":[-74.80426999999997,-12.35935],"type":"Point"}
}