{
  "type": "Feature",
  "properties": {
    "gn:admin1_code":"13.0",
    "gn:admin2_code":"1308.0",
    "gn:asciiname":"Yurjiaco",
    "gn:country_code":"PE",
    "gn:dem":1802,
    "gn:feature_class":"P",
    "gn:feature_code":"PPL",
    "gn:name":"Yurjiaco",
    "gn:population":0,
    "gn:timezone":"America/Lima",
    "iso:country":"PE",
    "wof:name":"Yurjiaco",
    "wof:placetype":"locality"
},
  "geometry": {"coordinates":[-77.40971999999999,-8.38],"type":"Point"}
}