{
  "type": "Feature",
  "properties": {
    "gn:admin1_code":"06",
    "gn:admin2_code":"603.0",
    "gn:admin3_code":"60306.0",
    "gn:asciiname":"Tingo",
    "gn:country_code":"PE",
    "gn:dem":2746,
    "gn:feature_class":"P",
    "gn:feature_code":"PPL",
    "gn:name":"Tingo",
    "gn:population":0,
    "gn:timezone":"America/Lima",
    "iso:country":"PE",
    "wof:name":"Tingo",
    "wof:placetype":"locality"
},
  "geometry": {"coordinates":[-78.14372,-6.89473],"type":"Point"}
}