{
  "type": "Feature",
  "properties": {
    "gn:admin1_code":"4",
    "gn:admin2_code":"404.0",
    "gn:admin3_code":"40409.0",
    "gn:asciiname":"Calachane",
    "gn:country_code":"PE",
    "gn:dem":4471,
    "gn:feature_class":"P",
    "gn:feature_code":"PPL",
    "gn:name":"Calachane",
    "gn:population":0,
    "gn:timezone":"America/Lima",
    "iso:country":"PE",
    "wof:name":"Calachane",
    "wof:placetype":"locality"
},
  "geometry": {"coordinates":[-72.33131999999998,-15.10078],"type":"Point"}
}