{
  "type": "Feature",
  "properties": {
    "gn:admin1_code":"04",
    "gn:admin2_code":"407.0",
    "gn:admin3_code":"40702.0",
    "gn:asciiname":"La Laja Hacienda",
    "gn:country_code":"PE",
    "gn:dem":80,
    "gn:feature_class":"P",
    "gn:feature_code":"PPL",
    "gn:name":"La Laja Hacienda",
    "gn:population":0,
    "gn:timezone":"America/Lima",
    "iso:country":"PE",
    "wof:name":"La Laja Hacienda",
    "wof:placetype":"locality"
},
  "geometry": {"coordinates":[-71.75539000000001,-17.08492],"type":"Point"}
}