{
  "type": "Feature",
  "properties": {
    "gn:admin1_code":"20",
    "gn:admin2_code":"2002.0",
    "gn:admin3_code":"200202.0",
    "gn:asciiname":"Huayabal",
    "gn:country_code":"PE",
    "gn:dem":936,
    "gn:feature_class":"P",
    "gn:feature_code":"PPL",
    "gn:name":"Huayabal",
    "gn:population":0,
    "gn:timezone":"America/Lima",
    "iso:country":"PE",
    "wof:name":"Huayabal",
    "wof:placetype":"locality"
},
  "geometry": {"coordinates":[-80.05334000000001,-4.89708],"type":"Point"}
}