{
  "type": "Feature",
  "properties": {
    "gn:admin1_code":"11.0",
    "gn:admin2_code":"1101.0",
    "gn:admin3_code":"110105.0",
    "gn:asciiname":"La Colmena",
    "gn:country_code":"PE",
    "gn:dem":431,
    "gn:feature_class":"P",
    "gn:feature_code":"PPLL",
    "gn:name":"La Colmena",
    "gn:population":0,
    "gn:timezone":"America/Lima",
    "iso:country":"PE",
    "wof:name":"La Colmena",
    "wof:placetype":"locality"
},
  "geometry": {"coordinates":[-75.66471999999997,-14.135],"type":"Point"}
}