{
  "type": "Feature",
  "properties": {
    "iso:country":"PE",
    "name:zho_x_preferred":[
        "\u63da\u514b\u5c71"
    ],
    "qs:gn_country":"PE",
    "qs:gn_fcode":"PPL",
    "qs:gn_pop":0,
    "qs:name":"Yanque",
    "qs:name_adm0":"Per\u00fa",
    "qs:name_adm1":"Arequipa",
    "qs:photos":428,
    "qs:photos_1k":87,
    "qs:photos_9k":2,
    "qs:photos_9r":5,
    "qs:photos_all":428,
    "qs:photos_sr":6,
    "qs:placetype":"Town",
    "qs:pop_sr":"0",
    "qs:woe_adm0":23424919,
    "wof:name":"Yanque",
    "wof:placetype":"locality"
},
  "geometry": {"coordinates":[-71.43832999999999,-15.87417],"type":"Point"}
}