{
  "type": "Feature",
  "properties": {
    "gn:admin1_code":"21.0",
    "gn:admin2_code":"2104.0",
    "gn:admin3_code":"210405.0",
    "gn:asciiname":"Quilane",
    "gn:country_code":"PE",
    "gn:dem":4244,
    "gn:feature_class":"P",
    "gn:feature_code":"PPL",
    "gn:name":"Quilane",
    "gn:population":0,
    "gn:timezone":"America/Lima",
    "iso:country":"PE",
    "wof:name":"Quilane",
    "wof:placetype":"locality"
},
  "geometry": {"coordinates":[-69.51454,-17.11182],"type":"Point"}
}