{
  "type": "Feature",
  "properties": {
    "gn:admin1_code":"04",
    "gn:admin2_code":"403.0",
    "gn:asciiname":"Concoma",
    "gn:country_code":"PE",
    "gn:dem":584,
    "gn:feature_class":"P",
    "gn:feature_code":"PPL",
    "gn:name":"Concoma",
    "gn:population":0,
    "gn:timezone":"America/Lima",
    "iso:country":"PE",
    "name:und_x_variant":[
        "Concona",
        "Concoma"
    ],
    "wof:name":"Concoma",
    "wof:placetype":"locality"
},
  "geometry": {"coordinates":[-74.35228000000002,-15.34876],"type":"Point"}
}