{
  "type": "Feature",
  "properties": {
    "gn:admin1_code":"18",
    "gn:admin2_code":"1802.0",
    "gn:admin3_code":"180207.0",
    "gn:asciiname":"Yalaque",
    "gn:country_code":"PE",
    "gn:dem":3069,
    "gn:feature_class":"P",
    "gn:feature_code":"PPL",
    "gn:name":"Yalaque",
    "gn:population":0,
    "gn:timezone":"America/Lima",
    "iso:country":"PE",
    "wof:name":"Yalaque",
    "wof:placetype":"locality"
},
  "geometry": {"coordinates":[-70.73969,-16.60388],"type":"Point"}
}