{
  "type": "Feature",
  "properties": {
    "gn:admin1_code":"10.0",
    "gn:admin2_code":"1003.0",
    "gn:admin3_code":"100313.0",
    "gn:asciiname":"Pincullo",
    "gn:country_code":"PE",
    "gn:dem":4220,
    "gn:feature_class":"P",
    "gn:feature_code":"PPL",
    "gn:name":"Pincullo",
    "gn:population":0,
    "gn:timezone":"America/Lima",
    "iso:country":"PE",
    "wof:name":"Pincullo",
    "wof:placetype":"locality"
},
  "geometry": {"coordinates":[-76.89123000000002,-9.70105],"type":"Point"}
}