{
  "type": "Feature",
  "properties": {
    "gn:admin1_code":"4",
    "gn:admin2_code":"405.0",
    "gn:admin3_code":"40504.0",
    "gn:asciiname":"Huanacalla",
    "gn:country_code":"PE",
    "gn:dem":4394,
    "gn:feature_class":"P",
    "gn:feature_code":"PPL",
    "gn:name":"Hua\u00f1acalla",
    "gn:population":0,
    "gn:timezone":"America/Lima",
    "iso:country":"PE",
    "wof:name":"Huanacalla",
    "wof:placetype":"locality"
},
  "geometry": {"coordinates":[-71.29364,-15.46265],"type":"Point"}
}