{
  "type": "Feature",
  "properties": {
    "gn:admin1_code":"12",
    "gn:admin2_code":"1207.0",
    "gn:admin3_code":"120702.0",
    "gn:asciiname":"Tupin",
    "gn:country_code":"PE",
    "gn:dem":3020,
    "gn:feature_class":"P",
    "gn:feature_code":"PPL",
    "gn:name":"Tupin",
    "gn:population":0,
    "gn:timezone":"America/Lima",
    "iso:country":"PE",
    "wof:name":"Tupin",
    "wof:placetype":"locality"
},
  "geometry": {"coordinates":[-75.68526999999997,-11.36624],"type":"Point"}
}