{
  "type": "Feature",
  "properties": {
    "gn:admin1_code":"03",
    "gn:admin2_code":"305.0",
    "gn:admin3_code":"30505.0",
    "gn:asciiname":"Pitij",
    "gn:country_code":"PE",
    "gn:dem":3802,
    "gn:feature_class":"P",
    "gn:feature_code":"PPL",
    "gn:name":"Pitij",
    "gn:population":0,
    "gn:timezone":"America/Lima",
    "iso:country":"PE",
    "wof:name":"Pitij",
    "wof:placetype":"locality"
},
  "geometry": {"coordinates":[-72.08333,-14.05],"type":"Point"}
}