{
  "type": "Feature",
  "properties": {
    "gn:admin1_code":"05",
    "gn:admin2_code":"508.0",
    "gn:admin3_code":"50810.0",
    "gn:asciiname":"Huaculla",
    "gn:country_code":"PE",
    "gn:dem":3496,
    "gn:feature_class":"P",
    "gn:feature_code":"PPL",
    "gn:name":"Huaculla",
    "gn:population":0,
    "gn:timezone":"America/Lima",
    "iso:country":"PE",
    "wof:name":"Huaculla",
    "wof:placetype":"locality"
},
  "geometry": {"coordinates":[-73.48278000000001,-15.24694],"type":"Point"}
}