{
  "type": "Feature",
  "properties": {
    "gn:admin1_code":"10.0",
    "gn:admin2_code":"1005.0",
    "gn:admin3_code":"100505.0",
    "gn:asciiname":"Urpish",
    "gn:country_code":"PE",
    "gn:dem":3427,
    "gn:feature_class":"P",
    "gn:feature_code":"PPL",
    "gn:name":"Urpish",
    "gn:population":0,
    "gn:timezone":"America/Lima",
    "iso:country":"PE",
    "name:spa_x_preferred":[
        "Urpish"
    ],
    "wof:name":"Urpish",
    "wof:placetype":"locality"
},
  "geometry": {"coordinates":[-76.72785,-9.27782],"type":"Point"}
}