{
  "type": "Feature",
  "properties": {
    "gn:admin1_code":"02",
    "gn:admin2_code":"205.0",
    "gn:admin3_code":"20509.0",
    "gn:asciiname":"Huayi",
    "gn:country_code":"PE",
    "gn:dem":3911,
    "gn:feature_class":"P",
    "gn:feature_code":"PPL",
    "gn:name":"Huayi",
    "gn:population":0,
    "gn:timezone":"America/Lima",
    "iso:country":"PE",
    "name:und_x_variant":[
        "Hacienda Huayi",
        "Huayi"
    ],
    "wof:name":"Huayi",
    "wof:placetype":"locality"
},
  "geometry": {"coordinates":[-77.04179000000001,-10.06247],"type":"Point"}
}