{
  "type": "Feature",
  "properties": {
    "gn:admin1_code":"08",
    "gn:admin2_code":"804.0",
    "gn:admin3_code":"80408.0",
    "gn:asciiname":"Tocchualla",
    "gn:cc2":"PE",
    "gn:country_code":"PE",
    "gn:dem":2437,
    "gn:feature_class":"P",
    "gn:feature_code":"PPL",
    "gn:name":"Tocchualla",
    "gn:population":0,
    "gn:timezone":"America/Lima",
    "iso:country":"PE",
    "name:und_x_variant":[
        "Techuailla",
        "Tocchualla"
    ],
    "wof:name":"Tocchualla",
    "wof:placetype":"locality"
},
  "geometry": {"coordinates":[-71.84999999999999,-12.96667],"type":"Point"}
}