{
  "type": "Feature",
  "properties": {
    "gn:admin1_code":"13",
    "gn:admin2_code":"1308.0",
    "gn:admin3_code":"130803.0",
    "gn:asciiname":"Floresta",
    "gn:cc2":"PE",
    "gn:country_code":"PE",
    "gn:dem":4235,
    "gn:feature_class":"P",
    "gn:feature_code":"PPL",
    "gn:name":"Floresta",
    "gn:population":0,
    "gn:timezone":"America/Lima",
    "iso:country":"PE",
    "name:und_x_variant":[
        "Floresta Hacienda",
        "Floresta"
    ],
    "wof:name":"Floresta",
    "wof:placetype":"locality"
},
  "geometry": {"coordinates":[-77.46666999999999,-8.15],"type":"Point"}
}