{
  "type": "Feature",
  "properties": {
    "gn:admin1_code":"04",
    "gn:admin2_code":"404.0",
    "gn:admin3_code":"40404.0",
    "gn:asciiname":"Marcane",
    "gn:country_code":"PE",
    "gn:dem":4690,
    "gn:feature_class":"P",
    "gn:feature_code":"PPL",
    "gn:name":"Marcane",
    "gn:population":0,
    "gn:timezone":"America/Lima",
    "iso:country":"PE",
    "name:spa_x_preferred":[
        "Marcane"
    ],
    "wof:name":"Marcane",
    "wof:placetype":"locality"
},
  "geometry": {"coordinates":[-72.07823,-15.11155],"type":"Point"}
}