{
  "type": "Feature",
  "properties": {
    "gn:admin1_code":"15",
    "gn:admin2_code":"1510.0",
    "gn:admin3_code":"151016.0",
    "gn:asciiname":"Urcay",
    "gn:country_code":"PE",
    "gn:dem":4416,
    "gn:feature_class":"P",
    "gn:feature_code":"PPL",
    "gn:name":"Urcay",
    "gn:population":0,
    "gn:timezone":"America/Lima",
    "iso:country":"PE",
    "name:und_x_variant":[
        "Urcuy",
        "Urcay"
    ],
    "wof:name":"Urcay",
    "wof:placetype":"locality"
},
  "geometry": {"coordinates":[-75.64249000000002,-12.53357],"type":"Point"}
}