{
  "type": "Feature",
  "properties": {
    "gn:admin1_code":"04",
    "gn:admin2_code":"403.0",
    "gn:admin3_code":"40310.0",
    "gn:asciiname":"Pampa Redonda",
    "gn:country_code":"PE",
    "gn:dem":254,
    "gn:feature_class":"P",
    "gn:feature_code":"PPL",
    "gn:name":"Pampa Redonda",
    "gn:population":0,
    "gn:timezone":"America/Lima",
    "iso:country":"PE",
    "name:und_x_variant":[
        "Pampa Redonda Hacienda",
        "Pampa Redonda"
    ],
    "wof:name":"Pampa Redonda",
    "wof:placetype":"locality"
},
  "geometry": {"coordinates":[-74.45612,-15.48057],"type":"Point"}
}