{
  "type": "Feature",
  "properties": {
    "gn:admin1_code":"21",
    "gn:admin2_code":"2101.0",
    "gn:admin3_code":"210112.0",
    "gn:asciiname":"Acora",
    "gn:country_code":"PE",
    "gn:dem":3843,
    "gn:feature_class":"P",
    "gn:feature_code":"PPL",
    "gn:name":"Acora",
    "gn:population":0,
    "gn:timezone":"America/Lima",
    "iso:country":"PE",
    "wof:name":"Acora",
    "wof:placetype":"locality"
},
  "geometry": {"coordinates":[-69.79741999999999,-15.9739],"type":"Point"}
}