{
  "type": "Feature",
  "properties": {
    "gn:admin1_code":"20",
    "gn:admin2_code":"2003.0",
    "gn:admin3_code":"200301.0",
    "gn:asciiname":"Huaylas",
    "gn:country_code":"PE",
    "gn:dem":2682,
    "gn:feature_class":"P",
    "gn:feature_code":"PPL",
    "gn:name":"Huaylas",
    "gn:population":0,
    "gn:timezone":"America/Lima",
    "iso:country":"PE",
    "wof:name":"Huaylas",
    "wof:placetype":"locality"
},
  "geometry": {"coordinates":[-79.48333000000002,-5.28333],"type":"Point"}
}