{
  "type": "Feature",
  "properties": {
    "gn:admin1_code":"12.0",
    "gn:admin2_code":"1204.0",
    "gn:admin3_code":"120414.0",
    "gn:asciiname":"Huarucloma",
    "gn:country_code":"PE",
    "gn:dem":3898,
    "gn:feature_class":"P",
    "gn:feature_code":"PPL",
    "gn:name":"Huarucloma",
    "gn:population":0,
    "gn:timezone":"America/Lima",
    "iso:country":"PE",
    "wof:name":"Huarucloma",
    "wof:placetype":"locality"
},
  "geometry": {"coordinates":[-75.66169000000002,-11.82134],"type":"Point"}
}