{
  "type": "Feature",
  "properties": {
    "gn:admin1_code":"22",
    "gn:admin2_code":"2209.0",
    "gn:admin3_code":"220911.0",
    "gn:asciiname":"Papa Playa",
    "gn:country_code":"PE",
    "gn:dem":146,
    "gn:feature_class":"P",
    "gn:feature_code":"PPL",
    "gn:name":"Papa Playa",
    "gn:population":0,
    "gn:timezone":"America/Lima",
    "iso:country":"PE",
    "wof:name":"Papa Playa",
    "wof:placetype":"locality"
},
  "geometry": {"coordinates":[-75.76666999999998,-6.23333],"type":"Point"}
}