{
  "type": "Feature",
  "properties": {
    "gn:admin1_code":"10",
    "gn:admin2_code":"1001.0",
    "gn:admin3_code":"100108.0",
    "gn:asciiname":"Cochapampa",
    "gn:country_code":"PE",
    "gn:dem":4014,
    "gn:feature_class":"P",
    "gn:feature_code":"PPL",
    "gn:name":"Cochapampa",
    "gn:population":0,
    "gn:timezone":"America/Lima",
    "iso:country":"PE",
    "name:und_x_variant":[
        "Gochapampa"
    ],
    "wof:name":"Cochapampa",
    "wof:placetype":"locality"
},
  "geometry": {"coordinates":[-76.39045,-10.1101],"type":"Point"}
}