{
  "type": "Feature",
  "properties": {
    "gn:admin1_code":"9.0",
    "gn:admin2_code":"907.0",
    "gn:admin3_code":"90702.0",
    "gn:asciiname":"Llamarumi",
    "gn:country_code":"PE",
    "gn:dem":3548,
    "gn:feature_class":"P",
    "gn:feature_code":"PPL",
    "gn:name":"Llamarumi",
    "gn:population":0,
    "gn:timezone":"America/Lima",
    "iso:country":"PE",
    "wof:name":"Llamarumi",
    "wof:placetype":"locality"
},
  "geometry": {"coordinates":[-74.99878000000002,-12.46383],"type":"Point"}
}