{
  "type": "Feature",
  "properties": {
    "gn:admin1_code":"17.0",
    "gn:admin2_code":"1701.0",
    "gn:asciiname":"Puerto Nuevo Sol Naciente",
    "gn:country_code":"PE",
    "gn:dem":187,
    "gn:feature_class":"P",
    "gn:feature_code":"PPL",
    "gn:name":"Puerto Nuevo Sol Naciente",
    "gn:population":0,
    "gn:timezone":"America/Lima",
    "iso:country":"PE",
    "name:spa_x_preferred":[
        "Puerto Nuevo Sol Naciente"
    ],
    "wof:name":"Puerto Nuevo Sol Naciente",
    "wof:placetype":"locality"
},
  "geometry": {"coordinates":[-69.16233000000001,-12.63338],"type":"Point"}
}