{
  "type": "Feature",
  "properties": {
    "gn:admin1_code":"20",
    "gn:admin2_code":"2006.0",
    "gn:admin3_code":"200605.0",
    "gn:asciiname":"Lobos",
    "gn:country_code":"PE",
    "gn:dem":401,
    "gn:feature_class":"P",
    "gn:feature_code":"PPL",
    "gn:name":"Lobos",
    "gn:population":0,
    "gn:timezone":"America/Lima",
    "iso:country":"PE",
    "name:ara_x_preferred":[
        "\u0644\u0648\u0628\u0648\u0633"
    ],
    "name:cat_x_preferred":[
        "Lobos"
    ],
    "name:ceb_x_preferred":[
        "Lobos"
    ],
    "name:deu_x_preferred":[
        "Lobos"
    ],
    "name:fra_x_preferred":[
        "Lobos"
    ],
    "name:ita_x_preferred":[
        "Lobos"
    ],
    "name:lit_x_preferred":[
        "Lobosas"
    ],
    "name:nld_x_preferred":[
        "Lobos"
    ],
    "name:pol_x_preferred":[
        "Lobos"
    ],
    "name:por_x_preferred":[
        "Lobos"
    ],
    "name:slk_x_preferred":[
        "Lobos"
    ],
    "name:spa_x_preferred":[
        "Lobos"
    ],
    "name:swe_x_preferred":[
        "Lobos"
    ],
    "wof:name":"Lobos",
    "wof:placetype":"locality"
},
  "geometry": {"coordinates":[-80.83583,-4.23611],"type":"Point"}
}