{
  "type": "Feature",
  "properties": {
    "gn:admin1_code":"20",
    "gn:admin2_code":"2004.0",
    "gn:admin3_code":"200405.0",
    "gn:asciiname":"Pampa de la Hacienda",
    "gn:country_code":"PE",
    "gn:dem":141,
    "gn:feature_class":"P",
    "gn:feature_code":"PPL",
    "gn:name":"Pampa de la Hacienda",
    "gn:population":0,
    "gn:timezone":"America/Lima",
    "iso:country":"PE",
    "wof:name":"Pampa de la Hacienda",
    "wof:placetype":"locality"
},
  "geometry": {"coordinates":[-79.95573,-5.20399],"type":"Point"}
}