{
  "type": "Feature",
  "properties": {
    "gn:admin1_code":"15",
    "gn:admin2_code":"1510.0",
    "gn:admin3_code":"151030.0",
    "gn:asciiname":"Llacsa",
    "gn:country_code":"PE",
    "gn:dem":4132,
    "gn:feature_class":"P",
    "gn:feature_code":"PPL",
    "gn:name":"Llacsa",
    "gn:population":0,
    "gn:timezone":"America/Lima",
    "iso:country":"PE",
    "wof:name":"Llacsa",
    "wof:placetype":"locality"
},
  "geometry": {"coordinates":[-75.71778,-12.15167],"type":"Point"}
}