{
  "type": "Feature",
  "properties": {
    "gn:admin1_code":"15",
    "gn:admin2_code":"1510.0",
    "gn:admin3_code":"151032.0",
    "gn:asciiname":"Pampa Una",
    "gn:country_code":"PE",
    "gn:dem":3386,
    "gn:feature_class":"P",
    "gn:feature_code":"PPL",
    "gn:name":"Pampa U\u00f1a",
    "gn:population":0,
    "gn:timezone":"America/Lima",
    "iso:country":"PE",
    "wof:name":"Pampa Una",
    "wof:placetype":"locality"
},
  "geometry": {"coordinates":[-75.79916,-12.88707],"type":"Point"}
}