{
  "type": "Feature",
  "properties": {
    "gn:admin1_code":"10.0",
    "gn:admin2_code":"1006.0",
    "gn:admin3_code":"100606.0",
    "gn:asciiname":"Chontaplaya",
    "gn:country_code":"PE",
    "gn:dem":905,
    "gn:feature_class":"P",
    "gn:feature_code":"PPL",
    "gn:name":"Chontaplaya",
    "gn:population":0,
    "gn:timezone":"America/Lima",
    "iso:country":"PE",
    "wof:name":"Chontaplaya",
    "wof:placetype":"locality"
},
  "geometry": {"coordinates":[-75.9558,-9.45311],"type":"Point"}
}