{
  "type": "Feature",
  "properties": {
    "gn:admin1_code":"18",
    "gn:admin2_code":"1801.0",
    "gn:admin3_code":"180101.0",
    "gn:asciiname":"Taquila",
    "gn:country_code":"PE",
    "gn:dem":950,
    "gn:feature_class":"P",
    "gn:feature_code":"PPL",
    "gn:name":"Taquila",
    "gn:population":0,
    "gn:timezone":"America/Lima",
    "iso:country":"PE",
    "wof:name":"Taquila",
    "wof:placetype":"locality"
},
  "geometry": {"coordinates":[-71.0034,-17.34989],"type":"Point"}
}