{
  "type": "Feature",
  "properties": {
    "gn:admin1_code":"20",
    "gn:admin2_code":"2005.0",
    "gn:admin3_code":"200505.0",
    "gn:asciiname":"Viviare",
    "gn:country_code":"PE",
    "gn:dem":31,
    "gn:feature_class":"P",
    "gn:feature_code":"PPL",
    "gn:name":"Viviare",
    "gn:population":0,
    "gn:timezone":"America/Lima",
    "iso:country":"PE",
    "wof:name":"Viviare",
    "wof:placetype":"locality"
},
  "geometry": {"coordinates":[-80.92064999999999,-4.92355],"type":"Point"}
}