{
  "type": "Feature",
  "properties": {
    "gn:admin1_code":"3",
    "gn:admin2_code":"302.0",
    "gn:admin3_code":"30201.0",
    "gn:asciiname":"Yayan",
    "gn:country_code":"PE",
    "gn:dem":4152,
    "gn:feature_class":"P",
    "gn:feature_code":"PPL",
    "gn:name":"Yayan",
    "gn:population":0,
    "gn:timezone":"America/Lima",
    "iso:country":"PE",
    "wof:name":"Yayan",
    "wof:placetype":"locality"
},
  "geometry": {"coordinates":[-73.32111,-13.8875],"type":"Point"}
}