{
  "type": "Feature",
  "properties": {
    "gn:admin1_code":"05",
    "gn:admin2_code":"501.0",
    "gn:admin3_code":"50105.0",
    "gn:asciiname":"Lachocmayo",
    "gn:country_code":"PE",
    "gn:dem":3676,
    "gn:feature_class":"P",
    "gn:feature_code":"PPL",
    "gn:name":"Lachocmayo",
    "gn:population":0,
    "gn:timezone":"America/Lima",
    "iso:country":"PE",
    "wof:name":"Lachocmayo",
    "wof:placetype":"locality"
},
  "geometry": {"coordinates":[-74.2363,-13.40157],"type":"Point"}
}