{
  "type": "Feature",
  "properties": {
    "gn:admin1_code":"24",
    "gn:admin2_code":"2402.0",
    "gn:admin3_code":"240202.0",
    "gn:asciiname":"Samorondon",
    "gn:country_code":"PE",
    "gn:dem":288,
    "gn:feature_class":"P",
    "gn:feature_code":"PPL",
    "gn:name":"Samorond\u00f3n",
    "gn:population":0,
    "gn:timezone":"America/Lima",
    "iso:country":"PE",
    "wof:name":"Samorondon",
    "wof:placetype":"locality"
},
  "geometry": {"coordinates":[-80.78471,-4.14492],"type":"Point"}
}