{
  "type": "Feature",
  "properties": {
    "gn:admin1_code":"21",
    "gn:admin2_code":"2111.0",
    "gn:admin3_code":"211101.0",
    "gn:asciiname":"Acomerine",
    "gn:country_code":"PE",
    "gn:dem":3842,
    "gn:feature_class":"P",
    "gn:feature_code":"PPL",
    "gn:name":"Acomer\u00edne",
    "gn:population":0,
    "gn:timezone":"America/Lima",
    "iso:country":"PE",
    "wof:name":"Acomerine",
    "wof:placetype":"locality"
},
  "geometry": {"coordinates":[-70.24606999999999,-15.50967],"type":"Point"}
}