{
  "type": "Feature",
  "properties": {
    "gn:admin1_code":"11",
    "gn:admin2_code":"1105.0",
    "gn:admin3_code":"110503.0",
    "gn:asciiname":"Pantayco",
    "gn:country_code":"PE",
    "gn:dem":605,
    "gn:feature_class":"P",
    "gn:feature_code":"PPL",
    "gn:name":"Pantayco",
    "gn:population":0,
    "gn:timezone":"America/Lima",
    "iso:country":"PE",
    "name:spa_x_preferred":[
        "Pantayco"
    ],
    "name:spa_x_variant":[
        "Pantaico"
    ],
    "wof:name":"Pantayco",
    "wof:placetype":"locality"
},
  "geometry": {"coordinates":[-75.83924,-13.70665],"type":"Point"}
}