{
  "type": "Feature",
  "properties": {
    "gn:admin1_code":"02",
    "gn:admin2_code":"210.0",
    "gn:admin3_code":"21001.0",
    "gn:asciiname":"Rahuapampa",
    "gn:country_code":"PE",
    "gn:dem":3246,
    "gn:feature_class":"P",
    "gn:feature_code":"PPL",
    "gn:name":"Rahuapampa",
    "gn:population":0,
    "gn:timezone":"America/Lima",
    "iso:country":"PE",
    "name:und_x_variant":[
        "Huachis",
        "Rahuapampa"
    ],
    "wof:name":"Rahuapampa",
    "wof:placetype":"locality"
},
  "geometry": {"coordinates":[-77.10080000000001,-9.41037],"type":"Point"}
}