{
  "type": "Feature",
  "properties": {
    "gn:admin1_code":"10.0",
    "gn:admin2_code":"1010.0",
    "gn:admin3_code":"101007.0",
    "gn:asciiname":"Pashuyari",
    "gn:country_code":"PE",
    "gn:dem":3993,
    "gn:feature_class":"P",
    "gn:feature_code":"PPL",
    "gn:name":"Pashuyari",
    "gn:population":0,
    "gn:timezone":"America/Lima",
    "iso:country":"PE",
    "wof:name":"Pashuyari",
    "wof:placetype":"locality"
},
  "geometry": {"coordinates":[-76.63528000000002,-10.19611],"type":"Point"}
}