{
  "type": "Feature",
  "properties": {
    "gn:admin1_code":"2.0",
    "gn:admin2_code":"205.0",
    "gn:admin3_code":"20501.0",
    "gn:asciiname":"Rosapampa",
    "gn:country_code":"PE",
    "gn:dem":3361,
    "gn:feature_class":"P",
    "gn:feature_code":"PPL",
    "gn:name":"Rosapampa",
    "gn:population":0,
    "gn:timezone":"America/Lima",
    "iso:country":"PE",
    "wof:name":"Rosapampa",
    "wof:placetype":"locality"
},
  "geometry": {"coordinates":[-77.14094,-10.1588],"type":"Point"}
}