{
  "type": "Feature",
  "properties": {
    "gn:admin1_code":"11",
    "gn:admin2_code":"1101.0",
    "gn:admin3_code":"110111.0",
    "gn:asciiname":"La Venta",
    "gn:country_code":"PE",
    "gn:dem":344,
    "gn:feature_class":"P",
    "gn:feature_code":"PPL",
    "gn:name":"La Venta",
    "gn:population":0,
    "gn:timezone":"America/Lima",
    "iso:country":"PE",
    "name:und_x_variant":[
        "La Venta Hacienda",
        "La Venta"
    ],
    "wof:name":"La Venta",
    "wof:placetype":"locality"
},
  "geometry": {"coordinates":[-75.68001,-14.28762],"type":"Point"}
}