{
  "type": "Feature",
  "properties": {
    "gn:admin1_code":"04",
    "gn:admin2_code":"401.0",
    "gn:admin3_code":"40119.0",
    "gn:asciiname":"Laccoco",
    "gn:cc2":"PE",
    "gn:country_code":"PE",
    "gn:dem":4352,
    "gn:feature_class":"P",
    "gn:feature_code":"PPL",
    "gn:name":"Laccoco",
    "gn:population":0,
    "gn:timezone":"America/Lima",
    "iso:country":"PE",
    "name:und_x_variant":[
        "Laceoco",
        "Laccoco"
    ],
    "wof:name":"Laccoco",
    "wof:placetype":"locality"
},
  "geometry": {"coordinates":[-71.23333000000002,-16.11667000000001],"type":"Point"}
}