{
  "type": "Feature",
  "properties": {
    "gn:admin1_code":"04",
    "gn:admin2_code":"404.0",
    "gn:admin3_code":"40404.0",
    "gn:asciiname":"Huaytapalca",
    "gn:country_code":"PE",
    "gn:dem":4481,
    "gn:feature_class":"P",
    "gn:feature_code":"PPL",
    "gn:name":"Huaytapalca",
    "gn:population":0,
    "gn:timezone":"America/Lima",
    "iso:country":"PE",
    "name:spa_x_preferred":[
        "Huaytapalca"
    ],
    "wof:name":"Huaytapalca",
    "wof:placetype":"locality"
},
  "geometry": {"coordinates":[-72.07384999999999,-15.23717],"type":"Point"}
}