{
  "type": "Feature",
  "properties": {
    "gn:admin1_code":"10.0",
    "gn:admin2_code":"1003.0",
    "gn:admin3_code":"100307.0",
    "gn:asciiname":"Hogobamba",
    "gn:country_code":"PE",
    "gn:dem":3582,
    "gn:feature_class":"P",
    "gn:feature_code":"PPL",
    "gn:name":"Hogobamba",
    "gn:population":0,
    "gn:timezone":"America/Lima",
    "iso:country":"PE",
    "wof:name":"Hogobamba",
    "wof:placetype":"locality"
},
  "geometry": {"coordinates":[-76.68796,-9.68541],"type":"Point"}
}