{
  "type": "Feature",
  "properties": {
    "gn:admin1_code":"16",
    "gn:admin2_code":"1604.0",
    "gn:admin3_code":"160404.0",
    "gn:asciiname":"Beirut",
    "gn:country_code":"PE",
    "gn:dem":71,
    "gn:feature_class":"P",
    "gn:feature_code":"PPL",
    "gn:name":"Beirut",
    "gn:population":0,
    "gn:timezone":"America/Lima",
    "iso:country":"PE",
    "wof:name":"Beirut",
    "wof:placetype":"locality"
},
  "geometry": {"coordinates":[-71.46139000000002,-3.88],"type":"Point"}
}