{
  "type": "Feature",
  "properties": {
    "gn:admin1_code":"06",
    "gn:admin2_code":"602.0",
    "gn:admin3_code":"60203.0",
    "gn:asciiname":"Lucuma Pampa",
    "gn:country_code":"PE",
    "gn:dem":2554,
    "gn:feature_class":"P",
    "gn:feature_code":"PPL",
    "gn:name":"Lucuma Pampa",
    "gn:population":0,
    "gn:timezone":"America/Lima",
    "iso:country":"PE",
    "wof:name":"Lucuma Pampa",
    "wof:placetype":"locality"
},
  "geometry": {"coordinates":[-78.09634,-7.58234],"type":"Point"}
}