{
  "type": "Feature",
  "properties": {
    "gn:admin1_code":"21.0",
    "gn:admin2_code":"2104.0",
    "gn:admin3_code":"210405.0",
    "gn:asciiname":"Jaratatpata",
    "gn:country_code":"PE",
    "gn:dem":4287,
    "gn:feature_class":"P",
    "gn:feature_code":"PPL",
    "gn:name":"Jaratatpata",
    "gn:population":0,
    "gn:timezone":"America/Lima",
    "iso:country":"PE",
    "wof:name":"Jaratatpata",
    "wof:placetype":"locality"
},
  "geometry": {"coordinates":[-69.41028,-17.04667],"type":"Point"}
}