{
  "type": "Feature",
  "properties": {
    "gn:admin1_code":"05",
    "gn:admin2_code":"507.0",
    "gn:admin3_code":"50701.0",
    "gn:asciiname":"Rupasjahuasi",
    "gn:country_code":"PE",
    "gn:dem":3613,
    "gn:feature_class":"P",
    "gn:feature_code":"PPL",
    "gn:name":"Rupasjahuasi",
    "gn:population":0,
    "gn:timezone":"America/Lima",
    "iso:country":"PE",
    "wof:name":"Rupasjahuasi",
    "wof:placetype":"locality"
},
  "geometry": {"coordinates":[-73.84334,-14.90667],"type":"Point"}
}