{
  "type": "Feature",
  "properties": {
    "gn:admin1_code":"21",
    "gn:admin2_code":"2111.0",
    "gn:admin3_code":"211101.0",
    "gn:asciiname":"Sancaune",
    "gn:country_code":"PE",
    "gn:dem":3839,
    "gn:feature_class":"P",
    "gn:feature_code":"PPL",
    "gn:name":"Sancaune",
    "gn:population":0,
    "gn:timezone":"America/Lima",
    "iso:country":"PE",
    "wof:name":"Sancaune",
    "wof:placetype":"locality"
},
  "geometry": {"coordinates":[-70.15000000000001,-15.53333],"type":"Point"}
}