{
  "type": "Feature",
  "properties": {
    "gn:admin1_code":"23",
    "gn:admin2_code":"2301.0",
    "gn:admin3_code":"230109.0",
    "gn:asciiname":"El Huayco",
    "gn:country_code":"PE",
    "gn:dem":219,
    "gn:feature_class":"P",
    "gn:feature_code":"PPL",
    "gn:name":"El Huayco",
    "gn:population":0,
    "gn:timezone":"America/Lima",
    "iso:country":"PE",
    "name:und_x_variant":[
        "El Huayco Hacienda",
        "El Huayco"
    ],
    "wof:name":"El Huayco",
    "wof:placetype":"locality"
},
  "geometry": {"coordinates":[-70.63556,-17.97417],"type":"Point"}
}