{
  "type": "Feature",
  "properties": {
    "gn:admin1_code":"9",
    "gn:admin2_code":"906.0",
    "gn:admin3_code":"90608.0",
    "gn:asciiname":"Collisora",
    "gn:country_code":"PE",
    "gn:dem":4296,
    "gn:feature_class":"P",
    "gn:feature_code":"PPL",
    "gn:name":"Collisora",
    "gn:population":0,
    "gn:timezone":"America/Lima",
    "iso:country":"PE",
    "wof:name":"Collisora",
    "wof:placetype":"locality"
},
  "geometry": {"coordinates":[-74.95222,-13.74694],"type":"Point"}
}