{
  "type": "Feature",
  "properties": {
    "gn:admin1_code":"15",
    "gn:admin2_code":"1510.0",
    "gn:admin3_code":"151002.0",
    "gn:asciiname":"Tragadero",
    "gn:country_code":"PE",
    "gn:dem":4539,
    "gn:feature_class":"P",
    "gn:feature_code":"PPL",
    "gn:name":"Tragadero",
    "gn:population":0,
    "gn:timezone":"America/Lima",
    "iso:country":"PE",
    "wof:name":"Tragadero",
    "wof:placetype":"locality"
},
  "geometry": {"coordinates":[-75.60778000000001,-12.28417],"type":"Point"}
}