{
  "type": "Feature",
  "properties": {
    "gn:admin1_code":"20",
    "gn:admin2_code":"2006.0",
    "gn:admin3_code":"200601.0",
    "gn:asciiname":"Riecito",
    "gn:country_code":"PE",
    "gn:dem":73,
    "gn:feature_class":"P",
    "gn:feature_code":"PPL",
    "gn:name":"Riecito",
    "gn:population":0,
    "gn:timezone":"America/Lima",
    "iso:country":"PE",
    "name:und_x_variant":[
        "Reicito Hacienda",
        "Riecito Hacienda",
        "Riecito"
    ],
    "wof:name":"Riecito",
    "wof:placetype":"locality"
},
  "geometry": {"coordinates":[-80.50713,-4.71387],"type":"Point"}
}