{
  "type": "Feature",
  "properties": {
    "gn:admin1_code":"9",
    "gn:admin2_code":"906.0",
    "gn:admin3_code":"90613.0",
    "gn:asciiname":"Yauri",
    "gn:country_code":"PE",
    "gn:dem":3305,
    "gn:feature_class":"P",
    "gn:feature_code":"PPL",
    "gn:name":"Yauri",
    "gn:population":0,
    "gn:timezone":"America/Lima",
    "iso:country":"PE",
    "name:ceb_x_preferred":[
        "Yauri"
    ],
    "name:swe_x_preferred":[
        "Yauri"
    ],
    "wof:name":"Yauri",
    "wof:placetype":"locality"
},
  "geometry": {"coordinates":[-75.14610999999999,-13.80972],"type":"Point"}
}