{
  "type": "Feature",
  "properties": {
    "gn:admin1_code":"14",
    "gn:admin2_code":"1401.0",
    "gn:admin3_code":"140111.0",
    "gn:asciiname":"Chescope",
    "gn:country_code":"PE",
    "gn:dem":44,
    "gn:feature_class":"P",
    "gn:feature_code":"PPL",
    "gn:name":"Chescope",
    "gn:population":0,
    "gn:timezone":"America/Lima",
    "iso:country":"PE",
    "name:spa_x_preferred":[
        "Chescope"
    ],
    "wof:name":"Chescope",
    "wof:placetype":"locality"
},
  "geometry": {"coordinates":[-79.76312,-6.73688],"type":"Point"}
}