{
  "type": "Feature",
  "properties": {
    "gn:admin1_code":"21",
    "gn:admin2_code":"2107.0",
    "gn:admin3_code":"210705.0",
    "gn:asciiname":"Condorsora",
    "gn:country_code":"PE",
    "gn:dem":4914,
    "gn:feature_class":"P",
    "gn:feature_code":"PPL",
    "gn:name":"Condorsora",
    "gn:population":0,
    "gn:timezone":"America/Lima",
    "iso:country":"PE",
    "wof:name":"Condorsora",
    "wof:placetype":"locality"
},
  "geometry": {"coordinates":[-70.78194000000001,-15.32861],"type":"Point"}
}