{
  "type": "Feature",
  "properties": {
    "gn:admin1_code":"11",
    "gn:admin2_code":"1101.0",
    "gn:admin3_code":"110109.0",
    "gn:asciiname":"Callejon de Romero",
    "gn:country_code":"PE",
    "gn:dem":495,
    "gn:feature_class":"P",
    "gn:feature_code":"PPL",
    "gn:name":"Callej\u00f3n de Romero",
    "gn:population":0,
    "gn:timezone":"America/Lima",
    "iso:country":"PE",
    "wof:name":"Callejon de Romero",
    "wof:placetype":"locality"
},
  "geometry": {"coordinates":[-75.68196,-13.9419],"type":"Point"}
}