{
  "type": "Feature",
  "properties": {
    "gn:admin1_code":"11",
    "gn:admin2_code":"1103.0",
    "gn:admin3_code":"110302.0",
    "gn:asciiname":"Hacienda Jumana",
    "gn:country_code":"PE",
    "gn:dem":222,
    "gn:feature_class":"P",
    "gn:feature_code":"PPL",
    "gn:name":"Hacienda Jumana",
    "gn:population":0,
    "gn:timezone":"America/Lima",
    "iso:country":"PE",
    "name:und_x_variant":[
        "Jumana Hacienda",
        "Jumana",
        "Hacienda Jumana"
    ],
    "wof:name":"Hacienda Jumana",
    "wof:placetype":"locality"
},
  "geometry": {"coordinates":[-75.2343,-14.75338],"type":"Point"}
}