{
  "type": "Feature",
  "properties": {
    "gn:admin1_code":"4",
    "gn:admin2_code":"403.0",
    "gn:admin3_code":"40308.0",
    "gn:asciiname":"Cangallo Grande",
    "gn:country_code":"PE",
    "gn:dem":302,
    "gn:feature_class":"P",
    "gn:feature_code":"PPL",
    "gn:name":"Cangallo Grande",
    "gn:population":0,
    "gn:timezone":"America/Lima",
    "iso:country":"PE",
    "name:spa_x_preferred":[
        "Cangallo Grande"
    ],
    "wof:name":"Cangallo Grande",
    "wof:placetype":"locality"
},
  "geometry": {"coordinates":[-74.05778000000002,-15.84869],"type":"Point"}
}