{
  "type": "Feature",
  "properties": {
    "gn:admin1_code":"21.0",
    "gn:admin2_code":"2105.0",
    "gn:admin3_code":"210502.0",
    "gn:asciiname":"Iscazurani",
    "gn:country_code":"PE",
    "gn:dem":4241,
    "gn:feature_class":"P",
    "gn:feature_code":"PPL",
    "gn:name":"Iscazurani",
    "gn:population":0,
    "gn:timezone":"America/Lima",
    "iso:country":"PE",
    "wof:name":"Iscazurani",
    "wof:placetype":"locality"
},
  "geometry": {"coordinates":[-69.72884999999999,-17.28984],"type":"Point"}
}