{
  "type": "Feature",
  "properties": {
    "gn:admin1_code":"20",
    "gn:admin2_code":"2002.0",
    "gn:admin3_code":"200202.0",
    "gn:asciiname":"Tanlama",
    "gn:country_code":"PE",
    "gn:dem":812,
    "gn:feature_class":"P",
    "gn:feature_code":"PPL",
    "gn:name":"Tanlama",
    "gn:population":0,
    "gn:timezone":"America/Lima",
    "iso:country":"PE",
    "wof:name":"Tanlama",
    "wof:placetype":"locality"
},
  "geometry": {"coordinates":[-79.97417,-5.00889],"type":"Point"}
}