{
  "type": "Feature",
  "properties": {
    "gn:admin1_code":"21",
    "gn:admin2_code":"2102.0",
    "gn:admin3_code":"210205.0",
    "gn:asciiname":"Caminaca",
    "gn:country_code":"PE",
    "gn:dem":3898,
    "gn:feature_class":"P",
    "gn:feature_code":"PPLA3",
    "gn:name":"Caminaca",
    "gn:population":0,
    "gn:timezone":"America/Lima",
    "iso:country":"PE",
    "wof:name":"Caminaca",
    "wof:placetype":"locality"
},
  "geometry": {"coordinates":[-70.06667,-15.31667],"type":"Point"}
}