{
  "type": "Feature",
  "properties": {
    "gn:admin1_code":"2.0",
    "gn:admin2_code":"205.0",
    "gn:admin3_code":"20501.0",
    "gn:asciiname":"Matara",
    "gn:country_code":"PE",
    "gn:dem":3879,
    "gn:feature_class":"P",
    "gn:feature_code":"PPL",
    "gn:name":"Matara",
    "gn:population":0,
    "gn:timezone":"America/Lima",
    "iso:country":"PE",
    "wof:name":"Matara",
    "wof:placetype":"locality"
},
  "geometry": {"coordinates":[-77.15761999999999,-10.21386],"type":"Point"}
}