{
  "type": "Feature",
  "properties": {
    "gn:admin1_code":"2.0",
    "gn:admin2_code":"205.0",
    "gn:admin3_code":"20501.0",
    "gn:asciiname":"Matara",
    "gn:country_code":"PE",
    "gn:dem":3879,
    "gn:feature_class":"P",
    "gn:feature_code":"PPL",
    "gn:name":"Matara",
    "gn:population":0,
    "gn:timezone":"America/Lima",
    "iso:country":"PE",
    "name:ceb_x_preferred":[
        "Matara"
    ],
    "name:ind_x_preferred":[
        "Matara"
    ],
    "name:ita_x_preferred":[
        "Matara"
    ],
    "name:nld_x_preferred":[
        "Matara"
    ],
    "name:pol_x_preferred":[
        "Matara"
    ],
    "name:por_x_preferred":[
        "Matara"
    ],
    "name:por_x_variant":[
        "Matar\u00e1"
    ],
    "name:rus_x_preferred":[
        "\u041c\u0430\u0442\u0430\u0440\u0430"
    ],
    "name:spa_x_preferred":[
        "Matar\u00e1"
    ],
    "name:swe_x_preferred":[
        "Matara"
    ],
    "wof:name":"Matara",
    "wof:placetype":"locality"
},
  "geometry": {"coordinates":[-77.15761999999999,-10.21386],"type":"Point"}
}