{
  "type": "Feature",
  "properties": {
    "gn:admin1_code":"11",
    "gn:admin2_code":"1102.0",
    "gn:admin3_code":"110205.0",
    "gn:asciiname":"El Carmen",
    "gn:country_code":"PE",
    "gn:dem":146,
    "gn:feature_class":"P",
    "gn:feature_code":"PPLA3",
    "gn:name":"El Carmen",
    "gn:population":0,
    "gn:timezone":"America/Lima",
    "iso:country":"PE",
    "name:und_x_variant":[
        "Carmen",
        "El Carmen"
    ],
    "wof:name":"El Carmen",
    "wof:placetype":"locality"
},
  "geometry": {"coordinates":[-76.05724000000002,-13.49714],"type":"Point"}
}