{
  "type": "Feature",
  "properties": {
    "gn:admin1_code":"15",
    "gn:admin2_code":"1510.0",
    "gn:admin3_code":"151011.0",
    "gn:asciiname":"Quische",
    "gn:country_code":"PE",
    "gn:dem":2452,
    "gn:feature_class":"P",
    "gn:feature_code":"PPL",
    "gn:name":"Quische",
    "gn:population":0,
    "gn:timezone":"America/Lima",
    "iso:country":"PE",
    "wof:name":"Quische",
    "wof:placetype":"locality"
},
  "geometry": {"coordinates":[-75.93942,-12.60757],"type":"Point"}
}