{
  "type": "Feature",
  "properties": {
    "gn:admin1_code":"9.0",
    "gn:admin2_code":"903.0",
    "gn:admin3_code":"90304.0",
    "gn:asciiname":"Sasaylla",
    "gn:country_code":"PE",
    "gn:dem":4083,
    "gn:feature_class":"P",
    "gn:feature_code":"PPL",
    "gn:name":"Sasaylla",
    "gn:population":0,
    "gn:timezone":"America/Lima",
    "iso:country":"PE",
    "wof:name":"Sasaylla",
    "wof:placetype":"locality"
},
  "geometry": {"coordinates":[-74.75301999999998,-12.93079],"type":"Point"}
}