{
  "type": "Feature",
  "properties": {
    "gn:admin1_code":"06",
    "gn:admin2_code":"604.0",
    "gn:admin3_code":"60412.0",
    "gn:asciiname":"Tangasca",
    "gn:country_code":"PE",
    "gn:dem":692,
    "gn:feature_class":"P",
    "gn:feature_code":"PPL",
    "gn:name":"Tangasca",
    "gn:population":0,
    "gn:timezone":"America/Lima",
    "iso:country":"PE",
    "wof:name":"Tangasca",
    "wof:placetype":"locality"
},
  "geometry": {"coordinates":[-79.39904,-6.37661],"type":"Point"}
}