{
  "type": "Feature",
  "properties": {
    "gn:admin1_code":"5",
    "gn:admin2_code":"506.0",
    "gn:admin3_code":"50606.0",
    "gn:asciiname":"Ochuviaco",
    "gn:country_code":"PE",
    "gn:dem":4154,
    "gn:feature_class":"P",
    "gn:feature_code":"PPL",
    "gn:name":"Ochuviaco",
    "gn:population":0,
    "gn:timezone":"America/Lima",
    "iso:country":"PE",
    "wof:name":"Ochuviaco",
    "wof:placetype":"locality"
},
  "geometry": {"coordinates":[-73.69917,-14.42861],"type":"Point"}
}