{
  "type": "Feature",
  "properties": {
    "gn:admin1_code":"04",
    "gn:admin2_code":"401.0",
    "gn:admin3_code":"40121.0",
    "gn:asciiname":"San Antonio Hacienda",
    "gn:country_code":"PE",
    "gn:dem":1246,
    "gn:feature_class":"P",
    "gn:feature_code":"PPL",
    "gn:name":"San Antonio Hacienda",
    "gn:population":0,
    "gn:timezone":"America/Lima",
    "iso:country":"PE",
    "wof:name":"San Antonio Hacienda",
    "wof:placetype":"locality"
},
  "geometry": {"coordinates":[-72.09010000000001,-16.51747],"type":"Point"}
}