{
  "type": "Feature",
  "properties": {
    "gn:admin1_code":"8.0",
    "gn:admin2_code":"813.0",
    "gn:admin3_code":"81303.0",
    "gn:asciiname":"Molinocucho",
    "gn:country_code":"PE",
    "gn:dem":2900,
    "gn:feature_class":"P",
    "gn:feature_code":"PPL",
    "gn:name":"Molinocucho",
    "gn:population":0,
    "gn:timezone":"America/Lima",
    "iso:country":"PE",
    "wof:name":"Molinocucho",
    "wof:placetype":"locality"
},
  "geometry": {"coordinates":[-72.045,-13.33639],"type":"Point"}
}