{
  "type": "Feature",
  "properties": {
    "gn:admin1_code":"14",
    "gn:admin2_code":"1403.0",
    "gn:admin3_code":"140312.0",
    "gn:asciiname":"La Pintada",
    "gn:country_code":"PE",
    "gn:dem":51,
    "gn:feature_class":"P",
    "gn:feature_code":"PPL",
    "gn:name":"La Pintada",
    "gn:population":0,
    "gn:timezone":"America/Lima",
    "iso:country":"PE",
    "name:ceb_x_preferred":[
        "La Pintada"
    ],
    "name:deu_x_preferred":[
        "La Pintada"
    ],
    "name:fra_x_preferred":[
        "La Pintada"
    ],
    "name:ita_x_preferred":[
        "La Pintada"
    ],
    "name:spa_x_preferred":[
        "La Pintada"
    ],
    "name:srp_x_preferred":[
        "\u041b\u0430 \u041f\u0438\u043d\u0442\u0430\u0434\u0430"
    ],
    "name:swe_x_preferred":[
        "La Pintada"
    ],
    "wof:name":"La Pintada",
    "wof:placetype":"locality"
},
  "geometry": {"coordinates":[-79.85207,-6.49877],"type":"Point"}
}