{
  "type": "Feature",
  "properties": {
    "gn:admin1_code":"09",
    "gn:admin2_code":"903.0",
    "gn:admin3_code":"90301.0",
    "gn:asciiname":"Pirca",
    "gn:country_code":"PE",
    "gn:dem":3691,
    "gn:feature_class":"P",
    "gn:feature_code":"PPL",
    "gn:name":"Pirca",
    "gn:population":0,
    "gn:timezone":"America/Lima",
    "iso:country":"PE",
    "wof:name":"Pirca",
    "wof:placetype":"locality"
},
  "geometry": {"coordinates":[-74.75633000000001,-13.04916],"type":"Point"}
}