{
  "type": "Feature",
  "properties": {
    "gn:admin1_code":"10.0",
    "gn:admin2_code":"1008.0",
    "gn:admin3_code":"100803.0",
    "gn:asciiname":"Pozopunta",
    "gn:country_code":"PE",
    "gn:dem":3516,
    "gn:feature_class":"P",
    "gn:feature_code":"PPL",
    "gn:name":"Pozopunta",
    "gn:population":0,
    "gn:timezone":"America/Lima",
    "iso:country":"PE",
    "wof:name":"Pozopunta",
    "wof:placetype":"locality"
},
  "geometry": {"coordinates":[-76.08513000000001,-9.9833],"type":"Point"}
}