{
  "type": "Feature",
  "properties": {
    "gn:admin1_code":"5",
    "gn:admin2_code":"506.0",
    "gn:admin3_code":"50606.0",
    "gn:asciiname":"Pesebre",
    "gn:country_code":"PE",
    "gn:dem":4262,
    "gn:feature_class":"P",
    "gn:feature_code":"PPL",
    "gn:name":"Pesebre",
    "gn:population":0,
    "gn:timezone":"America/Lima",
    "iso:country":"PE",
    "wof:name":"Pesebre",
    "wof:placetype":"locality"
},
  "geometry": {"coordinates":[-73.69806,-14.41194],"type":"Point"}
}