{
  "type": "Feature",
  "properties": {
    "gn:admin1_code":"21.0",
    "gn:admin2_code":"2112.0",
    "gn:asciiname":"Mina Yapo",
    "gn:country_code":"PE",
    "gn:dem":1876,
    "gn:feature_class":"P",
    "gn:feature_code":"PPL",
    "gn:name":"Mina Yapo",
    "gn:population":0,
    "gn:timezone":"America/Lima",
    "iso:country":"PE",
    "name:spa_x_preferred":[
        "Mina Yapo"
    ],
    "wof:name":"Mina Yapo",
    "wof:placetype":"locality"
},
  "geometry": {"coordinates":[-69.08329999999999,-14.37095],"type":"Point"}
}