{
  "type": "Feature",
  "properties": {
    "gn:admin1_code":"18",
    "gn:admin2_code":"1802.0",
    "gn:admin3_code":"180210.0",
    "gn:asciiname":"Postocone",
    "gn:country_code":"PE",
    "gn:dem":4489,
    "gn:feature_class":"P",
    "gn:feature_code":"PPL",
    "gn:name":"Postocone",
    "gn:population":0,
    "gn:timezone":"America/Lima",
    "iso:country":"PE",
    "wof:name":"Postocone",
    "wof:placetype":"locality"
},
  "geometry": {"coordinates":[-70.95635,-16.37733],"type":"Point"}
}