{
  "type": "Feature",
  "properties": {
    "gn:admin1_code":"12",
    "gn:admin2_code":"1207.0",
    "gn:admin3_code":"120706.0",
    "gn:asciiname":"Shicshar",
    "gn:country_code":"PE",
    "gn:dem":2669,
    "gn:feature_class":"P",
    "gn:feature_code":"PPL",
    "gn:name":"Shicshar",
    "gn:population":0,
    "gn:timezone":"America/Lima",
    "iso:country":"PE",
    "name:und_x_variant":[
        "Stieshar"
    ],
    "wof:name":"Shicshar",
    "wof:placetype":"locality"
},
  "geometry": {"coordinates":[-75.55471999999997,-11.30861],"type":"Point"}
}