{
  "type": "Feature",
  "properties": {
    "gn:admin1_code":"9.0",
    "gn:admin2_code":"907.0",
    "gn:admin3_code":"90705.0",
    "gn:asciiname":"Chinchipampa",
    "gn:country_code":"PE",
    "gn:dem":3423,
    "gn:feature_class":"P",
    "gn:feature_code":"PPL",
    "gn:name":"Chinchipampa",
    "gn:population":0,
    "gn:timezone":"America/Lima",
    "iso:country":"PE",
    "wof:name":"Chinchipampa",
    "wof:placetype":"locality"
},
  "geometry": {"coordinates":[-74.69943000000001,-12.41931],"type":"Point"}
}