{
  "type": "Feature",
  "properties": {
    "gn:admin1_code":"3",
    "gn:admin2_code":"302.0",
    "gn:admin3_code":"30214.0",
    "gn:asciiname":"Jellocoise",
    "gn:country_code":"PE",
    "gn:dem":3201,
    "gn:feature_class":"P",
    "gn:feature_code":"PPL",
    "gn:name":"Jellocoise",
    "gn:population":0,
    "gn:timezone":"America/Lima",
    "iso:country":"PE",
    "wof:name":"Jellocoise",
    "wof:placetype":"locality"
},
  "geometry": {"coordinates":[-73.57183000000001,-13.98041],"type":"Point"}
}