{
  "type": "Feature",
  "properties": {
    "gn:admin1_code":"21.0",
    "gn:admin2_code":"2112.0",
    "gn:asciiname":"Cruz Pata",
    "gn:country_code":"PE",
    "gn:dem":1754,
    "gn:feature_class":"P",
    "gn:feature_code":"PPL",
    "gn:name":"Cruz Pata",
    "gn:population":0,
    "gn:timezone":"America/Lima",
    "iso:country":"PE",
    "name:spa_x_preferred":[
        "Cruz Pata"
    ],
    "wof:name":"Cruz Pata",
    "wof:placetype":"locality"
},
  "geometry": {"coordinates":[-69.27673,-14.15712],"type":"Point"}
}