{
  "type": "Feature",
  "properties": {
    "gn:admin1_code":"19",
    "gn:admin2_code":"1901.0",
    "gn:asciiname":"Chunomarca",
    "gn:country_code":"PE",
    "gn:dem":4172,
    "gn:feature_class":"P",
    "gn:feature_code":"PPL",
    "gn:name":"Chunomarca",
    "gn:population":0,
    "gn:timezone":"America/Lima",
    "iso:country":"PE",
    "wof:name":"Chunomarca",
    "wof:placetype":"locality"
},
  "geometry": {"coordinates":[-76.14319999999999,-10.44412],"type":"Point"}
}