{
  "type": "Feature",
  "properties": {
    "gn:admin1_code":"04",
    "gn:admin2_code":"401.0",
    "gn:admin3_code":"40114.0",
    "gn:asciiname":"San Jose de Uzuna",
    "gn:country_code":"PE",
    "gn:dem":3292,
    "gn:feature_class":"P",
    "gn:feature_code":"PPL",
    "gn:name":"San Jos\u00e9 de Uzu\u00f1a",
    "gn:population":0,
    "gn:timezone":"America/Lima",
    "iso:country":"PE",
    "wof:name":"San Jose de Uzuna",
    "wof:placetype":"locality"
},
  "geometry": {"coordinates":[-71.30861,-16.59005],"type":"Point"}
}