{
  "type": "Feature",
  "properties": {
    "gn:admin1_code":"01",
    "gn:admin2_code":"101.0",
    "gn:admin3_code":"10105.0",
    "gn:asciiname":"Chiliquini",
    "gn:country_code":"PE",
    "gn:dem":2665,
    "gn:feature_class":"P",
    "gn:feature_code":"PPL",
    "gn:name":"Chiliquini",
    "gn:population":0,
    "gn:timezone":"America/Lima",
    "iso:country":"PE",
    "name:und_x_variant":[
        "Chiquilin",
        "Chiliquin",
        "Chiliquini"
    ],
    "wof:name":"Chiliquini",
    "wof:placetype":"locality"
},
  "geometry": {"coordinates":[-77.73739999999999,-6.07738],"type":"Point"}
}