{
  "type": "Feature",
  "properties": {
    "gn:admin1_code":"21",
    "gn:admin2_code":"2111.0",
    "gn:admin3_code":"211103.0",
    "gn:asciiname":"San Antonio Hacienda",
    "gn:country_code":"PE",
    "gn:dem":3990,
    "gn:feature_class":"P",
    "gn:feature_code":"PPL",
    "gn:name":"San Antonio Hacienda",
    "gn:population":0,
    "gn:timezone":"America/Lima",
    "iso:country":"PE",
    "wof:name":"San Antonio Hacienda",
    "wof:placetype":"locality"
},
  "geometry": {"coordinates":[-70.52155999999999,-15.69324],"type":"Point"}
}