{
  "type": "Feature",
  "properties": {
    "gn:admin1_code":"12.0",
    "gn:admin2_code":"1205.0",
    "gn:admin3_code":"120503.0",
    "gn:asciiname":"Yuraccaca",
    "gn:country_code":"PE",
    "gn:dem":4171,
    "gn:feature_class":"P",
    "gn:feature_code":"PPL",
    "gn:name":"Yuraccaca",
    "gn:population":0,
    "gn:timezone":"America/Lima",
    "iso:country":"PE",
    "wof:name":"Yuraccaca",
    "wof:placetype":"locality"
},
  "geometry": {"coordinates":[-76.21984,-11.02742],"type":"Point"}
}