{
  "type": "Feature",
  "properties": {
    "gn:admin1_code":"13",
    "gn:admin2_code":"1302.0",
    "gn:admin3_code":"130206.0",
    "gn:asciiname":"Pancal",
    "gn:country_code":"PE",
    "gn:dem":14,
    "gn:feature_class":"P",
    "gn:feature_code":"PPL",
    "gn:name":"Pancal",
    "gn:population":0,
    "gn:timezone":"America/Lima",
    "iso:country":"PE",
    "wof:name":"Pancal",
    "wof:placetype":"locality"
},
  "geometry": {"coordinates":[-79.39458,-7.73444],"type":"Point"}
}