{
  "type": "Feature",
  "properties": {
    "gn:admin1_code":"25",
    "gn:admin2_code":"2501.0",
    "gn:admin3_code":"250103.0",
    "gn:asciiname":"Santa Rosa",
    "gn:country_code":"PE",
    "gn:dem":161,
    "gn:feature_class":"P",
    "gn:feature_code":"PPL",
    "gn:name":"Santa Rosa",
    "gn:population":0,
    "gn:timezone":"America/Lima",
    "iso:country":"PE",
    "wof:name":"Santa Rosa",
    "wof:placetype":"locality"
},
  "geometry": {"coordinates":[-74.57333,-8.81556],"type":"Point"}
}