{
  "type": "Feature",
  "properties": {
    "gn:admin1_code":"10.0",
    "gn:admin2_code":"1005.0",
    "gn:asciiname":"Churana",
    "gn:country_code":"PE",
    "gn:dem":4413,
    "gn:feature_class":"P",
    "gn:feature_code":"PPL",
    "gn:name":"Churana",
    "gn:population":0,
    "gn:timezone":"America/Lima",
    "iso:country":"PE",
    "wof:name":"Churana",
    "wof:placetype":"locality"
},
  "geometry": {"coordinates":[-76.90205999999998,-9.41347],"type":"Point"}
}