{
  "type": "Feature",
  "properties": {
    "gn:admin1_code":"04",
    "gn:admin2_code":"404.0",
    "gn:admin3_code":"40404.0",
    "gn:asciiname":"Umapallca",
    "gn:country_code":"PE",
    "gn:dem":4490,
    "gn:feature_class":"P",
    "gn:feature_code":"PPL",
    "gn:name":"Umapallca",
    "gn:population":0,
    "gn:timezone":"America/Lima",
    "iso:country":"PE",
    "wof:name":"Umapallca",
    "wof:placetype":"locality"
},
  "geometry": {"coordinates":[-72.22221,-15.47552],"type":"Point"}
}