{
  "type": "Feature",
  "properties": {
    "gn:admin1_code":"16",
    "gn:admin2_code":"1604.0",
    "gn:admin3_code":"160404.0",
    "gn:asciiname":"Santo Tomas",
    "gn:country_code":"PE",
    "gn:dem":107,
    "gn:feature_class":"P",
    "gn:feature_code":"PPL",
    "gn:name":"Santo Tom\u00e1s",
    "gn:population":0,
    "gn:timezone":"America/Lima",
    "iso:country":"PE",
    "wof:name":"Santo Tomas",
    "wof:placetype":"locality"
},
  "geometry": {"coordinates":[-71.39502,-3.88434],"type":"Point"}
}