{
  "type": "Feature",
  "properties": {
    "gn:admin1_code":"05",
    "gn:admin2_code":"506.0",
    "gn:admin3_code":"50612.0",
    "gn:asciiname":"Lucmayo",
    "gn:country_code":"PE",
    "gn:dem":2572,
    "gn:feature_class":"P",
    "gn:feature_code":"PPL",
    "gn:name":"Lucmayo",
    "gn:population":0,
    "gn:timezone":"America/Lima",
    "iso:country":"PE",
    "wof:name":"Lucmayo",
    "wof:placetype":"locality"
},
  "geometry": {"coordinates":[-74.66829,-14.39621],"type":"Point"}
}