{
  "type": "Feature",
  "properties": {
    "gn:admin1_code":"5",
    "gn:admin2_code":"509.0",
    "gn:admin3_code":"50904.0",
    "gn:asciiname":"Ccanana",
    "gn:country_code":"PE",
    "gn:dem":3312,
    "gn:feature_class":"P",
    "gn:feature_code":"PPL",
    "gn:name":"Cca\u00f1ana",
    "gn:population":0,
    "gn:timezone":"America/Lima",
    "iso:country":"PE",
    "wof:name":"Ccanana",
    "wof:placetype":"locality"
},
  "geometry": {"coordinates":[-73.73369,-13.89721],"type":"Point"}
}