{
  "type": "Feature",
  "properties": {
    "gn:admin1_code":"14",
    "gn:admin2_code":"1403.0",
    "gn:admin3_code":"140302.0",
    "gn:asciiname":"Pelala",
    "gn:country_code":"PE",
    "gn:dem":561,
    "gn:feature_class":"P",
    "gn:feature_code":"PPL",
    "gn:name":"Pelala",
    "gn:population":0,
    "gn:timezone":"America/Lima",
    "iso:country":"PE",
    "name:und_x_variant":[
        "Plala"
    ],
    "wof:name":"Pelala",
    "wof:placetype":"locality"
},
  "geometry": {"coordinates":[-79.57525,-6.15666],"type":"Point"}
}