{
  "type": "Feature",
  "properties": {
    "gn:admin1_code":"04",
    "gn:admin2_code":"408.0",
    "gn:admin3_code":"40803.0",
    "gn:asciiname":"Chusacay",
    "gn:country_code":"PE",
    "gn:dem":1955,
    "gn:feature_class":"P",
    "gn:feature_code":"PPL",
    "gn:name":"Chusacay",
    "gn:population":0,
    "gn:timezone":"America/Lima",
    "iso:country":"PE",
    "wof:name":"Chusacay",
    "wof:placetype":"locality"
},
  "geometry": {"coordinates":[-73.00583,-15.25278],"type":"Point"}
}