{
  "type": "Feature",
  "properties": {
    "gn:admin1_code":"21.0",
    "gn:admin2_code":"2112.0",
    "gn:asciiname":"Jalachaca",
    "gn:country_code":"PE",
    "gn:dem":3611,
    "gn:feature_class":"P",
    "gn:feature_code":"PPL",
    "gn:name":"Jalachaca",
    "gn:population":0,
    "gn:timezone":"America/Lima",
    "iso:country":"PE",
    "name:spa_x_preferred":[
        "Jalachaca"
    ],
    "wof:name":"Jalachaca",
    "wof:placetype":"locality"
},
  "geometry": {"coordinates":[-69.33326,-14.47926],"type":"Point"}
}