{
  "type": "Feature",
  "properties": {
    "gn:admin1_code":"4.0",
    "gn:admin2_code":"408.0",
    "gn:admin3_code":"40811.0",
    "gn:asciiname":"Otto",
    "gn:country_code":"PE",
    "gn:dem":2877,
    "gn:feature_class":"P",
    "gn:feature_code":"PPL",
    "gn:name":"Otto",
    "gn:population":0,
    "gn:timezone":"America/Lima",
    "iso:country":"PE",
    "name:spa_x_preferred":[
        "Otto"
    ],
    "wof:name":"Otto",
    "wof:placetype":"locality"
},
  "geometry": {"coordinates":[-73.005,-15.31542],"type":"Point"}
}