{
  "type": "Feature",
  "properties": {
    "gn:admin1_code":"13",
    "gn:admin2_code":"1309.0",
    "gn:admin3_code":"130902.0",
    "gn:asciiname":"Purgatorio",
    "gn:country_code":"PE",
    "gn:dem":2752,
    "gn:feature_class":"P",
    "gn:feature_code":"PPL",
    "gn:name":"Purgatorio",
    "gn:population":0,
    "gn:timezone":"America/Lima",
    "iso:country":"PE",
    "name:ben_x_preferred":[
        "\u09aa\u09c1\u09b0\u0997\u09be\u09a4\u09cb\u09b0\u09bf\u0993"
    ],
    "name:cat_x_preferred":[
        "Purgatori"
    ],
    "name:ces_x_preferred":[
        "O\u010distec"
    ],
    "name:fra_x_preferred":[
        "Purgatoire"
    ],
    "name:hun_x_preferred":[
        "Dante Purgat\u00f3riuma"
    ],
    "name:ita_x_preferred":[
        "Purgatorio"
    ],
    "name:por_x_preferred":[
        "Purgat\u00f3rio"
    ],
    "name:ron_x_preferred":[
        "Purgatoriul"
    ],
    "name:rus_x_preferred":[
        "\u0427\u0438\u0441\u0442\u0438\u043b\u0438\u0449\u0435"
    ],
    "name:spa_x_preferred":[
        "Purgatorio"
    ],
    "name:tgk_x_preferred":[
        "\u0411\u0430\u0440\u0437\u0430\u0445"
    ],
    "name:ukr_x_preferred":[
        "\u0427\u0438\u0441\u0442\u0438\u043b\u0438\u0449\u0435"
    ],
    "wof:name":"Purgatorio",
    "wof:placetype":"locality"
},
  "geometry": {"coordinates":[-77.87443,-7.82696],"type":"Point"}
}