{
  "type": "Feature",
  "properties": {
    "gn:admin1_code":"12.0",
    "gn:admin2_code":"1208.0",
    "gn:admin3_code":"120807.0",
    "gn:asciiname":"Goyatayoj",
    "gn:country_code":"PE",
    "gn:dem":4538,
    "gn:feature_class":"P",
    "gn:feature_code":"PPL",
    "gn:name":"Goyatayoj",
    "gn:population":0,
    "gn:timezone":"America/Lima",
    "iso:country":"PE",
    "wof:name":"Goyatayoj",
    "wof:placetype":"locality"
},
  "geometry": {"coordinates":[-76.30831999999999,-11.15881],"type":"Point"}
}