{
  "type": "Feature",
  "properties": {
    "gn:admin1_code":"05",
    "gn:admin2_code":"505.0",
    "gn:admin3_code":"50502.0",
    "gn:asciiname":"Chiquintirca",
    "gn:country_code":"PE",
    "gn:dem":3383,
    "gn:feature_class":"P",
    "gn:feature_code":"PPL",
    "gn:name":"Chiquintirca",
    "gn:population":0,
    "gn:timezone":"America/Lima",
    "iso:country":"PE",
    "wof:name":"Chiquintirca",
    "wof:placetype":"locality"
},
  "geometry": {"coordinates":[-73.68333,-13.15],"type":"Point"}
}