{
  "type": "Feature",
  "properties": {
    "gn:admin1_code":"14",
    "gn:admin2_code":"1403.0",
    "gn:admin3_code":"140306.0",
    "gn:asciiname":"Lagartera",
    "gn:country_code":"PE",
    "gn:dem":28,
    "gn:feature_class":"P",
    "gn:feature_code":"PPL",
    "gn:name":"Lagartera",
    "gn:population":0,
    "gn:timezone":"America/Lima",
    "iso:country":"PE",
    "name:ara_x_preferred":[
        "\u0644\u0627\u062c\u0627\u0631\u062a\u064a\u0631\u0627"
    ],
    "name:arg_x_preferred":[
        "Lagartera"
    ],
    "name:ast_x_preferred":[
        "Llagartera"
    ],
    "name:azb_x_preferred":[
        "\u0644\u0627\u0642\u0627\u0631\u062a\u0631\u0627"
    ],
    "name:cat_x_preferred":[
        "Lagartera"
    ],
    "name:ceb_x_preferred":[
        "Lagartera"
    ],
    "name:epo_x_preferred":[
        "Lagartera"
    ],
    "name:eus_x_preferred":[
        "Lagartera"
    ],
    "name:fas_x_preferred":[
        "\u0644\u0627\u06af\u0627\u0631\u062a\u0631\u0627"
    ],
    "name:fra_x_preferred":[
        "Lagartera"
    ],
    "name:glg_x_preferred":[
        "Lagartera"
    ],
    "name:hun_x_preferred":[
        "Lagartera"
    ],
    "name:hye_x_preferred":[
        "\u053c\u0561\u0563\u0561\u0580\u057f\u0565\u0580\u0561"
    ],
    "name:ina_x_preferred":[
        "Lagartera"
    ],
    "name:ita_x_preferred":[
        "Lagartera"
    ],
    "name:kaz_x_preferred":[
        "\u041b\u0430\u0433\u0430\u0440\u0442\u0435\u0440\u0430"
    ],
    "name:msa_x_preferred":[
        "Lagartera"
    ],
    "name:nld_x_preferred":[
        "Lagartera"
    ],
    "name:oci_x_preferred":[
        "Lagartera"
    ],
    "name:pol_x_preferred":[
        "Lagartera"
    ],
    "name:por_x_preferred":[
        "Lagartera"
    ],
    "name:ron_x_preferred":[
        "Lagartera"
    ],
    "name:rus_x_preferred":[
        "\u041b\u0430\u0433\u0430\u0440\u0442\u0435\u0440\u0430"
    ],
    "name:spa_x_preferred":[
        "Lagartera"
    ],
    "name:swe_x_preferred":[
        "Lagartera"
    ],
    "name:ukr_x_preferred":[
        "\u041b\u0430\u0433\u0430\u0440\u0442\u0435\u0440\u0430"
    ],
    "name:vie_x_preferred":[
        "Lagartera"
    ],
    "name:war_x_preferred":[
        "Lagartera"
    ],
    "name:zho_x_preferred":[
        "\u62c9\u52a0\u5c14\u7279\u62c9"
    ],
    "wof:name":"Lagartera",
    "wof:placetype":"locality"
},
  "geometry": {"coordinates":[-79.98345,-6.49546],"type":"Point"}
}