{
  "type": "Feature",
  "properties": {
    "gn:admin1_code":"10.0",
    "gn:admin2_code":"1005.0",
    "gn:admin3_code":"100508.0",
    "gn:asciiname":"Ructuc",
    "gn:country_code":"PE",
    "gn:dem":3842,
    "gn:feature_class":"P",
    "gn:feature_code":"PPL",
    "gn:name":"Ructuc",
    "gn:population":0,
    "gn:timezone":"America/Lima",
    "iso:country":"PE",
    "wof:name":"Ructuc",
    "wof:placetype":"locality"
},
  "geometry": {"coordinates":[-76.86378000000001,-9.43611],"type":"Point"}
}