{
  "type": "Feature",
  "properties": {
    "gn:admin1_code":"04",
    "gn:admin2_code":"405.0",
    "gn:admin3_code":"40511.0",
    "gn:asciiname":"Vanllay",
    "gn:country_code":"PE",
    "gn:dem":3716,
    "gn:feature_class":"P",
    "gn:feature_code":"PPL",
    "gn:name":"Vanllay",
    "gn:population":0,
    "gn:timezone":"America/Lima",
    "iso:country":"PE",
    "wof:name":"Vanllay",
    "wof:placetype":"locality"
},
  "geometry": {"coordinates":[-71.93229000000002,-15.96936],"type":"Point"}
}