{
  "type": "Feature",
  "properties": {
    "gn:admin1_code":"08",
    "gn:admin2_code":"807.0",
    "gn:admin3_code":"80702.0",
    "gn:asciiname":"Mapay",
    "gn:country_code":"PE",
    "gn:dem":3346,
    "gn:feature_class":"P",
    "gn:feature_code":"PPL",
    "gn:name":"Mapay",
    "gn:population":0,
    "gn:timezone":"America/Lima",
    "iso:country":"PE",
    "name:und_x_variant":[
        "Mapay Hacienda",
        "Mapay"
    ],
    "wof:name":"Mapay",
    "wof:placetype":"locality"
},
  "geometry": {"coordinates":[-72.01085999999999,-13.95656],"type":"Point"}
}