{
  "type": "Feature",
  "properties": {
    "gn:admin1_code":"20",
    "gn:admin2_code":"2003.0",
    "gn:admin3_code":"200306.0",
    "gn:asciiname":"Las Huacas",
    "gn:country_code":"PE",
    "gn:dem":224,
    "gn:feature_class":"P",
    "gn:feature_code":"PPL",
    "gn:name":"Las Huacas",
    "gn:population":0,
    "gn:timezone":"America/Lima",
    "iso:country":"PE",
    "name:ceb_x_preferred":[
        "Las Huacas"
    ],
    "name:spa_x_preferred":[
        "Las Huacas"
    ],
    "name:swe_x_preferred":[
        "Las Huacas"
    ],
    "name:und_x_variant":[
        "Huacas"
    ],
    "wof:name":"Las Huacas",
    "wof:placetype":"locality"
},
  "geometry": {"coordinates":[-79.74481999999998,-5.43421],"type":"Point"}
}