{
  "type": "Feature",
  "properties": {
    "gn:admin1_code":"12",
    "gn:admin2_code":"1207.0",
    "gn:admin3_code":"120708.0",
    "gn:asciiname":"Tinyahuarco",
    "gn:country_code":"PE",
    "gn:dem":4198,
    "gn:feature_class":"P",
    "gn:feature_code":"PPL",
    "gn:name":"Tinyahuarco",
    "gn:population":0,
    "gn:timezone":"America/Lima",
    "iso:country":"PE",
    "wof:name":"Tinyahuarco",
    "wof:placetype":"locality"
},
  "geometry": {"coordinates":[-75.86583,-11.20056],"type":"Point"}
}