{
  "type": "Feature",
  "properties": {
    "iso:country":"PE",
    "name:spa_x_preferred":[
        "Tingue"
    ],
    "qs:gn_country":"PE",
    "qs:gn_fcode":"PPL",
    "qs:gn_pop":490,
    "qs:name":"Ting\u00fce",
    "qs:name_adm0":"Per\u00fa",
    "qs:name_adm1":"Ica",
    "qs:photos":0,
    "qs:photos_1k":0,
    "qs:photos_9k":0,
    "qs:photos_9r":0,
    "qs:photos_all":0,
    "qs:photos_sr":0,
    "qs:placetype":"Town",
    "qs:pop_sr":"2",
    "qs:woe_adm0":23424919,
    "wof:name":"Ting\u00fce",
    "wof:placetype":"locality",
    "wof:population":490
},
  "geometry": {"coordinates":[-75.54392,-14.21848],"type":"Point"}
}