{
  "type": "Feature",
  "properties": {
    "gn:admin1_code":"8",
    "gn:admin2_code":"808.0",
    "gn:asciiname":"Huilaccacca",
    "gn:country_code":"PE",
    "gn:dem":4704,
    "gn:feature_class":"P",
    "gn:feature_code":"PPL",
    "gn:name":"Huilaccacca",
    "gn:population":0,
    "gn:timezone":"America/Lima",
    "iso:country":"PE",
    "wof:name":"Huilaccacca",
    "wof:placetype":"locality"
},
  "geometry": {"coordinates":[-71.15098,-15.38795],"type":"Point"}
}