{
  "type": "Feature",
  "properties": {
    "gn:admin1_code":"23",
    "gn:admin2_code":"2302.0",
    "gn:asciiname":"Estancia Chanjamoco",
    "gn:country_code":"PE",
    "gn:dem":4642,
    "gn:feature_class":"P",
    "gn:feature_code":"PPL",
    "gn:name":"Estancia Chanjamoco",
    "gn:population":0,
    "gn:timezone":"America/Lima",
    "iso:country":"PE",
    "wof:name":"Estancia Chanjamoco",
    "wof:placetype":"locality"
},
  "geometry": {"coordinates":[-70.27546,-16.79359],"type":"Point"}
}