{
  "type": "Feature",
  "properties": {
    "gn:admin1_code":"1.0",
    "gn:admin2_code":"106.0",
    "gn:admin3_code":"10605.0",
    "gn:asciiname":"Yuracyacu",
    "gn:country_code":"PE",
    "gn:dem":1732,
    "gn:feature_class":"P",
    "gn:feature_code":"PPL",
    "gn:name":"Yuracyacu",
    "gn:population":0,
    "gn:timezone":"America/Lima",
    "iso:country":"PE",
    "wof:name":"Yuracyacu",
    "wof:placetype":"locality"
},
  "geometry": {"coordinates":[-77.62201999999998,-6.45813],"type":"Point"}
}