{
  "type": "Feature",
  "properties": {
    "gn:admin1_code":"21.0",
    "gn:admin2_code":"2105.0",
    "gn:admin3_code":"210504.0",
    "gn:asciiname":"Challapatija",
    "gn:country_code":"PE",
    "gn:dem":4528,
    "gn:feature_class":"P",
    "gn:feature_code":"PPL",
    "gn:name":"Challapatija",
    "gn:population":0,
    "gn:timezone":"America/Lima",
    "iso:country":"PE",
    "wof:name":"Challapatija",
    "wof:placetype":"locality"
},
  "geometry": {"coordinates":[-69.95083000000001,-17.01028],"type":"Point"}
}