{
  "type": "Feature",
  "properties": {
    "gn:admin1_code":"12",
    "gn:admin2_code":"1202.0",
    "gn:admin3_code":"120203.0",
    "gn:asciiname":"Cana",
    "gn:country_code":"PE",
    "gn:dem":2681,
    "gn:feature_class":"P",
    "gn:feature_code":"PPL",
    "gn:name":"Ca\u00f1a",
    "gn:population":0,
    "gn:timezone":"America/Lima",
    "iso:country":"PE",
    "name:bel_x_preferred":[
        "\u041a\u0430\u043d\u0430 \u0413\u0430\u043b\u0456\u043b\u0435\u0439\u0441\u043a\u0430\u044f"
    ],
    "name:bre_x_preferred":[
        "Kana"
    ],
    "name:cat_x_preferred":[
        "Can\u00e0"
    ],
    "name:ces_x_preferred":[
        "K\u00e1na"
    ],
    "name:dan_x_preferred":[
        "Kana"
    ],
    "name:deu_x_preferred":[
        "Kana"
    ],
    "name:ell_x_preferred":[
        "\u039a\u03b1\u03bd\u03ac"
    ],
    "name:glg_x_preferred":[
        "Can\u00e1"
    ],
    "name:hun_x_preferred":[
        "K\u00e1na"
    ],
    "name:ind_x_preferred":[
        "Kana"
    ],
    "name:ita_x_preferred":[
        "Cana"
    ],
    "name:jpn_x_preferred":[
        "\u30ab\u30ca"
    ],
    "name:kor_x_preferred":[
        "\uac00\ub098"
    ],
    "name:lat_x_preferred":[
        "Cana Galilaeae"
    ],
    "name:pol_x_preferred":[
        "Kana Galilejska"
    ],
    "name:por_x_preferred":[
        "Can\u00e1"
    ],
    "name:rus_x_preferred":[
        "\u041a\u0430\u043d\u0430 \u0413\u0430\u043b\u0438\u043b\u0435\u0439\u0441\u043a\u0430\u044f"
    ],
    "name:srp_x_preferred":[
        "\u041a\u0430\u043d\u0430 \u0413\u0430\u043b\u0438\u043b\u0435\u0458\u0441\u043a\u0430"
    ],
    "name:tam_x_preferred":[
        "\u0b95\u0bbe\u0ba9\u0bbe"
    ],
    "name:ukr_x_preferred":[
        "\u041a\u0430\u043d\u0430 \u0413\u0430\u043b\u0456\u043b\u0435\u0439\u0441\u044c\u043a\u0430"
    ],
    "name:urd_x_preferred":[
        "\u0642\u0627\u0646\u0627"
    ],
    "wof:name":"Cana",
    "wof:placetype":"locality"
},
  "geometry": {"coordinates":[-74.83803,-11.75951],"type":"Point"}
}