{
  "type": "Feature",
  "properties": {
    "gn:admin1_code":"12",
    "gn:admin2_code":"1202.0",
    "gn:admin3_code":"120203.0",
    "gn:asciiname":"Cana",
    "gn:country_code":"PE",
    "gn:dem":2681,
    "gn:feature_class":"P",
    "gn:feature_code":"PPL",
    "gn:name":"Ca\u00f1a",
    "gn:population":0,
    "gn:timezone":"America/Lima",
    "iso:country":"PE",
    "wof:name":"Cana",
    "wof:placetype":"locality"
},
  "geometry": {"coordinates":[-74.83803,-11.75951],"type":"Point"}
}