{
  "type": "Feature",
  "properties": {
    "gn:admin1_code":"04",
    "gn:admin2_code":"406.0",
    "gn:admin3_code":"40603.0",
    "gn:asciiname":"Huanajahua",
    "gn:country_code":"PE",
    "gn:dem":4682,
    "gn:feature_class":"P",
    "gn:feature_code":"PPL",
    "gn:name":"Hua\u00f1ajahua",
    "gn:population":0,
    "gn:timezone":"America/Lima",
    "iso:country":"PE",
    "wof:name":"Huanajahua",
    "wof:placetype":"locality"
},
  "geometry": {"coordinates":[-72.40079,-15.04368],"type":"Point"}
}