{
  "type": "Feature",
  "properties": {
    "gn:admin1_code":"5.0",
    "gn:admin2_code":"504.0",
    "gn:asciiname":"Mayhuavilca",
    "gn:country_code":"PE",
    "gn:dem":3510,
    "gn:feature_class":"P",
    "gn:feature_code":"PPL",
    "gn:name":"Mayhuavilca",
    "gn:population":0,
    "gn:timezone":"America/Lima",
    "iso:country":"PE",
    "name:spa_x_preferred":[
        "Mayhuavilca"
    ],
    "wof:name":"Mayhuavilca",
    "wof:placetype":"locality"
},
  "geometry": {"coordinates":[-74.38158,-12.42663],"type":"Point"}
}