{
  "type": "Feature",
  "properties": {
    "gn:admin1_code":"22",
    "gn:admin2_code":"2201.0",
    "gn:admin3_code":"220101.0",
    "gn:asciiname":"Quillualpa",
    "gn:country_code":"PE",
    "gn:dem":1024,
    "gn:feature_class":"P",
    "gn:feature_code":"PPL",
    "gn:name":"Quillualpa",
    "gn:population":0,
    "gn:timezone":"America/Lima",
    "iso:country":"PE",
    "name:und_x_variant":[
        "Quilluallpa",
        "Quillualpa"
    ],
    "wof:name":"Quillualpa",
    "wof:placetype":"locality"
},
  "geometry": {"coordinates":[-76.93938,-5.92731],"type":"Point"}
}