{
  "type": "Feature",
  "properties": {
    "gn:admin1_code":"5",
    "gn:admin2_code":"509.0",
    "gn:admin3_code":"50911.0",
    "gn:asciiname":"Huayllane",
    "gn:country_code":"PE",
    "gn:dem":4142,
    "gn:feature_class":"P",
    "gn:feature_code":"PPL",
    "gn:name":"Huayllane",
    "gn:population":0,
    "gn:timezone":"America/Lima",
    "iso:country":"PE",
    "wof:name":"Huayllane",
    "wof:placetype":"locality"
},
  "geometry": {"coordinates":[-73.74556,-14.21889],"type":"Point"}
}