{
  "type": "Feature",
  "properties": {
    "gn:admin1_code":"05",
    "gn:admin2_code":"506.0",
    "gn:admin3_code":"50619.0",
    "gn:asciiname":"Rosas Chayoc",
    "gn:country_code":"PE",
    "gn:dem":2804,
    "gn:feature_class":"P",
    "gn:feature_code":"PPL",
    "gn:name":"Rosas Chayoc",
    "gn:population":0,
    "gn:timezone":"America/Lima",
    "iso:country":"PE",
    "wof:name":"Rosas Chayoc",
    "wof:placetype":"locality"
},
  "geometry": {"coordinates":[-74.21358000000002,-15.09789],"type":"Point"}
}