{
  "type": "Feature",
  "properties": {
    "gn:admin1_code":"11",
    "gn:admin2_code":"1105.0",
    "gn:admin3_code":"110504.0",
    "gn:asciiname":"Moll",
    "gn:country_code":"PE",
    "gn:dem":300,
    "gn:feature_class":"P",
    "gn:feature_code":"PPL",
    "gn:name":"Moll",
    "gn:population":0,
    "gn:timezone":"America/Lima",
    "iso:country":"PE",
    "name:cat_x_preferred":[
        "Moll"
    ],
    "name:ceb_x_preferred":[
        "Moll"
    ],
    "name:deu_x_preferred":[
        "Moll"
    ],
    "name:fra_x_preferred":[
        "Moll"
    ],
    "name:ita_x_preferred":[
        "Moll"
    ],
    "name:nld_x_preferred":[
        "Moll"
    ],
    "name:rus_x_preferred":[
        "\u041c\u043e\u043b\u043b\u044c"
    ],
    "name:spa_x_preferred":[
        "Moll"
    ],
    "wof:name":"Moll",
    "wof:placetype":"locality"
},
  "geometry": {"coordinates":[-76.00468000000002,-13.63504],"type":"Point"}
}