{
  "type": "Feature",
  "properties": {
    "gn:admin1_code":"12",
    "gn:admin2_code":"1207.0",
    "gn:admin3_code":"120702.0",
    "gn:asciiname":"Hualhuash",
    "gn:country_code":"PE",
    "gn:dem":3000,
    "gn:feature_class":"P",
    "gn:feature_code":"PPL",
    "gn:name":"Hualhuash",
    "gn:population":0,
    "gn:timezone":"America/Lima",
    "iso:country":"PE",
    "wof:name":"Hualhuash",
    "wof:placetype":"locality"
},
  "geometry": {"coordinates":[-75.68333,-11.36667],"type":"Point"}
}