{
  "type": "Feature",
  "properties": {
    "gn:admin1_code":"20",
    "gn:admin2_code":"2002.0",
    "gn:admin3_code":"200206.0",
    "gn:asciiname":"Cumbicus",
    "gn:country_code":"PE",
    "gn:dem":2355,
    "gn:feature_class":"P",
    "gn:feature_code":"PPL",
    "gn:name":"Cumbicus",
    "gn:population":0,
    "gn:timezone":"America/Lima",
    "iso:country":"PE",
    "name:und_x_variant":[
        "Cumbicus Hacienda",
        "Cumbicus"
    ],
    "wof:name":"Cumbicus",
    "wof:placetype":"locality"
},
  "geometry": {"coordinates":[-79.62285,-5.01667],"type":"Point"}
}