{
  "type": "Feature",
  "properties": {
    "gn:admin1_code":"15",
    "gn:admin2_code":"1506.0",
    "gn:admin3_code":"150601.0",
    "gn:asciiname":"Pozo Azul",
    "gn:country_code":"PE",
    "gn:dem":209,
    "gn:feature_class":"P",
    "gn:feature_code":"PPL",
    "gn:name":"Pozo Azul",
    "gn:population":0,
    "gn:timezone":"America/Lima",
    "iso:country":"PE",
    "wof:name":"Pozo Azul",
    "wof:placetype":"locality"
},
  "geometry": {"coordinates":[-77.18639,-11.50472],"type":"Point"}
}