{
  "type": "Feature",
  "properties": {
    "gn:admin1_code":"4",
    "gn:admin2_code":"405.0",
    "gn:admin3_code":"40517.0",
    "gn:asciiname":"Cataque Puquio",
    "gn:country_code":"PE",
    "gn:dem":4380,
    "gn:feature_class":"P",
    "gn:feature_code":"PPL",
    "gn:name":"Cataque Puquio",
    "gn:population":0,
    "gn:timezone":"America/Lima",
    "iso:country":"PE",
    "wof:name":"Cataque Puquio",
    "wof:placetype":"locality"
},
  "geometry": {"coordinates":[-71.40878000000002,-15.30741],"type":"Point"}
}