{
  "type": "Feature",
  "properties": {
    "gn:admin1_code":"05",
    "gn:admin2_code":"506.0",
    "gn:admin3_code":"50602.0",
    "gn:asciiname":"Espinozayoc",
    "gn:country_code":"PE",
    "gn:dem":3995,
    "gn:feature_class":"P",
    "gn:feature_code":"PPL",
    "gn:name":"Espinozayoc",
    "gn:population":0,
    "gn:timezone":"America/Lima",
    "iso:country":"PE",
    "wof:name":"Espinozayoc",
    "wof:placetype":"locality"
},
  "geometry": {"coordinates":[-74.37978000000003,-14.20941],"type":"Point"}
}