{
  "type": "Feature",
  "properties": {
    "gn:admin1_code":"3",
    "gn:admin2_code":"302.0",
    "gn:admin3_code":"30209.0",
    "gn:asciiname":"Tarhue Pata",
    "gn:country_code":"PE",
    "gn:dem":3047,
    "gn:feature_class":"P",
    "gn:feature_code":"PPL",
    "gn:name":"Tarhue Pata",
    "gn:population":0,
    "gn:timezone":"America/Lima",
    "iso:country":"PE",
    "wof:name":"Tarhue Pata",
    "wof:placetype":"locality"
},
  "geometry": {"coordinates":[-73.35616999999998,-13.58657],"type":"Point"}
}