{
  "type": "Feature",
  "properties": {
    "gn:admin1_code":"10.0",
    "gn:admin2_code":"1005.0",
    "gn:admin3_code":"100501.0",
    "gn:asciiname":"Purpuro",
    "gn:country_code":"PE",
    "gn:dem":3973,
    "gn:feature_class":"P",
    "gn:feature_code":"PPL",
    "gn:name":"Purpuro",
    "gn:population":0,
    "gn:timezone":"America/Lima",
    "iso:country":"PE",
    "wof:name":"Purpuro",
    "wof:placetype":"locality"
},
  "geometry": {"coordinates":[-76.76647,-9.59252],"type":"Point"}
}