{
  "type": "Feature",
  "properties": {
    "gn:admin1_code":"12.0",
    "gn:admin2_code":"1204.0",
    "gn:admin3_code":"120405.0",
    "gn:asciiname":"Cruzpata",
    "gn:country_code":"PE",
    "gn:dem":4187,
    "gn:feature_class":"P",
    "gn:feature_code":"PPL",
    "gn:name":"Cruzpata",
    "gn:population":0,
    "gn:timezone":"America/Lima",
    "iso:country":"PE",
    "wof:name":"Cruzpata",
    "wof:placetype":"locality"
},
  "geometry": {"coordinates":[-75.70326999999997,-11.96271],"type":"Point"}
}