{
  "type": "Feature",
  "properties": {
    "gn:admin1_code":"11.0",
    "gn:admin2_code":"1102.0",
    "gn:admin3_code":"110208.0",
    "gn:asciiname":"Iscu",
    "gn:country_code":"PE",
    "gn:dem":1959,
    "gn:feature_class":"P",
    "gn:feature_code":"PPL",
    "gn:name":"Iscu",
    "gn:population":0,
    "gn:timezone":"America/Lima",
    "iso:country":"PE",
    "name:spa_x_preferred":[
        "Iscu"
    ],
    "wof:name":"Iscu",
    "wof:placetype":"locality"
},
  "geometry": {"coordinates":[-75.89423000000002,-13.212],"type":"Point"}
}