{
  "type": "Feature",
  "properties": {
    "gn:admin1_code":"10.0",
    "gn:admin2_code":"1001.0",
    "gn:admin3_code":"100101.0",
    "gn:asciiname":"Jigaragra",
    "gn:country_code":"PE",
    "gn:dem":2631,
    "gn:feature_class":"P",
    "gn:feature_code":"PPL",
    "gn:name":"Jigaragra",
    "gn:population":0,
    "gn:timezone":"America/Lima",
    "iso:country":"PE",
    "wof:name":"Jigaragra",
    "wof:placetype":"locality"
},
  "geometry": {"coordinates":[-76.30964,-9.89953],"type":"Point"}
}