{
  "type": "Feature",
  "properties": {
    "gn:country":"PE",
    "gn:fcode":"PPLX",
    "gn:population":0,
    "iso:country":"PE",
    "name:spa_x_preferred":[
        "Santa Luisa"
    ],
    "name:spa_x_variant":[
        "Sta. Luisa",
        "Sta Luisa"
    ],
    "qs:gn_adm0_cc":"PE",
    "qs:gn_fcode":"PPLX",
    "qs:gn_local":3947322,
    "qs:gn_nam_loc":"Arequipa",
    "qs:gn_namadm1":"04",
    "qs:gn_name":"Santa Luisa",
    "qs:local_max":8512,
    "qs:local_sum":10013,
    "qs:localhoods":9,
    "qs:name":"Santa Luisa",
    "qs:name_adm0":"Per\u00fa",
    "qs:name_adm1":"Arequipa",
    "qs:name_adm2":"Arequipa",
    "qs:name_local":"Arequipa",
    "qs:photo_max":34,
    "qs:photo_sum":66,
    "qs:placetype":"Suburb",
    "qs:quad_count":9,
    "qs:woe_adm0":23424919,
    "qs:woe_adm1":2346471,
    "qs:woe_adm2":26805784,
    "qs:woe_lau":0,
    "qs:woe_local":418442,
    "qs:woe_ver":"7.10.0",
    "qs_pg:aaroncc":"PE",
    "qs_pg:gn_country":"PE",
    "qs_pg:gn_fcode":"PPLX",
    "qs_pg:gn_pop":0,
    "qs_pg:name":"Santa Luisa",
    "qs_pg:name_adm0":"Per\u00fa",
    "qs_pg:name_adm1":"Arequipa",
    "qs_pg:photos":88,
    "qs_pg:photos_1k":18,
    "qs_pg:photos_9k":1,
    "qs_pg:photos_9r":3,
    "qs_pg:photos_all":88,
    "qs_pg:photos_sr":3,
    "qs_pg:pop_sr":0,
    "qs_pg:qs_pg_placetype":"neighbourhood",
    "qs_pg:qs_pg_placetype_gp":"Suburb",
    "qs_pg:woe_adm0":23424919,
    "wof:lang":[
        "spa"
    ],
    "wof:name":"Santa Luisa",
    "wof:placetype":"neighbourhood"
},
  "geometry": {"coordinates":[-71.52583199999999,-16.37875],"type":"Point"}
}