{
  "type": "Feature",
  "properties": {
    "gn:admin1_code":"4",
    "gn:admin2_code":"403.0",
    "gn:admin3_code":"40305.0",
    "gn:asciiname":"Pampa Redonda Chica",
    "gn:country_code":"PE",
    "gn:dem":608,
    "gn:feature_class":"P",
    "gn:feature_code":"PPL",
    "gn:name":"Pampa Redonda Chica",
    "gn:population":0,
    "gn:timezone":"America/Lima",
    "iso:country":"PE",
    "wof:name":"Pampa Redonda Chica",
    "wof:placetype":"locality"
},
  "geometry": {"coordinates":[-74.55461,-15.22951],"type":"Point"}
}