{
  "type": "Feature",
  "properties": {
    "gn:admin1_code":"12.0",
    "gn:admin2_code":"1201.0",
    "gn:admin3_code":"120130.0",
    "gn:asciiname":"Lastay",
    "gn:country_code":"PE",
    "gn:dem":3419,
    "gn:feature_class":"P",
    "gn:feature_code":"PPL",
    "gn:name":"Lastay",
    "gn:population":0,
    "gn:timezone":"America/Lima",
    "iso:country":"PE",
    "wof:name":"Lastay",
    "wof:placetype":"locality"
},
  "geometry": {"coordinates":[-75.28555,-11.9132],"type":"Point"}
}