{
  "type": "Feature",
  "properties": {
    "gn:admin1_code":"12",
    "gn:admin2_code":"1207.0",
    "gn:admin3_code":"120707.0",
    "gn:asciiname":"Guagapo",
    "gn:country_code":"PE",
    "gn:dem":3608,
    "gn:feature_class":"P",
    "gn:feature_code":"PPL",
    "gn:name":"Guagapo",
    "gn:population":0,
    "gn:timezone":"America/Lima",
    "iso:country":"PE",
    "name:und_x_variant":[
        "Cuaganno"
    ],
    "wof:name":"Guagapo",
    "wof:placetype":"locality"
},
  "geometry": {"coordinates":[-75.78935,-11.27013],"type":"Point"}
}