{
  "type": "Feature",
  "properties": {
    "gn:admin1_code":"06",
    "gn:admin2_code":"603.0",
    "gn:admin3_code":"60312.0",
    "gn:asciiname":"Sigues",
    "gn:country_code":"PE",
    "gn:dem":2165,
    "gn:feature_class":"P",
    "gn:feature_code":"PPL",
    "gn:name":"Sigues",
    "gn:population":0,
    "gn:timezone":"America/Lima",
    "iso:country":"PE",
    "wof:name":"Sigues",
    "wof:placetype":"locality"
},
  "geometry": {"coordinates":[-78.22544000000001,-6.76499],"type":"Point"}
}