{
  "type": "Feature",
  "properties": {
    "gn:admin1_code":"10.0",
    "gn:admin2_code":"1011.0",
    "gn:admin3_code":"101104.0",
    "gn:asciiname":"Shayhua",
    "gn:country_code":"PE",
    "gn:dem":3371,
    "gn:feature_class":"P",
    "gn:feature_code":"PPL",
    "gn:name":"Shayhua",
    "gn:population":0,
    "gn:timezone":"America/Lima",
    "iso:country":"PE",
    "wof:name":"Shayhua",
    "wof:placetype":"locality"
},
  "geometry": {"coordinates":[-76.64719000000002,-9.73043],"type":"Point"}
}