{
  "type": "Feature",
  "properties": {
    "gn:admin1_code":"9",
    "gn:admin2_code":"906.0",
    "gn:admin3_code":"90607.0",
    "gn:asciiname":"Ayapauman",
    "gn:country_code":"PE",
    "gn:dem":4763,
    "gn:feature_class":"P",
    "gn:feature_code":"PPL",
    "gn:name":"Ayapauman",
    "gn:population":0,
    "gn:timezone":"America/Lima",
    "iso:country":"PE",
    "name:und_x_variant":[
        "Ayapa Uman"
    ],
    "wof:name":"Ayapauman",
    "wof:placetype":"locality"
},
  "geometry": {"coordinates":[-74.91725,-13.238],"type":"Point"}
}