{
  "type": "Feature",
  "properties": {
    "gn:admin1_code":"14",
    "gn:admin2_code":"1402.0",
    "gn:admin3_code":"140205.0",
    "gn:asciiname":"Otoya",
    "gn:country_code":"PE",
    "gn:dem":37,
    "gn:feature_class":"P",
    "gn:feature_code":"PPL",
    "gn:name":"Otoya",
    "gn:population":0,
    "gn:timezone":"America/Lima",
    "iso:country":"PE",
    "name:spa_x_preferred":[
        "Otoya"
    ],
    "wof:name":"Otoya",
    "wof:placetype":"locality"
},
  "geometry": {"coordinates":[-79.81393,-6.57285],"type":"Point"}
}