{
  "type": "Feature",
  "properties": {
    "gn:admin1_code":"9",
    "gn:admin2_code":"906.0",
    "gn:admin3_code":"90616.0",
    "gn:asciiname":"Tastapata",
    "gn:country_code":"PE",
    "gn:dem":4391,
    "gn:feature_class":"P",
    "gn:feature_code":"PPL",
    "gn:name":"Tastapata",
    "gn:population":0,
    "gn:timezone":"America/Lima",
    "iso:country":"PE",
    "wof:name":"Tastapata",
    "wof:placetype":"locality"
},
  "geometry": {"coordinates":[-75.26889,-13.64111],"type":"Point"}
}