{
  "type": "Feature",
  "properties": {
    "gn:admin1_code":"23",
    "gn:admin2_code":"2302.0",
    "gn:admin3_code":"230203.0",
    "gn:asciiname":"Vitalaca",
    "gn:country_code":"PE",
    "gn:dem":3040,
    "gn:feature_class":"P",
    "gn:feature_code":"PPL",
    "gn:name":"Vitalaca",
    "gn:population":0,
    "gn:timezone":"America/Lima",
    "iso:country":"PE",
    "wof:name":"Vitalaca",
    "wof:placetype":"locality"
},
  "geometry": {"coordinates":[-70.42962,-17.28994],"type":"Point"}
}