{
  "type": "Feature",
  "properties": {
    "gn:admin1_code":"22",
    "gn:admin2_code":"2206.0",
    "gn:admin3_code":"220603.0",
    "gn:asciiname":"Achiras",
    "gn:country_code":"PE",
    "gn:dem":1855,
    "gn:feature_class":"P",
    "gn:feature_code":"PPL",
    "gn:name":"Achiras",
    "gn:population":0,
    "gn:timezone":"America/Lima",
    "iso:country":"PE",
    "wof:name":"Achiras",
    "wof:placetype":"locality"
},
  "geometry": {"coordinates":[-77.12324,-7.72829],"type":"Point"}
}