{
  "type": "Feature",
  "properties": {
    "gn:admin1_code":"15",
    "gn:admin2_code":"1510.0",
    "gn:admin3_code":"151011.0",
    "gn:asciiname":"Huyzapampa",
    "gn:country_code":"PE",
    "gn:dem":3018,
    "gn:feature_class":"P",
    "gn:feature_code":"PPL",
    "gn:name":"Huyzapampa",
    "gn:population":0,
    "gn:timezone":"America/Lima",
    "iso:country":"PE",
    "wof:name":"Huyzapampa",
    "wof:placetype":"locality"
},
  "geometry": {"coordinates":[-75.87591,-12.55265],"type":"Point"}
}