{
  "type": "Feature",
  "properties": {
    "gn:admin1_code":"15",
    "gn:admin2_code":"1508.0",
    "gn:admin3_code":"150811.0",
    "gn:asciiname":"Chuquiquintay",
    "gn:country_code":"PE",
    "gn:dem":730,
    "gn:feature_class":"P",
    "gn:feature_code":"PPL",
    "gn:name":"Chuquiquintay",
    "gn:population":0,
    "gn:timezone":"America/Lima",
    "iso:country":"PE",
    "wof:name":"Chuquiquintay",
    "wof:placetype":"locality"
},
  "geometry": {"coordinates":[-77.17806,-11.10722],"type":"Point"}
}