{
  "type": "Feature",
  "properties": {
    "gn:admin1_code":"21",
    "gn:admin2_code":"2104.0",
    "gn:admin3_code":"210401.0",
    "gn:asciiname":"Moyopampa",
    "gn:country_code":"PE",
    "gn:dem":3826,
    "gn:feature_class":"P",
    "gn:feature_code":"PPL",
    "gn:name":"Moyopampa",
    "gn:population":0,
    "gn:timezone":"America/Lima",
    "iso:country":"PE",
    "wof:name":"Moyopampa",
    "wof:placetype":"locality"
},
  "geometry": {"coordinates":[-69.50089,-16.2127],"type":"Point"}
}