{
  "type": "Feature",
  "properties": {
    "gn:admin1_code":"13",
    "gn:admin2_code":"1308.0",
    "gn:admin3_code":"130810.0",
    "gn:asciiname":"Llaupa",
    "gn:country_code":"PE",
    "gn:dem":2465,
    "gn:feature_class":"P",
    "gn:feature_code":"PPL",
    "gn:name":"Llaupa",
    "gn:population":0,
    "gn:timezone":"America/Lima",
    "iso:country":"PE",
    "wof:name":"Llaupa",
    "wof:placetype":"locality"
},
  "geometry": {"coordinates":[-77.54809,-7.93952],"type":"Point"}
}