{
  "type": "Feature",
  "properties": {
    "gn:admin1_code":"15",
    "gn:admin2_code":"1510.0",
    "gn:admin3_code":"151011.0",
    "gn:asciiname":"Pilla",
    "gn:country_code":"PE",
    "gn:dem":3605,
    "gn:feature_class":"P",
    "gn:feature_code":"PPL",
    "gn:name":"Pilla",
    "gn:population":0,
    "gn:timezone":"America/Lima",
    "iso:country":"PE",
    "wof:name":"Pilla",
    "wof:placetype":"locality"
},
  "geometry": {"coordinates":[-75.87414,-12.64083],"type":"Point"}
}