{
  "type": "Feature",
  "properties": {
    "gn:admin1_code":"10.0",
    "gn:admin2_code":"1011.0",
    "gn:admin3_code":"101106.0",
    "gn:asciiname":"Pampa Corral",
    "gn:country_code":"PE",
    "gn:dem":3651,
    "gn:feature_class":"P",
    "gn:feature_code":"PPL",
    "gn:name":"Pampa Corral",
    "gn:population":0,
    "gn:timezone":"America/Lima",
    "iso:country":"PE",
    "wof:name":"Pampa Corral",
    "wof:placetype":"locality"
},
  "geometry": {"coordinates":[-76.67983000000002,-9.84772],"type":"Point"}
}