{
  "type": "Feature",
  "properties": {
    "gn:admin1_code":"11",
    "gn:admin2_code":"1103.0",
    "gn:asciiname":"Pulla",
    "gn:country_code":"PE",
    "gn:dem":2014,
    "gn:feature_class":"P",
    "gn:feature_code":"PPL",
    "gn:name":"Pulla",
    "gn:population":0,
    "gn:timezone":"America/Lima",
    "iso:country":"PE",
    "name:ara_x_preferred":[
        "\u0628\u0648\u0644\u0627"
    ],
    "name:bar_x_preferred":[
        "Pulla"
    ],
    "name:deu_x_preferred":[
        "Pulla"
    ],
    "name:fin_x_preferred":[
        "Pulla"
    ],
    "name:pol_x_preferred":[
        "Pulla"
    ],
    "name:por_x_preferred":[
        "Pulla"
    ],
    "name:spa_x_preferred":[
        "Pulla"
    ],
    "wof:name":"Pulla",
    "wof:placetype":"locality"
},
  "geometry": {"coordinates":[-74.6982,-14.85277],"type":"Point"}
}