{
  "type": "Feature",
  "properties": {
    "gn:admin1_code":"04",
    "gn:admin2_code":"405.0",
    "gn:admin3_code":"40505.0",
    "gn:asciiname":"Limahuiri",
    "gn:country_code":"PE",
    "gn:dem":4296,
    "gn:feature_class":"P",
    "gn:feature_code":"PPL",
    "gn:name":"Limahuiri",
    "gn:population":0,
    "gn:timezone":"America/Lima",
    "iso:country":"PE",
    "wof:name":"Limahuiri",
    "wof:placetype":"locality"
},
  "geometry": {"coordinates":[-71.73528,-15.15889],"type":"Point"}
}