{
  "type": "Feature",
  "properties": {
    "gn:admin1_code":"11",
    "gn:admin2_code":"1101.0",
    "gn:admin3_code":"110105.0",
    "gn:asciiname":"Pachacute",
    "gn:country_code":"PE",
    "gn:dem":410,
    "gn:feature_class":"P",
    "gn:feature_code":"PPL",
    "gn:name":"Pachacute",
    "gn:population":0,
    "gn:timezone":"America/Lima",
    "iso:country":"PE",
    "name:spa_x_preferred":[
        "Pachacute"
    ],
    "name:spa_x_variant":[
        "Pampa de Tate"
    ],
    "wof:name":"Pachacute",
    "wof:placetype":"locality"
},
  "geometry": {"coordinates":[-75.69179,-14.1453],"type":"Point"}
}