{
  "type": "Feature",
  "properties": {
    "gn:admin1_code":"05",
    "gn:admin2_code":"501.0",
    "gn:admin3_code":"50114.0",
    "gn:asciiname":"Ojo Pampa",
    "gn:country_code":"PE",
    "gn:dem":3534,
    "gn:feature_class":"P",
    "gn:feature_code":"PPL",
    "gn:name":"Ojo Pampa",
    "gn:population":0,
    "gn:timezone":"America/Lima",
    "iso:country":"PE",
    "name:und_x_variant":[
        "Ojopampa"
    ],
    "wof:name":"Ojo Pampa",
    "wof:placetype":"locality"
},
  "geometry": {"coordinates":[-74.44278,-13.23626],"type":"Point"}
}