{
  "type": "Feature",
  "properties": {
    "gn:admin1_code":"22",
    "gn:admin2_code":"2206.0",
    "gn:admin3_code":"220603.0",
    "gn:asciiname":"Juscusbamba",
    "gn:country_code":"PE",
    "gn:dem":1807,
    "gn:feature_class":"P",
    "gn:feature_code":"PPL",
    "gn:name":"Juscusbamba",
    "gn:population":0,
    "gn:timezone":"America/Lima",
    "iso:country":"PE",
    "name:und_x_variant":[
        "Iucusbamba",
        "Jacusbamba",
        "Jucusbamba",
        "Juscusbamba"
    ],
    "wof:name":"Juscusbamba",
    "wof:placetype":"locality"
},
  "geometry": {"coordinates":[-77.185,-7.87864],"type":"Point"}
}