{
  "type": "Feature",
  "properties": {
    "gn:admin1_code":"20",
    "gn:admin2_code":"2004.0",
    "gn:admin3_code":"200402.0",
    "gn:asciiname":"La Maravilla",
    "gn:country_code":"PE",
    "gn:dem":155,
    "gn:feature_class":"P",
    "gn:feature_code":"PPL",
    "gn:name":"La Maravilla",
    "gn:population":0,
    "gn:timezone":"America/Lima",
    "iso:country":"PE",
    "name:und_x_variant":[
        "Maravilla",
        "La Maravilla"
    ],
    "wof:name":"La Maravilla",
    "wof:placetype":"locality"
},
  "geometry": {"coordinates":[-79.9385,-5.22587],"type":"Point"}
}