{
  "type": "Feature",
  "properties": {
    "gn:admin1_code":"14",
    "gn:admin2_code":"1402.0",
    "gn:admin3_code":"140203.0",
    "gn:asciiname":"Hacienda Occhapampa",
    "gn:country_code":"PE",
    "gn:dem":1171,
    "gn:feature_class":"P",
    "gn:feature_code":"PPL",
    "gn:name":"Hacienda Occhapampa",
    "gn:population":0,
    "gn:timezone":"America/Lima",
    "iso:country":"PE",
    "wof:name":"Hacienda Occhapampa",
    "wof:placetype":"locality"
},
  "geometry": {"coordinates":[-79.4371,-6.29927],"type":"Point"}
}