{
  "type": "Feature",
  "properties": {
    "gn:admin1_code":"3",
    "gn:admin2_code":"302.0",
    "gn:admin3_code":"30212.0",
    "gn:asciiname":"Cachihuancaray",
    "gn:country_code":"PE",
    "gn:dem":3643,
    "gn:feature_class":"P",
    "gn:feature_code":"PPL",
    "gn:name":"Cachihuancaray",
    "gn:population":0,
    "gn:timezone":"America/Lima",
    "iso:country":"PE",
    "wof:name":"Cachihuancaray",
    "wof:placetype":"locality"
},
  "geometry": {"coordinates":[-73.59036,-13.78435],"type":"Point"}
}