{
  "type": "Feature",
  "properties": {
    "gn:admin1_code":"06",
    "gn:admin2_code":"608.0",
    "gn:asciiname":"La Cerma",
    "gn:country_code":"PE",
    "gn:dem":398,
    "gn:feature_class":"P",
    "gn:feature_code":"PPL",
    "gn:name":"La Cerma",
    "gn:population":0,
    "gn:timezone":"America/Lima",
    "iso:country":"PE",
    "wof:name":"La Cerma",
    "wof:placetype":"locality"
},
  "geometry": {"coordinates":[-78.63460000000001,-5.623],"type":"Point"}
}