{
  "type": "Feature",
  "properties": {
    "gn:admin1_code":"5",
    "gn:admin2_code":"503.0",
    "gn:admin3_code":"50304.0",
    "gn:asciiname":"Yanacolpa",
    "gn:country_code":"PE",
    "gn:dem":4264,
    "gn:feature_class":"P",
    "gn:feature_code":"PPL",
    "gn:name":"Yanacolpa",
    "gn:population":0,
    "gn:timezone":"America/Lima",
    "iso:country":"PE",
    "wof:name":"Yanacolpa",
    "wof:placetype":"locality"
},
  "geometry": {"coordinates":[-74.57222,-13.83833],"type":"Point"}
}