{
  "type": "Feature",
  "properties": {
    "gn:admin1_code":"15",
    "gn:admin2_code":"1507.0",
    "gn:admin3_code":"150722.0",
    "gn:asciiname":"La Caliza",
    "gn:country_code":"PE",
    "gn:dem":3448,
    "gn:feature_class":"P",
    "gn:feature_code":"PPL",
    "gn:name":"La Caliza",
    "gn:population":0,
    "gn:timezone":"America/Lima",
    "iso:country":"PE",
    "wof:name":"La Caliza",
    "wof:placetype":"locality"
},
  "geometry": {"coordinates":[-76.28749999999999,-11.74889],"type":"Point"}
}