{
  "type": "Feature",
  "properties": {
    "gn:admin1_code":"05",
    "gn:admin2_code":"506.0",
    "gn:admin3_code":"50621.0",
    "gn:asciiname":"Chillca",
    "gn:country_code":"PE",
    "gn:dem":3170,
    "gn:feature_class":"P",
    "gn:feature_code":"PPL",
    "gn:name":"Chillca",
    "gn:population":0,
    "gn:timezone":"America/Lima",
    "iso:country":"PE",
    "name:und_x_variant":[
        "Chilca",
        "Chillca Hacienda",
        "Chillca"
    ],
    "wof:name":"Chillca",
    "wof:placetype":"locality"
},
  "geometry": {"coordinates":[-74.48387,-14.81446],"type":"Point"}
}