{
  "type": "Feature",
  "properties": {
    "gn:admin1_code":"04",
    "gn:admin2_code":"404.0",
    "gn:admin3_code":"40413.0",
    "gn:asciiname":"Paican",
    "gn:country_code":"PE",
    "gn:dem":270,
    "gn:feature_class":"P",
    "gn:feature_code":"PPL",
    "gn:name":"Paican",
    "gn:population":0,
    "gn:timezone":"America/Lima",
    "iso:country":"PE",
    "name:und_x_variant":[
        "Hacienda Paican",
        "Paican Hacienda",
        "Paican"
    ],
    "wof:name":"Paican",
    "wof:placetype":"locality"
},
  "geometry": {"coordinates":[-72.51609000000001,-16.39608],"type":"Point"}
}