{
  "type": "Feature",
  "properties": {
    "gn:admin1_code":"05",
    "gn:admin2_code":"507.0",
    "gn:admin3_code":"50706.0",
    "gn:asciiname":"Quishuarani",
    "gn:country_code":"PE",
    "gn:dem":3300,
    "gn:feature_class":"P",
    "gn:feature_code":"PPL",
    "gn:name":"Quishuarani",
    "gn:population":0,
    "gn:timezone":"America/Lima",
    "iso:country":"PE",
    "name:und_x_variant":[
        "Hacienda Quishuarani",
        "Quishuarani Hacienda",
        "Quishuarani"
    ],
    "wof:name":"Quishuarani",
    "wof:placetype":"locality"
},
  "geometry": {"coordinates":[-73.58709,-15.24193],"type":"Point"}
}