{
  "type": "Feature",
  "properties": {
    "gn:admin1_code":"5.0",
    "gn:admin2_code":"504.0",
    "gn:admin3_code":"50401.0",
    "gn:asciiname":"Huaychao",
    "gn:country_code":"PE",
    "gn:dem":3839,
    "gn:feature_class":"P",
    "gn:feature_code":"PPL",
    "gn:name":"Huaychao",
    "gn:population":0,
    "gn:timezone":"America/Lima",
    "iso:country":"PE",
    "wof:name":"Huaychao",
    "wof:placetype":"locality"
},
  "geometry": {"coordinates":[-74.11154000000001,-12.77388],"type":"Point"}
}