{
  "type": "Feature",
  "properties": {
    "gn:admin1_code":"12",
    "gn:admin2_code":"1202.0",
    "gn:admin3_code":"120203.0",
    "gn:asciiname":"Tacupata",
    "gn:country_code":"PE",
    "gn:dem":2454,
    "gn:feature_class":"P",
    "gn:feature_code":"PPL",
    "gn:name":"Tacupata",
    "gn:population":0,
    "gn:timezone":"America/Lima",
    "iso:country":"PE",
    "wof:name":"Tacupata",
    "wof:placetype":"locality"
},
  "geometry": {"coordinates":[-74.78944,-11.72583],"type":"Point"}
}