{
  "type": "Feature",
  "properties": {
    "gn:admin1_code":"22.0",
    "gn:admin2_code":"2204.0",
    "gn:admin3_code":"220403.0",
    "gn:asciiname":"Puquio",
    "gn:country_code":"PE",
    "gn:dem":434,
    "gn:feature_class":"P",
    "gn:feature_code":"PPL",
    "gn:name":"Puquio",
    "gn:population":0,
    "gn:timezone":"America/Lima",
    "iso:country":"PE",
    "name:ara_x_preferred":[
        "\u0628\u0648\u0643\u0648\u064a\u0648"
    ],
    "name:aym_x_preferred":[
        "Pukyu"
    ],
    "name:ceb_x_preferred":[
        "Puquio"
    ],
    "name:fra_x_preferred":[
        "Puquio"
    ],
    "name:ita_x_preferred":[
        "Puquio"
    ],
    "name:lit_x_preferred":[
        "Pukijas"
    ],
    "name:pol_x_preferred":[
        "Puquio"
    ],
    "name:que_x_preferred":[
        "Pukyu llaqta"
    ],
    "name:spa_x_preferred":[
        "Puquio"
    ],
    "name:war_x_preferred":[
        "Puquio"
    ],
    "name:zho_x_preferred":[
        "\u666e\u57fa\u5967"
    ],
    "wof:name":"Puquio",
    "wof:placetype":"locality"
},
  "geometry": {"coordinates":[-76.7491,-7.03156],"type":"Point"}
}