{
  "type": "Feature",
  "properties": {
    "gn:admin1_code":"13.0",
    "gn:admin2_code":"1301.0",
    "gn:admin3_code":"130101.0",
    "gn:asciiname":"La noria",
    "gn:country_code":"PE",
    "gn:dem":51,
    "gn:elevation":"10.0",
    "gn:feature_class":"P",
    "gn:feature_code":"PPL",
    "gn:name":"La noria",
    "gn:population":0,
    "gn:timezone":"America/Lima",
    "iso:country":"PE",
    "wof:name":"La noria",
    "wof:placetype":"locality"
},
  "geometry": {"coordinates":[-79.00851999999998,-8.10457],"type":"Point"}
}