{
  "type": "Feature",
  "properties": {
    "gn:admin1_code":"12",
    "gn:admin2_code":"1209.0",
    "gn:asciiname":"Viscacocha",
    "gn:country_code":"PE",
    "gn:dem":4556,
    "gn:feature_class":"P",
    "gn:feature_code":"PPL",
    "gn:name":"Viscacocha",
    "gn:population":0,
    "gn:timezone":"America/Lima",
    "iso:country":"PE",
    "wof:name":"Viscacocha",
    "wof:placetype":"locality"
},
  "geometry": {"coordinates":[-75.54163,-12.38366],"type":"Point"}
}