{
  "type": "Feature",
  "properties": {
    "gn:admin1_code":"8",
    "gn:admin2_code":"805.0",
    "gn:admin3_code":"80507.0",
    "gn:asciiname":"Huinchiri",
    "gn:country_code":"PE",
    "gn:dem":3765,
    "gn:feature_class":"P",
    "gn:feature_code":"PPL",
    "gn:name":"Huinchiri",
    "gn:population":0,
    "gn:timezone":"America/Lima",
    "iso:country":"PE",
    "wof:name":"Huinchiri",
    "wof:placetype":"locality"
},
  "geometry": {"coordinates":[-71.48935,-14.38302],"type":"Point"}
}