{
  "type": "Feature",
  "properties": {
    "gn:admin1_code":"11",
    "gn:admin2_code":"1104.0",
    "gn:admin3_code":"110403.0",
    "gn:asciiname":"Hacienda San Borjas",
    "gn:country_code":"PE",
    "gn:dem":348,
    "gn:feature_class":"P",
    "gn:feature_code":"PPL",
    "gn:name":"Hacienda San Borjas",
    "gn:population":0,
    "gn:timezone":"America/Lima",
    "iso:country":"PE",
    "wof:name":"Hacienda San Borjas",
    "wof:placetype":"locality"
},
  "geometry": {"coordinates":[-75.20222,-14.51806],"type":"Point"}
}