{
  "type": "Feature",
  "properties": {
    "gn:admin1_code":"20",
    "gn:admin2_code":"2004.0",
    "gn:admin3_code":"200403.0",
    "gn:asciiname":"Totera",
    "gn:country_code":"PE",
    "gn:dem":2192,
    "gn:feature_class":"P",
    "gn:feature_code":"PPL",
    "gn:name":"Totera",
    "gn:population":0,
    "gn:timezone":"America/Lima",
    "iso:country":"PE",
    "wof:name":"Totera",
    "wof:placetype":"locality"
},
  "geometry": {"coordinates":[-79.75997,-5.0466],"type":"Point"}
}