{
  "type": "Feature",
  "properties": {
    "gn:admin1_code":"16",
    "gn:admin2_code":"1601.0",
    "gn:admin3_code":"160104.0",
    "gn:asciiname":"Fatima",
    "gn:country_code":"PE",
    "gn:dem":101,
    "gn:feature_class":"P",
    "gn:feature_code":"PPL",
    "gn:name":"F\u00e1tima",
    "gn:population":0,
    "gn:timezone":"America/Lima",
    "iso:country":"PE",
    "wof:name":"Fatima",
    "wof:placetype":"locality"
},
  "geometry": {"coordinates":[-72.98658,-3.64233],"type":"Point"}
}