{
  "type": "Feature",
  "properties": {
    "gn:admin1_code":"05",
    "gn:admin2_code":"509.0",
    "gn:admin3_code":"50902.0",
    "gn:asciiname":"Socos",
    "gn:country_code":"PE",
    "gn:dem":2993,
    "gn:feature_class":"P",
    "gn:feature_code":"PPL",
    "gn:name":"Socos",
    "gn:population":0,
    "gn:timezone":"America/Lima",
    "iso:country":"PE",
    "wof:name":"Socos",
    "wof:placetype":"locality"
},
  "geometry": {"coordinates":[-73.78841,-13.81465],"type":"Point"}
}