{
  "type": "Feature",
  "properties": {
    "gn:admin1_code":"16",
    "gn:admin2_code":"1601.0",
    "gn:admin3_code":"160107.0",
    "gn:asciiname":"San Luis de Tacsha Curaray",
    "gn:country_code":"PE",
    "gn:dem":109,
    "gn:feature_class":"P",
    "gn:feature_code":"PPL",
    "gn:name":"San Luis de Tacsha Curaray",
    "gn:population":0,
    "gn:timezone":"America/Lima",
    "iso:country":"PE",
    "wof:name":"San Luis de Tacsha Curaray",
    "wof:placetype":"locality"
},
  "geometry": {"coordinates":[-73.54215000000001,-2.8055],"type":"Point"}
}