{
  "type": "Feature",
  "properties": {
    "gn:admin1_code":"06",
    "gn:admin2_code":"608.0",
    "gn:admin3_code":"60802.0",
    "gn:asciiname":"Monte Redondo",
    "gn:country_code":"PE",
    "gn:dem":1229,
    "gn:feature_class":"P",
    "gn:feature_code":"PPL",
    "gn:name":"Monte Redondo",
    "gn:population":0,
    "gn:timezone":"America/Lima",
    "iso:country":"PE",
    "wof:name":"Monte Redondo",
    "wof:placetype":"locality"
},
  "geometry": {"coordinates":[-78.85771,-5.53415],"type":"Point"}
}