{
  "type": "Feature",
  "properties": {
    "gn:admin1_code":"14",
    "gn:admin2_code":"1403.0",
    "gn:admin3_code":"140312.0",
    "gn:asciiname":"Chepito",
    "gn:country_code":"PE",
    "gn:dem":31,
    "gn:feature_class":"P",
    "gn:feature_code":"PPL",
    "gn:name":"Chepito",
    "gn:population":0,
    "gn:timezone":"America/Lima",
    "iso:country":"PE",
    "wof:name":"Chepito",
    "wof:placetype":"locality"
},
  "geometry": {"coordinates":[-79.93603,-6.52729],"type":"Point"}
}