{
  "type": "Feature",
  "properties": {
    "gn:admin1_code":"13",
    "gn:admin2_code":"1309.0",
    "gn:admin3_code":"130905.0",
    "gn:asciiname":"Machay",
    "gn:country_code":"PE",
    "gn:dem":2013,
    "gn:feature_class":"P",
    "gn:feature_code":"PPL",
    "gn:name":"Machay",
    "gn:population":0,
    "gn:timezone":"America/Lima",
    "iso:country":"PE",
    "name:zho_x_preferred":[
        "\u99ac\u67f4\u5c71"
    ],
    "wof:name":"Machay",
    "wof:placetype":"locality"
},
  "geometry": {"coordinates":[-77.86751,-7.72089],"type":"Point"}
}