{
  "type": "Feature",
  "properties": {
    "gn:admin1_code":"3.0",
    "gn:admin2_code":"305.0",
    "gn:admin3_code":"30502.0",
    "gn:asciiname":"Accomocco",
    "gn:country_code":"PE",
    "gn:dem":3107,
    "gn:feature_class":"P",
    "gn:feature_code":"PPL",
    "gn:name":"Accomocco",
    "gn:population":0,
    "gn:timezone":"America/Lima",
    "iso:country":"PE",
    "wof:name":"Accomocco",
    "wof:placetype":"locality"
},
  "geometry": {"coordinates":[-72.345,-13.74778],"type":"Point"}
}