{
  "type": "Feature",
  "properties": {
    "gn:admin1_code":"21",
    "gn:admin2_code":"2105.0",
    "gn:admin3_code":"210501.0",
    "gn:asciiname":"Tolacollo",
    "gn:country_code":"PE",
    "gn:dem":3982,
    "gn:feature_class":"P",
    "gn:feature_code":"PPL",
    "gn:name":"Tolacollo",
    "gn:population":0,
    "gn:timezone":"America/Lima",
    "iso:country":"PE",
    "wof:name":"Tolacollo",
    "wof:placetype":"locality"
},
  "geometry": {"coordinates":[-69.62721999999999,-16.30861],"type":"Point"}
}