{
  "type": "Feature",
  "properties": {
    "gn:admin1_code":"9.0",
    "gn:admin2_code":"901.0",
    "gn:admin3_code":"90103.0",
    "gn:asciiname":"Saccsa",
    "gn:country_code":"PE",
    "gn:dem":3234,
    "gn:feature_class":"P",
    "gn:feature_code":"PPL",
    "gn:name":"Saccsa",
    "gn:population":0,
    "gn:timezone":"America/Lima",
    "iso:country":"PE",
    "wof:name":"Saccsa",
    "wof:placetype":"locality"
},
  "geometry": {"coordinates":[-74.88376,-12.58377],"type":"Point"}
}