{
  "type": "Feature",
  "properties": {
    "gn:admin1_code":"17.0",
    "gn:admin2_code":"1703.0",
    "gn:asciiname":"Luchador",
    "gn:country_code":"PE",
    "gn:dem":293,
    "gn:feature_class":"P",
    "gn:feature_code":"PPL",
    "gn:name":"Luchador",
    "gn:population":0,
    "gn:timezone":"America/Lima",
    "iso:country":"PE",
    "name:spa_x_preferred":[
        "Luchador"
    ],
    "wof:name":"Luchador",
    "wof:placetype":"locality"
},
  "geometry": {"coordinates":[-69.33672,-11.39171],"type":"Point"}
}