{
  "type": "Feature",
  "properties": {
    "gn:admin1_code":"12.0",
    "gn:admin2_code":"1208.0",
    "gn:admin3_code":"120801.0",
    "gn:asciiname":"Chuspo",
    "gn:country_code":"PE",
    "gn:dem":3990,
    "gn:feature_class":"P",
    "gn:feature_code":"PPL",
    "gn:name":"Chuspo",
    "gn:population":0,
    "gn:timezone":"America/Lima",
    "iso:country":"PE",
    "wof:name":"Chuspo",
    "wof:placetype":"locality"
},
  "geometry": {"coordinates":[-75.8831,-11.61791],"type":"Point"}
}