{
  "type": "Feature",
  "properties": {
    "gn:admin1_code":"15",
    "gn:admin2_code":"1502.0",
    "gn:admin3_code":"150201.0",
    "gn:asciiname":"Crucero",
    "gn:country_code":"PE",
    "gn:dem":154,
    "gn:feature_class":"P",
    "gn:feature_code":"PPL",
    "gn:name":"Crucero",
    "gn:population":0,
    "gn:timezone":"America/Lima",
    "iso:country":"PE",
    "wof:name":"Crucero",
    "wof:placetype":"locality"
},
  "geometry": {"coordinates":[-77.72833,-10.713],"type":"Point"}
}