{
  "type": "Feature",
  "properties": {
    "gn:admin1_code":"01",
    "gn:admin2_code":"102.0",
    "gn:admin3_code":"10205.0",
    "gn:asciiname":"Almendro",
    "gn:country_code":"PE",
    "gn:dem":535,
    "gn:feature_class":"P",
    "gn:feature_code":"PPL",
    "gn:name":"Almendro",
    "gn:population":0,
    "gn:timezone":"America/Lima",
    "iso:country":"PE",
    "wof:name":"Almendro",
    "wof:placetype":"locality"
},
  "geometry": {"coordinates":[-78.37345000000001,-5.26353],"type":"Point"}
}