{
  "type": "Feature",
  "properties": {
    "gn:admin1_code":"23",
    "gn:admin2_code":"2304.0",
    "gn:admin3_code":"230406.0",
    "gn:asciiname":"Senoraca",
    "gn:country_code":"PE",
    "gn:dem":4629,
    "gn:feature_class":"P",
    "gn:feature_code":"PPL",
    "gn:name":"Se\u00f1oraca",
    "gn:population":0,
    "gn:timezone":"America/Lima",
    "iso:country":"PE",
    "wof:name":"Senoraca",
    "wof:placetype":"locality"
},
  "geometry": {"coordinates":[-70.07295999999999,-17.18736],"type":"Point"}
}