{
  "type": "Feature",
  "properties": {
    "gn:admin1_code":"12.0",
    "gn:admin2_code":"1208.0",
    "gn:admin3_code":"120801.0",
    "gn:asciiname":"Calioc",
    "gn:country_code":"PE",
    "gn:dem":4123,
    "gn:feature_class":"P",
    "gn:feature_code":"PPL",
    "gn:name":"Calioc",
    "gn:population":0,
    "gn:timezone":"America/Lima",
    "iso:country":"PE",
    "wof:name":"Calioc",
    "wof:placetype":"locality"
},
  "geometry": {"coordinates":[-75.86471999999998,-11.63292],"type":"Point"}
}