{
  "type": "Feature",
  "properties": {
    "gn:admin1_code":"10",
    "gn:admin2_code":"1004.0",
    "gn:admin3_code":"100404.0",
    "gn:asciiname":"Acobamba",
    "gn:cc2":"PE",
    "gn:country_code":"PE",
    "gn:dem":3899,
    "gn:feature_class":"P",
    "gn:feature_code":"PPL",
    "gn:name":"Acobamba",
    "gn:population":0,
    "gn:timezone":"America/Lima",
    "iso:country":"PE",
    "name:und_x_variant":[
        "Acobamba Hacienda",
        "Acobamba"
    ],
    "wof:name":"Acobamba",
    "wof:placetype":"locality"
},
  "geometry": {"coordinates":[-77.01666999999998,-8.95],"type":"Point"}
}