{
  "type": "Feature",
  "properties": {
    "gn:admin1_code":"20",
    "gn:admin2_code":"2008.0",
    "gn:asciiname":"El Venado",
    "gn:country_code":"PE",
    "gn:dem":93,
    "gn:feature_class":"P",
    "gn:feature_code":"PPL",
    "gn:name":"El Venado",
    "gn:population":0,
    "gn:timezone":"America/Lima",
    "iso:country":"PE",
    "name:und_x_variant":[
        "El Caballo",
        "El Venado"
    ],
    "wof:name":"El Venado",
    "wof:placetype":"locality"
},
  "geometry": {"coordinates":[-80.32425000000001,-5.68128],"type":"Point"}
}