{
  "type": "Feature",
  "properties": {
    "gn:admin1_code":"21.0",
    "gn:admin2_code":"2112.0",
    "gn:asciiname":"Jatun Misca",
    "gn:country_code":"PE",
    "gn:dem":1244,
    "gn:feature_class":"P",
    "gn:feature_code":"PPL",
    "gn:name":"Jatun Misca",
    "gn:population":0,
    "gn:timezone":"America/Lima",
    "iso:country":"PE",
    "name:spa_x_preferred":[
        "Jatun Misca"
    ],
    "wof:name":"Jatun Misca",
    "wof:placetype":"locality"
},
  "geometry": {"coordinates":[-69.15334,-14.02459],"type":"Point"}
}