{
  "type": "Feature",
  "properties": {
    "gn:admin1_code":"10.0",
    "gn:admin2_code":"1005.0",
    "gn:admin3_code":"100504.0",
    "gn:asciiname":"Jacas Grande",
    "gn:country_code":"PE",
    "gn:dem":3617,
    "gn:feature_class":"P",
    "gn:feature_code":"PPLA3",
    "gn:name":"Jacas Grande",
    "gn:population":0,
    "gn:timezone":"America/Lima",
    "iso:country":"PE",
    "wof:name":"Jacas Grande",
    "wof:placetype":"locality"
},
  "geometry": {"coordinates":[-76.73639,-9.53965],"type":"Point"}
}