{
  "type": "Feature",
  "properties": {
    "gn:admin1_code":"18",
    "gn:admin2_code":"1802.0",
    "gn:admin3_code":"180203.0",
    "gn:asciiname":"Mayuguaya",
    "gn:country_code":"PE",
    "gn:dem":2289,
    "gn:feature_class":"P",
    "gn:feature_code":"PPL",
    "gn:name":"Mayuguaya",
    "gn:population":0,
    "gn:timezone":"America/Lima",
    "iso:country":"PE",
    "wof:name":"Mayuguaya",
    "wof:placetype":"locality"
},
  "geometry": {"coordinates":[-71.03055999999999,-16.64417000000001],"type":"Point"}
}