{
  "type": "Feature",
  "properties": {
    "gn:admin1_code":"16",
    "gn:admin2_code":"1605.0",
    "gn:admin3_code":"160508.0",
    "gn:asciiname":"Liquidacion",
    "gn:country_code":"PE",
    "gn:dem":172,
    "gn:feature_class":"P",
    "gn:feature_code":"PPL",
    "gn:name":"Liquidaci\u00f3n",
    "gn:population":0,
    "gn:timezone":"America/Lima",
    "iso:country":"PE",
    "wof:name":"Liquidacion",
    "wof:placetype":"locality"
},
  "geometry": {"coordinates":[-73.55,-6.45],"type":"Point"}
}