{
  "type": "Feature",
  "properties": {
    "gn:admin1_code":"04",
    "gn:admin2_code":"404.0",
    "gn:admin3_code":"40412.0",
    "gn:asciiname":"Hacienda Piraucho",
    "gn:country_code":"PE",
    "gn:dem":3053,
    "gn:feature_class":"P",
    "gn:feature_code":"PPL",
    "gn:name":"Hacienda Piraucho",
    "gn:population":0,
    "gn:timezone":"America/Lima",
    "iso:country":"PE",
    "wof:name":"Hacienda Piraucho",
    "wof:placetype":"locality"
},
  "geometry": {"coordinates":[-72.41808,-15.68979],"type":"Point"}
}