{
  "type": "Feature",
  "properties": {
    "gn:admin1_code":"01",
    "gn:admin2_code":"107.0",
    "gn:admin3_code":"10704.0",
    "gn:asciiname":"Aviacion",
    "gn:country_code":"PE",
    "gn:dem":391,
    "gn:feature_class":"P",
    "gn:feature_code":"PPL",
    "gn:name":"Aviaci\u00f3n",
    "gn:population":0,
    "gn:timezone":"America/Lima",
    "iso:country":"PE",
    "wof:name":"Aviacion",
    "wof:placetype":"locality"
},
  "geometry": {"coordinates":[-78.5979,-5.61495],"type":"Point"}
}