{
  "type": "Feature",
  "properties": {
    "gn:admin1_code":"09",
    "gn:admin2_code":"906.0",
    "gn:admin3_code":"90611.0",
    "gn:asciiname":"Tomac",
    "gn:country_code":"PE",
    "gn:dem":3421,
    "gn:feature_class":"P",
    "gn:feature_code":"PPL",
    "gn:name":"Tomac",
    "gn:population":0,
    "gn:timezone":"America/Lima",
    "iso:country":"PE",
    "wof:name":"Tomac",
    "wof:placetype":"locality"
},
  "geometry": {"coordinates":[-75.29611,-13.76917],"type":"Point"}
}