{
  "type": "Feature",
  "properties": {
    "gn:admin1_code":"22.0",
    "gn:admin2_code":"2208.0",
    "gn:admin3_code":"220803.0",
    "gn:asciiname":"Naciente de Rio Negro",
    "gn:country_code":"PE",
    "gn:dem":1022,
    "gn:feature_class":"P",
    "gn:feature_code":"PPL",
    "gn:name":"Naciente de R\u00edo Negro",
    "gn:population":0,
    "gn:timezone":"America/Lima",
    "iso:country":"PE",
    "wof:name":"Naciente de Rio Negro",
    "wof:placetype":"locality"
},
  "geometry": {"coordinates":[-77.26861,-6.09083],"type":"Point"}
}