{
  "type": "Feature",
  "properties": {
    "gn:admin1_code":"10.0",
    "gn:admin2_code":"1005.0",
    "gn:asciiname":"Sacracocha",
    "gn:country_code":"PE",
    "gn:dem":4342,
    "gn:feature_class":"P",
    "gn:feature_code":"PPL",
    "gn:name":"Sacracocha",
    "gn:population":0,
    "gn:timezone":"America/Lima",
    "iso:country":"PE",
    "wof:name":"Sacracocha",
    "wof:placetype":"locality"
},
  "geometry": {"coordinates":[-76.98111,-9.60351],"type":"Point"}
}