{
  "type": "Feature",
  "properties": {
    "gn:admin1_code":"11",
    "gn:admin2_code":"1104.0",
    "gn:admin3_code":"110403.0",
    "gn:asciiname":"La Isla",
    "gn:country_code":"PE",
    "gn:dem":435,
    "gn:feature_class":"P",
    "gn:feature_code":"PPL",
    "gn:name":"La Isla",
    "gn:population":0,
    "gn:timezone":"America/Lima",
    "iso:country":"PE",
    "name:ceb_x_preferred":[
        "La Isla"
    ],
    "name:spa_x_preferred":[
        "La isla"
    ],
    "name:srp_x_preferred":[
        "\u041b\u0430 \u0418\u0441\u043b\u0430"
    ],
    "name:swe_x_preferred":[
        "La Isla"
    ],
    "name:und_x_variant":[
        "Isla",
        "La Isla"
    ],
    "wof:name":"La Isla",
    "wof:placetype":"locality"
},
  "geometry": {"coordinates":[-75.19181,-14.44405],"type":"Point"}
}