{
  "type": "Feature",
  "properties": {
    "gn:admin1_code":"15",
    "gn:admin2_code":"1509.0",
    "gn:admin3_code":"150906.0",
    "gn:asciiname":"San Pedro de Palpas",
    "gn:country_code":"PE",
    "gn:dem":3392,
    "gn:feature_class":"P",
    "gn:feature_code":"PPL",
    "gn:name":"San Pedro de Palpas",
    "gn:population":0,
    "gn:timezone":"America/Lima",
    "iso:country":"PE",
    "wof:name":"San Pedro de Palpas",
    "wof:placetype":"locality"
},
  "geometry": {"coordinates":[-76.83444,-10.79278],"type":"Point"}
}