{
  "type": "Feature",
  "properties": {
    "gn:admin1_code":"12",
    "gn:admin2_code":"1205.0",
    "gn:admin3_code":"120501.0",
    "gn:asciiname":"Garbanzo Cancha",
    "gn:country_code":"PE",
    "gn:dem":4403,
    "gn:feature_class":"P",
    "gn:feature_code":"PPL",
    "gn:name":"Garbanzo Cancha",
    "gn:population":0,
    "gn:timezone":"America/Lima",
    "iso:country":"PE",
    "wof:name":"Garbanzo Cancha",
    "wof:placetype":"locality"
},
  "geometry": {"coordinates":[-75.91883,-11.14044],"type":"Point"}
}