{
  "type": "Feature",
  "properties": {
    "gn:admin1_code":"06",
    "gn:admin2_code":"613.0",
    "gn:admin3_code":"61303.0",
    "gn:asciiname":"El Conde",
    "gn:country_code":"PE",
    "gn:dem":407,
    "gn:feature_class":"P",
    "gn:feature_code":"PPL",
    "gn:name":"El Conde",
    "gn:population":0,
    "gn:timezone":"America/Lima",
    "iso:country":"PE",
    "wof:name":"El Conde",
    "wof:placetype":"locality"
},
  "geometry": {"coordinates":[-79.18333,-6.83333],"type":"Point"}
}