{
  "type": "Feature",
  "properties": {
    "gn:admin1_code":"15",
    "gn:admin2_code":"1505.0",
    "gn:admin3_code":"150501.0",
    "gn:asciiname":"Cochahuasi",
    "gn:country_code":"PE",
    "gn:dem":5,
    "gn:feature_class":"P",
    "gn:feature_code":"PPL",
    "gn:name":"Cochahuasi",
    "gn:population":0,
    "gn:timezone":"America/Lima",
    "iso:country":"PE",
    "name:und_x_variant":[
        "Cocha Huasi",
        "Cochahuasi"
    ],
    "wof:name":"Cochahuasi",
    "wof:placetype":"locality"
},
  "geometry": {"coordinates":[-76.41101999999999,-13.11417],"type":"Point"}
}