{
  "type": "Feature",
  "properties": {
    "gn:admin1_code":"06",
    "gn:admin2_code":"613.0",
    "gn:admin3_code":"61309.0",
    "gn:asciiname":"La Tranca",
    "gn:country_code":"PE",
    "gn:dem":1910,
    "gn:feature_class":"P",
    "gn:feature_code":"PPL",
    "gn:name":"La Tranca",
    "gn:population":0,
    "gn:timezone":"America/Lima",
    "iso:country":"PE",
    "wof:name":"La Tranca",
    "wof:placetype":"locality"
},
  "geometry": {"coordinates":[-79.06341,-6.591],"type":"Point"}
}