{
  "type": "Feature",
  "properties": {
    "gn:admin1_code":"14",
    "gn:admin2_code":"1403.0",
    "gn:admin3_code":"140310.0",
    "gn:asciiname":"Polvareda",
    "gn:country_code":"PE",
    "gn:dem":183,
    "gn:feature_class":"P",
    "gn:feature_code":"PPL",
    "gn:name":"Polvareda",
    "gn:population":0,
    "gn:timezone":"America/Lima",
    "iso:country":"PE",
    "wof:name":"Polvareda",
    "wof:placetype":"locality"
},
  "geometry": {"coordinates":[-79.58716,-6.28857],"type":"Point"}
}