{
  "type": "Feature",
  "properties": {
    "gn:admin1_code":"4",
    "gn:admin2_code":"406.0",
    "gn:admin3_code":"40602.0",
    "gn:asciiname":"Andaray",
    "gn:country_code":"PE",
    "gn:dem":3035,
    "gn:feature_class":"P",
    "gn:feature_code":"PPLA3",
    "gn:name":"Andaray",
    "gn:population":0,
    "gn:timezone":"America/Lima",
    "iso:country":"PE",
    "wof:name":"Andaray",
    "wof:placetype":"locality"
},
  "geometry": {"coordinates":[-72.86055999999998,-15.79667],"type":"Point"}
}