{
  "type": "Feature",
  "properties": {
    "gn:admin1_code":"21",
    "gn:admin2_code":"2104.0",
    "gn:admin3_code":"210407.0",
    "gn:asciiname":"Cuncaicha",
    "gn:country_code":"PE",
    "gn:dem":3854,
    "gn:feature_class":"P",
    "gn:feature_code":"PPL",
    "gn:name":"Cuncaicha",
    "gn:population":0,
    "gn:timezone":"America/Lima",
    "iso:country":"PE",
    "wof:name":"Cuncaicha",
    "wof:placetype":"locality"
},
  "geometry": {"coordinates":[-69.25445999999999,-16.5615],"type":"Point"}
}