{
  "type": "Feature",
  "properties": {
    "gn:admin1_code":"06",
    "gn:admin2_code":"604.0",
    "gn:admin3_code":"60415.0",
    "gn:asciiname":"Pacopampa",
    "gn:country_code":"PE",
    "gn:dem":2412,
    "gn:feature_class":"P",
    "gn:feature_code":"PPL",
    "gn:name":"Pacopampa",
    "gn:population":0,
    "gn:timezone":"America/Lima",
    "iso:country":"PE",
    "name:rus_x_preferred":[
        "\u041f\u0430\u043a\u043e\u043f\u0430\u043c\u043f\u0430"
    ],
    "name:spa_x_preferred":[
        "Pacopampa"
    ],
    "name:ukr_x_preferred":[
        "\u041f\u0430\u043a\u043e\u043f\u0430\u043c\u043f\u0430"
    ],
    "wof:name":"Pacopampa",
    "wof:placetype":"locality"
},
  "geometry": {"coordinates":[-79.02159,-6.33772],"type":"Point"}
}