{
  "type": "Feature",
  "properties": {
    "gn:admin1_code":"10",
    "gn:admin2_code":"1002.0",
    "gn:admin3_code":"100206.0",
    "gn:asciiname":"Nuishca",
    "gn:country_code":"PE",
    "gn:dem":4162,
    "gn:feature_class":"P",
    "gn:feature_code":"PPL",
    "gn:name":"Nuishca",
    "gn:population":0,
    "gn:timezone":"America/Lima",
    "iso:country":"PE",
    "wof:name":"Nuishca",
    "wof:placetype":"locality"
},
  "geometry": {"coordinates":[-76.27620999999998,-10.36359],"type":"Point"}
}