{
  "type": "Feature",
  "properties": {
    "gn:admin1_code":"11.0",
    "gn:admin2_code":"1101.0",
    "gn:admin3_code":"110111.0",
    "gn:asciiname":"Paraje",
    "gn:country_code":"PE",
    "gn:dem":398,
    "gn:feature_class":"P",
    "gn:feature_code":"PPL",
    "gn:name":"Paraje",
    "gn:population":0,
    "gn:timezone":"America/Lima",
    "iso:country":"PE",
    "name:por_x_preferred":[
        "Paraje"
    ],
    "name:spa_x_preferred":[
        "Paraje"
    ],
    "wof:name":"Paraje",
    "wof:placetype":"locality"
},
  "geometry": {"coordinates":[-75.66755000000001,-14.2055],"type":"Point"}
}