{
  "type": "Feature",
  "properties": {
    "gn:admin1_code":"12",
    "gn:admin2_code":"1202.0",
    "gn:admin3_code":"120206.0",
    "gn:asciiname":"Cuyo",
    "gn:country_code":"PE",
    "gn:dem":4210,
    "gn:feature_class":"P",
    "gn:feature_code":"PPL",
    "gn:name":"Cuyo",
    "gn:population":0,
    "gn:timezone":"America/Lima",
    "iso:country":"PE",
    "name:ceb_x_preferred":[
        "Cuyo"
    ],
    "name:deu_x_preferred":[
        "Cuyo"
    ],
    "name:fra_x_preferred":[
        "Cuyo"
    ],
    "name:ind_x_preferred":[
        "Cuyo"
    ],
    "name:ita_x_preferred":[
        "Cuyo"
    ],
    "name:nld_x_preferred":[
        "Cuyo"
    ],
    "name:por_x_preferred":[
        "Cuyo"
    ],
    "name:rus_x_preferred":[
        "\u041a\u0443\u0439\u043e"
    ],
    "name:spa_x_preferred":[
        "Cuyo"
    ],
    "wof:name":"Cuyo",
    "wof:placetype":"locality"
},
  "geometry": {"coordinates":[-74.88880999999998,-11.67672],"type":"Point"}
}