{
  "type": "Feature",
  "properties": {
    "gn:admin1_code":"8",
    "gn:admin2_code":"807.0",
    "gn:admin3_code":"80708.0",
    "gn:asciiname":"Huamanota",
    "gn:country_code":"PE",
    "gn:dem":4016,
    "gn:feature_class":"P",
    "gn:feature_code":"PPL",
    "gn:name":"Huamanota",
    "gn:population":0,
    "gn:timezone":"America/Lima",
    "iso:country":"PE",
    "wof:name":"Huamanota",
    "wof:placetype":"locality"
},
  "geometry": {"coordinates":[-71.93316,-14.57005],"type":"Point"}
}