{
  "type": "Feature",
  "properties": {
    "gn:admin1_code":"6.0",
    "gn:admin2_code":"605.0",
    "gn:admin3_code":"60508.0",
    "gn:asciiname":"Las Varas",
    "gn:country_code":"PE",
    "gn:dem":333,
    "gn:feature_class":"P",
    "gn:feature_code":"PPL",
    "gn:name":"Las Varas",
    "gn:population":0,
    "gn:timezone":"America/Lima",
    "iso:country":"PE",
    "name:ceb_x_preferred":[
        "Las Varas"
    ],
    "name:spa_x_preferred":[
        "Las Varas"
    ],
    "name:srp_x_preferred":[
        "\u041b\u0430\u0441 \u0412\u0430\u0440\u0430\u0441"
    ],
    "name:swe_x_preferred":[
        "Las Varas"
    ],
    "wof:name":"Las Varas",
    "wof:placetype":"locality"
},
  "geometry": {"coordinates":[-79.21958000000002,-7.25249],"type":"Point"}
}