{
  "type": "Feature",
  "properties": {
    "gn:admin1_code":"8",
    "gn:admin2_code":"806.0",
    "gn:admin3_code":"80601.0",
    "gn:asciiname":"Mojon",
    "gn:country_code":"PE",
    "gn:dem":3565,
    "gn:feature_class":"P",
    "gn:feature_code":"PPL",
    "gn:name":"Moj\u00f3n",
    "gn:population":0,
    "gn:timezone":"America/Lima",
    "iso:country":"PE",
    "wof:name":"Mojon",
    "wof:placetype":"locality"
},
  "geometry": {"coordinates":[-71.22118,-14.24723],"type":"Point"}
}