{
  "type": "Feature",
  "properties": {
    "gn:admin1_code":"09",
    "gn:admin2_code":"906.0",
    "gn:admin3_code":"90607.0",
    "gn:asciiname":"Yanamachay",
    "gn:country_code":"PE",
    "gn:dem":4629,
    "gn:feature_class":"P",
    "gn:feature_code":"PPL",
    "gn:name":"Yanamachay",
    "gn:population":0,
    "gn:timezone":"America/Lima",
    "iso:country":"PE",
    "wof:name":"Yanamachay",
    "wof:placetype":"locality"
},
  "geometry": {"coordinates":[-74.83333,-13.16667],"type":"Point"}
}