{
  "type": "Feature",
  "properties": {
    "gn:admin1_code":"3",
    "gn:admin2_code":"304.0",
    "gn:admin3_code":"30415.0",
    "gn:asciiname":"Huancarirca",
    "gn:country_code":"PE",
    "gn:dem":2957,
    "gn:feature_class":"P",
    "gn:feature_code":"PPL",
    "gn:name":"Huancarirca",
    "gn:population":0,
    "gn:timezone":"America/Lima",
    "iso:country":"PE",
    "wof:name":"Huancarirca",
    "wof:placetype":"locality"
},
  "geometry": {"coordinates":[-73.20976999999998,-13.95833],"type":"Point"}
}