{
  "type": "Feature",
  "properties": {
    "gn:admin1_code":"20",
    "gn:admin2_code":"2006.0",
    "gn:admin3_code":"200605.0",
    "gn:asciiname":"Macunio",
    "gn:country_code":"PE",
    "gn:dem":383,
    "gn:feature_class":"P",
    "gn:feature_code":"PPL",
    "gn:name":"Macunio",
    "gn:population":0,
    "gn:timezone":"America/Lima",
    "iso:country":"PE",
    "name:spa_x_preferred":[
        "Macunio"
    ],
    "wof:name":"Macunio",
    "wof:placetype":"locality"
},
  "geometry": {"coordinates":[-80.73912,-4.50195],"type":"Point"}
}