{
  "type": "Feature",
  "properties": {
    "gn:admin1_code":"2.0",
    "gn:admin2_code":"214.0",
    "gn:admin3_code":"21407.0",
    "gn:asciiname":"Pishaypay",
    "gn:country_code":"PE",
    "gn:dem":4360,
    "gn:feature_class":"P",
    "gn:feature_code":"PPL",
    "gn:name":"Pishaypay",
    "gn:population":0,
    "gn:timezone":"America/Lima",
    "iso:country":"PE",
    "wof:name":"Pishaypay",
    "wof:placetype":"locality"
},
  "geometry": {"coordinates":[-77.24304000000002,-10.34115],"type":"Point"}
}