{
  "type": "Feature",
  "properties": {
    "gn:admin1_code":"16",
    "gn:admin2_code":"1602.0",
    "gn:admin3_code":"160206.0",
    "gn:asciiname":"Zancudo",
    "gn:country_code":"PE",
    "gn:dem":151,
    "gn:feature_class":"P",
    "gn:feature_code":"PPL",
    "gn:name":"Zancudo",
    "gn:population":0,
    "gn:timezone":"America/Lima",
    "iso:country":"PE",
    "wof:name":"Zancudo",
    "wof:placetype":"locality"
},
  "geometry": {"coordinates":[-76.14794999999999,-4.34738],"type":"Point"}
}