{
  "type": "Feature",
  "properties": {
    "gn:admin1_code":"8.0",
    "gn:admin2_code":"813.0",
    "gn:admin3_code":"81301.0",
    "gn:asciiname":"Jajapunco",
    "gn:country_code":"PE",
    "gn:dem":3034,
    "gn:feature_class":"P",
    "gn:feature_code":"PPL",
    "gn:name":"Jajapunco",
    "gn:population":0,
    "gn:timezone":"America/Lima",
    "iso:country":"PE",
    "wof:name":"Jajapunco",
    "wof:placetype":"locality"
},
  "geometry": {"coordinates":[-72.12639,-13.28028],"type":"Point"}
}