{
  "type": "Feature",
  "properties": {
    "gn:admin1_code":"12",
    "gn:admin2_code":"1201.0",
    "gn:admin3_code":"120121.0",
    "gn:asciiname":"Viques",
    "gn:country_code":"PE",
    "gn:dem":3182,
    "gn:feature_class":"P",
    "gn:feature_code":"PPL",
    "gn:name":"Viques",
    "gn:population":0,
    "gn:timezone":"America/Lima",
    "iso:country":"PE",
    "wof:name":"Viques",
    "wof:placetype":"locality"
},
  "geometry": {"coordinates":[-75.23333000000002,-12.15],"type":"Point"}
}