{
  "type": "Feature",
  "properties": {
    "gn:admin1_code":"16.0",
    "gn:admin2_code":"1607.0",
    "gn:admin3_code":"160703.0",
    "gn:asciiname":"Gasolina",
    "gn:country_code":"PE",
    "gn:dem":148,
    "gn:feature_class":"P",
    "gn:feature_code":"PPL",
    "gn:name":"Gasolina",
    "gn:population":0,
    "gn:timezone":"America/Lima",
    "iso:country":"PE",
    "wof:name":"Gasolina",
    "wof:placetype":"locality"
},
  "geometry": {"coordinates":[-77.37166999999999,-4.58694],"type":"Point"}
}