{
  "type": "Feature",
  "properties": {
    "gn:admin1_code":"04",
    "gn:admin2_code":"401.0",
    "gn:admin3_code":"40119.0",
    "gn:asciiname":"Rio Blanco",
    "gn:country_code":"PE",
    "gn:dem":4097,
    "gn:feature_class":"P",
    "gn:feature_code":"PPL",
    "gn:name":"R\u00edo Blanco",
    "gn:population":0,
    "gn:timezone":"America/Lima",
    "iso:country":"PE",
    "wof:name":"Rio Blanco",
    "wof:placetype":"locality"
},
  "geometry": {"coordinates":[-71.16544,-16.13114],"type":"Point"}
}