{
  "type": "Feature",
  "properties": {
    "gn:admin1_code":"12.0",
    "gn:admin2_code":"1204.0",
    "gn:admin3_code":"120407.0",
    "gn:asciiname":"Sillahuacta",
    "gn:country_code":"PE",
    "gn:dem":3672,
    "gn:feature_class":"P",
    "gn:feature_code":"PPL",
    "gn:name":"Sillahuacta",
    "gn:population":0,
    "gn:timezone":"America/Lima",
    "iso:country":"PE",
    "wof:name":"Sillahuacta",
    "wof:placetype":"locality"
},
  "geometry": {"coordinates":[-75.40071999999998,-11.80249],"type":"Point"}
}