{
  "type": "Feature",
  "properties": {
    "gn:admin1_code":"21.0",
    "gn:admin2_code":"2112.0",
    "gn:asciiname":"San Cristobal",
    "gn:country_code":"PE",
    "gn:dem":1722,
    "gn:feature_class":"P",
    "gn:feature_code":"PPL",
    "gn:name":"San Crist\u00f3bal",
    "gn:population":0,
    "gn:timezone":"America/Lima",
    "iso:country":"PE",
    "name:spa_x_preferred":[
        "San Crist\u00f3bal"
    ],
    "wof:name":"San Cristobal",
    "wof:placetype":"locality"
},
  "geometry": {"coordinates":[-69.06371999999999,-14.36482],"type":"Point"}
}