{
  "type": "Feature",
  "properties": {
    "gn:admin1_code":"12.0",
    "gn:admin2_code":"1202.0",
    "gn:admin3_code":"120206.0",
    "gn:asciiname":"Ingenio",
    "gn:country_code":"PE",
    "gn:dem":3694,
    "gn:feature_class":"P",
    "gn:feature_code":"PPL",
    "gn:name":"Ingenio",
    "gn:population":0,
    "gn:timezone":"America/Lima",
    "iso:country":"PE",
    "wof:name":"Ingenio",
    "wof:placetype":"locality"
},
  "geometry": {"coordinates":[-75.13623,-11.75413],"type":"Point"}
}