{
  "type": "Feature",
  "properties": {
    "gn:admin1_code":"9.0",
    "gn:admin2_code":"903.0",
    "gn:admin3_code":"90301.0",
    "gn:asciiname":"Yurachuaycco",
    "gn:country_code":"PE",
    "gn:dem":4408,
    "gn:feature_class":"P",
    "gn:feature_code":"PPL",
    "gn:name":"Yurachuaycco",
    "gn:population":0,
    "gn:timezone":"America/Lima",
    "iso:country":"PE",
    "wof:name":"Yurachuaycco",
    "wof:placetype":"locality"
},
  "geometry": {"coordinates":[-74.79453000000002,-13.14513],"type":"Point"}
}