{
  "type": "Feature",
  "properties": {
    "gn:admin1_code":"15",
    "gn:admin2_code":"1506.0",
    "gn:admin3_code":"150608.0",
    "gn:asciiname":"Rapacan",
    "gn:country_code":"PE",
    "gn:dem":2724,
    "gn:feature_class":"P",
    "gn:feature_code":"PPL",
    "gn:name":"Rapacan",
    "gn:population":0,
    "gn:timezone":"America/Lima",
    "iso:country":"PE",
    "wof:name":"Rapacan",
    "wof:placetype":"locality"
},
  "geometry": {"coordinates":[-76.69944,-11.23972],"type":"Point"}
}