{
  "type": "Feature",
  "properties": {
    "gn:admin1_code":"21",
    "gn:admin2_code":"2101.0",
    "gn:admin3_code":"210111.0",
    "gn:asciiname":"Cachicucho",
    "gn:country_code":"PE",
    "gn:dem":3965,
    "gn:feature_class":"P",
    "gn:feature_code":"PPL",
    "gn:name":"Cachicucho",
    "gn:population":0,
    "gn:timezone":"America/Lima",
    "iso:country":"PE",
    "wof:name":"Cachicucho",
    "wof:placetype":"locality"
},
  "geometry": {"coordinates":[-70.07938,-16.15967],"type":"Point"}
}