{
  "type": "Feature",
  "properties": {
    "gn:admin1_code":"21.0",
    "gn:admin2_code":"2112.0",
    "gn:asciiname":"Yanacocha",
    "gn:country_code":"PE",
    "gn:dem":2077,
    "gn:feature_class":"P",
    "gn:feature_code":"PPL",
    "gn:name":"Yanacocha",
    "gn:population":0,
    "gn:timezone":"America/Lima",
    "iso:country":"PE",
    "name:dan_x_preferred":[
        "Yanacocha"
    ],
    "name:deu_x_preferred":[
        "Yanacocha"
    ],
    "name:epo_x_preferred":[
        "\u011canako\u0109o"
    ],
    "name:nld_x_preferred":[
        "Yanacocha"
    ],
    "name:que_x_preferred":[
        "Yanaqucha qhuya"
    ],
    "name:ron_x_preferred":[
        "Yanacocha"
    ],
    "name:spa_x_preferred":[
        "Yanacocha"
    ],
    "name:ukr_x_preferred":[
        "\u042f\u043d\u0430\u043a\u043e\u0447\u0430"
    ],
    "wof:name":"Yanacocha",
    "wof:placetype":"locality"
},
  "geometry": {"coordinates":[-69.26047,-14.19306],"type":"Point"}
}