{
  "type": "Feature",
  "properties": {
    "iso:country":"PE",
    "name:ara_x_preferred":[
        "\u0647\u0648\u0627\u062a\u0634\u0648"
    ],
    "name:arz_x_preferred":[
        "\u0647\u0648\u0627\u062a\u0634\u0648"
    ],
    "name:ast_x_preferred":[
        "Huacho"
    ],
    "name:ben_x_preferred":[
        "\u09b9\u09c1\u09df\u09be\u099b\u09cb"
    ],
    "name:ceb_x_preferred":[
        "Huacho"
    ],
    "name:ces_x_preferred":[
        "Huacho"
    ],
    "name:deu_x_preferred":[
        "Huacho"
    ],
    "name:ell_x_preferred":[
        "\u03a7\u03bf\u03c5\u03ac\u03c4\u03c3\u03bf"
    ],
    "name:eng_x_preferred":[
        "Huacho"
    ],
    "name:epo_x_preferred":[
        "Huacho"
    ],
    "name:fas_x_preferred":[
        "\u0627\u0648\u0627\u0686\u0648"
    ],
    "name:fin_x_preferred":[
        "Huacho"
    ],
    "name:fra_x_preferred":[
        "Huacho"
    ],
    "name:frr_x_preferred":[
        "Huacho"
    ],
    "name:heb_x_preferred":[
        "\u05d4\u05d5\u05d0\u05e6'\u05d5"
    ],
    "name:hin_x_preferred":[
        "\u0939\u0941\u0906\u091a\u094b"
    ],
    "name:hun_x_preferred":[
        "Huacho"
    ],
    "name:ind_x_preferred":[
        "Huacho"
    ],
    "name:ita_x_preferred":[
        "Huacho"
    ],
    "name:jpn_x_preferred":[
        "\u30ef\u30c1\u30e7"
    ],
    "name:kat_x_preferred":[
        "\u10e3\u10d0\u10e9\u10dd"
    ],
    "name:kor_x_preferred":[
        "\uc6b0\uc544\ucd08"
    ],
    "name:nah_x_preferred":[
        "Huacho"
    ],
    "name:nld_x_preferred":[
        "Huacho"
    ],
    "name:pol_x_preferred":[
        "Huacho"
    ],
    "name:por_x_preferred":[
        "Huacho"
    ],
    "name:que_x_preferred":[
        "Wachu llaqta"
    ],
    "name:ron_x_preferred":[
        "Huacho"
    ],
    "name:rus_x_preferred":[
        "\u0423\u0430\u0447\u043e"
    ],
    "name:spa_x_preferred":[
        "Huacho"
    ],
    "name:swe_x_preferred":[
        "Huacho"
    ],
    "name:tat_x_preferred":[
        "\u0412\u0430\u0447\u043e"
    ],
    "name:tha_x_preferred":[
        "\u0e27\u0e32\u0e42\u0e0a"
    ],
    "name:tur_x_preferred":[
        "Huacho"
    ],
    "name:ukr_x_preferred":[
        "\u0423\u0430\u0447\u043e"
    ],
    "name:urd_x_preferred":[
        "\u0648\u0627\u0686\u0648"
    ],
    "name:vie_x_preferred":[
        "Huacho"
    ],
    "name:war_x_preferred":[
        "Huacho"
    ],
    "name:zho_x_preferred":[
        "\u74e6\u55ac"
    ],
    "qs:gn_country":"PE",
    "qs:gn_fcode":"PPL",
    "qs:gn_pop":0,
    "qs:name":"Huacho",
    "qs:name_adm0":"Per\u00fa",
    "qs:name_adm1":"Lima",
    "qs:photos":27,
    "qs:photos_1k":5,
    "qs:photos_9k":1,
    "qs:photos_9r":2,
    "qs:photos_all":27,
    "qs:photos_sr":2,
    "qs:placetype":"Town",
    "qs:pop_sr":"0",
    "qs:woe_adm0":23424919,
    "wd:wordcount":613,
    "wof:name":"Huacho",
    "wof:placetype":"locality"
},
  "geometry": {"coordinates":[-76.99472,-11.17028],"type":"Point"}
}