{
  "type": "Feature",
  "properties": {
    "gn:admin1_code":"4",
    "gn:admin2_code":"401.0",
    "gn:admin3_code":"40128.0",
    "gn:asciiname":"Cincha",
    "gn:country_code":"PE",
    "gn:dem":2475,
    "gn:feature_class":"P",
    "gn:feature_code":"PPL",
    "gn:name":"Cincha",
    "gn:population":0,
    "gn:timezone":"America/Lima",
    "iso:country":"PE",
    "wof:name":"Cincha",
    "wof:placetype":"locality"
},
  "geometry": {"coordinates":[-71.82029,-16.213],"type":"Point"}
}