{
  "type": "Feature",
  "properties": {
    "gn:admin1_code":"15",
    "gn:admin2_code":"1507.0",
    "gn:admin3_code":"150715.0",
    "gn:asciiname":"Pacota",
    "gn:country_code":"PE",
    "gn:dem":3405,
    "gn:feature_class":"P",
    "gn:feature_code":"PPL",
    "gn:name":"Pacota",
    "gn:population":0,
    "gn:timezone":"America/Lima",
    "iso:country":"PE",
    "wof:name":"Pacota",
    "wof:placetype":"locality"
},
  "geometry": {"coordinates":[-76.45,-12.03333],"type":"Point"}
}