{
  "type": "Feature",
  "properties": {
    "gn:admin1_code":"9.0",
    "gn:admin2_code":"902.0",
    "gn:admin3_code":"90206.0",
    "gn:asciiname":"Uchuypuquio",
    "gn:country_code":"PE",
    "gn:dem":3998,
    "gn:feature_class":"P",
    "gn:feature_code":"PPL",
    "gn:name":"Uchuypuquio",
    "gn:population":0,
    "gn:timezone":"America/Lima",
    "iso:country":"PE",
    "wof:name":"Uchuypuquio",
    "wof:placetype":"locality"
},
  "geometry": {"coordinates":[-74.68571999999998,-12.72737],"type":"Point"}
}