{
  "type": "Feature",
  "properties": {
    "gn:admin1_code":"08",
    "gn:admin2_code":"808.0",
    "gn:admin3_code":"80807.0",
    "gn:asciiname":"Laicamayo",
    "gn:country_code":"PE",
    "gn:dem":4373,
    "gn:feature_class":"P",
    "gn:feature_code":"PPL",
    "gn:name":"Laicamayo",
    "gn:population":0,
    "gn:timezone":"America/Lima",
    "iso:country":"PE",
    "wof:name":"Laicamayo",
    "wof:placetype":"locality"
},
  "geometry": {"coordinates":[-71.69662,-15.04725],"type":"Point"}
}