{
  "type": "Feature",
  "properties": {
    "gn:admin1_code":"15",
    "gn:admin2_code":"1510.0",
    "gn:admin3_code":"151011.0",
    "gn:asciiname":"Colonia",
    "gn:cc2":"PE",
    "gn:country_code":"PE",
    "gn:dem":3366,
    "gn:feature_class":"P",
    "gn:feature_code":"PPLA3",
    "gn:name":"Colonia",
    "gn:population":0,
    "gn:timezone":"America/Lima",
    "iso:country":"PE",
    "name:und_x_variant":[
        "Pampas",
        "Colonia"
    ],
    "wof:name":"Colonia",
    "wof:placetype":"locality"
},
  "geometry": {"coordinates":[-75.89055999999999,-12.63278],"type":"Point"}
}