{
  "type": "Feature",
  "properties": {
    "gn:admin1_code":"02",
    "gn:admin2_code":"211.0",
    "gn:admin3_code":"21101.0",
    "gn:asciiname":"La Zorra",
    "gn:country_code":"PE",
    "gn:dem":29,
    "gn:feature_class":"P",
    "gn:feature_code":"PPL",
    "gn:name":"La Zorra",
    "gn:population":0,
    "gn:timezone":"America/Lima",
    "iso:country":"PE",
    "name:und_x_variant":[
        "Hacienda la Zorra",
        "Las Zorras",
        "La Zorra"
    ],
    "wof:name":"La Zorra",
    "wof:placetype":"locality"
},
  "geometry": {"coordinates":[-78.03679,-10.26124],"type":"Point"}
}