{
  "type": "Feature",
  "properties": {
    "gn:admin1_code":"4",
    "gn:admin2_code":"405.0",
    "gn:admin3_code":"40504.0",
    "gn:asciiname":"Salcana",
    "gn:country_code":"PE",
    "gn:dem":4459,
    "gn:feature_class":"P",
    "gn:feature_code":"PPL",
    "gn:name":"Salca\u00f1a",
    "gn:population":0,
    "gn:timezone":"America/Lima",
    "iso:country":"PE",
    "wof:name":"Salcana",
    "wof:placetype":"locality"
},
  "geometry": {"coordinates":[-71.21139000000002,-15.53111],"type":"Point"}
}