{
  "type": "Feature",
  "properties": {
    "gn:admin1_code":"17.0",
    "gn:admin2_code":"1701.0",
    "gn:asciiname":"Fundo San Francisco",
    "gn:country_code":"PE",
    "gn:dem":249,
    "gn:feature_class":"P",
    "gn:feature_code":"PPL",
    "gn:name":"Fundo San Francisco",
    "gn:population":0,
    "gn:timezone":"America/Lima",
    "iso:country":"PE",
    "name:spa_x_preferred":[
        "Fundo San Francisco"
    ],
    "wof:name":"Fundo San Francisco",
    "wof:placetype":"locality"
},
  "geometry": {"coordinates":[-69.46049000000001,-12.71112],"type":"Point"}
}