{
  "type": "Feature",
  "properties": {
    "gn:admin1_code":"04",
    "gn:admin2_code":"405.0",
    "gn:admin3_code":"40517.0",
    "gn:asciiname":"Sayana",
    "gn:country_code":"PE",
    "gn:dem":4546,
    "gn:feature_class":"P",
    "gn:feature_code":"PPL",
    "gn:name":"Saya\u00f1a",
    "gn:population":0,
    "gn:timezone":"America/Lima",
    "iso:country":"PE",
    "wof:name":"Sayana",
    "wof:placetype":"locality"
},
  "geometry": {"coordinates":[-71.27009,-15.22983],"type":"Point"}
}