{
  "type": "Feature",
  "properties": {
    "gn:admin1_code":"04",
    "gn:admin2_code":"405.0",
    "gn:admin3_code":"40517.0",
    "gn:asciiname":"Sayana",
    "gn:country_code":"PE",
    "gn:dem":4546,
    "gn:feature_class":"P",
    "gn:feature_code":"PPL",
    "gn:name":"Saya\u00f1a",
    "gn:population":0,
    "gn:timezone":"America/Lima",
    "iso:country":"PE",
    "name:deu_x_preferred":[
        "Sayana"
    ],
    "name:fra_x_preferred":[
        "S\u00e2yana"
    ],
    "name:hin_x_preferred":[
        "\u0938\u093e\u092f\u0923"
    ],
    "name:ita_x_preferred":[
        "S\u0101ya\u1e47a"
    ],
    "name:lit_x_preferred":[
        "Sajana"
    ],
    "name:ron_x_preferred":[
        "Sayana"
    ],
    "name:rus_x_preferred":[
        "\u0421\u0430\u044f\u043d\u0430"
    ],
    "name:san_x_preferred":[
        "\u0938\u093e\u092f\u0923\u0903"
    ],
    "name:spa_x_preferred":[
        "Saiana"
    ],
    "name:tam_x_preferred":[
        "\u0b9a\u0bbe\u0baf\u0ba9\u0bb0\u0bcd"
    ],
    "name:ukr_x_preferred":[
        "\u0421\u0430\u044f\u043d\u0430"
    ],
    "name:urd_x_preferred":[
        "\u0633\u06cc\u0627\u0646\u0627"
    ],
    "wof:name":"Sayana",
    "wof:placetype":"locality"
},
  "geometry": {"coordinates":[-71.27009,-15.22983],"type":"Point"}
}