{
  "type": "Feature",
  "properties": {
    "gn:admin1_code":"22",
    "gn:admin2_code":"2209.0",
    "gn:admin3_code":"220908.0",
    "gn:asciiname":"Huruhuasha",
    "gn:country_code":"PE",
    "gn:dem":320,
    "gn:feature_class":"P",
    "gn:feature_code":"PPL",
    "gn:name":"Huruhuasha",
    "gn:population":0,
    "gn:timezone":"America/Lima",
    "iso:country":"PE",
    "name:spa_x_preferred":[
        "Huruhuasha"
    ],
    "wof:name":"Huruhuasha",
    "wof:placetype":"locality"
},
  "geometry": {"coordinates":[-76.32758000000003,-6.5715],"type":"Point"}
}