{
  "type": "Feature",
  "properties": {
    "gn:admin1_code":"17.0",
    "gn:admin2_code":"1703.0",
    "gn:asciiname":"La Novia",
    "gn:country_code":"PE",
    "gn:dem":261,
    "gn:feature_class":"P",
    "gn:feature_code":"PPL",
    "gn:name":"La Novia",
    "gn:population":0,
    "gn:timezone":"America/Lima",
    "iso:country":"PE",
    "name:spa_x_preferred":[
        "La Novia"
    ],
    "wof:name":"La Novia",
    "wof:placetype":"locality"
},
  "geometry": {"coordinates":[-69.13882,-11.86775],"type":"Point"}
}