{
  "type": "Feature",
  "properties": {
    "gn:admin1_code":"5",
    "gn:admin2_code":"506.0",
    "gn:admin3_code":"50606.0",
    "gn:asciiname":"Chupahuaijo",
    "gn:country_code":"PE",
    "gn:dem":3266,
    "gn:feature_class":"P",
    "gn:feature_code":"PPL",
    "gn:name":"Chupahuaijo",
    "gn:population":0,
    "gn:timezone":"America/Lima",
    "iso:country":"PE",
    "wof:name":"Chupahuaijo",
    "wof:placetype":"locality"
},
  "geometry": {"coordinates":[-73.89028,-14.34583],"type":"Point"}
}