{
  "type": "Feature",
  "properties": {
    "gn:admin1_code":"5",
    "gn:admin2_code":"509.0",
    "gn:asciiname":"Huaichau",
    "gn:country_code":"PE",
    "gn:dem":3747,
    "gn:feature_class":"P",
    "gn:feature_code":"PPL",
    "gn:name":"Huaichau",
    "gn:population":0,
    "gn:timezone":"America/Lima",
    "iso:country":"PE",
    "wof:name":"Huaichau",
    "wof:placetype":"locality"
},
  "geometry": {"coordinates":[-73.62056,-14.17417],"type":"Point"}
}