{
  "type": "Feature",
  "properties": {
    "gn:admin1_code":"12.0",
    "gn:admin2_code":"1204.0",
    "gn:admin3_code":"120431.0",
    "gn:asciiname":"Hinostroza",
    "gn:country_code":"PE",
    "gn:dem":3825,
    "gn:feature_class":"P",
    "gn:feature_code":"PPL",
    "gn:name":"Hinostroza",
    "gn:population":0,
    "gn:timezone":"America/Lima",
    "iso:country":"PE",
    "wof:name":"Hinostroza",
    "wof:placetype":"locality"
},
  "geometry": {"coordinates":[-75.46465000000001,-11.89587],"type":"Point"}
}