{
  "type": "Feature",
  "properties": {
    "gn:admin1_code":"05",
    "gn:admin2_code":"507.0",
    "gn:admin3_code":"50706.0",
    "gn:asciiname":"Sallasalla",
    "gn:country_code":"PE",
    "gn:dem":3354,
    "gn:feature_class":"P",
    "gn:feature_code":"PPL",
    "gn:name":"Sallasalla",
    "gn:population":0,
    "gn:timezone":"America/Lima",
    "iso:country":"PE",
    "name:spa_x_preferred":[
        "Sallasalla"
    ],
    "wof:name":"Sallasalla",
    "wof:placetype":"locality"
},
  "geometry": {"coordinates":[-73.6049,-15.3512],"type":"Point"}
}