{
  "type": "Feature",
  "properties": {
    "gn:admin1_code":"21",
    "gn:admin2_code":"2105.0",
    "gn:admin3_code":"210503.0",
    "gn:asciiname":"Ubijuvo",
    "gn:country_code":"PE",
    "gn:dem":3831,
    "gn:feature_class":"P",
    "gn:feature_code":"PPL",
    "gn:name":"Ubijuvo",
    "gn:population":0,
    "gn:timezone":"America/Lima",
    "iso:country":"PE",
    "name:und_x_variant":[
        "Ubijuyo",
        "Ubijuvo"
    ],
    "wof:name":"Ubijuvo",
    "wof:placetype":"locality"
},
  "geometry": {"coordinates":[-69.55728000000001,-16.12461],"type":"Point"}
}