{
  "type": "Feature",
  "properties": {
    "gn:admin1_code":"02",
    "gn:admin2_code":"214.0",
    "gn:admin3_code":"21402.0",
    "gn:asciiname":"Rayan",
    "gn:country_code":"PE",
    "gn:dem":3235,
    "gn:feature_class":"P",
    "gn:feature_code":"PPL",
    "gn:name":"Ray\u00e1n",
    "gn:population":0,
    "gn:timezone":"America/Lima",
    "iso:country":"PE",
    "name:ara_x_preferred":[
        "\u0631\u064a\u0627\u0646"
    ],
    "name:fra_x_preferred":[
        "Rayan"
    ],
    "name:ita_x_preferred":[
        "Rayyan"
    ],
    "wof:name":"Rayan",
    "wof:placetype":"locality"
},
  "geometry": {"coordinates":[-77.28333000000001,-10.46667],"type":"Point"}
}