{
  "type": "Feature",
  "properties": {
    "gn:admin1_code":"5.0",
    "gn:admin2_code":"502.0",
    "gn:asciiname":"Sontorhuasi",
    "gn:country_code":"PE",
    "gn:dem":4335,
    "gn:feature_class":"P",
    "gn:feature_code":"PPL",
    "gn:name":"Sontorhuasi",
    "gn:population":0,
    "gn:timezone":"America/Lima",
    "iso:country":"PE",
    "wof:name":"Sontorhuasi",
    "wof:placetype":"locality"
},
  "geometry": {"coordinates":[-74.51469,-13.46406],"type":"Point"}
}