{
  "type": "Feature",
  "properties": {
    "gn:admin1_code":"21",
    "gn:admin2_code":"2104.0",
    "gn:admin3_code":"210402.0",
    "gn:asciiname":"Caracotana",
    "gn:country_code":"PE",
    "gn:dem":3826,
    "gn:feature_class":"P",
    "gn:feature_code":"PPL",
    "gn:name":"Caracotana",
    "gn:population":0,
    "gn:timezone":"America/Lima",
    "iso:country":"PE",
    "wof:name":"Caracotana",
    "wof:placetype":"locality"
},
  "geometry": {"coordinates":[-69.03025,-16.67385],"type":"Point"}
}