{
  "type": "Feature",
  "properties": {
    "gn:admin1_code":"21",
    "gn:admin2_code":"2107.0",
    "gn:admin3_code":"210709.0",
    "gn:asciiname":"Churuma Hacienda",
    "gn:country_code":"PE",
    "gn:dem":4191,
    "gn:feature_class":"P",
    "gn:feature_code":"PPL",
    "gn:name":"Churuma Hacienda",
    "gn:population":0,
    "gn:timezone":"America/Lima",
    "iso:country":"PE",
    "wof:name":"Churuma Hacienda",
    "wof:placetype":"locality"
},
  "geometry": {"coordinates":[-70.72360999999999,-15.60322],"type":"Point"}
}