{
  "type": "Feature",
  "properties": {
    "gn:admin1_code":"25",
    "gn:admin2_code":"2501.0",
    "gn:admin3_code":"250101.0",
    "gn:asciiname":"Chancay",
    "gn:country_code":"PE",
    "gn:dem":146,
    "gn:feature_class":"P",
    "gn:feature_code":"PPL",
    "gn:name":"Chancay",
    "gn:population":0,
    "gn:timezone":"America/Lima",
    "iso:country":"PE",
    "wof:name":"Chancay",
    "wof:placetype":"locality"
},
  "geometry": {"coordinates":[-74.48317,-8.29174],"type":"Point"}
}