{
  "type": "Feature",
  "properties": {
    "gn:admin1_code":"15",
    "gn:admin2_code":"1505.0",
    "gn:admin3_code":"150511.0",
    "gn:asciiname":"Jacalla",
    "gn:country_code":"PE",
    "gn:dem":1302,
    "gn:feature_class":"P",
    "gn:feature_code":"PPL",
    "gn:name":"Jacalla",
    "gn:population":0,
    "gn:timezone":"America/Lima",
    "iso:country":"PE",
    "wof:name":"Jacalla",
    "wof:placetype":"locality"
},
  "geometry": {"coordinates":[-76.09999999999999,-12.88333],"type":"Point"}
}