{
  "type": "Feature",
  "properties": {
    "gn:admin1_code":"5.0",
    "gn:admin2_code":"504.0",
    "gn:admin3_code":"50401.0",
    "gn:asciiname":"Espinacuy",
    "gn:country_code":"PE",
    "gn:dem":3337,
    "gn:feature_class":"P",
    "gn:feature_code":"PPL",
    "gn:name":"Espinacuy",
    "gn:population":0,
    "gn:timezone":"America/Lima",
    "iso:country":"PE",
    "wof:name":"Espinacuy",
    "wof:placetype":"locality"
},
  "geometry": {"coordinates":[-74.07583000000002,-12.78205],"type":"Point"}
}