{
  "type": "Feature",
  "properties": {
    "gn:admin1_code":"21",
    "gn:admin2_code":"2111.0",
    "gn:asciiname":"Viluyo",
    "gn:country_code":"PE",
    "gn:dem":4058,
    "gn:feature_class":"P",
    "gn:feature_code":"PPL",
    "gn:name":"Viluyo",
    "gn:population":0,
    "gn:timezone":"America/Lima",
    "iso:country":"PE",
    "wof:name":"Viluyo",
    "wof:placetype":"locality"
},
  "geometry": {"coordinates":[-70.70056,-15.99389],"type":"Point"}
}