{
  "type": "Feature",
  "properties": {
    "gn:admin1_code":"21",
    "gn:admin2_code":"2102.0",
    "gn:admin3_code":"210215.0",
    "gn:asciiname":"Tirapata",
    "gn:country_code":"PE",
    "gn:dem":3887,
    "gn:feature_class":"P",
    "gn:feature_code":"PPLA3",
    "gn:name":"Tirapata",
    "gn:population":0,
    "gn:timezone":"America/Lima",
    "iso:country":"PE",
    "name:kat_x_preferred":[
        "\u10e2\u10d8\u10e0\u10d0\u10de\u10d0\u10e2\u10d8\u10e1 \u10e0\u10d0\u10d8\u10dd\u10dc\u10d8"
    ],
    "name:por_x_preferred":[
        "Tirapata"
    ],
    "name:que_x_preferred":[
        "Tirapata distritu"
    ],
    "name:zho_x_preferred":[
        "\u8482\u62c9\u5e15\u5854\u5340"
    ],
    "wof:name":"Tirapata",
    "wof:placetype":"locality"
},
  "geometry": {"coordinates":[-70.40000000000001,-14.95],"type":"Point"}
}