{
  "type": "Feature",
  "properties": {
    "gn:admin1_code":"21",
    "gn:admin2_code":"2102.0",
    "gn:admin3_code":"210215.0",
    "gn:asciiname":"Tirapata",
    "gn:country_code":"PE",
    "gn:dem":3887,
    "gn:feature_class":"P",
    "gn:feature_code":"PPLA3",
    "gn:name":"Tirapata",
    "gn:population":0,
    "gn:timezone":"America/Lima",
    "iso:country":"PE",
    "wof:name":"Tirapata",
    "wof:placetype":"locality"
},
  "geometry": {"coordinates":[-70.40000000000001,-14.95],"type":"Point"}
}