{
  "type": "Feature",
  "properties": {
    "gn:admin1_code":"05",
    "gn:admin2_code":"503.0",
    "gn:admin3_code":"50301.0",
    "gn:asciiname":"Manzanayoc",
    "gn:country_code":"PE",
    "gn:dem":3880,
    "gn:feature_class":"P",
    "gn:feature_code":"PPL",
    "gn:name":"Manzanayoc",
    "gn:population":0,
    "gn:timezone":"America/Lima",
    "iso:country":"PE",
    "wof:name":"Manzanayoc",
    "wof:placetype":"locality"
},
  "geometry": {"coordinates":[-74.34999999999999,-13.98333],"type":"Point"}
}