{
  "type": "Feature",
  "properties": {
    "gn:admin1_code":"9",
    "gn:admin2_code":"906.0",
    "gn:admin3_code":"90607.0",
    "gn:asciiname":"Ladera",
    "gn:country_code":"PE",
    "gn:dem":4085,
    "gn:feature_class":"P",
    "gn:feature_code":"PPL",
    "gn:name":"Ladera",
    "gn:population":0,
    "gn:timezone":"America/Lima",
    "iso:country":"PE",
    "wof:name":"Ladera",
    "wof:placetype":"locality"
},
  "geometry": {"coordinates":[-75.04416999999999,-13.63556],"type":"Point"}
}