{
  "type": "Feature",
  "properties": {
    "gn:admin1_code":"15",
    "gn:admin2_code":"1507.0",
    "gn:admin3_code":"150713.0",
    "gn:asciiname":"Chatacancha",
    "gn:country_code":"PE",
    "gn:dem":2673,
    "gn:feature_class":"P",
    "gn:feature_code":"PPL",
    "gn:name":"Chatacancha",
    "gn:population":0,
    "gn:timezone":"America/Lima",
    "iso:country":"PE",
    "wof:name":"Chatacancha",
    "wof:placetype":"locality"
},
  "geometry": {"coordinates":[-76.43333,-12.28333],"type":"Point"}
}