{
  "type": "Feature",
  "properties": {
    "gn:admin1_code":"05",
    "gn:admin2_code":"506.0",
    "gn:admin3_code":"50619.0",
    "gn:asciiname":"Kajilla",
    "gn:country_code":"PE",
    "gn:dem":952,
    "gn:feature_class":"P",
    "gn:feature_code":"PPL",
    "gn:name":"Kajilla",
    "gn:population":0,
    "gn:timezone":"America/Lima",
    "iso:country":"PE",
    "wof:name":"Kajilla",
    "wof:placetype":"locality"
},
  "geometry": {"coordinates":[-74.23333000000002,-15.23333],"type":"Point"}
}