{
  "type": "Feature",
  "properties": {
    "gn:admin1_code":"2.0",
    "gn:admin2_code":"212.0",
    "gn:admin3_code":"21207.0",
    "gn:asciiname":"Consar",
    "gn:country_code":"PE",
    "gn:dem":3575,
    "gn:feature_class":"P",
    "gn:feature_code":"PPL",
    "gn:name":"Consar",
    "gn:population":0,
    "gn:timezone":"America/Lima",
    "iso:country":"PE",
    "wof:name":"Consar",
    "wof:placetype":"locality"
},
  "geometry": {"coordinates":[-77.80694,-9.19778],"type":"Point"}
}