{
  "type": "Feature",
  "properties": {
    "gn:admin1_code":"05",
    "gn:admin2_code":"501.0",
    "gn:admin3_code":"50105.0",
    "gn:asciiname":"Huanu Huanu",
    "gn:country_code":"PE",
    "gn:dem":3368,
    "gn:feature_class":"P",
    "gn:feature_code":"PPL",
    "gn:name":"Huanu Huanu",
    "gn:population":0,
    "gn:timezone":"America/Lima",
    "iso:country":"PE",
    "wof:name":"Huanu Huanu",
    "wof:placetype":"locality"
},
  "geometry": {"coordinates":[-74.08333,-13.51667],"type":"Point"}
}