{
  "type": "Feature",
  "properties": {
    "gn:admin1_code":"03",
    "gn:admin2_code":"301.0",
    "gn:admin3_code":"30104.0",
    "gn:asciiname":"Choquemarca",
    "gn:country_code":"PE",
    "gn:dem":3998,
    "gn:feature_class":"P",
    "gn:feature_code":"PPL",
    "gn:name":"Choquemarca",
    "gn:population":0,
    "gn:timezone":"America/Lima",
    "iso:country":"PE",
    "wof:name":"Choquemarca",
    "wof:placetype":"locality"
},
  "geometry": {"coordinates":[-72.53333000000001,-13.71667],"type":"Point"}
}