{
  "type": "Feature",
  "properties": {
    "gn:admin1_code":"03",
    "gn:admin2_code":"301.0",
    "gn:admin3_code":"30106.0",
    "gn:asciiname":"Lanbrama",
    "gn:country_code":"PE",
    "gn:dem":3201,
    "gn:feature_class":"P",
    "gn:feature_code":"PPL",
    "gn:name":"Lanbrama",
    "gn:population":0,
    "gn:timezone":"America/Lima",
    "iso:country":"PE",
    "name:und_x_variant":[
        "Lambrama"
    ],
    "wof:name":"Lanbrama",
    "wof:placetype":"locality"
},
  "geometry": {"coordinates":[-72.77174000000002,-13.87234],"type":"Point"}
}