{
  "type": "Feature",
  "properties": {
    "gn:admin1_code":"05",
    "gn:admin2_code":"505.0",
    "gn:admin3_code":"50505.0",
    "gn:asciiname":"Putuchay",
    "gn:country_code":"PE",
    "gn:dem":3064,
    "gn:feature_class":"P",
    "gn:feature_code":"PPL",
    "gn:name":"Putuchay",
    "gn:population":0,
    "gn:timezone":"America/Lima",
    "iso:country":"PE",
    "name:und_x_variant":[
        "Putucnay",
        "Putuchay"
    ],
    "wof:name":"Putuchay",
    "wof:placetype":"locality"
},
  "geometry": {"coordinates":[-73.50118000000001,-13.34178],"type":"Point"}
}