{
  "type": "Feature",
  "properties": {
    "gn:admin1_code":"12",
    "gn:admin2_code":"1207.0",
    "gn:admin3_code":"120709.0",
    "gn:asciiname":"Yaroca",
    "gn:country_code":"PE",
    "gn:dem":2928,
    "gn:feature_class":"P",
    "gn:feature_code":"PPL",
    "gn:name":"Yaroca",
    "gn:population":0,
    "gn:timezone":"America/Lima",
    "iso:country":"PE",
    "wof:name":"Yaroca",
    "wof:placetype":"locality"
},
  "geometry": {"coordinates":[-75.54736,-11.37051],"type":"Point"}
}