{
  "type": "Feature",
  "properties": {
    "gn:admin1_code":"21",
    "gn:admin2_code":"2113.0",
    "gn:admin3_code":"211301.0",
    "gn:asciiname":"Huareleque",
    "gn:country_code":"PE",
    "gn:dem":3834,
    "gn:feature_class":"P",
    "gn:feature_code":"PPL",
    "gn:name":"Huareleque",
    "gn:population":0,
    "gn:timezone":"America/Lima",
    "iso:country":"PE",
    "wof:name":"Huareleque",
    "wof:placetype":"locality"
},
  "geometry": {"coordinates":[-69.03404,-16.3531],"type":"Point"}
}