{
  "type": "Feature",
  "properties": {
    "gn:admin1_code":"14",
    "gn:admin2_code":"1403.0",
    "gn:admin3_code":"140301.0",
    "gn:asciiname":"Rio Hondo",
    "gn:country_code":"PE",
    "gn:dem":27,
    "gn:feature_class":"P",
    "gn:feature_code":"PPL",
    "gn:name":"R\u00edo Hondo",
    "gn:population":0,
    "gn:timezone":"America/Lima",
    "iso:country":"PE",
    "name:ceb_x_preferred":[
        "Rio Hondo"
    ],
    "name:deu_x_preferred":[
        "R\u00edo Hondo"
    ],
    "name:ita_x_preferred":[
        "Rio Hondo"
    ],
    "name:nds_x_preferred":[
        "R\u00edo Hondo"
    ],
    "name:nld_x_preferred":[
        "R\u00edo Hondo"
    ],
    "name:por_x_preferred":[
        "Rio Hondo"
    ],
    "name:spa_x_preferred":[
        "R\u00edo Hondo"
    ],
    "name:swe_x_preferred":[
        "Rio Hondo"
    ],
    "wof:name":"Rio Hondo",
    "wof:placetype":"locality"
},
  "geometry": {"coordinates":[-79.91176,-6.61032],"type":"Point"}
}