{
  "type": "Feature",
  "properties": {
    "gn:admin1_code":"15",
    "gn:admin2_code":"1510.0",
    "gn:admin3_code":"151001.0",
    "gn:asciiname":"Llipllepampa",
    "gn:country_code":"PE",
    "gn:dem":4451,
    "gn:feature_class":"P",
    "gn:feature_code":"PPL",
    "gn:name":"Llipllepampa",
    "gn:population":0,
    "gn:timezone":"America/Lima",
    "iso:country":"PE",
    "wof:name":"Llipllepampa",
    "wof:placetype":"locality"
},
  "geometry": {"coordinates":[-75.94086999999998,-12.36634],"type":"Point"}
}