{
  "type": "Feature",
  "properties": {
    "gn:admin1_code":"4",
    "gn:admin2_code":"405.0",
    "gn:admin3_code":"40504.0",
    "gn:asciiname":"Hacienda Precentacion",
    "gn:country_code":"PE",
    "gn:dem":4511,
    "gn:feature_class":"P",
    "gn:feature_code":"PPL",
    "gn:name":"Hacienda Precentaci\u00f3n",
    "gn:population":0,
    "gn:timezone":"America/Lima",
    "iso:country":"PE",
    "wof:name":"Hacienda Precentacion",
    "wof:placetype":"locality"
},
  "geometry": {"coordinates":[-71.07711999999999,-15.62454],"type":"Point"}
}