{
  "type": "Feature",
  "properties": {
    "gn:admin1_code":"9.0",
    "gn:admin2_code":"907.0",
    "gn:admin3_code":"90718.0",
    "gn:asciiname":"Uchuy Sune",
    "gn:country_code":"PE",
    "gn:dem":3841,
    "gn:feature_class":"P",
    "gn:feature_code":"PPL",
    "gn:name":"Uchuy Sune",
    "gn:population":0,
    "gn:timezone":"America/Lima",
    "iso:country":"PE",
    "wof:name":"Uchuy Sune",
    "wof:placetype":"locality"
},
  "geometry": {"coordinates":[-74.57866999999997,-12.23685],"type":"Point"}
}