{
  "type": "Feature",
  "properties": {
    "gn:admin1_code":"13.0",
    "gn:admin2_code":"1308.0",
    "gn:admin3_code":"130808.0",
    "gn:asciiname":"Cerro Negro",
    "gn:country_code":"PE",
    "gn:dem":3642,
    "gn:feature_class":"P",
    "gn:feature_code":"PPL",
    "gn:name":"Cerro Negro",
    "gn:population":0,
    "gn:timezone":"America/Lima",
    "iso:country":"PE",
    "wof:name":"Cerro Negro",
    "wof:placetype":"locality"
},
  "geometry": {"coordinates":[-77.41722,-8.03722],"type":"Point"}
}