{
  "type": "Feature",
  "properties": {
    "gn:admin1_code":"14.0",
    "gn:admin2_code":"1401.0",
    "gn:admin3_code":"140117.0",
    "gn:asciiname":"Primoreal",
    "gn:country_code":"PE",
    "gn:dem":69,
    "gn:feature_class":"P",
    "gn:feature_code":"PPL",
    "gn:name":"Primoreal",
    "gn:population":0,
    "gn:timezone":"America/Lima",
    "iso:country":"PE",
    "name:spa_x_preferred":[
        "Primoreal"
    ],
    "wof:name":"Primoreal",
    "wof:placetype":"locality"
},
  "geometry": {"coordinates":[-79.67005,-6.72965],"type":"Point"}
}