{
  "type": "Feature",
  "properties": {
    "gn:admin1_code":"21.0",
    "gn:admin2_code":"2112.0",
    "gn:asciiname":"Rio Blanco",
    "gn:country_code":"PE",
    "gn:dem":1206,
    "gn:feature_class":"P",
    "gn:feature_code":"PPL",
    "gn:name":"Rio Blanco",
    "gn:population":0,
    "gn:timezone":"America/Lima",
    "iso:country":"PE",
    "name:spa_x_preferred":[
        "Rio Blanco"
    ],
    "wof:name":"Rio Blanco",
    "wof:placetype":"locality"
},
  "geometry": {"coordinates":[-69.04534,-14.18048],"type":"Point"}
}