{
  "type": "Feature",
  "properties": {
    "gn:admin1_code":"03",
    "gn:admin2_code":"305.0",
    "gn:admin3_code":"30501.0",
    "gn:asciiname":"Quillilli",
    "gn:country_code":"PE",
    "gn:dem":4100,
    "gn:feature_class":"P",
    "gn:feature_code":"PPL",
    "gn:name":"Quillilli",
    "gn:population":0,
    "gn:timezone":"America/Lima",
    "iso:country":"PE",
    "wof:name":"Quillilli",
    "wof:placetype":"locality"
},
  "geometry": {"coordinates":[-72.18751999999998,-13.8018],"type":"Point"}
}