{
  "type": "Feature",
  "properties": {
    "gn:admin1_code":"9.0",
    "gn:admin2_code":"905.0",
    "gn:asciiname":"Millpocasa",
    "gn:country_code":"PE",
    "gn:dem":4132,
    "gn:feature_class":"P",
    "gn:feature_code":"PPL",
    "gn:name":"Millpocasa",
    "gn:population":0,
    "gn:timezone":"America/Lima",
    "iso:country":"PE",
    "wof:name":"Millpocasa",
    "wof:placetype":"locality"
},
  "geometry": {"coordinates":[-74.44485999999998,-12.65267],"type":"Point"}
}