{
  "type": "Feature",
  "properties": {
    "gn:admin1_code":"3",
    "gn:admin2_code":"302.0",
    "gn:admin3_code":"30213.0",
    "gn:asciiname":"Cutapi",
    "gn:country_code":"PE",
    "gn:dem":4332,
    "gn:feature_class":"P",
    "gn:feature_code":"PPL",
    "gn:name":"Cutapi",
    "gn:population":0,
    "gn:timezone":"America/Lima",
    "iso:country":"PE",
    "wof:name":"Cutapi",
    "wof:placetype":"locality"
},
  "geometry": {"coordinates":[-73.23721999999999,-13.805],"type":"Point"}
}