{
  "type": "Feature",
  "properties": {
    "gn:admin1_code":"4",
    "gn:admin2_code":"401.0",
    "gn:admin3_code":"40119.0",
    "gn:asciiname":"Amayane",
    "gn:country_code":"PE",
    "gn:dem":4120,
    "gn:feature_class":"P",
    "gn:feature_code":"PPL",
    "gn:name":"Amayane",
    "gn:population":0,
    "gn:timezone":"America/Lima",
    "iso:country":"PE",
    "wof:name":"Amayane",
    "wof:placetype":"locality"
},
  "geometry": {"coordinates":[-71.12501,-16.13058],"type":"Point"}
}