{
  "type": "Feature",
  "properties": {
    "gn:admin1_code":"16",
    "gn:admin2_code":"1601.0",
    "gn:admin3_code":"160104.0",
    "gn:asciiname":"Nuevo Eden",
    "gn:country_code":"PE",
    "gn:dem":91,
    "gn:feature_class":"P",
    "gn:feature_code":"PPL",
    "gn:name":"Nuevo Ed\u00e9n",
    "gn:population":0,
    "gn:timezone":"America/Lima",
    "iso:country":"PE",
    "wof:name":"Nuevo Eden",
    "wof:placetype":"locality"
},
  "geometry": {"coordinates":[-72.98965,-3.62797],"type":"Point"}
}