{
  "type": "Feature",
  "properties": {
    "gn:admin1_code":"17.0",
    "gn:admin2_code":"1703.0",
    "gn:asciiname":"Bellavista Dos",
    "gn:country_code":"PE",
    "gn:dem":300,
    "gn:feature_class":"P",
    "gn:feature_code":"PPL",
    "gn:name":"Bellavista Dos",
    "gn:population":0,
    "gn:timezone":"America/Lima",
    "iso:country":"PE",
    "name:spa_x_preferred":[
        "Bellavista Dos"
    ],
    "wof:name":"Bellavista Dos",
    "wof:placetype":"locality"
},
  "geometry": {"coordinates":[-69.36878,-11.30506],"type":"Point"}
}