{
  "type": "Feature",
  "properties": {
    "gn:admin1_code":"4",
    "gn:admin2_code":"405.0",
    "gn:admin3_code":"40504.0",
    "gn:asciiname":"Huallanocco",
    "gn:country_code":"PE",
    "gn:dem":4231,
    "gn:feature_class":"P",
    "gn:feature_code":"PPL",
    "gn:name":"Huallanocco",
    "gn:population":0,
    "gn:timezone":"America/Lima",
    "iso:country":"PE",
    "wof:name":"Huallanocco",
    "wof:placetype":"locality"
},
  "geometry": {"coordinates":[-71.24083,-15.44861],"type":"Point"}
}