{
  "type": "Feature",
  "properties": {
    "gn:admin1_code":"21",
    "gn:admin2_code":"2102.0",
    "gn:admin3_code":"210206.0",
    "gn:asciiname":"Catrachupa",
    "gn:country_code":"PE",
    "gn:dem":3886,
    "gn:feature_class":"P",
    "gn:feature_code":"PPL",
    "gn:name":"Catrachupa",
    "gn:population":0,
    "gn:timezone":"America/Lima",
    "iso:country":"PE",
    "wof:name":"Catrachupa",
    "wof:placetype":"locality"
},
  "geometry": {"coordinates":[-69.95744000000001,-15.1695],"type":"Point"}
}