{
  "type": "Feature",
  "properties": {
    "iso:country":"PE",
    "qs:gn_pop":0,
    "qs:name":"M\u00e1ncora Hacienda",
    "qs:name_adm0":"Per\u00fa",
    "qs:name_adm1":"Piura",
    "qs:photos":934,
    "qs:photos_1k":189,
    "qs:photos_9k":4,
    "qs:photos_9r":6,
    "qs:photos_all":934,
    "qs:photos_sr":10,
    "qs:placetype":"Town",
    "qs:pop_sr":"0",
    "qs:woe_adm0":23424919,
    "wof:name":"M\u00e1ncora Hacienda",
    "wof:placetype":"locality"
},
  "geometry": {"coordinates":[-81.034469,-4.095609],"type":"Point"}
}