{
  "type": "Feature",
  "properties": {
    "gn:admin1_code":"12.0",
    "gn:admin2_code":"1204.0",
    "gn:admin3_code":"120423.0",
    "gn:asciiname":"Hualichaca",
    "gn:country_code":"PE",
    "gn:dem":3812,
    "gn:feature_class":"P",
    "gn:feature_code":"PPL",
    "gn:name":"Hualichaca",
    "gn:population":0,
    "gn:timezone":"America/Lima",
    "iso:country":"PE",
    "wof:name":"Hualichaca",
    "wof:placetype":"locality"
},
  "geometry": {"coordinates":[-75.52181999999998,-11.83872],"type":"Point"}
}