{
  "type": "Feature",
  "properties": {
    "gn:admin1_code":"21",
    "gn:admin2_code":"2104.0",
    "gn:admin3_code":"210405.0",
    "gn:asciiname":"Tuturuma",
    "gn:country_code":"PE",
    "gn:dem":4089,
    "gn:feature_class":"P",
    "gn:feature_code":"PPL",
    "gn:name":"Tuturuma",
    "gn:population":0,
    "gn:timezone":"America/Lima",
    "iso:country":"PE",
    "wof:name":"Tuturuma",
    "wof:placetype":"locality"
},
  "geometry": {"coordinates":[-69.40083,-16.9775],"type":"Point"}
}