{
  "type": "Feature",
  "properties": {
    "gn:admin1_code":"25",
    "gn:admin2_code":"2504.0",
    "gn:admin3_code":"250401.0",
    "gn:asciiname":"Puerto Venecia",
    "gn:country_code":"PE",
    "gn:dem":224,
    "gn:feature_class":"P",
    "gn:feature_code":"PPL",
    "gn:name":"Puerto Venecia",
    "gn:population":0,
    "gn:timezone":"America/Lima",
    "iso:country":"PE",
    "wof:name":"Puerto Venecia",
    "wof:placetype":"locality"
},
  "geometry": {"coordinates":[-70.55,-9.53333],"type":"Point"}
}