{
  "type": "Feature",
  "properties": {
    "gn:admin1_code":"13",
    "gn:admin2_code":"1306.0",
    "gn:admin3_code":"130601.0",
    "gn:asciiname":"Samne",
    "gn:country_code":"PE",
    "gn:dem":1348,
    "gn:feature_class":"P",
    "gn:feature_code":"PPL",
    "gn:name":"Samne",
    "gn:population":0,
    "gn:timezone":"America/Lima",
    "iso:country":"PE",
    "name:und_x_variant":[
        "Samme",
        "Samne"
    ],
    "wof:name":"Samne",
    "wof:placetype":"locality"
},
  "geometry": {"coordinates":[-78.68971999999999,-7.99464],"type":"Point"}
}