{
  "type": "Feature",
  "properties": {
    "gn:admin1_code":"13",
    "gn:admin2_code":"1308.0",
    "gn:admin3_code":"130808.0",
    "gn:asciiname":"Huayabas",
    "gn:country_code":"PE",
    "gn:dem":2304,
    "gn:feature_class":"P",
    "gn:feature_code":"PPL",
    "gn:name":"Huayabas",
    "gn:population":0,
    "gn:timezone":"America/Lima",
    "iso:country":"PE",
    "wof:name":"Huayabas",
    "wof:placetype":"locality"
},
  "geometry": {"coordinates":[-77.58035,-7.98256],"type":"Point"}
}