{
  "type": "Feature",
  "properties": {
    "gn:admin1_code":"9.0",
    "gn:admin2_code":"902.0",
    "gn:admin3_code":"90206.0",
    "gn:asciiname":"Corralniyoc",
    "gn:country_code":"PE",
    "gn:dem":3739,
    "gn:feature_class":"P",
    "gn:feature_code":"PPL",
    "gn:name":"Corralniyoc",
    "gn:population":0,
    "gn:timezone":"America/Lima",
    "iso:country":"PE",
    "wof:name":"Corralniyoc",
    "wof:placetype":"locality"
},
  "geometry": {"coordinates":[-74.74221999999997,-12.76571],"type":"Point"}
}