{
  "type": "Feature",
  "properties": {
    "gn:admin1_code":"9.0",
    "gn:admin2_code":"906.0",
    "gn:admin3_code":"90607.0",
    "gn:asciiname":"Tajrapampa",
    "gn:country_code":"PE",
    "gn:dem":4470,
    "gn:feature_class":"P",
    "gn:feature_code":"PPL",
    "gn:name":"Tajrapampa",
    "gn:population":0,
    "gn:timezone":"America/Lima",
    "iso:country":"PE",
    "wof:name":"Tajrapampa",
    "wof:placetype":"locality"
},
  "geometry": {"coordinates":[-74.94141999999999,-13.20812],"type":"Point"}
}