{
  "type": "Feature",
  "properties": {
    "gn:admin1_code":"20",
    "gn:admin2_code":"2001.0",
    "gn:admin3_code":"200105.0",
    "gn:asciiname":"Monte Castillo",
    "gn:country_code":"PE",
    "gn:dem":24,
    "gn:feature_class":"P",
    "gn:feature_code":"PPL",
    "gn:name":"Monte Castillo",
    "gn:population":0,
    "gn:timezone":"America/Lima",
    "iso:country":"PE",
    "wof:name":"Monte Castillo",
    "wof:placetype":"locality"
},
  "geometry": {"coordinates":[-80.71366999999999,-5.28172],"type":"Point"}
}