{
  "type": "Feature",
  "properties": {
    "gn:admin1_code":"10",
    "gn:admin2_code":"1002.0",
    "gn:admin3_code":"100206.0",
    "gn:asciiname":"Antacalla",
    "gn:country_code":"PE",
    "gn:dem":3602,
    "gn:feature_class":"P",
    "gn:feature_code":"PPL",
    "gn:name":"Antacalla",
    "gn:population":0,
    "gn:timezone":"America/Lima",
    "iso:country":"PE",
    "wof:name":"Antacalla",
    "wof:placetype":"locality"
},
  "geometry": {"coordinates":[-76.30662,-10.36436],"type":"Point"}
}