{
  "type": "Feature",
  "properties": {
    "gn:admin1_code":"5",
    "gn:admin2_code":"506.0",
    "gn:admin3_code":"50619.0",
    "gn:asciiname":"Calapampa",
    "gn:country_code":"PE",
    "gn:dem":684,
    "gn:feature_class":"P",
    "gn:feature_code":"PPL",
    "gn:name":"Calapampa",
    "gn:population":0,
    "gn:timezone":"America/Lima",
    "iso:country":"PE",
    "name:und_x_variant":[
        "Hacienda Calapampa",
        "Calapampa"
    ],
    "wof:name":"Calapampa",
    "wof:placetype":"locality"
},
  "geometry": {"coordinates":[-74.29864999999999,-15.28763],"type":"Point"}
}