{
  "type": "Feature",
  "properties": {
    "gn:admin1_code":"20",
    "gn:admin2_code":"2003.0",
    "gn:admin3_code":"200306.0",
    "gn:asciiname":"Surupite",
    "gn:country_code":"PE",
    "gn:dem":3161,
    "gn:feature_class":"P",
    "gn:feature_code":"PPL",
    "gn:name":"Surupite",
    "gn:population":0,
    "gn:timezone":"America/Lima",
    "iso:country":"PE",
    "wof:name":"Surupite",
    "wof:placetype":"locality"
},
  "geometry": {"coordinates":[-79.53975,-5.3465],"type":"Point"}
}