{
  "type": "Feature",
  "properties": {
    "gn:admin1_code":"4",
    "gn:admin2_code":"405.0",
    "gn:admin3_code":"40505.0",
    "gn:asciiname":"Tonquipa",
    "gn:country_code":"PE",
    "gn:dem":4408,
    "gn:feature_class":"P",
    "gn:feature_code":"PPL",
    "gn:name":"Tonquipa",
    "gn:population":0,
    "gn:timezone":"America/Lima",
    "iso:country":"PE",
    "wof:name":"Tonquipa",
    "wof:placetype":"locality"
},
  "geometry": {"coordinates":[-71.80074,-14.92505],"type":"Point"}
}