{
  "type": "Feature",
  "properties": {
    "gn:admin1_code":"06",
    "gn:admin2_code":"603.0",
    "gn:admin3_code":"60304.0",
    "gn:asciiname":"Lloquemayo",
    "gn:country_code":"PE",
    "gn:dem":1975,
    "gn:feature_class":"P",
    "gn:feature_code":"PPL",
    "gn:name":"Lloquemayo",
    "gn:population":0,
    "gn:timezone":"America/Lima",
    "iso:country":"PE",
    "wof:name":"Lloquemayo",
    "wof:placetype":"locality"
},
  "geometry": {"coordinates":[-78.2692,-6.82945],"type":"Point"}
}