{
  "type": "Feature",
  "properties": {
    "gn:admin1_code":"04",
    "gn:admin2_code":"401.0",
    "gn:admin3_code":"40121.0",
    "gn:asciiname":"La Victoria Hacienda",
    "gn:country_code":"PE",
    "gn:dem":1241,
    "gn:feature_class":"P",
    "gn:feature_code":"PPL",
    "gn:name":"La Victoria Hacienda",
    "gn:population":0,
    "gn:timezone":"America/Lima",
    "iso:country":"PE",
    "wof:name":"La Victoria Hacienda",
    "wof:placetype":"locality"
},
  "geometry": {"coordinates":[-72.10016,-16.51675],"type":"Point"}
}