{
  "type": "Feature",
  "properties": {
    "gn:admin1_code":"19.0",
    "gn:admin2_code":"1902.0",
    "gn:asciiname":"Gredaucro",
    "gn:country_code":"PE",
    "gn:dem":4366,
    "gn:feature_class":"P",
    "gn:feature_code":"PPL",
    "gn:name":"Gredaucro",
    "gn:population":0,
    "gn:timezone":"America/Lima",
    "iso:country":"PE",
    "wof:name":"Gredaucro",
    "wof:placetype":"locality"
},
  "geometry": {"coordinates":[-76.59971999999998,-10.35917],"type":"Point"}
}