{
  "type": "Feature",
  "properties": {
    "gn:admin1_code":"23",
    "gn:admin2_code":"2303.0",
    "gn:admin3_code":"230302.0",
    "gn:asciiname":"Alameda",
    "gn:country_code":"PE",
    "gn:dem":1409,
    "gn:feature_class":"P",
    "gn:feature_code":"PPL",
    "gn:name":"Alameda",
    "gn:population":0,
    "gn:timezone":"America/Lima",
    "iso:country":"PE",
    "name:cat_x_preferred":[
        "Alameda"
    ],
    "name:ceb_x_preferred":[
        "Alameda"
    ],
    "name:deu_x_preferred":[
        "Alameda"
    ],
    "name:epo_x_preferred":[
        "Alameda"
    ],
    "name:fas_x_preferred":[
        "\u0622\u0644\u0627\u0645\u062f\u0627"
    ],
    "name:fra_x_preferred":[
        "Alameda"
    ],
    "name:glg_x_preferred":[
        "Alameda"
    ],
    "name:ita_x_preferred":[
        "Alameda"
    ],
    "name:jpn_x_preferred":[
        "\u30a2\u30e9\u30e1\u30c0"
    ],
    "name:kor_x_preferred":[
        "\uc568\ub7ec\ubbf8\ub2e4"
    ],
    "name:nld_x_preferred":[
        "Alameda"
    ],
    "name:pol_x_preferred":[
        "Alameda"
    ],
    "name:por_x_preferred":[
        "Alameda"
    ],
    "name:rus_x_preferred":[
        "\u0410\u043b\u0430\u043c\u0438\u0434\u0430"
    ],
    "name:spa_x_preferred":[
        "Alameda"
    ],
    "name:srp_x_preferred":[
        "\u0410\u043b\u0430\u043c\u0438\u0434\u0430"
    ],
    "name:swe_x_preferred":[
        "Alameda"
    ],
    "name:tur_x_preferred":[
        "Alameda"
    ],
    "name:ukr_x_preferred":[
        "\u0410\u043b\u0430\u043c\u0435\u0434\u0430"
    ],
    "wof:name":"Alameda",
    "wof:placetype":"locality"
},
  "geometry": {"coordinates":[-70.51371999999998,-17.42304],"type":"Point"}
}