{
  "type": "Feature",
  "properties": {
    "gn:admin1_code":"23",
    "gn:admin2_code":"2303.0",
    "gn:admin3_code":"230302.0",
    "gn:asciiname":"Alameda",
    "gn:country_code":"PE",
    "gn:dem":1409,
    "gn:feature_class":"P",
    "gn:feature_code":"PPL",
    "gn:name":"Alameda",
    "gn:population":0,
    "gn:timezone":"America/Lima",
    "iso:country":"PE",
    "wof:name":"Alameda",
    "wof:placetype":"locality"
},
  "geometry": {"coordinates":[-70.51371999999998,-17.42304],"type":"Point"}
}