{
  "type": "Feature",
  "properties": {
    "gn:admin1_code":"5",
    "gn:admin2_code":"509.0",
    "gn:admin3_code":"50908.0",
    "gn:asciiname":"Huiccocho",
    "gn:country_code":"PE",
    "gn:dem":3705,
    "gn:feature_class":"P",
    "gn:feature_code":"PPL",
    "gn:name":"Huiccocho",
    "gn:population":0,
    "gn:timezone":"America/Lima",
    "iso:country":"PE",
    "wof:name":"Huiccocho",
    "wof:placetype":"locality"
},
  "geometry": {"coordinates":[-73.62111,-14.2375],"type":"Point"}
}