{
  "type": "Feature",
  "properties": {
    "gn:admin1_code":"2.0",
    "gn:admin2_code":"218.0",
    "gn:admin3_code":"21801.0",
    "gn:asciiname":"Alto Canal",
    "gn:country_code":"PE",
    "gn:dem":78,
    "gn:feature_class":"P",
    "gn:feature_code":"PPL",
    "gn:name":"Alto Canal",
    "gn:population":0,
    "gn:timezone":"America/Lima",
    "iso:country":"PE",
    "name:spa_x_preferred":[
        "Alto Canal"
    ],
    "wof:name":"Alto Canal",
    "wof:placetype":"locality"
},
  "geometry": {"coordinates":[-78.56244000000002,-8.94341],"type":"Point"}
}