{
  "type": "Feature",
  "properties": {
    "gn:admin1_code":"06",
    "gn:admin2_code":"611.0",
    "gn:admin3_code":"61113.0",
    "gn:asciiname":"Mutis",
    "gn:country_code":"PE",
    "gn:dem":2949,
    "gn:feature_class":"P",
    "gn:feature_code":"PPL",
    "gn:name":"Mutis",
    "gn:population":0,
    "gn:timezone":"America/Lima",
    "iso:country":"PE",
    "wof:name":"Mutis",
    "wof:placetype":"locality"
},
  "geometry": {"coordinates":[-79.05,-7.05],"type":"Point"}
}