{
  "type": "Feature",
  "properties": {
    "gn:admin1_code":"04",
    "gn:admin2_code":"403.0",
    "gn:admin3_code":"40305.0",
    "gn:asciiname":"Chavina",
    "gn:country_code":"PE",
    "gn:dem":60,
    "gn:feature_class":"P",
    "gn:feature_code":"PPL",
    "gn:name":"Chavi\u00f1a",
    "gn:population":0,
    "gn:timezone":"America/Lima",
    "iso:country":"PE",
    "wof:name":"Chavina",
    "wof:placetype":"locality"
},
  "geometry": {"coordinates":[-74.63894000000001,-15.62535],"type":"Point"}
}