{
  "type": "Feature",
  "properties": {
    "gn:admin1_code":"22.0",
    "gn:admin2_code":"2210.0",
    "gn:admin3_code":"221001.0",
    "gn:asciiname":"Alto Peso",
    "gn:country_code":"PE",
    "gn:dem":581,
    "gn:feature_class":"P",
    "gn:feature_code":"PPLL",
    "gn:name":"Alto Peso",
    "gn:population":0,
    "gn:timezone":"America/Lima",
    "iso:country":"PE",
    "wof:name":"Alto Peso",
    "wof:placetype":"locality"
},
  "geometry": {"coordinates":[-76.48203000000002,-8.43596],"type":"Point"}
}