{
  "type": "Feature",
  "properties": {
    "gn:admin1_code":"8",
    "gn:admin2_code":"808.0",
    "gn:admin3_code":"80807.0",
    "gn:asciiname":"Carhuaycollo",
    "gn:country_code":"PE",
    "gn:dem":4519,
    "gn:feature_class":"P",
    "gn:feature_code":"PPL",
    "gn:name":"Carhuaycollo",
    "gn:population":0,
    "gn:timezone":"America/Lima",
    "iso:country":"PE",
    "wof:name":"Carhuaycollo",
    "wof:placetype":"locality"
},
  "geometry": {"coordinates":[-71.74248,-14.96477],"type":"Point"}
}