{
  "type": "Feature",
  "properties": {
    "gn:admin1_code":"25",
    "gn:admin2_code":"2502.0",
    "gn:admin3_code":"250201.0",
    "gn:asciiname":"Pajonal Kepitoni",
    "gn:country_code":"PE",
    "gn:dem":1265,
    "gn:feature_class":"P",
    "gn:feature_code":"PPL",
    "gn:name":"Pajonal Kepitoni",
    "gn:population":0,
    "gn:timezone":"America/Lima",
    "iso:country":"PE",
    "name:spa_x_preferred":[
        "Pajonal Kepitoni"
    ],
    "wof:name":"Pajonal Kepitoni",
    "wof:placetype":"locality"
},
  "geometry": {"coordinates":[-74.34798000000001,-10.86656],"type":"Point"}
}