{
  "type": "Feature",
  "properties": {
    "gn:admin1_code":"16",
    "gn:admin2_code":"1601.0",
    "gn:admin3_code":"160105.0",
    "gn:asciiname":"Morupa",
    "gn:country_code":"PE",
    "gn:dem":86,
    "gn:feature_class":"P",
    "gn:feature_code":"PPL",
    "gn:name":"Morupa",
    "gn:population":0,
    "gn:timezone":"America/Lima",
    "iso:country":"PE",
    "wof:name":"Morupa",
    "wof:placetype":"locality"
},
  "geometry": {"coordinates":[-72.63424999999999,-3.47091],"type":"Point"}
}