{
  "type": "Feature",
  "properties": {
    "gn:admin1_code":"12.0",
    "gn:admin2_code":"1203.0",
    "gn:admin3_code":"120305.0",
    "gn:asciiname":"Gallinazo",
    "gn:country_code":"PE",
    "gn:dem":1418,
    "gn:feature_class":"P",
    "gn:feature_code":"PPLL",
    "gn:name":"Gallinazo",
    "gn:population":0,
    "gn:timezone":"America/Lima",
    "iso:country":"PE",
    "wof:name":"Gallinazo",
    "wof:placetype":"locality"
},
  "geometry": {"coordinates":[-75.39511,-11.16193],"type":"Point"}
}