{
  "type": "Feature",
  "properties": {
    "gn:admin1_code":"18",
    "gn:admin2_code":"1802.0",
    "gn:admin3_code":"180208.0",
    "gn:asciiname":"Talasquia",
    "gn:country_code":"PE",
    "gn:dem":2716,
    "gn:feature_class":"P",
    "gn:feature_code":"PPL",
    "gn:name":"Talasquia",
    "gn:population":0,
    "gn:timezone":"America/Lima",
    "iso:country":"PE",
    "wof:name":"Talasquia",
    "wof:placetype":"locality"
},
  "geometry": {"coordinates":[-71.17882,-16.65093],"type":"Point"}
}