{
  "type": "Feature",
  "properties": {
    "gn:admin1_code":"15",
    "gn:admin2_code":"1509.0",
    "gn:admin3_code":"150905.0",
    "gn:asciiname":"Liple",
    "gn:country_code":"PE",
    "gn:dem":2235,
    "gn:feature_class":"P",
    "gn:feature_code":"PPL",
    "gn:name":"Liple",
    "gn:population":0,
    "gn:timezone":"America/Lima",
    "iso:country":"PE",
    "wof:name":"Liple",
    "wof:placetype":"locality"
},
  "geometry": {"coordinates":[-76.98815,-10.86802],"type":"Point"}
}