{
  "type": "Feature",
  "properties": {
    "gn:admin1_code":"06",
    "gn:admin2_code":"607.0",
    "gn:admin3_code":"60701.0",
    "gn:asciiname":"Sugar",
    "gn:country_code":"PE",
    "gn:dem":3462,
    "gn:feature_class":"P",
    "gn:feature_code":"PPL",
    "gn:name":"Sugar",
    "gn:population":0,
    "gn:timezone":"America/Lima",
    "iso:country":"PE",
    "wof:name":"Sugar",
    "wof:placetype":"locality"
},
  "geometry": {"coordinates":[-78.41364,-6.69507],"type":"Point"}
}