{
  "type": "Feature",
  "properties": {
    "gn:admin1_code":"06",
    "gn:admin2_code":"608.0",
    "gn:asciiname":"Alizo",
    "gn:country_code":"PE",
    "gn:dem":2588,
    "gn:feature_class":"P",
    "gn:feature_code":"PPL",
    "gn:name":"Alizo",
    "gn:population":0,
    "gn:timezone":"America/Lima",
    "iso:country":"PE",
    "wof:name":"Alizo",
    "wof:placetype":"locality"
},
  "geometry": {"coordinates":[-79.43709,-5.99759],"type":"Point"}
}