{
  "type": "Feature",
  "properties": {
    "gn:admin1_code":"10.0",
    "gn:admin2_code":"1006.0",
    "gn:admin3_code":"100604.0",
    "gn:asciiname":"Sangapilla",
    "gn:country_code":"PE",
    "gn:dem":596,
    "gn:feature_class":"P",
    "gn:feature_code":"PPL",
    "gn:name":"Sangapilla",
    "gn:population":0,
    "gn:timezone":"America/Lima",
    "iso:country":"PE",
    "wof:name":"Sangapilla",
    "wof:placetype":"locality"
},
  "geometry": {"coordinates":[-76.10576,-8.94391],"type":"Point"}
}