{
  "type": "Feature",
  "properties": {
    "gn:admin1_code":"14.0",
    "gn:admin2_code":"1402.0",
    "gn:admin3_code":"140205.0",
    "gn:asciiname":"La Coralito",
    "gn:country_code":"PE",
    "gn:dem":46,
    "gn:feature_class":"P",
    "gn:feature_code":"PPL",
    "gn:name":"La Coralito",
    "gn:population":0,
    "gn:timezone":"America/Lima",
    "iso:country":"PE",
    "name:spa_x_preferred":[
        "La Coralito"
    ],
    "wof:name":"La Coralito",
    "wof:placetype":"locality"
},
  "geometry": {"coordinates":[-79.79006,-6.56527],"type":"Point"}
}