{
  "type": "Feature",
  "properties": {
    "gn:admin1_code":"05",
    "gn:admin2_code":"506.0",
    "gn:admin3_code":"50612.0",
    "gn:asciiname":"Espenca",
    "gn:country_code":"PE",
    "gn:dem":1870,
    "gn:feature_class":"P",
    "gn:feature_code":"PPL",
    "gn:name":"Espenca",
    "gn:population":0,
    "gn:timezone":"America/Lima",
    "iso:country":"PE",
    "wof:name":"Espenca",
    "wof:placetype":"locality"
},
  "geometry": {"coordinates":[-74.90000000000001,-14.41667],"type":"Point"}
}