{
  "type": "Feature",
  "properties": {
    "gn:admin1_code":"8",
    "gn:admin2_code":"809.0",
    "gn:admin3_code":"80906.0",
    "gn:asciiname":"Santosaire Alto",
    "gn:country_code":"PE",
    "gn:dem":1512,
    "gn:feature_class":"P",
    "gn:feature_code":"PPL",
    "gn:name":"Santosaire Alto",
    "gn:population":0,
    "gn:timezone":"America/Lima",
    "iso:country":"PE",
    "wof:name":"Santosaire Alto",
    "wof:placetype":"locality"
},
  "geometry": {"coordinates":[-72.52786999999999,-12.54471],"type":"Point"}
}