{
  "type": "Feature",
  "properties": {
    "gn:admin1_code":"14",
    "gn:admin2_code":"1401.0",
    "gn:admin3_code":"140105.0",
    "gn:asciiname":"San Carlos",
    "gn:country_code":"PE",
    "gn:dem":32,
    "gn:feature_class":"P",
    "gn:feature_code":"PPLL",
    "gn:name":"San Carlos",
    "gn:population":0,
    "gn:timezone":"America/Lima",
    "iso:country":"PE",
    "name:spa_x_preferred":[
        "San Carlos"
    ],
    "wof:name":"San Carlos",
    "wof:placetype":"locality"
},
  "geometry": {"coordinates":[-79.83684000000002,-6.75582],"type":"Point"}
}