{
  "type": "Feature",
  "properties": {
    "gn:admin1_code":"04",
    "gn:admin2_code":"403.0",
    "gn:admin3_code":"40309.0",
    "gn:asciiname":"Sulcacha",
    "gn:country_code":"PE",
    "gn:dem":946,
    "gn:feature_class":"P",
    "gn:feature_code":"PPL",
    "gn:name":"Sulcacha",
    "gn:population":0,
    "gn:timezone":"America/Lima",
    "iso:country":"PE",
    "name:spa_x_preferred":[
        "Sulcacha"
    ],
    "wof:name":"Sulcacha",
    "wof:placetype":"locality"
},
  "geometry": {"coordinates":[-74.1023,-15.66202],"type":"Point"}
}