{
  "type": "Feature",
  "properties": {
    "gn:admin1_code":"1.0",
    "gn:admin2_code":"105.0",
    "gn:admin3_code":"10519.0",
    "gn:asciiname":"Graneros",
    "gn:country_code":"PE",
    "gn:dem":2959,
    "gn:feature_class":"P",
    "gn:feature_code":"PPL",
    "gn:name":"Graneros",
    "gn:population":0,
    "gn:timezone":"America/Lima",
    "iso:country":"PE",
    "name:bak_x_preferred":[
        "\u0413\u0440\u0430\u043d\u0435\u0440\u043e\u0441"
    ],
    "name:cat_x_preferred":[
        "Graneros"
    ],
    "name:ceb_x_preferred":[
        "Graneros"
    ],
    "name:eus_x_preferred":[
        "Graneros"
    ],
    "name:fas_x_preferred":[
        "\u06af\u0631\u0627\u0646\u0631\u0648\u0633"
    ],
    "name:fra_x_preferred":[
        "Graneros"
    ],
    "name:ita_x_preferred":[
        "Graneros"
    ],
    "name:kor_x_preferred":[
        "\uadf8\ub77c\ub124\ub85c\uc2a4"
    ],
    "name:nld_x_preferred":[
        "Graneros"
    ],
    "name:pol_x_preferred":[
        "Graneros"
    ],
    "name:por_x_preferred":[
        "Graneros"
    ],
    "name:ron_x_preferred":[
        "Graneros"
    ],
    "name:rus_x_preferred":[
        "\u0413\u0440\u0430\u043d\u0435\u0440\u043e\u0441"
    ],
    "name:sco_x_preferred":[
        "Graneros"
    ],
    "name:spa_x_preferred":[
        "Graneros"
    ],
    "name:srp_x_preferred":[
        "\u0413\u0440\u0430\u043d\u0435\u0440\u043e\u0441"
    ],
    "name:swe_x_preferred":[
        "Graneros"
    ],
    "name:zho_x_preferred":[
        "\u683c\u62c9\u5167\u7f85\u65af"
    ],
    "wof:name":"Graneros",
    "wof:placetype":"locality"
},
  "geometry": {"coordinates":[-77.88706999999999,-6.45746],"type":"Point"}
}