{
  "type": "Feature",
  "properties": {
    "gn:admin1_code":"1.0",
    "gn:admin2_code":"105.0",
    "gn:admin3_code":"10519.0",
    "gn:asciiname":"Graneros",
    "gn:country_code":"PE",
    "gn:dem":2959,
    "gn:feature_class":"P",
    "gn:feature_code":"PPL",
    "gn:name":"Graneros",
    "gn:population":0,
    "gn:timezone":"America/Lima",
    "iso:country":"PE",
    "wof:name":"Graneros",
    "wof:placetype":"locality"
},
  "geometry": {"coordinates":[-77.88706999999999,-6.45746],"type":"Point"}
}