{
  "type": "Feature",
  "properties": {
    "gn:admin1_code":"2.0",
    "gn:admin2_code":"206.0",
    "gn:admin3_code":"20606.0",
    "gn:asciiname":"Huicoshpachan",
    "gn:country_code":"PE",
    "gn:dem":3175,
    "gn:feature_class":"P",
    "gn:feature_code":"PPL",
    "gn:name":"Huicoshpachan",
    "gn:population":0,
    "gn:timezone":"America/Lima",
    "iso:country":"PE",
    "wof:name":"Huicoshpachan",
    "wof:placetype":"locality"
},
  "geometry": {"coordinates":[-77.54971999999999,-9.32333],"type":"Point"}
}