{
  "type": "Feature",
  "properties": {
    "gn:admin1_code":"06",
    "gn:admin2_code":"606.0",
    "gn:admin3_code":"60612.0",
    "gn:asciiname":"Santo Domingo de Capilla",
    "gn:country_code":"PE",
    "gn:dem":1777,
    "gn:feature_class":"P",
    "gn:feature_code":"PPL",
    "gn:name":"Santo Domingo de Capilla",
    "gn:population":0,
    "gn:timezone":"America/Lima",
    "iso:country":"PE",
    "wof:name":"Santo Domingo de Capilla",
    "wof:placetype":"locality"
},
  "geometry": {"coordinates":[-78.85448000000002,-6.24524],"type":"Point"}
}