{
  "type": "Feature",
  "properties": {
    "gn:admin1_code":"15.0",
    "gn:admin2_code":"1505.0",
    "gn:admin3_code":"150514.0",
    "gn:asciiname":"Laura Caller",
    "gn:country_code":"PE",
    "gn:dem":34,
    "gn:feature_class":"P",
    "gn:feature_code":"PPL",
    "gn:name":"Laura Caller",
    "gn:population":0,
    "gn:timezone":"America/Lima",
    "iso:country":"PE",
    "wof:name":"Laura Caller",
    "wof:placetype":"locality"
},
  "geometry": {"coordinates":[-76.425,-13.04239],"type":"Point"}
}