{
  "type": "Feature",
  "properties": {
    "gn:admin1_code":"16",
    "gn:admin2_code":"1601.0",
    "gn:admin3_code":"160107.0",
    "gn:asciiname":"Tarqui",
    "gn:cc2":"PE",
    "gn:country_code":"PE",
    "gn:dem":172,
    "gn:feature_class":"P",
    "gn:feature_code":"PPL",
    "gn:name":"Tarqui",
    "gn:population":0,
    "gn:timezone":"America/Lima",
    "iso:country":"PE",
    "name:und_x_variant":[
        "Posto Ecuatoriano",
        "Tarqui"
    ],
    "wof:name":"Tarqui",
    "wof:placetype":"locality"
},
  "geometry": {"coordinates":[-75.25,-1.58333],"type":"Point"}
}