{
  "type": "Feature",
  "properties": {
    "gn:admin1_code":"9.0",
    "gn:admin2_code":"907.0",
    "gn:admin3_code":"90705.0",
    "gn:asciiname":"Trancapata",
    "gn:country_code":"PE",
    "gn:dem":3366,
    "gn:feature_class":"P",
    "gn:feature_code":"PPL",
    "gn:name":"Trancapata",
    "gn:population":0,
    "gn:timezone":"America/Lima",
    "iso:country":"PE",
    "wof:name":"Trancapata",
    "wof:placetype":"locality"
},
  "geometry": {"coordinates":[-74.64861999999999,-12.46465],"type":"Point"}
}