{
  "type": "Feature",
  "properties": {
    "gn:admin1_code":"16",
    "gn:admin2_code":"1606.0",
    "gn:admin3_code":"160605.0",
    "gn:asciiname":"Carolina",
    "gn:country_code":"PE",
    "gn:dem":124,
    "gn:feature_class":"P",
    "gn:feature_code":"PPL",
    "gn:name":"Carolina",
    "gn:population":0,
    "gn:timezone":"America/Lima",
    "iso:country":"PE",
    "wof:name":"Carolina",
    "wof:placetype":"locality"
},
  "geometry": {"coordinates":[-75.18275,-6.4422],"type":"Point"}
}