{
  "type": "Feature",
  "properties": {
    "gn:admin1_code":"10.0",
    "gn:admin2_code":"1011.0",
    "gn:admin3_code":"101104.0",
    "gn:asciiname":"Yanayanta",
    "gn:country_code":"PE",
    "gn:dem":3904,
    "gn:feature_class":"P",
    "gn:feature_code":"PPL",
    "gn:name":"Yanayanta",
    "gn:population":0,
    "gn:timezone":"America/Lima",
    "iso:country":"PE",
    "wof:name":"Yanayanta",
    "wof:placetype":"locality"
},
  "geometry": {"coordinates":[-76.55499,-9.70421],"type":"Point"}
}