{
  "type": "Feature",
  "properties": {
    "gn:admin1_code":"11",
    "gn:admin2_code":"1104.0",
    "gn:admin3_code":"110401.0",
    "gn:asciiname":"Chicchitara",
    "gn:country_code":"PE",
    "gn:dem":548,
    "gn:feature_class":"P",
    "gn:feature_code":"PPL",
    "gn:name":"Chicchitara",
    "gn:population":0,
    "gn:timezone":"America/Lima",
    "iso:country":"PE",
    "name:und_x_variant":[
        "Chicchitara Hacienda",
        "Chicchitara"
    ],
    "wof:name":"Chicchitara",
    "wof:placetype":"locality"
},
  "geometry": {"coordinates":[-75.13534,-14.47001],"type":"Point"}
}