{
  "type": "Feature",
  "properties": {
    "gn:admin1_code":"21",
    "gn:admin2_code":"2103",
    "gn:asciiname":"Uscuri",
    "gn:country_code":"PE",
    "gn:dem":3708,
    "gn:feature_class":"P",
    "gn:feature_code":"PPL",
    "gn:name":"Uscuri",
    "gn:population":0,
    "gn:timezone":"America/Lima",
    "iso:country":"PE",
    "name:spa_x_preferred":[
        "Uscuri"
    ],
    "wof:name":"Uscuri",
    "wof:placetype":"locality"
},
  "geometry": {"coordinates":[-69.87373000000001,-13.89855],"type":"Point"}
}