{
  "type": "Feature",
  "properties": {
    "gn:admin1_code":"06",
    "gn:admin2_code":"611.0",
    "gn:admin3_code":"61110.0",
    "gn:asciiname":"Las Viejas",
    "gn:country_code":"PE",
    "gn:dem":270,
    "gn:feature_class":"P",
    "gn:feature_code":"PPL",
    "gn:name":"Las Viejas",
    "gn:population":0,
    "gn:timezone":"America/Lima",
    "iso:country":"PE",
    "name:spa_x_preferred":[
        "Las Viejas"
    ],
    "name:spa_x_variant":[
        "Casa Blanca"
    ],
    "wof:name":"Las Viejas",
    "wof:placetype":"locality"
},
  "geometry": {"coordinates":[-79.27103000000002,-7.12378],"type":"Point"}
}