{
  "type": "Feature",
  "properties": {
    "gn:admin1_code":"11.0",
    "gn:admin2_code":"1102.0",
    "gn:admin3_code":"110203.0",
    "gn:asciiname":"Catach",
    "gn:country_code":"PE",
    "gn:dem":3346,
    "gn:feature_class":"P",
    "gn:feature_code":"PPL",
    "gn:name":"Catach",
    "gn:population":0,
    "gn:timezone":"America/Lima",
    "iso:country":"PE",
    "name:spa_x_preferred":[
        "Catach"
    ],
    "wof:name":"Catach",
    "wof:placetype":"locality"
},
  "geometry": {"coordinates":[-75.89681,-13.07903],"type":"Point"}
}