{
  "type": "Feature",
  "properties": {
    "gn:admin1_code":"23",
    "gn:admin2_code":"2302.0",
    "gn:admin3_code":"230201.0",
    "gn:asciiname":"Pacotine",
    "gn:country_code":"PE",
    "gn:dem":4756,
    "gn:feature_class":"P",
    "gn:feature_code":"PPL",
    "gn:name":"Pacotine",
    "gn:population":0,
    "gn:timezone":"America/Lima",
    "iso:country":"PE",
    "wof:name":"Pacotine",
    "wof:placetype":"locality"
},
  "geometry": {"coordinates":[-70.09389,-17.10278],"type":"Point"}
}