{
  "type": "Feature",
  "properties": {
    "gn:admin1_code":"16",
    "gn:admin2_code":"1603.0",
    "gn:admin3_code":"160301.0",
    "gn:asciiname":"San Rafael de Tapirilla",
    "gn:country_code":"PE",
    "gn:dem":92,
    "gn:feature_class":"P",
    "gn:feature_code":"PPL",
    "gn:name":"San Rafa\u00e9l de Tapirilla",
    "gn:population":0,
    "gn:timezone":"America/Lima",
    "iso:country":"PE",
    "wof:name":"San Rafael de Tapirilla",
    "wof:placetype":"locality"
},
  "geometry": {"coordinates":[-73.44889000000001,-4.34778],"type":"Point"}
}