{
  "type": "Feature",
  "properties": {
    "gn:admin1_code":"13",
    "gn:admin2_code":"1311.0",
    "gn:admin3_code":"131101.0",
    "gn:asciiname":"Septen",
    "gn:country_code":"PE",
    "gn:dem":637,
    "gn:feature_class":"P",
    "gn:feature_code":"PPL",
    "gn:name":"Septen",
    "gn:population":0,
    "gn:timezone":"America/Lima",
    "iso:country":"PE",
    "wof:name":"Septen",
    "wof:placetype":"locality"
},
  "geometry": {"coordinates":[-78.74495999999998,-7.56227],"type":"Point"}
}