{
  "type": "Feature",
  "properties": {
    "gn:admin1_code":"1.0",
    "gn:admin2_code":"101.0",
    "gn:admin3_code":"10104.0",
    "gn:asciiname":"Huacapampa",
    "gn:country_code":"PE",
    "gn:dem":2166,
    "gn:feature_class":"P",
    "gn:feature_code":"PPL",
    "gn:name":"Huacapampa",
    "gn:population":0,
    "gn:timezone":"America/Lima",
    "iso:country":"PE",
    "wof:name":"Huacapampa",
    "wof:placetype":"locality"
},
  "geometry": {"coordinates":[-77.69333,-6.2875],"type":"Point"}
}