{
  "type": "Feature",
  "properties": {
    "gn:admin1_code":"02",
    "gn:admin2_code":"208.0",
    "gn:admin3_code":"20801.0",
    "gn:asciiname":"Hacienda Mojeque",
    "gn:country_code":"PE",
    "gn:dem":125,
    "gn:feature_class":"P",
    "gn:feature_code":"PPL",
    "gn:name":"Hacienda Mojeque",
    "gn:population":0,
    "gn:timezone":"America/Lima",
    "iso:country":"PE",
    "name:und_x_variant":[
        "Mojeque"
    ],
    "wof:name":"Hacienda Mojeque",
    "wof:placetype":"locality"
},
  "geometry": {"coordinates":[-78.22526999999999,-9.5154],"type":"Point"}
}