{
  "type": "Feature",
  "properties": {
    "gn:admin1_code":"20",
    "gn:admin2_code":"2002.0",
    "gn:admin3_code":"200207.0",
    "gn:asciiname":"Toma Pampa de Quiroz",
    "gn:country_code":"PE",
    "gn:dem":432,
    "gn:feature_class":"P",
    "gn:feature_code":"PPL",
    "gn:name":"Toma Pampa de Quiroz",
    "gn:population":0,
    "gn:timezone":"America/Lima",
    "iso:country":"PE",
    "wof:name":"Toma Pampa de Quiroz",
    "wof:placetype":"locality"
},
  "geometry": {"coordinates":[-80.03794000000001,-4.61341],"type":"Point"}
}