{
  "type": "Feature",
  "properties": {
    "gn:admin1_code":"18",
    "gn:admin2_code":"1802.0",
    "gn:admin3_code":"180205.0",
    "gn:asciiname":"Capilla Vieja",
    "gn:country_code":"PE",
    "gn:dem":2309,
    "gn:feature_class":"P",
    "gn:feature_code":"PPL",
    "gn:name":"Capilla Vieja",
    "gn:population":0,
    "gn:timezone":"America/Lima",
    "iso:country":"PE",
    "wof:name":"Capilla Vieja",
    "wof:placetype":"locality"
},
  "geometry": {"coordinates":[-71.32437,-16.75725],"type":"Point"}
}