{
  "type": "Feature",
  "properties": {
    "gn:admin1_code":"8.0",
    "gn:admin2_code":"809.0",
    "gn:admin3_code":"80910.0",
    "gn:asciiname":"Shiantuishari",
    "gn:country_code":"PE",
    "gn:dem":760,
    "gn:feature_class":"P",
    "gn:feature_code":"PPL",
    "gn:name":"Shiantuishari",
    "gn:population":0,
    "gn:timezone":"America/Lima",
    "iso:country":"PE",
    "name:spa_x_preferred":[
        "Shiantuishari"
    ],
    "wof:name":"Shiantuishari",
    "wof:placetype":"locality"
},
  "geometry": {"coordinates":[-73.94591,-12.2859],"type":"Point"}
}