{
  "type": "Feature",
  "properties": {
    "gn:admin1_code":"15",
    "gn:admin2_code":"1508.0",
    "gn:admin3_code":"150806.0",
    "gn:asciiname":"Caldera",
    "gn:country_code":"PE",
    "gn:dem":257,
    "gn:feature_class":"P",
    "gn:feature_code":"PPL",
    "gn:name":"Caldera",
    "gn:population":0,
    "gn:timezone":"America/Lima",
    "iso:country":"PE",
    "name:und_x_variant":[
        "Hacienda Caldera",
        "Caldera Hacienda",
        "Caldera"
    ],
    "wof:name":"Caldera",
    "wof:placetype":"locality"
},
  "geometry": {"coordinates":[-77.45833,-11.08611],"type":"Point"}
}