{
  "type": "Feature",
  "properties": {
    "gn:admin1_code":"8",
    "gn:admin2_code":"808.0",
    "gn:admin3_code":"80803.0",
    "gn:asciiname":"Pucahuasi",
    "gn:country_code":"PE",
    "gn:dem":4333,
    "gn:feature_class":"P",
    "gn:feature_code":"PPL",
    "gn:name":"Pucahuasi",
    "gn:population":0,
    "gn:timezone":"America/Lima",
    "iso:country":"PE",
    "wof:name":"Pucahuasi",
    "wof:placetype":"locality"
},
  "geometry": {"coordinates":[-71.61624,-14.61056],"type":"Point"}
}