{
  "type": "Feature",
  "properties": {
    "gn:admin1_code":"2.0",
    "gn:admin2_code":"210.0",
    "gn:admin3_code":"21002.0",
    "gn:asciiname":"Pampa Cabildo",
    "gn:country_code":"PE",
    "gn:dem":3216,
    "gn:feature_class":"P",
    "gn:feature_code":"PPL",
    "gn:name":"Pampa Cabildo",
    "gn:population":0,
    "gn:timezone":"America/Lima",
    "iso:country":"PE",
    "wof:name":"Pampa Cabildo",
    "wof:placetype":"locality"
},
  "geometry": {"coordinates":[-76.94986999999998,-9.24653],"type":"Point"}
}