{
  "type": "Feature",
  "properties": {
    "gn:admin1_code":"5",
    "gn:admin2_code":"510.0",
    "gn:admin3_code":"51012.0",
    "gn:asciiname":"Huashuapujuna",
    "gn:country_code":"PE",
    "gn:dem":4391,
    "gn:feature_class":"P",
    "gn:feature_code":"PPL",
    "gn:name":"Huashuapujuna",
    "gn:population":0,
    "gn:timezone":"America/Lima",
    "iso:country":"PE",
    "wof:name":"Huashuapujuna",
    "wof:placetype":"locality"
},
  "geometry": {"coordinates":[-74.55333,-13.69028],"type":"Point"}
}