{
  "type": "Feature",
  "properties": {
    "gn:admin1_code":"10",
    "gn:admin2_code":"1001.0",
    "gn:admin3_code":"100108.0",
    "gn:asciiname":"Cebada Ucro",
    "gn:country_code":"PE",
    "gn:dem":3596,
    "gn:feature_class":"P",
    "gn:feature_code":"PPL",
    "gn:name":"Cebada Ucro",
    "gn:population":0,
    "gn:timezone":"America/Lima",
    "iso:country":"PE",
    "name:und_x_variant":[
        "Cebaba Ucro"
    ],
    "wof:name":"Cebada Ucro",
    "wof:placetype":"locality"
},
  "geometry": {"coordinates":[-76.45488,-10.02134],"type":"Point"}
}