{
  "type": "Feature",
  "properties": {
    "gn:admin1_code":"09",
    "gn:admin2_code":"903.0",
    "gn:admin3_code":"90305.0",
    "gn:asciiname":"Malepampa",
    "gn:country_code":"PE",
    "gn:dem":2504,
    "gn:feature_class":"P",
    "gn:feature_code":"PPL",
    "gn:name":"Malepampa",
    "gn:population":0,
    "gn:timezone":"America/Lima",
    "iso:country":"PE",
    "wof:name":"Malepampa",
    "wof:placetype":"locality"
},
  "geometry": {"coordinates":[-74.31729,-13.05128],"type":"Point"}
}