{
  "type": "Feature",
  "properties": {
    "gn:admin1_code":"13",
    "gn:admin2_code":"1307.0",
    "gn:admin3_code":"130702.0",
    "gn:asciiname":"Chafan Grande",
    "gn:country_code":"PE",
    "gn:dem":125,
    "gn:feature_class":"P",
    "gn:feature_code":"PPL",
    "gn:name":"Chaf\u00e1n Grande",
    "gn:population":0,
    "gn:timezone":"America/Lima",
    "iso:country":"PE",
    "name:und_x_variant":[
        "Chafan Grande Hacienda",
        "Chal\u00e1n Grande Hacienda",
        "Chaf\u00e1n Grande"
    ],
    "wof:name":"Chafan Grande",
    "wof:placetype":"locality"
},
  "geometry": {"coordinates":[-79.39343000000002,-7.31679],"type":"Point"}
}