{
  "type": "Feature",
  "properties": {
    "gn:admin1_code":"10.0",
    "gn:admin2_code":"1005.0",
    "gn:admin3_code":"100509.0",
    "gn:asciiname":"Jirin",
    "gn:country_code":"PE",
    "gn:dem":4073,
    "gn:feature_class":"P",
    "gn:feature_code":"PPL",
    "gn:name":"Jirin",
    "gn:population":0,
    "gn:timezone":"America/Lima",
    "iso:country":"PE",
    "wof:name":"Jirin",
    "wof:placetype":"locality"
},
  "geometry": {"coordinates":[-76.93153000000002,-9.49472],"type":"Point"}
}