{
  "type": "Feature",
  "properties": {
    "gn:admin1_code":"12.0",
    "gn:admin2_code":"1202.0",
    "gn:admin3_code":"120210.0",
    "gn:asciiname":"Canto",
    "gn:country_code":"PE",
    "gn:dem":3278,
    "gn:feature_class":"P",
    "gn:feature_code":"PPL",
    "gn:name":"Canto",
    "gn:population":0,
    "gn:timezone":"America/Lima",
    "iso:country":"PE",
    "name:deu_x_preferred":[
        "Canto"
    ],
    "name:fas_x_preferred":[
        "\u06a9\u0627\u0646\u062a\u0648"
    ],
    "name:fra_x_preferred":[
        "Chant"
    ],
    "name:ind_x_preferred":[
        "Canto"
    ],
    "name:ita_x_preferred":[
        "Canto"
    ],
    "name:por_x_preferred":[
        "Canto"
    ],
    "name:swe_x_preferred":[
        "Canto"
    ],
    "wof:name":"Canto",
    "wof:placetype":"locality"
},
  "geometry": {"coordinates":[-75.35296,-11.88395],"type":"Point"}
}