{
  "type": "Feature",
  "properties": {
    "gn:admin1_code":"13.0",
    "gn:admin2_code":"1308.0",
    "gn:admin3_code":"130801.0",
    "gn:asciiname":"Yuraccpaccha",
    "gn:country_code":"PE",
    "gn:dem":3722,
    "gn:feature_class":"P",
    "gn:feature_code":"PPL",
    "gn:name":"Yuraccpaccha",
    "gn:population":0,
    "gn:timezone":"America/Lima",
    "iso:country":"PE",
    "wof:name":"Yuraccpaccha",
    "wof:placetype":"locality"
},
  "geometry": {"coordinates":[-77.17610999999999,-8.37889],"type":"Point"}
}