{
  "type": "Feature",
  "properties": {
    "gn:admin1_code":"16",
    "gn:admin2_code":"1607.0",
    "gn:admin3_code":"160704.0",
    "gn:asciiname":"Sargento Puno",
    "gn:country_code":"PE",
    "gn:dem":193,
    "gn:feature_class":"P",
    "gn:feature_code":"PPL",
    "gn:name":"Sargento Pu\u00f1o",
    "gn:population":0,
    "gn:timezone":"America/Lima",
    "iso:country":"PE",
    "wof:name":"Sargento Puno",
    "wof:placetype":"locality"
},
  "geometry": {"coordinates":[-77.53333000000001,-3.48333],"type":"Point"}
}