{
  "type": "Feature",
  "properties": {
    "gn:admin1_code":"5",
    "gn:admin2_code":"506.0",
    "gn:admin3_code":"50604.0",
    "gn:asciiname":"Chejosno",
    "gn:country_code":"PE",
    "gn:dem":4333,
    "gn:feature_class":"P",
    "gn:feature_code":"PPL",
    "gn:name":"Chejosno",
    "gn:population":0,
    "gn:timezone":"America/Lima",
    "iso:country":"PE",
    "wof:name":"Chejosno",
    "wof:placetype":"locality"
},
  "geometry": {"coordinates":[-73.88472,-14.46639],"type":"Point"}
}