{
  "type": "Feature",
  "properties": {
    "gn:admin1_code":"18",
    "gn:admin2_code":"1802.0",
    "gn:admin3_code":"180210.0",
    "gn:asciiname":"Chacantape",
    "gn:country_code":"PE",
    "gn:dem":4452,
    "gn:feature_class":"P",
    "gn:feature_code":"PPL",
    "gn:name":"Chacantape",
    "gn:population":0,
    "gn:timezone":"America/Lima",
    "iso:country":"PE",
    "wof:name":"Chacantape",
    "wof:placetype":"locality"
},
  "geometry": {"coordinates":[-70.79816,-16.30733],"type":"Point"}
}