{
  "type": "Feature",
  "properties": {
    "gn:admin1_code":"4",
    "gn:admin2_code":"407.0",
    "gn:admin3_code":"40702.0",
    "gn:asciiname":"Haciendita Hacienda",
    "gn:country_code":"PE",
    "gn:dem":260,
    "gn:feature_class":"P",
    "gn:feature_code":"PPL",
    "gn:name":"Haciendita Hacienda",
    "gn:population":0,
    "gn:timezone":"America/Lima",
    "iso:country":"PE",
    "wof:name":"Haciendita Hacienda",
    "wof:placetype":"locality"
},
  "geometry": {"coordinates":[-71.60944000000001,-17.00222],"type":"Point"}
}