{
  "type": "Feature",
  "properties": {
    "gn:admin1_code":"06",
    "gn:admin2_code":"602.0",
    "gn:admin3_code":"60204.0",
    "gn:asciiname":"Cochapampa",
    "gn:country_code":"PE",
    "gn:dem":3242,
    "gn:feature_class":"P",
    "gn:feature_code":"PPL",
    "gn:name":"Cochapampa",
    "gn:population":0,
    "gn:timezone":"America/Lima",
    "iso:country":"PE",
    "wof:name":"Cochapampa",
    "wof:placetype":"locality"
},
  "geometry": {"coordinates":[-77.98269999999999,-7.52205],"type":"Point"}
}