{
  "type": "Feature",
  "properties": {
    "gn:admin1_code":"06",
    "gn:admin2_code":"603.0",
    "gn:admin3_code":"60304.0",
    "gn:asciiname":"Victoria",
    "gn:country_code":"PE",
    "gn:dem":3495,
    "gn:feature_class":"P",
    "gn:feature_code":"PPL",
    "gn:name":"Victoria",
    "gn:population":0,
    "gn:timezone":"America/Lima",
    "iso:country":"PE",
    "wof:name":"Victoria",
    "wof:placetype":"locality"
},
  "geometry": {"coordinates":[-78.31971,-6.85819],"type":"Point"}
}