{
  "type": "Feature",
  "properties": {
    "gn:admin1_code":"8",
    "gn:admin2_code":"807.0",
    "gn:admin3_code":"80705.0",
    "gn:asciiname":"Milluni",
    "gn:country_code":"PE",
    "gn:dem":4442,
    "gn:feature_class":"P",
    "gn:feature_code":"PPL",
    "gn:name":"Milluni",
    "gn:population":0,
    "gn:timezone":"America/Lima",
    "iso:country":"PE",
    "wof:name":"Milluni",
    "wof:placetype":"locality"
},
  "geometry": {"coordinates":[-71.69337,-14.52913],"type":"Point"}
}