{
  "type": "Feature",
  "properties": {
    "gn:admin1_code":"02",
    "gn:admin2_code":"211.0",
    "gn:admin3_code":"21101.0",
    "gn:asciiname":"Hacienda Mandinga",
    "gn:country_code":"PE",
    "gn:dem":106,
    "gn:feature_class":"P",
    "gn:feature_code":"PPL",
    "gn:name":"Hacienda Mandinga",
    "gn:population":0,
    "gn:timezone":"America/Lima",
    "iso:country":"PE",
    "name:und_x_variant":[
        "Mandinga"
    ],
    "wof:name":"Hacienda Mandinga",
    "wof:placetype":"locality"
},
  "geometry": {"coordinates":[-78.08443,-10.0545],"type":"Point"}
}