{
  "type": "Feature",
  "properties": {
    "gn:admin1_code":"9.0",
    "gn:admin2_code":"907.0",
    "gn:admin3_code":"90709.0",
    "gn:asciiname":"Pichu",
    "gn:country_code":"PE",
    "gn:dem":2956,
    "gn:feature_class":"P",
    "gn:feature_code":"PPL",
    "gn:name":"Pichu",
    "gn:population":0,
    "gn:timezone":"America/Lima",
    "iso:country":"PE",
    "name:hrv_x_preferred":[
        "Pichu"
    ],
    "name:ita_x_preferred":[
        "Pichu"
    ],
    "name:jpn_x_preferred":[
        "\u30d4\u30c1\u30e5\u30fc"
    ],
    "name:msa_x_preferred":[
        "Pichu"
    ],
    "name:nor_x_preferred":[
        "Pichu"
    ],
    "name:slk_x_preferred":[
        "Pi\u010d\u00fa"
    ],
    "name:tur_x_preferred":[
        "Pichu"
    ],
    "name:vie_x_preferred":[
        "Pichu"
    ],
    "wof:name":"Pichu",
    "wof:placetype":"locality"
},
  "geometry": {"coordinates":[-74.93658000000001,-12.23203],"type":"Point"}
}