{
  "type": "Feature",
  "properties": {
    "gn:admin1_code":"5.0",
    "gn:admin2_code":"504.0",
    "gn:asciiname":"Nueva Esperanza",
    "gn:country_code":"PE",
    "gn:dem":508,
    "gn:feature_class":"P",
    "gn:feature_code":"PPL",
    "gn:name":"Nueva Esperanza",
    "gn:population":0,
    "gn:timezone":"America/Lima",
    "iso:country":"PE",
    "name:spa_x_preferred":[
        "Nueva Esperanza"
    ],
    "wof:name":"Nueva Esperanza",
    "wof:placetype":"locality"
},
  "geometry": {"coordinates":[-73.88755999999999,-12.42072],"type":"Point"}
}