{
  "type": "Feature",
  "properties": {
    "gn:admin1_code":"22",
    "gn:admin2_code":"2201.0",
    "gn:admin3_code":"220101.0",
    "gn:asciiname":"Playa Hermosa",
    "gn:country_code":"PE",
    "gn:dem":1066,
    "gn:feature_class":"P",
    "gn:feature_code":"PPL",
    "gn:name":"Playa Hermosa",
    "gn:population":0,
    "gn:timezone":"America/Lima",
    "iso:country":"PE",
    "name:spa_x_preferred":[
        "Playa Hermosa"
    ],
    "wof:name":"Playa Hermosa",
    "wof:placetype":"locality"
},
  "geometry": {"coordinates":[-76.99038,-5.91436],"type":"Point"}
}