{
  "type": "Feature",
  "properties": {
    "gn:admin1_code":"9",
    "gn:admin2_code":"903.0",
    "gn:admin3_code":"90301.0",
    "gn:asciiname":"Ajopampa",
    "gn:country_code":"PE",
    "gn:dem":3607,
    "gn:feature_class":"P",
    "gn:feature_code":"PPL",
    "gn:name":"Ajopampa",
    "gn:population":0,
    "gn:timezone":"America/Lima",
    "iso:country":"PE",
    "wof:name":"Ajopampa",
    "wof:placetype":"locality"
},
  "geometry": {"coordinates":[-74.69608000000002,-13.03871],"type":"Point"}
}