{
  "type": "Feature",
  "properties": {
    "gn:admin1_code":"4",
    "gn:admin2_code":"405.0",
    "gn:admin3_code":"40515.0",
    "gn:asciiname":"Aucasaya",
    "gn:country_code":"PE",
    "gn:dem":4706,
    "gn:feature_class":"P",
    "gn:feature_code":"PPL",
    "gn:name":"Aucasaya",
    "gn:population":0,
    "gn:timezone":"America/Lima",
    "iso:country":"PE",
    "wof:name":"Aucasaya",
    "wof:placetype":"locality"
},
  "geometry": {"coordinates":[-71.57353000000001,-15.37132],"type":"Point"}
}