{
  "type": "Feature",
  "properties": {
    "gn:admin1_code":"12.0",
    "gn:admin2_code":"1202.0",
    "gn:admin3_code":"120209.0",
    "gn:asciiname":"Mucllo",
    "gn:country_code":"PE",
    "gn:dem":2493,
    "gn:feature_class":"P",
    "gn:feature_code":"PPLA3",
    "gn:name":"Mucllo",
    "gn:population":0,
    "gn:timezone":"America/Lima",
    "iso:country":"PE",
    "wof:name":"Mucllo",
    "wof:placetype":"locality"
},
  "geometry": {"coordinates":[-75.09115,-11.61607],"type":"Point"}
}