{
  "type": "Feature",
  "properties": {
    "gn:admin1_code":"3",
    "gn:admin2_code":"302.0",
    "gn:admin3_code":"30211.0",
    "gn:asciiname":"Paujar",
    "gn:country_code":"PE",
    "gn:dem":3917,
    "gn:feature_class":"P",
    "gn:feature_code":"PPL",
    "gn:name":"Paujar",
    "gn:population":0,
    "gn:timezone":"America/Lima",
    "iso:country":"PE",
    "wof:name":"Paujar",
    "wof:placetype":"locality"
},
  "geometry": {"coordinates":[-73.55,-14.09056],"type":"Point"}
}