{
  "type": "Feature",
  "properties": {
    "gn:admin1_code":"4",
    "gn:admin2_code":"404.0",
    "gn:admin3_code":"40402.0",
    "gn:asciiname":"Ocoruro",
    "gn:country_code":"PE",
    "gn:dem":3910,
    "gn:feature_class":"P",
    "gn:feature_code":"PPL",
    "gn:name":"Ocoruro",
    "gn:population":0,
    "gn:timezone":"America/Lima",
    "iso:country":"PE",
    "wof:name":"Ocoruro",
    "wof:placetype":"locality"
},
  "geometry": {"coordinates":[-72.44806,-15.39556],"type":"Point"}
}