{
  "type": "Feature",
  "properties": {
    "gn:admin1_code":"06",
    "gn:admin2_code":"602.0",
    "gn:admin3_code":"60204.0",
    "gn:asciiname":"Marcamachay",
    "gn:country_code":"PE",
    "gn:dem":2874,
    "gn:feature_class":"P",
    "gn:feature_code":"PPL",
    "gn:name":"Marcamachay",
    "gn:population":0,
    "gn:timezone":"America/Lima",
    "iso:country":"PE",
    "wof:name":"Marcamachay",
    "wof:placetype":"locality"
},
  "geometry": {"coordinates":[-77.95,-7.43333],"type":"Point"}
}