{
  "type": "Feature",
  "properties": {
    "gn:admin1_code":"4",
    "gn:admin2_code":"405.0",
    "gn:admin3_code":"40517.0",
    "gn:asciiname":"Cotapujio",
    "gn:country_code":"PE",
    "gn:dem":4170,
    "gn:feature_class":"P",
    "gn:feature_code":"PPL",
    "gn:name":"Cotapujio",
    "gn:population":0,
    "gn:timezone":"America/Lima",
    "iso:country":"PE",
    "wof:name":"Cotapujio",
    "wof:placetype":"locality"
},
  "geometry": {"coordinates":[-71.56551,-15.11745],"type":"Point"}
}