{
  "type": "Feature",
  "properties": {
    "gn:admin1_code":"17.0",
    "gn:admin2_code":"1703.0",
    "gn:asciiname":"Solitario",
    "gn:country_code":"PE",
    "gn:dem":285,
    "gn:feature_class":"P",
    "gn:feature_code":"PPL",
    "gn:name":"Solitario",
    "gn:population":0,
    "gn:timezone":"America/Lima",
    "iso:country":"PE",
    "name:spa_x_preferred":[
        "Solitario"
    ],
    "wof:name":"Solitario",
    "wof:placetype":"locality"
},
  "geometry": {"coordinates":[-69.42404000000001,-11.40487],"type":"Point"}
}