{
  "type": "Feature",
  "properties": {
    "gn:admin1_code":"12.0",
    "gn:admin2_code":"1202.0",
    "gn:admin3_code":"120206.0",
    "gn:asciiname":"Mullacayoc",
    "gn:country_code":"PE",
    "gn:dem":3912,
    "gn:feature_class":"P",
    "gn:feature_code":"PPL",
    "gn:name":"Mullacayoc",
    "gn:population":0,
    "gn:timezone":"America/Lima",
    "iso:country":"PE",
    "wof:name":"Mullacayoc",
    "wof:placetype":"locality"
},
  "geometry": {"coordinates":[-75.00683000000002,-11.65778],"type":"Point"}
}