{
  "type": "Feature",
  "properties": {
    "gn:admin1_code":"8",
    "gn:admin2_code":"808.0",
    "gn:admin3_code":"80807.0",
    "gn:asciiname":"Pacuchohuana",
    "gn:country_code":"PE",
    "gn:dem":4417,
    "gn:feature_class":"P",
    "gn:feature_code":"PPL",
    "gn:name":"Pacuchohua\u00f1a",
    "gn:population":0,
    "gn:timezone":"America/Lima",
    "iso:country":"PE",
    "wof:name":"Pacuchohuana",
    "wof:placetype":"locality"
},
  "geometry": {"coordinates":[-71.5197,-15.04525],"type":"Point"}
}