{
  "type": "Feature",
  "properties": {
    "gn:admin1_code":"5.0",
    "gn:admin2_code":"502.0",
    "gn:asciiname":"Huayratajinga",
    "gn:country_code":"PE",
    "gn:dem":4599,
    "gn:feature_class":"P",
    "gn:feature_code":"PPL",
    "gn:name":"Huayratajinga",
    "gn:population":0,
    "gn:timezone":"America/Lima",
    "iso:country":"PE",
    "wof:name":"Huayratajinga",
    "wof:placetype":"locality"
},
  "geometry": {"coordinates":[-74.76919000000002,-13.402],"type":"Point"}
}