{
  "type": "Feature",
  "properties": {
    "gn:admin1_code":"05",
    "gn:admin2_code":"511.0",
    "gn:admin3_code":"51101.0",
    "gn:asciiname":"Viscachayoc",
    "gn:country_code":"PE",
    "gn:dem":3601,
    "gn:feature_class":"P",
    "gn:feature_code":"PPL",
    "gn:name":"Viscachayoc",
    "gn:population":0,
    "gn:timezone":"America/Lima",
    "iso:country":"PE",
    "wof:name":"Viscachayoc",
    "wof:placetype":"locality"
},
  "geometry": {"coordinates":[-73.93946,-13.66173],"type":"Point"}
}