{
  "type": "Feature",
  "properties": {
    "gn:admin1_code":"9.0",
    "gn:admin2_code":"907.0",
    "gn:admin3_code":"90714.0",
    "gn:asciiname":"Tanquis Pampa",
    "gn:country_code":"PE",
    "gn:dem":3784,
    "gn:feature_class":"P",
    "gn:feature_code":"PPL",
    "gn:name":"Tanquis Pampa",
    "gn:population":0,
    "gn:timezone":"America/Lima",
    "iso:country":"PE",
    "wof:name":"Tanquis Pampa",
    "wof:placetype":"locality"
},
  "geometry": {"coordinates":[-74.77301,-12.17592],"type":"Point"}
}