{
  "type": "Feature",
  "properties": {
    "gn:admin1_code":"13.0",
    "gn:admin2_code":"1308.0",
    "gn:admin3_code":"130804.0",
    "gn:asciiname":"Huanga",
    "gn:country_code":"PE",
    "gn:dem":2689,
    "gn:feature_class":"P",
    "gn:feature_code":"PPL",
    "gn:name":"Huanga",
    "gn:population":0,
    "gn:timezone":"America/Lima",
    "iso:country":"PE",
    "wof:name":"Huanga",
    "wof:placetype":"locality"
},
  "geometry": {"coordinates":[-77.29111,-8.48222],"type":"Point"}
}