{
  "type": "Feature",
  "properties": {
    "gn:admin1_code":"9.0",
    "gn:admin2_code":"905.0",
    "gn:asciiname":"Marjarcay",
    "gn:country_code":"PE",
    "gn:dem":2967,
    "gn:feature_class":"P",
    "gn:feature_code":"PPL",
    "gn:name":"Marjarcay",
    "gn:population":0,
    "gn:timezone":"America/Lima",
    "iso:country":"PE",
    "wof:name":"Marjarcay",
    "wof:placetype":"locality"
},
  "geometry": {"coordinates":[-74.42188,-12.77925],"type":"Point"}
}