{
  "type": "Feature",
  "properties": {
    "gn:admin1_code":"16",
    "gn:admin2_code":"1605.0",
    "gn:admin3_code":"160510.0",
    "gn:asciiname":"Puesto Guerra",
    "gn:country_code":"PE",
    "gn:dem":111,
    "gn:feature_class":"P",
    "gn:feature_code":"PPL",
    "gn:name":"Puesto Guerra",
    "gn:population":0,
    "gn:timezone":"America/Lima",
    "iso:country":"PE",
    "wof:name":"Puesto Guerra",
    "wof:placetype":"locality"
},
  "geometry": {"coordinates":[-73.71973,-4.98561],"type":"Point"}
}