{
  "type": "Feature",
  "properties": {
    "gn:admin1_code":"5",
    "gn:admin2_code":"509.0",
    "gn:asciiname":"San Pedro de Larcay",
    "gn:country_code":"PE",
    "gn:dem":3387,
    "gn:feature_class":"P",
    "gn:feature_code":"PPL",
    "gn:name":"San Pedro de Larcay",
    "gn:population":0,
    "gn:timezone":"America/Lima",
    "iso:country":"PE",
    "wof:name":"San Pedro de Larcay",
    "wof:placetype":"locality"
},
  "geometry": {"coordinates":[-73.57333,-14.16889],"type":"Point"}
}