{
  "type": "Feature",
  "properties": {
    "gn:admin1_code":"04",
    "gn:admin2_code":"403.0",
    "gn:admin3_code":"40301.0",
    "gn:asciiname":"Olleria",
    "gn:country_code":"PE",
    "gn:dem":1690,
    "gn:feature_class":"P",
    "gn:feature_code":"PPL",
    "gn:name":"Oller\u00eda",
    "gn:population":0,
    "gn:timezone":"America/Lima",
    "iso:country":"PE",
    "wof:name":"Olleria",
    "wof:placetype":"locality"
},
  "geometry": {"coordinates":[-73.33333,-15.78333],"type":"Point"}
}