{
  "type": "Feature",
  "properties": {
    "gn:admin1_code":"5",
    "gn:admin2_code":"506.0",
    "gn:admin3_code":"50604.0",
    "gn:asciiname":"Soitojo",
    "gn:country_code":"PE",
    "gn:dem":4138,
    "gn:feature_class":"P",
    "gn:feature_code":"PPL",
    "gn:name":"Soitojo",
    "gn:population":0,
    "gn:timezone":"America/Lima",
    "iso:country":"PE",
    "wof:name":"Soitojo",
    "wof:placetype":"locality"
},
  "geometry": {"coordinates":[-73.9225,-14.48222],"type":"Point"}
}