{
  "type": "Feature",
  "properties": {
    "gn:admin1_code":"05",
    "gn:admin2_code":"503.0",
    "gn:admin3_code":"50302.0",
    "gn:asciiname":"Carapo",
    "gn:country_code":"PE",
    "gn:dem":3265,
    "gn:feature_class":"P",
    "gn:feature_code":"PPLA3",
    "gn:name":"Carapo",
    "gn:population":0,
    "gn:timezone":"America/Lima",
    "iso:country":"PE",
    "wof:name":"Carapo",
    "wof:placetype":"locality"
},
  "geometry": {"coordinates":[-74.31194000000001,-13.83889],"type":"Point"}
}