{
  "type": "Feature",
  "properties": {
    "gn:admin1_code":"23",
    "gn:admin2_code":"2302.0",
    "gn:admin3_code":"230202.0",
    "gn:asciiname":"Calacala",
    "gn:country_code":"PE",
    "gn:dem":3632,
    "gn:feature_class":"P",
    "gn:feature_code":"PPL",
    "gn:name":"Calacala",
    "gn:population":0,
    "gn:timezone":"America/Lima",
    "iso:country":"PE",
    "wof:name":"Calacala",
    "wof:placetype":"locality"
},
  "geometry": {"coordinates":[-70.34458000000001,-17.26014],"type":"Point"}
}