{
  "type": "Feature",
  "properties": {
    "gn:admin1_code":"1.0",
    "gn:admin2_code":"106.0",
    "gn:admin3_code":"10606.0",
    "gn:asciiname":"Shucus",
    "gn:country_code":"PE",
    "gn:dem":1598,
    "gn:feature_class":"P",
    "gn:feature_code":"PPL",
    "gn:name":"Shucus",
    "gn:population":0,
    "gn:timezone":"America/Lima",
    "iso:country":"PE",
    "wof:name":"Shucus",
    "wof:placetype":"locality"
},
  "geometry": {"coordinates":[-77.56565000000001,-6.39322],"type":"Point"}
}