{
  "type": "Feature",
  "properties": {
    "gn:admin1_code":"12",
    "gn:admin2_code":"1209.0",
    "gn:admin3_code":"120909.0",
    "gn:asciiname":"Isla",
    "gn:country_code":"PE",
    "gn:dem":4482,
    "gn:feature_class":"P",
    "gn:feature_code":"PPL",
    "gn:name":"Isla",
    "gn:population":0,
    "gn:timezone":"America/Lima",
    "iso:country":"PE",
    "wof:name":"Isla",
    "wof:placetype":"locality"
},
  "geometry": {"coordinates":[-75.55583,-12.27861],"type":"Point"}
}