{
  "type": "Feature",
  "properties": {
    "gn:admin1_code":"16",
    "gn:admin2_code":"1606.0",
    "gn:admin3_code":"160601.0",
    "gn:asciiname":"Monte Blanco",
    "gn:country_code":"PE",
    "gn:dem":137,
    "gn:feature_class":"P",
    "gn:feature_code":"PPL",
    "gn:name":"Monte Blanco",
    "gn:population":0,
    "gn:timezone":"America/Lima",
    "iso:country":"PE",
    "name:spa_x_preferred":[
        "Monte Blanco"
    ],
    "wof:name":"Monte Blanco",
    "wof:placetype":"locality"
},
  "geometry": {"coordinates":[-75.02441999999998,-7.56588],"type":"Point"}
}