{
  "type": "Feature",
  "properties": {
    "gn:admin1_code":"5",
    "gn:admin2_code":"511.0",
    "gn:admin3_code":"51101.0",
    "gn:asciiname":"Apachita",
    "gn:country_code":"PE",
    "gn:dem":3581,
    "gn:feature_class":"P",
    "gn:feature_code":"PPL",
    "gn:name":"Apachita",
    "gn:population":0,
    "gn:timezone":"America/Lima",
    "iso:country":"PE",
    "wof:name":"Apachita",
    "wof:placetype":"locality"
},
  "geometry": {"coordinates":[-73.94516999999998,-13.65154],"type":"Point"}
}