{
  "type": "Feature",
  "properties": {
    "gn:admin1_code":"03",
    "gn:admin2_code":"305.0",
    "gn:admin3_code":"30505.0",
    "gn:asciiname":"Pisacasa",
    "gn:country_code":"PE",
    "gn:dem":3761,
    "gn:feature_class":"P",
    "gn:feature_code":"PPL",
    "gn:name":"Pisacasa",
    "gn:population":0,
    "gn:timezone":"America/Lima",
    "iso:country":"PE",
    "wof:name":"Pisacasa",
    "wof:placetype":"locality"
},
  "geometry": {"coordinates":[-72.18333,-14.08333],"type":"Point"}
}