{
  "type": "Feature",
  "properties": {
    "gn:admin1_code":"4.0",
    "gn:admin2_code":"408.0",
    "gn:admin3_code":"40808.0",
    "gn:asciiname":"Caypayqui",
    "gn:country_code":"PE",
    "gn:dem":3071,
    "gn:feature_class":"P",
    "gn:feature_code":"PPL",
    "gn:name":"Caypayqui",
    "gn:population":0,
    "gn:timezone":"America/Lima",
    "iso:country":"PE",
    "name:spa_x_preferred":[
        "Caypayqui"
    ],
    "wof:name":"Caypayqui",
    "wof:placetype":"locality"
},
  "geometry": {"coordinates":[-73.23250999999998,-15.33973],"type":"Point"}
}