{
  "type": "Feature",
  "properties": {
    "gn:admin1_code":"8",
    "gn:admin2_code":"809.0",
    "gn:admin3_code":"80902.0",
    "gn:asciiname":"Sangobatea",
    "gn:country_code":"PE",
    "gn:dem":689,
    "gn:feature_class":"P",
    "gn:feature_code":"PPL",
    "gn:name":"Sangobatea",
    "gn:population":0,
    "gn:timezone":"America/Lima",
    "iso:country":"PE",
    "wof:name":"Sangobatea",
    "wof:placetype":"locality"
},
  "geometry": {"coordinates":[-73.07670999999998,-12.63061],"type":"Point"}
}