{
  "type": "Feature",
  "properties": {
    "gn:admin1_code":"5.0",
    "gn:admin2_code":"501.0",
    "gn:admin3_code":"50110.0",
    "gn:asciiname":"Llanopata",
    "gn:country_code":"PE",
    "gn:dem":2677,
    "gn:feature_class":"P",
    "gn:feature_code":"PPL",
    "gn:name":"Llanopata",
    "gn:population":0,
    "gn:timezone":"America/Lima",
    "iso:country":"PE",
    "wof:name":"Llanopata",
    "wof:placetype":"locality"
},
  "geometry": {"coordinates":[-74.19475,-13.16732],"type":"Point"}
}