{
  "type": "Feature",
  "properties": {
    "gn:admin1_code":"15",
    "gn:admin2_code":"1510.0",
    "gn:admin3_code":"151015.0",
    "gn:asciiname":"Huaylluran",
    "gn:country_code":"PE",
    "gn:dem":3369,
    "gn:feature_class":"P",
    "gn:feature_code":"PPL",
    "gn:name":"Huaylluran",
    "gn:population":0,
    "gn:timezone":"America/Lima",
    "iso:country":"PE",
    "wof:name":"Huaylluran",
    "wof:placetype":"locality"
},
  "geometry": {"coordinates":[-75.7899,-12.91262],"type":"Point"}
}