{
  "type": "Feature",
  "properties": {
    "gn:admin1_code":"05",
    "gn:admin2_code":"507.0",
    "gn:admin3_code":"50706.0",
    "gn:asciiname":"Trapiche",
    "gn:country_code":"PE",
    "gn:dem":3429,
    "gn:feature_class":"P",
    "gn:feature_code":"PPL",
    "gn:name":"Trapiche",
    "gn:population":0,
    "gn:timezone":"America/Lima",
    "iso:country":"PE",
    "name:cat_x_preferred":[
        "Trapig"
    ],
    "name:fra_x_preferred":[
        "Trapiche"
    ],
    "name:por_x_preferred":[
        "Trapiche"
    ],
    "name:spa_x_preferred":[
        "Trapiche"
    ],
    "wof:name":"Trapiche",
    "wof:placetype":"locality"
},
  "geometry": {"coordinates":[-73.55534,-15.30837],"type":"Point"}
}