{
  "type": "Feature",
  "properties": {
    "gn:admin1_code":"19",
    "gn:admin2_code":"1901.0",
    "gn:admin3_code":"190108.0",
    "gn:asciiname":"Tingo",
    "gn:cc2":"PE",
    "gn:country_code":"PE",
    "gn:dem":4066,
    "gn:feature_class":"P",
    "gn:feature_code":"PPL",
    "gn:name":"Tingo",
    "gn:population":0,
    "gn:timezone":"America/Lima",
    "iso:country":"PE",
    "name:und_x_variant":[
        "Tingo Alacocha",
        "Tingo"
    ],
    "wof:name":"Tingo",
    "wof:placetype":"locality"
},
  "geometry": {"coordinates":[-76.25,-10.56667],"type":"Point"}
}