{
  "type": "Feature",
  "properties": {
    "gn:admin1_code":"12.0",
    "gn:admin2_code":"1208.0",
    "gn:admin3_code":"120803.0",
    "gn:asciiname":"Pilcocancha",
    "gn:country_code":"PE",
    "gn:dem":4377,
    "gn:feature_class":"P",
    "gn:feature_code":"PPL",
    "gn:name":"Pilcocancha",
    "gn:population":0,
    "gn:timezone":"America/Lima",
    "iso:country":"PE",
    "wof:name":"Pilcocancha",
    "wof:placetype":"locality"
},
  "geometry": {"coordinates":[-75.92164,-11.74852],"type":"Point"}
}