{
  "type": "Feature",
  "properties": {
    "gn:admin1_code":"5.0",
    "gn:admin2_code":"501.0",
    "gn:admin3_code":"50114.0",
    "gn:asciiname":"Chupajasa",
    "gn:country_code":"PE",
    "gn:dem":3306,
    "gn:feature_class":"P",
    "gn:feature_code":"PPL",
    "gn:name":"Chupajasa",
    "gn:population":0,
    "gn:timezone":"America/Lima",
    "iso:country":"PE",
    "wof:name":"Chupajasa",
    "wof:placetype":"locality"
},
  "geometry": {"coordinates":[-74.33424000000002,-13.30825],"type":"Point"}
}