{
  "type": "Feature",
  "properties": {
    "gn:admin1_code":"09",
    "gn:admin2_code":"906.0",
    "gn:admin3_code":"90601.0",
    "gn:asciiname":"Itanacancha",
    "gn:country_code":"PE",
    "gn:dem":3995,
    "gn:feature_class":"P",
    "gn:feature_code":"PPL",
    "gn:name":"Ita\u00f1acancha",
    "gn:population":0,
    "gn:timezone":"America/Lima",
    "iso:country":"PE",
    "wof:name":"Itanacancha",
    "wof:placetype":"locality"
},
  "geometry": {"coordinates":[-75.23666999999998,-13.58278],"type":"Point"}
}