{
  "type": "Feature",
  "properties": {
    "gn:admin1_code":"2.0",
    "gn:admin2_code":"212.0",
    "gn:admin3_code":"21203.0",
    "gn:asciiname":"Pucllanca",
    "gn:country_code":"PE",
    "gn:dem":3822,
    "gn:feature_class":"P",
    "gn:feature_code":"PPL",
    "gn:name":"Pucllanca",
    "gn:population":0,
    "gn:timezone":"America/Lima",
    "iso:country":"PE",
    "wof:name":"Pucllanca",
    "wof:placetype":"locality"
},
  "geometry": {"coordinates":[-77.89694,-9.05139],"type":"Point"}
}