{
  "type": "Feature",
  "properties": {
    "gn:admin1_code":"6.0",
    "gn:admin2_code":"605.0",
    "gn:admin3_code":"60503.0",
    "gn:asciiname":"Cajon",
    "gn:country_code":"PE",
    "gn:dem":2471,
    "gn:feature_class":"P",
    "gn:feature_code":"PPL",
    "gn:name":"Caj\u00f3n",
    "gn:population":0,
    "gn:timezone":"America/Lima",
    "iso:country":"PE",
    "name:spa_x_preferred":[
        "Caj\u00f3n"
    ],
    "wof:name":"Cajon",
    "wof:placetype":"locality"
},
  "geometry": {"coordinates":[-79.00636,-7.35107],"type":"Point"}
}