{
  "type": "Feature",
  "properties": {
    "gn:admin1_code":"8",
    "gn:admin2_code":"806.0",
    "gn:admin3_code":"80602.0",
    "gn:asciiname":"Pampa Cullunuma",
    "gn:country_code":"PE",
    "gn:dem":4521,
    "gn:feature_class":"P",
    "gn:feature_code":"PPL",
    "gn:name":"Pampa Cullunuma",
    "gn:population":0,
    "gn:timezone":"America/Lima",
    "iso:country":"PE",
    "wof:name":"Pampa Cullunuma",
    "wof:placetype":"locality"
},
  "geometry": {"coordinates":[-71.00305999999998,-14.02472],"type":"Point"}
}