{
  "type": "Feature",
  "properties": {
    "gn:admin1_code":"24",
    "gn:admin2_code":"2403.0",
    "gn:admin3_code":"240304.0",
    "gn:asciiname":"Papayal",
    "gn:country_code":"PE",
    "gn:dem":33,
    "gn:feature_class":"P",
    "gn:feature_code":"PPLA3",
    "gn:name":"Papayal",
    "gn:population":0,
    "gn:timezone":"America/Lima",
    "iso:country":"PE",
    "wof:name":"Papayal",
    "wof:placetype":"locality"
},
  "geometry": {"coordinates":[-80.20889,-3.59667],"type":"Point"}
}