{
  "type": "Feature",
  "properties": {
    "gn:admin1_code":"4",
    "gn:admin2_code":"408.0",
    "gn:admin3_code":"40801.0",
    "gn:asciiname":"Cuchaca",
    "gn:country_code":"PE",
    "gn:dem":3395,
    "gn:feature_class":"P",
    "gn:feature_code":"PPL",
    "gn:name":"Cuchaca",
    "gn:population":0,
    "gn:timezone":"America/Lima",
    "iso:country":"PE",
    "wof:name":"Cuchaca",
    "wof:placetype":"locality"
},
  "geometry": {"coordinates":[-72.85554999999999,-15.21883],"type":"Point"}
}