{
  "type": "Feature",
  "properties": {
    "gn:admin1_code":"8",
    "gn:admin2_code":"808.0",
    "gn:admin3_code":"80807.0",
    "gn:asciiname":"Pausa",
    "gn:country_code":"PE",
    "gn:dem":4134,
    "gn:feature_class":"P",
    "gn:feature_code":"PPL",
    "gn:name":"Pausa",
    "gn:population":0,
    "gn:timezone":"America/Lima",
    "iso:country":"PE",
    "name:ara_x_preferred":[
        "\u0648\u0642\u0641"
    ],
    "name:bre_x_preferred":[
        "Pausa"
    ],
    "name:deu_x_preferred":[
        "Pausalform"
    ],
    "name:heb_x_preferred":[
        "\u05e6\u05d5\u05e8\u05ea \u05d4\u05e4\u05e1\u05e7"
    ],
    "name:ind_x_preferred":[
        "Wakaf"
    ],
    "name:msa_x_preferred":[
        "Wakaf"
    ],
    "name:ron_x_preferred":[
        "Pausa"
    ],
    "name:spa_x_preferred":[
        "Pausa"
    ],
    "wof:name":"Pausa",
    "wof:placetype":"locality"
},
  "geometry": {"coordinates":[-71.61523000000003,-14.91767],"type":"Point"}
}