{
  "type": "Feature",
  "properties": {
    "gn:admin1_code":"06",
    "gn:admin2_code":"611.0",
    "gn:admin3_code":"61109.0",
    "gn:asciiname":"Alfalfilla",
    "gn:country_code":"PE",
    "gn:dem":2445,
    "gn:feature_class":"P",
    "gn:feature_code":"PPL",
    "gn:name":"Alfalfilla",
    "gn:population":0,
    "gn:timezone":"America/Lima",
    "iso:country":"PE",
    "wof:name":"Alfalfilla",
    "wof:placetype":"locality"
},
  "geometry": {"coordinates":[-79.09389,-6.90472],"type":"Point"}
}