{
  "type": "Feature",
  "properties": {
    "gn:admin1_code":"20",
    "gn:admin2_code":"2006.0",
    "gn:admin3_code":"200604.0",
    "gn:asciiname":"Dos Orquetas",
    "gn:country_code":"PE",
    "gn:dem":165,
    "gn:feature_class":"P",
    "gn:feature_code":"PPL",
    "gn:name":"Dos Orquetas",
    "gn:population":0,
    "gn:timezone":"America/Lima",
    "iso:country":"PE",
    "wof:name":"Dos Orquetas",
    "wof:placetype":"locality"
},
  "geometry": {"coordinates":[-80.5025,-4.44611],"type":"Point"}
}