{
  "type": "Feature",
  "properties": {
    "gn:admin1_code":"5",
    "gn:admin2_code":"505.0",
    "gn:admin3_code":"50504.0",
    "gn:asciiname":"Rupasnioc",
    "gn:country_code":"PE",
    "gn:dem":3066,
    "gn:feature_class":"P",
    "gn:feature_code":"PPL",
    "gn:name":"Rupasnioc",
    "gn:population":0,
    "gn:timezone":"America/Lima",
    "iso:country":"PE",
    "wof:name":"Rupasnioc",
    "wof:placetype":"locality"
},
  "geometry": {"coordinates":[-73.91289999999999,-13.15658],"type":"Point"}
}