{
  "type": "Feature",
  "properties": {
    "gn:admin1_code":"05",
    "gn:admin2_code":"503.0",
    "gn:admin3_code":"50301.0",
    "gn:asciiname":"Tecrarpo",
    "gn:country_code":"PE",
    "gn:dem":3879,
    "gn:feature_class":"P",
    "gn:feature_code":"PPL",
    "gn:name":"Tecrarpo",
    "gn:population":0,
    "gn:timezone":"America/Lima",
    "iso:country":"PE",
    "wof:name":"Tecrarpo",
    "wof:placetype":"locality"
},
  "geometry": {"coordinates":[-74.41051999999998,-14.00676],"type":"Point"}
}