{
  "type": "Feature",
  "properties": {
    "gn:admin1_code":"22",
    "gn:admin2_code":"2205.0",
    "gn:admin3_code":"220511.0",
    "gn:asciiname":"Zapatero",
    "gn:country_code":"PE",
    "gn:dem":281,
    "gn:feature_class":"P",
    "gn:feature_code":"PPLA3",
    "gn:name":"Zapatero",
    "gn:population":0,
    "gn:timezone":"America/Lima",
    "iso:country":"PE",
    "wof:name":"Zapatero",
    "wof:placetype":"locality"
},
  "geometry": {"coordinates":[-76.49250000000001,-6.52972],"type":"Point"}
}