{
  "type": "Feature",
  "properties": {
    "gn:admin1_code":"15",
    "gn:admin2_code":"1509.0",
    "gn:admin3_code":"150901.0",
    "gn:asciiname":"Racracancha",
    "gn:country_code":"PE",
    "gn:dem":4169,
    "gn:feature_class":"P",
    "gn:feature_code":"PPL",
    "gn:name":"Racracancha",
    "gn:population":0,
    "gn:timezone":"America/Lima",
    "iso:country":"PE",
    "wof:name":"Racracancha",
    "wof:placetype":"locality"
},
  "geometry": {"coordinates":[-76.72004,-10.72187],"type":"Point"}
}