{
  "type": "Feature",
  "properties": {
    "gn:admin1_code":"21",
    "gn:admin2_code":"2104.0",
    "gn:admin3_code":"210403.0",
    "gn:asciiname":"Callonuma",
    "gn:country_code":"PE",
    "gn:dem":3902,
    "gn:feature_class":"P",
    "gn:feature_code":"PPL",
    "gn:name":"Callonuma",
    "gn:population":0,
    "gn:timezone":"America/Lima",
    "iso:country":"PE",
    "wof:name":"Callonuma",
    "wof:placetype":"locality"
},
  "geometry": {"coordinates":[-69.38637,-16.53824],"type":"Point"}
}