{
  "type": "Feature",
  "properties": {
    "gn:admin1_code":"3",
    "gn:admin2_code":"304.0",
    "gn:admin3_code":"30411.0",
    "gn:asciiname":"Pacuni",
    "gn:country_code":"PE",
    "gn:dem":3166,
    "gn:feature_class":"P",
    "gn:feature_code":"PPL",
    "gn:name":"Pacuni",
    "gn:population":0,
    "gn:timezone":"America/Lima",
    "iso:country":"PE",
    "wof:name":"Pacuni",
    "wof:placetype":"locality"
},
  "geometry": {"coordinates":[-73.15418000000003,-13.93212],"type":"Point"}
}