{
  "type": "Feature",
  "properties": {
    "gn:admin1_code":"22.0",
    "gn:admin2_code":"2204.0",
    "gn:admin3_code":"220403.0",
    "gn:asciiname":"La Granja",
    "gn:country_code":"PE",
    "gn:dem":394,
    "gn:feature_class":"P",
    "gn:feature_code":"PPL",
    "gn:name":"La Granja",
    "gn:population":0,
    "gn:timezone":"America/Lima",
    "iso:country":"PE",
    "name:ceb_x_preferred":[
        "La Granja"
    ],
    "name:deu_x_preferred":[
        "La Granja"
    ],
    "name:eus_x_preferred":[
        "La Granja"
    ],
    "name:fra_x_preferred":[
        "La Granja"
    ],
    "name:glg_x_preferred":[
        "La Granja"
    ],
    "name:hun_x_preferred":[
        "La Granja"
    ],
    "name:msa_x_preferred":[
        "La Granja"
    ],
    "name:nld_x_preferred":[
        "La Granja"
    ],
    "name:oci_x_preferred":[
        "La Granja"
    ],
    "name:pol_x_preferred":[
        "La Granja"
    ],
    "name:por_x_preferred":[
        "La Granja"
    ],
    "name:ron_x_preferred":[
        "La Granja"
    ],
    "name:rus_x_preferred":[
        "\u041b\u0430-\u0413\u0440\u0430\u043d\u0445\u0430"
    ],
    "name:spa_x_preferred":[
        "La Granja"
    ],
    "name:spa_x_variant":[
        "La granja"
    ],
    "name:swe_x_preferred":[
        "La Granja"
    ],
    "name:ukr_x_preferred":[
        "\u041b\u0430 \u0413\u0440\u0430\u043d\u0445\u0430"
    ],
    "name:vie_x_preferred":[
        "La Granja"
    ],
    "name:war_x_preferred":[
        "La Granja"
    ],
    "wof:name":"La Granja",
    "wof:placetype":"locality"
},
  "geometry": {"coordinates":[-76.70237,-7.02516],"type":"Point"}
}