{
  "type": "Feature",
  "properties": {
    "gn:admin1_code":"22.0",
    "gn:admin2_code":"2204.0",
    "gn:admin3_code":"220403.0",
    "gn:asciiname":"La Granja",
    "gn:country_code":"PE",
    "gn:dem":394,
    "gn:feature_class":"P",
    "gn:feature_code":"PPL",
    "gn:name":"La Granja",
    "gn:population":0,
    "gn:timezone":"America/Lima",
    "iso:country":"PE",
    "name:spa_x_preferred":[
        "La Granja"
    ],
    "wof:name":"La Granja",
    "wof:placetype":"locality"
},
  "geometry": {"coordinates":[-76.70237,-7.02516],"type":"Point"}
}