{
  "type": "Feature",
  "properties": {
    "gn:admin1_code":"14.0",
    "gn:admin2_code":"1401.0",
    "gn:admin3_code":"140101.0",
    "gn:asciiname":"Fray Martin",
    "gn:country_code":"PE",
    "gn:dem":35,
    "gn:feature_class":"P",
    "gn:feature_code":"PPL",
    "gn:name":"Fray Martin",
    "gn:population":0,
    "gn:timezone":"America/Lima",
    "iso:country":"PE",
    "name:spa_x_preferred":[
        "Fray Martin"
    ],
    "wof:name":"Fray Martin",
    "wof:placetype":"locality"
},
  "geometry": {"coordinates":[-79.80531999999999,-6.76759],"type":"Point"}
}