{
  "type": "Feature",
  "properties": {
    "gn:admin1_code":"7.0",
    "gn:admin2_code":"701.0",
    "gn:asciiname":"Fundo Monte Culebra",
    "gn:country_code":"PE",
    "gn:dem":83,
    "gn:feature_class":"P",
    "gn:feature_code":"PPL",
    "gn:name":"Fundo Monte Culebra",
    "gn:population":0,
    "gn:timezone":"America/Lima",
    "iso:country":"PE",
    "name:spa_x_preferred":[
        "Fundo Monte Culebra"
    ],
    "wof:name":"Fundo Monte Culebra",
    "wof:placetype":"locality"
},
  "geometry": {"coordinates":[-77.10616999999998,-11.94144],"type":"Point"}
}