{
  "type": "Feature",
  "properties": {
    "gn:admin1_code":"8.0",
    "gn:admin2_code":"801.0",
    "gn:admin3_code":"80102.0",
    "gn:asciiname":"Cuchimachay",
    "gn:country_code":"PE",
    "gn:dem":3907,
    "gn:feature_class":"P",
    "gn:feature_code":"PPL",
    "gn:name":"Cuchimachay",
    "gn:population":0,
    "gn:timezone":"America/Lima",
    "iso:country":"PE",
    "wof:name":"Cuchimachay",
    "wof:placetype":"locality"
},
  "geometry": {"coordinates":[-72.09194000000002,-13.64889],"type":"Point"}
}