{
  "type": "Feature",
  "properties": {
    "gn:admin1_code":"04",
    "gn:admin2_code":"405.0",
    "gn:admin3_code":"40514.0",
    "gn:asciiname":"Jatun Zapato",
    "gn:country_code":"PE",
    "gn:dem":4278,
    "gn:feature_class":"P",
    "gn:feature_code":"PPL",
    "gn:name":"Jatun Zapato",
    "gn:population":0,
    "gn:timezone":"America/Lima",
    "iso:country":"PE",
    "wof:name":"Jatun Zapato",
    "wof:placetype":"locality"
},
  "geometry": {"coordinates":[-71.30280999999999,-15.88494],"type":"Point"}
}