{
  "type": "Feature",
  "properties": {
    "gn:admin1_code":"3",
    "gn:admin2_code":"302.0",
    "gn:admin3_code":"30204.0",
    "gn:asciiname":"Huaycahaopata",
    "gn:country_code":"PE",
    "gn:dem":2839,
    "gn:feature_class":"P",
    "gn:feature_code":"PPL",
    "gn:name":"Huaycahaopata",
    "gn:population":0,
    "gn:timezone":"America/Lima",
    "iso:country":"PE",
    "wof:name":"Huaycahaopata",
    "wof:placetype":"locality"
},
  "geometry": {"coordinates":[-73.06277,-13.6304],"type":"Point"}
}