{
  "type": "Feature",
  "properties": {
    "gn:admin1_code":"2.0",
    "gn:admin2_code":"212.0",
    "gn:admin3_code":"21206.0",
    "gn:asciiname":"Chunya",
    "gn:country_code":"PE",
    "gn:dem":3253,
    "gn:feature_class":"P",
    "gn:feature_code":"PPL",
    "gn:name":"Chunya",
    "gn:population":0,
    "gn:timezone":"America/Lima",
    "iso:country":"PE",
    "wof:name":"Chunya",
    "wof:placetype":"locality"
},
  "geometry": {"coordinates":[-77.97417,-9.16361],"type":"Point"}
}