{
  "type": "Feature",
  "properties": {
    "gn:admin1_code":"22.0",
    "gn:admin2_code":"2205.0",
    "gn:admin3_code":"220511.0",
    "gn:asciiname":"Pashacal",
    "gn:country_code":"PE",
    "gn:dem":810,
    "gn:feature_class":"P",
    "gn:feature_code":"PPL",
    "gn:name":"Pashacal",
    "gn:population":0,
    "gn:timezone":"America/Lima",
    "iso:country":"PE",
    "name:spa_x_preferred":[
        "Pashacal"
    ],
    "wof:name":"Pashacal",
    "wof:placetype":"locality"
},
  "geometry": {"coordinates":[-76.51855999999999,-6.60033],"type":"Point"}
}