{
  "type": "Feature",
  "properties": {
    "gn:admin1_code":"9",
    "gn:admin2_code":"903.0",
    "gn:admin3_code":"90301.0",
    "gn:asciiname":"Accocucho",
    "gn:country_code":"PE",
    "gn:dem":4449,
    "gn:feature_class":"P",
    "gn:feature_code":"PPL",
    "gn:name":"Accocucho",
    "gn:population":0,
    "gn:timezone":"America/Lima",
    "iso:country":"PE",
    "wof:name":"Accocucho",
    "wof:placetype":"locality"
},
  "geometry": {"coordinates":[-74.70591999999998,-13.25963],"type":"Point"}
}