{
  "type": "Feature",
  "properties": {
    "gn:admin1_code":"9",
    "gn:admin2_code":"906.0",
    "gn:admin3_code":"90606.0",
    "gn:asciiname":"Salvillayoj",
    "gn:country_code":"PE",
    "gn:dem":3406,
    "gn:feature_class":"P",
    "gn:feature_code":"PPL",
    "gn:name":"Salvillayoj",
    "gn:population":0,
    "gn:timezone":"America/Lima",
    "iso:country":"PE",
    "wof:name":"Salvillayoj",
    "wof:placetype":"locality"
},
  "geometry": {"coordinates":[-75.08333,-13.98222],"type":"Point"}
}