{
  "type": "Feature",
  "properties": {
    "gn:admin1_code":"21",
    "gn:admin2_code":"2107.0",
    "gn:admin3_code":"210709.0",
    "gn:asciiname":"Misitulaya",
    "gn:country_code":"PE",
    "gn:dem":3970,
    "gn:feature_class":"P",
    "gn:feature_code":"PPL",
    "gn:name":"Misitulaya",
    "gn:population":0,
    "gn:timezone":"America/Lima",
    "iso:country":"PE",
    "wof:name":"Misitulaya",
    "wof:placetype":"locality"
},
  "geometry": {"coordinates":[-70.50245,-15.65956],"type":"Point"}
}