{
  "type": "Feature",
  "properties": {
    "gn:admin1_code":"12",
    "gn:admin2_code":"1206.0",
    "gn:admin3_code":"120606.0",
    "gn:asciiname":"Cachequia",
    "gn:country_code":"PE",
    "gn:dem":569,
    "gn:feature_class":"P",
    "gn:feature_code":"PPL",
    "gn:name":"Cachequ\u00eda",
    "gn:population":0,
    "gn:timezone":"America/Lima",
    "iso:country":"PE",
    "name:spa_x_preferred":[
        "Cachequ\u00eda"
    ],
    "wof:name":"Cachequia",
    "wof:placetype":"locality"
},
  "geometry": {"coordinates":[-74.12430999999999,-11.78568],"type":"Point"}
}