{
  "type": "Feature",
  "properties": {
    "gn:admin1_code":"8",
    "gn:admin2_code":"805.0",
    "gn:admin3_code":"80504.0",
    "gn:asciiname":"Nahui",
    "gn:country_code":"PE",
    "gn:dem":4013,
    "gn:feature_class":"P",
    "gn:feature_code":"PPL",
    "gn:name":"\u00d1ahui",
    "gn:population":0,
    "gn:timezone":"America/Lima",
    "iso:country":"PE",
    "wof:name":"Nahui",
    "wof:placetype":"locality"
},
  "geometry": {"coordinates":[-71.29855999999999,-14.41018],"type":"Point"}
}