{
  "type": "Feature",
  "properties": {
    "gn:admin1_code":"04",
    "gn:admin2_code":"406.0",
    "gn:admin3_code":"40601.0",
    "gn:asciiname":"Tojoroyoc",
    "gn:country_code":"PE",
    "gn:dem":2210,
    "gn:feature_class":"P",
    "gn:feature_code":"PPL",
    "gn:name":"Tojoroyoc",
    "gn:population":0,
    "gn:timezone":"America/Lima",
    "iso:country":"PE",
    "wof:name":"Tojoroyoc",
    "wof:placetype":"locality"
},
  "geometry": {"coordinates":[-72.72268000000003,-15.99658],"type":"Point"}
}