{
  "type": "Feature",
  "properties": {
    "gn:admin1_code":"2.0",
    "gn:admin2_code":"212.0",
    "gn:admin3_code":"21201.0",
    "gn:asciiname":"Chosica",
    "gn:country_code":"PE",
    "gn:dem":2914,
    "gn:feature_class":"P",
    "gn:feature_code":"PPLL",
    "gn:name":"Chosica",
    "gn:population":0,
    "gn:timezone":"America/Lima",
    "iso:country":"PE",
    "name:ben_x_preferred":[
        "\u099a\u09b8\u09bf\u0995\u09be"
    ],
    "name:deu_x_preferred":[
        "Chosica"
    ],
    "name:ell_x_preferred":[
        "\u03a4\u03c3\u03bf\u03c3\u03af\u03ba\u03b1"
    ],
    "name:fas_x_preferred":[
        "\u0686\u0648\u0633\u06cc\u06a9\u0627"
    ],
    "name:heb_x_preferred":[
        "\u05e6'\u05d5\u05e1\u05d9\u05e7\u05d4"
    ],
    "name:hin_x_preferred":[
        "\u0915\u094b\u0938\u093f\u0915\u093e"
    ],
    "name:hun_x_preferred":[
        "Chosica"
    ],
    "name:ind_x_preferred":[
        "Chosica"
    ],
    "name:ita_x_preferred":[
        "Chosica"
    ],
    "name:jpn_x_preferred":[
        "\u30c1\u30e7\u30b7\u30ab"
    ],
    "name:kor_x_preferred":[
        "\ucd08\uc2dc\uce74"
    ],
    "name:nld_x_preferred":[
        "Chosica"
    ],
    "name:pol_x_preferred":[
        "Chosica"
    ],
    "name:rus_x_preferred":[
        "\u0427\u043e\u0441\u0438\u043a\u0430"
    ],
    "name:swe_x_preferred":[
        "Chosica"
    ],
    "name:tur_x_preferred":[
        "Chosica"
    ],
    "name:ukr_x_preferred":[
        "\u0427\u043e\u0441\u0456\u043a\u0430"
    ],
    "name:urd_x_preferred":[
        "\u0686\u0648\u0633\u06cc\u06a9\u0627"
    ],
    "name:vie_x_preferred":[
        "Chosica"
    ],
    "name:zho_cn_x_preferred":[
        "\u4e54\u897f\u5361"
    ],
    "name:zho_tw_x_preferred":[
        "\u55ac\u897f\u5361"
    ],
    "wof:name":"Chosica",
    "wof:placetype":"locality"
},
  "geometry": {"coordinates":[-77.77444,-9.04972],"type":"Point"}
}