{
  "type": "Feature",
  "properties": {
    "gn:admin1_code":"2.0",
    "gn:admin2_code":"212.0",
    "gn:admin3_code":"21201.0",
    "gn:asciiname":"Chosica",
    "gn:country_code":"PE",
    "gn:dem":2914,
    "gn:feature_class":"P",
    "gn:feature_code":"PPLL",
    "gn:name":"Chosica",
    "gn:population":0,
    "gn:timezone":"America/Lima",
    "iso:country":"PE",
    "wof:name":"Chosica",
    "wof:placetype":"locality"
},
  "geometry": {"coordinates":[-77.77444,-9.04972],"type":"Point"}
}