{
  "type": "Feature",
  "properties": {
    "gn:admin1_code":"20",
    "gn:admin2_code":"2003.0",
    "gn:admin3_code":"200304.0",
    "gn:asciiname":"La Loma",
    "gn:country_code":"PE",
    "gn:dem":1309,
    "gn:feature_class":"P",
    "gn:feature_code":"PPL",
    "gn:name":"La Loma",
    "gn:population":0,
    "gn:timezone":"America/Lima",
    "iso:country":"PE",
    "name:ceb_x_preferred":[
        "La Loma"
    ],
    "name:deu_x_preferred":[
        "La Loma"
    ],
    "name:spa_x_preferred":[
        "La Loma"
    ],
    "name:srp_x_preferred":[
        "\u041b\u0430 \u041b\u043e\u043c\u0430"
    ],
    "name:swe_x_preferred":[
        "La Loma"
    ],
    "wof:name":"La Loma",
    "wof:placetype":"locality"
},
  "geometry": {"coordinates":[-79.61011999999999,-5.61013],"type":"Point"}
}