{
  "type": "Feature",
  "properties": {
    "gn:admin1_code":"3",
    "gn:admin2_code":"302.0",
    "gn:admin3_code":"30204.0",
    "gn:asciiname":"Mateclla",
    "gn:country_code":"PE",
    "gn:dem":2987,
    "gn:feature_class":"P",
    "gn:feature_code":"PPL",
    "gn:name":"Mateclla",
    "gn:population":0,
    "gn:timezone":"America/Lima",
    "iso:country":"PE",
    "wof:name":"Mateclla",
    "wof:placetype":"locality"
},
  "geometry": {"coordinates":[-73.06024000000002,-13.65601],"type":"Point"}
}