{
  "type": "Feature",
  "properties": {
    "gn:admin1_code":"04",
    "gn:admin2_code":"401.0",
    "gn:admin3_code":"40119.0",
    "gn:asciiname":"Lajore",
    "gn:country_code":"PE",
    "gn:dem":4404,
    "gn:feature_class":"P",
    "gn:feature_code":"PPL",
    "gn:name":"Lajore",
    "gn:population":0,
    "gn:timezone":"America/Lima",
    "iso:country":"PE",
    "name:und_x_variant":[
        "Lajara",
        "Lajore"
    ],
    "wof:name":"Lajore",
    "wof:placetype":"locality"
},
  "geometry": {"coordinates":[-71.10995,-16.03108],"type":"Point"}
}