{
  "type": "Feature",
  "properties": {
    "gn:admin1_code":"15.0",
    "gn:admin2_code":"1508.0",
    "gn:admin3_code":"150811.0",
    "gn:asciiname":"El Carmen",
    "gn:country_code":"PE",
    "gn:dem":414,
    "gn:feature_class":"P",
    "gn:feature_code":"PPL",
    "gn:name":"El Carmen",
    "gn:population":0,
    "gn:timezone":"America/Lima",
    "iso:country":"PE",
    "wof:name":"El Carmen",
    "wof:placetype":"locality"
},
  "geometry": {"coordinates":[-77.34944,-11.1075],"type":"Point"}
}