{
  "type": "Feature",
  "properties": {
    "gn:admin1_code":"13",
    "gn:admin2_code":"1309.0",
    "gn:admin3_code":"130908.0",
    "gn:asciiname":"Chugurbamba",
    "gn:country_code":"PE",
    "gn:dem":2951,
    "gn:feature_class":"P",
    "gn:feature_code":"PPL",
    "gn:name":"Chugurbamba",
    "gn:population":0,
    "gn:timezone":"America/Lima",
    "iso:country":"PE",
    "wof:name":"Chugurbamba",
    "wof:placetype":"locality"
},
  "geometry": {"coordinates":[-77.75671,-7.59416],"type":"Point"}
}