{
  "type": "Feature",
  "properties": {
    "gn:admin1_code":"06",
    "gn:admin2_code":"609.0",
    "gn:admin3_code":"60902.0",
    "gn:asciiname":"Las Juntas",
    "gn:country_code":"PE",
    "gn:dem":446,
    "gn:feature_class":"P",
    "gn:feature_code":"PPL",
    "gn:name":"Las Juntas",
    "gn:population":0,
    "gn:timezone":"America/Lima",
    "iso:country":"PE",
    "name:ceb_x_preferred":[
        "Las Juntas"
    ],
    "name:deu_x_preferred":[
        "Las Juntas"
    ],
    "name:spa_x_preferred":[
        "Las Juntas"
    ],
    "name:swe_x_preferred":[
        "Las Juntas"
    ],
    "wof:name":"Las Juntas",
    "wof:placetype":"locality"
},
  "geometry": {"coordinates":[-78.77188000000002,-5.37645],"type":"Point"}
}