{
  "type": "Feature",
  "properties": {
    "gn:admin1_code":"2.0",
    "gn:admin2_code":"210.0",
    "gn:admin3_code":"21010.0",
    "gn:asciiname":"Chincho",
    "gn:country_code":"PE",
    "gn:dem":3110,
    "gn:feature_class":"P",
    "gn:feature_code":"PPL",
    "gn:name":"Chincho",
    "gn:population":0,
    "gn:timezone":"America/Lima",
    "iso:country":"PE",
    "wof:name":"Chincho",
    "wof:placetype":"locality"
},
  "geometry": {"coordinates":[-76.91339000000001,-9.15387],"type":"Point"}
}