{
  "type": "Feature",
  "properties": {
    "gn:admin1_code":"01",
    "gn:admin2_code":"107.0",
    "gn:admin3_code":"10703.0",
    "gn:asciiname":"Tabacales",
    "gn:country_code":"PE",
    "gn:dem":1125,
    "gn:feature_class":"P",
    "gn:feature_code":"PPL",
    "gn:name":"Tabacales",
    "gn:population":0,
    "gn:timezone":"America/Lima",
    "iso:country":"PE",
    "wof:name":"Tabacales",
    "wof:placetype":"locality"
},
  "geometry": {"coordinates":[-78.60930999999999,-5.93567],"type":"Point"}
}