{
  "type": "Feature",
  "properties": {
    "gn:admin1_code":"02",
    "gn:admin2_code":"218.0",
    "gn:asciiname":"La Vibora",
    "gn:country_code":"PE",
    "gn:dem":109,
    "gn:feature_class":"P",
    "gn:feature_code":"PPL",
    "gn:name":"La V\u00edbora",
    "gn:population":0,
    "gn:timezone":"America/Lima",
    "iso:country":"PE",
    "wof:name":"La Vibora",
    "wof:placetype":"locality"
},
  "geometry": {"coordinates":[-78.58333,-8.86667],"type":"Point"}
}