{
  "type": "Feature",
  "properties": {
    "gn:admin1_code":"20",
    "gn:admin2_code":"2006.0",
    "gn:admin3_code":"200604.0",
    "gn:asciiname":"Requena",
    "gn:country_code":"PE",
    "gn:dem":145,
    "gn:feature_class":"P",
    "gn:feature_code":"PPL",
    "gn:name":"Requena",
    "gn:population":0,
    "gn:timezone":"America/Lima",
    "iso:country":"PE",
    "name:ara_x_preferred":[
        "\u0631\u064a\u0643\u064a\u0646\u0627"
    ],
    "name:ben_x_preferred":[
        "\u09b0\u09c7\u0995\u09c1\u09df\u09c7\u09a8\u09be"
    ],
    "name:ceb_x_preferred":[
        "Requena"
    ],
    "name:deu_x_preferred":[
        "Requena"
    ],
    "name:ell_x_preferred":[
        "\u03a1\u03b5\u03b3\u03bf\u03c5\u03ad\u03bd\u03b1"
    ],
    "name:fas_x_preferred":[
        "\u0631\u06a9\u0648\u0646\u0646\u0627"
    ],
    "name:fra_x_preferred":[
        "Requena"
    ],
    "name:heb_x_preferred":[
        "\u05e8\u05e7\u05d5\u05d5\u05e0\u05d4"
    ],
    "name:hin_x_preferred":[
        "\u0930\u0947\u0915\u0947\u0928\u093e"
    ],
    "name:hun_x_preferred":[
        "Requena"
    ],
    "name:ind_x_preferred":[
        "Requena"
    ],
    "name:ita_x_preferred":[
        "Requena"
    ],
    "name:kor_x_preferred":[
        "\ub808\ud018\ub098"
    ],
    "name:nds_x_preferred":[
        "Requena"
    ],
    "name:nld_x_preferred":[
        "Requena"
    ],
    "name:pol_x_preferred":[
        "Requena"
    ],
    "name:por_x_preferred":[
        "Requena"
    ],
    "name:rus_x_preferred":[
        "\u0420\u0435\u043a\u0435\u043d\u0430"
    ],
    "name:spa_x_preferred":[
        "Requena"
    ],
    "name:swe_x_preferred":[
        "Requena"
    ],
    "name:tur_x_preferred":[
        "Requena"
    ],
    "name:ukr_x_preferred":[
        "\u0420\u0435\u043a\u0435\u043d\u0430"
    ],
    "name:urd_x_preferred":[
        "\u0631\u06cc\u06a9\u0648\u0626\u06cc\u0646\u0627"
    ],
    "name:vie_x_preferred":[
        "Requena"
    ],
    "wof:name":"Requena",
    "wof:placetype":"locality"
},
  "geometry": {"coordinates":[-80.41667,-4.46667],"type":"Point"}
}