{
  "type": "Feature",
  "properties": {
    "gn:admin1_code":"20",
    "gn:admin2_code":"2006.0",
    "gn:admin3_code":"200604.0",
    "gn:asciiname":"Requena",
    "gn:country_code":"PE",
    "gn:dem":145,
    "gn:feature_class":"P",
    "gn:feature_code":"PPL",
    "gn:name":"Requena",
    "gn:population":0,
    "gn:timezone":"America/Lima",
    "iso:country":"PE",
    "name:ceb_x_preferred":[
        "Requena"
    ],
    "name:deu_x_preferred":[
        "Requena"
    ],
    "name:fra_x_preferred":[
        "Requena"
    ],
    "name:ita_x_preferred":[
        "Requena"
    ],
    "name:nds_x_preferred":[
        "Requena"
    ],
    "name:nld_x_preferred":[
        "Requena"
    ],
    "name:por_x_preferred":[
        "Requena"
    ],
    "name:rus_x_preferred":[
        "\u0420\u0435\u043a\u0435\u043d\u0430"
    ],
    "name:spa_x_preferred":[
        "Requena"
    ],
    "name:swe_x_preferred":[
        "Requena"
    ],
    "wof:name":"Requena",
    "wof:placetype":"locality"
},
  "geometry": {"coordinates":[-80.41667,-4.46667],"type":"Point"}
}