{
  "type": "Feature",
  "properties": {
    "gn:admin1_code":"2.0",
    "gn:admin2_code":"212.0",
    "gn:admin3_code":"21203.0",
    "gn:asciiname":"Racracallan",
    "gn:country_code":"PE",
    "gn:dem":3347,
    "gn:feature_class":"P",
    "gn:feature_code":"PPL",
    "gn:name":"Racracallan",
    "gn:population":0,
    "gn:timezone":"America/Lima",
    "iso:country":"PE",
    "wof:name":"Racracallan",
    "wof:placetype":"locality"
},
  "geometry": {"coordinates":[-77.88916999999999,-9.03056],"type":"Point"}
}