{
  "type": "Feature",
  "properties": {
    "gn:admin1_code":"21",
    "gn:admin2_code":"2112",
    "gn:asciiname":"Pilcomayo",
    "gn:country_code":"PE",
    "gn:dem":1326,
    "gn:feature_class":"P",
    "gn:feature_code":"PPL",
    "gn:name":"Pilcomayo",
    "gn:population":0,
    "gn:timezone":"America/Lima",
    "iso:country":"PE",
    "name:ceb_x_preferred":[
        "Pilcomayo"
    ],
    "name:deu_x_preferred":[
        "Pilcomayo"
    ],
    "name:hrv_x_preferred":[
        "Pilcomayo"
    ],
    "name:ita_x_preferred":[
        "Pilcomayo"
    ],
    "name:nld_x_preferred":[
        "Pilcomayo"
    ],
    "name:por_x_preferred":[
        "Pilcomayo"
    ],
    "name:rus_x_preferred":[
        "\u0440\u0435\u043a\u0430 \u041f\u0438\u043b\u044c\u043a\u043e\u043c\u0430\u0301\u0439\u043e"
    ],
    "name:rus_x_variant":[
        "\u041f\u0438\u043b\u044c\u043a\u043e\u043c\u0430\u0439\u043e"
    ],
    "name:slk_x_preferred":[
        "Pilcomayo"
    ],
    "name:spa_x_preferred":[
        "Pilcomayo"
    ],
    "name:swe_x_preferred":[
        "Pilcomayo"
    ],
    "name:tur_x_preferred":[
        "Pilcomayo"
    ],
    "name:ukr_x_preferred":[
        "\u041f\u0456\u043b\u043a\u043e\u043c\u0430\u0439\u043e"
    ],
    "name:urd_x_preferred":[
        "\u067e\u0644\u06a9\u0648\u0645\u0627\u06cc\u0648"
    ],
    "name:vie_x_preferred":[
        "S\u00f4ng Pilcomayo"
    ],
    "name:zho_cn_x_preferred":[
        "\u76ae\u79d1\u9a6c\u7ea6\u6cb3"
    ],
    "name:zho_tw_x_preferred":[
        "\u76ae\u53ef\u99ac\u7d04\u6cb3"
    ],
    "wof:name":"Pilcomayo",
    "wof:placetype":"locality"
},
  "geometry": {"coordinates":[-69.59582,-13.90977],"type":"Point"}
}