{
  "type": "Feature",
  "properties": {
    "gn:admin1_code":"21",
    "gn:admin2_code":"2112",
    "gn:asciiname":"Pilcomayo",
    "gn:country_code":"PE",
    "gn:dem":1326,
    "gn:feature_class":"P",
    "gn:feature_code":"PPL",
    "gn:name":"Pilcomayo",
    "gn:population":0,
    "gn:timezone":"America/Lima",
    "iso:country":"PE",
    "name:spa_x_preferred":[
        "Pilcomayo"
    ],
    "wof:name":"Pilcomayo",
    "wof:placetype":"locality"
},
  "geometry": {"coordinates":[-69.59581999999999,-13.90977],"type":"Point"}
}