{
  "type": "Feature",
  "properties": {
    "gn:admin1_code":"21",
    "gn:admin2_code":"2112",
    "gn:asciiname":"Pilcomayo",
    "gn:country_code":"PE",
    "gn:dem":1326,
    "gn:feature_class":"P",
    "gn:feature_code":"PPL",
    "gn:name":"Pilcomayo",
    "gn:population":0,
    "gn:timezone":"America/Lima",
    "iso:country":"PE",
    "name:ceb_x_preferred":[
        "Pilcomayo"
    ],
    "name:deu_x_preferred":[
        "Pilcomayo"
    ],
    "name:hrv_x_preferred":[
        "Pilcomayo"
    ],
    "name:ita_x_preferred":[
        "Pilcomayo"
    ],
    "name:nld_x_preferred":[
        "Pilcomayo"
    ],
    "name:por_x_preferred":[
        "Pilcomayo"
    ],
    "name:rus_x_preferred":[
        "\u041f\u0438\u043b\u044c\u043a\u043e\u043c\u0430\u0439\u043e"
    ],
    "name:slk_x_preferred":[
        "Pilcomayo"
    ],
    "name:spa_x_preferred":[
        "Pilcomayo"
    ],
    "name:swe_x_preferred":[
        "Pilcomayo"
    ],
    "wof:name":"Pilcomayo",
    "wof:placetype":"locality"
},
  "geometry": {"coordinates":[-69.59581999999999,-13.90977],"type":"Point"}
}