{
  "type": "Feature",
  "properties": {
    "gn:admin1_code":"5",
    "gn:admin2_code":"506.0",
    "gn:admin3_code":"50604.0",
    "gn:asciiname":"Andamarca",
    "gn:country_code":"PE",
    "gn:dem":3451,
    "gn:feature_class":"P",
    "gn:feature_code":"PPLA3",
    "gn:name":"Andamarca",
    "gn:population":0,
    "gn:timezone":"America/Lima",
    "iso:country":"PE",
    "wof:name":"Andamarca",
    "wof:placetype":"locality"
},
  "geometry": {"coordinates":[-73.96083,-14.38722],"type":"Point"}
}