{
  "type": "Feature",
  "properties": {
    "gn:admin1_code":"10.0",
    "gn:admin2_code":"1011.0",
    "gn:admin3_code":"101101.0",
    "gn:asciiname":"Supayucro",
    "gn:country_code":"PE",
    "gn:dem":3579,
    "gn:feature_class":"P",
    "gn:feature_code":"PPL",
    "gn:name":"Supayucro",
    "gn:population":0,
    "gn:timezone":"America/Lima",
    "iso:country":"PE",
    "wof:name":"Supayucro",
    "wof:placetype":"locality"
},
  "geometry": {"coordinates":[-76.60335000000001,-9.83883],"type":"Point"}
}