{
  "type": "Feature",
  "properties": {
    "gn:admin1_code":"12.0",
    "gn:admin2_code":"1204.0",
    "gn:admin3_code":"120427.0",
    "gn:asciiname":"Chajlla",
    "gn:country_code":"PE",
    "gn:dem":4169,
    "gn:feature_class":"P",
    "gn:feature_code":"PPL",
    "gn:name":"Chajlla",
    "gn:population":0,
    "gn:timezone":"America/Lima",
    "iso:country":"PE",
    "wof:name":"Chajlla",
    "wof:placetype":"locality"
},
  "geometry": {"coordinates":[-75.48026999999998,-11.58555],"type":"Point"}
}