{
  "type": "Feature",
  "properties": {
    "gn:admin1_code":"06",
    "gn:admin2_code":"611.0",
    "gn:admin3_code":"61110.0",
    "gn:asciiname":"Uvidi",
    "gn:country_code":"PE",
    "gn:dem":2347,
    "gn:feature_class":"P",
    "gn:feature_code":"PPL",
    "gn:name":"Uvidi",
    "gn:population":0,
    "gn:timezone":"America/Lima",
    "iso:country":"PE",
    "wof:name":"Uvidi",
    "wof:placetype":"locality"
},
  "geometry": {"coordinates":[-79.06565999999999,-7.06788],"type":"Point"}
}