{
  "type": "Feature",
  "properties": {
    "gn:admin1_code":"10",
    "gn:admin2_code":"1002.0",
    "gn:admin3_code":"100203.0",
    "gn:asciiname":"Huacrarumi",
    "gn:country_code":"PE",
    "gn:dem":3818,
    "gn:feature_class":"P",
    "gn:feature_code":"PPL",
    "gn:name":"Huacrarumi",
    "gn:population":0,
    "gn:timezone":"America/Lima",
    "iso:country":"PE",
    "wof:name":"Huacrarumi",
    "wof:placetype":"locality"
},
  "geometry": {"coordinates":[-76.49733000000001,-10.24382],"type":"Point"}
}