{
  "type": "Feature",
  "properties": {
    "gn:admin1_code":"12",
    "gn:admin2_code":"1202.0",
    "gn:admin3_code":"120202.0",
    "gn:asciiname":"Aco",
    "gn:country_code":"PE",
    "gn:dem":3469,
    "gn:feature_class":"P",
    "gn:feature_code":"PPLA3",
    "gn:name":"Aco",
    "gn:population":0,
    "gn:timezone":"America/Lima",
    "iso:country":"PE",
    "wof:name":"Aco",
    "wof:placetype":"locality"
},
  "geometry": {"coordinates":[-75.36995999999998,-11.95707],"type":"Point"}
}