{
  "type": "Feature",
  "properties": {
    "gn:admin1_code":"16",
    "gn:admin2_code":"1603.0",
    "gn:admin3_code":"160303.0",
    "gn:asciiname":"Leoncio Prado",
    "gn:country_code":"PE",
    "gn:dem":181,
    "gn:feature_class":"P",
    "gn:feature_code":"PPL",
    "gn:name":"Leoncio Prado",
    "gn:population":0,
    "gn:timezone":"America/Lima",
    "iso:country":"PE",
    "name:ceb_x_preferred":[
        "Leoncio Prado"
    ],
    "name:nld_x_preferred":[
        "Leoncio Prado"
    ],
    "name:por_x_preferred":[
        "Leoncio Prado"
    ],
    "wof:name":"Leoncio Prado",
    "wof:placetype":"locality"
},
  "geometry": {"coordinates":[-75.68333,-2.66667],"type":"Point"}
}