{
  "type": "Feature",
  "properties": {
    "gn:admin1_code":"18",
    "gn:admin2_code":"1803.0",
    "gn:admin3_code":"180303.0",
    "gn:asciiname":"Tentacion",
    "gn:country_code":"PE",
    "gn:dem":226,
    "gn:feature_class":"P",
    "gn:feature_code":"PPL",
    "gn:name":"Tentaci\u00f3n",
    "gn:population":0,
    "gn:timezone":"America/Lima",
    "iso:country":"PE",
    "wof:name":"Tentacion",
    "wof:placetype":"locality"
},
  "geometry": {"coordinates":[-71.38278000000003,-17.39333],"type":"Point"}
}