{
  "type": "Feature",
  "properties": {
    "gn:admin1_code":"13",
    "gn:admin2_code":"1303.0",
    "gn:admin3_code":"130304.0",
    "gn:asciiname":"Longotea",
    "gn:cc2":"PE",
    "gn:country_code":"PE",
    "gn:dem":2708,
    "gn:feature_class":"P",
    "gn:feature_code":"PPLA3",
    "gn:name":"Longotea",
    "gn:population":0,
    "gn:timezone":"America/Lima",
    "iso:country":"PE",
    "name:und_x_variant":[
        "Langotea",
        "Longotea"
    ],
    "wof:name":"Longotea",
    "wof:placetype":"locality"
},
  "geometry": {"coordinates":[-77.91667,-7.06667],"type":"Point"}
}