{
  "type": "Feature",
  "properties": {
    "gn:admin1_code":"9.0",
    "gn:admin2_code":"901.0",
    "gn:admin3_code":"90106.0",
    "gn:asciiname":"Gentil Machay",
    "gn:country_code":"PE",
    "gn:dem":4107,
    "gn:feature_class":"P",
    "gn:feature_code":"PPL",
    "gn:name":"Gentil Machay",
    "gn:population":0,
    "gn:timezone":"America/Lima",
    "iso:country":"PE",
    "wof:name":"Gentil Machay",
    "wof:placetype":"locality"
},
  "geometry": {"coordinates":[-74.87271,-12.98116],"type":"Point"}
}