{
  "type": "Feature",
  "properties": {
    "gn:admin1_code":"5.0",
    "gn:admin2_code":"502.0",
    "gn:asciiname":"Jacupa",
    "gn:country_code":"PE",
    "gn:dem":4093,
    "gn:feature_class":"P",
    "gn:feature_code":"PPL",
    "gn:name":"Jacupa",
    "gn:population":0,
    "gn:timezone":"America/Lima",
    "iso:country":"PE",
    "wof:name":"Jacupa",
    "wof:placetype":"locality"
},
  "geometry": {"coordinates":[-74.82200999999998,-13.47627],"type":"Point"}
}