{
  "type": "Feature",
  "properties": {
    "gn:admin1_code":"09",
    "gn:admin2_code":"901.0",
    "gn:admin3_code":"90113.0",
    "gn:asciiname":"Nuevo Occoro",
    "gn:country_code":"PE",
    "gn:dem":3907,
    "gn:feature_class":"P",
    "gn:feature_code":"PPL",
    "gn:name":"Nuevo Occoro",
    "gn:population":0,
    "gn:timezone":"America/Lima",
    "iso:country":"PE",
    "wof:name":"Nuevo Occoro",
    "wof:placetype":"locality"
},
  "geometry": {"coordinates":[-75.02056,-12.59264],"type":"Point"}
}