{
  "type": "Feature",
  "properties": {
    "gn:admin1_code":"2.0",
    "gn:admin2_code":"205.0",
    "gn:asciiname":"Ututo",
    "gn:country_code":"PE",
    "gn:dem":4007,
    "gn:feature_class":"P",
    "gn:feature_code":"PPL",
    "gn:name":"Ututo",
    "gn:population":0,
    "gn:timezone":"America/Lima",
    "iso:country":"PE",
    "name:ara_x_preferred":[
        "\u0623\u0648\u062a\u0648\u062a\u0648"
    ],
    "name:ben_x_preferred":[
        "\u0987\u0989\u099f\u09c1\u099f\u09cb"
    ],
    "name:cat_x_preferred":[
        "Ututo"
    ],
    "name:deu_x_preferred":[
        "Ututo"
    ],
    "name:epo_x_preferred":[
        "Ututo"
    ],
    "name:fas_x_preferred":[
        "\u0627\u0648\u062a\u0648\u062a\u0648"
    ],
    "name:fra_x_preferred":[
        "Ututo"
    ],
    "name:ita_x_preferred":[
        "Ututo"
    ],
    "name:nor_x_preferred":[
        "Ututo"
    ],
    "name:pol_x_preferred":[
        "Ututo"
    ],
    "name:por_x_preferred":[
        "Ututo"
    ],
    "name:ron_x_preferred":[
        "Ututo"
    ],
    "name:rus_x_preferred":[
        "Ututo"
    ],
    "name:spa_x_preferred":[
        "Ututo"
    ],
    "name:tgl_x_preferred":[
        "Ututo-e"
    ],
    "wof:name":"Ututo",
    "wof:placetype":"locality"
},
  "geometry": {"coordinates":[-76.91993000000002,-9.85251],"type":"Point"}
}