{
  "type": "Feature",
  "properties": {
    "gn:admin1_code":"02",
    "gn:admin2_code":"214.0",
    "gn:admin3_code":"21402.0",
    "gn:asciiname":"Cuchillas",
    "gn:country_code":"PE",
    "gn:dem":1413,
    "gn:feature_class":"P",
    "gn:feature_code":"PPL",
    "gn:name":"Cuchillas",
    "gn:population":0,
    "gn:timezone":"America/Lima",
    "iso:country":"PE",
    "name:ceb_x_preferred":[
        "Cuchillas"
    ],
    "name:spa_x_preferred":[
        "Cuchillas"
    ],
    "name:swe_x_preferred":[
        "Cuchillas"
    ],
    "wof:name":"Cuchillas",
    "wof:placetype":"locality"
},
  "geometry": {"coordinates":[-77.4064,-10.52977],"type":"Point"}
}