{
  "type": "Feature",
  "properties": {
    "gn:admin1_code":"8",
    "gn:admin2_code":"808.0",
    "gn:admin3_code":"80803.0",
    "gn:asciiname":"Otana",
    "gn:country_code":"PE",
    "gn:dem":4367,
    "gn:feature_class":"P",
    "gn:feature_code":"PPL",
    "gn:name":"Ota\u00f1a",
    "gn:population":0,
    "gn:timezone":"America/Lima",
    "iso:country":"PE",
    "wof:name":"Otana",
    "wof:placetype":"locality"
},
  "geometry": {"coordinates":[-71.83806,-14.74528],"type":"Point"}
}