{
  "type": "Feature",
  "properties": {
    "gn:admin1_code":"12",
    "gn:admin2_code":"1209.0",
    "gn:admin3_code":"120909.0",
    "gn:asciiname":"Alampa",
    "gn:country_code":"PE",
    "gn:dem":4547,
    "gn:feature_class":"P",
    "gn:feature_code":"PPL",
    "gn:name":"Alampa",
    "gn:population":0,
    "gn:timezone":"America/Lima",
    "iso:country":"PE",
    "wof:name":"Alampa",
    "wof:placetype":"locality"
},
  "geometry": {"coordinates":[-75.52167,-12.36556],"type":"Point"}
}