{
  "type": "Feature",
  "properties": {
    "gn:admin1_code":"4",
    "gn:admin2_code":"405.0",
    "gn:admin3_code":"40511.0",
    "gn:asciiname":"Torre Torre",
    "gn:country_code":"PE",
    "gn:dem":4008,
    "gn:feature_class":"P",
    "gn:feature_code":"PPL",
    "gn:name":"Torre Torre",
    "gn:population":0,
    "gn:timezone":"America/Lima",
    "iso:country":"PE",
    "wof:name":"Torre Torre",
    "wof:placetype":"locality"
},
  "geometry": {"coordinates":[-71.96536,-15.89857],"type":"Point"}
}