{
  "type": "Feature",
  "properties": {
    "gn:admin1_code":"21",
    "gn:admin2_code":"2104.0",
    "gn:admin3_code":"210405.0",
    "gn:asciiname":"Ancomoco",
    "gn:country_code":"PE",
    "gn:dem":3949,
    "gn:feature_class":"P",
    "gn:feature_code":"PPL",
    "gn:name":"Ancomoco",
    "gn:population":0,
    "gn:timezone":"America/Lima",
    "iso:country":"PE",
    "wof:name":"Ancomoco",
    "wof:placetype":"locality"
},
  "geometry": {"coordinates":[-69.36173000000001,-16.91431],"type":"Point"}
}