{
  "type": "Feature",
  "properties": {
    "gn:admin1_code":"16",
    "gn:admin2_code":"1601.0",
    "gn:admin3_code":"160114.0",
    "gn:asciiname":"Puerto Buenos Aires",
    "gn:country_code":"PE",
    "gn:dem":171,
    "gn:feature_class":"P",
    "gn:feature_code":"PPL",
    "gn:name":"Puerto Buenos Aires",
    "gn:population":0,
    "gn:timezone":"America/Lima",
    "iso:country":"PE",
    "wof:name":"Puerto Buenos Aires",
    "wof:placetype":"locality"
},
  "geometry": {"coordinates":[-74.38333,-1.01667],"type":"Point"}
}