{
  "type": "Feature",
  "properties": {
    "gn:admin1_code":"21",
    "gn:admin2_code":"2105.0",
    "gn:admin3_code":"210502.0",
    "gn:asciiname":"Colluta",
    "gn:country_code":"PE",
    "gn:dem":4246,
    "gn:feature_class":"P",
    "gn:feature_code":"PPL",
    "gn:name":"Colluta",
    "gn:population":0,
    "gn:timezone":"America/Lima",
    "iso:country":"PE",
    "wof:name":"Colluta",
    "wof:placetype":"locality"
},
  "geometry": {"coordinates":[-69.67151,-17.23802],"type":"Point"}
}