{
  "type": "Feature",
  "properties": {
    "gn:admin1_code":"5.0",
    "gn:admin2_code":"504.0",
    "gn:admin3_code":"50403.0",
    "gn:asciiname":"Yanapampa",
    "gn:country_code":"PE",
    "gn:dem":2998,
    "gn:feature_class":"P",
    "gn:feature_code":"PPL",
    "gn:name":"Yanapampa",
    "gn:population":0,
    "gn:timezone":"America/Lima",
    "iso:country":"PE",
    "wof:name":"Yanapampa",
    "wof:placetype":"locality"
},
  "geometry": {"coordinates":[-74.20314,-13.01374],"type":"Point"}
}