{
  "type": "Feature",
  "properties": {
    "gn:admin1_code":"21",
    "gn:admin2_code":"2112.0",
    "gn:admin3_code":"211210.0",
    "gn:asciiname":"Misquimayo",
    "gn:country_code":"PE",
    "gn:dem":1056,
    "gn:feature_class":"P",
    "gn:feature_code":"PPL",
    "gn:name":"Misquimayo",
    "gn:population":0,
    "gn:timezone":"America/Lima",
    "iso:country":"PE",
    "name:spa_x_preferred":[
        "Misquimayo"
    ],
    "wof:name":"Misquimayo",
    "wof:placetype":"locality"
},
  "geometry": {"coordinates":[-68.95,-14.01944],"type":"Point"}
}