{
  "type": "Feature",
  "properties": {
    "gn:admin1_code":"15",
    "gn:admin2_code":"1504.0",
    "gn:admin3_code":"150403.0",
    "gn:asciiname":"Shimay",
    "gn:country_code":"PE",
    "gn:dem":3106,
    "gn:feature_class":"P",
    "gn:feature_code":"PPL",
    "gn:name":"Shimay",
    "gn:population":0,
    "gn:timezone":"America/Lima",
    "iso:country":"PE",
    "wof:name":"Shimay",
    "wof:placetype":"locality"
},
  "geometry": {"coordinates":[-76.7675,-11.49861],"type":"Point"}
}