{
  "type": "Feature",
  "properties": {
    "gn:admin1_code":"9.0",
    "gn:admin2_code":"907.0",
    "gn:admin3_code":"90701.0",
    "gn:asciiname":"Vinas",
    "gn:country_code":"PE",
    "gn:dem":3323,
    "gn:feature_class":"P",
    "gn:feature_code":"PPL",
    "gn:name":"Vi\u00f1as",
    "gn:population":0,
    "gn:timezone":"America/Lima",
    "iso:country":"PE",
    "wof:name":"Vinas",
    "wof:placetype":"locality"
},
  "geometry": {"coordinates":[-74.86575000000001,-12.41318],"type":"Point"}
}