{
  "type": "Feature",
  "properties": {
    "gn:admin1_code":"8",
    "gn:admin2_code":"806.0",
    "gn:admin3_code":"80604.0",
    "gn:asciiname":"Chinchina",
    "gn:country_code":"PE",
    "gn:dem":4794,
    "gn:feature_class":"P",
    "gn:feature_code":"PPL",
    "gn:name":"Chinchina",
    "gn:population":0,
    "gn:timezone":"America/Lima",
    "iso:country":"PE",
    "wof:name":"Chinchina",
    "wof:placetype":"locality"
},
  "geometry": {"coordinates":[-71.00556,-14.395],"type":"Point"}
}