{
  "type": "Feature",
  "properties": {
    "gn:admin1_code":"21",
    "gn:admin2_code":"2102.0",
    "gn:admin3_code":"210202.0",
    "gn:asciiname":"Achaya",
    "gn:country_code":"PE",
    "gn:dem":3852,
    "gn:feature_class":"P",
    "gn:feature_code":"PPLA3",
    "gn:name":"Achaya",
    "gn:population":0,
    "gn:timezone":"America/Lima",
    "iso:country":"PE",
    "wof:name":"Achaya",
    "wof:placetype":"locality"
},
  "geometry": {"coordinates":[-70.15000000000001,-15.26667],"type":"Point"}
}