{
  "type": "Feature",
  "properties": {
    "gn:admin1_code":"21",
    "gn:admin2_code":"2102.0",
    "gn:admin3_code":"210202.0",
    "gn:asciiname":"Achaya",
    "gn:country_code":"PE",
    "gn:dem":3852,
    "gn:feature_class":"P",
    "gn:feature_code":"PPLA3",
    "gn:name":"Achaya",
    "gn:population":0,
    "gn:timezone":"America/Lima",
    "iso:country":"PE",
    "name:fas_x_preferred":[
        "\u0645\u0646\u0637\u0642\u0647 \u0627\u06a9\u0627\u06cc\u0627"
    ],
    "name:kat_x_preferred":[
        "\u10d0\u10e9\u10d0\u10d8\u10d8\u10e1 \u10e0\u10d0\u10d8\u10dd\u10dc\u10d8"
    ],
    "name:por_x_preferred":[
        "Achaya"
    ],
    "name:que_x_preferred":[
        "Achaya distritu"
    ],
    "name:zho_x_preferred":[
        "\u963f\u67e5\u4e9e\u5340"
    ],
    "wof:name":"Achaya",
    "wof:placetype":"locality"
},
  "geometry": {"coordinates":[-70.15000000000001,-15.26667],"type":"Point"}
}