{
  "type": "Feature",
  "properties": {
    "gn:admin1_code":"11.0",
    "gn:admin2_code":"1101.0",
    "gn:admin3_code":"110102.0",
    "gn:asciiname":"Fundicion Alta",
    "gn:country_code":"PE",
    "gn:dem":426,
    "gn:feature_class":"P",
    "gn:feature_code":"PPL",
    "gn:name":"Fundicion Alta",
    "gn:population":0,
    "gn:timezone":"America/Lima",
    "iso:country":"PE",
    "name:spa_x_preferred":[
        "Fundicion Alta"
    ],
    "wof:name":"Fundicion Alta",
    "wof:placetype":"locality"
},
  "geometry": {"coordinates":[-75.72444,-14.00046],"type":"Point"}
}