{
  "type": "Feature",
  "properties": {
    "gn:admin1_code":"20",
    "gn:admin2_code":"2003.0",
    "gn:admin3_code":"200303.0",
    "gn:asciiname":"Putaga",
    "gn:country_code":"PE",
    "gn:dem":2984,
    "gn:feature_class":"P",
    "gn:feature_code":"PPL",
    "gn:name":"Putaga",
    "gn:population":0,
    "gn:timezone":"America/Lima",
    "iso:country":"PE",
    "wof:name":"Putaga",
    "wof:placetype":"locality"
},
  "geometry": {"coordinates":[-79.46302,-5.1043],"type":"Point"}
}