{
  "type": "Feature",
  "properties": {
    "gn:admin1_code":"4.0",
    "gn:admin2_code":"401.0",
    "gn:admin3_code":"40108.0",
    "gn:asciiname":"Los Medanos",
    "gn:country_code":"PE",
    "gn:dem":1587,
    "gn:feature_class":"P",
    "gn:feature_code":"PPL",
    "gn:name":"Los Medanos",
    "gn:population":0,
    "gn:timezone":"America/Lima",
    "iso:country":"PE",
    "wof:name":"Los Medanos",
    "wof:placetype":"locality"
},
  "geometry": {"coordinates":[-71.81421,-16.48858],"type":"Point"}
}