{
  "type": "Feature",
  "properties": {
    "gn:admin1_code":"13",
    "gn:admin2_code":"1309.0",
    "gn:admin3_code":"130907.0",
    "gn:asciiname":"Mumalca",
    "gn:cc2":"PE",
    "gn:country_code":"PE",
    "gn:dem":3254,
    "gn:feature_class":"P",
    "gn:feature_code":"PPL",
    "gn:name":"Mumalca",
    "gn:population":0,
    "gn:timezone":"America/Lima",
    "iso:country":"PE",
    "name:und_x_variant":[
        "Humalca",
        "Mumalca Hacienda",
        "Hacienda Mumalea",
        "Hacienda Mumalca",
        "Mumalca"
    ],
    "wof:name":"Mumalca",
    "wof:placetype":"locality"
},
  "geometry": {"coordinates":[-77.88861,-7.97139],"type":"Point"}
}