{
  "type": "Feature",
  "properties": {
    "gn:admin1_code":"9.0",
    "gn:admin2_code":"905.0",
    "gn:admin3_code":"90502.0",
    "gn:asciiname":"Machaycuchu",
    "gn:country_code":"PE",
    "gn:dem":4094,
    "gn:feature_class":"P",
    "gn:feature_code":"PPL",
    "gn:name":"Machaycuchu",
    "gn:population":0,
    "gn:timezone":"America/Lima",
    "iso:country":"PE",
    "wof:name":"Machaycuchu",
    "wof:placetype":"locality"
},
  "geometry": {"coordinates":[-74.53907,-12.59494],"type":"Point"}
}