{
  "type": "Feature",
  "properties": {
    "gn:admin1_code":"21",
    "gn:admin2_code":"2110.0",
    "gn:admin3_code":"211003.0",
    "gn:asciiname":"Vizachane",
    "gn:country_code":"PE",
    "gn:dem":3871,
    "gn:feature_class":"P",
    "gn:feature_code":"PPL",
    "gn:name":"Vizachane",
    "gn:population":0,
    "gn:timezone":"America/Lima",
    "iso:country":"PE",
    "wof:name":"Vizachane",
    "wof:placetype":"locality"
},
  "geometry": {"coordinates":[-69.90298,-15.04255],"type":"Point"}
}