{
  "type": "Feature",
  "properties": {
    "gn:admin1_code":"11",
    "gn:admin2_code":"1105.0",
    "gn:admin3_code":"110504.0",
    "gn:asciiname":"Lima La Vieja",
    "gn:country_code":"PE",
    "gn:dem":356,
    "gn:feature_class":"P",
    "gn:feature_code":"PPL",
    "gn:name":"Lima La Vieja",
    "gn:population":0,
    "gn:timezone":"America/Lima",
    "iso:country":"PE",
    "name:spa_x_preferred":[
        "Lima La Vieja"
    ],
    "name:spa_x_variant":[
        "Lima Vieja"
    ],
    "wof:name":"Lima La Vieja",
    "wof:placetype":"locality"
},
  "geometry": {"coordinates":[-75.94382,-13.72535],"type":"Point"}
}