{
  "type": "Feature",
  "properties": {
    "gn:admin1_code":"21",
    "gn:admin2_code":"2112.0",
    "gn:admin3_code":"211210.0",
    "gn:asciiname":"Pampas de Moho",
    "gn:country_code":"PE",
    "gn:dem":1110,
    "gn:feature_class":"P",
    "gn:feature_code":"PPL",
    "gn:name":"Pampas de Moho",
    "gn:population":0,
    "gn:timezone":"America/Lima",
    "iso:country":"PE",
    "name:spa_x_preferred":[
        "Pampas de Moho"
    ],
    "wof:name":"Pampas de Moho",
    "wof:placetype":"locality"
},
  "geometry": {"coordinates":[-68.96796999999999,-14.09148],"type":"Point"}
}