{
  "type": "Feature",
  "properties": {
    "gn:admin1_code":"12.0",
    "gn:admin2_code":"1206.0",
    "gn:admin3_code":"120601.0",
    "gn:asciiname":"Shimongani",
    "gn:country_code":"PE",
    "gn:dem":1239,
    "gn:feature_class":"P",
    "gn:feature_code":"PPL",
    "gn:name":"Shimongani",
    "gn:population":0,
    "gn:timezone":"America/Lima",
    "iso:country":"PE",
    "wof:name":"Shimongani",
    "wof:placetype":"locality"
},
  "geometry": {"coordinates":[-74.46023000000002,-11.07854],"type":"Point"}
}