{
  "type": "Feature",
  "properties": {
    "gn:admin1_code":"9.0",
    "gn:admin2_code":"901.0",
    "gn:admin3_code":"90106.0",
    "gn:asciiname":"Tangana",
    "gn:country_code":"PE",
    "gn:dem":4672,
    "gn:feature_class":"P",
    "gn:feature_code":"PPL",
    "gn:name":"Tangana",
    "gn:population":0,
    "gn:timezone":"America/Lima",
    "iso:country":"PE",
    "wof:name":"Tangana",
    "wof:placetype":"locality"
},
  "geometry": {"coordinates":[-74.99800999999999,-13.01548],"type":"Point"}
}