{
  "type": "Feature",
  "properties": {
    "gn:admin1_code":"09",
    "gn:admin2_code":"905.0",
    "gn:admin3_code":"90502.0",
    "gn:asciiname":"La Esmeralda",
    "gn:cc2":"PE",
    "gn:country_code":"PE",
    "gn:dem":3427,
    "gn:feature_class":"P",
    "gn:feature_code":"PPLA3",
    "gn:name":"La Esmeralda",
    "gn:population":0,
    "gn:timezone":"America/Lima",
    "iso:country":"PE",
    "name:und_x_variant":[
        "Anco",
        "La Esmeralda"
    ],
    "wof:name":"La Esmeralda",
    "wof:placetype":"locality"
},
  "geometry": {"coordinates":[-74.59999999999999,-12.63333],"type":"Point"}
}