{
  "type": "Feature",
  "properties": {
    "gn:admin1_code":"09",
    "gn:admin2_code":"905.0",
    "gn:admin3_code":"90502.0",
    "gn:asciiname":"La Esmeralda",
    "gn:cc2":"PE",
    "gn:country_code":"PE",
    "gn:dem":3427,
    "gn:feature_class":"P",
    "gn:feature_code":"PPLA3",
    "gn:name":"La Esmeralda",
    "gn:population":0,
    "gn:timezone":"America/Lima",
    "iso:country":"PE",
    "name:ceb_x_preferred":[
        "La Esmeralda"
    ],
    "name:deu_x_preferred":[
        "La Esmeralda"
    ],
    "name:ita_x_preferred":[
        "La Esmeralda"
    ],
    "name:sco_x_preferred":[
        "La Esmeralda"
    ],
    "name:spa_x_preferred":[
        "La Esmeralda"
    ],
    "name:srp_x_preferred":[
        "\u041b\u0430 \u0415\u0441\u043c\u0435\u0440\u0430\u043b\u0434\u0430"
    ],
    "name:swe_x_preferred":[
        "La Esmeralda"
    ],
    "name:und_x_variant":[
        "Anco"
    ],
    "wof:name":"La Esmeralda",
    "wof:placetype":"locality"
},
  "geometry": {"coordinates":[-74.59999999999999,-12.63333],"type":"Point"}
}