{
  "type": "Feature",
  "properties": {
    "gn:admin1_code":"22.0",
    "gn:admin2_code":"2210.0",
    "gn:admin3_code":"221005.0",
    "gn:asciiname":"Cruzpampa",
    "gn:country_code":"PE",
    "gn:dem":524,
    "gn:feature_class":"P",
    "gn:feature_code":"PPL",
    "gn:name":"Cruzpampa",
    "gn:population":0,
    "gn:timezone":"America/Lima",
    "iso:country":"PE",
    "wof:name":"Cruzpampa",
    "wof:placetype":"locality"
},
  "geometry": {"coordinates":[-76.44009,-8.43123],"type":"Point"}
}