{
  "type": "Feature",
  "properties": {
    "gn:admin1_code":"06",
    "gn:admin2_code":"603.0",
    "gn:admin3_code":"60304.0",
    "gn:asciiname":"Olorongo",
    "gn:country_code":"PE",
    "gn:dem":2205,
    "gn:feature_class":"P",
    "gn:feature_code":"PPL",
    "gn:name":"Olorongo",
    "gn:population":0,
    "gn:timezone":"America/Lima",
    "iso:country":"PE",
    "wof:name":"Olorongo",
    "wof:placetype":"locality"
},
  "geometry": {"coordinates":[-78.26430000000001,-6.84512],"type":"Point"}
}