{
  "type": "Feature",
  "properties": {
    "gn:admin1_code":"08",
    "gn:admin2_code":"808.0",
    "gn:admin3_code":"80807.0",
    "gn:asciiname":"Munja",
    "gn:country_code":"PE",
    "gn:dem":4316,
    "gn:feature_class":"P",
    "gn:feature_code":"PPL",
    "gn:name":"Munja",
    "gn:population":0,
    "gn:timezone":"America/Lima",
    "iso:country":"PE",
    "name:und_x_variant":[
        "Munia",
        "Munja"
    ],
    "wof:name":"Munja",
    "wof:placetype":"locality"
},
  "geometry": {"coordinates":[-71.54001,-15.03456],"type":"Point"}
}