{
  "type": "Feature",
  "properties": {
    "gn:admin1_code":"21",
    "gn:admin2_code":"2103",
    "gn:asciiname":"Draga Pampa",
    "gn:country_code":"PE",
    "gn:dem":1159,
    "gn:feature_class":"P",
    "gn:feature_code":"PPL",
    "gn:name":"Draga Pampa",
    "gn:population":0,
    "gn:timezone":"America/Lima",
    "iso:country":"PE",
    "name:spa_x_preferred":[
        "Draga Pampa"
    ],
    "wof:name":"Draga Pampa",
    "wof:placetype":"locality"
},
  "geometry": {"coordinates":[-69.79770000000001,-13.74874],"type":"Point"}
}