{
  "type": "Feature",
  "properties": {
    "gn:admin1_code":"15",
    "gn:admin2_code":"1506.0",
    "gn:admin3_code":"150606.0",
    "gn:asciiname":"Otec",
    "gn:cc2":"PE",
    "gn:country_code":"PE",
    "gn:dem":3266,
    "gn:feature_class":"P",
    "gn:feature_code":"PPL",
    "gn:name":"Otec",
    "gn:population":0,
    "gn:timezone":"America/Lima",
    "iso:country":"PE",
    "name:und_x_variant":[
        "Otac",
        "Otec"
    ],
    "wof:name":"Otec",
    "wof:placetype":"locality"
},
  "geometry": {"coordinates":[-76.90639,-11.17639],"type":"Point"}
}