{
  "type": "Feature",
  "properties": {
    "gn:admin1_code":"15.0",
    "gn:admin2_code":"1504.0",
    "gn:admin3_code":"150402.0",
    "gn:asciiname":"Culluy",
    "gn:country_code":"PE",
    "gn:dem":4141,
    "gn:feature_class":"P",
    "gn:feature_code":"PPL",
    "gn:name":"Culluy",
    "gn:population":0,
    "gn:timezone":"America/Lima",
    "iso:country":"PE",
    "name:spa_x_preferred":[
        "Culluy"
    ],
    "wof:name":"Culluy",
    "wof:placetype":"locality"
},
  "geometry": {"coordinates":[-76.61434,-11.61492],"type":"Point"}
}