{
  "type": "Feature",
  "properties": {
    "gn:admin1_code":"20",
    "gn:admin2_code":"2001.0",
    "gn:admin3_code":"200101.0",
    "gn:asciiname":"La Palma",
    "gn:country_code":"PE",
    "gn:dem":50,
    "gn:feature_class":"P",
    "gn:feature_code":"PPL",
    "gn:name":"La Palma",
    "gn:population":0,
    "gn:timezone":"America/Lima",
    "iso:country":"PE",
    "name:und_x_variant":[
        "La Palma Hacienda",
        "La Palma"
    ],
    "wof:name":"La Palma",
    "wof:placetype":"locality"
},
  "geometry": {"coordinates":[-80.63929,-5.10459],"type":"Point"}
}