{
  "type": "Feature",
  "properties": {
    "gn:admin1_code":"19",
    "gn:admin2_code":"1901.0",
    "gn:admin3_code":"190106.0",
    "gn:asciiname":"La Curva",
    "gn:country_code":"PE",
    "gn:dem":3181,
    "gn:feature_class":"P",
    "gn:feature_code":"PPL",
    "gn:name":"La Curva",
    "gn:population":0,
    "gn:timezone":"America/Lima",
    "iso:country":"PE",
    "wof:name":"La Curva",
    "wof:placetype":"locality"
},
  "geometry": {"coordinates":[-76.23595999999998,-10.42596],"type":"Point"}
}