{
  "type": "Feature",
  "properties": {
    "gn:admin1_code":"4",
    "gn:admin2_code":"404.0",
    "gn:admin3_code":"40404.0",
    "gn:asciiname":"Corralnioc",
    "gn:country_code":"PE",
    "gn:dem":4323,
    "gn:feature_class":"P",
    "gn:feature_code":"PPL",
    "gn:name":"Corralnioc",
    "gn:population":0,
    "gn:timezone":"America/Lima",
    "iso:country":"PE",
    "wof:name":"Corralnioc",
    "wof:placetype":"locality"
},
  "geometry": {"coordinates":[-71.97744,-14.91152],"type":"Point"}
}