{
  "type": "Feature",
  "properties": {
    "gn:admin1_code":"04",
    "gn:admin2_code":"401.0",
    "gn:admin3_code":"40119.0",
    "gn:asciiname":"Pillone",
    "gn:country_code":"PE",
    "gn:dem":4561,
    "gn:feature_class":"P",
    "gn:feature_code":"PPL",
    "gn:name":"Pillone",
    "gn:population":0,
    "gn:timezone":"America/Lima",
    "iso:country":"PE",
    "wof:name":"Pillone",
    "wof:placetype":"locality"
},
  "geometry": {"coordinates":[-70.88807,-16.24278],"type":"Point"}
}