{
  "type": "Feature",
  "properties": {
    "gn:admin1_code":"21",
    "gn:admin2_code":"2107.0",
    "gn:admin3_code":"210702.0",
    "gn:asciiname":"Pasallao",
    "gn:country_code":"PE",
    "gn:dem":4033,
    "gn:feature_class":"P",
    "gn:feature_code":"PPL",
    "gn:name":"Pasallao",
    "gn:population":0,
    "gn:timezone":"America/Lima",
    "iso:country":"PE",
    "wof:name":"Pasallao",
    "wof:placetype":"locality"
},
  "geometry": {"coordinates":[-70.38763,-15.62374],"type":"Point"}
}