{
  "type": "Feature",
  "properties": {
    "gn:admin1_code":"12.0",
    "gn:admin2_code":"1206.0",
    "gn:admin3_code":"120608.0",
    "gn:asciiname":"Selvaverde",
    "gn:country_code":"PE",
    "gn:dem":304,
    "gn:feature_class":"P",
    "gn:feature_code":"PPL",
    "gn:name":"Selvaverde",
    "gn:population":0,
    "gn:timezone":"America/Lima",
    "iso:country":"PE",
    "wof:name":"Selvaverde",
    "wof:placetype":"locality"
},
  "geometry": {"coordinates":[-73.58139,-11.19139],"type":"Point"}
}