{
  "type": "Feature",
  "properties": {
    "gn:admin1_code":"9",
    "gn:admin2_code":"906.0",
    "gn:admin3_code":"90613.0",
    "gn:asciiname":"Tolderayoc",
    "gn:country_code":"PE",
    "gn:dem":3582,
    "gn:feature_class":"P",
    "gn:feature_code":"PPL",
    "gn:name":"Tolderayoc",
    "gn:population":0,
    "gn:timezone":"America/Lima",
    "iso:country":"PE",
    "wof:name":"Tolderayoc",
    "wof:placetype":"locality"
},
  "geometry": {"coordinates":[-75.16861,-13.87833],"type":"Point"}
}