{
  "type": "Feature",
  "properties": {
    "gn:admin1_code":"22.0",
    "gn:admin2_code":"2207.0",
    "gn:admin3_code":"220705.0",
    "gn:asciiname":"Bella Aurora",
    "gn:country_code":"PE",
    "gn:dem":209,
    "gn:feature_class":"P",
    "gn:feature_code":"PPL",
    "gn:name":"Bella Aurora",
    "gn:population":0,
    "gn:timezone":"America/Lima",
    "iso:country":"PE",
    "name:spa_x_preferred":[
        "Bella Aurora"
    ],
    "wof:name":"Bella Aurora",
    "wof:placetype":"locality"
},
  "geometry": {"coordinates":[-76.31676999999998,-6.84796],"type":"Point"}
}