{
  "type": "Feature",
  "properties": {
    "gn:admin1_code":"12.0",
    "gn:admin2_code":"1204.0",
    "gn:admin3_code":"120428.0",
    "gn:asciiname":"Charquihuasi",
    "gn:country_code":"PE",
    "gn:dem":3539,
    "gn:feature_class":"P",
    "gn:feature_code":"PPL",
    "gn:name":"Charquihuasi",
    "gn:population":0,
    "gn:timezone":"America/Lima",
    "iso:country":"PE",
    "wof:name":"Charquihuasi",
    "wof:placetype":"locality"
},
  "geometry": {"coordinates":[-75.36651999999999,-11.81752],"type":"Point"}
}