{
  "type": "Feature",
  "properties": {
    "gn:admin1_code":"22.0",
    "gn:admin2_code":"2202.0",
    "gn:admin3_code":"220203.0",
    "gn:asciiname":"El Encanto",
    "gn:country_code":"PE",
    "gn:dem":246,
    "gn:feature_class":"P",
    "gn:feature_code":"PPL",
    "gn:name":"El Encanto",
    "gn:population":0,
    "gn:timezone":"America/Lima",
    "iso:country":"PE",
    "name:spa_x_preferred":[
        "El Encanto"
    ],
    "wof:name":"El Encanto",
    "wof:placetype":"locality"
},
  "geometry": {"coordinates":[-76.50466,-7.14258],"type":"Point"}
}