{
  "type": "Feature",
  "properties": {
    "gn:admin1_code":"9",
    "gn:admin2_code":"906.0",
    "gn:admin3_code":"90613.0",
    "gn:asciiname":"Chugrapucro",
    "gn:country_code":"PE",
    "gn:dem":3891,
    "gn:feature_class":"P",
    "gn:feature_code":"PPL",
    "gn:name":"Chugrapucro",
    "gn:population":0,
    "gn:timezone":"America/Lima",
    "iso:country":"PE",
    "wof:name":"Chugrapucro",
    "wof:placetype":"locality"
},
  "geometry": {"coordinates":[-75.12472,-13.72833],"type":"Point"}
}