{
  "type": "Feature",
  "properties": {
    "gn:admin1_code":"20",
    "gn:admin2_code":"2003.0",
    "gn:admin3_code":"200308.0",
    "gn:asciiname":"Mitopampa",
    "gn:country_code":"PE",
    "gn:dem":2738,
    "gn:feature_class":"P",
    "gn:feature_code":"PPLL",
    "gn:name":"Mitopampa",
    "gn:population":0,
    "gn:timezone":"America/Lima",
    "iso:country":"PE",
    "wof:name":"Mitopampa",
    "wof:placetype":"locality"
},
  "geometry": {"coordinates":[-79.48034,-5.3304],"type":"Point"}
}