{
  "type": "Feature",
  "properties": {
    "gn:admin1_code":"24",
    "gn:admin2_code":"2403.0",
    "gn:admin3_code":"240303.0",
    "gn:asciiname":"Puesto Condor Flores",
    "gn:country_code":"PE",
    "gn:dem":291,
    "gn:feature_class":"P",
    "gn:feature_code":"PPL",
    "gn:name":"Puesto C\u00f3ndor Flores",
    "gn:population":0,
    "gn:timezone":"America/Lima",
    "iso:country":"PE",
    "wof:name":"Puesto Condor Flores",
    "wof:placetype":"locality"
},
  "geometry": {"coordinates":[-80.13279,-3.89111],"type":"Point"}
}