{
  "type": "Feature",
  "properties": {
    "gn:admin1_code":"21",
    "gn:admin2_code":"2102.0",
    "gn:admin3_code":"210211.0",
    "gn:asciiname":"San Anton",
    "gn:country_code":"PE",
    "gn:dem":3969,
    "gn:feature_class":"P",
    "gn:feature_code":"PPL",
    "gn:name":"San Ant\u00f3n",
    "gn:population":0,
    "gn:timezone":"America/Lima",
    "iso:country":"PE",
    "name:kat_x_preferred":[
        "\u10e1\u10d0\u10dc-\u10d0\u10dc\u10e2\u10dd\u10dc\u10d8\u10e1 \u10e0\u10d0\u10d8\u10dd\u10dc\u10d8"
    ],
    "name:por_x_preferred":[
        "San Ant\u00f3n"
    ],
    "name:que_x_preferred":[
        "San Antun distritu"
    ],
    "name:und_x_variant":[
        "San Ant\u00f3n"
    ],
    "name:zho_x_preferred":[
        "\u8056\u5b89\u901a\u5340"
    ],
    "wof:name":"San Anton",
    "wof:placetype":"locality"
},
  "geometry": {"coordinates":[-70.31229,-14.59188],"type":"Point"}
}