{
  "type": "Feature",
  "properties": {
    "gn:admin1_code":"6.0",
    "gn:admin2_code":"605.0",
    "gn:admin3_code":"60503.0",
    "gn:asciiname":"El Puquio",
    "gn:country_code":"PE",
    "gn:dem":2059,
    "gn:feature_class":"P",
    "gn:feature_code":"PPL",
    "gn:name":"El Puquio",
    "gn:population":0,
    "gn:timezone":"America/Lima",
    "iso:country":"PE",
    "name:spa_x_preferred":[
        "El Puquio"
    ],
    "wof:name":"El Puquio",
    "wof:placetype":"locality"
},
  "geometry": {"coordinates":[-79.02065,-7.33046],"type":"Point"}
}