{
  "type": "Feature",
  "properties": {
    "gn:admin1_code":"22",
    "gn:admin2_code":"2207.0",
    "gn:admin3_code":"220706.0",
    "gn:asciiname":"Puerto Rico",
    "gn:cc2":"PE",
    "gn:country_code":"PE",
    "gn:dem":232,
    "gn:feature_class":"P",
    "gn:feature_code":"PPLA3",
    "gn:name":"Puerto Rico",
    "gn:population":0,
    "gn:timezone":"America/Lima",
    "iso:country":"PE",
    "name:und_x_variant":[
        "Esperanza",
        "Puerto Rico"
    ],
    "wof:name":"Puerto Rico",
    "wof:placetype":"locality"
},
  "geometry": {"coordinates":[-76.41916999999999,-6.99222],"type":"Point"}
}