{
  "type": "Feature",
  "properties": {
    "gn:admin1_code":"05",
    "gn:admin2_code":"507.0",
    "gn:admin3_code":"50706.0",
    "gn:asciiname":"Molino",
    "gn:country_code":"PE",
    "gn:dem":3200,
    "gn:feature_class":"P",
    "gn:feature_code":"PPL",
    "gn:name":"Molino",
    "gn:population":0,
    "gn:timezone":"America/Lima",
    "iso:country":"PE",
    "wof:name":"Molino",
    "wof:placetype":"locality"
},
  "geometry": {"coordinates":[-73.55,-15.25],"type":"Point"}
}