{
  "type": "Feature",
  "properties": {
    "gn:admin1_code":"12.0",
    "gn:admin2_code":"1203.0",
    "gn:admin3_code":"120302.0",
    "gn:asciiname":"San Roman",
    "gn:country_code":"PE",
    "gn:dem":1231,
    "gn:feature_class":"P",
    "gn:feature_code":"PPL",
    "gn:name":"San Rom\u00e1n",
    "gn:population":0,
    "gn:timezone":"America/Lima",
    "iso:country":"PE",
    "name:spa_x_preferred":[
        "San Rom\u00e1n"
    ],
    "wof:name":"San Roman",
    "wof:placetype":"locality"
},
  "geometry": {"coordinates":[-75.05631,-10.84008],"type":"Point"}
}