{
  "type": "Feature",
  "properties": {
    "gn:admin1_code":"06",
    "gn:admin2_code":"606.0",
    "gn:admin3_code":"60602.0",
    "gn:asciiname":"Hacienda Queromarca",
    "gn:country_code":"PE",
    "gn:dem":1871,
    "gn:feature_class":"P",
    "gn:feature_code":"PPL",
    "gn:name":"Hacienda Queromarca",
    "gn:population":0,
    "gn:timezone":"America/Lima",
    "iso:country":"PE",
    "wof:name":"Hacienda Queromarca",
    "wof:placetype":"locality"
},
  "geometry": {"coordinates":[-79.00954,-6.08803],"type":"Point"}
}