{
  "type": "Feature",
  "properties": {
    "gn:admin1_code":"13",
    "gn:admin2_code":"1309.0",
    "gn:admin3_code":"130902.0",
    "gn:asciiname":"Llucurque",
    "gn:country_code":"PE",
    "gn:dem":2748,
    "gn:feature_class":"P",
    "gn:feature_code":"PPL",
    "gn:name":"Llucurque",
    "gn:population":0,
    "gn:timezone":"America/Lima",
    "iso:country":"PE",
    "wof:name":"Llucurque",
    "wof:placetype":"locality"
},
  "geometry": {"coordinates":[-77.87863,-7.84179],"type":"Point"}
}