{
  "type": "Feature",
  "properties": {
    "gn:admin1_code":"20",
    "gn:admin2_code":"2001.0",
    "gn:admin3_code":"200105.0",
    "gn:asciiname":"La Legua",
    "gn:country_code":"PE",
    "gn:dem":28,
    "gn:feature_class":"P",
    "gn:feature_code":"PPL",
    "gn:name":"La Legua",
    "gn:population":0,
    "gn:timezone":"America/Lima",
    "iso:country":"PE",
    "name:und_x_variant":[
        "La Legua Hacienda",
        "La Legua"
    ],
    "wof:name":"La Legua",
    "wof:placetype":"locality"
},
  "geometry": {"coordinates":[-80.65928000000002,-5.23584],"type":"Point"}
}