{
  "type": "Feature",
  "properties": {
    "gn:admin1_code":"13.0",
    "gn:admin2_code":"1308.0",
    "gn:admin3_code":"130812.0",
    "gn:asciiname":"Huayao",
    "gn:country_code":"PE",
    "gn:dem":2691,
    "gn:feature_class":"P",
    "gn:feature_code":"PPL",
    "gn:name":"Huayao",
    "gn:population":0,
    "gn:timezone":"America/Lima",
    "iso:country":"PE",
    "wof:name":"Huayao",
    "wof:placetype":"locality"
},
  "geometry": {"coordinates":[-77.44917,-8.29444],"type":"Point"}
}