{
  "type": "Feature",
  "properties": {
    "gn:admin1_code":"10.0",
    "gn:admin2_code":"1001.0",
    "gn:admin3_code":"100105.0",
    "gn:asciiname":"Paltacalan",
    "gn:country_code":"PE",
    "gn:dem":4115,
    "gn:feature_class":"P",
    "gn:feature_code":"PPL",
    "gn:name":"Paltacal\u00e1n",
    "gn:population":0,
    "gn:timezone":"America/Lima",
    "iso:country":"PE",
    "wof:name":"Paltacalan",
    "wof:placetype":"locality"
},
  "geometry": {"coordinates":[-76.51583000000002,-10.11111],"type":"Point"}
}