{
  "type": "Feature",
  "properties": {
    "gn:admin1_code":"22.0",
    "gn:admin2_code":"2207.0",
    "gn:admin3_code":"220707.0",
    "gn:asciiname":"Chimbote",
    "gn:country_code":"PE",
    "gn:dem":280,
    "gn:feature_class":"P",
    "gn:feature_code":"PPL",
    "gn:name":"Chimbote",
    "gn:population":0,
    "gn:timezone":"America/Lima",
    "iso:country":"PE",
    "name:spa_x_preferred":[
        "Chimbote"
    ],
    "wof:name":"Chimbote",
    "wof:placetype":"locality"
},
  "geometry": {"coordinates":[-76.52426,-6.94715],"type":"Point"}
}