{
  "type": "Feature",
  "properties": {
    "gn:admin1_code":"09",
    "gn:admin2_code":"904.0",
    "gn:admin3_code":"90401.0",
    "gn:asciiname":"Rupahuasi",
    "gn:country_code":"PE",
    "gn:dem":3908,
    "gn:feature_class":"P",
    "gn:feature_code":"PPL",
    "gn:name":"Rupahuasi",
    "gn:population":0,
    "gn:timezone":"America/Lima",
    "iso:country":"PE",
    "wof:name":"Rupahuasi",
    "wof:placetype":"locality"
},
  "geometry": {"coordinates":[-75.34599,-13.19648],"type":"Point"}
}