{
  "type": "Feature",
  "properties": {
    "gn:admin1_code":"12.0",
    "gn:admin2_code":"1208.0",
    "gn:admin3_code":"120807.0",
    "gn:asciiname":"Piticocha",
    "gn:country_code":"PE",
    "gn:dem":4481,
    "gn:feature_class":"P",
    "gn:feature_code":"PPL",
    "gn:name":"Piticocha",
    "gn:population":0,
    "gn:timezone":"America/Lima",
    "iso:country":"PE",
    "wof:name":"Piticocha",
    "wof:placetype":"locality"
},
  "geometry": {"coordinates":[-76.29025,-11.16466],"type":"Point"}
}