{
  "type": "Feature",
  "properties": {
    "gn:admin1_code":"12",
    "gn:admin2_code":"1204.0",
    "gn:admin3_code":"120432.0",
    "gn:asciiname":"Concho",
    "gn:country_code":"PE",
    "gn:dem":3473,
    "gn:feature_class":"P",
    "gn:feature_code":"PPLA3",
    "gn:name":"Concho",
    "gn:population":0,
    "gn:timezone":"America/Lima",
    "iso:country":"PE",
    "name:und_x_variant":[
        "Cconcho",
        "Concho"
    ],
    "wof:name":"Concho",
    "wof:placetype":"locality"
},
  "geometry": {"coordinates":[-75.57086,-11.72503],"type":"Point"}
}