{
  "type": "Feature",
  "properties": {
    "gn:admin1_code":"5",
    "gn:admin2_code":"507.0",
    "gn:admin3_code":"50705.0",
    "gn:asciiname":"Aichune",
    "gn:country_code":"PE",
    "gn:dem":1947,
    "gn:feature_class":"P",
    "gn:feature_code":"PPL",
    "gn:name":"Aichune",
    "gn:population":0,
    "gn:timezone":"America/Lima",
    "iso:country":"PE",
    "name:spa_x_preferred":[
        "Aichune"
    ],
    "wof:name":"Aichune",
    "wof:placetype":"locality"
},
  "geometry": {"coordinates":[-74.01918000000001,-15.51581],"type":"Point"}
}