{
  "type": "Feature",
  "properties": {
    "gn:admin1_code":"10.0",
    "gn:admin2_code":"1005.0",
    "gn:admin3_code":"100501.0",
    "gn:asciiname":"Irma Grande",
    "gn:country_code":"PE",
    "gn:dem":3499,
    "gn:feature_class":"P",
    "gn:feature_code":"PPL",
    "gn:name":"Irma Grande",
    "gn:population":0,
    "gn:timezone":"America/Lima",
    "iso:country":"PE",
    "wof:name":"Irma Grande",
    "wof:placetype":"locality"
},
  "geometry": {"coordinates":[-76.75919,-9.60097],"type":"Point"}
}