{
  "type": "Feature",
  "properties": {
    "gn:admin1_code":"23",
    "gn:admin2_code":"2302.0",
    "gn:admin3_code":"230201.0",
    "gn:asciiname":"Patapatani",
    "gn:country_code":"PE",
    "gn:dem":3743,
    "gn:feature_class":"P",
    "gn:feature_code":"PPL",
    "gn:name":"Patapatani",
    "gn:population":0,
    "gn:timezone":"America/Lima",
    "iso:country":"PE",
    "name:zho_x_preferred":[
        "\u5e15\u5854\u5e15\u5854\u5c3c\u5c71"
    ],
    "wof:name":"Patapatani",
    "wof:placetype":"locality"
},
  "geometry": {"coordinates":[-70.25891,-17.23546],"type":"Point"}
}