{
  "type": "Feature",
  "properties": {
    "iso:country":"PE",
    "name:aym_x_preferred":[
        "Saband\u00eda jisk'a t'aqa suyu"
    ],
    "name:ita_x_preferred":[
        "Distretto di Saband\u00eda"
    ],
    "name:kat_x_preferred":[
        "\u10e1\u10d0\u10d1\u10d0\u10dc\u10d3\u10d8\u10d8\u10e1 \u10e0\u10d0\u10d8\u10dd\u10dc\u10d8"
    ],
    "name:nor_x_preferred":[
        "Saband\u00eda"
    ],
    "name:por_x_preferred":[
        "Saband\u00eda"
    ],
    "name:que_x_preferred":[
        "Saband\u00eda distritu"
    ],
    "name:spa_x_preferred":[
        "Distrito de Saband\u00eda"
    ],
    "name:urd_x_preferred":[
        "\u0633\u0628\u0646\u062f\u06c1 \u0636\u0644\u0639"
    ],
    "name:zho_x_preferred":[
        "\u85a9\u73ed\u8fea\u4e9e\u5340"
    ],
    "qs:gn_pop":0,
    "qs:name":"Sabandia",
    "qs:name_adm0":"Per\u00fa",
    "qs:name_adm1":"Arequipa",
    "qs:photos":90,
    "qs:photos_1k":18,
    "qs:photos_9k":1,
    "qs:photos_9r":3,
    "qs:photos_all":90,
    "qs:photos_sr":3,
    "qs:placetype":"Town",
    "qs:pop_sr":"0",
    "qs:woe_adm0":23424919,
    "wof:name":"Sabandia",
    "wof:placetype":"locality"
},
  "geometry": {"coordinates":[-71.4997535,-16.453787],"type":"Point"}
}