{
  "type": "Feature",
  "properties": {
    "gn:admin1_code":"15.0",
    "gn:admin2_code":"1506.0",
    "gn:admin3_code":"150604.0",
    "gn:asciiname":"Huaca Chica",
    "gn:country_code":"PE",
    "gn:dem":151,
    "gn:feature_class":"P",
    "gn:feature_code":"PPL",
    "gn:name":"Huaca Chica",
    "gn:population":0,
    "gn:timezone":"America/Lima",
    "iso:country":"PE",
    "name:spa_x_preferred":[
        "Huaca Chica"
    ],
    "wof:name":"Huaca Chica",
    "wof:placetype":"locality"
},
  "geometry": {"coordinates":[-77.17917,-11.54983],"type":"Point"}
}