{
  "type": "Feature",
  "properties": {
    "gn:admin1_code":"12",
    "gn:admin2_code":"1206.0",
    "gn:admin3_code":"120606.0",
    "gn:asciiname":"Mazaronquiari",
    "gn:country_code":"PE",
    "gn:dem":1230,
    "gn:feature_class":"P",
    "gn:feature_code":"PPL",
    "gn:name":"Mazaronquiari",
    "gn:population":0,
    "gn:timezone":"America/Lima",
    "iso:country":"PE",
    "wof:name":"Mazaronquiari",
    "wof:placetype":"locality"
},
  "geometry": {"coordinates":[-74.36881,-11.64848],"type":"Point"}
}