{
  "type": "Feature",
  "properties": {
    "gn:admin1_code":"08",
    "gn:admin2_code":"803.0",
    "gn:admin3_code":"80304.0",
    "gn:asciiname":"Rocoto",
    "gn:country_code":"PE",
    "gn:dem":3147,
    "gn:feature_class":"P",
    "gn:feature_code":"PPL",
    "gn:name":"Rocoto",
    "gn:population":0,
    "gn:timezone":"America/Lima",
    "iso:country":"PE",
    "name:und_x_variant":[
        "Rocoto Hacienda",
        "Rocoto"
    ],
    "wof:name":"Rocoto",
    "wof:placetype":"locality"
},
  "geometry": {"coordinates":[-72.32222,-13.67556],"type":"Point"}
}