{
  "type": "Feature",
  "properties": {
    "gn:admin1_code":"4",
    "gn:admin2_code":"406.0",
    "gn:admin3_code":"40608.0",
    "gn:asciiname":"Chilcane",
    "gn:country_code":"PE",
    "gn:dem":3266,
    "gn:feature_class":"P",
    "gn:feature_code":"PPL",
    "gn:name":"Chilcane",
    "gn:population":0,
    "gn:timezone":"America/Lima",
    "iso:country":"PE",
    "wof:name":"Chilcane",
    "wof:placetype":"locality"
},
  "geometry": {"coordinates":[-72.93585999999998,-15.70187],"type":"Point"}
}