{
  "type": "Feature",
  "properties": {
    "gn:admin1_code":"16",
    "gn:admin2_code":"1606.0",
    "gn:admin3_code":"160601.0",
    "gn:asciiname":"Puerto Cashiboya",
    "gn:country_code":"PE",
    "gn:dem":160,
    "gn:feature_class":"P",
    "gn:feature_code":"PPL",
    "gn:name":"Puerto Cashiboya",
    "gn:population":0,
    "gn:timezone":"America/Lima",
    "iso:country":"PE",
    "wof:name":"Puerto Cashiboya",
    "wof:placetype":"locality"
},
  "geometry": {"coordinates":[-74.93333,-7.43333],"type":"Point"}
}