{
  "type": "Feature",
  "properties": {
    "gn:admin1_code":"15",
    "gn:admin2_code":"1508.0",
    "gn:admin3_code":"150804.0",
    "gn:asciiname":"Lagsaura",
    "gn:country_code":"PE",
    "gn:dem":2257,
    "gn:feature_class":"P",
    "gn:feature_code":"PPL",
    "gn:name":"Lagsaura",
    "gn:population":0,
    "gn:timezone":"America/Lima",
    "iso:country":"PE",
    "name:und_x_variant":[
        "Lacsaura",
        "Laczaura",
        "Lagsaura"
    ],
    "wof:name":"Lagsaura",
    "wof:placetype":"locality"
},
  "geometry": {"coordinates":[-76.86458,-10.86706],"type":"Point"}
}