{
  "type": "Feature",
  "properties": {
    "iso:country":"PE",
    "name:unk_x_variant":[
        "Santa Rosa Hacienda"
    ],
    "qs:gn_country":"PE",
    "qs:gn_fcode":"PPL",
    "qs:gn_pop":10625,
    "qs:name":"Santa Rosa",
    "qs:name_adm0":"Per\u00fa",
    "qs:name_adm1":"Lambayeque",
    "qs:photos":133,
    "qs:photos_1k":27,
    "qs:photos_9k":1,
    "qs:photos_9r":3,
    "qs:photos_all":133,
    "qs:photos_sr":3,
    "qs:placetype":"Town",
    "qs:pop_sr":"6",
    "qs:woe_adm0":23424919,
    "wof:name":"Santa Rosa",
    "wof:placetype":"locality",
    "wof:population":10625
},
  "geometry": {"coordinates":[-79.83333,-6.76667],"type":"Point"}
}