{
  "type": "Feature",
  "properties": {
    "gn:admin1_code":"21",
    "gn:admin2_code":"2106.0",
    "gn:admin3_code":"210601.0",
    "gn:asciiname":"Isancuyomunaypa",
    "gn:country_code":"PE",
    "gn:dem":3857,
    "gn:feature_class":"P",
    "gn:feature_code":"PPL",
    "gn:name":"Isancuyomunaypa",
    "gn:population":0,
    "gn:timezone":"America/Lima",
    "iso:country":"PE",
    "wof:name":"Isancuyomunaypa",
    "wof:placetype":"locality"
},
  "geometry": {"coordinates":[-69.75285,-15.15846],"type":"Point"}
}