{
  "type": "Feature",
  "properties": {
    "gn:admin1_code":"13",
    "gn:admin2_code":"1306.0",
    "gn:admin3_code":"130613.0",
    "gn:asciiname":"Quirripe",
    "gn:country_code":"PE",
    "gn:dem":972,
    "gn:feature_class":"P",
    "gn:feature_code":"PPL",
    "gn:name":"Quirripe",
    "gn:population":0,
    "gn:timezone":"America/Lima",
    "iso:country":"PE",
    "name:und_x_variant":[
        "Hacienda Quirripe",
        "Quirripe Hacienda",
        "Quirripe"
    ],
    "wof:name":"Quirripe",
    "wof:placetype":"locality"
},
  "geometry": {"coordinates":[-78.8259,-7.71478],"type":"Point"}
}