{
  "type": "Feature",
  "properties": {
    "gn:admin1_code":"14",
    "gn:admin2_code":"1403.0",
    "gn:admin3_code":"140308.0",
    "gn:asciiname":"Noria de Pan de Azucar",
    "gn:country_code":"PE",
    "gn:dem":94,
    "gn:feature_class":"P",
    "gn:feature_code":"PPL",
    "gn:name":"Noria de Pan de Az\u00facar",
    "gn:population":0,
    "gn:timezone":"America/Lima",
    "iso:country":"PE",
    "wof:name":"Noria de Pan de Azucar",
    "wof:placetype":"locality"
},
  "geometry": {"coordinates":[-79.95,-6.03333],"type":"Point"}
}