{
  "type": "Feature",
  "properties": {
    "gn:admin1_code":"4",
    "gn:admin2_code":"405.0",
    "gn:admin3_code":"40504.0",
    "gn:asciiname":"Amayamaya",
    "gn:country_code":"PE",
    "gn:dem":4210,
    "gn:feature_class":"P",
    "gn:feature_code":"PPL",
    "gn:name":"Amayamaya",
    "gn:population":0,
    "gn:timezone":"America/Lima",
    "iso:country":"PE",
    "wof:name":"Amayamaya",
    "wof:placetype":"locality"
},
  "geometry": {"coordinates":[-71.31196,-15.56364],"type":"Point"}
}