{
  "type": "Feature",
  "properties": {
    "gn:admin1_code":"10.0",
    "gn:admin2_code":"1010.0",
    "gn:admin3_code":"101006.0",
    "gn:asciiname":"Churin",
    "gn:country_code":"PE",
    "gn:dem":3578,
    "gn:feature_class":"P",
    "gn:feature_code":"PPL",
    "gn:name":"Churin",
    "gn:population":0,
    "gn:timezone":"America/Lima",
    "iso:country":"PE",
    "name:spa_x_preferred":[
        "Chur\u00edn"
    ],
    "wof:name":"Churin",
    "wof:placetype":"locality"
},
  "geometry": {"coordinates":[-76.63887,-9.97146],"type":"Point"}
}