{
  "type": "Feature",
  "properties": {
    "gn:admin1_code":"15.0",
    "gn:admin2_code":"1504.0",
    "gn:admin3_code":"150404.0",
    "gn:asciiname":"Chuncal",
    "gn:country_code":"PE",
    "gn:dem":4295,
    "gn:feature_class":"P",
    "gn:feature_code":"PPL",
    "gn:name":"Chuncal",
    "gn:population":0,
    "gn:timezone":"America/Lima",
    "iso:country":"PE",
    "wof:name":"Chuncal",
    "wof:placetype":"locality"
},
  "geometry": {"coordinates":[-76.46451999999999,-11.37332],"type":"Point"}
}