{
  "type": "Feature",
  "properties": {
    "gn:admin1_code":"5.0",
    "gn:admin2_code":"501.0",
    "gn:admin3_code":"50113.0",
    "gn:asciiname":"Ticcahuasi",
    "gn:country_code":"PE",
    "gn:dem":2967,
    "gn:feature_class":"P",
    "gn:feature_code":"PPL",
    "gn:name":"Ticcahuasi",
    "gn:population":0,
    "gn:timezone":"America/Lima",
    "iso:country":"PE",
    "name:und_x_variant":[
        "Hacienda Ticcahuasi"
    ],
    "wof:name":"Ticcahuasi",
    "wof:placetype":"locality"
},
  "geometry": {"coordinates":[-74.12435000000001,-13.19229],"type":"Point"}
}