{
  "type": "Feature",
  "properties": {
    "gn:admin1_code":"8.0",
    "gn:admin2_code":"804.0",
    "gn:admin3_code":"80404.0",
    "gn:asciiname":"Huacahuasi",
    "gn:country_code":"PE",
    "gn:dem":3814,
    "gn:feature_class":"P",
    "gn:feature_code":"PPL",
    "gn:name":"Huacahuasi",
    "gn:population":0,
    "gn:timezone":"America/Lima",
    "iso:country":"PE",
    "wof:name":"Huacahuasi",
    "wof:placetype":"locality"
},
  "geometry": {"coordinates":[-72.10722,-13.13917],"type":"Point"}
}