{
  "type": "Feature",
  "properties": {
    "gn:admin1_code":"10.0",
    "gn:admin2_code":"1011.0",
    "gn:admin3_code":"101101.0",
    "gn:asciiname":"Mashuapata",
    "gn:country_code":"PE",
    "gn:dem":3858,
    "gn:feature_class":"P",
    "gn:feature_code":"PPL",
    "gn:name":"Mashuapata",
    "gn:population":0,
    "gn:timezone":"America/Lima",
    "iso:country":"PE",
    "wof:name":"Mashuapata",
    "wof:placetype":"locality"
},
  "geometry": {"coordinates":[-76.56161999999998,-9.78042],"type":"Point"}
}