{
  "type": "Feature",
  "properties": {
    "gn:admin1_code":"21.0",
    "gn:admin2_code":"2112.0",
    "gn:asciiname":"Massiapo",
    "gn:country_code":"PE",
    "gn:dem":1348,
    "gn:feature_class":"P",
    "gn:feature_code":"PPL",
    "gn:name":"Massiapo",
    "gn:population":0,
    "gn:timezone":"America/Lima",
    "iso:country":"PE",
    "name:spa_x_preferred":[
        "Massiapo"
    ],
    "name:spa_x_variant":[
        "Masiapo"
    ],
    "wof:name":"Massiapo",
    "wof:placetype":"locality"
},
  "geometry": {"coordinates":[-69.2433,-14.09035],"type":"Point"}
}