{
  "type": "Feature",
  "properties": {
    "gn:admin1_code":"2.0",
    "gn:admin2_code":"205.0",
    "gn:asciiname":"Cocha Cochay",
    "gn:country_code":"PE",
    "gn:dem":3369,
    "gn:feature_class":"P",
    "gn:feature_code":"PPL",
    "gn:name":"Cocha Cochay",
    "gn:population":0,
    "gn:timezone":"America/Lima",
    "iso:country":"PE",
    "wof:name":"Cocha Cochay",
    "wof:placetype":"locality"
},
  "geometry": {"coordinates":[-77.12576,-10.37194],"type":"Point"}
}