{
  "type": "Feature",
  "properties": {
    "gn:admin1_code":"8",
    "gn:admin2_code":"806.0",
    "gn:admin3_code":"80608.0",
    "gn:asciiname":"Quellocunca",
    "gn:country_code":"PE",
    "gn:dem":3485,
    "gn:feature_class":"P",
    "gn:feature_code":"PPL",
    "gn:name":"Quellocunca",
    "gn:population":0,
    "gn:timezone":"America/Lima",
    "iso:country":"PE",
    "wof:name":"Quellocunca",
    "wof:placetype":"locality"
},
  "geometry": {"coordinates":[-71.38713,-14.15845],"type":"Point"}
}