{
  "type": "Feature",
  "properties": {
    "gn:admin1_code":"21",
    "gn:admin2_code":"2111.0",
    "gn:admin3_code":"211102.0",
    "gn:asciiname":"Silarane",
    "gn:country_code":"PE",
    "gn:dem":3843,
    "gn:feature_class":"P",
    "gn:feature_code":"PPL",
    "gn:name":"Silarane",
    "gn:population":0,
    "gn:timezone":"America/Lima",
    "iso:country":"PE",
    "wof:name":"Silarane",
    "wof:placetype":"locality"
},
  "geometry": {"coordinates":[-70.23605999999999,-15.58922],"type":"Point"}
}