{
  "type": "Feature",
  "properties": {
    "gn:admin1_code":"04",
    "gn:admin2_code":"406.0",
    "gn:admin3_code":"40601.0",
    "gn:asciiname":"Tambo",
    "gn:country_code":"PE",
    "gn:dem":3973,
    "gn:feature_class":"P",
    "gn:feature_code":"PPL",
    "gn:name":"Tambo",
    "gn:population":0,
    "gn:timezone":"America/Lima",
    "iso:country":"PE",
    "name:ceb_x_preferred":[
        "Tambo"
    ],
    "name:deu_x_preferred":[
        "Tambo"
    ],
    "name:fra_x_preferred":[
        "Tambo"
    ],
    "name:hrv_x_preferred":[
        "Tambo"
    ],
    "name:nor_x_preferred":[
        "Tambo"
    ],
    "name:por_x_preferred":[
        "Tambo"
    ],
    "name:rus_x_preferred":[
        "\u0440\u0435\u043a\u0430 \u0422\u0430\u043c\u0431\u043e"
    ],
    "name:rus_x_variant":[
        "\u0422\u0430\u043c\u0431\u043e"
    ],
    "name:spa_x_preferred":[
        "Tambo"
    ],
    "name:swe_x_preferred":[
        "Tambo"
    ],
    "name:ukr_x_preferred":[
        "\u0422\u0430\u043c\u0431\u043e"
    ],
    "name:urd_x_preferred":[
        "\u062a\u0627\u0645\u0628\u0648"
    ],
    "wof:name":"Tambo",
    "wof:placetype":"locality"
},
  "geometry": {"coordinates":[-72.68835,-15.70745],"type":"Point"}
}