{
  "type": "Feature",
  "properties": {
    "gn:admin1_code":"20",
    "gn:admin2_code":"2004.0",
    "gn:admin3_code":"200404.0",
    "gn:asciiname":"Santos",
    "gn:country_code":"PE",
    "gn:dem":159,
    "gn:feature_class":"P",
    "gn:feature_code":"PPL",
    "gn:name":"Santos",
    "gn:population":0,
    "gn:timezone":"America/Lima",
    "iso:country":"PE",
    "wof:name":"Santos",
    "wof:placetype":"locality"
},
  "geometry": {"coordinates":[-80.08333,-5.36667],"type":"Point"}
}