{
  "type": "Feature",
  "properties": {
    "gn:admin1_code":"06",
    "gn:admin2_code":"608.0",
    "gn:admin3_code":"60801.0",
    "gn:asciiname":"Cruz Grande",
    "gn:country_code":"PE",
    "gn:dem":1057,
    "gn:feature_class":"P",
    "gn:feature_code":"PPL",
    "gn:name":"Cruz Grande",
    "gn:population":0,
    "gn:timezone":"America/Lima",
    "iso:country":"PE",
    "name:sco_x_preferred":[
        "Cruz Grande"
    ],
    "name:spa_x_preferred":[
        "Cruz Grande"
    ],
    "name:srp_x_preferred":[
        "\u041a\u0440\u0443\u0437 \u0413\u0440\u0430\u043d\u0434\u0435"
    ],
    "wof:name":"Cruz Grande",
    "wof:placetype":"locality"
},
  "geometry": {"coordinates":[-78.83247,-5.72813],"type":"Point"}
}