{
  "type": "Feature",
  "properties": {
    "gn:admin1_code":"21",
    "gn:admin2_code":"2111.0",
    "gn:admin3_code":"211103.0",
    "gn:asciiname":"Casiria",
    "gn:country_code":"PE",
    "gn:dem":4434,
    "gn:feature_class":"P",
    "gn:feature_code":"PPL",
    "gn:name":"Casiria",
    "gn:population":0,
    "gn:timezone":"America/Lima",
    "iso:country":"PE",
    "wof:name":"Casiria",
    "wof:placetype":"locality"
},
  "geometry": {"coordinates":[-70.47968,-15.88773],"type":"Point"}
}