{
  "type": "Feature",
  "properties": {
    "gn:admin1_code":"3",
    "gn:admin2_code":"304.0",
    "gn:admin3_code":"30404.0",
    "gn:asciiname":"Patacorral",
    "gn:country_code":"PE",
    "gn:dem":4154,
    "gn:feature_class":"P",
    "gn:feature_code":"PPL",
    "gn:name":"Patacorral",
    "gn:population":0,
    "gn:timezone":"America/Lima",
    "iso:country":"PE",
    "wof:name":"Patacorral",
    "wof:placetype":"locality"
},
  "geometry": {"coordinates":[-73.04583000000002,-13.98833],"type":"Point"}
}