{
  "type": "Feature",
  "properties": {
    "gn:admin1_code":"21",
    "gn:admin2_code":"2102.0",
    "gn:admin3_code":"210210.0",
    "gn:asciiname":"Totopujo",
    "gn:country_code":"PE",
    "gn:dem":3845,
    "gn:feature_class":"P",
    "gn:feature_code":"PPL",
    "gn:name":"Totopujo",
    "gn:population":0,
    "gn:timezone":"America/Lima",
    "iso:country":"PE",
    "wof:name":"Totopujo",
    "wof:placetype":"locality"
},
  "geometry": {"coordinates":[-70.03416999999999,-15.39363],"type":"Point"}
}