{
  "type": "Feature",
  "properties": {
    "gn:admin1_code":"8.0",
    "gn:admin2_code":"813.0",
    "gn:admin3_code":"81303.0",
    "gn:asciiname":"Tancarpata",
    "gn:country_code":"PE",
    "gn:dem":3728,
    "gn:feature_class":"P",
    "gn:feature_code":"PPL",
    "gn:name":"Tancarpata",
    "gn:population":0,
    "gn:timezone":"America/Lima",
    "iso:country":"PE",
    "wof:name":"Tancarpata",
    "wof:placetype":"locality"
},
  "geometry": {"coordinates":[-72.07889,-13.37639],"type":"Point"}
}