{
  "type": "Feature",
  "properties": {
    "gn:admin1_code":"21",
    "gn:admin2_code":"2104.0",
    "gn:admin3_code":"210404.0",
    "gn:asciiname":"Mosina",
    "gn:country_code":"PE",
    "gn:dem":4050,
    "gn:feature_class":"P",
    "gn:feature_code":"PPL",
    "gn:name":"Mosi\u00f1a",
    "gn:population":0,
    "gn:timezone":"America/Lima",
    "iso:country":"PE",
    "wof:name":"Mosina",
    "wof:placetype":"locality"
},
  "geometry": {"coordinates":[-69.35611,-16.76083],"type":"Point"}
}