{
  "type": "Feature",
  "properties": {
    "gn:admin1_code":"21",
    "gn:admin2_code":"2109.0",
    "gn:admin3_code":"210901.0",
    "gn:asciiname":"Ocopampa",
    "gn:country_code":"PE",
    "gn:dem":4009,
    "gn:feature_class":"P",
    "gn:feature_code":"PPL",
    "gn:name":"Ocopampa",
    "gn:population":0,
    "gn:timezone":"America/Lima",
    "iso:country":"PE",
    "name:spa_x_preferred":[
        "Occobamba"
    ],
    "name:und_x_variant":[
        "Occopampa",
        "Ocopampa"
    ],
    "wof:name":"Ocopampa",
    "wof:placetype":"locality"
},
  "geometry": {"coordinates":[-69.37891999999999,-15.35633],"type":"Point"}
}