{
  "type": "Feature",
  "properties": {
    "gn:admin1_code":"02",
    "gn:admin2_code":"214.0",
    "gn:admin3_code":"21404.0",
    "gn:asciiname":"Carhuapampa",
    "gn:country_code":"PE",
    "gn:dem":3660,
    "gn:feature_class":"P",
    "gn:feature_code":"PPL",
    "gn:name":"Carhuapampa",
    "gn:population":0,
    "gn:timezone":"America/Lima",
    "iso:country":"PE",
    "wof:name":"Carhuapampa",
    "wof:placetype":"locality"
},
  "geometry": {"coordinates":[-77.24398000000002,-10.46894],"type":"Point"}
}