{
  "type": "Feature",
  "properties": {
    "iso:country":"PE",
    "name:aym_x_preferred":[
        "Chaclacayo jisk'a t'aqa suyu"
    ],
    "name:cat_x_preferred":[
        "Chaclacayo"
    ],
    "name:ceb_x_preferred":[
        "Chaclacayo"
    ],
    "name:eng_x_preferred":[
        "Chaclacayo"
    ],
    "name:fra_x_preferred":[
        "Chaclacayo"
    ],
    "name:ita_x_preferred":[
        "Distretto di Chaclacayo"
    ],
    "name:ita_x_variant":[
        "Chaclacayo"
    ],
    "name:nld_x_preferred":[
        "Chaclacayo"
    ],
    "name:por_x_preferred":[
        "Chaclacayo"
    ],
    "name:que_x_preferred":[
        "Chaqlakayu distritu"
    ],
    "name:spa_x_preferred":[
        "Distrito de Chaclacayo"
    ],
    "name:spa_x_variant":[
        "Chaclacayo"
    ],
    "name:zho_x_preferred":[
        "\u67e5\u514b\u62c9\u5361\u7d04\u5340"
    ],
    "qs:gn_pop":0,
    "qs:name":"Chaclacayo",
    "qs:name_adm0":"Per\u00fa",
    "qs:name_adm1":"Lima Metropolitan Area",
    "qs:photos":72,
    "qs:photos_1k":15,
    "qs:photos_9k":1,
    "qs:photos_9r":2,
    "qs:photos_all":72,
    "qs:photos_sr":2,
    "qs:placetype":"Town",
    "qs:pop_sr":"0",
    "qs:woe_adm0":23424919,
    "wd:wordcount":279,
    "wof:name":"Chaclacayo",
    "wof:placetype":"locality"
},
  "geometry": {"coordinates":[-76.861999,-12.068195],"type":"Point"}
}