{
  "type": "Feature",
  "properties": {
    "gn:admin1_code":"8",
    "gn:admin2_code":"806.0",
    "gn:admin3_code":"80606.0",
    "gn:asciiname":"Sillapata",
    "gn:country_code":"PE",
    "gn:dem":4788,
    "gn:feature_class":"P",
    "gn:feature_code":"PPL",
    "gn:name":"Sillapata",
    "gn:population":0,
    "gn:timezone":"America/Lima",
    "iso:country":"PE",
    "wof:name":"Sillapata",
    "wof:placetype":"locality"
},
  "geometry": {"coordinates":[-71.04472,-14.14028],"type":"Point"}
}