{
  "type": "Feature",
  "properties": {
    "gn:admin1_code":"05",
    "gn:admin2_code":"506.0",
    "gn:admin3_code":"50619.0",
    "gn:asciiname":"Hacienda Huac-Huaca",
    "gn:country_code":"PE",
    "gn:dem":757,
    "gn:feature_class":"P",
    "gn:feature_code":"PPL",
    "gn:name":"Hacienda Huac-Huaca",
    "gn:population":0,
    "gn:timezone":"America/Lima",
    "iso:country":"PE",
    "wof:name":"Hacienda Huac-Huaca",
    "wof:placetype":"locality"
},
  "geometry": {"coordinates":[-74.29051,-15.28712],"type":"Point"}
}