{
  "type": "Feature",
  "properties": {
    "gn:admin1_code":"10.0",
    "gn:admin2_code":"1011.0",
    "gn:admin3_code":"101106.0",
    "gn:asciiname":"Jircanhuay",
    "gn:country_code":"PE",
    "gn:dem":3555,
    "gn:feature_class":"P",
    "gn:feature_code":"PPL",
    "gn:name":"Jircanhuay",
    "gn:population":0,
    "gn:timezone":"America/Lima",
    "iso:country":"PE",
    "wof:name":"Jircanhuay",
    "wof:placetype":"locality"
},
  "geometry": {"coordinates":[-76.68494,-9.8313],"type":"Point"}
}