{
  "type": "Feature",
  "properties": {
    "gn:admin1_code":"20",
    "gn:admin2_code":"2002.0",
    "gn:admin3_code":"200201.0",
    "gn:asciiname":"Sausal",
    "gn:country_code":"PE",
    "gn:dem":895,
    "gn:feature_class":"P",
    "gn:feature_code":"PPL",
    "gn:name":"Sausal",
    "gn:population":0,
    "gn:timezone":"America/Lima",
    "iso:country":"PE",
    "name:ceb_x_preferred":[
        "Sausal Gebirge"
    ],
    "name:swe_x_preferred":[
        "Sausal Gebirge"
    ],
    "wof:name":"Sausal",
    "wof:placetype":"locality"
},
  "geometry": {"coordinates":[-79.64485999999999,-4.43665],"type":"Point"}
}