{
  "type": "Feature",
  "properties": {
    "gn:admin1_code":"21",
    "gn:admin2_code":"2104.0",
    "gn:admin3_code":"210406.0",
    "gn:asciiname":"Umajalso",
    "gn:country_code":"PE",
    "gn:dem":4053,
    "gn:feature_class":"P",
    "gn:feature_code":"PPL",
    "gn:name":"Umajalso",
    "gn:population":0,
    "gn:timezone":"America/Lima",
    "iso:country":"PE",
    "wof:name":"Umajalso",
    "wof:placetype":"locality"
},
  "geometry": {"coordinates":[-69.35626999999999,-16.41121],"type":"Point"}
}