{
  "type": "Feature",
  "properties": {
    "gn:admin1_code":"22",
    "gn:admin2_code":"2202.0",
    "gn:admin3_code":"220206.0",
    "gn:asciiname":"Miraflores",
    "gn:country_code":"PE",
    "gn:dem":236,
    "gn:feature_class":"P",
    "gn:feature_code":"PPL",
    "gn:name":"Miraflores",
    "gn:population":0,
    "gn:timezone":"America/Lima",
    "iso:country":"PE",
    "name:cat_x_preferred":[
        "Miraflores"
    ],
    "name:ceb_x_preferred":[
        "Miraflores"
    ],
    "name:deu_x_preferred":[
        "Miraflores"
    ],
    "name:fra_x_preferred":[
        "Miraflores"
    ],
    "name:glg_x_preferred":[
        "Miraflores"
    ],
    "name:ita_x_preferred":[
        "Miraflores"
    ],
    "name:nld_x_preferred":[
        "Miraflores"
    ],
    "name:pol_x_preferred":[
        "Miraflores"
    ],
    "name:por_x_preferred":[
        "Miraflores"
    ],
    "name:spa_x_preferred":[
        "Miraflores"
    ],
    "name:srp_x_preferred":[
        "\u041c\u0438\u0440\u0430\u0444\u043b\u043e\u0440\u0435\u0441"
    ],
    "name:swe_x_preferred":[
        "Miraflores"
    ],
    "wof:name":"Miraflores",
    "wof:placetype":"locality"
},
  "geometry": {"coordinates":[-76.45596,-7.03182],"type":"Point"}
}