{
  "type": "Feature",
  "properties": {
    "gn:admin1_code":"15",
    "gn:admin2_code":"1510.0",
    "gn:admin3_code":"151028.0",
    "gn:asciiname":"Huascac",
    "gn:country_code":"PE",
    "gn:dem":4442,
    "gn:feature_class":"P",
    "gn:feature_code":"PPL",
    "gn:name":"Huascac",
    "gn:population":0,
    "gn:timezone":"America/Lima",
    "iso:country":"PE",
    "wof:name":"Huascac",
    "wof:placetype":"locality"
},
  "geometry": {"coordinates":[-75.99694000000002,-12.09278],"type":"Point"}
}