{
  "type": "Feature",
  "properties": {
    "gn:admin1_code":"05",
    "gn:admin2_code":"501.0",
    "gn:admin3_code":"50103.0",
    "gn:asciiname":"Huarhuas",
    "gn:country_code":"PE",
    "gn:dem":3142,
    "gn:feature_class":"P",
    "gn:feature_code":"PPL",
    "gn:name":"Huarhuas",
    "gn:population":0,
    "gn:timezone":"America/Lima",
    "iso:country":"PE",
    "name:und_x_variant":[
        "hacienda Huarhuas"
    ],
    "wof:name":"Huarhuas",
    "wof:placetype":"locality"
},
  "geometry": {"coordinates":[-74.05864,-13.15762],"type":"Point"}
}