{
  "type": "Feature",
  "properties": {
    "gn:admin1_code":"06",
    "gn:admin2_code":"601.0",
    "gn:admin3_code":"60104.0",
    "gn:asciiname":"Sunchubamba",
    "gn:country_code":"PE",
    "gn:dem":2487,
    "gn:feature_class":"P",
    "gn:feature_code":"PPL",
    "gn:name":"Sunchubamba",
    "gn:population":0,
    "gn:timezone":"America/Lima",
    "iso:country":"PE",
    "name:und_x_variant":[
        "Sunchubamba Hacienda",
        "Sunchubamba"
    ],
    "wof:name":"Sunchubamba",
    "wof:placetype":"locality"
},
  "geometry": {"coordinates":[-78.38499,-7.48618],"type":"Point"}
}