{
  "type": "Feature",
  "properties": {
    "gn:admin1_code":"9.0",
    "gn:admin2_code":"901.0",
    "gn:admin3_code":"90103.0",
    "gn:asciiname":"Ichupucro",
    "gn:country_code":"PE",
    "gn:dem":3855,
    "gn:feature_class":"P",
    "gn:feature_code":"PPL",
    "gn:name":"Ichupucro",
    "gn:population":0,
    "gn:timezone":"America/Lima",
    "iso:country":"PE",
    "wof:name":"Ichupucro",
    "wof:placetype":"locality"
},
  "geometry": {"coordinates":[-74.82746999999998,-12.67718],"type":"Point"}
}