{
  "type": "Feature",
  "properties": {
    "gn:admin1_code":"20",
    "gn:admin2_code":"2001.0",
    "gn:admin3_code":"200114.0",
    "gn:asciiname":"Ocoto Alto",
    "gn:cc2":"PE",
    "gn:country_code":"PE",
    "gn:dem":101,
    "gn:feature_class":"P",
    "gn:feature_code":"PPL",
    "gn:name":"Ocoto Alto",
    "gn:population":0,
    "gn:timezone":"America/Lima",
    "iso:country":"PE",
    "name:und_x_variant":[
        "Ocoto Alto Hacienda",
        "Ocoto Alto"
    ],
    "wof:name":"Ocoto Alto",
    "wof:placetype":"locality"
},
  "geometry": {"coordinates":[-80.395,-4.93778],"type":"Point"}
}