{
  "type": "Feature",
  "properties": {
    "gn:admin1_code":"2.0",
    "gn:admin2_code":"218.0",
    "gn:admin3_code":"21805.0",
    "gn:asciiname":"Hueco",
    "gn:country_code":"PE",
    "gn:dem":559,
    "gn:feature_class":"P",
    "gn:feature_code":"PPLL",
    "gn:name":"Hueco",
    "gn:population":0,
    "gn:timezone":"America/Lima",
    "iso:country":"PE",
    "wof:name":"Hueco",
    "wof:placetype":"locality"
},
  "geometry": {"coordinates":[-78.16389000000002,-9.14806],"type":"Point"}
}