{
  "type": "Feature",
  "properties": {
    "gn:admin1_code":"15",
    "gn:admin2_code":"1505.0",
    "gn:admin3_code":"150513.0",
    "gn:asciiname":"Fundo Esquivilca",
    "gn:country_code":"PE",
    "gn:dem":22,
    "gn:feature_class":"P",
    "gn:feature_code":"PPL",
    "gn:name":"Fundo Esquivilca",
    "gn:population":0,
    "gn:timezone":"America/Lima",
    "iso:country":"PE",
    "name:spa_x_preferred":[
        "Fundo Esquivilca"
    ],
    "name:spa_x_variant":[
        "Esquivilca"
    ],
    "wof:name":"Fundo Esquivilca",
    "wof:placetype":"locality"
},
  "geometry": {"coordinates":[-76.64858000000002,-12.65123],"type":"Point"}
}