{
  "type": "Feature",
  "properties": {
    "gn:admin1_code":"11",
    "gn:admin2_code":"1101.0",
    "gn:admin3_code":"110107.0",
    "gn:asciiname":"Callejon Los Espinos",
    "gn:country_code":"PE",
    "gn:dem":407,
    "gn:feature_class":"P",
    "gn:feature_code":"PPL",
    "gn:name":"Callej\u00f3n Los Espinos",
    "gn:population":0,
    "gn:timezone":"America/Lima",
    "iso:country":"PE",
    "name:und_x_variant":[
        "Callej\u00f3n de los Espinos",
        "Callej\u00f3n Los Espinos"
    ],
    "wof:name":"Callejon Los Espinos",
    "wof:placetype":"locality"
},
  "geometry": {"coordinates":[-75.6974,-14.13196],"type":"Point"}
}