{
  "type": "Feature",
  "properties": {
    "gn:admin1_code":"10.0",
    "gn:admin2_code":"1003.0",
    "gn:admin3_code":"100311.0",
    "gn:asciiname":"Jancahuasi",
    "gn:country_code":"PE",
    "gn:dem":3861,
    "gn:feature_class":"P",
    "gn:feature_code":"PPL",
    "gn:name":"Jancahuasi",
    "gn:population":0,
    "gn:timezone":"America/Lima",
    "iso:country":"PE",
    "wof:name":"Jancahuasi",
    "wof:placetype":"locality"
},
  "geometry": {"coordinates":[-76.45001999999999,-9.6331],"type":"Point"}
}