{
  "type": "Feature",
  "properties": {
    "gn:admin1_code":"13",
    "gn:admin2_code":"1311.0",
    "gn:admin3_code":"131103.0",
    "gn:asciiname":"Compin",
    "gn:country_code":"PE",
    "gn:dem":1538,
    "gn:feature_class":"P",
    "gn:feature_code":"PPL",
    "gn:name":"Comp\u00edn",
    "gn:population":0,
    "gn:timezone":"America/Lima",
    "iso:country":"PE",
    "wof:name":"Compin",
    "wof:placetype":"locality"
},
  "geometry": {"coordinates":[-78.6234,-7.69899],"type":"Point"}
}