{
  "type": "Feature",
  "properties": {
    "gn:admin1_code":"9.0",
    "gn:admin2_code":"906.0",
    "gn:admin3_code":"90607.0",
    "gn:asciiname":"Patahuasi",
    "gn:country_code":"PE",
    "gn:dem":4330,
    "gn:feature_class":"P",
    "gn:feature_code":"PPL",
    "gn:name":"Patahuasi",
    "gn:population":0,
    "gn:timezone":"America/Lima",
    "iso:country":"PE",
    "wof:name":"Patahuasi",
    "wof:placetype":"locality"
},
  "geometry": {"coordinates":[-74.93318000000002,-13.34577],"type":"Point"}
}