{
  "type": "Feature",
  "properties": {
    "gn:admin1_code":"08",
    "gn:admin2_code":"807.0",
    "gn:admin3_code":"80703.0",
    "gn:asciiname":"Chamaca",
    "gn:country_code":"PE",
    "gn:dem":3787,
    "gn:feature_class":"P",
    "gn:feature_code":"PPLA3",
    "gn:name":"Chamaca",
    "gn:population":0,
    "gn:timezone":"America/Lima",
    "iso:country":"PE",
    "wof:name":"Chamaca",
    "wof:placetype":"locality"
},
  "geometry": {"coordinates":[-71.84305999999999,-14.30833],"type":"Point"}
}