{
  "type": "Feature",
  "properties": {
    "gn:admin1_code":"04",
    "gn:admin2_code":"406.0",
    "gn:admin3_code":"40603.0",
    "gn:asciiname":"Llojeta",
    "gn:country_code":"PE",
    "gn:dem":4509,
    "gn:feature_class":"P",
    "gn:feature_code":"PPL",
    "gn:name":"Llojeta",
    "gn:population":0,
    "gn:timezone":"America/Lima",
    "iso:country":"PE",
    "wof:name":"Llojeta",
    "wof:placetype":"locality"
},
  "geometry": {"coordinates":[-72.31014999999999,-15.0754],"type":"Point"}
}