{
  "type": "Feature",
  "properties": {
    "gn:admin1_code":"10.0",
    "gn:admin2_code":"1001.0",
    "gn:admin3_code":"100104.0",
    "gn:asciiname":"Linda",
    "gn:country_code":"PE",
    "gn:dem":1948,
    "gn:feature_class":"P",
    "gn:feature_code":"PPL",
    "gn:name":"Linda",
    "gn:population":0,
    "gn:timezone":"America/Lima",
    "iso:country":"PE",
    "name:ceb_x_preferred":[
        "Linda"
    ],
    "name:ces_x_preferred":[
        "Linda"
    ],
    "name:deu_x_preferred":[
        "Linda"
    ],
    "name:epo_x_preferred":[
        "Linda"
    ],
    "name:est_x_preferred":[
        "Linda"
    ],
    "name:fin_x_preferred":[
        "Linda"
    ],
    "name:fra_x_preferred":[
        "Linda"
    ],
    "name:heb_x_preferred":[
        "\u05dc\u05d9\u05e0\u05d3\u05d4"
    ],
    "name:hsb_x_preferred":[
        "Linda"
    ],
    "name:hun_x_preferred":[
        "Linda"
    ],
    "name:ita_x_preferred":[
        "Linda"
    ],
    "name:jpn_x_preferred":[
        "\u30ea\u30f3\u30c0"
    ],
    "name:nld_x_preferred":[
        "Linda"
    ],
    "name:pol_x_preferred":[
        "Linda"
    ],
    "name:por_x_preferred":[
        "Linda"
    ],
    "name:ron_x_preferred":[
        "Linda"
    ],
    "name:rus_x_preferred":[
        "\u041b\u0438\u043d\u0434\u0430"
    ],
    "name:spa_x_preferred":[
        "Linda"
    ],
    "name:ukr_x_preferred":[
        "\u041b\u0456\u043d\u0434\u0430"
    ],
    "name:vie_x_preferred":[
        "Linda"
    ],
    "wof:name":"Linda",
    "wof:placetype":"locality"
},
  "geometry": {"coordinates":[-76.09466,-9.83576],"type":"Point"}
}