{
  "type": "Feature",
  "properties": {
    "gn:admin1_code":"4",
    "gn:admin2_code":"405.0",
    "gn:admin3_code":"40504.0",
    "gn:asciiname":"Anacana",
    "gn:country_code":"PE",
    "gn:dem":4589,
    "gn:feature_class":"P",
    "gn:feature_code":"PPL",
    "gn:name":"A\u00f1aca\u00f1a",
    "gn:population":0,
    "gn:timezone":"America/Lima",
    "iso:country":"PE",
    "wof:name":"Anacana",
    "wof:placetype":"locality"
},
  "geometry": {"coordinates":[-71.18209,-15.32723],"type":"Point"}
}