{
  "type": "Feature",
  "properties": {
    "gn:admin1_code":"2.0",
    "gn:admin2_code":"206.0",
    "gn:admin3_code":"20601.0",
    "gn:asciiname":"Cunyac",
    "gn:country_code":"PE",
    "gn:dem":3681,
    "gn:feature_class":"P",
    "gn:feature_code":"PPL",
    "gn:name":"Cunyac",
    "gn:population":0,
    "gn:timezone":"America/Lima",
    "iso:country":"PE",
    "wof:name":"Cunyac",
    "wof:placetype":"locality"
},
  "geometry": {"coordinates":[-77.65666999999998,-9.33222],"type":"Point"}
}