{
  "type": "Feature",
  "properties": {
    "gn:admin1_code":"8",
    "gn:admin2_code":"809.0",
    "gn:admin3_code":"80902.0",
    "gn:asciiname":"Sonampiato",
    "gn:country_code":"PE",
    "gn:dem":1214,
    "gn:feature_class":"P",
    "gn:feature_code":"PPL",
    "gn:name":"Sonampiato",
    "gn:population":0,
    "gn:timezone":"America/Lima",
    "iso:country":"PE",
    "wof:name":"Sonampiato",
    "wof:placetype":"locality"
},
  "geometry": {"coordinates":[-73.13868000000002,-12.65342],"type":"Point"}
}