{
  "type": "Feature",
  "properties": {
    "gn:admin1_code":"4",
    "gn:admin2_code":"405.0",
    "gn:admin3_code":"40514.0",
    "gn:asciiname":"Chacala",
    "gn:country_code":"PE",
    "gn:dem":4473,
    "gn:feature_class":"P",
    "gn:feature_code":"PPL",
    "gn:name":"Chacala",
    "gn:population":0,
    "gn:timezone":"America/Lima",
    "iso:country":"PE",
    "name:spa_x_preferred":[
        "Chacala"
    ],
    "wof:name":"Chacala",
    "wof:placetype":"locality"
},
  "geometry": {"coordinates":[-71.09555999999998,-15.90056],"type":"Point"}
}