{
  "type": "Feature",
  "properties": {
    "gn:admin1_code":"15",
    "gn:admin2_code":"1508.0",
    "gn:admin3_code":"150807.0",
    "gn:asciiname":"Turumachay",
    "gn:country_code":"PE",
    "gn:dem":4453,
    "gn:feature_class":"P",
    "gn:feature_code":"PPL",
    "gn:name":"Turumachay",
    "gn:population":0,
    "gn:timezone":"America/Lima",
    "iso:country":"PE",
    "wof:name":"Turumachay",
    "wof:placetype":"locality"
},
  "geometry": {"coordinates":[-76.84305999999999,-11.01889],"type":"Point"}
}