{
  "type": "Feature",
  "properties": {
    "gn:admin1_code":"21",
    "gn:admin2_code":"2112.0",
    "gn:admin3_code":"211201.0",
    "gn:asciiname":"Quisuarani",
    "gn:country_code":"PE",
    "gn:dem":3554,
    "gn:feature_class":"P",
    "gn:feature_code":"PPL",
    "gn:name":"Quisuarani",
    "gn:population":0,
    "gn:timezone":"America/Lima",
    "iso:country":"PE",
    "wof:name":"Quisuarani",
    "wof:placetype":"locality"
},
  "geometry": {"coordinates":[-69.52811,-14.35848],"type":"Point"}
}