{
  "type": "Feature",
  "properties": {
    "gn:admin1_code":"05",
    "gn:admin2_code":"502.0",
    "gn:admin3_code":"50206.0",
    "gn:asciiname":"Lambras Monte",
    "gn:country_code":"PE",
    "gn:dem":3393,
    "gn:feature_class":"P",
    "gn:feature_code":"PPL",
    "gn:name":"Lambras Monte",
    "gn:population":0,
    "gn:timezone":"America/Lima",
    "iso:country":"PE",
    "wof:name":"Lambras Monte",
    "wof:placetype":"locality"
},
  "geometry": {"coordinates":[-74.51666,-13.57152],"type":"Point"}
}