{
  "type": "Feature",
  "properties": {
    "gn:admin1_code":"18",
    "gn:admin2_code":"1801.0",
    "gn:admin3_code":"180105.0",
    "gn:asciiname":"Yaragua",
    "gn:country_code":"PE",
    "gn:dem":1760,
    "gn:feature_class":"P",
    "gn:feature_code":"PPL",
    "gn:name":"Yaragua",
    "gn:population":0,
    "gn:timezone":"America/Lima",
    "iso:country":"PE",
    "wof:name":"Yaragua",
    "wof:placetype":"locality"
},
  "geometry": {"coordinates":[-70.81029000000002,-16.76486],"type":"Point"}
}