{
  "type": "Feature",
  "properties": {
    "gn:admin1_code":"05",
    "gn:admin2_code":"509.0",
    "gn:admin3_code":"50901.0",
    "gn:asciiname":"Cayhua",
    "gn:country_code":"PE",
    "gn:dem":2326,
    "gn:feature_class":"P",
    "gn:feature_code":"PPL",
    "gn:name":"Cayhua",
    "gn:population":0,
    "gn:timezone":"America/Lima",
    "iso:country":"PE",
    "wof:name":"Cayhua",
    "wof:placetype":"locality"
},
  "geometry": {"coordinates":[-73.88942,-13.96217],"type":"Point"}
}