{
  "type": "Feature",
  "properties": {
    "gn:admin1_code":"01",
    "gn:admin2_code":"104.0",
    "gn:admin3_code":"10401.0",
    "gn:asciiname":"Caucaya",
    "gn:country_code":"PE",
    "gn:dem":203,
    "gn:feature_class":"P",
    "gn:feature_code":"PPL",
    "gn:name":"Caucaya",
    "gn:population":0,
    "gn:timezone":"America/Lima",
    "iso:country":"PE",
    "wof:name":"Caucaya",
    "wof:placetype":"locality"
},
  "geometry": {"coordinates":[-77.93581,-4.62326],"type":"Point"}
}