{
  "type": "Feature",
  "properties": {
    "gn:admin1_code":"25",
    "gn:admin2_code":"2502.0",
    "gn:admin3_code":"250201.0",
    "gn:asciiname":"Puerto Mapuyo",
    "gn:country_code":"PE",
    "gn:dem":276,
    "gn:feature_class":"P",
    "gn:feature_code":"PPL",
    "gn:name":"Puerto Mapuyo",
    "gn:population":0,
    "gn:timezone":"America/Lima",
    "iso:country":"PE",
    "wof:name":"Puerto Mapuyo",
    "wof:placetype":"locality"
},
  "geometry": {"coordinates":[-73.06667,-10.56667],"type":"Point"}
}