{
  "type": "Feature",
  "properties": {
    "gn:admin1_code":"15",
    "gn:admin2_code":"1508.0",
    "gn:admin3_code":"150809.0",
    "gn:asciiname":"Gilgay",
    "gn:country_code":"PE",
    "gn:dem":4355,
    "gn:feature_class":"P",
    "gn:feature_code":"PPL",
    "gn:name":"Gilgay",
    "gn:population":0,
    "gn:timezone":"America/Lima",
    "iso:country":"PE",
    "wof:name":"Gilgay",
    "wof:placetype":"locality"
},
  "geometry": {"coordinates":[-76.63835999999998,-10.95547],"type":"Point"}
}