{
  "type": "Feature",
  "properties": {
    "gn:admin1_code":"21",
    "gn:admin2_code":"2103",
    "gn:asciiname":"Chococarga",
    "gn:country_code":"PE",
    "gn:dem":4257,
    "gn:feature_class":"P",
    "gn:feature_code":"PPL",
    "gn:name":"Chococarga",
    "gn:population":0,
    "gn:timezone":"America/Lima",
    "iso:country":"PE",
    "name:spa_x_preferred":[
        "Chococarga"
    ],
    "wof:name":"Chococarga",
    "wof:placetype":"locality"
},
  "geometry": {"coordinates":[-69.95593000000001,-13.98218],"type":"Point"}
}