{
  "type": "Feature",
  "properties": {
    "gn:admin1_code":"08",
    "gn:admin2_code":"809.0",
    "gn:admin3_code":"80908.0",
    "gn:asciiname":"Huadquina",
    "gn:country_code":"PE",
    "gn:dem":3025,
    "gn:feature_class":"P",
    "gn:feature_code":"PPL",
    "gn:name":"Huadqui\u00f1a",
    "gn:population":0,
    "gn:timezone":"America/Lima",
    "iso:country":"PE",
    "wof:name":"Huadquina",
    "wof:placetype":"locality"
},
  "geometry": {"coordinates":[-72.65000000000001,-13.11667],"type":"Point"}
}