{
  "type": "Feature",
  "properties": {
    "gn:admin1_code":"3",
    "gn:admin2_code":"302.0",
    "gn:admin3_code":"30209.0",
    "gn:asciiname":"Poltocsa",
    "gn:country_code":"PE",
    "gn:dem":2971,
    "gn:feature_class":"P",
    "gn:feature_code":"PPL",
    "gn:name":"Poltocsa",
    "gn:population":0,
    "gn:timezone":"America/Lima",
    "iso:country":"PE",
    "wof:name":"Poltocsa",
    "wof:placetype":"locality"
},
  "geometry": {"coordinates":[-73.27093000000001,-13.59513],"type":"Point"}
}