{
  "type": "Feature",
  "properties": {
    "gn:admin1_code":"12",
    "gn:admin2_code":"1201.0",
    "gn:admin3_code":"120135.0",
    "gn:asciiname":"Tolejala",
    "gn:country_code":"PE",
    "gn:dem":2541,
    "gn:feature_class":"P",
    "gn:feature_code":"PPL",
    "gn:name":"Tolejala",
    "gn:population":0,
    "gn:timezone":"America/Lima",
    "iso:country":"PE",
    "wof:name":"Tolejala",
    "wof:placetype":"locality"
},
  "geometry": {"coordinates":[-74.77098000000002,-11.77187],"type":"Point"}
}