{
  "type": "Feature",
  "properties": {
    "gn:admin1_code":"05",
    "gn:admin2_code":"506.0",
    "gn:admin3_code":"50605.0",
    "gn:asciiname":"Ccarcarquina",
    "gn:country_code":"PE",
    "gn:dem":3281,
    "gn:feature_class":"P",
    "gn:feature_code":"PPL",
    "gn:name":"Ccarcarqui\u00f1a",
    "gn:population":0,
    "gn:timezone":"America/Lima",
    "iso:country":"PE",
    "name:spa_x_preferred":[
        "Ccarcarqui\u00f1a"
    ],
    "wof:name":"Ccarcarquina",
    "wof:placetype":"locality"
},
  "geometry": {"coordinates":[-73.8425,-15.04258],"type":"Point"}
}