{
  "type": "Feature",
  "properties": {
    "gn:admin1_code":"16.0",
    "gn:admin2_code":"1606.0",
    "gn:asciiname":"Nuevo Sunaya",
    "gn:country_code":"PE",
    "gn:dem":132,
    "gn:feature_class":"P",
    "gn:feature_code":"PPL",
    "gn:name":"Nuevo Sunaya",
    "gn:population":0,
    "gn:timezone":"America/Lima",
    "iso:country":"PE",
    "name:spa_x_preferred":[
        "Nuevo Sunaya"
    ],
    "wof:name":"Nuevo Sunaya",
    "wof:placetype":"locality"
},
  "geometry": {"coordinates":[-75.17668,-7.35874],"type":"Point"}
}