{
  "type": "Feature",
  "properties": {
    "gn:admin1_code":"10.0",
    "gn:admin2_code":"1005.0",
    "gn:admin3_code":"100501.0",
    "gn:asciiname":"Libertad",
    "gn:country_code":"PE",
    "gn:dem":3642,
    "gn:feature_class":"P",
    "gn:feature_code":"PPL",
    "gn:name":"Libertad",
    "gn:population":0,
    "gn:timezone":"America/Lima",
    "iso:country":"PE",
    "name:cat_x_preferred":[
        "Libertad"
    ],
    "name:ceb_x_preferred":[
        "Libertad"
    ],
    "name:deu_x_preferred":[
        "Libertad"
    ],
    "name:epo_x_preferred":[
        "Libereco"
    ],
    "name:fra_x_preferred":[
        "Libertad"
    ],
    "name:hin_x_preferred":[
        "\u0906\u091c\u093c\u093e\u0926\u0940"
    ],
    "name:ilo_x_preferred":[
        "Libertad"
    ],
    "name:ita_x_preferred":[
        "Libertad"
    ],
    "name:kat_x_preferred":[
        "\u10d7\u10d0\u10d5\u10d8\u10e1\u10e3\u10e4\u10da\u10d4\u10d1\u10d0"
    ],
    "name:nds_x_preferred":[
        "Libertad"
    ],
    "name:nld_x_preferred":[
        "Libertad"
    ],
    "name:pol_x_preferred":[
        "Libertad"
    ],
    "name:por_x_preferred":[
        "Libertad"
    ],
    "name:ron_x_preferred":[
        "Libertate"
    ],
    "name:rus_x_preferred":[
        "\u041b\u0438\u0431\u0435\u0440\u0442\u0430\u0434"
    ],
    "name:spa_x_preferred":[
        "Libertad"
    ],
    "name:srp_x_preferred":[
        "\u041b\u0438\u0431\u0435\u0440\u0442\u0430\u0434"
    ],
    "name:swe_x_preferred":[
        "Libertad"
    ],
    "name:ukr_x_preferred":[
        "\u041b\u0456\u0431\u0435\u0440\u0442\u0430\u0434"
    ],
    "name:war_x_preferred":[
        "Libertad"
    ],
    "wof:name":"Libertad",
    "wof:placetype":"locality"
},
  "geometry": {"coordinates":[-76.83813000000001,-9.54448],"type":"Point"}
}