{
  "type": "Feature",
  "properties": {
    "gn:admin1_code":"18",
    "gn:admin2_code":"1801.0",
    "gn:admin3_code":"180106.0",
    "gn:asciiname":"Quebrada Negra",
    "gn:country_code":"PE",
    "gn:dem":4262,
    "gn:feature_class":"P",
    "gn:feature_code":"PPL",
    "gn:name":"Quebrada Negra",
    "gn:population":0,
    "gn:timezone":"America/Lima",
    "iso:country":"PE",
    "wof:name":"Quebrada Negra",
    "wof:placetype":"locality"
},
  "geometry": {"coordinates":[-70.57598,-16.96796],"type":"Point"}
}