{
  "type": "Feature",
  "properties": {
    "gn:admin1_code":"15",
    "gn:admin2_code":"1510.0",
    "gn:admin3_code":"151027.0",
    "gn:asciiname":"Pilas",
    "gn:country_code":"PE",
    "gn:dem":2668,
    "gn:feature_class":"P",
    "gn:feature_code":"PPL",
    "gn:name":"Pilas",
    "gn:population":0,
    "gn:timezone":"America/Lima",
    "iso:country":"PE",
    "name:ceb_x_preferred":[
        "Pilas"
    ],
    "name:ita_x_preferred":[
        "Pilas"
    ],
    "name:swe_x_preferred":[
        "Pilas"
    ],
    "wof:name":"Pilas",
    "wof:placetype":"locality"
},
  "geometry": {"coordinates":[-76.22669999999999,-12.45486],"type":"Point"}
}