{
  "type": "Feature",
  "properties": {
    "gn:admin1_code":"06",
    "gn:admin2_code":"610.0",
    "gn:admin3_code":"61003.0",
    "gn:asciiname":"Puerto Arturo",
    "gn:country_code":"PE",
    "gn:dem":2081,
    "gn:feature_class":"P",
    "gn:feature_code":"PPL",
    "gn:name":"Puerto Arturo",
    "gn:population":0,
    "gn:timezone":"America/Lima",
    "iso:country":"PE",
    "wof:name":"Puerto Arturo",
    "wof:placetype":"locality"
},
  "geometry": {"coordinates":[-78.1725,-7.4426],"type":"Point"}
}