{
  "type": "Feature",
  "properties": {
    "gn:admin1_code":"4",
    "gn:admin2_code":"406.0",
    "gn:admin3_code":"40603.0",
    "gn:asciiname":"Toclla",
    "gn:country_code":"PE",
    "gn:dem":4253,
    "gn:feature_class":"P",
    "gn:feature_code":"PPL",
    "gn:name":"Toclla",
    "gn:population":0,
    "gn:timezone":"America/Lima",
    "iso:country":"PE",
    "wof:name":"Toclla",
    "wof:placetype":"locality"
},
  "geometry": {"coordinates":[-71.99778000000001,-14.87296],"type":"Point"}
}