{
  "type": "Feature",
  "properties": {
    "gn:admin1_code":"15",
    "gn:admin2_code":"1505.0",
    "gn:admin3_code":"150502.0",
    "gn:asciiname":"Flores",
    "gn:country_code":"PE",
    "gn:dem":11,
    "gn:feature_class":"P",
    "gn:feature_code":"PPL",
    "gn:name":"Flores",
    "gn:population":0,
    "gn:timezone":"America/Lima",
    "iso:country":"PE",
    "wof:name":"Flores",
    "wof:placetype":"locality"
},
  "geometry": {"coordinates":[-76.58348000000002,-12.77426],"type":"Point"}
}