{
  "type": "Feature",
  "properties": {
    "gn:admin1_code":"03",
    "gn:admin2_code":"306.0",
    "gn:admin3_code":"30605.0",
    "gn:asciiname":"Ocobamba",
    "gn:country_code":"PE",
    "gn:dem":3005,
    "gn:feature_class":"P",
    "gn:feature_code":"PPLA3",
    "gn:name":"Ocobamba",
    "gn:population":0,
    "gn:timezone":"America/Lima",
    "iso:country":"PE",
    "name:und_x_variant":[
        "Occobamba",
        "Ocobamba"
    ],
    "wof:name":"Ocobamba",
    "wof:placetype":"locality"
},
  "geometry": {"coordinates":[-73.56111,-13.48194],"type":"Point"}
}