{
  "type": "Feature",
  "properties": {
    "gn:admin1_code":"11",
    "gn:admin2_code":"1105.0",
    "gn:admin3_code":"110503.0",
    "gn:asciiname":"Hacienda San Ignacio",
    "gn:country_code":"PE",
    "gn:dem":395,
    "gn:feature_class":"P",
    "gn:feature_code":"PPL",
    "gn:name":"Hacienda San Ignacio",
    "gn:population":0,
    "gn:timezone":"America/Lima",
    "iso:country":"PE",
    "name:spa_x_preferred":[
        "Hacienda San Ignacio"
    ],
    "name:und_x_variant":[
        "San Ignacio Hacienda",
        "San Ignacio"
    ],
    "wof:name":"Hacienda San Ignacio",
    "wof:placetype":"locality"
},
  "geometry": {"coordinates":[-75.91,-13.72452],"type":"Point"}
}