{
  "type": "Feature",
  "properties": {
    "gn:admin1_code":"8",
    "gn:admin2_code":"806.0",
    "gn:admin3_code":"80604.0",
    "gn:asciiname":"Pampaccasi",
    "gn:country_code":"PE",
    "gn:dem":3771,
    "gn:feature_class":"P",
    "gn:feature_code":"PPL",
    "gn:name":"Pampaccasi",
    "gn:population":0,
    "gn:timezone":"America/Lima",
    "iso:country":"PE",
    "wof:name":"Pampaccasi",
    "wof:placetype":"locality"
},
  "geometry": {"coordinates":[-71.13375000000001,-14.39304],"type":"Point"}
}