{
  "type": "Feature",
  "properties": {
    "gn:admin1_code":"22.0",
    "gn:admin2_code":"2204.0",
    "gn:admin3_code":"220405.0",
    "gn:asciiname":"Gallito",
    "gn:country_code":"PE",
    "gn:dem":291,
    "gn:elevation":"493.0",
    "gn:feature_class":"P",
    "gn:feature_code":"PPL",
    "gn:name":"Gallito",
    "gn:population":0,
    "gn:timezone":"America/Lima",
    "iso:country":"PE",
    "name:spa_x_preferred":[
        "Gallito"
    ],
    "wof:name":"Gallito",
    "wof:placetype":"locality"
},
  "geometry": {"coordinates":[-76.68420999999999,-7.0678],"type":"Point"}
}