{
  "type": "Feature",
  "properties": {
    "gn:admin1_code":"08",
    "gn:admin2_code":"811.0",
    "gn:admin3_code":"81106.0",
    "gn:asciiname":"Pillcopata",
    "gn:country_code":"PE",
    "gn:dem":968,
    "gn:feature_class":"P",
    "gn:feature_code":"PPLA3",
    "gn:name":"Pillcopata",
    "gn:population":0,
    "gn:timezone":"America/Lima",
    "iso:country":"PE",
    "wof:name":"Pillcopata",
    "wof:placetype":"locality"
},
  "geometry": {"coordinates":[-71.16667,-13.06667],"type":"Point"}
}