{
  "type": "Feature",
  "properties": {
    "gn:admin1_code":"4",
    "gn:admin2_code":"403.0",
    "gn:admin3_code":"40301.0",
    "gn:asciiname":"Alto del Molino",
    "gn:country_code":"PE",
    "gn:dem":1795,
    "gn:feature_class":"P",
    "gn:feature_code":"PPL",
    "gn:name":"Alto del Molino",
    "gn:population":0,
    "gn:timezone":"America/Lima",
    "iso:country":"PE",
    "wof:name":"Alto del Molino",
    "wof:placetype":"locality"
},
  "geometry": {"coordinates":[-73.36971,-15.76136],"type":"Point"}
}