{
  "type": "Feature",
  "properties": {
    "gn:admin1_code":"4",
    "gn:admin2_code":"404.0",
    "gn:admin3_code":"40409.0",
    "gn:asciiname":"Mancalojro",
    "gn:country_code":"PE",
    "gn:dem":4513,
    "gn:feature_class":"P",
    "gn:feature_code":"PPL",
    "gn:name":"Mancalojro",
    "gn:population":0,
    "gn:timezone":"America/Lima",
    "iso:country":"PE",
    "wof:name":"Mancalojro",
    "wof:placetype":"locality"
},
  "geometry": {"coordinates":[-72.339,-15.10497],"type":"Point"}
}