{
  "type": "Feature",
  "properties": {
    "gn:admin1_code":"12",
    "gn:admin2_code":"1206.0",
    "gn:admin3_code":"120605.0",
    "gn:asciiname":"Santa Rosita",
    "gn:country_code":"PE",
    "gn:dem":920,
    "gn:feature_class":"P",
    "gn:feature_code":"PPL",
    "gn:name":"Santa Rosita",
    "gn:population":0,
    "gn:timezone":"America/Lima",
    "iso:country":"PE",
    "name:ceb_x_preferred":[
        "Santa Rosita"
    ],
    "name:srp_x_preferred":[
        "\u0421\u0430\u043d\u0442\u0430 \u0420\u043e\u0441\u0438\u0442\u0430"
    ],
    "name:swe_x_preferred":[
        "Santa Rosita"
    ],
    "wof:name":"Santa Rosita",
    "wof:placetype":"locality"
},
  "geometry": {"coordinates":[-74.73235,-11.33488],"type":"Point"}
}