{
  "type": "Feature",
  "properties": {
    "gn:admin1_code":"3",
    "gn:admin2_code":"302.0",
    "gn:admin3_code":"30203.0",
    "gn:asciiname":"Yacto",
    "gn:country_code":"PE",
    "gn:dem":3896,
    "gn:feature_class":"P",
    "gn:feature_code":"PPL",
    "gn:name":"Yacto",
    "gn:population":0,
    "gn:timezone":"America/Lima",
    "iso:country":"PE",
    "wof:name":"Yacto",
    "wof:placetype":"locality"
},
  "geometry": {"coordinates":[-73.58278,-13.87667],"type":"Point"}
}