{
  "type": "Feature",
  "properties": {
    "gn:admin1_code":"15",
    "gn:admin2_code":"1507.0",
    "gn:admin3_code":"150706.0",
    "gn:asciiname":"Simplaya",
    "gn:country_code":"PE",
    "gn:dem":2751,
    "gn:feature_class":"P",
    "gn:feature_code":"PPL",
    "gn:name":"Simplaya",
    "gn:population":0,
    "gn:timezone":"America/Lima",
    "iso:country":"PE",
    "wof:name":"Simplaya",
    "wof:placetype":"locality"
},
  "geometry": {"coordinates":[-76.45,-12.13333],"type":"Point"}
}