{
  "type": "Feature",
  "properties": {
    "gn:admin1_code":"2.0",
    "gn:admin2_code":"205.0",
    "gn:admin3_code":"20509.0",
    "gn:asciiname":"Matibamba",
    "gn:country_code":"PE",
    "gn:dem":3288,
    "gn:feature_class":"P",
    "gn:feature_code":"PPL",
    "gn:name":"Matibamba",
    "gn:population":0,
    "gn:timezone":"America/Lima",
    "iso:country":"PE",
    "wof:name":"Matibamba",
    "wof:placetype":"locality"
},
  "geometry": {"coordinates":[-77.07051,-10.18005],"type":"Point"}
}