{
  "type": "Feature",
  "properties": {
    "gn:admin1_code":"16.0",
    "gn:admin2_code":"1607.0",
    "gn:admin3_code":"160706.0",
    "gn:asciiname":"Shanshococha",
    "gn:country_code":"PE",
    "gn:dem":209,
    "gn:feature_class":"P",
    "gn:feature_code":"PPL",
    "gn:name":"Shanshococha",
    "gn:population":0,
    "gn:timezone":"America/Lima",
    "iso:country":"PE",
    "wof:name":"Shanshococha",
    "wof:placetype":"locality"
},
  "geometry": {"coordinates":[-77.03331999999997,-3.29796],"type":"Point"}
}