{
  "type": "Feature",
  "properties": {
    "gn:admin1_code":"22.0",
    "gn:admin2_code":"2202.0",
    "gn:admin3_code":"220201.0",
    "gn:asciiname":"Algarrobo",
    "gn:country_code":"PE",
    "gn:dem":241,
    "gn:feature_class":"P",
    "gn:feature_code":"PPL",
    "gn:name":"Algarrobo",
    "gn:population":0,
    "gn:timezone":"America/Lima",
    "iso:country":"PE",
    "name:ceb_x_preferred":[
        "Algarrobo"
    ],
    "name:deu_x_preferred":[
        "Algarrobo"
    ],
    "name:eus_x_preferred":[
        "Algarrobo"
    ],
    "name:fra_x_preferred":[
        "Algarrobo"
    ],
    "name:ita_x_preferred":[
        "Algarrobo"
    ],
    "name:kor_x_preferred":[
        "\uc54c\uac00\ub85c\ubcf4"
    ],
    "name:nld_x_preferred":[
        "Algarrobo"
    ],
    "name:pol_x_preferred":[
        "Algarrobo"
    ],
    "name:por_x_preferred":[
        "Algarrobo"
    ],
    "name:que_x_preferred":[
        "Algarrobo"
    ],
    "name:sco_x_preferred":[
        "Algarrobo"
    ],
    "name:spa_x_preferred":[
        "Algarrobo"
    ],
    "name:swe_x_preferred":[
        "Algarrobo"
    ],
    "name:zho_x_preferred":[
        "\u963f\u5c14\u52a0\u7f57\u6c83"
    ],
    "wof:name":"Algarrobo",
    "wof:placetype":"locality"
},
  "geometry": {"coordinates":[-76.53574,-7.0393],"type":"Point"}
}