{
  "type": "Feature",
  "properties": {
    "gn:admin1_code":"22.0",
    "gn:admin2_code":"2202.0",
    "gn:admin3_code":"220201.0",
    "gn:asciiname":"Algarrobo",
    "gn:country_code":"PE",
    "gn:dem":241,
    "gn:feature_class":"P",
    "gn:feature_code":"PPL",
    "gn:name":"Algarrobo",
    "gn:population":0,
    "gn:timezone":"America/Lima",
    "iso:country":"PE",
    "name:spa_x_preferred":[
        "Algarrobo"
    ],
    "wof:name":"Algarrobo",
    "wof:placetype":"locality"
},
  "geometry": {"coordinates":[-76.53574,-7.0393],"type":"Point"}
}