{
  "type": "Feature",
  "properties": {
    "gn:admin1_code":"2.0",
    "gn:admin2_code":"217.0",
    "gn:admin3_code":"21702.0",
    "gn:asciiname":"Santo Domingo",
    "gn:country_code":"PE",
    "gn:dem":4122,
    "gn:feature_class":"P",
    "gn:feature_code":"PPL",
    "gn:name":"Santo Domingo",
    "gn:population":0,
    "gn:timezone":"America/Lima",
    "iso:country":"PE",
    "wof:name":"Santo Domingo",
    "wof:placetype":"locality"
},
  "geometry": {"coordinates":[-77.26533000000001,-10.04661],"type":"Point"}
}