{
  "type": "Feature",
  "properties": {
    "gn:admin1_code":"19",
    "gn:admin2_code":"1903.0",
    "gn:admin3_code":"190304.0",
    "gn:asciiname":"Puerto Laguna",
    "gn:country_code":"PE",
    "gn:dem":328,
    "gn:feature_class":"P",
    "gn:feature_code":"PPL",
    "gn:name":"Puerto Laguna",
    "gn:population":0,
    "gn:timezone":"America/Lima",
    "iso:country":"PE",
    "wof:name":"Puerto Laguna",
    "wof:placetype":"locality"
},
  "geometry": {"coordinates":[-75.09333000000002,-10.33611],"type":"Point"}
}