{
  "type": "Feature",
  "properties": {
    "gn:admin1_code":"16",
    "gn:admin2_code":"1603.0",
    "gn:admin3_code":"160302.0",
    "gn:asciiname":"Santa Teresa",
    "gn:country_code":"PE",
    "gn:dem":117,
    "gn:feature_class":"P",
    "gn:feature_code":"PPL",
    "gn:name":"Santa Teresa",
    "gn:population":0,
    "gn:timezone":"America/Lima",
    "iso:country":"PE",
    "wof:name":"Santa Teresa",
    "wof:placetype":"locality"
},
  "geometry": {"coordinates":[-74.09999999999999,-4.93333],"type":"Point"}
}