{
  "type": "Feature",
  "properties": {
    "gn:admin1_code":"9.0",
    "gn:admin2_code":"905.0",
    "gn:admin3_code":"90510.0",
    "gn:asciiname":"Leclepata",
    "gn:country_code":"PE",
    "gn:dem":2904,
    "gn:feature_class":"P",
    "gn:feature_code":"PPL",
    "gn:name":"Leclepata",
    "gn:population":0,
    "gn:timezone":"America/Lima",
    "iso:country":"PE",
    "wof:name":"Leclepata",
    "wof:placetype":"locality"
},
  "geometry": {"coordinates":[-74.52831999999999,-12.52431],"type":"Point"}
}