{
  "type": "Feature",
  "properties": {
    "gn:admin1_code":"20",
    "gn:admin2_code":"2001.0",
    "gn:admin3_code":"200105.0",
    "gn:asciiname":"Cumbibira",
    "gn:country_code":"PE",
    "gn:dem":21,
    "gn:feature_class":"P",
    "gn:feature_code":"PPL",
    "gn:name":"Cumbibir\u00e1",
    "gn:population":0,
    "gn:timezone":"America/Lima",
    "iso:country":"PE",
    "name:und_x_variant":[
        "Cumbibir\u00e1 Hacienda",
        "Cumbibir\u00e1"
    ],
    "wof:name":"Cumbibira",
    "wof:placetype":"locality"
},
  "geometry": {"coordinates":[-80.74327,-5.28105],"type":"Point"}
}