{
  "type": "Feature",
  "properties": {
    "gn:admin1_code":"18",
    "gn:admin2_code":"1803.0",
    "gn:admin3_code":"180303.0",
    "gn:asciiname":"Mostazal",
    "gn:country_code":"PE",
    "gn:dem":19,
    "gn:feature_class":"P",
    "gn:feature_code":"PPL",
    "gn:name":"Mostazal",
    "gn:population":0,
    "gn:timezone":"America/Lima",
    "iso:country":"PE",
    "name:und_x_variant":[
        "Mostazal Hacienda",
        "Mostazal"
    ],
    "wof:name":"Mostazal",
    "wof:placetype":"locality"
},
  "geometry": {"coordinates":[-71.33872,-17.61884],"type":"Point"}
}