{
  "type": "Feature",
  "properties": {
    "gn:admin1_code":"20",
    "gn:admin2_code":"2003.0",
    "gn:admin3_code":"200302.0",
    "gn:asciiname":"Las Minas",
    "gn:country_code":"PE",
    "gn:dem":2637,
    "gn:feature_class":"P",
    "gn:feature_code":"PPL",
    "gn:name":"Las Minas",
    "gn:population":0,
    "gn:timezone":"America/Lima",
    "iso:country":"PE",
    "name:ceb_x_preferred":[
        "Las Minas"
    ],
    "name:deu_x_preferred":[
        "Las Minas"
    ],
    "name:spa_x_preferred":[
        "Las Minas"
    ],
    "name:swe_x_preferred":[
        "Las Minas"
    ],
    "wof:name":"Las Minas",
    "wof:placetype":"locality"
},
  "geometry": {"coordinates":[-79.56416999999998,-5.36278],"type":"Point"}
}