{
  "type": "Feature",
  "properties": {
    "gn:admin1_code":"12.0",
    "gn:admin2_code":"1208.0",
    "gn:admin3_code":"120802.0",
    "gn:asciiname":"Nununllalo",
    "gn:country_code":"PE",
    "gn:dem":3852,
    "gn:feature_class":"P",
    "gn:feature_code":"PPL",
    "gn:name":"Nununllalo",
    "gn:population":0,
    "gn:timezone":"America/Lima",
    "iso:country":"PE",
    "wof:name":"Nununllalo",
    "wof:placetype":"locality"
},
  "geometry": {"coordinates":[-75.79770000000001,-11.67789],"type":"Point"}
}