{
  "type": "Feature",
  "properties": {
    "gn:admin1_code":"04",
    "gn:admin2_code":"405.0",
    "gn:admin3_code":"40519.0",
    "gn:asciiname":"Sueterapa Pata",
    "gn:country_code":"PE",
    "gn:dem":3403,
    "gn:feature_class":"P",
    "gn:feature_code":"PPL",
    "gn:name":"Sueterapa Pata",
    "gn:population":0,
    "gn:timezone":"America/Lima",
    "iso:country":"PE",
    "wof:name":"Sueterapa Pata",
    "wof:placetype":"locality"
},
  "geometry": {"coordinates":[-71.6765,-15.6635],"type":"Point"}
}