{
  "type": "Feature",
  "properties": {
    "gn:admin1_code":"10",
    "gn:admin2_code":"1002.0",
    "gn:admin3_code":"100203.0",
    "gn:asciiname":"Candercanchi",
    "gn:country_code":"PE",
    "gn:dem":3826,
    "gn:feature_class":"P",
    "gn:feature_code":"PPL",
    "gn:name":"Candercanchi",
    "gn:population":0,
    "gn:timezone":"America/Lima",
    "iso:country":"PE",
    "wof:name":"Candercanchi",
    "wof:placetype":"locality"
},
  "geometry": {"coordinates":[-76.47946,-10.25077],"type":"Point"}
}