{
  "type": "Feature",
  "properties": {
    "gn:admin1_code":"19.0",
    "gn:admin2_code":"1902.0",
    "gn:asciiname":"Mesapata",
    "gn:country_code":"PE",
    "gn:dem":4298,
    "gn:feature_class":"P",
    "gn:feature_code":"PPL",
    "gn:name":"Mesapata",
    "gn:population":0,
    "gn:timezone":"America/Lima",
    "iso:country":"PE",
    "wof:name":"Mesapata",
    "wof:placetype":"locality"
},
  "geometry": {"coordinates":[-76.62306,-10.37528],"type":"Point"}
}