{
  "type": "Feature",
  "properties": {
    "gn:admin1_code":"09",
    "gn:admin2_code":"906.0",
    "gn:admin3_code":"90607.0",
    "gn:asciiname":"Curiray",
    "gn:country_code":"PE",
    "gn:dem":3892,
    "gn:feature_class":"P",
    "gn:feature_code":"PPL",
    "gn:name":"Curiray",
    "gn:population":0,
    "gn:timezone":"America/Lima",
    "iso:country":"PE",
    "wof:name":"Curiray",
    "wof:placetype":"locality"
},
  "geometry": {"coordinates":[-74.91264,-13.59475],"type":"Point"}
}