{
  "type": "Feature",
  "properties": {
    "gn:admin1_code":"14.0",
    "gn:admin2_code":"1402.0",
    "gn:admin3_code":"140205.0",
    "gn:asciiname":"La Supo",
    "gn:country_code":"PE",
    "gn:dem":37,
    "gn:feature_class":"P",
    "gn:feature_code":"PPL",
    "gn:name":"La Supo",
    "gn:population":0,
    "gn:timezone":"America/Lima",
    "iso:country":"PE",
    "name:spa_x_preferred":[
        "La Supo"
    ],
    "wof:name":"La Supo",
    "wof:placetype":"locality"
},
  "geometry": {"coordinates":[-79.82426,-6.56007],"type":"Point"}
}