{
  "type": "Feature",
  "properties": {
    "gn:admin1_code":"01",
    "gn:admin2_code":"104.0",
    "gn:admin3_code":"10403.0",
    "gn:asciiname":"Sambis",
    "gn:country_code":"PE",
    "gn:dem":269,
    "gn:feature_class":"P",
    "gn:feature_code":"PPL",
    "gn:name":"Sambis",
    "gn:population":0,
    "gn:timezone":"America/Lima",
    "iso:country":"PE",
    "wof:name":"Sambis",
    "wof:placetype":"locality"
},
  "geometry": {"coordinates":[-77.92765,-3.07622],"type":"Point"}
}