{
  "type": "Feature",
  "properties": {
    "gn:admin1_code":"06",
    "gn:admin2_code":"604.0",
    "gn:asciiname":"Succha",
    "gn:country_code":"PE",
    "gn:dem":2639,
    "gn:feature_class":"P",
    "gn:feature_code":"PPL",
    "gn:name":"Succha",
    "gn:population":0,
    "gn:timezone":"America/Lima",
    "iso:country":"PE",
    "wof:name":"Succha",
    "wof:placetype":"locality"
},
  "geometry": {"coordinates":[-79.33587,-6.28955],"type":"Point"}
}