{
  "type": "Feature",
  "properties": {
    "gn:admin1_code":"05",
    "gn:admin2_code":"501.0",
    "gn:admin3_code":"50114.0",
    "gn:asciiname":"Paccha",
    "gn:country_code":"PE",
    "gn:dem":3281,
    "gn:feature_class":"P",
    "gn:feature_code":"PPL",
    "gn:name":"Paccha",
    "gn:population":0,
    "gn:timezone":"America/Lima",
    "iso:country":"PE",
    "name:que_x_preferred":[
        "Pakcha kitilli"
    ],
    "wof:name":"Paccha",
    "wof:placetype":"locality"
},
  "geometry": {"coordinates":[-74.40463000000003,-13.20537],"type":"Point"}
}