{
  "type": "Feature",
  "properties": {
    "gn:admin1_code":"12.0",
    "gn:admin2_code":"1204.0",
    "gn:admin3_code":"120403.0",
    "gn:asciiname":"Illaccancha",
    "gn:country_code":"PE",
    "gn:dem":3931,
    "gn:feature_class":"P",
    "gn:feature_code":"PPL",
    "gn:name":"Illaccancha",
    "gn:population":0,
    "gn:timezone":"America/Lima",
    "iso:country":"PE",
    "wof:name":"Illaccancha",
    "wof:placetype":"locality"
},
  "geometry": {"coordinates":[-75.31829,-11.79665],"type":"Point"}
}