{
  "type": "Feature",
  "properties": {
    "gn:admin1_code":"05",
    "gn:admin2_code":"502.0",
    "gn:admin3_code":"50202.0",
    "gn:asciiname":"Jatun Jarhuay",
    "gn:country_code":"PE",
    "gn:dem":4389,
    "gn:feature_class":"P",
    "gn:feature_code":"PPL",
    "gn:name":"Jatun Jarhuay",
    "gn:population":0,
    "gn:timezone":"America/Lima",
    "iso:country":"PE",
    "name:und_x_variant":[
        "Jatunjarhuay"
    ],
    "wof:name":"Jatun Jarhuay",
    "wof:placetype":"locality"
},
  "geometry": {"coordinates":[-74.51499,-13.48294],"type":"Point"}
}