{
  "type": "Feature",
  "properties": {
    "gn:admin1_code":"8",
    "gn:admin2_code":"805.0",
    "gn:admin3_code":"80502.0",
    "gn:asciiname":"Tantabanda",
    "gn:country_code":"PE",
    "gn:dem":3882,
    "gn:feature_class":"P",
    "gn:feature_code":"PPL",
    "gn:name":"Tantabanda",
    "gn:population":0,
    "gn:timezone":"America/Lima",
    "iso:country":"PE",
    "wof:name":"Tantabanda",
    "wof:placetype":"locality"
},
  "geometry": {"coordinates":[-71.47388000000002,-14.42357],"type":"Point"}
}