{
  "type": "Feature",
  "properties": {
    "gn:admin1_code":"2.0",
    "gn:admin2_code":"217.0",
    "gn:admin3_code":"21702.0",
    "gn:asciiname":"Yanahuanca",
    "gn:country_code":"PE",
    "gn:dem":4069,
    "gn:feature_class":"P",
    "gn:feature_code":"PPL",
    "gn:name":"Yanahuanca",
    "gn:population":0,
    "gn:timezone":"America/Lima",
    "iso:country":"PE",
    "name:aym_x_preferred":[
        "Yanawanka"
    ],
    "name:que_x_preferred":[
        "Yanawanka"
    ],
    "name:spa_x_preferred":[
        "Yanahuanca"
    ],
    "name:urd_x_preferred":[
        "\u06cc\u0627\u0646\u06c1\u06be\u0627\u0646\u06a9\u0627"
    ],
    "name:war_x_preferred":[
        "Yanahuanca"
    ],
    "name:zho_x_preferred":[
        "\u4e9e\u7d0d\u842c\u5361"
    ],
    "wof:name":"Yanahuanca",
    "wof:placetype":"locality"
},
  "geometry": {"coordinates":[-77.28773000000002,-10.03415],"type":"Point"}
}