{
  "type": "Feature",
  "properties": {
    "gn:admin1_code":"15",
    "gn:admin2_code":"1506.0",
    "gn:admin3_code":"150606.0",
    "gn:asciiname":"Yauringa",
    "gn:country_code":"PE",
    "gn:dem":1701,
    "gn:feature_class":"P",
    "gn:feature_code":"PPL",
    "gn:name":"Yauringa",
    "gn:population":0,
    "gn:timezone":"America/Lima",
    "iso:country":"PE",
    "wof:name":"Yauringa",
    "wof:placetype":"locality"
},
  "geometry": {"coordinates":[-77.02056,-11.13583],"type":"Point"}
}