{
  "type": "Feature",
  "properties": {
    "gn:admin1_code":"8",
    "gn:admin2_code":"809.0",
    "gn:admin3_code":"80902.0",
    "gn:asciiname":"Lucmapata",
    "gn:country_code":"PE",
    "gn:dem":1516,
    "gn:feature_class":"P",
    "gn:feature_code":"PPL",
    "gn:name":"Lucmapata",
    "gn:population":0,
    "gn:timezone":"America/Lima",
    "iso:country":"PE",
    "wof:name":"Lucmapata",
    "wof:placetype":"locality"
},
  "geometry": {"coordinates":[-72.59534000000002,-12.82075],"type":"Point"}
}