{
  "type": "Feature",
  "properties": {
    "gn:admin1_code":"8",
    "gn:admin2_code":"808.0",
    "gn:admin3_code":"80801.0",
    "gn:asciiname":"Pacrapucra",
    "gn:country_code":"PE",
    "gn:dem":4212,
    "gn:feature_class":"P",
    "gn:feature_code":"PPL",
    "gn:name":"Pacrapucra",
    "gn:population":0,
    "gn:timezone":"America/Lima",
    "iso:country":"PE",
    "wof:name":"Pacrapucra",
    "wof:placetype":"locality"
},
  "geometry": {"coordinates":[-71.248,-15.00756],"type":"Point"}
}