{
  "type": "Feature",
  "properties": {
    "gn:admin1_code":"17.0",
    "gn:admin2_code":"1703.0",
    "gn:asciiname":"Ramal",
    "gn:country_code":"PE",
    "gn:dem":311,
    "gn:feature_class":"P",
    "gn:feature_code":"PPL",
    "gn:name":"Ramal",
    "gn:population":0,
    "gn:timezone":"America/Lima",
    "iso:country":"PE",
    "name:azb_x_preferred":[
        "\u0631\u0627\u0645\u0627\u0644"
    ],
    "name:aze_x_preferred":[
        "Ramal"
    ],
    "name:ceb_x_preferred":[
        "Ramal"
    ],
    "name:fas_x_preferred":[
        "\u0631\u0627\u0645\u0627\u0644"
    ],
    "name:ita_x_preferred":[
        "Ramal"
    ],
    "name:msa_x_preferred":[
        "Ramal"
    ],
    "name:spa_x_preferred":[
        "Ramal"
    ],
    "name:swe_x_preferred":[
        "Ramal"
    ],
    "wof:name":"Ramal",
    "wof:placetype":"locality"
},
  "geometry": {"coordinates":[-69.39843,-11.35805],"type":"Point"}
}