{
  "type": "Feature",
  "properties": {
    "gn:admin1_code":"9.0",
    "gn:admin2_code":"907.0",
    "gn:admin3_code":"90715.0",
    "gn:asciiname":"Yurac Allpa",
    "gn:country_code":"PE",
    "gn:dem":3132,
    "gn:feature_class":"P",
    "gn:feature_code":"PPL",
    "gn:name":"Yurac Allpa",
    "gn:population":0,
    "gn:timezone":"America/Lima",
    "iso:country":"PE",
    "wof:name":"Yurac Allpa",
    "wof:placetype":"locality"
},
  "geometry": {"coordinates":[-74.75508000000001,-12.14518],"type":"Point"}
}