{
  "type": "Feature",
  "properties": {
    "gn:admin1_code":"06",
    "gn:admin2_code":"604.0",
    "gn:admin3_code":"60415.0",
    "gn:asciiname":"Tabacal",
    "gn:country_code":"PE",
    "gn:dem":2267,
    "gn:feature_class":"P",
    "gn:feature_code":"PPL",
    "gn:name":"Tabacal",
    "gn:population":0,
    "gn:timezone":"America/Lima",
    "iso:country":"PE",
    "wof:name":"Tabacal",
    "wof:placetype":"locality"
},
  "geometry": {"coordinates":[-79.01392,-6.38814],"type":"Point"}
}