{
  "type": "Feature",
  "properties": {
    "gn:admin1_code":"5",
    "gn:admin2_code":"509.0",
    "gn:admin3_code":"50906.0",
    "gn:asciiname":"Ojoruyoc",
    "gn:country_code":"PE",
    "gn:dem":3920,
    "gn:feature_class":"P",
    "gn:feature_code":"PPL",
    "gn:name":"Ojoruyoc",
    "gn:population":0,
    "gn:timezone":"America/Lima",
    "iso:country":"PE",
    "wof:name":"Ojoruyoc",
    "wof:placetype":"locality"
},
  "geometry": {"coordinates":[-73.81889,-14.14833],"type":"Point"}
}