{
  "type": "Feature",
  "properties": {
    "gn:admin1_code":"13",
    "gn:admin2_code":"1310.0",
    "gn:admin3_code":"131008.0",
    "gn:asciiname":"Huancabamba",
    "gn:country_code":"PE",
    "gn:dem":3108,
    "gn:feature_class":"P",
    "gn:feature_code":"PPL",
    "gn:name":"Huancabamba",
    "gn:population":0,
    "gn:timezone":"America/Lima",
    "iso:country":"PE",
    "name:fra_x_preferred":[
        "Huancabamba"
    ],
    "name:ita_x_preferred":[
        "Huancabamba"
    ],
    "name:que_x_preferred":[
        "Wankapampa"
    ],
    "name:spa_x_preferred":[
        "Huancabamba"
    ],
    "name:war_x_preferred":[
        "Huancabamba"
    ],
    "name:zho_x_preferred":[
        "\u5b9b\u5361\u73ed\u5df4"
    ],
    "wof:name":"Huancabamba",
    "wof:placetype":"locality"
},
  "geometry": {"coordinates":[-77.73833,-8.00769],"type":"Point"}
}