{
  "type": "Feature",
  "properties": {
    "gn:admin1_code":"10",
    "gn:admin2_code":"1002.0",
    "gn:asciiname":"Huertas",
    "gn:country_code":"PE",
    "gn:dem":2337,
    "gn:feature_class":"P",
    "gn:feature_code":"PPL",
    "gn:name":"Huertas",
    "gn:population":0,
    "gn:timezone":"America/Lima",
    "iso:country":"PE",
    "name:und_x_variant":[
        "Hacienda Huertas",
        "Huertas"
    ],
    "wof:name":"Huertas",
    "wof:placetype":"locality"
},
  "geometry": {"coordinates":[-76.33956999999999,-10.28608],"type":"Point"}
}