{
  "type": "Feature",
  "properties": {
    "gn:admin1_code":"2.0",
    "gn:admin2_code":"217.0",
    "gn:admin3_code":"21702.0",
    "gn:asciiname":"Llama Cancha",
    "gn:country_code":"PE",
    "gn:dem":4096,
    "gn:feature_class":"P",
    "gn:feature_code":"PPL",
    "gn:name":"Llama Cancha",
    "gn:population":0,
    "gn:timezone":"America/Lima",
    "iso:country":"PE",
    "wof:name":"Llama Cancha",
    "wof:placetype":"locality"
},
  "geometry": {"coordinates":[-77.30809000000001,-10.00466],"type":"Point"}
}