{
  "type": "Feature",
  "properties": {
    "gn:admin1_code":"13",
    "gn:admin2_code":"1302.0",
    "gn:admin3_code":"130202.0",
    "gn:asciiname":"Cerro Minas",
    "gn:country_code":"PE",
    "gn:dem":1975,
    "gn:feature_class":"P",
    "gn:feature_code":"PPL",
    "gn:name":"Cerro Minas",
    "gn:population":0,
    "gn:timezone":"America/Lima",
    "iso:country":"PE",
    "wof:name":"Cerro Minas",
    "wof:placetype":"locality"
},
  "geometry": {"coordinates":[-78.90000000000001,-7.83333],"type":"Point"}
}