{
  "type": "Feature",
  "properties": {
    "gn:admin1_code":"2.0",
    "gn:admin2_code":"205.0",
    "gn:admin3_code":"20502.0",
    "gn:asciiname":"Remate",
    "gn:country_code":"PE",
    "gn:dem":2194,
    "gn:feature_class":"P",
    "gn:feature_code":"PPL",
    "gn:name":"Remate",
    "gn:population":0,
    "gn:timezone":"America/Lima",
    "iso:country":"PE",
    "wof:name":"Remate",
    "wof:placetype":"locality"
},
  "geometry": {"coordinates":[-77.14914,-10.30774],"type":"Point"}
}