{
  "type": "Feature",
  "properties": {
    "gn:admin1_code":"12",
    "gn:admin2_code":"1207.0",
    "gn:admin3_code":"120708.0",
    "gn:asciiname":"Ucuruyoc",
    "gn:country_code":"PE",
    "gn:dem":4424,
    "gn:feature_class":"P",
    "gn:feature_code":"PPL",
    "gn:name":"Ucuruyoc",
    "gn:population":0,
    "gn:timezone":"America/Lima",
    "iso:country":"PE",
    "wof:name":"Ucuruyoc",
    "wof:placetype":"locality"
},
  "geometry": {"coordinates":[-75.88523000000001,-11.17679],"type":"Point"}
}