{
  "type": "Feature",
  "properties": {
    "gn:admin1_code":"1.0",
    "gn:admin2_code":"101.0",
    "gn:admin3_code":"10103.0",
    "gn:asciiname":"Siete Lagunas",
    "gn:country_code":"PE",
    "gn:dem":3982,
    "gn:feature_class":"P",
    "gn:feature_code":"PPLL",
    "gn:name":"Siete Lagunas",
    "gn:population":0,
    "gn:timezone":"America/Lima",
    "iso:country":"PE",
    "name:und_x_variant":[
        "7 Lagunas",
        "Siete Lagunas"
    ],
    "wof:name":"Siete Lagunas",
    "wof:placetype":"locality"
},
  "geometry": {"coordinates":[-77.8809,-6.83424],"type":"Point"}
}