{
  "type": "Feature",
  "properties": {
    "gn:admin1_code":"15",
    "gn:admin2_code":"1506.0",
    "gn:admin3_code":"150604.0",
    "gn:asciiname":"Quilca",
    "gn:country_code":"PE",
    "gn:dem":796,
    "gn:feature_class":"P",
    "gn:feature_code":"PPL",
    "gn:name":"Quilca",
    "gn:population":0,
    "gn:timezone":"America/Lima",
    "iso:country":"PE",
    "name:und_x_variant":[
        "Hacienda Quilca",
        "Quilca Hacienda",
        "Quilca"
    ],
    "wof:name":"Quilca",
    "wof:placetype":"locality"
},
  "geometry": {"coordinates":[-76.99405,-11.50957],"type":"Point"}
}