{
  "type": "Feature",
  "properties": {
    "gn:country":"PE",
    "gn:fcode":"PPLA3",
    "gn:population":3811,
    "iso:country":"PE",
    "name:deu_x_preferred":[
        "Distrikt Pampamarca"
    ],
    "name:eng_x_preferred":[
        "Pampamarca District"
    ],
    "name:kat_x_preferred":[
        "\u10de\u10d0\u10db\u10de\u10d0\u10db\u10d0\u10e0\u10d9\u10d8\u10e1 \u10e0\u10d0\u10d8\u10dd\u10dc\u10d8"
    ],
    "name:nld_x_preferred":[
        "Pampamarca District"
    ],
    "name:por_x_preferred":[
        "Pampamarca"
    ],
    "name:que_x_preferred":[
        "Pampamarka distritu"
    ],
    "name:zho_x_preferred":[
        "\u6f58\u5e15\u99ac\u5361\u5340"
    ],
    "qs:name":"Pampamarca",
    "qs:photos_9r":0,
    "qs:photos_sr":0,
    "qs:pop_sr":"4",
    "wd:wordcount":95,
    "wof:name":"Pampamarca",
    "wof:placetype":"locality",
    "wof:population":3811
},
  "geometry": {"coordinates":[-71.45944,-14.14639],"type":"Point"}
}