{
  "type": "Feature",
  "properties": {
    "gn:country":"PE",
    "gn:fcode":"PPLA3",
    "gn:pop":3811,
    "iso:country":"PE",
    "qs:name":"Pampamarca",
    "qs:photos_9r":0,
    "qs:photos_sr":0,
    "qs:pop_sr":"4",
    "wd:wordcount":95,
    "wof:name":"Pampamarca",
    "wof:placetype":"locality",
    "wof:population":3811
},
  "geometry": {"coordinates":[-71.45944,-14.14639],"type":"Point"}
}