{
  "type": "Feature",
  "properties": {
    "gn:admin1_code":"14",
    "gn:admin2_code":"1401.0",
    "gn:admin3_code":"140107.0",
    "gn:asciiname":"San Aurelio",
    "gn:country_code":"PE",
    "gn:dem":36,
    "gn:feature_class":"P",
    "gn:feature_code":"PPL",
    "gn:name":"San Aurelio",
    "gn:population":0,
    "gn:timezone":"America/Lima",
    "iso:country":"PE",
    "name:spa_x_preferred":[
        "San Aurelio"
    ],
    "wof:name":"San Aurelio",
    "wof:placetype":"locality"
},
  "geometry": {"coordinates":[-79.62796999999998,-6.98912],"type":"Point"}
}