{
  "type": "Feature",
  "properties": {
    "gn:admin1_code":"15",
    "gn:admin2_code":"1505.0",
    "gn:admin3_code":"150503.0",
    "gn:asciiname":"Correviento Bajo",
    "gn:country_code":"PE",
    "gn:dem":215,
    "gn:feature_class":"P",
    "gn:feature_code":"PPL",
    "gn:name":"Correviento Bajo",
    "gn:population":0,
    "gn:timezone":"America/Lima",
    "iso:country":"PE",
    "wof:name":"Correviento Bajo",
    "wof:placetype":"locality"
},
  "geometry": {"coordinates":[-76.58698000000003,-12.53867],"type":"Point"}
}