{
  "type": "Feature",
  "properties": {
    "gn:admin1_code":"10.0",
    "gn:admin2_code":"1005.0",
    "gn:asciiname":"Auquicorral",
    "gn:country_code":"PE",
    "gn:dem":4256,
    "gn:feature_class":"P",
    "gn:feature_code":"PPL",
    "gn:name":"Auquicorral",
    "gn:population":0,
    "gn:timezone":"America/Lima",
    "iso:country":"PE",
    "wof:name":"Auquicorral",
    "wof:placetype":"locality"
},
  "geometry": {"coordinates":[-76.91854000000002,-9.44894],"type":"Point"}
}