{
  "type": "Feature",
  "properties": {
    "gn:admin1_code":"8.0",
    "gn:admin2_code":"803.0",
    "gn:admin3_code":"80301.0",
    "gn:asciiname":"Ocoruro",
    "gn:country_code":"PE",
    "gn:dem":3329,
    "gn:feature_class":"P",
    "gn:feature_code":"PPL",
    "gn:name":"Ocoruro",
    "gn:population":0,
    "gn:timezone":"America/Lima",
    "iso:country":"PE",
    "wof:name":"Ocoruro",
    "wof:placetype":"locality"
},
  "geometry": {"coordinates":[-72.16889,-13.45972],"type":"Point"}
}