{
  "type": "Feature",
  "properties": {
    "gn:admin1_code":"04",
    "gn:admin2_code":"405.0",
    "gn:admin3_code":"40505.0",
    "gn:asciiname":"Flor del Mundo",
    "gn:country_code":"PE",
    "gn:dem":4765,
    "gn:feature_class":"P",
    "gn:feature_code":"PPL",
    "gn:name":"Flor del Mundo",
    "gn:population":0,
    "gn:timezone":"America/Lima",
    "iso:country":"PE",
    "wof:name":"Flor del Mundo",
    "wof:placetype":"locality"
},
  "geometry": {"coordinates":[-71.85599000000001,-15.18272],"type":"Point"}
}