{
  "type": "Feature",
  "properties": {
    "gn:admin1_code":"23",
    "gn:admin2_code":"2304.0",
    "gn:admin3_code":"230401.0",
    "gn:asciiname":"Chiluyo Grande",
    "gn:country_code":"PE",
    "gn:dem":4287,
    "gn:feature_class":"P",
    "gn:feature_code":"PPL",
    "gn:name":"Chiluyo Grande",
    "gn:population":0,
    "gn:timezone":"America/Lima",
    "iso:country":"PE",
    "wof:name":"Chiluyo Grande",
    "wof:placetype":"locality"
},
  "geometry": {"coordinates":[-69.65314000000001,-17.35414],"type":"Point"}
}