{
  "type": "Feature",
  "properties": {
    "gn:admin1_code":"15",
    "gn:admin2_code":"1504.0",
    "gn:admin3_code":"150401.0",
    "gn:asciiname":"Torocancha",
    "gn:country_code":"PE",
    "gn:dem":3768,
    "gn:feature_class":"P",
    "gn:feature_code":"PPL",
    "gn:name":"Torocancha",
    "gn:population":0,
    "gn:timezone":"America/Lima",
    "iso:country":"PE",
    "wof:name":"Torocancha",
    "wof:placetype":"locality"
},
  "geometry": {"coordinates":[-76.58278,-11.43833],"type":"Point"}
}