{
  "type": "Feature",
  "properties": {
    "gn:admin1_code":"08",
    "gn:admin2_code":"805.0",
    "gn:admin3_code":"80505.0",
    "gn:asciiname":"Quelcapampa",
    "gn:cc2":"PE",
    "gn:country_code":"PE",
    "gn:dem":3971,
    "gn:feature_class":"P",
    "gn:feature_code":"PPL",
    "gn:name":"Quelcapampa",
    "gn:population":0,
    "gn:timezone":"America/Lima",
    "iso:country":"PE",
    "name:und_x_variant":[
        "Quellcapampa",
        "Quelcapampa"
    ],
    "wof:name":"Quelcapampa",
    "wof:placetype":"locality"
},
  "geometry": {"coordinates":[-71.15000000000001,-14.51667],"type":"Point"}
}