{
  "type": "Feature",
  "properties": {
    "gn:admin1_code":"21",
    "gn:admin2_code":"2104.0",
    "gn:admin3_code":"210403.0",
    "gn:asciiname":"Yorocco",
    "gn:country_code":"PE",
    "gn:dem":3943,
    "gn:feature_class":"P",
    "gn:feature_code":"PPL",
    "gn:name":"Yorocco",
    "gn:population":0,
    "gn:timezone":"America/Lima",
    "iso:country":"PE",
    "wof:name":"Yorocco",
    "wof:placetype":"locality"
},
  "geometry": {"coordinates":[-69.32812,-16.55102],"type":"Point"}
}