{
  "type": "Feature",
  "properties": {
    "gn:admin1_code":"05",
    "gn:admin2_code":"506.0",
    "gn:admin3_code":"50611.0",
    "gn:asciiname":"Tambochayoc",
    "gn:country_code":"PE",
    "gn:dem":4119,
    "gn:feature_class":"P",
    "gn:feature_code":"PPL",
    "gn:name":"Tambochayoc",
    "gn:population":0,
    "gn:timezone":"America/Lima",
    "iso:country":"PE",
    "wof:name":"Tambochayoc",
    "wof:placetype":"locality"
},
  "geometry": {"coordinates":[-74.28333000000001,-14.68333],"type":"Point"}
}