{
  "type": "Feature",
  "properties": {
    "gn:admin1_code":"15",
    "gn:admin2_code":"1510.0",
    "gn:admin3_code":"151031.0",
    "gn:asciiname":"Chucullo",
    "gn:country_code":"PE",
    "gn:dem":4575,
    "gn:feature_class":"P",
    "gn:feature_code":"PPL",
    "gn:name":"Chucullo",
    "gn:population":0,
    "gn:timezone":"America/Lima",
    "iso:country":"PE",
    "wof:name":"Chucullo",
    "wof:placetype":"locality"
},
  "geometry": {"coordinates":[-75.60429000000001,-12.6021],"type":"Point"}
}