{
  "type": "Feature",
  "properties": {
    "gn:admin1_code":"15",
    "gn:admin2_code":"1505.0",
    "gn:admin3_code":"150506.0",
    "gn:asciiname":"Quisque",
    "gn:country_code":"PE",
    "gn:dem":189,
    "gn:feature_class":"P",
    "gn:feature_code":"PPL",
    "gn:name":"Quisque",
    "gn:population":0,
    "gn:timezone":"America/Lima",
    "iso:country":"PE",
    "name:und_x_variant":[
        "San Juan de Quisque",
        "Quisque"
    ],
    "wof:name":"Quisque",
    "wof:placetype":"locality"
},
  "geometry": {"coordinates":[-76.49256,-12.74912],"type":"Point"}
}