{
  "type": "Feature",
  "properties": {
    "gn:admin1_code":"17.0",
    "gn:admin2_code":"1703.0",
    "gn:asciiname":"Ignacio Mazola",
    "gn:country_code":"PE",
    "gn:dem":275,
    "gn:feature_class":"P",
    "gn:feature_code":"PPL",
    "gn:name":"Ignacio Mazola",
    "gn:population":0,
    "gn:timezone":"America/Lima",
    "iso:country":"PE",
    "name:spa_x_preferred":[
        "Ignacio Mazola"
    ],
    "wof:name":"Ignacio Mazola",
    "wof:placetype":"locality"
},
  "geometry": {"coordinates":[-69.21669,-11.65545],"type":"Point"}
}