{
  "type": "Feature",
  "properties": {
    "gn:admin1_code":"12",
    "gn:admin2_code":"1203.0",
    "gn:admin3_code":"120302.0",
    "gn:asciiname":"Shankivironi",
    "gn:country_code":"PE",
    "gn:dem":509,
    "gn:feature_class":"P",
    "gn:feature_code":"PPL",
    "gn:name":"Shankivironi",
    "gn:population":0,
    "gn:timezone":"America/Lima",
    "iso:country":"PE",
    "name:spa_x_preferred":[
        "Shankivironi"
    ],
    "wof:name":"Shankivironi",
    "wof:placetype":"locality"
},
  "geometry": {"coordinates":[-74.93868000000001,-10.89115],"type":"Point"}
}