{
  "type": "Feature",
  "properties": {
    "gn:admin1_code":"12",
    "gn:admin2_code":"1209.0",
    "gn:admin3_code":"120909.0",
    "gn:asciiname":"Tuctopampa",
    "gn:country_code":"PE",
    "gn:dem":4339,
    "gn:feature_class":"P",
    "gn:feature_code":"PPL",
    "gn:name":"Tuctopampa",
    "gn:population":0,
    "gn:timezone":"America/Lima",
    "iso:country":"PE",
    "wof:name":"Tuctopampa",
    "wof:placetype":"locality"
},
  "geometry": {"coordinates":[-75.54444000000002,-12.21611],"type":"Point"}
}