{
  "type": "Feature",
  "properties": {
    "gn:admin1_code":"5",
    "gn:admin2_code":"509.0",
    "gn:admin3_code":"50908.0",
    "gn:asciiname":"Puyhuascha",
    "gn:country_code":"PE",
    "gn:dem":4135,
    "gn:feature_class":"P",
    "gn:feature_code":"PPL",
    "gn:name":"Puyhuascha",
    "gn:population":0,
    "gn:timezone":"America/Lima",
    "iso:country":"PE",
    "wof:name":"Puyhuascha",
    "wof:placetype":"locality"
},
  "geometry": {"coordinates":[-73.6375,-14.32028],"type":"Point"}
}