{
  "type": "Feature",
  "properties": {
    "gn:admin1_code":"05",
    "gn:admin2_code":"503.0",
    "gn:admin3_code":"50304.0",
    "gn:asciiname":"Chucupalla",
    "gn:country_code":"PE",
    "gn:dem":3411,
    "gn:feature_class":"P",
    "gn:feature_code":"PPL",
    "gn:name":"Chucupalla",
    "gn:population":0,
    "gn:timezone":"America/Lima",
    "iso:country":"PE",
    "wof:name":"Chucupalla",
    "wof:placetype":"locality"
},
  "geometry": {"coordinates":[-74.36667,-13.83333],"type":"Point"}
}