{
  "type": "Feature",
  "properties": {
    "gn:admin1_code":"11",
    "gn:admin2_code":"1101.0",
    "gn:admin3_code":"110114.0",
    "gn:asciiname":"Huachac Monte",
    "gn:country_code":"PE",
    "gn:dem":1507,
    "gn:feature_class":"P",
    "gn:feature_code":"PPL",
    "gn:name":"Huachac Monte",
    "gn:population":0,
    "gn:timezone":"America/Lima",
    "iso:country":"PE",
    "wof:name":"Huachac Monte",
    "wof:placetype":"locality"
},
  "geometry": {"coordinates":[-75.38056,-14.01889],"type":"Point"}
}