{
  "type": "Feature",
  "properties": {
    "gn:admin1_code":"10",
    "gn:admin2_code":"1002.0",
    "gn:admin3_code":"100207.0",
    "gn:asciiname":"Chacatama",
    "gn:country_code":"PE",
    "gn:dem":3162,
    "gn:feature_class":"P",
    "gn:feature_code":"PPL",
    "gn:name":"Chacatama",
    "gn:population":0,
    "gn:timezone":"America/Lima",
    "iso:country":"PE",
    "wof:name":"Chacatama",
    "wof:placetype":"locality"
},
  "geometry": {"coordinates":[-76.19203,-10.32873],"type":"Point"}
}