{
  "type": "Feature",
  "properties": {
    "gn:admin1_code":"9.0",
    "gn:admin2_code":"907.0",
    "gn:admin3_code":"90715.0",
    "gn:asciiname":"Chota Pata",
    "gn:country_code":"PE",
    "gn:dem":2496,
    "gn:feature_class":"P",
    "gn:feature_code":"PPL",
    "gn:name":"Chota Pata",
    "gn:population":0,
    "gn:timezone":"America/Lima",
    "iso:country":"PE",
    "wof:name":"Chota Pata",
    "wof:placetype":"locality"
},
  "geometry": {"coordinates":[-74.74554000000001,-12.14309],"type":"Point"}
}