{
  "type": "Feature",
  "properties": {
    "gn:admin1_code":"21",
    "gn:admin2_code":"2104.0",
    "gn:admin3_code":"210404.0",
    "gn:asciiname":"Ichocollo",
    "gn:country_code":"PE",
    "gn:dem":3890,
    "gn:feature_class":"P",
    "gn:feature_code":"PPL",
    "gn:name":"Ichocollo",
    "gn:population":0,
    "gn:timezone":"America/Lima",
    "iso:country":"PE",
    "wof:name":"Ichocollo",
    "wof:placetype":"locality"
},
  "geometry": {"coordinates":[-69.21935999999999,-16.79748],"type":"Point"}
}