{
  "type": "Feature",
  "properties": {
    "gn:admin1_code":"20",
    "gn:admin2_code":"2003.0",
    "gn:admin3_code":"200301.0",
    "gn:asciiname":"Pampa De Pasteo",
    "gn:country_code":"PE",
    "gn:dem":1991,
    "gn:feature_class":"P",
    "gn:feature_code":"PPLL",
    "gn:name":"Pampa De Pasteo",
    "gn:population":0,
    "gn:timezone":"America/Lima",
    "iso:country":"PE",
    "wof:name":"Pampa De Pasteo",
    "wof:placetype":"locality"
},
  "geometry": {"coordinates":[-79.44499999999999,-5.25889],"type":"Point"}
}