{
  "type": "Feature",
  "properties": {
    "gn:admin1_code":"12.0",
    "gn:admin2_code":"1208.0",
    "gn:admin3_code":"120807.0",
    "gn:asciiname":"Vicharayoc",
    "gn:country_code":"PE",
    "gn:dem":4336,
    "gn:feature_class":"P",
    "gn:feature_code":"PPL",
    "gn:name":"Vicharayoc",
    "gn:population":0,
    "gn:timezone":"America/Lima",
    "iso:country":"PE",
    "wof:name":"Vicharayoc",
    "wof:placetype":"locality"
},
  "geometry": {"coordinates":[-76.39284000000001,-11.20573],"type":"Point"}
}