{
  "type": "Feature",
  "properties": {
    "gn:admin1_code":"06",
    "gn:admin2_code":"606.0",
    "gn:admin3_code":"60607.0",
    "gn:asciiname":"Sillangate",
    "gn:country_code":"PE",
    "gn:dem":1139,
    "gn:feature_class":"P",
    "gn:feature_code":"PPL",
    "gn:name":"Sillangate",
    "gn:population":0,
    "gn:timezone":"America/Lima",
    "iso:country":"PE",
    "wof:name":"Sillangate",
    "wof:placetype":"locality"
},
  "geometry": {"coordinates":[-79.05,-6.21667],"type":"Point"}
}