{
  "type": "Feature",
  "properties": {
    "gn:admin1_code":"16",
    "gn:admin2_code":"1606.0",
    "gn:admin3_code":"160603.0",
    "gn:asciiname":"Roaboya",
    "gn:country_code":"PE",
    "gn:dem":138,
    "gn:feature_class":"P",
    "gn:feature_code":"PPL",
    "gn:name":"Roaboya",
    "gn:population":0,
    "gn:timezone":"America/Lima",
    "iso:country":"PE",
    "wof:name":"Roaboya",
    "wof:placetype":"locality"
},
  "geometry": {"coordinates":[-74.9263,-7.76006],"type":"Point"}
}