{
  "type": "Feature",
  "properties": {
    "gn:admin1_code":"10",
    "gn:admin2_code":"1002.0",
    "gn:admin3_code":"100205.0",
    "gn:asciiname":"Yuracpirga",
    "gn:country_code":"PE",
    "gn:dem":3417,
    "gn:feature_class":"P",
    "gn:feature_code":"PPL",
    "gn:name":"Yuracpirga",
    "gn:population":0,
    "gn:timezone":"America/Lima",
    "iso:country":"PE",
    "wof:name":"Yuracpirga",
    "wof:placetype":"locality"
},
  "geometry": {"coordinates":[-76.31786,-10.13562],"type":"Point"}
}