{
  "type": "Feature",
  "properties": {
    "gn:admin1_code":"25",
    "gn:admin2_code":"2502.0",
    "gn:admin3_code":"250201.0",
    "gn:asciiname":"Unini",
    "gn:country_code":"PE",
    "gn:dem":276,
    "gn:feature_class":"P",
    "gn:feature_code":"PPL",
    "gn:name":"Unini",
    "gn:population":0,
    "gn:timezone":"America/Lima",
    "iso:country":"PE",
    "name:ara_x_preferred":[
        "\u0623\u0648\u0646\u064a\u0646\u064a"
    ],
    "name:ben_x_preferred":[
        "\u0987\u0989\u09a8\u09bf\u09a8\u09bf"
    ],
    "name:deu_x_preferred":[
        "Rio Unini"
    ],
    "name:ell_x_preferred":[
        "\u039f\u03c5\u03bd\u03af\u03bd\u03b9"
    ],
    "name:fas_x_preferred":[
        "\u06cc\u0648\u0646\u06cc\u0646\u06cc"
    ],
    "name:fra_x_preferred":[
        "Inini"
    ],
    "name:heb_x_preferred":[
        "\u05d0\u05d5\u05e0\u05d9\u05e0\u05d9"
    ],
    "name:hin_x_preferred":[
        "\u092f\u0942\u0928\u093f\u0928\u0940"
    ],
    "name:hun_x_preferred":[
        "Unini"
    ],
    "name:ind_x_preferred":[
        "Unini"
    ],
    "name:ita_x_preferred":[
        "Unini"
    ],
    "name:jpn_x_preferred":[
        "\u30a6\u30cb\u30cb\u5ddd"
    ],
    "name:kor_x_preferred":[
        "\uc720\ub2c8\ub2c8"
    ],
    "name:nld_x_preferred":[
        "Unini"
    ],
    "name:pol_x_preferred":[
        "Unini"
    ],
    "name:por_x_preferred":[
        "Unini"
    ],
    "name:rus_x_preferred":[
        "\u0440\u0435\u043a\u0430 \u0423\u043d\u0438\u043d\u0438"
    ],
    "name:tur_x_preferred":[
        "Unini"
    ],
    "name:ukr_x_preferred":[
        "\u0423\u043d\u0456\u043d\u0456"
    ],
    "name:urd_x_preferred":[
        "\u0627\u0648\u0646\u06cc\u0646\u06cc"
    ],
    "name:vie_x_preferred":[
        "S\u00f4ng Unini"
    ],
    "wof:name":"Unini",
    "wof:placetype":"locality"
},
  "geometry": {"coordinates":[-73.90000000000001,-10.66667],"type":"Point"}
}