{
  "type": "Feature",
  "properties": {
    "gn:admin1_code":"05",
    "gn:admin2_code":"507.0",
    "gn:admin3_code":"50705.0",
    "gn:asciiname":"Pucahuanca",
    "gn:country_code":"PE",
    "gn:dem":2816,
    "gn:feature_class":"P",
    "gn:feature_code":"PPL",
    "gn:name":"Pucahuanca",
    "gn:population":0,
    "gn:timezone":"America/Lima",
    "iso:country":"PE",
    "wof:name":"Pucahuanca",
    "wof:placetype":"locality"
},
  "geometry": {"coordinates":[-74.03206999999998,-15.39865],"type":"Point"}
}