{
  "type": "Feature",
  "properties": {
    "gn:admin1_code":"10",
    "gn:admin2_code":"1008.0",
    "gn:asciiname":"Atoc Huaganan",
    "gn:country_code":"PE",
    "gn:dem":3645,
    "gn:feature_class":"P",
    "gn:feature_code":"PPL",
    "gn:name":"Atoc Huaganan",
    "gn:population":0,
    "gn:timezone":"America/Lima",
    "iso:country":"PE",
    "wof:name":"Atoc Huaganan",
    "wof:placetype":"locality"
},
  "geometry": {"coordinates":[-75.80417,-10.17056],"type":"Point"}
}