{
  "type": "Feature",
  "properties": {
    "gn:admin1_code":"02",
    "gn:admin2_code":"218.0",
    "gn:admin3_code":"21802.0",
    "gn:asciiname":"Marco",
    "gn:country_code":"PE",
    "gn:dem":2534,
    "gn:feature_class":"P",
    "gn:feature_code":"PPL",
    "gn:name":"Marco",
    "gn:population":0,
    "gn:timezone":"America/Lima",
    "iso:country":"PE",
    "wof:name":"Marco",
    "wof:placetype":"locality"
},
  "geometry": {"coordinates":[-78.13333,-8.91667],"type":"Point"}
}