{
  "type": "Feature",
  "properties": {
    "gn:admin1_code":"12.0",
    "gn:admin2_code":"1208.0",
    "gn:admin3_code":"120804.0",
    "gn:asciiname":"Malpaso",
    "gn:country_code":"PE",
    "gn:dem":3966,
    "gn:feature_class":"P",
    "gn:feature_code":"PPL",
    "gn:name":"Malpaso",
    "gn:population":0,
    "gn:timezone":"America/Lima",
    "iso:country":"PE",
    "name:ceb_x_preferred":[
        "Malpaso"
    ],
    "name:deu_x_preferred":[
        "Malpaso"
    ],
    "name:fra_x_preferred":[
        "Malpaso"
    ],
    "name:nor_x_preferred":[
        "Malpaso"
    ],
    "name:spa_x_preferred":[
        "Malpaso"
    ],
    "name:srp_x_preferred":[
        "\u041c\u0430\u043b\u043f\u0430\u0441\u043e"
    ],
    "name:swe_x_preferred":[
        "Malpaso"
    ],
    "wof:name":"Malpaso",
    "wof:placetype":"locality"
},
  "geometry": {"coordinates":[-76.15589,-11.35351],"type":"Point"}
}