{
  "type": "Feature",
  "properties": {
    "gn:admin1_code":"3",
    "gn:admin2_code":"302.0",
    "gn:admin3_code":"30216.0",
    "gn:asciiname":"Huanca",
    "gn:country_code":"PE",
    "gn:dem":3014,
    "gn:feature_class":"P",
    "gn:feature_code":"PPL",
    "gn:name":"Huanca",
    "gn:population":0,
    "gn:timezone":"America/Lima",
    "iso:country":"PE",
    "wof:name":"Huanca",
    "wof:placetype":"locality"
},
  "geometry": {"coordinates":[-73.41415000000001,-13.64757],"type":"Point"}
}