{
  "type": "Feature",
  "properties": {
    "gn:admin1_code":"20",
    "gn:admin2_code":"2003.0",
    "gn:admin3_code":"200302.0",
    "gn:asciiname":"Maraypampa",
    "gn:country_code":"PE",
    "gn:dem":1313,
    "gn:feature_class":"P",
    "gn:feature_code":"PPL",
    "gn:name":"Maraypampa",
    "gn:population":0,
    "gn:timezone":"America/Lima",
    "iso:country":"PE",
    "wof:name":"Maraypampa",
    "wof:placetype":"locality"
},
  "geometry": {"coordinates":[-79.63818000000001,-5.35301],"type":"Point"}
}