{
  "type": "Feature",
  "properties": {
    "gn:admin1_code":"23.0",
    "gn:admin2_code":"2304.0",
    "gn:admin3_code":"230401.0",
    "gn:asciiname":"Murmuntana",
    "gn:country_code":"PE",
    "gn:dem":4316,
    "gn:feature_class":"P",
    "gn:feature_code":"PPL",
    "gn:name":"Murmuntana",
    "gn:population":0,
    "gn:timezone":"America/Lima",
    "iso:country":"PE",
    "wof:name":"Murmuntana",
    "wof:placetype":"locality"
},
  "geometry": {"coordinates":[-69.78839000000001,-17.32292],"type":"Point"}
}