{
  "type": "Feature",
  "properties": {
    "gn:admin1_code":"15.0",
    "gn:admin2_code":"1503.0",
    "gn:admin3_code":"150301.0",
    "gn:asciiname":"Astobamba",
    "gn:country_code":"PE",
    "gn:dem":3535,
    "gn:feature_class":"P",
    "gn:feature_code":"PPL",
    "gn:name":"Astobamba",
    "gn:population":0,
    "gn:timezone":"America/Lima",
    "iso:country":"PE",
    "wof:name":"Astobamba",
    "wof:placetype":"locality"
},
  "geometry": {"coordinates":[-76.98694,-10.4875],"type":"Point"}
}