{
  "type": "Feature",
  "properties": {
    "gn:admin1_code":"10",
    "gn:admin2_code":"1007.0",
    "gn:admin3_code":"100702.0",
    "gn:asciiname":"Tantaquillo",
    "gn:cc2":"PE",
    "gn:country_code":"PE",
    "gn:dem":1397,
    "gn:feature_class":"P",
    "gn:feature_code":"PPL",
    "gn:name":"Tantaquillo",
    "gn:population":0,
    "gn:timezone":"America/Lima",
    "iso:country":"PE",
    "name:und_x_variant":[
        "Tantaquilla",
        "Tantaquillo"
    ],
    "wof:name":"Tantaquillo",
    "wof:placetype":"locality"
},
  "geometry": {"coordinates":[-76.58333,-8.63333],"type":"Point"}
}