{
  "type": "Feature",
  "properties": {
    "gn:admin1_code":"8.0",
    "gn:admin2_code":"813.0",
    "gn:admin3_code":"81306.0",
    "gn:asciiname":"Cachijata",
    "gn:country_code":"PE",
    "gn:dem":4243,
    "gn:feature_class":"P",
    "gn:feature_code":"PPL",
    "gn:name":"Cachijata",
    "gn:population":0,
    "gn:timezone":"America/Lima",
    "iso:country":"PE",
    "wof:name":"Cachijata",
    "wof:placetype":"locality"
},
  "geometry": {"coordinates":[-72.30944000000002,-13.28583],"type":"Point"}
}