{
  "type": "Feature",
  "properties": {
    "gn:admin1_code":"5.0",
    "gn:admin2_code":"504.0",
    "gn:admin3_code":"50402.0",
    "gn:asciiname":"Lirio",
    "gn:country_code":"PE",
    "gn:dem":3688,
    "gn:feature_class":"P",
    "gn:feature_code":"PPL",
    "gn:name":"Lirio",
    "gn:population":0,
    "gn:timezone":"America/Lima",
    "iso:country":"PE",
    "name:ara_x_preferred":[
        "\u0644\u064a\u0631\u064a\u0648"
    ],
    "name:azb_x_preferred":[
        "\u0644\u06cc\u0631\u06cc\u0648"
    ],
    "name:bel_x_preferred":[
        "\u041b\u0456\u0440\u044b\u0430"
    ],
    "name:bul_x_preferred":[
        "\u041b\u0438\u0440\u0438\u043e"
    ],
    "name:ceb_x_preferred":[
        "Lirio"
    ],
    "name:deu_x_preferred":[
        "Lirio"
    ],
    "name:epo_x_preferred":[
        "Lirio"
    ],
    "name:eus_x_preferred":[
        "Lirio"
    ],
    "name:fas_x_preferred":[
        "\u0644\u06cc\u0631\u06cc\u0648"
    ],
    "name:fra_x_preferred":[
        "Lirio"
    ],
    "name:hun_x_preferred":[
        "Lirio"
    ],
    "name:hye_x_preferred":[
        "\u053c\u056b\u0580\u056b\u0578"
    ],
    "name:ita_x_preferred":[
        "Lirio"
    ],
    "name:jpn_x_preferred":[
        "\u30ea\u30fc\u30ea\u30aa"
    ],
    "name:kaz_x_preferred":[
        "\u041b\u0438\u0440\u0438\u043e"
    ],
    "name:lat_x_preferred":[
        "Lirium"
    ],
    "name:lmo_x_preferred":[
        "Lir"
    ],
    "name:msa_x_preferred":[
        "Lirio"
    ],
    "name:nap_x_preferred":[
        "Lirio"
    ],
    "name:nld_x_preferred":[
        "Lirio"
    ],
    "name:pms_x_preferred":[
        "Lirio"
    ],
    "name:pol_x_preferred":[
        "Lirio"
    ],
    "name:por_x_preferred":[
        "Lirio"
    ],
    "name:ron_x_preferred":[
        "Lirio"
    ],
    "name:rus_x_preferred":[
        "\u041b\u0438\u0440\u0438\u043e"
    ],
    "name:scn_x_preferred":[
        "Lirio"
    ],
    "name:spa_x_preferred":[
        "Lirio"
    ],
    "name:srp_x_preferred":[
        "\u041b\u0438\u0440\u0438\u043e"
    ],
    "name:tgl_x_preferred":[
        "Lirio"
    ],
    "name:ukr_x_preferred":[
        "\u041b\u0456\u0440\u0456\u043e"
    ],
    "name:uzb_x_preferred":[
        "Lirio"
    ],
    "name:vie_x_preferred":[
        "Lirio"
    ],
    "name:vol_x_preferred":[
        "Lirio"
    ],
    "name:war_x_preferred":[
        "Lirio"
    ],
    "wof:name":"Lirio",
    "wof:placetype":"locality"
},
  "geometry": {"coordinates":[-74.29386,-12.60345],"type":"Point"}
}