{
  "type": "Feature",
  "properties": {
    "gn:admin1_code":"04",
    "gn:admin2_code":"403.0",
    "gn:admin3_code":"40312.0",
    "gn:asciiname":"Chumillo",
    "gn:country_code":"PE",
    "gn:dem":3364,
    "gn:feature_class":"P",
    "gn:feature_code":"PPL",
    "gn:name":"Chumillo",
    "gn:population":0,
    "gn:timezone":"America/Lima",
    "iso:country":"PE",
    "name:und_x_variant":[
        "Chamillo"
    ],
    "wof:name":"Chumillo",
    "wof:placetype":"locality"
},
  "geometry": {"coordinates":[-73.67771999999999,-15.45912],"type":"Point"}
}