{
  "type": "Feature",
  "properties": {
    "gn:admin1_code":"21",
    "gn:admin2_code":"2112.0",
    "gn:admin3_code":"211203.0",
    "gn:asciiname":"La Pampa",
    "gn:country_code":"PE",
    "gn:dem":847,
    "gn:feature_class":"P",
    "gn:feature_code":"PPL",
    "gn:name":"La Pampa",
    "gn:population":0,
    "gn:timezone":"America/Lima",
    "iso:country":"PE",
    "name:bre_x_preferred":[
        "La Pampa"
    ],
    "name:ceb_x_preferred":[
        "La Pampa"
    ],
    "name:hun_x_preferred":[
        "La Pampa"
    ],
    "name:por_x_preferred":[
        "La Pampa"
    ],
    "name:spa_x_preferred":[
        "La Pampa"
    ],
    "name:swe_x_preferred":[
        "La Pampa"
    ],
    "wof:name":"La Pampa",
    "wof:placetype":"locality"
},
  "geometry": {"coordinates":[-69.59531,-13.67561],"type":"Point"}
}