{
  "type": "Feature",
  "properties": {
    "gn:admin1_code":"11",
    "gn:admin2_code":"1105.0",
    "gn:admin3_code":"110507.0",
    "gn:asciiname":"Botija",
    "gn:country_code":"PE",
    "gn:dem":127,
    "gn:feature_class":"P",
    "gn:feature_code":"PPL",
    "gn:name":"Botija",
    "gn:population":0,
    "gn:timezone":"America/Lima",
    "iso:country":"PE",
    "name:spa_x_preferred":[
        "Botija"
    ],
    "wof:name":"Botija",
    "wof:placetype":"locality"
},
  "geometry": {"coordinates":[-76.10629,-13.63926],"type":"Point"}
}