{
  "type": "Feature",
  "properties": {
    "gn:admin1_code":"20",
    "gn:admin2_code":"2002.0",
    "gn:admin3_code":"200207.0",
    "gn:asciiname":"Culqui",
    "gn:country_code":"PE",
    "gn:dem":518,
    "gn:feature_class":"P",
    "gn:feature_code":"PPL",
    "gn:name":"Culqui",
    "gn:population":0,
    "gn:timezone":"America/Lima",
    "iso:country":"PE",
    "name:und_x_variant":[
        "Culqui Hacienda",
        "Culqui"
    ],
    "wof:name":"Culqui",
    "wof:placetype":"locality"
},
  "geometry": {"coordinates":[-80.00718000000001,-4.63442],"type":"Point"}
}