{
  "type": "Feature",
  "properties": {
    "gn:admin1_code":"03",
    "gn:admin2_code":"302.0",
    "gn:asciiname":"Yanama",
    "gn:country_code":"PE",
    "gn:dem":4418,
    "gn:feature_class":"P",
    "gn:feature_code":"PPL",
    "gn:name":"Yanama",
    "gn:population":0,
    "gn:timezone":"America/Lima",
    "iso:country":"PE",
    "wof:name":"Yanama",
    "wof:placetype":"locality"
},
  "geometry": {"coordinates":[-73.53362,-14.47048],"type":"Point"}
}