{
  "type": "Feature",
  "properties": {
    "gn:admin1_code":"4",
    "gn:admin2_code":"408.0",
    "gn:admin3_code":"40801.0",
    "gn:asciiname":"Huallullo",
    "gn:country_code":"PE",
    "gn:dem":4120,
    "gn:feature_class":"P",
    "gn:feature_code":"PPL",
    "gn:name":"Huallullo",
    "gn:population":0,
    "gn:timezone":"America/Lima",
    "iso:country":"PE",
    "wof:name":"Huallullo",
    "wof:placetype":"locality"
},
  "geometry": {"coordinates":[-72.86339,-15.28435],"type":"Point"}
}