{
  "type": "Feature",
  "properties": {
    "gn:admin1_code":"06",
    "gn:admin2_code":"604.0",
    "gn:admin3_code":"60416.0",
    "gn:asciiname":"Ramalpon",
    "gn:country_code":"PE",
    "gn:dem":1082,
    "gn:feature_class":"P",
    "gn:feature_code":"PPL",
    "gn:name":"Ramalp\u00f3n",
    "gn:population":0,
    "gn:timezone":"America/Lima",
    "iso:country":"PE",
    "wof:name":"Ramalpon",
    "wof:placetype":"locality"
},
  "geometry": {"coordinates":[-79.26791,-6.48798],"type":"Point"}
}