{
  "type": "Feature",
  "properties": {
    "gn:admin1_code":"9.0",
    "gn:admin2_code":"907.0",
    "gn:admin3_code":"90705.0",
    "gn:asciiname":"Quellorami",
    "gn:country_code":"PE",
    "gn:dem":3206,
    "gn:feature_class":"P",
    "gn:feature_code":"PPL",
    "gn:name":"Quellorami",
    "gn:population":0,
    "gn:timezone":"America/Lima",
    "iso:country":"PE",
    "wof:name":"Quellorami",
    "wof:placetype":"locality"
},
  "geometry": {"coordinates":[-74.64636,-12.45766],"type":"Point"}
}