{
  "type": "Feature",
  "properties": {
    "gn:admin1_code":"2.0",
    "gn:admin2_code":"205.0",
    "gn:admin3_code":"20501.0",
    "gn:asciiname":"Chaquis",
    "gn:country_code":"PE",
    "gn:dem":3672,
    "gn:feature_class":"P",
    "gn:feature_code":"PPL",
    "gn:name":"Chaquis",
    "gn:population":0,
    "gn:timezone":"America/Lima",
    "iso:country":"PE",
    "wof:name":"Chaquis",
    "wof:placetype":"locality"
},
  "geometry": {"coordinates":[-77.14593000000001,-10.1722],"type":"Point"}
}