{
  "type": "Feature",
  "properties": {
    "gn:admin1_code":"12.0",
    "gn:admin2_code":"1204.0",
    "gn:admin3_code":"120403.0",
    "gn:asciiname":"Tambo Muyoc",
    "gn:country_code":"PE",
    "gn:dem":4248,
    "gn:feature_class":"P",
    "gn:feature_code":"PPL",
    "gn:name":"Tambo Muyoc",
    "gn:population":0,
    "gn:timezone":"America/Lima",
    "iso:country":"PE",
    "wof:name":"Tambo Muyoc",
    "wof:placetype":"locality"
},
  "geometry": {"coordinates":[-75.30101999999999,-11.64284],"type":"Point"}
}