{
  "type": "Feature",
  "properties": {
    "gn:admin1_code":"11.0",
    "gn:admin2_code":"1102.0",
    "gn:admin3_code":"110208.0",
    "gn:asciiname":"Callamachay",
    "gn:country_code":"PE",
    "gn:dem":1905,
    "gn:feature_class":"P",
    "gn:feature_code":"PPL",
    "gn:name":"Callamachay",
    "gn:population":0,
    "gn:timezone":"America/Lima",
    "iso:country":"PE",
    "name:spa_x_preferred":[
        "Callamachay"
    ],
    "wof:name":"Callamachay",
    "wof:placetype":"locality"
},
  "geometry": {"coordinates":[-75.81533,-13.25533],"type":"Point"}
}