{
  "type": "Feature",
  "properties": {
    "gn:admin1_code":"04",
    "gn:admin2_code":"401.0",
    "gn:asciiname":"Corahuaya",
    "gn:country_code":"PE",
    "gn:dem":3204,
    "gn:feature_class":"P",
    "gn:feature_code":"PPL",
    "gn:name":"Corahuaya",
    "gn:population":0,
    "gn:timezone":"America/Lima",
    "iso:country":"PE",
    "wof:name":"Corahuaya",
    "wof:placetype":"locality"
},
  "geometry": {"coordinates":[-71.28966,-16.63375],"type":"Point"}
}