{
  "type": "Feature",
  "properties": {
    "gn:admin1_code":"7",
    "gn:admin2_code":"701.0",
    "gn:admin3_code":"70101.0",
    "gn:asciiname":"Bocanegra",
    "gn:cc2":"PE",
    "gn:country_code":"PE",
    "gn:dem":19,
    "gn:feature_class":"P",
    "gn:feature_code":"PPL",
    "gn:name":"Bocanegra",
    "gn:population":0,
    "gn:timezone":"America/Lima",
    "iso:country":"PE",
    "name:und_x_variant":[
        "Bocanegra Hacienda",
        "Bocanegra"
    ],
    "wof:name":"Bocanegra",
    "wof:placetype":"locality"
},
  "geometry": {"coordinates":[-77.11667,-12.01667],"type":"Point"}
}