{
  "type": "Feature",
  "properties": {
    "gn:admin1_code":"2.0",
    "gn:admin2_code":"205.0",
    "gn:admin3_code":"20504.0",
    "gn:asciiname":"Sanca Pampa",
    "gn:country_code":"PE",
    "gn:dem":3913,
    "gn:feature_class":"P",
    "gn:feature_code":"PPL",
    "gn:name":"Sanca Pampa",
    "gn:population":0,
    "gn:timezone":"America/Lima",
    "iso:country":"PE",
    "wof:name":"Sanca Pampa",
    "wof:placetype":"locality"
},
  "geometry": {"coordinates":[-77.13533000000002,-10.08808],"type":"Point"}
}