{
  "type": "Feature",
  "properties": {
    "gn:country":"PE",
    "gn:fcode":"PPLA3",
    "gn:population":5385,
    "iso:country":"PE",
    "qs_pg:aaroncc":"PE",
    "qs_pg:gn_country":"PE",
    "qs_pg:gn_fcode":"PPLA3",
    "qs_pg:gn_pop":5385,
    "qs_pg:name":"Salitral",
    "qs_pg:photos_9r":0,
    "qs_pg:photos_sr":0,
    "qs_pg:pop_sr":5,
    "qs_pg:qs_pg_placetype":"locality",
    "wof:name":"Salitral",
    "wof:placetype":"locality",
    "wof:population":5385
},
  "geometry": {"coordinates":[-80.68111,-4.85722],"type":"Point"}
}