{
  "type": "Feature",
  "properties": {
    "gn:admin1_code":"05",
    "gn:admin2_code":"509.0",
    "gn:admin3_code":"50909.0",
    "gn:asciiname":"Huicana",
    "gn:country_code":"PE",
    "gn:dem":3243,
    "gn:feature_class":"P",
    "gn:feature_code":"PPL",
    "gn:name":"Huicana",
    "gn:population":0,
    "gn:timezone":"America/Lima",
    "iso:country":"PE",
    "wof:name":"Huicana",
    "wof:placetype":"locality"
},
  "geometry": {"coordinates":[-73.72278,-13.98917],"type":"Point"}
}