{
  "type": "Feature",
  "properties": {
    "gn:admin1_code":"22.0",
    "gn:admin2_code":"2207.0",
    "gn:admin3_code":"220706.0",
    "gn:asciiname":"Granja Experimental",
    "gn:country_code":"PE",
    "gn:dem":227,
    "gn:feature_class":"P",
    "gn:feature_code":"PPL",
    "gn:name":"Granja Experimental",
    "gn:population":0,
    "gn:timezone":"America/Lima",
    "iso:country":"PE",
    "name:spa_x_preferred":[
        "Granja Experimental"
    ],
    "wof:name":"Granja Experimental",
    "wof:placetype":"locality"
},
  "geometry": {"coordinates":[-76.42025,-6.97938],"type":"Point"}
}