{
  "type": "Feature",
  "properties": {
    "gn:admin1_code":"10.0",
    "gn:admin2_code":"1001.0",
    "gn:admin3_code":"100105.0",
    "gn:asciiname":"Yuracrumi",
    "gn:country_code":"PE",
    "gn:dem":3768,
    "gn:feature_class":"P",
    "gn:feature_code":"PPL",
    "gn:name":"Yuracrumi",
    "gn:population":0,
    "gn:timezone":"America/Lima",
    "iso:country":"PE",
    "wof:name":"Yuracrumi",
    "wof:placetype":"locality"
},
  "geometry": {"coordinates":[-76.51045000000001,-9.96007],"type":"Point"}
}