{
  "type": "Feature",
  "properties": {
    "gn:admin1_code":"05",
    "gn:admin2_code":"507.0",
    "gn:admin3_code":"50705.0",
    "gn:asciiname":"Sacsara",
    "gn:country_code":"PE",
    "gn:dem":2963,
    "gn:feature_class":"P",
    "gn:feature_code":"PPL",
    "gn:name":"Sacsara",
    "gn:population":0,
    "gn:timezone":"America/Lima",
    "iso:country":"PE",
    "name:spa_x_preferred":[
        "Sacsara"
    ],
    "wof:name":"Sacsara",
    "wof:placetype":"locality"
},
  "geometry": {"coordinates":[-73.85811,-15.19127],"type":"Point"}
}