{
  "type": "Feature",
  "properties": {
    "gn:admin1_code":"11.0",
    "gn:admin2_code":"1102.0",
    "gn:admin3_code":"110204.0",
    "gn:asciiname":"Puqio Santo",
    "gn:country_code":"PE",
    "gn:dem":30,
    "gn:feature_class":"P",
    "gn:feature_code":"PPL",
    "gn:name":"Puq\u00edo Santo",
    "gn:population":0,
    "gn:timezone":"America/Lima",
    "iso:country":"PE",
    "name:spa_x_preferred":[
        "Puq\u00edo Santo"
    ],
    "wof:name":"Puqio Santo",
    "wof:placetype":"locality"
},
  "geometry": {"coordinates":[-76.16048000000001,-13.51556],"type":"Point"}
}