{
  "type": "Feature",
  "properties": {
    "gn:admin1_code":"4",
    "gn:admin2_code":"405.0",
    "gn:admin3_code":"40518.0",
    "gn:asciiname":"Chayallita",
    "gn:country_code":"PE",
    "gn:dem":3891,
    "gn:feature_class":"P",
    "gn:feature_code":"PPL",
    "gn:name":"Chayallita",
    "gn:population":0,
    "gn:timezone":"America/Lima",
    "iso:country":"PE",
    "wof:name":"Chayallita",
    "wof:placetype":"locality"
},
  "geometry": {"coordinates":[-71.54793000000002,-15.52143],"type":"Point"}
}