{
  "type": "Feature",
  "properties": {
    "gn:admin1_code":"20",
    "gn:admin2_code":"2003.0",
    "gn:admin3_code":"200308.0",
    "gn:asciiname":"Hacienda Cascapampa",
    "gn:country_code":"PE",
    "gn:dem":3232,
    "gn:feature_class":"P",
    "gn:feature_code":"PPL",
    "gn:name":"Hacienda Cascapampa",
    "gn:population":0,
    "gn:timezone":"America/Lima",
    "iso:country":"PE",
    "name:und_x_variant":[
        "Cascapampa Hacienda",
        "Cascapampa",
        "Hacienda Cascapampa"
    ],
    "wof:name":"Hacienda Cascapampa",
    "wof:placetype":"locality"
},
  "geometry": {"coordinates":[-79.53178,-5.31653],"type":"Point"}
}