{
  "type": "Feature",
  "properties": {
    "gn:admin1_code":"5.0",
    "gn:admin2_code":"504.0",
    "gn:admin3_code":"50407.0",
    "gn:asciiname":"Japia",
    "gn:country_code":"PE",
    "gn:dem":3572,
    "gn:feature_class":"P",
    "gn:feature_code":"PPL",
    "gn:name":"Japia",
    "gn:population":0,
    "gn:timezone":"America/Lima",
    "iso:country":"PE",
    "wof:name":"Japia",
    "wof:placetype":"locality"
},
  "geometry": {"coordinates":[-74.01127,-12.65883],"type":"Point"}
}