{
  "type": "Feature",
  "properties": {
    "gn:admin1_code":"09",
    "gn:admin2_code":"904.0",
    "gn:admin3_code":"90409.0",
    "gn:asciiname":"Quirripa",
    "gn:country_code":"PE",
    "gn:dem":3593,
    "gn:feature_class":"P",
    "gn:feature_code":"PPL",
    "gn:name":"Quirripa",
    "gn:population":0,
    "gn:timezone":"America/Lima",
    "iso:country":"PE",
    "wof:name":"Quirripa",
    "wof:placetype":"locality"
},
  "geometry": {"coordinates":[-75.39934000000002,-13.27911],"type":"Point"}
}