{
  "type": "Feature",
  "properties": {
    "gn:admin1_code":"2.0",
    "gn:admin2_code":"212.0",
    "gn:admin3_code":"21207.0",
    "gn:asciiname":"Incaya",
    "gn:country_code":"PE",
    "gn:dem":2455,
    "gn:feature_class":"P",
    "gn:feature_code":"PPL",
    "gn:name":"Incaya",
    "gn:population":0,
    "gn:timezone":"America/Lima",
    "iso:country":"PE",
    "wof:name":"Incaya",
    "wof:placetype":"locality"
},
  "geometry": {"coordinates":[-77.80056,-9.10889],"type":"Point"}
}