{
  "type": "Feature",
  "properties": {
    "gn:admin1_code":"13",
    "gn:admin2_code":"1309.0",
    "gn:admin3_code":"130907.0",
    "gn:asciiname":"Turismalca",
    "gn:country_code":"PE",
    "gn:dem":3356,
    "gn:feature_class":"P",
    "gn:feature_code":"PPL",
    "gn:name":"Turismalca",
    "gn:population":0,
    "gn:timezone":"America/Lima",
    "iso:country":"PE",
    "wof:name":"Turismalca",
    "wof:placetype":"locality"
},
  "geometry": {"coordinates":[-77.87645000000001,-7.97302],"type":"Point"}
}