{
  "type": "Feature",
  "properties": {
    "gn:admin1_code":"19",
    "gn:admin2_code":"1903.0",
    "gn:admin3_code":"190304.0",
    "gn:asciiname":"Shiringamazu",
    "gn:country_code":"PE",
    "gn:dem":291,
    "gn:feature_class":"P",
    "gn:feature_code":"PPL",
    "gn:name":"Shiringamaz\u00fa",
    "gn:population":0,
    "gn:timezone":"America/Lima",
    "iso:country":"PE",
    "wof:name":"Shiringamazu",
    "wof:placetype":"locality"
},
  "geometry": {"coordinates":[-75.12805999999998,-10.26111],"type":"Point"}
}