{
  "type": "Feature",
  "properties": {
    "gn:admin1_code":"22.0",
    "gn:admin2_code":"2201.0",
    "gn:admin3_code":"220101.0",
    "gn:asciiname":"Sapote",
    "gn:country_code":"PE",
    "gn:dem":810,
    "gn:feature_class":"P",
    "gn:feature_code":"PPL",
    "gn:name":"Sapote",
    "gn:population":0,
    "gn:timezone":"America/Lima",
    "iso:country":"PE",
    "name:deu_x_preferred":[
        "Sapote"
    ],
    "name:kor_x_preferred":[
        "\uc0ac\ud3ec\ud14c"
    ],
    "name:nah_x_preferred":[
        "Tzapotl"
    ],
    "name:nor_x_preferred":[
        "Sapote"
    ],
    "name:rus_x_preferred":[
        "\u0421\u0430\u043f\u043e\u0442\u0430"
    ],
    "name:spa_x_preferred":[
        "Zapote"
    ],
    "name:vie_x_preferred":[
        "Sap\u00f4ch\u00ea"
    ],
    "wof:name":"Sapote",
    "wof:placetype":"locality"
},
  "geometry": {"coordinates":[-77.03166999999998,-5.9375],"type":"Point"}
}