{
  "type": "Feature",
  "properties": {
    "gn:admin1_code":"9.0",
    "gn:admin2_code":"903.0",
    "gn:admin3_code":"90301.0",
    "gn:asciiname":"Anayhuaycco",
    "gn:country_code":"PE",
    "gn:dem":4204,
    "gn:feature_class":"P",
    "gn:feature_code":"PPL",
    "gn:name":"Anayhuaycco",
    "gn:population":0,
    "gn:timezone":"America/Lima",
    "iso:country":"PE",
    "wof:name":"Anayhuaycco",
    "wof:placetype":"locality"
},
  "geometry": {"coordinates":[-74.76375,-13.03948],"type":"Point"}
}