{
  "type": "Feature",
  "properties": {
    "gn:admin1_code":"21",
    "gn:admin2_code":"2104.0",
    "gn:admin3_code":"210404.0",
    "gn:asciiname":"Ayala",
    "gn:country_code":"PE",
    "gn:dem":3947,
    "gn:feature_class":"P",
    "gn:feature_code":"PPL",
    "gn:name":"Ayala",
    "gn:population":0,
    "gn:timezone":"America/Lima",
    "iso:country":"PE",
    "name:bre_x_preferred":[
        "Ayala"
    ],
    "name:cat_x_preferred":[
        "Ayala"
    ],
    "name:ceb_x_preferred":[
        "Ayala"
    ],
    "name:ces_x_preferred":[
        "Ayala"
    ],
    "name:deu_x_preferred":[
        "Ayala"
    ],
    "name:fra_x_preferred":[
        "Ayala"
    ],
    "name:hun_x_preferred":[
        "Ayala"
    ],
    "name:ita_x_preferred":[
        "Ayala"
    ],
    "name:jpn_x_preferred":[
        "\u30a2\u30b8\u30e3\u30e9"
    ],
    "name:kor_x_preferred":[
        "\uc544\uc584\ub77c"
    ],
    "name:lit_x_preferred":[
        "Ayala"
    ],
    "name:nld_x_preferred":[
        "Ayala"
    ],
    "name:pol_x_preferred":[
        "Ayala"
    ],
    "name:por_x_preferred":[
        "Ayala"
    ],
    "name:rus_x_preferred":[
        "\u0410\u0439\u044f\u043b\u0430"
    ],
    "name:slk_x_preferred":[
        "Ayala"
    ],
    "name:spa_x_preferred":[
        "Ayala"
    ],
    "name:swe_x_preferred":[
        "Ayala"
    ],
    "name:ukr_x_preferred":[
        "\u0410\u044f\u043b\u0430"
    ],
    "name:vie_x_preferred":[
        "Ayala"
    ],
    "name:zho_x_preferred":[
        "\u963f\u4e9a\u62c9"
    ],
    "wof:name":"Ayala",
    "wof:placetype":"locality"
},
  "geometry": {"coordinates":[-69.30736,-16.78918],"type":"Point"}
}