{
  "type": "Feature",
  "properties": {
    "gn:admin1_code":"24",
    "gn:admin2_code":"2402.0",
    "gn:admin3_code":"240202.0",
    "gn:asciiname":"Huaquilla",
    "gn:country_code":"PE",
    "gn:dem":118,
    "gn:feature_class":"P",
    "gn:feature_code":"PPL",
    "gn:name":"Huaquilla",
    "gn:population":0,
    "gn:timezone":"America/Lima",
    "iso:country":"PE",
    "wof:name":"Huaquilla",
    "wof:placetype":"locality"
},
  "geometry": {"coordinates":[-80.63333,-3.91667],"type":"Point"}
}