{
  "type": "Feature",
  "properties": {
    "gn:admin1_code":"15",
    "gn:admin2_code":"1507.0",
    "gn:admin3_code":"150722.0",
    "gn:asciiname":"Puquihuayaco",
    "gn:country_code":"PE",
    "gn:dem":4297,
    "gn:feature_class":"P",
    "gn:feature_code":"PPL",
    "gn:name":"Puquihuayaco",
    "gn:population":0,
    "gn:timezone":"America/Lima",
    "iso:country":"PE",
    "wof:name":"Puquihuayaco",
    "wof:placetype":"locality"
},
  "geometry": {"coordinates":[-76.16778000000002,-11.82111],"type":"Point"}
}