{
  "type": "Feature",
  "properties": {
    "gn:admin1_code":"8",
    "gn:admin2_code":"807.0",
    "gn:admin3_code":"80701.0",
    "gn:asciiname":"Arcopunco",
    "gn:country_code":"PE",
    "gn:dem":4163,
    "gn:feature_class":"P",
    "gn:feature_code":"PPL",
    "gn:name":"Arcopunco",
    "gn:population":0,
    "gn:timezone":"America/Lima",
    "iso:country":"PE",
    "wof:name":"Arcopunco",
    "wof:placetype":"locality"
},
  "geometry": {"coordinates":[-71.92548000000002,-14.6262],"type":"Point"}
}