{
  "type": "Feature",
  "properties": {
    "gn:admin1_code":"02",
    "gn:admin2_code":"205.0",
    "gn:admin3_code":"20507.0",
    "gn:asciiname":"Chiquiahuanca",
    "gn:country_code":"PE",
    "gn:dem":628,
    "gn:feature_class":"P",
    "gn:feature_code":"PPL",
    "gn:name":"Chiquiahuanca",
    "gn:population":0,
    "gn:timezone":"America/Lima",
    "iso:country":"PE",
    "wof:name":"Chiquiahuanca",
    "wof:placetype":"locality"
},
  "geometry": {"coordinates":[-77.62635,-10.3374],"type":"Point"}
}