{
  "type": "Feature",
  "properties": {
    "gn:admin1_code":"8.0",
    "gn:admin2_code":"810.0",
    "gn:admin3_code":"81005.0",
    "gn:asciiname":"Yocquesinca",
    "gn:country_code":"PE",
    "gn:dem":3386,
    "gn:feature_class":"P",
    "gn:feature_code":"PPL",
    "gn:name":"Yocquesinca",
    "gn:population":0,
    "gn:timezone":"America/Lima",
    "iso:country":"PE",
    "wof:name":"Yocquesinca",
    "wof:placetype":"locality"
},
  "geometry": {"coordinates":[-72.03889000000002,-13.64194],"type":"Point"}
}