{
  "type": "Feature",
  "properties": {
    "gn:admin1_code":"15",
    "gn:admin2_code":"1501.0",
    "gn:admin3_code":"150123.0",
    "gn:asciiname":"Cardal",
    "gn:country_code":"PE",
    "gn:dem":157,
    "gn:feature_class":"P",
    "gn:feature_code":"PPL",
    "gn:name":"Cardal",
    "gn:population":0,
    "gn:timezone":"America/Lima",
    "iso:country":"PE",
    "name:ceb_x_preferred":[
        "Cardal"
    ],
    "name:glg_x_preferred":[
        "Cardal"
    ],
    "name:spa_x_preferred":[
        "Cardal"
    ],
    "wof:name":"Cardal",
    "wof:placetype":"locality"
},
  "geometry": {"coordinates":[-76.84968000000001,-12.18169],"type":"Point"}
}