{
  "type": "Feature",
  "properties": {
    "gn:admin1_code":"3",
    "gn:admin2_code":"302.0",
    "gn:admin3_code":"30213.0",
    "gn:asciiname":"Larillacucho",
    "gn:country_code":"PE",
    "gn:dem":3809,
    "gn:feature_class":"P",
    "gn:feature_code":"PPL",
    "gn:name":"Larillacucho",
    "gn:population":0,
    "gn:timezone":"America/Lima",
    "iso:country":"PE",
    "wof:name":"Larillacucho",
    "wof:placetype":"locality"
},
  "geometry": {"coordinates":[-73.39511,-13.6072],"type":"Point"}
}