{
  "type": "Feature",
  "properties": {
    "gn:admin1_code":"8",
    "gn:admin2_code":"806.0",
    "gn:admin3_code":"80601.0",
    "gn:asciiname":"Mocopata",
    "gn:country_code":"PE",
    "gn:dem":3893,
    "gn:feature_class":"P",
    "gn:feature_code":"PPL",
    "gn:name":"Mocopata",
    "gn:population":0,
    "gn:timezone":"America/Lima",
    "iso:country":"PE",
    "wof:name":"Mocopata",
    "wof:placetype":"locality"
},
  "geometry": {"coordinates":[-71.23853000000003,-14.18972],"type":"Point"}
}