{
  "type": "Feature",
  "properties": {
    "gn:admin1_code":"06",
    "gn:admin2_code":"611.0",
    "gn:admin3_code":"61109.0",
    "gn:asciiname":"Barro Alto",
    "gn:country_code":"PE",
    "gn:dem":3141,
    "gn:feature_class":"P",
    "gn:feature_code":"PPL",
    "gn:name":"Barro Alto",
    "gn:population":0,
    "gn:timezone":"America/Lima",
    "iso:country":"PE",
    "name:ceb_x_preferred":[
        "Barro Alto"
    ],
    "name:ita_x_preferred":[
        "Barro Alto"
    ],
    "name:nld_x_preferred":[
        "Barro Alto"
    ],
    "name:nor_x_preferred":[
        "Barro Alto"
    ],
    "name:por_x_preferred":[
        "Barro Alto"
    ],
    "name:ron_x_preferred":[
        "Barro Alto"
    ],
    "name:rus_x_preferred":[
        "\u0411\u0430\u0440\u0440\u0443-\u0410\u043b\u0442\u0443"
    ],
    "name:swe_x_preferred":[
        "Barro Alto"
    ],
    "name:vol_x_preferred":[
        "Barro Alto"
    ],
    "wof:name":"Barro Alto",
    "wof:placetype":"locality"
},
  "geometry": {"coordinates":[-79.0924,-6.95036],"type":"Point"}
}