{
  "type": "Feature",
  "properties": {
    "gn:admin1_code":"21",
    "gn:admin2_code":"2112.0",
    "gn:admin3_code":"211202.0",
    "gn:asciiname":"Cojene",
    "gn:country_code":"PE",
    "gn:dem":3732,
    "gn:feature_class":"P",
    "gn:feature_code":"PPL",
    "gn:name":"Cojene",
    "gn:population":0,
    "gn:timezone":"America/Lima",
    "iso:country":"PE",
    "wof:name":"Cojene",
    "wof:placetype":"locality"
},
  "geometry": {"coordinates":[-69.53708,-14.47736],"type":"Point"}
}