{
  "type": "Feature",
  "properties": {
    "gn:admin1_code":"3",
    "gn:admin2_code":"302.0",
    "gn:admin3_code":"30202.0",
    "gn:asciiname":"Huaracopa",
    "gn:country_code":"PE",
    "gn:dem":3810,
    "gn:feature_class":"P",
    "gn:feature_code":"PPL",
    "gn:name":"Huaracopa",
    "gn:population":0,
    "gn:timezone":"America/Lima",
    "iso:country":"PE",
    "wof:name":"Huaracopa",
    "wof:placetype":"locality"
},
  "geometry": {"coordinates":[-73.32563,-13.5522],"type":"Point"}
}