{
  "type": "Feature",
  "properties": {
    "gn:admin1_code":"8",
    "gn:admin2_code":"806.0",
    "gn:admin3_code":"80607.0",
    "gn:asciiname":"Cuchuma",
    "gn:country_code":"PE",
    "gn:dem":3715,
    "gn:feature_class":"P",
    "gn:feature_code":"PPL",
    "gn:name":"Cuchuma",
    "gn:population":0,
    "gn:timezone":"America/Lima",
    "iso:country":"PE",
    "wof:name":"Cuchuma",
    "wof:placetype":"locality"
},
  "geometry": {"coordinates":[-71.33048000000002,-14.15496],"type":"Point"}
}