{
  "type": "Feature",
  "properties": {
    "gn:admin1_code":"21",
    "gn:admin2_code":"2101.0",
    "gn:admin3_code":"210101.0",
    "gn:asciiname":"Pamputa",
    "gn:country_code":"PE",
    "gn:dem":3936,
    "gn:feature_class":"P",
    "gn:feature_code":"PPL",
    "gn:name":"Pamputa",
    "gn:population":0,
    "gn:timezone":"America/Lima",
    "iso:country":"PE",
    "name:und_x_variant":[
        "Estancia Pamputa",
        "Pamputa"
    ],
    "wof:name":"Pamputa",
    "wof:placetype":"locality"
},
  "geometry": {"coordinates":[-70.04786999999999,-15.99677],"type":"Point"}
}