{
  "type": "Feature",
  "properties": {
    "gn:admin1_code":"10.0",
    "gn:admin2_code":"1010.0",
    "gn:admin3_code":"101003.0",
    "gn:asciiname":"Juprocpampa",
    "gn:country_code":"PE",
    "gn:dem":3411,
    "gn:feature_class":"P",
    "gn:feature_code":"PPL",
    "gn:name":"Juprocpampa",
    "gn:population":0,
    "gn:timezone":"America/Lima",
    "iso:country":"PE",
    "wof:name":"Juprocpampa",
    "wof:placetype":"locality"
},
  "geometry": {"coordinates":[-76.66194,-10.03694],"type":"Point"}
}