{
  "type": "Feature",
  "properties": {
    "gn:admin1_code":"05",
    "gn:admin2_code":"501.0",
    "gn:admin3_code":"50105.0",
    "gn:asciiname":"Pucaccasa",
    "gn:country_code":"PE",
    "gn:dem":3663,
    "gn:feature_class":"P",
    "gn:feature_code":"PPL",
    "gn:name":"Pucaccasa",
    "gn:population":0,
    "gn:timezone":"America/Lima",
    "iso:country":"PE",
    "wof:name":"Pucaccasa",
    "wof:placetype":"locality"
},
  "geometry": {"coordinates":[-74.09844,-13.43694],"type":"Point"}
}