{
  "type": "Feature",
  "properties": {
    "gn:admin1_code":"24",
    "gn:admin2_code":"2403.0",
    "gn:admin3_code":"240303.0",
    "gn:asciiname":"El Caucho",
    "gn:country_code":"PE",
    "gn:dem":529,
    "gn:feature_class":"P",
    "gn:feature_code":"PPL",
    "gn:name":"El Caucho",
    "gn:population":0,
    "gn:timezone":"America/Lima",
    "iso:country":"PE",
    "wof:name":"El Caucho",
    "wof:placetype":"locality"
},
  "geometry": {"coordinates":[-80.26916999999997,-3.80944],"type":"Point"}
}