{
  "type": "Feature",
  "properties": {
    "gn:admin1_code":"12.0",
    "gn:admin2_code":"1204.0",
    "gn:admin3_code":"120417.0",
    "gn:asciiname":"Nananguayo",
    "gn:country_code":"PE",
    "gn:dem":3823,
    "gn:feature_class":"P",
    "gn:feature_code":"PPL",
    "gn:name":"\u00d1a\u00f1anguayo",
    "gn:population":0,
    "gn:timezone":"America/Lima",
    "iso:country":"PE",
    "wof:name":"Nananguayo",
    "wof:placetype":"locality"
},
  "geometry": {"coordinates":[-75.33854000000002,-11.80392],"type":"Point"}
}