{
  "type": "Feature",
  "properties": {
    "gn:admin1_code":"12",
    "gn:admin2_code":"1201.0",
    "gn:admin3_code":"120133.0",
    "gn:asciiname":"Sapallanga",
    "gn:country_code":"PE",
    "gn:dem":3267,
    "gn:feature_class":"P",
    "gn:feature_code":"PPLA3",
    "gn:name":"Sapallanga",
    "gn:population":0,
    "gn:timezone":"America/Lima",
    "iso:country":"PE",
    "wof:name":"Sapallanga",
    "wof:placetype":"locality"
},
  "geometry": {"coordinates":[-75.18333,-12.15],"type":"Point"}
}