{
  "type": "Feature",
  "properties": {
    "gn:admin1_code":"20",
    "gn:admin2_code":"2003.0",
    "gn:admin3_code":"200304.0",
    "gn:asciiname":"Soso",
    "gn:country_code":"PE",
    "gn:dem":2573,
    "gn:feature_class":"P",
    "gn:feature_code":"PPL",
    "gn:name":"Soso",
    "gn:population":0,
    "gn:timezone":"America/Lima",
    "iso:country":"PE",
    "name:ceb_x_preferred":[
        "Soso"
    ],
    "name:fra_x_preferred":[
        "Soso"
    ],
    "name:ita_x_preferred":[
        "Soso"
    ],
    "name:rus_x_preferred":[
        "\u0421\u043e\u0441\u043e"
    ],
    "name:swe_x_preferred":[
        "Soso"
    ],
    "wof:name":"Soso",
    "wof:placetype":"locality"
},
  "geometry": {"coordinates":[-79.47667,-5.54551],"type":"Point"}
}