{
  "type": "Feature",
  "properties": {
    "gn:admin1_code":"06",
    "gn:admin2_code":"606.0",
    "gn:admin3_code":"60607.0",
    "gn:asciiname":"Sabuindo",
    "gn:country_code":"PE",
    "gn:dem":1958,
    "gn:feature_class":"P",
    "gn:feature_code":"PPL",
    "gn:name":"Sabuindo",
    "gn:population":0,
    "gn:timezone":"America/Lima",
    "iso:country":"PE",
    "wof:name":"Sabuindo",
    "wof:placetype":"locality"
},
  "geometry": {"coordinates":[-79.11343000000002,-6.19142],"type":"Point"}
}