{
  "type": "Feature",
  "properties": {
    "gn:admin1_code":"9.0",
    "gn:admin2_code":"907.0",
    "gn:admin3_code":"90705.0",
    "gn:asciiname":"Campo Armino",
    "gn:country_code":"PE",
    "gn:dem":1914,
    "gn:feature_class":"P",
    "gn:feature_code":"PPL",
    "gn:name":"Campo Armi\u00f1o",
    "gn:population":0,
    "gn:timezone":"America/Lima",
    "iso:country":"PE",
    "wof:name":"Campo Armino",
    "wof:placetype":"locality"
},
  "geometry": {"coordinates":[-74.64775999999998,-12.35095],"type":"Point"}
}