{
  "type": "Feature",
  "properties": {
    "gn:admin1_code":"21",
    "gn:admin2_code":"2101.0",
    "gn:admin3_code":"210107.0",
    "gn:asciiname":"Sacanagachi",
    "gn:country_code":"PE",
    "gn:dem":3835,
    "gn:feature_class":"P",
    "gn:feature_code":"PPL",
    "gn:name":"Sacanagachi",
    "gn:population":0,
    "gn:timezone":"America/Lima",
    "iso:country":"PE",
    "name:und_x_variant":[
        "Sacanagachi Hacienda",
        "Sacanagachi"
    ],
    "wof:name":"Sacanagachi",
    "wof:placetype":"locality"
},
  "geometry": {"coordinates":[-69.87300999999999,-15.55281],"type":"Point"}
}