{
  "type": "Feature",
  "properties": {
    "gn:admin1_code":"12",
    "gn:admin2_code":"1206.0",
    "gn:admin3_code":"120608.0",
    "gn:asciiname":"Sabado De Gloria",
    "gn:country_code":"PE",
    "gn:dem":222,
    "gn:feature_class":"P",
    "gn:feature_code":"PPL",
    "gn:name":"S\u00e1bado De Gloria",
    "gn:population":0,
    "gn:timezone":"America/Lima",
    "iso:country":"PE",
    "name:spa_x_preferred":[
        "S\u00e1bado De Gloria"
    ],
    "wof:name":"Sabado De Gloria",
    "wof:placetype":"locality"
},
  "geometry": {"coordinates":[-73.74544,-10.76862],"type":"Point"}
}