{
  "type": "Feature",
  "properties": {
    "gn:admin1_code":"21",
    "gn:admin2_code":"2102.0",
    "gn:admin3_code":"210209.0",
    "gn:asciiname":"Apasja Mana",
    "gn:country_code":"PE",
    "gn:dem":4235,
    "gn:feature_class":"P",
    "gn:feature_code":"PPL",
    "gn:name":"Apasja Ma\u00f1a",
    "gn:population":0,
    "gn:timezone":"America/Lima",
    "iso:country":"PE",
    "wof:name":"Apasja Mana",
    "wof:placetype":"locality"
},
  "geometry": {"coordinates":[-69.92036,-14.42254],"type":"Point"}
}