{
  "type": "Feature",
  "properties": {
    "gn:admin1_code":"24",
    "gn:admin2_code":"2403.0",
    "gn:admin3_code":"240301.0",
    "gn:asciiname":"Puerto Gallego Chico",
    "gn:country_code":"PE",
    "gn:dem":3,
    "gn:feature_class":"P",
    "gn:feature_code":"PPL",
    "gn:name":"Puerto Gallego Chico",
    "gn:population":0,
    "gn:timezone":"America/Lima",
    "iso:country":"PE",
    "wof:name":"Puerto Gallego Chico",
    "wof:placetype":"locality"
},
  "geometry": {"coordinates":[-80.28161,-3.44968],"type":"Point"}
}