{
  "type": "Feature",
  "properties": {
    "gn:admin1_code":"15.0",
    "gn:admin2_code":"1506.0",
    "gn:admin3_code":"150601.0",
    "gn:asciiname":"Maria Luisa",
    "gn:country_code":"PE",
    "gn:dem":231,
    "gn:feature_class":"P",
    "gn:feature_code":"PPL",
    "gn:name":"Mar\u00eda Luisa",
    "gn:population":0,
    "gn:timezone":"America/Lima",
    "iso:country":"PE",
    "wof:name":"Maria Luisa",
    "wof:placetype":"locality"
},
  "geometry": {"coordinates":[-77.2175,-11.43694],"type":"Point"}
}