{
  "type": "Feature",
  "properties": {
    "gn:admin1_code":"12",
    "gn:admin2_code":"1204.0",
    "gn:admin3_code":"120433.0",
    "gn:asciiname":"Yauli",
    "gn:country_code":"PE",
    "gn:dem":3418,
    "gn:feature_class":"P",
    "gn:feature_code":"PPLA3",
    "gn:name":"Yauli",
    "gn:population":0,
    "gn:timezone":"America/Lima",
    "iso:country":"PE",
    "name:ceb_x_preferred":[
        "Yauli"
    ],
    "name:nld_x_preferred":[
        "Yauli"
    ],
    "name:por_x_preferred":[
        "Yauli"
    ],
    "wof:name":"Yauli",
    "wof:placetype":"locality"
},
  "geometry": {"coordinates":[-75.47466,-11.71366],"type":"Point"}
}