{
  "type": "Feature",
  "properties": {
    "gn:admin1_code":"04",
    "gn:admin2_code":"406.0",
    "gn:admin3_code":"40602.0",
    "gn:asciiname":"Hacienda Tomapampa",
    "gn:country_code":"PE",
    "gn:dem":3208,
    "gn:feature_class":"P",
    "gn:feature_code":"PPL",
    "gn:name":"Hacienda Tomapampa",
    "gn:population":0,
    "gn:timezone":"America/Lima",
    "iso:country":"PE",
    "wof:name":"Hacienda Tomapampa",
    "wof:placetype":"locality"
},
  "geometry": {"coordinates":[-72.83471999999998,-15.84311],"type":"Point"}
}