{
  "type": "Feature",
  "properties": {
    "gn:admin1_code":"06",
    "gn:admin2_code":"602.0",
    "gn:admin3_code":"60202.0",
    "gn:asciiname":"Pauquilla",
    "gn:country_code":"PE",
    "gn:dem":2856,
    "gn:feature_class":"P",
    "gn:feature_code":"PPL",
    "gn:name":"Pauquilla",
    "gn:population":0,
    "gn:timezone":"America/Lima",
    "iso:country":"PE",
    "wof:name":"Pauquilla",
    "wof:placetype":"locality"
},
  "geometry": {"coordinates":[-78.21213,-7.56914],"type":"Point"}
}