{
  "type": "Feature",
  "properties": {
    "gn:admin1_code":"2.0",
    "gn:admin2_code":"208.0",
    "gn:admin3_code":"20804.0",
    "gn:asciiname":"Carancayoc",
    "gn:country_code":"PE",
    "gn:dem":1944,
    "gn:feature_class":"P",
    "gn:feature_code":"PPL",
    "gn:name":"Carancayoc",
    "gn:population":0,
    "gn:timezone":"America/Lima",
    "iso:country":"PE",
    "wof:name":"Carancayoc",
    "wof:placetype":"locality"
},
  "geometry": {"coordinates":[-77.96110999999998,-9.44639],"type":"Point"}
}