{
  "type": "Feature",
  "properties": {
    "gn:admin1_code":"8",
    "gn:admin2_code":"810.0",
    "gn:admin3_code":"81006.0",
    "gn:asciiname":"Antapallpa",
    "gn:country_code":"PE",
    "gn:dem":3882,
    "gn:feature_class":"P",
    "gn:feature_code":"PPL",
    "gn:name":"Antapallpa",
    "gn:population":0,
    "gn:timezone":"America/Lima",
    "iso:country":"PE",
    "wof:name":"Antapallpa",
    "wof:placetype":"locality"
},
  "geometry": {"coordinates":[-71.71694000000002,-14.12778],"type":"Point"}
}