{
  "type": "Feature",
  "properties": {
    "gn:admin1_code":"11.0",
    "gn:admin2_code":"1102.0",
    "gn:admin3_code":"110210.0",
    "gn:asciiname":"Santa Catalina",
    "gn:country_code":"PE",
    "gn:dem":49,
    "gn:feature_class":"P",
    "gn:feature_code":"PPL",
    "gn:name":"Santa Catalina",
    "gn:population":0,
    "gn:timezone":"America/Lima",
    "iso:country":"PE",
    "wof:name":"Santa Catalina",
    "wof:placetype":"locality"
},
  "geometry": {"coordinates":[-76.16946999999998,-13.43744],"type":"Point"}
}