{
  "type": "Feature",
  "properties": {
    "gn:admin1_code":"16",
    "gn:admin2_code":"1603.0",
    "gn:admin3_code":"160305.0",
    "gn:asciiname":"San Pedro",
    "gn:country_code":"PE",
    "gn:dem":109,
    "gn:feature_class":"P",
    "gn:feature_code":"PPL",
    "gn:name":"San Pedro",
    "gn:population":0,
    "gn:timezone":"America/Lima",
    "iso:country":"PE",
    "wof:name":"San Pedro",
    "wof:placetype":"locality"
},
  "geometry": {"coordinates":[-75.06276,-4.76114],"type":"Point"}
}