{
  "type": "Feature",
  "properties": {
    "gn:admin1_code":"3",
    "gn:admin2_code":"302.0",
    "gn:admin3_code":"30202.0",
    "gn:asciiname":"Chuco",
    "gn:country_code":"PE",
    "gn:dem":3187,
    "gn:feature_class":"P",
    "gn:feature_code":"PPL",
    "gn:name":"Chuco",
    "gn:population":0,
    "gn:timezone":"America/Lima",
    "iso:country":"PE",
    "wof:name":"Chuco",
    "wof:placetype":"locality"
},
  "geometry": {"coordinates":[-73.381,-13.54349],"type":"Point"}
}