{
  "type": "Feature",
  "properties": {
    "gn:admin1_code":"7.0",
    "gn:admin2_code":"701.0",
    "gn:asciiname":"Asentamiento Humano Piedra Liza",
    "gn:country_code":"PE",
    "gn:dem":17,
    "gn:feature_class":"P",
    "gn:feature_code":"PPL",
    "gn:name":"Asentamiento Humano Piedra Liza",
    "gn:population":0,
    "gn:timezone":"America/Lima",
    "iso:country":"PE",
    "name:spa_x_preferred":[
        "Asentamiento Humano Piedra Liza"
    ],
    "wof:name":"Asentamiento Humano Piedra Liza",
    "wof:placetype":"locality"
},
  "geometry": {"coordinates":[-77.11547,-11.98547],"type":"Point"}
}