{
  "type": "Feature",
  "properties": {
    "gn:admin1_code":"2.0",
    "gn:admin2_code":"214.0",
    "gn:admin3_code":"21409.0",
    "gn:asciiname":"Shambracoto",
    "gn:country_code":"PE",
    "gn:dem":1771,
    "gn:feature_class":"P",
    "gn:feature_code":"PPL",
    "gn:name":"Shambracoto",
    "gn:population":0,
    "gn:timezone":"America/Lima",
    "iso:country":"PE",
    "wof:name":"Shambracoto",
    "wof:placetype":"locality"
},
  "geometry": {"coordinates":[-77.48659000000001,-10.41831],"type":"Point"}
}