{
  "type": "Feature",
  "properties": {
    "gn:admin1_code":"8",
    "gn:admin2_code":"805.0",
    "gn:admin3_code":"80501.0",
    "gn:asciiname":"Pusacucho",
    "gn:country_code":"PE",
    "gn:dem":4018,
    "gn:feature_class":"P",
    "gn:feature_code":"PPL",
    "gn:name":"Pusacucho",
    "gn:population":0,
    "gn:timezone":"America/Lima",
    "iso:country":"PE",
    "wof:name":"Pusacucho",
    "wof:placetype":"locality"
},
  "geometry": {"coordinates":[-71.45973000000002,-14.24147],"type":"Point"}
}