{
  "type": "Feature",
  "properties": {
    "gn:admin1_code":"5.0",
    "gn:admin2_code":"504.0",
    "gn:admin3_code":"50407.0",
    "gn:asciiname":"Jeullacocha",
    "gn:country_code":"PE",
    "gn:dem":3798,
    "gn:feature_class":"P",
    "gn:feature_code":"PPL",
    "gn:name":"Jeullacocha",
    "gn:population":0,
    "gn:timezone":"America/Lima",
    "iso:country":"PE",
    "wof:name":"Jeullacocha",
    "wof:placetype":"locality"
},
  "geometry": {"coordinates":[-74.14086999999998,-12.63586],"type":"Point"}
}