{
  "type": "Feature",
  "properties": {
    "gn:admin1_code":"11",
    "gn:admin2_code":"1101.0",
    "gn:admin3_code":"110114.0",
    "gn:asciiname":"Pampahuasi",
    "gn:cc2":"PE",
    "gn:country_code":"PE",
    "gn:dem":839,
    "gn:feature_class":"P",
    "gn:feature_code":"PPL",
    "gn:name":"Pampahuasi",
    "gn:population":0,
    "gn:timezone":"America/Lima",
    "iso:country":"PE",
    "name:und_x_variant":[
        "Hacienda Pampa Huasi",
        "Pampa Huasi Hacienda",
        "Pampa Huasi",
        "Pampahuasi"
    ],
    "wof:name":"Pampahuasi",
    "wof:placetype":"locality"
},
  "geometry": {"coordinates":[-75.47667,-14.10083],"type":"Point"}
}