{
  "type": "Feature",
  "properties": {
    "gn:admin1_code":"21",
    "gn:admin2_code":"2104.0",
    "gn:admin3_code":"210406.0",
    "gn:asciiname":"Sallullohuinto",
    "gn:country_code":"PE",
    "gn:dem":3841,
    "gn:feature_class":"P",
    "gn:feature_code":"PPL",
    "gn:name":"Sallullohuinto",
    "gn:population":0,
    "gn:timezone":"America/Lima",
    "iso:country":"PE",
    "wof:name":"Sallullohuinto",
    "wof:placetype":"locality"
},
  "geometry": {"coordinates":[-69.25538,-16.38419],"type":"Point"}
}