{
  "type": "Feature",
  "properties": {
    "gn:admin1_code":"06",
    "gn:admin2_code":"603.0",
    "gn:admin3_code":"60309.0",
    "gn:asciiname":"Faro",
    "gn:country_code":"PE",
    "gn:dem":2829,
    "gn:feature_class":"P",
    "gn:feature_code":"PPL",
    "gn:name":"Faro",
    "gn:population":0,
    "gn:timezone":"America/Lima",
    "iso:country":"PE",
    "wof:name":"Faro",
    "wof:placetype":"locality"
},
  "geometry": {"coordinates":[-78.27417,-6.92306],"type":"Point"}
}