{
  "type": "Feature",
  "properties": {
    "gn:admin1_code":"04",
    "gn:admin2_code":"401.0",
    "gn:admin3_code":"40113.0",
    "gn:asciiname":"Pena Blanca",
    "gn:country_code":"PE",
    "gn:dem":3451,
    "gn:feature_class":"P",
    "gn:feature_code":"PPL",
    "gn:name":"Pe\u00f1a Blanca",
    "gn:population":0,
    "gn:timezone":"America/Lima",
    "iso:country":"PE",
    "wof:name":"Pena Blanca",
    "wof:placetype":"locality"
},
  "geometry": {"coordinates":[-71.30067,-16.53901],"type":"Point"}
}