{
  "type": "Feature",
  "properties": {
    "gn:admin1_code":"21",
    "gn:admin2_code":"2106.0",
    "gn:admin3_code":"210604.0",
    "gn:asciiname":"Layune",
    "gn:country_code":"PE",
    "gn:dem":3977,
    "gn:feature_class":"P",
    "gn:feature_code":"PPL",
    "gn:name":"Layune",
    "gn:population":0,
    "gn:timezone":"America/Lima",
    "iso:country":"PE",
    "wof:name":"Layune",
    "wof:placetype":"locality"
},
  "geometry": {"coordinates":[-69.69609,-15.04581],"type":"Point"}
}