{
  "type": "Feature",
  "properties": {
    "gn:admin1_code":"21",
    "gn:admin2_code":"2104.0",
    "gn:admin3_code":"210404.0",
    "gn:asciiname":"Jachacirca",
    "gn:country_code":"PE",
    "gn:dem":3940,
    "gn:feature_class":"P",
    "gn:feature_code":"PPL",
    "gn:name":"Jachacirca",
    "gn:population":0,
    "gn:timezone":"America/Lima",
    "iso:country":"PE",
    "wof:name":"Jachacirca",
    "wof:placetype":"locality"
},
  "geometry": {"coordinates":[-69.27888,-16.72856],"type":"Point"}
}