{
  "type": "Feature",
  "properties": {
    "gn:admin1_code":"11",
    "gn:admin2_code":"1101.0",
    "gn:admin3_code":"110107.0",
    "gn:asciiname":"Pueblo Nuevo",
    "gn:country_code":"PE",
    "gn:dem":403,
    "gn:feature_class":"P",
    "gn:feature_code":"PPLA3",
    "gn:name":"Pueblo Nuevo",
    "gn:population":0,
    "gn:timezone":"America/Lima",
    "iso:country":"PE",
    "name:ceb_x_preferred":[
        "Pueblo Nuevo"
    ],
    "name:deu_x_preferred":[
        "Pueblo Nuevo"
    ],
    "name:epo_x_preferred":[
        "Pueblo Nuevo"
    ],
    "name:fra_x_preferred":[
        "Pueblo Nuevo"
    ],
    "name:ita_x_preferred":[
        "Pueblo Nuevo"
    ],
    "name:nds_x_preferred":[
        "Pueblo Nuevo"
    ],
    "name:nld_x_preferred":[
        "Pueblo Nuevo"
    ],
    "name:pol_x_preferred":[
        "Pueblo Nuevo"
    ],
    "name:por_x_preferred":[
        "Pueblo Nuevo"
    ],
    "name:rus_x_preferred":[
        "\u041f\u0443\u044d\u0431\u043b\u043e-\u041d\u0443\u044d\u0432\u043e"
    ],
    "name:sco_x_preferred":[
        "Pueblo Nuevo"
    ],
    "name:spa_x_preferred":[
        "Pueblo Nuevo"
    ],
    "name:srp_x_preferred":[
        "\u041f\u0443\u0435\u0431\u043b\u043e \u041d\u0443\u0435\u0432\u043e"
    ],
    "name:swe_x_preferred":[
        "Pueblo Nuevo"
    ],
    "name:und_x_variant":[
        "Pueblo Nueva",
        "Pueblo Nuevo"
    ],
    "name:vie_x_preferred":[
        "Pueblo Nuevo"
    ],
    "wof:name":"Pueblo Nuevo",
    "wof:placetype":"locality"
},
  "geometry": {"coordinates":[-75.70666999999997,-14.12806],"type":"Point"}
}