{
  "type": "Feature",
  "properties": {
    "gn:admin1_code":"21",
    "gn:admin2_code":"2101.0",
    "gn:admin3_code":"210101.0",
    "gn:asciiname":"Collpaculco",
    "gn:country_code":"PE",
    "gn:dem":3962,
    "gn:feature_class":"P",
    "gn:feature_code":"PPL",
    "gn:name":"Collpaculco",
    "gn:population":0,
    "gn:timezone":"America/Lima",
    "iso:country":"PE",
    "name:und_x_variant":[
        "Collpaculco Hacienda",
        "Collpaculco"
    ],
    "wof:name":"Collpaculco",
    "wof:placetype":"locality"
},
  "geometry": {"coordinates":[-70.08282,-15.98981],"type":"Point"}
}