{
  "type": "Feature",
  "properties": {
    "gn:admin1_code":"8.0",
    "gn:admin2_code":"803.0",
    "gn:admin3_code":"80302.0",
    "gn:asciiname":"Canomanyoc",
    "gn:country_code":"PE",
    "gn:dem":3626,
    "gn:feature_class":"P",
    "gn:feature_code":"PPL",
    "gn:name":"Ca\u00f1oma\u00f1yoc",
    "gn:population":0,
    "gn:timezone":"America/Lima",
    "iso:country":"PE",
    "wof:name":"Canomanyoc",
    "wof:placetype":"locality"
},
  "geometry": {"coordinates":[-72.31111,-13.49333],"type":"Point"}
}