{
  "type": "Feature",
  "properties": {
    "gn:admin1_code":"12.0",
    "gn:admin2_code":"1201.0",
    "gn:asciiname":"Vilcamarca",
    "gn:country_code":"PE",
    "gn:dem":1989,
    "gn:feature_class":"P",
    "gn:feature_code":"PPL",
    "gn:name":"Vilcamarca",
    "gn:population":0,
    "gn:timezone":"America/Lima",
    "iso:country":"PE",
    "wof:name":"Vilcamarca",
    "wof:placetype":"locality"
},
  "geometry": {"coordinates":[-74.73007,-12.03604],"type":"Point"}
}