{
  "type": "Feature",
  "properties": {
    "gn:admin1_code":"9",
    "gn:admin2_code":"904.0",
    "gn:asciiname":"Ripayoc",
    "gn:country_code":"PE",
    "gn:dem":4386,
    "gn:feature_class":"P",
    "gn:feature_code":"PPL",
    "gn:name":"Ripayoc",
    "gn:population":0,
    "gn:timezone":"America/Lima",
    "iso:country":"PE",
    "wof:name":"Ripayoc",
    "wof:placetype":"locality"
},
  "geometry": {"coordinates":[-75.59389,-12.87667],"type":"Point"}
}