{
  "type": "Feature",
  "properties": {
    "gn:admin1_code":"5",
    "gn:admin2_code":"505.0",
    "gn:admin3_code":"50501.0",
    "gn:asciiname":"Campana",
    "gn:country_code":"PE",
    "gn:dem":3819,
    "gn:feature_class":"P",
    "gn:feature_code":"PPL",
    "gn:name":"Campana",
    "gn:population":0,
    "gn:timezone":"America/Lima",
    "iso:country":"PE",
    "name:cat_x_preferred":[
        "Campana"
    ],
    "name:ceb_x_preferred":[
        "Campana"
    ],
    "name:deu_x_preferred":[
        "Campana"
    ],
    "name:epo_x_preferred":[
        "Campana"
    ],
    "name:eus_x_preferred":[
        "Campana"
    ],
    "name:fra_x_preferred":[
        "Campana"
    ],
    "name:glg_x_preferred":[
        "Camp\u00e1"
    ],
    "name:ita_x_preferred":[
        "Campana"
    ],
    "name:nds_x_preferred":[
        "Campana"
    ],
    "name:nld_x_preferred":[
        "Campana"
    ],
    "name:pol_x_preferred":[
        "Campana"
    ],
    "name:por_x_preferred":[
        "Campana"
    ],
    "name:rus_x_preferred":[
        "\u041a\u0430\u043c\u043f\u0430\u043d\u0430"
    ],
    "name:scn_x_preferred":[
        "Campana"
    ],
    "name:slk_x_preferred":[
        "Campana"
    ],
    "name:slv_x_preferred":[
        "Campana"
    ],
    "name:spa_x_preferred":[
        "Campana"
    ],
    "name:srp_x_preferred":[
        "Kampana"
    ],
    "name:swe_x_preferred":[
        "Campana"
    ],
    "name:ukr_x_preferred":[
        "\u041a\u0430\u043c\u043f\u0430\u043d\u0430"
    ],
    "name:vol_x_preferred":[
        "Campana"
    ],
    "name:zho_x_preferred":[
        "\u574e\u5e15\u7d0d"
    ],
    "wof:name":"Campana",
    "wof:placetype":"locality"
},
  "geometry": {"coordinates":[-73.84475999999999,-13.00734],"type":"Point"}
}