{
  "type": "Feature",
  "properties": {
    "iso:country":"PE",
    "name:deu_x_preferred":[
        "Chulucanas"
    ],
    "name:fra_x_preferred":[
        "Chulucanas"
    ],
    "name:ita_x_preferred":[
        "Chulucanas"
    ],
    "name:pol_x_preferred":[
        "Chulucanas"
    ],
    "name:que_x_preferred":[
        "Chulucanas"
    ],
    "name:spa_x_preferred":[
        "Chulucanas"
    ],
    "name:unk_x_variant":[
        "Chulucanas Hacienda"
    ],
    "name:war_x_preferred":[
        "Chulucanas"
    ],
    "name:zho_x_preferred":[
        "\u4e18\u76e7\u5361\u7d0d\u65af"
    ],
    "qs:gn_country":"PE",
    "qs:gn_fcode":"PPL",
    "qs:gn_pop":0,
    "qs:name":"Chulucanas",
    "qs:name_adm0":"Per\u00fa",
    "qs:name_adm1":"Piura",
    "qs:photos":1034,
    "qs:photos_1k":210,
    "qs:photos_9k":5,
    "qs:photos_9r":7,
    "qs:photos_all":1034,
    "qs:photos_sr":11,
    "qs:placetype":"Town",
    "qs:pop_sr":"0",
    "qs:woe_adm0":23424919,
    "wd:wordcount":328,
    "wof:name":"Chulucanas",
    "wof:placetype":"locality"
},
  "geometry": {"coordinates":[-79.58333,-5.1],"type":"Point"}
}