{
  "type": "Feature",
  "properties": {
    "gn:admin1_code":"15.0",
    "gn:admin2_code":"1505.0",
    "gn:admin3_code":"150507.0",
    "gn:asciiname":"La Mejora",
    "gn:country_code":"PE",
    "gn:dem":91,
    "gn:feature_class":"P",
    "gn:feature_code":"PPL",
    "gn:name":"La Mejora",
    "gn:population":0,
    "gn:timezone":"America/Lima",
    "iso:country":"PE",
    "wof:name":"La Mejora",
    "wof:placetype":"locality"
},
  "geometry": {"coordinates":[-76.38786,-13.01593],"type":"Point"}
}