{
  "type": "Feature",
  "properties": {
    "gn:admin1_code":"18",
    "gn:admin2_code":"1802.0",
    "gn:admin3_code":"180201.0",
    "gn:asciiname":"Carabava",
    "gn:country_code":"PE",
    "gn:dem":2669,
    "gn:feature_class":"P",
    "gn:feature_code":"PPL",
    "gn:name":"Carabava",
    "gn:population":0,
    "gn:timezone":"America/Lima",
    "iso:country":"PE",
    "wof:name":"Carabava",
    "wof:placetype":"locality"
},
  "geometry": {"coordinates":[-70.96605,-16.63666],"type":"Point"}
}