{
  "type": "Feature",
  "properties": {
    "gn:admin1_code":"15",
    "gn:admin2_code":"1510.0",
    "gn:admin3_code":"151001.0",
    "gn:asciiname":"Zanin",
    "gn:country_code":"PE",
    "gn:dem":1848,
    "gn:feature_class":"P",
    "gn:feature_code":"PPL",
    "gn:name":"Za\u00f1in",
    "gn:population":0,
    "gn:timezone":"America/Lima",
    "iso:country":"PE",
    "wof:name":"Zanin",
    "wof:placetype":"locality"
},
  "geometry": {"coordinates":[-75.97595,-12.62205],"type":"Point"}
}