{
  "type": "Feature",
  "properties": {
    "gn:admin1_code":"4",
    "gn:admin2_code":"403.0",
    "gn:admin3_code":"40305.0",
    "gn:asciiname":"Aguada de Lomas",
    "gn:country_code":"PE",
    "gn:dem":50,
    "gn:feature_class":"P",
    "gn:feature_code":"PPL",
    "gn:name":"Aguada de Lomas",
    "gn:population":0,
    "gn:timezone":"America/Lima",
    "iso:country":"PE",
    "name:und_x_variant":[
        "Aquada de Lomas",
        "Aguada de Lomas"
    ],
    "wof:name":"Aguada de Lomas",
    "wof:placetype":"locality"
},
  "geometry": {"coordinates":[-74.79850999999999,-15.50747],"type":"Point"}
}