{
  "type": "Feature",
  "properties": {
    "gn:admin1_code":"8.0",
    "gn:admin2_code":"813.0",
    "gn:admin3_code":"81305.0",
    "gn:asciiname":"Rurucancha",
    "gn:country_code":"PE",
    "gn:dem":3700,
    "gn:feature_class":"P",
    "gn:feature_code":"PPL",
    "gn:name":"Rurucancha",
    "gn:population":0,
    "gn:timezone":"America/Lima",
    "iso:country":"PE",
    "wof:name":"Rurucancha",
    "wof:placetype":"locality"
},
  "geometry": {"coordinates":[-72.20056,-13.34056],"type":"Point"}
}