{
  "type": "Feature",
  "properties": {
    "gn:admin1_code":"06",
    "gn:admin2_code":"604.0",
    "gn:admin3_code":"60416.0",
    "gn:asciiname":"Camellon",
    "gn:country_code":"PE",
    "gn:dem":607,
    "gn:feature_class":"P",
    "gn:feature_code":"PPL",
    "gn:name":"Camell\u00f3n",
    "gn:population":0,
    "gn:timezone":"America/Lima",
    "iso:country":"PE",
    "wof:name":"Camellon",
    "wof:placetype":"locality"
},
  "geometry": {"coordinates":[-79.2728,-6.53717],"type":"Point"}
}