{
  "type": "Feature",
  "properties": {
    "gn:admin1_code":"9.0",
    "gn:admin2_code":"907.0",
    "gn:admin3_code":"90714.0",
    "gn:asciiname":"Mollipata",
    "gn:country_code":"PE",
    "gn:dem":2946,
    "gn:feature_class":"P",
    "gn:feature_code":"PPL",
    "gn:name":"Mollipata",
    "gn:population":0,
    "gn:timezone":"America/Lima",
    "iso:country":"PE",
    "wof:name":"Mollipata",
    "wof:placetype":"locality"
},
  "geometry": {"coordinates":[-74.82399000000002,-12.27357],"type":"Point"}
}