{
  "type": "Feature",
  "properties": {
    "gn:admin1_code":"4",
    "gn:admin2_code":"405.0",
    "gn:admin3_code":"40515.0",
    "gn:asciiname":"Chachue",
    "gn:country_code":"PE",
    "gn:dem":4052,
    "gn:feature_class":"P",
    "gn:feature_code":"PPL",
    "gn:name":"Chachue",
    "gn:population":0,
    "gn:timezone":"America/Lima",
    "iso:country":"PE",
    "wof:name":"Chachue",
    "wof:placetype":"locality"
},
  "geometry": {"coordinates":[-71.46970999999998,-15.47518],"type":"Point"}
}