{
  "type": "Feature",
  "properties": {
    "gn:admin1_code":"21",
    "gn:admin2_code":"2112",
    "gn:asciiname":"Cajatira",
    "gn:country_code":"PE",
    "gn:dem":1024,
    "gn:feature_class":"P",
    "gn:feature_code":"PPL",
    "gn:name":"Cajatira",
    "gn:population":0,
    "gn:timezone":"America/Lima",
    "iso:country":"PE",
    "name:spa_x_preferred":[
        "Cajatira"
    ],
    "wof:name":"Cajatira",
    "wof:placetype":"locality"
},
  "geometry": {"coordinates":[-69.60968000000001,-13.9035],"type":"Point"}
}