{
  "type": "Feature",
  "properties": {
    "gn:admin1_code":"16",
    "gn:admin2_code":"1606.0",
    "gn:admin3_code":"160605.0",
    "gn:asciiname":"Grau",
    "gn:country_code":"PE",
    "gn:dem":122,
    "gn:feature_class":"P",
    "gn:feature_code":"PPL",
    "gn:name":"Grau",
    "gn:population":0,
    "gn:timezone":"America/Lima",
    "iso:country":"PE",
    "name:arg_x_preferred":[
        "Grau"
    ],
    "name:ast_x_preferred":[
        "Grau"
    ],
    "name:bre_x_preferred":[
        "Grau"
    ],
    "name:cat_x_preferred":[
        "Grau"
    ],
    "name:deu_x_preferred":[
        "Grau"
    ],
    "name:fra_x_preferred":[
        "Grau"
    ],
    "name:lav_x_preferred":[
        "Grau"
    ],
    "name:nld_x_preferred":[
        "Grau"
    ],
    "name:pol_x_preferred":[
        "Grau"
    ],
    "name:por_x_preferred":[
        "Grau"
    ],
    "name:spa_x_preferred":[
        "Grau"
    ],
    "wof:name":"Grau",
    "wof:placetype":"locality"
},
  "geometry": {"coordinates":[-75.06851,-6.60011],"type":"Point"}
}