{
  "type": "Feature",
  "properties": {
    "gn:admin1_code":"14",
    "gn:admin2_code":"1401.0",
    "gn:admin3_code":"140108.0",
    "gn:asciiname":"Palmo",
    "gn:country_code":"PE",
    "gn:dem":12,
    "gn:feature_class":"P",
    "gn:feature_code":"PPL",
    "gn:name":"Palmo",
    "gn:population":0,
    "gn:timezone":"America/Lima",
    "iso:country":"PE",
    "name:deu_x_preferred":[
        "Palmo"
    ],
    "name:ita_x_preferred":[
        "Palmo"
    ],
    "wof:name":"Palmo",
    "wof:placetype":"locality"
},
  "geometry": {"coordinates":[-79.86667,-6.86667],"type":"Point"}
}