{
  "type": "Feature",
  "properties": {
    "gn:admin1_code":"06",
    "gn:admin2_code":"611.0",
    "gn:admin3_code":"61106.0",
    "gn:asciiname":"La Florida",
    "gn:cc2":"PE",
    "gn:country_code":"PE",
    "gn:dem":1041,
    "gn:feature_class":"P",
    "gn:feature_code":"PPLA3",
    "gn:name":"La Florida",
    "gn:population":0,
    "gn:timezone":"America/Lima",
    "iso:country":"PE",
    "name:bre_x_preferred":[
        "La Florida"
    ],
    "name:ceb_x_preferred":[
        "La Florida"
    ],
    "name:fra_x_preferred":[
        "La Florida"
    ],
    "name:ita_x_preferred":[
        "La Florida"
    ],
    "name:nld_x_preferred":[
        "La Florida"
    ],
    "name:sco_x_preferred":[
        "La Florida"
    ],
    "name:spa_x_preferred":[
        "La Florida"
    ],
    "name:srp_x_preferred":[
        "\u041b\u0430 \u0424\u043b\u043e\u0440\u0438\u0434\u0430"
    ],
    "name:swe_x_preferred":[
        "La Florida"
    ],
    "name:und_x_variant":[
        "Florida"
    ],
    "wof:name":"La Florida",
    "wof:placetype":"locality"
},
  "geometry": {"coordinates":[-79.12111,-6.86972],"type":"Point"}
}