{
  "type": "Feature",
  "properties": {
    "gn:admin1_code":"15",
    "gn:admin2_code":"1506.0",
    "gn:admin3_code":"150602.0",
    "gn:asciiname":"Rancatama",
    "gn:country_code":"PE",
    "gn:dem":2686,
    "gn:feature_class":"P",
    "gn:feature_code":"PPL",
    "gn:name":"Rancatama",
    "gn:population":0,
    "gn:timezone":"America/Lima",
    "iso:country":"PE",
    "wof:name":"Rancatama",
    "wof:placetype":"locality"
},
  "geometry": {"coordinates":[-76.68333,-11.24417],"type":"Point"}
}