{
  "type": "Feature",
  "properties": {
    "gn:admin1_code":"13",
    "gn:admin2_code":"1310.0",
    "gn:admin3_code":"131003.0",
    "gn:asciiname":"Calamalca",
    "gn:country_code":"PE",
    "gn:dem":3718,
    "gn:feature_class":"P",
    "gn:feature_code":"PPL",
    "gn:name":"Calamalca",
    "gn:population":0,
    "gn:timezone":"America/Lima",
    "iso:country":"PE",
    "wof:name":"Calamalca",
    "wof:placetype":"locality"
},
  "geometry": {"coordinates":[-78.09198000000001,-7.98286],"type":"Point"}
}