{
  "type": "Feature",
  "properties": {
    "gn:admin1_code":"04",
    "gn:admin2_code":"406.0",
    "gn:admin3_code":"40608.0",
    "gn:asciiname":"Hacienda Asillo",
    "gn:country_code":"PE",
    "gn:dem":3494,
    "gn:feature_class":"P",
    "gn:feature_code":"PPL",
    "gn:name":"Hacienda Asillo",
    "gn:population":0,
    "gn:timezone":"America/Lima",
    "iso:country":"PE",
    "name:und_x_variant":[
        "Hacienda Asilio"
    ],
    "wof:name":"Hacienda Asillo",
    "wof:placetype":"locality"
},
  "geometry": {"coordinates":[-72.89694,-15.71972],"type":"Point"}
}