{
  "type": "Feature",
  "properties": {
    "gn:admin1_code":"9.0",
    "gn:admin2_code":"907.0",
    "gn:admin3_code":"90704.0",
    "gn:asciiname":"Occoro",
    "gn:country_code":"PE",
    "gn:dem":4202,
    "gn:feature_class":"P",
    "gn:feature_code":"PPL",
    "gn:name":"Occoro",
    "gn:population":0,
    "gn:timezone":"America/Lima",
    "iso:country":"PE",
    "wof:name":"Occoro",
    "wof:placetype":"locality"
},
  "geometry": {"coordinates":[-74.93141,-12.47133],"type":"Point"}
}