{
  "type": "Feature",
  "properties": {
    "gn:admin1_code":"2.0",
    "gn:admin2_code":"205.0",
    "gn:asciiname":"Rumirumi",
    "gn:country_code":"PE",
    "gn:dem":4055,
    "gn:feature_class":"P",
    "gn:feature_code":"PPL",
    "gn:name":"Rumirumi",
    "gn:population":0,
    "gn:timezone":"America/Lima",
    "iso:country":"PE",
    "wof:name":"Rumirumi",
    "wof:placetype":"locality"
},
  "geometry": {"coordinates":[-76.9803,-9.76639],"type":"Point"}
}