{
  "type": "Feature",
  "properties": {
    "gn:admin1_code":"09",
    "gn:admin2_code":"906.0",
    "gn:admin3_code":"90616.0",
    "gn:asciiname":"Tincocc",
    "gn:country_code":"PE",
    "gn:dem":3762,
    "gn:feature_class":"P",
    "gn:feature_code":"PPL",
    "gn:name":"Tincocc",
    "gn:population":0,
    "gn:timezone":"America/Lima",
    "iso:country":"PE",
    "name:und_x_variant":[
        "Tincco",
        "Tincocc"
    ],
    "wof:name":"Tincocc",
    "wof:placetype":"locality"
},
  "geometry": {"coordinates":[-75.21869000000002,-13.62854],"type":"Point"}
}