{
  "type": "Feature",
  "properties": {
    "gn:admin1_code":"4",
    "gn:admin2_code":"401.0",
    "gn:admin3_code":"40125.0",
    "gn:asciiname":"Santa Rosa Hacienda",
    "gn:country_code":"PE",
    "gn:dem":1037,
    "gn:feature_class":"P",
    "gn:feature_code":"PPL",
    "gn:name":"Santa Rosa Hacienda",
    "gn:population":0,
    "gn:timezone":"America/Lima",
    "iso:country":"PE",
    "wof:name":"Santa Rosa Hacienda",
    "wof:placetype":"locality"
},
  "geometry": {"coordinates":[-71.98166999999999,-16.56361],"type":"Point"}
}