{
  "type": "Feature",
  "properties": {
    "gn:admin1_code":"9.0",
    "gn:admin2_code":"902.0",
    "gn:admin3_code":"90206.0",
    "gn:asciiname":"Tierra Colorada",
    "gn:country_code":"PE",
    "gn:dem":3701,
    "gn:feature_class":"P",
    "gn:feature_code":"PPL",
    "gn:name":"Tierra Colorada",
    "gn:population":0,
    "gn:timezone":"America/Lima",
    "iso:country":"PE",
    "wof:name":"Tierra Colorada",
    "wof:placetype":"locality"
},
  "geometry": {"coordinates":[-74.69733000000002,-12.77411],"type":"Point"}
}