{
  "type": "Feature",
  "properties": {
    "gn:admin1_code":"14",
    "gn:admin2_code":"1402.0",
    "gn:admin3_code":"140205.0",
    "gn:asciiname":"Botija",
    "gn:country_code":"PE",
    "gn:dem":60,
    "gn:feature_class":"P",
    "gn:feature_code":"PPL",
    "gn:name":"Botija",
    "gn:population":0,
    "gn:timezone":"America/Lima",
    "iso:country":"PE",
    "name:spa_x_preferred":[
        "Botija"
    ],
    "wof:name":"Botija",
    "wof:placetype":"locality"
},
  "geometry": {"coordinates":[-79.76564999999999,-6.56915],"type":"Point"}
}