{
  "type": "Feature",
  "properties": {
    "gn:admin1_code":"15",
    "gn:admin2_code":"1510.0",
    "gn:admin3_code":"151009.0",
    "gn:asciiname":"San Juanito",
    "gn:country_code":"PE",
    "gn:dem":898,
    "gn:feature_class":"P",
    "gn:feature_code":"PPL",
    "gn:name":"San Juanito",
    "gn:population":0,
    "gn:timezone":"America/Lima",
    "iso:country":"PE",
    "wof:name":"San Juanito",
    "wof:placetype":"locality"
},
  "geometry": {"coordinates":[-75.97643000000002,-12.83849],"type":"Point"}
}