{
  "type": "Feature",
  "properties": {
    "gn:admin1_code":"5.0",
    "gn:admin2_code":"508.0",
    "gn:asciiname":"Pallcca",
    "gn:country_code":"PE",
    "gn:dem":3559,
    "gn:feature_class":"P",
    "gn:feature_code":"PPL",
    "gn:name":"Pallcca",
    "gn:population":0,
    "gn:timezone":"America/Lima",
    "iso:country":"PE",
    "name:spa_x_preferred":[
        "Pallcca"
    ],
    "wof:name":"Pallcca",
    "wof:placetype":"locality"
},
  "geometry": {"coordinates":[-73.37092,-15.3312],"type":"Point"}
}