{
  "type": "Feature",
  "properties": {
    "gn:admin1_code":"21",
    "gn:admin2_code":"2107.0",
    "gn:admin3_code":"210702.0",
    "gn:asciiname":"Purutuyo",
    "gn:country_code":"PE",
    "gn:dem":4343,
    "gn:feature_class":"P",
    "gn:feature_code":"PPL",
    "gn:name":"Purutuyo",
    "gn:population":0,
    "gn:timezone":"America/Lima",
    "iso:country":"PE",
    "wof:name":"Purutuyo",
    "wof:placetype":"locality"
},
  "geometry": {"coordinates":[-70.46893,-15.62158],"type":"Point"}
}