{
  "type": "Feature",
  "properties": {
    "gn:admin1_code":"04",
    "gn:admin2_code":"403.0",
    "gn:admin3_code":"40312.0",
    "gn:asciiname":"Caylla",
    "gn:country_code":"PE",
    "gn:dem":3465,
    "gn:feature_class":"P",
    "gn:feature_code":"PPL",
    "gn:name":"Caylla",
    "gn:population":0,
    "gn:timezone":"America/Lima",
    "iso:country":"PE",
    "name:spa_x_preferred":[
        "Caylla"
    ],
    "wof:name":"Caylla",
    "wof:placetype":"locality"
},
  "geometry": {"coordinates":[-73.6525,-15.44195],"type":"Point"}
}