{
  "type": "Feature",
  "properties": {
    "gn:admin1_code":"12.0",
    "gn:admin2_code":"1203.0",
    "gn:admin3_code":"120305.0",
    "gn:asciiname":"Oxabamba Alto",
    "gn:country_code":"PE",
    "gn:dem":1378,
    "gn:feature_class":"P",
    "gn:feature_code":"PPL",
    "gn:name":"Oxabamba Alto",
    "gn:population":0,
    "gn:timezone":"America/Lima",
    "iso:country":"PE",
    "wof:name":"Oxabamba Alto",
    "wof:placetype":"locality"
},
  "geometry": {"coordinates":[-75.38816,-11.06395],"type":"Point"}
}