{
  "type": "Feature",
  "properties": {
    "gn:admin1_code":"21",
    "gn:admin2_code":"2104.0",
    "gn:admin3_code":"210407.0",
    "gn:asciiname":"Chullo",
    "gn:country_code":"PE",
    "gn:dem":3827,
    "gn:feature_class":"P",
    "gn:feature_code":"PPL",
    "gn:name":"Chullo",
    "gn:population":0,
    "gn:timezone":"America/Lima",
    "iso:country":"PE",
    "name:deu_x_preferred":[
        "Chullo"
    ],
    "name:eus_x_preferred":[
        "Txuilo"
    ],
    "name:fra_x_preferred":[
        "Bonnet p\u00e9ruvien"
    ],
    "name:ita_x_preferred":[
        "Chullo"
    ],
    "name:jpn_x_preferred":[
        "\u30c1\u30e5\u30fc\u30b8\u30e7"
    ],
    "name:lit_x_preferred":[
        "\u010ciulas"
    ],
    "name:nld_x_preferred":[
        "Chullo"
    ],
    "name:que_x_preferred":[
        "Ch'ullu"
    ],
    "name:spa_x_preferred":[
        "Chullo"
    ],
    "name:ukr_x_preferred":[
        "\u0427\u0443\u043b\u044c\u0439\u043e"
    ],
    "wof:name":"Chullo",
    "wof:placetype":"locality"
},
  "geometry": {"coordinates":[-69.08196,-16.50958],"type":"Point"}
}