{
  "type": "Feature",
  "properties": {
    "gn:admin1_code":"15",
    "gn:admin2_code":"1510.0",
    "gn:admin3_code":"151006.0",
    "gn:asciiname":"Huancamachay",
    "gn:country_code":"PE",
    "gn:dem":4520,
    "gn:feature_class":"P",
    "gn:feature_code":"PPL",
    "gn:name":"Huancamachay",
    "gn:population":0,
    "gn:timezone":"America/Lima",
    "iso:country":"PE",
    "wof:name":"Huancamachay",
    "wof:placetype":"locality"
},
  "geometry": {"coordinates":[-75.68993,-12.72038],"type":"Point"}
}