{
  "type": "Feature",
  "properties": {
    "gn:admin1_code":"10",
    "gn:admin2_code":"1010.0",
    "gn:admin3_code":"101005.0",
    "gn:asciiname":"Huaracayog",
    "gn:country_code":"PE",
    "gn:dem":4210,
    "gn:feature_class":"P",
    "gn:feature_code":"PPL",
    "gn:name":"Huaracayog",
    "gn:population":0,
    "gn:timezone":"America/Lima",
    "iso:country":"PE",
    "wof:name":"Huaracayog",
    "wof:placetype":"locality"
},
  "geometry": {"coordinates":[-76.77873000000002,-10.01606],"type":"Point"}
}