{
  "type": "Feature",
  "properties": {
    "gn:admin1_code":"2",
    "gn:admin2_code":"218.0",
    "gn:admin3_code":"21802.0",
    "gn:asciiname":"Cotohuain",
    "gn:country_code":"PE",
    "gn:dem":3215,
    "gn:feature_class":"P",
    "gn:feature_code":"PPL",
    "gn:name":"Cotohuain",
    "gn:population":0,
    "gn:timezone":"America/Lima",
    "iso:country":"PE",
    "wof:name":"Cotohuain",
    "wof:placetype":"locality"
},
  "geometry": {"coordinates":[-78.05249999999999,-8.89972],"type":"Point"}
}