{
  "type": "Feature",
  "properties": {
    "gn:admin1_code":"13.0",
    "gn:admin2_code":"1304.0",
    "gn:admin3_code":"130402.0",
    "gn:asciiname":"La Trocha",
    "gn:country_code":"PE",
    "gn:dem":112,
    "gn:feature_class":"P",
    "gn:feature_code":"PPL",
    "gn:name":"La Trocha",
    "gn:population":0,
    "gn:timezone":"America/Lima",
    "iso:country":"PE",
    "name:spa_x_preferred":[
        "La Trocha"
    ],
    "wof:name":"La Trocha",
    "wof:placetype":"locality"
},
  "geometry": {"coordinates":[-79.43810999999999,-7.16807],"type":"Point"}
}