{
  "type": "Feature",
  "properties": {
    "gn:admin1_code":"16.0",
    "gn:admin2_code":"1601.0",
    "gn:admin3_code":"160104.0",
    "gn:asciiname":"Varadero",
    "gn:country_code":"PE",
    "gn:dem":85,
    "gn:feature_class":"P",
    "gn:feature_code":"PPL",
    "gn:name":"Varadero",
    "gn:population":0,
    "gn:timezone":"America/Lima",
    "iso:country":"PE",
    "name:bul_x_preferred":[
        "\u0412\u0430\u0440\u0430\u0434\u0435\u0440\u043e"
    ],
    "name:ceb_x_preferred":[
        "Varadero"
    ],
    "name:ces_x_preferred":[
        "Varadero"
    ],
    "name:deu_x_preferred":[
        "Varadero"
    ],
    "name:epo_x_preferred":[
        "Varadero"
    ],
    "name:fas_x_preferred":[
        "\u0648\u0627\u0631\u0627\u062f\u0631\u0648"
    ],
    "name:fin_x_preferred":[
        "Varadero"
    ],
    "name:fra_x_preferred":[
        "Varadero"
    ],
    "name:hun_x_preferred":[
        "Varadero"
    ],
    "name:ita_x_preferred":[
        "Varadero"
    ],
    "name:jpn_x_preferred":[
        "\u30d0\u30e9\u30c7\u30fc\u30ed"
    ],
    "name:kat_x_preferred":[
        "\u10d5\u10d0\u10e0\u10d0\u10d3\u10d4\u10e0\u10dd"
    ],
    "name:kir_x_preferred":[
        "\u0412\u0430\u0440\u0430\u0434\u0435\u0440\u043e"
    ],
    "name:kor_x_preferred":[
        "\ubc14\ub77c\ub370\ub85c"
    ],
    "name:lit_x_preferred":[
        "Varaderas"
    ],
    "name:ltz_x_preferred":[
        "Varadero"
    ],
    "name:nld_x_preferred":[
        "Varadero"
    ],
    "name:nor_x_preferred":[
        "Varadero"
    ],
    "name:pol_x_preferred":[
        "Varadero"
    ],
    "name:por_x_preferred":[
        "Varadero"
    ],
    "name:rus_x_preferred":[
        "\u0412\u0430\u0440\u0430\u0434\u0435\u0440\u043e"
    ],
    "name:sco_x_preferred":[
        "Varadero"
    ],
    "name:spa_x_preferred":[
        "Varadero"
    ],
    "name:srp_x_preferred":[
        "\u0412\u0430\u0440\u0430\u0434\u0435\u0440\u043e"
    ],
    "name:swe_x_preferred":[
        "Varadero"
    ],
    "name:tur_x_preferred":[
        "Varadero"
    ],
    "name:ukr_x_preferred":[
        "\u0412\u0430\u0440\u0430\u0434\u0435\u0440\u043e"
    ],
    "name:urd_x_preferred":[
        "\u0648\u0631\u0627\u0688\u06cc\u0631\u0648"
    ],
    "name:vie_x_preferred":[
        "Varadero"
    ],
    "name:zho_x_preferred":[
        "\u5df4\u62c9\u5fb7\u7f57"
    ],
    "wof:name":"Varadero",
    "wof:placetype":"locality"
},
  "geometry": {"coordinates":[-73.09725,-3.53866],"type":"Point"}
}