{
  "type": "Feature",
  "properties": {
    "gn:admin1_code":"10",
    "gn:admin2_code":"1002.0",
    "gn:admin3_code":"100207.0",
    "gn:asciiname":"Saunaj",
    "gn:country_code":"PE",
    "gn:dem":2660,
    "gn:feature_class":"P",
    "gn:feature_code":"PPL",
    "gn:name":"Saunaj",
    "gn:population":0,
    "gn:timezone":"America/Lima",
    "iso:country":"PE",
    "wof:name":"Saunaj",
    "wof:placetype":"locality"
},
  "geometry": {"coordinates":[-76.15730000000001,-10.29419],"type":"Point"}
}