{
  "type": "Feature",
  "properties": {
    "gn:admin1_code":"02",
    "gn:admin2_code":"218.0",
    "gn:admin3_code":"21801.0",
    "gn:asciiname":"La Cramarca",
    "gn:country_code":"PE",
    "gn:dem":924,
    "gn:feature_class":"P",
    "gn:feature_code":"PPL",
    "gn:name":"La Cramarca",
    "gn:population":0,
    "gn:timezone":"America/Lima",
    "iso:country":"PE",
    "name:spa_x_preferred":[
        "La Cramarca"
    ],
    "name:und_x_variant":[
        "Lacramarca Hacienda",
        "Lacramarca"
    ],
    "wof:name":"La Cramarca",
    "wof:placetype":"locality"
},
  "geometry": {"coordinates":[-78.2647,-8.88892],"type":"Point"}
}