{
  "type": "Feature",
  "properties": {
    "gn:admin1_code":"22.0",
    "gn:admin2_code":"2207.0",
    "gn:admin3_code":"220703.0",
    "gn:asciiname":"La Florida",
    "gn:country_code":"PE",
    "gn:dem":225,
    "gn:feature_class":"P",
    "gn:feature_code":"PPL",
    "gn:name":"La Florida",
    "gn:population":0,
    "gn:timezone":"America/Lima",
    "iso:country":"PE",
    "name:spa_x_preferred":[
        "La Florida"
    ],
    "wof:name":"La Florida",
    "wof:placetype":"locality"
},
  "geometry": {"coordinates":[-76.41208,-6.94846],"type":"Point"}
}