{
  "type": "Feature",
  "properties": {
    "gn:admin1_code":"14",
    "gn:admin2_code":"1403.0",
    "gn:admin3_code":"140309.0",
    "gn:asciiname":"Trapiche Bronce",
    "gn:country_code":"PE",
    "gn:dem":41,
    "gn:feature_class":"P",
    "gn:feature_code":"PPL",
    "gn:name":"Trapiche Bronce",
    "gn:population":0,
    "gn:timezone":"America/Lima",
    "iso:country":"PE",
    "wof:name":"Trapiche Bronce",
    "wof:placetype":"locality"
},
  "geometry": {"coordinates":[-79.92263,-6.45413],"type":"Point"}
}