{
  "type": "Feature",
  "properties": {
    "gn:admin1_code":"21.0",
    "gn:admin2_code":"2110.0",
    "gn:asciiname":"Abra Huchuy",
    "gn:country_code":"PE",
    "gn:dem":3766,
    "gn:feature_class":"P",
    "gn:feature_code":"PPL",
    "gn:name":"Abra Huchuy",
    "gn:population":0,
    "gn:timezone":"America/Lima",
    "iso:country":"PE",
    "name:spa_x_preferred":[
        "Abra Huchuy"
    ],
    "wof:name":"Abra Huchuy",
    "wof:placetype":"locality"
},
  "geometry": {"coordinates":[-69.22289000000001,-14.48614],"type":"Point"}
}