{
  "type": "Feature",
  "properties": {
    "gn:admin1_code":"08",
    "gn:admin2_code":"803.0",
    "gn:admin3_code":"80307.0",
    "gn:asciiname":"Marcahuasi",
    "gn:cc2":"PE",
    "gn:country_code":"PE",
    "gn:dem":2205,
    "gn:feature_class":"P",
    "gn:feature_code":"PPL",
    "gn:name":"Marcahuasi",
    "gn:population":0,
    "gn:timezone":"America/Lima",
    "iso:country":"PE",
    "name:bul_x_preferred":[
        "\u041c\u0430\u0440\u043a\u0430\u0443\u0430\u0441\u0438"
    ],
    "name:ita_x_preferred":[
        "Marcahuasi"
    ],
    "name:mkd_x_preferred":[
        "\u041c\u0430\u0440\u043a\u0430\u0432\u0430\u0441\u0438"
    ],
    "name:ron_x_preferred":[
        "Marcahuasi"
    ],
    "name:spa_x_preferred":[
        "Marcahuasi"
    ],
    "name:und_x_variant":[
        "Marcahuasi Hacienda"
    ],
    "wof:name":"Marcahuasi",
    "wof:placetype":"locality"
},
  "geometry": {"coordinates":[-72.55,-13.55],"type":"Point"}
}