{
  "type": "Feature",
  "properties": {
    "gn:admin1_code":"15.0",
    "gn:admin2_code":"1507.0",
    "gn:admin3_code":"150723.0",
    "gn:asciiname":"Purhuay",
    "gn:country_code":"PE",
    "gn:dem":1520,
    "gn:feature_class":"P",
    "gn:feature_code":"PPL",
    "gn:name":"Purhuay",
    "gn:population":0,
    "gn:timezone":"America/Lima",
    "iso:country":"PE",
    "name:spa_x_preferred":[
        "Purhuay"
    ],
    "wof:name":"Purhuay",
    "wof:placetype":"locality"
},
  "geometry": {"coordinates":[-76.59052,-11.9018],"type":"Point"}
}