{
  "type": "Feature",
  "properties": {
    "gn:admin1_code":"23",
    "gn:admin2_code":"2301.0",
    "gn:admin3_code":"230107.0",
    "gn:asciiname":"Charicahua",
    "gn:country_code":"PE",
    "gn:dem":3736,
    "gn:feature_class":"P",
    "gn:feature_code":"PPL",
    "gn:name":"Charicahua",
    "gn:population":0,
    "gn:timezone":"America/Lima",
    "iso:country":"PE",
    "wof:name":"Charicahua",
    "wof:placetype":"locality"
},
  "geometry": {"coordinates":[-69.89889000000001,-17.68972],"type":"Point"}
}