{
  "type": "Feature",
  "properties": {
    "gn:admin1_code":"9.0",
    "gn:admin2_code":"903.0",
    "gn:asciiname":"Socorro",
    "gn:country_code":"PE",
    "gn:dem":3470,
    "gn:feature_class":"P",
    "gn:feature_code":"PPL",
    "gn:name":"Socorro",
    "gn:population":0,
    "gn:timezone":"America/Lima",
    "iso:country":"PE",
    "wof:name":"Socorro",
    "wof:placetype":"locality"
},
  "geometry": {"coordinates":[-74.41915,-13.00858],"type":"Point"}
}