{
  "type": "Feature",
  "properties": {
    "gn:admin1_code":"22.0",
    "gn:admin2_code":"2205.0",
    "gn:admin3_code":"220511.0",
    "gn:asciiname":"Shapaja",
    "gn:country_code":"PE",
    "gn:dem":548,
    "gn:feature_class":"P",
    "gn:feature_code":"PPL",
    "gn:name":"Shapaja",
    "gn:population":0,
    "gn:timezone":"America/Lima",
    "iso:country":"PE",
    "name:spa_x_preferred":[
        "Shapaja"
    ],
    "wof:name":"Shapaja",
    "wof:placetype":"locality"
},
  "geometry": {"coordinates":[-76.52945,-6.5189],"type":"Point"}
}