{
  "type": "Feature",
  "properties": {
    "gn:admin1_code":"12.0",
    "gn:admin2_code":"1206.0",
    "gn:admin3_code":"120608.0",
    "gn:asciiname":"Boca Nenquichani",
    "gn:country_code":"PE",
    "gn:dem":317,
    "gn:feature_class":"P",
    "gn:feature_code":"PPL",
    "gn:name":"Boca Nenquichani",
    "gn:population":0,
    "gn:timezone":"America/Lima",
    "iso:country":"PE",
    "wof:name":"Boca Nenquichani",
    "wof:placetype":"locality"
},
  "geometry": {"coordinates":[-74.23223,-11.19391],"type":"Point"}
}