{
  "type": "Feature",
  "properties": {
    "gn:admin1_code":"15.0",
    "gn:admin2_code":"1508.0",
    "gn:admin3_code":"150811.0",
    "gn:asciiname":"La Campania",
    "gn:country_code":"PE",
    "gn:dem":477,
    "gn:feature_class":"P",
    "gn:feature_code":"PPL",
    "gn:name":"La Campania",
    "gn:population":0,
    "gn:timezone":"America/Lima",
    "iso:country":"PE",
    "wof:name":"La Campania",
    "wof:placetype":"locality"
},
  "geometry": {"coordinates":[-77.32528000000001,-11.22306],"type":"Point"}
}