{
  "type": "Feature",
  "properties": {
    "gn:admin1_code":"2.0",
    "gn:admin2_code":"206.0",
    "gn:admin3_code":"20608.0",
    "gn:asciiname":"Maruacatac",
    "gn:country_code":"PE",
    "gn:dem":3293,
    "gn:feature_class":"P",
    "gn:feature_code":"PPL",
    "gn:name":"Maruacatac",
    "gn:population":0,
    "gn:timezone":"America/Lima",
    "iso:country":"PE",
    "wof:name":"Maruacatac",
    "wof:placetype":"locality"
},
  "geometry": {"coordinates":[-77.54222,-9.37139],"type":"Point"}
}