{
  "type": "Feature",
  "properties": {
    "gn:admin1_code":"3.0",
    "gn:admin2_code":"305.0",
    "gn:admin3_code":"30503.0",
    "gn:asciiname":"Lladquiri",
    "gn:country_code":"PE",
    "gn:dem":3416,
    "gn:feature_class":"P",
    "gn:feature_code":"PPL",
    "gn:name":"Lladquiri",
    "gn:population":0,
    "gn:timezone":"America/Lima",
    "iso:country":"PE",
    "wof:name":"Lladquiri",
    "wof:placetype":"locality"
},
  "geometry": {"coordinates":[-72.39889000000002,-13.86361],"type":"Point"}
}