{
  "type": "Feature",
  "properties": {
    "gn:admin1_code":"08",
    "gn:admin2_code":"803.0",
    "gn:admin3_code":"80306.0",
    "gn:asciiname":"Sondor",
    "gn:cc2":"PE",
    "gn:country_code":"PE",
    "gn:dem":2537,
    "gn:feature_class":"P",
    "gn:feature_code":"PPL",
    "gn:name":"S\u00f3ndor",
    "gn:population":0,
    "gn:timezone":"America/Lima",
    "iso:country":"PE",
    "name:und_x_variant":[
        "Sondor Hacienda",
        "S\u00f3ndor"
    ],
    "wof:name":"Sondor",
    "wof:placetype":"locality"
},
  "geometry": {"coordinates":[-72.45,-13.48333],"type":"Point"}
}