{
  "type": "Feature",
  "properties": {
    "gn:admin1_code":"2.0",
    "gn:admin2_code":"219.0",
    "gn:admin3_code":"21907.0",
    "gn:asciiname":"Tinyayo",
    "gn:country_code":"PE",
    "gn:dem":3126,
    "gn:feature_class":"P",
    "gn:feature_code":"PPL",
    "gn:name":"Tinyayo",
    "gn:population":0,
    "gn:timezone":"America/Lima",
    "iso:country":"PE",
    "wof:name":"Tinyayo",
    "wof:placetype":"locality"
},
  "geometry": {"coordinates":[-77.49278000000002,-8.40028],"type":"Point"}
}