{
  "type": "Feature",
  "properties": {
    "gn:admin1_code":"11.0",
    "gn:admin2_code":"1103.0",
    "gn:admin3_code":"110301.0",
    "gn:asciiname":"Huancavelica",
    "gn:country_code":"PE",
    "gn:dem":817,
    "gn:feature_class":"P",
    "gn:feature_code":"PPL",
    "gn:name":"Huancavelica",
    "gn:population":0,
    "gn:timezone":"America/Lima",
    "iso:country":"PE",
    "name:spa_x_preferred":[
        "Huancavelica"
    ],
    "wof:name":"Huancavelica",
    "wof:placetype":"locality"
},
  "geometry": {"coordinates":[-74.87591,-14.79365],"type":"Point"}
}