{
  "type": "Feature",
  "properties": {
    "gn:admin1_code":"11.0",
    "gn:admin2_code":"1103.0",
    "gn:admin3_code":"110301.0",
    "gn:asciiname":"Huancavelica",
    "gn:country_code":"PE",
    "gn:dem":817,
    "gn:feature_class":"P",
    "gn:feature_code":"PPL",
    "gn:name":"Huancavelica",
    "gn:population":0,
    "gn:timezone":"America/Lima",
    "iso:country":"PE",
    "name:ara_x_preferred":[
        "\u0647\u0648\u0627\u0646\u0643\u0627\u0641\u0644\u064a\u0643\u0627"
    ],
    "name:aym_x_preferred":[
        "Wankawillka"
    ],
    "name:cat_x_preferred":[
        "Huancavelica"
    ],
    "name:ceb_x_preferred":[
        "Huancavelica"
    ],
    "name:deu_x_preferred":[
        "Huancavelica"
    ],
    "name:fas_x_preferred":[
        "\u0627\u0648\u0627\u0646\u06a9\u0627\u0648\u0644\u06cc\u06a9\u0627"
    ],
    "name:fin_x_preferred":[
        "Huancavelica"
    ],
    "name:fra_x_preferred":[
        "Huancavelica"
    ],
    "name:ita_x_preferred":[
        "Huancavelica"
    ],
    "name:kat_x_preferred":[
        "\u10e3\u10d0\u10dc\u10d9\u10d0\u10d5\u10d4\u10da\u10d8\u10d9\u10d0"
    ],
    "name:kor_x_preferred":[
        "\uc6b0\uc559\uce74\ubca8\ub9ac\uce74"
    ],
    "name:lit_x_preferred":[
        "Huankavelika"
    ],
    "name:nld_x_preferred":[
        "Huancavelica"
    ],
    "name:nor_x_preferred":[
        "Huancavelica"
    ],
    "name:pol_x_preferred":[
        "Huancavelica"
    ],
    "name:por_x_preferred":[
        "Huancavelica"
    ],
    "name:que_x_preferred":[
        "Wankawillka"
    ],
    "name:rus_x_preferred":[
        "\u0423\u0430\u043d\u043a\u0430\u0432\u0435\u043b\u0438\u043a\u0430"
    ],
    "name:spa_x_preferred":[
        "Huancavelica"
    ],
    "name:swe_x_preferred":[
        "Huancavelica"
    ],
    "name:ukr_x_preferred":[
        "\u0423\u0430\u043d\u043a\u0430\u0432\u0435\u043b\u0456\u043a\u0430"
    ],
    "name:urd_x_preferred":[
        "\u0648\u0627\u0646\u06a9\u0627\u0628\u06cc\u0644\u06cc\u06a9\u0627"
    ],
    "name:war_x_preferred":[
        "Huancavelica"
    ],
    "name:zho_x_preferred":[
        "\u842c\u5361\u97cb\u5229\u5361"
    ],
    "wof:name":"Huancavelica",
    "wof:placetype":"locality"
},
  "geometry": {"coordinates":[-74.87591,-14.79365],"type":"Point"}
}