{
  "type": "Feature",
  "properties": {
    "gn:admin1_code":"18",
    "gn:admin2_code":"1802.0",
    "gn:admin3_code":"180208.0",
    "gn:asciiname":"Talamolle",
    "gn:country_code":"PE",
    "gn:dem":3596,
    "gn:feature_class":"P",
    "gn:feature_code":"PPL",
    "gn:name":"Talamolle",
    "gn:population":0,
    "gn:timezone":"America/Lima",
    "iso:country":"PE",
    "wof:name":"Talamolle",
    "wof:placetype":"locality"
},
  "geometry": {"coordinates":[-71.23380999999998,-16.56591],"type":"Point"}
}