{
  "type": "Feature",
  "properties": {
    "gn:admin1_code":"20",
    "gn:admin2_code":"2003.0",
    "gn:admin3_code":"200304.0",
    "gn:asciiname":"Tayaca",
    "gn:country_code":"PE",
    "gn:dem":2764,
    "gn:feature_class":"P",
    "gn:feature_code":"PPL",
    "gn:name":"Tayaca",
    "gn:population":0,
    "gn:timezone":"America/Lima",
    "iso:country":"PE",
    "wof:name":"Tayaca",
    "wof:placetype":"locality"
},
  "geometry": {"coordinates":[-79.44417,-5.849],"type":"Point"}
}