{
  "type": "Feature",
  "properties": {
    "gn:admin1_code":"23",
    "gn:admin2_code":"2304.0",
    "gn:admin3_code":"230405.0",
    "gn:asciiname":"Chaspaya",
    "gn:country_code":"PE",
    "gn:dem":2561,
    "gn:feature_class":"P",
    "gn:feature_code":"PPL",
    "gn:name":"Chaspaya",
    "gn:population":0,
    "gn:timezone":"America/Lima",
    "iso:country":"PE",
    "wof:name":"Chaspaya",
    "wof:placetype":"locality"
},
  "geometry": {"coordinates":[-70.15369,-17.42245],"type":"Point"}
}