{
  "type": "Feature",
  "properties": {
    "gn:admin1_code":"8",
    "gn:admin2_code":"806.0",
    "gn:admin3_code":"80605.0",
    "gn:asciiname":"Huatabamba",
    "gn:country_code":"PE",
    "gn:dem":4233,
    "gn:feature_class":"P",
    "gn:feature_code":"PPL",
    "gn:name":"Huatabamba",
    "gn:population":0,
    "gn:timezone":"America/Lima",
    "iso:country":"PE",
    "wof:name":"Huatabamba",
    "wof:placetype":"locality"
},
  "geometry": {"coordinates":[-71.38977,-14.0039],"type":"Point"}
}