{
  "type": "Feature",
  "properties": {
    "gn:admin1_code":"9",
    "gn:admin2_code":"903.0",
    "gn:admin3_code":"90301.0",
    "gn:asciiname":"Bombomyac",
    "gn:country_code":"PE",
    "gn:dem":3966,
    "gn:feature_class":"P",
    "gn:feature_code":"PPL",
    "gn:name":"Bombomyac",
    "gn:population":0,
    "gn:timezone":"America/Lima",
    "iso:country":"PE",
    "wof:name":"Bombomyac",
    "wof:placetype":"locality"
},
  "geometry": {"coordinates":[-74.67811,-13.05146],"type":"Point"}
}