{
  "type": "Feature",
  "properties": {
    "gn:admin1_code":"5",
    "gn:admin2_code":"506.0",
    "gn:admin3_code":"50619.0",
    "gn:asciiname":"Alpayoc",
    "gn:country_code":"PE",
    "gn:dem":2665,
    "gn:feature_class":"P",
    "gn:feature_code":"PPL",
    "gn:name":"Alpayoc",
    "gn:population":0,
    "gn:timezone":"America/Lima",
    "iso:country":"PE",
    "wof:name":"Alpayoc",
    "wof:placetype":"locality"
},
  "geometry": {"coordinates":[-74.22880000000001,-15.11092],"type":"Point"}
}