{
  "type": "Feature",
  "properties": {
    "gn:admin1_code":"21",
    "gn:admin2_code":"2105.0",
    "gn:admin3_code":"210504.0",
    "gn:asciiname":"Surada",
    "gn:country_code":"PE",
    "gn:dem":4630,
    "gn:feature_class":"P",
    "gn:feature_code":"PPL",
    "gn:name":"Surada",
    "gn:population":0,
    "gn:timezone":"America/Lima",
    "iso:country":"PE",
    "name:ben_x_preferred":[
        "\u09b8\u09c1\u09b0\u09a1\u09be"
    ],
    "name:bpy_x_preferred":[
        "\u09b8\u09c1\u09b0\u09a6\u09be"
    ],
    "name:cat_x_preferred":[
        "Surada"
    ],
    "name:ceb_x_preferred":[
        "Sorada"
    ],
    "name:ita_x_preferred":[
        "Surada"
    ],
    "name:msa_x_preferred":[
        "Surada"
    ],
    "name:nld_x_preferred":[
        "Surada"
    ],
    "name:ori_x_preferred":[
        "\u0b38\u0b4b\u0b30\u0b21\u0b3c\u0b3e"
    ],
    "name:por_x_preferred":[
        "Surada"
    ],
    "name:swe_x_preferred":[
        "Sorada"
    ],
    "name:vie_x_preferred":[
        "Surada"
    ],
    "name:zho_x_preferred":[
        "\u82cf\u62c9\u8fbe"
    ],
    "wof:name":"Surada",
    "wof:placetype":"locality"
},
  "geometry": {"coordinates":[-69.92165,-17.12677],"type":"Point"}
}