{
  "type": "Feature",
  "properties": {
    "gn:admin1_code":"10.0",
    "gn:admin2_code":"1003.0",
    "gn:admin3_code":"100311.0",
    "gn:asciiname":"Mojon Punta",
    "gn:country_code":"PE",
    "gn:dem":4181,
    "gn:feature_class":"P",
    "gn:feature_code":"PPL",
    "gn:name":"Moj\u00f3n Punta",
    "gn:population":0,
    "gn:timezone":"America/Lima",
    "iso:country":"PE",
    "wof:name":"Mojon Punta",
    "wof:placetype":"locality"
},
  "geometry": {"coordinates":[-76.54651,-9.56709],"type":"Point"}
}