{
  "type": "Feature",
  "properties": {
    "gn:admin1_code":"5",
    "gn:admin2_code":"502.0",
    "gn:admin3_code":"50205.0",
    "gn:asciiname":"Vista Alegre",
    "gn:country_code":"PE",
    "gn:dem":3669,
    "gn:feature_class":"P",
    "gn:feature_code":"PPL",
    "gn:name":"Vista Alegre",
    "gn:population":0,
    "gn:timezone":"America/Lima",
    "iso:country":"PE",
    "wof:name":"Vista Alegre",
    "wof:placetype":"locality"
},
  "geometry": {"coordinates":[-74.62889,-13.54611],"type":"Point"}
}