{
  "type": "Feature",
  "properties": {
    "gn:admin1_code":"04",
    "gn:admin2_code":"404.0",
    "gn:admin3_code":"40413.0",
    "gn:asciiname":"Mesana",
    "gn:country_code":"PE",
    "gn:dem":420,
    "gn:feature_class":"P",
    "gn:feature_code":"PPL",
    "gn:name":"Mesana",
    "gn:population":0,
    "gn:timezone":"America/Lima",
    "iso:country":"PE",
    "name:bul_x_preferred":[
        "\u041c\u0435\u0441\u0430\u043d\u0430"
    ],
    "name:ell_x_preferred":[
        "\u039c\u03ad\u03c3\u03b1\u03bd\u03b1"
    ],
    "name:hye_x_preferred":[
        "\u0544\u0565\u057d\u0561\u0576\u0561"
    ],
    "name:pol_x_preferred":[
        "Mesana"
    ],
    "name:urd_x_preferred":[
        "\u0645\u06cc\u0633\u0627\u0646\u0627"
    ],
    "wof:name":"Mesana",
    "wof:placetype":"locality"
},
  "geometry": {"coordinates":[-72.45009,-16.26521],"type":"Point"}
}