{
  "type": "Feature",
  "properties": {
    "gn:admin1_code":"06",
    "gn:admin2_code":"611.0",
    "gn:admin3_code":"61113.0",
    "gn:asciiname":"Platanal",
    "gn:country_code":"PE",
    "gn:dem":845,
    "gn:feature_class":"P",
    "gn:feature_code":"PPL",
    "gn:name":"Platanal",
    "gn:population":0,
    "gn:timezone":"America/Lima",
    "iso:country":"PE",
    "name:und_x_variant":[
        "Plantanal",
        "Platanal"
    ],
    "wof:name":"Platanal",
    "wof:placetype":"locality"
},
  "geometry": {"coordinates":[-79.02542,-7.13315],"type":"Point"}
}