{
  "type": "Feature",
  "properties": {
    "gn:admin1_code":"04",
    "gn:admin2_code":"408.0",
    "gn:admin3_code":"40806.0",
    "gn:asciiname":"Chulca",
    "gn:country_code":"PE",
    "gn:dem":3833,
    "gn:feature_class":"P",
    "gn:feature_code":"PPL",
    "gn:name":"Chulca",
    "gn:population":0,
    "gn:timezone":"America/Lima",
    "iso:country":"PE",
    "wof:name":"Chulca",
    "wof:placetype":"locality"
},
  "geometry": {"coordinates":[-72.71666999999999,-14.95],"type":"Point"}
}