{
  "type": "Feature",
  "properties": {
    "gn:admin1_code":"15",
    "gn:admin2_code":"1510.0",
    "gn:admin3_code":"151018.0",
    "gn:asciiname":"Jatun Huasi",
    "gn:country_code":"PE",
    "gn:dem":4421,
    "gn:feature_class":"P",
    "gn:feature_code":"PPL",
    "gn:name":"Jatun Huasi",
    "gn:population":0,
    "gn:timezone":"America/Lima",
    "iso:country":"PE",
    "name:und_x_variant":[
        "Jarun Huasi",
        "Jatun Huasi"
    ],
    "wof:name":"Jatun Huasi",
    "wof:placetype":"locality"
},
  "geometry": {"coordinates":[-75.74478000000001,-12.41392],"type":"Point"}
}