{
  "type": "Feature",
  "properties": {
    "gn:admin1_code":"20",
    "gn:admin2_code":"2001.0",
    "gn:admin3_code":"200101.0",
    "gn:asciiname":"El Chipe",
    "gn:cc2":"PE",
    "gn:country_code":"PE",
    "gn:dem":39,
    "gn:feature_class":"P",
    "gn:feature_code":"PPL",
    "gn:name":"El Chipe",
    "gn:population":0,
    "gn:timezone":"America/Lima",
    "iso:country":"PE",
    "name:und_x_variant":[
        "El Chipe Hacienda",
        "El Chipe"
    ],
    "wof:name":"El Chipe",
    "wof:placetype":"locality"
},
  "geometry": {"coordinates":[-80.63333,-5.16667],"type":"Point"}
}