{
  "type": "Feature",
  "properties": {
    "gn:admin1_code":"04",
    "gn:admin2_code":"405.0",
    "gn:admin3_code":"40508.0",
    "gn:asciiname":"Huanca",
    "gn:country_code":"PE",
    "gn:dem":4384,
    "gn:feature_class":"P",
    "gn:feature_code":"PPL",
    "gn:name":"Huanca",
    "gn:population":0,
    "gn:timezone":"America/Lima",
    "iso:country":"PE",
    "wof:name":"Huanca",
    "wof:placetype":"locality"
},
  "geometry": {"coordinates":[-71.78959999999999,-15.88921],"type":"Point"}
}