{
  "type": "Feature",
  "properties": {
    "gn:admin1_code":"04",
    "gn:admin2_code":"401.0",
    "gn:admin3_code":"40119.0",
    "gn:asciiname":"Huaillacucho",
    "gn:country_code":"PE",
    "gn:dem":4340,
    "gn:feature_class":"P",
    "gn:feature_code":"PPL",
    "gn:name":"Huaillacucho",
    "gn:population":0,
    "gn:timezone":"America/Lima",
    "iso:country":"PE",
    "name:und_x_variant":[
        "Huallacucho",
        "Huaillacucho"
    ],
    "wof:name":"Huaillacucho",
    "wof:placetype":"locality"
},
  "geometry": {"coordinates":[-71.23962,-16.04204],"type":"Point"}
}