{
  "type": "Feature",
  "properties": {
    "gn:admin1_code":"09",
    "gn:admin2_code":"901.0",
    "gn:admin3_code":"90106.0",
    "gn:asciiname":"Hacienda Chunumayo",
    "gn:country_code":"PE",
    "gn:dem":4170,
    "gn:feature_class":"P",
    "gn:feature_code":"PPL",
    "gn:name":"Hacienda Chu\u00f1umayo",
    "gn:population":0,
    "gn:timezone":"America/Lima",
    "iso:country":"PE",
    "wof:name":"Hacienda Chunumayo",
    "wof:placetype":"locality"
},
  "geometry": {"coordinates":[-74.91667,-12.96667],"type":"Point"}
}