{
  "type": "Feature",
  "properties": {
    "gn:admin1_code":"15.0",
    "gn:admin2_code":"1504.0",
    "gn:admin3_code":"150405.0",
    "gn:asciiname":"Huayoco",
    "gn:country_code":"PE",
    "gn:dem":3560,
    "gn:feature_class":"P",
    "gn:feature_code":"PPL",
    "gn:name":"Huayoco",
    "gn:population":0,
    "gn:timezone":"America/Lima",
    "iso:country":"PE",
    "wof:name":"Huayoco",
    "wof:placetype":"locality"
},
  "geometry": {"coordinates":[-76.64062,-11.53709],"type":"Point"}
}