{
  "type": "Feature",
  "properties": {
    "gn:admin1_code":"15",
    "gn:admin2_code":"1505.0",
    "gn:admin3_code":"150503.0",
    "gn:asciiname":"Limon",
    "gn:country_code":"PE",
    "gn:dem":161,
    "gn:feature_class":"P",
    "gn:feature_code":"PPL",
    "gn:name":"Lim\u00f3n",
    "gn:population":0,
    "gn:timezone":"America/Lima",
    "iso:country":"PE",
    "wof:name":"Limon",
    "wof:placetype":"locality"
},
  "geometry": {"coordinates":[-76.60298,-12.56082],"type":"Point"}
}