{
  "type": "Feature",
  "properties": {
    "gn:admin1_code":"21",
    "gn:admin2_code":"2103",
    "gn:asciiname":"Patarani",
    "gn:country_code":"PE",
    "gn:dem":3454,
    "gn:feature_class":"P",
    "gn:feature_code":"PPL",
    "gn:name":"Patarani",
    "gn:population":0,
    "gn:timezone":"America/Lima",
    "iso:country":"PE",
    "name:spa_x_preferred":[
        "Patarani"
    ],
    "wof:name":"Patarani",
    "wof:placetype":"locality"
},
  "geometry": {"coordinates":[-69.9293,-13.84087],"type":"Point"}
}