{
  "type": "Feature",
  "properties": {
    "gn:admin1_code":"11",
    "gn:admin2_code":"1102.0",
    "gn:admin3_code":"110208.0",
    "gn:asciiname":"Sano",
    "gn:country_code":"PE",
    "gn:dem":2590,
    "gn:feature_class":"P",
    "gn:feature_code":"PPL",
    "gn:name":"Sa\u00f1o",
    "gn:population":0,
    "gn:timezone":"America/Lima",
    "iso:country":"PE",
    "name:ceb_x_preferred":[
        "Sano"
    ],
    "name:deu_x_preferred":[
        "Sano"
    ],
    "name:fra_x_preferred":[
        "Sano"
    ],
    "name:mlg_x_preferred":[
        "Sano"
    ],
    "name:rus_x_preferred":[
        "\u0421\u0430\u043d\u043e"
    ],
    "name:spa_x_preferred":[
        "Sa\u00f1o"
    ],
    "name:swe_x_preferred":[
        "Sano"
    ],
    "name:ukr_x_preferred":[
        "\u0421\u0430\u043d\u043e"
    ],
    "name:uzb_x_preferred":[
        "Sano"
    ],
    "wof:name":"Sano",
    "wof:placetype":"locality"
},
  "geometry": {"coordinates":[-75.90144000000002,-13.17966],"type":"Point"}
}