{
  "type": "Feature",
  "properties": {
    "gn:admin1_code":"15",
    "gn:admin2_code":"1509.0",
    "gn:admin3_code":"150901.0",
    "gn:asciiname":"Rirco",
    "gn:country_code":"PE",
    "gn:dem":4654,
    "gn:feature_class":"P",
    "gn:feature_code":"PPL",
    "gn:name":"Rirco",
    "gn:population":0,
    "gn:timezone":"America/Lima",
    "iso:country":"PE",
    "wof:name":"Rirco",
    "wof:placetype":"locality"
},
  "geometry": {"coordinates":[-76.81361,-10.62639],"type":"Point"}
}