{
  "type": "Feature",
  "properties": {
    "gn:admin1_code":"02",
    "gn:admin2_code":"214.0",
    "gn:admin3_code":"21409.0",
    "gn:asciiname":"Julquillas",
    "gn:country_code":"PE",
    "gn:dem":230,
    "gn:feature_class":"P",
    "gn:feature_code":"PPL",
    "gn:name":"Julquillas",
    "gn:population":0,
    "gn:timezone":"America/Lima",
    "iso:country":"PE",
    "wof:name":"Julquillas",
    "wof:placetype":"locality"
},
  "geometry": {"coordinates":[-77.72731999999998,-10.53414],"type":"Point"}
}