{
  "type": "Feature",
  "properties": {
    "iso:country":"PE",
    "name:bre_x_preferred":[
        "Agua Caliente"
    ],
    "name:deu_x_preferred":[
        "Agua Caliente"
    ],
    "name:hbs_x_preferred":[
        "Agua Caliente"
    ],
    "name:unk_x_variant":[
        "Aguas Caliente"
    ],
    "qs:gn_country":"PE",
    "qs:gn_fcode":"PPL",
    "qs:gn_pop":0,
    "qs:name":"Aguas Calientes",
    "qs:name_adm0":"Per\u00fa",
    "qs:name_adm1":"Hu\u00e1nuco",
    "qs:photos":3344,
    "qs:photos_1k":678,
    "qs:photos_9k":15,
    "qs:photos_9r":11,
    "qs:photos_all":3344,
    "qs:photos_sr":20,
    "qs:placetype":"Town",
    "qs:pop_sr":"0",
    "qs:woe_adm0":23424919,
    "wd:wordcount":218,
    "wof:name":"Aguas Calientes",
    "wof:placetype":"locality"
},
  "geometry": {"coordinates":[-74.68333,-8.83333],"type":"Point"}
}