{
  "type": "Feature",
  "properties": {
    "gn:admin1_code":"25",
    "gn:admin2_code":"2501.0",
    "gn:admin3_code":"250101.0",
    "gn:asciiname":"Veintiocho de Julio",
    "gn:country_code":"PE",
    "gn:dem":177,
    "gn:feature_class":"P",
    "gn:feature_code":"PPL",
    "gn:name":"Veintiocho de Julio",
    "gn:population":0,
    "gn:timezone":"America/Lima",
    "iso:country":"PE",
    "wof:name":"Veintiocho de Julio",
    "wof:placetype":"locality"
},
  "geometry": {"coordinates":[-73.86223000000003,-8.40842],"type":"Point"}
}