{
  "type": "Feature",
  "properties": {
    "gn:admin1_code":"9.0",
    "gn:admin2_code":"902.0",
    "gn:asciiname":"Huaman Era",
    "gn:country_code":"PE",
    "gn:dem":3568,
    "gn:feature_class":"P",
    "gn:feature_code":"PPL",
    "gn:name":"Huaman Era",
    "gn:population":0,
    "gn:timezone":"America/Lima",
    "iso:country":"PE",
    "wof:name":"Huaman Era",
    "wof:placetype":"locality"
},
  "geometry": {"coordinates":[-74.44526999999999,-12.93263],"type":"Point"}
}