{
  "type": "Feature",
  "properties": {
    "gn:admin1_code":"1.0",
    "gn:admin2_code":"105.0",
    "gn:admin3_code":"10519.0",
    "gn:asciiname":"Llactapampa",
    "gn:country_code":"PE",
    "gn:dem":2792,
    "gn:feature_class":"P",
    "gn:feature_code":"PPL",
    "gn:name":"Llactapampa",
    "gn:population":0,
    "gn:timezone":"America/Lima",
    "iso:country":"PE",
    "wof:name":"Llactapampa",
    "wof:placetype":"locality"
},
  "geometry": {"coordinates":[-77.92028000000001,-6.48111],"type":"Point"}
}