{
  "type": "Feature",
  "properties": {
    "gn:admin1_code":"06",
    "gn:admin2_code":"601.0",
    "gn:admin3_code":"60106.0",
    "gn:asciiname":"Lucmapampa",
    "gn:country_code":"PE",
    "gn:dem":3448,
    "gn:feature_class":"P",
    "gn:feature_code":"PPL",
    "gn:name":"Lucmapampa",
    "gn:population":0,
    "gn:timezone":"America/Lima",
    "iso:country":"PE",
    "wof:name":"Lucmapampa",
    "wof:placetype":"locality"
},
  "geometry": {"coordinates":[-78.32753000000002,-7.33085],"type":"Point"}
}