{
  "type": "Feature",
  "properties": {
    "gn:admin1_code":"1",
    "gn:admin2_code":"105.0",
    "gn:admin3_code":"10502.0",
    "gn:asciiname":"Santa Rosa",
    "gn:country_code":"PE",
    "gn:dem":1731,
    "gn:feature_class":"P",
    "gn:feature_code":"PPL",
    "gn:name":"Santa Rosa",
    "gn:population":0,
    "gn:timezone":"America/Lima",
    "iso:country":"PE",
    "name:cat_x_preferred":[
        "Santa Rosa"
    ],
    "name:ceb_x_preferred":[
        "Santa Rosa"
    ],
    "name:ces_x_preferred":[
        "Santa Rosa"
    ],
    "name:deu_x_preferred":[
        "Santa Rosa"
    ],
    "name:epo_x_preferred":[
        "Santa Rosa"
    ],
    "name:fin_x_preferred":[
        "Santa Rosa"
    ],
    "name:fra_x_preferred":[
        "Santa Rosa"
    ],
    "name:glg_x_preferred":[
        "Santa Rosa"
    ],
    "name:heb_x_preferred":[
        "\u05e1\u05e0\u05d8\u05d4 \u05e8\u05d5\u05e1\u05d4"
    ],
    "name:hun_x_preferred":[
        "Santa Rosa"
    ],
    "name:ilo_x_preferred":[
        "Santa Rosa"
    ],
    "name:ind_x_preferred":[
        "Santa Rosa"
    ],
    "name:ita_x_preferred":[
        "Santa Rosa"
    ],
    "name:jpn_x_preferred":[
        "\u30b5\u30f3\u30bf\u30ed\u30fc\u30b6"
    ],
    "name:kor_x_preferred":[
        "\uc0b0\ud0c0\ub85c\uc0ac"
    ],
    "name:lit_x_preferred":[
        "Santa Rosa"
    ],
    "name:mlg_x_preferred":[
        "Santa Rosa"
    ],
    "name:nds_x_preferred":[
        "Santa Rosa"
    ],
    "name:nld_x_preferred":[
        "Santa Rosa"
    ],
    "name:nor_x_preferred":[
        "Santa Rosa"
    ],
    "name:pol_x_preferred":[
        "Santa Rosa"
    ],
    "name:por_x_preferred":[
        "Santa Rosa"
    ],
    "name:rus_x_preferred":[
        "\u0421\u0430\u043d\u0442\u0430-\u0420\u043e\u0437\u0430"
    ],
    "name:sco_x_preferred":[
        "Santa Rosa"
    ],
    "name:slk_x_preferred":[
        "Santa Rosa"
    ],
    "name:spa_x_preferred":[
        "Santa Rosa"
    ],
    "name:srp_x_preferred":[
        "\u0421\u0430\u043d\u0442\u0430 \u0420\u043e\u0441\u0430"
    ],
    "name:swa_x_preferred":[
        "Santa Rosa"
    ],
    "name:swe_x_preferred":[
        "Santa Rosa"
    ],
    "name:vol_x_preferred":[
        "Santa Rosa"
    ],
    "name:war_x_preferred":[
        "Santa Rosa"
    ],
    "wof:name":"Santa Rosa",
    "wof:placetype":"locality"
},
  "geometry": {"coordinates":[-78.33485,-6.15743],"type":"Point"}
}