{
  "type": "Feature",
  "properties": {
    "gn:admin1_code":"08",
    "gn:admin2_code":"804.0",
    "gn:admin3_code":"80404.0",
    "gn:asciiname":"Manto",
    "gn:country_code":"PE",
    "gn:dem":4423,
    "gn:feature_class":"P",
    "gn:feature_code":"PPL",
    "gn:name":"Manto",
    "gn:population":0,
    "gn:timezone":"America/Lima",
    "iso:country":"PE",
    "name:cat_x_preferred":[
        "Manto"
    ],
    "name:ceb_x_preferred":[
        "Manto"
    ],
    "name:deu_x_preferred":[
        "Manto"
    ],
    "name:epo_x_preferred":[
        "Manto"
    ],
    "name:fra_x_preferred":[
        "Manto"
    ],
    "name:glg_x_preferred":[
        "Manto"
    ],
    "name:jpn_x_preferred":[
        "\u30de\u30f3\u30c8"
    ],
    "name:nds_x_preferred":[
        "Manto"
    ],
    "name:nld_x_preferred":[
        "Manto"
    ],
    "name:por_x_preferred":[
        "Manto"
    ],
    "name:slk_x_preferred":[
        "Manto"
    ],
    "name:spa_x_preferred":[
        "Manto"
    ],
    "name:swe_x_preferred":[
        "Manto"
    ],
    "name:ukr_x_preferred":[
        "\u041c\u0430\u043d\u0442\u043e"
    ],
    "wof:name":"Manto",
    "wof:placetype":"locality"
},
  "geometry": {"coordinates":[-71.96666999999999,-13.13333],"type":"Point"}
}