{
  "type": "Feature",
  "properties": {
    "gn:admin1_code":"20",
    "gn:admin2_code":"2004.0",
    "gn:admin3_code":"200407.0",
    "gn:asciiname":"Guayaquil",
    "gn:country_code":"PE",
    "gn:dem":1206,
    "gn:feature_class":"P",
    "gn:feature_code":"PPL",
    "gn:name":"Guayaquil",
    "gn:population":0,
    "gn:timezone":"America/Lima",
    "iso:country":"PE",
    "wof:name":"Guayaquil",
    "wof:placetype":"locality"
},
  "geometry": {"coordinates":[-79.66614,-5.33931],"type":"Point"}
}