{
  "type": "Feature",
  "properties": {
    "gn:admin1_code":"3",
    "gn:admin2_code":"306.0",
    "gn:admin3_code":"30606.0",
    "gn:asciiname":"Inguino",
    "gn:country_code":"PE",
    "gn:dem":2588,
    "gn:feature_class":"P",
    "gn:feature_code":"PPL",
    "gn:name":"Ingui\u00f1o",
    "gn:population":0,
    "gn:timezone":"America/Lima",
    "iso:country":"PE",
    "name:und_x_variant":[
        "Hacienda Ingui\u00f1o",
        "Ingui\u00f1o"
    ],
    "wof:name":"Inguino",
    "wof:placetype":"locality"
},
  "geometry": {"coordinates":[-73.61624999999999,-13.42995],"type":"Point"}
}