{
  "type": "Feature",
  "properties": {
    "gn:admin1_code":"3.0",
    "gn:admin2_code":"305.0",
    "gn:admin3_code":"30501.0",
    "gn:asciiname":"Yanamache",
    "gn:country_code":"PE",
    "gn:dem":3914,
    "gn:feature_class":"P",
    "gn:feature_code":"PPL",
    "gn:name":"Yanamache",
    "gn:population":0,
    "gn:timezone":"America/Lima",
    "iso:country":"PE",
    "wof:name":"Yanamache",
    "wof:placetype":"locality"
},
  "geometry": {"coordinates":[-72.21278000000002,-13.94028],"type":"Point"}
}