{
  "type": "Feature",
  "properties": {
    "gn:admin1_code":"6.0",
    "gn:admin2_code":"605.0",
    "gn:admin3_code":"60503.0",
    "gn:asciiname":"Gallito",
    "gn:country_code":"PE",
    "gn:dem":1708,
    "gn:feature_class":"P",
    "gn:feature_code":"PPL",
    "gn:name":"Gallito",
    "gn:population":0,
    "gn:timezone":"America/Lima",
    "iso:country":"PE",
    "name:spa_x_preferred":[
        "Gallito"
    ],
    "wof:name":"Gallito",
    "wof:placetype":"locality"
},
  "geometry": {"coordinates":[-79.03886,-7.34632],"type":"Point"}
}