{
  "type": "Feature",
  "properties": {
    "gn:admin1_code":"1.0",
    "gn:admin2_code":"107.0",
    "gn:admin3_code":"10707.0",
    "gn:asciiname":"Huamboya",
    "gn:country_code":"PE",
    "gn:dem":1815,
    "gn:feature_class":"P",
    "gn:feature_code":"PPL",
    "gn:name":"Huamboya",
    "gn:population":0,
    "gn:timezone":"America/Lima",
    "iso:country":"PE",
    "name:spa_x_preferred":[
        "Huamboya"
    ],
    "wof:name":"Huamboya",
    "wof:placetype":"locality"
},
  "geometry": {"coordinates":[-78.48338000000003,-5.96912],"type":"Point"}
}