{
  "type": "Feature",
  "properties": {
    "gn:admin1_code":"15",
    "gn:admin2_code":"1510.0",
    "gn:admin3_code":"151031.0",
    "gn:asciiname":"Curcunta",
    "gn:country_code":"PE",
    "gn:dem":4241,
    "gn:feature_class":"P",
    "gn:feature_code":"PPL",
    "gn:name":"Curcunta",
    "gn:population":0,
    "gn:timezone":"America/Lima",
    "iso:country":"PE",
    "wof:name":"Curcunta",
    "wof:placetype":"locality"
},
  "geometry": {"coordinates":[-75.75641999999998,-12.67895],"type":"Point"}
}