{
  "type": "Feature",
  "properties": {
    "gn:admin1_code":"12",
    "gn:admin2_code":"1209.0",
    "gn:admin3_code":"120909.0",
    "gn:asciiname":"Huantucancha",
    "gn:country_code":"PE",
    "gn:dem":4516,
    "gn:feature_class":"P",
    "gn:feature_code":"PPL",
    "gn:name":"Huantucancha",
    "gn:population":0,
    "gn:timezone":"America/Lima",
    "iso:country":"PE",
    "wof:name":"Huantucancha",
    "wof:placetype":"locality"
},
  "geometry": {"coordinates":[-75.6275,-12.20611],"type":"Point"}
}