{
  "type": "Feature",
  "properties": {
    "gn:admin1_code":"5.0",
    "gn:admin2_code":"504.0",
    "gn:admin3_code":"50404.0",
    "gn:asciiname":"Orconcocha",
    "gn:country_code":"PE",
    "gn:dem":2897,
    "gn:feature_class":"P",
    "gn:feature_code":"PPL",
    "gn:name":"Orconcocha",
    "gn:population":0,
    "gn:timezone":"America/Lima",
    "iso:country":"PE",
    "wof:name":"Orconcocha",
    "wof:placetype":"locality"
},
  "geometry": {"coordinates":[-74.22131999999998,-12.9779],"type":"Point"}
}