{
  "type": "Feature",
  "properties": {
    "gn:admin1_code":"05",
    "gn:admin2_code":"510.0",
    "gn:admin3_code":"51011.0",
    "gn:asciiname":"Sarhua",
    "gn:country_code":"PE",
    "gn:dem":3138,
    "gn:feature_class":"P",
    "gn:feature_code":"PPLA3",
    "gn:name":"Sarhua",
    "gn:population":0,
    "gn:timezone":"America/Lima",
    "iso:country":"PE",
    "wof:name":"Sarhua",
    "wof:placetype":"locality"
},
  "geometry": {"coordinates":[-74.31999999999999,-13.67417],"type":"Point"}
}