{
  "type": "Feature",
  "properties": {
    "gn:admin1_code":"5.0",
    "gn:admin2_code":"506.0",
    "gn:admin3_code":"50609.0",
    "gn:asciiname":"Jarhuaj",
    "gn:country_code":"PE",
    "gn:dem":2629,
    "gn:feature_class":"P",
    "gn:feature_code":"PPL",
    "gn:name":"Jarhuaj",
    "gn:population":0,
    "gn:timezone":"America/Lima",
    "iso:country":"PE",
    "name:spa_x_preferred":[
        "Jarhuaj"
    ],
    "wof:name":"Jarhuaj",
    "wof:placetype":"locality"
},
  "geometry": {"coordinates":[-74.67073000000001,-14.65321],"type":"Point"}
}