{
  "type": "Feature",
  "properties": {
    "gn:admin1_code":"4",
    "gn:admin2_code":"406.0",
    "gn:admin3_code":"40605.0",
    "gn:asciiname":"Suros",
    "gn:country_code":"PE",
    "gn:dem":2675,
    "gn:feature_class":"P",
    "gn:feature_code":"PPL",
    "gn:name":"Suros",
    "gn:population":0,
    "gn:timezone":"America/Lima",
    "iso:country":"PE",
    "wof:name":"Suros",
    "wof:placetype":"locality"
},
  "geometry": {"coordinates":[-72.64528,-15.86556],"type":"Point"}
}