{
  "type": "Feature",
  "properties": {
    "gn:admin1_code":"15",
    "gn:admin2_code":"1508.0",
    "gn:admin3_code":"150807.0",
    "gn:asciiname":"Tunsucancha",
    "gn:country_code":"PE",
    "gn:dem":4309,
    "gn:feature_class":"P",
    "gn:feature_code":"PPL",
    "gn:name":"Tunsucancha",
    "gn:population":0,
    "gn:timezone":"America/Lima",
    "iso:country":"PE",
    "wof:name":"Tunsucancha",
    "wof:placetype":"locality"
},
  "geometry": {"coordinates":[-76.86306,-11.07583],"type":"Point"}
}