{
  "type": "Feature",
  "properties": {
    "gn:admin1_code":"11",
    "gn:admin2_code":"1102.0",
    "gn:admin3_code":"110202.0",
    "gn:asciiname":"Hacienda Luchumarca",
    "gn:country_code":"PE",
    "gn:dem":635,
    "gn:feature_class":"P",
    "gn:feature_code":"PPL",
    "gn:name":"Hacienda Luchumarca",
    "gn:population":0,
    "gn:timezone":"America/Lima",
    "iso:country":"PE",
    "name:spa_x_preferred":[
        "Hacienda Luchumarca"
    ],
    "name:und_x_variant":[
        "Luchumarca",
        "Luchomarca"
    ],
    "wof:name":"Hacienda Luchumarca",
    "wof:placetype":"locality"
},
  "geometry": {"coordinates":[-75.8571,-13.36735],"type":"Point"}
}