{
  "type": "Feature",
  "properties": {
    "gn:admin1_code":"12.0",
    "gn:admin2_code":"1204.0",
    "gn:admin3_code":"120419.0",
    "gn:asciiname":"Callanca",
    "gn:country_code":"PE",
    "gn:dem":3974,
    "gn:feature_class":"P",
    "gn:feature_code":"PPL",
    "gn:name":"Callanca",
    "gn:population":0,
    "gn:timezone":"America/Lima",
    "iso:country":"PE",
    "wof:name":"Callanca",
    "wof:placetype":"locality"
},
  "geometry": {"coordinates":[-75.21522,-11.59475],"type":"Point"}
}