{
  "type": "Feature",
  "properties": {
    "gn:admin1_code":"15.0",
    "gn:admin2_code":"1504.0",
    "gn:admin3_code":"150404.0",
    "gn:asciiname":"Jollaj",
    "gn:country_code":"PE",
    "gn:dem":4432,
    "gn:feature_class":"P",
    "gn:feature_code":"PPL",
    "gn:name":"Jollaj",
    "gn:population":0,
    "gn:timezone":"America/Lima",
    "iso:country":"PE",
    "wof:name":"Jollaj",
    "wof:placetype":"locality"
},
  "geometry": {"coordinates":[-76.46726,-11.36273],"type":"Point"}
}