{
  "type": "Feature",
  "properties": {
    "gn:admin1_code":"3.0",
    "gn:admin2_code":"305.0",
    "gn:admin3_code":"30502.0",
    "gn:asciiname":"Ccana",
    "gn:country_code":"PE",
    "gn:dem":3248,
    "gn:feature_class":"P",
    "gn:feature_code":"PPL",
    "gn:name":"Cca\u00f1a",
    "gn:population":0,
    "gn:timezone":"America/Lima",
    "iso:country":"PE",
    "wof:name":"Ccana",
    "wof:placetype":"locality"
},
  "geometry": {"coordinates":[-72.35056,-13.7325],"type":"Point"}
}