{
  "type": "Feature",
  "properties": {
    "gn:admin1_code":"12.0",
    "gn:admin2_code":"1204.0",
    "gn:admin3_code":"120426.0",
    "gn:asciiname":"Huicllo",
    "gn:country_code":"PE",
    "gn:dem":4020,
    "gn:feature_class":"P",
    "gn:feature_code":"PPL",
    "gn:name":"Huicllo",
    "gn:population":0,
    "gn:timezone":"America/Lima",
    "iso:country":"PE",
    "wof:name":"Huicllo",
    "wof:placetype":"locality"
},
  "geometry": {"coordinates":[-75.70394,-11.61663],"type":"Point"}
}