{
  "type": "Feature",
  "properties": {
    "gn:admin1_code":"2.0",
    "gn:admin2_code":"217.0",
    "gn:admin3_code":"21706.0",
    "gn:asciiname":"Pillan",
    "gn:country_code":"PE",
    "gn:dem":2846,
    "gn:feature_class":"P",
    "gn:feature_code":"PPL",
    "gn:name":"Pillan",
    "gn:population":0,
    "gn:timezone":"America/Lima",
    "iso:country":"PE",
    "name:spa_x_preferred":[
        "Pill\u00e1n"
    ],
    "name:swe_x_preferred":[
        "Pillan"
    ],
    "wof:name":"Pillan",
    "wof:placetype":"locality"
},
  "geometry": {"coordinates":[-77.47998,-10.08552],"type":"Point"}
}