{
  "type": "Feature",
  "properties": {
    "gn:admin1_code":"19",
    "gn:admin2_code":"1902.0",
    "gn:admin3_code":"190205.0",
    "gn:asciiname":"Colquipucro",
    "gn:country_code":"PE",
    "gn:dem":3094,
    "gn:feature_class":"P",
    "gn:feature_code":"PPL",
    "gn:name":"Colquipucro",
    "gn:population":0,
    "gn:timezone":"America/Lima",
    "iso:country":"PE",
    "name:und_x_variant":[
        "Colqnipucro"
    ],
    "wof:name":"Colquipucro",
    "wof:placetype":"locality"
},
  "geometry": {"coordinates":[-76.48466999999999,-10.42704],"type":"Point"}
}