{
  "type": "Feature",
  "properties": {
    "gn:admin1_code":"3",
    "gn:admin2_code":"302.0",
    "gn:admin3_code":"30216.0",
    "gn:asciiname":"Casacancha",
    "gn:country_code":"PE",
    "gn:dem":3121,
    "gn:feature_class":"P",
    "gn:feature_code":"PPL",
    "gn:name":"Casacancha",
    "gn:population":0,
    "gn:timezone":"America/Lima",
    "iso:country":"PE",
    "wof:name":"Casacancha",
    "wof:placetype":"locality"
},
  "geometry": {"coordinates":[-73.46670999999998,-13.63764],"type":"Point"}
}