{
  "type": "Feature",
  "properties": {
    "gn:admin1_code":"8",
    "gn:admin2_code":"805.0",
    "gn:admin3_code":"80508.0",
    "gn:asciiname":"Huancane",
    "gn:country_code":"PE",
    "gn:dem":3798,
    "gn:feature_class":"P",
    "gn:feature_code":"PPL",
    "gn:name":"Huancane",
    "gn:population":0,
    "gn:timezone":"America/Lima",
    "iso:country":"PE",
    "wof:name":"Huancane",
    "wof:placetype":"locality"
},
  "geometry": {"coordinates":[-71.49708000000003,-14.14649],"type":"Point"}
}