{
  "type": "Feature",
  "properties": {
    "gn:admin1_code":"15",
    "gn:admin2_code":"1510.0",
    "gn:admin3_code":"151021.0",
    "gn:asciiname":"Yupanca",
    "gn:country_code":"PE",
    "gn:dem":4471,
    "gn:feature_class":"P",
    "gn:feature_code":"PPL",
    "gn:name":"Yupanca",
    "gn:population":0,
    "gn:timezone":"America/Lima",
    "iso:country":"PE",
    "wof:name":"Yupanca",
    "wof:placetype":"locality"
},
  "geometry": {"coordinates":[-75.91500000000001,-12.14638],"type":"Point"}
}