{
  "type": "Feature",
  "properties": {
    "gn:admin1_code":"5.0",
    "gn:admin2_code":"501.0",
    "gn:admin3_code":"50102.0",
    "gn:asciiname":"Cocolillo",
    "gn:country_code":"PE",
    "gn:dem":3409,
    "gn:feature_class":"P",
    "gn:feature_code":"PPL",
    "gn:name":"Cocolillo",
    "gn:population":0,
    "gn:timezone":"America/Lima",
    "iso:country":"PE",
    "wof:name":"Cocolillo",
    "wof:placetype":"locality"
},
  "geometry": {"coordinates":[-74.06576,-13.24352],"type":"Point"}
}