{
  "type": "Feature",
  "properties": {
    "gn:admin1_code":"16",
    "gn:admin2_code":"1601.0",
    "gn:admin3_code":"160103.0",
    "gn:asciiname":"Serafin Filomeno",
    "gn:country_code":"PE",
    "gn:dem":111,
    "gn:feature_class":"P",
    "gn:feature_code":"PPL",
    "gn:name":"Seraf\u00edn Filomeno",
    "gn:population":0,
    "gn:timezone":"America/Lima",
    "iso:country":"PE",
    "wof:name":"Serafin Filomeno",
    "wof:placetype":"locality"
},
  "geometry": {"coordinates":[-72.94521,-4.15523],"type":"Point"}
}