{
  "type": "Feature",
  "properties": {
    "gn:admin1_code":"23",
    "gn:admin2_code":"2304.0",
    "gn:admin3_code":"230406.0",
    "gn:asciiname":"Chincana",
    "gn:country_code":"PE",
    "gn:dem":4487,
    "gn:feature_class":"P",
    "gn:feature_code":"PPL",
    "gn:name":"Chincana",
    "gn:population":0,
    "gn:timezone":"America/Lima",
    "iso:country":"PE",
    "wof:name":"Chincana",
    "wof:placetype":"locality"
},
  "geometry": {"coordinates":[-70.04694000000001,-17.08418],"type":"Point"}
}