{
  "type": "Feature",
  "properties": {
    "gn:admin1_code":"3.0",
    "gn:admin2_code":"305.0",
    "gn:admin3_code":"30501.0",
    "gn:asciiname":"Huancayo",
    "gn:country_code":"PE",
    "gn:dem":3308,
    "gn:feature_class":"P",
    "gn:feature_code":"PPL",
    "gn:name":"Huancayo",
    "gn:population":0,
    "gn:timezone":"America/Lima",
    "iso:country":"PE",
    "wof:name":"Huancayo",
    "wof:placetype":"locality"
},
  "geometry": {"coordinates":[-72.15639,-13.93194],"type":"Point"}
}