{
  "type": "Feature",
  "properties": {
    "gn:admin1_code":"06",
    "gn:admin2_code":"611.0",
    "gn:admin3_code":"61106.0",
    "gn:asciiname":"Ajosmayo",
    "gn:country_code":"PE",
    "gn:dem":462,
    "gn:feature_class":"P",
    "gn:feature_code":"PPL",
    "gn:name":"Ajosmayo",
    "gn:population":0,
    "gn:timezone":"America/Lima",
    "iso:country":"PE",
    "wof:name":"Ajosmayo",
    "wof:placetype":"locality"
},
  "geometry": {"coordinates":[-79.17025,-6.84864],"type":"Point"}
}