{
  "type": "Feature",
  "properties": {
    "gn:admin1_code":"15",
    "gn:admin2_code":"1510.0",
    "gn:admin3_code":"151001.0",
    "gn:asciiname":"Quichualla",
    "gn:country_code":"PE",
    "gn:dem":2641,
    "gn:feature_class":"P",
    "gn:feature_code":"PPL",
    "gn:name":"Quichualla",
    "gn:population":0,
    "gn:timezone":"America/Lima",
    "iso:country":"PE",
    "wof:name":"Quichualla",
    "wof:placetype":"locality"
},
  "geometry": {"coordinates":[-75.92220999999998,-12.50807],"type":"Point"}
}