{
  "type": "Feature",
  "properties": {
    "gn:admin1_code":"10",
    "gn:admin2_code":"1002.0",
    "gn:asciiname":"Huari",
    "gn:country_code":"PE",
    "gn:dem":2948,
    "gn:feature_class":"P",
    "gn:feature_code":"PPL",
    "gn:name":"Huari",
    "gn:population":0,
    "gn:timezone":"America/Lima",
    "iso:country":"PE",
    "name:ceb_x_preferred":[
        "Huari"
    ],
    "name:deu_x_preferred":[
        "Huari"
    ],
    "name:lit_x_preferred":[
        "Varis"
    ],
    "name:nld_x_preferred":[
        "Huari"
    ],
    "name:pol_x_preferred":[
        "Huari"
    ],
    "name:por_x_preferred":[
        "Huari"
    ],
    "name:rus_x_preferred":[
        "\u0423\u0430\u0440\u0438"
    ],
    "name:spa_x_preferred":[
        "Huari"
    ],
    "wof:name":"Huari",
    "wof:placetype":"locality"
},
  "geometry": {"coordinates":[-76.41046999999998,-10.28846],"type":"Point"}
}