{
  "type": "Feature",
  "properties": {
    "gn:admin1_code":"10",
    "gn:admin2_code":"1002.0",
    "gn:asciiname":"Huari",
    "gn:country_code":"PE",
    "gn:dem":2948,
    "gn:feature_class":"P",
    "gn:feature_code":"PPL",
    "gn:name":"Huari",
    "gn:population":0,
    "gn:timezone":"America/Lima",
    "iso:country":"PE",
    "wof:name":"Huari",
    "wof:placetype":"locality"
},
  "geometry": {"coordinates":[-76.41046999999998,-10.28846],"type":"Point"}
}