{
  "type": "Feature",
  "properties": {
    "gn:admin1_code":"10.0",
    "gn:admin2_code":"1011.0",
    "gn:admin3_code":"101104.0",
    "gn:asciiname":"Yanajaga",
    "gn:country_code":"PE",
    "gn:dem":3570,
    "gn:feature_class":"P",
    "gn:feature_code":"PPL",
    "gn:name":"Yanajaga",
    "gn:population":0,
    "gn:timezone":"America/Lima",
    "iso:country":"PE",
    "wof:name":"Yanajaga",
    "wof:placetype":"locality"
},
  "geometry": {"coordinates":[-76.59718000000002,-9.727],"type":"Point"}
}