{
  "type": "Feature",
  "properties": {
    "gn:admin1_code":"20",
    "gn:admin2_code":"2003.0",
    "gn:admin3_code":"200302.0",
    "gn:asciiname":"Silia",
    "gn:country_code":"PE",
    "gn:dem":775,
    "gn:feature_class":"P",
    "gn:feature_code":"PPL",
    "gn:name":"Silia",
    "gn:population":0,
    "gn:timezone":"America/Lima",
    "iso:country":"PE",
    "name:und_x_variant":[
        "Silia Ciudad",
        "Silia"
    ],
    "wof:name":"Silia",
    "wof:placetype":"locality"
},
  "geometry": {"coordinates":[-79.6495,-5.30795],"type":"Point"}
}