{
  "type": "Feature",
  "properties": {
    "gn:admin1_code":"4",
    "gn:admin2_code":"408.0",
    "gn:admin3_code":"40811.0",
    "gn:asciiname":"Sonjo",
    "gn:country_code":"PE",
    "gn:dem":3054,
    "gn:feature_class":"P",
    "gn:feature_code":"PPL",
    "gn:name":"Sonjo",
    "gn:population":0,
    "gn:timezone":"America/Lima",
    "iso:country":"PE",
    "wof:name":"Sonjo",
    "wof:placetype":"locality"
},
  "geometry": {"coordinates":[-73.00083000000002,-15.31556],"type":"Point"}
}