{
  "type": "Feature",
  "properties": {
    "gn:admin1_code":"15",
    "gn:admin2_code":"1510.0",
    "gn:admin3_code":"151018.0",
    "gn:asciiname":"Challhuani",
    "gn:country_code":"PE",
    "gn:dem":4558,
    "gn:feature_class":"P",
    "gn:feature_code":"PPL",
    "gn:name":"Challhuani",
    "gn:population":0,
    "gn:timezone":"America/Lima",
    "iso:country":"PE",
    "name:zho_x_preferred":[
        "\u67e5\u723e\u74e6\u5c3c\u5c71"
    ],
    "wof:name":"Challhuani",
    "wof:placetype":"locality"
},
  "geometry": {"coordinates":[-75.66611,-12.34139],"type":"Point"}
}