{
  "type": "Feature",
  "properties": {
    "iso:country":"PE",
    "name:aym_x_preferred":[
        "Muchumi jisk'a t'aqa suyu"
    ],
    "name:ita_x_preferred":[
        "Distretto di Mochumi"
    ],
    "name:kat_x_preferred":[
        "\u10db\u10dd\u10e9\u10e3\u10db\u10d8\u10e1 \u10e0\u10d0\u10d8\u10dd\u10dc\u10d8"
    ],
    "name:por_x_preferred":[
        "Mochum\u00ed"
    ],
    "name:que_x_preferred":[
        "Muchumi distritu"
    ],
    "name:spa_x_preferred":[
        "Distrito de Mochum\u00ed"
    ],
    "name:unk_x_variant":[
        "Muchumi"
    ],
    "qs:gn_country":"PE",
    "qs:gn_fcode":"PPL",
    "qs:gn_pop":7460,
    "qs:name":"Mochum\u00ed",
    "qs:name_adm0":"Per\u00fa",
    "qs:name_adm1":"Lambayeque",
    "qs:photos":0,
    "qs:photos_1k":0,
    "qs:photos_9k":1,
    "qs:photos_9r":1,
    "qs:photos_all":1,
    "qs:photos_sr":0,
    "qs:placetype":"Town",
    "qs:pop_sr":"5",
    "qs:woe_adm0":23424919,
    "wd:wordcount":47,
    "wof:name":"Mochum\u00ed",
    "wof:placetype":"locality",
    "wof:population":7460
},
  "geometry": {"coordinates":[-79.86372,-6.54774],"type":"Point"}
}