{
  "type": "Feature",
  "properties": {
    "gn:admin1_code":"04",
    "gn:admin2_code":"402.0",
    "gn:admin3_code":"40206.0",
    "gn:asciiname":"La Planchada",
    "gn:country_code":"PE",
    "gn:dem":30,
    "gn:feature_class":"P",
    "gn:feature_code":"PPL",
    "gn:name":"La Planchada",
    "gn:population":0,
    "gn:timezone":"America/Lima",
    "iso:country":"PE",
    "wof:name":"La Planchada",
    "wof:placetype":"locality"
},
  "geometry": {"coordinates":[-73.22334000000002,-16.40367],"type":"Point"}
}