{
  "type": "Feature",
  "properties": {
    "gn:admin1_code":"14.0",
    "gn:admin2_code":"1401.0",
    "gn:admin3_code":"140112.0",
    "gn:asciiname":"Maria Cruz",
    "gn:country_code":"PE",
    "gn:dem":25,
    "gn:feature_class":"P",
    "gn:feature_code":"PPL",
    "gn:name":"Maria Cruz",
    "gn:population":0,
    "gn:timezone":"America/Lima",
    "iso:country":"PE",
    "name:spa_x_preferred":[
        "Maria Cruz"
    ],
    "wof:name":"Maria Cruz",
    "wof:placetype":"locality"
},
  "geometry": {"coordinates":[-79.86462,-6.75455],"type":"Point"}
}