{
  "type": "Feature",
  "properties": {
    "gn:admin1_code":"21",
    "gn:admin2_code":"2112.0",
    "gn:admin3_code":"211204.0",
    "gn:asciiname":"Paccha Juchu",
    "gn:country_code":"PE",
    "gn:dem":4347,
    "gn:feature_class":"P",
    "gn:feature_code":"PPL",
    "gn:name":"Paccha Juchu",
    "gn:population":0,
    "gn:timezone":"America/Lima",
    "iso:country":"PE",
    "wof:name":"Paccha Juchu",
    "wof:placetype":"locality"
},
  "geometry": {"coordinates":[-69.6566,-14.43087],"type":"Point"}
}