{
  "type": "Feature",
  "properties": {
    "gn:admin1_code":"15",
    "gn:admin2_code":"1510.0",
    "gn:admin3_code":"151014.0",
    "gn:asciiname":"Pachachaca",
    "gn:country_code":"PE",
    "gn:dem":3985,
    "gn:feature_class":"P",
    "gn:feature_code":"PPL",
    "gn:name":"Pachachaca",
    "gn:population":0,
    "gn:timezone":"America/Lima",
    "iso:country":"PE",
    "wof:name":"Pachachaca",
    "wof:placetype":"locality"
},
  "geometry": {"coordinates":[-75.87056,-12.08833],"type":"Point"}
}