{
  "type": "Feature",
  "properties": {
    "gn:admin1_code":"10",
    "gn:admin2_code":"1008.0",
    "gn:asciiname":"Yanamachay",
    "gn:country_code":"PE",
    "gn:dem":3651,
    "gn:feature_class":"P",
    "gn:feature_code":"PPL",
    "gn:name":"Yanamachay",
    "gn:population":0,
    "gn:timezone":"America/Lima",
    "iso:country":"PE",
    "wof:name":"Yanamachay",
    "wof:placetype":"locality"
},
  "geometry": {"coordinates":[-75.80194,-10.15444],"type":"Point"}
}