{
  "type": "Feature",
  "properties": {
    "gn:admin1_code":"22.0",
    "gn:admin2_code":"2204.0",
    "gn:admin3_code":"220403.0",
    "gn:asciiname":"San Miguel",
    "gn:country_code":"PE",
    "gn:dem":490,
    "gn:feature_class":"P",
    "gn:feature_code":"PPL",
    "gn:name":"San Miguel",
    "gn:population":0,
    "gn:timezone":"America/Lima",
    "iso:country":"PE",
    "name:spa_x_preferred":[
        "San Miguel"
    ],
    "wof:name":"San Miguel",
    "wof:placetype":"locality"
},
  "geometry": {"coordinates":[-76.68164,-7.01235],"type":"Point"}
}