{
  "type": "Feature",
  "properties": {
    "gn:admin1_code":"15.0",
    "gn:admin2_code":"1501.0",
    "gn:admin3_code":"150108.0",
    "gn:asciiname":"Huertos de Villa",
    "gn:country_code":"PE",
    "gn:dem":2,
    "gn:feature_class":"P",
    "gn:feature_code":"PPL",
    "gn:name":"Huertos de Villa",
    "gn:population":0,
    "gn:timezone":"America/Lima",
    "iso:country":"PE",
    "name:spa_x_preferred":[
        "Huertos de Villa"
    ],
    "wof:name":"Huertos de Villa",
    "wof:placetype":"locality"
},
  "geometry": {"coordinates":[-76.99523000000001,-12.20126],"type":"Point"}
}