{
  "type": "Feature",
  "properties": {
    "gn:admin1_code":"18",
    "gn:admin2_code":"1801.0",
    "gn:admin3_code":"180104.0",
    "gn:asciiname":"La Chimba",
    "gn:country_code":"PE",
    "gn:dem":1845,
    "gn:feature_class":"P",
    "gn:feature_code":"PPL",
    "gn:name":"La Chimba",
    "gn:population":0,
    "gn:timezone":"America/Lima",
    "iso:country":"PE",
    "wof:name":"La Chimba",
    "wof:placetype":"locality"
},
  "geometry": {"coordinates":[-70.85429000000001,-17.13658],"type":"Point"}
}