{
  "type": "Feature",
  "properties": {
    "gn:admin1_code":"05",
    "gn:admin2_code":"505.0",
    "gn:admin3_code":"50502.0",
    "gn:asciiname":"Rangracancha",
    "gn:country_code":"PE",
    "gn:dem":3844,
    "gn:feature_class":"P",
    "gn:feature_code":"PPL",
    "gn:name":"Rangracancha",
    "gn:population":0,
    "gn:timezone":"America/Lima",
    "iso:country":"PE",
    "name:und_x_variant":[
        "Rangrachancha",
        "Rangracancha"
    ],
    "wof:name":"Rangracancha",
    "wof:placetype":"locality"
},
  "geometry": {"coordinates":[-73.84322,-13.04594],"type":"Point"}
}