{
  "type": "Feature",
  "properties": {
    "gn:admin1_code":"11",
    "gn:admin2_code":"1101.0",
    "gn:admin3_code":"110102.0",
    "gn:asciiname":"Manco Capac",
    "gn:country_code":"PE",
    "gn:dem":449,
    "gn:feature_class":"P",
    "gn:feature_code":"PPL",
    "gn:name":"Manco Capac",
    "gn:population":0,
    "gn:timezone":"America/Lima",
    "iso:country":"PE",
    "wof:name":"Manco Capac",
    "wof:placetype":"locality"
},
  "geometry": {"coordinates":[-75.70203000000002,-13.98593],"type":"Point"}
}