{
  "type": "Feature",
  "properties": {
    "gn:admin1_code":"16",
    "gn:admin2_code":"1602.0",
    "gn:admin3_code":"160206.0",
    "gn:asciiname":"Siete de Junio",
    "gn:country_code":"PE",
    "gn:dem":134,
    "gn:feature_class":"P",
    "gn:feature_code":"PPL",
    "gn:name":"Siete de Junio",
    "gn:population":0,
    "gn:timezone":"America/Lima",
    "iso:country":"PE",
    "wof:name":"Siete de Junio",
    "wof:placetype":"locality"
},
  "geometry": {"coordinates":[-76.06269,-4.49159],"type":"Point"}
}