{
  "type": "Feature",
  "properties": {
    "gn:admin1_code":"5",
    "gn:admin2_code":"509.0",
    "gn:admin3_code":"50906.0",
    "gn:asciiname":"Atiquipa",
    "gn:country_code":"PE",
    "gn:dem":3729,
    "gn:feature_class":"P",
    "gn:feature_code":"PPL",
    "gn:name":"Atiquipa",
    "gn:population":0,
    "gn:timezone":"America/Lima",
    "iso:country":"PE",
    "wof:name":"Atiquipa",
    "wof:placetype":"locality"
},
  "geometry": {"coordinates":[-73.84639,-14.09528],"type":"Point"}
}