{
  "type": "Feature",
  "properties": {
    "gn:admin1_code":"25",
    "gn:admin2_code":"2502.0",
    "gn:admin3_code":"250201.0",
    "gn:asciiname":"Puerto Inuya",
    "gn:country_code":"PE",
    "gn:dem":256,
    "gn:feature_class":"P",
    "gn:feature_code":"PPL",
    "gn:name":"Puerto Inuya",
    "gn:population":0,
    "gn:timezone":"America/Lima",
    "iso:country":"PE",
    "wof:name":"Puerto Inuya",
    "wof:placetype":"locality"
},
  "geometry": {"coordinates":[-73.48333000000002,-10.68333],"type":"Point"}
}