{
  "type": "Feature",
  "properties": {
    "gn:admin1_code":"22.0",
    "gn:admin2_code":"2210.0",
    "gn:admin3_code":"221002.0",
    "gn:asciiname":"Consuelo",
    "gn:country_code":"PE",
    "gn:dem":631,
    "gn:feature_class":"P",
    "gn:feature_code":"PPL",
    "gn:name":"Consuelo",
    "gn:population":0,
    "gn:timezone":"America/Lima",
    "iso:country":"PE",
    "name:ceb_x_preferred":[
        "Consuelo"
    ],
    "name:deu_x_preferred":[
        "Consuelo"
    ],
    "name:ita_x_preferred":[
        "Consuelo"
    ],
    "name:rus_x_preferred":[
        "\u041a\u043e\u043d\u0441\u0443\u044d\u043b\u043e"
    ],
    "name:swe_x_preferred":[
        "Consuelo"
    ],
    "wof:name":"Consuelo",
    "wof:placetype":"locality"
},
  "geometry": {"coordinates":[-76.12897,-8.62579],"type":"Point"}
}