{
  "type": "Feature",
  "properties": {
    "gn:admin1_code":"10.0",
    "gn:admin2_code":"1005.0",
    "gn:admin3_code":"100511.0",
    "gn:asciiname":"Cebolla Pampa",
    "gn:country_code":"PE",
    "gn:dem":4283,
    "gn:feature_class":"P",
    "gn:feature_code":"PPL",
    "gn:name":"Cebolla Pampa",
    "gn:population":0,
    "gn:timezone":"America/Lima",
    "iso:country":"PE",
    "wof:name":"Cebolla Pampa",
    "wof:placetype":"locality"
},
  "geometry": {"coordinates":[-76.68812,-9.45785],"type":"Point"}
}