{
  "type": "Feature",
  "properties": {
    "gn:admin1_code":"13.0",
    "gn:admin2_code":"1308.0",
    "gn:admin3_code":"130801.0",
    "gn:asciiname":"Chongos",
    "gn:country_code":"PE",
    "gn:dem":3193,
    "gn:feature_class":"P",
    "gn:feature_code":"PPL",
    "gn:name":"Chongos",
    "gn:population":0,
    "gn:timezone":"America/Lima",
    "iso:country":"PE",
    "wof:name":"Chongos",
    "wof:placetype":"locality"
},
  "geometry": {"coordinates":[-77.32444,-8.24083],"type":"Point"}
}