{
  "type": "Feature",
  "properties": {
    "gn:admin1_code":"10.0",
    "gn:admin2_code":"1003.0",
    "gn:admin3_code":"100311.0",
    "gn:asciiname":"Quinta",
    "gn:country_code":"PE",
    "gn:dem":3478,
    "gn:feature_class":"P",
    "gn:feature_code":"PPL",
    "gn:name":"Quinta",
    "gn:population":0,
    "gn:timezone":"America/Lima",
    "iso:country":"PE",
    "wof:name":"Quinta",
    "wof:placetype":"locality"
},
  "geometry": {"coordinates":[-76.68571,-9.60879],"type":"Point"}
}