{
  "type": "Feature",
  "properties": {
    "gn:admin1_code":"8.0",
    "gn:admin2_code":"813.0",
    "gn:admin3_code":"81306.0",
    "gn:asciiname":"Marcacocha",
    "gn:country_code":"PE",
    "gn:dem":3887,
    "gn:feature_class":"P",
    "gn:feature_code":"PPL",
    "gn:name":"Marcacocha",
    "gn:population":0,
    "gn:timezone":"America/Lima",
    "iso:country":"PE",
    "wof:name":"Marcacocha",
    "wof:placetype":"locality"
},
  "geometry": {"coordinates":[-72.19055999999998,-13.21083],"type":"Point"}
}