{
  "type": "Feature",
  "properties": {
    "gn:admin1_code":"9.0",
    "gn:admin2_code":"905.0",
    "gn:admin3_code":"90510.0",
    "gn:asciiname":"Paltamarca",
    "gn:country_code":"PE",
    "gn:dem":3000,
    "gn:feature_class":"P",
    "gn:feature_code":"PPL",
    "gn:name":"Paltamarca",
    "gn:population":0,
    "gn:timezone":"America/Lima",
    "iso:country":"PE",
    "wof:name":"Paltamarca",
    "wof:placetype":"locality"
},
  "geometry": {"coordinates":[-74.51588000000002,-12.50641],"type":"Point"}
}