{
  "type": "Feature",
  "properties": {
    "gn:admin1_code":"09",
    "gn:admin2_code":"903.0",
    "gn:admin3_code":"90308.0",
    "gn:asciiname":"Huallay Grande",
    "gn:country_code":"PE",
    "gn:dem":3526,
    "gn:feature_class":"P",
    "gn:feature_code":"PPL",
    "gn:name":"Huallay Grande",
    "gn:population":0,
    "gn:timezone":"America/Lima",
    "iso:country":"PE",
    "wof:name":"Huallay Grande",
    "wof:placetype":"locality"
},
  "geometry": {"coordinates":[-74.69838,-12.93939],"type":"Point"}
}