{
  "type": "Feature",
  "properties": {
    "gn:admin1_code":"23",
    "gn:admin2_code":"2301.0",
    "gn:admin3_code":"230108.0",
    "gn:asciiname":"Picchay",
    "gn:cc2":"PE",
    "gn:country_code":"PE",
    "gn:dem":642,
    "gn:feature_class":"P",
    "gn:feature_code":"PPL",
    "gn:name":"Picchay",
    "gn:population":0,
    "gn:timezone":"America/Lima",
    "iso:country":"PE",
    "name:und_x_variant":[
        "Peschai",
        "Picchay Hacienda",
        "Picchay"
    ],
    "wof:name":"Picchay",
    "wof:placetype":"locality"
},
  "geometry": {"coordinates":[-70.21666999999999,-18.01667],"type":"Point"}
}