{
  "type": "Feature",
  "properties": {
    "gn:admin1_code":"06",
    "gn:admin2_code":"611.0",
    "gn:admin3_code":"61109.0",
    "gn:asciiname":"Pampa de Lanche",
    "gn:country_code":"PE",
    "gn:dem":2939,
    "gn:feature_class":"P",
    "gn:feature_code":"PPL",
    "gn:name":"Pampa de Lanche",
    "gn:population":0,
    "gn:timezone":"America/Lima",
    "iso:country":"PE",
    "wof:name":"Pampa de Lanche",
    "wof:placetype":"locality"
},
  "geometry": {"coordinates":[-79.08870999999998,-6.92715],"type":"Point"}
}