{
  "type": "Feature",
  "properties": {
    "gn:admin1_code":"9",
    "gn:admin2_code":"904.0",
    "gn:admin3_code":"90401.0",
    "gn:asciiname":"Bonanza",
    "gn:country_code":"PE",
    "gn:dem":4649,
    "gn:feature_class":"P",
    "gn:feature_code":"PPL",
    "gn:name":"Bonanza",
    "gn:population":0,
    "gn:timezone":"America/Lima",
    "iso:country":"PE",
    "wof:name":"Bonanza",
    "wof:placetype":"locality"
},
  "geometry": {"coordinates":[-75.31667,-13.18333],"type":"Point"}
}