{
  "type": "Feature",
  "properties": {
    "gn:admin1_code":"14",
    "gn:admin2_code":"1403.0",
    "gn:admin3_code":"140301.0",
    "gn:asciiname":"Cartajena",
    "gn:country_code":"PE",
    "gn:dem":26,
    "gn:feature_class":"P",
    "gn:feature_code":"PPL",
    "gn:name":"Cartajena",
    "gn:population":0,
    "gn:timezone":"America/Lima",
    "iso:country":"PE",
    "name:spa_x_preferred":[
        "Cartajena"
    ],
    "wof:name":"Cartajena",
    "wof:placetype":"locality"
},
  "geometry": {"coordinates":[-79.84470999999998,-6.68468],"type":"Point"}
}