{
  "type": "Feature",
  "properties": {
    "gn:admin1_code":"02",
    "gn:admin2_code":"205.0",
    "gn:admin3_code":"20510.0",
    "gn:asciiname":"Carhuac",
    "gn:country_code":"PE",
    "gn:dem":3694,
    "gn:feature_class":"P",
    "gn:feature_code":"PPL",
    "gn:name":"Carhuac",
    "gn:population":0,
    "gn:timezone":"America/Lima",
    "iso:country":"PE",
    "wof:name":"Carhuac",
    "wof:placetype":"locality"
},
  "geometry": {"coordinates":[-77.39587,-10.2561],"type":"Point"}
}