{
  "type": "Feature",
  "properties": {
    "gn:admin1_code":"1",
    "gn:admin2_code":"107.0",
    "gn:admin3_code":"10706.0",
    "gn:asciiname":"Nuevo Triunfo",
    "gn:country_code":"PE",
    "gn:dem":1140,
    "gn:feature_class":"P",
    "gn:feature_code":"PPL",
    "gn:name":"Nuevo Triunfo",
    "gn:population":0,
    "gn:timezone":"America/Lima",
    "iso:country":"PE",
    "wof:name":"Nuevo Triunfo",
    "wof:placetype":"locality"
},
  "geometry": {"coordinates":[-78.47511999999998,-6.07942],"type":"Point"}
}