{
  "type": "Feature",
  "properties": {
    "gn:admin1_code":"16",
    "gn:admin2_code":"1603.0",
    "gn:admin3_code":"160304.0",
    "gn:asciiname":"Dos de Mayo",
    "gn:country_code":"PE",
    "gn:dem":151,
    "gn:feature_class":"P",
    "gn:feature_code":"PPL",
    "gn:name":"Dos de Mayo",
    "gn:population":0,
    "gn:timezone":"America/Lima",
    "iso:country":"PE",
    "wof:name":"Dos de Mayo",
    "wof:placetype":"locality"
},
  "geometry": {"coordinates":[-75.46772,-3.40918],"type":"Point"}
}