{
  "type": "Feature",
  "properties": {
    "iso:country":"PE",
    "name:aym_x_preferred":[
        "Nu\u00f1uwa jisk'a t'aqa suyu"
    ],
    "name:ceb_x_preferred":[
        "Nu\u00f1oa"
    ],
    "name:deu_x_preferred":[
        "Distrikt Nu\u00f1oa"
    ],
    "name:eng_x_preferred":[
        "Nu\u00f1oa District"
    ],
    "name:ita_x_preferred":[
        "Distretto di Nu\u00f1oa"
    ],
    "name:kat_x_preferred":[
        "\u10dc\u10e3\u10dc\u10d8\u10dd\u10d8\u10e1 \u10e0\u10d0\u10d8\u10dd\u10dc\u10d8"
    ],
    "name:nld_x_preferred":[
        "Nu\u00f1oa District"
    ],
    "name:por_x_preferred":[
        "Nu\u00f1oa"
    ],
    "name:que_x_preferred":[
        "Nu\u00f1uwa distritu"
    ],
    "name:spa_x_preferred":[
        "Distrito de Nu\u00f1oa"
    ],
    "name:und_x_variant":[
        "\u00d1u\u00f1oa"
    ],
    "name:zho_x_preferred":[
        "\u52aa\u5c3c\u5967\u74e6\u5340"
    ],
    "qs:gn_country":"PE",
    "qs:gn_fcode":"PPL",
    "qs:gn_pop":4271,
    "qs:name":"Nu\u00f1oa",
    "qs:name_adm0":"Per\u00fa",
    "qs:name_adm1":"Puno",
    "qs:photos":59,
    "qs:photos_1k":12,
    "qs:photos_9k":1,
    "qs:photos_9r":2,
    "qs:photos_all":59,
    "qs:photos_sr":2,
    "qs:placetype":"Town",
    "qs:pop_sr":"4",
    "qs:woe_adm0":23424919,
    "wof:name":"Nu\u00f1oa",
    "wof:placetype":"locality",
    "wof:population":4271
},
  "geometry": {"coordinates":[-70.63583,-14.47788],"type":"Point"}
}