{
  "type": "Feature",
  "properties": {
    "gn:admin1_code":"02",
    "gn:admin2_code":"206.0",
    "gn:admin3_code":"20607.0",
    "gn:asciiname":"Pariahuanca",
    "gn:country_code":"PE",
    "gn:dem":2813,
    "gn:feature_class":"P",
    "gn:feature_code":"PPL",
    "gn:name":"Pariahuanca",
    "gn:population":0,
    "gn:timezone":"America/Lima",
    "iso:country":"PE",
    "wof:name":"Pariahuanca",
    "wof:placetype":"locality"
},
  "geometry": {"coordinates":[-77.58111,-9.36556],"type":"Point"}
}