{
  "type": "Feature",
  "properties": {
    "gn:admin1_code":"15",
    "gn:admin2_code":"1507.0",
    "gn:admin3_code":"150701.0",
    "gn:asciiname":"Burricopuquio",
    "gn:country_code":"PE",
    "gn:dem":3192,
    "gn:feature_class":"P",
    "gn:feature_code":"PPL",
    "gn:name":"Burricopuquio",
    "gn:population":0,
    "gn:timezone":"America/Lima",
    "iso:country":"PE",
    "wof:name":"Burricopuquio",
    "wof:placetype":"locality"
},
  "geometry": {"coordinates":[-76.36028,-11.78167],"type":"Point"}
}