{
  "type": "Feature",
  "properties": {
    "gn:admin1_code":"21.0",
    "gn:admin2_code":"2104.0",
    "gn:admin3_code":"210405.0",
    "gn:asciiname":"Tupo",
    "gn:country_code":"PE",
    "gn:dem":4284,
    "gn:feature_class":"P",
    "gn:feature_code":"PPL",
    "gn:name":"Tupo",
    "gn:population":0,
    "gn:timezone":"America/Lima",
    "iso:country":"PE",
    "wof:name":"Tupo",
    "wof:placetype":"locality"
},
  "geometry": {"coordinates":[-69.5462,-17.13947000000001],"type":"Point"}
}