{
  "type": "Feature",
  "properties": {
    "gn:admin1_code":"16",
    "gn:admin2_code":"1603.0",
    "gn:admin3_code":"160303.0",
    "gn:asciiname":"Intuto",
    "gn:country_code":"PE",
    "gn:dem":120,
    "gn:feature_class":"P",
    "gn:feature_code":"PPL",
    "gn:name":"Intuto",
    "gn:population":0,
    "gn:timezone":"America/Lima",
    "iso:country":"PE",
    "wof:name":"Intuto",
    "wof:placetype":"locality"
},
  "geometry": {"coordinates":[-74.78205,-3.49031],"type":"Point"}
}