{
  "type": "Feature",
  "properties": {
    "gn:admin1_code":"10.0",
    "gn:admin2_code":"1005.0",
    "gn:admin3_code":"100510.0",
    "gn:asciiname":"Coshpay",
    "gn:country_code":"PE",
    "gn:dem":3047,
    "gn:feature_class":"P",
    "gn:feature_code":"PPL",
    "gn:name":"Coshpay",
    "gn:population":0,
    "gn:timezone":"America/Lima",
    "iso:country":"PE",
    "wof:name":"Coshpay",
    "wof:placetype":"locality"
},
  "geometry": {"coordinates":[-76.80298000000001,-9.39916],"type":"Point"}
}