{
  "type": "Feature",
  "properties": {
    "gn:admin1_code":"3",
    "gn:admin2_code":"302.0",
    "gn:admin3_code":"30207.0",
    "gn:asciiname":"Urpay",
    "gn:country_code":"PE",
    "gn:dem":3365,
    "gn:feature_class":"P",
    "gn:feature_code":"PPL",
    "gn:name":"Urpay",
    "gn:population":0,
    "gn:timezone":"America/Lima",
    "iso:country":"PE",
    "wof:name":"Urpay",
    "wof:placetype":"locality"
},
  "geometry": {"coordinates":[-73.14267,-13.56099],"type":"Point"}
}