{
  "type": "Feature",
  "properties": {
    "gn:admin1_code":"12.0",
    "gn:admin2_code":"1206.0",
    "gn:admin3_code":"120608.0",
    "gn:asciiname":"Sheboja",
    "gn:country_code":"PE",
    "gn:dem":253,
    "gn:feature_class":"P",
    "gn:feature_code":"PPL",
    "gn:name":"Sheboja",
    "gn:population":0,
    "gn:timezone":"America/Lima",
    "iso:country":"PE",
    "name:spa_x_preferred":[
        "Sheboja"
    ],
    "wof:name":"Sheboja",
    "wof:placetype":"locality"
},
  "geometry": {"coordinates":[-73.73451999999997,-11.03115],"type":"Point"}
}