{
  "type": "Feature",
  "properties": {
    "gn:admin1_code":"20",
    "gn:admin2_code":"2007.0",
    "gn:admin3_code":"200704.0",
    "gn:asciiname":"Barrio Castilla",
    "gn:country_code":"PE",
    "gn:dem":8,
    "gn:feature_class":"P",
    "gn:feature_code":"PPL",
    "gn:name":"Barrio Castilla",
    "gn:population":0,
    "gn:timezone":"America/Lima",
    "iso:country":"PE",
    "wof:name":"Barrio Castilla",
    "wof:placetype":"locality"
},
  "geometry": {"coordinates":[-81.27143000000002,-4.44432],"type":"Point"}
}