{
  "type": "Feature",
  "properties": {
    "gn:admin1_code":"22.0",
    "gn:admin2_code":"2205.0",
    "gn:admin3_code":"220511.0",
    "gn:asciiname":"Huerta",
    "gn:country_code":"PE",
    "gn:dem":445,
    "gn:feature_class":"P",
    "gn:feature_code":"PPL",
    "gn:name":"Huerta",
    "gn:population":0,
    "gn:timezone":"America/Lima",
    "iso:country":"PE",
    "name:fra_x_preferred":[
        "Jardin potager"
    ],
    "name:glg_x_preferred":[
        "Horta"
    ],
    "name:ita_x_preferred":[
        "Orto"
    ],
    "name:pol_x_preferred":[
        "Huerta"
    ],
    "name:por_x_preferred":[
        "Horta"
    ],
    "name:que_x_preferred":[
        "Muya"
    ],
    "name:rus_x_preferred":[
        "\u0423\u044d\u0440\u0442\u0430"
    ],
    "name:scn_x_preferred":[
        "Ortu"
    ],
    "name:spa_x_preferred":[
        "Huerta"
    ],
    "wof:name":"Huerta",
    "wof:placetype":"locality"
},
  "geometry": {"coordinates":[-76.48487,-6.53272],"type":"Point"}
}