{
  "type": "Feature",
  "properties": {
    "gn:admin1_code":"21",
    "gn:admin2_code":"2112",
    "gn:asciiname":"Pacay Huata",
    "gn:country_code":"PE",
    "gn:dem":1870,
    "gn:feature_class":"P",
    "gn:feature_code":"PPL",
    "gn:name":"Pacay Huata",
    "gn:population":0,
    "gn:timezone":"America/Lima",
    "iso:country":"PE",
    "name:spa_x_preferred":[
        "Pacay Huata"
    ],
    "wof:name":"Pacay Huata",
    "wof:placetype":"locality"
},
  "geometry": {"coordinates":[-69.62876999999999,-13.93569],"type":"Point"}
}