{
  "type": "Feature",
  "properties": {
    "gn:admin1_code":"3",
    "gn:admin2_code":"304.0",
    "gn:admin3_code":"30411.0",
    "gn:asciiname":"Seccseccalla",
    "gn:country_code":"PE",
    "gn:dem":3082,
    "gn:feature_class":"P",
    "gn:feature_code":"PPL",
    "gn:name":"Seccseccalla",
    "gn:population":0,
    "gn:timezone":"America/Lima",
    "iso:country":"PE",
    "wof:name":"Seccseccalla",
    "wof:placetype":"locality"
},
  "geometry": {"coordinates":[-73.17833,-13.9155],"type":"Point"}
}