{
  "type": "Feature",
  "properties": {
    "gn:admin1_code":"8",
    "gn:admin2_code":"805.0",
    "gn:admin3_code":"80503.0",
    "gn:asciiname":"Cochucho",
    "gn:country_code":"PE",
    "gn:dem":4223,
    "gn:feature_class":"P",
    "gn:feature_code":"PPL",
    "gn:name":"Cochucho",
    "gn:population":0,
    "gn:timezone":"America/Lima",
    "iso:country":"PE",
    "wof:name":"Cochucho",
    "wof:placetype":"locality"
},
  "geometry": {"coordinates":[-71.31049,-14.47842],"type":"Point"}
}