{
  "type": "Feature",
  "properties": {
    "gn:admin1_code":"06",
    "gn:admin2_code":"610.0",
    "gn:admin3_code":"61007.0",
    "gn:asciiname":"El Tingo",
    "gn:cc2":"PE",
    "gn:country_code":"PE",
    "gn:dem":1044,
    "gn:feature_class":"P",
    "gn:feature_code":"PPL",
    "gn:name":"El Tingo",
    "gn:population":0,
    "gn:timezone":"America/Lima",
    "iso:country":"PE",
    "name:und_x_variant":[
        "Tingo",
        "Marcamachay",
        "El Tingo"
    ],
    "wof:name":"El Tingo",
    "wof:placetype":"locality"
},
  "geometry": {"coordinates":[-77.83333,-7.35],"type":"Point"}
}