{
  "type": "Feature",
  "properties": {
    "gn:admin1_code":"12.0",
    "gn:admin2_code":"1205.0",
    "gn:admin3_code":"120501.0",
    "gn:asciiname":"Cunchipunta",
    "gn:country_code":"PE",
    "gn:dem":4248,
    "gn:feature_class":"P",
    "gn:feature_code":"PPL",
    "gn:name":"Cunchipunta",
    "gn:population":0,
    "gn:timezone":"America/Lima",
    "iso:country":"PE",
    "wof:name":"Cunchipunta",
    "wof:placetype":"locality"
},
  "geometry": {"coordinates":[-76.05855,-11.18292],"type":"Point"}
}