{
  "type": "Feature",
  "properties": {
    "gn:admin1_code":"05",
    "gn:admin2_code":"506.0",
    "gn:admin3_code":"50609.0",
    "gn:asciiname":"Chuquimaran",
    "gn:country_code":"PE",
    "gn:dem":2625,
    "gn:feature_class":"P",
    "gn:feature_code":"PPL",
    "gn:name":"Chuquimar\u00e1n",
    "gn:population":0,
    "gn:timezone":"America/Lima",
    "iso:country":"PE",
    "wof:name":"Chuquimaran",
    "wof:placetype":"locality"
},
  "geometry": {"coordinates":[-74.64149,-14.82496],"type":"Point"}
}