{
  "type": "Feature",
  "properties": {
    "gn:admin1_code":"21",
    "gn:admin2_code":"2101.0",
    "gn:admin3_code":"210105.0",
    "gn:asciiname":"Capachica",
    "gn:cc2":"PE",
    "gn:country_code":"PE",
    "gn:dem":3830,
    "gn:feature_class":"P",
    "gn:feature_code":"PPLA3",
    "gn:name":"Capachica",
    "gn:population":0,
    "gn:timezone":"America/Lima",
    "iso:country":"PE",
    "name:und_x_variant":[
        "Capachico",
        "Capachica"
    ],
    "wof:name":"Capachica",
    "wof:placetype":"locality"
},
  "geometry": {"coordinates":[-69.81667,-15.63333],"type":"Point"}
}