{
  "type": "Feature",
  "properties": {
    "gn:admin1_code":"10",
    "gn:admin2_code":"1001.0",
    "gn:admin3_code":"100108.0",
    "gn:asciiname":"Piruco",
    "gn:country_code":"PE",
    "gn:dem":3985,
    "gn:feature_class":"P",
    "gn:feature_code":"PPL",
    "gn:name":"Piruco",
    "gn:population":0,
    "gn:timezone":"America/Lima",
    "iso:country":"PE",
    "wof:name":"Piruco",
    "wof:placetype":"locality"
},
  "geometry": {"coordinates":[-76.4431,-10.04948],"type":"Point"}
}