{
  "type": "Feature",
  "properties": {
    "gn:admin1_code":"13.0",
    "gn:admin2_code":"1308.0",
    "gn:asciiname":"Anchic",
    "gn:country_code":"PE",
    "gn:dem":2254,
    "gn:feature_class":"P",
    "gn:feature_code":"PPL",
    "gn:name":"Anchic",
    "gn:population":0,
    "gn:timezone":"America/Lima",
    "iso:country":"PE",
    "wof:name":"Anchic",
    "wof:placetype":"locality"
},
  "geometry": {"coordinates":[-77.26416999999999,-8.47167],"type":"Point"}
}