{
  "type": "Feature",
  "properties": {
    "gn:admin1_code":"13",
    "gn:admin2_code":"1309.0",
    "gn:admin3_code":"130905.0",
    "gn:asciiname":"Pauca",
    "gn:country_code":"PE",
    "gn:dem":2862,
    "gn:feature_class":"P",
    "gn:feature_code":"PPL",
    "gn:name":"Pauca",
    "gn:population":0,
    "gn:timezone":"America/Lima",
    "iso:country":"PE",
    "wof:name":"Pauca",
    "wof:placetype":"locality"
},
  "geometry": {"coordinates":[-77.88306,-7.73139],"type":"Point"}
}