{
  "type": "Feature",
  "properties": {
    "gn:admin1_code":"4",
    "gn:admin2_code":"406.0",
    "gn:asciiname":"Changachanga",
    "gn:country_code":"PE",
    "gn:dem":4484,
    "gn:feature_class":"P",
    "gn:feature_code":"PPL",
    "gn:name":"Changachanga",
    "gn:population":0,
    "gn:timezone":"America/Lima",
    "iso:country":"PE",
    "wof:name":"Changachanga",
    "wof:placetype":"locality"
},
  "geometry": {"coordinates":[-71.92737,-14.77616],"type":"Point"}
}