{
  "type": "Feature",
  "properties": {
    "gn:admin1_code":"18",
    "gn:admin2_code":"1802.0",
    "gn:admin3_code":"180209.0",
    "gn:asciiname":"Chimpapampa",
    "gn:country_code":"PE",
    "gn:dem":1833,
    "gn:feature_class":"P",
    "gn:feature_code":"PPL",
    "gn:name":"Chimpapampa",
    "gn:population":0,
    "gn:timezone":"America/Lima",
    "iso:country":"PE",
    "wof:name":"Chimpapampa",
    "wof:placetype":"locality"
},
  "geometry": {"coordinates":[-70.86785,-16.753],"type":"Point"}
}