{
  "type": "Feature",
  "properties": {
    "gn:admin1_code":"20",
    "gn:admin2_code":"2004.0",
    "gn:admin3_code":"200401.0",
    "gn:asciiname":"Chapica",
    "gn:country_code":"PE",
    "gn:dem":130,
    "gn:feature_class":"P",
    "gn:feature_code":"PPL",
    "gn:name":"Chapica",
    "gn:population":0,
    "gn:timezone":"America/Lima",
    "iso:country":"PE",
    "wof:name":"Chapica",
    "wof:placetype":"locality"
},
  "geometry": {"coordinates":[-80.10164,-5.07518],"type":"Point"}
}