{
  "type": "Feature",
  "properties": {
    "gn:admin1_code":"06",
    "gn:admin2_code":"606.0",
    "gn:admin3_code":"60607.0",
    "gn:asciiname":"Hacienda El Sauce",
    "gn:country_code":"PE",
    "gn:dem":906,
    "gn:feature_class":"P",
    "gn:feature_code":"PPL",
    "gn:name":"Hacienda El Sauce",
    "gn:population":0,
    "gn:timezone":"America/Lima",
    "iso:country":"PE",
    "wof:name":"Hacienda El Sauce",
    "wof:placetype":"locality"
},
  "geometry": {"coordinates":[-79.08915999999998,-6.11308],"type":"Point"}
}