{
  "type": "Feature",
  "properties": {
    "gn:admin1_code":"22",
    "gn:admin2_code":"2205.0",
    "gn:admin3_code":"220504.0",
    "gn:asciiname":"San Cristobal",
    "gn:country_code":"PE",
    "gn:dem":194,
    "gn:feature_class":"P",
    "gn:feature_code":"PPL",
    "gn:name":"San Crist\u00f3bal",
    "gn:population":0,
    "gn:timezone":"America/Lima",
    "iso:country":"PE",
    "wof:name":"San Cristobal",
    "wof:placetype":"locality"
},
  "geometry": {"coordinates":[-76.23333000000002,-6.18333],"type":"Point"}
}