{
  "type": "Feature",
  "properties": {
    "gn:admin1_code":"21",
    "gn:admin2_code":"2106.0",
    "gn:asciiname":"Kapara",
    "gn:country_code":"PE",
    "gn:dem":3814,
    "gn:feature_class":"P",
    "gn:feature_code":"PPL",
    "gn:name":"Kapara",
    "gn:population":0,
    "gn:timezone":"America/Lima",
    "iso:country":"PE",
    "name:nor_x_preferred":[
        "Kapara"
    ],
    "name:spa_x_preferred":[
        "Kapara"
    ],
    "wof:name":"Kapara",
    "wof:placetype":"locality"
},
  "geometry": {"coordinates":[-69.90000000000001,-15.48333],"type":"Point"}
}