{
  "type": "Feature",
  "properties": {
    "gn:admin1_code":"12",
    "gn:admin2_code":"1204.0",
    "gn:admin3_code":"120429.0",
    "gn:asciiname":"San Pedro de Chunan",
    "gn:country_code":"PE",
    "gn:dem":3399,
    "gn:feature_class":"P",
    "gn:feature_code":"PPL",
    "gn:name":"San Pedro de Chunan",
    "gn:population":0,
    "gn:timezone":"America/Lima",
    "iso:country":"PE",
    "name:und_x_variant":[
        "Chun\u00e1n",
        "San Pedro de Chunan"
    ],
    "wof:name":"San Pedro de Chunan",
    "wof:placetype":"locality"
},
  "geometry": {"coordinates":[-75.48650000000001,-11.72447],"type":"Point"}
}