{
  "type": "Feature",
  "properties": {
    "gn:admin1_code":"13.0",
    "gn:admin2_code":"1308.0",
    "gn:admin3_code":"130813.0",
    "gn:asciiname":"Chavirca",
    "gn:country_code":"PE",
    "gn:dem":3534,
    "gn:feature_class":"P",
    "gn:feature_code":"PPL",
    "gn:name":"Chavirca",
    "gn:population":0,
    "gn:timezone":"America/Lima",
    "iso:country":"PE",
    "wof:name":"Chavirca",
    "wof:placetype":"locality"
},
  "geometry": {"coordinates":[-77.33583,-8.3275],"type":"Point"}
}