{
  "type": "Feature",
  "properties": {
    "gn:admin1_code":"14",
    "gn:admin2_code":"1403.0",
    "gn:admin3_code":"140308.0",
    "gn:asciiname":"Escute",
    "gn:country_code":"PE",
    "gn:dem":115,
    "gn:feature_class":"P",
    "gn:feature_code":"PPL",
    "gn:name":"Escute",
    "gn:population":0,
    "gn:timezone":"America/Lima",
    "iso:country":"PE",
    "name:und_x_variant":[
        "Escute Ciudad",
        "Escute"
    ],
    "wof:name":"Escute",
    "wof:placetype":"locality"
},
  "geometry": {"coordinates":[-79.89461999999997,-5.78293],"type":"Point"}
}