{
  "type": "Feature",
  "properties": {
    "gn:admin1_code":"21",
    "gn:admin2_code":"2104.0",
    "gn:admin3_code":"210404.0",
    "gn:asciiname":"Taancache",
    "gn:country_code":"PE",
    "gn:dem":3997,
    "gn:feature_class":"P",
    "gn:feature_code":"PPL",
    "gn:name":"Taancache",
    "gn:population":0,
    "gn:timezone":"America/Lima",
    "iso:country":"PE",
    "wof:name":"Taancache",
    "wof:placetype":"locality"
},
  "geometry": {"coordinates":[-69.28967,-16.72807],"type":"Point"}
}