{
  "type": "Feature",
  "properties": {
    "gn:admin1_code":"10.0",
    "gn:admin2_code":"1001.0",
    "gn:admin3_code":"100109.0",
    "gn:asciiname":"Jatunpampa",
    "gn:country_code":"PE",
    "gn:dem":2671,
    "gn:feature_class":"P",
    "gn:feature_code":"PPLL",
    "gn:name":"Jatunpampa",
    "gn:population":0,
    "gn:timezone":"America/Lima",
    "iso:country":"PE",
    "wof:name":"Jatunpampa",
    "wof:placetype":"locality"
},
  "geometry": {"coordinates":[-76.29468,-9.81668],"type":"Point"}
}