{
  "type": "Feature",
  "properties": {
    "gn:admin1_code":"12.0",
    "gn:admin2_code":"1208.0",
    "gn:admin3_code":"120801.0",
    "gn:asciiname":"Luichupuquio",
    "gn:country_code":"PE",
    "gn:dem":4125,
    "gn:feature_class":"P",
    "gn:feature_code":"PPL",
    "gn:name":"Luichupuquio",
    "gn:population":0,
    "gn:timezone":"America/Lima",
    "iso:country":"PE",
    "wof:name":"Luichupuquio",
    "wof:placetype":"locality"
},
  "geometry": {"coordinates":[-75.85675999999999,-11.65263],"type":"Point"}
}