{
  "type": "Feature",
  "properties": {
    "gn:admin1_code":"8",
    "gn:admin2_code":"806.0",
    "gn:admin3_code":"80601.0",
    "gn:asciiname":"Velacunca",
    "gn:country_code":"PE",
    "gn:dem":4169,
    "gn:feature_class":"P",
    "gn:feature_code":"PPL",
    "gn:name":"Velacunca",
    "gn:population":0,
    "gn:timezone":"America/Lima",
    "iso:country":"PE",
    "wof:name":"Velacunca",
    "wof:placetype":"locality"
},
  "geometry": {"coordinates":[-71.07833000000002,-14.26611],"type":"Point"}
}