{
  "type": "Feature",
  "properties": {
    "gn:admin1_code":"06",
    "gn:admin2_code":"604.0",
    "gn:admin3_code":"60415.0",
    "gn:asciiname":"Layuran",
    "gn:country_code":"PE",
    "gn:dem":1926,
    "gn:feature_class":"P",
    "gn:feature_code":"PPL",
    "gn:name":"Layuran",
    "gn:population":0,
    "gn:timezone":"America/Lima",
    "iso:country":"PE",
    "wof:name":"Layuran",
    "wof:placetype":"locality"
},
  "geometry": {"coordinates":[-79.02435,-6.37446],"type":"Point"}
}