{
  "type": "Feature",
  "properties": {
    "gn:admin1_code":"4",
    "gn:admin2_code":"405.0",
    "gn:admin3_code":"40506.0",
    "gn:asciiname":"Canayaque",
    "gn:country_code":"PE",
    "gn:dem":3583,
    "gn:feature_class":"P",
    "gn:feature_code":"PPL",
    "gn:name":"Canayaque",
    "gn:population":0,
    "gn:timezone":"America/Lima",
    "iso:country":"PE",
    "wof:name":"Canayaque",
    "wof:placetype":"locality"
},
  "geometry": {"coordinates":[-71.62108000000001,-15.64012],"type":"Point"}
}