{
  "type": "Feature",
  "properties": {
    "gn:admin1_code":"21",
    "gn:admin2_code":"2101.0",
    "gn:admin3_code":"210111.0",
    "gn:asciiname":"Estancia Coline",
    "gn:country_code":"PE",
    "gn:dem":4443,
    "gn:feature_class":"P",
    "gn:feature_code":"PPL",
    "gn:name":"Estancia Coline",
    "gn:population":0,
    "gn:timezone":"America/Lima",
    "iso:country":"PE",
    "wof:name":"Estancia Coline",
    "wof:placetype":"locality"
},
  "geometry": {"coordinates":[-70.09999999999999,-16.26667],"type":"Point"}
}