{
  "type": "Feature",
  "properties": {
    "gn:admin1_code":"01",
    "gn:admin2_code":"107.0",
    "gn:admin3_code":"10701.0",
    "gn:asciiname":"Nuevo Horizonte",
    "gn:country_code":"PE",
    "gn:dem":1241,
    "gn:feature_class":"P",
    "gn:feature_code":"PPL",
    "gn:name":"Nuevo Horizonte",
    "gn:population":0,
    "gn:timezone":"America/Lima",
    "iso:country":"PE",
    "wof:name":"Nuevo Horizonte",
    "wof:placetype":"locality"
},
  "geometry": {"coordinates":[-78.52853,-5.83631],"type":"Point"}
}