{
  "type": "Feature",
  "properties": {
    "gn:admin1_code":"15",
    "gn:admin2_code":"1510.0",
    "gn:admin3_code":"151023.0",
    "gn:asciiname":"Erhuaca",
    "gn:country_code":"PE",
    "gn:dem":1642,
    "gn:feature_class":"P",
    "gn:feature_code":"PPL",
    "gn:name":"Erhuaca",
    "gn:population":0,
    "gn:timezone":"America/Lima",
    "iso:country":"PE",
    "wof:name":"Erhuaca",
    "wof:placetype":"locality"
},
  "geometry": {"coordinates":[-75.95828,-12.66933],"type":"Point"}
}