{
  "type": "Feature",
  "properties": {
    "gn:admin1_code":"12",
    "gn:admin2_code":"1202.0",
    "gn:admin3_code":"120211.0",
    "gn:asciiname":"Mito",
    "gn:country_code":"PE",
    "gn:dem":3265,
    "gn:feature_class":"P",
    "gn:feature_code":"PPL",
    "gn:name":"Mito",
    "gn:population":0,
    "gn:timezone":"America/Lima",
    "iso:country":"PE",
    "name:ceb_x_preferred":[
        "Mito"
    ],
    "name:ces_x_preferred":[
        "Mito"
    ],
    "name:deu_x_preferred":[
        "Mito"
    ],
    "name:hun_x_preferred":[
        "Mito"
    ],
    "name:ita_x_preferred":[
        "Mito"
    ],
    "name:mlg_x_preferred":[
        "Mito"
    ],
    "name:por_x_preferred":[
        "Mito"
    ],
    "name:rus_x_preferred":[
        "\u041c\u0438\u0442\u043e"
    ],
    "name:spa_x_preferred":[
        "Mito"
    ],
    "name:swe_x_preferred":[
        "Mito"
    ],
    "name:tgl_x_preferred":[
        "Mito"
    ],
    "name:ukr_x_preferred":[
        "\u041c\u0456\u0442\u043e"
    ],
    "wof:name":"Mito",
    "wof:placetype":"locality"
},
  "geometry": {"coordinates":[-75.33862999999999,-11.93787],"type":"Point"}
}