{
  "type": "Feature",
  "properties": {
    "gn:admin1_code":"12",
    "gn:admin2_code":"1202.0",
    "gn:admin3_code":"120211.0",
    "gn:asciiname":"Mito",
    "gn:country_code":"PE",
    "gn:dem":3265,
    "gn:feature_class":"P",
    "gn:feature_code":"PPL",
    "gn:name":"Mito",
    "gn:population":0,
    "gn:timezone":"America/Lima",
    "iso:country":"PE",
    "wof:name":"Mito",
    "wof:placetype":"locality"
},
  "geometry": {"coordinates":[-75.33863000000002,-11.93787],"type":"Point"}
}