{
  "type": "Feature",
  "properties": {
    "gn:admin1_code":"03",
    "gn:admin2_code":"301.0",
    "gn:admin3_code":"30104.0",
    "gn:asciiname":"Pompeya",
    "gn:cc2":"PE",
    "gn:country_code":"PE",
    "gn:dem":2783,
    "gn:feature_class":"P",
    "gn:feature_code":"PPL",
    "gn:name":"Pompeya",
    "gn:population":0,
    "gn:timezone":"America/Lima",
    "iso:country":"PE",
    "name:ceb_x_preferred":[
        "Pompeya"
    ],
    "name:spa_x_preferred":[
        "Pompeya"
    ],
    "name:swe_x_preferred":[
        "Pompeya"
    ],
    "name:und_x_variant":[
        "Pompeya Hacienda",
        "Pompeya"
    ],
    "wof:name":"Pompeya",
    "wof:placetype":"locality"
},
  "geometry": {"coordinates":[-72.68333,-13.55],"type":"Point"}
}