{
  "type": "Feature",
  "properties": {
    "gn:admin1_code":"14",
    "gn:admin2_code":"1402.0",
    "gn:admin3_code":"140204.0",
    "gn:asciiname":"Manuel Antonio Mesones Muro",
    "gn:country_code":"PE",
    "gn:dem":63,
    "gn:feature_class":"P",
    "gn:feature_code":"PPLA3",
    "gn:name":"Manuel Antonio Mesones Muro",
    "gn:population":0,
    "gn:timezone":"America/Lima",
    "iso:country":"PE",
    "name:spa_x_preferred":[
        "Manuel Antonio Mesones Muro"
    ],
    "wof:name":"Manuel Antonio Mesones Muro",
    "wof:placetype":"locality"
},
  "geometry": {"coordinates":[-79.73806,-6.64361],"type":"Point"}
}