{
  "type": "Feature",
  "properties": {
    "gn:admin1_code":"2.0",
    "gn:admin2_code":"214.0",
    "gn:admin3_code":"21403.0",
    "gn:asciiname":"Quenriracra",
    "gn:country_code":"PE",
    "gn:dem":3862,
    "gn:feature_class":"P",
    "gn:feature_code":"PPL",
    "gn:name":"Quenriracra",
    "gn:population":0,
    "gn:timezone":"America/Lima",
    "iso:country":"PE",
    "wof:name":"Quenriracra",
    "wof:placetype":"locality"
},
  "geometry": {"coordinates":[-77.22180999999998,-10.3554],"type":"Point"}
}