{
  "type": "Feature",
  "properties": {
    "gn:admin1_code":"02",
    "gn:admin2_code":"218.0",
    "gn:admin3_code":"21802.0",
    "gn:asciiname":"Huacapampa",
    "gn:country_code":"PE",
    "gn:dem":3126,
    "gn:feature_class":"P",
    "gn:feature_code":"PPL",
    "gn:name":"Huacapampa",
    "gn:population":0,
    "gn:timezone":"America/Lima",
    "iso:country":"PE",
    "wof:name":"Huacapampa",
    "wof:placetype":"locality"
},
  "geometry": {"coordinates":[-78.06001999999999,-8.93028],"type":"Point"}
}