{
  "type": "Feature",
  "properties": {
    "gn:admin1_code":"22",
    "gn:admin2_code":"2209.0",
    "gn:admin3_code":"220909.0",
    "gn:asciiname":"Ucsha",
    "gn:country_code":"PE",
    "gn:dem":368,
    "gn:feature_class":"P",
    "gn:feature_code":"PPL",
    "gn:name":"Ucsha",
    "gn:population":0,
    "gn:timezone":"America/Lima",
    "iso:country":"PE",
    "name:spa_x_preferred":[
        "Ucsha"
    ],
    "wof:name":"Ucsha",
    "wof:placetype":"locality"
},
  "geometry": {"coordinates":[-76.31175999999998,-6.50809],"type":"Point"}
}