{
  "type": "Feature",
  "properties": {
    "gn:admin1_code":"13.0",
    "gn:admin2_code":"1308.0",
    "gn:admin3_code":"130804.0",
    "gn:asciiname":"Rosas",
    "gn:country_code":"PE",
    "gn:dem":2740,
    "gn:feature_class":"P",
    "gn:feature_code":"PPL",
    "gn:name":"Rosas",
    "gn:population":0,
    "gn:timezone":"America/Lima",
    "iso:country":"PE",
    "name:cat_x_preferred":[
        "Rosas"
    ],
    "name:ceb_x_preferred":[
        "Rosas"
    ],
    "name:deu_x_preferred":[
        "Rosas"
    ],
    "name:fin_x_preferred":[
        "Rosas"
    ],
    "name:fra_x_preferred":[
        "Rosas"
    ],
    "name:ita_x_preferred":[
        "Rosas"
    ],
    "name:nld_x_preferred":[
        "Rosas"
    ],
    "name:rus_x_preferred":[
        "\u0420\u043e\u0441\u0430\u0441"
    ],
    "name:spa_x_preferred":[
        "Rosas"
    ],
    "name:srp_x_preferred":[
        "\u0420\u043e\u0441\u0430\u0441"
    ],
    "name:swe_x_preferred":[
        "Rosas"
    ],
    "name:tgl_x_preferred":[
        "Rosas"
    ],
    "name:vie_x_preferred":[
        "Rosas"
    ],
    "wof:name":"Rosas",
    "wof:placetype":"locality"
},
  "geometry": {"coordinates":[-77.35333,-8.39139],"type":"Point"}
}