{
  "type": "Feature",
  "properties": {
    "gn:admin1_code":"20",
    "gn:admin2_code":"2006.0",
    "gn:admin3_code":"200604.0",
    "gn:asciiname":"Pampa El Cerro",
    "gn:country_code":"PE",
    "gn:dem":472,
    "gn:feature_class":"P",
    "gn:feature_code":"PPL",
    "gn:name":"Pampa El Cerro",
    "gn:population":0,
    "gn:timezone":"America/Lima",
    "iso:country":"PE",
    "wof:name":"Pampa El Cerro",
    "wof:placetype":"locality"
},
  "geometry": {"coordinates":[-80.68861,-4.40722],"type":"Point"}
}