{
  "type": "Feature",
  "properties": {
    "gn:admin1_code":"9.0",
    "gn:admin2_code":"902.0",
    "gn:asciiname":"Pata Corral",
    "gn:country_code":"PE",
    "gn:dem":3234,
    "gn:feature_class":"P",
    "gn:feature_code":"PPL",
    "gn:name":"Pata Corral",
    "gn:population":0,
    "gn:timezone":"America/Lima",
    "iso:country":"PE",
    "wof:name":"Pata Corral",
    "wof:placetype":"locality"
},
  "geometry": {"coordinates":[-74.39516,-12.89966],"type":"Point"}
}