{
  "type": "Feature",
  "properties": {
    "gn:admin1_code":"8",
    "gn:admin2_code":"808.0",
    "gn:asciiname":"Cotalla",
    "gn:country_code":"PE",
    "gn:dem":4670,
    "gn:feature_class":"P",
    "gn:feature_code":"PPL",
    "gn:name":"Cotalla",
    "gn:population":0,
    "gn:timezone":"America/Lima",
    "iso:country":"PE",
    "wof:name":"Cotalla",
    "wof:placetype":"locality"
},
  "geometry": {"coordinates":[-71.13579,-15.2583],"type":"Point"}
}