{
  "type": "Feature",
  "properties": {
    "gn:admin1_code":"12",
    "gn:admin2_code":"1202.0",
    "gn:admin3_code":"120206.0",
    "gn:asciiname":"Mismi",
    "gn:country_code":"PE",
    "gn:dem":3945,
    "gn:feature_class":"P",
    "gn:feature_code":"PPL",
    "gn:name":"Mismi",
    "gn:population":0,
    "gn:timezone":"America/Lima",
    "iso:country":"PE",
    "name:spa_x_preferred":[
        "Mismi"
    ],
    "wof:name":"Mismi",
    "wof:placetype":"locality"
},
  "geometry": {"coordinates":[-74.95475,-11.7056],"type":"Point"}
}