{
  "type": "Feature",
  "properties": {
    "gn:admin1_code":"12",
    "gn:admin2_code":"1202.0",
    "gn:admin3_code":"120206.0",
    "gn:asciiname":"Mismi",
    "gn:country_code":"PE",
    "gn:dem":3945,
    "gn:feature_class":"P",
    "gn:feature_code":"PPL",
    "gn:name":"Mismi",
    "gn:population":0,
    "gn:timezone":"America/Lima",
    "iso:country":"PE",
    "name:ast_x_preferred":[
        "Mismi"
    ],
    "name:ben_x_preferred":[
        "\u09ae\u09bf\u09b8\u09ae\u09bf"
    ],
    "name:bul_x_preferred":[
        "\u041d\u0435\u0432\u0430\u0434\u043e \u041c\u0438\u0441\u043c\u0438"
    ],
    "name:cat_x_preferred":[
        "Nevado Mismi"
    ],
    "name:ceb_x_preferred":[
        "Nevado Mismi"
    ],
    "name:deu_x_preferred":[
        "Nevado Mismi"
    ],
    "name:epo_x_preferred":[
        "Nevado Mismi"
    ],
    "name:fra_x_preferred":[
        "Nevado Mismi"
    ],
    "name:ita_x_preferred":[
        "Nevado Mismi"
    ],
    "name:lit_x_preferred":[
        "Mismi"
    ],
    "name:mal_x_preferred":[
        "\u0d2e\u0d3f\u0d38\u0d4d\u0d2e\u0d3f"
    ],
    "name:nld_x_preferred":[
        "Nevado Mismi"
    ],
    "name:nor_x_preferred":[
        "Nevado Mismi"
    ],
    "name:por_x_preferred":[
        "Nevado Mismi"
    ],
    "name:que_x_preferred":[
        "Mismi"
    ],
    "name:ron_x_preferred":[
        "Nevado Mismi"
    ],
    "name:spa_x_preferred":[
        "Mismi"
    ],
    "name:swa_x_preferred":[
        "Nevado Mismi"
    ],
    "name:swe_x_preferred":[
        "Mismi"
    ],
    "name:war_x_preferred":[
        "Nevado Mismi"
    ],
    "name:zho_x_preferred":[
        "\u5bc6\u65af\u7c73\u96ea\u5c71"
    ],
    "wof:name":"Mismi",
    "wof:placetype":"locality"
},
  "geometry": {"coordinates":[-74.95475,-11.7056],"type":"Point"}
}