{
  "type": "Feature",
  "properties": {
    "iso:country":"PE",
    "name:ara_x_preferred":[
        "\u0628\u0627\u064a\u062e\u0627\u0646"
    ],
    "name:ast_x_preferred":[
        "Paij\u00e1n"
    ],
    "name:ceb_x_preferred":[
        "Paij\u00e1n"
    ],
    "name:eng_x_preferred":[
        "Paij\u00e1n"
    ],
    "name:nld_x_preferred":[
        "Paij\u00e1n"
    ],
    "name:spa_x_preferred":[
        "Paij\u00e1n"
    ],
    "qs:gn_country":"PE",
    "qs:gn_fcode":"PPL",
    "qs:gn_pop":21128,
    "qs:name":"Paij\u00e1n",
    "qs:name_adm0":"Per\u00fa",
    "qs:name_adm1":"La Libertad",
    "qs:photos":0,
    "qs:photos_1k":0,
    "qs:photos_9k":1,
    "qs:photos_9r":1,
    "qs:photos_all":1,
    "qs:photos_sr":0,
    "qs:placetype":"Town",
    "qs:pop_sr":"7",
    "qs:woe_adm0":23424919,
    "wd:wordcount":57,
    "wof:name":"Paij\u00e1n",
    "wof:placetype":"locality",
    "wof:population":21128
},
  "geometry": {"coordinates":[-79.3015,-7.73291],"type":"Point"}
}