{
  "type": "Feature",
  "properties": {
    "gn:admin1_code":"16",
    "gn:admin2_code":"1601.0",
    "gn:admin3_code":"160107.0",
    "gn:asciiname":"Puca Barranca",
    "gn:country_code":"PE",
    "gn:dem":114,
    "gn:feature_class":"P",
    "gn:feature_code":"PPL",
    "gn:name":"Puca Barranca",
    "gn:population":0,
    "gn:timezone":"America/Lima",
    "iso:country":"PE",
    "wof:name":"Puca Barranca",
    "wof:placetype":"locality"
},
  "geometry": {"coordinates":[-73.51835,-2.70646],"type":"Point"}
}