{
  "type": "Feature",
  "properties": {
    "gn:admin1_code":"8",
    "gn:admin2_code":"808.0",
    "gn:admin3_code":"80807.0",
    "gn:asciiname":"Challoa",
    "gn:country_code":"PE",
    "gn:dem":4500,
    "gn:feature_class":"P",
    "gn:feature_code":"PPL",
    "gn:name":"Challoa",
    "gn:population":0,
    "gn:timezone":"America/Lima",
    "iso:country":"PE",
    "wof:name":"Challoa",
    "wof:placetype":"locality"
},
  "geometry": {"coordinates":[-71.72296,-14.92917],"type":"Point"}
}