{
  "type": "Feature",
  "properties": {
    "gn:admin1_code":"10.0",
    "gn:admin2_code":"1003.0",
    "gn:admin3_code":"100307.0",
    "gn:asciiname":"Tingo Chico",
    "gn:country_code":"PE",
    "gn:dem":2957,
    "gn:feature_class":"P",
    "gn:feature_code":"PPL",
    "gn:name":"Tingo Chico",
    "gn:population":0,
    "gn:timezone":"America/Lima",
    "iso:country":"PE",
    "wof:name":"Tingo Chico",
    "wof:placetype":"locality"
},
  "geometry": {"coordinates":[-76.72309,-9.64386],"type":"Point"}
}