{
  "type": "Feature",
  "properties": {
    "gn:admin1_code":"14.0",
    "gn:admin2_code":"1403.0",
    "gn:admin3_code":"140305.0",
    "gn:asciiname":"Palo Parado",
    "gn:country_code":"PE",
    "gn:dem":31,
    "gn:feature_class":"P",
    "gn:feature_code":"PPL",
    "gn:name":"Palo Parado",
    "gn:population":0,
    "gn:timezone":"America/Lima",
    "iso:country":"PE",
    "name:spa_x_preferred":[
        "Palo Parado"
    ],
    "wof:name":"Palo Parado",
    "wof:placetype":"locality"
},
  "geometry": {"coordinates":[-79.85455,-6.59732],"type":"Point"}
}