{
  "type": "Feature",
  "properties": {
    "gn:admin1_code":"06",
    "gn:admin2_code":"606.0",
    "gn:admin3_code":"60607.0",
    "gn:asciiname":"Patipampa",
    "gn:country_code":"PE",
    "gn:dem":1893,
    "gn:feature_class":"P",
    "gn:feature_code":"PPL",
    "gn:name":"Patipampa",
    "gn:population":0,
    "gn:timezone":"America/Lima",
    "iso:country":"PE",
    "wof:name":"Patipampa",
    "wof:placetype":"locality"
},
  "geometry": {"coordinates":[-79.10954,-6.22337],"type":"Point"}
}