{
  "type": "Feature",
  "properties": {
    "gn:admin1_code":"04",
    "gn:admin2_code":"403.0",
    "gn:admin3_code":"40307.0",
    "gn:asciiname":"Josefita",
    "gn:country_code":"PE",
    "gn:dem":223,
    "gn:feature_class":"P",
    "gn:feature_code":"PPL",
    "gn:name":"Josefita",
    "gn:population":0,
    "gn:timezone":"America/Lima",
    "iso:country":"PE",
    "name:spa_x_preferred":[
        "Josefita"
    ],
    "wof:name":"Josefita",
    "wof:placetype":"locality"
},
  "geometry": {"coordinates":[-74.21623000000002,-15.79017],"type":"Point"}
}