{
  "type": "Feature",
  "properties": {
    "gn:admin1_code":"25",
    "gn:admin2_code":"2502.0",
    "gn:admin3_code":"250201.0",
    "gn:asciiname":"Selva Alegre",
    "gn:country_code":"PE",
    "gn:dem":242,
    "gn:feature_class":"P",
    "gn:feature_code":"PPL",
    "gn:name":"Selva Alegre",
    "gn:population":0,
    "gn:timezone":"America/Lima",
    "iso:country":"PE",
    "name:spa_x_preferred":[
        "Selva Alegre"
    ],
    "wof:name":"Selva Alegre",
    "wof:placetype":"locality"
},
  "geometry": {"coordinates":[-73.85636,-10.60477],"type":"Point"}
}