{
  "type": "Feature",
  "properties": {
    "gn:admin1_code":"04",
    "gn:admin2_code":"401.0",
    "gn:admin3_code":"40119.0",
    "gn:asciiname":"Patalla",
    "gn:country_code":"PE",
    "gn:dem":4344,
    "gn:feature_class":"P",
    "gn:feature_code":"PPL",
    "gn:name":"Patalla",
    "gn:population":0,
    "gn:timezone":"America/Lima",
    "iso:country":"PE",
    "wof:name":"Patalla",
    "wof:placetype":"locality"
},
  "geometry": {"coordinates":[-71.09363,-16.41637],"type":"Point"}
}