{
  "type": "Feature",
  "properties": {
    "gn:admin1_code":"13",
    "gn:admin2_code":"1303.0",
    "gn:admin3_code":"130303.0",
    "gn:asciiname":"Chuquique",
    "gn:country_code":"PE",
    "gn:dem":2610,
    "gn:feature_class":"P",
    "gn:feature_code":"PPL",
    "gn:name":"Chuquique",
    "gn:population":0,
    "gn:timezone":"America/Lima",
    "iso:country":"PE",
    "name:und_x_variant":[
        "Hacienda Chuquique",
        "Chuquique Hacienda",
        "Chuquique"
    ],
    "wof:name":"Chuquique",
    "wof:placetype":"locality"
},
  "geometry": {"coordinates":[-77.65640999999999,-7.56012],"type":"Point"}
}