{
  "type": "Feature",
  "properties": {
    "gn:admin1_code":"05",
    "gn:admin2_code":"507.0",
    "gn:admin3_code":"50705.0",
    "gn:asciiname":"Chilaccasa",
    "gn:country_code":"PE",
    "gn:dem":3929,
    "gn:feature_class":"P",
    "gn:feature_code":"PPL",
    "gn:name":"Chilaccasa",
    "gn:population":0,
    "gn:timezone":"America/Lima",
    "iso:country":"PE",
    "name:spa_x_preferred":[
        "Chilaccasa"
    ],
    "wof:name":"Chilaccasa",
    "wof:placetype":"locality"
},
  "geometry": {"coordinates":[-73.79034,-15.33155],"type":"Point"}
}