{
  "type": "Feature",
  "properties": {
    "gn:admin1_code":"17.0",
    "gn:admin2_code":"1703.0",
    "gn:asciiname":"Lechera",
    "gn:country_code":"PE",
    "gn:dem":301,
    "gn:feature_class":"P",
    "gn:feature_code":"PPL",
    "gn:name":"Lechera",
    "gn:population":0,
    "gn:timezone":"America/Lima",
    "iso:country":"PE",
    "name:spa_x_preferred":[
        "Lechera"
    ],
    "wof:name":"Lechera",
    "wof:placetype":"locality"
},
  "geometry": {"coordinates":[-69.5827,-11.37401],"type":"Point"}
}