{
  "type": "Feature",
  "properties": {
    "gn:admin1_code":"3.0",
    "gn:admin2_code":"305.0",
    "gn:admin3_code":"30502.0",
    "gn:asciiname":"Torreccacca",
    "gn:country_code":"PE",
    "gn:dem":3626,
    "gn:feature_class":"P",
    "gn:feature_code":"PPL",
    "gn:name":"Torreccacca",
    "gn:population":0,
    "gn:timezone":"America/Lima",
    "iso:country":"PE",
    "wof:name":"Torreccacca",
    "wof:placetype":"locality"
},
  "geometry": {"coordinates":[-72.38028,-13.76667],"type":"Point"}
}