{
  "type": "Feature",
  "properties": {
    "gn:admin1_code":"08",
    "gn:admin2_code":"808.0",
    "gn:admin3_code":"80804.0",
    "gn:asciiname":"Chilluata",
    "gn:country_code":"PE",
    "gn:dem":4155,
    "gn:feature_class":"P",
    "gn:feature_code":"PPL",
    "gn:name":"Chilluata",
    "gn:population":0,
    "gn:timezone":"America/Lima",
    "iso:country":"PE",
    "wof:name":"Chilluata",
    "wof:placetype":"locality"
},
  "geometry": {"coordinates":[-71.12394,-15.04771],"type":"Point"}
}