{
  "type": "Feature",
  "properties": {
    "gn:admin1_code":"03",
    "gn:admin2_code":"305.0",
    "gn:admin3_code":"30503.0",
    "gn:asciiname":"Yerbabuena",
    "gn:country_code":"PE",
    "gn:dem":4108,
    "gn:feature_class":"P",
    "gn:feature_code":"PPL",
    "gn:name":"Yerbabuena",
    "gn:population":0,
    "gn:timezone":"America/Lima",
    "iso:country":"PE",
    "wof:name":"Yerbabuena",
    "wof:placetype":"locality"
},
  "geometry": {"coordinates":[-72.41667,-13.99361],"type":"Point"}
}