{
  "type": "Feature",
  "properties": {
    "gn:admin1_code":"10",
    "gn:admin2_code":"1002.0",
    "gn:admin3_code":"100207.0",
    "gn:asciiname":"Tecte",
    "gn:country_code":"PE",
    "gn:dem":2752,
    "gn:feature_class":"P",
    "gn:feature_code":"PPL",
    "gn:name":"Tecte",
    "gn:population":0,
    "gn:timezone":"America/Lima",
    "iso:country":"PE",
    "wof:name":"Tecte",
    "wof:placetype":"locality"
},
  "geometry": {"coordinates":[-76.15172,-10.26237],"type":"Point"}
}