{
  "type": "Feature",
  "properties": {
    "gn:admin1_code":"5.0",
    "gn:admin2_code":"507.0",
    "gn:admin3_code":"50705.0",
    "gn:asciiname":"Taipicirca",
    "gn:country_code":"PE",
    "gn:dem":3493,
    "gn:feature_class":"P",
    "gn:feature_code":"PPL",
    "gn:name":"Taipicirca",
    "gn:population":0,
    "gn:timezone":"America/Lima",
    "iso:country":"PE",
    "name:spa_x_preferred":[
        "Taipicirca"
    ],
    "wof:name":"Taipicirca",
    "wof:placetype":"locality"
},
  "geometry": {"coordinates":[-73.95657,-15.38429],"type":"Point"}
}