{
  "type": "Feature",
  "properties": {
    "gn:admin1_code":"10",
    "gn:admin2_code":"1009.0",
    "gn:admin3_code":"100902.0",
    "gn:asciiname":"Santa Marta",
    "gn:country_code":"PE",
    "gn:dem":287,
    "gn:feature_class":"P",
    "gn:feature_code":"PPL",
    "gn:name":"Santa Marta",
    "gn:population":0,
    "gn:timezone":"America/Lima",
    "iso:country":"PE",
    "wof:name":"Santa Marta",
    "wof:placetype":"locality"
},
  "geometry": {"coordinates":[-75.31376999999998,-9.55957],"type":"Point"}
}