{
  "type": "Feature",
  "properties": {
    "gn:admin1_code":"14.0",
    "gn:admin2_code":"1401.0",
    "gn:admin3_code":"140107.0",
    "gn:asciiname":"San Jorge",
    "gn:country_code":"PE",
    "gn:dem":44,
    "gn:feature_class":"P",
    "gn:feature_code":"PPL",
    "gn:name":"San Jorge",
    "gn:population":0,
    "gn:timezone":"America/Lima",
    "iso:country":"PE",
    "name:spa_x_preferred":[
        "San Jorge"
    ],
    "wof:name":"San Jorge",
    "wof:placetype":"locality"
},
  "geometry": {"coordinates":[-79.62619000000002,-6.98699],"type":"Point"}
}