{
  "type": "Feature",
  "properties": {
    "gn:admin1_code":"15",
    "gn:admin2_code":"1510.0",
    "gn:admin3_code":"151018.0",
    "gn:asciiname":"Yacana",
    "gn:country_code":"PE",
    "gn:dem":4391,
    "gn:feature_class":"P",
    "gn:feature_code":"PPL",
    "gn:name":"Yaca\u00f1a",
    "gn:population":0,
    "gn:timezone":"America/Lima",
    "iso:country":"PE",
    "wof:name":"Yacana",
    "wof:placetype":"locality"
},
  "geometry": {"coordinates":[-75.65666999999998,-12.33611],"type":"Point"}
}