{
  "type": "Feature",
  "properties": {
    "gn:admin1_code":"11",
    "gn:admin2_code":"1104.0",
    "gn:admin3_code":"110405.0",
    "gn:asciiname":"San Andres de Quilcanto",
    "gn:country_code":"PE",
    "gn:dem":2351,
    "gn:feature_class":"P",
    "gn:feature_code":"PPL",
    "gn:name":"San Andr\u00e9s de Quilcanto",
    "gn:population":0,
    "gn:timezone":"America/Lima",
    "iso:country":"PE",
    "name:und_x_variant":[
        "Quilcanta",
        "Quilcanto",
        "Quillcanto",
        "San Andr\u00e9s de Quilcanto"
    ],
    "wof:name":"San Andres de Quilcanto",
    "wof:placetype":"locality"
},
  "geometry": {"coordinates":[-75.18666999999998,-14.08017],"type":"Point"}
}