{
  "type": "Feature",
  "properties": {
    "gn:admin1_code":"15",
    "gn:admin2_code":"1507.0",
    "gn:admin3_code":"150710.0",
    "gn:asciiname":"Huancasana",
    "gn:country_code":"PE",
    "gn:dem":3550,
    "gn:feature_class":"P",
    "gn:feature_code":"PPL",
    "gn:name":"Huancasana",
    "gn:population":0,
    "gn:timezone":"America/Lima",
    "iso:country":"PE",
    "wof:name":"Huancasana",
    "wof:placetype":"locality"
},
  "geometry": {"coordinates":[-76.38333,-12.11667],"type":"Point"}
}