{
  "type": "Feature",
  "properties": {
    "gn:admin1_code":"20",
    "gn:admin2_code":"2002.0",
    "gn:admin3_code":"200202.0",
    "gn:asciiname":"Angurgo",
    "gn:country_code":"PE",
    "gn:dem":875,
    "gn:feature_class":"P",
    "gn:feature_code":"PPL",
    "gn:name":"Angurgo",
    "gn:population":0,
    "gn:timezone":"America/Lima",
    "iso:country":"PE",
    "wof:name":"Angurgo",
    "wof:placetype":"locality"
},
  "geometry": {"coordinates":[-80.03333000000001,-4.98333],"type":"Point"}
}