{
  "type": "Feature",
  "properties": {
    "gn:admin1_code":"06",
    "gn:admin2_code":"608.0",
    "gn:admin3_code":"60808.0",
    "gn:asciiname":"Pucara",
    "gn:country_code":"PE",
    "gn:dem":893,
    "gn:feature_class":"P",
    "gn:feature_code":"PPL",
    "gn:name":"Pucar\u00e1",
    "gn:population":0,
    "gn:timezone":"America/Lima",
    "iso:country":"PE",
    "name:eng_x_preferred":[
        "Pucara"
    ],
    "wof:name":"Pucara",
    "wof:placetype":"locality"
},
  "geometry": {"coordinates":[-79.13203,-6.03885],"type":"Point"}
}