{
  "type": "Feature",
  "properties": {
    "gn:admin1_code":"21",
    "gn:admin2_code":"2102.0",
    "gn:admin3_code":"210209.0",
    "gn:asciiname":"Rosas Tillana",
    "gn:country_code":"PE",
    "gn:dem":4263,
    "gn:feature_class":"P",
    "gn:feature_code":"PPL",
    "gn:name":"Rosas Tillana",
    "gn:population":0,
    "gn:timezone":"America/Lima",
    "iso:country":"PE",
    "wof:name":"Rosas Tillana",
    "wof:placetype":"locality"
},
  "geometry": {"coordinates":[-69.96557,-14.4664],"type":"Point"}
}