{
  "type": "Feature",
  "properties": {
    "gn:admin1_code":"4",
    "gn:admin2_code":"408.0",
    "gn:admin3_code":"40805.0",
    "gn:asciiname":"Cancahue",
    "gn:country_code":"PE",
    "gn:dem":4358,
    "gn:feature_class":"P",
    "gn:feature_code":"PPL",
    "gn:name":"Cancahue",
    "gn:population":0,
    "gn:timezone":"America/Lima",
    "iso:country":"PE",
    "wof:name":"Cancahue",
    "wof:placetype":"locality"
},
  "geometry": {"coordinates":[-73.00111,-15.14972],"type":"Point"}
}