{
  "type": "Feature",
  "properties": {
    "gn:admin1_code":"1.0",
    "gn:admin2_code":"104.0",
    "gn:asciiname":"Puesto de Vigilancia Teniente Nunez",
    "gn:country_code":"PE",
    "gn:dem":530,
    "gn:feature_class":"P",
    "gn:feature_code":"PPL",
    "gn:name":"Puesto de Vigilancia Teniente N\u00fa\u00f1ez",
    "gn:population":0,
    "gn:timezone":"America/Lima",
    "iso:country":"PE",
    "name:spa_x_preferred":[
        "Puesto de Vigilancia Teniente N\u00fa\u00f1ez"
    ],
    "wof:name":"Puesto de Vigilancia Teniente Nunez",
    "wof:placetype":"locality"
},
  "geometry": {"coordinates":[-78.56926999999997,-4.31949],"type":"Point"}
}