{
  "type": "Feature",
  "properties": {
    "gn:admin1_code":"8.0",
    "gn:admin2_code":"810.0",
    "gn:admin3_code":"81005.0",
    "gn:asciiname":"Pitiquillay",
    "gn:country_code":"PE",
    "gn:dem":3564,
    "gn:feature_class":"P",
    "gn:feature_code":"PPL",
    "gn:name":"Pitiquillay",
    "gn:population":0,
    "gn:timezone":"America/Lima",
    "iso:country":"PE",
    "wof:name":"Pitiquillay",
    "wof:placetype":"locality"
},
  "geometry": {"coordinates":[-72.00333000000001,-13.7375],"type":"Point"}
}