{
  "type": "Feature",
  "properties": {
    "gn:admin1_code":"15.0",
    "gn:admin2_code":"1505.0",
    "gn:admin3_code":"150505.0",
    "gn:asciiname":"San Hilarion",
    "gn:country_code":"PE",
    "gn:dem":45,
    "gn:feature_class":"P",
    "gn:feature_code":"PPL",
    "gn:name":"San Hilari\u00f3n",
    "gn:population":0,
    "gn:timezone":"America/Lima",
    "iso:country":"PE",
    "name:spa_x_preferred":[
        "San Hilari\u00f3n"
    ],
    "wof:name":"San Hilarion",
    "wof:placetype":"locality"
},
  "geometry": {"coordinates":[-76.71651999999997,-12.52008],"type":"Point"}
}