{
  "type": "Feature",
  "properties": {
    "gn:admin1_code":"16",
    "gn:admin2_code":"1601.0",
    "gn:admin3_code":"160103.0",
    "gn:asciiname":"Tamshiyacu",
    "gn:country_code":"PE",
    "gn:dem":104,
    "gn:feature_class":"P",
    "gn:feature_code":"PPL",
    "gn:name":"Tamshiyacu",
    "gn:population":0,
    "gn:timezone":"America/Lima",
    "iso:country":"PE",
    "name:ceb_x_preferred":[
        "Tamshiyacu"
    ],
    "name:fra_x_preferred":[
        "Tamshiyacu"
    ],
    "name:spa_x_preferred":[
        "Tamshiyacu"
    ],
    "wof:name":"Tamshiyacu",
    "wof:placetype":"locality"
},
  "geometry": {"coordinates":[-73.1525,-4.00833],"type":"Point"}
}