{
  "type": "Feature",
  "properties": {
    "gn:admin1_code":"11",
    "gn:admin2_code":"1102.0",
    "gn:admin3_code":"110209.0",
    "gn:asciiname":"Bacahuasi",
    "gn:country_code":"PE",
    "gn:dem":3462,
    "gn:feature_class":"P",
    "gn:feature_code":"PPL",
    "gn:name":"Bacahuasi",
    "gn:population":0,
    "gn:timezone":"America/Lima",
    "iso:country":"PE",
    "wof:name":"Bacahuasi",
    "wof:placetype":"locality"
},
  "geometry": {"coordinates":[-75.75277,-13.10596],"type":"Point"}
}