{
  "type": "Feature",
  "properties": {
    "gn:admin1_code":"18",
    "gn:admin2_code":"1801.0",
    "gn:admin3_code":"180106.0",
    "gn:asciiname":"Sajena",
    "gn:country_code":"PE",
    "gn:dem":2775,
    "gn:feature_class":"P",
    "gn:feature_code":"PPL",
    "gn:name":"Sajena",
    "gn:population":0,
    "gn:timezone":"America/Lima",
    "iso:country":"PE",
    "name:und_x_variant":[
        "Sajena Alta",
        "Sajena"
    ],
    "wof:name":"Sajena",
    "wof:placetype":"locality"
},
  "geometry": {"coordinates":[-70.83594000000002,-16.97988],"type":"Point"}
}