{
  "type": "Feature",
  "properties": {
    "gn:admin1_code":"5.0",
    "gn:admin2_code":"504.0",
    "gn:admin3_code":"50401.0",
    "gn:asciiname":"Chuvas",
    "gn:country_code":"PE",
    "gn:dem":2550,
    "gn:feature_class":"P",
    "gn:feature_code":"PPL",
    "gn:name":"Chuvas",
    "gn:population":0,
    "gn:timezone":"America/Lima",
    "iso:country":"PE",
    "wof:name":"Chuvas",
    "wof:placetype":"locality"
},
  "geometry": {"coordinates":[-74.03258000000002,-12.75173],"type":"Point"}
}