{
  "type": "Feature",
  "properties": {
    "gn:admin1_code":"3",
    "gn:admin2_code":"302.0",
    "gn:admin3_code":"30213.0",
    "gn:asciiname":"Chacahuayoc",
    "gn:country_code":"PE",
    "gn:dem":3534,
    "gn:feature_class":"P",
    "gn:feature_code":"PPL",
    "gn:name":"Chacahuayoc",
    "gn:population":0,
    "gn:timezone":"America/Lima",
    "iso:country":"PE",
    "wof:name":"Chacahuayoc",
    "wof:placetype":"locality"
},
  "geometry": {"coordinates":[-73.3159,-13.66972],"type":"Point"}
}