{
  "type": "Feature",
  "properties": {
    "gn:admin1_code":"2.0",
    "gn:admin2_code":"205.0",
    "gn:admin3_code":"20505.0",
    "gn:asciiname":"Cachirpayoc",
    "gn:country_code":"PE",
    "gn:dem":3851,
    "gn:feature_class":"P",
    "gn:feature_code":"PPL",
    "gn:name":"Cachirpayoc",
    "gn:population":0,
    "gn:timezone":"America/Lima",
    "iso:country":"PE",
    "wof:name":"Cachirpayoc",
    "wof:placetype":"locality"
},
  "geometry": {"coordinates":[-77.31095000000001,-10.17737],"type":"Point"}
}