{
  "type": "Feature",
  "properties": {
    "gn:admin1_code":"17.0",
    "gn:admin2_code":"1701.0",
    "gn:asciiname":"Kano",
    "gn:country_code":"PE",
    "gn:dem":246,
    "gn:feature_class":"P",
    "gn:feature_code":"PPL",
    "gn:name":"Kano",
    "gn:population":0,
    "gn:timezone":"America/Lima",
    "iso:country":"PE",
    "name:spa_x_preferred":[
        "Kano"
    ],
    "wof:name":"Kano",
    "wof:placetype":"locality"
},
  "geometry": {"coordinates":[-69.08365999999999,-12.2052],"type":"Point"}
}