{
  "type": "Feature",
  "properties": {
    "gn:country":"PE",
    "gn:fcode":"PPLA3",
    "gn:pop":9800,
    "iso:country":"PE",
    "ne:ADM0CAP":0.0,
    "ne:ADM0NAME":"Peru",
    "ne:ADM0_A3":"PER",
    "ne:ADM1NAME":"Lambayeque",
    "ne:ADMIN1_COD":14,
    "ne:CAPALT":0,
    "ne:CHANGED":0,
    "ne:CHECKME":0,
    "ne:COMPARE":0,
    "ne:DIFFASCII":0,
    "ne:ELEVATION":0.0,
    "ne:FEATURECLA":"Populated place",
    "ne:FEATURE_CL":"P",
    "ne:FEATURE_CO":"PPL",
    "ne:GEONAMEID":3694256,
    "ne:GEONAMESNO":"Geonames ascii name + lat.d + long.d matching.",
    "ne:GN_ASCII":"Olmos",
    "ne:GN_POP":9800,
    "ne:GTOPO30":230.0,
    "ne:ISO_A2":"PE",
    "ne:LABELRANK":5,
    "ne:LATITUDE":-5.979598,
    "ne:LONGITUDE":-79.749975,
    "ne:LS_MATCH":1,
    "ne:LS_NAME":"Olmos",
    "ne:MAX_AREAKM":5.0,
    "ne:MAX_AREAMI":2.0,
    "ne:MAX_BBXMAX":-79.741667,
    "ne:MAX_BBXMIN":-79.766667,
    "ne:MAX_BBYMAX":-5.975,
    "ne:MAX_BBYMIN":-6.0,
    "ne:MAX_NATSCA":20.0,
    "ne:MAX_PERKM":11.0,
    "ne:MAX_PERMI":7.0,
    "ne:MAX_POP10":5359,
    "ne:MAX_POP20":5359,
    "ne:MAX_POP300":0,
    "ne:MAX_POP310":0,
    "ne:MAX_POP50":0,
    "ne:MEAN_BBXC":-79.752778,
    "ne:MEAN_BBYC":-5.988889,
    "ne:MEGACITY":0,
    "ne:MIN_AREAKM":5.0,
    "ne:MIN_AREAMI":2.0,
    "ne:MIN_BBXMAX":-79.741667,
    "ne:MIN_BBXMIN":-79.766667,
    "ne:MIN_BBYMAX":-5.975,
    "ne:MIN_BBYMIN":-6.0,
    "ne:MIN_PERKM":11.0,
    "ne:MIN_PERMI":7.0,
    "ne:NAME":"Olmos",
    "ne:NAMEASCII":"Olmos",
    "ne:NAMEDIFF":0,
    "ne:NATSCALE":20,
    "ne:POP1950":0,
    "ne:POP1955":0,
    "ne:POP1960":0,
    "ne:POP1965":0,
    "ne:POP1970":0,
    "ne:POP1975":0,
    "ne:POP1980":0,
    "ne:POP1985":0,
    "ne:POP1990":0,
    "ne:POP1995":0,
    "ne:POP2000":0,
    "ne:POP2005":0,
    "ne:POP2010":0,
    "ne:POP2015":0,
    "ne:POP2020":0,
    "ne:POP2025":0,
    "ne:POP2050":0,
    "ne:POP_MAX":9800,
    "ne:POP_MIN":5359,
    "ne:POP_OTHER":0,
    "ne:RANK_MAX":5,
    "ne:RANK_MIN":5,
    "ne:SCALERANK":7,
    "ne:SOV0NAME":"Peru",
    "ne:SOV_A3":"PER",
    "ne:TIMEZONE":"America/Lima",
    "ne:UN_FID":0,
    "ne:UN_LAT":0.0,
    "ne:UN_LONG":0.0,
    "ne:WORLDCITY":0,
    "qs:name":"Olmos",
    "qs:photos_9r":0,
    "qs:photos_sr":0,
    "qs:pop_sr":"5",
    "wd:wordcount":83,
    "wof:name":"Olmos",
    "wof:placetype":"locality",
    "wof:population":9800
},
  "geometry": {"coordinates":[-79.74527999999999,-5.98472],"type":"Point"}
}