{
  "type": "Feature",
  "properties": {
    "gn:admin1_code":"5",
    "gn:admin2_code":"502.0",
    "gn:admin3_code":"50205.0",
    "gn:asciiname":"Achcahuasi",
    "gn:country_code":"PE",
    "gn:dem":4607,
    "gn:feature_class":"P",
    "gn:feature_code":"PPL",
    "gn:name":"Achcahuasi",
    "gn:population":0,
    "gn:timezone":"America/Lima",
    "iso:country":"PE",
    "wof:name":"Achcahuasi",
    "wof:placetype":"locality"
},
  "geometry": {"coordinates":[-74.67123000000002,-13.3782],"type":"Point"}
}