{
  "type": "Feature",
  "properties": {
    "gn:admin1_code":"15",
    "gn:admin2_code":"1507.0",
    "gn:admin3_code":"150701.0",
    "gn:asciiname":"Huanarca",
    "gn:country_code":"PE",
    "gn:dem":3663,
    "gn:feature_class":"P",
    "gn:feature_code":"PPL",
    "gn:name":"Huanarca",
    "gn:population":0,
    "gn:timezone":"America/Lima",
    "iso:country":"PE",
    "wof:name":"Huanarca",
    "wof:placetype":"locality"
},
  "geometry": {"coordinates":[-76.35889,-11.87361],"type":"Point"}
}