{
  "type": "Feature",
  "properties": {
    "gn:admin1_code":"8.0",
    "gn:admin2_code":"813.0",
    "gn:admin3_code":"81306.0",
    "gn:asciiname":"Ocororuyoc",
    "gn:country_code":"PE",
    "gn:dem":4121,
    "gn:feature_class":"P",
    "gn:feature_code":"PPLL",
    "gn:name":"Ocororuyoc",
    "gn:population":0,
    "gn:timezone":"America/Lima",
    "iso:country":"PE",
    "wof:name":"Ocororuyoc",
    "wof:placetype":"locality"
},
  "geometry": {"coordinates":[-72.20083000000002,-13.1325],"type":"Point"}
}