{
  "type": "Feature",
  "properties": {
    "gn:admin1_code":"23",
    "gn:admin2_code":"2301.0",
    "gn:admin3_code":"230106.0",
    "gn:asciiname":"Challata",
    "gn:country_code":"PE",
    "gn:dem":1433,
    "gn:feature_class":"P",
    "gn:feature_code":"PPL",
    "gn:name":"Challata",
    "gn:population":0,
    "gn:timezone":"America/Lima",
    "iso:country":"PE",
    "wof:name":"Challata",
    "wof:placetype":"locality"
},
  "geometry": {"coordinates":[-70.11084,-17.83587],"type":"Point"}
}