{
  "type": "Feature",
  "properties": {
    "gn:admin1_code":"2",
    "gn:admin2_code":"209.0",
    "gn:admin3_code":"20903.0",
    "gn:asciiname":"Limena",
    "gn:country_code":"PE",
    "gn:dem":805,
    "gn:feature_class":"P",
    "gn:feature_code":"PPL",
    "gn:name":"Limena",
    "gn:population":0,
    "gn:timezone":"America/Lima",
    "iso:country":"PE",
    "name:azb_x_preferred":[
        "\u0644\u06cc\u0645\u0646\u0627"
    ],
    "name:bul_x_preferred":[
        "\u041b\u0438\u043c\u0435\u043d\u0430"
    ],
    "name:ceb_x_preferred":[
        "Limena"
    ],
    "name:deu_x_preferred":[
        "Limena"
    ],
    "name:epo_x_preferred":[
        "Limena"
    ],
    "name:eus_x_preferred":[
        "Limena"
    ],
    "name:fas_x_preferred":[
        "\u0644\u06cc\u0645\u0646\u0627"
    ],
    "name:fin_x_preferred":[
        "Limena"
    ],
    "name:fra_x_preferred":[
        "Limena"
    ],
    "name:hun_x_preferred":[
        "Limena"
    ],
    "name:hye_x_preferred":[
        "\u053c\u056b\u0574\u0565\u0576\u0561"
    ],
    "name:ind_x_preferred":[
        "Limena"
    ],
    "name:ita_x_preferred":[
        "Limena"
    ],
    "name:jpn_x_preferred":[
        "\u30ea\u30fc\u30e1\u30ca"
    ],
    "name:kaz_x_preferred":[
        "\u041b\u0438\u043c\u0435\u043d\u0430"
    ],
    "name:lat_x_preferred":[
        "Limina"
    ],
    "name:lmo_x_preferred":[
        "Limena"
    ],
    "name:msa_x_preferred":[
        "Limena"
    ],
    "name:nap_x_preferred":[
        "Limena"
    ],
    "name:nld_x_preferred":[
        "Limena"
    ],
    "name:pms_x_preferred":[
        "Limena"
    ],
    "name:pol_x_preferred":[
        "Limena"
    ],
    "name:por_x_preferred":[
        "Limena"
    ],
    "name:ron_x_preferred":[
        "Limena"
    ],
    "name:rus_x_preferred":[
        "\u041b\u0438\u043c\u0435\u043d\u0430"
    ],
    "name:scn_x_preferred":[
        "Limena"
    ],
    "name:spa_x_preferred":[
        "Limena"
    ],
    "name:srp_x_preferred":[
        "\u041b\u0438\u043c\u0435\u043d\u0430"
    ],
    "name:tgl_x_preferred":[
        "Limena"
    ],
    "name:ukr_x_preferred":[
        "\u041b\u0456\u043c\u0435\u043d\u0430"
    ],
    "name:uzb_x_preferred":[
        "Limena"
    ],
    "name:vec_x_preferred":[
        "\u0141\u00ecmena"
    ],
    "name:vie_x_preferred":[
        "Limena"
    ],
    "name:vol_x_preferred":[
        "Limena"
    ],
    "name:war_x_preferred":[
        "Limena"
    ],
    "name:zho_x_preferred":[
        "\u5229\u6885\u7eb3"
    ],
    "wof:name":"Limena",
    "wof:placetype":"locality"
},
  "geometry": {"coordinates":[-78.05556,-8.66472],"type":"Point"}
}