{
  "type": "Feature",
  "properties": {
    "gn:admin1_code":"2",
    "gn:admin2_code":"209.0",
    "gn:admin3_code":"20903.0",
    "gn:asciiname":"Limena",
    "gn:country_code":"PE",
    "gn:dem":805,
    "gn:feature_class":"P",
    "gn:feature_code":"PPL",
    "gn:name":"Limena",
    "gn:population":0,
    "gn:timezone":"America/Lima",
    "iso:country":"PE",
    "wof:name":"Limena",
    "wof:placetype":"locality"
},
  "geometry": {"coordinates":[-78.05556,-8.66472],"type":"Point"}
}