{
  "type": "Feature",
  "properties": {
    "gn:admin1_code":"15",
    "gn:admin2_code":"1503.0",
    "gn:admin3_code":"150301.0",
    "gn:asciiname":"Tilarnioc",
    "gn:country_code":"PE",
    "gn:dem":4463,
    "gn:feature_class":"P",
    "gn:feature_code":"PPL",
    "gn:name":"Tilarnioc",
    "gn:population":0,
    "gn:timezone":"America/Lima",
    "iso:country":"PE",
    "wof:name":"Tilarnioc",
    "wof:placetype":"locality"
},
  "geometry": {"coordinates":[-76.89673000000001,-10.53313],"type":"Point"}
}