{
  "type": "Feature",
  "properties": {
    "gn:admin1_code":"22.0",
    "gn:admin2_code":"2208.0",
    "gn:admin3_code":"220807.0",
    "gn:asciiname":"Perlamayo",
    "gn:country_code":"PE",
    "gn:dem":819,
    "gn:feature_class":"P",
    "gn:feature_code":"PPL",
    "gn:name":"Perlamayo",
    "gn:population":0,
    "gn:timezone":"America/Lima",
    "iso:country":"PE",
    "wof:name":"Perlamayo",
    "wof:placetype":"locality"
},
  "geometry": {"coordinates":[-77.28749999999999,-5.855],"type":"Point"}
}