{
  "type": "Feature",
  "properties": {
    "gn:admin1_code":"11.0",
    "gn:admin2_code":"1101.0",
    "gn:admin3_code":"110111.0",
    "gn:asciiname":"San Matias",
    "gn:country_code":"PE",
    "gn:dem":372,
    "gn:feature_class":"P",
    "gn:feature_code":"PPLL",
    "gn:name":"San Mat\u00edas",
    "gn:population":0,
    "gn:timezone":"America/Lima",
    "iso:country":"PE",
    "name:spa_x_preferred":[
        "San Mat\u00edas"
    ],
    "wof:name":"San Matias",
    "wof:placetype":"locality"
},
  "geometry": {"coordinates":[-75.68940000000001,-14.22898],"type":"Point"}
}