{
  "type": "Feature",
  "properties": {
    "gn:admin1_code":"06",
    "gn:admin2_code":"601.0",
    "gn:admin3_code":"60105.0",
    "gn:asciiname":"Hacienda Polloquito",
    "gn:country_code":"PE",
    "gn:dem":3061,
    "gn:feature_class":"P",
    "gn:feature_code":"PPL",
    "gn:name":"Hacienda Polloquito",
    "gn:population":0,
    "gn:timezone":"America/Lima",
    "iso:country":"PE",
    "wof:name":"Hacienda Polloquito",
    "wof:placetype":"locality"
},
  "geometry": {"coordinates":[-78.30259000000002,-7.13968],"type":"Point"}
}