{
  "type": "Feature",
  "properties": {
    "gn:admin1_code":"02",
    "gn:admin2_code":"220.0",
    "gn:admin3_code":"22005.0",
    "gn:asciiname":"Ataco Pampa",
    "gn:country_code":"PE",
    "gn:dem":2220,
    "gn:feature_class":"P",
    "gn:feature_code":"PPL",
    "gn:name":"Ataco Pampa",
    "gn:population":0,
    "gn:timezone":"America/Lima",
    "iso:country":"PE",
    "wof:name":"Ataco Pampa",
    "wof:placetype":"locality"
},
  "geometry": {"coordinates":[-78.01732,-9.26725],"type":"Point"}
}