{
  "type": "Feature",
  "properties": {
    "gn:admin1_code":"12",
    "gn:admin2_code":"1207.0",
    "gn:admin3_code":"120708.0",
    "gn:asciiname":"Viscacancha",
    "gn:country_code":"PE",
    "gn:dem":4188,
    "gn:feature_class":"P",
    "gn:feature_code":"PPL",
    "gn:name":"Viscacancha",
    "gn:population":0,
    "gn:timezone":"America/Lima",
    "iso:country":"PE",
    "wof:name":"Viscacancha",
    "wof:placetype":"locality"
},
  "geometry": {"coordinates":[-75.87179,-11.2831],"type":"Point"}
}