{
  "type": "Feature",
  "properties": {
    "gn:admin1_code":"14",
    "gn:admin2_code":"1403.0",
    "gn:admin3_code":"140306.0",
    "gn:asciiname":"Monte Hermoso",
    "gn:country_code":"PE",
    "gn:dem":38,
    "gn:feature_class":"P",
    "gn:feature_code":"PPL",
    "gn:name":"Monte Hermoso",
    "gn:population":0,
    "gn:timezone":"America/Lima",
    "iso:country":"PE",
    "wof:name":"Monte Hermoso",
    "wof:placetype":"locality"
},
  "geometry": {"coordinates":[-79.94583,-6.46792],"type":"Point"}
}