{
  "type": "Feature",
  "properties": {
    "iso:country":"PE",
    "name:unk_x_variant":[
        "Fundici\u00f3n de Tinyahuarco"
    ],
    "qs:gn_country":"PE",
    "qs:gn_fcode":"PPL",
    "qs:gn_pop":5066,
    "qs:name":"Tinllahuarco",
    "qs:name_adm0":"Per\u00fa",
    "qs:name_adm1":"Pasco",
    "qs:photos":0,
    "qs:photos_1k":0,
    "qs:photos_9k":0,
    "qs:photos_9r":0,
    "qs:photos_all":0,
    "qs:photos_sr":0,
    "qs:placetype":"Town",
    "qs:pop_sr":"5",
    "qs:woe_adm0":23424919,
    "wof:name":"Tinllahuarco",
    "wof:placetype":"locality",
    "wof:population":5066
},
  "geometry": {"coordinates":[-76.27522999999999,-10.76771],"type":"Point"}
}