{
  "type": "Feature",
  "properties": {
    "gn:admin1_code":"20",
    "gn:admin2_code":"2007.0",
    "gn:admin3_code":"200701.0",
    "gn:asciiname":"Planta Pozo",
    "gn:country_code":"PE",
    "gn:dem":68,
    "gn:feature_class":"P",
    "gn:feature_code":"PPL",
    "gn:name":"Planta Pozo",
    "gn:population":0,
    "gn:timezone":"America/Lima",
    "iso:country":"PE",
    "wof:name":"Planta Pozo",
    "wof:placetype":"locality"
},
  "geometry": {"coordinates":[-81.24278000000002,-4.60167],"type":"Point"}
}