{
  "type": "Feature",
  "properties": {
    "gn:admin1_code":"21",
    "gn:admin2_code":"2103.0",
    "gn:admin3_code":"210309.0",
    "gn:asciiname":"Casahuiri",
    "gn:country_code":"PE",
    "gn:dem":2359,
    "gn:feature_class":"P",
    "gn:feature_code":"PPL",
    "gn:name":"Casahuiri",
    "gn:population":0,
    "gn:timezone":"America/Lima",
    "iso:country":"PE",
    "wof:name":"Casahuiri",
    "wof:placetype":"locality"
},
  "geometry": {"coordinates":[-70.43333,-13.63333],"type":"Point"}
}