{
  "type": "Feature",
  "properties": {
    "gn:admin1_code":"20",
    "gn:admin2_code":"2002.0",
    "gn:admin3_code":"200206.0",
    "gn:asciiname":"Los Alisos",
    "gn:country_code":"PE",
    "gn:dem":2273,
    "gn:feature_class":"P",
    "gn:feature_code":"PPL",
    "gn:name":"Los Alisos",
    "gn:population":0,
    "gn:timezone":"America/Lima",
    "iso:country":"PE",
    "wof:name":"Los Alisos",
    "wof:placetype":"locality"
},
  "geometry": {"coordinates":[-79.51666999999998,-4.96667],"type":"Point"}
}