{
  "type": "Feature",
  "properties": {
    "gn:admin1_code":"05",
    "gn:admin2_code":"503.0",
    "gn:admin3_code":"50303.0",
    "gn:asciiname":"Occra",
    "gn:country_code":"PE",
    "gn:dem":3890,
    "gn:feature_class":"P",
    "gn:feature_code":"PPL",
    "gn:name":"Occra",
    "gn:population":0,
    "gn:timezone":"America/Lima",
    "iso:country":"PE",
    "wof:name":"Occra",
    "wof:placetype":"locality"
},
  "geometry": {"coordinates":[-74.26666999999998,-13.95],"type":"Point"}
}