{
  "type": "Feature",
  "properties": {
    "gn:admin1_code":"12",
    "gn:admin2_code":"1206.0",
    "gn:admin3_code":"120607.0",
    "gn:asciiname":"Villa Capiri",
    "gn:country_code":"PE",
    "gn:dem":736,
    "gn:feature_class":"P",
    "gn:feature_code":"PPL",
    "gn:name":"Villa Capiri",
    "gn:population":0,
    "gn:timezone":"America/Lima",
    "iso:country":"PE",
    "wof:name":"Villa Capiri",
    "wof:placetype":"locality"
},
  "geometry": {"coordinates":[-74.67334,-11.12967],"type":"Point"}
}