{
  "type": "Feature",
  "properties": {
    "gn:admin1_code":"2",
    "gn:admin2_code":"218.0",
    "gn:admin3_code":"21804.0",
    "gn:asciiname":"Lampi",
    "gn:country_code":"PE",
    "gn:dem":2674,
    "gn:feature_class":"P",
    "gn:feature_code":"PPL",
    "gn:name":"Lampi",
    "gn:population":0,
    "gn:timezone":"America/Lima",
    "iso:country":"PE",
    "name:deu_x_preferred":[
        "Lambi"
    ],
    "name:ell_x_preferred":[
        "\u0394\u03ae\u03bc\u03bf\u03c2 \u039b\u03ac\u03bc\u03c0\u03b7\u03c2"
    ],
    "name:fin_x_preferred":[
        "L\u00e1mpi"
    ],
    "name:ita_x_preferred":[
        "Lambi"
    ],
    "name:nno_x_preferred":[
        "L\u00e1mbi"
    ],
    "name:srp_x_preferred":[
        "\u041b\u0430\u043c\u043f\u0438"
    ],
    "wof:name":"Lampi",
    "wof:placetype":"locality"
},
  "geometry": {"coordinates":[-78.06194000000001,-8.76694],"type":"Point"}
}