{
  "type": "Feature",
  "properties": {
    "gn:admin1_code":"05",
    "gn:admin2_code":"507.0",
    "gn:admin3_code":"50701.0",
    "gn:asciiname":"Challhua",
    "gn:country_code":"PE",
    "gn:dem":4513,
    "gn:feature_class":"P",
    "gn:feature_code":"PPL",
    "gn:name":"Challhua",
    "gn:population":0,
    "gn:timezone":"America/Lima",
    "iso:country":"PE",
    "wof:name":"Challhua",
    "wof:placetype":"locality"
},
  "geometry": {"coordinates":[-73.78898000000002,-14.67712],"type":"Point"}
}