{
  "type": "Feature",
  "properties": {
    "gn:admin1_code":"06",
    "gn:admin2_code":"609.0",
    "gn:asciiname":"Campamento El Desague",
    "gn:country_code":"PE",
    "gn:dem":2829,
    "gn:feature_class":"P",
    "gn:feature_code":"PPL",
    "gn:name":"Campamento El Desague",
    "gn:population":0,
    "gn:timezone":"America/Lima",
    "iso:country":"PE",
    "wof:name":"Campamento El Desague",
    "wof:placetype":"locality"
},
  "geometry": {"coordinates":[-78.90278000000001,-4.79778],"type":"Point"}
}