{
  "type": "Feature",
  "properties": {
    "gn:admin1_code":"21",
    "gn:admin2_code":"2102.0",
    "gn:admin3_code":"210209.0",
    "gn:asciiname":"Otanani",
    "gn:country_code":"PE",
    "gn:dem":4409,
    "gn:feature_class":"P",
    "gn:feature_code":"PPL",
    "gn:name":"Ota\u00f1ani",
    "gn:population":0,
    "gn:timezone":"America/Lima",
    "iso:country":"PE",
    "wof:name":"Otanani",
    "wof:placetype":"locality"
},
  "geometry": {"coordinates":[-69.93553,-14.44819],"type":"Point"}
}