{
  "type": "Feature",
  "properties": {
    "gn:admin1_code":"04",
    "gn:admin2_code":"404.0",
    "gn:admin3_code":"40402.0",
    "gn:asciiname":"Latoma",
    "gn:country_code":"PE",
    "gn:dem":3663,
    "gn:feature_class":"P",
    "gn:feature_code":"PPL",
    "gn:name":"Latoma",
    "gn:population":0,
    "gn:timezone":"America/Lima",
    "iso:country":"PE",
    "wof:name":"Latoma",
    "wof:placetype":"locality"
},
  "geometry": {"coordinates":[-72.38914,-15.46558],"type":"Point"}
}