{
  "type": "Feature",
  "properties": {
    "gn:admin1_code":"14",
    "gn:admin2_code":"1403.0",
    "gn:admin3_code":"140312.0",
    "gn:asciiname":"Tabacal",
    "gn:country_code":"PE",
    "gn:dem":44,
    "gn:feature_class":"P",
    "gn:feature_code":"PPL",
    "gn:name":"Tabacal",
    "gn:population":0,
    "gn:timezone":"America/Lima",
    "iso:country":"PE",
    "wof:name":"Tabacal",
    "wof:placetype":"locality"
},
  "geometry": {"coordinates":[-79.88283,-6.49019],"type":"Point"}
}