{
  "type": "Feature",
  "properties": {
    "gn:gn_country":"PE",
    "gn:gn_fcode":"PPLA3",
    "gn:gn_pop":6865,
    "gn:population":6865,
    "iso:country":"PE",
    "name:cat_x_preferred":[
        "Ambo"
    ],
    "name:deu_x_preferred":[
        "Ambo"
    ],
    "name:eng_x_preferred":[
        "Ambo"
    ],
    "name:fas_x_preferred":[
        "\u0627\u0645\u0628\u0648\u060c \u067e\u0631\u0648"
    ],
    "name:fra_x_preferred":[
        "Ambo"
    ],
    "name:ita_x_preferred":[
        "Ambo"
    ],
    "name:nld_x_preferred":[
        "Ambo"
    ],
    "name:por_x_preferred":[
        "Ambo"
    ],
    "name:que_x_preferred":[
        "Ampuq"
    ],
    "name:spa_x_preferred":[
        "Ambo"
    ],
    "name:war_x_preferred":[
        "Ambo"
    ],
    "name:zho_x_preferred":[
        "\u5b89\u535a"
    ],
    "qs_pg:aaroncc":"PE",
    "qs_pg:gn_country":"PE",
    "qs_pg:gn_fcode":"PPLA3",
    "qs_pg:gn_pop":6865,
    "qs_pg:name":"Ambo",
    "qs_pg:photos_9r":0,
    "qs_pg:photos_sr":0,
    "qs_pg:pop_sr":5,
    "qs_pg:qs_pg_placetype":"locality",
    "wof:name":"Ambo",
    "wof:placetype":"locality",
    "wof:population":6865
},
  "geometry": {"coordinates":[-76.20471999999999,-10.13083],"type":"Point"}
}