{
  "type": "Feature",
  "properties": {
    "gn:admin1_code":"5.0",
    "gn:admin2_code":"505.0",
    "gn:admin3_code":"50501.0",
    "gn:asciiname":"Chaca",
    "gn:country_code":"PE",
    "gn:dem":2766,
    "gn:feature_class":"P",
    "gn:feature_code":"PPL",
    "gn:name":"Chaca",
    "gn:population":0,
    "gn:timezone":"America/Lima",
    "iso:country":"PE",
    "name:ceb_x_preferred":[
        "Chaca"
    ],
    "name:kor_x_preferred":[
        "\ucc28\uce74\uc18d"
    ],
    "name:swe_x_preferred":[
        "Chaca"
    ],
    "wof:name":"Chaca",
    "wof:placetype":"locality"
},
  "geometry": {"coordinates":[-73.98526,-12.97445],"type":"Point"}
}