{
  "type": "Feature",
  "properties": {
    "gn:admin1_code":"18",
    "gn:admin2_code":"1802.0",
    "gn:admin3_code":"180210.0",
    "gn:asciiname":"Paltuture",
    "gn:country_code":"PE",
    "gn:dem":3966,
    "gn:feature_class":"P",
    "gn:feature_code":"PPL",
    "gn:name":"Paltuture",
    "gn:population":0,
    "gn:timezone":"America/Lima",
    "iso:country":"PE",
    "wof:name":"Paltuture",
    "wof:placetype":"locality"
},
  "geometry": {"coordinates":[-70.67003000000003,-16.06563],"type":"Point"}
}