{
  "type": "Feature",
  "properties": {
    "gn:admin1_code":"15",
    "gn:admin2_code":"1510.0",
    "gn:admin3_code":"151006.0",
    "gn:asciiname":"Cruz",
    "gn:country_code":"PE",
    "gn:dem":2704,
    "gn:feature_class":"P",
    "gn:feature_code":"PPL",
    "gn:name":"Cruz",
    "gn:population":0,
    "gn:timezone":"America/Lima",
    "iso:country":"PE",
    "name:ces_x_preferred":[
        "Cruz"
    ],
    "name:deu_x_preferred":[
        "Cruz"
    ],
    "wof:name":"Cruz",
    "wof:placetype":"locality"
},
  "geometry": {"coordinates":[-75.83333,-12.85],"type":"Point"}
}