{
  "type": "Feature",
  "properties": {
    "gn:admin1_code":"06",
    "gn:admin2_code":"604.0",
    "gn:admin3_code":"60414.0",
    "gn:asciiname":"Pion",
    "gn:country_code":"PE",
    "gn:dem":1948,
    "gn:feature_class":"P",
    "gn:feature_code":"PPL",
    "gn:name":"Pi\u00f3n",
    "gn:population":0,
    "gn:timezone":"America/Lima",
    "iso:country":"PE",
    "name:und_x_variant":[
        "Pi\u00f3n"
    ],
    "wof:name":"Pion",
    "wof:placetype":"locality"
},
  "geometry": {"coordinates":[-78.48278000000001,-6.16222],"type":"Point"}
}