{
  "type": "Feature",
  "properties": {
    "gn:admin1_code":"06",
    "gn:admin2_code":"604.0",
    "gn:admin3_code":"60414.0",
    "gn:asciiname":"Pion",
    "gn:country_code":"PE",
    "gn:dem":1948,
    "gn:feature_class":"P",
    "gn:feature_code":"PPL",
    "gn:name":"Pi\u00f3n",
    "gn:population":0,
    "gn:timezone":"America/Lima",
    "iso:country":"PE",
    "name:afr_x_preferred":[
        "Pion"
    ],
    "name:ara_x_preferred":[
        "\u0628\u064a\u0648\u0646"
    ],
    "name:bel_x_preferred":[
        "\u041f\u0456-\u043c\u0435\u0437\u043e\u043d"
    ],
    "name:bre_x_preferred":[
        "Pion"
    ],
    "name:bul_x_preferred":[
        "\u041f\u0438\u043e\u043d"
    ],
    "name:cat_x_preferred":[
        "Pi\u00f3"
    ],
    "name:ces_x_preferred":[
        "Pion"
    ],
    "name:dan_x_preferred":[
        "Pion"
    ],
    "name:deu_x_preferred":[
        "Pion"
    ],
    "name:ell_x_preferred":[
        "\u03a0\u03b9\u03cc\u03bd\u03b9\u03bf"
    ],
    "name:epo_x_preferred":[
        "Piono"
    ],
    "name:est_x_preferred":[
        "Piion"
    ],
    "name:eus_x_preferred":[
        "Pioi"
    ],
    "name:fas_x_preferred":[
        "\u067e\u06cc\u0648\u0646"
    ],
    "name:fin_x_preferred":[
        "Pioni"
    ],
    "name:fra_x_preferred":[
        "Pion"
    ],
    "name:gle_x_preferred":[
        "Pi\u00f3n"
    ],
    "name:heb_x_preferred":[
        "\u05e4\u05d0\u05d9\u05d5\u05df"
    ],
    "name:hin_x_preferred":[
        "\u092a\u093e\u0907\u0906\u0928"
    ],
    "name:hrv_x_preferred":[
        "Pion"
    ],
    "name:hun_x_preferred":[
        "Pion"
    ],
    "name:hye_x_preferred":[
        "\u054a\u056b\u0578\u0576\u0576\u0565\u0580"
    ],
    "name:ind_x_preferred":[
        "Pion"
    ],
    "name:ita_x_preferred":[
        "Pione"
    ],
    "name:jpn_x_preferred":[
        "\u30d1\u30a4\u4e2d\u9593\u5b50"
    ],
    "name:kat_x_preferred":[
        "\u10de\u10d8-\u10db\u10d4\u10d6\u10dd\u10dc\u10d4\u10d1\u10d8"
    ],
    "name:kaz_x_preferred":[
        "\u041f\u0438\u043e\u043d"
    ],
    "name:kor_x_preferred":[
        "\ud30c\uc774 \uc911\uac04\uc790"
    ],
    "name:lav_x_preferred":[
        "Pions"
    ],
    "name:lit_x_preferred":[
        "Pionas"
    ],
    "name:mkd_x_preferred":[
        "\u041f\u0438\u043e\u043d"
    ],
    "name:nld_x_preferred":[
        "Pion"
    ],
    "name:nno_x_preferred":[
        "Pion"
    ],
    "name:nor_x_preferred":[
        "Pion"
    ],
    "name:pnb_x_preferred":[
        "\u067e\u06cc\u0648\u0646"
    ],
    "name:pol_x_preferred":[
        "Pion"
    ],
    "name:por_x_preferred":[
        "P\u00edon"
    ],
    "name:ron_x_preferred":[
        "Pion"
    ],
    "name:rus_x_preferred":[
        "\u041f\u0438\u043e\u043d"
    ],
    "name:sco_x_preferred":[
        "Pion"
    ],
    "name:slk_x_preferred":[
        "Pi\u00f3n"
    ],
    "name:slv_x_preferred":[
        "Pion"
    ],
    "name:spa_x_preferred":[
        "Pion"
    ],
    "name:swe_x_preferred":[
        "Pimeson"
    ],
    "name:tgl_x_preferred":[
        "Pion"
    ],
    "name:tur_x_preferred":[
        "Pion"
    ],
    "name:ukr_x_preferred":[
        "\u041f\u0456\u043e\u043d\u0438"
    ],
    "name:und_x_variant":[
        "Pi\u00f3n"
    ],
    "wof:name":"Pion",
    "wof:placetype":"locality"
},
  "geometry": {"coordinates":[-78.48278000000001,-6.16222],"type":"Point"}
}