{
  "type": "Feature",
  "properties": {
    "gn:admin1_code":"10.0",
    "gn:admin2_code":"1001.0",
    "gn:admin3_code":"100105.0",
    "gn:asciiname":"Culcush",
    "gn:country_code":"PE",
    "gn:dem":3759,
    "gn:feature_class":"P",
    "gn:feature_code":"PPL",
    "gn:name":"Culcush",
    "gn:population":0,
    "gn:timezone":"America/Lima",
    "iso:country":"PE",
    "wof:name":"Culcush",
    "wof:placetype":"locality"
},
  "geometry": {"coordinates":[-76.53389,-10.02861],"type":"Point"}
}