{
  "type": "Feature",
  "properties": {
    "gn:admin1_code":"17.0",
    "gn:admin2_code":"1703.0",
    "gn:asciiname":"Vivero",
    "gn:country_code":"PE",
    "gn:dem":275,
    "gn:feature_class":"P",
    "gn:feature_code":"PPL",
    "gn:name":"Vivero",
    "gn:population":0,
    "gn:timezone":"America/Lima",
    "iso:country":"PE",
    "name:spa_x_preferred":[
        "Vivero"
    ],
    "wof:name":"Vivero",
    "wof:placetype":"locality"
},
  "geometry": {"coordinates":[-69.40105,-11.41253],"type":"Point"}
}