{
  "type": "Feature",
  "properties": {
    "gn:admin1_code":"10.0",
    "gn:admin2_code":"1005.0",
    "gn:asciiname":"Querobamba",
    "gn:country_code":"PE",
    "gn:dem":3259,
    "gn:feature_class":"P",
    "gn:feature_code":"PPL",
    "gn:name":"Querobamba",
    "gn:population":0,
    "gn:timezone":"America/Lima",
    "iso:country":"PE",
    "wof:name":"Querobamba",
    "wof:placetype":"locality"
},
  "geometry": {"coordinates":[-76.74153000000003,-9.17763],"type":"Point"}
}