{
  "type": "Feature",
  "properties": {
    "gn:admin1_code":"16",
    "gn:admin2_code":"1605.0",
    "gn:admin3_code":"160507.0",
    "gn:asciiname":"Capitan Clavero",
    "gn:country_code":"PE",
    "gn:dem":97,
    "gn:feature_class":"P",
    "gn:feature_code":"PPL",
    "gn:name":"Capit\u00e1n Clavero",
    "gn:population":0,
    "gn:timezone":"America/Lima",
    "iso:country":"PE",
    "wof:name":"Capitan Clavero",
    "wof:placetype":"locality"
},
  "geometry": {"coordinates":[-73.56798000000001,-4.66111],"type":"Point"}
}