{
  "type": "Feature",
  "properties": {
    "gn:admin1_code":"09",
    "gn:admin2_code":"906.0",
    "gn:admin3_code":"90602.0",
    "gn:asciiname":"Caquiani",
    "gn:country_code":"PE",
    "gn:dem":1360,
    "gn:feature_class":"P",
    "gn:feature_code":"PPL",
    "gn:name":"Caquiani",
    "gn:population":0,
    "gn:timezone":"America/Lima",
    "iso:country":"PE",
    "wof:name":"Caquiani",
    "wof:placetype":"locality"
},
  "geometry": {"coordinates":[-75.48166999999999,-13.8025],"type":"Point"}
}