{
  "type": "Feature",
  "properties": {
    "gn:admin1_code":"8.0",
    "gn:admin2_code":"803.0",
    "gn:admin3_code":"80306.0",
    "gn:asciiname":"Pumaorjo",
    "gn:country_code":"PE",
    "gn:dem":3044,
    "gn:feature_class":"P",
    "gn:feature_code":"PPL",
    "gn:name":"Pumaorjo",
    "gn:population":0,
    "gn:timezone":"America/Lima",
    "iso:country":"PE",
    "wof:name":"Pumaorjo",
    "wof:placetype":"locality"
},
  "geometry": {"coordinates":[-72.42610999999999,-13.45278],"type":"Point"}
}