{
  "type": "Feature",
  "properties": {
    "gn:admin1_code":"03",
    "gn:admin2_code":"305.0",
    "gn:admin3_code":"30502.0",
    "gn:asciiname":"Gentegente",
    "gn:cc2":"PE",
    "gn:country_code":"PE",
    "gn:dem":2485,
    "gn:feature_class":"P",
    "gn:feature_code":"PPL",
    "gn:name":"Gentegente",
    "gn:population":0,
    "gn:timezone":"America/Lima",
    "iso:country":"PE",
    "name:und_x_variant":[
        "Gentegente Hacienda",
        "Gentegente"
    ],
    "wof:name":"Gentegente",
    "wof:placetype":"locality"
},
  "geometry": {"coordinates":[-72.31667,-13.71667],"type":"Point"}
}