{
  "type": "Feature",
  "properties": {
    "gn:admin1_code":"21",
    "gn:admin2_code":"2107.0",
    "gn:admin3_code":"210706.0",
    "gn:asciiname":"Suteca",
    "gn:country_code":"PE",
    "gn:dem":4075,
    "gn:feature_class":"P",
    "gn:feature_code":"PPL",
    "gn:name":"Suteca",
    "gn:population":0,
    "gn:timezone":"America/Lima",
    "iso:country":"PE",
    "wof:name":"Suteca",
    "wof:placetype":"locality"
},
  "geometry": {"coordinates":[-70.57111,-15.24583],"type":"Point"}
}