{
  "type": "Feature",
  "properties": {
    "gn:admin1_code":"15",
    "gn:admin2_code":"1510.0",
    "gn:admin3_code":"151001.0",
    "gn:asciiname":"Nahuinpuquio",
    "gn:country_code":"PE",
    "gn:dem":3320,
    "gn:feature_class":"P",
    "gn:feature_code":"PPL",
    "gn:name":"\u00d1ahuinpuquio",
    "gn:population":0,
    "gn:timezone":"America/Lima",
    "iso:country":"PE",
    "wof:name":"Nahuinpuquio",
    "wof:placetype":"locality"
},
  "geometry": {"coordinates":[-75.88444,-12.43472],"type":"Point"}
}