{
  "type": "Feature",
  "properties": {
    "gn:country":"PE",
    "gn:fcode":"PPLA3",
    "gn:population":8553,
    "iso:country":"PE",
    "name:ast_x_preferred":[
        "Huancabamba"
    ],
    "name:ceb_x_preferred":[
        "Huancabamba"
    ],
    "name:ces_x_preferred":[
        "Huancabamba"
    ],
    "name:deu_x_preferred":[
        "Huancabamba"
    ],
    "name:eng_x_preferred":[
        "Huancabamba"
    ],
    "name:fas_x_preferred":[
        "\u0627\u0648\u0626\u0627\u0646\u06a9\u0627\u0628\u0627\u0645\u0628\u0627"
    ],
    "name:fra_x_preferred":[
        "Huancabamba"
    ],
    "name:heb_x_preferred":[
        "\u05d5\u05d0\u05e0\u05e7\u05d0\u05d1\u05de\u05d1\u05d4"
    ],
    "name:ita_x_preferred":[
        "Huancabamba"
    ],
    "name:nld_x_preferred":[
        "Huancabamba"
    ],
    "name:por_x_preferred":[
        "Huancabamba"
    ],
    "name:que_x_preferred":[
        "Wankapampa"
    ],
    "name:rus_x_preferred":[
        "\u0423\u0430\u043d\u043a\u0430\u0431\u0430\u043c\u0431\u0430"
    ],
    "name:spa_x_preferred":[
        "Huancabamba"
    ],
    "name:war_x_preferred":[
        "Huancabamba"
    ],
    "name:zho_x_preferred":[
        "\u5b9b\u5361\u73ed\u5df4"
    ],
    "qs:name":"Huancabamba",
    "qs:photos_9r":0,
    "qs:photos_sr":0,
    "qs:pop_sr":"5",
    "wd:elevation":1929.0,
    "wd:wordcount":74,
    "wof:name":"Huancabamba",
    "wof:placetype":"locality",
    "wof:population":8553
},
  "geometry": {"coordinates":[-79.45056,-5.23861],"type":"Point"}
}