{
  "type": "Feature",
  "properties": {
    "gn:admin1_code":"03",
    "gn:admin2_code":"306.0",
    "gn:admin3_code":"30601.0",
    "gn:asciiname":"Pumaranra",
    "gn:country_code":"PE",
    "gn:dem":3486,
    "gn:feature_class":"P",
    "gn:feature_code":"PPL",
    "gn:name":"Pumaranra",
    "gn:population":0,
    "gn:timezone":"America/Lima",
    "iso:country":"PE",
    "wof:name":"Pumaranra",
    "wof:placetype":"locality"
},
  "geometry": {"coordinates":[-73.75,-13.56667],"type":"Point"}
}