{
  "type": "Feature",
  "properties": {
    "gn:admin1_code":"05",
    "gn:admin2_code":"506.0",
    "gn:admin3_code":"50619.0",
    "gn:asciiname":"Chaquidanda",
    "gn:country_code":"PE",
    "gn:dem":3503,
    "gn:feature_class":"P",
    "gn:feature_code":"PPL",
    "gn:name":"Chaquidanda",
    "gn:population":0,
    "gn:timezone":"America/Lima",
    "iso:country":"PE",
    "name:spa_x_preferred":[
        "Chaquidanda"
    ],
    "name:spa_x_variant":[
        "Chaquipampa"
    ],
    "wof:name":"Chaquidanda",
    "wof:placetype":"locality"
},
  "geometry": {"coordinates":[-73.98662,-15.00164],"type":"Point"}
}