{
  "type": "Feature",
  "properties": {
    "gn:admin1_code":"12.0",
    "gn:admin2_code":"1208.0",
    "gn:admin3_code":"120807.0",
    "gn:asciiname":"Pillococha",
    "gn:country_code":"PE",
    "gn:dem":4742,
    "gn:feature_class":"P",
    "gn:feature_code":"PPL",
    "gn:name":"Pillococha",
    "gn:population":0,
    "gn:timezone":"America/Lima",
    "iso:country":"PE",
    "wof:name":"Pillococha",
    "wof:placetype":"locality"
},
  "geometry": {"coordinates":[-76.47484,-11.12347],"type":"Point"}
}