{
  "type": "Feature",
  "properties": {
    "gn:admin1_code":"05",
    "gn:admin2_code":"506.0",
    "gn:admin3_code":"50604.0",
    "gn:asciiname":"Mayobamba",
    "gn:country_code":"PE",
    "gn:dem":3188,
    "gn:feature_class":"P",
    "gn:feature_code":"PPL",
    "gn:name":"Mayobamba",
    "gn:population":0,
    "gn:timezone":"America/Lima",
    "iso:country":"PE",
    "name:und_x_variant":[
        "Moyobamba",
        "Mayobamba"
    ],
    "wof:name":"Mayobamba",
    "wof:placetype":"locality"
},
  "geometry": {"coordinates":[-73.89194000000001,-14.37583],"type":"Point"}
}