{
  "type": "Feature",
  "properties": {
    "gn:admin1_code":"05",
    "gn:admin2_code":"505.0",
    "gn:admin3_code":"50506.0",
    "gn:asciiname":"Comespucro",
    "gn:country_code":"PE",
    "gn:dem":2936,
    "gn:feature_class":"P",
    "gn:feature_code":"PPL",
    "gn:name":"Comespucro",
    "gn:population":0,
    "gn:timezone":"America/Lima",
    "iso:country":"PE",
    "name:und_x_variant":[
        "Comesprucro",
        "Comespucro"
    ],
    "wof:name":"Comespucro",
    "wof:placetype":"locality"
},
  "geometry": {"coordinates":[-73.84139,-13.30556],"type":"Point"}
}