{
  "type": "Feature",
  "properties": {
    "gn:admin1_code":"06",
    "gn:admin2_code":"603.0",
    "gn:admin3_code":"60304.0",
    "gn:asciiname":"Hacienda Jerez",
    "gn:country_code":"PE",
    "gn:dem":2686,
    "gn:feature_class":"P",
    "gn:feature_code":"PPL",
    "gn:name":"Hacienda Jerez",
    "gn:population":0,
    "gn:timezone":"America/Lima",
    "iso:country":"PE",
    "name:und_x_variant":[
        "Jerez",
        "Jer\u00e9s",
        "Jerez Hacienda",
        "Hacienda Jerez"
    ],
    "wof:name":"Hacienda Jerez",
    "wof:placetype":"locality"
},
  "geometry": {"coordinates":[-78.29345000000001,-6.79753],"type":"Point"}
}