{
  "type": "Feature",
  "properties": {
    "gn:admin1_code":"14.0",
    "gn:admin2_code":"1402.0",
    "gn:admin3_code":"140205.0",
    "gn:asciiname":"Canu",
    "gn:country_code":"PE",
    "gn:dem":46,
    "gn:feature_class":"P",
    "gn:feature_code":"PPL",
    "gn:name":"Canu",
    "gn:population":0,
    "gn:timezone":"America/Lima",
    "iso:country":"PE",
    "name:spa_x_preferred":[
        "Canu"
    ],
    "wof:name":"Canu",
    "wof:placetype":"locality"
},
  "geometry": {"coordinates":[-79.78447,-6.57431],"type":"Point"}
}