{
  "type": "Feature",
  "properties": {
    "gn:admin1_code":"13.0",
    "gn:admin2_code":"1308.0",
    "gn:admin3_code":"130802.0",
    "gn:asciiname":"La Rangra",
    "gn:country_code":"PE",
    "gn:dem":3486,
    "gn:feature_class":"P",
    "gn:feature_code":"PPL",
    "gn:name":"La Rangra",
    "gn:population":0,
    "gn:timezone":"America/Lima",
    "iso:country":"PE",
    "wof:name":"La Rangra",
    "wof:placetype":"locality"
},
  "geometry": {"coordinates":[-77.41417,-8.12083],"type":"Point"}
}