{
  "type": "Feature",
  "properties": {
    "gn:admin1_code":"12",
    "gn:admin2_code":"1207.0",
    "gn:admin3_code":"120706.0",
    "gn:asciiname":"Palca",
    "gn:country_code":"PE",
    "gn:dem":2738,
    "gn:feature_class":"P",
    "gn:feature_code":"PPLA3",
    "gn:name":"Palca",
    "gn:population":0,
    "gn:timezone":"America/Lima",
    "iso:country":"PE",
    "wof:name":"Palca",
    "wof:placetype":"locality"
},
  "geometry": {"coordinates":[-75.56860999999998,-11.34611],"type":"Point"}
}