{
  "type": "Feature",
  "properties": {
    "gn:admin1_code":"04",
    "gn:admin2_code":"403.0",
    "gn:admin3_code":"40312.0",
    "gn:asciiname":"Media Noche",
    "gn:country_code":"PE",
    "gn:dem":1608,
    "gn:feature_class":"P",
    "gn:feature_code":"PPL",
    "gn:name":"Media Noche",
    "gn:population":0,
    "gn:timezone":"America/Lima",
    "iso:country":"PE",
    "wof:name":"Media Noche",
    "wof:placetype":"locality"
},
  "geometry": {"coordinates":[-73.81090999999998,-15.67115],"type":"Point"}
}