{
  "type": "Feature",
  "properties": {
    "gn:admin1_code":"11",
    "gn:admin2_code":"1102.0",
    "gn:admin3_code":"110208.0",
    "gn:asciiname":"Santuario",
    "gn:country_code":"PE",
    "gn:dem":3194,
    "gn:feature_class":"P",
    "gn:feature_code":"PPL",
    "gn:name":"Santuario",
    "gn:population":0,
    "gn:timezone":"America/Lima",
    "iso:country":"PE",
    "name:spa_x_preferred":[
        "Santuario"
    ],
    "wof:name":"Santuario",
    "wof:placetype":"locality"
},
  "geometry": {"coordinates":[-75.73267,-13.26967],"type":"Point"}
}