{
  "type": "Feature",
  "properties": {
    "gn:admin1_code":"9.0",
    "gn:admin2_code":"907.0",
    "gn:admin3_code":"90705.0",
    "gn:asciiname":"Palca",
    "gn:country_code":"PE",
    "gn:dem":2927,
    "gn:feature_class":"P",
    "gn:feature_code":"PPL",
    "gn:name":"Palca",
    "gn:population":0,
    "gn:timezone":"America/Lima",
    "iso:country":"PE",
    "wof:name":"Palca",
    "wof:placetype":"locality"
},
  "geometry": {"coordinates":[-74.60805999999999,-12.31647],"type":"Point"}
}