{
  "type": "Feature",
  "properties": {
    "gn:admin1_code":"13",
    "gn:admin2_code":"1302.0",
    "gn:admin3_code":"130206.0",
    "gn:asciiname":"Macabi Alto",
    "gn:country_code":"PE",
    "gn:dem":32,
    "gn:feature_class":"P",
    "gn:feature_code":"PPL",
    "gn:name":"Macab\u00ed Alto",
    "gn:population":0,
    "gn:timezone":"America/Lima",
    "iso:country":"PE",
    "name:und_x_variant":[
        "Hacienda Macabi",
        "Macabi",
        "Macabi Hacienda",
        "Macab\u00ed Alto"
    ],
    "wof:name":"Macabi Alto",
    "wof:placetype":"locality"
},
  "geometry": {"coordinates":[-79.36946,-7.71565],"type":"Point"}
}