{
  "type": "Feature",
  "properties": {
    "gn:admin1_code":"20",
    "gn:admin2_code":"2004.0",
    "gn:admin3_code":"200409.0",
    "gn:asciiname":"Chanchas",
    "gn:country_code":"PE",
    "gn:dem":1596,
    "gn:feature_class":"P",
    "gn:feature_code":"PPL",
    "gn:name":"Chanchas",
    "gn:population":0,
    "gn:timezone":"America/Lima",
    "iso:country":"PE",
    "name:und_x_variant":[
        "Chancha",
        "Chanchas"
    ],
    "wof:name":"Chanchas",
    "wof:placetype":"locality"
},
  "geometry": {"coordinates":[-79.89183,-5.03187],"type":"Point"}
}