{
  "type": "Feature",
  "properties": {
    "gn:admin1_code":"23.0",
    "gn:admin2_code":"2304.0",
    "gn:admin3_code":"230401.0",
    "gn:asciiname":"Jachacahua",
    "gn:country_code":"PE",
    "gn:dem":4151,
    "gn:feature_class":"P",
    "gn:feature_code":"PPL",
    "gn:name":"Jachacahua",
    "gn:population":0,
    "gn:timezone":"America/Lima",
    "iso:country":"PE",
    "wof:name":"Jachacahua",
    "wof:placetype":"locality"
},
  "geometry": {"coordinates":[-69.47471999999999,-17.43806],"type":"Point"}
}