{
  "type": "Feature",
  "properties": {
    "gn:admin1_code":"21",
    "gn:admin2_code":"2103.0",
    "gn:admin3_code":"210309.0",
    "gn:asciiname":"Chiripampa",
    "gn:country_code":"PE",
    "gn:dem":1117,
    "gn:feature_class":"P",
    "gn:feature_code":"PPL",
    "gn:name":"Chiripampa",
    "gn:population":0,
    "gn:timezone":"America/Lima",
    "iso:country":"PE",
    "wof:name":"Chiripampa",
    "wof:placetype":"locality"
},
  "geometry": {"coordinates":[-70.28333000000001,-13.45],"type":"Point"}
}