{
  "type": "Feature",
  "properties": {
    "gn:admin1_code":"10",
    "gn:admin2_code":"1007.0",
    "gn:admin3_code":"100702.0",
    "gn:asciiname":"Achiras",
    "gn:country_code":"PE",
    "gn:dem":2095,
    "gn:feature_class":"P",
    "gn:feature_code":"PPL",
    "gn:name":"Achiras",
    "gn:population":0,
    "gn:timezone":"America/Lima",
    "iso:country":"PE",
    "wof:name":"Achiras",
    "wof:placetype":"locality"
},
  "geometry": {"coordinates":[-76.53333000000001,-8.65],"type":"Point"}
}