{
  "type": "Feature",
  "properties": {
    "gn:admin1_code":"23",
    "gn:admin2_code":"2301.0",
    "gn:admin3_code":"230107.0",
    "gn:asciiname":"Chachacomani",
    "gn:country_code":"PE",
    "gn:dem":4012,
    "gn:feature_class":"P",
    "gn:feature_code":"PPLL",
    "gn:name":"Chachacomani",
    "gn:population":0,
    "gn:timezone":"America/Lima",
    "iso:country":"PE",
    "wof:name":"Chachacomani",
    "wof:placetype":"locality"
},
  "geometry": {"coordinates":[-69.91194,-17.68306],"type":"Point"}
}