{
  "type": "Feature",
  "properties": {
    "gn:admin1_code":"23",
    "gn:admin2_code":"2301.0",
    "gn:admin3_code":"230107.0",
    "gn:asciiname":"Chachacomani",
    "gn:country_code":"PE",
    "gn:dem":4012,
    "gn:feature_class":"P",
    "gn:feature_code":"PPLL",
    "gn:name":"Chachacomani",
    "gn:population":0,
    "gn:timezone":"America/Lima",
    "iso:country":"PE",
    "name:aym_x_preferred":[
        "Chachakumani"
    ],
    "name:deu_x_preferred":[
        "Chachacomani"
    ],
    "name:ita_x_preferred":[
        "Chachacomani"
    ],
    "name:kat_x_preferred":[
        "\u10e9\u10d0\u10e9\u10d0\u10d9\u10dd\u10db\u10d0\u10dc\u10d8"
    ],
    "name:lit_x_preferred":[
        "\u010ca\u010dakomanis"
    ],
    "name:por_x_preferred":[
        "Chachacomani"
    ],
    "name:que_x_preferred":[
        "Chachakumani"
    ],
    "name:rus_x_preferred":[
        "\u0427\u0430\u0447\u0430\u043a\u0443\u043c\u0430\u043d\u0438"
    ],
    "name:spa_x_preferred":[
        "Chachacomani"
    ],
    "name:swa_x_preferred":[
        "Chachacomani"
    ],
    "name:zho_x_preferred":[
        "\u67e5\u67e5\u79d1\u99ac\u5c3c\u5c71"
    ],
    "wof:name":"Chachacomani",
    "wof:placetype":"locality"
},
  "geometry": {"coordinates":[-69.91194,-17.68306],"type":"Point"}
}