{
  "type": "Feature",
  "properties": {
    "gn:admin1_code":"20",
    "gn:admin2_code":"2004.0",
    "gn:admin3_code":"200402.0",
    "gn:asciiname":"Chihuahua",
    "gn:country_code":"PE",
    "gn:dem":124,
    "gn:feature_class":"P",
    "gn:feature_code":"PPL",
    "gn:name":"Chihuahua",
    "gn:population":0,
    "gn:timezone":"America/Lima",
    "iso:country":"PE",
    "name:afr_x_preferred":[
        "Chihuahua"
    ],
    "name:ara_x_preferred":[
        "\u0634\u064a\u0648\u0627\u0648\u0627"
    ],
    "name:bar_x_preferred":[
        "Chihuahua"
    ],
    "name:bre_x_preferred":[
        "Chihuahua"
    ],
    "name:cat_x_preferred":[
        "Chihuahua"
    ],
    "name:ceb_x_preferred":[
        "Chihuahua"
    ],
    "name:ces_x_preferred":[
        "Chihuahua"
    ],
    "name:cym_x_preferred":[
        "Chihuahua"
    ],
    "name:dan_x_preferred":[
        "Chihuahua"
    ],
    "name:deu_x_preferred":[
        "Chihuahua"
    ],
    "name:epo_x_preferred":[
        "Chihuahua"
    ],
    "name:eus_x_preferred":[
        "Chihuahua"
    ],
    "name:fas_x_preferred":[
        "\u0686\u06cc\u200c\u0648\u0627\u0648\u0627"
    ],
    "name:fin_x_preferred":[
        "Chihuahua"
    ],
    "name:fra_x_preferred":[
        "Chihuahua"
    ],
    "name:glg_x_preferred":[
        "Chihuahua"
    ],
    "name:heb_x_preferred":[
        "\u05e6'\u05d9\u05d5\u05d5\u05d0\u05d5\u05d5\u05d4"
    ],
    "name:hrv_x_preferred":[
        "Chihuahua"
    ],
    "name:hun_x_preferred":[
        "Chihuahua"
    ],
    "name:ind_x_preferred":[
        "Chihuahua"
    ],
    "name:ita_x_preferred":[
        "Chihuahua"
    ],
    "name:jpn_x_preferred":[
        "\u30c1\u30ef\u30ef"
    ],
    "name:kat_x_preferred":[
        "\u10e9\u10d8\u10e3\u10d0\u10e3\u10d0"
    ],
    "name:kor_x_preferred":[
        "\uce58\uc640\uc640"
    ],
    "name:lit_x_preferred":[
        "\u010cihuahua"
    ],
    "name:mzn_x_preferred":[
        "\u0686\u06cc\u0626\u0648\u0627\u0626\u0648\u0627 \u0627\u06cc\u0627\u0644\u062a"
    ],
    "name:nds_x_preferred":[
        "Chihuahua"
    ],
    "name:nld_x_preferred":[
        "Chihuahua"
    ],
    "name:nor_x_preferred":[
        "Chihuahua"
    ],
    "name:oci_x_preferred":[
        "Chihuahua"
    ],
    "name:pol_x_preferred":[
        "Chihuahua"
    ],
    "name:por_x_preferred":[
        "Chihuahua"
    ],
    "name:ron_x_preferred":[
        "Chihuahua"
    ],
    "name:rus_x_preferred":[
        "\u0427\u0438\u0443\u0430\u0443\u0430"
    ],
    "name:sco_x_preferred":[
        "Chihuahua"
    ],
    "name:slk_x_preferred":[
        "Chihuahua"
    ],
    "name:slv_x_preferred":[
        "Chihuahua"
    ],
    "name:spa_x_preferred":[
        "Chihuahua"
    ],
    "name:srp_x_preferred":[
        "\u0427\u0438\u0432\u0430\u0432\u0430"
    ],
    "name:swa_x_preferred":[
        "Chihuahua"
    ],
    "name:swe_x_preferred":[
        "Chihuahua"
    ],
    "name:szl_x_preferred":[
        "Chihuahua"
    ],
    "name:tgl_x_preferred":[
        "Chihuahua"
    ],
    "name:tur_x_preferred":[
        "Chihuahua"
    ],
    "name:ukr_x_preferred":[
        "\u0427\u0456\u0443\u0430\u0443\u0430"
    ],
    "name:vie_x_preferred":[
        "Chihuahua"
    ],
    "name:zho_x_preferred":[
        "\u5947\u74e6\u74e6"
    ],
    "wof:name":"Chihuahua",
    "wof:placetype":"locality"
},
  "geometry": {"coordinates":[-79.99868000000002,-5.22955],"type":"Point"}
}