{
  "type": "Feature",
  "properties": {
    "gn:admin1_code":"05",
    "gn:admin2_code":"511.0",
    "gn:admin3_code":"51108.0",
    "gn:asciiname":"Ccatunpampa",
    "gn:country_code":"PE",
    "gn:dem":3864,
    "gn:feature_class":"P",
    "gn:feature_code":"PPL",
    "gn:name":"Ccatunpampa",
    "gn:population":0,
    "gn:timezone":"America/Lima",
    "iso:country":"PE",
    "wof:name":"Ccatunpampa",
    "wof:placetype":"locality"
},
  "geometry": {"coordinates":[-73.94326,-13.59456],"type":"Point"}
}