{
  "type": "Feature",
  "properties": {
    "gn:admin1_code":"13.0",
    "gn:admin2_code":"1308.0",
    "gn:admin3_code":"130804.0",
    "gn:asciiname":"Huanchil",
    "gn:country_code":"PE",
    "gn:dem":3035,
    "gn:feature_class":"P",
    "gn:feature_code":"PPL",
    "gn:name":"Huanchil",
    "gn:population":0,
    "gn:timezone":"America/Lima",
    "iso:country":"PE",
    "wof:name":"Huanchil",
    "wof:placetype":"locality"
},
  "geometry": {"coordinates":[-77.28763000000002,-8.44148],"type":"Point"}
}