{
  "type": "Feature",
  "properties": {
    "gn:admin1_code":"4",
    "gn:admin2_code":"405.0",
    "gn:admin3_code":"40519.0",
    "gn:asciiname":"Huisca Orco",
    "gn:country_code":"PE",
    "gn:dem":4324,
    "gn:feature_class":"P",
    "gn:feature_code":"PPL",
    "gn:name":"Huisca Orco",
    "gn:population":0,
    "gn:timezone":"America/Lima",
    "iso:country":"PE",
    "wof:name":"Huisca Orco",
    "wof:placetype":"locality"
},
  "geometry": {"coordinates":[-71.34595,-15.74276],"type":"Point"}
}