{
  "type": "Feature",
  "properties": {
    "gn:admin1_code":"21",
    "gn:admin2_code":"2105.0",
    "gn:admin3_code":"210503.0",
    "gn:asciiname":"Maquera",
    "gn:country_code":"PE",
    "gn:dem":3860,
    "gn:feature_class":"P",
    "gn:feature_code":"PPL",
    "gn:name":"Maquera",
    "gn:population":0,
    "gn:timezone":"America/Lima",
    "iso:country":"PE",
    "wof:name":"Maquera",
    "wof:placetype":"locality"
},
  "geometry": {"coordinates":[-69.55179,-16.17024],"type":"Point"}
}