{
  "type": "Feature",
  "properties": {
    "gn:admin1_code":"9.0",
    "gn:admin2_code":"901.0",
    "gn:admin3_code":"90119.0",
    "gn:asciiname":"Churcosca",
    "gn:country_code":"PE",
    "gn:dem":4160,
    "gn:feature_class":"P",
    "gn:feature_code":"PPL",
    "gn:name":"Churcosca",
    "gn:population":0,
    "gn:timezone":"America/Lima",
    "iso:country":"PE",
    "wof:name":"Churcosca",
    "wof:placetype":"locality"
},
  "geometry": {"coordinates":[-74.99478000000001,-12.6101],"type":"Point"}
}