{
  "type": "Feature",
  "properties": {
    "gn:admin1_code":"8",
    "gn:admin2_code":"806.0",
    "gn:admin3_code":"80608.0",
    "gn:asciiname":"Cruzmoco",
    "gn:country_code":"PE",
    "gn:dem":3515,
    "gn:feature_class":"P",
    "gn:feature_code":"PPL",
    "gn:name":"Cruzmoco",
    "gn:population":0,
    "gn:timezone":"America/Lima",
    "iso:country":"PE",
    "wof:name":"Cruzmoco",
    "wof:placetype":"locality"
},
  "geometry": {"coordinates":[-71.37586999999998,-14.14807],"type":"Point"}
}