{
  "type": "Feature",
  "properties": {
    "gn:admin1_code":"8",
    "gn:admin2_code":"809.0",
    "gn:admin3_code":"80902.0",
    "gn:asciiname":"Alto Cirialo",
    "gn:country_code":"PE",
    "gn:dem":1591,
    "gn:feature_class":"P",
    "gn:feature_code":"PPL",
    "gn:name":"Alto Cirialo",
    "gn:population":0,
    "gn:timezone":"America/Lima",
    "iso:country":"PE",
    "wof:name":"Alto Cirialo",
    "wof:placetype":"locality"
},
  "geometry": {"coordinates":[-72.92784,-12.75735],"type":"Point"}
}