{
  "type": "Feature",
  "properties": {
    "gn:admin1_code":"09",
    "gn:admin2_code":"906.0",
    "gn:admin3_code":"90607.0",
    "gn:asciiname":"Ninacha",
    "gn:country_code":"PE",
    "gn:dem":4324,
    "gn:feature_class":"P",
    "gn:feature_code":"PPL",
    "gn:name":"Ni\u00f1acha",
    "gn:population":0,
    "gn:timezone":"America/Lima",
    "iso:country":"PE",
    "wof:name":"Ninacha",
    "wof:placetype":"locality"
},
  "geometry": {"coordinates":[-74.68333,-13.35],"type":"Point"}
}