{
  "type": "Feature",
  "properties": {
    "gn:admin1_code":"10.0",
    "gn:admin2_code":"1009.0",
    "gn:admin3_code":"100905.0",
    "gn:asciiname":"Yuyapichis",
    "gn:country_code":"PE",
    "gn:dem":216,
    "gn:feature_class":"P",
    "gn:feature_code":"PPLA3",
    "gn:name":"Yuyapichis",
    "gn:population":0,
    "gn:timezone":"America/Lima",
    "iso:country":"PE",
    "wof:name":"Yuyapichis",
    "wof:placetype":"locality"
},
  "geometry": {"coordinates":[-74.97658,-9.62732],"type":"Point"}
}