{
  "type": "Feature",
  "properties": {
    "gn:admin1_code":"04",
    "gn:admin2_code":"406.0",
    "gn:admin3_code":"40607.0",
    "gn:asciiname":"Purhua-Purhua",
    "gn:country_code":"PE",
    "gn:dem":4408,
    "gn:feature_class":"P",
    "gn:feature_code":"PPL",
    "gn:name":"Purhua-Purhua",
    "gn:population":0,
    "gn:timezone":"America/Lima",
    "iso:country":"PE",
    "name:und_x_variant":[
        "Purhua Purhua",
        "Purhua-Purhua"
    ],
    "wof:name":"Purhua-Purhua",
    "wof:placetype":"locality"
},
  "geometry": {"coordinates":[-72.64842,-15.4001],"type":"Point"}
}