{
  "type": "Feature",
  "properties": {
    "gn:admin1_code":"21.0",
    "gn:admin2_code":"2112.0",
    "gn:asciiname":"Yanacocha",
    "gn:country_code":"PE",
    "gn:dem":1297,
    "gn:feature_class":"P",
    "gn:feature_code":"PPL",
    "gn:name":"Yanacocha",
    "gn:population":0,
    "gn:timezone":"America/Lima",
    "iso:country":"PE",
    "name:spa_x_preferred":[
        "Yanacocha"
    ],
    "wof:name":"Yanacocha",
    "wof:placetype":"locality"
},
  "geometry": {"coordinates":[-69.38521999999999,-13.99199],"type":"Point"}
}