{
  "type": "Feature",
  "properties": {
    "gn:admin1_code":"12.0",
    "gn:admin2_code":"1204.0",
    "gn:admin3_code":"120420.0",
    "gn:asciiname":"Barrio Arriba",
    "gn:country_code":"PE",
    "gn:dem":3327,
    "gn:feature_class":"P",
    "gn:feature_code":"PPL",
    "gn:name":"Barrio Arriba",
    "gn:population":0,
    "gn:timezone":"America/Lima",
    "iso:country":"PE",
    "wof:name":"Barrio Arriba",
    "wof:placetype":"locality"
},
  "geometry": {"coordinates":[-75.43803,-11.8274],"type":"Point"}
}