{
  "type": "Feature",
  "properties": {
    "gn:admin1_code":"22.0",
    "gn:admin2_code":"2207.0",
    "gn:admin3_code":"220702.0",
    "gn:asciiname":"Tiraquillo",
    "gn:country_code":"PE",
    "gn:dem":221,
    "gn:feature_class":"P",
    "gn:feature_code":"PPL",
    "gn:name":"Tiraquillo",
    "gn:population":0,
    "gn:timezone":"America/Lima",
    "iso:country":"PE",
    "name:spa_x_preferred":[
        "Tiraquillo"
    ],
    "wof:name":"Tiraquillo",
    "wof:placetype":"locality"
},
  "geometry": {"coordinates":[-76.31214,-6.77769],"type":"Point"}
}