{
  "type": "Feature",
  "properties": {
    "gn:admin1_code":"12.0",
    "gn:admin2_code":"1204.0",
    "gn:admin3_code":"120407.0",
    "gn:asciiname":"Huacho",
    "gn:country_code":"PE",
    "gn:dem":3314,
    "gn:feature_class":"P",
    "gn:feature_code":"PPL",
    "gn:name":"Huacho",
    "gn:population":0,
    "gn:timezone":"America/Lima",
    "iso:country":"PE",
    "name:ara_x_preferred":[
        "\u0647\u0648\u0627\u062a\u0634\u0648"
    ],
    "name:ceb_x_preferred":[
        "Huacho"
    ],
    "name:deu_x_preferred":[
        "Huacho"
    ],
    "name:epo_x_preferred":[
        "Huacho"
    ],
    "name:fas_x_preferred":[
        "\u0627\u0648\u0627\u0686\u0648"
    ],
    "name:fin_x_preferred":[
        "Huacho"
    ],
    "name:fra_x_preferred":[
        "Huacho"
    ],
    "name:ind_x_preferred":[
        "Huacho"
    ],
    "name:ita_x_preferred":[
        "Huacho"
    ],
    "name:kat_x_preferred":[
        "\u10e3\u10d0\u10e9\u10dd"
    ],
    "name:kor_x_preferred":[
        "\uc6b0\uc544\ucd08"
    ],
    "name:nld_x_preferred":[
        "Huacho"
    ],
    "name:pol_x_preferred":[
        "Huacho"
    ],
    "name:por_x_preferred":[
        "Huacho"
    ],
    "name:que_x_preferred":[
        "Wachu llaqta"
    ],
    "name:ron_x_preferred":[
        "Huacho"
    ],
    "name:rus_x_preferred":[
        "\u0423\u0430\u0447\u043e"
    ],
    "name:spa_x_preferred":[
        "Huacho"
    ],
    "name:swe_x_preferred":[
        "Huacho"
    ],
    "name:tat_x_preferred":[
        "\u0412\u0430\u0447\u043e"
    ],
    "name:ukr_x_preferred":[
        "\u0423\u0430\u0447\u043e"
    ],
    "name:urd_x_preferred":[
        "\u0648\u0627\u0686\u0648"
    ],
    "name:war_x_preferred":[
        "Huacho"
    ],
    "wof:name":"Huacho",
    "wof:placetype":"locality"
},
  "geometry": {"coordinates":[-75.38985,-11.82746],"type":"Point"}
}