{
  "type": "Feature",
  "properties": {
    "gn:admin1_code":"12.0",
    "gn:admin2_code":"1204.0",
    "gn:admin3_code":"120407.0",
    "gn:asciiname":"Huacho",
    "gn:country_code":"PE",
    "gn:dem":3314,
    "gn:feature_class":"P",
    "gn:feature_code":"PPL",
    "gn:name":"Huacho",
    "gn:population":0,
    "gn:timezone":"America/Lima",
    "iso:country":"PE",
    "wof:name":"Huacho",
    "wof:placetype":"locality"
},
  "geometry": {"coordinates":[-75.38985,-11.82746],"type":"Point"}
}