{
  "type": "Feature",
  "properties": {
    "gn:admin1_code":"11",
    "gn:admin2_code":"1101.0",
    "gn:admin3_code":"110103.0",
    "gn:asciiname":"Jupanquis",
    "gn:country_code":"PE",
    "gn:dem":419,
    "gn:feature_class":"P",
    "gn:feature_code":"PPL",
    "gn:name":"Jupanquis",
    "gn:population":0,
    "gn:timezone":"America/Lima",
    "iso:country":"PE",
    "name:spa_x_preferred":[
        "Jupanquis"
    ],
    "name:spa_x_variant":[
        "Yupanquis"
    ],
    "wof:name":"Jupanquis",
    "wof:placetype":"locality"
},
  "geometry": {"coordinates":[-75.68656999999997,-14.09992],"type":"Point"}
}