{
  "type": "Feature",
  "properties": {
    "gn:admin1_code":"11.0",
    "gn:admin2_code":"1102.0",
    "gn:admin3_code":"110202.0",
    "gn:asciiname":"La Semilla",
    "gn:country_code":"PE",
    "gn:dem":84,
    "gn:feature_class":"P",
    "gn:feature_code":"PPLL",
    "gn:name":"La Semilla",
    "gn:population":0,
    "gn:timezone":"America/Lima",
    "iso:country":"PE",
    "wof:name":"La Semilla",
    "wof:placetype":"locality"
},
  "geometry": {"coordinates":[-76.11503,-13.45286],"type":"Point"}
}