{
  "type": "Feature",
  "properties": {
    "gn:admin1_code":"2.0",
    "gn:admin2_code":"218.0",
    "gn:admin3_code":"21808.0",
    "gn:asciiname":"El Cruce",
    "gn:country_code":"PE",
    "gn:dem":20,
    "gn:feature_class":"P",
    "gn:feature_code":"PPL",
    "gn:name":"El Cruce",
    "gn:population":0,
    "gn:timezone":"America/Lima",
    "iso:country":"PE",
    "name:spa_x_preferred":[
        "El Cruce"
    ],
    "wof:name":"El Cruce",
    "wof:placetype":"locality"
},
  "geometry": {"coordinates":[-78.61943000000002,-8.97334],"type":"Point"}
}