{
  "type": "Feature",
  "properties": {
    "gn:admin1_code":"15",
    "gn:admin2_code":"1504.0",
    "gn:admin3_code":"150406.0",
    "gn:asciiname":"San Buenaventura",
    "gn:country_code":"PE",
    "gn:dem":2707,
    "gn:feature_class":"P",
    "gn:feature_code":"PPLA3",
    "gn:name":"San Buenaventura",
    "gn:population":0,
    "gn:timezone":"America/Lima",
    "iso:country":"PE",
    "name:ceb_x_preferred":[
        "San Buenaventura"
    ],
    "name:deu_x_preferred":[
        "San Buenaventura"
    ],
    "name:epo_x_preferred":[
        "San Buenaventura"
    ],
    "name:fin_x_preferred":[
        "San Buenaventura"
    ],
    "name:ita_x_preferred":[
        "San Buenaventura"
    ],
    "name:nld_x_preferred":[
        "San Buenaventura"
    ],
    "name:pol_x_preferred":[
        "San Buenaventura"
    ],
    "name:por_x_preferred":[
        "San Buenaventura"
    ],
    "name:rus_x_preferred":[
        "\u0421\u0430\u043d-\u0411\u0443\u044d\u043d\u0430\u0432\u0435\u043d\u0442\u0443\u0440\u0430"
    ],
    "name:sco_x_preferred":[
        "San Buenaventura"
    ],
    "name:spa_x_preferred":[
        "San Buenaventura"
    ],
    "name:srp_x_preferred":[
        "\u0421\u0430\u043d \u0411\u0443\u0435\u043d\u0430\u0432\u0435\u043d\u0442\u0443\u0440\u0430"
    ],
    "name:swe_x_preferred":[
        "San Buenaventura"
    ],
    "name:und_x_variant":[
        "Buenaventura"
    ],
    "wof:name":"San Buenaventura",
    "wof:placetype":"locality"
},
  "geometry": {"coordinates":[-76.66194,-11.48889],"type":"Point"}
}