{
  "type": "Feature",
  "properties": {
    "gn:admin1_code":"1.0",
    "gn:admin2_code":"101.0",
    "gn:admin3_code":"10103.0",
    "gn:asciiname":"San Basilio",
    "gn:country_code":"PE",
    "gn:dem":2328,
    "gn:feature_class":"P",
    "gn:feature_code":"PPL",
    "gn:name":"San Basilio",
    "gn:population":0,
    "gn:timezone":"America/Lima",
    "iso:country":"PE",
    "name:arg_x_preferred":[
        "Santu 'Asili"
    ],
    "name:azb_x_preferred":[
        "\u0633\u0646 \u0628\u0627\u0633\u06cc\u0644\u06cc\u0648"
    ],
    "name:bul_x_preferred":[
        "\u0421\u0430\u043d \u0411\u0430\u0437\u0438\u043b\u0438\u043e"
    ],
    "name:cat_x_preferred":[
        "San Basilio"
    ],
    "name:ceb_x_preferred":[
        "San Basilio"
    ],
    "name:ces_x_preferred":[
        "San Basilio"
    ],
    "name:dan_x_preferred":[
        "San Basilio"
    ],
    "name:deu_x_preferred":[
        "San Basilio"
    ],
    "name:epo_x_preferred":[
        "San Basilio"
    ],
    "name:eus_x_preferred":[
        "San Basilio"
    ],
    "name:fas_x_preferred":[
        "\u0633\u0646 \u0628\u0627\u0633\u06cc\u0644\u06cc\u0648"
    ],
    "name:fin_x_preferred":[
        "San Basilio"
    ],
    "name:fra_x_preferred":[
        "San Basilio"
    ],
    "name:hrv_x_preferred":[
        "San Basilio"
    ],
    "name:hun_x_preferred":[
        "San Basilio"
    ],
    "name:hye_x_preferred":[
        "\u054d\u0561\u0576 \u0532\u0561\u0566\u056b\u056c\u056b\u0578"
    ],
    "name:ind_x_preferred":[
        "San Basilio"
    ],
    "name:ita_x_preferred":[
        "San Basilio"
    ],
    "name:jpn_x_preferred":[
        "\u30b5\u30f3\u30fb\u30d0\u30b8\u30fc\u30ea\u30aa"
    ],
    "name:kaz_x_preferred":[
        "\u0421\u0430\u043d-\u0411\u0430\u0437\u0438\u043b\u0438\u043e"
    ],
    "name:lat_x_preferred":[
        "Sanctus Basilius"
    ],
    "name:lmo_x_preferred":[
        "San Basilio"
    ],
    "name:msa_x_preferred":[
        "San Basilio"
    ],
    "name:nap_x_preferred":[
        "San Basilio"
    ],
    "name:nld_x_preferred":[
        "San Basilio"
    ],
    "name:nno_x_preferred":[
        "San Basilio"
    ],
    "name:nor_x_preferred":[
        "San Basilio"
    ],
    "name:pms_x_preferred":[
        "San Basilio"
    ],
    "name:pol_x_preferred":[
        "San Basilio"
    ],
    "name:por_x_preferred":[
        "San Basilio"
    ],
    "name:ron_x_preferred":[
        "San Basilio"
    ],
    "name:rus_x_preferred":[
        "\u0421\u0430\u043d-\u0411\u0430\u0437\u0438\u043b\u0438\u043e"
    ],
    "name:spa_x_preferred":[
        "San Basilio"
    ],
    "name:sqi_x_preferred":[
        "San Basilio"
    ],
    "name:srd_x_preferred":[
        "Santu 'Asili 'e Monti"
    ],
    "name:srp_x_preferred":[
        "\u0421\u0430\u043d \u0411\u0430\u0437\u0438\u043b\u0438\u043e"
    ],
    "name:tur_x_preferred":[
        "San Basilio"
    ],
    "name:ukr_x_preferred":[
        "\u0421\u0430\u043d-\u0411\u0430\u0437\u0456\u043b\u0456\u043e"
    ],
    "name:uzb_x_preferred":[
        "San Basilio"
    ],
    "name:vec_x_preferred":[
        "San Basilio"
    ],
    "name:vie_x_preferred":[
        "San Basilio"
    ],
    "name:vol_x_preferred":[
        "San Basilio"
    ],
    "name:war_x_preferred":[
        "San Basilio"
    ],
    "name:zho_x_preferred":[
        "\u5723\u5df4\u897f\u5ed6"
    ],
    "wof:name":"San Basilio",
    "wof:placetype":"locality"
},
  "geometry": {"coordinates":[-77.93316,-6.8404],"type":"Point"}
}