{
  "type": "Feature",
  "properties": {
    "gn:admin1_code":"20",
    "gn:admin2_code":"2006.0",
    "gn:admin3_code":"200605.0",
    "gn:asciiname":"El Penco",
    "gn:country_code":"PE",
    "gn:dem":375,
    "gn:feature_class":"P",
    "gn:feature_code":"PPL",
    "gn:name":"El Penco",
    "gn:population":0,
    "gn:timezone":"America/Lima",
    "iso:country":"PE",
    "name:spa_x_preferred":[
        "El Penco"
    ],
    "name:spa_x_variant":[
        "El Perico"
    ],
    "wof:name":"El Penco",
    "wof:placetype":"locality"
},
  "geometry": {"coordinates":[-80.68893,-4.49833],"type":"Point"}
}