{
  "type": "Feature",
  "properties": {
    "gn:admin1_code":"2.0",
    "gn:admin2_code":"205.0",
    "gn:admin3_code":"20503.0",
    "gn:asciiname":"Puclla",
    "gn:country_code":"PE",
    "gn:dem":3369,
    "gn:feature_class":"P",
    "gn:feature_code":"PPL",
    "gn:name":"Puclla",
    "gn:population":0,
    "gn:timezone":"America/Lima",
    "iso:country":"PE",
    "wof:name":"Puclla",
    "wof:placetype":"locality"
},
  "geometry": {"coordinates":[-77.46514000000001,-10.22355],"type":"Point"}
}