{
  "type": "Feature",
  "properties": {
    "gn:admin1_code":"03",
    "gn:admin2_code":"307.0",
    "gn:admin3_code":"30708.0",
    "gn:asciiname":"Huaillac",
    "gn:cc2":"PE",
    "gn:country_code":"PE",
    "gn:dem":3781,
    "gn:feature_class":"P",
    "gn:feature_code":"PPL",
    "gn:name":"Huaillac",
    "gn:population":0,
    "gn:timezone":"America/Lima",
    "iso:country":"PE",
    "name:und_x_variant":[
        "Huaillac Hacienda",
        "Huaillac"
    ],
    "wof:name":"Huaillac",
    "wof:placetype":"locality"
},
  "geometry": {"coordinates":[-72.53333000000001,-14.03333],"type":"Point"}
}