{
  "type": "Feature",
  "properties": {
    "gn:admin1_code":"5.0",
    "gn:admin2_code":"504.0",
    "gn:admin3_code":"50402.0",
    "gn:asciiname":"Sachapata",
    "gn:country_code":"PE",
    "gn:dem":3588,
    "gn:feature_class":"P",
    "gn:feature_code":"PPL",
    "gn:name":"Sachapata",
    "gn:population":0,
    "gn:timezone":"America/Lima",
    "iso:country":"PE",
    "wof:name":"Sachapata",
    "wof:placetype":"locality"
},
  "geometry": {"coordinates":[-74.25324999999999,-12.5418],"type":"Point"}
}