{
  "type": "Feature",
  "properties": {
    "gn:admin1_code":"21",
    "gn:admin2_code":"2106.0",
    "gn:admin3_code":"210607.0",
    "gn:asciiname":"Silca",
    "gn:country_code":"PE",
    "gn:dem":3822,
    "gn:feature_class":"P",
    "gn:feature_code":"PPL",
    "gn:name":"Silca",
    "gn:population":0,
    "gn:timezone":"America/Lima",
    "iso:country":"PE",
    "name:ceb_x_preferred":[
        "Silca"
    ],
    "name:fra_x_preferred":[
        "Silca"
    ],
    "name:ita_x_preferred":[
        "Silca"
    ],
    "name:nld_x_preferred":[
        "Silca"
    ],
    "name:por_x_preferred":[
        "Silca"
    ],
    "name:spa_x_preferred":[
        "Silca"
    ],
    "name:swe_x_preferred":[
        "Silca"
    ],
    "name:zho_x_preferred":[
        "\u932b\u723e\u5361"
    ],
    "wof:name":"Silca",
    "wof:placetype":"locality"
},
  "geometry": {"coordinates":[-69.93052,-15.26134],"type":"Point"}
}