{
  "type": "Feature",
  "properties": {
    "gn:admin1_code":"8",
    "gn:admin2_code":"808.0",
    "gn:admin3_code":"80803.0",
    "gn:asciiname":"Moyuna",
    "gn:country_code":"PE",
    "gn:dem":3924,
    "gn:feature_class":"P",
    "gn:feature_code":"PPL",
    "gn:name":"Moyuna",
    "gn:population":0,
    "gn:timezone":"America/Lima",
    "iso:country":"PE",
    "wof:name":"Moyuna",
    "wof:placetype":"locality"
},
  "geometry": {"coordinates":[-71.50655999999999,-14.86991],"type":"Point"}
}