{
  "type": "Feature",
  "properties": {
    "gn:admin1_code":"15",
    "gn:admin2_code":"1510.0",
    "gn:admin3_code":"151029.0",
    "gn:asciiname":"Yantuya",
    "gn:country_code":"PE",
    "gn:dem":1465,
    "gn:feature_class":"P",
    "gn:feature_code":"PPL",
    "gn:name":"Yantuya",
    "gn:population":0,
    "gn:timezone":"America/Lima",
    "iso:country":"PE",
    "wof:name":"Yantuya",
    "wof:placetype":"locality"
},
  "geometry": {"coordinates":[-76.20664000000002,-12.77988],"type":"Point"}
}