{
  "type": "Feature",
  "properties": {
    "gn:admin1_code":"12.0",
    "gn:admin2_code":"1203.0",
    "gn:admin3_code":"120302.0",
    "gn:asciiname":"Pucharani",
    "gn:country_code":"PE",
    "gn:dem":589,
    "gn:feature_class":"P",
    "gn:feature_code":"PPL",
    "gn:name":"Pucharani",
    "gn:population":0,
    "gn:timezone":"America/Lima",
    "iso:country":"PE",
    "name:spa_x_preferred":[
        "Pucharani"
    ],
    "wof:name":"Pucharani",
    "wof:placetype":"locality"
},
  "geometry": {"coordinates":[-75.07228000000001,-10.8656],"type":"Point"}
}