{
  "type": "Feature",
  "properties": {
    "gn:admin1_code":"11",
    "gn:admin2_code":"1103.0",
    "gn:admin3_code":"110302.0",
    "gn:asciiname":"Hacienda Monte Grande",
    "gn:country_code":"PE",
    "gn:dem":43,
    "gn:feature_class":"P",
    "gn:feature_code":"PPL",
    "gn:name":"Hacienda Monte Grande",
    "gn:population":0,
    "gn:timezone":"America/Lima",
    "iso:country":"PE",
    "name:und_x_variant":[
        "Monte Grande",
        "Hacienda Monte Grande"
    ],
    "wof:name":"Hacienda Monte Grande",
    "wof:placetype":"locality"
},
  "geometry": {"coordinates":[-75.41049,-14.93533],"type":"Point"}
}