{
  "type": "Feature",
  "properties": {
    "gn:admin1_code":"9.0",
    "gn:admin2_code":"902.0",
    "gn:admin3_code":"90202.0",
    "gn:asciiname":"Chilcapucro",
    "gn:country_code":"PE",
    "gn:dem":4096,
    "gn:feature_class":"P",
    "gn:feature_code":"PPL",
    "gn:name":"Chilcapucro",
    "gn:population":0,
    "gn:timezone":"America/Lima",
    "iso:country":"PE",
    "wof:name":"Chilcapucro",
    "wof:placetype":"locality"
},
  "geometry": {"coordinates":[-74.66309,-12.69421],"type":"Point"}
}