{
  "type": "Feature",
  "properties": {
    "gn:admin1_code":"20",
    "gn:admin2_code":"2003.0",
    "gn:admin3_code":"200305.0",
    "gn:asciiname":"Caraveli",
    "gn:country_code":"PE",
    "gn:dem":798,
    "gn:feature_class":"P",
    "gn:feature_code":"PPL",
    "gn:name":"Caravel\u00ed",
    "gn:population":0,
    "gn:timezone":"America/Lima",
    "iso:country":"PE",
    "name:und_x_variant":[
        "Caravel",
        "Caravel\u00ed"
    ],
    "wof:name":"Caraveli",
    "wof:placetype":"locality"
},
  "geometry": {"coordinates":[-79.65559,-5.22697],"type":"Point"}
}