{
  "type": "Feature",
  "properties": {
    "gn:admin1_code":"17.0",
    "gn:admin2_code":"1703.0",
    "gn:asciiname":"Lucitania",
    "gn:country_code":"PE",
    "gn:dem":248,
    "gn:feature_class":"P",
    "gn:feature_code":"PPL",
    "gn:name":"Lucitania",
    "gn:population":0,
    "gn:timezone":"America/Lima",
    "iso:country":"PE",
    "name:spa_x_preferred":[
        "Lucitania"
    ],
    "wof:name":"Lucitania",
    "wof:placetype":"locality"
},
  "geometry": {"coordinates":[-69.58443,-10.98753],"type":"Point"}
}