{
  "type": "Feature",
  "properties": {
    "gn:admin1_code":"5",
    "gn:admin2_code":"510.0",
    "gn:admin3_code":"51005.0",
    "gn:asciiname":"Ajolla",
    "gn:country_code":"PE",
    "gn:dem":3264,
    "gn:feature_class":"P",
    "gn:feature_code":"PPL",
    "gn:name":"Ajolla",
    "gn:population":0,
    "gn:timezone":"America/Lima",
    "iso:country":"PE",
    "wof:name":"Ajolla",
    "wof:placetype":"locality"
},
  "geometry": {"coordinates":[-73.90315,-13.98466],"type":"Point"}
}