{
  "type": "Feature",
  "properties": {
    "gn:admin1_code":"12.0",
    "gn:admin2_code":"1203.0",
    "gn:admin3_code":"120302.0",
    "gn:asciiname":"Pueblo Libre",
    "gn:country_code":"PE",
    "gn:dem":971,
    "gn:feature_class":"P",
    "gn:feature_code":"PPL",
    "gn:name":"Pueblo Libre",
    "gn:population":0,
    "gn:timezone":"America/Lima",
    "iso:country":"PE",
    "name:spa_x_preferred":[
        "Pueblo Libre"
    ],
    "wof:name":"Pueblo Libre",
    "wof:placetype":"locality"
},
  "geometry": {"coordinates":[-75.16133000000001,-10.7579],"type":"Point"}
}