{
  "type": "Feature",
  "properties": {
    "gn:admin1_code":"2.0",
    "gn:admin2_code":"205.0",
    "gn:admin3_code":"20504.0",
    "gn:asciiname":"Canto Cuta",
    "gn:country_code":"PE",
    "gn:dem":3638,
    "gn:feature_class":"P",
    "gn:feature_code":"PPL",
    "gn:name":"Canto Cuta",
    "gn:population":0,
    "gn:timezone":"America/Lima",
    "iso:country":"PE",
    "wof:name":"Canto Cuta",
    "wof:placetype":"locality"
},
  "geometry": {"coordinates":[-77.13225,-10.03036],"type":"Point"}
}