{
  "type": "Feature",
  "properties": {
    "gn:admin1_code":"19.0",
    "gn:admin2_code":"1901.0",
    "gn:admin3_code":"190104.0",
    "gn:asciiname":"Anascocha",
    "gn:country_code":"PE",
    "gn:dem":4387,
    "gn:feature_class":"P",
    "gn:feature_code":"PPL",
    "gn:name":"Anascocha",
    "gn:population":0,
    "gn:timezone":"America/Lima",
    "iso:country":"PE",
    "wof:name":"Anascocha",
    "wof:placetype":"locality"
},
  "geometry": {"coordinates":[-76.3351,-11.01593],"type":"Point"}
}