{
  "type": "Feature",
  "properties": {
    "gn:admin1_code":"4",
    "gn:admin2_code":"407.0",
    "gn:admin3_code":"40703.0",
    "gn:asciiname":"Buenos Aires Hacienda",
    "gn:country_code":"PE",
    "gn:dem":13,
    "gn:feature_class":"P",
    "gn:feature_code":"PPL",
    "gn:name":"Buenos Aires Hacienda",
    "gn:population":0,
    "gn:timezone":"America/Lima",
    "iso:country":"PE",
    "wof:name":"Buenos Aires Hacienda",
    "wof:placetype":"locality"
},
  "geometry": {"coordinates":[-71.84867,-17.14725],"type":"Point"}
}