{
  "type": "Feature",
  "properties": {
    "gn:admin1_code":"15.0",
    "gn:admin2_code":"1501.0",
    "gn:admin3_code":"150114.0",
    "gn:asciiname":"Terreno Los Condes de la Planicie",
    "gn:country_code":"PE",
    "gn:dem":328,
    "gn:feature_class":"P",
    "gn:feature_code":"PPLS",
    "gn:name":"Terreno Los Condes de la Planicie",
    "gn:population":0,
    "gn:timezone":"America/Lima",
    "iso:country":"PE",
    "wof:name":"Terreno Los Condes de la Planicie",
    "wof:placetype":"locality"
},
  "geometry": {"coordinates":[-76.91849999999999,-12.0743],"type":"Point"}
}