{
  "type": "Feature",
  "properties": {
    "gn:admin1_code":"16",
    "gn:admin2_code":"1601.0",
    "gn:admin3_code":"160108.0",
    "gn:asciiname":"Astoria",
    "gn:country_code":"PE",
    "gn:dem":101,
    "gn:feature_class":"P",
    "gn:feature_code":"PPL",
    "gn:name":"Astoria",
    "gn:population":0,
    "gn:timezone":"America/Lima",
    "iso:country":"PE",
    "name:cat_x_preferred":[
        "Astoria"
    ],
    "name:ceb_x_preferred":[
        "Astoria"
    ],
    "name:ces_x_preferred":[
        "Astoria"
    ],
    "name:deu_x_preferred":[
        "Astoria"
    ],
    "name:fas_x_preferred":[
        "\u0622\u0633\u062a\u0648\u0631\u06cc\u0627"
    ],
    "name:fin_x_preferred":[
        "Astoria"
    ],
    "name:fra_x_preferred":[
        "Astoria"
    ],
    "name:hun_x_preferred":[
        "Astoria"
    ],
    "name:ita_x_preferred":[
        "Astoria"
    ],
    "name:jpn_x_preferred":[
        "\u30a2\u30b9\u30c8\u30ea\u30a2"
    ],
    "name:kor_x_preferred":[
        "\uc560\uc2a4\ud1a0\ub9ac\uc544"
    ],
    "name:nld_x_preferred":[
        "Astoria"
    ],
    "name:pol_x_preferred":[
        "Astoria"
    ],
    "name:por_x_preferred":[
        "Astoria"
    ],
    "name:rus_x_preferred":[
        "\u0410\u0441\u0442\u043e\u0440\u0438\u044f"
    ],
    "name:spa_x_preferred":[
        "Astoria"
    ],
    "name:srp_x_preferred":[
        "\u0410\u0441\u0442\u043e\u0440\u0438\u0458\u0430"
    ],
    "name:swe_x_preferred":[
        "Astoria"
    ],
    "name:tur_x_preferred":[
        "Astoria"
    ],
    "name:ukr_x_preferred":[
        "\u0410\u0441\u0442\u043e\u0440\u0456\u044f"
    ],
    "name:vol_x_preferred":[
        "Astoria"
    ],
    "name:zho_x_preferred":[
        "\u963f\u65af\u6258\u91cc\u4e9e"
    ],
    "wof:name":"Astoria",
    "wof:placetype":"locality"
},
  "geometry": {"coordinates":[-73.25,-3.66667],"type":"Point"}
}