{
  "type": "Feature",
  "properties": {
    "gn:admin1_code":"13.0",
    "gn:admin2_code":"1308.0",
    "gn:admin3_code":"130812.0",
    "gn:asciiname":"Querobamba",
    "gn:country_code":"PE",
    "gn:dem":2919,
    "gn:feature_class":"P",
    "gn:feature_code":"PPL",
    "gn:name":"Querobamba",
    "gn:population":0,
    "gn:timezone":"America/Lima",
    "iso:country":"PE",
    "name:aym_x_preferred":[
        "Qirupampa"
    ],
    "name:lit_x_preferred":[
        "Kerobamba"
    ],
    "name:pol_x_preferred":[
        "Querobamba"
    ],
    "name:que_x_preferred":[
        "Qirupampa"
    ],
    "name:spa_x_preferred":[
        "Querobamba"
    ],
    "name:war_x_preferred":[
        "Querobamba"
    ],
    "name:zho_x_preferred":[
        "\u514b\u7f85\u73ed\u5df4"
    ],
    "wof:name":"Querobamba",
    "wof:placetype":"locality"
},
  "geometry": {"coordinates":[-77.44722,-8.28583],"type":"Point"}
}