{
  "type": "Feature",
  "properties": {
    "gn:admin1_code":"10.0",
    "gn:admin2_code":"1003.0",
    "gn:admin3_code":"100317.0",
    "gn:asciiname":"Tacta Ucro",
    "gn:country_code":"PE",
    "gn:dem":3787,
    "gn:feature_class":"P",
    "gn:feature_code":"PPL",
    "gn:name":"Tacta Ucro",
    "gn:population":0,
    "gn:timezone":"America/Lima",
    "iso:country":"PE",
    "wof:name":"Tacta Ucro",
    "wof:placetype":"locality"
},
  "geometry": {"coordinates":[-76.81838,-9.82755],"type":"Point"}
}