{
  "type": "Feature",
  "properties": {
    "gn:admin1_code":"06",
    "gn:admin2_code":"601.0",
    "gn:admin3_code":"60101.0",
    "gn:asciiname":"Casapampa",
    "gn:country_code":"PE",
    "gn:dem":2789,
    "gn:feature_class":"P",
    "gn:feature_code":"PPL",
    "gn:name":"Casapampa",
    "gn:population":0,
    "gn:timezone":"America/Lima",
    "iso:country":"PE",
    "wof:name":"Casapampa",
    "wof:placetype":"locality"
},
  "geometry": {"coordinates":[-78.48132,-7.21645],"type":"Point"}
}