{
  "type": "Feature",
  "properties": {
    "gn:admin1_code":"06",
    "gn:admin2_code":"610.0",
    "gn:admin3_code":"61004.0",
    "gn:asciiname":"Trancachimba",
    "gn:country_code":"PE",
    "gn:dem":3623,
    "gn:feature_class":"P",
    "gn:feature_code":"PPL",
    "gn:name":"Trancachimba",
    "gn:population":0,
    "gn:timezone":"America/Lima",
    "iso:country":"PE",
    "wof:name":"Trancachimba",
    "wof:placetype":"locality"
},
  "geometry": {"coordinates":[-78.10540999999998,-7.23365],"type":"Point"}
}