{
  "type": "Feature",
  "properties": {
    "gn:admin1_code":"11.0",
    "gn:admin2_code":"1101.0",
    "gn:admin3_code":"110106.0",
    "gn:asciiname":"Carrizales",
    "gn:country_code":"PE",
    "gn:dem":418,
    "gn:feature_class":"P",
    "gn:feature_code":"PPL",
    "gn:name":"Carrizales",
    "gn:population":0,
    "gn:timezone":"America/Lima",
    "iso:country":"PE",
    "name:spa_x_preferred":[
        "Carrizales"
    ],
    "wof:name":"Carrizales",
    "wof:placetype":"locality"
},
  "geometry": {"coordinates":[-75.6999,-14.07007],"type":"Point"}
}