{
  "type": "Feature",
  "properties": {
    "gn:admin1_code":"22.0",
    "gn:admin2_code":"2210.0",
    "gn:admin3_code":"221001.0",
    "gn:asciiname":"Manco Capac",
    "gn:country_code":"PE",
    "gn:dem":816,
    "gn:feature_class":"P",
    "gn:feature_code":"PPLL",
    "gn:name":"Manco Capac",
    "gn:population":0,
    "gn:timezone":"America/Lima",
    "iso:country":"PE",
    "wof:name":"Manco Capac",
    "wof:placetype":"locality"
},
  "geometry": {"coordinates":[-76.45811999999999,-8.20839],"type":"Point"}
}