{
  "type": "Feature",
  "properties": {
    "gn:admin1_code":"18",
    "gn:admin2_code":"1803.0",
    "gn:admin3_code":"180303.0",
    "gn:asciiname":"Los Molles",
    "gn:country_code":"PE",
    "gn:dem":264,
    "gn:feature_class":"P",
    "gn:feature_code":"PPL",
    "gn:name":"Los Molles",
    "gn:population":0,
    "gn:timezone":"America/Lima",
    "iso:country":"PE",
    "wof:name":"Los Molles",
    "wof:placetype":"locality"
},
  "geometry": {"coordinates":[-71.40028000000002,-17.37639],"type":"Point"}
}