{
  "type": "Feature",
  "properties": {
    "gn:admin1_code":"4",
    "gn:admin2_code":"406.0",
    "gn:admin3_code":"40603.0",
    "gn:asciiname":"Salviani",
    "gn:country_code":"PE",
    "gn:dem":4562,
    "gn:feature_class":"P",
    "gn:feature_code":"PPL",
    "gn:name":"Salviani",
    "gn:population":0,
    "gn:timezone":"America/Lima",
    "iso:country":"PE",
    "wof:name":"Salviani",
    "wof:placetype":"locality"
},
  "geometry": {"coordinates":[-72.28104999999999,-15.03101],"type":"Point"}
}