{
  "type": "Feature",
  "properties": {
    "gn:admin1_code":"04",
    "gn:admin2_code":"405.0",
    "gn:admin3_code":"40514.0",
    "gn:asciiname":"Paradero Colca",
    "gn:country_code":"PE",
    "gn:dem":4476,
    "gn:feature_class":"P",
    "gn:feature_code":"PPL",
    "gn:name":"Paradero Colca",
    "gn:population":0,
    "gn:timezone":"America/Lima",
    "iso:country":"PE",
    "wof:name":"Paradero Colca",
    "wof:placetype":"locality"
},
  "geometry": {"coordinates":[-70.98907,-15.76543],"type":"Point"}
}