{
  "type": "Feature",
  "properties": {
    "gn:admin1_code":"21",
    "gn:admin2_code":"2101.0",
    "gn:admin3_code":"210112.0",
    "gn:asciiname":"Cotempoyo",
    "gn:country_code":"PE",
    "gn:dem":4010,
    "gn:feature_class":"P",
    "gn:feature_code":"PPL",
    "gn:name":"Cotempoyo",
    "gn:population":0,
    "gn:timezone":"America/Lima",
    "iso:country":"PE",
    "wof:name":"Cotempoyo",
    "wof:placetype":"locality"
},
  "geometry": {"coordinates":[-69.86667,-15.95],"type":"Point"}
}