{
  "type": "Feature",
  "properties": {
    "gn:admin1_code":"4.0",
    "gn:admin2_code":"403.0",
    "gn:admin3_code":"40309.0",
    "gn:asciiname":"Agcochiuche",
    "gn:country_code":"PE",
    "gn:dem":1049,
    "gn:feature_class":"P",
    "gn:feature_code":"PPL",
    "gn:name":"Agcochiuche",
    "gn:population":0,
    "gn:timezone":"America/Lima",
    "iso:country":"PE",
    "name:spa_x_preferred":[
        "Agcochiuche"
    ],
    "wof:name":"Agcochiuche",
    "wof:placetype":"locality"
},
  "geometry": {"coordinates":[-74.09631999999998,-15.65719],"type":"Point"}
}