{
  "type": "Feature",
  "properties": {
    "gn:admin1_code":"20",
    "gn:admin2_code":"2006.0",
    "gn:admin3_code":"200605.0",
    "gn:asciiname":"Saman de Afuera",
    "gn:country_code":"PE",
    "gn:dem":49,
    "gn:feature_class":"P",
    "gn:feature_code":"PPL",
    "gn:name":"Saman de Afuera",
    "gn:population":0,
    "gn:timezone":"America/Lima",
    "iso:country":"PE",
    "name:spa_x_preferred":[
        "Saman de Afuera"
    ],
    "name:und_x_variant":[
        "Saman Hacienda",
        "Sam\u00e1n"
    ],
    "wof:name":"Saman de Afuera",
    "wof:placetype":"locality"
},
  "geometry": {"coordinates":[-80.76538000000002,-4.83901],"type":"Point"}
}