{
  "type": "Feature",
  "properties": {
    "gn:admin1_code":"03",
    "gn:admin2_code":"303.0",
    "gn:admin3_code":"30305.0",
    "gn:asciiname":"Huaraiuito",
    "gn:country_code":"PE",
    "gn:dem":4381,
    "gn:feature_class":"P",
    "gn:feature_code":"PPL",
    "gn:name":"Huaraiuito",
    "gn:population":0,
    "gn:timezone":"America/Lima",
    "iso:country":"PE",
    "wof:name":"Huaraiuito",
    "wof:placetype":"locality"
},
  "geometry": {"coordinates":[-72.48333000000002,-14.36667],"type":"Point"}
}