{
  "type": "Feature",
  "properties": {
    "gn:admin1_code":"18",
    "gn:admin2_code":"1801.0",
    "gn:admin3_code":"180101.0",
    "gn:asciiname":"Escapalaque",
    "gn:country_code":"PE",
    "gn:dem":1536,
    "gn:feature_class":"P",
    "gn:feature_code":"PPL",
    "gn:name":"Escapalaque",
    "gn:population":0,
    "gn:timezone":"America/Lima",
    "iso:country":"PE",
    "wof:name":"Escapalaque",
    "wof:placetype":"locality"
},
  "geometry": {"coordinates":[-70.90732,-17.18445],"type":"Point"}
}