{
  "type": "Feature",
  "properties": {
    "gn:admin1_code":"15",
    "gn:admin2_code":"1510.0",
    "gn:admin3_code":"151016.0",
    "gn:asciiname":"Turpo",
    "gn:country_code":"PE",
    "gn:dem":4664,
    "gn:feature_class":"P",
    "gn:feature_code":"PPL",
    "gn:name":"Turpo",
    "gn:population":0,
    "gn:timezone":"America/Lima",
    "iso:country":"PE",
    "wof:name":"Turpo",
    "wof:placetype":"locality"
},
  "geometry": {"coordinates":[-75.65000000000001,-12.61667],"type":"Point"}
}