{
  "type": "Feature",
  "properties": {
    "gn:admin1_code":"12",
    "gn:admin2_code":"1201.0",
    "gn:admin3_code":"120108.0",
    "gn:asciiname":"Tablachata",
    "gn:country_code":"PE",
    "gn:dem":4141,
    "gn:feature_class":"P",
    "gn:feature_code":"PPL",
    "gn:name":"Tablachata",
    "gn:population":0,
    "gn:timezone":"America/Lima",
    "iso:country":"PE",
    "wof:name":"Tablachata",
    "wof:placetype":"locality"
},
  "geometry": {"coordinates":[-75.38003,-12.4091],"type":"Point"}
}