{
  "type": "Feature",
  "properties": {
    "gn:admin1_code":"06",
    "gn:admin2_code":"605.0",
    "gn:admin3_code":"60503.0",
    "gn:asciiname":"Juque",
    "gn:country_code":"PE",
    "gn:dem":2753,
    "gn:feature_class":"P",
    "gn:feature_code":"PPL",
    "gn:name":"Juque",
    "gn:population":0,
    "gn:timezone":"America/Lima",
    "iso:country":"PE",
    "name:spa_x_preferred":[
        "Juque"
    ],
    "wof:name":"Juque",
    "wof:placetype":"locality"
},
  "geometry": {"coordinates":[-79.00439,-7.36493],"type":"Point"}
}