{
  "type": "Feature",
  "properties": {
    "gn:admin1_code":"05",
    "gn:admin2_code":"501.0",
    "gn:admin3_code":"50108.0",
    "gn:asciiname":"Moya",
    "gn:country_code":"PE",
    "gn:dem":3387,
    "gn:feature_class":"P",
    "gn:feature_code":"PPL",
    "gn:name":"Moya",
    "gn:population":0,
    "gn:timezone":"America/Lima",
    "iso:country":"PE",
    "name:cat_x_preferred":[
        "Moya"
    ],
    "name:ceb_x_preferred":[
        "Moya"
    ],
    "name:deu_x_preferred":[
        "Moya"
    ],
    "name:eus_x_preferred":[
        "Moya"
    ],
    "name:fra_x_preferred":[
        "Moya"
    ],
    "name:glg_x_preferred":[
        "Moya"
    ],
    "name:heb_x_preferred":[
        "\u05de\u05d5\u05d9\u05d4"
    ],
    "name:hun_x_preferred":[
        "Moya"
    ],
    "name:hye_x_preferred":[
        "\u0544\u0578\u0575\u0561"
    ],
    "name:ita_x_preferred":[
        "Moya"
    ],
    "name:msa_x_preferred":[
        "Moya"
    ],
    "name:nld_x_preferred":[
        "Moya"
    ],
    "name:oci_x_preferred":[
        "Moya"
    ],
    "name:pol_x_preferred":[
        "Moya"
    ],
    "name:por_x_preferred":[
        "Moya"
    ],
    "name:rus_x_preferred":[
        "\u041c\u043e\u0439\u044f"
    ],
    "name:spa_x_preferred":[
        "Moya"
    ],
    "name:swe_x_preferred":[
        "Moya"
    ],
    "name:ukr_x_preferred":[
        "\u041c\u043e\u044f"
    ],
    "name:uzb_x_preferred":[
        "Moya"
    ],
    "name:vie_x_preferred":[
        "Moya"
    ],
    "name:war_x_preferred":[
        "Moya"
    ],
    "wof:name":"Moya",
    "wof:placetype":"locality"
},
  "geometry": {"coordinates":[-74.13579,-13.02528],"type":"Point"}
}