{
  "type": "Feature",
  "properties": {
    "gn:admin1_code":"05",
    "gn:admin2_code":"501.0",
    "gn:admin3_code":"50108.0",
    "gn:asciiname":"Moya",
    "gn:country_code":"PE",
    "gn:dem":3387,
    "gn:feature_class":"P",
    "gn:feature_code":"PPL",
    "gn:name":"Moya",
    "gn:population":0,
    "gn:timezone":"America/Lima",
    "iso:country":"PE",
    "wof:name":"Moya",
    "wof:placetype":"locality"
},
  "geometry": {"coordinates":[-74.13579,-13.02528],"type":"Point"}
}