{
  "type": "Feature",
  "properties": {
    "gn:admin1_code":"04",
    "gn:admin2_code":"403.0",
    "gn:admin3_code":"40310.0",
    "gn:asciiname":"Jarajali",
    "gn:cc2":"PE",
    "gn:country_code":"PE",
    "gn:dem":480,
    "gn:feature_class":"P",
    "gn:feature_code":"PPL",
    "gn:name":"Jarajali",
    "gn:population":0,
    "gn:timezone":"America/Lima",
    "iso:country":"PE",
    "name:und_x_variant":[
        "Arajali",
        "Jarajali Hacienda",
        "Araguay",
        "Jarajali"
    ],
    "wof:name":"Jarajali",
    "wof:placetype":"locality"
},
  "geometry": {"coordinates":[-74.41667,-15.45],"type":"Point"}
}