{
  "type": "Feature",
  "properties": {
    "gn:admin1_code":"5.0",
    "gn:admin2_code":"504.0",
    "gn:admin3_code":"50401.0",
    "gn:asciiname":"Uchuracay",
    "gn:country_code":"PE",
    "gn:dem":3884,
    "gn:feature_class":"P",
    "gn:feature_code":"PPL",
    "gn:name":"Uchuracay",
    "gn:population":0,
    "gn:timezone":"America/Lima",
    "iso:country":"PE",
    "wof:name":"Uchuracay",
    "wof:placetype":"locality"
},
  "geometry": {"coordinates":[-74.10491,-12.82646],"type":"Point"}
}