{
  "type": "Feature",
  "properties": {
    "gn:admin1_code":"21",
    "gn:admin2_code":"2104.0",
    "gn:admin3_code":"210404.0",
    "gn:asciiname":"Chillihua",
    "gn:country_code":"PE",
    "gn:dem":3875,
    "gn:feature_class":"P",
    "gn:feature_code":"PPL",
    "gn:name":"Chillihua",
    "gn:population":0,
    "gn:timezone":"America/Lima",
    "iso:country":"PE",
    "name:zho_x_preferred":[
        "\u5947\u5229\u74e6\u5c71"
    ],
    "wof:name":"Chillihua",
    "wof:placetype":"locality"
},
  "geometry": {"coordinates":[-69.23416,-16.83459],"type":"Point"}
}