{
  "type": "Feature",
  "properties": {
    "gn:admin1_code":"9.0",
    "gn:admin2_code":"905.0",
    "gn:asciiname":"Arma",
    "gn:country_code":"PE",
    "gn:dem":3356,
    "gn:feature_class":"P",
    "gn:feature_code":"PPL",
    "gn:name":"Arma",
    "gn:population":0,
    "gn:timezone":"America/Lima",
    "iso:country":"PE",
    "wof:name":"Arma",
    "wof:placetype":"locality"
},
  "geometry": {"coordinates":[-74.47728000000002,-12.72192],"type":"Point"}
}