{
  "type": "Feature",
  "properties": {
    "gn:admin1_code":"9.0",
    "gn:admin2_code":"905.0",
    "gn:asciiname":"Arma",
    "gn:country_code":"PE",
    "gn:dem":3356,
    "gn:feature_class":"P",
    "gn:feature_code":"PPL",
    "gn:name":"Arma",
    "gn:population":0,
    "gn:timezone":"America/Lima",
    "iso:country":"PE",
    "name:ceb_x_preferred":[
        "Arma"
    ],
    "name:deu_x_preferred":[
        "Arma"
    ],
    "name:eus_x_preferred":[
        "Arma"
    ],
    "name:fra_x_preferred":[
        "Arma"
    ],
    "name:hun_x_preferred":[
        "Arma"
    ],
    "name:hye_x_preferred":[
        "\u0531\u0580\u0574\u0561"
    ],
    "name:ita_x_preferred":[
        "Arma"
    ],
    "name:new_x_preferred":[
        "\u0905\u0930\u094d\u092e\u093e"
    ],
    "name:nld_x_preferred":[
        "Arma"
    ],
    "name:pol_x_preferred":[
        "Arma"
    ],
    "name:por_x_preferred":[
        "Arma"
    ],
    "name:scn_x_preferred":[
        "Arma"
    ],
    "name:slk_x_preferred":[
        "Arma"
    ],
    "name:spa_x_preferred":[
        "Arma"
    ],
    "name:swe_x_preferred":[
        "Arma"
    ],
    "name:tur_x_preferred":[
        "Arma"
    ],
    "wof:name":"Arma",
    "wof:placetype":"locality"
},
  "geometry": {"coordinates":[-74.47728000000002,-12.72192],"type":"Point"}
}