{
  "type": "Feature",
  "properties": {
    "gn:admin1_code":"06",
    "gn:admin2_code":"603.0",
    "gn:admin3_code":"60301.0",
    "gn:asciiname":"Cahuaypampa",
    "gn:country_code":"PE",
    "gn:dem":2879,
    "gn:feature_class":"P",
    "gn:feature_code":"PPL",
    "gn:name":"Cahuaypampa",
    "gn:population":0,
    "gn:timezone":"America/Lima",
    "iso:country":"PE",
    "wof:name":"Cahuaypampa",
    "wof:placetype":"locality"
},
  "geometry": {"coordinates":[-78.16501,-6.85177],"type":"Point"}
}