{
  "type": "Feature",
  "properties": {
    "gn:admin1_code":"24",
    "gn:admin2_code":"2403.0",
    "gn:admin3_code":"240303.0",
    "gn:asciiname":"Campo Verde",
    "gn:country_code":"PE",
    "gn:dem":643,
    "gn:feature_class":"P",
    "gn:feature_code":"PPL",
    "gn:name":"Campo Verde",
    "gn:population":0,
    "gn:timezone":"America/Lima",
    "iso:country":"PE",
    "wof:name":"Campo Verde",
    "wof:placetype":"locality"
},
  "geometry": {"coordinates":[-80.16667,-3.85],"type":"Point"}
}