{
  "type": "Feature",
  "properties": {
    "gn:admin1_code":"24",
    "gn:admin2_code":"2403.0",
    "gn:admin3_code":"240303.0",
    "gn:asciiname":"Campo Verde",
    "gn:country_code":"PE",
    "gn:dem":643,
    "gn:feature_class":"P",
    "gn:feature_code":"PPL",
    "gn:name":"Campo Verde",
    "gn:population":0,
    "gn:timezone":"America/Lima",
    "iso:country":"PE",
    "name:bpy_x_preferred":[
        "\u0995\u09be\u09ae\u09cd\u09aa\u09cb \u09ad\u09c7\u09b0\u09cd\u09a1\u09c7"
    ],
    "name:ceb_x_preferred":[
        "Campo Verde"
    ],
    "name:eus_x_preferred":[
        "Campo Verde"
    ],
    "name:fra_x_preferred":[
        "Campo Verde"
    ],
    "name:hye_x_preferred":[
        "\u053f\u0561\u0574\u057a\u0578\u0582 \u054e\u0565\u0580\u0564\u056b"
    ],
    "name:ita_x_preferred":[
        "Campo Verde"
    ],
    "name:kaz_x_preferred":[
        "\u041a\u0430\u043c\u043f\u0443-\u0412\u0435\u0440\u0434\u0438"
    ],
    "name:nld_x_preferred":[
        "Campo Verde"
    ],
    "name:nor_x_preferred":[
        "Campo Verde"
    ],
    "name:pol_x_preferred":[
        "Campo Verde"
    ],
    "name:por_x_preferred":[
        "Campo Verde"
    ],
    "name:ron_x_preferred":[
        "Campo Verde"
    ],
    "name:rus_x_preferred":[
        "\u041a\u0430\u043c\u043f\u0443-\u0412\u0435\u0440\u0434\u0438"
    ],
    "name:swe_x_preferred":[
        "Campo Verde"
    ],
    "name:vie_x_preferred":[
        "Campo Verde"
    ],
    "name:vol_x_preferred":[
        "Campo Verde"
    ],
    "name:war_x_preferred":[
        "Campo Verde"
    ],
    "name:zho_x_preferred":[
        "\u574e\u6ce2\u97e6\u5c14\u8fea"
    ],
    "wof:name":"Campo Verde",
    "wof:placetype":"locality"
},
  "geometry": {"coordinates":[-80.16667,-3.85],"type":"Point"}
}