{
  "type": "Feature",
  "properties": {
    "gn:admin1_code":"08",
    "gn:admin2_code":"807.0",
    "gn:admin3_code":"80704.0",
    "gn:asciiname":"Totorane",
    "gn:country_code":"PE",
    "gn:dem":3414,
    "gn:feature_class":"P",
    "gn:feature_code":"PPL",
    "gn:name":"Totorane",
    "gn:population":0,
    "gn:timezone":"America/Lima",
    "iso:country":"PE",
    "wof:name":"Totorane",
    "wof:placetype":"locality"
},
  "geometry": {"coordinates":[-72.06667,-14.25],"type":"Point"}
}