{
  "type": "Feature",
  "properties": {
    "iso:country":"PE",
    "name:ben_x_preferred":[
        "\u09b8\u09be\u09a8 \u09ae\u09be\u09b0\u09cd\u0995\u09cb\u09b8"
    ],
    "name:ell_x_preferred":[
        "\u03a3\u03b1\u03bd \u039c\u03ac\u03c1\u03ba\u03bf\u03c2"
    ],
    "name:eng_x_preferred":[
        "San Marcos"
    ],
    "name:fas_x_preferred":[
        "\u0633\u0627\u0646 \u0645\u0627\u0631\u06a9\u0648\u0633"
    ],
    "name:heb_x_preferred":[
        "\u05e1\u05df \u05de\u05e8\u05e7\u05d5\u05e1"
    ],
    "name:hin_x_preferred":[
        "\u0938\u0948\u0928 \u092e\u093e\u0930\u094d\u0915\u0949\u0938"
    ],
    "name:hun_x_preferred":[
        "San Marcos"
    ],
    "name:ind_x_preferred":[
        "San Marcos"
    ],
    "name:kor_x_preferred":[
        "\uc0b0 \ub9c8\ub974\ucf54\uc2a4"
    ],
    "name:que_x_preferred":[
        "San Markus"
    ],
    "name:spa_x_preferred":[
        "San Marcos"
    ],
    "name:tur_x_preferred":[
        "San Marcos"
    ],
    "name:vie_x_preferred":[
        "San Marcos"
    ],
    "qs:gn_pop":0,
    "qs:name":"San Marcos",
    "qs:name_adm0":"Per\u00fa",
    "qs:name_adm1":"Ancash",
    "qs:photos":95,
    "qs:photos_1k":19,
    "qs:photos_9k":1,
    "qs:photos_9r":3,
    "qs:photos_all":95,
    "qs:photos_sr":3,
    "qs:placetype":"Town",
    "qs:pop_sr":"0",
    "qs:woe_adm0":23424919,
    "wof:name":"San Marcos",
    "wof:placetype":"locality"
},
  "geometry": {"coordinates":[-77.21328699999999,-9.521528],"type":"Point"}
}