{
  "type": "Feature",
  "properties": {
    "iso:country":"PE",
    "name:eng_x_preferred":[
        "San Marcos"
    ],
    "name:que_x_preferred":[
        "San Markus"
    ],
    "name:spa_x_preferred":[
        "San Marcos"
    ],
    "qs:gn_pop":0,
    "qs:name":"San Marcos",
    "qs:name_adm0":"Per\u00fa",
    "qs:name_adm1":"Ancash",
    "qs:photos":95,
    "qs:photos_1k":19,
    "qs:photos_9k":1,
    "qs:photos_9r":3,
    "qs:photos_all":95,
    "qs:photos_sr":3,
    "qs:placetype":"Town",
    "qs:pop_sr":"0",
    "qs:woe_adm0":23424919,
    "wof:name":"San Marcos",
    "wof:placetype":"locality"
},
  "geometry": {"coordinates":[-77.21328699999999,-9.521528],"type":"Point"}
}