{
  "type": "Feature",
  "properties": {
    "gn:admin1_code":"10.0",
    "gn:admin2_code":"1011.0",
    "gn:admin3_code":"101108.0",
    "gn:asciiname":"Chiparajra",
    "gn:country_code":"PE",
    "gn:dem":3823,
    "gn:feature_class":"P",
    "gn:feature_code":"PPL",
    "gn:name":"Chiparajra",
    "gn:population":0,
    "gn:timezone":"America/Lima",
    "iso:country":"PE",
    "wof:name":"Chiparajra",
    "wof:placetype":"locality"
},
  "geometry": {"coordinates":[-76.54524000000001,-9.88709],"type":"Point"}
}