{
  "type": "Feature",
  "properties": {
    "gn:admin1_code":"24",
    "gn:admin2_code":"2402.0",
    "gn:admin3_code":"240202.0",
    "gn:asciiname":"Carrizalillo",
    "gn:country_code":"PE",
    "gn:dem":176,
    "gn:feature_class":"P",
    "gn:feature_code":"PPL",
    "gn:name":"Carrizalillo",
    "gn:population":0,
    "gn:timezone":"America/Lima",
    "iso:country":"PE",
    "wof:name":"Carrizalillo",
    "wof:placetype":"locality"
},
  "geometry": {"coordinates":[-80.58915,-3.86514],"type":"Point"}
}