{
  "type": "Feature",
  "properties": {
    "gn:admin1_code":"10",
    "gn:admin2_code":"1001.0",
    "gn:admin3_code":"100101.0",
    "gn:asciiname":"Nauyan Rondos",
    "gn:country_code":"PE",
    "gn:dem":2784,
    "gn:feature_class":"P",
    "gn:feature_code":"PPL",
    "gn:name":"Nauyan Rondos",
    "gn:population":0,
    "gn:timezone":"America/Lima",
    "iso:country":"PE",
    "name:und_x_variant":[
        "Rondos",
        "Nauyan Rondos"
    ],
    "wof:name":"Nauyan Rondos",
    "wof:placetype":"locality"
},
  "geometry": {"coordinates":[-76.26130000000001,-9.89312],"type":"Point"}
}