{
  "type": "Feature",
  "properties": {
    "gn:admin1_code":"8",
    "gn:admin2_code":"805.0",
    "gn:admin3_code":"80504.0",
    "gn:asciiname":"Huasahuasi",
    "gn:country_code":"PE",
    "gn:dem":3947,
    "gn:feature_class":"P",
    "gn:feature_code":"PPL",
    "gn:name":"Huasahuasi",
    "gn:population":0,
    "gn:timezone":"America/Lima",
    "iso:country":"PE",
    "wof:name":"Huasahuasi",
    "wof:placetype":"locality"
},
  "geometry": {"coordinates":[-71.31565999999999,-14.38597],"type":"Point"}
}