{
  "type": "Feature",
  "properties": {
    "gn:admin1_code":"10.0",
    "gn:admin2_code":"1008.0",
    "gn:admin3_code":"100804.0",
    "gn:asciiname":"Cabracancha",
    "gn:country_code":"PE",
    "gn:dem":2624,
    "gn:feature_class":"P",
    "gn:feature_code":"PPL",
    "gn:name":"Cabracancha",
    "gn:population":0,
    "gn:timezone":"America/Lima",
    "iso:country":"PE",
    "wof:name":"Cabracancha",
    "wof:placetype":"locality"
},
  "geometry": {"coordinates":[-76.05696999999998,-9.85446],"type":"Point"}
}