{
  "type": "Feature",
  "properties": {
    "gn:admin1_code":"13",
    "gn:admin2_code":"1301.0",
    "gn:admin3_code":"130111.0",
    "gn:asciiname":"California",
    "gn:country_code":"PE",
    "gn:dem":18,
    "gn:feature_class":"P",
    "gn:feature_code":"PPL",
    "gn:name":"California",
    "gn:population":0,
    "gn:timezone":"America/Lima",
    "iso:country":"PE",
    "wof:name":"California",
    "wof:placetype":"locality"
},
  "geometry": {"coordinates":[-79.03556,-8.13333],"type":"Point"}
}