{
  "type": "Feature",
  "properties": {
    "gn:admin1_code":"22.0",
    "gn:admin2_code":"2208.0",
    "gn:admin3_code":"220802.0",
    "gn:asciiname":"Bajo Naranjillo",
    "gn:country_code":"PE",
    "gn:dem":876,
    "gn:feature_class":"P",
    "gn:feature_code":"PPLA3",
    "gn:name":"Bajo Naranjillo",
    "gn:population":0,
    "gn:timezone":"America/Lima",
    "iso:country":"PE",
    "wof:name":"Bajo Naranjillo",
    "wof:placetype":"locality"
},
  "geometry": {"coordinates":[-77.38278000000003,-5.81528],"type":"Point"}
}