{
  "type": "Feature",
  "properties": {
    "gn:admin1_code":"21",
    "gn:admin2_code":"2109.0",
    "gn:admin3_code":"210901.0",
    "gn:asciiname":"Pacchani",
    "gn:country_code":"PE",
    "gn:dem":3890,
    "gn:feature_class":"P",
    "gn:feature_code":"PPL",
    "gn:name":"Pacchani",
    "gn:population":0,
    "gn:timezone":"America/La_Paz",
    "iso:country":"PE",
    "name:spa_x_preferred":[
        "Pacchani"
    ],
    "name:spa_x_variant":[
        "Pacchani Chico",
        "Hacienda Pacchani"
    ],
    "wof:name":"Pacchani",
    "wof:placetype":"locality"
},
  "geometry": {"coordinates":[-69.25525,-15.44311],"type":"Point"}
}