{
  "type": "Feature",
  "properties": {
    "gn:admin1_code":"4",
    "gn:admin2_code":"404.0",
    "gn:admin3_code":"40408.0",
    "gn:asciiname":"Anchapalla",
    "gn:country_code":"PE",
    "gn:dem":4757,
    "gn:feature_class":"P",
    "gn:feature_code":"PPL",
    "gn:name":"Anchapalla",
    "gn:population":0,
    "gn:timezone":"America/Lima",
    "iso:country":"PE",
    "wof:name":"Anchapalla",
    "wof:placetype":"locality"
},
  "geometry": {"coordinates":[-72.41568000000002,-15.56412],"type":"Point"}
}