{
  "type": "Feature",
  "properties": {
    "gn:admin1_code":"17.0",
    "gn:admin2_code":"1703.0",
    "gn:asciiname":"Bruno Canahuiri",
    "gn:country_code":"PE",
    "gn:dem":278,
    "gn:feature_class":"P",
    "gn:feature_code":"PPL",
    "gn:name":"Bruno Canahuiri",
    "gn:population":0,
    "gn:timezone":"America/Lima",
    "iso:country":"PE",
    "name:spa_x_preferred":[
        "Bruno Canahuiri"
    ],
    "wof:name":"Bruno Canahuiri",
    "wof:placetype":"locality"
},
  "geometry": {"coordinates":[-69.0425,-11.87525],"type":"Point"}
}