{
  "type": "Feature",
  "properties": {
    "gn:admin1_code":"13",
    "gn:admin2_code":"1301.0",
    "gn:admin3_code":"130101.0",
    "gn:asciiname":"Palmo",
    "gn:cc2":"PE",
    "gn:country_code":"PE",
    "gn:dem":26,
    "gn:feature_class":"P",
    "gn:feature_code":"PPL",
    "gn:name":"Palmo",
    "gn:population":0,
    "gn:timezone":"America/Lima",
    "iso:country":"PE",
    "name:und_x_variant":[
        "El Palmo",
        "Palmo Hacienda",
        "Palmo"
    ],
    "wof:name":"Palmo",
    "wof:placetype":"locality"
},
  "geometry": {"coordinates":[-79.00444,-8.13111],"type":"Point"}
}