{
  "type": "Feature",
  "properties": {
    "gn:admin1_code":"4.0",
    "gn:admin2_code":"401.0",
    "gn:admin3_code":"40125.0",
    "gn:asciiname":"La Cano",
    "gn:country_code":"PE",
    "gn:dem":1148,
    "gn:feature_class":"P",
    "gn:feature_code":"PPL",
    "gn:name":"La Cano",
    "gn:population":0,
    "gn:timezone":"America/Lima",
    "iso:country":"PE",
    "wof:name":"La Cano",
    "wof:placetype":"locality"
},
  "geometry": {"coordinates":[-71.93777,-16.49707],"type":"Point"}
}