{
  "type": "Feature",
  "properties": {
    "gn:admin1_code":"8",
    "gn:admin2_code":"808.0",
    "gn:admin3_code":"80803.0",
    "gn:asciiname":"Mayupata",
    "gn:country_code":"PE",
    "gn:dem":3947,
    "gn:feature_class":"P",
    "gn:feature_code":"PPL",
    "gn:name":"Mayupata",
    "gn:population":0,
    "gn:timezone":"America/Lima",
    "iso:country":"PE",
    "wof:name":"Mayupata",
    "wof:placetype":"locality"
},
  "geometry": {"coordinates":[-71.60162,-14.74805],"type":"Point"}
}