{
  "type": "Feature",
  "properties": {
    "gn:admin1_code":"15",
    "gn:admin2_code":"1507.0",
    "gn:admin3_code":"150702.0",
    "gn:asciiname":"Chillace Chico",
    "gn:country_code":"PE",
    "gn:dem":1337,
    "gn:feature_class":"P",
    "gn:feature_code":"PPL",
    "gn:name":"Chillace Chico",
    "gn:population":0,
    "gn:timezone":"America/Lima",
    "iso:country":"PE",
    "name:spa_x_preferred":[
        "Chillace Chico"
    ],
    "wof:name":"Chillace Chico",
    "wof:placetype":"locality"
},
  "geometry": {"coordinates":[-76.58747,-12.03696],"type":"Point"}
}