{
  "type": "Feature",
  "properties": {
    "gn:admin1_code":"3",
    "gn:admin2_code":"304.0",
    "gn:admin3_code":"30415.0",
    "gn:asciiname":"Jullo",
    "gn:country_code":"PE",
    "gn:dem":3286,
    "gn:feature_class":"P",
    "gn:feature_code":"PPL",
    "gn:name":"Jullo",
    "gn:population":0,
    "gn:timezone":"America/Lima",
    "iso:country":"PE",
    "wof:name":"Jullo",
    "wof:placetype":"locality"
},
  "geometry": {"coordinates":[-73.10751999999999,-13.89383],"type":"Point"}
}