{
  "type": "Feature",
  "properties": {
    "gn:admin1_code":"22.0",
    "gn:admin2_code":"2205.0",
    "gn:admin3_code":"220505.0",
    "gn:asciiname":"Belgica",
    "gn:country_code":"PE",
    "gn:dem":229,
    "gn:feature_class":"P",
    "gn:feature_code":"PPL",
    "gn:name":"B\u00e9lgica",
    "gn:population":0,
    "gn:timezone":"America/Lima",
    "iso:country":"PE",
    "name:spa_x_preferred":[
        "B\u00e9lgica"
    ],
    "wof:name":"Belgica",
    "wof:placetype":"locality"
},
  "geometry": {"coordinates":[-76.46711999999999,-6.53454],"type":"Point"}
}