{
  "type": "Feature",
  "properties": {
    "gn:admin1_code":"9.0",
    "gn:admin2_code":"907.0",
    "gn:admin3_code":"90714.0",
    "gn:asciiname":"Chagueleta",
    "gn:country_code":"PE",
    "gn:dem":3129,
    "gn:feature_class":"P",
    "gn:feature_code":"PPL",
    "gn:name":"Chagueleta",
    "gn:population":0,
    "gn:timezone":"America/Lima",
    "iso:country":"PE",
    "wof:name":"Chagueleta",
    "wof:placetype":"locality"
},
  "geometry": {"coordinates":[-74.74195999999998,-12.21918],"type":"Point"}
}