{
  "type": "Feature",
  "properties": {
    "gn:admin1_code":"2.0",
    "gn:admin2_code":"205.0",
    "gn:asciiname":"Moyahuain",
    "gn:country_code":"PE",
    "gn:dem":3904,
    "gn:feature_class":"P",
    "gn:feature_code":"PPL",
    "gn:name":"Moyahuain",
    "gn:population":0,
    "gn:timezone":"America/Lima",
    "iso:country":"PE",
    "wof:name":"Moyahuain",
    "wof:placetype":"locality"
},
  "geometry": {"coordinates":[-76.89220999999998,-9.97041],"type":"Point"}
}