{
  "type": "Feature",
  "properties": {
    "gn:admin1_code":"05",
    "gn:admin2_code":"502.0",
    "gn:admin3_code":"50205.0",
    "gn:asciiname":"Rangrahuasi",
    "gn:country_code":"PE",
    "gn:dem":4368,
    "gn:feature_class":"P",
    "gn:feature_code":"PPL",
    "gn:name":"Rangrahuasi",
    "gn:population":0,
    "gn:timezone":"America/Lima",
    "iso:country":"PE",
    "wof:name":"Rangrahuasi",
    "wof:placetype":"locality"
},
  "geometry": {"coordinates":[-74.71212,-13.45681],"type":"Point"}
}