{
  "type": "Feature",
  "properties": {
    "gn:admin1_code":"11",
    "gn:admin2_code":"1101.0",
    "gn:admin3_code":"110108.0",
    "gn:asciiname":"Hacienda Rio Seco",
    "gn:country_code":"PE",
    "gn:dem":386,
    "gn:feature_class":"P",
    "gn:feature_code":"PPL",
    "gn:name":"Hacienda Rio Seco",
    "gn:population":0,
    "gn:timezone":"America/Lima",
    "iso:country":"PE",
    "wof:name":"Hacienda Rio Seco",
    "wof:placetype":"locality"
},
  "geometry": {"coordinates":[-75.88459,-13.90723],"type":"Point"}
}