{
  "type": "Feature",
  "properties": {
    "gn:admin1_code":"04",
    "gn:admin2_code":"404.0",
    "gn:admin3_code":"40401.0",
    "gn:asciiname":"Hacienda Ongoro",
    "gn:country_code":"PE",
    "gn:dem":808,
    "gn:feature_class":"P",
    "gn:feature_code":"PPL",
    "gn:name":"Hacienda Ongoro",
    "gn:population":0,
    "gn:timezone":"America/Lima",
    "iso:country":"PE",
    "name:und_x_variant":[
        "Ongoro",
        "Ongoro Hacienda",
        "Hacienda Ongoro"
    ],
    "wof:name":"Hacienda Ongoro",
    "wof:placetype":"locality"
},
  "geometry": {"coordinates":[-72.47041999999998,-15.91783],"type":"Point"}
}