{
  "type": "Feature",
  "properties": {
    "gn:admin1_code":"9.0",
    "gn:admin2_code":"907.0",
    "gn:admin3_code":"90701.0",
    "gn:asciiname":"Sequespere",
    "gn:country_code":"PE",
    "gn:dem":4185,
    "gn:feature_class":"P",
    "gn:feature_code":"PPL",
    "gn:name":"Sequespere",
    "gn:population":0,
    "gn:timezone":"America/Lima",
    "iso:country":"PE",
    "wof:name":"Sequespere",
    "wof:placetype":"locality"
},
  "geometry": {"coordinates":[-74.87136,-12.34417],"type":"Point"}
}