{
  "type": "Feature",
  "properties": {
    "gn:admin1_code":"2",
    "gn:admin2_code":"215.0",
    "gn:admin3_code":"21510.0",
    "gn:asciiname":"Chucacala",
    "gn:country_code":"PE",
    "gn:dem":2108,
    "gn:feature_class":"P",
    "gn:feature_code":"PPLL",
    "gn:name":"Chucacala",
    "gn:population":0,
    "gn:timezone":"America/Lima",
    "iso:country":"PE",
    "wof:name":"Chucacala",
    "wof:placetype":"locality"
},
  "geometry": {"coordinates":[-78.07083,-8.51],"type":"Point"}
}