{
  "type": "Feature",
  "properties": {
    "gn:admin1_code":"10",
    "gn:admin2_code":"1002.0",
    "gn:admin3_code":"100201.0",
    "gn:asciiname":"Salapampa",
    "gn:country_code":"PE",
    "gn:dem":2549,
    "gn:feature_class":"P",
    "gn:feature_code":"PPL",
    "gn:name":"Salapampa",
    "gn:population":0,
    "gn:timezone":"America/Lima",
    "iso:country":"PE",
    "wof:name":"Salapampa",
    "wof:placetype":"locality"
},
  "geometry": {"coordinates":[-76.16656,-10.20993],"type":"Point"}
}