{
  "type": "Feature",
  "properties": {
    "gn:admin1_code":"21",
    "gn:admin2_code":"2103",
    "gn:asciiname":"Pacha Pata",
    "gn:country_code":"PE",
    "gn:dem":3981,
    "gn:feature_class":"P",
    "gn:feature_code":"PPL",
    "gn:name":"Pacha Pata",
    "gn:population":0,
    "gn:timezone":"America/Lima",
    "iso:country":"PE",
    "name:spa_x_preferred":[
        "Pacha Pata"
    ],
    "wof:name":"Pacha Pata",
    "wof:placetype":"locality"
},
  "geometry": {"coordinates":[-69.92832,-13.95016],"type":"Point"}
}