{
  "type": "Feature",
  "properties": {
    "gn:admin1_code":"15",
    "gn:admin2_code":"1503.0",
    "gn:admin3_code":"150303.0",
    "gn:asciiname":"Raianllo",
    "gn:country_code":"PE",
    "gn:dem":2528,
    "gn:feature_class":"P",
    "gn:feature_code":"PPL",
    "gn:name":"Raianllo",
    "gn:population":0,
    "gn:timezone":"America/Lima",
    "iso:country":"PE",
    "wof:name":"Raianllo",
    "wof:placetype":"locality"
},
  "geometry": {"coordinates":[-77.09489000000001,-10.60156],"type":"Point"}
}