{
  "type": "Feature",
  "properties": {
    "gn:admin1_code":"25",
    "gn:admin2_code":"2501.0",
    "gn:admin3_code":"250103.0",
    "gn:asciiname":"Cabana",
    "gn:country_code":"PE",
    "gn:dem":156,
    "gn:feature_class":"P",
    "gn:feature_code":"PPL",
    "gn:name":"Caba\u00f1a",
    "gn:population":0,
    "gn:timezone":"America/Lima",
    "iso:country":"PE",
    "name:bre_x_preferred":[
        "Cabana"
    ],
    "name:ceb_x_preferred":[
        "Cabana"
    ],
    "name:deu_x_preferred":[
        "Cabana"
    ],
    "name:fra_x_preferred":[
        "Cabana"
    ],
    "name:glg_x_preferred":[
        "Cabana"
    ],
    "name:ita_x_preferred":[
        "Cabana"
    ],
    "name:por_x_preferred":[
        "Cabana"
    ],
    "name:spa_x_preferred":[
        "Cabana"
    ],
    "wof:name":"Cabana",
    "wof:placetype":"locality"
},
  "geometry": {"coordinates":[-74.49665999999998,-8.94268],"type":"Point"}
}