{
  "type": "Feature",
  "properties": {
    "gn:admin1_code":"01",
    "gn:admin2_code":"107.0",
    "gn:admin3_code":"10706.0",
    "gn:asciiname":"Yamon",
    "gn:country_code":"PE",
    "gn:dem":1039,
    "gn:feature_class":"P",
    "gn:feature_code":"PPL",
    "gn:name":"Yam\u00f3n",
    "gn:population":0,
    "gn:timezone":"America/Lima",
    "iso:country":"PE",
    "wof:name":"Yamon",
    "wof:placetype":"locality"
},
  "geometry": {"coordinates":[-78.5283,-6.04984],"type":"Point"}
}