{
  "type": "Feature",
  "properties": {
    "gn:admin1_code":"16",
    "gn:admin2_code":"1602.0",
    "gn:admin3_code":"160202.0",
    "gn:asciiname":"San Juan de Palometayacu",
    "gn:country_code":"PE",
    "gn:dem":218,
    "gn:feature_class":"P",
    "gn:feature_code":"PPL",
    "gn:name":"San Juan de Palometayacu",
    "gn:population":0,
    "gn:timezone":"America/Lima",
    "iso:country":"PE",
    "name:spa_x_preferred":[
        "San Juan de Palometayacu"
    ],
    "wof:name":"San Juan de Palometayacu",
    "wof:placetype":"locality"
},
  "geometry": {"coordinates":[-76.6622,-5.55185],"type":"Point"}
}