{
  "type": "Feature",
  "properties": {
    "gn:admin1_code":"04",
    "gn:admin2_code":"406.0",
    "gn:admin3_code":"40602.0",
    "gn:asciiname":"Pariaviri",
    "gn:country_code":"PE",
    "gn:dem":4626,
    "gn:feature_class":"P",
    "gn:feature_code":"PPL",
    "gn:name":"Pariaviri",
    "gn:population":0,
    "gn:timezone":"America/Lima",
    "iso:country":"PE",
    "wof:name":"Pariaviri",
    "wof:placetype":"locality"
},
  "geometry": {"coordinates":[-72.75,-15.61667],"type":"Point"}
}