{
  "type": "Feature",
  "properties": {
    "gn:admin1_code":"05",
    "gn:admin2_code":"501.0",
    "gn:admin3_code":"50113.0",
    "gn:asciiname":"Ccechca",
    "gn:country_code":"PE",
    "gn:dem":3166,
    "gn:feature_class":"P",
    "gn:feature_code":"PPL",
    "gn:name":"Ccechca",
    "gn:population":0,
    "gn:timezone":"America/Lima",
    "iso:country":"PE",
    "wof:name":"Ccechca",
    "wof:placetype":"locality"
},
  "geometry": {"coordinates":[-74.10535,-13.20692],"type":"Point"}
}