{
  "type": "Feature",
  "properties": {
    "gn:admin1_code":"6",
    "gn:admin2_code":"604.0",
    "gn:admin3_code":"60419.0",
    "gn:asciiname":"Chalamarca",
    "gn:country_code":"PE",
    "gn:dem":2377,
    "gn:feature_class":"P",
    "gn:feature_code":"PPLA3",
    "gn:name":"Chalamarca",
    "gn:population":0,
    "gn:timezone":"America/Lima",
    "iso:country":"PE",
    "wof:name":"Chalamarca",
    "wof:placetype":"locality"
},
  "geometry": {"coordinates":[-78.46861,-6.49139],"type":"Point"}
}