{
  "type": "Feature",
  "properties": {
    "gn:admin1_code":"17.0",
    "gn:admin2_code":"1703.0",
    "gn:asciiname":"Meliton Mejia",
    "gn:country_code":"PE",
    "gn:dem":300,
    "gn:feature_class":"P",
    "gn:feature_code":"PPL",
    "gn:name":"Meliton Mejia",
    "gn:population":0,
    "gn:timezone":"America/Lima",
    "iso:country":"PE",
    "name:spa_x_preferred":[
        "Meliton Mejia"
    ],
    "wof:name":"Meliton Mejia",
    "wof:placetype":"locality"
},
  "geometry": {"coordinates":[-69.105,-11.80526],"type":"Point"}
}