{
  "type": "Feature",
  "properties": {
    "gn:admin1_code":"21",
    "gn:admin2_code":"2106.0",
    "gn:admin3_code":"210602.0",
    "gn:asciiname":"Coricancha",
    "gn:country_code":"PE",
    "gn:dem":4340,
    "gn:feature_class":"P",
    "gn:feature_code":"PPL",
    "gn:name":"Coricancha",
    "gn:population":0,
    "gn:timezone":"America/Lima",
    "iso:country":"PE",
    "name:spa_x_preferred":[
        "Coricancha"
    ],
    "wof:name":"Coricancha",
    "wof:placetype":"locality"
},
  "geometry": {"coordinates":[-69.33333,-15.01667],"type":"Point"}
}