{
  "type": "Feature",
  "properties": {
    "gn:admin1_code":"21",
    "gn:admin2_code":"2106.0",
    "gn:admin3_code":"210602.0",
    "gn:asciiname":"Coricancha",
    "gn:country_code":"PE",
    "gn:dem":4340,
    "gn:feature_class":"P",
    "gn:feature_code":"PPL",
    "gn:name":"Coricancha",
    "gn:population":0,
    "gn:timezone":"America/Lima",
    "iso:country":"PE",
    "name:cat_x_preferred":[
        "Coricancha"
    ],
    "name:deu_x_preferred":[
        "Coricancha"
    ],
    "name:epo_x_preferred":[
        "Korikan\u0109a"
    ],
    "name:hrv_x_preferred":[
        "Coricancha"
    ],
    "name:ita_x_preferred":[
        "Coricancha"
    ],
    "name:jpn_x_preferred":[
        "\u592a\u967d\u795e\u6bbf"
    ],
    "name:kat_x_preferred":[
        "\u10d9\u10dd\u10e0\u10d8\u10d9\u10d0\u10dc\u10e9\u10d0"
    ],
    "name:kor_x_preferred":[
        "\ucf54\ub9ac\uce78\ucc28"
    ],
    "name:nld_x_preferred":[
        "Coricancha"
    ],
    "name:nno_x_preferred":[
        "Coricancha"
    ],
    "name:nor_x_preferred":[
        "Qurikancha"
    ],
    "name:pol_x_preferred":[
        "Coricancha"
    ],
    "name:por_x_preferred":[
        "Coricancha"
    ],
    "name:que_x_preferred":[
        "Qurikancha"
    ],
    "name:rus_x_preferred":[
        "\u041a\u043e\u0440\u0438\u043a\u0430\u043d\u0447\u0430"
    ],
    "name:slk_x_preferred":[
        "Coricancha"
    ],
    "name:spa_x_preferred":[
        "Coricancha"
    ],
    "name:srp_x_preferred":[
        "\u041a\u043e\u0440\u0438\u043a\u0430\u043d\u0447\u0430"
    ],
    "name:swe_x_preferred":[
        "Coricancha"
    ],
    "name:tur_x_preferred":[
        "Coricancha"
    ],
    "name:ukr_x_preferred":[
        "\u041a\u043e\u0440\u0456\u043a\u0430\u043d\u0447\u0430"
    ],
    "name:vie_x_preferred":[
        "Coricancha"
    ],
    "name:zho_x_preferred":[
        "\u592a\u9633\u795e\u6bbf"
    ],
    "wof:name":"Coricancha",
    "wof:placetype":"locality"
},
  "geometry": {"coordinates":[-69.33333,-15.01667],"type":"Point"}
}