{
  "type": "Feature",
  "properties": {
    "gn:admin1_code":"16.0",
    "gn:admin2_code":"1601.0",
    "gn:admin3_code":"160102.0",
    "gn:asciiname":"Diamante Azul",
    "gn:country_code":"PE",
    "gn:dem":94,
    "gn:feature_class":"P",
    "gn:feature_code":"PPL",
    "gn:name":"Diamante Azul",
    "gn:population":0,
    "gn:timezone":"America/Lima",
    "iso:country":"PE",
    "name:jpn_x_preferred":[
        "\u30c7\u30a3\u30a2\u30de\u30f3\u30c6\u30fb\u30a2\u30b9\u30eb"
    ],
    "wof:name":"Diamante Azul",
    "wof:placetype":"locality"
},
  "geometry": {"coordinates":[-73.77939000000001,-3.90083],"type":"Point"}
}