{
  "type": "Feature",
  "properties": {
    "gn:admin1_code":"04",
    "gn:admin2_code":"403.0",
    "gn:admin3_code":"40306.0",
    "gn:asciiname":"Yanamachay",
    "gn:country_code":"PE",
    "gn:dem":3285,
    "gn:feature_class":"P",
    "gn:feature_code":"PPL",
    "gn:name":"Yanamachay",
    "gn:population":0,
    "gn:timezone":"America/Lima",
    "iso:country":"PE",
    "wof:name":"Yanamachay",
    "wof:placetype":"locality"
},
  "geometry": {"coordinates":[-73.62958,-15.53748],"type":"Point"}
}