{
  "type": "Feature",
  "properties": {
    "gn:admin1_code":"2.0",
    "gn:admin2_code":"210.0",
    "gn:admin3_code":"21011.0",
    "gn:asciiname":"Chequil",
    "gn:country_code":"PE",
    "gn:dem":3157,
    "gn:feature_class":"P",
    "gn:feature_code":"PPL",
    "gn:name":"Chequil",
    "gn:population":0,
    "gn:timezone":"America/Lima",
    "iso:country":"PE",
    "wof:name":"Chequil",
    "wof:placetype":"locality"
},
  "geometry": {"coordinates":[-76.99606999999997,-9.33651],"type":"Point"}
}