{
  "type": "Feature",
  "properties": {
    "gn:admin1_code":"13",
    "gn:admin2_code":"1302.0",
    "gn:admin3_code":"130205.0",
    "gn:asciiname":"Manco Capac",
    "gn:country_code":"PE",
    "gn:dem":47,
    "gn:feature_class":"P",
    "gn:feature_code":"PPL",
    "gn:name":"Manco C\u00e1pac",
    "gn:population":0,
    "gn:timezone":"America/Lima",
    "iso:country":"PE",
    "wof:name":"Manco Capac",
    "wof:placetype":"locality"
},
  "geometry": {"coordinates":[-79.32015,-7.7693],"type":"Point"}
}