{
  "type": "Feature",
  "properties": {
    "gn:admin1_code":"12",
    "gn:admin2_code":"1206.0",
    "gn:admin3_code":"120606.0",
    "gn:asciiname":"La Brena",
    "gn:country_code":"PE",
    "gn:dem":1160,
    "gn:feature_class":"P",
    "gn:feature_code":"PPL",
    "gn:name":"La Bre\u00f1a",
    "gn:population":0,
    "gn:timezone":"America/Lima",
    "iso:country":"PE",
    "wof:name":"La Brena",
    "wof:placetype":"locality"
},
  "geometry": {"coordinates":[-74.50811,-11.49967],"type":"Point"}
}