{
  "type": "Feature",
  "properties": {
    "gn:admin1_code":"09",
    "gn:admin2_code":"906.0",
    "gn:admin3_code":"90607.0",
    "gn:asciiname":"Tablacocha",
    "gn:country_code":"PE",
    "gn:dem":4502,
    "gn:feature_class":"P",
    "gn:feature_code":"PPL",
    "gn:name":"Tablacocha",
    "gn:population":0,
    "gn:timezone":"America/Lima",
    "iso:country":"PE",
    "wof:name":"Tablacocha",
    "wof:placetype":"locality"
},
  "geometry": {"coordinates":[-75.06103,-13.48939],"type":"Point"}
}