{
  "type": "Feature",
  "properties": {
    "gn:admin1_code":"17",
    "gn:admin2_code":"1701.0",
    "gn:admin3_code":"170101.0",
    "gn:asciiname":"Cachuela",
    "gn:country_code":"PE",
    "gn:dem":181,
    "gn:feature_class":"P",
    "gn:feature_code":"PPL",
    "gn:name":"Cachuela",
    "gn:population":0,
    "gn:timezone":"America/Lima",
    "iso:country":"PE",
    "name:spa_x_preferred":[
        "Cachuela"
    ],
    "name:spa_x_variant":[
        "La Cachuela"
    ],
    "wof:name":"Cachuela",
    "wof:placetype":"locality"
},
  "geometry": {"coordinates":[-69.16428000000001,-12.53177],"type":"Point"}
}