{
  "type": "Feature",
  "properties": {
    "gn:admin1_code":"04",
    "gn:admin2_code":"405.0",
    "gn:admin3_code":"40504.0",
    "gn:asciiname":"Urayjayune",
    "gn:country_code":"PE",
    "gn:dem":4460,
    "gn:feature_class":"P",
    "gn:feature_code":"PPL",
    "gn:name":"Urayjayune",
    "gn:population":0,
    "gn:timezone":"America/Lima",
    "iso:country":"PE",
    "wof:name":"Urayjayune",
    "wof:placetype":"locality"
},
  "geometry": {"coordinates":[-71.03055999999999,-15.57333],"type":"Point"}
}