{
  "type": "Feature",
  "properties": {
    "gn:admin1_code":"01",
    "gn:admin2_code":"103.0",
    "gn:admin3_code":"10302.0",
    "gn:asciiname":"Chisquilla",
    "gn:country_code":"PE",
    "gn:dem":2879,
    "gn:feature_class":"P",
    "gn:feature_code":"PPLA3",
    "gn:name":"Chisquilla",
    "gn:population":0,
    "gn:timezone":"America/Lima",
    "iso:country":"PE",
    "wof:name":"Chisquilla",
    "wof:placetype":"locality"
},
  "geometry": {"coordinates":[-77.73333000000002,-5.88333],"type":"Point"}
}