{
  "type": "Feature",
  "properties": {
    "gn:country":"PE",
    "iso:country":"PE",
    "qs:name":"Magdalena Nueva",
    "qs:name_adm0":"Per\u00fa",
    "qs:name_adm1":"Lima Metropolitan Area",
    "qs:photos":2723,
    "qs:photos_1k":552,
    "qs:photos_9k":12,
    "qs:photos_9r":10,
    "qs:photos_all":2723,
    "qs:photos_sr":18,
    "qs:placetype":"Town",
    "qs:pop_sr":"0",
    "wof:name":"Magdalena Nueva",
    "wof:placetype":"locality"
},
  "geometry": {"coordinates":[-77.069091,-12.100759],"type":"Point"}
}