{
  "type": "Feature",
  "properties": {
    "gn:admin1_code":"04",
    "gn:admin2_code":"403.0",
    "gn:admin3_code":"40308.0",
    "gn:asciiname":"El Convento",
    "gn:country_code":"PE",
    "gn:dem":1277,
    "gn:feature_class":"P",
    "gn:feature_code":"PPL",
    "gn:name":"El Convento",
    "gn:population":0,
    "gn:timezone":"America/Lima",
    "iso:country":"PE",
    "name:und_x_variant":[
        "Convento",
        "El Convento"
    ],
    "wof:name":"El Convento",
    "wof:placetype":"locality"
},
  "geometry": {"coordinates":[-73.83821999999998,-15.72191],"type":"Point"}
}