{
  "type": "Feature",
  "properties": {
    "gn:admin1_code":"13",
    "gn:admin2_code":"1309.0",
    "gn:admin3_code":"130908.0",
    "gn:asciiname":"Sartimbamba",
    "gn:cc2":"PE",
    "gn:country_code":"PE",
    "gn:dem":2685,
    "gn:feature_class":"P",
    "gn:feature_code":"PPLA3",
    "gn:name":"Sartimbamba",
    "gn:population":0,
    "gn:timezone":"America/Lima",
    "iso:country":"PE",
    "name:und_x_variant":[
        "Sart\u00edn",
        "Sartibamba",
        "Sartimbamba"
    ],
    "wof:name":"Sartimbamba",
    "wof:placetype":"locality"
},
  "geometry": {"coordinates":[-77.74361,-7.69917],"type":"Point"}
}