{
  "type": "Feature",
  "properties": {
    "gn:admin1_code":"08",
    "gn:admin2_code":"801.0",
    "gn:admin3_code":"80103.0",
    "gn:asciiname":"Poroy",
    "gn:country_code":"PE",
    "gn:dem":3490,
    "gn:feature_class":"P",
    "gn:feature_code":"PPLA3",
    "gn:name":"Poroy",
    "gn:population":0,
    "gn:timezone":"America/Lima",
    "iso:country":"PE",
    "name:und_x_variant":[
        "Poro",
        "Poroy"
    ],
    "wof:name":"Poroy",
    "wof:placetype":"locality"
},
  "geometry": {"coordinates":[-72.04333000000003,-13.495],"type":"Point"}
}