{
  "type": "Feature",
  "properties": {
    "gn:admin1_code":"04",
    "gn:admin2_code":"408.0",
    "gn:admin3_code":"40811.0",
    "gn:asciiname":"Ushqui",
    "gn:country_code":"PE",
    "gn:dem":3252,
    "gn:feature_class":"P",
    "gn:feature_code":"PPL",
    "gn:name":"Ushqui",
    "gn:population":0,
    "gn:timezone":"America/Lima",
    "iso:country":"PE",
    "name:spa_x_preferred":[
        "Ushqui"
    ],
    "wof:name":"Ushqui",
    "wof:placetype":"locality"
},
  "geometry": {"coordinates":[-73.02676,-15.49502],"type":"Point"}
}