{
  "type": "Feature",
  "properties": {
    "gn:admin1_code":"21",
    "gn:admin2_code":"2101.0",
    "gn:admin3_code":"210110.0",
    "gn:asciiname":"Totorane",
    "gn:cc2":"PE",
    "gn:country_code":"PE",
    "gn:dem":3989,
    "gn:feature_class":"P",
    "gn:feature_code":"PPL",
    "gn:name":"Totorane",
    "gn:population":0,
    "gn:timezone":"America/Lima",
    "iso:country":"PE",
    "name:und_x_variant":[
        "Totorane Hacienda",
        "Totorane"
    ],
    "wof:name":"Totorane",
    "wof:placetype":"locality"
},
  "geometry": {"coordinates":[-70.09999999999999,-15.78333],"type":"Point"}
}