{
  "type": "Feature",
  "properties": {
    "gn:admin1_code":"05",
    "gn:admin2_code":"501.0",
    "gn:asciiname":"Jahuilca",
    "gn:country_code":"PE",
    "gn:dem":3071,
    "gn:feature_class":"P",
    "gn:feature_code":"PPL",
    "gn:name":"Jahuilca",
    "gn:population":0,
    "gn:timezone":"America/Lima",
    "iso:country":"PE",
    "wof:name":"Jahuilca",
    "wof:placetype":"locality"
},
  "geometry": {"coordinates":[-74.02873000000002,-13.22931],"type":"Point"}
}