{
  "type": "Feature",
  "properties": {
    "gn:admin1_code":"14",
    "gn:admin2_code":"1401.0",
    "gn:admin3_code":"140113.0",
    "gn:asciiname":"Nuevo Reque",
    "gn:country_code":"PE",
    "gn:dem":23,
    "gn:feature_class":"P",
    "gn:feature_code":"PPL",
    "gn:name":"Nuevo Reque",
    "gn:population":0,
    "gn:timezone":"America/Lima",
    "iso:country":"PE",
    "wof:name":"Nuevo Reque",
    "wof:placetype":"locality"
},
  "geometry": {"coordinates":[-79.81411,-6.87795],"type":"Point"}
}