{
  "type": "Feature",
  "properties": {
    "gn:admin1_code":"5.0",
    "gn:admin2_code":"504.0",
    "gn:admin3_code":"50406.0",
    "gn:asciiname":"Llulluchapata",
    "gn:country_code":"PE",
    "gn:dem":3512,
    "gn:feature_class":"P",
    "gn:feature_code":"PPL",
    "gn:name":"Llulluchapata",
    "gn:population":0,
    "gn:timezone":"America/Lima",
    "iso:country":"PE",
    "wof:name":"Llulluchapata",
    "wof:placetype":"locality"
},
  "geometry": {"coordinates":[-74.14881,-12.60416],"type":"Point"}
}