{
  "type": "Feature",
  "properties": {
    "gn:admin1_code":"12",
    "gn:admin2_code":"1206.0",
    "gn:admin3_code":"120601.0",
    "gn:asciiname":"San Pascual",
    "gn:country_code":"PE",
    "gn:dem":568,
    "gn:feature_class":"P",
    "gn:feature_code":"PPL",
    "gn:name":"San Pascual",
    "gn:population":0,
    "gn:timezone":"America/Lima",
    "iso:country":"PE",
    "name:ceb_x_preferred":[
        "San Pascual"
    ],
    "name:deu_x_preferred":[
        "San Pascual"
    ],
    "name:fra_x_preferred":[
        "San Pascual"
    ],
    "name:ilo_x_preferred":[
        "San Pascual"
    ],
    "name:ita_x_preferred":[
        "San Pascual"
    ],
    "name:nld_x_preferred":[
        "San Pascual"
    ],
    "name:sco_x_preferred":[
        "San Pascual"
    ],
    "name:spa_x_preferred":[
        "San Pascual"
    ],
    "name:swe_x_preferred":[
        "San Pascual"
    ],
    "name:vie_x_preferred":[
        "San Pascual"
    ],
    "name:war_x_preferred":[
        "San Pascual"
    ],
    "wof:name":"San Pascual",
    "wof:placetype":"locality"
},
  "geometry": {"coordinates":[-74.57409,-11.19148],"type":"Point"}
}