{
  "type": "Feature",
  "properties": {
    "gn:admin1_code":"15",
    "gn:admin2_code":"1510.0",
    "gn:admin3_code":"151022.0",
    "gn:asciiname":"San Pedro de Pilas",
    "gn:country_code":"PE",
    "gn:dem":2519,
    "gn:feature_class":"P",
    "gn:feature_code":"PPL",
    "gn:name":"San Pedro de Pilas",
    "gn:population":0,
    "gn:timezone":"America/Lima",
    "iso:country":"PE",
    "wof:name":"San Pedro de Pilas",
    "wof:placetype":"locality"
},
  "geometry": {"coordinates":[-76.23333000000002,-12.48333],"type":"Point"}
}