{
  "type": "Feature",
  "properties": {
    "gn:admin1_code":"9.0",
    "gn:admin2_code":"903.0",
    "gn:admin3_code":"90306.0",
    "gn:asciiname":"Huichccapata",
    "gn:country_code":"PE",
    "gn:dem":4182,
    "gn:feature_class":"P",
    "gn:feature_code":"PPL",
    "gn:name":"Huichccapata",
    "gn:population":0,
    "gn:timezone":"America/Lima",
    "iso:country":"PE",
    "wof:name":"Huichccapata",
    "wof:placetype":"locality"
},
  "geometry": {"coordinates":[-74.60718,-13.03407],"type":"Point"}
}