{
  "type": "Feature",
  "properties": {
    "gn:admin1_code":"1",
    "gn:admin2_code":"101.0",
    "gn:admin3_code":"10110.0",
    "gn:asciiname":"Puromacho",
    "gn:country_code":"PE",
    "gn:dem":3015,
    "gn:feature_class":"P",
    "gn:feature_code":"PPLL",
    "gn:name":"Puromacho",
    "gn:population":0,
    "gn:timezone":"America/Lima",
    "iso:country":"PE",
    "wof:name":"Puromacho",
    "wof:placetype":"locality"
},
  "geometry": {"coordinates":[-77.81780999999999,-6.7656],"type":"Point"}
}