{
  "type": "Feature",
  "properties": {
    "gn:admin1_code":"05",
    "gn:admin2_code":"501.0",
    "gn:admin3_code":"50114.0",
    "gn:asciiname":"Huamanccasa",
    "gn:country_code":"PE",
    "gn:dem":4024,
    "gn:feature_class":"P",
    "gn:feature_code":"PPL",
    "gn:name":"Huamanccasa",
    "gn:population":0,
    "gn:timezone":"America/Lima",
    "iso:country":"PE",
    "wof:name":"Huamanccasa",
    "wof:placetype":"locality"
},
  "geometry": {"coordinates":[-74.47765,-13.37458],"type":"Point"}
}