{
  "type": "Feature",
  "properties": {
    "gn:admin1_code":"3",
    "gn:admin2_code":"302.0",
    "gn:admin3_code":"30212.0",
    "gn:asciiname":"Cahuayna",
    "gn:country_code":"PE",
    "gn:dem":4003,
    "gn:feature_class":"P",
    "gn:feature_code":"PPL",
    "gn:name":"Cahuayna",
    "gn:population":0,
    "gn:timezone":"America/Lima",
    "iso:country":"PE",
    "wof:name":"Cahuayna",
    "wof:placetype":"locality"
},
  "geometry": {"coordinates":[-73.58199999999999,-13.82013],"type":"Point"}
}