{
  "type": "Feature",
  "properties": {
    "gn:admin1_code":"16",
    "gn:admin2_code":"1604.0",
    "gn:admin3_code":"160404.0",
    "gn:asciiname":"Prosperidad",
    "gn:country_code":"PE",
    "gn:dem":83,
    "gn:feature_class":"P",
    "gn:feature_code":"PPL",
    "gn:name":"Prosperidad",
    "gn:population":0,
    "gn:timezone":"America/Lima",
    "iso:country":"PE",
    "wof:name":"Prosperidad",
    "wof:placetype":"locality"
},
  "geometry": {"coordinates":[-71.01971999999998,-3.97722],"type":"Point"}
}