{
  "type": "Feature",
  "properties": {
    "gn:admin1_code":"8",
    "gn:admin2_code":"805.0",
    "gn:admin3_code":"80505.0",
    "gn:asciiname":"Tecra",
    "gn:country_code":"PE",
    "gn:dem":4093,
    "gn:feature_class":"P",
    "gn:feature_code":"PPL",
    "gn:name":"Tecra",
    "gn:population":0,
    "gn:timezone":"America/Lima",
    "iso:country":"PE",
    "wof:name":"Tecra",
    "wof:placetype":"locality"
},
  "geometry": {"coordinates":[-71.22414000000001,-14.44999],"type":"Point"}
}