{
  "type": "Feature",
  "properties": {
    "gn:admin1_code":"9.0",
    "gn:admin2_code":"903.0",
    "gn:admin3_code":"90302.0",
    "gn:asciiname":"Cashacancha",
    "gn:country_code":"PE",
    "gn:dem":3827,
    "gn:feature_class":"P",
    "gn:feature_code":"PPL",
    "gn:name":"Cashacancha",
    "gn:population":0,
    "gn:timezone":"America/Lima",
    "iso:country":"PE",
    "wof:name":"Cashacancha",
    "wof:placetype":"locality"
},
  "geometry": {"coordinates":[-74.73114,-12.91547],"type":"Point"}
}