{
  "type": "Feature",
  "properties": {
    "gn:admin1_code":"05",
    "gn:admin2_code":"510.0",
    "gn:admin3_code":"51008.0",
    "gn:asciiname":"Carapo",
    "gn:country_code":"PE",
    "gn:dem":4434,
    "gn:feature_class":"P",
    "gn:feature_code":"PPL",
    "gn:name":"Carapo",
    "gn:population":0,
    "gn:timezone":"America/Lima",
    "iso:country":"PE",
    "wof:name":"Carapo",
    "wof:placetype":"locality"
},
  "geometry": {"coordinates":[-74.23333000000002,-13.75],"type":"Point"}
}