{
  "type": "Feature",
  "properties": {
    "gn:admin1_code":"6.0",
    "gn:admin2_code":"605.0",
    "gn:admin3_code":"60503.0",
    "gn:asciiname":"Quesquera",
    "gn:country_code":"PE",
    "gn:dem":1830,
    "gn:feature_class":"P",
    "gn:feature_code":"PPL",
    "gn:name":"Quesquera",
    "gn:population":0,
    "gn:timezone":"America/Lima",
    "iso:country":"PE",
    "name:spa_x_preferred":[
        "Quesquera"
    ],
    "wof:name":"Quesquera",
    "wof:placetype":"locality"
},
  "geometry": {"coordinates":[-79.03691999999999,-7.36595],"type":"Point"}
}