{
  "type": "Feature",
  "properties": {
    "gn:admin1_code":"10.0",
    "gn:admin2_code":"1010.0",
    "gn:admin3_code":"101007.0",
    "gn:asciiname":"Yurac Cuchush",
    "gn:country_code":"PE",
    "gn:dem":4174,
    "gn:feature_class":"P",
    "gn:feature_code":"PPL",
    "gn:name":"Yurac Cuchush",
    "gn:population":0,
    "gn:timezone":"America/Lima",
    "iso:country":"PE",
    "wof:name":"Yurac Cuchush",
    "wof:placetype":"locality"
},
  "geometry": {"coordinates":[-76.57444,-10.14556],"type":"Point"}
}