{
  "type": "Feature",
  "properties": {
    "gn:admin1_code":"8",
    "gn:admin2_code":"808.0",
    "gn:asciiname":"Yacaso",
    "gn:country_code":"PE",
    "gn:dem":4828,
    "gn:feature_class":"P",
    "gn:feature_code":"PPL",
    "gn:name":"Yacaso",
    "gn:population":0,
    "gn:timezone":"America/Lima",
    "iso:country":"PE",
    "wof:name":"Yacaso",
    "wof:placetype":"locality"
},
  "geometry": {"coordinates":[-71.09990000000001,-15.30631],"type":"Point"}
}