{
  "type": "Feature",
  "properties": {
    "gn:admin1_code":"21",
    "gn:admin2_code":"2105.0",
    "gn:admin3_code":"210502.0",
    "gn:asciiname":"Challamuco",
    "gn:country_code":"PE",
    "gn:dem":4238,
    "gn:feature_class":"P",
    "gn:feature_code":"PPL",
    "gn:name":"Challamuco",
    "gn:population":0,
    "gn:timezone":"America/Lima",
    "iso:country":"PE",
    "wof:name":"Challamuco",
    "wof:placetype":"locality"
},
  "geometry": {"coordinates":[-69.71151999999999,-17.06519],"type":"Point"}
}