{
  "type": "Feature",
  "properties": {
    "gn:admin1_code":"12.0",
    "gn:admin2_code":"1208.0",
    "gn:admin3_code":"120804.0",
    "gn:asciiname":"Curihuay",
    "gn:country_code":"PE",
    "gn:dem":4523,
    "gn:feature_class":"P",
    "gn:feature_code":"PPL",
    "gn:name":"Curihuay",
    "gn:population":0,
    "gn:timezone":"America/Lima",
    "iso:country":"PE",
    "wof:name":"Curihuay",
    "wof:placetype":"locality"
},
  "geometry": {"coordinates":[-76.36323,-11.43731],"type":"Point"}
}