{
  "type": "Feature",
  "properties": {
    "gn:admin1_code":"12",
    "gn:admin2_code":"1202.0",
    "gn:admin3_code":"120214.0",
    "gn:asciiname":"Irayo",
    "gn:country_code":"PE",
    "gn:dem":4318,
    "gn:feature_class":"P",
    "gn:feature_code":"PPL",
    "gn:name":"Irayo",
    "gn:population":0,
    "gn:timezone":"America/Lima",
    "iso:country":"PE",
    "wof:name":"Irayo",
    "wof:placetype":"locality"
},
  "geometry": {"coordinates":[-75.58417,-12.11694],"type":"Point"}
}