{
  "type": "Feature",
  "properties": {
    "gn:admin1_code":"20",
    "gn:admin2_code":"2002.0",
    "gn:asciiname":"Samanamaca",
    "gn:country_code":"PE",
    "gn:dem":931,
    "gn:feature_class":"P",
    "gn:feature_code":"PPL",
    "gn:name":"Samanamaca",
    "gn:population":0,
    "gn:timezone":"America/Lima",
    "iso:country":"PE",
    "name:und_x_variant":[
        "Samanamaca Hacienda",
        "Samanamaca"
    ],
    "wof:name":"Samanamaca",
    "wof:placetype":"locality"
},
  "geometry": {"coordinates":[-79.63594999999999,-4.43592],"type":"Point"}
}