{
  "type": "Feature",
  "properties": {
    "gn:admin1_code":"25.0",
    "gn:admin2_code":"2503.0",
    "gn:admin3_code":"250301.0",
    "gn:asciiname":"Yurac",
    "gn:country_code":"PE",
    "gn:dem":372,
    "gn:feature_class":"P",
    "gn:feature_code":"PPL",
    "gn:name":"Yurac",
    "gn:population":0,
    "gn:timezone":"America/Lima",
    "iso:country":"PE",
    "wof:name":"Yurac",
    "wof:placetype":"locality"
},
  "geometry": {"coordinates":[-75.60111999999999,-9.05406],"type":"Point"}
}