{
  "type": "Feature",
  "properties": {
    "gn:admin1_code":"1.0",
    "gn:admin2_code":"106.0",
    "gn:admin3_code":"10611.0",
    "gn:asciiname":"La Perla",
    "gn:country_code":"PE",
    "gn:dem":1759,
    "gn:feature_class":"P",
    "gn:feature_code":"PPL",
    "gn:name":"La Perla",
    "gn:population":0,
    "gn:timezone":"America/Lima",
    "iso:country":"PE",
    "name:ceb_x_preferred":[
        "La Perla"
    ],
    "name:deu_x_preferred":[
        "La Perla"
    ],
    "name:epo_x_preferred":[
        "La Perla"
    ],
    "name:fra_x_preferred":[
        "La Perla"
    ],
    "name:ita_x_preferred":[
        "La perla"
    ],
    "name:nld_x_preferred":[
        "La Perla"
    ],
    "name:spa_x_preferred":[
        "La Perla"
    ],
    "name:srp_x_preferred":[
        "\u041b\u0430 \u041f\u0435\u0440\u043b\u0430"
    ],
    "name:swe_x_preferred":[
        "La Perla"
    ],
    "wof:name":"La Perla",
    "wof:placetype":"locality"
},
  "geometry": {"coordinates":[-77.45583000000001,-6.49139],"type":"Point"}
}