{
  "type": "Feature",
  "properties": {
    "gn:admin1_code":"20",
    "gn:admin2_code":"2002.0",
    "gn:admin3_code":"200206.0",
    "gn:asciiname":"Tulmancito",
    "gn:cc2":"PE",
    "gn:country_code":"PE",
    "gn:dem":2034,
    "gn:feature_class":"P",
    "gn:feature_code":"PPL",
    "gn:name":"Tulmancito",
    "gn:population":0,
    "gn:timezone":"America/Lima",
    "iso:country":"PE",
    "name:und_x_variant":[
        "Tulmoncito",
        "Tulmancito"
    ],
    "wof:name":"Tulmancito",
    "wof:placetype":"locality"
},
  "geometry": {"coordinates":[-79.71666999999999,-4.91667],"type":"Point"}
}