{
  "type": "Feature",
  "properties": {
    "gn:admin1_code":"4",
    "gn:admin2_code":"405.0",
    "gn:admin3_code":"40517.0",
    "gn:asciiname":"Callutana",
    "gn:country_code":"PE",
    "gn:dem":4691,
    "gn:feature_class":"P",
    "gn:feature_code":"PPL",
    "gn:name":"Calluta\u00f1a",
    "gn:population":0,
    "gn:timezone":"America/Lima",
    "iso:country":"PE",
    "wof:name":"Callutana",
    "wof:placetype":"locality"
},
  "geometry": {"coordinates":[-71.27523000000002,-15.27673],"type":"Point"}
}