{
  "type": "Feature",
  "properties": {
    "gn:admin1_code":"11",
    "gn:admin2_code":"1102.0",
    "gn:admin3_code":"110203.0",
    "gn:asciiname":"Cuyara",
    "gn:country_code":"PE",
    "gn:dem":2776,
    "gn:feature_class":"P",
    "gn:feature_code":"PPL",
    "gn:name":"Cuyara",
    "gn:population":0,
    "gn:timezone":"America/Lima",
    "iso:country":"PE",
    "name:spa_x_preferred":[
        "Cuyara"
    ],
    "wof:name":"Cuyara",
    "wof:placetype":"locality"
},
  "geometry": {"coordinates":[-75.94833,-13.14477],"type":"Point"}
}