{
  "type": "Feature",
  "properties": {
    "gn:admin1_code":"22",
    "gn:admin2_code":"2201.0",
    "gn:admin3_code":"220106.0",
    "gn:asciiname":"Yantalo",
    "gn:country_code":"PE",
    "gn:dem":840,
    "gn:feature_class":"P",
    "gn:feature_code":"PPL",
    "gn:name":"Yantal\u00f3",
    "gn:population":0,
    "gn:timezone":"America/Lima",
    "iso:country":"PE",
    "wof:name":"Yantalo",
    "wof:placetype":"locality"
},
  "geometry": {"coordinates":[-77.02,-5.97417],"type":"Point"}
}