{
  "type": "Feature",
  "properties": {
    "gn:admin1_code":"13",
    "gn:admin2_code":"1309.0",
    "gn:admin3_code":"130907.0",
    "gn:asciiname":"Ollocopamba",
    "gn:country_code":"PE",
    "gn:dem":3120,
    "gn:feature_class":"P",
    "gn:feature_code":"PPL",
    "gn:name":"Ollocopamba",
    "gn:population":0,
    "gn:timezone":"America/Lima",
    "iso:country":"PE",
    "wof:name":"Ollocopamba",
    "wof:placetype":"locality"
},
  "geometry": {"coordinates":[-77.9074,-7.87824],"type":"Point"}
}