{
  "type": "Feature",
  "properties": {
    "gn:admin1_code":"17.0",
    "gn:admin2_code":"1703.0",
    "gn:asciiname":"Martines",
    "gn:country_code":"PE",
    "gn:dem":279,
    "gn:feature_class":"P",
    "gn:feature_code":"PPL",
    "gn:name":"Martines",
    "gn:population":0,
    "gn:timezone":"America/Lima",
    "iso:country":"PE",
    "name:spa_x_preferred":[
        "Martines"
    ],
    "wof:name":"Martines",
    "wof:placetype":"locality"
},
  "geometry": {"coordinates":[-69.08187,-11.81112],"type":"Point"}
}