{
  "type": "Feature",
  "properties": {
    "gn:admin1_code":"15",
    "gn:admin2_code":"1510.0",
    "gn:admin3_code":"151028.0",
    "gn:asciiname":"Mullucocha",
    "gn:country_code":"PE",
    "gn:dem":4247,
    "gn:feature_class":"P",
    "gn:feature_code":"PPL",
    "gn:name":"Mullucocha",
    "gn:population":0,
    "gn:timezone":"America/Lima",
    "iso:country":"PE",
    "wof:name":"Mullucocha",
    "wof:placetype":"locality"
},
  "geometry": {"coordinates":[-75.96880999999998,-12.05903],"type":"Point"}
}