{
  "type": "Feature",
  "properties": {
    "gn:admin1_code":"15",
    "gn:admin2_code":"1510.0",
    "gn:admin3_code":"151011.0",
    "gn:asciiname":"San Marcelo",
    "gn:country_code":"PE",
    "gn:dem":2304,
    "gn:feature_class":"P",
    "gn:feature_code":"PPL",
    "gn:name":"San Marcelo",
    "gn:population":0,
    "gn:timezone":"America/Lima",
    "iso:country":"PE",
    "name:ita_x_preferred":[
        "San Marcelo"
    ],
    "name:spa_x_preferred":[
        "San Marcelo"
    ],
    "name:zho_x_preferred":[
        "\u8056\u99ac\u723e\u585e\u6d1b"
    ],
    "wof:name":"San Marcelo",
    "wof:placetype":"locality"
},
  "geometry": {"coordinates":[-75.95237,-12.59811],"type":"Point"}
}