{
  "type": "Feature",
  "properties": {
    "gn:admin1_code":"5",
    "gn:admin2_code":"509.0",
    "gn:admin3_code":"50910.0",
    "gn:asciiname":"Matara",
    "gn:country_code":"PE",
    "gn:dem":3242,
    "gn:feature_class":"P",
    "gn:feature_code":"PPL",
    "gn:name":"Matara",
    "gn:population":0,
    "gn:timezone":"America/Lima",
    "iso:country":"PE",
    "wof:name":"Matara",
    "wof:placetype":"locality"
},
  "geometry": {"coordinates":[-73.63500000000001,-14.08083],"type":"Point"}
}