{
  "type": "Feature",
  "properties": {
    "gn:admin1_code":"9.0",
    "gn:admin2_code":"903.0",
    "gn:asciiname":"Yarccapampa",
    "gn:country_code":"PE",
    "gn:dem":3362,
    "gn:feature_class":"P",
    "gn:feature_code":"PPL",
    "gn:name":"Yarccapampa",
    "gn:population":0,
    "gn:timezone":"America/Lima",
    "iso:country":"PE",
    "wof:name":"Yarccapampa",
    "wof:placetype":"locality"
},
  "geometry": {"coordinates":[-74.41601,-13.15314],"type":"Point"}
}