{
  "type": "Feature",
  "properties": {
    "gn:admin1_code":"20",
    "gn:admin2_code":"2004.0",
    "gn:admin3_code":"200401.0",
    "gn:asciiname":"Casana",
    "gn:country_code":"PE",
    "gn:dem":86,
    "gn:feature_class":"P",
    "gn:feature_code":"PPL",
    "gn:name":"Casana",
    "gn:population":0,
    "gn:timezone":"America/Lima",
    "iso:country":"PE",
    "wof:name":"Casana",
    "wof:placetype":"locality"
},
  "geometry": {"coordinates":[-80.2165,-4.99661],"type":"Point"}
}