{
  "type": "Feature",
  "properties": {
    "gn:admin1_code":"15.0",
    "gn:admin2_code":"1506.0",
    "gn:admin3_code":"150604.0",
    "gn:asciiname":"Gramalote",
    "gn:country_code":"PE",
    "gn:dem":151,
    "gn:feature_class":"P",
    "gn:feature_code":"PPL",
    "gn:name":"Gramalote",
    "gn:population":0,
    "gn:timezone":"America/Lima",
    "iso:country":"PE",
    "name:spa_x_preferred":[
        "Gramalote"
    ],
    "wof:name":"Gramalote",
    "wof:placetype":"locality"
},
  "geometry": {"coordinates":[-77.17702,-11.5536],"type":"Point"}
}