{
  "type": "Feature",
  "properties": {
    "gn:admin1_code":"15.0",
    "gn:admin2_code":"1506.0",
    "gn:admin3_code":"150604.0",
    "gn:asciiname":"Gramalote",
    "gn:country_code":"PE",
    "gn:dem":151,
    "gn:feature_class":"P",
    "gn:feature_code":"PPL",
    "gn:name":"Gramalote",
    "gn:population":0,
    "gn:timezone":"America/Lima",
    "iso:country":"PE",
    "name:ceb_x_preferred":[
        "Gramalote"
    ],
    "name:fra_x_preferred":[
        "Gramalote"
    ],
    "name:ita_x_preferred":[
        "Gramalote"
    ],
    "name:kat_x_preferred":[
        "\u10d2\u10e0\u10d0\u10db\u10d0\u10da\u10dd\u10e2\u10d4"
    ],
    "name:lat_x_preferred":[
        "Gramalote"
    ],
    "name:msa_x_preferred":[
        "Gramalote"
    ],
    "name:nld_x_preferred":[
        "Gramalote"
    ],
    "name:por_x_preferred":[
        "Gramalote"
    ],
    "name:spa_x_preferred":[
        "Gramalote"
    ],
    "name:swe_x_preferred":[
        "Gramalote"
    ],
    "name:tgl_x_preferred":[
        "Gramalote"
    ],
    "name:vie_x_preferred":[
        "Gramalote"
    ],
    "name:war_x_preferred":[
        "Gramalote"
    ],
    "name:zho_x_preferred":[
        "\u683c\u62c9\u99ac\u6d1b\u7279"
    ],
    "wof:name":"Gramalote",
    "wof:placetype":"locality"
},
  "geometry": {"coordinates":[-77.17702,-11.5536],"type":"Point"}
}