{
  "type": "Feature",
  "properties": {
    "gn:admin1_code":"23",
    "gn:admin2_code":"2304.0",
    "gn:admin3_code":"230401.0",
    "gn:asciiname":"Pampa Collota",
    "gn:country_code":"PE",
    "gn:dem":4266,
    "gn:feature_class":"P",
    "gn:feature_code":"PPL",
    "gn:name":"Pampa Collota",
    "gn:population":0,
    "gn:timezone":"America/Lima",
    "iso:country":"PE",
    "wof:name":"Pampa Collota",
    "wof:placetype":"locality"
},
  "geometry": {"coordinates":[-69.72018,-17.3111],"type":"Point"}
}