{
  "type": "Feature",
  "properties": {
    "gn:admin1_code":"20",
    "gn:admin2_code":"2006.0",
    "gn:admin3_code":"200603.0",
    "gn:asciiname":"Hacienda Ventarrones",
    "gn:country_code":"PE",
    "gn:dem":35,
    "gn:feature_class":"P",
    "gn:feature_code":"PPL",
    "gn:name":"Hacienda Ventarrones",
    "gn:population":0,
    "gn:timezone":"America/Lima",
    "iso:country":"PE",
    "name:spa_x_preferred":[
        "Hacienda Ventarrones"
    ],
    "name:spa_x_variant":[
        "Ventarrones"
    ],
    "wof:name":"Hacienda Ventarrones",
    "wof:placetype":"locality"
},
  "geometry": {"coordinates":[-80.83501,-4.84019],"type":"Point"}
}