{
  "type": "Feature",
  "properties": {
    "gn:admin1_code":"14",
    "gn:admin2_code":"1403.0",
    "gn:admin3_code":"140310.0",
    "gn:asciiname":"Jarchipe C",
    "gn:country_code":"PE",
    "gn:dem":135,
    "gn:feature_class":"P",
    "gn:feature_code":"PPL",
    "gn:name":"Jarchipe C",
    "gn:population":0,
    "gn:timezone":"America/Lima",
    "iso:country":"PE",
    "wof:name":"Jarchipe C",
    "wof:placetype":"locality"
},
  "geometry": {"coordinates":[-79.64627,-6.2718],"type":"Point"}
}