{
  "type": "Feature",
  "properties": {
    "gn:admin1_code":"15",
    "gn:admin2_code":"1509.0",
    "gn:admin3_code":"150904.0",
    "gn:asciiname":"Yarucalla",
    "gn:country_code":"PE",
    "gn:dem":4765,
    "gn:feature_class":"P",
    "gn:feature_code":"PPL",
    "gn:name":"Yarucalla",
    "gn:population":0,
    "gn:timezone":"America/Lima",
    "iso:country":"PE",
    "wof:name":"Yarucalla",
    "wof:placetype":"locality"
},
  "geometry": {"coordinates":[-77.09999999999999,-10.75],"type":"Point"}
}