{
  "type": "Feature",
  "properties": {
    "gn:admin1_code":"13.0",
    "gn:admin2_code":"1301.0",
    "gn:admin3_code":"130101.0",
    "gn:asciiname":"Primavera",
    "gn:country_code":"PE",
    "gn:dem":45,
    "gn:feature_class":"P",
    "gn:feature_code":"PPL",
    "gn:name":"Primavera",
    "gn:population":0,
    "gn:timezone":"America/Lima",
    "iso:country":"PE",
    "wof:name":"Primavera",
    "wof:placetype":"locality"
},
  "geometry": {"coordinates":[-79.03369000000001,-8.09792],"type":"Point"}
}