{
  "type": "Feature",
  "properties": {
    "gn:admin1_code":"4",
    "gn:admin2_code":"405.0",
    "gn:admin3_code":"40505.0",
    "gn:asciiname":"Minca",
    "gn:country_code":"PE",
    "gn:dem":4532,
    "gn:feature_class":"P",
    "gn:feature_code":"PPL",
    "gn:name":"Minca",
    "gn:population":0,
    "gn:timezone":"America/Lima",
    "iso:country":"PE",
    "wof:name":"Minca",
    "wof:placetype":"locality"
},
  "geometry": {"coordinates":[-71.845,-15.26528],"type":"Point"}
}