{
  "type": "Feature",
  "properties": {
    "gn:admin1_code":"22.0",
    "gn:admin2_code":"2204.0",
    "gn:admin3_code":"220405.0",
    "gn:asciiname":"Pinar",
    "gn:country_code":"PE",
    "gn:dem":281,
    "gn:feature_class":"P",
    "gn:feature_code":"PPL",
    "gn:name":"Pinar",
    "gn:population":0,
    "gn:timezone":"America/Lima",
    "iso:country":"PE",
    "name:spa_x_preferred":[
        "Pinar"
    ],
    "wof:name":"Pinar",
    "wof:placetype":"locality"
},
  "geometry": {"coordinates":[-76.70239000000002,-7.07037],"type":"Point"}
}