{
  "type": "Feature",
  "properties": {
    "gn:admin1_code":"2.0",
    "gn:admin2_code":"205.0",
    "gn:admin3_code":"20501.0",
    "gn:asciiname":"Sinsan",
    "gn:country_code":"PE",
    "gn:dem":3589,
    "gn:feature_class":"P",
    "gn:feature_code":"PPL",
    "gn:name":"Sinsan",
    "gn:population":0,
    "gn:timezone":"America/Lima",
    "iso:country":"PE",
    "wof:name":"Sinsan",
    "wof:placetype":"locality"
},
  "geometry": {"coordinates":[-77.1639,-10.21915],"type":"Point"}
}