{
  "type": "Feature",
  "properties": {
    "gn:admin1_code":"9.0",
    "gn:admin2_code":"907.0",
    "gn:admin3_code":"90715.0",
    "gn:asciiname":"Verde Pata",
    "gn:country_code":"PE",
    "gn:dem":2797,
    "gn:feature_class":"P",
    "gn:feature_code":"PPL",
    "gn:name":"Verde Pata",
    "gn:population":0,
    "gn:timezone":"America/Lima",
    "iso:country":"PE",
    "wof:name":"Verde Pata",
    "wof:placetype":"locality"
},
  "geometry": {"coordinates":[-74.72153,-12.11776],"type":"Point"}
}