{
  "type": "Feature",
  "properties": {
    "gn:admin1_code":"10.0",
    "gn:admin2_code":"1001.0",
    "gn:admin3_code":"100105.0",
    "gn:asciiname":"Ruyro Corral",
    "gn:country_code":"PE",
    "gn:dem":3887,
    "gn:feature_class":"P",
    "gn:feature_code":"PPL",
    "gn:name":"Ruyro Corral",
    "gn:population":0,
    "gn:timezone":"America/Lima",
    "iso:country":"PE",
    "wof:name":"Ruyro Corral",
    "wof:placetype":"locality"
},
  "geometry": {"coordinates":[-76.59860999999999,-10.0675],"type":"Point"}
}