{
  "type": "Feature",
  "properties": {
    "gn:admin1_code":"06",
    "gn:admin2_code":"601.0",
    "gn:admin3_code":"60105.0",
    "gn:asciiname":"Pabellon",
    "gn:country_code":"PE",
    "gn:dem":4043,
    "gn:feature_class":"P",
    "gn:feature_code":"PPL",
    "gn:name":"Pabell\u00f3n",
    "gn:population":0,
    "gn:timezone":"America/Lima",
    "iso:country":"PE",
    "wof:name":"Pabellon",
    "wof:placetype":"locality"
},
  "geometry": {"coordinates":[-78.43794,-6.96583],"type":"Point"}
}