{
  "type": "Feature",
  "properties": {
    "gn:admin1_code":"16",
    "gn:admin2_code":"1602.0",
    "gn:admin3_code":"160206.0",
    "gn:asciiname":"Actual Tipishca",
    "gn:country_code":"PE",
    "gn:dem":120,
    "gn:feature_class":"P",
    "gn:feature_code":"PPL",
    "gn:name":"Actual Tipishca",
    "gn:population":0,
    "gn:timezone":"America/Lima",
    "iso:country":"PE",
    "name:und_x_variant":[
        "Tipishca",
        "Achual Tipisca",
        "Actual Tipishca"
    ],
    "wof:name":"Actual Tipishca",
    "wof:placetype":"locality"
},
  "geometry": {"coordinates":[-75.81535,-5.45301],"type":"Point"}
}