{
  "type": "Feature",
  "properties": {
    "gn:admin1_code":"2.0",
    "gn:admin2_code":"205.0",
    "gn:admin3_code":"20503.0",
    "gn:asciiname":"Ulpicaca",
    "gn:country_code":"PE",
    "gn:dem":3147,
    "gn:feature_class":"P",
    "gn:feature_code":"PPL",
    "gn:name":"Ulpicaca",
    "gn:population":0,
    "gn:timezone":"America/Lima",
    "iso:country":"PE",
    "wof:name":"Ulpicaca",
    "wof:placetype":"locality"
},
  "geometry": {"coordinates":[-77.46083,-10.20937],"type":"Point"}
}