{
  "type": "Feature",
  "properties": {
    "gn:admin1_code":"15",
    "gn:admin2_code":"1508.0",
    "gn:admin3_code":"150804.0",
    "gn:asciiname":"Piedra Blanca",
    "gn:country_code":"PE",
    "gn:dem":2278,
    "gn:feature_class":"P",
    "gn:feature_code":"PPL",
    "gn:name":"Piedra Blanca",
    "gn:population":0,
    "gn:timezone":"America/Lima",
    "iso:country":"PE",
    "name:ceb_x_preferred":[
        "Piedra Blanca"
    ],
    "name:fra_x_preferred":[
        "Piedra Blanca"
    ],
    "name:ita_x_preferred":[
        "Piedra Blanca"
    ],
    "name:por_x_preferred":[
        "Piedra Blanca"
    ],
    "name:spa_x_preferred":[
        "Piedra Blanca"
    ],
    "name:zho_x_preferred":[
        "\u5f7c\u5fb7\u62c9\u5e03\u862d\u5361"
    ],
    "wof:name":"Piedra Blanca",
    "wof:placetype":"locality"
},
  "geometry": {"coordinates":[-76.86960000000001,-10.86613],"type":"Point"}
}