{
  "type": "Feature",
  "properties": {
    "gn:admin1_code":"21",
    "gn:admin2_code":"2112.0",
    "gn:admin3_code":"211202.0",
    "gn:asciiname":"Muchucach",
    "gn:country_code":"PE",
    "gn:dem":3462,
    "gn:feature_class":"P",
    "gn:feature_code":"PPL",
    "gn:name":"Muchucach",
    "gn:population":0,
    "gn:timezone":"America/Lima",
    "iso:country":"PE",
    "wof:name":"Muchucach",
    "wof:placetype":"locality"
},
  "geometry": {"coordinates":[-69.53740999999999,-14.45499],"type":"Point"}
}