{
  "type": "Feature",
  "properties": {
    "gn:admin1_code":"16",
    "gn:admin2_code":"1605.0",
    "gn:admin3_code":"160510.0",
    "gn:asciiname":"Yanaallpa",
    "gn:country_code":"PE",
    "gn:dem":102,
    "gn:feature_class":"P",
    "gn:feature_code":"PPL",
    "gn:name":"Yanaallpa",
    "gn:population":0,
    "gn:timezone":"America/Lima",
    "iso:country":"PE",
    "wof:name":"Yanaallpa",
    "wof:placetype":"locality"
},
  "geometry": {"coordinates":[-73.77384000000001,-4.88821],"type":"Point"}
}