{
  "type": "Feature",
  "properties": {
    "gn:admin1_code":"15",
    "gn:admin2_code":"1510.0",
    "gn:admin3_code":"151008.0",
    "gn:asciiname":"Huanca Corral",
    "gn:country_code":"PE",
    "gn:dem":2894,
    "gn:feature_class":"P",
    "gn:feature_code":"PPL",
    "gn:name":"Huanca Corral",
    "gn:population":0,
    "gn:timezone":"America/Lima",
    "iso:country":"PE",
    "wof:name":"Huanca Corral",
    "wof:placetype":"locality"
},
  "geometry": {"coordinates":[-75.90255999999999,-12.72801],"type":"Point"}
}