{
  "type": "Feature",
  "properties": {
    "gn:admin1_code":"8",
    "gn:admin2_code":"807.0",
    "gn:admin3_code":"80708.0",
    "gn:asciiname":"Huilca",
    "gn:country_code":"PE",
    "gn:dem":4117,
    "gn:feature_class":"P",
    "gn:feature_code":"PPL",
    "gn:name":"Huilca",
    "gn:population":0,
    "gn:timezone":"America/Lima",
    "iso:country":"PE",
    "wof:name":"Huilca",
    "wof:placetype":"locality"
},
  "geometry": {"coordinates":[-71.81528,-14.52306],"type":"Point"}
}