{
  "type": "Feature",
  "properties": {
    "gn:admin1_code":"14",
    "gn:admin2_code":"1402.0",
    "gn:admin3_code":"140203.0",
    "gn:asciiname":"Cueva Blanca",
    "gn:country_code":"PE",
    "gn:dem":3325,
    "gn:feature_class":"P",
    "gn:feature_code":"PPL",
    "gn:name":"Cueva Blanca",
    "gn:population":0,
    "gn:timezone":"America/Lima",
    "iso:country":"PE",
    "wof:name":"Cueva Blanca",
    "wof:placetype":"locality"
},
  "geometry": {"coordinates":[-79.39636999999998,-6.14526],"type":"Point"}
}