{
  "type": "Feature",
  "properties": {
    "gn:admin1_code":"03",
    "gn:admin2_code":"305.0",
    "gn:admin3_code":"30503.0",
    "gn:asciiname":"Yanama",
    "gn:country_code":"PE",
    "gn:dem":3913,
    "gn:feature_class":"P",
    "gn:feature_code":"PPL",
    "gn:name":"Yanama",
    "gn:population":0,
    "gn:timezone":"America/Lima",
    "iso:country":"PE",
    "name:zho_x_preferred":[
        "\u4e9e\u7d0d\u99ac\u5c71"
    ],
    "wof:name":"Yanama",
    "wof:placetype":"locality"
},
  "geometry": {"coordinates":[-72.44278,-13.94167],"type":"Point"}
}