{
  "type": "Feature",
  "properties": {
    "gn:admin1_code":"4",
    "gn:admin2_code":"401.0",
    "gn:admin3_code":"40128.0",
    "gn:asciiname":"Ojule",
    "gn:country_code":"PE",
    "gn:dem":2969,
    "gn:feature_class":"P",
    "gn:feature_code":"PPL",
    "gn:name":"Ojule",
    "gn:population":0,
    "gn:timezone":"America/Lima",
    "iso:country":"PE",
    "wof:name":"Ojule",
    "wof:placetype":"locality"
},
  "geometry": {"coordinates":[-71.77916999999999,-16.13861],"type":"Point"}
}