{
  "type": "Feature",
  "properties": {
    "gn:admin1_code":"5",
    "gn:admin2_code":"509.0",
    "gn:admin3_code":"50904.0",
    "gn:asciiname":"Anccasilla",
    "gn:country_code":"PE",
    "gn:dem":3061,
    "gn:feature_class":"P",
    "gn:feature_code":"PPL",
    "gn:name":"Anccasilla",
    "gn:population":0,
    "gn:timezone":"America/Lima",
    "iso:country":"PE",
    "wof:name":"Anccasilla",
    "wof:placetype":"locality"
},
  "geometry": {"coordinates":[-73.71644999999999,-13.89212],"type":"Point"}
}