{
  "type": "Feature",
  "properties": {
    "gn:admin1_code":"22",
    "gn:admin2_code":"2206.0",
    "gn:admin3_code":"220602.0",
    "gn:asciiname":"Cayumba",
    "gn:country_code":"PE",
    "gn:dem":412,
    "gn:feature_class":"P",
    "gn:feature_code":"PPL",
    "gn:name":"Cayumba",
    "gn:population":0,
    "gn:timezone":"America/Lima",
    "iso:country":"PE",
    "wof:name":"Cayumba",
    "wof:placetype":"locality"
},
  "geometry": {"coordinates":[-76.79278000000002,-7.56472],"type":"Point"}
}