{
  "type": "Feature",
  "properties": {
    "gn:admin1_code":"06",
    "gn:admin2_code":"610.0",
    "gn:admin3_code":"61005.0",
    "gn:asciiname":"Ichocan",
    "gn:country_code":"PE",
    "gn:dem":2542,
    "gn:feature_class":"P",
    "gn:feature_code":"PPL",
    "gn:name":"Ichoc\u00e1n",
    "gn:population":0,
    "gn:timezone":"America/Lima",
    "iso:country":"PE",
    "name:und_x_variant":[
        "Chocan",
        "Ichoc\u00e1n"
    ],
    "wof:name":"Ichocan",
    "wof:placetype":"locality"
},
  "geometry": {"coordinates":[-78.13515,-7.36255],"type":"Point"}
}