{
  "type": "Feature",
  "properties": {
    "gn:admin1_code":"2.0",
    "gn:admin2_code":"210.0",
    "gn:admin3_code":"21010.0",
    "gn:asciiname":"Chilia",
    "gn:country_code":"PE",
    "gn:dem":3742,
    "gn:feature_class":"P",
    "gn:feature_code":"PPLL",
    "gn:name":"Chilia",
    "gn:population":0,
    "gn:timezone":"America/Lima",
    "iso:country":"PE",
    "wof:name":"Chilia",
    "wof:placetype":"locality"
},
  "geometry": {"coordinates":[-76.89614,-9.12293],"type":"Point"}
}