{
  "type": "Feature",
  "properties": {
    "gn:admin1_code":"8",
    "gn:admin2_code":"809.0",
    "gn:admin3_code":"80902.0",
    "gn:asciiname":"Mantoreal",
    "gn:country_code":"PE",
    "gn:dem":760,
    "gn:feature_class":"P",
    "gn:feature_code":"PPL",
    "gn:name":"Mantoreal",
    "gn:population":0,
    "gn:timezone":"America/Lima",
    "iso:country":"PE",
    "wof:name":"Mantoreal",
    "wof:placetype":"locality"
},
  "geometry": {"coordinates":[-72.56971999999998,-12.6525],"type":"Point"}
}