{
  "type": "Feature",
  "properties": {
    "gn:admin1_code":"21",
    "gn:admin2_code":"2110.0",
    "gn:admin3_code":"211001.0",
    "gn:asciiname":"Huallu Pampa",
    "gn:country_code":"PE",
    "gn:dem":4570,
    "gn:feature_class":"P",
    "gn:feature_code":"PPL",
    "gn:name":"Huallu Pampa",
    "gn:population":0,
    "gn:timezone":"America/Lima",
    "iso:country":"PE",
    "wof:name":"Huallu Pampa",
    "wof:placetype":"locality"
},
  "geometry": {"coordinates":[-69.89352,-14.4867],"type":"Point"}
}