{
  "type": "Feature",
  "properties": {
    "gn:admin1_code":"8",
    "gn:admin2_code":"808.0",
    "gn:admin3_code":"80805.0",
    "gn:asciiname":"Tocollo",
    "gn:country_code":"PE",
    "gn:dem":4256,
    "gn:feature_class":"P",
    "gn:feature_code":"PPL",
    "gn:name":"Tocollo",
    "gn:population":0,
    "gn:timezone":"America/Lima",
    "iso:country":"PE",
    "wof:name":"Tocollo",
    "wof:placetype":"locality"
},
  "geometry": {"coordinates":[-71.02648000000001,-15.04924],"type":"Point"}
}