{
  "type": "Feature",
  "properties": {
    "gn:admin1_code":"09",
    "gn:admin2_code":"906.0",
    "gn:admin3_code":"90607.0",
    "gn:asciiname":"Jollota",
    "gn:country_code":"PE",
    "gn:dem":4484,
    "gn:feature_class":"P",
    "gn:feature_code":"PPL",
    "gn:name":"Jollota",
    "gn:population":0,
    "gn:timezone":"America/Lima",
    "iso:country":"PE",
    "wof:name":"Jollota",
    "wof:placetype":"locality"
},
  "geometry": {"coordinates":[-74.88606999999998,-13.2673],"type":"Point"}
}