{
  "type": "Feature",
  "properties": {
    "gn:admin1_code":"10",
    "gn:admin2_code":"1010.0",
    "gn:admin3_code":"101002.0",
    "gn:asciiname":"Cocanmachay",
    "gn:country_code":"PE",
    "gn:dem":4185,
    "gn:feature_class":"P",
    "gn:feature_code":"PPL",
    "gn:name":"Cocanmachay",
    "gn:population":0,
    "gn:timezone":"America/Lima",
    "iso:country":"PE",
    "wof:name":"Cocanmachay",
    "wof:placetype":"locality"
},
  "geometry": {"coordinates":[-76.83353000000002,-10.12231],"type":"Point"}
}