{
  "type": "Feature",
  "properties": {
    "gn:admin1_code":"08",
    "gn:admin2_code":"807.0",
    "gn:admin3_code":"80702.0",
    "gn:asciiname":"Cuchina",
    "gn:country_code":"PE",
    "gn:dem":3503,
    "gn:feature_class":"P",
    "gn:feature_code":"PPL",
    "gn:name":"Cuchina",
    "gn:population":0,
    "gn:timezone":"America/Lima",
    "iso:country":"PE",
    "name:und_x_variant":[
        "Chuchina Hacienda",
        "Chuchina",
        "Cuchina"
    ],
    "wof:name":"Cuchina",
    "wof:placetype":"locality"
},
  "geometry": {"coordinates":[-72.01024,-13.96508],"type":"Point"}
}