{
  "type": "Feature",
  "properties": {
    "gn:admin1_code":"12",
    "gn:admin2_code":"1207.0",
    "gn:admin3_code":"120708.0",
    "gn:asciiname":"Yanec",
    "gn:country_code":"PE",
    "gn:dem":3728,
    "gn:feature_class":"P",
    "gn:feature_code":"PPL",
    "gn:name":"Yanec",
    "gn:population":0,
    "gn:timezone":"America/Lima",
    "iso:country":"PE",
    "name:und_x_variant":[
        "Yanac",
        "Ya\u00f1ec",
        "Yanec"
    ],
    "wof:name":"Yanec",
    "wof:placetype":"locality"
},
  "geometry": {"coordinates":[-75.73774,-11.06278],"type":"Point"}
}