{
  "type": "Feature",
  "properties": {
    "gn:admin1_code":"10",
    "gn:admin2_code":"1002.0",
    "gn:admin3_code":"100202.0",
    "gn:asciiname":"Sebada",
    "gn:country_code":"PE",
    "gn:dem":3626,
    "gn:feature_class":"P",
    "gn:feature_code":"PPL",
    "gn:name":"Sebada",
    "gn:population":0,
    "gn:timezone":"America/Lima",
    "iso:country":"PE",
    "wof:name":"Sebada",
    "wof:placetype":"locality"
},
  "geometry": {"coordinates":[-76.35717,-10.23457],"type":"Point"}
}