{
  "type": "Feature",
  "properties": {
    "gn:admin1_code":"9.0",
    "gn:admin2_code":"907.0",
    "gn:admin3_code":"90709.0",
    "gn:asciiname":"Huinachaca",
    "gn:country_code":"PE",
    "gn:dem":3891,
    "gn:feature_class":"P",
    "gn:feature_code":"PPL",
    "gn:name":"Hui\u00f1achaca",
    "gn:population":0,
    "gn:timezone":"America/Lima",
    "iso:country":"PE",
    "wof:name":"Huinachaca",
    "wof:placetype":"locality"
},
  "geometry": {"coordinates":[-74.91853,-12.18319],"type":"Point"}
}