{
  "type": "Feature",
  "properties": {
    "gn:admin1_code":"21",
    "gn:admin2_code":"2112",
    "gn:asciiname":"Capac Orcco",
    "gn:country_code":"PE",
    "gn:dem":1394,
    "gn:feature_class":"P",
    "gn:feature_code":"PPL",
    "gn:name":"Capac Orcco",
    "gn:population":0,
    "gn:timezone":"America/Lima",
    "iso:country":"PE",
    "name:spa_x_preferred":[
        "Capac Orcco"
    ],
    "wof:name":"Capac Orcco",
    "wof:placetype":"locality"
},
  "geometry": {"coordinates":[-69.53564,-13.96459],"type":"Point"}
}