{
  "type": "Feature",
  "properties": {
    "gn:admin1_code":"15",
    "gn:admin2_code":"1507.0",
    "gn:admin3_code":"150722.0",
    "gn:asciiname":"Chocna",
    "gn:cc2":"PE",
    "gn:country_code":"PE",
    "gn:dem":4547,
    "gn:feature_class":"P",
    "gn:feature_code":"PPL",
    "gn:name":"Chocna",
    "gn:population":0,
    "gn:timezone":"America/Lima",
    "iso:country":"PE",
    "name:und_x_variant":[
        "Chocha",
        "Chocna"
    ],
    "wof:name":"Chocna",
    "wof:placetype":"locality"
},
  "geometry": {"coordinates":[-76.24028,-11.84167],"type":"Point"}
}