{
  "type": "Feature",
  "properties": {
    "gn:admin1_code":"12",
    "gn:admin2_code":"1207.0",
    "gn:admin3_code":"120708.0",
    "gn:asciiname":"Chupan",
    "gn:country_code":"PE",
    "gn:dem":3877,
    "gn:feature_class":"P",
    "gn:feature_code":"PPL",
    "gn:name":"Chup\u00e1n",
    "gn:population":0,
    "gn:timezone":"America/Lima",
    "iso:country":"PE",
    "wof:name":"Chupan",
    "wof:placetype":"locality"
},
  "geometry": {"coordinates":[-75.78721999999998,-11.05167],"type":"Point"}
}