{
  "type": "Feature",
  "properties": {
    "gn:admin1_code":"12",
    "gn:admin2_code":"1207.0",
    "gn:admin3_code":"120708.0",
    "gn:asciiname":"Chupan",
    "gn:country_code":"PE",
    "gn:dem":3877,
    "gn:feature_class":"P",
    "gn:feature_code":"PPL",
    "gn:name":"Chup\u00e1n",
    "gn:population":0,
    "gn:timezone":"America/Lima",
    "iso:country":"PE",
    "name:cat_x_preferred":[
        "Amir Coban"
    ],
    "name:deu_x_preferred":[
        "Amir Tschupan"
    ],
    "name:fas_x_preferred":[
        "\u0627\u0645\u06cc\u0631 \u0686\u0648\u067e\u0627\u0646"
    ],
    "name:fra_x_preferred":[
        "Chupan"
    ],
    "name:ita_x_preferred":[
        "Chupan"
    ],
    "name:jpn_x_preferred":[
        "\u30c1\u30e7\u30d0\u30f3"
    ],
    "name:kat_x_preferred":[
        "\u10e9\u10dd\u10d1\u10d0\u10dc \u10dc\u10dd\u10d8\u10dc\u10d8"
    ],
    "name:rus_x_preferred":[
        "\u0427\u043e\u0431\u0430\u043d"
    ],
    "name:tur_x_preferred":[
        "Emir \u00c7oban"
    ],
    "wof:name":"Chupan",
    "wof:placetype":"locality"
},
  "geometry": {"coordinates":[-75.78721999999998,-11.05167],"type":"Point"}
}