{
  "type": "Feature",
  "properties": {
    "gn:admin1_code":"5",
    "gn:admin2_code":"506.0",
    "gn:admin3_code":"50605.0",
    "gn:asciiname":"Atunhuasi",
    "gn:cc2":"PE",
    "gn:country_code":"PE",
    "gn:dem":2809,
    "gn:feature_class":"P",
    "gn:feature_code":"PPL",
    "gn:name":"Atunhuasi",
    "gn:population":0,
    "gn:timezone":"America/Lima",
    "iso:country":"PE",
    "name:und_x_variant":[
        "Atunhuasi Hacienda",
        "Atunhuasi"
    ],
    "wof:name":"Atunhuasi",
    "wof:placetype":"locality"
},
  "geometry": {"coordinates":[-73.81667,-15.01667],"type":"Point"}
}