{
  "type": "Feature",
  "properties": {
    "gn:admin1_code":"02",
    "gn:admin2_code":"205.0",
    "gn:admin3_code":"20508.0",
    "gn:asciiname":"Huallanca",
    "gn:country_code":"PE",
    "gn:dem":3539,
    "gn:feature_class":"P",
    "gn:feature_code":"PPLA3",
    "gn:name":"Huallanca",
    "gn:population":0,
    "gn:timezone":"America/Lima",
    "iso:country":"PE",
    "wof:name":"Huallanca",
    "wof:placetype":"locality"
},
  "geometry": {"coordinates":[-76.94089,-9.89796],"type":"Point"}
}