{
  "type": "Feature",
  "properties": {
    "gn:admin1_code":"21",
    "gn:admin2_code":"2105.0",
    "gn:admin3_code":"210502.0",
    "gn:asciiname":"Anahuane",
    "gn:country_code":"PE",
    "gn:dem":4230,
    "gn:feature_class":"P",
    "gn:feature_code":"PPL",
    "gn:name":"A\u00f1ahuane",
    "gn:population":0,
    "gn:timezone":"America/Lima",
    "iso:country":"PE",
    "wof:name":"Anahuane",
    "wof:placetype":"locality"
},
  "geometry": {"coordinates":[-69.64775999999999,-17.19019],"type":"Point"}
}