{
  "type": "Feature",
  "properties": {
    "gn:admin1_code":"04",
    "gn:admin2_code":"404.0",
    "gn:admin3_code":"40413.0",
    "gn:asciiname":"Pitis",
    "gn:country_code":"PE",
    "gn:dem":452,
    "gn:feature_class":"P",
    "gn:feature_code":"PPL",
    "gn:name":"Pitis",
    "gn:population":0,
    "gn:timezone":"America/Lima",
    "iso:country":"PE",
    "name:und_x_variant":[
        "Pitis Hacienda",
        "Pitis"
    ],
    "wof:name":"Pitis",
    "wof:placetype":"locality"
},
  "geometry": {"coordinates":[-72.4494,-16.24996],"type":"Point"}
}