{
  "type": "Feature",
  "properties": {
    "gn:admin1_code":"12.0",
    "gn:admin2_code":"1208.0",
    "gn:admin3_code":"120803.0",
    "gn:asciiname":"Llipllinan",
    "gn:country_code":"PE",
    "gn:dem":4310,
    "gn:feature_class":"P",
    "gn:feature_code":"PPL",
    "gn:name":"Llipllin\u00e1n",
    "gn:population":0,
    "gn:timezone":"America/Lima",
    "iso:country":"PE",
    "wof:name":"Llipllinan",
    "wof:placetype":"locality"
},
  "geometry": {"coordinates":[-75.89267,-11.70581],"type":"Point"}
}