{
  "type": "Feature",
  "properties": {
    "gn:admin1_code":"20",
    "gn:admin2_code":"2003.0",
    "gn:admin3_code":"200304.0",
    "gn:asciiname":"Piedra Parada",
    "gn:country_code":"PE",
    "gn:dem":1834,
    "gn:feature_class":"P",
    "gn:feature_code":"PPL",
    "gn:name":"Piedra Parada",
    "gn:population":0,
    "gn:timezone":"America/Lima",
    "iso:country":"PE",
    "wof:name":"Piedra Parada",
    "wof:placetype":"locality"
},
  "geometry": {"coordinates":[-79.54649000000001,-5.86808],"type":"Point"}
}