{
  "type": "Feature",
  "properties": {
    "gn:admin1_code":"02",
    "gn:admin2_code":"218.0",
    "gn:admin3_code":"21806.0",
    "gn:asciiname":"San Gregorio",
    "gn:country_code":"PE",
    "gn:dem":88,
    "gn:feature_class":"P",
    "gn:feature_code":"PPL",
    "gn:name":"San Gregorio",
    "gn:population":0,
    "gn:timezone":"America/Lima",
    "iso:country":"PE",
    "name:ceb_x_preferred":[
        "San Gregorio"
    ],
    "name:ces_x_preferred":[
        "San Gregorio"
    ],
    "name:deu_x_preferred":[
        "San Gregorio"
    ],
    "name:fra_x_preferred":[
        "San Gregorio"
    ],
    "name:glg_x_preferred":[
        "San Gregorio"
    ],
    "name:ita_x_preferred":[
        "San Gregorio"
    ],
    "name:nld_x_preferred":[
        "San Gregorio"
    ],
    "name:por_x_preferred":[
        "San Gregorio"
    ],
    "name:sco_x_preferred":[
        "San Gregorio"
    ],
    "name:spa_x_preferred":[
        "San Gregorio"
    ],
    "name:srp_x_preferred":[
        "San Gregorio"
    ],
    "name:swe_x_preferred":[
        "San Gregorio"
    ],
    "wof:name":"San Gregorio",
    "wof:placetype":"locality"
},
  "geometry": {"coordinates":[-78.38333,-9.21667],"type":"Point"}
}