{
  "type": "Feature",
  "properties": {
    "gn:admin1_code":"04",
    "gn:admin2_code":"406.0",
    "gn:admin3_code":"40605.0",
    "gn:asciiname":"Corrales",
    "gn:country_code":"PE",
    "gn:dem":3069,
    "gn:feature_class":"P",
    "gn:feature_code":"PPL",
    "gn:name":"Corrales",
    "gn:population":0,
    "gn:timezone":"America/Lima",
    "iso:country":"PE",
    "name:cat_x_preferred":[
        "Corrales"
    ],
    "name:ceb_x_preferred":[
        "Corrales"
    ],
    "name:deu_x_preferred":[
        "Corrales"
    ],
    "name:eus_x_preferred":[
        "Corrales"
    ],
    "name:fra_x_preferred":[
        "Corrales"
    ],
    "name:ita_x_preferred":[
        "Corrales"
    ],
    "name:nld_x_preferred":[
        "Corrales"
    ],
    "name:pol_x_preferred":[
        "Corrales"
    ],
    "name:por_x_preferred":[
        "Corrales"
    ],
    "name:rus_x_preferred":[
        "\u041a\u043e\u0440\u0440\u0430\u043b\u0435\u0441"
    ],
    "name:spa_x_preferred":[
        "Corrales"
    ],
    "name:swe_x_preferred":[
        "Corrales"
    ],
    "name:vie_x_preferred":[
        "Corrales"
    ],
    "name:war_x_preferred":[
        "Corrales"
    ],
    "wof:name":"Corrales",
    "wof:placetype":"locality"
},
  "geometry": {"coordinates":[-72.65864000000001,-15.93388],"type":"Point"}
}