{
  "type": "Feature",
  "properties": {
    "gn:admin1_code":"15",
    "gn:admin2_code":"1508.0",
    "gn:admin3_code":"150812.0",
    "gn:asciiname":"Mazo",
    "gn:country_code":"PE",
    "gn:dem":65,
    "gn:feature_class":"P",
    "gn:feature_code":"PPL",
    "gn:name":"Mazo",
    "gn:population":0,
    "gn:timezone":"America/Lima",
    "iso:country":"PE",
    "wof:name":"Mazo",
    "wof:placetype":"locality"
},
  "geometry": {"coordinates":[-77.60668000000003,-11.02339],"type":"Point"}
}