{
  "type": "Feature",
  "properties": {
    "gn:admin1_code":"19.0",
    "gn:admin2_code":"1902.0",
    "gn:asciiname":"Pogo",
    "gn:country_code":"PE",
    "gn:dem":4306,
    "gn:feature_class":"P",
    "gn:feature_code":"PPL",
    "gn:name":"Pogo",
    "gn:population":0,
    "gn:timezone":"America/Lima",
    "iso:country":"PE",
    "name:deu_x_preferred":[
        "Pogo"
    ],
    "name:est_x_preferred":[
        "Pogo"
    ],
    "name:fin_x_preferred":[
        "Pogo"
    ],
    "name:fra_x_preferred":[
        "Pogo"
    ],
    "name:hun_x_preferred":[
        "Pogo"
    ],
    "name:ita_x_preferred":[
        "Pogo"
    ],
    "name:nld_x_preferred":[
        "Pogo"
    ],
    "name:pol_x_preferred":[
        "Pogo"
    ],
    "name:rus_x_preferred":[
        "\u041f\u043e\u0433\u043e"
    ],
    "name:spa_x_preferred":[
        "Pogo"
    ],
    "wof:name":"Pogo",
    "wof:placetype":"locality"
},
  "geometry": {"coordinates":[-76.53610999999999,-10.3825],"type":"Point"}
}