{
  "type": "Feature",
  "properties": {
    "gn:admin1_code":"19.0",
    "gn:admin2_code":"1902.0",
    "gn:asciiname":"Pogo",
    "gn:country_code":"PE",
    "gn:dem":4306,
    "gn:feature_class":"P",
    "gn:feature_code":"PPL",
    "gn:name":"Pogo",
    "gn:population":0,
    "gn:timezone":"America/Lima",
    "iso:country":"PE",
    "wof:name":"Pogo",
    "wof:placetype":"locality"
},
  "geometry": {"coordinates":[-76.53610999999999,-10.3825],"type":"Point"}
}