{
  "type": "Feature",
  "properties": {
    "gn:admin1_code":"20",
    "gn:admin2_code":"2002.0",
    "gn:admin3_code":"200208.0",
    "gn:asciiname":"Llicsa Saccha Palmo",
    "gn:country_code":"PE",
    "gn:dem":1445,
    "gn:feature_class":"P",
    "gn:feature_code":"PPL",
    "gn:name":"Llicsa Saccha Palmo",
    "gn:population":0,
    "gn:timezone":"America/Lima",
    "iso:country":"PE",
    "name:und_x_variant":[
        "Soccha Palmo",
        "Hacienda Llicsa Saccha Palmo",
        "Llicsa Saccha Palmo"
    ],
    "wof:name":"Llicsa Saccha Palmo",
    "wof:placetype":"locality"
},
  "geometry": {"coordinates":[-80.04193000000002,-4.83594],"type":"Point"}
}