{
  "type": "Feature",
  "properties": {
    "gn:admin1_code":"18",
    "gn:admin2_code":"1801.0",
    "gn:admin3_code":"180106.0",
    "gn:asciiname":"La Banda",
    "gn:country_code":"PE",
    "gn:dem":2217,
    "gn:feature_class":"P",
    "gn:feature_code":"PPL",
    "gn:name":"La Banda",
    "gn:population":0,
    "gn:timezone":"America/Lima",
    "iso:country":"PE",
    "wof:name":"La Banda",
    "wof:placetype":"locality"
},
  "geometry": {"coordinates":[-70.85046,-17.07329],"type":"Point"}
}