{
  "type": "Feature",
  "properties": {
    "gn:admin1_code":"18",
    "gn:admin2_code":"1801.0",
    "gn:admin3_code":"180106.0",
    "gn:asciiname":"La Banda",
    "gn:country_code":"PE",
    "gn:dem":2217,
    "gn:feature_class":"P",
    "gn:feature_code":"PPL",
    "gn:name":"La Banda",
    "gn:population":0,
    "gn:timezone":"America/Lima",
    "iso:country":"PE",
    "name:ara_x_preferred":[
        "\u0644\u0627 \u0628\u0627\u0646\u062f\u0627"
    ],
    "name:ceb_x_preferred":[
        "La Banda"
    ],
    "name:ces_x_preferred":[
        "La Banda"
    ],
    "name:deu_x_preferred":[
        "La Banda"
    ],
    "name:fra_x_preferred":[
        "La Banda"
    ],
    "name:heb_x_preferred":[
        "\u05dc\u05d4 \u05d1\u05e0\u05d3\u05d4"
    ],
    "name:ita_x_preferred":[
        "La Banda"
    ],
    "name:kat_x_preferred":[
        "\u10da\u10d0-\u10d1\u10d0\u10dc\u10d3\u10d0"
    ],
    "name:lit_x_preferred":[
        "La Banda"
    ],
    "name:nld_x_preferred":[
        "La Banda"
    ],
    "name:pol_x_preferred":[
        "La Banda"
    ],
    "name:que_x_preferred":[
        "La Banda"
    ],
    "name:slk_x_preferred":[
        "La Banda"
    ],
    "name:spa_x_preferred":[
        "La Banda"
    ],
    "name:srp_x_preferred":[
        "\u0411\u0430\u043d\u0434\u0430"
    ],
    "name:swe_x_preferred":[
        "La Banda"
    ],
    "name:szl_x_preferred":[
        "La Banda"
    ],
    "name:urd_x_preferred":[
        "\u0644\u0627 \u0628\u0627\u0646\u0688\u0627"
    ],
    "name:zho_x_preferred":[
        "\u62c9\u73ed\u9054"
    ],
    "wof:name":"La Banda",
    "wof:placetype":"locality"
},
  "geometry": {"coordinates":[-70.85046,-17.07329],"type":"Point"}
}