{
  "type": "Feature",
  "properties": {
    "gn:admin1_code":"10.0",
    "gn:admin2_code":"1007.0",
    "gn:asciiname":"Mono",
    "gn:country_code":"PE",
    "gn:dem":526,
    "gn:feature_class":"P",
    "gn:feature_code":"PPLL",
    "gn:name":"Mono",
    "gn:population":0,
    "gn:timezone":"America/Lima",
    "iso:country":"PE",
    "wof:name":"Mono",
    "wof:placetype":"locality"
},
  "geometry": {"coordinates":[-76.40889,-8.47694],"type":"Point"}
}