{
  "type": "Feature",
  "properties": {
    "gn:admin1_code":"5",
    "gn:admin2_code":"511.0",
    "gn:admin3_code":"51104.0",
    "gn:asciiname":"Ccaccahuasan",
    "gn:country_code":"PE",
    "gn:dem":3626,
    "gn:feature_class":"P",
    "gn:feature_code":"PPL",
    "gn:name":"Ccaccahuas\u00e1n",
    "gn:population":0,
    "gn:timezone":"America/Lima",
    "iso:country":"PE",
    "wof:name":"Ccaccahuasan",
    "wof:placetype":"locality"
},
  "geometry": {"coordinates":[-73.91133000000001,-13.5237],"type":"Point"}
}