{
  "type": "Feature",
  "properties": {
    "gn:admin1_code":"4",
    "gn:admin2_code":"406.0",
    "gn:admin3_code":"40603.0",
    "gn:asciiname":"Palcuyo",
    "gn:country_code":"PE",
    "gn:dem":4278,
    "gn:feature_class":"P",
    "gn:feature_code":"PPL",
    "gn:name":"Palcuyo",
    "gn:population":0,
    "gn:timezone":"America/Lima",
    "iso:country":"PE",
    "wof:name":"Palcuyo",
    "wof:placetype":"locality"
},
  "geometry": {"coordinates":[-72.47148,-15.3724],"type":"Point"}
}