{
  "type": "Feature",
  "properties": {
    "gn:admin1_code":"04",
    "gn:admin2_code":"401.0",
    "gn:admin3_code":"40129.0",
    "gn:asciiname":"Tasahuay",
    "gn:country_code":"PE",
    "gn:dem":2367,
    "gn:feature_class":"P",
    "gn:feature_code":"PPL",
    "gn:name":"Tasahuay",
    "gn:population":0,
    "gn:timezone":"America/Lima",
    "iso:country":"PE",
    "wof:name":"Tasahuay",
    "wof:placetype":"locality"
},
  "geometry": {"coordinates":[-71.51666999999998,-16.43333],"type":"Point"}
}