{
  "type": "Feature",
  "properties": {
    "gn:admin1_code":"10.0",
    "gn:admin2_code":"1001.0",
    "gn:admin3_code":"100109.0",
    "gn:asciiname":"Palaspata",
    "gn:country_code":"PE",
    "gn:dem":2043,
    "gn:feature_class":"P",
    "gn:feature_code":"PPLL",
    "gn:name":"Palaspata",
    "gn:population":0,
    "gn:timezone":"America/Lima",
    "iso:country":"PE",
    "wof:name":"Palaspata",
    "wof:placetype":"locality"
},
  "geometry": {"coordinates":[-76.17294,-9.87535],"type":"Point"}
}