{
  "type": "Feature",
  "properties": {
    "gn:admin1_code":"14",
    "gn:admin2_code":"1403.0",
    "gn:admin3_code":"140309.0",
    "gn:asciiname":"Rescate",
    "gn:country_code":"PE",
    "gn:dem":59,
    "gn:feature_class":"P",
    "gn:feature_code":"PPL",
    "gn:name":"Rescate",
    "gn:population":0,
    "gn:timezone":"America/Lima",
    "iso:country":"PE",
    "wof:name":"Rescate",
    "wof:placetype":"locality"
},
  "geometry": {"coordinates":[-79.81493,-6.43492],"type":"Point"}
}