{
  "type": "Feature",
  "properties": {
    "gn:admin1_code":"11",
    "gn:admin2_code":"1101.0",
    "gn:admin3_code":"110113.0",
    "gn:asciiname":"Calderones",
    "gn:country_code":"PE",
    "gn:dem":404,
    "gn:feature_class":"P",
    "gn:feature_code":"PPL",
    "gn:name":"Calderones",
    "gn:population":0,
    "gn:timezone":"America/Lima",
    "iso:country":"PE",
    "name:spa_x_preferred":[
        "Calderones"
    ],
    "wof:name":"Calderones",
    "wof:placetype":"locality"
},
  "geometry": {"coordinates":[-75.69757,-14.15351],"type":"Point"}
}