{
  "type": "Feature",
  "properties": {
    "gn:admin1_code":"19",
    "gn:admin2_code":"1902.0",
    "gn:admin3_code":"190201.0",
    "gn:asciiname":"Pachanganan",
    "gn:country_code":"PE",
    "gn:dem":3853,
    "gn:feature_class":"P",
    "gn:feature_code":"PPL",
    "gn:name":"Pachanganan",
    "gn:population":0,
    "gn:timezone":"America/Lima",
    "iso:country":"PE",
    "wof:name":"Pachanganan",
    "wof:placetype":"locality"
},
  "geometry": {"coordinates":[-76.53738,-10.59824],"type":"Point"}
}