{
  "type": "Feature",
  "properties": {
    "gn:admin1_code":"01",
    "gn:admin2_code":"102.0",
    "gn:admin3_code":"10205.0",
    "gn:asciiname":"Indio Nashipa",
    "gn:country_code":"PE",
    "gn:dem":724,
    "gn:feature_class":"P",
    "gn:feature_code":"PPL",
    "gn:name":"Indio Nashipa",
    "gn:population":0,
    "gn:timezone":"America/Lima",
    "iso:country":"PE",
    "wof:name":"Indio Nashipa",
    "wof:placetype":"locality"
},
  "geometry": {"coordinates":[-78.26666999999998,-4.93333],"type":"Point"}
}