{
  "type": "Feature",
  "properties": {
    "gn:admin1_code":"9.0",
    "gn:admin2_code":"903.0",
    "gn:admin3_code":"90304.0",
    "gn:asciiname":"Huayrapata",
    "gn:country_code":"PE",
    "gn:dem":4151,
    "gn:feature_class":"P",
    "gn:feature_code":"PPL",
    "gn:name":"Huayrapata",
    "gn:population":0,
    "gn:timezone":"America/Lima",
    "iso:country":"PE",
    "wof:name":"Huayrapata",
    "wof:placetype":"locality"
},
  "geometry": {"coordinates":[-74.75605999999998,-12.92369],"type":"Point"}
}