{
  "type": "Feature",
  "properties": {
    "gn:admin1_code":"4",
    "gn:admin2_code":"404.0",
    "gn:admin3_code":"40404.0",
    "gn:asciiname":"Chachas",
    "gn:country_code":"PE",
    "gn:dem":3064,
    "gn:feature_class":"P",
    "gn:feature_code":"PPL",
    "gn:name":"Chachas",
    "gn:population":0,
    "gn:timezone":"America/Lima",
    "iso:country":"PE",
    "wof:name":"Chachas",
    "wof:placetype":"locality"
},
  "geometry": {"coordinates":[-72.26917,-15.50139],"type":"Point"}
}