{
  "type": "Feature",
  "properties": {
    "gn:admin1_code":"15",
    "gn:admin2_code":"1502.0",
    "gn:admin3_code":"150203.0",
    "gn:asciiname":"Molino",
    "gn:country_code":"PE",
    "gn:dem":107,
    "gn:feature_class":"P",
    "gn:feature_code":"PPL",
    "gn:name":"Molino",
    "gn:population":0,
    "gn:timezone":"America/Lima",
    "iso:country":"PE",
    "name:ceb_x_preferred":[
        "Molino"
    ],
    "name:deu_x_preferred":[
        "Molino"
    ],
    "name:epo_x_preferred":[
        "Molino"
    ],
    "name:fra_x_preferred":[
        "Molino"
    ],
    "name:ita_x_preferred":[
        "Molino"
    ],
    "name:por_x_preferred":[
        "Molino"
    ],
    "name:spa_x_preferred":[
        "Molino"
    ],
    "name:srp_x_preferred":[
        "Molino"
    ],
    "name:swe_x_preferred":[
        "Molino"
    ],
    "name:tgl_x_preferred":[
        "Molino"
    ],
    "wof:name":"Molino",
    "wof:placetype":"locality"
},
  "geometry": {"coordinates":[-77.76276999999997,-10.6986],"type":"Point"}
}