{
  "type": "Feature",
  "properties": {
    "gn:admin1_code":"5",
    "gn:admin2_code":"507.0",
    "gn:admin3_code":"50705.0",
    "gn:asciiname":"Allate",
    "gn:country_code":"PE",
    "gn:dem":3415,
    "gn:feature_class":"P",
    "gn:feature_code":"PPL",
    "gn:name":"Allate",
    "gn:population":0,
    "gn:timezone":"America/Lima",
    "iso:country":"PE",
    "name:spa_x_preferred":[
        "Allate"
    ],
    "wof:name":"Allate",
    "wof:placetype":"locality"
},
  "geometry": {"coordinates":[-73.9765,-15.38874],"type":"Point"}
}