{
  "type": "Feature",
  "properties": {
    "gn:admin1_code":"12",
    "gn:admin2_code":"1202.0",
    "gn:admin3_code":"120214.0",
    "gn:asciiname":"Acushchuri",
    "gn:country_code":"PE",
    "gn:dem":3870,
    "gn:feature_class":"P",
    "gn:feature_code":"PPL",
    "gn:name":"Acushchuri",
    "gn:population":0,
    "gn:timezone":"America/Lima",
    "iso:country":"PE",
    "wof:name":"Acushchuri",
    "wof:placetype":"locality"
},
  "geometry": {"coordinates":[-75.53971999999997,-12.06833],"type":"Point"}
}