{
  "type": "Feature",
  "properties": {
    "gn:admin1_code":"1.0",
    "gn:admin2_code":"101.0",
    "gn:admin3_code":"10118.0",
    "gn:asciiname":"Triunfololto",
    "gn:country_code":"PE",
    "gn:dem":2474,
    "gn:feature_class":"P",
    "gn:feature_code":"PPL",
    "gn:name":"Triunfololto",
    "gn:population":0,
    "gn:timezone":"America/Lima",
    "iso:country":"PE",
    "wof:name":"Triunfololto",
    "wof:placetype":"locality"
},
  "geometry": {"coordinates":[-77.74366999999999,-6.2489],"type":"Point"}
}