{
  "type": "Feature",
  "properties": {
    "gn:admin1_code":"23",
    "gn:admin2_code":"2301.0",
    "gn:admin3_code":"230107.0",
    "gn:asciiname":"El Porvenir",
    "gn:country_code":"PE",
    "gn:dem":4188,
    "gn:feature_class":"P",
    "gn:feature_code":"PPL",
    "gn:name":"El Porvenir",
    "gn:population":0,
    "gn:timezone":"America/Lima",
    "iso:country":"PE",
    "name:ben_x_preferred":[
        "\u098f\u09b2 \u09aa\u09b0\u09ad\u09c7\u09a8\u09bf\u09b0"
    ],
    "name:ceb_x_preferred":[
        "El Porvenir"
    ],
    "name:deu_x_preferred":[
        "El Porvenir"
    ],
    "name:ell_x_preferred":[
        "\u0395\u03bb \u03a0\u03bf\u03c1\u03b2\u03b5\u03bd\u03af\u03c1"
    ],
    "name:epo_x_preferred":[
        "El Porvenir"
    ],
    "name:fas_x_preferred":[
        "\u0627\u0644 \u067e\u0648\u0631\u0648\u0646\u06cc\u0631"
    ],
    "name:fra_x_preferred":[
        "El Porvenir"
    ],
    "name:glg_x_preferred":[
        "El Porvenir"
    ],
    "name:heb_x_preferred":[
        "\u05d0\u05dc \u05e4\u05d5\u05e8\u05d1\u05e0\u05d9\u05e8"
    ],
    "name:hin_x_preferred":[
        "\u090f\u0932 \u092a\u094b\u0930\u094d\u0935\u0947\u0928\u0940\u0930"
    ],
    "name:hun_x_preferred":[
        "El Porvenir"
    ],
    "name:ind_x_preferred":[
        "El Porvenir"
    ],
    "name:ita_x_preferred":[
        "El Porvenir"
    ],
    "name:kor_x_preferred":[
        "\uc5d8 \ud3ec\ub974\ubca0\ub2c8\ub974"
    ],
    "name:nld_x_preferred":[
        "El Porvenir"
    ],
    "name:pol_x_preferred":[
        "El Porvenir"
    ],
    "name:rus_x_preferred":[
        "\u042d\u043b\u044c-\u041f\u043e\u0440\u0432\u0435\u043d\u0438\u0440"
    ],
    "name:spa_x_preferred":[
        "El Porvenir"
    ],
    "name:srp_x_preferred":[
        "\u0415\u043b \u041f\u043e\u0440\u0432\u0435\u043d\u0438\u0440"
    ],
    "name:swe_x_preferred":[
        "El Porvenir"
    ],
    "name:tur_x_preferred":[
        "El Porvenir"
    ],
    "name:ukr_x_preferred":[
        "\u0415\u043b\u044c-\u041f\u043e\u0440\u0432\u0435\u043d\u0456\u0440"
    ],
    "name:vie_x_preferred":[
        "El Porvenir"
    ],
    "name:zho_cn_x_preferred":[
        "\u57c3\u5c14\u6ce2\u97e6\u5c3c\u5c14"
    ],
    "name:zho_tw_x_preferred":[
        "\u6ce2\u723e\u51e1\u5c3c\u723e"
    ],
    "wof:name":"El Porvenir",
    "wof:placetype":"locality"
},
  "geometry": {"coordinates":[-69.55,-17.53333],"type":"Point"}
}