{
  "type": "Feature",
  "properties": {
    "gn:admin1_code":"24",
    "gn:admin2_code":"2401.0",
    "gn:admin3_code":"240104.0",
    "gn:asciiname":"Cabeza de Lagarto",
    "gn:country_code":"PE",
    "gn:dem":34,
    "gn:feature_class":"P",
    "gn:feature_code":"PPL",
    "gn:name":"Cabeza de Lagarto",
    "gn:population":0,
    "gn:timezone":"America/Lima",
    "iso:country":"PE",
    "wof:name":"Cabeza de Lagarto",
    "wof:placetype":"locality"
},
  "geometry": {"coordinates":[-80.43021999999998,-3.67652],"type":"Point"}
}