{
  "type": "Feature",
  "properties": {
    "gn:admin1_code":"22.0",
    "gn:admin2_code":"2204.0",
    "gn:admin3_code":"220405.0",
    "gn:asciiname":"Nuevo Ambiente",
    "gn:country_code":"PE",
    "gn:dem":284,
    "gn:feature_class":"P",
    "gn:feature_code":"PPL",
    "gn:name":"Nuevo Ambiente",
    "gn:population":0,
    "gn:timezone":"America/Lima",
    "iso:country":"PE",
    "name:spa_x_preferred":[
        "Nuevo Ambiente"
    ],
    "wof:name":"Nuevo Ambiente",
    "wof:placetype":"locality"
},
  "geometry": {"coordinates":[-76.73106,-7.07334],"type":"Point"}
}