{
  "type": "Feature",
  "properties": {
    "gn:admin1_code":"11.0",
    "gn:admin2_code":"1101.0",
    "gn:admin3_code":"110103.0",
    "gn:asciiname":"San Alfonso",
    "gn:country_code":"PE",
    "gn:dem":407,
    "gn:feature_class":"P",
    "gn:feature_code":"PPL",
    "gn:name":"San Alfonso",
    "gn:population":0,
    "gn:timezone":"America/Lima",
    "iso:country":"PE",
    "name:spa_x_preferred":[
        "San Alfonso"
    ],
    "wof:name":"San Alfonso",
    "wof:placetype":"locality"
},
  "geometry": {"coordinates":[-75.70766,-14.0822],"type":"Point"}
}