{
  "type": "Feature",
  "properties": {
    "gn:admin1_code":"16",
    "gn:admin2_code":"1607.0",
    "gn:admin3_code":"160705.0",
    "gn:asciiname":"Raona",
    "gn:country_code":"PE",
    "gn:dem":147,
    "gn:feature_class":"P",
    "gn:feature_code":"PPL",
    "gn:name":"Raona",
    "gn:population":0,
    "gn:timezone":"America/Lima",
    "iso:country":"PE",
    "wof:name":"Raona",
    "wof:placetype":"locality"
},
  "geometry": {"coordinates":[-76.52524,-4.7105],"type":"Point"}
}