{
  "type": "Feature",
  "properties": {
    "gn:admin1_code":"20.0",
    "gn:admin2_code":"2002.0",
    "gn:admin3_code":"200206.0",
    "gn:asciiname":"Los Encuentros",
    "gn:country_code":"PE",
    "gn:dem":1325,
    "gn:feature_class":"P",
    "gn:feature_code":"PPL",
    "gn:name":"Los Encuentros",
    "gn:population":0,
    "gn:timezone":"America/Lima",
    "iso:country":"PE",
    "wof:name":"Los Encuentros",
    "wof:placetype":"locality"
},
  "geometry": {"coordinates":[-79.6221,-4.88475],"type":"Point"}
}