{
  "type": "Feature",
  "properties": {
    "gn:admin1_code":"02",
    "gn:admin2_code":"211.0",
    "gn:admin3_code":"21104.0",
    "gn:asciiname":"Huayan",
    "gn:country_code":"PE",
    "gn:dem":2703,
    "gn:feature_class":"P",
    "gn:feature_code":"PPL",
    "gn:name":"Huay\u00e1n",
    "gn:population":0,
    "gn:timezone":"America/Lima",
    "iso:country":"PE",
    "wof:name":"Huayan",
    "wof:placetype":"locality"
},
  "geometry": {"coordinates":[-77.70761999999998,-9.87558],"type":"Point"}
}