{
  "type": "Feature",
  "properties": {
    "gn:admin1_code":"2.0",
    "gn:admin2_code":"214.0",
    "gn:admin3_code":"21403.0",
    "gn:asciiname":"Pachas",
    "gn:country_code":"PE",
    "gn:dem":2862,
    "gn:feature_class":"P",
    "gn:feature_code":"PPL",
    "gn:name":"Pachas",
    "gn:population":0,
    "gn:timezone":"America/Lima",
    "iso:country":"PE",
    "wof:name":"Pachas",
    "wof:placetype":"locality"
},
  "geometry": {"coordinates":[-77.19299000000002,-10.37056],"type":"Point"}
}