{
  "type": "Feature",
  "properties": {
    "gn:admin1_code":"15",
    "gn:admin2_code":"1506.0",
    "gn:admin3_code":"150611.0",
    "gn:asciiname":"Piscocoto",
    "gn:country_code":"PE",
    "gn:dem":2232,
    "gn:feature_class":"P",
    "gn:feature_code":"PPL",
    "gn:name":"Piscocoto",
    "gn:population":0,
    "gn:timezone":"America/Lima",
    "iso:country":"PE",
    "wof:name":"Piscocoto",
    "wof:placetype":"locality"
},
  "geometry": {"coordinates":[-76.81305999999999,-11.36472],"type":"Point"}
}