{
  "type": "Feature",
  "properties": {
    "gn:admin1_code":"15",
    "gn:admin2_code":"1510.0",
    "gn:admin3_code":"151025.0",
    "gn:asciiname":"Pancao",
    "gn:country_code":"PE",
    "gn:dem":1400,
    "gn:feature_class":"P",
    "gn:feature_code":"PPL",
    "gn:name":"Pancao",
    "gn:population":0,
    "gn:timezone":"America/Lima",
    "iso:country":"PE",
    "wof:name":"Pancao",
    "wof:placetype":"locality"
},
  "geometry": {"coordinates":[-76.28333000000001,-12.33333],"type":"Point"}
}