{
  "type": "Feature",
  "properties": {
    "gn:admin1_code":"14",
    "gn:admin2_code":"1403.0",
    "gn:admin3_code":"140302.0",
    "gn:asciiname":"Las Pampas",
    "gn:country_code":"PE",
    "gn:dem":192,
    "gn:feature_class":"P",
    "gn:feature_code":"PPL",
    "gn:name":"Las Pampas",
    "gn:population":0,
    "gn:timezone":"America/Lima",
    "iso:country":"PE",
    "wof:name":"Las Pampas",
    "wof:placetype":"locality"
},
  "geometry": {"coordinates":[-79.65000000000001,-6.15],"type":"Point"}
}