{
  "type": "Feature",
  "properties": {
    "gn:admin1_code":"10.0",
    "gn:admin2_code":"1010.0",
    "gn:admin3_code":"101001.0",
    "gn:asciiname":"Cayranatoc",
    "gn:country_code":"PE",
    "gn:dem":3546,
    "gn:feature_class":"P",
    "gn:feature_code":"PPL",
    "gn:name":"Cayranatoc",
    "gn:population":0,
    "gn:timezone":"America/Lima",
    "iso:country":"PE",
    "wof:name":"Cayranatoc",
    "wof:placetype":"locality"
},
  "geometry": {"coordinates":[-76.63110999999998,-10.06056],"type":"Point"}
}