{
  "type": "Feature",
  "properties": {
    "gn:admin1_code":"08",
    "gn:admin2_code":"807.0",
    "gn:admin3_code":"80701.0",
    "gn:asciiname":"Challa",
    "gn:country_code":"PE",
    "gn:dem":4114,
    "gn:feature_class":"P",
    "gn:feature_code":"PPL",
    "gn:name":"Challa",
    "gn:population":0,
    "gn:timezone":"America/Lima",
    "iso:country":"PE",
    "name:nld_x_preferred":[
        "Challa"
    ],
    "name:tel_x_preferred":[
        "\u0c1a\u0c32\u0c4d\u0c32\u0c3e"
    ],
    "wof:name":"Challa",
    "wof:placetype":"locality"
},
  "geometry": {"coordinates":[-72.03333000000001,-14.63333],"type":"Point"}
}