{
  "type": "Feature",
  "properties": {
    "gn:admin1_code":"11.0",
    "gn:admin2_code":"1101.0",
    "gn:admin3_code":"110101.0",
    "gn:asciiname":"Robles",
    "gn:country_code":"PE",
    "gn:dem":408,
    "gn:feature_class":"P",
    "gn:feature_code":"PPL",
    "gn:name":"Robles",
    "gn:population":0,
    "gn:timezone":"America/Lima",
    "iso:country":"PE",
    "name:ara_x_preferred":[
        "\u0631\u0648\u0628\u0644\u0633"
    ],
    "name:cat_x_preferred":[
        "Robles"
    ],
    "name:ceb_x_preferred":[
        "Robles"
    ],
    "name:ces_x_preferred":[
        "Robles"
    ],
    "name:deu_x_preferred":[
        "Robles"
    ],
    "name:fra_x_preferred":[
        "Robles"
    ],
    "name:jpn_x_preferred":[
        "\u30ed\u30d6\u30ec\u30b9"
    ],
    "name:nld_x_preferred":[
        "Robles"
    ],
    "name:rus_x_preferred":[
        "\u0420\u043e\u0431\u043b\u0435\u0441"
    ],
    "name:spa_x_preferred":[
        "Robles"
    ],
    "name:srp_x_preferred":[
        "\u0420\u043e\u0431\u043b\u0435\u0441"
    ],
    "name:swe_x_preferred":[
        "Robles"
    ],
    "name:ukr_x_preferred":[
        "\u0420\u043e\u0431\u043b\u0435\u0441"
    ],
    "name:zho_x_preferred":[
        "Robles"
    ],
    "wof:name":"Robles",
    "wof:placetype":"locality"
},
  "geometry": {"coordinates":[-75.73453000000001,-14.06569],"type":"Point"}
}