{
  "type": "Feature",
  "properties": {
    "gn:admin1_code":"15",
    "gn:admin2_code":"1501.0",
    "gn:admin3_code":"150118.0",
    "gn:asciiname":"Lotizacion Nana",
    "gn:country_code":"PE",
    "gn:dem":590,
    "gn:feature_class":"P",
    "gn:feature_code":"PPL",
    "gn:name":"Lotizaci\u00f3n \u00d1a\u00f1a",
    "gn:population":0,
    "gn:timezone":"America/Lima",
    "iso:country":"PE",
    "name:und_x_variant":[
        "Na\u00f1a Hacienda",
        "\u00d1a\u00f1a",
        "Lotizaci\u00f3n \u00d1a\u00f1a"
    ],
    "wof:name":"Lotizacion Nana",
    "wof:placetype":"locality"
},
  "geometry": {"coordinates":[-76.83421,-11.98114],"type":"Point"}
}