{
  "type": "Feature",
  "properties": {
    "gn:admin1_code":"4",
    "gn:admin2_code":"403.0",
    "gn:admin3_code":"40310.0",
    "gn:asciiname":"Bonaparte",
    "gn:country_code":"PE",
    "gn:dem":859,
    "gn:feature_class":"P",
    "gn:feature_code":"PPL",
    "gn:name":"Bonaparte",
    "gn:population":0,
    "gn:timezone":"America/Lima",
    "iso:country":"PE",
    "wof:name":"Bonaparte",
    "wof:placetype":"locality"
},
  "geometry": {"coordinates":[-74.33192,-15.42236],"type":"Point"}
}