{
  "type": "Feature",
  "properties": {
    "gn:admin1_code":"4",
    "gn:admin2_code":"403.0",
    "gn:admin3_code":"40310.0",
    "gn:asciiname":"Bonaparte",
    "gn:country_code":"PE",
    "gn:dem":859,
    "gn:feature_class":"P",
    "gn:feature_code":"PPL",
    "gn:name":"Bonaparte",
    "gn:population":0,
    "gn:timezone":"America/Lima",
    "iso:country":"PE",
    "name:ara_x_preferred":[
        "\u0628\u0648\u0646\u0627\u0628\u0631\u062a"
    ],
    "name:ben_x_preferred":[
        "\u09ac\u09cb\u09a8\u09be\u09aa\u09be\u09b0\u09cd\u09a4\u09c7"
    ],
    "name:cat_x_preferred":[
        "Bonaparte"
    ],
    "name:ceb_x_preferred":[
        "Bonaparte"
    ],
    "name:deu_x_preferred":[
        "Bonaparte"
    ],
    "name:ell_x_preferred":[
        "\u039c\u03c0\u03bf\u03bd\u03b1\u03c0\u03ac\u03c1\u03c4\u03b5"
    ],
    "name:fas_x_preferred":[
        "\u0628\u0646\u0627\u067e\u0627\u0631\u062a"
    ],
    "name:fra_x_preferred":[
        "Bonaparte"
    ],
    "name:hin_x_preferred":[
        "\u092c\u094b\u0928\u093e\u092a\u093e\u0930\u094d\u091f"
    ],
    "name:hun_x_preferred":[
        "Bonaparte"
    ],
    "name:ind_x_preferred":[
        "Bonaparte"
    ],
    "name:ita_x_preferred":[
        "Bonaparte"
    ],
    "name:jpn_x_preferred":[
        "\u30dc\u30ca\u30d1\u30eb\u30c8\u8af8\u5cf6"
    ],
    "name:kor_x_preferred":[
        "\ubcf4\ub098\ud30c\ub974\ud2b8"
    ],
    "name:lav_x_preferred":[
        "Bonaparts"
    ],
    "name:nld_x_preferred":[
        "Bonaparte"
    ],
    "name:nor_x_preferred":[
        "Bonaparte"
    ],
    "name:pol_x_preferred":[
        "Bonaparte"
    ],
    "name:por_x_preferred":[
        "Bonaparte"
    ],
    "name:rus_x_preferred":[
        "\u0430\u0440\u0445\u0438\u043f\u0435\u043b\u0430\u0433 \u0411\u043e\u043d\u0430\u043f\u0430\u0440\u0442\u0430"
    ],
    "name:spa_x_preferred":[
        "Bonaparte"
    ],
    "name:swe_x_preferred":[
        "Bonaparte"
    ],
    "name:tur_x_preferred":[
        "Bonaparte"
    ],
    "name:ukr_x_preferred":[
        "\u0411\u043e\u043d\u0430\u043f\u0430\u0440\u0442"
    ],
    "name:urd_x_preferred":[
        "\u0628\u0648\u0646\u0627\u067e\u0627\u0631\u0679\u06d2"
    ],
    "name:vie_x_preferred":[
        "Qu\u1ea7n \u0111\u1ea3o Bonaparte"
    ],
    "name:zho_cn_x_preferred":[
        "\u6ce2\u62ff\u5df4\u7fa4\u5c9b"
    ],
    "name:zho_tw_x_preferred":[
        "\u6ce2\u62ff\u5e15\u7fa4\u5cf6"
    ],
    "wof:name":"Bonaparte",
    "wof:placetype":"locality"
},
  "geometry": {"coordinates":[-74.33192,-15.42236],"type":"Point"}
}