{
  "type": "Feature",
  "properties": {
    "gn:admin1_code":"9.0",
    "gn:admin2_code":"907.0",
    "gn:admin3_code":"90717.0",
    "gn:asciiname":"Huajayrumi",
    "gn:country_code":"PE",
    "gn:dem":3285,
    "gn:feature_class":"P",
    "gn:feature_code":"PPL",
    "gn:name":"Huajayrumi",
    "gn:population":0,
    "gn:timezone":"America/Lima",
    "iso:country":"PE",
    "wof:name":"Huajayrumi",
    "wof:placetype":"locality"
},
  "geometry": {"coordinates":[-74.67442,-12.15209],"type":"Point"}
}