{
  "type": "Feature",
  "properties": {
    "gn:admin1_code":"21",
    "gn:admin2_code":"2103.0",
    "gn:admin3_code":"210306.0",
    "gn:asciiname":"Chascajota",
    "gn:country_code":"PE",
    "gn:dem":4595,
    "gn:feature_class":"P",
    "gn:feature_code":"PPL",
    "gn:name":"Chascajota",
    "gn:population":0,
    "gn:timezone":"America/Lima",
    "iso:country":"PE",
    "wof:name":"Chascajota",
    "wof:placetype":"locality"
},
  "geometry": {"coordinates":[-69.95976999999999,-14.31721],"type":"Point"}
}