{
  "type": "Feature",
  "properties": {
    "gn:admin1_code":"04",
    "gn:admin2_code":"403.0",
    "gn:admin3_code":"40302.0",
    "gn:asciiname":"Tres Palos",
    "gn:country_code":"PE",
    "gn:dem":84,
    "gn:feature_class":"P",
    "gn:feature_code":"PPL",
    "gn:name":"Tres Palos",
    "gn:population":0,
    "gn:timezone":"America/Lima",
    "iso:country":"PE",
    "wof:name":"Tres Palos",
    "wof:placetype":"locality"
},
  "geometry": {"coordinates":[-74.63409,-15.51424],"type":"Point"}
}