{
  "type": "Feature",
  "properties": {
    "gn:admin1_code":"5",
    "gn:admin2_code":"503.0",
    "gn:admin3_code":"50304.0",
    "gn:asciiname":"Angas",
    "gn:country_code":"PE",
    "gn:dem":4378,
    "gn:feature_class":"P",
    "gn:feature_code":"PPL",
    "gn:name":"Angas",
    "gn:population":0,
    "gn:timezone":"America/Lima",
    "iso:country":"PE",
    "wof:name":"Angas",
    "wof:placetype":"locality"
},
  "geometry": {"coordinates":[-74.56955000000001,-13.78655],"type":"Point"}
}