{
  "type": "Feature",
  "properties": {
    "gn:admin1_code":"8",
    "gn:admin2_code":"806.0",
    "gn:admin3_code":"80606.0",
    "gn:asciiname":"Carachuma",
    "gn:country_code":"PE",
    "gn:dem":4293,
    "gn:feature_class":"P",
    "gn:feature_code":"PPL",
    "gn:name":"Carachuma",
    "gn:population":0,
    "gn:timezone":"America/Lima",
    "iso:country":"PE",
    "wof:name":"Carachuma",
    "wof:placetype":"locality"
},
  "geometry": {"coordinates":[-71.14525,-14.10218],"type":"Point"}
}