{
  "type": "Feature",
  "properties": {
    "gn:admin1_code":"12",
    "gn:admin2_code":"1203.0",
    "gn:asciiname":"San Jose de Anapiari",
    "gn:country_code":"PE",
    "gn:dem":1095,
    "gn:feature_class":"P",
    "gn:feature_code":"PPL",
    "gn:name":"San Jos\u00e9 de Anapiari",
    "gn:population":0,
    "gn:timezone":"America/Lima",
    "iso:country":"PE",
    "name:spa_x_preferred":[
        "San Jos\u00e9 de Anapiari"
    ],
    "wof:name":"San Jose de Anapiari",
    "wof:placetype":"locality"
},
  "geometry": {"coordinates":[-74.73203000000002,-10.88692],"type":"Point"}
}