{
  "type": "Feature",
  "properties": {
    "gn:admin1_code":"1.0",
    "gn:admin2_code":"101.0",
    "gn:asciiname":"Buenaparte",
    "gn:country_code":"PE",
    "gn:dem":3739,
    "gn:feature_class":"P",
    "gn:feature_code":"PPLL",
    "gn:name":"Buenaparte",
    "gn:population":0,
    "gn:timezone":"America/Lima",
    "iso:country":"PE",
    "wof:name":"Buenaparte",
    "wof:placetype":"locality"
},
  "geometry": {"coordinates":[-77.74769000000001,-6.86391],"type":"Point"}
}