{
  "type": "Feature",
  "properties": {
    "gn:admin1_code":"12",
    "gn:admin2_code":"1206.0",
    "gn:admin3_code":"120604.0",
    "gn:asciiname":"Boca Sanibeni",
    "gn:country_code":"PE",
    "gn:dem":378,
    "gn:feature_class":"P",
    "gn:feature_code":"PPL",
    "gn:name":"Boca Sanibeni",
    "gn:population":0,
    "gn:timezone":"America/Lima",
    "iso:country":"PE",
    "name:spa_x_preferred":[
        "Boca Sanibeni"
    ],
    "wof:name":"Boca Sanibeni",
    "wof:placetype":"locality"
},
  "geometry": {"coordinates":[-74.08422,-11.59226],"type":"Point"}
}