{
  "type": "Feature",
  "properties": {
    "gn:admin1_code":"17.0",
    "gn:admin2_code":"1703.0",
    "gn:asciiname":"Ana Maria",
    "gn:country_code":"PE",
    "gn:dem":350,
    "gn:feature_class":"P",
    "gn:feature_code":"PPL",
    "gn:name":"Ana Maria",
    "gn:population":0,
    "gn:timezone":"America/Lima",
    "iso:country":"PE",
    "name:spa_x_preferred":[
        "Ana Maria"
    ],
    "wof:name":"Ana Maria",
    "wof:placetype":"locality"
},
  "geometry": {"coordinates":[-69.35991999999999,-11.61231],"type":"Point"}
}