{
  "type": "Feature",
  "properties": {
    "gn:admin1_code":"8.0",
    "gn:admin2_code":"809.0",
    "gn:asciiname":"Camonachari",
    "gn:country_code":"PE",
    "gn:dem":623,
    "gn:feature_class":"P",
    "gn:feature_code":"PPL",
    "gn:name":"Camonachari",
    "gn:population":0,
    "gn:timezone":"America/Lima",
    "iso:country":"PE",
    "wof:name":"Camonachari",
    "wof:placetype":"locality"
},
  "geometry": {"coordinates":[-73.78346999999999,-12.58832],"type":"Point"}
}