{
  "type": "Feature",
  "properties": {
    "gn:admin1_code":"16",
    "gn:admin2_code":"1605.0",
    "gn:admin3_code":"160508.0",
    "gn:asciiname":"Curinga",
    "gn:country_code":"PE",
    "gn:dem":119,
    "gn:feature_class":"P",
    "gn:feature_code":"PPL",
    "gn:name":"Curinga",
    "gn:population":0,
    "gn:timezone":"America/Lima",
    "iso:country":"PE",
    "wof:name":"Curinga",
    "wof:placetype":"locality"
},
  "geometry": {"coordinates":[-73.69119000000001,-6.00528],"type":"Point"}
}