{
  "type": "Feature",
  "properties": {
    "gn:admin1_code":"16",
    "gn:admin2_code":"1605.0",
    "gn:admin3_code":"160508.0",
    "gn:asciiname":"Curinga",
    "gn:country_code":"PE",
    "gn:dem":119,
    "gn:feature_class":"P",
    "gn:feature_code":"PPL",
    "gn:name":"Curinga",
    "gn:population":0,
    "gn:timezone":"America/Lima",
    "iso:country":"PE",
    "name:azb_x_preferred":[
        "\u06a9\u0648\u0631\u06cc\u0646\u062c\u0627"
    ],
    "name:bcl_x_preferred":[
        "Curinga"
    ],
    "name:bul_x_preferred":[
        "\u041a\u0443\u0440\u0438\u043d\u0433\u0430"
    ],
    "name:ceb_x_preferred":[
        "Curinga"
    ],
    "name:deu_x_preferred":[
        "Curinga"
    ],
    "name:epo_x_preferred":[
        "Curinga"
    ],
    "name:eus_x_preferred":[
        "Curinga"
    ],
    "name:fas_x_preferred":[
        "\u06a9\u0648\u0631\u06cc\u0646\u062c\u0627"
    ],
    "name:fra_x_preferred":[
        "Curinga"
    ],
    "name:hun_x_preferred":[
        "Curinga"
    ],
    "name:hye_x_preferred":[
        "\u053f\u0578\u0582\u0580\u056b\u0576\u0563\u0561"
    ],
    "name:ina_x_preferred":[
        "Curinga"
    ],
    "name:ita_x_preferred":[
        "Curinga"
    ],
    "name:jpn_x_preferred":[
        "\u30af\u30ea\u30f3\u30ac"
    ],
    "name:kaz_x_preferred":[
        "\u041a\u0443\u0440\u0438\u043d\u0433\u0430"
    ],
    "name:lat_x_preferred":[
        "Curinga"
    ],
    "name:lmo_x_preferred":[
        "Curinga"
    ],
    "name:msa_x_preferred":[
        "Curinga"
    ],
    "name:nap_x_preferred":[
        "Curinga"
    ],
    "name:nld_x_preferred":[
        "Curinga"
    ],
    "name:pms_x_preferred":[
        "Curinga"
    ],
    "name:pol_x_preferred":[
        "Curinga"
    ],
    "name:por_x_preferred":[
        "Curinga"
    ],
    "name:ron_x_preferred":[
        "Curinga"
    ],
    "name:rus_x_preferred":[
        "\u041a\u0443\u0440\u0438\u043d\u0433\u0430"
    ],
    "name:scn_x_preferred":[
        "Curinga"
    ],
    "name:sco_x_preferred":[
        "Curinga"
    ],
    "name:spa_x_preferred":[
        "Curinga"
    ],
    "name:srp_x_preferred":[
        "\u041a\u0443\u0440\u0438\u043d\u0433\u0430"
    ],
    "name:tgl_x_preferred":[
        "Curinga"
    ],
    "name:ukr_x_preferred":[
        "\u041a\u0443\u0440\u0438\u043d\u0433\u0430"
    ],
    "name:uzb_x_preferred":[
        "Curinga"
    ],
    "name:vie_x_preferred":[
        "Curinga"
    ],
    "name:vol_x_preferred":[
        "Curinga"
    ],
    "name:war_x_preferred":[
        "Curinga"
    ],
    "name:zho_x_preferred":[
        "\u5e93\u6797\u52a0"
    ],
    "wof:name":"Curinga",
    "wof:placetype":"locality"
},
  "geometry": {"coordinates":[-73.69119000000001,-6.00528],"type":"Point"}
}