{
  "type": "Feature",
  "properties": {
    "gn:admin1_code":"12",
    "gn:admin2_code":"1207.0",
    "gn:admin3_code":"120704.0",
    "gn:asciiname":"Quenua",
    "gn:country_code":"PE",
    "gn:dem":4042,
    "gn:feature_class":"P",
    "gn:feature_code":"PPL",
    "gn:name":"Quenua",
    "gn:population":0,
    "gn:timezone":"America/Lima",
    "iso:country":"PE",
    "wof:name":"Quenua",
    "wof:placetype":"locality"
},
  "geometry": {"coordinates":[-75.67368,-11.14679],"type":"Point"}
}