{
  "type": "Feature",
  "properties": {
    "gn:admin1_code":"13.0",
    "gn:admin2_code":"1308.0",
    "gn:asciiname":"Lucumaragra",
    "gn:country_code":"PE",
    "gn:dem":2790,
    "gn:feature_class":"P",
    "gn:feature_code":"PPL",
    "gn:name":"Lucumaragra",
    "gn:population":0,
    "gn:timezone":"America/Lima",
    "iso:country":"PE",
    "wof:name":"Lucumaragra",
    "wof:placetype":"locality"
},
  "geometry": {"coordinates":[-77.24139,-8.48194],"type":"Point"}
}