{
  "type": "Feature",
  "properties": {
    "gn:admin1_code":"06",
    "gn:admin2_code":"602.0",
    "gn:asciiname":"Casgabamba",
    "gn:country_code":"PE",
    "gn:dem":3676,
    "gn:feature_class":"P",
    "gn:feature_code":"PPL",
    "gn:name":"Casgabamba",
    "gn:population":0,
    "gn:timezone":"America/Lima",
    "iso:country":"PE",
    "wof:name":"Casgabamba",
    "wof:placetype":"locality"
},
  "geometry": {"coordinates":[-78.23421,-7.75169],"type":"Point"}
}