{
  "type": "Feature",
  "properties": {
    "gn:admin1_code":"12",
    "gn:admin2_code":"1201.0",
    "gn:admin3_code":"120114.0",
    "gn:asciiname":"Vilcacoto",
    "gn:country_code":"PE",
    "gn:dem":3438,
    "gn:feature_class":"P",
    "gn:feature_code":"PPL",
    "gn:name":"Vilcacoto",
    "gn:population":0,
    "gn:timezone":"America/Lima",
    "iso:country":"PE",
    "wof:name":"Vilcacoto",
    "wof:placetype":"locality"
},
  "geometry": {"coordinates":[-75.18208,-12.015],"type":"Point"}
}