{
  "type": "Feature",
  "properties": {
    "gn:admin1_code":"21",
    "gn:admin2_code":"2102.0",
    "gn:admin3_code":"210205.0",
    "gn:asciiname":"Inaspata",
    "gn:country_code":"PE",
    "gn:dem":3829,
    "gn:feature_class":"P",
    "gn:feature_code":"PPL",
    "gn:name":"Inaspata",
    "gn:population":0,
    "gn:timezone":"America/Lima",
    "iso:country":"PE",
    "wof:name":"Inaspata",
    "wof:placetype":"locality"
},
  "geometry": {"coordinates":[-70.08333,-15.33333],"type":"Point"}
}