{
  "type": "Feature",
  "properties": {
    "gn:admin1_code":"20",
    "gn:admin2_code":"2004.0",
    "gn:admin3_code":"200404.0",
    "gn:asciiname":"Chanchape",
    "gn:country_code":"PE",
    "gn:dem":128,
    "gn:feature_class":"P",
    "gn:feature_code":"PPL",
    "gn:name":"Chanchape",
    "gn:population":0,
    "gn:timezone":"America/Lima",
    "iso:country":"PE",
    "wof:name":"Chanchape",
    "wof:placetype":"locality"
},
  "geometry": {"coordinates":[-80.05099,-5.27007],"type":"Point"}
}