{
  "type": "Feature",
  "properties": {
    "gn:admin1_code":"3",
    "gn:admin2_code":"301.0",
    "gn:admin3_code":"30102.0",
    "gn:asciiname":"Accobambas",
    "gn:country_code":"PE",
    "gn:dem":2871,
    "gn:feature_class":"P",
    "gn:feature_code":"PPL",
    "gn:name":"Accobambas",
    "gn:population":0,
    "gn:timezone":"America/Lima",
    "iso:country":"PE",
    "wof:name":"Accobambas",
    "wof:placetype":"locality"
},
  "geometry": {"coordinates":[-73.02091999999998,-13.94551],"type":"Point"}
}