{
  "type": "Feature",
  "properties": {
    "gn:admin1_code":"15",
    "gn:admin2_code":"1509.0",
    "gn:admin3_code":"150901.0",
    "gn:asciiname":"Cutacancha",
    "gn:country_code":"PE",
    "gn:dem":4530,
    "gn:feature_class":"P",
    "gn:feature_code":"PPL",
    "gn:name":"Cutacancha",
    "gn:population":0,
    "gn:timezone":"America/Lima",
    "iso:country":"PE",
    "wof:name":"Cutacancha",
    "wof:placetype":"locality"
},
  "geometry": {"coordinates":[-76.8443,-10.63491],"type":"Point"}
}