{
  "type": "Feature",
  "properties": {
    "gn:admin1_code":"21",
    "gn:admin2_code":"2112.0",
    "gn:admin3_code":"211203.0",
    "gn:asciiname":"Moroncoasa",
    "gn:country_code":"PE",
    "gn:dem":4005,
    "gn:feature_class":"P",
    "gn:feature_code":"PPL",
    "gn:name":"Moroncoasa",
    "gn:population":0,
    "gn:timezone":"America/Lima",
    "iso:country":"PE",
    "wof:name":"Moroncoasa",
    "wof:placetype":"locality"
},
  "geometry": {"coordinates":[-69.82608,-14.13917],"type":"Point"}
}