{
  "type": "Feature",
  "properties": {
    "gn:admin1_code":"8",
    "gn:admin2_code":"805.0",
    "gn:admin3_code":"80503.0",
    "gn:asciiname":"Chilacunca",
    "gn:country_code":"PE",
    "gn:dem":3959,
    "gn:feature_class":"P",
    "gn:feature_code":"PPL",
    "gn:name":"Chilacunca",
    "gn:population":0,
    "gn:timezone":"America/Lima",
    "iso:country":"PE",
    "wof:name":"Chilacunca",
    "wof:placetype":"locality"
},
  "geometry": {"coordinates":[-71.36333,-14.50278],"type":"Point"}
}