{
  "type": "Feature",
  "properties": {
    "gn:admin1_code":"20",
    "gn:admin2_code":"2003.0",
    "gn:admin3_code":"200307.0",
    "gn:asciiname":"Saucepampa",
    "gn:country_code":"PE",
    "gn:dem":2028,
    "gn:feature_class":"P",
    "gn:feature_code":"PPL",
    "gn:name":"Saucepampa",
    "gn:population":0,
    "gn:timezone":"America/Lima",
    "iso:country":"PE",
    "name:und_x_variant":[
        "Saucepampa Ciudad",
        "Saucapampa Ciudad",
        "Saucepampa"
    ],
    "wof:name":"Saucepampa",
    "wof:placetype":"locality"
},
  "geometry": {"coordinates":[-79.35129000000001,-5.46935],"type":"Point"}
}