{
  "type": "Feature",
  "properties": {
    "gn:admin1_code":"16",
    "gn:admin2_code":"1601.0",
    "gn:admin3_code":"160106.0",
    "gn:asciiname":"Oro Blanco",
    "gn:country_code":"PE",
    "gn:dem":103,
    "gn:feature_class":"P",
    "gn:feature_code":"PPL",
    "gn:name":"Oro Blanco",
    "gn:population":0,
    "gn:timezone":"America/Lima",
    "iso:country":"PE",
    "wof:name":"Oro Blanco",
    "wof:placetype":"locality"
},
  "geometry": {"coordinates":[-73.21552,-3.17785],"type":"Point"}
}