{
  "type": "Feature",
  "properties": {
    "gn:admin1_code":"23.0",
    "gn:admin2_code":"2304.0",
    "gn:admin3_code":"230401.0",
    "gn:asciiname":"Lipitaca",
    "gn:country_code":"PE",
    "gn:dem":4388,
    "gn:feature_class":"P",
    "gn:feature_code":"PPL",
    "gn:name":"Lipitaca",
    "gn:population":0,
    "gn:timezone":"America/Lima",
    "iso:country":"PE",
    "wof:name":"Lipitaca",
    "wof:placetype":"locality"
},
  "geometry": {"coordinates":[-69.74563000000001,-17.38521],"type":"Point"}
}