{
  "type": "Feature",
  "properties": {
    "gn:admin1_code":"4",
    "gn:admin2_code":"405.0",
    "gn:admin3_code":"40501.0",
    "gn:asciiname":"Taquipalcca",
    "gn:country_code":"PE",
    "gn:dem":3656,
    "gn:feature_class":"P",
    "gn:feature_code":"PPL",
    "gn:name":"Taquipalcca",
    "gn:population":0,
    "gn:timezone":"America/Lima",
    "iso:country":"PE",
    "wof:name":"Taquipalcca",
    "wof:placetype":"locality"
},
  "geometry": {"coordinates":[-71.57966,-15.58919],"type":"Point"}
}