{
  "type": "Feature",
  "properties": {
    "gn:admin1_code":"18",
    "gn:admin2_code":"1802.0",
    "gn:admin3_code":"180201.0",
    "gn:asciiname":"Charicucho",
    "gn:country_code":"PE",
    "gn:dem":3058,
    "gn:feature_class":"P",
    "gn:feature_code":"PPL",
    "gn:name":"Charicucho",
    "gn:population":0,
    "gn:timezone":"America/Lima",
    "iso:country":"PE",
    "wof:name":"Charicucho",
    "wof:placetype":"locality"
},
  "geometry": {"coordinates":[-70.9675,-16.60881],"type":"Point"}
}