{
  "type": "Feature",
  "properties": {
    "gn:admin1_code":"09",
    "gn:admin2_code":"904.0",
    "gn:admin3_code":"90404.0",
    "gn:asciiname":"Hacienda Cochacc",
    "gn:country_code":"PE",
    "gn:dem":1682,
    "gn:feature_class":"P",
    "gn:feature_code":"PPL",
    "gn:name":"Hacienda Cochacc",
    "gn:population":0,
    "gn:timezone":"America/Lima",
    "iso:country":"PE",
    "name:spa_x_preferred":[
        "Hacienda Cochacc"
    ],
    "name:spa_x_variant":[
        "Cochacc"
    ],
    "wof:name":"Hacienda Cochacc",
    "wof:placetype":"locality"
},
  "geometry": {"coordinates":[-75.61883,-13.25176],"type":"Point"}
}