{
  "type": "Feature",
  "properties": {
    "gn:admin1_code":"10",
    "gn:admin2_code":"1005.0",
    "gn:admin3_code":"100507.0",
    "gn:asciiname":"Puente Maria",
    "gn:country_code":"PE",
    "gn:dem":784,
    "gn:feature_class":"P",
    "gn:feature_code":"PPL",
    "gn:name":"Puente Mar\u00eda",
    "gn:population":0,
    "gn:timezone":"America/Lima",
    "iso:country":"PE",
    "wof:name":"Puente Maria",
    "wof:placetype":"locality"
},
  "geometry": {"coordinates":[-76.24083,-9.21667],"type":"Point"}
}