{
  "type": "Feature",
  "properties": {
    "gn:admin1_code":"8.0",
    "gn:admin2_code":"803.0",
    "gn:admin3_code":"80306.0",
    "gn:asciiname":"Yanapata",
    "gn:country_code":"PE",
    "gn:dem":3787,
    "gn:feature_class":"P",
    "gn:feature_code":"PPL",
    "gn:name":"Yanapata",
    "gn:population":0,
    "gn:timezone":"America/Lima",
    "iso:country":"PE",
    "wof:name":"Yanapata",
    "wof:placetype":"locality"
},
  "geometry": {"coordinates":[-72.38972,-13.60167],"type":"Point"}
}