{
  "type": "Feature",
  "properties": {
    "gn:admin1_code":"15.0",
    "gn:admin2_code":"1505.0",
    "gn:admin3_code":"150504.0",
    "gn:asciiname":"Paguatodo",
    "gn:country_code":"PE",
    "gn:dem":8,
    "gn:feature_class":"P",
    "gn:feature_code":"PPL",
    "gn:name":"Paguatodo",
    "gn:population":0,
    "gn:timezone":"America/Lima",
    "iso:country":"PE",
    "wof:name":"Paguatodo",
    "wof:placetype":"locality"
},
  "geometry": {"coordinates":[-76.47173000000002,-13.0259],"type":"Point"}
}