{
  "type": "Feature",
  "properties": {
    "gn:admin1_code":"12.0",
    "gn:admin2_code":"1204.0",
    "gn:admin3_code":"120423.0",
    "gn:asciiname":"Mata Coto",
    "gn:country_code":"PE",
    "gn:dem":3832,
    "gn:feature_class":"P",
    "gn:feature_code":"PPL",
    "gn:name":"Mata Coto",
    "gn:population":0,
    "gn:timezone":"America/Lima",
    "iso:country":"PE",
    "wof:name":"Mata Coto",
    "wof:placetype":"locality"
},
  "geometry": {"coordinates":[-75.48180000000001,-11.87513],"type":"Point"}
}