{
  "type": "Feature",
  "properties": {
    "gn:admin1_code":"3",
    "gn:admin2_code":"302.0",
    "gn:admin3_code":"30201.0",
    "gn:asciiname":"Cuchimachay",
    "gn:country_code":"PE",
    "gn:dem":3884,
    "gn:feature_class":"P",
    "gn:feature_code":"PPL",
    "gn:name":"Cuchimachay",
    "gn:population":0,
    "gn:timezone":"America/Lima",
    "iso:country":"PE",
    "wof:name":"Cuchimachay",
    "wof:placetype":"locality"
},
  "geometry": {"coordinates":[-73.3325,-13.77389],"type":"Point"}
}