{
  "type": "Feature",
  "properties": {
    "gn:admin1_code":"05",
    "gn:admin2_code":"507.0",
    "gn:admin3_code":"50706.0",
    "gn:asciiname":"Huacachipa",
    "gn:country_code":"PE",
    "gn:dem":3482,
    "gn:feature_class":"P",
    "gn:feature_code":"PPL",
    "gn:name":"Huacachipa",
    "gn:population":0,
    "gn:timezone":"America/Lima",
    "iso:country":"PE",
    "name:spa_x_preferred":[
        "Huacachipa"
    ],
    "wof:name":"Huacachipa",
    "wof:placetype":"locality"
},
  "geometry": {"coordinates":[-73.54083,-15.28943],"type":"Point"}
}