{
  "type": "Feature",
  "properties": {
    "gn:admin1_code":"9.0",
    "gn:admin2_code":"907.0",
    "gn:admin3_code":"90705.0",
    "gn:asciiname":"Fundicion",
    "gn:country_code":"PE",
    "gn:dem":2363,
    "gn:feature_class":"P",
    "gn:feature_code":"PPL",
    "gn:name":"Fundici\u00f3n",
    "gn:population":0,
    "gn:timezone":"America/Lima",
    "iso:country":"PE",
    "wof:name":"Fundicion",
    "wof:placetype":"locality"
},
  "geometry": {"coordinates":[-74.66244,-12.28944],"type":"Point"}
}