{
  "type": "Feature",
  "properties": {
    "gn:admin1_code":"05",
    "gn:admin2_code":"511.0",
    "gn:admin3_code":"51106.0",
    "gn:asciiname":"Puca Paccana",
    "gn:country_code":"PE",
    "gn:dem":3487,
    "gn:feature_class":"P",
    "gn:feature_code":"PPL",
    "gn:name":"Puca Paccana",
    "gn:population":0,
    "gn:timezone":"America/Lima",
    "iso:country":"PE",
    "name:und_x_variant":[
        "Pucapaccana",
        "Puca Paccana"
    ],
    "wof:name":"Puca Paccana",
    "wof:placetype":"locality"
},
  "geometry": {"coordinates":[-73.84314999999999,-13.89696],"type":"Point"}
}