{
  "type": "Feature",
  "properties": {
    "gn:admin1_code":"10.0",
    "gn:admin2_code":"1005.0",
    "gn:admin3_code":"100508.0",
    "gn:asciiname":"Sagray",
    "gn:country_code":"PE",
    "gn:dem":3603,
    "gn:feature_class":"P",
    "gn:feature_code":"PPL",
    "gn:name":"Sagray",
    "gn:population":0,
    "gn:timezone":"America/Lima",
    "iso:country":"PE",
    "wof:name":"Sagray",
    "wof:placetype":"locality"
},
  "geometry": {"coordinates":[-76.82653000000001,-9.459],"type":"Point"}
}