{
  "type": "Feature",
  "properties": {
    "gn:admin1_code":"05",
    "gn:admin2_code":"506.0",
    "gn:admin3_code":"50619.0",
    "gn:asciiname":"Tocyasca",
    "gn:country_code":"PE",
    "gn:dem":3571,
    "gn:feature_class":"P",
    "gn:feature_code":"PPL",
    "gn:name":"Tocyasca",
    "gn:population":0,
    "gn:timezone":"America/Lima",
    "iso:country":"PE",
    "name:und_x_variant":[
        "Tocyasja",
        "Tocyasca"
    ],
    "wof:name":"Tocyasca",
    "wof:placetype":"locality"
},
  "geometry": {"coordinates":[-74.03766,-14.98134],"type":"Point"}
}