{
  "type": "Feature",
  "properties": {
    "gn:admin1_code":"13",
    "gn:admin2_code":"1305.0",
    "gn:admin3_code":"130504.0",
    "gn:asciiname":"Pena Blanca",
    "gn:country_code":"PE",
    "gn:dem":3429,
    "gn:feature_class":"P",
    "gn:feature_code":"PPL",
    "gn:name":"Pe\u00f1a Blanca",
    "gn:population":0,
    "gn:timezone":"America/Lima",
    "iso:country":"PE",
    "wof:name":"Pena Blanca",
    "wof:placetype":"locality"
},
  "geometry": {"coordinates":[-78.47134,-8.22854],"type":"Point"}
}