{
  "type": "Feature",
  "properties": {
    "gn:admin1_code":"15",
    "gn:admin2_code":"1510.0",
    "gn:admin3_code":"151032.0",
    "gn:asciiname":"Cruzpampa",
    "gn:country_code":"PE",
    "gn:dem":3299,
    "gn:feature_class":"P",
    "gn:feature_code":"PPL",
    "gn:name":"Cruzpampa",
    "gn:population":0,
    "gn:timezone":"America/Lima",
    "iso:country":"PE",
    "wof:name":"Cruzpampa",
    "wof:placetype":"locality"
},
  "geometry": {"coordinates":[-75.82337,-12.86481],"type":"Point"}
}