{
  "type": "Feature",
  "properties": {
    "gn:admin1_code":"20.0",
    "gn:admin2_code":"2002.0",
    "gn:admin3_code":"200202.0",
    "gn:asciiname":"Las Huacas",
    "gn:country_code":"PE",
    "gn:dem":3077,
    "gn:feature_class":"P",
    "gn:feature_code":"PPL",
    "gn:name":"Las Huacas",
    "gn:population":0,
    "gn:timezone":"America/Lima",
    "iso:country":"PE",
    "name:ceb_x_preferred":[
        "Las Huacas"
    ],
    "name:spa_x_preferred":[
        "Las Huacas"
    ],
    "name:swe_x_preferred":[
        "Las Huacas"
    ],
    "wof:name":"Las Huacas",
    "wof:placetype":"locality"
},
  "geometry": {"coordinates":[-79.88221,-4.92991],"type":"Point"}
}