{
  "type": "Feature",
  "properties": {
    "gn:admin1_code":"21",
    "gn:admin2_code":"2101.0",
    "gn:admin3_code":"210102.0",
    "gn:asciiname":"Estancia Chelapata",
    "gn:country_code":"PE",
    "gn:dem":4333,
    "gn:feature_class":"P",
    "gn:feature_code":"PPL",
    "gn:name":"Estancia Chelapata",
    "gn:population":0,
    "gn:timezone":"America/Lima",
    "iso:country":"PE",
    "wof:name":"Estancia Chelapata",
    "wof:placetype":"locality"
},
  "geometry": {"coordinates":[-70.01201999999999,-16.34705],"type":"Point"}
}