{
  "type": "Feature",
  "properties": {
    "gn:admin1_code":"12.0",
    "gn:admin2_code":"1203.0",
    "gn:admin3_code":"120302.0",
    "gn:asciiname":"Pachacutec",
    "gn:country_code":"PE",
    "gn:dem":1262,
    "gn:feature_class":"P",
    "gn:feature_code":"PPL",
    "gn:name":"Pachacutec",
    "gn:population":0,
    "gn:timezone":"America/Lima",
    "iso:country":"PE",
    "name:spa_x_preferred":[
        "Pachacutec"
    ],
    "wof:name":"Pachacutec",
    "wof:placetype":"locality"
},
  "geometry": {"coordinates":[-74.94149,-10.79267],"type":"Point"}
}