{
  "type": "Feature",
  "properties": {
    "gn:admin1_code":"5",
    "gn:admin2_code":"506.0",
    "gn:admin3_code":"50620.0",
    "gn:asciiname":"Huilcaya",
    "gn:country_code":"PE",
    "gn:dem":3234,
    "gn:feature_class":"P",
    "gn:feature_code":"PPL",
    "gn:name":"Huilcaya",
    "gn:population":0,
    "gn:timezone":"America/Lima",
    "iso:country":"PE",
    "wof:name":"Huilcaya",
    "wof:placetype":"locality"
},
  "geometry": {"coordinates":[-73.94275999999998,-14.20741],"type":"Point"}
}