{
  "type": "Feature",
  "properties": {
    "gn:admin1_code":"10.0",
    "gn:admin2_code":"1010.0",
    "gn:admin3_code":"101002.0",
    "gn:asciiname":"Majadapata",
    "gn:country_code":"PE",
    "gn:dem":3972,
    "gn:feature_class":"P",
    "gn:feature_code":"PPL",
    "gn:name":"Majadapata",
    "gn:population":0,
    "gn:timezone":"America/Lima",
    "iso:country":"PE",
    "wof:name":"Majadapata",
    "wof:placetype":"locality"
},
  "geometry": {"coordinates":[-76.75028,-10.15694],"type":"Point"}
}