{
  "type": "Feature",
  "properties": {
    "gn:admin1_code":"19.0",
    "gn:admin2_code":"1902.0",
    "gn:asciiname":"Pucahuay",
    "gn:country_code":"PE",
    "gn:dem":4369,
    "gn:feature_class":"P",
    "gn:feature_code":"PPL",
    "gn:name":"Pucahuay",
    "gn:population":0,
    "gn:timezone":"America/Lima",
    "iso:country":"PE",
    "wof:name":"Pucahuay",
    "wof:placetype":"locality"
},
  "geometry": {"coordinates":[-76.61528,-10.35889],"type":"Point"}
}