{
  "type": "Feature",
  "properties": {
    "gn:admin1_code":"15",
    "gn:admin2_code":"1510.0",
    "gn:admin3_code":"151021.0",
    "gn:asciiname":"Cotrac",
    "gn:country_code":"PE",
    "gn:dem":4536,
    "gn:feature_class":"P",
    "gn:feature_code":"PPL",
    "gn:name":"Cotrac",
    "gn:population":0,
    "gn:timezone":"America/Lima",
    "iso:country":"PE",
    "wof:name":"Cotrac",
    "wof:placetype":"locality"
},
  "geometry": {"coordinates":[-75.93889,-12.12306],"type":"Point"}
}