{
  "type": "Feature",
  "properties": {
    "gn:admin1_code":"12",
    "gn:admin2_code":"1206.0",
    "gn:admin3_code":"120602.0",
    "gn:asciiname":"Reparticion",
    "gn:country_code":"PE",
    "gn:dem":824,
    "gn:feature_class":"P",
    "gn:feature_code":"PPL",
    "gn:name":"Repartici\u00f3n",
    "gn:population":0,
    "gn:timezone":"America/Lima",
    "iso:country":"PE",
    "wof:name":"Reparticion",
    "wof:placetype":"locality"
},
  "geometry": {"coordinates":[-74.69776,-11.31777],"type":"Point"}
}