{
  "type": "Feature",
  "properties": {
    "gn:admin1_code":"09",
    "gn:admin2_code":"904.0",
    "gn:admin3_code":"90404.0",
    "gn:asciiname":"Hacienda Huayanquilla",
    "gn:country_code":"PE",
    "gn:dem":1571,
    "gn:feature_class":"P",
    "gn:feature_code":"PPL",
    "gn:name":"Hacienda Huayanquilla",
    "gn:population":0,
    "gn:timezone":"America/Lima",
    "iso:country":"PE",
    "name:spa_x_preferred":[
        "Hacienda Huayanquilla"
    ],
    "name:und_x_variant":[
        "Huayunquilla Hacienda",
        "Huayunquilla"
    ],
    "wof:name":"Hacienda Huayanquilla",
    "wof:placetype":"locality"
},
  "geometry": {"coordinates":[-75.63178000000001,-13.28362],"type":"Point"}
}