{
  "type": "Feature",
  "properties": {
    "gn:admin1_code":"22.0",
    "gn:admin2_code":"2209.0",
    "gn:admin3_code":"220904.0",
    "gn:asciiname":"Yanayoc",
    "gn:country_code":"PE",
    "gn:dem":198,
    "gn:feature_class":"P",
    "gn:feature_code":"PPL",
    "gn:name":"Yanayoc",
    "gn:population":0,
    "gn:timezone":"America/Lima",
    "iso:country":"PE",
    "name:spa_x_preferred":[
        "Yanayoc"
    ],
    "wof:name":"Yanayoc",
    "wof:placetype":"locality"
},
  "geometry": {"coordinates":[-76.05501,-6.56442],"type":"Point"}
}