{
  "type": "Feature",
  "properties": {
    "gn:admin1_code":"9.0",
    "gn:admin2_code":"903.0",
    "gn:admin3_code":"90301.0",
    "gn:asciiname":"Quihuancucho",
    "gn:country_code":"PE",
    "gn:dem":4206,
    "gn:feature_class":"P",
    "gn:feature_code":"PPL",
    "gn:name":"Quihuancucho",
    "gn:population":0,
    "gn:timezone":"America/Lima",
    "iso:country":"PE",
    "wof:name":"Quihuancucho",
    "wof:placetype":"locality"
},
  "geometry": {"coordinates":[-74.77804,-13.09819],"type":"Point"}
}