{
  "type": "Feature",
  "properties": {
    "gn:admin1_code":"04",
    "gn:admin2_code":"405.0",
    "gn:admin3_code":"40514.0",
    "gn:asciiname":"Huallpane",
    "gn:cc2":"PE",
    "gn:country_code":"PE",
    "gn:dem":4475,
    "gn:feature_class":"P",
    "gn:feature_code":"PPL",
    "gn:name":"Huallpane",
    "gn:population":0,
    "gn:timezone":"America/Lima",
    "iso:country":"PE",
    "name:und_x_variant":[
        "Huarayane",
        "Huallpane"
    ],
    "wof:name":"Huallpane",
    "wof:placetype":"locality"
},
  "geometry": {"coordinates":[-71.1825,-15.99972],"type":"Point"}
}