{
  "type": "Feature",
  "properties": {
    "gn:admin1_code":"05",
    "gn:admin2_code":"507.0",
    "gn:asciiname":"Horquilla",
    "gn:country_code":"PE",
    "gn:dem":1761,
    "gn:feature_class":"P",
    "gn:feature_code":"PPL",
    "gn:name":"Horquilla",
    "gn:population":0,
    "gn:timezone":"America/Lima",
    "iso:country":"PE",
    "name:spa_x_preferred":[
        "Horquilla"
    ],
    "wof:name":"Horquilla",
    "wof:placetype":"locality"
},
  "geometry": {"coordinates":[-74.03319999999999,-15.5422],"type":"Point"}
}