{
  "type": "Feature",
  "properties": {
    "gn:admin1_code":"13",
    "gn:admin2_code":"1309.0",
    "gn:admin3_code":"130906.0",
    "gn:asciiname":"Chillin",
    "gn:country_code":"PE",
    "gn:dem":3584,
    "gn:feature_class":"P",
    "gn:feature_code":"PPL",
    "gn:name":"Chillin",
    "gn:population":0,
    "gn:timezone":"America/Lima",
    "iso:country":"PE",
    "wof:name":"Chillin",
    "wof:placetype":"locality"
},
  "geometry": {"coordinates":[-78.21811,-7.85851],"type":"Point"}
}