{
  "type": "Feature",
  "properties": {
    "gn:admin1_code":"1.0",
    "gn:admin2_code":"101.0",
    "gn:admin3_code":"10105.0",
    "gn:asciiname":"Cliche",
    "gn:country_code":"PE",
    "gn:dem":2756,
    "gn:feature_class":"P",
    "gn:feature_code":"PPL",
    "gn:name":"Cliche",
    "gn:population":0,
    "gn:timezone":"America/Lima",
    "iso:country":"PE",
    "wof:name":"Cliche",
    "wof:placetype":"locality"
},
  "geometry": {"coordinates":[-77.71714,-6.06551],"type":"Point"}
}