{
  "type": "Feature",
  "properties": {
    "gn:admin1_code":"5.0",
    "gn:admin2_code":"501.0",
    "gn:admin3_code":"50108.0",
    "gn:asciiname":"Ipacorara",
    "gn:country_code":"PE",
    "gn:dem":2793,
    "gn:feature_class":"P",
    "gn:feature_code":"PPL",
    "gn:name":"Ipacorara",
    "gn:population":0,
    "gn:timezone":"America/Lima",
    "iso:country":"PE",
    "name:und_x_variant":[
        "Hacienda Ipacorara"
    ],
    "wof:name":"Ipacorara",
    "wof:placetype":"locality"
},
  "geometry": {"coordinates":[-74.13256,-13.09665],"type":"Point"}
}