{
  "type": "Feature",
  "properties": {
    "gn:admin1_code":"12.0",
    "gn:admin2_code":"1208.0",
    "gn:admin3_code":"120801.0",
    "gn:asciiname":"Piruro",
    "gn:country_code":"PE",
    "gn:dem":3902,
    "gn:feature_class":"P",
    "gn:feature_code":"PPL",
    "gn:name":"Piruro",
    "gn:population":0,
    "gn:timezone":"America/Lima",
    "iso:country":"PE",
    "name:bel_x_preferred":[
        "\u041f\u0456\u0440\u0443\u0440\u0430"
    ],
    "name:kat_x_preferred":[
        "\u10de\u10d8\u10e0\u10e3\u10e0\u10dd"
    ],
    "name:que_x_preferred":[
        "Phiruru"
    ],
    "name:spa_x_preferred":[
        "Piruro"
    ],
    "wof:name":"Piruro",
    "wof:placetype":"locality"
},
  "geometry": {"coordinates":[-75.85011,-11.62121],"type":"Point"}
}