{
  "type": "Feature",
  "properties": {
    "gn:admin1_code":"05",
    "gn:admin2_code":"502.0",
    "gn:admin3_code":"50203.0",
    "gn:asciiname":"Manaipata",
    "gn:cc2":"PE",
    "gn:country_code":"PE",
    "gn:dem":3780,
    "gn:feature_class":"P",
    "gn:feature_code":"PPL",
    "gn:name":"Manaipata",
    "gn:population":0,
    "gn:timezone":"America/Lima",
    "iso:country":"PE",
    "name:und_x_variant":[
        "Munaypata",
        "Manaipata"
    ],
    "wof:name":"Manaipata",
    "wof:placetype":"locality"
},
  "geometry": {"coordinates":[-74.25,-13.45],"type":"Point"}
}