{
  "type": "Feature",
  "properties": {
    "gn:admin1_code":"06",
    "gn:admin2_code":"609.0",
    "gn:admin3_code":"60904.0",
    "gn:asciiname":"Potrero",
    "gn:country_code":"PE",
    "gn:dem":2001,
    "gn:feature_class":"P",
    "gn:feature_code":"PPL",
    "gn:name":"Potrero",
    "gn:population":0,
    "gn:timezone":"America/Lima",
    "iso:country":"PE",
    "name:ceb_x_preferred":[
        "Potrero"
    ],
    "name:deu_x_preferred":[
        "Potrero"
    ],
    "name:ita_x_preferred":[
        "Potrero"
    ],
    "name:spa_x_preferred":[
        "Potrero"
    ],
    "name:srp_x_preferred":[
        "\u041f\u043e\u0442\u0440\u0435\u0440\u043e"
    ],
    "name:swe_x_preferred":[
        "Potrero"
    ],
    "wof:name":"Potrero",
    "wof:placetype":"locality"
},
  "geometry": {"coordinates":[-78.93333,-5.41667],"type":"Point"}
}