{
  "type": "Feature",
  "properties": {
    "gn:admin1_code":"8",
    "gn:admin2_code":"807.0",
    "gn:admin3_code":"80701.0",
    "gn:asciiname":"Coronta",
    "gn:country_code":"PE",
    "gn:dem":4272,
    "gn:feature_class":"P",
    "gn:feature_code":"PPL",
    "gn:name":"Coronta",
    "gn:population":0,
    "gn:timezone":"America/Lima",
    "iso:country":"PE",
    "name:cat_x_preferred":[
        "Coronta"
    ],
    "name:spa_x_preferred":[
        "Corontas"
    ],
    "wof:name":"Coronta",
    "wof:placetype":"locality"
},
  "geometry": {"coordinates":[-71.93621999999998,-14.70986],"type":"Point"}
}