{
  "type": "Feature",
  "properties": {
    "gn:admin1_code":"20",
    "gn:admin2_code":"2004.0",
    "gn:admin3_code":"200410.0",
    "gn:asciiname":"Windon",
    "gn:country_code":"PE",
    "gn:dem":1616,
    "gn:feature_class":"P",
    "gn:feature_code":"PPL",
    "gn:name":"Wind\u00f3n",
    "gn:population":0,
    "gn:timezone":"America/Lima",
    "iso:country":"PE",
    "wof:name":"Windon",
    "wof:placetype":"locality"
},
  "geometry": {"coordinates":[-79.73348,-5.12274],"type":"Point"}
}