{
  "type": "Feature",
  "properties": {
    "gn:admin1_code":"16",
    "gn:admin2_code":"1601.0",
    "gn:admin3_code":"160109.0",
    "gn:asciiname":"Fonseca",
    "gn:country_code":"PE",
    "gn:dem":116,
    "gn:feature_class":"P",
    "gn:feature_code":"PPL",
    "gn:name":"Fonseca",
    "gn:population":0,
    "gn:timezone":"America/Lima",
    "iso:country":"PE",
    "wof:name":"Fonseca",
    "wof:placetype":"locality"
},
  "geometry": {"coordinates":[-70.66667,-3.15],"type":"Point"}
}