{
  "type": "Feature",
  "properties": {
    "gn:admin1_code":"16",
    "gn:admin2_code":"1601.0",
    "gn:admin3_code":"160109.0",
    "gn:asciiname":"Fonseca",
    "gn:country_code":"PE",
    "gn:dem":116,
    "gn:feature_class":"P",
    "gn:feature_code":"PPL",
    "gn:name":"Fonseca",
    "gn:population":0,
    "gn:timezone":"America/Lima",
    "iso:country":"PE",
    "name:cat_x_preferred":[
        "Fonseca"
    ],
    "name:ceb_x_preferred":[
        "Fonseca"
    ],
    "name:ces_x_preferred":[
        "Fonseca"
    ],
    "name:fin_x_preferred":[
        "Fonseca"
    ],
    "name:fra_x_preferred":[
        "Fonseca"
    ],
    "name:glg_x_preferred":[
        "Fonseca"
    ],
    "name:ita_x_preferred":[
        "Fonseca"
    ],
    "name:jpn_x_preferred":[
        "\u30d5\u30a9\u30f3\u30bb\u30ab"
    ],
    "name:kor_x_preferred":[
        "\ud3f0\uc138\uce74"
    ],
    "name:lit_x_preferred":[
        "Fonseca"
    ],
    "name:nld_x_preferred":[
        "Fonseca"
    ],
    "name:pol_x_preferred":[
        "Fonseca"
    ],
    "name:por_x_preferred":[
        "Fonseca"
    ],
    "name:rus_x_preferred":[
        "\u0424\u043e\u043d\u0441\u0435\u043a\u0430"
    ],
    "name:spa_x_preferred":[
        "Fonseca"
    ],
    "name:swe_x_preferred":[
        "Fonseca"
    ],
    "name:ukr_x_preferred":[
        "\u0424\u043e\u043d\u0441\u0435\u043a\u0430"
    ],
    "name:vie_x_preferred":[
        "Fonseca"
    ],
    "wof:name":"Fonseca",
    "wof:placetype":"locality"
},
  "geometry": {"coordinates":[-70.66667,-3.15],"type":"Point"}
}