{
  "type": "Feature",
  "properties": {
    "gn:admin1_code":"2.0",
    "gn:admin2_code":"205.0",
    "gn:admin3_code":"20501.0",
    "gn:asciiname":"Paccha",
    "gn:country_code":"PE",
    "gn:dem":3408,
    "gn:feature_class":"P",
    "gn:feature_code":"PPL",
    "gn:name":"Paccha",
    "gn:population":0,
    "gn:timezone":"America/Lima",
    "iso:country":"PE",
    "wof:name":"Paccha",
    "wof:placetype":"locality"
},
  "geometry": {"coordinates":[-77.17104,-10.1155],"type":"Point"}
}