{
  "type": "Feature",
  "properties": {
    "gn:admin1_code":"15",
    "gn:admin2_code":"1508.0",
    "gn:admin3_code":"150812.0",
    "gn:asciiname":"Ruquia",
    "gn:country_code":"PE",
    "gn:dem":19,
    "gn:feature_class":"P",
    "gn:feature_code":"PPL",
    "gn:name":"Ruquia",
    "gn:population":0,
    "gn:timezone":"America/Lima",
    "iso:country":"PE",
    "name:und_x_variant":[
        "Hacienda Ruquia",
        "Ruquia Hacienda",
        "Ruquia"
    ],
    "wof:name":"Ruquia",
    "wof:placetype":"locality"
},
  "geometry": {"coordinates":[-77.63726,-11.04123],"type":"Point"}
}