{
  "type": "Feature",
  "properties": {
    "gn:admin1_code":"02",
    "gn:admin2_code":"219.0",
    "gn:admin3_code":"21906.0",
    "gn:asciiname":"Huallobamba",
    "gn:country_code":"PE",
    "gn:dem":3334,
    "gn:feature_class":"P",
    "gn:feature_code":"PPL",
    "gn:name":"Huallobamba",
    "gn:population":0,
    "gn:timezone":"America/Lima",
    "iso:country":"PE",
    "name:und_x_variant":[
        "Huayllabamba",
        "Huallobamba"
    ],
    "wof:name":"Huallobamba",
    "wof:placetype":"locality"
},
  "geometry": {"coordinates":[-77.56768000000002,-8.53596],"type":"Point"}
}