{
  "type": "Feature",
  "properties": {
    "gn:admin1_code":"25",
    "gn:admin2_code":"2504.0",
    "gn:asciiname":"Jose Pardo",
    "gn:country_code":"PE",
    "gn:dem":224,
    "gn:feature_class":"P",
    "gn:feature_code":"PPL",
    "gn:name":"Jos\u00e9 Pardo",
    "gn:population":0,
    "gn:timezone":"America/Lima",
    "iso:country":"PE",
    "wof:name":"Jose Pardo",
    "wof:placetype":"locality"
},
  "geometry": {"coordinates":[-70.63333,-9.48333],"type":"Point"}
}