{
  "type": "Feature",
  "properties": {
    "gn:admin1_code":"10",
    "gn:admin2_code":"1002.0",
    "gn:admin3_code":"100205.0",
    "gn:asciiname":"Cochatama",
    "gn:country_code":"PE",
    "gn:dem":2766,
    "gn:feature_class":"P",
    "gn:feature_code":"PPL",
    "gn:name":"Cochatama",
    "gn:population":0,
    "gn:timezone":"America/Lima",
    "iso:country":"PE",
    "wof:name":"Cochatama",
    "wof:placetype":"locality"
},
  "geometry": {"coordinates":[-76.25378000000001,-10.12685],"type":"Point"}
}