{
  "type": "Feature",
  "properties": {
    "gn:admin1_code":"21",
    "gn:admin2_code":"2106.0",
    "gn:admin3_code":"210608.0",
    "gn:asciiname":"Sisinahuyo",
    "gn:country_code":"PE",
    "gn:dem":3886,
    "gn:feature_class":"P",
    "gn:feature_code":"PPL",
    "gn:name":"Sisinahuyo",
    "gn:population":0,
    "gn:timezone":"America/Lima",
    "iso:country":"PE",
    "wof:name":"Sisinahuyo",
    "wof:placetype":"locality"
},
  "geometry": {"coordinates":[-69.61428000000001,-15.21907],"type":"Point"}
}