{
  "type": "Feature",
  "properties": {
    "gn:admin1_code":"21",
    "gn:admin2_code":"2104.0",
    "gn:admin3_code":"210404.0",
    "gn:asciiname":"Maycopujo",
    "gn:country_code":"PE",
    "gn:dem":3862,
    "gn:feature_class":"P",
    "gn:feature_code":"PPL",
    "gn:name":"Maycopujo",
    "gn:population":0,
    "gn:timezone":"America/Lima",
    "iso:country":"PE",
    "wof:name":"Maycopujo",
    "wof:placetype":"locality"
},
  "geometry": {"coordinates":[-69.21250999999999,-16.76534],"type":"Point"}
}