{
  "type": "Feature",
  "properties": {
    "gn:admin1_code":"4",
    "gn:admin2_code":"408.0",
    "gn:admin3_code":"40801.0",
    "gn:asciiname":"Parjapuquio",
    "gn:country_code":"PE",
    "gn:dem":4153,
    "gn:feature_class":"P",
    "gn:feature_code":"PPL",
    "gn:name":"Parjapuquio",
    "gn:population":0,
    "gn:timezone":"America/Lima",
    "iso:country":"PE",
    "wof:name":"Parjapuquio",
    "wof:placetype":"locality"
},
  "geometry": {"coordinates":[-72.85972,-15.26556],"type":"Point"}
}