{
  "type": "Feature",
  "properties": {
    "gn:admin1_code":"23.0",
    "gn:admin2_code":"2303.0",
    "gn:admin3_code":"230301.0",
    "gn:asciiname":"Valdivia",
    "gn:country_code":"PE",
    "gn:dem":555,
    "gn:feature_class":"P",
    "gn:feature_code":"PPL",
    "gn:name":"Valdivia",
    "gn:population":0,
    "gn:timezone":"America/Lima",
    "iso:country":"PE",
    "wof:name":"Valdivia",
    "wof:placetype":"locality"
},
  "geometry": {"coordinates":[-70.77417,-17.61861],"type":"Point"}
}