{
  "type": "Feature",
  "properties": {
    "gn:admin1_code":"15",
    "gn:admin2_code":"1507.0",
    "gn:admin3_code":"150715.0",
    "gn:asciiname":"Malcanchi",
    "gn:country_code":"PE",
    "gn:dem":3357,
    "gn:feature_class":"P",
    "gn:feature_code":"PPL",
    "gn:name":"Malcanchi",
    "gn:population":0,
    "gn:timezone":"America/Lima",
    "iso:country":"PE",
    "wof:name":"Malcanchi",
    "wof:placetype":"locality"
},
  "geometry": {"coordinates":[-76.48361,-11.95889],"type":"Point"}
}