{
  "type": "Feature",
  "properties": {
    "gn:admin1_code":"11",
    "gn:admin2_code":"1101.0",
    "gn:asciiname":"Orcaya",
    "gn:country_code":"PE",
    "gn:dem":2139,
    "gn:feature_class":"P",
    "gn:feature_code":"PPL",
    "gn:name":"Orcaya",
    "gn:population":0,
    "gn:timezone":"America/Lima",
    "iso:country":"PE",
    "wof:name":"Orcaya",
    "wof:placetype":"locality"
},
  "geometry": {"coordinates":[-75.31555999999998,-13.97861],"type":"Point"}
}