{
  "type": "Feature",
  "properties": {
    "gn:admin1_code":"05",
    "gn:admin2_code":"506.0",
    "gn:admin3_code":"50619.0",
    "gn:asciiname":"Jarahuanca",
    "gn:country_code":"PE",
    "gn:dem":3396,
    "gn:feature_class":"P",
    "gn:feature_code":"PPL",
    "gn:name":"Jarahuanca",
    "gn:population":0,
    "gn:timezone":"America/Lima",
    "iso:country":"PE",
    "name:spa_x_preferred":[
        "Jarahuanca"
    ],
    "wof:name":"Jarahuanca",
    "wof:placetype":"locality"
},
  "geometry": {"coordinates":[-73.96968000000003,-15.04398],"type":"Point"}
}