{
  "type": "Feature",
  "properties": {
    "iso:country":"PE",
    "name:aym_x_preferred":[
        "Miraflores jiska taqa suyu"
    ],
    "name:eng_x_preferred":[
        "Miraflores District"
    ],
    "name:fra_x_preferred":[
        "District de Miraflores"
    ],
    "name:ita_x_preferred":[
        "Distretto di Miraflores"
    ],
    "name:que_x_preferred":[
        "Miraflores distritu"
    ],
    "name:spa_x_preferred":[
        "Distrito de Miraflores"
    ],
    "name:zho_x_preferred":[
        "\u7c73\u62c9\u5f17\u6d1b\u96f7\u65af\u5340"
    ],
    "qs:gn_country":"PE",
    "qs:gn_fcode":"PPL",
    "qs:gn_pop":0,
    "qs:name":"Miraflores",
    "qs:name_adm0":"Per\u00fa",
    "qs:name_adm1":"Lima Metropolitan Area",
    "qs:photos":4837,
    "qs:photos_1k":980,
    "qs:photos_9k":21,
    "qs:photos_9r":13,
    "qs:photos_all":4837,
    "qs:photos_sr":23,
    "qs:placetype":"Town",
    "qs:pop_sr":"0",
    "qs:woe_adm0":23424919,
    "wof:name":"Miraflores",
    "wof:placetype":"locality"
},
  "geometry": {"coordinates":[-77.03939,-12.11427],"type":"Point"}
}