{
  "type": "Feature",
  "properties": {
    "iso:country":"PE",
    "name:ara_x_preferred":[
        "\u0645\u0642\u0627\u0637\u0639\u0629 \u0645\u064a\u0631\u0627\u0641\u0644\u0648\u0631\u064a\u0633"
    ],
    "name:aym_x_preferred":[
        "Miraflores jiska taqa suyu"
    ],
    "name:cat_x_preferred":[
        "Miraflores"
    ],
    "name:deu_x_preferred":[
        "Miraflores"
    ],
    "name:eng_x_preferred":[
        "Miraflores District"
    ],
    "name:eng_x_variant":[
        "Miraflores"
    ],
    "name:fra_x_preferred":[
        "District de Miraflores"
    ],
    "name:fra_x_variant":[
        "Miraflores"
    ],
    "name:hun_x_preferred":[
        "Miraflores"
    ],
    "name:ita_x_preferred":[
        "Distretto di Miraflores"
    ],
    "name:ita_x_variant":[
        "Miraflores"
    ],
    "name:mkd_x_preferred":[
        "\u041c\u0438\u0440\u0430\u0444\u043b\u043e\u0440\u0435\u0441"
    ],
    "name:nld_x_preferred":[
        "Miraflores"
    ],
    "name:nno_x_preferred":[
        "Miraflores"
    ],
    "name:nob_x_preferred":[
        "Miraflores"
    ],
    "name:por_x_preferred":[
        "Miraflores"
    ],
    "name:que_x_preferred":[
        "Miraflores distritu"
    ],
    "name:spa_x_preferred":[
        "Distrito de Miraflores"
    ],
    "name:spa_x_variant":[
        "Miraflores"
    ],
    "name:swe_x_preferred":[
        "Miraflores"
    ],
    "name:ukr_x_preferred":[
        "Miraflores"
    ],
    "name:zho_x_preferred":[
        "\u7c73\u62c9\u5f17\u6d1b\u96f7\u65af\u5340"
    ],
    "qs:gn_country":"PE",
    "qs:gn_fcode":"PPL",
    "qs:gn_pop":0,
    "qs:name":"Miraflores",
    "qs:name_adm0":"Per\u00fa",
    "qs:name_adm1":"Lima Metropolitan Area",
    "qs:photos":4837,
    "qs:photos_1k":980,
    "qs:photos_9k":21,
    "qs:photos_9r":13,
    "qs:photos_all":4837,
    "qs:photos_sr":23,
    "qs:placetype":"Town",
    "qs:pop_sr":"0",
    "qs:woe_adm0":23424919,
    "wof:name":"Miraflores",
    "wof:placetype":"locality"
},
  "geometry": {"coordinates":[-77.03939,-12.11427],"type":"Point"}
}