{
  "type": "Feature",
  "properties": {
    "gn:admin1_code":"12.0",
    "gn:admin2_code":"1203.0",
    "gn:admin3_code":"120305.0",
    "gn:asciiname":"Casca",
    "gn:country_code":"PE",
    "gn:dem":3527,
    "gn:feature_class":"P",
    "gn:feature_code":"PPL",
    "gn:name":"Casca",
    "gn:population":0,
    "gn:timezone":"America/Lima",
    "iso:country":"PE",
    "name:arg_x_preferred":[
        "Casca"
    ],
    "name:bpy_x_preferred":[
        "\u0995\u09be\u09b8\u0995\u09be"
    ],
    "name:bul_x_preferred":[
        "\u041a\u0430\u0441\u043a\u0430"
    ],
    "name:ceb_x_preferred":[
        "Casca"
    ],
    "name:deu_x_preferred":[
        "Casca"
    ],
    "name:fra_x_preferred":[
        "Casca"
    ],
    "name:nld_x_preferred":[
        "Casca"
    ],
    "name:por_x_preferred":[
        "Casca"
    ],
    "name:ron_x_preferred":[
        "Casca"
    ],
    "name:rus_x_preferred":[
        "\u041a\u0430\u0441\u043a\u0430"
    ],
    "name:swe_x_preferred":[
        "Casca"
    ],
    "name:ukr_x_preferred":[
        "\u041a\u0430\u0441\u043a\u0430"
    ],
    "wof:name":"Casca",
    "wof:placetype":"locality"
},
  "geometry": {"coordinates":[-75.60221,-11.13834],"type":"Point"}
}