{
  "type": "Feature",
  "properties": {
    "gn:admin1_code":"5.0",
    "gn:admin2_code":"501.0",
    "gn:admin3_code":"50108.0",
    "gn:asciiname":"Tutapa",
    "gn:country_code":"PE",
    "gn:dem":3010,
    "gn:feature_class":"P",
    "gn:feature_code":"PPL",
    "gn:name":"Tutapa",
    "gn:population":0,
    "gn:timezone":"America/Lima",
    "iso:country":"PE",
    "name:und_x_variant":[
        "Hacienda Tutapa"
    ],
    "wof:name":"Tutapa",
    "wof:placetype":"locality"
},
  "geometry": {"coordinates":[-74.13085,-13.07575],"type":"Point"}
}