{
  "type": "Feature",
  "properties": {
    "gn:admin1_code":"2.0",
    "gn:admin2_code":"205.0",
    "gn:admin3_code":"20515.0",
    "gn:asciiname":"Salca Pata",
    "gn:country_code":"PE",
    "gn:dem":3056,
    "gn:feature_class":"P",
    "gn:feature_code":"PPL",
    "gn:name":"Salca Pata",
    "gn:population":0,
    "gn:timezone":"America/Lima",
    "iso:country":"PE",
    "wof:name":"Salca Pata",
    "wof:placetype":"locality"
},
  "geometry": {"coordinates":[-77.16767,-10.27139],"type":"Point"}
}