{
  "type": "Feature",
  "properties": {
    "gn:admin1_code":"04",
    "gn:admin2_code":"405.0",
    "gn:admin3_code":"40518.0",
    "gn:asciiname":"Ran Ran",
    "gn:country_code":"PE",
    "gn:dem":4514,
    "gn:feature_class":"P",
    "gn:feature_code":"PPL",
    "gn:name":"Ran Ran",
    "gn:population":0,
    "gn:timezone":"America/Lima",
    "iso:country":"PE",
    "wof:name":"Ran Ran",
    "wof:placetype":"locality"
},
  "geometry": {"coordinates":[-71.58667,-15.45941],"type":"Point"}
}