{
  "type": "Feature",
  "properties": {
    "gn:admin1_code":"3",
    "gn:admin2_code":"302.0",
    "gn:admin3_code":"30217.0",
    "gn:asciiname":"Yanamachay",
    "gn:country_code":"PE",
    "gn:dem":4035,
    "gn:feature_class":"P",
    "gn:feature_code":"PPL",
    "gn:name":"Yanamachay",
    "gn:population":0,
    "gn:timezone":"America/Lima",
    "iso:country":"PE",
    "wof:name":"Yanamachay",
    "wof:placetype":"locality"
},
  "geometry": {"coordinates":[-73.49666999999999,-13.96083],"type":"Point"}
}