{
  "type": "Feature",
  "properties": {
    "gn:admin1_code":"03",
    "gn:admin2_code":"306.0",
    "gn:admin3_code":"30608.0",
    "gn:asciiname":"Sinhuapaca",
    "gn:country_code":"PE",
    "gn:dem":3168,
    "gn:feature_class":"P",
    "gn:feature_code":"PPL",
    "gn:name":"Sinhuapaca",
    "gn:population":0,
    "gn:timezone":"America/Lima",
    "iso:country":"PE",
    "name:und_x_variant":[
        "Sinhuapata",
        "Sinhuapaca"
    ],
    "wof:name":"Sinhuapaca",
    "wof:placetype":"locality"
},
  "geometry": {"coordinates":[-73.57332,-13.52268],"type":"Point"}
}