{
  "type": "Feature",
  "properties": {
    "gn:admin1_code":"25",
    "gn:admin2_code":"2502.0",
    "gn:admin3_code":"250201.0",
    "gn:asciiname":"Soledad",
    "gn:country_code":"PE",
    "gn:dem":219,
    "gn:feature_class":"P",
    "gn:feature_code":"PPL",
    "gn:name":"Soledad",
    "gn:population":0,
    "gn:timezone":"America/Lima",
    "iso:country":"PE",
    "name:ara_x_preferred":[
        "\u0633\u0648\u0644\u064a\u062f\u0627\u062f"
    ],
    "name:ben_x_preferred":[
        "\u09b8\u09cb\u09b2\u09c7\u09a6\u09be\u09a6"
    ],
    "name:bre_x_preferred":[
        "Soledad"
    ],
    "name:cat_x_preferred":[
        "Soledad"
    ],
    "name:ceb_x_preferred":[
        "Soledad"
    ],
    "name:deu_x_preferred":[
        "Soledad"
    ],
    "name:fra_x_preferred":[
        "Soledad"
    ],
    "name:heb_x_preferred":[
        "\u05e1\u05d5\u05dc\u05d3\u05d0\u05d3"
    ],
    "name:hin_x_preferred":[
        "\u0938\u094b\u0932\u0921\u0948\u0921"
    ],
    "name:hun_x_preferred":[
        "Soledad"
    ],
    "name:ind_x_preferred":[
        "Soledad"
    ],
    "name:ita_x_preferred":[
        "Soledad"
    ],
    "name:kor_x_preferred":[
        "\uc194\ub808\ub2e4\ub4dc"
    ],
    "name:lit_x_preferred":[
        "Soledad"
    ],
    "name:nld_x_preferred":[
        "Soledad"
    ],
    "name:pol_x_preferred":[
        "Soledad"
    ],
    "name:por_x_preferred":[
        "Soledad"
    ],
    "name:spa_x_preferred":[
        "Soledad"
    ],
    "name:srp_x_preferred":[
        "\u0421\u043e\u043b\u0435\u0434\u0430\u0434"
    ],
    "name:swe_x_preferred":[
        "Soledad"
    ],
    "name:vie_x_preferred":[
        "Soledad"
    ],
    "name:vol_x_preferred":[
        "Soledad"
    ],
    "name:war_x_preferred":[
        "Soledad"
    ],
    "wof:name":"Soledad",
    "wof:placetype":"locality"
},
  "geometry": {"coordinates":[-73.76277,-10.66983],"type":"Point"}
}