{
  "type": "Feature",
  "properties": {
    "gn:admin1_code":"05",
    "gn:admin2_code":"505.0",
    "gn:admin3_code":"50504.0",
    "gn:asciiname":"Sojoshuilca",
    "gn:country_code":"PE",
    "gn:dem":3253,
    "gn:feature_class":"P",
    "gn:feature_code":"PPL",
    "gn:name":"Sojoshuilca",
    "gn:population":0,
    "gn:timezone":"America/Lima",
    "iso:country":"PE",
    "wof:name":"Sojoshuilca",
    "wof:placetype":"locality"
},
  "geometry": {"coordinates":[-73.93651,-13.12739],"type":"Point"}
}