{
  "type": "Feature",
  "properties": {
    "gn:admin1_code":"04",
    "gn:admin2_code":"405.0",
    "gn:admin3_code":"40504.0",
    "gn:asciiname":"Sullullumpa",
    "gn:country_code":"PE",
    "gn:dem":4813,
    "gn:feature_class":"P",
    "gn:feature_code":"PPL",
    "gn:name":"Sullullumpa",
    "gn:population":0,
    "gn:timezone":"America/Lima",
    "iso:country":"PE",
    "wof:name":"Sullullumpa",
    "wof:placetype":"locality"
},
  "geometry": {"coordinates":[-71.23555999999998,-15.27833],"type":"Point"}
}