{
  "type": "Feature",
  "properties": {
    "gn:admin1_code":"12",
    "gn:admin2_code":"1207.0",
    "gn:admin3_code":"120703.0",
    "gn:asciiname":"Huancal",
    "gn:country_code":"PE",
    "gn:dem":3702,
    "gn:feature_class":"P",
    "gn:feature_code":"PPL",
    "gn:name":"Huancal",
    "gn:population":0,
    "gn:timezone":"America/Lima",
    "iso:country":"PE",
    "wof:name":"Huancal",
    "wof:placetype":"locality"
},
  "geometry": {"coordinates":[-75.66324,-11.49537],"type":"Point"}
}