{
  "type": "Feature",
  "properties": {
    "gn:admin1_code":"3",
    "gn:admin2_code":"302.0",
    "gn:admin3_code":"30210.0",
    "gn:asciiname":"Ayapampa",
    "gn:country_code":"PE",
    "gn:dem":3406,
    "gn:feature_class":"P",
    "gn:feature_code":"PPL",
    "gn:name":"Ayapampa",
    "gn:population":0,
    "gn:timezone":"America/Lima",
    "iso:country":"PE",
    "wof:name":"Ayapampa",
    "wof:placetype":"locality"
},
  "geometry": {"coordinates":[-73.53528,-14.20889],"type":"Point"}
}