{
  "type": "Feature",
  "properties": {
    "gn:admin1_code":"16",
    "gn:admin2_code":"1601.0",
    "gn:admin3_code":"160114.0",
    "gn:asciiname":"Puerto Peru",
    "gn:country_code":"PE",
    "gn:dem":190,
    "gn:feature_class":"P",
    "gn:feature_code":"PPL",
    "gn:name":"Puerto Per\u00fa",
    "gn:population":0,
    "gn:timezone":"America/Lima",
    "iso:country":"PE",
    "wof:name":"Puerto Peru",
    "wof:placetype":"locality"
},
  "geometry": {"coordinates":[-75.28660000000001,-0.15298],"type":"Point"}
}