{
  "type": "Feature",
  "properties": {
    "gn:admin1_code":"15",
    "gn:admin2_code":"1509.0",
    "gn:admin3_code":"150906.0",
    "gn:asciiname":"Chinca",
    "gn:country_code":"PE",
    "gn:dem":4002,
    "gn:feature_class":"P",
    "gn:feature_code":"PPL",
    "gn:name":"Chinca",
    "gn:population":0,
    "gn:timezone":"America/Lima",
    "iso:country":"PE",
    "wof:name":"Chinca",
    "wof:placetype":"locality"
},
  "geometry": {"coordinates":[-76.76454,-10.82517],"type":"Point"}
}