{
  "type": "Feature",
  "properties": {
    "gn:admin1_code":"2.0",
    "gn:admin2_code":"218.0",
    "gn:admin3_code":"21809.0",
    "gn:asciiname":"Buenos Aires",
    "gn:country_code":"PE",
    "gn:dem":73,
    "gn:feature_class":"P",
    "gn:feature_code":"PPLA3",
    "gn:name":"Buenos Aires",
    "gn:population":0,
    "gn:timezone":"America/Lima",
    "iso:country":"PE",
    "wof:name":"Buenos Aires",
    "wof:placetype":"locality"
},
  "geometry": {"coordinates":[-78.4975,-9.12417],"type":"Point"}
}