{
  "type": "Feature",
  "properties": {
    "gn:admin1_code":"21.0",
    "gn:admin2_code":"2112.0",
    "gn:asciiname":"Puerto Chico",
    "gn:country_code":"PE",
    "gn:dem":1622,
    "gn:feature_class":"P",
    "gn:feature_code":"PPL",
    "gn:name":"Puerto Chico",
    "gn:population":0,
    "gn:timezone":"America/Lima",
    "iso:country":"PE",
    "name:spa_x_preferred":[
        "Puerto Chico"
    ],
    "wof:name":"Puerto Chico",
    "wof:placetype":"locality"
},
  "geometry": {"coordinates":[-69.39579000000001,-13.92803],"type":"Point"}
}