{
  "type": "Feature",
  "properties": {
    "gn:admin1_code":"23",
    "gn:admin2_code":"2302.0",
    "gn:admin3_code":"230201.0",
    "gn:asciiname":"Cupuni",
    "gn:country_code":"PE",
    "gn:dem":3793,
    "gn:feature_class":"P",
    "gn:feature_code":"PPL",
    "gn:name":"Cupuni",
    "gn:population":0,
    "gn:timezone":"America/Lima",
    "iso:country":"PE",
    "wof:name":"Cupuni",
    "wof:placetype":"locality"
},
  "geometry": {"coordinates":[-70.11558000000001,-17.31053],"type":"Point"}
}