{
  "type": "Feature",
  "properties": {
    "gn:admin1_code":"04",
    "gn:admin2_code":"405.0",
    "gn:admin3_code":"40501.0",
    "gn:asciiname":"Charapura",
    "gn:country_code":"PE",
    "gn:dem":4570,
    "gn:feature_class":"P",
    "gn:feature_code":"PPL",
    "gn:name":"Charapura",
    "gn:population":0,
    "gn:timezone":"America/Lima",
    "iso:country":"PE",
    "wof:name":"Charapura",
    "wof:placetype":"locality"
},
  "geometry": {"coordinates":[-71.53400999999999,-15.58551],"type":"Point"}
}