{
  "type": "Feature",
  "properties": {
    "gn:admin1_code":"22.0",
    "gn:admin2_code":"2207.0",
    "gn:admin3_code":"220705.0",
    "gn:asciiname":"Cacayco",
    "gn:country_code":"PE",
    "gn:dem":214,
    "gn:feature_class":"P",
    "gn:feature_code":"PPL",
    "gn:name":"Cacayco",
    "gn:population":0,
    "gn:timezone":"America/Lima",
    "iso:country":"PE",
    "name:spa_x_preferred":[
        "Cacayco"
    ],
    "wof:name":"Cacayco",
    "wof:placetype":"locality"
},
  "geometry": {"coordinates":[-76.34227,-6.86394],"type":"Point"}
}