{
  "type": "Feature",
  "properties": {
    "gn:admin1_code":"04",
    "gn:admin2_code":"401.0",
    "gn:admin3_code":"40114.0",
    "gn:asciiname":"Usuna",
    "gn:country_code":"PE",
    "gn:dem":3135,
    "gn:feature_class":"P",
    "gn:feature_code":"PPL",
    "gn:name":"Usu\u00f1a",
    "gn:population":0,
    "gn:timezone":"America/Lima",
    "iso:country":"PE",
    "name:und_x_variant":[
        "Uzu\u00f1a",
        "Usu\u00f1a"
    ],
    "wof:name":"Usuna",
    "wof:placetype":"locality"
},
  "geometry": {"coordinates":[-71.35849,-16.57476],"type":"Point"}
}