{
  "type": "Feature",
  "properties": {
    "gn:admin1_code":"14",
    "gn:admin2_code":"1403.0",
    "gn:admin3_code":"140308.0",
    "gn:asciiname":"Toma del Rio",
    "gn:country_code":"PE",
    "gn:dem":237,
    "gn:feature_class":"P",
    "gn:feature_code":"PPL",
    "gn:name":"Toma del R\u00edo",
    "gn:population":0,
    "gn:timezone":"America/Lima",
    "iso:country":"PE",
    "wof:name":"Toma del Rio",
    "wof:placetype":"locality"
},
  "geometry": {"coordinates":[-79.70083000000002,-5.97611],"type":"Point"}
}