{
  "type": "Feature",
  "properties": {
    "gn:admin1_code":"23",
    "gn:admin2_code":"2302.0",
    "gn:admin3_code":"230204.0",
    "gn:asciiname":"Angostura",
    "gn:country_code":"PE",
    "gn:dem":1841,
    "gn:feature_class":"P",
    "gn:feature_code":"PPL",
    "gn:name":"Angostura",
    "gn:population":0,
    "gn:timezone":"America/Lima",
    "iso:country":"PE",
    "wof:name":"Angostura",
    "wof:placetype":"locality"
},
  "geometry": {"coordinates":[-70.38450999999998,-17.40875],"type":"Point"}
}