{
  "type": "Feature",
  "properties": {
    "gn:admin1_code":"21",
    "gn:admin2_code":"2101.0",
    "gn:admin3_code":"210102.0",
    "gn:asciiname":"Imata",
    "gn:cc2":"PE",
    "gn:country_code":"PE",
    "gn:dem":3917,
    "gn:feature_class":"P",
    "gn:feature_code":"PPL",
    "gn:name":"Imata",
    "gn:population":0,
    "gn:timezone":"America/Lima",
    "iso:country":"PE",
    "name:und_x_variant":[
        "Ymata",
        "Imata Hacienda",
        "Imata"
    ],
    "wof:name":"Imata",
    "wof:placetype":"locality"
},
  "geometry": {"coordinates":[-69.90000000000001,-16.23333],"type":"Point"}
}