{
  "type": "Feature",
  "properties": {
    "gn:admin1_code":"15",
    "gn:admin2_code":"1507.0",
    "gn:admin3_code":"150721.0",
    "gn:asciiname":"Carhuapampa",
    "gn:country_code":"PE",
    "gn:dem":3904,
    "gn:feature_class":"P",
    "gn:feature_code":"PPL",
    "gn:name":"Carhuapampa",
    "gn:population":0,
    "gn:timezone":"America/Lima",
    "iso:country":"PE",
    "wof:name":"Carhuapampa",
    "wof:placetype":"locality"
},
  "geometry": {"coordinates":[-76.12000999999999,-12.03903],"type":"Point"}
}