{
  "type": "Feature",
  "properties": {
    "gn:admin1_code":"21",
    "gn:admin2_code":"2101.0",
    "gn:admin3_code":"210114.0",
    "gn:asciiname":"Picotane",
    "gn:cc2":"PE",
    "gn:country_code":"PE",
    "gn:dem":4068,
    "gn:feature_class":"P",
    "gn:feature_code":"PPL",
    "gn:name":"Picotane",
    "gn:population":0,
    "gn:timezone":"America/Lima",
    "iso:country":"PE",
    "name:und_x_variant":[
        "Picotane Hacienda",
        "Picotane"
    ],
    "wof:name":"Picotane",
    "wof:placetype":"locality"
},
  "geometry": {"coordinates":[-70.16667,-15.88333],"type":"Point"}
}