{
  "type": "Feature",
  "properties": {
    "gn:admin1_code":"05",
    "gn:admin2_code":"506.0",
    "gn:admin3_code":"50619.0",
    "gn:asciiname":"Ccerccuyoc",
    "gn:country_code":"PE",
    "gn:dem":2944,
    "gn:feature_class":"P",
    "gn:feature_code":"PPL",
    "gn:name":"Ccerccuyoc",
    "gn:population":0,
    "gn:timezone":"America/Lima",
    "iso:country":"PE",
    "wof:name":"Ccerccuyoc",
    "wof:placetype":"locality"
},
  "geometry": {"coordinates":[-74.10394000000002,-15.16219],"type":"Point"}
}