{
  "type": "Feature",
  "properties": {
    "gn:admin1_code":"3",
    "gn:admin2_code":"306.0",
    "gn:admin3_code":"30605.0",
    "gn:asciiname":"Huallhuay",
    "gn:country_code":"PE",
    "gn:dem":2888,
    "gn:feature_class":"P",
    "gn:feature_code":"PPL",
    "gn:name":"Huallhuay",
    "gn:population":0,
    "gn:timezone":"America/Lima",
    "iso:country":"PE",
    "wof:name":"Huallhuay",
    "wof:placetype":"locality"
},
  "geometry": {"coordinates":[-73.52249999999999,-13.48401],"type":"Point"}
}