{
  "type": "Feature",
  "properties": {
    "gn:admin1_code":"9.0",
    "gn:admin2_code":"905.0",
    "gn:admin3_code":"90502.0",
    "gn:asciiname":"Tomapata",
    "gn:country_code":"PE",
    "gn:dem":4108,
    "gn:feature_class":"P",
    "gn:feature_code":"PPL",
    "gn:name":"Tomapata",
    "gn:population":0,
    "gn:timezone":"America/Lima",
    "iso:country":"PE",
    "wof:name":"Tomapata",
    "wof:placetype":"locality"
},
  "geometry": {"coordinates":[-74.51384,-12.6639],"type":"Point"}
}