{
  "type": "Feature",
  "properties": {
    "gn:admin1_code":"21",
    "gn:admin2_code":"2104.0",
    "gn:admin3_code":"210405.0",
    "gn:asciiname":"Yupiura",
    "gn:country_code":"PE",
    "gn:dem":4310,
    "gn:feature_class":"P",
    "gn:feature_code":"PPL",
    "gn:name":"Yupiura",
    "gn:population":0,
    "gn:timezone":"America/Lima",
    "iso:country":"PE",
    "wof:name":"Yupiura",
    "wof:placetype":"locality"
},
  "geometry": {"coordinates":[-69.48554,-16.91871],"type":"Point"}
}