{
  "type": "Feature",
  "properties": {
    "gn:admin1_code":"3.0",
    "gn:admin2_code":"305.0",
    "gn:admin3_code":"30501.0",
    "gn:asciiname":"Ccuchuhuasi",
    "gn:country_code":"PE",
    "gn:dem":4368,
    "gn:feature_class":"P",
    "gn:feature_code":"PPL",
    "gn:name":"Ccuchuhuasi",
    "gn:population":0,
    "gn:timezone":"America/Lima",
    "iso:country":"PE",
    "wof:name":"Ccuchuhuasi",
    "wof:placetype":"locality"
},
  "geometry": {"coordinates":[-72.2375,-13.88917],"type":"Point"}
}