{
  "type": "Feature",
  "properties": {
    "gn:admin1_code":"25",
    "gn:admin2_code":"2501.0",
    "gn:admin3_code":"250104.0",
    "gn:asciiname":"Puerto Putaya",
    "gn:country_code":"PE",
    "gn:dem":211,
    "gn:feature_class":"P",
    "gn:feature_code":"PPL",
    "gn:name":"Puerto Putaya",
    "gn:population":0,
    "gn:timezone":"America/Lima",
    "iso:country":"PE",
    "wof:name":"Puerto Putaya",
    "wof:placetype":"locality"
},
  "geometry": {"coordinates":[-73.18293,-8.9785],"type":"Point"}
}