{
  "type": "Feature",
  "properties": {
    "gn:admin1_code":"04",
    "gn:admin2_code":"403.0",
    "gn:admin3_code":"40310.0",
    "gn:asciiname":"Pampa Nueva",
    "gn:country_code":"PE",
    "gn:dem":403,
    "gn:feature_class":"P",
    "gn:feature_code":"PPL",
    "gn:name":"Pampa Nueva",
    "gn:population":0,
    "gn:timezone":"America/Lima",
    "iso:country":"PE",
    "wof:name":"Pampa Nueva",
    "wof:placetype":"locality"
},
  "geometry": {"coordinates":[-74.38795,-15.39663],"type":"Point"}
}