{
  "type": "Feature",
  "properties": {
    "gn:admin1_code":"16",
    "gn:admin2_code":"1602.0",
    "gn:admin3_code":"160205.0",
    "gn:asciiname":"Jeberos",
    "gn:cc2":"PE",
    "gn:country_code":"PE",
    "gn:dem":148,
    "gn:feature_class":"P",
    "gn:feature_code":"PPLA3",
    "gn:name":"Jeberos",
    "gn:population":0,
    "gn:timezone":"America/Lima",
    "iso:country":"PE",
    "name:spa_x_preferred":[
        "Jeberos"
    ],
    "name:und_x_variant":[
        "Nuestra Se\u00f1ora de la Concepc\u00edon de Jeberos",
        "Jeveros"
    ],
    "wof:name":"Jeberos",
    "wof:placetype":"locality"
},
  "geometry": {"coordinates":[-76.28333000000001,-5.28333],"type":"Point"}
}