{
  "type": "Feature",
  "properties": {
    "gn:admin1_code":"8",
    "gn:admin2_code":"806.0",
    "gn:admin3_code":"80601.0",
    "gn:asciiname":"Palla",
    "gn:country_code":"PE",
    "gn:dem":4365,
    "gn:feature_class":"P",
    "gn:feature_code":"PPL",
    "gn:name":"Palla",
    "gn:population":0,
    "gn:timezone":"America/Lima",
    "iso:country":"PE",
    "name:deu_x_preferred":[
        "Palla eh!"
    ],
    "name:ita_x_preferred":[
        "Palla eh!"
    ],
    "wof:name":"Palla",
    "wof:placetype":"locality"
},
  "geometry": {"coordinates":[-71.02376,-14.22396],"type":"Point"}
}