{
  "type": "Feature",
  "properties": {
    "gn:admin1_code":"4",
    "gn:admin2_code":"405.0",
    "gn:admin3_code":"40511.0",
    "gn:asciiname":"Chajtillo",
    "gn:country_code":"PE",
    "gn:dem":3452,
    "gn:feature_class":"P",
    "gn:feature_code":"PPL",
    "gn:name":"Chajtillo",
    "gn:population":0,
    "gn:timezone":"America/Lima",
    "iso:country":"PE",
    "wof:name":"Chajtillo",
    "wof:placetype":"locality"
},
  "geometry": {"coordinates":[-71.98598,-15.97172],"type":"Point"}
}