{
  "type": "Feature",
  "properties": {
    "gn:admin1_code":"3",
    "gn:admin2_code":"302.0",
    "gn:admin3_code":"30214.0",
    "gn:asciiname":"Ruyac Corral",
    "gn:country_code":"PE",
    "gn:dem":3628,
    "gn:feature_class":"P",
    "gn:feature_code":"PPL",
    "gn:name":"Ruyac Corral",
    "gn:population":0,
    "gn:timezone":"America/Lima",
    "iso:country":"PE",
    "wof:name":"Ruyac Corral",
    "wof:placetype":"locality"
},
  "geometry": {"coordinates":[-73.56169,-13.96081],"type":"Point"}
}