{
  "type": "Feature",
  "properties": {
    "gn:admin1_code":"19",
    "gn:admin2_code":"1902.0",
    "gn:asciiname":"Tinya",
    "gn:country_code":"PE",
    "gn:dem":4320,
    "gn:feature_class":"P",
    "gn:feature_code":"PPL",
    "gn:name":"Tinya",
    "gn:population":0,
    "gn:timezone":"America/Lima",
    "iso:country":"PE",
    "name:bul_x_preferred":[
        "\u0422\u0438\u043d\u044f"
    ],
    "name:que_x_preferred":[
        "Tinya"
    ],
    "name:spa_x_preferred":[
        "Tinya"
    ],
    "wof:name":"Tinya",
    "wof:placetype":"locality"
},
  "geometry": {"coordinates":[-76.55551,-10.38278],"type":"Point"}
}