{
  "type": "Feature",
  "properties": {
    "gn:admin1_code":"2.0",
    "gn:admin2_code":"220.0",
    "gn:admin3_code":"22003.0",
    "gn:asciiname":"Huaishcana",
    "gn:country_code":"PE",
    "gn:dem":3266,
    "gn:feature_class":"P",
    "gn:feature_code":"PPL",
    "gn:name":"Huaishcana",
    "gn:population":0,
    "gn:timezone":"America/Lima",
    "iso:country":"PE",
    "wof:name":"Huaishcana",
    "wof:placetype":"locality"
},
  "geometry": {"coordinates":[-77.66,-9.20611],"type":"Point"}
}