{
  "type": "Feature",
  "properties": {
    "gn:admin1_code":"20",
    "gn:admin2_code":"2002.0",
    "gn:admin3_code":"200204.0",
    "gn:asciiname":"Chicu",
    "gn:country_code":"PE",
    "gn:dem":2416,
    "gn:feature_class":"P",
    "gn:feature_code":"PPL",
    "gn:name":"Chicu",
    "gn:population":0,
    "gn:timezone":"America/Lima",
    "iso:country":"PE",
    "name:und_x_variant":[
        "Chieu",
        "Chicu"
    ],
    "wof:name":"Chicu",
    "wof:placetype":"locality"
},
  "geometry": {"coordinates":[-79.89263000000003,-4.74034],"type":"Point"}
}