{
  "type": "Feature",
  "properties": {
    "gn:admin1_code":"20",
    "gn:admin2_code":"2006.0",
    "gn:admin3_code":"200604.0",
    "gn:asciiname":"Huaypira Baja",
    "gn:country_code":"PE",
    "gn:dem":127,
    "gn:feature_class":"P",
    "gn:feature_code":"PPL",
    "gn:name":"Huaypira Baja",
    "gn:population":0,
    "gn:timezone":"America/Lima",
    "iso:country":"PE",
    "name:und_x_variant":[
        "Huaipir\u00e1",
        "Hiaipira",
        "Huaypir\u00e1",
        "Hueypira",
        "Huaypira Baja"
    ],
    "wof:name":"Huaypira Baja",
    "wof:placetype":"locality"
},
  "geometry": {"coordinates":[-80.50655,-4.6321],"type":"Point"}
}