{
  "type": "Feature",
  "properties": {
    "gn:admin1_code":"21",
    "gn:admin2_code":"2102.0",
    "gn:admin3_code":"210210.0",
    "gn:asciiname":"Huancapata",
    "gn:country_code":"PE",
    "gn:dem":3830,
    "gn:feature_class":"P",
    "gn:feature_code":"PPL",
    "gn:name":"Huancapata",
    "gn:population":0,
    "gn:timezone":"America/Lima",
    "iso:country":"PE",
    "wof:name":"Huancapata",
    "wof:placetype":"locality"
},
  "geometry": {"coordinates":[-70.05291,-15.30312],"type":"Point"}
}