{
  "type": "Feature",
  "properties": {
    "gn:admin1_code":"11",
    "gn:admin2_code":"1103.0",
    "gn:admin3_code":"110302.0",
    "gn:asciiname":"El Puente",
    "gn:country_code":"PE",
    "gn:dem":218,
    "gn:feature_class":"P",
    "gn:feature_code":"PPL",
    "gn:name":"El Puente",
    "gn:population":0,
    "gn:timezone":"America/Lima",
    "iso:country":"PE",
    "name:ceb_x_preferred":[
        "El Puente"
    ],
    "name:deu_x_preferred":[
        "El Puente"
    ],
    "name:ita_x_preferred":[
        "El Puente"
    ],
    "name:nld_x_preferred":[
        "El Puente"
    ],
    "name:pol_x_preferred":[
        "El Puente"
    ],
    "name:spa_x_preferred":[
        "El Puente"
    ],
    "name:srp_x_preferred":[
        "\u0415\u043b \u041f\u0443\u0435\u043d\u0442\u0435"
    ],
    "name:swe_x_preferred":[
        "El Puente"
    ],
    "wof:name":"El Puente",
    "wof:placetype":"locality"
},
  "geometry": {"coordinates":[-75.23309999999999,-14.64939],"type":"Point"}
}