{
  "type": "Feature",
  "properties": {
    "gn:admin1_code":"9",
    "gn:admin2_code":"903.0",
    "gn:admin3_code":"90301.0",
    "gn:asciiname":"Acuay",
    "gn:country_code":"PE",
    "gn:dem":3749,
    "gn:feature_class":"P",
    "gn:feature_code":"PPL",
    "gn:name":"Acuay",
    "gn:population":0,
    "gn:timezone":"America/Lima",
    "iso:country":"PE",
    "wof:name":"Acuay",
    "wof:placetype":"locality"
},
  "geometry": {"coordinates":[-74.68975999999998,-13.0474],"type":"Point"}
}