{
  "type": "Feature",
  "properties": {
    "gn:admin1_code":"12",
    "gn:admin2_code":"1203.0",
    "gn:admin3_code":"120303.0",
    "gn:asciiname":"Yaroni",
    "gn:country_code":"PE",
    "gn:dem":1030,
    "gn:feature_class":"P",
    "gn:feature_code":"PPL",
    "gn:name":"Yaroni",
    "gn:population":0,
    "gn:timezone":"America/Lima",
    "iso:country":"PE",
    "wof:name":"Yaroni",
    "wof:placetype":"locality"
},
  "geometry": {"coordinates":[-74.84555999999998,-11.10528],"type":"Point"}
}