{
  "type": "Feature",
  "properties": {
    "gn:admin1_code":"10.0",
    "gn:admin2_code":"1005.0",
    "gn:admin3_code":"100509.0",
    "gn:asciiname":"Huamachacra",
    "gn:country_code":"PE",
    "gn:dem":3754,
    "gn:feature_class":"P",
    "gn:feature_code":"PPL",
    "gn:name":"Huamachacra",
    "gn:population":0,
    "gn:timezone":"America/Lima",
    "iso:country":"PE",
    "wof:name":"Huamachacra",
    "wof:placetype":"locality"
},
  "geometry": {"coordinates":[-76.87003,-9.48619],"type":"Point"}
}