{
  "type": "Feature",
  "properties": {
    "gn:admin1_code":"15.0",
    "gn:admin2_code":"1505.0",
    "gn:admin3_code":"150507.0",
    "gn:asciiname":"Villarreal",
    "gn:country_code":"PE",
    "gn:dem":94,
    "gn:feature_class":"P",
    "gn:feature_code":"PPL",
    "gn:name":"Villarreal",
    "gn:population":0,
    "gn:timezone":"America/Lima",
    "iso:country":"PE",
    "wof:name":"Villarreal",
    "wof:placetype":"locality"
},
  "geometry": {"coordinates":[-76.33879,-13.07076],"type":"Point"}
}