{
  "type": "Feature",
  "properties": {
    "gn:admin1_code":"10.0",
    "gn:admin2_code":"1008.0",
    "gn:admin3_code":"100804.0",
    "gn:asciiname":"Huchpajoto",
    "gn:country_code":"PE",
    "gn:dem":1840,
    "gn:feature_class":"P",
    "gn:feature_code":"PPLL",
    "gn:name":"Huchpajoto",
    "gn:population":0,
    "gn:timezone":"America/Lima",
    "iso:country":"PE",
    "wof:name":"Huchpajoto",
    "wof:placetype":"locality"
},
  "geometry": {"coordinates":[-76.07449,-9.82467],"type":"Point"}
}