{
  "type": "Feature",
  "properties": {
    "gn:admin1_code":"20",
    "gn:admin2_code":"2002.0",
    "gn:admin3_code":"200206.0",
    "gn:asciiname":"Chunque",
    "gn:country_code":"PE",
    "gn:dem":3160,
    "gn:feature_class":"P",
    "gn:feature_code":"PPL",
    "gn:name":"Chunque",
    "gn:population":0,
    "gn:timezone":"America/Lima",
    "iso:country":"PE",
    "wof:name":"Chunque",
    "wof:placetype":"locality"
},
  "geometry": {"coordinates":[-79.65875,-5.0527],"type":"Point"}
}