{
  "type": "Feature",
  "properties": {
    "gn:admin1_code":"4",
    "gn:admin2_code":"408.0",
    "gn:admin3_code":"40810.0",
    "gn:asciiname":"Achombi",
    "gn:country_code":"PE",
    "gn:dem":3778,
    "gn:feature_class":"P",
    "gn:feature_code":"PPL",
    "gn:name":"Achombi",
    "gn:population":0,
    "gn:timezone":"America/Lima",
    "iso:country":"PE",
    "wof:name":"Achombi",
    "wof:placetype":"locality"
},
  "geometry": {"coordinates":[-72.8175,-15.20306],"type":"Point"}
}