{
  "type": "Feature",
  "properties": {
    "gn:admin1_code":"11",
    "gn:admin2_code":"1105.0",
    "gn:admin3_code":"110501.0",
    "gn:asciiname":"Hacienda La Venturosa",
    "gn:country_code":"PE",
    "gn:dem":24,
    "gn:feature_class":"P",
    "gn:feature_code":"PPL",
    "gn:name":"Hacienda La Venturosa",
    "gn:population":0,
    "gn:timezone":"America/Lima",
    "iso:country":"PE",
    "name:spa_x_preferred":[
        "Hacienda La Venturosa"
    ],
    "name:und_x_variant":[
        "Venturosa Hacienda",
        "Venturosa"
    ],
    "wof:name":"Hacienda La Venturosa",
    "wof:placetype":"locality"
},
  "geometry": {"coordinates":[-76.19171,-13.68809],"type":"Point"}
}