{
  "type": "Feature",
  "properties": {
    "gn:admin1_code":"15",
    "gn:admin2_code":"1505.0",
    "gn:admin3_code":"150507.0",
    "gn:asciiname":"Chico",
    "gn:country_code":"PE",
    "gn:dem":78,
    "gn:feature_class":"P",
    "gn:feature_code":"PPL",
    "gn:name":"Chico",
    "gn:population":0,
    "gn:timezone":"America/Lima",
    "iso:country":"PE",
    "name:ara_x_preferred":[
        "\u0634\u064a\u0643\u0648"
    ],
    "name:ceb_x_preferred":[
        "Chico"
    ],
    "name:ces_x_preferred":[
        "Chico"
    ],
    "name:deu_x_preferred":[
        "Chico"
    ],
    "name:fra_x_preferred":[
        "Chico"
    ],
    "name:hrv_x_preferred":[
        "Chico"
    ],
    "name:hun_x_preferred":[
        "Chico"
    ],
    "name:ind_x_preferred":[
        "Chico"
    ],
    "name:ita_x_preferred":[
        "Chico"
    ],
    "name:pol_x_preferred":[
        "Chico"
    ],
    "name:por_x_preferred":[
        "Chico"
    ],
    "name:spa_x_preferred":[
        "Chico"
    ],
    "name:swe_x_preferred":[
        "Chico"
    ],
    "name:tgl_x_preferred":[
        "Chico"
    ],
    "name:ukr_x_preferred":[
        "\u0427\u0438\u043a\u043e"
    ],
    "name:vol_x_preferred":[
        "Chico"
    ],
    "name:war_x_preferred":[
        "Chico"
    ],
    "wof:name":"Chico",
    "wof:placetype":"locality"
},
  "geometry": {"coordinates":[-76.40496999999998,-13.01289],"type":"Point"}
}