{
  "type": "Feature",
  "properties": {
    "gn:admin1_code":"3",
    "gn:admin2_code":"306.0",
    "gn:admin3_code":"30606.0",
    "gn:asciiname":"Illapacancha",
    "gn:country_code":"PE",
    "gn:dem":2963,
    "gn:feature_class":"P",
    "gn:feature_code":"PPL",
    "gn:name":"Illapacancha",
    "gn:population":0,
    "gn:timezone":"America/Lima",
    "iso:country":"PE",
    "wof:name":"Illapacancha",
    "wof:placetype":"locality"
},
  "geometry": {"coordinates":[-73.67331,-13.41173],"type":"Point"}
}