{
  "type": "Feature",
  "properties": {
    "gn:admin1_code":"4",
    "gn:admin2_code":"405.0",
    "gn:admin3_code":"40517.0",
    "gn:asciiname":"Ampato",
    "gn:country_code":"PE",
    "gn:dem":4315,
    "gn:feature_class":"P",
    "gn:feature_code":"PPL",
    "gn:name":"Ampato",
    "gn:population":0,
    "gn:timezone":"America/Lima",
    "iso:country":"PE",
    "name:bos_x_preferred":[
        "Ampato"
    ],
    "name:cat_x_preferred":[
        "Ampato"
    ],
    "name:ceb_x_preferred":[
        "Nevado Ampato"
    ],
    "name:deu_x_preferred":[
        "Ampato"
    ],
    "name:est_x_preferred":[
        "Ampato"
    ],
    "name:fra_x_preferred":[
        "Ampato"
    ],
    "name:hye_x_preferred":[
        "\u0531\u0574\u057a\u0561\u057f\u0578"
    ],
    "name:ita_x_preferred":[
        "Ampato"
    ],
    "name:lit_x_preferred":[
        "Ampatas"
    ],
    "name:mkd_x_preferred":[
        "\u0410\u043c\u043f\u0430\u0442\u043e"
    ],
    "name:nld_x_preferred":[
        "Ampato"
    ],
    "name:pol_x_preferred":[
        "Ampato"
    ],
    "name:por_x_preferred":[
        "Ampato"
    ],
    "name:que_x_preferred":[
        "Hamp'atu urqu"
    ],
    "name:rus_x_preferred":[
        "\u0410\u043c\u043f\u0430\u0442\u043e"
    ],
    "name:spa_x_preferred":[
        "Ampato"
    ],
    "name:ukr_x_preferred":[
        "\u0410\u043c\u043f\u0430\u0442\u043e"
    ],
    "name:zho_x_preferred":[
        "\u5b89\u5e15\u6258\u5cf0"
    ],
    "wof:name":"Ampato",
    "wof:placetype":"locality"
},
  "geometry": {"coordinates":[-71.40514,-15.18318],"type":"Point"}
}