{
  "type": "Feature",
  "properties": {
    "gn:admin1_code":"02",
    "gn:admin2_code":"214.0",
    "gn:admin3_code":"21409.0",
    "gn:asciiname":"Copavilca",
    "gn:country_code":"PE",
    "gn:dem":1414,
    "gn:feature_class":"P",
    "gn:feature_code":"PPL",
    "gn:name":"Copavilca",
    "gn:population":0,
    "gn:timezone":"America/Lima",
    "iso:country":"PE",
    "wof:name":"Copavilca",
    "wof:placetype":"locality"
},
  "geometry": {"coordinates":[-77.53333000000001,-10.43333],"type":"Point"}
}