{
  "type": "Feature",
  "properties": {
    "gn:admin1_code":"2.0",
    "gn:admin2_code":"220.0",
    "gn:admin3_code":"22001.0",
    "gn:asciiname":"Cayepampa",
    "gn:country_code":"PE",
    "gn:dem":3390,
    "gn:feature_class":"P",
    "gn:feature_code":"PPLL",
    "gn:name":"Cayepampa",
    "gn:population":0,
    "gn:timezone":"America/Lima",
    "iso:country":"PE",
    "wof:name":"Cayepampa",
    "wof:placetype":"locality"
},
  "geometry": {"coordinates":[-77.69750000000001,-9.10083],"type":"Point"}
}