{
  "type": "Feature",
  "properties": {
    "gn:admin1_code":"14",
    "gn:admin2_code":"1403.0",
    "gn:admin3_code":"140306.0",
    "gn:asciiname":"Annape",
    "gn:country_code":"PE",
    "gn:dem":24,
    "gn:feature_class":"P",
    "gn:feature_code":"PPL",
    "gn:name":"Annape",
    "gn:population":0,
    "gn:timezone":"America/Lima",
    "iso:country":"PE",
    "wof:name":"Annape",
    "wof:placetype":"locality"
},
  "geometry": {"coordinates":[-80.00398,-6.51674],"type":"Point"}
}