{
  "type": "Feature",
  "properties": {
    "iso:country":"PE",
    "name:spa_x_preferred":[
        "Tranca de Reque"
    ],
    "name:spa_x_variant":[
        "La Tranca"
    ],
    "name:unk_x_variant":[
        "La Tranca de Reque"
    ],
    "qs:gn_country":"PE",
    "qs:gn_fcode":"PPL",
    "qs:gn_pop":0,
    "qs:name":"Tranca de Reque",
    "qs:name_adm0":"Per\u00fa",
    "qs:name_adm1":"Lambayeque",
    "qs:photos":389,
    "qs:photos_1k":79,
    "qs:photos_9k":2,
    "qs:photos_9r":5,
    "qs:photos_all":389,
    "qs:photos_sr":6,
    "qs:placetype":"Town",
    "qs:pop_sr":"0",
    "qs:woe_adm0":23424919,
    "wof:name":"Tranca de Reque",
    "wof:placetype":"locality"
},
  "geometry": {"coordinates":[-79.78333000000001,-6.83333],"type":"Point"}
}