{
  "type": "Feature",
  "properties": {
    "gn:admin1_code":"04",
    "gn:admin2_code":"404.0",
    "gn:admin3_code":"40404.0",
    "gn:asciiname":"Puclluta",
    "gn:country_code":"PE",
    "gn:dem":4712,
    "gn:feature_class":"P",
    "gn:feature_code":"PPL",
    "gn:name":"Puclluta",
    "gn:population":0,
    "gn:timezone":"America/Lima",
    "iso:country":"PE",
    "name:spa_x_preferred":[
        "Puclluta"
    ],
    "wof:name":"Puclluta",
    "wof:placetype":"locality"
},
  "geometry": {"coordinates":[-72.00863000000003,-15.10732],"type":"Point"}
}