{
  "type": "Feature",
  "properties": {
    "gn:admin1_code":"8",
    "gn:admin2_code":"806.0",
    "gn:admin3_code":"80603.0",
    "gn:asciiname":"Coracora",
    "gn:country_code":"PE",
    "gn:dem":3532,
    "gn:feature_class":"P",
    "gn:feature_code":"PPL",
    "gn:name":"Coracora",
    "gn:population":0,
    "gn:timezone":"America/Lima",
    "iso:country":"PE",
    "wof:name":"Coracora",
    "wof:placetype":"locality"
},
  "geometry": {"coordinates":[-71.4025,-14.09694],"type":"Point"}
}