{
  "type": "Feature",
  "properties": {
    "gn:admin1_code":"8",
    "gn:admin2_code":"806.0",
    "gn:admin3_code":"80603.0",
    "gn:asciiname":"Coracora",
    "gn:country_code":"PE",
    "gn:dem":3532,
    "gn:feature_class":"P",
    "gn:feature_code":"PPL",
    "gn:name":"Coracora",
    "gn:population":0,
    "gn:timezone":"America/Lima",
    "iso:country":"PE",
    "name:ara_x_preferred":[
        "\u0643\u0648\u0631\u0627\u0643\u0648\u0631\u0627"
    ],
    "name:aym_x_preferred":[
        "Qura Qura"
    ],
    "name:ceb_x_preferred":[
        "Coracora"
    ],
    "name:ita_x_preferred":[
        "Coracora"
    ],
    "name:lit_x_preferred":[
        "Korakora"
    ],
    "name:pol_x_preferred":[
        "Coracora"
    ],
    "name:que_x_preferred":[
        "Qura Qura"
    ],
    "name:spa_x_preferred":[
        "Coracora"
    ],
    "name:war_x_preferred":[
        "Coracora"
    ],
    "name:zho_x_preferred":[
        "\u79d1\u62c9\u79d1\u62c9"
    ],
    "wof:name":"Coracora",
    "wof:placetype":"locality"
},
  "geometry": {"coordinates":[-71.4025,-14.09694],"type":"Point"}
}