{
  "type": "Feature",
  "properties": {
    "gn:admin1_code":"20",
    "gn:admin2_code":"2003.0",
    "gn:admin3_code":"200304.0",
    "gn:asciiname":"Pampa Grande",
    "gn:country_code":"PE",
    "gn:dem":2487,
    "gn:feature_class":"P",
    "gn:feature_code":"PPL",
    "gn:name":"Pampa Grande",
    "gn:population":0,
    "gn:timezone":"America/Lima",
    "iso:country":"PE",
    "name:spa_x_preferred":[
        "Pampa Grande"
    ],
    "wof:name":"Pampa Grande",
    "wof:placetype":"locality"
},
  "geometry": {"coordinates":[-79.45659000000001,-5.58447],"type":"Point"}
}