{
  "type": "Feature",
  "properties": {
    "gn:admin1_code":"6.0",
    "gn:admin2_code":"608.0",
    "gn:admin3_code":"60801.0",
    "gn:asciiname":"Vista Alegre Bajo",
    "gn:country_code":"PE",
    "gn:dem":1475,
    "gn:feature_class":"P",
    "gn:feature_code":"PPL",
    "gn:name":"Vista Alegre Bajo",
    "gn:population":0,
    "gn:timezone":"America/Lima",
    "iso:country":"PE",
    "wof:name":"Vista Alegre Bajo",
    "wof:placetype":"locality"
},
  "geometry": {"coordinates":[-78.84111,-5.68361],"type":"Point"}
}