{
  "type": "Feature",
  "properties": {
    "gn:admin1_code":"12.0",
    "gn:admin2_code":"1204.0",
    "gn:admin3_code":"120423.0",
    "gn:asciiname":"Quihuala",
    "gn:country_code":"PE",
    "gn:dem":3899,
    "gn:feature_class":"P",
    "gn:feature_code":"PPL",
    "gn:name":"Quihuala",
    "gn:population":0,
    "gn:timezone":"America/Lima",
    "iso:country":"PE",
    "wof:name":"Quihuala",
    "wof:placetype":"locality"
},
  "geometry": {"coordinates":[-75.48076,-11.88358],"type":"Point"}
}