{
  "type": "Feature",
  "properties": {
    "gn:admin1_code":"8",
    "gn:admin2_code":"807.0",
    "gn:admin3_code":"80708.0",
    "gn:asciiname":"Chuspini",
    "gn:country_code":"PE",
    "gn:dem":4080,
    "gn:feature_class":"P",
    "gn:feature_code":"PPL",
    "gn:name":"Chuspini",
    "gn:population":0,
    "gn:timezone":"America/Lima",
    "iso:country":"PE",
    "wof:name":"Chuspini",
    "wof:placetype":"locality"
},
  "geometry": {"coordinates":[-71.93089000000001,-14.55278],"type":"Point"}
}