{
  "type": "Feature",
  "properties": {
    "gn:admin1_code":"04",
    "gn:admin2_code":"401.0",
    "gn:admin3_code":"40113.0",
    "gn:asciiname":"Rio Negro",
    "gn:country_code":"PE",
    "gn:dem":3252,
    "gn:feature_class":"P",
    "gn:feature_code":"PPL",
    "gn:name":"R\u00edo Negro",
    "gn:population":0,
    "gn:timezone":"America/Lima",
    "iso:country":"PE",
    "wof:name":"Rio Negro",
    "wof:placetype":"locality"
},
  "geometry": {"coordinates":[-71.34248000000002,-16.53451],"type":"Point"}
}