{
  "type": "Feature",
  "properties": {
    "gn:admin1_code":"22",
    "gn:admin2_code":"2210.0",
    "gn:asciiname":"Huilacochan",
    "gn:country_code":"PE",
    "gn:dem":3603,
    "gn:feature_class":"P",
    "gn:feature_code":"PPL",
    "gn:name":"Huilacoch\u00e1n",
    "gn:population":0,
    "gn:timezone":"America/Lima",
    "iso:country":"PE",
    "wof:name":"Huilacochan",
    "wof:placetype":"locality"
},
  "geometry": {"coordinates":[-77.0038,-8.42803],"type":"Point"}
}