{
  "type": "Feature",
  "properties": {
    "gn:admin1_code":"03",
    "gn:admin2_code":"302.0",
    "gn:admin3_code":"30210.0",
    "gn:asciiname":"Pampachiri",
    "gn:country_code":"PE",
    "gn:dem":3384,
    "gn:feature_class":"P",
    "gn:feature_code":"PPLA3",
    "gn:name":"Pampachiri",
    "gn:population":0,
    "gn:timezone":"America/Lima",
    "iso:country":"PE",
    "name:kat_x_preferred":[
        "\u10de\u10d0\u10db\u10de\u10d0\u10e9\u10d8\u10e0\u10d8\u10e1 \u10e0\u10d0\u10d8\u10dd\u10dc\u10d8"
    ],
    "name:nor_x_preferred":[
        "Pampachiri"
    ],
    "name:por_x_preferred":[
        "Pampachiri"
    ],
    "name:que_x_preferred":[
        "Pampachiri distritu"
    ],
    "name:zho_x_preferred":[
        "\u6f58\u5e15\u5947\u91cc\u5340"
    ],
    "wof:name":"Pampachiri",
    "wof:placetype":"locality"
},
  "geometry": {"coordinates":[-73.54389,-14.18694],"type":"Point"}
}