{
  "type": "Feature",
  "properties": {
    "gn:admin1_code":"10.0",
    "gn:admin2_code":"1010.0",
    "gn:admin3_code":"101007.0",
    "gn:asciiname":"Luta",
    "gn:country_code":"PE",
    "gn:dem":4068,
    "gn:feature_class":"P",
    "gn:feature_code":"PPL",
    "gn:name":"Luta",
    "gn:population":0,
    "gn:timezone":"America/Lima",
    "iso:country":"PE",
    "name:ceb_x_preferred":[
        "Luta"
    ],
    "name:deu_x_preferred":[
        "Luta"
    ],
    "name:fra_x_preferred":[
        "Luta"
    ],
    "name:pol_x_preferred":[
        "Luta"
    ],
    "name:swe_x_preferred":[
        "Luta"
    ],
    "wof:name":"Luta",
    "wof:placetype":"locality"
},
  "geometry": {"coordinates":[-76.76306,-10.36667],"type":"Point"}
}