{
  "type": "Feature",
  "properties": {
    "gn:admin1_code":"24",
    "gn:admin2_code":"2401.0",
    "gn:admin3_code":"240101.0",
    "gn:asciiname":"Puerto Pizarro",
    "gn:country_code":"PE",
    "gn:dem":4,
    "gn:feature_class":"P",
    "gn:feature_code":"PPL",
    "gn:name":"Puerto Pizarro",
    "gn:population":0,
    "gn:timezone":"America/Lima",
    "iso:country":"PE",
    "name:ast_x_preferred":[
        "Puertu Pizarro"
    ],
    "name:spa_x_preferred":[
        "Puerto Pizarro"
    ],
    "wof:name":"Puerto Pizarro",
    "wof:placetype":"locality"
},
  "geometry": {"coordinates":[-80.38998000000002,-3.50136],"type":"Point"}
}