{
  "type": "Feature",
  "properties": {
    "gn:admin1_code":"9.0",
    "gn:admin2_code":"907.0",
    "gn:admin3_code":"90706.0",
    "gn:asciiname":"Mombrilluyo",
    "gn:country_code":"PE",
    "gn:dem":2560,
    "gn:feature_class":"P",
    "gn:feature_code":"PPL",
    "gn:name":"Mombrilluyo",
    "gn:population":0,
    "gn:timezone":"America/Lima",
    "iso:country":"PE",
    "wof:name":"Mombrilluyo",
    "wof:placetype":"locality"
},
  "geometry": {"coordinates":[-74.79039,-12.29967],"type":"Point"}
}