{
  "type": "Feature",
  "properties": {
    "gn:admin1_code":"13.0",
    "gn:admin2_code":"1308.0",
    "gn:asciiname":"Yurpir Marca",
    "gn:country_code":"PE",
    "gn:dem":3606,
    "gn:feature_class":"P",
    "gn:feature_code":"PPL",
    "gn:name":"Yurpir Marca",
    "gn:population":0,
    "gn:timezone":"America/Lima",
    "iso:country":"PE",
    "wof:name":"Yurpir Marca",
    "wof:placetype":"locality"
},
  "geometry": {"coordinates":[-77.35221999999997,-8.46139],"type":"Point"}
}