{
  "type": "Feature",
  "properties": {
    "gn:admin1_code":"05",
    "gn:admin2_code":"501.0",
    "gn:admin3_code":"50103.0",
    "gn:asciiname":"Collpa",
    "gn:country_code":"PE",
    "gn:dem":2951,
    "gn:feature_class":"P",
    "gn:feature_code":"PPL",
    "gn:name":"Collpa",
    "gn:population":0,
    "gn:timezone":"America/Lima",
    "iso:country":"PE",
    "name:und_x_variant":[
        "Hacienda Collpa"
    ],
    "wof:name":"Collpa",
    "wof:placetype":"locality"
},
  "geometry": {"coordinates":[-74.11153,-13.08449],"type":"Point"}
}