{
  "type": "Feature",
  "properties": {
    "gn:admin1_code":"08",
    "gn:admin2_code":"808.0",
    "gn:admin3_code":"80804.0",
    "gn:asciiname":"Ullachica",
    "gn:country_code":"PE",
    "gn:dem":4189,
    "gn:feature_class":"P",
    "gn:feature_code":"PPL",
    "gn:name":"Ullachica",
    "gn:population":0,
    "gn:timezone":"America/Lima",
    "iso:country":"PE",
    "wof:name":"Ullachica",
    "wof:placetype":"locality"
},
  "geometry": {"coordinates":[-71.20969000000002,-15.02303],"type":"Point"}
}