{
  "type": "Feature",
  "properties": {
    "gn:admin1_code":"21",
    "gn:admin2_code":"2105.0",
    "gn:admin3_code":"210505.0",
    "gn:asciiname":"Lacapampa",
    "gn:country_code":"PE",
    "gn:dem":3989,
    "gn:feature_class":"P",
    "gn:feature_code":"PPL",
    "gn:name":"Lacapampa",
    "gn:population":0,
    "gn:timezone":"America/Lima",
    "iso:country":"PE",
    "wof:name":"Lacapampa",
    "wof:placetype":"locality"
},
  "geometry": {"coordinates":[-69.65066,-16.67471],"type":"Point"}
}