{
  "type": "Feature",
  "properties": {
    "gn:admin1_code":"24",
    "gn:admin2_code":"2402.0",
    "gn:admin3_code":"240203.0",
    "gn:asciiname":"Cerro Pelado",
    "gn:country_code":"PE",
    "gn:dem":1,
    "gn:feature_class":"P",
    "gn:feature_code":"PPL",
    "gn:name":"Cerro Pelado",
    "gn:population":0,
    "gn:timezone":"America/Lima",
    "iso:country":"PE",
    "name:cat_x_preferred":[
        "Cerro Pelado"
    ],
    "name:deu_x_preferred":[
        "Cerro Pelado"
    ],
    "name:fra_x_preferred":[
        "Cerro Pelado"
    ],
    "wof:name":"Cerro Pelado",
    "wof:placetype":"locality"
},
  "geometry": {"coordinates":[-81.02388000000001,-4.08706],"type":"Point"}
}