{
  "type": "Feature",
  "properties": {
    "gn:admin1_code":"21",
    "gn:admin2_code":"2107.0",
    "gn:admin3_code":"210709.0",
    "gn:asciiname":"Hacienda Lagunillas",
    "gn:country_code":"PE",
    "gn:dem":4195,
    "gn:feature_class":"P",
    "gn:feature_code":"PPL",
    "gn:name":"Hacienda Lagunillas",
    "gn:population":0,
    "gn:timezone":"America/Lima",
    "iso:country":"PE",
    "name:und_x_variant":[
        "Lagunillas Hacienda",
        "Hacienda Lagunillas"
    ],
    "wof:name":"Hacienda Lagunillas",
    "wof:placetype":"locality"
},
  "geometry": {"coordinates":[-70.76909000000001,-15.74629],"type":"Point"}
}