{
  "type": "Feature",
  "properties": {
    "gn:admin1_code":"10.0",
    "gn:admin2_code":"1001.0",
    "gn:admin3_code":"100109.0",
    "gn:asciiname":"Carpiragra",
    "gn:country_code":"PE",
    "gn:dem":2099,
    "gn:feature_class":"P",
    "gn:feature_code":"PPLL",
    "gn:name":"Carpiragra",
    "gn:population":0,
    "gn:timezone":"America/Lima",
    "iso:country":"PE",
    "wof:name":"Carpiragra",
    "wof:placetype":"locality"
},
  "geometry": {"coordinates":[-76.1652,-9.87673],"type":"Point"}
}