{
  "type": "Feature",
  "properties": {
    "gn:admin1_code":"8",
    "gn:admin2_code":"807.0",
    "gn:admin3_code":"80708.0",
    "gn:asciiname":"Huailla Huailla",
    "gn:country_code":"PE",
    "gn:dem":4512,
    "gn:feature_class":"P",
    "gn:feature_code":"PPL",
    "gn:name":"Huailla Huailla",
    "gn:population":0,
    "gn:timezone":"America/Lima",
    "iso:country":"PE",
    "name:und_x_variant":[
        "Huaylla Huaylla",
        "Huailla Huailla"
    ],
    "wof:name":"Huailla Huailla",
    "wof:placetype":"locality"
},
  "geometry": {"coordinates":[-71.78883,-14.64034],"type":"Point"}
}