{
  "type": "Feature",
  "properties": {
    "gn:admin1_code":"4",
    "gn:admin2_code":"406.0",
    "gn:admin3_code":"40604.0",
    "gn:asciiname":"Cahuanota",
    "gn:country_code":"PE",
    "gn:dem":2740,
    "gn:feature_class":"P",
    "gn:feature_code":"PPL",
    "gn:name":"Cahuanota",
    "gn:population":0,
    "gn:timezone":"America/Lima",
    "iso:country":"PE",
    "name:und_x_variant":[
        "Cahuanata",
        "Cahuanota"
    ],
    "wof:name":"Cahuanota",
    "wof:placetype":"locality"
},
  "geometry": {"coordinates":[-72.95104000000001,-15.47609],"type":"Point"}
}