{
  "type": "Feature",
  "properties": {
    "gn:admin1_code":"23",
    "gn:admin2_code":"2302.0",
    "gn:admin3_code":"230206.0",
    "gn:asciiname":"Miraflorez",
    "gn:country_code":"PE",
    "gn:dem":3242,
    "gn:feature_class":"P",
    "gn:feature_code":"PPL",
    "gn:name":"Miraflorez",
    "gn:population":0,
    "gn:timezone":"America/Lima",
    "iso:country":"PE",
    "wof:name":"Miraflorez",
    "wof:placetype":"locality"
},
  "geometry": {"coordinates":[-70.25906999999999,-17.31476],"type":"Point"}
}