{
  "type": "Feature",
  "properties": {
    "gn:admin1_code":"02",
    "gn:admin2_code":"201.0",
    "gn:admin3_code":"20104.0",
    "gn:asciiname":"Huanchay",
    "gn:country_code":"PE",
    "gn:dem":1880,
    "gn:feature_class":"P",
    "gn:feature_code":"PPLA3",
    "gn:name":"Huanchay",
    "gn:population":0,
    "gn:timezone":"America/Lima",
    "iso:country":"PE",
    "wof:name":"Huanchay",
    "wof:placetype":"locality"
},
  "geometry": {"coordinates":[-77.83333,-9.73333],"type":"Point"}
}