{
  "type": "Feature",
  "properties": {
    "gn:admin1_code":"2",
    "gn:admin2_code":"215.0",
    "gn:admin3_code":"21510.0",
    "gn:asciiname":"Collo Collo Allo",
    "gn:country_code":"PE",
    "gn:dem":2274,
    "gn:feature_class":"P",
    "gn:feature_code":"PPL",
    "gn:name":"Collo Collo Allo",
    "gn:population":0,
    "gn:timezone":"America/Lima",
    "iso:country":"PE",
    "wof:name":"Collo Collo Allo",
    "wof:placetype":"locality"
},
  "geometry": {"coordinates":[-78.07417,-8.51722],"type":"Point"}
}