{
  "type": "Feature",
  "properties": {
    "gn:admin1_code":"16",
    "gn:admin2_code":"1606.0",
    "gn:admin3_code":"160602.0",
    "gn:asciiname":"Ceilan",
    "gn:country_code":"PE",
    "gn:dem":130,
    "gn:feature_class":"P",
    "gn:feature_code":"PPL",
    "gn:name":"Ceilan",
    "gn:population":0,
    "gn:timezone":"America/Lima",
    "iso:country":"PE",
    "wof:name":"Ceilan",
    "wof:placetype":"locality"
},
  "geometry": {"coordinates":[-75.15465999999998,-6.97376],"type":"Point"}
}