{
  "type": "Feature",
  "properties": {
    "gn:admin1_code":"8",
    "gn:admin2_code":"806.0",
    "gn:admin3_code":"80606.0",
    "gn:asciiname":"Pucamachay",
    "gn:country_code":"PE",
    "gn:dem":4168,
    "gn:feature_class":"P",
    "gn:feature_code":"PPL",
    "gn:name":"Pucamachay",
    "gn:population":0,
    "gn:timezone":"America/Lima",
    "iso:country":"PE",
    "wof:name":"Pucamachay",
    "wof:placetype":"locality"
},
  "geometry": {"coordinates":[-71.16074,-14.15232],"type":"Point"}
}