{
  "type": "Feature",
  "properties": {
    "gn:admin1_code":"1",
    "gn:admin2_code":"101.0",
    "gn:admin3_code":"10109.0",
    "gn:asciiname":"Quinua",
    "gn:country_code":"PE",
    "gn:dem":2803,
    "gn:feature_class":"P",
    "gn:feature_code":"PPL",
    "gn:name":"Quinua",
    "gn:population":0,
    "gn:timezone":"America/Lima",
    "iso:country":"PE",
    "wof:name":"Quinua",
    "wof:placetype":"locality"
},
  "geometry": {"coordinates":[-77.80981,-6.51001],"type":"Point"}
}