{
  "type": "Feature",
  "properties": {
    "gn:admin1_code":"23",
    "gn:admin2_code":"2301.0",
    "gn:admin3_code":"230105.0",
    "gn:asciiname":"Tomasiri",
    "gn:country_code":"PE",
    "gn:dem":461,
    "gn:feature_class":"P",
    "gn:feature_code":"PPL",
    "gn:name":"Tomasiri",
    "gn:population":0,
    "gn:timezone":"America/Lima",
    "iso:country":"PE",
    "name:und_x_variant":[
        "Tomasiri Hacienda",
        "Tomasiri"
    ],
    "wof:name":"Tomasiri",
    "wof:placetype":"locality"
},
  "geometry": {"coordinates":[-70.51621,-17.84202999999999],"type":"Point"}
}