{
  "type": "Feature",
  "properties": {
    "gn:admin1_code":"19",
    "gn:admin2_code":"1901.0",
    "gn:admin3_code":"190103.0",
    "gn:asciiname":"Pachamachay",
    "gn:country_code":"PE",
    "gn:dem":4226,
    "gn:feature_class":"P",
    "gn:feature_code":"PPL",
    "gn:name":"Pachamachay",
    "gn:population":0,
    "gn:timezone":"America/Lima",
    "iso:country":"PE",
    "wof:name":"Pachamachay",
    "wof:placetype":"locality"
},
  "geometry": {"coordinates":[-76.11844000000001,-10.43617],"type":"Point"}
}