{
  "type": "Feature",
  "properties": {
    "gn:admin1_code":"5.0",
    "gn:admin2_code":"501.0",
    "gn:admin3_code":"50112.0",
    "gn:asciiname":"Orjopuquio",
    "gn:country_code":"PE",
    "gn:dem":3560,
    "gn:feature_class":"P",
    "gn:feature_code":"PPL",
    "gn:name":"Orjopuquio",
    "gn:population":0,
    "gn:timezone":"America/Lima",
    "iso:country":"PE",
    "wof:name":"Orjopuquio",
    "wof:placetype":"locality"
},
  "geometry": {"coordinates":[-74.28044,-13.22038],"type":"Point"}
}