{
  "type": "Feature",
  "properties": {
    "gn:admin1_code":"12.0",
    "gn:admin2_code":"1206.0",
    "gn:admin3_code":"120608.0",
    "gn:asciiname":"Shivatsine",
    "gn:country_code":"PE",
    "gn:dem":253,
    "gn:feature_class":"P",
    "gn:feature_code":"PPLL",
    "gn:name":"Shivatsine",
    "gn:population":0,
    "gn:timezone":"America/Lima",
    "iso:country":"PE",
    "name:spa_x_preferred":[
        "Shivatsine"
    ],
    "wof:name":"Shivatsine",
    "wof:placetype":"locality"
},
  "geometry": {"coordinates":[-73.73565000000001,-11.11707],"type":"Point"}
}