{
  "type": "Feature",
  "properties": {
    "gn:admin1_code":"10.0",
    "gn:admin2_code":"1004.0",
    "gn:admin3_code":"100401.0",
    "gn:asciiname":"Inciesopampa",
    "gn:country_code":"PE",
    "gn:dem":2781,
    "gn:feature_class":"P",
    "gn:feature_code":"PPL",
    "gn:name":"Inciesopampa",
    "gn:population":0,
    "gn:timezone":"America/Lima",
    "iso:country":"PE",
    "wof:name":"Inciesopampa",
    "wof:placetype":"locality"
},
  "geometry": {"coordinates":[-76.93615,-9.05091],"type":"Point"}
}