{
  "type": "Feature",
  "properties": {
    "gn:admin1_code":"8.0",
    "gn:admin2_code":"809.0",
    "gn:asciiname":"Libertadores",
    "gn:country_code":"PE",
    "gn:dem":764,
    "gn:feature_class":"P",
    "gn:feature_code":"PPL",
    "gn:name":"Libertadores",
    "gn:population":0,
    "gn:timezone":"America/Lima",
    "iso:country":"PE",
    "name:aym_x_preferred":[
        "Atini\u00f1aptayiri"
    ],
    "name:bre_x_preferred":[
        "Libertadores"
    ],
    "name:fra_x_preferred":[
        "Libertadores"
    ],
    "name:hin_x_preferred":[
        "\u0932\u093f\u092c\u0930\u091f\u093e\u0921\u094b\u0930\u094d\u0938"
    ],
    "name:ind_x_preferred":[
        "Libertadores"
    ],
    "name:jpn_x_preferred":[
        "\u30ea\u30d9\u30eb\u30bf\u30c9\u30fc\u30ec\u30b9"
    ],
    "name:kor_x_preferred":[
        "\ub9ac\ubca0\ub974\ud0c0\ub3c4\ub808\uc2a4"
    ],
    "name:mkd_x_preferred":[
        "\u041b\u0438\u0431\u0435\u0440\u0442\u0430\u0434\u043e\u0440\u0438"
    ],
    "name:nld_x_preferred":[
        "Libertadores"
    ],
    "name:por_x_preferred":[
        "Libertadores"
    ],
    "name:ron_x_preferred":[
        "Libertadores"
    ],
    "name:spa_x_preferred":[
        "Libertador"
    ],
    "name:ukr_x_preferred":[
        "\u0412\u0438\u0437\u0432\u043e\u043b\u0438\u0442\u0435\u043b\u0456"
    ],
    "name:war_x_preferred":[
        "Libertadores"
    ],
    "wof:name":"Libertadores",
    "wof:placetype":"locality"
},
  "geometry": {"coordinates":[-73.51266,-12.96054],"type":"Point"}
}