{
  "type": "Feature",
  "properties": {
    "gn:admin1_code":"12",
    "gn:admin2_code":"1207.0",
    "gn:admin3_code":"120701.0",
    "gn:asciiname":"Huanuquillo",
    "gn:country_code":"PE",
    "gn:dem":3099,
    "gn:feature_class":"P",
    "gn:feature_code":"PPL",
    "gn:name":"Huanuquillo",
    "gn:population":0,
    "gn:timezone":"America/Lima",
    "iso:country":"PE",
    "wof:name":"Huanuquillo",
    "wof:placetype":"locality"
},
  "geometry": {"coordinates":[-75.69031,-11.43911],"type":"Point"}
}