{
  "type": "Feature",
  "properties": {
    "gn:admin1_code":"15",
    "gn:admin2_code":"1505.0",
    "gn:admin3_code":"150509.0",
    "gn:asciiname":"Bujama Alta",
    "gn:country_code":"PE",
    "gn:dem":20,
    "gn:feature_class":"P",
    "gn:feature_code":"PPL",
    "gn:name":"Bujama Alta",
    "gn:population":0,
    "gn:timezone":"America/Lima",
    "iso:country":"PE",
    "name:und_x_variant":[
        "Bujama",
        "Bujama Alta"
    ],
    "wof:name":"Bujama Alta",
    "wof:placetype":"locality"
},
  "geometry": {"coordinates":[-76.61743,-12.70531],"type":"Point"}
}