{
  "type": "Feature",
  "properties": {
    "gn:admin1_code":"15",
    "gn:admin2_code":"1507.0",
    "gn:admin3_code":"150719.0",
    "gn:asciiname":"Felicidad",
    "gn:country_code":"PE",
    "gn:dem":4777,
    "gn:feature_class":"P",
    "gn:feature_code":"PPL",
    "gn:name":"Felicidad",
    "gn:population":0,
    "gn:timezone":"America/Lima",
    "iso:country":"PE",
    "wof:name":"Felicidad",
    "wof:placetype":"locality"
},
  "geometry": {"coordinates":[-76.43333,-11.73333],"type":"Point"}
}