{
  "type": "Feature",
  "properties": {
    "gn:admin1_code":"15.0",
    "gn:admin2_code":"1506.0",
    "gn:admin3_code":"150604.0",
    "gn:asciiname":"San Graciano Bajo",
    "gn:country_code":"PE",
    "gn:dem":130,
    "gn:feature_class":"P",
    "gn:feature_code":"PPLL",
    "gn:name":"San Graciano Bajo",
    "gn:population":0,
    "gn:timezone":"America/Lima",
    "iso:country":"PE",
    "name:spa_x_preferred":[
        "San Graciano Bajo"
    ],
    "wof:name":"San Graciano Bajo",
    "wof:placetype":"locality"
},
  "geometry": {"coordinates":[-77.17846,-11.57942],"type":"Point"}
}