{
  "type": "Feature",
  "properties": {
    "gn:admin1_code":"22.0",
    "gn:admin2_code":"2210.0",
    "gn:admin3_code":"221001.0",
    "gn:asciiname":"Lupuna",
    "gn:country_code":"PE",
    "gn:dem":507,
    "gn:feature_class":"P",
    "gn:feature_code":"PPL",
    "gn:name":"Lupuna",
    "gn:population":0,
    "gn:timezone":"America/Lima",
    "iso:country":"PE",
    "wof:name":"Lupuna",
    "wof:placetype":"locality"
},
  "geometry": {"coordinates":[-76.41991,-8.23656],"type":"Point"}
}