{
  "type": "Feature",
  "properties": {
    "gn:admin1_code":"12.0",
    "gn:admin2_code":"1204.0",
    "gn:admin3_code":"120408.0",
    "gn:asciiname":"Chupa",
    "gn:country_code":"PE",
    "gn:dem":3344,
    "gn:feature_class":"P",
    "gn:feature_code":"PPL",
    "gn:name":"Chupa",
    "gn:population":0,
    "gn:timezone":"America/Lima",
    "iso:country":"PE",
    "name:ceb_x_preferred":[
        "Chupa"
    ],
    "name:ita_x_preferred":[
        "Chupa"
    ],
    "name:spa_x_preferred":[
        "Chupa"
    ],
    "name:swe_x_preferred":[
        "Chupa"
    ],
    "wof:name":"Chupa",
    "wof:placetype":"locality"
},
  "geometry": {"coordinates":[-75.42945,-11.80305],"type":"Point"}
}