{
  "type": "Feature",
  "properties": {
    "gn:admin1_code":"01",
    "gn:admin2_code":"101.0",
    "gn:admin3_code":"10106.0",
    "gn:asciiname":"Chuquibamba",
    "gn:country_code":"PE",
    "gn:dem":2825,
    "gn:feature_class":"P",
    "gn:feature_code":"PPLA3",
    "gn:name":"Chuquibamba",
    "gn:population":0,
    "gn:timezone":"America/Lima",
    "iso:country":"PE",
    "wof:name":"Chuquibamba",
    "wof:placetype":"locality"
},
  "geometry": {"coordinates":[-77.85221999999997,-6.93417],"type":"Point"}
}