{
  "type": "Feature",
  "properties": {
    "gn:admin1_code":"5",
    "gn:admin2_code":"505.0",
    "gn:admin3_code":"50504.0",
    "gn:asciiname":"Huilculo",
    "gn:country_code":"PE",
    "gn:dem":2891,
    "gn:feature_class":"P",
    "gn:feature_code":"PPL",
    "gn:name":"Huilculo",
    "gn:population":0,
    "gn:timezone":"America/Lima",
    "iso:country":"PE",
    "name:und_x_variant":[
        "Huinculo",
        "Huilculo"
    ],
    "wof:name":"Huilculo",
    "wof:placetype":"locality"
},
  "geometry": {"coordinates":[-73.89190000000001,-13.15449],"type":"Point"}
}