{
  "type": "Feature",
  "properties": {
    "gn:admin1_code":"23",
    "gn:admin2_code":"2303.0",
    "gn:admin3_code":"230302.0",
    "gn:asciiname":"Puquio",
    "gn:country_code":"PE",
    "gn:dem":1600,
    "gn:feature_class":"P",
    "gn:feature_code":"PPL",
    "gn:name":"Puquio",
    "gn:population":0,
    "gn:timezone":"America/Lima",
    "iso:country":"PE",
    "wof:name":"Puquio",
    "wof:placetype":"locality"
},
  "geometry": {"coordinates":[-70.48333000000002,-17.39083],"type":"Point"}
}