{
  "type": "Feature",
  "properties": {
    "gn:admin1_code":"23",
    "gn:admin2_code":"2303.0",
    "gn:admin3_code":"230302.0",
    "gn:asciiname":"Puquio",
    "gn:country_code":"PE",
    "gn:dem":1600,
    "gn:feature_class":"P",
    "gn:feature_code":"PPL",
    "gn:name":"Puquio",
    "gn:population":0,
    "gn:timezone":"America/Lima",
    "iso:country":"PE",
    "name:ara_x_preferred":[
        "\u0628\u0648\u0643\u0648\u064a\u0648"
    ],
    "name:aym_x_preferred":[
        "Pukyu"
    ],
    "name:ben_x_preferred":[
        "\u09aa\u09c1\u0995\u09c1\u0987\u09df\u09cb"
    ],
    "name:ceb_x_preferred":[
        "Puquio"
    ],
    "name:deu_x_preferred":[
        "Puquio"
    ],
    "name:ell_x_preferred":[
        "\u03a0\u03bf\u03c5\u03ba\u03bf\u03cd\u03b9\u03bf"
    ],
    "name:fra_x_preferred":[
        "Puquio"
    ],
    "name:heb_x_preferred":[
        "\u05e4\u05d5\u05e7\u05d9\u05d5"
    ],
    "name:hin_x_preferred":[
        "\u092a\u0941\u0915\u093f\u092f\u094b"
    ],
    "name:hun_x_preferred":[
        "Puquio"
    ],
    "name:ind_x_preferred":[
        "Puquio"
    ],
    "name:ita_x_preferred":[
        "Puquio"
    ],
    "name:jpn_x_preferred":[
        "\u30d7\u30ad\u30aa"
    ],
    "name:kor_x_preferred":[
        "\ud478\ud0a4\uc624"
    ],
    "name:lit_x_preferred":[
        "Pukijas"
    ],
    "name:pol_x_preferred":[
        "Puquio"
    ],
    "name:que_x_preferred":[
        "Pukyu llaqta"
    ],
    "name:rus_x_preferred":[
        "\u041f\u0443\u043a\u0438\u043e"
    ],
    "name:spa_x_preferred":[
        "Puquio"
    ],
    "name:swe_x_preferred":[
        "Puquio"
    ],
    "name:tur_x_preferred":[
        "Puquio"
    ],
    "name:ukr_x_preferred":[
        "\u041f\u0443\u043a\u0456\u0439\u043e"
    ],
    "name:urd_x_preferred":[
        "\u067e\u0648\u0642\u06cc\u0648"
    ],
    "name:vie_x_preferred":[
        "Puquio"
    ],
    "name:war_x_preferred":[
        "Puquio"
    ],
    "name:zho_x_preferred":[
        "\u666e\u57fa\u5967"
    ],
    "wof:name":"Puquio",
    "wof:placetype":"locality"
},
  "geometry": {"coordinates":[-70.48333,-17.39083],"type":"Point"}
}