{
  "type": "Feature",
  "properties": {
    "gn:admin1_code":"5.0",
    "gn:admin2_code":"501.0",
    "gn:admin3_code":"50105.0",
    "gn:asciiname":"Chanchayllo",
    "gn:country_code":"PE",
    "gn:dem":3447,
    "gn:feature_class":"P",
    "gn:feature_code":"PPL",
    "gn:name":"Chanchayllo",
    "gn:population":0,
    "gn:timezone":"America/Lima",
    "iso:country":"PE",
    "name:und_x_variant":[
        "Fundo Chanchayllo"
    ],
    "wof:name":"Chanchayllo",
    "wof:placetype":"locality"
},
  "geometry": {"coordinates":[-74.07384,-13.48928],"type":"Point"}
}