{
  "type": "Feature",
  "properties": {
    "gn:admin1_code":"5.0",
    "gn:admin2_code":"504.0",
    "gn:admin3_code":"50402.0",
    "gn:asciiname":"Jatun Pampa",
    "gn:country_code":"PE",
    "gn:dem":3982,
    "gn:feature_class":"P",
    "gn:feature_code":"PPL",
    "gn:name":"Jatun Pampa",
    "gn:population":0,
    "gn:timezone":"America/Lima",
    "iso:country":"PE",
    "wof:name":"Jatun Pampa",
    "wof:placetype":"locality"
},
  "geometry": {"coordinates":[-74.33830999999998,-12.52647],"type":"Point"}
}