{
  "type": "Feature",
  "properties": {
    "gn:admin1_code":"16",
    "gn:admin2_code":"1604.0",
    "gn:admin3_code":"160401.0",
    "gn:asciiname":"Buenjardin",
    "gn:country_code":"PE",
    "gn:dem":78,
    "gn:feature_class":"P",
    "gn:feature_code":"PPL",
    "gn:name":"Buenjard\u00edn",
    "gn:population":0,
    "gn:timezone":"America/Lima",
    "iso:country":"PE",
    "wof:name":"Buenjardin",
    "wof:placetype":"locality"
},
  "geometry": {"coordinates":[-70.24807,-4.06545],"type":"Point"}
}