{
  "type": "Feature",
  "properties": {
    "gn:admin1_code":"9.0",
    "gn:admin2_code":"901.0",
    "gn:admin3_code":"90103.0",
    "gn:asciiname":"Tucupampa",
    "gn:country_code":"PE",
    "gn:dem":3424,
    "gn:feature_class":"P",
    "gn:feature_code":"PPL",
    "gn:name":"Tucupampa",
    "gn:population":0,
    "gn:timezone":"America/Lima",
    "iso:country":"PE",
    "wof:name":"Tucupampa",
    "wof:placetype":"locality"
},
  "geometry": {"coordinates":[-74.88023000000003,-12.63373],"type":"Point"}
}