{
  "type": "Feature",
  "properties": {
    "gn:admin1_code":"12.0",
    "gn:admin2_code":"1204.0",
    "gn:admin3_code":"120416.0",
    "gn:asciiname":"Yahuarjasha",
    "gn:country_code":"PE",
    "gn:dem":3474,
    "gn:feature_class":"P",
    "gn:feature_code":"PPL",
    "gn:name":"Yahuarjasha",
    "gn:population":0,
    "gn:timezone":"America/Lima",
    "iso:country":"PE",
    "wof:name":"Yahuarjasha",
    "wof:placetype":"locality"
},
  "geometry": {"coordinates":[-75.44587,-11.77718],"type":"Point"}
}