{
  "type": "Feature",
  "properties": {
    "iso:country":"PE",
    "name:ara_x_preferred":[
        "\u0645\u062d\u0627\u0641\u0638\u0629 \u0647\u0648\u0627\u0648\u0631\u0627"
    ],
    "name:ceb_x_preferred":[
        "Huaura"
    ],
    "name:eng_x_preferred":[
        "Huaura"
    ],
    "name:fra_x_preferred":[
        "Huaura"
    ],
    "name:por_x_preferred":[
        "Huaura"
    ],
    "name:spa_x_preferred":[
        "Huaura"
    ],
    "name:swe_x_preferred":[
        "Huaura"
    ],
    "ne:ADM0CAP":0.0,
    "ne:ADM0NAME":"Peru",
    "ne:ADM0_A3":"PER",
    "ne:ADM1NAME":"Lima",
    "ne:ADMIN1_COD":15,
    "ne:CAPALT":0,
    "ne:CHANGED":4,
    "ne:CHECKME":0,
    "ne:COMPARE":0,
    "ne:DIFFASCII":0,
    "ne:DIFFNOTE":"Changed feature class.",
    "ne:ELEVATION":0.0,
    "ne:FEATURECLA":"Admin-1 capital",
    "ne:FEATURE_CL":"P",
    "ne:FEATURE_CO":"PPL",
    "ne:GEONAMEID":3939023,
    "ne:GEONAMESNO":"Geonames ascii name + lat.d + long.d matching.",
    "ne:GN_ASCII":"Huaura",
    "ne:GN_POP":20723,
    "ne:GTOPO30":42.0,
    "ne:ISO_A2":"PE",
    "ne:LABELRANK":5,
    "ne:LATITUDE":-11.060011,
    "ne:LONGITUDE":-77.599977,
    "ne:LS_MATCH":1,
    "ne:LS_NAME":"Huaura",
    "ne:MAX_AREAKM":3.0,
    "ne:MAX_AREAMI":1.0,
    "ne:MAX_BBXMAX":-77.591667,
    "ne:MAX_BBXMIN":-77.608333,
    "ne:MAX_BBYMAX":-11.058333,
    "ne:MAX_BBYMIN":-11.075,
    "ne:MAX_NATSCA":10.0,
    "ne:MAX_PERKM":7.0,
    "ne:MAX_PERMI":5.0,
    "ne:MAX_POP10":40400,
    "ne:MAX_POP20":0,
    "ne:MAX_POP300":0,
    "ne:MAX_POP310":0,
    "ne:MAX_POP50":0,
    "ne:MEAN_BBXC":-77.6,
    "ne:MEAN_BBYC":-11.066667,
    "ne:MEGACITY":0,
    "ne:MIN_AREAKM":3.0,
    "ne:MIN_AREAMI":1.0,
    "ne:MIN_BBXMAX":-77.591667,
    "ne:MIN_BBXMIN":-77.608333,
    "ne:MIN_BBYMAX":-11.058333,
    "ne:MIN_BBYMIN":-11.075,
    "ne:MIN_PERKM":7.0,
    "ne:MIN_PERMI":5.0,
    "ne:NAME":"Huaura",
    "ne:NAMEASCII":"Huaura",
    "ne:NAMEDIFF":0,
    "ne:NATSCALE":10,
    "ne:POP1950":0,
    "ne:POP1955":0,
    "ne:POP1960":0,
    "ne:POP1965":0,
    "ne:POP1970":0,
    "ne:POP1975":0,
    "ne:POP1980":0,
    "ne:POP1985":0,
    "ne:POP1990":0,
    "ne:POP1995":0,
    "ne:POP2000":0,
    "ne:POP2005":0,
    "ne:POP2010":0,
    "ne:POP2015":0,
    "ne:POP2020":0,
    "ne:POP2025":0,
    "ne:POP2050":0,
    "ne:POP_MAX":40400,
    "ne:POP_MIN":20723,
    "ne:POP_OTHER":40400,
    "ne:RANK_MAX":7,
    "ne:RANK_MIN":7,
    "ne:SCALERANK":8,
    "ne:SOV0NAME":"Peru",
    "ne:SOV_A3":"PER",
    "ne:TIMEZONE":"America/Lima",
    "ne:UN_FID":0,
    "ne:UN_LAT":0.0,
    "ne:UN_LONG":0.0,
    "ne:WORLDCITY":0,
    "qs:gn_country":"PE",
    "qs:gn_fcode":"PPLA3",
    "qs:gn_pop":20723,
    "qs:name":"Huaura",
    "qs:name_adm0":"Per\u00fa",
    "qs:name_adm1":"Lima",
    "qs:photos":151,
    "qs:photos_1k":31,
    "qs:photos_9k":1,
    "qs:photos_9r":4,
    "qs:photos_all":151,
    "qs:photos_sr":4,
    "qs:placetype":"Town",
    "qs:pop_sr":"7",
    "qs:woe_adm0":23424919,
    "wof:name":"Huaura",
    "wof:placetype":"locality",
    "wof:population":20723
},
  "geometry": {"coordinates":[-77.59944,-11.07],"type":"Point"}
}