{
  "type": "Feature",
  "properties": {
    "gn:admin1_code":"05",
    "gn:admin2_code":"501.0",
    "gn:admin3_code":"50109.0",
    "gn:asciiname":"Urayparte",
    "gn:country_code":"PE",
    "gn:dem":2948,
    "gn:feature_class":"P",
    "gn:feature_code":"PPL",
    "gn:name":"Urayparte",
    "gn:population":0,
    "gn:timezone":"America/Lima",
    "iso:country":"PE",
    "wof:name":"Urayparte",
    "wof:placetype":"locality"
},
  "geometry": {"coordinates":[-74.29365,-13.16137],"type":"Point"}
}