{
  "type": "Feature",
  "properties": {
    "gn:country":"PE",
    "gn:fcode":"PPLA3",
    "gn:pop":3466,
    "iso:country":"PE",
    "name:cat_x_preferred":[
        "Tinta"
    ],
    "name:ces_x_preferred":[
        "Tinta"
    ],
    "name:deu_x_preferred":[
        "Tinta"
    ],
    "name:eng_x_preferred":[
        "Tinta"
    ],
    "name:nld_x_preferred":[
        "Tinta"
    ],
    "name:pol_x_preferred":[
        "Tinta"
    ],
    "name:que_x_preferred":[
        "Tinta"
    ],
    "name:spa_x_preferred":[
        "Tinta"
    ],
    "qs:name":"Tinta",
    "qs:photos_9r":0,
    "qs:photos_sr":0,
    "qs:pop_sr":"4",
    "wof:name":"Tinta",
    "wof:placetype":"locality",
    "wof:population":3466
},
  "geometry": {"coordinates":[-71.40694000000001,-14.145],"type":"Point"}
}