{
  "type": "Feature",
  "properties": {
    "gn:admin1_code":"2.0",
    "gn:admin2_code":"220.0",
    "gn:admin3_code":"22007.0",
    "gn:asciiname":"Cachus",
    "gn:country_code":"PE",
    "gn:dem":3731,
    "gn:feature_class":"P",
    "gn:feature_code":"PPL",
    "gn:name":"Cachus",
    "gn:population":0,
    "gn:timezone":"America/Lima",
    "iso:country":"PE",
    "wof:name":"Cachus",
    "wof:placetype":"locality"
},
  "geometry": {"coordinates":[-77.7375,-9.26667],"type":"Point"}
}