{
  "type": "Feature",
  "properties": {
    "gn:admin1_code":"20",
    "gn:admin2_code":"2006.0",
    "gn:admin3_code":"200607.0",
    "gn:asciiname":"La Pena",
    "gn:country_code":"PE",
    "gn:dem":87,
    "gn:feature_class":"P",
    "gn:feature_code":"PPL",
    "gn:name":"La Pe\u00f1a",
    "gn:population":0,
    "gn:timezone":"America/Lima",
    "iso:country":"PE",
    "wof:name":"La Pena",
    "wof:placetype":"locality"
},
  "geometry": {"coordinates":[-80.57949000000001,-4.77276],"type":"Point"}
}