{
  "type": "Feature",
  "properties": {
    "gn:admin1_code":"8",
    "gn:admin2_code":"808.0",
    "gn:admin3_code":"80804.0",
    "gn:asciiname":"Quisini",
    "gn:country_code":"PE",
    "gn:dem":4372,
    "gn:feature_class":"P",
    "gn:feature_code":"PPL",
    "gn:name":"Quisini",
    "gn:population":0,
    "gn:timezone":"America/Lima",
    "iso:country":"PE",
    "wof:name":"Quisini",
    "wof:placetype":"locality"
},
  "geometry": {"coordinates":[-71.11959,-15.15354],"type":"Point"}
}