{
  "type": "Feature",
  "properties": {
    "gn:admin1_code":"18",
    "gn:admin2_code":"1801.0",
    "gn:admin3_code":"180101.0",
    "gn:asciiname":"La Bodeguilla Hacienda",
    "gn:country_code":"PE",
    "gn:dem":1156,
    "gn:feature_class":"P",
    "gn:feature_code":"PPL",
    "gn:name":"La Bodeguilla Hacienda",
    "gn:population":0,
    "gn:timezone":"America/Lima",
    "iso:country":"PE",
    "name:und_x_variant":[
        "Bodeguilla",
        "La Bodeguilla Hacienda"
    ],
    "wof:name":"La Bodeguilla Hacienda",
    "wof:placetype":"locality"
},
  "geometry": {"coordinates":[-70.9819,-17.26415],"type":"Point"}
}