{
  "type": "Feature",
  "properties": {
    "gn:admin1_code":"20.0",
    "gn:admin2_code":"2002.0",
    "gn:admin3_code":"200203.0",
    "gn:asciiname":"Los Paltos",
    "gn:country_code":"PE",
    "gn:dem":1412,
    "gn:feature_class":"P",
    "gn:feature_code":"PPL",
    "gn:name":"Los Paltos",
    "gn:population":0,
    "gn:timezone":"America/Lima",
    "iso:country":"PE",
    "wof:name":"Los Paltos",
    "wof:placetype":"locality"
},
  "geometry": {"coordinates":[-79.83747,-4.53199],"type":"Point"}
}