{
  "type": "Feature",
  "properties": {
    "gn:admin1_code":"1.0",
    "gn:admin2_code":"106.0",
    "gn:admin3_code":"10609.0",
    "gn:asciiname":"Cushillo",
    "gn:country_code":"PE",
    "gn:dem":1665,
    "gn:feature_class":"P",
    "gn:feature_code":"PPL",
    "gn:name":"Cushillo",
    "gn:population":0,
    "gn:timezone":"America/Lima",
    "iso:country":"PE",
    "wof:name":"Cushillo",
    "wof:placetype":"locality"
},
  "geometry": {"coordinates":[-77.40000000000001,-6.43528],"type":"Point"}
}