{
  "type": "Feature",
  "properties": {
    "gn:admin1_code":"05",
    "gn:admin2_code":"501.0",
    "gn:admin3_code":"50114.0",
    "gn:asciiname":"Mesaray",
    "gn:country_code":"PE",
    "gn:dem":4516,
    "gn:feature_class":"P",
    "gn:feature_code":"PPL",
    "gn:name":"Mesaray",
    "gn:population":0,
    "gn:timezone":"America/Lima",
    "iso:country":"PE",
    "wof:name":"Mesaray",
    "wof:placetype":"locality"
},
  "geometry": {"coordinates":[-74.61896,-13.27781],"type":"Point"}
}