{
  "type": "Feature",
  "properties": {
    "gn:admin1_code":"15",
    "gn:admin2_code":"1501.0",
    "gn:admin3_code":"150109.0",
    "gn:asciiname":"Hacienda Cienguilla",
    "gn:country_code":"PE",
    "gn:dem":350,
    "gn:feature_class":"P",
    "gn:feature_code":"PPL",
    "gn:name":"Hacienda Cienguilla",
    "gn:population":0,
    "gn:timezone":"America/Lima",
    "iso:country":"PE",
    "name:spa_x_preferred":[
        "Hacienda Cienguilla"
    ],
    "wof:name":"Hacienda Cienguilla",
    "wof:placetype":"locality"
},
  "geometry": {"coordinates":[-76.80431999999998,-12.11999],"type":"Point"}
}