{
  "type": "Feature",
  "properties": {
    "gn:admin1_code":"4",
    "gn:admin2_code":"403.0",
    "gn:admin3_code":"40312.0",
    "gn:asciiname":"Achatayhua",
    "gn:country_code":"PE",
    "gn:dem":3723,
    "gn:feature_class":"P",
    "gn:feature_code":"PPL",
    "gn:name":"Achatayhua",
    "gn:population":0,
    "gn:timezone":"America/Lima",
    "iso:country":"PE",
    "name:spa_x_preferred":[
        "Achatayhua"
    ],
    "wof:name":"Achatayhua",
    "wof:placetype":"locality"
},
  "geometry": {"coordinates":[-73.83091,-15.45625],"type":"Point"}
}