{
  "type": "Feature",
  "properties": {
    "gn:admin1_code":"21",
    "gn:admin2_code":"2104.0",
    "gn:admin3_code":"210407.0",
    "gn:asciiname":"Huancarani",
    "gn:country_code":"PE",
    "gn:dem":3827,
    "gn:feature_class":"P",
    "gn:feature_code":"PPL",
    "gn:name":"Huancarani",
    "gn:population":0,
    "gn:timezone":"America/Lima",
    "iso:country":"PE",
    "wof:name":"Huancarani",
    "wof:placetype":"locality"
},
  "geometry": {"coordinates":[-69.07585999999999,-16.51788],"type":"Point"}
}