{
  "type": "Feature",
  "properties": {
    "gn:admin1_code":"9.0",
    "gn:admin2_code":"907.0",
    "gn:admin3_code":"90715.0",
    "gn:asciiname":"Totorapampa",
    "gn:country_code":"PE",
    "gn:dem":3157,
    "gn:feature_class":"P",
    "gn:feature_code":"PPL",
    "gn:name":"Totorapampa",
    "gn:population":0,
    "gn:timezone":"America/Lima",
    "iso:country":"PE",
    "wof:name":"Totorapampa",
    "wof:placetype":"locality"
},
  "geometry": {"coordinates":[-74.78756,-12.10464],"type":"Point"}
}