{
  "type": "Feature",
  "properties": {
    "gn:admin1_code":"11.0",
    "gn:admin2_code":"1103.0",
    "gn:admin3_code":"110303.0",
    "gn:asciiname":"Papagallo",
    "gn:country_code":"PE",
    "gn:dem":505,
    "gn:feature_class":"P",
    "gn:feature_code":"PPL",
    "gn:name":"Papagallo",
    "gn:population":0,
    "gn:timezone":"America/Lima",
    "iso:country":"PE",
    "name:spa_x_preferred":[
        "Papagallo"
    ],
    "wof:name":"Papagallo",
    "wof:placetype":"locality"
},
  "geometry": {"coordinates":[-75.024,-14.63551],"type":"Point"}
}