{
  "type": "Feature",
  "properties": {
    "gn:admin1_code":"20",
    "gn:admin2_code":"2002.0",
    "gn:admin3_code":"200210.0",
    "gn:asciiname":"La Monja",
    "gn:country_code":"PE",
    "gn:dem":378,
    "gn:feature_class":"P",
    "gn:feature_code":"PPL",
    "gn:name":"La Monja",
    "gn:population":0,
    "gn:timezone":"America/Lima",
    "iso:country":"PE",
    "name:und_x_variant":[
        "Las Monjas",
        "La Monja"
    ],
    "wof:name":"La Monja",
    "wof:placetype":"locality"
},
  "geometry": {"coordinates":[-80.05826999999999,-4.49256],"type":"Point"}
}