{
  "type": "Feature",
  "properties": {
    "gn:admin1_code":"14",
    "gn:admin2_code":"1403.0",
    "gn:admin3_code":"140310.0",
    "gn:asciiname":"El Higueron",
    "gn:country_code":"PE",
    "gn:dem":518,
    "gn:feature_class":"P",
    "gn:feature_code":"PPL",
    "gn:name":"El Higuer\u00f3n",
    "gn:population":0,
    "gn:timezone":"America/Lima",
    "iso:country":"PE",
    "name:und_x_variant":[
        "El Higuer\u00f3n"
    ],
    "wof:name":"El Higueron",
    "wof:placetype":"locality"
},
  "geometry": {"coordinates":[-79.57504,-6.08808],"type":"Point"}
}