{
  "type": "Feature",
  "properties": {
    "iso:country":"PE",
    "name:ast_x_preferred":[
        "Yanahuanca"
    ],
    "name:aym_x_preferred":[
        "Yanawanka"
    ],
    "name:eng_x_preferred":[
        "Yanahuanca"
    ],
    "name:fra_x_preferred":[
        "Yanahuanca"
    ],
    "name:nld_x_preferred":[
        "Yanahuanca"
    ],
    "name:por_x_preferred":[
        "Yanahuanca"
    ],
    "name:que_x_preferred":[
        "Yanawanka"
    ],
    "name:spa_x_preferred":[
        "Yanahuanca"
    ],
    "name:urd_x_preferred":[
        "\u06cc\u0627\u0646\u06c1\u06be\u0627\u0646\u06a9\u0627"
    ],
    "name:war_x_preferred":[
        "Yanahuanca"
    ],
    "name:zho_x_preferred":[
        "\u4e9e\u7d0d\u842c\u5361"
    ],
    "qs:gn_country":"PE",
    "qs:gn_fcode":"PPL",
    "qs:gn_pop":5992,
    "qs:name":"Yanahuanca",
    "qs:name_adm0":"Per\u00fa",
    "qs:name_adm1":"Pasco",
    "qs:photos":0,
    "qs:photos_1k":0,
    "qs:photos_9k":0,
    "qs:photos_9r":0,
    "qs:photos_all":0,
    "qs:photos_sr":0,
    "qs:placetype":"Town",
    "qs:pop_sr":"5",
    "qs:woe_adm0":23424919,
    "wd:elevation":3184.0,
    "wd:wordcount":56,
    "wof:name":"Yanahuanca",
    "wof:placetype":"locality",
    "wof:population":5992
},
  "geometry": {"coordinates":[-76.49861,-10.51667],"type":"Point"}
}