{
  "type": "Feature",
  "properties": {
    "gn:admin1_code":"4",
    "gn:admin2_code":"405.0",
    "gn:admin3_code":"40519.0",
    "gn:asciiname":"Acopecho",
    "gn:country_code":"PE",
    "gn:dem":4719,
    "gn:feature_class":"P",
    "gn:feature_code":"PPL",
    "gn:name":"Acopecho",
    "gn:population":0,
    "gn:timezone":"America/Lima",
    "iso:country":"PE",
    "wof:name":"Acopecho",
    "wof:placetype":"locality"
},
  "geometry": {"coordinates":[-71.24889,-15.68611],"type":"Point"}
}