{
  "type": "Feature",
  "properties": {
    "gn:admin1_code":"20.0",
    "gn:admin2_code":"2002.0",
    "gn:admin3_code":"200201.0",
    "gn:asciiname":"Mangas",
    "gn:country_code":"PE",
    "gn:dem":1986,
    "gn:feature_class":"P",
    "gn:feature_code":"PPL",
    "gn:name":"Mangas",
    "gn:population":0,
    "gn:timezone":"America/Lima",
    "iso:country":"PE",
    "name:ell_x_preferred":[
        "\u039c\u03ac\u03b3\u03ba\u03b1\u03c2"
    ],
    "name:spa_x_preferred":[
        "Mangas"
    ],
    "wof:name":"Mangas",
    "wof:placetype":"locality"
},
  "geometry": {"coordinates":[-79.69719000000001,-4.66755],"type":"Point"}
}