{
  "type": "Feature",
  "properties": {
    "gn:admin1_code":"14.0",
    "gn:admin2_code":"1403.0",
    "gn:admin3_code":"140301.0",
    "gn:asciiname":"El Cortijo",
    "gn:country_code":"PE",
    "gn:dem":20,
    "gn:feature_class":"P",
    "gn:feature_code":"PPL",
    "gn:name":"El Cortijo",
    "gn:population":0,
    "gn:timezone":"America/Lima",
    "iso:country":"PE",
    "name:spa_x_preferred":[
        "El Cortijo"
    ],
    "wof:name":"El Cortijo",
    "wof:placetype":"locality"
},
  "geometry": {"coordinates":[-79.88804,-6.69811],"type":"Point"}
}