{
  "type": "Feature",
  "properties": {
    "gn:admin1_code":"10.0",
    "gn:admin2_code":"1010.0",
    "gn:admin3_code":"101001.0",
    "gn:asciiname":"Pogoj",
    "gn:country_code":"PE",
    "gn:dem":3716,
    "gn:feature_class":"P",
    "gn:feature_code":"PPL",
    "gn:name":"Pogoj",
    "gn:population":0,
    "gn:timezone":"America/Lima",
    "iso:country":"PE",
    "wof:name":"Pogoj",
    "wof:placetype":"locality"
},
  "geometry": {"coordinates":[-76.64806,-10.07611],"type":"Point"}
}