{
  "type": "Feature",
  "properties": {
    "gn:admin1_code":"15.0",
    "gn:admin2_code":"1505.0",
    "gn:admin3_code":"150503.0",
    "gn:asciiname":"Piedra Angosta",
    "gn:country_code":"PE",
    "gn:dem":319,
    "gn:feature_class":"P",
    "gn:feature_code":"PPL",
    "gn:name":"Piedra Angosta",
    "gn:population":0,
    "gn:timezone":"America/Lima",
    "iso:country":"PE",
    "name:spa_x_preferred":[
        "Piedra Angosta"
    ],
    "wof:name":"Piedra Angosta",
    "wof:placetype":"locality"
},
  "geometry": {"coordinates":[-76.58688000000002,-12.54492],"type":"Point"}
}