{
  "type": "Feature",
  "properties": {
    "gn:admin1_code":"15",
    "gn:admin2_code":"1507.0",
    "gn:admin3_code":"150720.0",
    "gn:asciiname":"Pilcocancha",
    "gn:country_code":"PE",
    "gn:dem":4399,
    "gn:feature_class":"P",
    "gn:feature_code":"PPL",
    "gn:name":"Pilcocancha",
    "gn:population":0,
    "gn:timezone":"America/Lima",
    "iso:country":"PE",
    "wof:name":"Pilcocancha",
    "wof:placetype":"locality"
},
  "geometry": {"coordinates":[-76.19360999999998,-11.95333],"type":"Point"}
}