{
  "type": "Feature",
  "properties": {
    "gn:admin1_code":"22.0",
    "gn:admin2_code":"2210.0",
    "gn:asciiname":"Alto Manteca",
    "gn:country_code":"PE",
    "gn:dem":605,
    "gn:feature_class":"P",
    "gn:feature_code":"PPL",
    "gn:name":"Alto Manteca",
    "gn:population":0,
    "gn:timezone":"America/Lima",
    "iso:country":"PE",
    "wof:name":"Alto Manteca",
    "wof:placetype":"locality"
},
  "geometry": {"coordinates":[-76.30523000000002,-8.43382],"type":"Point"}
}