{
  "type": "Feature",
  "properties": {
    "gn:admin1_code":"12.0",
    "gn:admin2_code":"1202.0",
    "gn:admin3_code":"120209.0",
    "gn:asciiname":"Pucarapampa",
    "gn:country_code":"PE",
    "gn:dem":3470,
    "gn:feature_class":"P",
    "gn:feature_code":"PPL",
    "gn:name":"Pucarapampa",
    "gn:population":0,
    "gn:timezone":"America/Lima",
    "iso:country":"PE",
    "wof:name":"Pucarapampa",
    "wof:placetype":"locality"
},
  "geometry": {"coordinates":[-75.11454000000001,-11.6066],"type":"Point"}
}