{
  "type": "Feature",
  "properties": {
    "gn:admin1_code":"14",
    "gn:admin2_code":"1403.0",
    "gn:admin3_code":"140308.0",
    "gn:asciiname":"Laguna Larga",
    "gn:country_code":"PE",
    "gn:dem":110,
    "gn:feature_class":"P",
    "gn:feature_code":"PPL",
    "gn:name":"Laguna Larga",
    "gn:population":0,
    "gn:timezone":"America/Lima",
    "iso:country":"PE",
    "wof:name":"Laguna Larga",
    "wof:placetype":"locality"
},
  "geometry": {"coordinates":[-79.86,-5.86],"type":"Point"}
}