{
  "type": "Feature",
  "properties": {
    "gn:admin1_code":"21",
    "gn:admin2_code":"2103",
    "gn:asciiname":"Chullucunca",
    "gn:country_code":"PE",
    "gn:dem":3833,
    "gn:feature_class":"P",
    "gn:feature_code":"PPL",
    "gn:name":"Chullucunca",
    "gn:population":0,
    "gn:timezone":"America/Lima",
    "iso:country":"PE",
    "name:spa_x_preferred":[
        "Chullucunca"
    ],
    "wof:name":"Chullucunca",
    "wof:placetype":"locality"
},
  "geometry": {"coordinates":[-69.85311,-13.96658],"type":"Point"}
}