{
  "type": "Feature",
  "properties": {
    "gn:admin1_code":"05",
    "gn:admin2_code":"501.0",
    "gn:admin3_code":"50106.0",
    "gn:asciiname":"Pagcha",
    "gn:country_code":"PE",
    "gn:dem":3841,
    "gn:feature_class":"P",
    "gn:feature_code":"PPL",
    "gn:name":"Pagcha",
    "gn:population":0,
    "gn:timezone":"America/Lima",
    "iso:country":"PE",
    "name:und_x_variant":[
        "Paccha",
        "Pagcha"
    ],
    "wof:name":"Pagcha",
    "wof:placetype":"locality"
},
  "geometry": {"coordinates":[-73.94343000000001,-13.36364],"type":"Point"}
}