{
  "type": "Feature",
  "properties": {
    "gn:admin1_code":"15",
    "gn:admin2_code":"1508.0",
    "gn:admin3_code":"150809.0",
    "gn:asciiname":"Yuracchala",
    "gn:country_code":"PE",
    "gn:dem":4708,
    "gn:feature_class":"P",
    "gn:feature_code":"PPL",
    "gn:name":"Yuracchala",
    "gn:population":0,
    "gn:timezone":"America/Lima",
    "iso:country":"PE",
    "wof:name":"Yuracchala",
    "wof:placetype":"locality"
},
  "geometry": {"coordinates":[-76.68472,-11.04167],"type":"Point"}
}