{
  "type": "Feature",
  "properties": {
    "gn:admin1_code":"21",
    "gn:admin2_code":"2105.0",
    "gn:admin3_code":"210504.0",
    "gn:asciiname":"Vilakaya",
    "gn:country_code":"PE",
    "gn:dem":4530,
    "gn:feature_class":"P",
    "gn:feature_code":"PPL",
    "gn:name":"Vilakaya",
    "gn:population":0,
    "gn:timezone":"America/Lima",
    "iso:country":"PE",
    "wof:name":"Vilakaya",
    "wof:placetype":"locality"
},
  "geometry": {"coordinates":[-70.02472,-17.02167],"type":"Point"}
}