{
  "type": "Feature",
  "properties": {
    "gn:admin1_code":"21",
    "gn:admin2_code":"2103.0",
    "gn:admin3_code":"210303.0",
    "gn:asciiname":"Limapampa",
    "gn:country_code":"PE",
    "gn:dem":538,
    "gn:feature_class":"P",
    "gn:feature_code":"PPL",
    "gn:name":"Limapampa",
    "gn:population":0,
    "gn:timezone":"America/Lima",
    "iso:country":"PE",
    "wof:name":"Limapampa",
    "wof:placetype":"locality"
},
  "geometry": {"coordinates":[-70.34999999999999,-13.36667],"type":"Point"}
}