{
  "type": "Feature",
  "properties": {
    "gn:admin1_code":"03",
    "gn:admin2_code":"307.0",
    "gn:admin3_code":"30708.0",
    "gn:asciiname":"Palmadera",
    "gn:country_code":"PE",
    "gn:dem":4137,
    "gn:feature_class":"P",
    "gn:feature_code":"PPL",
    "gn:name":"Palmadera",
    "gn:population":0,
    "gn:timezone":"America/Lima",
    "iso:country":"PE",
    "wof:name":"Palmadera",
    "wof:placetype":"locality"
},
  "geometry": {"coordinates":[-72.40000000000001,-14.18333],"type":"Point"}
}