{
  "type": "Feature",
  "properties": {
    "gn:admin1_code":"15",
    "gn:admin2_code":"1506.0",
    "gn:admin3_code":"150601.0",
    "gn:asciiname":"Quisque Alto",
    "gn:country_code":"PE",
    "gn:dem":880,
    "gn:feature_class":"P",
    "gn:feature_code":"PPL",
    "gn:name":"Quisque Alto",
    "gn:population":0,
    "gn:timezone":"America/Lima",
    "iso:country":"PE",
    "wof:name":"Quisque Alto",
    "wof:placetype":"locality"
},
  "geometry": {"coordinates":[-76.96611,-11.33722],"type":"Point"}
}