{
  "type": "Feature",
  "properties": {
    "gn:admin1_code":"4",
    "gn:admin2_code":"405.0",
    "gn:admin3_code":"40515.0",
    "gn:asciiname":"Janco Amani",
    "gn:country_code":"PE",
    "gn:dem":4559,
    "gn:feature_class":"P",
    "gn:feature_code":"PPL",
    "gn:name":"Janco Amani",
    "gn:population":0,
    "gn:timezone":"America/Lima",
    "iso:country":"PE",
    "wof:name":"Janco Amani",
    "wof:placetype":"locality"
},
  "geometry": {"coordinates":[-71.56944,-15.27667],"type":"Point"}
}