{
  "type": "Feature",
  "properties": {
    "gn:admin1_code":"12.0",
    "gn:admin2_code":"1204.0",
    "gn:admin3_code":"120434.0",
    "gn:asciiname":"Cunas",
    "gn:country_code":"PE",
    "gn:dem":3469,
    "gn:feature_class":"P",
    "gn:feature_code":"PPL",
    "gn:name":"Cu\u00f1as",
    "gn:population":0,
    "gn:timezone":"America/Lima",
    "iso:country":"PE",
    "wof:name":"Cunas",
    "wof:placetype":"locality"
},
  "geometry": {"coordinates":[-75.52811,-11.7963],"type":"Point"}
}