{
  "type": "Feature",
  "properties": {
    "gn:admin1_code":"5.0",
    "gn:admin2_code":"501.0",
    "gn:admin3_code":"50101.0",
    "gn:asciiname":"Los Cabitos",
    "gn:country_code":"PE",
    "gn:dem":2615,
    "gn:feature_class":"P",
    "gn:feature_code":"PPL",
    "gn:name":"Los Cabitos",
    "gn:population":0,
    "gn:timezone":"America/Lima",
    "iso:country":"PE",
    "wof:name":"Los Cabitos",
    "wof:placetype":"locality"
},
  "geometry": {"coordinates":[-74.19866999999998,-13.13943],"type":"Point"}
}