{
  "type": "Feature",
  "properties": {
    "gn:admin1_code":"9",
    "gn:admin2_code":"906.0",
    "gn:admin3_code":"90607.0",
    "gn:asciiname":"Marayayoc",
    "gn:country_code":"PE",
    "gn:dem":4000,
    "gn:feature_class":"P",
    "gn:feature_code":"PPL",
    "gn:name":"Marayayoc",
    "gn:population":0,
    "gn:timezone":"America/Lima",
    "iso:country":"PE",
    "wof:name":"Marayayoc",
    "wof:placetype":"locality"
},
  "geometry": {"coordinates":[-74.81222,-13.62917],"type":"Point"}
}