{
  "type": "Feature",
  "properties": {
    "gn:admin1_code":"9.0",
    "gn:admin2_code":"901.0",
    "gn:admin3_code":"90117.0",
    "gn:asciiname":"Fierro Tacascca",
    "gn:country_code":"PE",
    "gn:dem":4025,
    "gn:feature_class":"P",
    "gn:feature_code":"PPL",
    "gn:name":"Fierro Tacascca",
    "gn:population":0,
    "gn:timezone":"America/Lima",
    "iso:country":"PE",
    "wof:name":"Fierro Tacascca",
    "wof:placetype":"locality"
},
  "geometry": {"coordinates":[-74.80513000000001,-12.74961],"type":"Point"}
}