{
  "type": "Feature",
  "properties": {
    "gn:admin1_code":"8",
    "gn:admin2_code":"805.0",
    "gn:admin3_code":"80501.0",
    "gn:asciiname":"Leguacuna",
    "gn:country_code":"PE",
    "gn:dem":3901,
    "gn:feature_class":"P",
    "gn:feature_code":"PPL",
    "gn:name":"Leguacuna",
    "gn:population":0,
    "gn:timezone":"America/Lima",
    "iso:country":"PE",
    "wof:name":"Leguacuna",
    "wof:placetype":"locality"
},
  "geometry": {"coordinates":[-71.44164000000001,-14.23469],"type":"Point"}
}