{
  "type": "Feature",
  "properties": {
    "gn:admin1_code":"13",
    "gn:admin2_code":"1309.0",
    "gn:admin3_code":"130908.0",
    "gn:asciiname":"San Mateo",
    "gn:country_code":"PE",
    "gn:dem":2741,
    "gn:feature_class":"P",
    "gn:feature_code":"PPL",
    "gn:name":"San Mateo",
    "gn:population":0,
    "gn:timezone":"America/Lima",
    "iso:country":"PE",
    "wof:name":"San Mateo",
    "wof:placetype":"locality"
},
  "geometry": {"coordinates":[-77.73011,-7.68323],"type":"Point"}
}