{
  "type": "Feature",
  "properties": {
    "gn:admin1_code":"19",
    "gn:admin2_code":"1902.0",
    "gn:admin3_code":"190201.0",
    "gn:asciiname":"Chonta",
    "gn:country_code":"PE",
    "gn:dem":4430,
    "gn:feature_class":"P",
    "gn:feature_code":"PPL",
    "gn:name":"Chonta",
    "gn:population":0,
    "gn:timezone":"America/Lima",
    "iso:country":"PE",
    "wof:name":"Chonta",
    "wof:placetype":"locality"
},
  "geometry": {"coordinates":[-76.65886999999999,-10.53671],"type":"Point"}
}