{
  "type": "Feature",
  "properties": {
    "gn:admin1_code":"14",
    "gn:admin2_code":"1401.0",
    "gn:admin3_code":"140117.0",
    "gn:asciiname":"Carretera Patapo",
    "gn:country_code":"PE",
    "gn:dem":115,
    "gn:feature_class":"P",
    "gn:feature_code":"PPL",
    "gn:name":"Carretera Patapo",
    "gn:population":0,
    "gn:timezone":"America/Lima",
    "iso:country":"PE",
    "name:spa_x_preferred":[
        "Carretera Patapo"
    ],
    "wof:name":"Carretera Patapo",
    "wof:placetype":"locality"
},
  "geometry": {"coordinates":[-79.55313000000002,-6.73749],"type":"Point"}
}