{
  "type": "Feature",
  "properties": {
    "gn:admin1_code":"14",
    "gn:admin2_code":"1401.0",
    "gn:admin3_code":"140106.0",
    "gn:asciiname":"Zorro Cote",
    "gn:country_code":"PE",
    "gn:dem":8,
    "gn:feature_class":"P",
    "gn:feature_code":"PPL",
    "gn:name":"Zorro Cote",
    "gn:population":0,
    "gn:timezone":"America/Lima",
    "iso:country":"PE",
    "name:spa_x_preferred":[
        "Zorro Cote"
    ],
    "name:spa_x_variant":[
        "Zorro-Cote",
        "Cote"
    ],
    "wof:name":"Zorro Cote",
    "wof:placetype":"locality"
},
  "geometry": {"coordinates":[-79.90053,-6.85316],"type":"Point"}
}