{
  "type": "Feature",
  "properties": {
    "gn:admin1_code":"21",
    "gn:admin2_code":"2107.0",
    "gn:admin3_code":"210705.0",
    "gn:asciiname":"Pacolaca",
    "gn:country_code":"PE",
    "gn:dem":4821,
    "gn:feature_class":"P",
    "gn:feature_code":"PPL",
    "gn:name":"Pacolaca",
    "gn:population":0,
    "gn:timezone":"America/Lima",
    "iso:country":"PE",
    "wof:name":"Pacolaca",
    "wof:placetype":"locality"
},
  "geometry": {"coordinates":[-70.93644999999999,-15.31274],"type":"Point"}
}