{
  "type": "Feature",
  "properties": {
    "gn:admin1_code":"23",
    "gn:admin2_code":"2304.0",
    "gn:admin3_code":"230401.0",
    "gn:asciiname":"Aichuta Grande",
    "gn:country_code":"PE",
    "gn:dem":4322,
    "gn:feature_class":"P",
    "gn:feature_code":"PPL",
    "gn:name":"Aichuta Grande",
    "gn:population":0,
    "gn:timezone":"America/Lima",
    "iso:country":"PE",
    "name:und_x_variant":[
        "Achuta",
        "Aichuta Grande"
    ],
    "wof:name":"Aichuta Grande",
    "wof:placetype":"locality"
},
  "geometry": {"coordinates":[-69.72586,-17.34816],"type":"Point"}
}