{
  "type": "Feature",
  "properties": {
    "gn:admin1_code":"04",
    "gn:admin2_code":"405.0",
    "gn:admin3_code":"40504.0",
    "gn:asciiname":"Yausa",
    "gn:country_code":"PE",
    "gn:dem":4479,
    "gn:feature_class":"P",
    "gn:feature_code":"PPL",
    "gn:name":"Yausa",
    "gn:population":0,
    "gn:timezone":"America/Lima",
    "iso:country":"PE",
    "wof:name":"Yausa",
    "wof:placetype":"locality"
},
  "geometry": {"coordinates":[-71.47593000000001,-15.59958],"type":"Point"}
}