{
  "type": "Feature",
  "properties": {
    "gn:admin1_code":"4",
    "gn:admin2_code":"404.0",
    "gn:admin3_code":"40408.0",
    "gn:asciiname":"Accota",
    "gn:country_code":"PE",
    "gn:dem":2495,
    "gn:feature_class":"P",
    "gn:feature_code":"PPL",
    "gn:name":"Accota",
    "gn:population":0,
    "gn:timezone":"America/Lima",
    "iso:country":"PE",
    "wof:name":"Accota",
    "wof:placetype":"locality"
},
  "geometry": {"coordinates":[-72.49082,-15.66701],"type":"Point"}
}