{
  "type": "Feature",
  "properties": {
    "gn:admin1_code":"2.0",
    "gn:admin2_code":"218.0",
    "gn:admin3_code":"21808.0",
    "gn:asciiname":"San Remblo",
    "gn:country_code":"PE",
    "gn:dem":26,
    "gn:feature_class":"P",
    "gn:feature_code":"PPL",
    "gn:name":"San Remblo",
    "gn:population":0,
    "gn:timezone":"America/Lima",
    "iso:country":"PE",
    "wof:name":"San Remblo",
    "wof:placetype":"locality"
},
  "geometry": {"coordinates":[-78.60583000000003,-8.97639],"type":"Point"}
}