{
  "type": "Feature",
  "properties": {
    "gn:admin1_code":"12",
    "gn:admin2_code":"1206.0",
    "gn:admin3_code":"120602.0",
    "gn:asciiname":"Coviriali",
    "gn:country_code":"PE",
    "gn:dem":677,
    "gn:feature_class":"P",
    "gn:feature_code":"PPLA3",
    "gn:name":"Coviriali",
    "gn:population":0,
    "gn:timezone":"America/Lima",
    "iso:country":"PE",
    "wof:name":"Coviriali",
    "wof:placetype":"locality"
},
  "geometry": {"coordinates":[-74.6275,-11.2925],"type":"Point"}
}