{
  "type": "Feature",
  "properties": {
    "gn:country":"PE",
    "gn:fcode":"PPL",
    "gn:population":12471,
    "iso:country":"PE",
    "name:ceb_x_preferred":[
        "Pueblo Nuevo"
    ],
    "name:deu_x_preferred":[
        "Pueblo Nuevo"
    ],
    "name:epo_x_preferred":[
        "Pueblo Nuevo"
    ],
    "name:fra_x_preferred":[
        "Pueblo Nuevo"
    ],
    "name:ita_x_preferred":[
        "Pueblo Nuevo"
    ],
    "name:nds_x_preferred":[
        "Pueblo Nuevo"
    ],
    "name:nld_x_preferred":[
        "Pueblo Nuevo"
    ],
    "name:pol_x_preferred":[
        "Pueblo Nuevo"
    ],
    "name:por_x_preferred":[
        "Pueblo Nuevo"
    ],
    "name:rus_x_preferred":[
        "\u041f\u0443\u044d\u0431\u043b\u043e-\u041d\u0443\u044d\u0432\u043e"
    ],
    "name:sco_x_preferred":[
        "Pueblo Nuevo"
    ],
    "name:spa_x_preferred":[
        "Pueblo Nuevo"
    ],
    "name:srp_x_preferred":[
        "\u041f\u0443\u0435\u0431\u043b\u043e \u041d\u0443\u0435\u0432\u043e"
    ],
    "name:swe_x_preferred":[
        "Pueblo Nuevo"
    ],
    "name:vie_x_preferred":[
        "Pueblo Nuevo"
    ],
    "qs:name":"Pueblo Nuevo",
    "qs:photos_9r":0,
    "qs:photos_sr":0,
    "qs:pop_sr":"6",
    "wd:wordcount":106,
    "wof:name":"Pueblo Nuevo",
    "wof:placetype":"locality",
    "wof:population":12471
},
  "geometry": {"coordinates":[-79.88333,-5.71667],"type":"Point"}
}