{
  "type": "Feature",
  "properties": {
    "gn:country":"PE",
    "gn:fcode":"PPL",
    "gn:pop":12471,
    "iso:country":"PE",
    "qs:name":"Pueblo Nuevo",
    "qs:photos_9r":0,
    "qs:photos_sr":0,
    "qs:pop_sr":"6",
    "wd:wordcount":106,
    "wof:name":"Pueblo Nuevo",
    "wof:placetype":"locality",
    "wof:population":12471
},
  "geometry": {"coordinates":[-79.88333,-5.71667],"type":"Point"}
}