{
  "type": "Feature",
  "properties": {
    "gn:admin1_code":"09",
    "gn:admin2_code":"906.0",
    "gn:admin3_code":"90608.0",
    "gn:asciiname":"Yanaocco",
    "gn:country_code":"PE",
    "gn:dem":3391,
    "gn:feature_class":"P",
    "gn:feature_code":"PPL",
    "gn:name":"Yanaocco",
    "gn:population":0,
    "gn:timezone":"America/Lima",
    "iso:country":"PE",
    "name:und_x_variant":[
        "Yanaocc"
    ],
    "wof:name":"Yanaocco",
    "wof:placetype":"locality"
},
  "geometry": {"coordinates":[-74.9145,-13.93466],"type":"Point"}
}