{
  "type": "Feature",
  "properties": {
    "gn:admin1_code":"13",
    "gn:admin2_code":"1309.0",
    "gn:admin3_code":"130905.0",
    "gn:asciiname":"Shalcapata",
    "gn:country_code":"PE",
    "gn:dem":3224,
    "gn:feature_class":"P",
    "gn:feature_code":"PPL",
    "gn:name":"Shalcapata",
    "gn:population":0,
    "gn:timezone":"America/Lima",
    "iso:country":"PE",
    "wof:name":"Shalcapata",
    "wof:placetype":"locality"
},
  "geometry": {"coordinates":[-77.89278,-7.62174],"type":"Point"}
}