{
  "type": "Feature",
  "properties": {
    "gn:admin1_code":"13",
    "gn:admin2_code":"1306.0",
    "gn:admin3_code":"130608.0",
    "gn:asciiname":"Sauco",
    "gn:country_code":"PE",
    "gn:dem":3418,
    "gn:feature_class":"P",
    "gn:feature_code":"PPL",
    "gn:name":"Sauco",
    "gn:population":0,
    "gn:timezone":"America/Lima",
    "iso:country":"PE",
    "wof:name":"Sauco",
    "wof:placetype":"locality"
},
  "geometry": {"coordinates":[-78.5476,-8.05807],"type":"Point"}
}