{
  "type": "Feature",
  "properties": {
    "gn:admin1_code":"11.0",
    "gn:admin2_code":"1101.0",
    "gn:admin3_code":"110102.0",
    "gn:asciiname":"Limon Platanal",
    "gn:country_code":"PE",
    "gn:dem":415,
    "gn:feature_class":"P",
    "gn:feature_code":"PPL",
    "gn:name":"Limon Platanal",
    "gn:population":0,
    "gn:timezone":"America/Lima",
    "iso:country":"PE",
    "name:spa_x_preferred":[
        "Limon Platanal"
    ],
    "wof:name":"Limon Platanal",
    "wof:placetype":"locality"
},
  "geometry": {"coordinates":[-75.72296999999998,-14.03555],"type":"Point"}
}