{
  "type": "Feature",
  "properties": {
    "gn:admin1_code":"8",
    "gn:admin2_code":"805.0",
    "gn:admin3_code":"80501.0",
    "gn:asciiname":"Vaqueria",
    "gn:country_code":"PE",
    "gn:dem":4103,
    "gn:feature_class":"P",
    "gn:feature_code":"PPL",
    "gn:name":"Vaqueria",
    "gn:population":0,
    "gn:timezone":"America/Lima",
    "iso:country":"PE",
    "wof:name":"Vaqueria",
    "wof:placetype":"locality"
},
  "geometry": {"coordinates":[-71.43269000000002,-14.31439],"type":"Point"}
}