{
  "type": "Feature",
  "properties": {
    "gn:admin1_code":"12.0",
    "gn:admin2_code":"1203.0",
    "gn:admin3_code":"120305.0",
    "gn:asciiname":"San Juan de Tulumayo",
    "gn:country_code":"PE",
    "gn:dem":953,
    "gn:feature_class":"P",
    "gn:feature_code":"PPL",
    "gn:name":"San Juan de Tulumayo",
    "gn:population":0,
    "gn:timezone":"America/Lima",
    "iso:country":"PE",
    "wof:name":"San Juan de Tulumayo",
    "wof:placetype":"locality"
},
  "geometry": {"coordinates":[-75.35179000000002,-11.14794],"type":"Point"}
}