{
  "type": "Feature",
  "properties": {
    "gn:admin1_code":"01",
    "gn:admin2_code":"102.0",
    "gn:admin3_code":"10205.0",
    "gn:asciiname":"Indios",
    "gn:country_code":"PE",
    "gn:dem":413,
    "gn:feature_class":"P",
    "gn:feature_code":"PPL",
    "gn:name":"Indios",
    "gn:population":0,
    "gn:timezone":"America/Lima",
    "iso:country":"PE",
    "wof:name":"Indios",
    "wof:placetype":"locality"
},
  "geometry": {"coordinates":[-78.23333000000002,-4.81667],"type":"Point"}
}