{
  "type": "Feature",
  "properties": {
    "gn:admin1_code":"15",
    "gn:admin2_code":"1507.0",
    "gn:admin3_code":"150732.0",
    "gn:asciiname":"Chacra Alta",
    "gn:country_code":"PE",
    "gn:dem":2026,
    "gn:feature_class":"P",
    "gn:feature_code":"PPL",
    "gn:name":"Chacra Alta",
    "gn:population":0,
    "gn:timezone":"America/Lima",
    "iso:country":"PE",
    "wof:name":"Chacra Alta",
    "wof:placetype":"locality"
},
  "geometry": {"coordinates":[-76.44360999999998,-11.88639],"type":"Point"}
}