{
  "type": "Feature",
  "properties": {
    "gn:admin1_code":"05",
    "gn:admin2_code":"506.0",
    "gn:admin3_code":"50609.0",
    "gn:asciiname":"Taral Chico",
    "gn:country_code":"PE",
    "gn:dem":2546,
    "gn:feature_class":"P",
    "gn:feature_code":"PPL",
    "gn:name":"Taral Chico",
    "gn:population":0,
    "gn:timezone":"America/Lima",
    "iso:country":"PE",
    "wof:name":"Taral Chico",
    "wof:placetype":"locality"
},
  "geometry": {"coordinates":[-74.73333000000002,-14.75],"type":"Point"}
}