{
  "type": "Feature",
  "properties": {
    "gn:admin1_code":"10.0",
    "gn:admin2_code":"1009.0",
    "gn:admin3_code":"100905.0",
    "gn:asciiname":"Modenas",
    "gn:country_code":"PE",
    "gn:dem":207,
    "gn:feature_class":"P",
    "gn:feature_code":"PPL",
    "gn:name":"Modenas",
    "gn:population":0,
    "gn:timezone":"America/Lima",
    "iso:country":"PE",
    "name:ara_x_preferred":[
        "\u0645\u0648\u062f\u064a\u0646\u0627\u0633"
    ],
    "name:azb_x_preferred":[
        "\u0645\u0648\u062f\u06cc\u0646\u0627\u0633"
    ],
    "name:fra_x_preferred":[
        "Modenas"
    ],
    "name:ita_x_preferred":[
        "Modenas"
    ],
    "name:jpn_x_preferred":[
        "\u30e2\u30c7\u30ca\u30b9"
    ],
    "name:msa_x_preferred":[
        "Modenas"
    ],
    "name:nld_x_preferred":[
        "Modenas"
    ],
    "name:por_x_preferred":[
        "Modenas"
    ],
    "name:tur_x_preferred":[
        "Modenas"
    ],
    "wof:name":"Modenas",
    "wof:placetype":"locality"
},
  "geometry": {"coordinates":[-74.96965,-9.55874],"type":"Point"}
}