{
  "type": "Feature",
  "properties": {
    "gn:admin1_code":"5.0",
    "gn:admin2_code":"504.0",
    "gn:asciiname":"Chuviviana",
    "gn:country_code":"PE",
    "gn:dem":1146,
    "gn:feature_class":"P",
    "gn:feature_code":"PPL",
    "gn:name":"Chuviviana",
    "gn:population":0,
    "gn:timezone":"America/Lima",
    "iso:country":"PE",
    "wof:name":"Chuviviana",
    "wof:placetype":"locality"
},
  "geometry": {"coordinates":[-73.89335,-12.51837],"type":"Point"}
}