{
  "type": "Feature",
  "properties": {
    "gn:admin1_code":"04",
    "gn:admin2_code":"406.0",
    "gn:admin3_code":"40603.0",
    "gn:asciiname":"Quenco",
    "gn:country_code":"PE",
    "gn:dem":4693,
    "gn:feature_class":"P",
    "gn:feature_code":"PPL",
    "gn:name":"Quenco",
    "gn:population":0,
    "gn:timezone":"America/Lima",
    "iso:country":"PE",
    "name:und_x_variant":[
        "Quimsa Puquio",
        "Quenco"
    ],
    "wof:name":"Quenco",
    "wof:placetype":"locality"
},
  "geometry": {"coordinates":[-72.44565,-15.06254],"type":"Point"}
}