{
  "type": "Feature",
  "properties": {
    "gn:admin1_code":"9",
    "gn:admin2_code":"906.0",
    "gn:admin3_code":"90613.0",
    "gn:asciiname":"Hualisga",
    "gn:country_code":"PE",
    "gn:dem":1589,
    "gn:feature_class":"P",
    "gn:feature_code":"PPL",
    "gn:name":"Hualisga",
    "gn:population":0,
    "gn:timezone":"America/Lima",
    "iso:country":"PE",
    "wof:name":"Hualisga",
    "wof:placetype":"locality"
},
  "geometry": {"coordinates":[-75.43111,-13.78639],"type":"Point"}
}