{
  "type": "Feature",
  "properties": {
    "gn:admin1_code":"1.0",
    "gn:admin2_code":"105.0",
    "gn:admin3_code":"10506.0",
    "gn:asciiname":"Tosan",
    "gn:country_code":"PE",
    "gn:dem":2265,
    "gn:feature_class":"P",
    "gn:feature_code":"PPL",
    "gn:name":"Tosan",
    "gn:population":0,
    "gn:timezone":"America/Lima",
    "iso:country":"PE",
    "wof:name":"Tosan",
    "wof:placetype":"locality"
},
  "geometry": {"coordinates":[-77.98488,-6.26552],"type":"Point"}
}