{
  "type": "Feature",
  "properties": {
    "gn:admin1_code":"12",
    "gn:admin2_code":"1205.0",
    "gn:admin3_code":"120501.0",
    "gn:asciiname":"Chaopicancha",
    "gn:country_code":"PE",
    "gn:dem":4311,
    "gn:feature_class":"P",
    "gn:feature_code":"PPL",
    "gn:name":"Chaopicancha",
    "gn:population":0,
    "gn:timezone":"America/Lima",
    "iso:country":"PE",
    "wof:name":"Chaopicancha",
    "wof:placetype":"locality"
},
  "geometry": {"coordinates":[-75.97469,-11.31429],"type":"Point"}
}