{
  "type": "Feature",
  "properties": {
    "gn:admin1_code":"25",
    "gn:admin2_code":"2504.0",
    "gn:admin3_code":"250401.0",
    "gn:asciiname":"Puerto Estiron de Marcos",
    "gn:country_code":"PE",
    "gn:dem":270,
    "gn:feature_class":"P",
    "gn:feature_code":"PPL",
    "gn:name":"Puerto Estir\u00f3n de Marcos",
    "gn:population":0,
    "gn:timezone":"America/Lima",
    "iso:country":"PE",
    "wof:name":"Puerto Estiron de Marcos",
    "wof:placetype":"locality"
},
  "geometry": {"coordinates":[-70.90000000000001,-9.93333],"type":"Point"}
}