{
  "type": "Feature",
  "properties": {
    "gn:admin1_code":"8.0",
    "gn:admin2_code":"803.0",
    "gn:admin3_code":"80309.0",
    "gn:asciiname":"Rahuanqui",
    "gn:country_code":"PE",
    "gn:dem":3319,
    "gn:feature_class":"P",
    "gn:feature_code":"PPLL",
    "gn:name":"Rahuanqui",
    "gn:population":0,
    "gn:timezone":"America/Lima",
    "iso:country":"PE",
    "wof:name":"Rahuanqui",
    "wof:placetype":"locality"
},
  "geometry": {"coordinates":[-72.23083000000003,-13.44944],"type":"Point"}
}