{
  "type": "Feature",
  "properties": {
    "gn:admin1_code":"08",
    "gn:admin2_code":"813.0",
    "gn:admin3_code":"81307.0",
    "gn:asciiname":"Yucay",
    "gn:country_code":"PE",
    "gn:dem":2856,
    "gn:feature_class":"P",
    "gn:feature_code":"PPLA3",
    "gn:name":"Yucay",
    "gn:population":0,
    "gn:timezone":"America/Lima",
    "iso:country":"PE",
    "name:que_x_preferred":[
        "Yukay"
    ],
    "name:spa_x_preferred":[
        "Yucay"
    ],
    "name:urd_x_preferred":[
        "\u06cc\u0648\u06a9\u06d2"
    ],
    "wof:name":"Yucay",
    "wof:placetype":"locality"
},
  "geometry": {"coordinates":[-72.08221999999998,-13.32139],"type":"Point"}
}