{
  "type": "Feature",
  "properties": {
    "gn:admin1_code":"02",
    "gn:admin2_code":"205.0",
    "gn:admin3_code":"20509.0",
    "gn:asciiname":"Punta Huayi",
    "gn:country_code":"PE",
    "gn:dem":4224,
    "gn:feature_class":"P",
    "gn:feature_code":"PPL",
    "gn:name":"Punta Huayi",
    "gn:population":0,
    "gn:timezone":"America/Lima",
    "iso:country":"PE",
    "wof:name":"Punta Huayi",
    "wof:placetype":"locality"
},
  "geometry": {"coordinates":[-76.99587,-10.04347],"type":"Point"}
}