{
  "type": "Feature",
  "properties": {
    "gn:admin1_code":"9.0",
    "gn:admin2_code":"907.0",
    "gn:admin3_code":"90701.0",
    "gn:asciiname":"Mulacorral",
    "gn:country_code":"PE",
    "gn:dem":4007,
    "gn:feature_class":"P",
    "gn:feature_code":"PPL",
    "gn:name":"Mulacorral",
    "gn:population":0,
    "gn:timezone":"America/Lima",
    "iso:country":"PE",
    "wof:name":"Mulacorral",
    "wof:placetype":"locality"
},
  "geometry": {"coordinates":[-74.84980999999998,-12.45166],"type":"Point"}
}