{
  "type": "Feature",
  "properties": {
    "gn:admin1_code":"8",
    "gn:admin2_code":"806.0",
    "gn:admin3_code":"80602.0",
    "gn:asciiname":"Puyno Mocco",
    "gn:country_code":"PE",
    "gn:dem":4675,
    "gn:feature_class":"P",
    "gn:feature_code":"PPL",
    "gn:name":"Puyno Mocco",
    "gn:population":0,
    "gn:timezone":"America/Lima",
    "iso:country":"PE",
    "wof:name":"Puyno Mocco",
    "wof:placetype":"locality"
},
  "geometry": {"coordinates":[-71.0175,-14.01],"type":"Point"}
}