{
  "type": "Feature",
  "properties": {
    "gn:admin1_code":"13",
    "gn:admin2_code":"1309.0",
    "gn:admin3_code":"130908.0",
    "gn:asciiname":"Pucara",
    "gn:country_code":"PE",
    "gn:dem":1250,
    "gn:feature_class":"P",
    "gn:feature_code":"PPL",
    "gn:name":"Pucar\u00e1",
    "gn:population":0,
    "gn:timezone":"America/Lima",
    "iso:country":"PE",
    "name:und_x_variant":[
        "Pauca",
        "Pucar\u00e1"
    ],
    "wof:name":"Pucara",
    "wof:placetype":"locality"
},
  "geometry": {"coordinates":[-77.84588000000002,-7.51822],"type":"Point"}
}