{
  "type": "Feature",
  "properties": {
    "gn:admin1_code":"02",
    "gn:admin2_code":"217.0",
    "gn:admin3_code":"21705.0",
    "gn:asciiname":"Chaucayan",
    "gn:country_code":"PE",
    "gn:dem":1395,
    "gn:feature_class":"P",
    "gn:feature_code":"PPL",
    "gn:name":"Chaucayan",
    "gn:population":0,
    "gn:timezone":"America/Lima",
    "iso:country":"PE",
    "wof:name":"Chaucayan",
    "wof:placetype":"locality"
},
  "geometry": {"coordinates":[-77.54841,-10.1812],"type":"Point"}
}