{
  "type": "Feature",
  "properties": {
    "gn:admin1_code":"21",
    "gn:admin2_code":"2103.0",
    "gn:admin3_code":"210310.0",
    "gn:asciiname":"Jacantara",
    "gn:country_code":"PE",
    "gn:dem":3028,
    "gn:feature_class":"P",
    "gn:feature_code":"PPL",
    "gn:name":"Jacantara",
    "gn:population":0,
    "gn:timezone":"America/Lima",
    "iso:country":"PE",
    "wof:name":"Jacantara",
    "wof:placetype":"locality"
},
  "geometry": {"coordinates":[-69.86310999999999,-14.11889],"type":"Point"}
}