{
  "type": "Feature",
  "properties": {
    "gn:admin1_code":"21.0",
    "gn:admin2_code":"2112.0",
    "gn:asciiname":"Chiquito Masiapo",
    "gn:country_code":"PE",
    "gn:dem":1515,
    "gn:feature_class":"P",
    "gn:feature_code":"PPL",
    "gn:name":"Chiquito Masiapo",
    "gn:population":0,
    "gn:timezone":"America/Lima",
    "iso:country":"PE",
    "name:spa_x_preferred":[
        "Chiquito Masiapo"
    ],
    "wof:name":"Chiquito Masiapo",
    "wof:placetype":"locality"
},
  "geometry": {"coordinates":[-69.25986999999999,-14.09075],"type":"Point"}
}