{
  "type": "Feature",
  "properties": {
    "gn:admin1_code":"1",
    "gn:admin2_code":"105.0",
    "gn:admin3_code":"10513.0",
    "gn:asciiname":"Collonce",
    "gn:country_code":"PE",
    "gn:dem":1834,
    "gn:feature_class":"P",
    "gn:feature_code":"PPLA3",
    "gn:name":"Collonce",
    "gn:population":0,
    "gn:timezone":"America/Lima",
    "iso:country":"PE",
    "wof:name":"Collonce",
    "wof:placetype":"locality"
},
  "geometry": {"coordinates":[-78.21278000000002,-6.28111],"type":"Point"}
}