{
  "type": "Feature",
  "properties": {
    "gn:admin1_code":"05",
    "gn:admin2_code":"501.0",
    "gn:admin3_code":"50113.0",
    "gn:asciiname":"Raimina",
    "gn:country_code":"PE",
    "gn:dem":3149,
    "gn:feature_class":"P",
    "gn:feature_code":"PPL",
    "gn:name":"Raimina",
    "gn:population":0,
    "gn:timezone":"America/Lima",
    "iso:country":"PE",
    "name:und_x_variant":[
        "Hacienda Raimina"
    ],
    "wof:name":"Raimina",
    "wof:placetype":"locality"
},
  "geometry": {"coordinates":[-74.14924000000001,-13.21984],"type":"Point"}
}