{
  "type": "Feature",
  "properties": {
    "gn:admin1_code":"20",
    "gn:admin2_code":"2006.0",
    "gn:admin3_code":"200607.0",
    "gn:asciiname":"Santa Victoria",
    "gn:country_code":"PE",
    "gn:dem":92,
    "gn:feature_class":"P",
    "gn:feature_code":"PPL",
    "gn:name":"Santa Victoria",
    "gn:population":0,
    "gn:timezone":"America/Lima",
    "iso:country":"PE",
    "name:spa_x_preferred":[
        "Santa Victoria"
    ],
    "wof:name":"Santa Victoria",
    "wof:placetype":"locality"
},
  "geometry": {"coordinates":[-80.56270000000001,-4.68983],"type":"Point"}
}