{
  "type": "Feature",
  "properties": {
    "gn:admin1_code":"05",
    "gn:admin2_code":"501.0",
    "gn:admin3_code":"50105.0",
    "gn:asciiname":"Paucho",
    "gn:country_code":"PE",
    "gn:dem":3774,
    "gn:feature_class":"P",
    "gn:feature_code":"PPL",
    "gn:name":"Paucho",
    "gn:population":0,
    "gn:timezone":"America/Lima",
    "iso:country":"PE",
    "name:und_x_variant":[
        "Hacienda Paucho"
    ],
    "wof:name":"Paucho",
    "wof:placetype":"locality"
},
  "geometry": {"coordinates":[-74.26149000000002,-13.28599],"type":"Point"}
}