{
  "type": "Feature",
  "properties": {
    "gn:admin1_code":"04",
    "gn:admin2_code":"405.0",
    "gn:admin3_code":"40518.0",
    "gn:asciiname":"Lagrampampa",
    "gn:country_code":"PE",
    "gn:dem":4216,
    "gn:feature_class":"P",
    "gn:feature_code":"PPL",
    "gn:name":"Lagrampampa",
    "gn:population":0,
    "gn:timezone":"America/Lima",
    "iso:country":"PE",
    "wof:name":"Lagrampampa",
    "wof:placetype":"locality"
},
  "geometry": {"coordinates":[-71.55989,-15.4853],"type":"Point"}
}