{
  "type": "Feature",
  "properties": {
    "gn:admin1_code":"13",
    "gn:admin2_code":"1302.0",
    "gn:admin3_code":"130204.0",
    "gn:asciiname":"La Cuadra",
    "gn:country_code":"PE",
    "gn:dem":42,
    "gn:feature_class":"P",
    "gn:feature_code":"PPL",
    "gn:name":"La Cuadra",
    "gn:population":0,
    "gn:timezone":"America/Lima",
    "iso:country":"PE",
    "name:spa_x_preferred":[
        "La Cuadra"
    ],
    "name:urd_x_preferred":[
        "\u0644\u0627 \u06a9\u0648\u0627\u0688\u0631\u0627"
    ],
    "wof:name":"La Cuadra",
    "wof:placetype":"locality"
},
  "geometry": {"coordinates":[-79.28586999999997,-7.85461],"type":"Point"}
}