{
  "type": "Feature",
  "properties": {
    "gn:admin1_code":"15",
    "gn:admin2_code":"1507.0",
    "gn:admin3_code":"150702.0",
    "gn:asciiname":"Chamana",
    "gn:country_code":"PE",
    "gn:dem":1515,
    "gn:feature_class":"P",
    "gn:feature_code":"PPL",
    "gn:name":"Chamana",
    "gn:population":0,
    "gn:timezone":"America/Lima",
    "iso:country":"PE",
    "wof:name":"Chamana",
    "wof:placetype":"locality"
},
  "geometry": {"coordinates":[-76.53333000000001,-12.06667],"type":"Point"}
}