{
  "type": "Feature",
  "properties": {
    "gn:admin1_code":"4.0",
    "gn:admin2_code":"405.0",
    "gn:admin3_code":"40508.0",
    "gn:asciiname":"Arayquipa",
    "gn:country_code":"PE",
    "gn:dem":3236,
    "gn:feature_class":"P",
    "gn:feature_code":"PPL",
    "gn:name":"Arayquipa",
    "gn:population":0,
    "gn:timezone":"America/Lima",
    "iso:country":"PE",
    "wof:name":"Arayquipa",
    "wof:placetype":"locality"
},
  "geometry": {"coordinates":[-71.83663,-16.03944],"type":"Point"}
}