{
  "type": "Feature",
  "properties": {
    "gn:admin1_code":"21",
    "gn:admin2_code":"2104.0",
    "gn:admin3_code":"210406.0",
    "gn:asciiname":"Huacani",
    "gn:country_code":"PE",
    "gn:dem":3873,
    "gn:feature_class":"P",
    "gn:feature_code":"PPL",
    "gn:name":"Huacani",
    "gn:population":0,
    "gn:timezone":"America/Lima",
    "iso:country":"PE",
    "wof:name":"Huacani",
    "wof:placetype":"locality"
},
  "geometry": {"coordinates":[-69.32771,-16.28308],"type":"Point"}
}