{
  "type": "Feature",
  "properties": {
    "gn:admin1_code":"8",
    "gn:admin2_code":"808.0",
    "gn:admin3_code":"80803.0",
    "gn:asciiname":"Chapicha",
    "gn:country_code":"PE",
    "gn:dem":4635,
    "gn:feature_class":"P",
    "gn:feature_code":"PPL",
    "gn:name":"Chapicha",
    "gn:population":0,
    "gn:timezone":"America/Lima",
    "iso:country":"PE",
    "wof:name":"Chapicha",
    "wof:placetype":"locality"
},
  "geometry": {"coordinates":[-71.84416999999998,-14.83417],"type":"Point"}
}