{
  "type": "Feature",
  "properties": {
    "gn:admin1_code":"17.0",
    "gn:admin2_code":"1703.0",
    "gn:asciiname":"Alto Belgica",
    "gn:country_code":"PE",
    "gn:dem":265,
    "gn:feature_class":"P",
    "gn:feature_code":"PPL",
    "gn:name":"Alto Belgica",
    "gn:population":0,
    "gn:timezone":"America/Lima",
    "iso:country":"PE",
    "name:spa_x_preferred":[
        "Alto Belgica"
    ],
    "wof:name":"Alto Belgica",
    "wof:placetype":"locality"
},
  "geometry": {"coordinates":[-69.75,-10.96985],"type":"Point"}
}