{
  "type": "Feature",
  "properties": {
    "gn:admin1_code":"04",
    "gn:admin2_code":"405.0",
    "gn:admin3_code":"40504.0",
    "gn:asciiname":"Marquichahue",
    "gn:country_code":"PE",
    "gn:dem":4344,
    "gn:feature_class":"P",
    "gn:feature_code":"PPL",
    "gn:name":"Marquichahue",
    "gn:population":0,
    "gn:timezone":"America/Lima",
    "iso:country":"PE",
    "wof:name":"Marquichahue",
    "wof:placetype":"locality"
},
  "geometry": {"coordinates":[-71.27944000000002,-15.45972],"type":"Point"}
}