{
  "type": "Feature",
  "properties": {
    "gn:admin1_code":"06",
    "gn:admin2_code":"604.0",
    "gn:admin3_code":"60415.0",
    "gn:asciiname":"Ayabamba",
    "gn:country_code":"PE",
    "gn:dem":1991,
    "gn:feature_class":"P",
    "gn:feature_code":"PPL",
    "gn:name":"Ayabamba",
    "gn:population":0,
    "gn:timezone":"America/Lima",
    "iso:country":"PE",
    "wof:name":"Ayabamba",
    "wof:placetype":"locality"
},
  "geometry": {"coordinates":[-79.10361999999998,-6.34002],"type":"Point"}
}