{
  "type": "Feature",
  "properties": {
    "gn:admin1_code":"10.0",
    "gn:admin2_code":"1005.0",
    "gn:asciiname":"Pilluy",
    "gn:country_code":"PE",
    "gn:dem":4471,
    "gn:feature_class":"P",
    "gn:feature_code":"PPL",
    "gn:name":"Pilluy",
    "gn:population":0,
    "gn:timezone":"America/Lima",
    "iso:country":"PE",
    "wof:name":"Pilluy",
    "wof:placetype":"locality"
},
  "geometry": {"coordinates":[-76.98100000000002,-9.5763],"type":"Point"}
}