{
  "type": "Feature",
  "properties": {
    "gn:admin1_code":"12",
    "gn:admin2_code":"1208.0",
    "gn:admin3_code":"120803.0",
    "gn:asciiname":"Pisgus",
    "gn:country_code":"PE",
    "gn:dem":4428,
    "gn:feature_class":"P",
    "gn:feature_code":"PPL",
    "gn:name":"Pisgus",
    "gn:population":0,
    "gn:timezone":"America/Lima",
    "iso:country":"PE",
    "wof:name":"Pisgus",
    "wof:placetype":"locality"
},
  "geometry": {"coordinates":[-76.01306,-11.74389],"type":"Point"}
}