{
  "type": "Feature",
  "properties": {
    "gn:admin1_code":"20",
    "gn:admin2_code":"2006.0",
    "gn:admin3_code":"200605.0",
    "gn:asciiname":"Salados",
    "gn:country_code":"PE",
    "gn:dem":469,
    "gn:feature_class":"P",
    "gn:feature_code":"PPL",
    "gn:name":"Salados",
    "gn:population":0,
    "gn:timezone":"America/Lima",
    "iso:country":"PE",
    "name:spa_x_preferred":[
        "Salados"
    ],
    "wof:name":"Salados",
    "wof:placetype":"locality"
},
  "geometry": {"coordinates":[-80.76778,-4.48076],"type":"Point"}
}