{
  "type": "Feature",
  "properties": {
    "gn:admin1_code":"13",
    "gn:admin2_code":"1309.0",
    "gn:admin3_code":"130907.0",
    "gn:asciiname":"Hacienda Moyan",
    "gn:country_code":"PE",
    "gn:dem":2726,
    "gn:feature_class":"P",
    "gn:feature_code":"PPL",
    "gn:name":"Hacienda Moyan",
    "gn:population":0,
    "gn:timezone":"America/Lima",
    "iso:country":"PE",
    "name:und_x_variant":[
        "Moyan",
        "Hacienda Moyan"
    ],
    "wof:name":"Hacienda Moyan",
    "wof:placetype":"locality"
},
  "geometry": {"coordinates":[-77.92336999999998,-7.88475],"type":"Point"}
}