{
  "type": "Feature",
  "properties": {
    "gn:admin1_code":"6.0",
    "gn:admin2_code":"605.0",
    "gn:admin3_code":"60503.0",
    "gn:asciiname":"Lluladon",
    "gn:country_code":"PE",
    "gn:dem":2486,
    "gn:feature_class":"P",
    "gn:feature_code":"PPL",
    "gn:name":"Llulad\u00f3n",
    "gn:population":0,
    "gn:timezone":"America/Lima",
    "iso:country":"PE",
    "name:spa_x_preferred":[
        "Llulad\u00f3n"
    ],
    "wof:name":"Lluladon",
    "wof:placetype":"locality"
},
  "geometry": {"coordinates":[-79.00400999999999,-7.38005],"type":"Point"}
}