{
  "type": "Feature",
  "properties": {
    "gn:admin1_code":"15",
    "gn:admin2_code":"1506.0",
    "gn:admin3_code":"150607.0",
    "gn:asciiname":"Raure",
    "gn:cc2":"PE",
    "gn:country_code":"PE",
    "gn:dem":1300,
    "gn:feature_class":"P",
    "gn:feature_code":"PPL",
    "gn:name":"Raure",
    "gn:population":0,
    "gn:timezone":"America/Lima",
    "iso:country":"PE",
    "name:und_x_variant":[
        "Raure Hacienda",
        "Raure"
    ],
    "wof:name":"Raure",
    "wof:placetype":"locality"
},
  "geometry": {"coordinates":[-76.85611,-11.30056],"type":"Point"}
}