{
  "type": "Feature",
  "properties": {
    "gn:admin1_code":"20",
    "gn:admin2_code":"2002.0",
    "gn:admin3_code":"200210.0",
    "gn:asciiname":"Guineo",
    "gn:country_code":"PE",
    "gn:dem":612,
    "gn:feature_class":"P",
    "gn:feature_code":"PPL",
    "gn:name":"Guineo",
    "gn:population":0,
    "gn:timezone":"America/Lima",
    "iso:country":"PE",
    "wof:name":"Guineo",
    "wof:placetype":"locality"
},
  "geometry": {"coordinates":[-79.89449,-4.49296],"type":"Point"}
}