{
  "type": "Feature",
  "properties": {
    "gn:admin1_code":"04",
    "gn:admin2_code":"405.0",
    "gn:admin3_code":"40517.0",
    "gn:asciiname":"Maqueruyo",
    "gn:country_code":"PE",
    "gn:dem":4462,
    "gn:feature_class":"P",
    "gn:feature_code":"PPL",
    "gn:name":"Maqueruyo",
    "gn:population":0,
    "gn:timezone":"America/Lima",
    "iso:country":"PE",
    "wof:name":"Maqueruyo",
    "wof:placetype":"locality"
},
  "geometry": {"coordinates":[-71.27540999999999,-15.18123],"type":"Point"}
}