{
  "type": "Feature",
  "properties": {
    "gn:admin1_code":"05",
    "gn:admin2_code":"507.0",
    "gn:admin3_code":"50705.0",
    "gn:asciiname":"Trigoloma",
    "gn:country_code":"PE",
    "gn:dem":2860,
    "gn:feature_class":"P",
    "gn:feature_code":"PPL",
    "gn:name":"Trigoloma",
    "gn:population":0,
    "gn:timezone":"America/Lima",
    "iso:country":"PE",
    "name:spa_x_preferred":[
        "Trigoloma"
    ],
    "wof:name":"Trigoloma",
    "wof:placetype":"locality"
},
  "geometry": {"coordinates":[-73.86469,-15.18437],"type":"Point"}
}