{
  "type": "Feature",
  "properties": {
    "gn:admin1_code":"4.0",
    "gn:admin2_code":"401.0",
    "gn:admin3_code":"40128.0",
    "gn:asciiname":"Chacra Nueva",
    "gn:country_code":"PE",
    "gn:dem":2681,
    "gn:feature_class":"P",
    "gn:feature_code":"PPL",
    "gn:name":"Chacra Nueva",
    "gn:population":0,
    "gn:timezone":"America/Lima",
    "iso:country":"PE",
    "wof:name":"Chacra Nueva",
    "wof:placetype":"locality"
},
  "geometry": {"coordinates":[-71.69484,-16.209],"type":"Point"}
}