{
  "type": "Feature",
  "properties": {
    "gn:admin1_code":"15",
    "gn:admin2_code":"1504.0",
    "gn:admin3_code":"150407.0",
    "gn:asciiname":"Huanchipuquio",
    "gn:country_code":"PE",
    "gn:dem":619,
    "gn:feature_class":"P",
    "gn:feature_code":"PPL",
    "gn:name":"Huanchipuquio",
    "gn:population":0,
    "gn:timezone":"America/Lima",
    "iso:country":"PE",
    "name:und_x_variant":[
        "Huanchipuquio Hacienda",
        "Huanchipuquio"
    ],
    "wof:name":"Huanchipuquio",
    "wof:placetype":"locality"
},
  "geometry": {"coordinates":[-76.94028,-11.70674],"type":"Point"}
}