{
  "type": "Feature",
  "properties": {
    "gn:admin1_code":"22.0",
    "gn:admin2_code":"2207.0",
    "gn:admin3_code":"220701.0",
    "gn:asciiname":"Filadelfia",
    "gn:country_code":"PE",
    "gn:dem":264,
    "gn:feature_class":"P",
    "gn:feature_code":"PPL",
    "gn:name":"Filadelfia",
    "gn:population":0,
    "gn:timezone":"America/Lima",
    "iso:country":"PE",
    "name:ara_x_preferred":[
        "\u0641\u064a\u0644\u0627\u062f\u0644\u0641\u064a\u0627"
    ],
    "name:cat_x_preferred":[
        "Filad\u00e8lfia"
    ],
    "name:deu_x_preferred":[
        "Filadelfia"
    ],
    "name:epo_x_preferred":[
        "Filadelfio"
    ],
    "name:eus_x_preferred":[
        "Filadelfia"
    ],
    "name:fas_x_preferred":[
        "\u0641\u06cc\u0644\u0627\u062f\u0644\u0641\u06cc\u0627"
    ],
    "name:fin_x_preferred":[
        "Filadelfia"
    ],
    "name:fra_x_preferred":[
        "Filadelfia"
    ],
    "name:grn_x_preferred":[
        "Filadelfia"
    ],
    "name:heb_x_preferred":[
        "\u05e4\u05d9\u05dc\u05d3\u05dc\u05e4\u05d9\u05d4"
    ],
    "name:hun_x_preferred":[
        "Filadelfia"
    ],
    "name:ita_x_preferred":[
        "Filadelfia"
    ],
    "name:jpn_x_preferred":[
        "\u30d5\u30a3\u30e9\u30c7\u30eb\u30d5\u30a3\u30a2"
    ],
    "name:kat_x_preferred":[
        "\u10e4\u10d8\u10da\u10d0\u10d3\u10d4\u10da\u10e4\u10d8\u10d0"
    ],
    "name:kor_x_preferred":[
        "\ud544\ub77c\ub378\ud53c\uc544"
    ],
    "name:lit_x_preferred":[
        "Filadelfija"
    ],
    "name:nld_x_preferred":[
        "Filadelfia"
    ],
    "name:pdc_x_preferred":[
        "Filadelfia"
    ],
    "name:pol_x_preferred":[
        "Filadelfia"
    ],
    "name:por_x_preferred":[
        "Filadelfia"
    ],
    "name:ron_x_preferred":[
        "Filadelfia"
    ],
    "name:rus_x_preferred":[
        "\u0424\u0438\u043b\u0430\u0434\u0435\u043b\u044c\u0444\u0438\u044f"
    ],
    "name:sco_x_preferred":[
        "Filadelfia"
    ],
    "name:spa_x_preferred":[
        "Filadelfia"
    ],
    "name:ukr_x_preferred":[
        "\u0424\u0456\u043b\u0430\u0434\u0435\u043b\u044c\u0444\u0456\u044f"
    ],
    "name:urd_x_preferred":[
        "\u0641\u06cc\u0644\u0627\u062f\u06cc\u0644\u0641\u06cc\u0627"
    ],
    "name:war_x_preferred":[
        "Filadelfia"
    ],
    "wof:name":"Filadelfia",
    "wof:placetype":"locality"
},
  "geometry": {"coordinates":[-76.34098,-6.91868],"type":"Point"}
}