{
  "type": "Feature",
  "properties": {
    "gn:admin1_code":"10",
    "gn:admin2_code":"1002.0",
    "gn:admin3_code":"100205.0",
    "gn:asciiname":"Cochachincha",
    "gn:country_code":"PE",
    "gn:dem":2178,
    "gn:feature_class":"P",
    "gn:feature_code":"PPL",
    "gn:name":"Cochachincha",
    "gn:population":0,
    "gn:timezone":"America/Lima",
    "iso:country":"PE",
    "wof:name":"Cochachincha",
    "wof:placetype":"locality"
},
  "geometry": {"coordinates":[-76.24198,-10.21046],"type":"Point"}
}