{
  "type": "Feature",
  "properties": {
    "gn:admin1_code":"4",
    "gn:admin2_code":"404.0",
    "gn:admin3_code":"40410.0",
    "gn:asciiname":"Ruruca",
    "gn:country_code":"PE",
    "gn:dem":2848,
    "gn:feature_class":"P",
    "gn:feature_code":"PPL",
    "gn:name":"Ruruca",
    "gn:population":0,
    "gn:timezone":"America/Lima",
    "iso:country":"PE",
    "wof:name":"Ruruca",
    "wof:placetype":"locality"
},
  "geometry": {"coordinates":[-72.54795,-15.7259],"type":"Point"}
}