{
  "type": "Feature",
  "properties": {
    "gn:admin1_code":"06",
    "gn:admin2_code":"602.0",
    "gn:admin3_code":"60202.0",
    "gn:asciiname":"San Francisco",
    "gn:country_code":"PE",
    "gn:dem":3111,
    "gn:feature_class":"P",
    "gn:feature_code":"PPL",
    "gn:name":"San Francisco",
    "gn:population":0,
    "gn:timezone":"America/Lima",
    "iso:country":"PE",
    "wof:name":"San Francisco",
    "wof:placetype":"locality"
},
  "geometry": {"coordinates":[-78.25060000000001,-7.47146],"type":"Point"}
}