{
  "type": "Feature",
  "properties": {
    "gn:admin1_code":"17.0",
    "gn:admin2_code":"1703.0",
    "gn:asciiname":"Baturita",
    "gn:country_code":"PE",
    "gn:dem":260,
    "gn:feature_class":"P",
    "gn:feature_code":"PPL",
    "gn:name":"Baturita",
    "gn:population":0,
    "gn:timezone":"America/Lima",
    "iso:country":"PE",
    "name:spa_x_preferred":[
        "Baturita"
    ],
    "wof:name":"Baturita",
    "wof:placetype":"locality"
},
  "geometry": {"coordinates":[-69.58610999999999,-11.01311],"type":"Point"}
}