{
  "type": "Feature",
  "properties": {
    "gn:admin1_code":"4",
    "gn:admin2_code":"403.0",
    "gn:admin3_code":"40308.0",
    "gn:asciiname":"Andenes",
    "gn:country_code":"PE",
    "gn:dem":568,
    "gn:feature_class":"P",
    "gn:feature_code":"PPL",
    "gn:name":"Andenes",
    "gn:population":0,
    "gn:timezone":"America/Lima",
    "iso:country":"PE",
    "name:bul_x_preferred":[
        "\u0410\u043d\u0434\u0435\u043d\u0435\u0441"
    ],
    "name:cat_x_preferred":[
        "Andenes"
    ],
    "name:ceb_x_preferred":[
        "Andenes"
    ],
    "name:dan_x_preferred":[
        "Andenes"
    ],
    "name:deu_x_preferred":[
        "Andenes"
    ],
    "name:fas_x_preferred":[
        "\u0627\u0646\u062f\u06cc\u0646\u0633"
    ],
    "name:fra_x_preferred":[
        "Andenes"
    ],
    "name:hye_x_preferred":[
        "\u0531\u0576\u0564\u0565\u0576\u0565\u057d"
    ],
    "name:ita_x_preferred":[
        "Andenes"
    ],
    "name:jav_x_preferred":[
        "Andenes"
    ],
    "name:msa_x_preferred":[
        "Andenes"
    ],
    "name:nld_x_preferred":[
        "Andenes"
    ],
    "name:nno_x_preferred":[
        "Andenes"
    ],
    "name:nor_x_preferred":[
        "Andenes"
    ],
    "name:pol_x_preferred":[
        "Andenes"
    ],
    "name:por_x_preferred":[
        "Andenes"
    ],
    "name:ron_x_preferred":[
        "Andenes"
    ],
    "name:rus_x_preferred":[
        "\u0410\u043d\u0434\u0435\u043d\u0435\u0441"
    ],
    "name:spa_x_preferred":[
        "Andenes"
    ],
    "name:swe_x_preferred":[
        "Andenes"
    ],
    "name:zho_x_preferred":[
        "\u5b89\u5fb7\u5167\u65af"
    ],
    "wof:name":"Andenes",
    "wof:placetype":"locality"
},
  "geometry": {"coordinates":[-73.97333,-15.80417],"type":"Point"}
}