{
  "type": "Feature",
  "properties": {
    "gn:admin1_code":"4",
    "gn:admin2_code":"403.0",
    "gn:admin3_code":"40308.0",
    "gn:asciiname":"Andenes",
    "gn:country_code":"PE",
    "gn:dem":568,
    "gn:feature_class":"P",
    "gn:feature_code":"PPL",
    "gn:name":"Andenes",
    "gn:population":0,
    "gn:timezone":"America/Lima",
    "iso:country":"PE",
    "wof:name":"Andenes",
    "wof:placetype":"locality"
},
  "geometry": {"coordinates":[-73.97333,-15.80417],"type":"Point"}
}