{
  "type": "Feature",
  "properties": {
    "gn:admin1_code":"5",
    "gn:admin2_code":"511.0",
    "gn:admin3_code":"51101.0",
    "gn:asciiname":"Asno Pacana",
    "gn:country_code":"PE",
    "gn:dem":3709,
    "gn:feature_class":"P",
    "gn:feature_code":"PPL",
    "gn:name":"Asno Pacana",
    "gn:population":0,
    "gn:timezone":"America/Lima",
    "iso:country":"PE",
    "wof:name":"Asno Pacana",
    "wof:placetype":"locality"
},
  "geometry": {"coordinates":[-73.91846,-13.69686],"type":"Point"}
}