{
  "type": "Feature",
  "properties": {
    "gn:admin1_code":"9.0",
    "gn:admin2_code":"906.0",
    "gn:admin3_code":"90607.0",
    "gn:asciiname":"Pumarangra",
    "gn:country_code":"PE",
    "gn:dem":4368,
    "gn:feature_class":"P",
    "gn:feature_code":"PPL",
    "gn:name":"Pumarangra",
    "gn:population":0,
    "gn:timezone":"America/Lima",
    "iso:country":"PE",
    "wof:name":"Pumarangra",
    "wof:placetype":"locality"
},
  "geometry": {"coordinates":[-74.85874,-13.26649],"type":"Point"}
}