{
  "type": "Feature",
  "properties": {
    "gn:admin1_code":"10.0",
    "gn:admin2_code":"1005.0",
    "gn:admin3_code":"100501.0",
    "gn:asciiname":"Genuaragra",
    "gn:country_code":"PE",
    "gn:dem":3906,
    "gn:feature_class":"P",
    "gn:feature_code":"PPL",
    "gn:name":"Genuaragra",
    "gn:population":0,
    "gn:timezone":"America/Lima",
    "iso:country":"PE",
    "wof:name":"Genuaragra",
    "wof:placetype":"locality"
},
  "geometry": {"coordinates":[-76.78273,-9.60832],"type":"Point"}
}