{
  "type": "Feature",
  "properties": {
    "gn:country":"PE",
    "gn:fcode":"PPLA3",
    "gn:population":32344,
    "iso:country":"PE",
    "qs:name":"Nuevo Imperial",
    "qs:photos_9r":0,
    "qs:photos_sr":0,
    "qs:pop_sr":"7",
    "wof:name":"Nuevo Imperial",
    "wof:placetype":"locality",
    "wof:population":32344
},
  "geometry": {"coordinates":[-76.31719,-13.07541],"type":"Point"}
}