{
  "type": "Feature",
  "properties": {
    "gn:admin1_code":"10.0",
    "gn:admin2_code":"1008.0",
    "gn:admin3_code":"100803.0",
    "gn:asciiname":"Perga Loma",
    "gn:country_code":"PE",
    "gn:dem":3130,
    "gn:feature_class":"P",
    "gn:feature_code":"PPL",
    "gn:name":"Perga Loma",
    "gn:population":0,
    "gn:timezone":"America/Lima",
    "iso:country":"PE",
    "wof:name":"Perga Loma",
    "wof:placetype":"locality"
},
  "geometry": {"coordinates":[-76.02741,-9.99837],"type":"Point"}
}