{
  "type": "Feature",
  "properties": {
    "gn:admin1_code":"4",
    "gn:admin2_code":"401.0",
    "gn:admin3_code":"40119.0",
    "gn:asciiname":"Aldabas",
    "gn:country_code":"PE",
    "gn:dem":4416,
    "gn:feature_class":"P",
    "gn:feature_code":"PPL",
    "gn:name":"Aldabas",
    "gn:population":0,
    "gn:timezone":"America/Lima",
    "iso:country":"PE",
    "wof:name":"Aldabas",
    "wof:placetype":"locality"
},
  "geometry": {"coordinates":[-71.12002,-16.15701],"type":"Point"}
}