{
  "type": "Feature",
  "properties": {
    "gn:admin1_code":"20",
    "gn:admin2_code":"2006.0",
    "gn:admin3_code":"200607.0",
    "gn:asciiname":"Hacienda Poechos",
    "gn:country_code":"PE",
    "gn:dem":107,
    "gn:feature_class":"P",
    "gn:feature_code":"PPL",
    "gn:name":"Hacienda Poechos",
    "gn:population":0,
    "gn:timezone":"America/Lima",
    "iso:country":"PE",
    "name:spa_x_preferred":[
        "Hacienda Poechos"
    ],
    "name:spa_x_variant":[
        "Poechos"
    ],
    "wof:name":"Hacienda Poechos",
    "wof:placetype":"locality"
},
  "geometry": {"coordinates":[-80.52513,-4.67945],"type":"Point"}
}