{
  "type": "Feature",
  "properties": {
    "gn:admin1_code":"9.0",
    "gn:admin2_code":"905.0",
    "gn:admin3_code":"90507.0",
    "gn:asciiname":"Tucujasa",
    "gn:country_code":"PE",
    "gn:dem":4159,
    "gn:feature_class":"P",
    "gn:feature_code":"PPL",
    "gn:name":"Tucujasa",
    "gn:population":0,
    "gn:timezone":"America/Lima",
    "iso:country":"PE",
    "wof:name":"Tucujasa",
    "wof:placetype":"locality"
},
  "geometry": {"coordinates":[-74.53516999999999,-12.58323],"type":"Point"}
}