{
  "type": "Feature",
  "properties": {
    "gn:admin1_code":"5",
    "gn:admin2_code":"509.0",
    "gn:admin3_code":"50907.0",
    "gn:asciiname":"Chailhuani",
    "gn:country_code":"PE",
    "gn:dem":3042,
    "gn:feature_class":"P",
    "gn:feature_code":"PPL",
    "gn:name":"Chailhuani",
    "gn:population":0,
    "gn:timezone":"America/Lima",
    "iso:country":"PE",
    "wof:name":"Chailhuani",
    "wof:placetype":"locality"
},
  "geometry": {"coordinates":[-73.66611,-13.9975],"type":"Point"}
}