{
  "type": "Feature",
  "properties": {
    "gn:admin1_code":"23",
    "gn:admin2_code":"2302.0",
    "gn:admin3_code":"230202.0",
    "gn:asciiname":"Cairani",
    "gn:country_code":"PE",
    "gn:dem":3394,
    "gn:feature_class":"P",
    "gn:feature_code":"PPLA3",
    "gn:name":"Cairani",
    "gn:population":0,
    "gn:timezone":"America/Lima",
    "iso:country":"PE",
    "wof:name":"Cairani",
    "wof:placetype":"locality"
},
  "geometry": {"coordinates":[-70.36360999999999,-17.28582999999999],"type":"Point"}
}