{
  "type": "Feature",
  "properties": {
    "gn:admin1_code":"17.0",
    "gn:admin2_code":"1703.0",
    "gn:asciiname":"Sol de Ica",
    "gn:country_code":"PE",
    "gn:dem":314,
    "gn:feature_class":"P",
    "gn:feature_code":"PPL",
    "gn:name":"Sol de Ica",
    "gn:population":0,
    "gn:timezone":"America/Lima",
    "iso:country":"PE",
    "name:spa_x_preferred":[
        "Sol de Ica"
    ],
    "wof:name":"Sol de Ica",
    "wof:placetype":"locality"
},
  "geometry": {"coordinates":[-69.35281999999999,-11.40781],"type":"Point"}
}