{
  "type": "Feature",
  "properties": {
    "gn:admin1_code":"06",
    "gn:admin2_code":"602.0",
    "gn:admin3_code":"60202.0",
    "gn:asciiname":"Cachachi",
    "gn:country_code":"PE",
    "gn:dem":3550,
    "gn:feature_class":"P",
    "gn:feature_code":"PPLA3",
    "gn:name":"Cachachi",
    "gn:population":0,
    "gn:timezone":"America/Lima",
    "iso:country":"PE",
    "wof:name":"Cachachi",
    "wof:placetype":"locality"
},
  "geometry": {"coordinates":[-78.28333000000001,-7.45],"type":"Point"}
}