{
  "type": "Feature",
  "properties": {
    "gn:admin1_code":"13",
    "gn:admin2_code":"1302.0",
    "gn:admin3_code":"130208.0",
    "gn:asciiname":"Mocan",
    "gn:cc2":"PE",
    "gn:country_code":"PE",
    "gn:dem":149,
    "gn:feature_class":"P",
    "gn:feature_code":"PPL",
    "gn:name":"Moc\u00e1n",
    "gn:population":0,
    "gn:timezone":"America/Lima",
    "iso:country":"PE",
    "name:und_x_variant":[
        "Hacienda Mocan",
        "Mocan Hacienda",
        "Moc\u00e1n"
    ],
    "wof:name":"Mocan",
    "wof:placetype":"locality"
},
  "geometry": {"coordinates":[-79.23999999999999,-7.65611],"type":"Point"}
}