{
  "type": "Feature",
  "properties": {
    "gn:admin1_code":"12.0",
    "gn:admin2_code":"1208.0",
    "gn:admin3_code":"120807.0",
    "gn:asciiname":"Husmacocha",
    "gn:country_code":"PE",
    "gn:dem":4518,
    "gn:feature_class":"P",
    "gn:feature_code":"PPL",
    "gn:name":"Husmacocha",
    "gn:population":0,
    "gn:timezone":"America/Lima",
    "iso:country":"PE",
    "wof:name":"Husmacocha",
    "wof:placetype":"locality"
},
  "geometry": {"coordinates":[-76.34149000000002,-11.0996],"type":"Point"}
}