{
  "type": "Feature",
  "properties": {
    "gn:admin1_code":"13",
    "gn:admin2_code":"1306.0",
    "gn:admin3_code":"130602.0",
    "gn:asciiname":"Miguel Grau",
    "gn:country_code":"PE",
    "gn:dem":2730,
    "gn:feature_class":"P",
    "gn:feature_code":"PPL",
    "gn:name":"Miguel Grau",
    "gn:population":0,
    "gn:timezone":"America/Lima",
    "iso:country":"PE",
    "wof:name":"Miguel Grau",
    "wof:placetype":"locality"
},
  "geometry": {"coordinates":[-78.55801,-7.93264],"type":"Point"}
}