{
  "type": "Feature",
  "properties": {
    "gn:admin1_code":"4",
    "gn:admin2_code":"405.0",
    "gn:admin3_code":"40514.0",
    "gn:asciiname":"Cononaca",
    "gn:country_code":"PE",
    "gn:dem":4630,
    "gn:feature_class":"P",
    "gn:feature_code":"PPL",
    "gn:name":"Cononaca",
    "gn:population":0,
    "gn:timezone":"America/Lima",
    "iso:country":"PE",
    "wof:name":"Cononaca",
    "wof:placetype":"locality"
},
  "geometry": {"coordinates":[-71.11166999999998,-15.75722],"type":"Point"}
}