{
  "type": "Feature",
  "properties": {
    "gn:admin1_code":"15.0",
    "gn:admin2_code":"1507.0",
    "gn:admin3_code":"150707.0",
    "gn:asciiname":"Upica",
    "gn:country_code":"PE",
    "gn:dem":2251,
    "gn:feature_class":"P",
    "gn:feature_code":"PPL",
    "gn:name":"Upica",
    "gn:population":0,
    "gn:timezone":"America/Lima",
    "iso:country":"PE",
    "name:spa_x_preferred":[
        "Upica"
    ],
    "wof:name":"Upica",
    "wof:placetype":"locality"
},
  "geometry": {"coordinates":[-76.60689000000001,-11.73957],"type":"Point"}
}