{
  "type": "Feature",
  "properties": {
    "gn:admin1_code":"2.0",
    "gn:admin2_code":"214.0",
    "gn:admin3_code":"21401.0",
    "gn:asciiname":"Contadera",
    "gn:country_code":"PE",
    "gn:dem":3694,
    "gn:feature_class":"P",
    "gn:feature_code":"PPL",
    "gn:name":"Contadera",
    "gn:population":0,
    "gn:timezone":"America/Lima",
    "iso:country":"PE",
    "wof:name":"Contadera",
    "wof:placetype":"locality"
},
  "geometry": {"coordinates":[-77.42234000000001,-10.36928],"type":"Point"}
}