{
  "type": "Feature",
  "properties": {
    "gn:country":"PE",
    "gn:fcode":"PPLA3",
    "gn:population":5044,
    "iso:country":"PE",
    "name:ast_x_preferred":[
        "Carhuaz"
    ],
    "name:aym_x_preferred":[
        "Qarwas"
    ],
    "name:ceb_x_preferred":[
        "Carhuaz"
    ],
    "name:deu_x_preferred":[
        "Carhuaz"
    ],
    "name:eng_x_preferred":[
        "Carhuas"
    ],
    "name:eng_x_variant":[
        "Carhuaz"
    ],
    "name:fas_x_preferred":[
        "\u06a9\u0627\u0631\u0647\u0648\u0627\u0632"
    ],
    "name:fra_x_preferred":[
        "Carhuaz"
    ],
    "name:ita_x_preferred":[
        "Carhuaz"
    ],
    "name:lit_x_preferred":[
        "Karuasas"
    ],
    "name:nld_x_preferred":[
        "Carhuaz"
    ],
    "name:por_x_preferred":[
        "Carhuaz"
    ],
    "name:que_x_preferred":[
        "Qarwa"
    ],
    "name:spa_x_preferred":[
        "Carhuas"
    ],
    "name:spa_x_variant":[
        "Carhuaz"
    ],
    "name:war_x_preferred":[
        "Carhuaz"
    ],
    "name:zho_x_preferred":[
        "\u5361\u723e\u74e6\u65af"
    ],
    "qs:name":"Carhuaz",
    "qs:photos_9r":0,
    "qs:photos_sr":0,
    "qs:pop_sr":"5",
    "wd:wordcount":257,
    "wof:name":"Carhuaz",
    "wof:placetype":"locality",
    "wof:population":5044
},
  "geometry": {"coordinates":[-77.64472000000001,-9.28194],"type":"Point"}
}