{
  "type": "Feature",
  "properties": {
    "iso:country":"PE",
    "name:deu_x_preferred":[
        "Mar\u00eda Sabina"
    ],
    "name:est_x_preferred":[
        "Mar\u00eda Sabina"
    ],
    "name:fra_x_preferred":[
        "Maria Sabina"
    ],
    "name:ita_x_preferred":[
        "Mar\u00eda Sabina"
    ],
    "name:pol_x_preferred":[
        "Mar\u00eda Sabina"
    ],
    "name:spa_x_preferred":[
        "Mar\u00eda Sabina"
    ],
    "qs:gn_pop":0,
    "qs:name":"Santa Luzmila",
    "qs:name_adm0":"Per\u00fa",
    "qs:name_adm1":"Lima Metropolitan Area",
    "qs:photos":8,
    "qs:photos_1k":2,
    "qs:photos_9k":1,
    "qs:photos_9r":1,
    "qs:photos_all":8,
    "qs:photos_sr":1,
    "qs:placetype":"Town",
    "qs:pop_sr":"0",
    "qs:woe_adm0":23424919,
    "wof:name":"Santa Luzmila",
    "wof:placetype":"locality"
},
  "geometry": {"coordinates":[-77.062202,-11.947157],"type":"Point"}
}