{
  "type": "Feature",
  "properties": {
    "gn:admin1_code":"10",
    "gn:admin2_code":"1008.0",
    "gn:admin3_code":"100801.0",
    "gn:asciiname":"Huayroc",
    "gn:country_code":"PE",
    "gn:dem":3300,
    "gn:feature_class":"P",
    "gn:feature_code":"PPL",
    "gn:name":"Huayroc",
    "gn:population":0,
    "gn:timezone":"America/Lima",
    "iso:country":"PE",
    "wof:name":"Huayroc",
    "wof:placetype":"locality"
},
  "geometry": {"coordinates":[-75.88028,-10.04472],"type":"Point"}
}