{
  "type": "Feature",
  "properties": {
    "iso:country":"PE",
    "qs:gn_pop":0,
    "qs:name":"Cocachacra",
    "qs:name_adm0":"Per\u00fa",
    "qs:name_adm1":"Lima",
    "qs:photos":1,
    "qs:photos_1k":1,
    "qs:photos_9k":1,
    "qs:photos_9r":1,
    "qs:photos_all":1,
    "qs:photos_sr":1,
    "qs:placetype":"Town",
    "qs:pop_sr":"0",
    "qs:woe_adm0":23424919,
    "wof:name":"Cocachacra",
    "wof:placetype":"locality"
},
  "geometry": {"coordinates":[-76.48790099999999,-11.889411],"type":"Point"}
}