{
  "type": "Feature",
  "properties": {
    "gn:admin1_code":"21",
    "gn:admin2_code":"2104.0",
    "gn:admin3_code":"210405.0",
    "gn:asciiname":"Huariquisare",
    "gn:country_code":"PE",
    "gn:dem":3974,
    "gn:feature_class":"P",
    "gn:feature_code":"PPL",
    "gn:name":"Huariquisare",
    "gn:population":0,
    "gn:timezone":"America/Lima",
    "iso:country":"PE",
    "wof:name":"Huariquisare",
    "wof:placetype":"locality"
},
  "geometry": {"coordinates":[-69.38583,-16.85222000000001],"type":"Point"}
}