{
  "type": "Feature",
  "properties": {
    "gn:admin1_code":"4",
    "gn:admin2_code":"405.0",
    "gn:admin3_code":"40514.0",
    "gn:asciiname":"Huilasaya",
    "gn:country_code":"PE",
    "gn:dem":4474,
    "gn:feature_class":"P",
    "gn:feature_code":"PPL",
    "gn:name":"Huilasaya",
    "gn:population":0,
    "gn:timezone":"America/Lima",
    "iso:country":"PE",
    "wof:name":"Huilasaya",
    "wof:placetype":"locality"
},
  "geometry": {"coordinates":[-71.06917,-15.76472],"type":"Point"}
}