{
  "type": "Feature",
  "properties": {
    "gn:admin1_code":"21",
    "gn:admin2_code":"2112.0",
    "gn:admin3_code":"211204.0",
    "gn:asciiname":"Quehare",
    "gn:country_code":"PE",
    "gn:dem":3897,
    "gn:feature_class":"P",
    "gn:feature_code":"PPL",
    "gn:name":"Quehare",
    "gn:population":0,
    "gn:timezone":"America/Lima",
    "iso:country":"PE",
    "wof:name":"Quehare",
    "wof:placetype":"locality"
},
  "geometry": {"coordinates":[-69.65616,-14.39073],"type":"Point"}
}