{
  "type": "Feature",
  "properties": {
    "gn:admin1_code":"12",
    "gn:admin2_code":"1206.0",
    "gn:admin3_code":"120607.0",
    "gn:asciiname":"Portillo",
    "gn:country_code":"PE",
    "gn:dem":799,
    "gn:feature_class":"P",
    "gn:feature_code":"PPL",
    "gn:name":"Portillo",
    "gn:population":0,
    "gn:timezone":"America/Lima",
    "iso:country":"PE",
    "name:ceb_x_preferred":[
        "Portillo"
    ],
    "name:deu_x_preferred":[
        "Portillo"
    ],
    "name:fin_x_preferred":[
        "Portillo"
    ],
    "name:fra_x_preferred":[
        "Portillo"
    ],
    "name:ita_x_preferred":[
        "Portillo"
    ],
    "name:nds_x_preferred":[
        "Portillo"
    ],
    "name:nld_x_preferred":[
        "Portillo"
    ],
    "name:rus_x_preferred":[
        "\u041f\u043e\u0440\u0442\u0438\u043b\u044c\u043e"
    ],
    "name:spa_x_preferred":[
        "Portillo"
    ],
    "name:swe_x_preferred":[
        "Portillo"
    ],
    "name:ukr_x_preferred":[
        "\u041f\u043e\u0440\u0442\u0456\u043b\u044c\u0439\u043e"
    ],
    "wof:name":"Portillo",
    "wof:placetype":"locality"
},
  "geometry": {"coordinates":[-74.65994999999999,-11.1606],"type":"Point"}
}