{
  "type": "Feature",
  "properties": {
    "gn:admin1_code":"5",
    "gn:admin2_code":"505.0",
    "gn:admin3_code":"50502.0",
    "gn:asciiname":"Ayaorca",
    "gn:country_code":"PE",
    "gn:dem":3414,
    "gn:feature_class":"P",
    "gn:feature_code":"PPL",
    "gn:name":"Ayaorca",
    "gn:population":0,
    "gn:timezone":"America/Lima",
    "iso:country":"PE",
    "wof:name":"Ayaorca",
    "wof:placetype":"locality"
},
  "geometry": {"coordinates":[-73.80410999999999,-13.10587],"type":"Point"}
}