{
  "type": "Feature",
  "properties": {
    "gn:admin1_code":"15.0",
    "gn:admin2_code":"1505.0",
    "gn:asciiname":"Topara",
    "gn:country_code":"PE",
    "gn:dem":486,
    "gn:feature_class":"P",
    "gn:feature_code":"PPL",
    "gn:name":"Topara",
    "gn:population":0,
    "gn:timezone":"America/Lima",
    "iso:country":"PE",
    "wof:name":"Topara",
    "wof:placetype":"locality"
},
  "geometry": {"coordinates":[-76.15169,-13.19586],"type":"Point"}
}