{
  "type": "Feature",
  "properties": {
    "gn:admin1_code":"05",
    "gn:admin2_code":"502.0",
    "gn:admin3_code":"50202.0",
    "gn:asciiname":"Llirccona",
    "gn:country_code":"PE",
    "gn:dem":4447,
    "gn:feature_class":"P",
    "gn:feature_code":"PPL",
    "gn:name":"Llirccona",
    "gn:population":0,
    "gn:timezone":"America/Lima",
    "iso:country":"PE",
    "wof:name":"Llirccona",
    "wof:placetype":"locality"
},
  "geometry": {"coordinates":[-74.55991,-13.45684],"type":"Point"}
}