{
  "type": "Feature",
  "properties": {
    "gn:admin1_code":"5.0",
    "gn:admin2_code":"501.0",
    "gn:admin3_code":"50114.0",
    "gn:asciiname":"Itanayoc",
    "gn:country_code":"PE",
    "gn:dem":3869,
    "gn:feature_class":"P",
    "gn:feature_code":"PPL",
    "gn:name":"Itanayoc",
    "gn:population":0,
    "gn:timezone":"America/Lima",
    "iso:country":"PE",
    "wof:name":"Itanayoc",
    "wof:placetype":"locality"
},
  "geometry": {"coordinates":[-74.35141999999998,-13.21113],"type":"Point"}
}