{
  "type": "Feature",
  "properties": {
    "gn:admin1_code":"8",
    "gn:admin2_code":"809.0",
    "gn:admin3_code":"80902.0",
    "gn:asciiname":"Sensa",
    "gn:country_code":"PE",
    "gn:dem":300,
    "gn:feature_class":"P",
    "gn:feature_code":"PPL",
    "gn:name":"Sensa",
    "gn:population":0,
    "gn:timezone":"America/Lima",
    "iso:country":"PE",
    "wof:name":"Sensa",
    "wof:placetype":"locality"
},
  "geometry": {"coordinates":[-73.00433000000002,-11.3855],"type":"Point"}
}