{
  "type": "Feature",
  "properties": {
    "gn:admin1_code":"03",
    "gn:admin2_code":"302.0",
    "gn:admin3_code":"30204.0",
    "gn:asciiname":"Huancarama",
    "gn:country_code":"PE",
    "gn:dem":2977,
    "gn:feature_class":"P",
    "gn:feature_code":"PPLA3",
    "gn:name":"Huancarama",
    "gn:population":0,
    "gn:timezone":"America/Lima",
    "iso:country":"PE",
    "wof:name":"Huancarama",
    "wof:placetype":"locality"
},
  "geometry": {"coordinates":[-73.08639000000002,-13.64528],"type":"Point"}
}