{
  "type": "Feature",
  "properties": {
    "gn:admin1_code":"5",
    "gn:admin2_code":"506.0",
    "gn:admin3_code":"50607.0",
    "gn:asciiname":"Campanario",
    "gn:country_code":"PE",
    "gn:dem":1125,
    "gn:feature_class":"P",
    "gn:feature_code":"PPL",
    "gn:name":"Campanario",
    "gn:population":0,
    "gn:timezone":"America/Lima",
    "iso:country":"PE",
    "name:ceb_x_preferred":[
        "Campanario"
    ],
    "name:epo_x_preferred":[
        "Campanario"
    ],
    "name:nld_x_preferred":[
        "Campanario"
    ],
    "name:spa_x_preferred":[
        "Campanario"
    ],
    "name:swe_x_preferred":[
        "Campanario"
    ],
    "wof:name":"Campanario",
    "wof:placetype":"locality"
},
  "geometry": {"coordinates":[-75.07991,-14.1921],"type":"Point"}
}