{
  "type": "Feature",
  "properties": {
    "gn:admin1_code":"21.0",
    "gn:admin2_code":"2112.0",
    "gn:asciiname":"Chilcayoc",
    "gn:country_code":"PE",
    "gn:dem":1561,
    "gn:feature_class":"P",
    "gn:feature_code":"PPL",
    "gn:name":"Chilcayoc",
    "gn:population":0,
    "gn:timezone":"America/Lima",
    "iso:country":"PE",
    "name:spa_x_preferred":[
        "Chilcayoc"
    ],
    "name:zho_x_preferred":[
        "\u5947\u723e\u5361\u7d04\u514b\u706b\u5c71"
    ],
    "wof:name":"Chilcayoc",
    "wof:placetype":"locality"
},
  "geometry": {"coordinates":[-69.20896,-14.00993],"type":"Point"}
}