{
  "type": "Feature",
  "properties": {
    "gn:admin1_code":"05",
    "gn:admin2_code":"506.0",
    "gn:admin3_code":"50611.0",
    "gn:asciiname":"Hatumpampa",
    "gn:country_code":"PE",
    "gn:dem":3507,
    "gn:feature_class":"P",
    "gn:feature_code":"PPL",
    "gn:name":"Hatumpampa",
    "gn:population":0,
    "gn:timezone":"America/Lima",
    "iso:country":"PE",
    "wof:name":"Hatumpampa",
    "wof:placetype":"locality"
},
  "geometry": {"coordinates":[-74.27225,-14.51792],"type":"Point"}
}