{
  "type": "Feature",
  "properties": {
    "gn:admin1_code":"12",
    "gn:admin2_code":"1201.0",
    "gn:admin3_code":"120135.0",
    "gn:asciiname":"Putcamayo",
    "gn:country_code":"PE",
    "gn:dem":3783,
    "gn:feature_class":"P",
    "gn:feature_code":"PPL",
    "gn:name":"Putcamayo",
    "gn:population":0,
    "gn:timezone":"America/Lima",
    "iso:country":"PE",
    "wof:name":"Putcamayo",
    "wof:placetype":"locality"
},
  "geometry": {"coordinates":[-74.84211999999999,-11.8593],"type":"Point"}
}