{
  "type": "Feature",
  "properties": {
    "gn:admin1_code":"16",
    "gn:admin2_code":"1604.0",
    "gn:admin3_code":"160403.0",
    "gn:asciiname":"Santarita",
    "gn:country_code":"PE",
    "gn:dem":71,
    "gn:feature_class":"P",
    "gn:feature_code":"PPL",
    "gn:name":"Santarita",
    "gn:population":0,
    "gn:timezone":"America/Lima",
    "iso:country":"PE",
    "wof:name":"Santarita",
    "wof:placetype":"locality"
},
  "geometry": {"coordinates":[-70.29800999999999,-4.24164],"type":"Point"}
}