{
  "type": "Feature",
  "properties": {
    "gn:admin1_code":"16",
    "gn:admin2_code":"1603.0",
    "gn:admin3_code":"160302.0",
    "gn:asciiname":"Arica",
    "gn:country_code":"PE",
    "gn:dem":111,
    "gn:feature_class":"P",
    "gn:feature_code":"PPL",
    "gn:name":"Arica",
    "gn:population":0,
    "gn:timezone":"America/Lima",
    "iso:country":"PE",
    "wof:name":"Arica",
    "wof:placetype":"locality"
},
  "geometry": {"coordinates":[-74.16667,-4.98333],"type":"Point"}
}