{
  "type": "Feature",
  "properties": {
    "gn:admin1_code":"25",
    "gn:admin2_code":"2502.0",
    "gn:admin3_code":"250201.0",
    "gn:asciiname":"Lagarto",
    "gn:country_code":"PE",
    "gn:dem":218,
    "gn:feature_class":"P",
    "gn:feature_code":"PPL",
    "gn:name":"Lagarto",
    "gn:population":0,
    "gn:timezone":"America/Lima",
    "iso:country":"PE",
    "name:bpy_x_preferred":[
        "\u09b2\u09be\u0997\u09be\u09b0\u09cd\u099f\u09cb"
    ],
    "name:ceb_x_preferred":[
        "Lagarto"
    ],
    "name:deu_x_preferred":[
        "Lagarto"
    ],
    "name:glg_x_preferred":[
        "Lagarto"
    ],
    "name:ita_x_preferred":[
        "Lagarto"
    ],
    "name:mlg_x_preferred":[
        "Lagarto"
    ],
    "name:por_x_preferred":[
        "Lagarto"
    ],
    "name:sco_x_preferred":[
        "Lagarto"
    ],
    "name:spa_x_preferred":[
        "Lagarto"
    ],
    "name:swe_x_preferred":[
        "Lagarto"
    ],
    "name:vie_x_preferred":[
        "Lagarto"
    ],
    "wof:name":"Lagarto",
    "wof:placetype":"locality"
},
  "geometry": {"coordinates":[-73.88333,-10.58667],"type":"Point"}
}