{
  "type": "Feature",
  "properties": {
    "gn:admin1_code":"02",
    "gn:admin2_code":"206.0",
    "gn:admin3_code":"20609.0",
    "gn:asciiname":"Shilla",
    "gn:country_code":"PE",
    "gn:dem":3026,
    "gn:feature_class":"P",
    "gn:feature_code":"PPLA3",
    "gn:name":"Shilla",
    "gn:population":0,
    "gn:timezone":"America/Lima",
    "iso:country":"PE",
    "name:ceb_x_preferred":[
        "Shilla"
    ],
    "name:rus_x_preferred":[
        "\u0428\u0438\u043b\u043b\u0430"
    ],
    "name:swe_x_preferred":[
        "Shilla"
    ],
    "wof:name":"Shilla",
    "wof:placetype":"locality"
},
  "geometry": {"coordinates":[-77.625,-9.23083],"type":"Point"}
}