{
  "type": "Feature",
  "properties": {
    "gn:admin1_code":"18",
    "gn:admin2_code":"1802.0",
    "gn:admin3_code":"180204.0",
    "gn:asciiname":"La Yunta",
    "gn:country_code":"PE",
    "gn:dem":4356,
    "gn:feature_class":"P",
    "gn:feature_code":"PPL",
    "gn:name":"La Yunta",
    "gn:population":0,
    "gn:timezone":"America/Lima",
    "iso:country":"PE",
    "wof:name":"La Yunta",
    "wof:placetype":"locality"
},
  "geometry": {"coordinates":[-70.60800999999999,-16.1086],"type":"Point"}
}