{
  "type": "Feature",
  "properties": {
    "gn:admin1_code":"22.0",
    "gn:admin2_code":"2203.0",
    "gn:admin3_code":"220301.0",
    "gn:asciiname":"Senorita Rosillo",
    "gn:country_code":"PE",
    "gn:dem":368,
    "gn:feature_class":"P",
    "gn:feature_code":"PPL",
    "gn:name":"Se\u00f1orita Rosillo",
    "gn:population":0,
    "gn:timezone":"America/Lima",
    "iso:country":"PE",
    "wof:name":"Senorita Rosillo",
    "wof:placetype":"locality"
},
  "geometry": {"coordinates":[-76.68113000000002,-6.64561],"type":"Point"}
}