{
  "type": "Feature",
  "properties": {
    "gn:admin1_code":"4",
    "gn:admin2_code":"404.0",
    "gn:admin3_code":"40410.0",
    "gn:asciiname":"Ranra",
    "gn:country_code":"PE",
    "gn:dem":3292,
    "gn:feature_class":"P",
    "gn:feature_code":"PPL",
    "gn:name":"Ranra",
    "gn:population":0,
    "gn:timezone":"America/Lima",
    "iso:country":"PE",
    "wof:name":"Ranra",
    "wof:placetype":"locality"
},
  "geometry": {"coordinates":[-72.59130999999999,-15.68412],"type":"Point"}
}