{
  "type": "Feature",
  "properties": {
    "gn:admin1_code":"11.0",
    "gn:admin2_code":"1101.0",
    "gn:admin3_code":"110113.0",
    "gn:asciiname":"Los Mendoza",
    "gn:country_code":"PE",
    "gn:dem":405,
    "gn:feature_class":"P",
    "gn:feature_code":"PPL",
    "gn:name":"Los Mendoza",
    "gn:population":0,
    "gn:timezone":"America/Lima",
    "iso:country":"PE",
    "name:spa_x_preferred":[
        "Los Mendoza"
    ],
    "wof:name":"Los Mendoza",
    "wof:placetype":"locality"
},
  "geometry": {"coordinates":[-75.69568000000002,-14.14016],"type":"Point"}
}