{
  "type": "Feature",
  "properties": {
    "gn:admin1_code":"15.0",
    "gn:admin2_code":"1506.0",
    "gn:admin3_code":"150606.0",
    "gn:asciiname":"Yancatama",
    "gn:country_code":"PE",
    "gn:dem":1350,
    "gn:feature_class":"P",
    "gn:feature_code":"PPL",
    "gn:name":"Yancatama",
    "gn:population":0,
    "gn:timezone":"America/Lima",
    "iso:country":"PE",
    "wof:name":"Yancatama",
    "wof:placetype":"locality"
},
  "geometry": {"coordinates":[-77.06806,-11.15139],"type":"Point"}
}