{
  "type": "Feature",
  "properties": {
    "gn:admin1_code":"9",
    "gn:admin2_code":"901.0",
    "gn:admin3_code":"90115.0",
    "gn:asciiname":"Acostambo",
    "gn:country_code":"PE",
    "gn:dem":3596,
    "gn:feature_class":"P",
    "gn:feature_code":"PPL",
    "gn:name":"Acostambo",
    "gn:population":0,
    "gn:timezone":"America/Lima",
    "iso:country":"PE",
    "wof:name":"Acostambo",
    "wof:placetype":"locality"
},
  "geometry": {"coordinates":[-75.05450999999999,-12.3653],"type":"Point"}
}