{
  "type": "Feature",
  "properties": {
    "gn:admin1_code":"22.0",
    "gn:admin2_code":"2206.0",
    "gn:admin3_code":"220605.0",
    "gn:asciiname":"Alto Junao",
    "gn:country_code":"PE",
    "gn:dem":313,
    "gn:feature_class":"P",
    "gn:feature_code":"PPL",
    "gn:name":"Alto Ju\u00f1ao",
    "gn:population":0,
    "gn:timezone":"America/Lima",
    "iso:country":"PE",
    "wof:name":"Alto Junao",
    "wof:placetype":"locality"
},
  "geometry": {"coordinates":[-76.69190999999999,-7.25056],"type":"Point"}
}