{
  "type": "Feature",
  "properties": {
    "gn:admin1_code":"12.0",
    "gn:admin2_code":"1205.0",
    "gn:admin3_code":"120501.0",
    "gn:asciiname":"Ropaway",
    "gn:country_code":"PE",
    "gn:dem":4511,
    "gn:feature_class":"P",
    "gn:feature_code":"PPL",
    "gn:name":"Ropaway",
    "gn:population":0,
    "gn:timezone":"America/Lima",
    "iso:country":"PE",
    "wof:name":"Ropaway",
    "wof:placetype":"locality"
},
  "geometry": {"coordinates":[-75.96438000000001,-11.00092],"type":"Point"}
}