{
  "type": "Feature",
  "properties": {
    "gn:admin1_code":"09",
    "gn:admin2_code":"903.0",
    "gn:admin3_code":"90311.0",
    "gn:asciiname":"Condoraypampa",
    "gn:country_code":"PE",
    "gn:dem":4251,
    "gn:feature_class":"P",
    "gn:feature_code":"PPL",
    "gn:name":"Condoraypampa",
    "gn:population":0,
    "gn:timezone":"America/Lima",
    "iso:country":"PE",
    "wof:name":"Condoraypampa",
    "wof:placetype":"locality"
},
  "geometry": {"coordinates":[-74.52675000000001,-13.15418],"type":"Point"}
}