{
  "type": "Feature",
  "properties": {
    "gn:admin1_code":"16.0",
    "gn:admin2_code":"1601.0",
    "gn:admin3_code":"160103.0",
    "gn:asciiname":"Panguana Segunda Zona",
    "gn:country_code":"PE",
    "gn:dem":87,
    "gn:feature_class":"P",
    "gn:feature_code":"PPL",
    "gn:name":"Panguana Segunda Zona",
    "gn:population":0,
    "gn:timezone":"America/Lima",
    "iso:country":"PE",
    "name:und_x_variant":[
        "Panguana 2nd Zona",
        "Panguana Segunda Zona"
    ],
    "wof:name":"Panguana Segunda Zona",
    "wof:placetype":"locality"
},
  "geometry": {"coordinates":[-73.14606999999999,-3.89119],"type":"Point"}
}