{
  "type": "Feature",
  "properties": {
    "gn:admin1_code":"03",
    "gn:admin2_code":"306.0",
    "gn:admin3_code":"30603.0",
    "gn:asciiname":"Cocharcas",
    "gn:country_code":"PE",
    "gn:dem":3022,
    "gn:feature_class":"P",
    "gn:feature_code":"PPLA3",
    "gn:name":"Cocharcas",
    "gn:population":0,
    "gn:timezone":"America/Lima",
    "iso:country":"PE",
    "wof:name":"Cocharcas",
    "wof:placetype":"locality"
},
  "geometry": {"coordinates":[-73.73999999999999,-13.61],"type":"Point"}
}