{
  "type": "Feature",
  "properties": {
    "gn:admin1_code":"10",
    "gn:admin2_code":"1001.0",
    "gn:admin3_code":"100103.0",
    "gn:asciiname":"Muna",
    "gn:country_code":"PE",
    "gn:dem":1708,
    "gn:feature_class":"P",
    "gn:feature_code":"PPL",
    "gn:name":"Mu\u00f1a",
    "gn:population":0,
    "gn:timezone":"America/Lima",
    "iso:country":"PE",
    "name:bel_x_preferred":[
        "\u041c\u0443\u043d\u0430"
    ],
    "name:ceb_x_preferred":[
        "Muna"
    ],
    "name:ces_x_preferred":[
        "Muna"
    ],
    "name:deu_x_preferred":[
        "Muna"
    ],
    "name:est_x_preferred":[
        "Muna"
    ],
    "name:fin_x_preferred":[
        "Muna"
    ],
    "name:fra_x_preferred":[
        "Muna"
    ],
    "name:ind_x_preferred":[
        "Muna"
    ],
    "name:ita_x_preferred":[
        "Muna"
    ],
    "name:lit_x_preferred":[
        "Muna"
    ],
    "name:nld_x_preferred":[
        "Muna"
    ],
    "name:rus_x_preferred":[
        "\u041c\u0443\u043d\u0430"
    ],
    "name:srp_x_preferred":[
        "\u041c\u0443\u043d\u0430"
    ],
    "name:swe_x_preferred":[
        "Muna"
    ],
    "name:ukr_x_preferred":[
        "\u041c\u0443\u043d\u0430"
    ],
    "wof:name":"Muna",
    "wof:placetype":"locality"
},
  "geometry": {"coordinates":[-75.81667,-9.66667],"type":"Point"}
}