{
  "type": "Feature",
  "properties": {
    "gn:admin1_code":"10.0",
    "gn:admin2_code":"1006.0",
    "gn:admin3_code":"100601.0",
    "gn:asciiname":"Asociation de Vivendia Buenos Aires",
    "gn:country_code":"PE",
    "gn:dem":656,
    "gn:feature_class":"P",
    "gn:feature_code":"PPLL",
    "gn:name":"Asociation de Vivendia Buenos Aires",
    "gn:population":0,
    "gn:timezone":"America/Lima",
    "iso:country":"PE",
    "wof:name":"Asociation de Vivendia Buenos Aires",
    "wof:placetype":"locality"
},
  "geometry": {"coordinates":[-75.99659,-9.32035],"type":"Point"}
}