{
  "type": "Feature",
  "properties": {
    "gn:admin1_code":"25",
    "gn:admin2_code":"2501.0",
    "gn:admin3_code":"250104.0",
    "gn:asciiname":"Tres Islas",
    "gn:country_code":"PE",
    "gn:dem":149,
    "gn:feature_class":"P",
    "gn:feature_code":"PPL",
    "gn:name":"Tres Islas",
    "gn:population":0,
    "gn:timezone":"America/Lima",
    "iso:country":"PE",
    "wof:name":"Tres Islas",
    "wof:placetype":"locality"
},
  "geometry": {"coordinates":[-74.27542,-8.53131],"type":"Point"}
}