{
  "type": "Feature",
  "properties": {
    "gn:admin1_code":"3",
    "gn:admin2_code":"302.0",
    "gn:asciiname":"Apuhuaijo",
    "gn:country_code":"PE",
    "gn:dem":3739,
    "gn:feature_class":"P",
    "gn:feature_code":"PPL",
    "gn:name":"Apuhuaijo",
    "gn:population":0,
    "gn:timezone":"America/Lima",
    "iso:country":"PE",
    "wof:name":"Apuhuaijo",
    "wof:placetype":"locality"
},
  "geometry": {"coordinates":[-73.5475,-14.11139],"type":"Point"}
}