{
  "type": "Feature",
  "properties": {
    "gn:admin1_code":"21",
    "gn:admin2_code":"2103.0",
    "gn:admin3_code":"210306.0",
    "gn:asciiname":"Pajo Pina",
    "gn:country_code":"PE",
    "gn:dem":4508,
    "gn:feature_class":"P",
    "gn:feature_code":"PPL",
    "gn:name":"Pajo Pi\u00f1a",
    "gn:population":0,
    "gn:timezone":"America/Lima",
    "iso:country":"PE",
    "wof:name":"Pajo Pina",
    "wof:placetype":"locality"
},
  "geometry": {"coordinates":[-69.77176999999999,-14.39214],"type":"Point"}
}