{
  "type": "Feature",
  "properties": {
    "gn:admin1_code":"12.0",
    "gn:admin2_code":"1204.0",
    "gn:admin3_code":"120427.0",
    "gn:asciiname":"Tambillo",
    "gn:country_code":"PE",
    "gn:dem":3411,
    "gn:feature_class":"P",
    "gn:feature_code":"PPL",
    "gn:name":"Tambillo",
    "gn:population":0,
    "gn:timezone":"America/Lima",
    "iso:country":"PE",
    "wof:name":"Tambillo",
    "wof:placetype":"locality"
},
  "geometry": {"coordinates":[-75.40934,-11.47152],"type":"Point"}
}