{
  "type": "Feature",
  "properties": {
    "gn:admin1_code":"09",
    "gn:admin2_code":"906.0",
    "gn:admin3_code":"90607.0",
    "gn:asciiname":"Yanasenega",
    "gn:country_code":"PE",
    "gn:dem":4310,
    "gn:feature_class":"P",
    "gn:feature_code":"PPL",
    "gn:name":"Yanasenega",
    "gn:population":0,
    "gn:timezone":"America/Lima",
    "iso:country":"PE",
    "wof:name":"Yanasenega",
    "wof:placetype":"locality"
},
  "geometry": {"coordinates":[-75.03489,-13.33046],"type":"Point"}
}