{
  "type": "Feature",
  "properties": {
    "gn:admin1_code":"21",
    "gn:admin2_code":"2105.0",
    "gn:admin3_code":"210501.0",
    "gn:asciiname":"Corpa",
    "gn:country_code":"PE",
    "gn:dem":3821,
    "gn:feature_class":"P",
    "gn:feature_code":"PPL",
    "gn:name":"Corpa",
    "gn:population":0,
    "gn:timezone":"America/Lima",
    "iso:country":"PE",
    "name:ara_x_preferred":[
        "\u0643\u0648\u0631\u0628\u0627"
    ],
    "name:ast_x_preferred":[
        "Corpa"
    ],
    "name:cat_x_preferred":[
        "Corpa"
    ],
    "name:ceb_x_preferred":[
        "Corpa"
    ],
    "name:epo_x_preferred":[
        "Corpa"
    ],
    "name:eus_x_preferred":[
        "Corpa"
    ],
    "name:fra_x_preferred":[
        "Corpa"
    ],
    "name:hun_x_preferred":[
        "Corpa"
    ],
    "name:ita_x_preferred":[
        "Corpa"
    ],
    "name:ltz_x_preferred":[
        "Corpa"
    ],
    "name:msa_x_preferred":[
        "Corpa"
    ],
    "name:oci_x_preferred":[
        "Corpa"
    ],
    "name:pol_x_preferred":[
        "Corpa"
    ],
    "name:por_x_preferred":[
        "Corpa"
    ],
    "name:sco_x_preferred":[
        "Corpa"
    ],
    "name:spa_x_preferred":[
        "Corpa"
    ],
    "name:sqi_x_preferred":[
        "Corpa"
    ],
    "name:swe_x_preferred":[
        "Corpa"
    ],
    "name:ukr_x_preferred":[
        "\u041a\u043e\u0440\u043f\u0430"
    ],
    "name:vie_x_preferred":[
        "Corpa"
    ],
    "name:war_x_preferred":[
        "Corpa"
    ],
    "name:zho_x_preferred":[
        "\u79d1\u5c14\u5e15"
    ],
    "wof:name":"Corpa",
    "wof:placetype":"locality"
},
  "geometry": {"coordinates":[-69.58749,-16.0283],"type":"Point"}
}