{
  "type": "Feature",
  "properties": {
    "gn:admin1_code":"21",
    "gn:admin2_code":"2105.0",
    "gn:admin3_code":"210501.0",
    "gn:asciiname":"Corpa",
    "gn:country_code":"PE",
    "gn:dem":3821,
    "gn:feature_class":"P",
    "gn:feature_code":"PPL",
    "gn:name":"Corpa",
    "gn:population":0,
    "gn:timezone":"America/Lima",
    "iso:country":"PE",
    "wof:name":"Corpa",
    "wof:placetype":"locality"
},
  "geometry": {"coordinates":[-69.58749,-16.0283],"type":"Point"}
}