{
  "type": "Feature",
  "properties": {
    "gn:admin1_code":"21",
    "gn:admin2_code":"2104.0",
    "gn:admin3_code":"210405.0",
    "gn:asciiname":"Asirune",
    "gn:country_code":"PE",
    "gn:dem":3953,
    "gn:feature_class":"P",
    "gn:feature_code":"PPL",
    "gn:name":"Asirune",
    "gn:population":0,
    "gn:timezone":"America/Lima",
    "iso:country":"PE",
    "wof:name":"Asirune",
    "wof:placetype":"locality"
},
  "geometry": {"coordinates":[-69.37791999999999,-16.87454],"type":"Point"}
}