{
  "type": "Feature",
  "properties": {
    "gn:admin1_code":"8.0",
    "gn:admin2_code":"809.0",
    "gn:asciiname":"Omaya",
    "gn:country_code":"PE",
    "gn:dem":595,
    "gn:feature_class":"P",
    "gn:feature_code":"PPL",
    "gn:name":"Omaya",
    "gn:population":0,
    "gn:timezone":"America/Lima",
    "iso:country":"PE",
    "wof:name":"Omaya",
    "wof:placetype":"locality"
},
  "geometry": {"coordinates":[-73.80785,-12.55772],"type":"Point"}
}