{
  "type": "Feature",
  "properties": {
    "gn:admin1_code":"9.0",
    "gn:admin2_code":"907.0",
    "gn:admin3_code":"90709.0",
    "gn:asciiname":"Manyahuasi",
    "gn:country_code":"PE",
    "gn:dem":3866,
    "gn:feature_class":"P",
    "gn:feature_code":"PPL",
    "gn:name":"Manyahuasi",
    "gn:population":0,
    "gn:timezone":"America/Lima",
    "iso:country":"PE",
    "wof:name":"Manyahuasi",
    "wof:placetype":"locality"
},
  "geometry": {"coordinates":[-74.90824000000001,-12.1564],"type":"Point"}
}