{
  "type": "Feature",
  "properties": {
    "gn:admin1_code":"20",
    "gn:admin2_code":"2004.0",
    "gn:admin3_code":"200405.0",
    "gn:asciiname":"Franco",
    "gn:country_code":"PE",
    "gn:dem":111,
    "gn:feature_class":"P",
    "gn:feature_code":"PPL",
    "gn:name":"Franco",
    "gn:population":0,
    "gn:timezone":"America/Lima",
    "iso:country":"PE",
    "name:ara_x_preferred":[
        "\u0641\u0631\u0627\u0646\u0643\u0648"
    ],
    "name:ast_x_preferred":[
        "Franco"
    ],
    "name:bel_x_preferred":[
        "\u0424\u0440\u0430\u043d\u043a\u0430"
    ],
    "name:bul_x_preferred":[
        "\u0424\u0440\u0430\u043d\u043a\u043e"
    ],
    "name:cat_x_preferred":[
        "Franco"
    ],
    "name:ceb_x_preferred":[
        "Franco"
    ],
    "name:deu_x_preferred":[
        "Franco"
    ],
    "name:eml_x_preferred":[
        "Franch"
    ],
    "name:eus_x_preferred":[
        "Franco"
    ],
    "name:fin_x_preferred":[
        "Franco"
    ],
    "name:fra_x_preferred":[
        "Franco"
    ],
    "name:glg_x_preferred":[
        "Franco"
    ],
    "name:hat_x_preferred":[
        "Franco"
    ],
    "name:heb_x_preferred":[
        "\u05e4\u05e8\u05e0\u05e7\u05d5"
    ],
    "name:ind_x_preferred":[
        "Franco"
    ],
    "name:ita_x_preferred":[
        "Franco"
    ],
    "name:jpn_x_preferred":[
        "\u30d5\u30e9\u30f3\u30b3"
    ],
    "name:kor_x_preferred":[
        "\ud504\ub791\ucf54"
    ],
    "name:lit_x_preferred":[
        "Franco"
    ],
    "name:nds_x_preferred":[
        "Franco"
    ],
    "name:nld_x_preferred":[
        "Franco"
    ],
    "name:pol_x_preferred":[
        "Franco"
    ],
    "name:por_x_preferred":[
        "Franco"
    ],
    "name:ron_x_preferred":[
        "Franco"
    ],
    "name:rus_x_preferred":[
        "\u0424\u0440\u0430\u043d\u043a\u043e"
    ],
    "name:slv_x_preferred":[
        "Franco"
    ],
    "name:spa_x_preferred":[
        "Franco"
    ],
    "name:srp_x_preferred":[
        "\u0424\u0440\u0430\u043d\u043a\u043e"
    ],
    "name:swe_x_preferred":[
        "Franco"
    ],
    "name:tur_x_preferred":[
        "Franco"
    ],
    "name:ukr_x_preferred":[
        "\u0424\u0440\u0430\u043d\u043a\u043e"
    ],
    "name:und_x_variant":[
        "Franco Hacienda"
    ],
    "wof:name":"Franco",
    "wof:placetype":"locality"
},
  "geometry": {"coordinates":[-80.03808000000002,-5.17349],"type":"Point"}
}