{
  "type": "Feature",
  "properties": {
    "gn:admin1_code":"20",
    "gn:admin2_code":"2004.0",
    "gn:admin3_code":"200405.0",
    "gn:asciiname":"Franco",
    "gn:country_code":"PE",
    "gn:dem":111,
    "gn:feature_class":"P",
    "gn:feature_code":"PPL",
    "gn:name":"Franco",
    "gn:population":0,
    "gn:timezone":"America/Lima",
    "iso:country":"PE",
    "name:und_x_variant":[
        "Franco Hacienda",
        "Franco"
    ],
    "wof:name":"Franco",
    "wof:placetype":"locality"
},
  "geometry": {"coordinates":[-80.03808000000002,-5.17349],"type":"Point"}
}