{
  "type": "Feature",
  "properties": {
    "gn:admin1_code":"9.0",
    "gn:admin2_code":"903.0",
    "gn:admin3_code":"90301.0",
    "gn:asciiname":"Canchapata",
    "gn:country_code":"PE",
    "gn:dem":3854,
    "gn:feature_class":"P",
    "gn:feature_code":"PPL",
    "gn:name":"Canchapata",
    "gn:population":0,
    "gn:timezone":"America/Lima",
    "iso:country":"PE",
    "wof:name":"Canchapata",
    "wof:placetype":"locality"
},
  "geometry": {"coordinates":[-74.77669,-12.97121],"type":"Point"}
}