{
  "type": "Feature",
  "properties": {
    "gn:admin1_code":"09",
    "gn:admin2_code":"906.0",
    "gn:admin3_code":"90607.0",
    "gn:asciiname":"Ccollpa",
    "gn:country_code":"PE",
    "gn:dem":4250,
    "gn:feature_class":"P",
    "gn:feature_code":"PPL",
    "gn:name":"Ccollpa",
    "gn:population":0,
    "gn:timezone":"America/Lima",
    "iso:country":"PE",
    "name:und_x_variant":[
        "Collpa",
        "Ccollpa"
    ],
    "wof:name":"Ccollpa",
    "wof:placetype":"locality"
},
  "geometry": {"coordinates":[-74.85786999999998,-13.72701],"type":"Point"}
}