{
  "type": "Feature",
  "properties": {
    "gn:admin1_code":"04",
    "gn:admin2_code":"404.0",
    "gn:admin3_code":"40413.0",
    "gn:asciiname":"Torete",
    "gn:country_code":"PE",
    "gn:dem":414,
    "gn:feature_class":"P",
    "gn:feature_code":"PPL",
    "gn:name":"Torete",
    "gn:population":0,
    "gn:timezone":"America/Lima",
    "iso:country":"PE",
    "name:und_x_variant":[
        "Torete Hacienda",
        "Torete"
    ],
    "wof:name":"Torete",
    "wof:placetype":"locality"
},
  "geometry": {"coordinates":[-72.46938,-16.24237999999999],"type":"Point"}
}