{
  "type": "Feature",
  "properties": {
    "gn:admin1_code":"10",
    "gn:admin2_code":"1010.0",
    "gn:admin3_code":"101002.0",
    "gn:asciiname":"Pachanan Arriero",
    "gn:country_code":"PE",
    "gn:dem":4246,
    "gn:feature_class":"P",
    "gn:feature_code":"PPL",
    "gn:name":"Pachanan Arriero",
    "gn:population":0,
    "gn:timezone":"America/Lima",
    "iso:country":"PE",
    "wof:name":"Pachanan Arriero",
    "wof:placetype":"locality"
},
  "geometry": {"coordinates":[-76.77764999999999,-10.17388],"type":"Point"}
}