{
  "type": "Feature",
  "properties": {
    "gn:admin1_code":"02",
    "gn:admin2_code":"220.0",
    "gn:admin3_code":"22005.0",
    "gn:asciiname":"Tinco",
    "gn:country_code":"PE",
    "gn:dem":1825,
    "gn:feature_class":"P",
    "gn:feature_code":"PPL",
    "gn:name":"Tinco",
    "gn:population":0,
    "gn:timezone":"America/Lima",
    "iso:country":"PE",
    "name:und_x_variant":[
        "Tingo",
        "Tinco"
    ],
    "wof:name":"Tinco",
    "wof:placetype":"locality"
},
  "geometry": {"coordinates":[-78.02861999999998,-9.28339],"type":"Point"}
}