{
  "type": "Feature",
  "properties": {
    "gn:admin1_code":"9",
    "gn:admin2_code":"906.0",
    "gn:admin3_code":"90615.0",
    "gn:asciiname":"Ccatun Corral",
    "gn:country_code":"PE",
    "gn:dem":4390,
    "gn:feature_class":"P",
    "gn:feature_code":"PPL",
    "gn:name":"Ccatun Corral",
    "gn:population":0,
    "gn:timezone":"America/Lima",
    "iso:country":"PE",
    "wof:name":"Ccatun Corral",
    "wof:placetype":"locality"
},
  "geometry": {"coordinates":[-75.18416999999999,-13.67111],"type":"Point"}
}