{
  "type": "Feature",
  "properties": {
    "gn:admin1_code":"04",
    "gn:admin2_code":"406.0",
    "gn:admin3_code":"40603.0",
    "gn:asciiname":"Chucchulla",
    "gn:country_code":"PE",
    "gn:dem":4531,
    "gn:feature_class":"P",
    "gn:feature_code":"PPL",
    "gn:name":"Chucchulla",
    "gn:population":0,
    "gn:timezone":"America/Lima",
    "iso:country":"PE",
    "wof:name":"Chucchulla",
    "wof:placetype":"locality"
},
  "geometry": {"coordinates":[-72.27041,-15.01919],"type":"Point"}
}