{
  "type": "Feature",
  "properties": {
    "gn:admin1_code":"3",
    "gn:admin2_code":"302.0",
    "gn:admin3_code":"30206.0",
    "gn:asciiname":"Yanayacu",
    "gn:country_code":"PE",
    "gn:dem":3438,
    "gn:feature_class":"P",
    "gn:feature_code":"PPL",
    "gn:name":"Yanayacu",
    "gn:population":0,
    "gn:timezone":"America/Lima",
    "iso:country":"PE",
    "wof:name":"Yanayacu",
    "wof:placetype":"locality"
},
  "geometry": {"coordinates":[-73.56971999999998,-14.01389],"type":"Point"}
}