{
  "type": "Feature",
  "properties": {
    "gn:admin1_code":"9.0",
    "gn:admin2_code":"907.0",
    "gn:admin3_code":"90705.0",
    "gn:asciiname":"Allhuallacay",
    "gn:country_code":"PE",
    "gn:dem":2792,
    "gn:feature_class":"P",
    "gn:feature_code":"PPL",
    "gn:name":"Allhuallacay",
    "gn:population":0,
    "gn:timezone":"America/Lima",
    "iso:country":"PE",
    "wof:name":"Allhuallacay",
    "wof:placetype":"locality"
},
  "geometry": {"coordinates":[-74.72589000000001,-12.36211],"type":"Point"}
}