{
  "type": "Feature",
  "properties": {
    "gn:admin1_code":"5",
    "gn:admin2_code":"501.0",
    "gn:admin3_code":"50106.0",
    "gn:asciiname":"Jurajaca",
    "gn:country_code":"PE",
    "gn:dem":2759,
    "gn:feature_class":"P",
    "gn:feature_code":"PPL",
    "gn:name":"Jurajaca",
    "gn:population":0,
    "gn:timezone":"America/Lima",
    "iso:country":"PE",
    "wof:name":"Jurajaca",
    "wof:placetype":"locality"
},
  "geometry": {"coordinates":[-73.88764,-13.39021],"type":"Point"}
}