{
  "type": "Feature",
  "properties": {
    "gn:admin1_code":"15",
    "gn:admin2_code":"1506.0",
    "gn:admin3_code":"150612.0",
    "gn:asciiname":"Cararin",
    "gn:country_code":"PE",
    "gn:dem":2334,
    "gn:feature_class":"P",
    "gn:feature_code":"PPL",
    "gn:name":"Cararin",
    "gn:population":0,
    "gn:timezone":"America/Lima",
    "iso:country":"PE",
    "wof:name":"Cararin",
    "wof:placetype":"locality"
},
  "geometry": {"coordinates":[-76.79916999999998,-11.21139],"type":"Point"}
}