{
  "type": "Feature",
  "properties": {
    "gn:admin1_code":"23",
    "gn:admin2_code":"2304.0",
    "gn:admin3_code":"230401.0",
    "gn:asciiname":"Challacucho",
    "gn:country_code":"PE",
    "gn:dem":4431,
    "gn:feature_class":"P",
    "gn:feature_code":"PPL",
    "gn:name":"Challacucho",
    "gn:population":0,
    "gn:timezone":"America/Lima",
    "iso:country":"PE",
    "wof:name":"Challacucho",
    "wof:placetype":"locality"
},
  "geometry": {"coordinates":[-69.74743000000001,-17.39479],"type":"Point"}
}