{
  "type": "Feature",
  "properties": {
    "gn:admin1_code":"12",
    "gn:admin2_code":"1206.0",
    "gn:admin3_code":"120607.0",
    "gn:asciiname":"Union Capiri",
    "gn:country_code":"PE",
    "gn:dem":588,
    "gn:feature_class":"P",
    "gn:feature_code":"PPL",
    "gn:name":"Uni\u00f3n Capiri",
    "gn:population":0,
    "gn:timezone":"America/Lima",
    "iso:country":"PE",
    "wof:name":"Union Capiri",
    "wof:placetype":"locality"
},
  "geometry": {"coordinates":[-74.70214,-11.09227],"type":"Point"}
}