{
  "type": "Feature",
  "properties": {
    "gn:admin1_code":"8",
    "gn:admin2_code":"808.0",
    "gn:admin3_code":"80804.0",
    "gn:asciiname":"Torre",
    "gn:country_code":"PE",
    "gn:dem":4332,
    "gn:feature_class":"P",
    "gn:feature_code":"PPL",
    "gn:name":"Torre",
    "gn:population":0,
    "gn:timezone":"America/Lima",
    "iso:country":"PE",
    "name:arg_x_preferred":[
        "Torre"
    ],
    "name:cat_x_preferred":[
        "Torre"
    ],
    "name:ceb_x_preferred":[
        "Torre"
    ],
    "name:deu_x_preferred":[
        "Torre"
    ],
    "name:eus_x_preferred":[
        "Torre"
    ],
    "name:fin_x_preferred":[
        "Torre"
    ],
    "name:fra_x_preferred":[
        "Torre"
    ],
    "name:glg_x_preferred":[
        "Torre"
    ],
    "name:ita_x_preferred":[
        "Torre"
    ],
    "name:nld_x_preferred":[
        "Torre"
    ],
    "name:pol_x_preferred":[
        "Torre"
    ],
    "name:por_x_preferred":[
        "Torre"
    ],
    "name:rus_x_preferred":[
        "\u0422\u043e\u0440\u0440\u0435"
    ],
    "name:sco_x_preferred":[
        "Torre"
    ],
    "name:spa_x_preferred":[
        "Torre"
    ],
    "name:srp_x_preferred":[
        "\u0422\u043e\u0440\u0435"
    ],
    "name:swe_x_preferred":[
        "Torre"
    ],
    "name:ukr_x_preferred":[
        "\u0422\u043e\u0440\u0440\u0435"
    ],
    "wof:name":"Torre",
    "wof:placetype":"locality"
},
  "geometry": {"coordinates":[-71.14646,-15.08969],"type":"Point"}
}