{
  "type": "Feature",
  "properties": {
    "gn:country":"PE",
    "gn:fcode":"PPL",
    "gn:pop":4199,
    "iso:country":"PE",
    "qs:name":"Orcotuna",
    "qs:photos_9r":0,
    "qs:photos_sr":0,
    "qs:pop_sr":"4",
    "wd:wordcount":28,
    "wof:name":"Orcotuna",
    "wof:placetype":"locality",
    "wof:population":4199
},
  "geometry": {"coordinates":[-75.3078,-11.96886],"type":"Point"}
}