{
  "type": "Feature",
  "properties": {
    "gn:country":"PE",
    "gn:fcode":"PPL",
    "gn:pop":4199,
    "iso:country":"PE",
    "name:ceb_x_preferred":[
        "Orcotuna"
    ],
    "name:eng_x_preferred":[
        "Orcotuna District"
    ],
    "name:kat_x_preferred":[
        "\u10dd\u10e0\u10d9\u10dd\u10e2\u10e3\u10dc\u10d8\u10e1 \u10e0\u10d0\u10d8\u10dd\u10dc\u10d8"
    ],
    "name:por_x_preferred":[
        "Orcotuna"
    ],
    "name:que_x_preferred":[
        "Urqutuna distritu"
    ],
    "name:zho_x_preferred":[
        "\u5967\u723e\u79d1\u5716\u7d0d\u5340"
    ],
    "qs:name":"Orcotuna",
    "qs:photos_9r":0,
    "qs:photos_sr":0,
    "qs:pop_sr":"4",
    "wd:wordcount":28,
    "wof:name":"Orcotuna",
    "wof:placetype":"locality",
    "wof:population":4199
},
  "geometry": {"coordinates":[-75.3078,-11.96886],"type":"Point"}
}