{
  "type": "Feature",
  "properties": {
    "gn:admin1_code":"02",
    "gn:admin2_code":"205.0",
    "gn:asciiname":"Ispag",
    "gn:country_code":"PE",
    "gn:dem":4220,
    "gn:feature_class":"P",
    "gn:feature_code":"PPL",
    "gn:name":"Ispag",
    "gn:population":0,
    "gn:timezone":"America/Lima",
    "iso:country":"PE",
    "wof:name":"Ispag",
    "wof:placetype":"locality"
},
  "geometry": {"coordinates":[-76.93333,-10.06667],"type":"Point"}
}