{
  "type": "Feature",
  "properties": {
    "gn:admin1_code":"9.0",
    "gn:admin2_code":"903.0",
    "gn:admin3_code":"90303.0",
    "gn:asciiname":"Yerbabuenayoc",
    "gn:country_code":"PE",
    "gn:dem":3801,
    "gn:feature_class":"P",
    "gn:feature_code":"PPL",
    "gn:name":"Yerbabuenayoc",
    "gn:population":0,
    "gn:timezone":"America/Lima",
    "iso:country":"PE",
    "wof:name":"Yerbabuenayoc",
    "wof:placetype":"locality"
},
  "geometry": {"coordinates":[-74.62379,-12.89312],"type":"Point"}
}