{
  "type": "Feature",
  "properties": {
    "gn:admin1_code":"8.0",
    "gn:admin2_code":"803.0",
    "gn:admin3_code":"80304.0",
    "gn:asciiname":"Llaullijasa",
    "gn:country_code":"PE",
    "gn:dem":3760,
    "gn:feature_class":"P",
    "gn:feature_code":"PPL",
    "gn:name":"Llaullijasa",
    "gn:population":0,
    "gn:timezone":"America/Lima",
    "iso:country":"PE",
    "wof:name":"Llaullijasa",
    "wof:placetype":"locality"
},
  "geometry": {"coordinates":[-72.34166999999999,-13.58861],"type":"Point"}
}