{
  "type": "Feature",
  "properties": {
    "gn:admin1_code":"10.0",
    "gn:admin2_code":"1007.0",
    "gn:admin3_code":"100702.0",
    "gn:asciiname":"Maldonado",
    "gn:country_code":"PE",
    "gn:dem":513,
    "gn:feature_class":"P",
    "gn:feature_code":"PPLL",
    "gn:name":"Maldonado",
    "gn:population":0,
    "gn:timezone":"America/Lima",
    "iso:country":"PE",
    "name:cat_x_preferred":[
        "Maldonado"
    ],
    "name:ceb_x_preferred":[
        "Maldonado"
    ],
    "name:ces_x_preferred":[
        "Maldonado"
    ],
    "name:deu_x_preferred":[
        "Maldonado"
    ],
    "name:fra_x_preferred":[
        "Maldonado"
    ],
    "name:ita_x_preferred":[
        "Maldonado"
    ],
    "name:mlg_x_preferred":[
        "Maldonado"
    ],
    "name:nld_x_preferred":[
        "Maldonado"
    ],
    "name:pol_x_preferred":[
        "Maldonado"
    ],
    "name:por_x_preferred":[
        "Maldonado"
    ],
    "name:rus_x_preferred":[
        "\u041c\u0430\u043b\u044c\u0434\u043e\u043d\u0430\u0434\u043e"
    ],
    "name:sco_x_preferred":[
        "Maldonado"
    ],
    "name:spa_x_preferred":[
        "Maldonado"
    ],
    "name:srp_x_preferred":[
        "\u041c\u0430\u043b\u0434\u043e\u043d\u0430\u0434\u043e"
    ],
    "wof:name":"Maldonado",
    "wof:placetype":"locality"
},
  "geometry": {"coordinates":[-76.35056999999998,-8.49241],"type":"Point"}
}