{
  "type": "Feature",
  "properties": {
    "gn:admin1_code":"4",
    "gn:admin2_code":"406.0",
    "gn:admin3_code":"40606.0",
    "gn:asciiname":"Taquila",
    "gn:country_code":"PE",
    "gn:dem":446,
    "gn:feature_class":"P",
    "gn:feature_code":"PPL",
    "gn:name":"Taquila",
    "gn:population":0,
    "gn:timezone":"America/Lima",
    "iso:country":"PE",
    "wof:name":"Taquila",
    "wof:placetype":"locality"
},
  "geometry": {"coordinates":[-73.1349,-15.94925],"type":"Point"}
}