{
  "type": "Feature",
  "properties": {
    "gn:admin1_code":"09",
    "gn:admin2_code":"906.0",
    "gn:admin3_code":"90607.0",
    "gn:asciiname":"Jatun Rumi",
    "gn:country_code":"PE",
    "gn:dem":4341,
    "gn:feature_class":"P",
    "gn:feature_code":"PPL",
    "gn:name":"Jatun Rumi",
    "gn:population":0,
    "gn:timezone":"America/Lima",
    "iso:country":"PE",
    "wof:name":"Jatun Rumi",
    "wof:placetype":"locality"
},
  "geometry": {"coordinates":[-74.95,-13.46667],"type":"Point"}
}