{
  "type": "Feature",
  "properties": {
    "gn:admin1_code":"15",
    "gn:admin2_code":"1506.0",
    "gn:admin3_code":"150612.0",
    "gn:asciiname":"Canchar",
    "gn:country_code":"PE",
    "gn:dem":1673,
    "gn:feature_class":"P",
    "gn:feature_code":"PPL",
    "gn:name":"Canchar",
    "gn:population":0,
    "gn:timezone":"America/Lima",
    "iso:country":"PE",
    "wof:name":"Canchar",
    "wof:placetype":"locality"
},
  "geometry": {"coordinates":[-76.78778,-11.26583],"type":"Point"}
}