{
  "type": "Feature",
  "properties": {
    "gn:admin1_code":"12.0",
    "gn:admin2_code":"1208.0",
    "gn:admin3_code":"120808.0",
    "gn:asciiname":"Araracmachay",
    "gn:country_code":"PE",
    "gn:dem":4277,
    "gn:feature_class":"P",
    "gn:feature_code":"PPL",
    "gn:name":"Araracmachay",
    "gn:population":0,
    "gn:timezone":"America/Lima",
    "iso:country":"PE",
    "wof:name":"Araracmachay",
    "wof:placetype":"locality"
},
  "geometry": {"coordinates":[-75.96585,-11.53819],"type":"Point"}
}