{
  "type": "Feature",
  "properties": {
    "gn:admin1_code":"10.0",
    "gn:admin2_code":"1003.0",
    "gn:admin3_code":"100317.0",
    "gn:asciiname":"Huishllac",
    "gn:country_code":"PE",
    "gn:dem":3444,
    "gn:feature_class":"P",
    "gn:feature_code":"PPL",
    "gn:name":"Huishllac",
    "gn:population":0,
    "gn:timezone":"America/Lima",
    "iso:country":"PE",
    "wof:name":"Huishllac",
    "wof:placetype":"locality"
},
  "geometry": {"coordinates":[-76.83372,-9.84992],"type":"Point"}
}