{
  "type": "Feature",
  "properties": {
    "gn:admin1_code":"09",
    "gn:admin2_code":"906.0",
    "gn:admin3_code":"90607.0",
    "gn:asciiname":"Taonayoc",
    "gn:country_code":"PE",
    "gn:dem":4631,
    "gn:feature_class":"P",
    "gn:feature_code":"PPL",
    "gn:name":"Taonayoc",
    "gn:population":0,
    "gn:timezone":"America/Lima",
    "iso:country":"PE",
    "wof:name":"Taonayoc",
    "wof:placetype":"locality"
},
  "geometry": {"coordinates":[-75.05866999999998,-13.25587],"type":"Point"}
}