{
  "type": "Feature",
  "properties": {
    "gn:country":"PE",
    "gn:fcode":"PPLA3",
    "gn:pop":12654,
    "iso:country":"PE",
    "qs:name":"Atuncolla",
    "qs:photos_9r":0,
    "qs:photos_sr":0,
    "qs:pop_sr":"6",
    "wd:wordcount":97,
    "wof:name":"Atuncolla",
    "wof:placetype":"locality",
    "wof:population":12654
},
  "geometry": {"coordinates":[-70.15000000000001,-15.68333],"type":"Point"}
}