{
  "type": "Feature",
  "properties": {
    "gn:admin1_code":"11",
    "gn:admin2_code":"1103.0",
    "gn:admin3_code":"110301.0",
    "gn:asciiname":"Corralones",
    "gn:country_code":"PE",
    "gn:dem":413,
    "gn:feature_class":"P",
    "gn:feature_code":"PPL",
    "gn:name":"Corralones",
    "gn:population":0,
    "gn:timezone":"America/Lima",
    "iso:country":"PE",
    "wof:name":"Corralones",
    "wof:placetype":"locality"
},
  "geometry": {"coordinates":[-75.0902,-14.95575],"type":"Point"}
}