{
  "type": "Feature",
  "properties": {
    "gn:country":"PE",
    "gn:fcode":"PPLA3",
    "gn:pop":25645,
    "iso:country":"PE",
    "name:unk_x_variant":[
        "Marcavelica Hacienda"
    ],
    "qs:name":"Marcavelica",
    "qs:photos_9r":0,
    "qs:photos_sr":0,
    "qs:pop_sr":"7",
    "wd:wordcount":302,
    "wof:name":"Marcavelica",
    "wof:placetype":"locality",
    "wof:population":25645
},
  "geometry": {"coordinates":[-80.70528,-4.87778],"type":"Point"}
}