{
  "type": "Feature",
  "properties": {
    "gn:country":"PE",
    "gn:fcode":"PPLA3",
    "gn:population":25645,
    "iso:country":"PE",
    "name:ceb_x_preferred":[
        "Marcavelica"
    ],
    "name:eng_x_preferred":[
        "Marcavelica District"
    ],
    "name:kat_x_preferred":[
        "\u10db\u10d0\u10e0\u10d9\u10d0\u10d5\u10d4\u10da\u10d8\u10d9\u10d8\u10e1 \u10e0\u10d0\u10d8\u10dd\u10dc\u10d8"
    ],
    "name:por_x_preferred":[
        "Marcavelica"
    ],
    "name:que_x_preferred":[
        "Markawillka distritu"
    ],
    "name:und_x_variant":[
        "Marcavelica Hacienda"
    ],
    "name:zho_x_preferred":[
        "\u99ac\u723e\u5361\u97cb\u5229\u5361\u5340"
    ],
    "qs:name":"Marcavelica",
    "qs:photos_9r":0,
    "qs:photos_sr":0,
    "qs:pop_sr":"7",
    "wd:wordcount":302,
    "wof:name":"Marcavelica",
    "wof:placetype":"locality",
    "wof:population":25645
},
  "geometry": {"coordinates":[-80.70528,-4.87778],"type":"Point"}
}