{
  "type": "Feature",
  "properties": {
    "gn:admin1_code":"15",
    "gn:admin2_code":"1506.0",
    "gn:admin3_code":"150611.0",
    "gn:asciiname":"Aco",
    "gn:country_code":"PE",
    "gn:dem":2625,
    "gn:feature_class":"P",
    "gn:feature_code":"PPL",
    "gn:name":"Aco",
    "gn:population":0,
    "gn:timezone":"America/Lima",
    "iso:country":"PE",
    "name:ceb_x_preferred":[
        "Aco"
    ],
    "name:por_x_preferred":[
        "Aco"
    ],
    "name:spa_x_preferred":[
        "Aco"
    ],
    "name:swe_x_preferred":[
        "Aco"
    ],
    "wof:name":"Aco",
    "wof:placetype":"locality"
},
  "geometry": {"coordinates":[-76.81222,-11.43111],"type":"Point"}
}