{
  "type": "Feature",
  "properties": {
    "gn:admin1_code":"9",
    "gn:admin2_code":"906.0",
    "gn:admin3_code":"90613.0",
    "gn:asciiname":"Huiltacho",
    "gn:country_code":"PE",
    "gn:dem":2082,
    "gn:feature_class":"P",
    "gn:feature_code":"PPL",
    "gn:name":"Huiltacho",
    "gn:population":0,
    "gn:timezone":"America/Lima",
    "iso:country":"PE",
    "wof:name":"Huiltacho",
    "wof:placetype":"locality"
},
  "geometry": {"coordinates":[-75.34416999999998,-13.79722],"type":"Point"}
}