{
  "type": "Feature",
  "properties": {
    "gn:admin1_code":"17.0",
    "gn:admin2_code":"1703.0",
    "gn:asciiname":"Parada",
    "gn:country_code":"PE",
    "gn:dem":290,
    "gn:feature_class":"P",
    "gn:feature_code":"PPL",
    "gn:name":"Parada",
    "gn:population":0,
    "gn:timezone":"America/Lima",
    "iso:country":"PE",
    "name:cat_x_preferred":[
        "Parada"
    ],
    "name:ceb_x_preferred":[
        "Parada"
    ],
    "name:deu_x_preferred":[
        "Parada"
    ],
    "name:eus_x_preferred":[
        "Parada"
    ],
    "name:fra_x_preferred":[
        "Parada"
    ],
    "name:glg_x_preferred":[
        "Parada"
    ],
    "name:nld_x_preferred":[
        "Parada"
    ],
    "name:pol_x_preferred":[
        "Parada"
    ],
    "name:por_x_preferred":[
        "Parada"
    ],
    "name:rus_x_preferred":[
        "\u041f\u0430\u0440\u0430\u0434\u0430"
    ],
    "name:slv_x_preferred":[
        "Parada"
    ],
    "name:spa_x_preferred":[
        "Parada"
    ],
    "name:srp_x_preferred":[
        "\u041f\u0430\u0440\u0430\u0434\u0430"
    ],
    "name:swe_x_preferred":[
        "Parada"
    ],
    "wof:name":"Parada",
    "wof:placetype":"locality"
},
  "geometry": {"coordinates":[-69.51787,-11.12304],"type":"Point"}
}