{
  "type": "Feature",
  "properties": {
    "gn:admin1_code":"06",
    "gn:admin2_code":"608.0",
    "gn:admin3_code":"60809.0",
    "gn:asciiname":"Los Cedros",
    "gn:country_code":"PE",
    "gn:dem":2461,
    "gn:feature_class":"P",
    "gn:feature_code":"PPL",
    "gn:name":"Los Cedros",
    "gn:population":0,
    "gn:timezone":"America/Lima",
    "iso:country":"PE",
    "wof:name":"Los Cedros",
    "wof:placetype":"locality"
},
  "geometry": {"coordinates":[-79.29609000000001,-5.67391],"type":"Point"}
}