{
  "type": "Feature",
  "properties": {
    "gn:admin1_code":"05",
    "gn:admin2_code":"508.0",
    "gn:admin3_code":"50806.0",
    "gn:asciiname":"Puico",
    "gn:country_code":"PE",
    "gn:dem":4621,
    "gn:feature_class":"P",
    "gn:feature_code":"PPL",
    "gn:name":"Puico",
    "gn:population":0,
    "gn:timezone":"America/Lima",
    "iso:country":"PE",
    "wof:name":"Puico",
    "wof:placetype":"locality"
},
  "geometry": {"coordinates":[-73.05069,-15.03275],"type":"Point"}
}