{
  "type": "Feature",
  "properties": {
    "gn:admin1_code":"12.0",
    "gn:admin2_code":"1208.0",
    "gn:admin3_code":"120802.0",
    "gn:asciiname":"Pucacancha",
    "gn:country_code":"PE",
    "gn:dem":4218,
    "gn:feature_class":"P",
    "gn:feature_code":"PPL",
    "gn:name":"Pucacancha",
    "gn:population":0,
    "gn:timezone":"America/Lima",
    "iso:country":"PE",
    "wof:name":"Pucacancha",
    "wof:placetype":"locality"
},
  "geometry": {"coordinates":[-75.88838,-11.7244],"type":"Point"}
}