{
  "type": "Feature",
  "properties": {
    "gn:admin1_code":"11",
    "gn:admin2_code":"1102.0",
    "gn:admin3_code":"110209.0",
    "gn:asciiname":"San Martin de Huarhua",
    "gn:country_code":"PE",
    "gn:dem":3578,
    "gn:feature_class":"P",
    "gn:feature_code":"PPL",
    "gn:name":"San Mart\u00edn de Huarhua",
    "gn:population":0,
    "gn:timezone":"America/Lima",
    "iso:country":"PE",
    "name:spa_x_preferred":[
        "San Mart\u00edn de Huarhua"
    ],
    "name:und_x_variant":[
        "Huarhua"
    ],
    "wof:name":"San Martin de Huarhua",
    "wof:placetype":"locality"
},
  "geometry": {"coordinates":[-75.76156999999998,-13.09169],"type":"Point"}
}