{
  "type": "Feature",
  "properties": {
    "iso:country":"PE",
    "name:eng_x_preferred":[
        "Vir\u00fa"
    ],
    "name:fra_x_preferred":[
        "Vir\u00fa"
    ],
    "name:nld_x_preferred":[
        "Vir\u00fa"
    ],
    "name:que_x_preferred":[
        "Wiru llaqta"
    ],
    "name:spa_x_preferred":[
        "Vir\u00fa"
    ],
    "name:war_x_preferred":[
        "Vir\u00fa"
    ],
    "name:zho_x_preferred":[
        "\u6bd4\u9b6f"
    ],
    "qs:gn_country":"PE",
    "qs:gn_fcode":"PPL",
    "qs:gn_pop":20774,
    "qs:name":"Vir\u00fa",
    "qs:name_adm0":"Per\u00fa",
    "qs:name_adm1":"La Libertad",
    "qs:photos":0,
    "qs:photos_1k":0,
    "qs:photos_9k":1,
    "qs:photos_9r":1,
    "qs:photos_all":2,
    "qs:photos_sr":0,
    "qs:placetype":"Town",
    "qs:pop_sr":"7",
    "qs:woe_adm0":23424919,
    "wd:wordcount":62,
    "wof:name":"Vir\u00fa",
    "wof:placetype":"locality",
    "wof:population":20774
},
  "geometry": {"coordinates":[-78.75201,-8.41554],"type":"Point"}
}