{
  "type": "Feature",
  "properties": {
    "gn:admin1_code":"22.0",
    "gn:admin2_code":"2203.0",
    "gn:admin3_code":"220301.0",
    "gn:asciiname":"Montelaya",
    "gn:country_code":"PE",
    "gn:dem":632,
    "gn:feature_class":"P",
    "gn:feature_code":"PPL",
    "gn:name":"Montelaya",
    "gn:population":0,
    "gn:timezone":"America/Lima",
    "iso:country":"PE",
    "name:spa_x_preferred":[
        "Montelaya"
    ],
    "wof:name":"Montelaya",
    "wof:placetype":"locality"
},
  "geometry": {"coordinates":[-76.68033,-6.53796],"type":"Point"}
}