{
  "type": "Feature",
  "properties": {
    "gn:admin1_code":"15",
    "gn:admin2_code":"1504.0",
    "gn:admin3_code":"150406.0",
    "gn:asciiname":"Cacan",
    "gn:country_code":"PE",
    "gn:dem":4624,
    "gn:feature_class":"P",
    "gn:feature_code":"PPL",
    "gn:name":"Cacan",
    "gn:population":0,
    "gn:timezone":"America/Lima",
    "iso:country":"PE",
    "wof:name":"Cacan",
    "wof:placetype":"locality"
},
  "geometry": {"coordinates":[-76.64778000000003,-11.39028],"type":"Point"}
}