{
  "type": "Feature",
  "properties": {
    "gn:admin1_code":"17.0",
    "gn:admin2_code":"1701.0",
    "gn:asciiname":"Playa Alta",
    "gn:country_code":"PE",
    "gn:dem":192,
    "gn:feature_class":"P",
    "gn:feature_code":"PPL",
    "gn:name":"Playa Alta",
    "gn:population":0,
    "gn:timezone":"America/Lima",
    "iso:country":"PE",
    "name:spa_x_preferred":[
        "Playa Alta"
    ],
    "wof:name":"Playa Alta",
    "wof:placetype":"locality"
},
  "geometry": {"coordinates":[-69.35863000000001,-12.5132],"type":"Point"}
}