{
  "type": "Feature",
  "properties": {
    "gn:admin1_code":"08",
    "gn:admin2_code":"809.0",
    "gn:admin3_code":"80906.0",
    "gn:asciiname":"Tunquimayo",
    "gn:country_code":"PE",
    "gn:dem":911,
    "gn:feature_class":"P",
    "gn:feature_code":"PPL",
    "gn:name":"Tunquimayo",
    "gn:population":0,
    "gn:timezone":"America/Lima",
    "iso:country":"PE",
    "wof:name":"Tunquimayo",
    "wof:placetype":"locality"
},
  "geometry": {"coordinates":[-72.48464,-12.62485],"type":"Point"}
}