{
  "type": "Feature",
  "properties": {
    "gn:admin1_code":"9.0",
    "gn:admin2_code":"905.0",
    "gn:admin3_code":"90507.0",
    "gn:asciiname":"Chunumastana",
    "gn:country_code":"PE",
    "gn:dem":3619,
    "gn:feature_class":"P",
    "gn:feature_code":"PPL",
    "gn:name":"Chu\u00f1umastana",
    "gn:population":0,
    "gn:timezone":"America/Lima",
    "iso:country":"PE",
    "wof:name":"Chunumastana",
    "wof:placetype":"locality"
},
  "geometry": {"coordinates":[-74.56868,-12.54935],"type":"Point"}
}