{
  "type": "Feature",
  "properties": {
    "gn:admin1_code":"20",
    "gn:admin2_code":"2001.0",
    "gn:admin3_code":"200114.0",
    "gn:asciiname":"Malinguitas",
    "gn:country_code":"PE",
    "gn:dem":81,
    "gn:feature_class":"P",
    "gn:feature_code":"PPL",
    "gn:name":"Malinguitas",
    "gn:population":0,
    "gn:timezone":"America/Lima",
    "iso:country":"PE",
    "name:und_x_variant":[
        "Malingu\u00edtas Hacienda",
        "Malinguitas"
    ],
    "wof:name":"Malinguitas",
    "wof:placetype":"locality"
},
  "geometry": {"coordinates":[-80.25631,-5.02883],"type":"Point"}
}