{
  "type": "Feature",
  "properties": {
    "gn:admin1_code":"21",
    "gn:admin2_code":"2111.0",
    "gn:admin3_code":"211104.0",
    "gn:asciiname":"Hacienda Yachahuy",
    "gn:country_code":"PE",
    "gn:dem":3820,
    "gn:feature_class":"P",
    "gn:feature_code":"PPL",
    "gn:name":"Hacienda Yachahuy",
    "gn:population":0,
    "gn:timezone":"America/Lima",
    "iso:country":"PE",
    "wof:name":"Hacienda Yachahuy",
    "wof:placetype":"locality"
},
  "geometry": {"coordinates":[-69.97991999999999,-15.55248],"type":"Point"}
}