{
  "type": "Feature",
  "properties": {
    "gn:admin1_code":"9.0",
    "gn:admin2_code":"907.0",
    "gn:admin3_code":"90705.0",
    "gn:asciiname":"Fundo Catapampa",
    "gn:country_code":"PE",
    "gn:dem":3857,
    "gn:feature_class":"P",
    "gn:feature_code":"PPL",
    "gn:name":"Fundo Catapampa",
    "gn:population":0,
    "gn:timezone":"America/Lima",
    "iso:country":"PE",
    "wof:name":"Fundo Catapampa",
    "wof:placetype":"locality"
},
  "geometry": {"coordinates":[-74.78978000000002,-12.39007],"type":"Point"}
}