{
  "type": "Feature",
  "properties": {
    "gn:admin1_code":"21",
    "gn:admin2_code":"2109.0",
    "gn:admin3_code":"210901.0",
    "gn:asciiname":"Ninantaya",
    "gn:country_code":"PE",
    "gn:dem":3903,
    "gn:feature_class":"P",
    "gn:feature_code":"PPL",
    "gn:name":"Ninantaya",
    "gn:population":0,
    "gn:timezone":"America/Lima",
    "iso:country":"PE",
    "name:und_x_variant":[
        "Hacienda Ninantaya",
        "Minantaya",
        "Ninantaya Hacienda",
        "Ninantaya"
    ],
    "wof:name":"Ninantaya",
    "wof:placetype":"locality"
},
  "geometry": {"coordinates":[-69.33017,-15.44925],"type":"Point"}
}