{
  "type": "Feature",
  "properties": {
    "gn:admin1_code":"10.0",
    "gn:admin2_code":"1006.0",
    "gn:admin3_code":"100604.0",
    "gn:asciiname":"Rio Frio",
    "gn:country_code":"PE",
    "gn:dem":616,
    "gn:feature_class":"P",
    "gn:feature_code":"PPL",
    "gn:name":"R\u00edo Fr\u00edo",
    "gn:population":0,
    "gn:timezone":"America/Lima",
    "iso:country":"PE",
    "wof:name":"Rio Frio",
    "wof:placetype":"locality"
},
  "geometry": {"coordinates":[-76.0909,-8.97435],"type":"Point"}
}