{
  "type": "Feature",
  "properties": {
    "gn:admin1_code":"02",
    "gn:admin2_code":"214.0",
    "gn:admin3_code":"21406.0",
    "gn:asciiname":"Congas",
    "gn:country_code":"PE",
    "gn:dem":3078,
    "gn:feature_class":"P",
    "gn:feature_code":"PPLA3",
    "gn:name":"Congas",
    "gn:population":0,
    "gn:timezone":"America/Lima",
    "iso:country":"PE",
    "wof:name":"Congas",
    "wof:placetype":"locality"
},
  "geometry": {"coordinates":[-77.44188,-10.33712],"type":"Point"}
}