{
  "type": "Feature",
  "properties": {
    "gn:admin1_code":"21",
    "gn:admin2_code":"2104.0",
    "gn:admin3_code":"210402.0",
    "gn:asciiname":"Iruvilque",
    "gn:country_code":"PE",
    "gn:dem":3846,
    "gn:feature_class":"P",
    "gn:feature_code":"PPL",
    "gn:name":"Iruvilque",
    "gn:population":0,
    "gn:timezone":"America/Lima",
    "iso:country":"PE",
    "wof:name":"Iruvilque",
    "wof:placetype":"locality"
},
  "geometry": {"coordinates":[-69.09858,-16.56777],"type":"Point"}
}