{
  "type": "Feature",
  "properties": {
    "gn:country":"PE",
    "gn:fcode":"PPLA3",
    "gn:pop":7281,
    "iso:country":"PE",
    "name:unk_x_variant":[
        "Cajarura"
    ],
    "qs:name":"Cajaruro",
    "qs:photos_9r":0,
    "qs:photos_sr":0,
    "qs:pop_sr":"5",
    "wd:wordcount":48,
    "wof:name":"Cajaruro",
    "wof:placetype":"locality",
    "wof:population":7281
},
  "geometry": {"coordinates":[-78.42556,-5.73639],"type":"Point"}
}