{
  "type": "Feature",
  "properties": {
    "gn:country":"PE",
    "gn:fcode":"PPLA3",
    "gn:pop":7281,
    "iso:country":"PE",
    "name:ceb_x_preferred":[
        "Cajaruro"
    ],
    "name:eng_x_preferred":[
        "Cajaruro District"
    ],
    "name:kat_x_preferred":[
        "\u10d9\u10d0\u10ee\u10d0\u10e0\u10e3\u10e0\u10dd\u10e1 \u10e0\u10d0\u10d8\u10dd\u10dc\u10d8"
    ],
    "name:nld_x_preferred":[
        "Cajaruro District"
    ],
    "name:nob_x_preferred":[
        "Cajaruro"
    ],
    "name:por_x_preferred":[
        "Cajaruro"
    ],
    "name:que_x_preferred":[
        "Kasharuru distritu"
    ],
    "name:unk_x_variant":[
        "Cajarura"
    ],
    "name:zho_x_preferred":[
        "\u5361\u54c8\u9b6f\u7f85\u5340"
    ],
    "qs:name":"Cajaruro",
    "qs:photos_9r":0,
    "qs:photos_sr":0,
    "qs:pop_sr":"5",
    "wd:wordcount":48,
    "wof:name":"Cajaruro",
    "wof:placetype":"locality",
    "wof:population":7281
},
  "geometry": {"coordinates":[-78.42556,-5.73639],"type":"Point"}
}