{
  "type": "Feature",
  "properties": {
    "gn:admin1_code":"9.0",
    "gn:admin2_code":"905.0",
    "gn:asciiname":"Jaraj Cancha",
    "gn:country_code":"PE",
    "gn:dem":3544,
    "gn:feature_class":"P",
    "gn:feature_code":"PPL",
    "gn:name":"Jaraj Cancha",
    "gn:population":0,
    "gn:timezone":"America/Lima",
    "iso:country":"PE",
    "wof:name":"Jaraj Cancha",
    "wof:placetype":"locality"
},
  "geometry": {"coordinates":[-74.49018000000002,-12.51793],"type":"Point"}
}