{
  "type": "Feature",
  "properties": {
    "gn:admin1_code":"10.0",
    "gn:admin2_code":"1001.0",
    "gn:admin3_code":"100109.0",
    "gn:asciiname":"San Juanpampa",
    "gn:country_code":"PE",
    "gn:dem":2902,
    "gn:feature_class":"P",
    "gn:feature_code":"PPL",
    "gn:name":"San Juanpampa",
    "gn:population":0,
    "gn:timezone":"America/Lima",
    "iso:country":"PE",
    "wof:name":"San Juanpampa",
    "wof:placetype":"locality"
},
  "geometry": {"coordinates":[-76.35637,-9.83185],"type":"Point"}
}