{
  "type": "Feature",
  "properties": {
    "gn:admin1_code":"9",
    "gn:admin2_code":"901.0",
    "gn:asciiname":"Una Astococha",
    "gn:country_code":"PE",
    "gn:dem":4674,
    "gn:feature_class":"P",
    "gn:feature_code":"PPL",
    "gn:name":"U\u00f1a Astococha",
    "gn:population":0,
    "gn:timezone":"America/Lima",
    "iso:country":"PE",
    "wof:name":"Una Astococha",
    "wof:placetype":"locality"
},
  "geometry": {"coordinates":[-75.50553000000002,-12.70411],"type":"Point"}
}