{
  "type": "Feature",
  "properties": {
    "gn:admin1_code":"08",
    "gn:admin2_code":"808.0",
    "gn:admin3_code":"80804.0",
    "gn:asciiname":"Caracollo",
    "gn:country_code":"PE",
    "gn:dem":4174,
    "gn:feature_class":"P",
    "gn:feature_code":"PPL",
    "gn:name":"Caracollo",
    "gn:population":0,
    "gn:timezone":"America/Lima",
    "iso:country":"PE",
    "name:ceb_x_preferred":[
        "Caracollo"
    ],
    "name:deu_x_preferred":[
        "Caracollo"
    ],
    "name:que_x_preferred":[
        "Q'araqullu"
    ],
    "name:spa_x_preferred":[
        "Caracollo"
    ],
    "name:swe_x_preferred":[
        "Caracollo"
    ],
    "name:zho_x_preferred":[
        "\u5361\u62c9\u79d1\u7d04"
    ],
    "wof:name":"Caracollo",
    "wof:placetype":"locality"
},
  "geometry": {"coordinates":[-71.14416999999997,-15.07167],"type":"Point"}
}