{
  "type": "Feature",
  "properties": {
    "gn:admin1_code":"2.0",
    "gn:admin2_code":"203.0",
    "gn:admin3_code":"20306.0",
    "gn:asciiname":"Curva",
    "gn:country_code":"PE",
    "gn:dem":3406,
    "gn:feature_class":"P",
    "gn:feature_code":"PPL",
    "gn:name":"Curva",
    "gn:population":0,
    "gn:timezone":"America/Lima",
    "iso:country":"PE",
    "wof:name":"Curva",
    "wof:placetype":"locality"
},
  "geometry": {"coordinates":[-76.99559000000001,-9.19049],"type":"Point"}
}