{
  "type": "Feature",
  "properties": {
    "gn:admin1_code":"8",
    "gn:admin2_code":"809.0",
    "gn:admin3_code":"80902.0",
    "gn:asciiname":"Coribeni",
    "gn:country_code":"PE",
    "gn:dem":680,
    "gn:feature_class":"P",
    "gn:feature_code":"PPL",
    "gn:name":"Coribeni",
    "gn:population":0,
    "gn:timezone":"America/Lima",
    "iso:country":"PE",
    "wof:name":"Coribeni",
    "wof:placetype":"locality"
},
  "geometry": {"coordinates":[-72.83644,-12.61665],"type":"Point"}
}