{
  "type": "Feature",
  "properties": {
    "gn:admin1_code":"3",
    "gn:admin2_code":"302.0",
    "gn:admin3_code":"30215.0",
    "gn:asciiname":"Macmajocha",
    "gn:country_code":"PE",
    "gn:dem":4172,
    "gn:feature_class":"P",
    "gn:feature_code":"PPL",
    "gn:name":"Macmajocha",
    "gn:population":0,
    "gn:timezone":"America/Lima",
    "iso:country":"PE",
    "wof:name":"Macmajocha",
    "wof:placetype":"locality"
},
  "geometry": {"coordinates":[-73.57375999999999,-13.60899],"type":"Point"}
}