{
  "type": "Feature",
  "properties": {
    "gn:admin1_code":"15.0",
    "gn:admin2_code":"1505.0",
    "gn:admin3_code":"150504.0",
    "gn:asciiname":"Dona Rosa",
    "gn:country_code":"PE",
    "gn:dem":6,
    "gn:feature_class":"P",
    "gn:feature_code":"PPL",
    "gn:name":"Do\u00f1a Rosa",
    "gn:population":0,
    "gn:timezone":"America/Lima",
    "iso:country":"PE",
    "wof:name":"Dona Rosa",
    "wof:placetype":"locality"
},
  "geometry": {"coordinates":[-76.44826999999999,-13.03274],"type":"Point"}
}