{
  "type": "Feature",
  "properties": {
    "gn:admin1_code":"15",
    "gn:admin2_code":"1510.0",
    "gn:admin3_code":"151001.0",
    "gn:asciiname":"Shina",
    "gn:country_code":"PE",
    "gn:dem":3974,
    "gn:feature_class":"P",
    "gn:feature_code":"PPL",
    "gn:name":"Shina",
    "gn:population":0,
    "gn:timezone":"America/Lima",
    "iso:country":"PE",
    "name:ceb_x_preferred":[
        "Shina"
    ],
    "name:swe_x_preferred":[
        "Shina"
    ],
    "name:uzb_x_preferred":[
        "Shina"
    ],
    "name:zho_x_preferred":[
        "\u652f\u90a3"
    ],
    "wof:name":"Shina",
    "wof:placetype":"locality"
},
  "geometry": {"coordinates":[-76.01441,-12.53009],"type":"Point"}
}