{
  "type": "Feature",
  "properties": {
    "gn:admin1_code":"2.0",
    "gn:admin2_code":"220.0",
    "gn:admin3_code":"22001.0",
    "gn:asciiname":"Chuquibamba",
    "gn:country_code":"PE",
    "gn:dem":2506,
    "gn:feature_class":"P",
    "gn:feature_code":"PPL",
    "gn:name":"Chuquibamba",
    "gn:population":0,
    "gn:timezone":"America/Lima",
    "iso:country":"PE",
    "name:ita_x_preferred":[
        "Chuquibamba"
    ],
    "name:lit_x_preferred":[
        "\u010cukibamba"
    ],
    "name:pol_x_preferred":[
        "Chuquibamba"
    ],
    "name:por_x_preferred":[
        "Chuquibamba"
    ],
    "name:que_x_preferred":[
        "Chuqipampa"
    ],
    "name:ron_x_preferred":[
        "Chuquibamba"
    ],
    "name:spa_x_preferred":[
        "Chuquibamba"
    ],
    "name:war_x_preferred":[
        "Chuquibamba"
    ],
    "name:zho_x_preferred":[
        "\u4e18\u57fa\u73ed\u5df4"
    ],
    "wof:name":"Chuquibamba",
    "wof:placetype":"locality"
},
  "geometry": {"coordinates":[-77.73666999999998,-9.15778],"type":"Point"}
}