{
  "type": "Feature",
  "properties": {
    "gn:admin1_code":"14.0",
    "gn:admin2_code":"1403.0",
    "gn:admin3_code":"140301.0",
    "gn:asciiname":"Santa Elena",
    "gn:country_code":"PE",
    "gn:dem":21,
    "gn:feature_class":"P",
    "gn:feature_code":"PPL",
    "gn:name":"Santa Elena",
    "gn:population":0,
    "gn:timezone":"America/Lima",
    "iso:country":"PE",
    "name:spa_x_preferred":[
        "Santa Elena"
    ],
    "wof:name":"Santa Elena",
    "wof:placetype":"locality"
},
  "geometry": {"coordinates":[-79.88181,-6.70126],"type":"Point"}
}