{
  "type": "Feature",
  "properties": {
    "gn:admin1_code":"14",
    "gn:admin2_code":"1403.0",
    "gn:admin3_code":"140306.0",
    "gn:asciiname":"Tranca Sasape",
    "gn:country_code":"PE",
    "gn:dem":37,
    "gn:feature_class":"P",
    "gn:feature_code":"PPL",
    "gn:name":"Tranca Sasape",
    "gn:population":0,
    "gn:timezone":"America/Lima",
    "iso:country":"PE",
    "wof:name":"Tranca Sasape",
    "wof:placetype":"locality"
},
  "geometry": {"coordinates":[-79.93035999999999,-6.49345],"type":"Point"}
}