{
  "type": "Feature",
  "properties": {
    "gn:admin1_code":"15.0",
    "gn:admin2_code":"1508.0",
    "gn:admin3_code":"150811.0",
    "gn:asciiname":"Don Alberto",
    "gn:country_code":"PE",
    "gn:dem":428,
    "gn:feature_class":"P",
    "gn:feature_code":"PPL",
    "gn:name":"Don Alberto",
    "gn:population":0,
    "gn:timezone":"America/Lima",
    "iso:country":"PE",
    "wof:name":"Don Alberto",
    "wof:placetype":"locality"
},
  "geometry": {"coordinates":[-77.32722,-11.25472],"type":"Point"}
}