{
  "type": "Feature",
  "properties": {
    "gn:admin1_code":"4.0",
    "gn:admin2_code":"408.0",
    "gn:admin3_code":"40803.0",
    "gn:asciiname":"Huayrapjunco",
    "gn:country_code":"PE",
    "gn:dem":1863,
    "gn:feature_class":"P",
    "gn:feature_code":"PPL",
    "gn:name":"Huayrapjunco",
    "gn:population":0,
    "gn:timezone":"America/Lima",
    "iso:country":"PE",
    "name:spa_x_preferred":[
        "Huayrapjunco"
    ],
    "wof:name":"Huayrapjunco",
    "wof:placetype":"locality"
},
  "geometry": {"coordinates":[-73.00497,-15.25585],"type":"Point"}
}