{
  "type": "Feature",
  "properties": {
    "gn:admin1_code":"08",
    "gn:admin2_code":"808.0",
    "gn:admin3_code":"80807.0",
    "gn:asciiname":"Puca Puca",
    "gn:country_code":"PE",
    "gn:dem":4784,
    "gn:feature_class":"P",
    "gn:feature_code":"PPL",
    "gn:name":"Puca Puca",
    "gn:population":0,
    "gn:timezone":"America/Lima",
    "iso:country":"PE",
    "wof:name":"Puca Puca",
    "wof:placetype":"locality"
},
  "geometry": {"coordinates":[-71.74842,-15.06419],"type":"Point"}
}