{
  "type": "Feature",
  "properties": {
    "gn:admin1_code":"4",
    "gn:admin2_code":"408.0",
    "gn:admin3_code":"40806.0",
    "gn:asciiname":"Pacupata",
    "gn:country_code":"PE",
    "gn:dem":4456,
    "gn:feature_class":"P",
    "gn:feature_code":"PPL",
    "gn:name":"Pacupata",
    "gn:population":0,
    "gn:timezone":"America/Lima",
    "iso:country":"PE",
    "wof:name":"Pacupata",
    "wof:placetype":"locality"
},
  "geometry": {"coordinates":[-72.51794,-15.00805],"type":"Point"}
}