{
  "type": "Feature",
  "properties": {
    "gn:country":"PE",
    "gn:fcode":"PPLA3",
    "gn:pop":12915,
    "iso:country":"PE",
    "qs:name":"Vice",
    "qs:photos_9r":0,
    "qs:photos_sr":0,
    "qs:pop_sr":"6",
    "wd:wordcount":1896,
    "wof:name":"Vice",
    "wof:placetype":"locality",
    "wof:population":12915
},
  "geometry": {"coordinates":[-80.78333000000001,-5.41667],"type":"Point"}
}