{
  "type": "Feature",
  "properties": {
    "gn:admin1_code":"22.0",
    "gn:admin2_code":"2202.0",
    "gn:admin3_code":"220205.0",
    "gn:asciiname":"San Cosme",
    "gn:country_code":"PE",
    "gn:dem":280,
    "gn:feature_class":"P",
    "gn:feature_code":"PPL",
    "gn:name":"San Cosme",
    "gn:population":0,
    "gn:timezone":"America/Lima",
    "iso:country":"PE",
    "name:ceb_x_preferred":[
        "San Cosme"
    ],
    "name:deu_x_preferred":[
        "San Cosme"
    ],
    "name:glg_x_preferred":[
        "San Cosme"
    ],
    "name:nld_x_preferred":[
        "San Cosme"
    ],
    "name:spa_x_preferred":[
        "San Cosme"
    ],
    "name:swe_x_preferred":[
        "San Cosme"
    ],
    "wof:name":"San Cosme",
    "wof:placetype":"locality"
},
  "geometry": {"coordinates":[-76.56135,-6.80488],"type":"Point"}
}