{
  "type": "Feature",
  "properties": {
    "gn:admin1_code":"05",
    "gn:admin2_code":"502.0",
    "gn:admin3_code":"50202.0",
    "gn:asciiname":"Totorapampa",
    "gn:country_code":"PE",
    "gn:dem":3753,
    "gn:feature_class":"P",
    "gn:feature_code":"PPL",
    "gn:name":"Totorapampa",
    "gn:population":0,
    "gn:timezone":"America/Lima",
    "iso:country":"PE",
    "wof:name":"Totorapampa",
    "wof:placetype":"locality"
},
  "geometry": {"coordinates":[-74.34999999999999,-13.56667],"type":"Point"}
}