{
  "type": "Feature",
  "properties": {
    "gn:admin1_code":"14",
    "gn:admin2_code":"1401.0",
    "gn:admin3_code":"140116.0",
    "gn:asciiname":"El Cafetal",
    "gn:country_code":"PE",
    "gn:dem":102,
    "gn:feature_class":"P",
    "gn:feature_code":"PPL",
    "gn:name":"El Cafetal",
    "gn:population":0,
    "gn:timezone":"America/Lima",
    "iso:country":"PE",
    "name:spa_x_preferred":[
        "El Cafetal"
    ],
    "name:spa_x_variant":[
        "Cafetal"
    ],
    "wof:name":"El Cafetal",
    "wof:placetype":"locality"
},
  "geometry": {"coordinates":[-79.52676,-6.8813],"type":"Point"}
}