{
  "type": "Feature",
  "properties": {
    "gn:admin1_code":"10",
    "gn:admin2_code":"1002.0",
    "gn:admin3_code":"100205.0",
    "gn:asciiname":"Chico",
    "gn:country_code":"PE",
    "gn:dem":2243,
    "gn:feature_class":"P",
    "gn:feature_code":"PPL",
    "gn:name":"Chico",
    "gn:population":0,
    "gn:timezone":"America/Lima",
    "iso:country":"PE",
    "name:ara_x_preferred":[
        "\u0634\u064a\u0643\u0648"
    ],
    "name:ceb_x_preferred":[
        "Chico"
    ],
    "name:ces_x_preferred":[
        "Chico"
    ],
    "name:deu_x_preferred":[
        "Chico"
    ],
    "name:fra_x_preferred":[
        "Chico"
    ],
    "name:hrv_x_preferred":[
        "Chico"
    ],
    "name:hun_x_preferred":[
        "Chico"
    ],
    "name:ind_x_preferred":[
        "Chico"
    ],
    "name:ita_x_preferred":[
        "Chico"
    ],
    "name:pol_x_preferred":[
        "Chico"
    ],
    "name:por_x_preferred":[
        "Chico"
    ],
    "name:spa_x_preferred":[
        "Chico"
    ],
    "name:swe_x_preferred":[
        "Chico"
    ],
    "name:tgl_x_preferred":[
        "Chico"
    ],
    "name:ukr_x_preferred":[
        "\u0427\u0456\u043a\u043e"
    ],
    "name:ukr_x_variant":[
        "\u0427\u0438\u043a\u043e"
    ],
    "name:urd_x_preferred":[
        "\u0686\u06cc\u06a9\u0648"
    ],
    "name:vie_x_preferred":[
        "S\u00f4ng Chico"
    ],
    "name:vol_x_preferred":[
        "Chico"
    ],
    "name:war_x_preferred":[
        "Chico"
    ],
    "name:zho_cn_x_preferred":[
        "\u5947\u79d1\u6cb3"
    ],
    "name:zho_tw_x_preferred":[
        "\u5947\u79d1\u6cb3"
    ],
    "wof:name":"Chico",
    "wof:placetype":"locality"
},
  "geometry": {"coordinates":[-76.26148999999999,-10.23292],"type":"Point"}
}