{
  "type": "Feature",
  "properties": {
    "gn:admin1_code":"05",
    "gn:admin2_code":"508.0",
    "gn:admin3_code":"50806.0",
    "gn:asciiname":"Santa Ana de Huaycahuacho",
    "gn:country_code":"PE",
    "gn:dem":4618,
    "gn:feature_class":"P",
    "gn:feature_code":"PPL",
    "gn:name":"Santa Ana de Huaycahuacho",
    "gn:population":0,
    "gn:timezone":"America/Lima",
    "iso:country":"PE",
    "wof:name":"Santa Ana de Huaycahuacho",
    "wof:placetype":"locality"
},
  "geometry": {"coordinates":[-73.21666999999999,-14.95],"type":"Point"}
}