{
  "type": "Feature",
  "properties": {
    "gn:admin1_code":"5",
    "gn:admin2_code":"507.0",
    "gn:admin3_code":"50702.0",
    "gn:asciiname":"Bellavista",
    "gn:country_code":"PE",
    "gn:dem":3689,
    "gn:feature_class":"P",
    "gn:feature_code":"PPL",
    "gn:name":"Bellavista",
    "gn:population":0,
    "gn:timezone":"America/Lima",
    "iso:country":"PE",
    "name:cat_x_preferred":[
        "Bellavista"
    ],
    "name:ceb_x_preferred":[
        "Bellavista"
    ],
    "name:deu_x_preferred":[
        "Bellavista"
    ],
    "name:fra_x_preferred":[
        "Bellavista"
    ],
    "name:ita_x_preferred":[
        "Bellavista"
    ],
    "name:kor_x_preferred":[
        "\ubca8\ub77c\ube44\uc2a4\ud0c0"
    ],
    "name:nld_x_preferred":[
        "Bellavista"
    ],
    "name:pol_x_preferred":[
        "Bellavista"
    ],
    "name:por_x_preferred":[
        "Bellavista"
    ],
    "name:spa_x_preferred":[
        "Bellavista"
    ],
    "name:srp_x_preferred":[
        "Bellavista"
    ],
    "name:swe_x_preferred":[
        "Bellavista"
    ],
    "wof:name":"Bellavista",
    "wof:placetype":"locality"
},
  "geometry": {"coordinates":[-73.7085,-15.06185],"type":"Point"}
}