{
  "type": "Feature",
  "properties": {
    "gn:admin1_code":"5.0",
    "gn:admin2_code":"507.0",
    "gn:admin3_code":"50705.0",
    "gn:asciiname":"Sayhuayocc",
    "gn:country_code":"PE",
    "gn:dem":3667,
    "gn:feature_class":"P",
    "gn:feature_code":"PPL",
    "gn:name":"Sayhuayocc",
    "gn:population":0,
    "gn:timezone":"America/Lima",
    "iso:country":"PE",
    "name:spa_x_preferred":[
        "Sayhuayocc"
    ],
    "wof:name":"Sayhuayocc",
    "wof:placetype":"locality"
},
  "geometry": {"coordinates":[-73.95423000000002,-15.25554],"type":"Point"}
}