{
  "type": "Feature",
  "properties": {
    "gn:admin1_code":"15",
    "gn:admin2_code":"1507.0",
    "gn:admin3_code":"150720.0",
    "gn:asciiname":"Laguna Puyhuancoto",
    "gn:country_code":"PE",
    "gn:dem":4685,
    "gn:feature_class":"P",
    "gn:feature_code":"PPL",
    "gn:name":"Laguna Puyhuancoto",
    "gn:population":0,
    "gn:timezone":"America/Lima",
    "iso:country":"PE",
    "wof:name":"Laguna Puyhuancoto",
    "wof:placetype":"locality"
},
  "geometry": {"coordinates":[-76.16500000000001,-11.90389],"type":"Point"}
}