{
  "type": "Feature",
  "properties": {
    "gn:admin1_code":"12.0",
    "gn:admin2_code":"1206.0",
    "gn:admin3_code":"120608.0",
    "gn:asciiname":"San Miguel de Otica",
    "gn:country_code":"PE",
    "gn:dem":283,
    "gn:feature_class":"P",
    "gn:feature_code":"PPL",
    "gn:name":"San Miguel de \u00d3tica",
    "gn:population":0,
    "gn:timezone":"America/Lima",
    "iso:country":"PE",
    "name:und_x_variant":[
        "San Miguel de \u00d3tica",
        "Mat\u00edas"
    ],
    "wof:name":"San Miguel de Otica",
    "wof:placetype":"locality"
},
  "geometry": {"coordinates":[-73.91754,-11.20727],"type":"Point"}
}