{
  "type": "Feature",
  "properties": {
    "gn:admin1_code":"11",
    "gn:admin2_code":"1101.0",
    "gn:admin3_code":"110101.0",
    "gn:asciiname":"Foronda",
    "gn:country_code":"PE",
    "gn:dem":413,
    "gn:feature_class":"P",
    "gn:feature_code":"PPL",
    "gn:name":"Foronda",
    "gn:population":0,
    "gn:timezone":"America/Lima",
    "iso:country":"PE",
    "wof:name":"Foronda",
    "wof:placetype":"locality"
},
  "geometry": {"coordinates":[-75.73333000000002,-14.05],"type":"Point"}
}