{
  "type": "Feature",
  "properties": {
    "gn:admin1_code":"13",
    "gn:admin2_code":"1304.0",
    "gn:admin3_code":"130402.0",
    "gn:asciiname":"Huaca Llerena",
    "gn:country_code":"PE",
    "gn:dem":52,
    "gn:feature_class":"P",
    "gn:feature_code":"PPL",
    "gn:name":"Huaca Llerena",
    "gn:population":0,
    "gn:timezone":"America/Lima",
    "iso:country":"PE",
    "wof:name":"Huaca Llerena",
    "wof:placetype":"locality"
},
  "geometry": {"coordinates":[-79.55,-7.13333],"type":"Point"}
}