{
  "type": "Feature",
  "properties": {
    "gn:admin1_code":"5",
    "gn:admin2_code":"506.0",
    "gn:admin3_code":"50607.0",
    "gn:asciiname":"Payllihua",
    "gn:country_code":"PE",
    "gn:dem":1650,
    "gn:feature_class":"P",
    "gn:feature_code":"PPL",
    "gn:name":"Payllihua",
    "gn:population":0,
    "gn:timezone":"America/Lima",
    "iso:country":"PE",
    "wof:name":"Payllihua",
    "wof:placetype":"locality"
},
  "geometry": {"coordinates":[-75.02755000000001,-14.11149],"type":"Point"}
}