{
  "type": "Feature",
  "properties": {
    "gn:admin1_code":"02",
    "gn:admin2_code":"214.0",
    "gn:admin3_code":"21406.0",
    "gn:asciiname":"Miramar",
    "gn:country_code":"PE",
    "gn:dem":3149,
    "gn:feature_class":"P",
    "gn:feature_code":"PPL",
    "gn:name":"Miramar",
    "gn:population":0,
    "gn:timezone":"America/Lima",
    "iso:country":"PE",
    "wof:name":"Miramar",
    "wof:placetype":"locality"
},
  "geometry": {"coordinates":[-77.46533000000002,-10.32023],"type":"Point"}
}