{
  "type": "Feature",
  "properties": {
    "gn:admin1_code":"05",
    "gn:admin2_code":"509.0",
    "gn:admin3_code":"50905.0",
    "gn:asciiname":"Llama Huasi",
    "gn:country_code":"PE",
    "gn:dem":4349,
    "gn:feature_class":"P",
    "gn:feature_code":"PPL",
    "gn:name":"Llama Huasi",
    "gn:population":0,
    "gn:timezone":"America/Lima",
    "iso:country":"PE",
    "wof:name":"Llama Huasi",
    "wof:placetype":"locality"
},
  "geometry": {"coordinates":[-73.83111,-14.19389],"type":"Point"}
}