{
  "type": "Feature",
  "properties": {
    "gn:admin1_code":"05",
    "gn:admin2_code":"508.0",
    "gn:admin3_code":"50805.0",
    "gn:asciiname":"Marcabamba",
    "gn:country_code":"PE",
    "gn:dem":2584,
    "gn:feature_class":"P",
    "gn:feature_code":"PPLA3",
    "gn:name":"Marcabamba",
    "gn:population":0,
    "gn:timezone":"America/Lima",
    "iso:country":"PE",
    "wof:name":"Marcabamba",
    "wof:placetype":"locality"
},
  "geometry": {"coordinates":[-73.34194000000002,-15.15056],"type":"Point"}
}