{
  "type": "Feature",
  "properties": {
    "gn:admin1_code":"21",
    "gn:admin2_code":"2104.0",
    "gn:admin3_code":"210407.0",
    "gn:asciiname":"Larajo",
    "gn:country_code":"PE",
    "gn:dem":3862,
    "gn:feature_class":"P",
    "gn:feature_code":"PPL",
    "gn:name":"Larajo",
    "gn:population":0,
    "gn:timezone":"America/Lima",
    "iso:country":"PE",
    "wof:name":"Larajo",
    "wof:placetype":"locality"
},
  "geometry": {"coordinates":[-69.17364000000001,-16.52383],"type":"Point"}
}