{
  "type": "Feature",
  "properties": {
    "gn:admin1_code":"14",
    "gn:admin2_code":"1403.0",
    "gn:admin3_code":"140310.0",
    "gn:asciiname":"Tempon Bajo",
    "gn:country_code":"PE",
    "gn:dem":123,
    "gn:feature_class":"P",
    "gn:feature_code":"PPL",
    "gn:name":"Temp\u00f3n Bajo",
    "gn:population":0,
    "gn:timezone":"America/Lima",
    "iso:country":"PE",
    "wof:name":"Tempon Bajo",
    "wof:placetype":"locality"
},
  "geometry": {"coordinates":[-79.66433000000001,-6.27896],"type":"Point"}
}