{
  "type": "Feature",
  "properties": {
    "gn:admin1_code":"23",
    "gn:admin2_code":"2304.0",
    "gn:admin3_code":"230403.0",
    "gn:asciiname":"Palquilla",
    "gn:country_code":"PE",
    "gn:dem":3494,
    "gn:feature_class":"P",
    "gn:feature_code":"PPL",
    "gn:name":"Palquilla",
    "gn:population":0,
    "gn:timezone":"America/Lima",
    "iso:country":"PE",
    "wof:name":"Palquilla",
    "wof:placetype":"locality"
},
  "geometry": {"coordinates":[-70.01208000000001,-17.58974],"type":"Point"}
}