{
  "type": "Feature",
  "properties": {
    "gn:admin1_code":"23",
    "gn:admin2_code":"2304.0",
    "gn:admin3_code":"230402.0",
    "gn:asciiname":"Coropuro",
    "gn:country_code":"PE",
    "gn:dem":1756,
    "gn:feature_class":"P",
    "gn:feature_code":"PPL",
    "gn:name":"Coropuro",
    "gn:population":0,
    "gn:timezone":"America/Lima",
    "iso:country":"PE",
    "wof:name":"Coropuro",
    "wof:placetype":"locality"
},
  "geometry": {"coordinates":[-70.26519,-17.47892],"type":"Point"}
}