{
  "type": "Feature",
  "properties": {
    "gn:admin1_code":"12",
    "gn:admin2_code":"1207.0",
    "gn:admin3_code":"120707.0",
    "gn:asciiname":"Cuaganno",
    "gn:country_code":"PE",
    "gn:dem":3553,
    "gn:feature_class":"P",
    "gn:feature_code":"PPL",
    "gn:name":"Cuaganno",
    "gn:population":0,
    "gn:timezone":"America/Lima",
    "iso:country":"PE",
    "wof:name":"Cuaganno",
    "wof:placetype":"locality"
},
  "geometry": {"coordinates":[-75.78610999999999,-11.26833],"type":"Point"}
}