{
  "type": "Feature",
  "properties": {
    "gn:admin1_code":"4",
    "gn:admin2_code":"401.0",
    "gn:admin3_code":"40128.0",
    "gn:asciiname":"Jullalli Chico",
    "gn:country_code":"PE",
    "gn:dem":2807,
    "gn:feature_class":"P",
    "gn:feature_code":"PPLL",
    "gn:name":"Jullalli Chico",
    "gn:population":0,
    "gn:timezone":"America/Lima",
    "iso:country":"PE",
    "wof:name":"Jullalli Chico",
    "wof:placetype":"locality"
},
  "geometry": {"coordinates":[-71.68867,-16.16473],"type":"Point"}
}