{
  "type": "Feature",
  "properties": {
    "gn:admin1_code":"3",
    "gn:admin2_code":"302.0",
    "gn:admin3_code":"30201.0",
    "gn:asciiname":"Chununa Pampa",
    "gn:country_code":"PE",
    "gn:dem":3541,
    "gn:feature_class":"P",
    "gn:feature_code":"PPL",
    "gn:name":"Chu\u00f1una Pampa",
    "gn:population":0,
    "gn:timezone":"America/Lima",
    "iso:country":"PE",
    "wof:name":"Chununa Pampa",
    "wof:placetype":"locality"
},
  "geometry": {"coordinates":[-73.35488000000002,-13.7034],"type":"Point"}
}