{
  "type": "Feature",
  "properties": {
    "gn:admin1_code":"20",
    "gn:admin2_code":"2006.0",
    "gn:admin3_code":"200605.0",
    "gn:asciiname":"El Fayque",
    "gn:country_code":"PE",
    "gn:dem":305,
    "gn:feature_class":"P",
    "gn:feature_code":"PPL",
    "gn:name":"El Fayque",
    "gn:population":0,
    "gn:timezone":"America/Lima",
    "iso:country":"PE",
    "name:spa_x_preferred":[
        "El Fayque"
    ],
    "wof:name":"El Fayque",
    "wof:placetype":"locality"
},
  "geometry": {"coordinates":[-80.68193000000002,-4.53881],"type":"Point"}
}