{
  "type": "Feature",
  "properties": {
    "gn:admin1_code":"9.0",
    "gn:admin2_code":"901.0",
    "gn:admin3_code":"90117.0",
    "gn:asciiname":"Yuraj Corral",
    "gn:country_code":"PE",
    "gn:dem":3739,
    "gn:feature_class":"P",
    "gn:feature_code":"PPL",
    "gn:name":"Yuraj Corral",
    "gn:population":0,
    "gn:timezone":"America/Lima",
    "iso:country":"PE",
    "wof:name":"Yuraj Corral",
    "wof:placetype":"locality"
},
  "geometry": {"coordinates":[-74.86588,-12.79521],"type":"Point"}
}