{
  "type": "Feature",
  "properties": {
    "gn:admin1_code":"13",
    "gn:admin2_code":"1309.0",
    "gn:admin3_code":"130904.0",
    "gn:asciiname":"Huayahual",
    "gn:country_code":"PE",
    "gn:dem":3341,
    "gn:feature_class":"P",
    "gn:feature_code":"PPL",
    "gn:name":"Huayahual",
    "gn:population":0,
    "gn:timezone":"America/Lima",
    "iso:country":"PE",
    "wof:name":"Huayahual",
    "wof:placetype":"locality"
},
  "geometry": {"coordinates":[-77.93696,-7.8135],"type":"Point"}
}