{
  "type": "Feature",
  "properties": {
    "gn:admin1_code":"06",
    "gn:admin2_code":"604.0",
    "gn:admin3_code":"60411.0",
    "gn:asciiname":"Carhuaquero",
    "gn:country_code":"PE",
    "gn:dem":361,
    "gn:feature_class":"P",
    "gn:feature_code":"PPL",
    "gn:name":"Carhuaquero",
    "gn:population":0,
    "gn:timezone":"America/Lima",
    "iso:country":"PE",
    "wof:name":"Carhuaquero",
    "wof:placetype":"locality"
},
  "geometry": {"coordinates":[-79.26056,-6.60694],"type":"Point"}
}