{
  "type": "Feature",
  "properties": {
    "gn:admin1_code":"22",
    "gn:admin2_code":"2201.0",
    "gn:admin3_code":"220101.0",
    "gn:asciiname":"Condor",
    "gn:country_code":"PE",
    "gn:dem":984,
    "gn:feature_class":"P",
    "gn:feature_code":"PPL",
    "gn:name":"C\u00f3ndor",
    "gn:population":0,
    "gn:timezone":"America/Lima",
    "iso:country":"PE",
    "name:spa_x_preferred":[
        "C\u00f3ndor"
    ],
    "wof:name":"Condor",
    "wof:placetype":"locality"
},
  "geometry": {"coordinates":[-76.89301,-5.92153],"type":"Point"}
}