{
  "type": "Feature",
  "properties": {
    "gn:admin1_code":"12",
    "gn:admin2_code":"1206.0",
    "gn:admin3_code":"120601.0",
    "gn:asciiname":"San Jacinto de Shauriate",
    "gn:country_code":"PE",
    "gn:dem":1127,
    "gn:feature_class":"P",
    "gn:feature_code":"PPL",
    "gn:name":"San Jacinto de Shauriate",
    "gn:population":0,
    "gn:timezone":"America/Lima",
    "iso:country":"PE",
    "wof:name":"San Jacinto de Shauriate",
    "wof:placetype":"locality"
},
  "geometry": {"coordinates":[-74.63776999999997,-11.11666],"type":"Point"}
}