{
  "type": "Feature",
  "properties": {
    "gn:admin1_code":"12.0",
    "gn:admin2_code":"1208.0",
    "gn:admin3_code":"120801.0",
    "gn:asciiname":"Quingranhuay",
    "gn:country_code":"PE",
    "gn:dem":4163,
    "gn:feature_class":"P",
    "gn:feature_code":"PPL",
    "gn:name":"Quingranhuay",
    "gn:population":0,
    "gn:timezone":"America/Lima",
    "iso:country":"PE",
    "wof:name":"Quingranhuay",
    "wof:placetype":"locality"
},
  "geometry": {"coordinates":[-75.8785,-11.64007],"type":"Point"}
}