{
  "type": "Feature",
  "properties": {
    "gn:admin1_code":"08",
    "gn:admin2_code":"803.0",
    "gn:admin3_code":"80304.0",
    "gn:asciiname":"Tapran",
    "gn:country_code":"PE",
    "gn:dem":3277,
    "gn:feature_class":"P",
    "gn:feature_code":"PPL",
    "gn:name":"Tapran",
    "gn:population":0,
    "gn:timezone":"America/Lima",
    "iso:country":"PE",
    "wof:name":"Tapran",
    "wof:placetype":"locality"
},
  "geometry": {"coordinates":[-72.33333,-13.63333],"type":"Point"}
}