{
  "type": "Feature",
  "properties": {
    "gn:admin1_code":"16",
    "gn:admin2_code":"1605.0",
    "gn:admin3_code":"160501.0",
    "gn:asciiname":"Galicia",
    "gn:country_code":"PE",
    "gn:dem":109,
    "gn:feature_class":"P",
    "gn:feature_code":"PPL",
    "gn:name":"Galicia",
    "gn:population":0,
    "gn:timezone":"America/Lima",
    "iso:country":"PE",
    "wof:name":"Galicia",
    "wof:placetype":"locality"
},
  "geometry": {"coordinates":[-73.86335,-5.41944],"type":"Point"}
}