{
  "type": "Feature",
  "properties": {
    "gn:admin1_code":"16",
    "gn:admin2_code":"1605.0",
    "gn:admin3_code":"160501.0",
    "gn:asciiname":"Galicia",
    "gn:country_code":"PE",
    "gn:dem":109,
    "gn:feature_class":"P",
    "gn:feature_code":"PPL",
    "gn:name":"Galicia",
    "gn:population":0,
    "gn:timezone":"America/Lima",
    "iso:country":"PE",
    "name:ast_x_preferred":[
        "Galicia"
    ],
    "name:ceb_x_preferred":[
        "Galicia"
    ],
    "name:deu_x_preferred":[
        "Galicia"
    ],
    "name:fin_x_preferred":[
        "Galicia"
    ],
    "name:glg_x_preferred":[
        "Galicia"
    ],
    "name:glv_x_preferred":[
        "Galicia"
    ],
    "name:nno_x_preferred":[
        "Galicia"
    ],
    "name:nor_x_preferred":[
        "Galicia"
    ],
    "name:spa_x_preferred":[
        "Galicia"
    ],
    "name:srp_x_preferred":[
        "\u0413\u0430\u043b\u0438\u0441\u0438\u0458\u0430"
    ],
    "name:swe_x_preferred":[
        "Galicia"
    ],
    "name:tgl_x_preferred":[
        "Galicia"
    ],
    "wof:name":"Galicia",
    "wof:placetype":"locality"
},
  "geometry": {"coordinates":[-73.86335,-5.41944],"type":"Point"}
}