{
  "type": "Feature",
  "properties": {
    "gn:admin1_code":"24",
    "gn:admin2_code":"2401.0",
    "gn:admin3_code":"240102.0",
    "gn:asciiname":"Las Parrales",
    "gn:country_code":"PE",
    "gn:dem":5,
    "gn:feature_class":"P",
    "gn:feature_code":"PPL",
    "gn:name":"Las Parrales",
    "gn:population":0,
    "gn:timezone":"America/Lima",
    "iso:country":"PE",
    "wof:name":"Las Parrales",
    "wof:placetype":"locality"
},
  "geometry": {"coordinates":[-80.49053000000001,-3.535],"type":"Point"}
}