{
  "type": "Feature",
  "properties": {
    "gn:admin1_code":"10.0",
    "gn:admin2_code":"1011.0",
    "gn:admin3_code":"101107.0",
    "gn:asciiname":"Tambo",
    "gn:country_code":"PE",
    "gn:dem":3436,
    "gn:feature_class":"P",
    "gn:feature_code":"PPL",
    "gn:name":"Tambo",
    "gn:population":0,
    "gn:timezone":"America/Lima",
    "iso:country":"PE",
    "name:ceb_x_preferred":[
        "Tambo"
    ],
    "name:deu_x_preferred":[
        "Tambo"
    ],
    "name:fra_x_preferred":[
        "Tambo"
    ],
    "name:hrv_x_preferred":[
        "Tambo"
    ],
    "name:nor_x_preferred":[
        "Tambo"
    ],
    "name:por_x_preferred":[
        "Tambo"
    ],
    "name:rus_x_preferred":[
        "\u0422\u0430\u043c\u0431\u043e"
    ],
    "name:spa_x_preferred":[
        "Tambo"
    ],
    "name:swe_x_preferred":[
        "Tambo"
    ],
    "wof:name":"Tambo",
    "wof:placetype":"locality"
},
  "geometry": {"coordinates":[-76.72118,-9.70567],"type":"Point"}
}