{
  "type": "Feature",
  "properties": {
    "gn:admin1_code":"3",
    "gn:admin2_code":"302.0",
    "gn:admin3_code":"30211.0",
    "gn:asciiname":"Pauche Cucho",
    "gn:country_code":"PE",
    "gn:dem":2954,
    "gn:feature_class":"P",
    "gn:feature_code":"PPL",
    "gn:name":"Pauche Cucho",
    "gn:population":0,
    "gn:timezone":"America/Lima",
    "iso:country":"PE",
    "wof:name":"Pauche Cucho",
    "wof:placetype":"locality"
},
  "geometry": {"coordinates":[-73.59666999999997,-14.06528],"type":"Point"}
}