{
  "type": "Feature",
  "properties": {
    "gn:admin1_code":"05",
    "gn:admin2_code":"510.0",
    "gn:admin3_code":"51011.0",
    "gn:asciiname":"Chunta Puntani",
    "gn:country_code":"PE",
    "gn:dem":4362,
    "gn:feature_class":"P",
    "gn:feature_code":"PPL",
    "gn:name":"Chunta Puntani",
    "gn:population":0,
    "gn:timezone":"America/Lima",
    "iso:country":"PE",
    "wof:name":"Chunta Puntani",
    "wof:placetype":"locality"
},
  "geometry": {"coordinates":[-74.38333,-13.66667],"type":"Point"}
}