{
  "type": "Feature",
  "properties": {
    "gn:admin1_code":"23",
    "gn:admin2_code":"2302.0",
    "gn:admin3_code":"230204.0",
    "gn:asciiname":"Ancocirca",
    "gn:country_code":"PE",
    "gn:dem":1805,
    "gn:feature_class":"P",
    "gn:feature_code":"PPL",
    "gn:name":"Ancocirca",
    "gn:population":0,
    "gn:timezone":"America/Lima",
    "iso:country":"PE",
    "wof:name":"Ancocirca",
    "wof:placetype":"locality"
},
  "geometry": {"coordinates":[-70.39738,-17.41778],"type":"Point"}
}