{
  "type": "Feature",
  "properties": {
    "gn:admin1_code":"09",
    "gn:admin2_code":"906.0",
    "gn:admin3_code":"90613.0",
    "gn:asciiname":"Quisuarccasa",
    "gn:country_code":"PE",
    "gn:dem":3390,
    "gn:feature_class":"P",
    "gn:feature_code":"PPL",
    "gn:name":"Quisuarccasa",
    "gn:population":0,
    "gn:timezone":"America/Lima",
    "iso:country":"PE",
    "wof:name":"Quisuarccasa",
    "wof:placetype":"locality"
},
  "geometry": {"coordinates":[-75.30972,-13.88083],"type":"Point"}
}