{
  "type": "Feature",
  "properties": {
    "gn:admin1_code":"11",
    "gn:admin2_code":"1101.0",
    "gn:admin3_code":"110106.0",
    "gn:asciiname":"Anamia",
    "gn:country_code":"PE",
    "gn:dem":421,
    "gn:feature_class":"P",
    "gn:feature_code":"PPL",
    "gn:name":"A\u00f1amia",
    "gn:population":0,
    "gn:timezone":"America/Lima",
    "iso:country":"PE",
    "name:spa_x_preferred":[
        "A\u00f1amia"
    ],
    "name:spa_x_variant":[
        "Anamias"
    ],
    "wof:name":"Anamia",
    "wof:placetype":"locality"
},
  "geometry": {"coordinates":[-75.71897,-14.04561],"type":"Point"}
}