{
  "type": "Feature",
  "properties": {
    "gn:admin1_code":"21",
    "gn:admin2_code":"2104.0",
    "gn:admin3_code":"210404.0",
    "gn:asciiname":"Limache",
    "gn:country_code":"PE",
    "gn:dem":3888,
    "gn:feature_class":"P",
    "gn:feature_code":"PPL",
    "gn:name":"Limache",
    "gn:population":0,
    "gn:timezone":"America/Lima",
    "iso:country":"PE",
    "name:ceb_x_preferred":[
        "Limache"
    ],
    "name:deu_x_preferred":[
        "Limache"
    ],
    "name:eus_x_preferred":[
        "Limache"
    ],
    "name:fas_x_preferred":[
        "\u0644\u06cc\u0645\u0627\u0686\u0647"
    ],
    "name:fra_x_preferred":[
        "Limache"
    ],
    "name:ita_x_preferred":[
        "Limache"
    ],
    "name:kor_x_preferred":[
        "\ub9ac\ub9c8\uccb4"
    ],
    "name:nld_x_preferred":[
        "Limache"
    ],
    "name:oci_x_preferred":[
        "Limache"
    ],
    "name:pol_x_preferred":[
        "Limache"
    ],
    "name:por_x_preferred":[
        "Limache"
    ],
    "name:ron_x_preferred":[
        "Limache"
    ],
    "name:rus_x_preferred":[
        "\u041b\u0438\u043c\u0430\u0447\u0435"
    ],
    "name:spa_x_preferred":[
        "Limache"
    ],
    "name:srp_x_preferred":[
        "\u041b\u0438\u043c\u0430\u0447\u0435"
    ],
    "name:swe_x_preferred":[
        "Limache"
    ],
    "name:zho_x_preferred":[
        "\u5229\u99ac\u5207"
    ],
    "wof:name":"Limache",
    "wof:placetype":"locality"
},
  "geometry": {"coordinates":[-69.24797,-16.69943],"type":"Point"}
}