{
  "type": "Feature",
  "properties": {
    "gn:admin1_code":"9.0",
    "gn:admin2_code":"907.0",
    "gn:admin3_code":"90705.0",
    "gn:asciiname":"Sirihuina",
    "gn:country_code":"PE",
    "gn:dem":3981,
    "gn:feature_class":"P",
    "gn:feature_code":"PPL",
    "gn:name":"Sirihui\u00f1a",
    "gn:population":0,
    "gn:timezone":"America/Lima",
    "iso:country":"PE",
    "wof:name":"Sirihuina",
    "wof:placetype":"locality"
},
  "geometry": {"coordinates":[-74.67234000000001,-12.49072],"type":"Point"}
}