{
  "type": "Feature",
  "properties": {
    "gn:admin1_code":"8",
    "gn:admin2_code":"805.0",
    "gn:admin3_code":"80504.0",
    "gn:asciiname":"Pertendes",
    "gn:country_code":"PE",
    "gn:dem":4052,
    "gn:feature_class":"P",
    "gn:feature_code":"PPL",
    "gn:name":"Pertendes",
    "gn:population":0,
    "gn:timezone":"America/Lima",
    "iso:country":"PE",
    "wof:name":"Pertendes",
    "wof:placetype":"locality"
},
  "geometry": {"coordinates":[-71.29255000000001,-14.44001],"type":"Point"}
}