{
  "type": "Feature",
  "properties": {
    "gn:admin1_code":"09",
    "gn:admin2_code":"903.0",
    "gn:admin3_code":"90301.0",
    "gn:asciiname":"Pircalla",
    "gn:country_code":"PE",
    "gn:dem":3903,
    "gn:feature_class":"P",
    "gn:feature_code":"PPL",
    "gn:name":"Pircalla",
    "gn:population":0,
    "gn:timezone":"America/Lima",
    "iso:country":"PE",
    "wof:name":"Pircalla",
    "wof:placetype":"locality"
},
  "geometry": {"coordinates":[-74.76094000000001,-13.04591],"type":"Point"}
}