{
  "type": "Feature",
  "properties": {
    "gn:admin1_code":"4",
    "gn:admin2_code":"405.0",
    "gn:admin3_code":"40502.0",
    "gn:asciiname":"Puricestancia",
    "gn:country_code":"PE",
    "gn:dem":4402,
    "gn:feature_class":"P",
    "gn:feature_code":"PPL",
    "gn:name":"Puricestancia",
    "gn:population":0,
    "gn:timezone":"America/Lima",
    "iso:country":"PE",
    "wof:name":"Puricestancia",
    "wof:placetype":"locality"
},
  "geometry": {"coordinates":[-71.75713,-15.86386],"type":"Point"}
}