{
  "type": "Feature",
  "properties": {
    "gn:admin1_code":"06",
    "gn:admin2_code":"610.0",
    "gn:admin3_code":"61006.0",
    "gn:asciiname":"Shirac",
    "gn:country_code":"PE",
    "gn:dem":2724,
    "gn:feature_class":"P",
    "gn:feature_code":"PPLA3",
    "gn:name":"Shirac",
    "gn:population":0,
    "gn:timezone":"America/Lima",
    "iso:country":"PE",
    "wof:name":"Shirac",
    "wof:placetype":"locality"
},
  "geometry": {"coordinates":[-78.05,-7.35],"type":"Point"}
}