{
  "type": "Feature",
  "properties": {
    "gn:admin1_code":"15",
    "gn:admin2_code":"1506.0",
    "gn:admin3_code":"150602.0",
    "gn:asciiname":"Uchco Machay",
    "gn:country_code":"PE",
    "gn:dem":4374,
    "gn:feature_class":"P",
    "gn:feature_code":"PPL",
    "gn:name":"Uchco Machay",
    "gn:population":0,
    "gn:timezone":"America/Lima",
    "iso:country":"PE",
    "wof:name":"Uchco Machay",
    "wof:placetype":"locality"
},
  "geometry": {"coordinates":[-76.52916999999999,-11.27861],"type":"Point"}
}