{
  "type": "Feature",
  "properties": {
    "gn:admin1_code":"5",
    "gn:admin2_code":"509.0",
    "gn:admin3_code":"50906.0",
    "gn:asciiname":"Yanapaccha",
    "gn:country_code":"PE",
    "gn:dem":4250,
    "gn:feature_class":"P",
    "gn:feature_code":"PPL",
    "gn:name":"Yanapaccha",
    "gn:population":0,
    "gn:timezone":"America/Lima",
    "iso:country":"PE",
    "wof:name":"Yanapaccha",
    "wof:placetype":"locality"
},
  "geometry": {"coordinates":[-73.77639000000001,-14.21861],"type":"Point"}
}