{
  "type": "Feature",
  "properties": {
    "gn:admin1_code":"15",
    "gn:admin2_code":"1510.0",
    "gn:admin3_code":"151032.0",
    "gn:asciiname":"Casanmayoc",
    "gn:country_code":"PE",
    "gn:dem":2836,
    "gn:feature_class":"P",
    "gn:feature_code":"PPL",
    "gn:name":"Casanmayoc",
    "gn:population":0,
    "gn:timezone":"America/Lima",
    "iso:country":"PE",
    "wof:name":"Casanmayoc",
    "wof:placetype":"locality"
},
  "geometry": {"coordinates":[-75.81667,-12.88333],"type":"Point"}
}