{
  "type": "Feature",
  "properties": {
    "gn:admin1_code":"11.0",
    "gn:admin2_code":"1102.0",
    "gn:admin3_code":"110209.0",
    "gn:asciiname":"Chuco",
    "gn:country_code":"PE",
    "gn:dem":3938,
    "gn:feature_class":"P",
    "gn:feature_code":"PPL",
    "gn:name":"Chuco",
    "gn:population":0,
    "gn:timezone":"America/Lima",
    "iso:country":"PE",
    "name:spa_x_preferred":[
        "Chuco"
    ],
    "wof:name":"Chuco",
    "wof:placetype":"locality"
},
  "geometry": {"coordinates":[-75.80365999999999,-13.14583],"type":"Point"}
}