{
  "type": "Feature",
  "properties": {
    "gn:admin1_code":"19",
    "gn:admin2_code":"1903.0",
    "gn:admin3_code":"190306.0",
    "gn:asciiname":"Puerto Porvenir",
    "gn:country_code":"PE",
    "gn:dem":229,
    "gn:feature_class":"P",
    "gn:feature_code":"PPL",
    "gn:name":"Puerto Porvenir",
    "gn:population":0,
    "gn:timezone":"America/Lima",
    "iso:country":"PE",
    "wof:name":"Puerto Porvenir",
    "wof:placetype":"locality"
},
  "geometry": {"coordinates":[-75.00508000000001,-9.94768],"type":"Point"}
}