{
  "type": "Feature",
  "properties": {
    "gn:admin1_code":"17.0",
    "gn:admin2_code":"1703.0",
    "gn:asciiname":"Rafael Caleron",
    "gn:country_code":"PE",
    "gn:dem":285,
    "gn:feature_class":"P",
    "gn:feature_code":"PPL",
    "gn:name":"Rafael Caler\u00f3n",
    "gn:population":0,
    "gn:timezone":"America/Lima",
    "iso:country":"PE",
    "name:spa_x_preferred":[
        "Rafael Caler\u00f3n"
    ],
    "wof:name":"Rafael Caleron",
    "wof:placetype":"locality"
},
  "geometry": {"coordinates":[-69.2371,-11.69639],"type":"Point"}
}