{
  "type": "Feature",
  "properties": {
    "gn:admin1_code":"15.0",
    "gn:admin2_code":"1505.0",
    "gn:admin3_code":"150501.0",
    "gn:asciiname":"Espiritu Santo de Palo",
    "gn:country_code":"PE",
    "gn:dem":140,
    "gn:feature_class":"P",
    "gn:feature_code":"PPL",
    "gn:name":"Esp\u00edritu Santo de Palo",
    "gn:population":0,
    "gn:timezone":"America/Lima",
    "iso:country":"PE",
    "wof:name":"Espiritu Santo de Palo",
    "wof:placetype":"locality"
},
  "geometry": {"coordinates":[-76.30377,-13.12886],"type":"Point"}
}