{
  "type": "Feature",
  "properties": {
    "gn:admin1_code":"11",
    "gn:admin2_code":"1101.0",
    "gn:admin3_code":"110107.0",
    "gn:asciiname":"Pampa La Juliana",
    "gn:country_code":"PE",
    "gn:dem":418,
    "gn:feature_class":"P",
    "gn:feature_code":"PPL",
    "gn:name":"Pampa La Juliana",
    "gn:population":0,
    "gn:timezone":"America/Lima",
    "iso:country":"PE",
    "name:und_x_variant":[
        "Pampa Juliana"
    ],
    "wof:name":"Pampa La Juliana",
    "wof:placetype":"locality"
},
  "geometry": {"coordinates":[-75.68064,-14.11795],"type":"Point"}
}