{
  "type": "Feature",
  "properties": {
    "gn:admin1_code":"23.0",
    "gn:admin2_code":"2301.0",
    "gn:admin3_code":"230107.0",
    "gn:asciiname":"Siquine",
    "gn:country_code":"PE",
    "gn:dem":4161,
    "gn:feature_class":"P",
    "gn:feature_code":"PPL",
    "gn:name":"Siquine",
    "gn:population":0,
    "gn:timezone":"America/Lima",
    "iso:country":"PE",
    "wof:name":"Siquine",
    "wof:placetype":"locality"
},
  "geometry": {"coordinates":[-69.55,-17.43806],"type":"Point"}
}