{
  "type": "Feature",
  "properties": {
    "gn:admin1_code":"12",
    "gn:admin2_code":"1201.0",
    "gn:admin3_code":"120124.0",
    "gn:asciiname":"Jalla Lampa",
    "gn:country_code":"PE",
    "gn:dem":3705,
    "gn:feature_class":"P",
    "gn:feature_code":"PPL",
    "gn:name":"Jalla Lampa",
    "gn:population":0,
    "gn:timezone":"America/Lima",
    "iso:country":"PE",
    "wof:name":"Jalla Lampa",
    "wof:placetype":"locality"
},
  "geometry": {"coordinates":[-74.85526,-11.93795],"type":"Point"}
}