{
  "type": "Feature",
  "properties": {
    "gn:admin1_code":"5",
    "gn:admin2_code":"503.0",
    "gn:asciiname":"Punta",
    "gn:country_code":"PE",
    "gn:dem":4242,
    "gn:feature_class":"P",
    "gn:feature_code":"PPL",
    "gn:name":"Punta",
    "gn:population":0,
    "gn:timezone":"America/Lima",
    "iso:country":"PE",
    "name:deu_x_preferred":[
        "Punta"
    ],
    "name:fin_x_preferred":[
        "Punta"
    ],
    "name:jpn_x_preferred":[
        "\u30d7\u30f3\u30bf"
    ],
    "name:spa_x_preferred":[
        "Punta"
    ],
    "name:swe_x_preferred":[
        "Punta"
    ],
    "wof:name":"Punta",
    "wof:placetype":"locality"
},
  "geometry": {"coordinates":[-74.63972,-13.97667],"type":"Point"}
}