{
  "type": "Feature",
  "properties": {
    "gn:admin1_code":"2.0",
    "gn:admin2_code":"220.0",
    "gn:admin3_code":"22001.0",
    "gn:asciiname":"Pampac",
    "gn:country_code":"PE",
    "gn:dem":2455,
    "gn:feature_class":"P",
    "gn:feature_code":"PPL",
    "gn:name":"Pampac",
    "gn:population":0,
    "gn:timezone":"America/Lima",
    "iso:country":"PE",
    "wof:name":"Pampac",
    "wof:placetype":"locality"
},
  "geometry": {"coordinates":[-77.75221999999999,-9.14222],"type":"Point"}
}