{
  "type": "Feature",
  "properties": {
    "gn:admin1_code":"21",
    "gn:admin2_code":"2104.0",
    "gn:admin3_code":"210404.0",
    "gn:asciiname":"Soncasipepampa",
    "gn:country_code":"PE",
    "gn:dem":4094,
    "gn:feature_class":"P",
    "gn:feature_code":"PPL",
    "gn:name":"Soncasipepampa",
    "gn:population":0,
    "gn:timezone":"America/Lima",
    "iso:country":"PE",
    "wof:name":"Soncasipepampa",
    "wof:placetype":"locality"
},
  "geometry": {"coordinates":[-69.35745,-16.75045],"type":"Point"}
}