{
  "type": "Feature",
  "properties": {
    "gn:admin1_code":"06",
    "gn:admin2_code":"603.0",
    "gn:admin3_code":"60301.0",
    "gn:asciiname":"Pumarumi",
    "gn:country_code":"PE",
    "gn:dem":2792,
    "gn:feature_class":"P",
    "gn:feature_code":"PPL",
    "gn:name":"Pumarumi",
    "gn:population":0,
    "gn:timezone":"America/Lima",
    "iso:country":"PE",
    "wof:name":"Pumarumi",
    "wof:placetype":"locality"
},
  "geometry": {"coordinates":[-78.15479000000001,-6.87982],"type":"Point"}
}