{
  "type": "Feature",
  "properties": {
    "gn:admin1_code":"03",
    "gn:admin2_code":"302.0",
    "gn:admin3_code":"30205.0",
    "gn:asciiname":"Natividad",
    "gn:country_code":"PE",
    "gn:dem":3045,
    "gn:feature_class":"P",
    "gn:feature_code":"PPL",
    "gn:name":"Natividad",
    "gn:population":0,
    "gn:timezone":"America/Lima",
    "iso:country":"PE",
    "name:ceb_x_preferred":[
        "Natividad"
    ],
    "name:deu_x_preferred":[
        "Natividad"
    ],
    "name:fra_x_preferred":[
        "Natividad"
    ],
    "name:sco_x_preferred":[
        "Natividad"
    ],
    "name:spa_x_preferred":[
        "Natividad"
    ],
    "name:srp_x_preferred":[
        "\u041d\u0430\u0442\u0438\u0432\u0438\u0434\u0430\u0434"
    ],
    "name:swe_x_preferred":[
        "Natividad"
    ],
    "name:vie_x_preferred":[
        "Natividad"
    ],
    "wof:name":"Natividad",
    "wof:placetype":"locality"
},
  "geometry": {"coordinates":[-73.52249999999999,-13.7525],"type":"Point"}
}