{
  "type": "Feature",
  "properties": {
    "gn:admin1_code":"04",
    "gn:admin2_code":"407.0",
    "gn:admin3_code":"40704.0",
    "gn:asciiname":"Chiguas",
    "gn:country_code":"PE",
    "gn:dem":76,
    "gn:feature_class":"P",
    "gn:feature_code":"PPL",
    "gn:name":"Chiguas",
    "gn:population":0,
    "gn:timezone":"America/Lima",
    "iso:country":"PE",
    "name:spa_x_preferred":[
        "Chiguas"
    ],
    "wof:name":"Chiguas",
    "wof:placetype":"locality"
},
  "geometry": {"coordinates":[-72.05893,-17.01328],"type":"Point"}
}