{
  "type": "Feature",
  "properties": {
    "gn:admin1_code":"2.0",
    "gn:admin2_code":"206.0",
    "gn:admin3_code":"20610.0",
    "gn:asciiname":"Tranca",
    "gn:country_code":"PE",
    "gn:dem":2624,
    "gn:feature_class":"P",
    "gn:feature_code":"PPL",
    "gn:name":"Tranca",
    "gn:population":0,
    "gn:timezone":"America/Lima",
    "iso:country":"PE",
    "wof:name":"Tranca",
    "wof:placetype":"locality"
},
  "geometry": {"coordinates":[-77.67694,-9.26639],"type":"Point"}
}