{
  "type": "Feature",
  "properties": {
    "gn:admin1_code":"5.0",
    "gn:admin2_code":"504.0",
    "gn:asciiname":"Puerto Acon",
    "gn:country_code":"PE",
    "gn:dem":536,
    "gn:feature_class":"P",
    "gn:feature_code":"PPL",
    "gn:name":"Puerto Ac\u00f3n",
    "gn:population":0,
    "gn:timezone":"America/Lima",
    "iso:country":"PE",
    "name:spa_x_preferred":[
        "Puerto Ac\u00f3n"
    ],
    "wof:name":"Puerto Acon",
    "wof:placetype":"locality"
},
  "geometry": {"coordinates":[-73.88965999999998,-12.43309],"type":"Point"}
}