{
  "type": "Feature",
  "properties": {
    "gn:admin1_code":"11",
    "gn:admin2_code":"1103.0",
    "gn:admin3_code":"110301.0",
    "gn:asciiname":"Hacienda Cantalloc",
    "gn:country_code":"PE",
    "gn:dem":637,
    "gn:feature_class":"P",
    "gn:feature_code":"PPL",
    "gn:name":"Hacienda Cantalloc",
    "gn:population":0,
    "gn:timezone":"America/Lima",
    "iso:country":"PE",
    "name:spa_x_preferred":[
        "Hacienda Cantalloc"
    ],
    "name:und_x_variant":[
        "Cantalloc Hacienda",
        "Cantalloc"
    ],
    "wof:name":"Hacienda Cantalloc",
    "wof:placetype":"locality"
},
  "geometry": {"coordinates":[-74.91361999999999,-14.8221],"type":"Point"}
}