{
  "type": "Feature",
  "properties": {
    "gn:admin1_code":"9.0",
    "gn:admin2_code":"906.0",
    "gn:admin3_code":"90607.0",
    "gn:asciiname":"Yurajcorral",
    "gn:country_code":"PE",
    "gn:dem":4460,
    "gn:feature_class":"P",
    "gn:feature_code":"PPL",
    "gn:name":"Yurajcorral",
    "gn:population":0,
    "gn:timezone":"America/Lima",
    "iso:country":"PE",
    "wof:name":"Yurajcorral",
    "wof:placetype":"locality"
},
  "geometry": {"coordinates":[-74.99325999999998,-13.22007],"type":"Point"}
}