{
  "type": "Feature",
  "properties": {
    "gn:admin1_code":"5",
    "gn:admin2_code":"509.0",
    "gn:admin3_code":"50911.0",
    "gn:asciiname":"Sicuani",
    "gn:country_code":"PE",
    "gn:dem":3729,
    "gn:feature_class":"P",
    "gn:feature_code":"PPL",
    "gn:name":"Sicuani",
    "gn:population":0,
    "gn:timezone":"America/Lima",
    "iso:country":"PE",
    "name:ara_x_preferred":[
        "\u0627\u0644\u0633\u064a\u0643\u0648\u0627\u0646\u064a"
    ],
    "name:aym_x_preferred":[
        "Sikuwani"
    ],
    "name:ben_x_preferred":[
        "\u09b8\u09bf\u0995\u09c1\u0986\u09a8\u09bf"
    ],
    "name:ceb_x_preferred":[
        "Sicuani"
    ],
    "name:deu_x_preferred":[
        "Sicuani"
    ],
    "name:ell_x_preferred":[
        "\u03a3\u03b9\u03ba\u03bf\u03c5\u03ac\u03bd\u03b9"
    ],
    "name:fra_x_preferred":[
        "Sicuani"
    ],
    "name:heb_x_preferred":[
        "\u05e1\u05d9\u05e7\u05d5\u05d0\u05e0\u05d9"
    ],
    "name:hin_x_preferred":[
        "\u0938\u093f\u0915\u0941\u0906\u0928\u0940"
    ],
    "name:hun_x_preferred":[
        "Sicuani"
    ],
    "name:ind_x_preferred":[
        "Sicuani"
    ],
    "name:ita_x_preferred":[
        "Sicuani"
    ],
    "name:jpn_x_preferred":[
        "\u30b7\u30af\u30a2\u30cb"
    ],
    "name:kor_x_preferred":[
        "\uc2dc\ucfe0\uc544\ub2c8"
    ],
    "name:pol_x_preferred":[
        "Sicuani"
    ],
    "name:por_x_preferred":[
        "Sicuani"
    ],
    "name:que_x_preferred":[
        "Sikuwani"
    ],
    "name:rus_x_preferred":[
        "\u0421\u0438\u043a\u0443\u0430\u043d\u0438"
    ],
    "name:spa_x_preferred":[
        "Sicuani"
    ],
    "name:swe_x_preferred":[
        "Sicuani"
    ],
    "name:tur_x_preferred":[
        "Sicuani"
    ],
    "name:ukr_x_preferred":[
        "\u0421\u0456\u043a\u0443\u0430\u043d\u0456"
    ],
    "name:urd_x_preferred":[
        "\u0633\u06cc\u06a9\u0648\u0646\u06cc"
    ],
    "name:vie_x_preferred":[
        "Sicuani"
    ],
    "name:war_x_preferred":[
        "Sicuani"
    ],
    "name:zho_x_preferred":[
        "\u932b\u5938\u5c3c"
    ],
    "wof:name":"Sicuani",
    "wof:placetype":"locality"
},
  "geometry": {"coordinates":[-73.62027999999999,-14.22583],"type":"Point"}
}