{
  "type": "Feature",
  "properties": {
    "gn:admin1_code":"15",
    "gn:admin2_code":"1510.0",
    "gn:admin3_code":"151030.0",
    "gn:asciiname":"Cullpana",
    "gn:country_code":"PE",
    "gn:dem":4433,
    "gn:feature_class":"P",
    "gn:feature_code":"PPL",
    "gn:name":"Cullpana",
    "gn:population":0,
    "gn:timezone":"America/Lima",
    "iso:country":"PE",
    "wof:name":"Cullpana",
    "wof:placetype":"locality"
},
  "geometry": {"coordinates":[-75.71472,-12.18917],"type":"Point"}
}