{
  "type": "Feature",
  "properties": {
    "gn:admin1_code":"17.0",
    "gn:admin2_code":"1703.0",
    "gn:asciiname":"Santa Rosa Dos",
    "gn:country_code":"PE",
    "gn:dem":338,
    "gn:feature_class":"P",
    "gn:feature_code":"PPL",
    "gn:name":"Santa Rosa Dos",
    "gn:population":0,
    "gn:timezone":"America/Lima",
    "iso:country":"PE",
    "name:spa_x_preferred":[
        "Santa Rosa Dos"
    ],
    "wof:name":"Santa Rosa Dos",
    "wof:placetype":"locality"
},
  "geometry": {"coordinates":[-69.48052,-11.20428],"type":"Point"}
}