{
  "type": "Feature",
  "properties": {
    "gn:admin1_code":"17.0",
    "gn:admin2_code":"1701.0",
    "gn:asciiname":"Micaela Bastidas",
    "gn:country_code":"PE",
    "gn:dem":207,
    "gn:feature_class":"P",
    "gn:feature_code":"PPL",
    "gn:name":"Micaela Bastidas",
    "gn:population":0,
    "gn:timezone":"America/Lima",
    "iso:country":"PE",
    "name:spa_x_preferred":[
        "Micaela Bastidas"
    ],
    "wof:name":"Micaela Bastidas",
    "wof:placetype":"locality"
},
  "geometry": {"coordinates":[-69.19784,-12.58804],"type":"Point"}
}