{
  "type": "Feature",
  "properties": {
    "gn:admin1_code":"1.0",
    "gn:admin2_code":"107.0",
    "gn:admin3_code":"10702.0",
    "gn:asciiname":"Bajo Naranjitos",
    "gn:country_code":"PE",
    "gn:dem":540,
    "gn:feature_class":"P",
    "gn:feature_code":"PPL",
    "gn:name":"Bajo Naranjitos",
    "gn:population":0,
    "gn:timezone":"America/Lima",
    "iso:country":"PE",
    "name:spa_x_preferred":[
        "Bajo Naranjitos"
    ],
    "wof:name":"Bajo Naranjitos",
    "wof:placetype":"locality"
},
  "geometry": {"coordinates":[-78.28168000000002,-5.80854],"type":"Point"}
}