{
  "type": "Feature",
  "properties": {
    "gn:admin1_code":"22",
    "gn:admin2_code":"2210.0",
    "gn:admin3_code":"221004.0",
    "gn:asciiname":"Maman",
    "gn:country_code":"PE",
    "gn:dem":1442,
    "gn:feature_class":"P",
    "gn:feature_code":"PPL",
    "gn:name":"Mam\u00e1n",
    "gn:population":0,
    "gn:timezone":"America/Lima",
    "iso:country":"PE",
    "name:fra_x_preferred":[
        "Maman"
    ],
    "name:heb_x_preferred":[
        "\u05de\u05de\u05df"
    ],
    "wof:name":"Maman",
    "wof:placetype":"locality"
},
  "geometry": {"coordinates":[-76.77014,-8.43226],"type":"Point"}
}