{
  "type": "Feature",
  "properties": {
    "gn:admin1_code":"21.0",
    "gn:admin2_code":"2112.0",
    "gn:asciiname":"Mina Vilauma",
    "gn:country_code":"PE",
    "gn:dem":1880,
    "gn:feature_class":"P",
    "gn:feature_code":"PPL",
    "gn:name":"Mina Vilauma",
    "gn:population":0,
    "gn:timezone":"America/Lima",
    "iso:country":"PE",
    "name:spa_x_preferred":[
        "Mina Vilauma"
    ],
    "wof:name":"Mina Vilauma",
    "wof:placetype":"locality"
},
  "geometry": {"coordinates":[-69.19852,-14.08784],"type":"Point"}
}