{
  "type": "Feature",
  "properties": {
    "gn:admin1_code":"21",
    "gn:admin2_code":"2104.0",
    "gn:admin3_code":"210401.0",
    "gn:asciiname":"Yaraoco Grande",
    "gn:cc2":"PE",
    "gn:country_code":"PE",
    "gn:dem":4041,
    "gn:feature_class":"P",
    "gn:feature_code":"PPL",
    "gn:name":"Yaraoco Grande",
    "gn:population":0,
    "gn:timezone":"America/Lima",
    "iso:country":"PE",
    "name:und_x_variant":[
        "Yaraoco Grande Hacienda",
        "Yaraoco Grande"
    ],
    "wof:name":"Yaraoco Grande",
    "wof:placetype":"locality"
},
  "geometry": {"coordinates":[-69.58333,-16.41667],"type":"Point"}
}