{
  "type": "Feature",
  "properties": {
    "gn:admin1_code":"12",
    "gn:admin2_code":"1207.0",
    "gn:admin3_code":"120708.0",
    "gn:asciiname":"Cuquipata",
    "gn:country_code":"PE",
    "gn:dem":3339,
    "gn:feature_class":"P",
    "gn:feature_code":"PPL",
    "gn:name":"Cuquipata",
    "gn:population":0,
    "gn:timezone":"America/Lima",
    "iso:country":"PE",
    "wof:name":"Cuquipata",
    "wof:placetype":"locality"
},
  "geometry": {"coordinates":[-75.7564,-11.0305],"type":"Point"}
}