{
  "type": "Feature",
  "properties": {
    "gn:admin1_code":"04",
    "gn:admin2_code":"408.0",
    "gn:admin3_code":"40805.0",
    "gn:asciiname":"Condorillo",
    "gn:country_code":"PE",
    "gn:dem":4391,
    "gn:feature_class":"P",
    "gn:feature_code":"PPL",
    "gn:name":"Condorillo",
    "gn:population":0,
    "gn:timezone":"America/Lima",
    "iso:country":"PE",
    "wof:name":"Condorillo",
    "wof:placetype":"locality"
},
  "geometry": {"coordinates":[-72.94832,-15.14491],"type":"Point"}
}