{
  "type": "Feature",
  "properties": {
    "gn:admin1_code":"05",
    "gn:admin2_code":"503.0",
    "gn:admin3_code":"50303.0",
    "gn:asciiname":"Purccay",
    "gn:country_code":"PE",
    "gn:dem":4235,
    "gn:feature_class":"P",
    "gn:feature_code":"PPL",
    "gn:name":"Purccay",
    "gn:population":0,
    "gn:timezone":"America/Lima",
    "iso:country":"PE",
    "wof:name":"Purccay",
    "wof:placetype":"locality"
},
  "geometry": {"coordinates":[-74.21666999999999,-13.91667],"type":"Point"}
}