{
  "type": "Feature",
  "properties": {
    "gn:admin1_code":"17.0",
    "gn:admin2_code":"1703.0",
    "gn:asciiname":"Limera",
    "gn:country_code":"PE",
    "gn:dem":265,
    "gn:feature_class":"P",
    "gn:feature_code":"PPL",
    "gn:name":"Limera",
    "gn:population":0,
    "gn:timezone":"America/Lima",
    "iso:country":"PE",
    "name:spa_x_preferred":[
        "Limera"
    ],
    "wof:name":"Limera",
    "wof:placetype":"locality"
},
  "geometry": {"coordinates":[-69.63124999999999,-11.0019],"type":"Point"}
}