{
  "type": "Feature",
  "properties": {
    "gn:admin1_code":"04",
    "gn:admin2_code":"401.0",
    "gn:admin3_code":"40124.0",
    "gn:asciiname":"Huayco",
    "gn:country_code":"PE",
    "gn:dem":2078,
    "gn:feature_class":"P",
    "gn:feature_code":"PPL",
    "gn:name":"Huayco",
    "gn:population":0,
    "gn:timezone":"America/Lima",
    "iso:country":"PE",
    "wof:name":"Huayco",
    "wof:placetype":"locality"
},
  "geometry": {"coordinates":[-71.63536999999999,-16.42525],"type":"Point"}
}