{
  "type": "Feature",
  "properties": {
    "gn:admin1_code":"03",
    "gn:admin2_code":"307.0",
    "gn:admin3_code":"30704.0",
    "gn:asciiname":"Ccullco",
    "gn:country_code":"PE",
    "gn:dem":3873,
    "gn:feature_class":"P",
    "gn:feature_code":"PPL",
    "gn:name":"Ccullco",
    "gn:population":0,
    "gn:timezone":"America/Lima",
    "iso:country":"PE",
    "wof:name":"Ccullco",
    "wof:placetype":"locality"
},
  "geometry": {"coordinates":[-72.49361,-13.95972],"type":"Point"}
}