{
  "type": "Feature",
  "properties": {
    "iso:country":"PE",
    "name:und_x_variant":[
        "Tanaco"
    ],
    "qs:gn_country":"PE",
    "qs:gn_fcode":"PPL",
    "qs:gn_pop":0,
    "qs:name":"Tanaca",
    "qs:name_adm0":"Per\u00fa",
    "qs:name_adm1":"Arequipa",
    "qs:photos":109,
    "qs:photos_1k":22,
    "qs:photos_9k":1,
    "qs:photos_9r":3,
    "qs:photos_all":109,
    "qs:photos_sr":3,
    "qs:placetype":"Town",
    "qs:pop_sr":"4",
    "qs:woe_adm0":23424919,
    "wof:name":"Tanaca",
    "wof:placetype":"locality"
},
  "geometry": {"coordinates":[-74.46093,-15.72755],"type":"Point"}
}