{
  "type": "Feature",
  "properties": {
    "gn:admin1_code":"07",
    "gn:admin2_code":"701.0",
    "gn:asciiname":"Veintisiete de Octubre",
    "gn:country_code":"PE",
    "gn:dem":2,
    "gn:feature_class":"P",
    "gn:feature_code":"PPL",
    "gn:name":"Veintisiete de Octubre",
    "gn:population":0,
    "gn:timezone":"America/Lima",
    "iso:country":"PE",
    "wof:name":"Veintisiete de Octubre",
    "wof:placetype":"locality"
},
  "geometry": {"coordinates":[-77.15000000000001,-12.03333],"type":"Point"}
}