{
  "type": "Feature",
  "properties": {
    "gn:admin1_code":"12.0",
    "gn:admin2_code":"1206.0",
    "gn:admin3_code":"120604.0",
    "gn:asciiname":"Boca Potsoteni",
    "gn:country_code":"PE",
    "gn:dem":362,
    "gn:feature_class":"P",
    "gn:feature_code":"PPLL",
    "gn:name":"Boca Potsoteni",
    "gn:population":0,
    "gn:timezone":"America/Lima",
    "iso:country":"PE",
    "wof:name":"Boca Potsoteni",
    "wof:placetype":"locality"
},
  "geometry": {"coordinates":[-74.14797,-11.42342],"type":"Point"}
}