{
  "type": "Feature",
  "properties": {
    "gn:admin1_code":"6",
    "gn:admin2_code":"603.0",
    "gn:admin3_code":"60303.0",
    "gn:asciiname":"Succha",
    "gn:country_code":"PE",
    "gn:dem":2424,
    "gn:feature_class":"P",
    "gn:feature_code":"PPL",
    "gn:name":"Succha",
    "gn:population":0,
    "gn:timezone":"America/Lima",
    "iso:country":"PE",
    "wof:name":"Succha",
    "wof:placetype":"locality"
},
  "geometry": {"coordinates":[-78.29901,-6.46613],"type":"Point"}
}