{
  "type": "Feature",
  "properties": {
    "gn:admin1_code":"2.0",
    "gn:admin2_code":"218.0",
    "gn:asciiname":"Bajo Canal",
    "gn:country_code":"PE",
    "gn:dem":118,
    "gn:feature_class":"P",
    "gn:feature_code":"PPL",
    "gn:name":"Bajo Canal",
    "gn:population":0,
    "gn:timezone":"America/Lima",
    "iso:country":"PE",
    "wof:name":"Bajo Canal",
    "wof:placetype":"locality"
},
  "geometry": {"coordinates":[-78.55221999999998,-8.94528],"type":"Point"}
}