{
  "type": "Feature",
  "properties": {
    "gn:admin1_code":"8",
    "gn:admin2_code":"806.0",
    "gn:admin3_code":"80608.0",
    "gn:asciiname":"Chigno",
    "gn:country_code":"PE",
    "gn:dem":3516,
    "gn:feature_class":"P",
    "gn:feature_code":"PPL",
    "gn:name":"Chigno",
    "gn:population":0,
    "gn:timezone":"America/Lima",
    "iso:country":"PE",
    "wof:name":"Chigno",
    "wof:placetype":"locality"
},
  "geometry": {"coordinates":[-71.37944,-14.14778],"type":"Point"}
}