{
  "type": "Feature",
  "properties": {
    "gn:admin1_code":"16",
    "gn:admin2_code":"1604.0",
    "gn:admin3_code":"160404.0",
    "gn:asciiname":"Peruate",
    "gn:cc2":"PE",
    "gn:country_code":"PE",
    "gn:dem":83,
    "gn:feature_class":"P",
    "gn:feature_code":"PPL",
    "gn:name":"Peruat\u00e9",
    "gn:population":0,
    "gn:timezone":"America/Lima",
    "iso:country":"PE",
    "name:und_x_variant":[
        "Santo Thomas P\u00e9ruate",
        "Peruat\u00e9"
    ],
    "wof:name":"Peruate",
    "wof:placetype":"locality"
},
  "geometry": {"coordinates":[-71.28333000000001,-3.75],"type":"Point"}
}