{
  "type": "Feature",
  "properties": {
    "gn:admin1_code":"06",
    "gn:admin2_code":"603.0",
    "gn:admin3_code":"60312.0",
    "gn:asciiname":"Hacienda Callacate",
    "gn:country_code":"PE",
    "gn:dem":2263,
    "gn:feature_class":"P",
    "gn:feature_code":"PPL",
    "gn:name":"Hacienda Callacate",
    "gn:population":0,
    "gn:timezone":"America/Lima",
    "iso:country":"PE",
    "wof:name":"Hacienda Callacate",
    "wof:placetype":"locality"
},
  "geometry": {"coordinates":[-78.26903,-6.77265],"type":"Point"}
}