{
  "type": "Feature",
  "properties": {
    "gn:admin1_code":"06",
    "gn:admin2_code":"611.0",
    "gn:admin3_code":"61109.0",
    "gn:asciiname":"Rejito",
    "gn:country_code":"PE",
    "gn:dem":3294,
    "gn:feature_class":"P",
    "gn:feature_code":"PPL",
    "gn:name":"Rejito",
    "gn:population":0,
    "gn:timezone":"America/Lima",
    "iso:country":"PE",
    "wof:name":"Rejito",
    "wof:placetype":"locality"
},
  "geometry": {"coordinates":[-79.08804000000001,-6.96307],"type":"Point"}
}