{
  "type": "Feature",
  "properties": {
    "gn:admin1_code":"21",
    "gn:admin2_code":"2103",
    "gn:asciiname":"Ccaruyo",
    "gn:country_code":"PE",
    "gn:dem":894,
    "gn:feature_class":"P",
    "gn:feature_code":"PPL",
    "gn:name":"Ccaruyo",
    "gn:population":0,
    "gn:timezone":"America/Lima",
    "iso:country":"PE",
    "name:spa_x_preferred":[
        "Ccaruyo"
    ],
    "wof:name":"Ccaruyo",
    "wof:placetype":"locality"
},
  "geometry": {"coordinates":[-69.78806,-13.74977],"type":"Point"}
}