{
  "type": "Feature",
  "properties": {
    "gn:admin1_code":"21",
    "gn:admin2_code":"2101.0",
    "gn:admin3_code":"210106.0",
    "gn:asciiname":"Carina",
    "gn:country_code":"PE",
    "gn:dem":3836,
    "gn:feature_class":"P",
    "gn:feature_code":"PPL",
    "gn:name":"Carina",
    "gn:population":0,
    "gn:timezone":"America/Lima",
    "iso:country":"PE",
    "name:bos_x_preferred":[
        "Carina"
    ],
    "name:ceb_x_preferred":[
        "Carina"
    ],
    "name:deu_x_preferred":[
        "Carina"
    ],
    "name:est_x_preferred":[
        "Carina"
    ],
    "name:fas_x_preferred":[
        "\u0634\u0627\u0647\u200c\u062a\u062e\u062a\u0647"
    ],
    "name:fin_x_preferred":[
        "Carina"
    ],
    "name:fra_x_preferred":[
        "Carina"
    ],
    "name:hrv_x_preferred":[
        "Carina"
    ],
    "name:hun_x_preferred":[
        "Carina"
    ],
    "name:ita_x_preferred":[
        "Carina"
    ],
    "name:jpn_x_preferred":[
        "\u30ab\u30ea\u30fc\u30ca"
    ],
    "name:kor_x_preferred":[
        "\uce74\ub9ac\ub098"
    ],
    "name:lat_x_preferred":[
        "Carina"
    ],
    "name:nld_x_preferred":[
        "Carina"
    ],
    "name:nno_x_preferred":[
        "Carina"
    ],
    "name:nor_x_preferred":[
        "Carina"
    ],
    "name:pol_x_preferred":[
        "Carina"
    ],
    "name:slv_x_preferred":[
        "Carina"
    ],
    "name:srp_x_preferred":[
        "\u0426\u0430\u0440\u0438\u043d\u0430"
    ],
    "name:swe_x_preferred":[
        "Carina"
    ],
    "wof:name":"Carina",
    "wof:placetype":"locality"
},
  "geometry": {"coordinates":[-69.80513000000001,-15.79341],"type":"Point"}
}