{
  "type": "Feature",
  "properties": {
    "gn:admin1_code":"21",
    "gn:admin2_code":"2101.0",
    "gn:admin3_code":"210106.0",
    "gn:asciiname":"Carina",
    "gn:country_code":"PE",
    "gn:dem":3836,
    "gn:feature_class":"P",
    "gn:feature_code":"PPL",
    "gn:name":"Carina",
    "gn:population":0,
    "gn:timezone":"America/Lima",
    "iso:country":"PE",
    "wof:name":"Carina",
    "wof:placetype":"locality"
},
  "geometry": {"coordinates":[-69.80513000000001,-15.79341],"type":"Point"}
}