{
  "type": "Feature",
  "properties": {
    "gn:admin1_code":"15",
    "gn:admin2_code":"1505.0",
    "gn:admin3_code":"150514.0",
    "gn:asciiname":"La Huaca",
    "gn:country_code":"PE",
    "gn:dem":48,
    "gn:feature_class":"P",
    "gn:feature_code":"PPL",
    "gn:name":"La Huaca",
    "gn:population":0,
    "gn:timezone":"America/Lima",
    "iso:country":"PE",
    "name:und_x_variant":[
        "La Huaca Hacienda",
        "La Huaca"
    ],
    "wof:name":"La Huaca",
    "wof:placetype":"locality"
},
  "geometry": {"coordinates":[-76.40946,-13.04948],"type":"Point"}
}