{
  "type": "Feature",
  "properties": {
    "gn:admin1_code":"15",
    "gn:admin2_code":"1508.0",
    "gn:admin3_code":"150808.0",
    "gn:asciiname":"San Juan de Huagar",
    "gn:country_code":"PE",
    "gn:dem":3047,
    "gn:feature_class":"P",
    "gn:feature_code":"PPL",
    "gn:name":"San Juan de Huagar",
    "gn:population":0,
    "gn:timezone":"America/Lima",
    "iso:country":"PE",
    "wof:name":"San Juan de Huagar",
    "wof:placetype":"locality"
},
  "geometry": {"coordinates":[-76.95401,-10.95733],"type":"Point"}
}