{
  "type": "Feature",
  "properties": {
    "gn:admin1_code":"15",
    "gn:admin2_code":"1510.0",
    "gn:admin3_code":"151009.0",
    "gn:asciiname":"Hacienda",
    "gn:country_code":"PE",
    "gn:dem":2559,
    "gn:feature_class":"P",
    "gn:feature_code":"PPL",
    "gn:name":"Hacienda",
    "gn:population":0,
    "gn:timezone":"America/Lima",
    "iso:country":"PE",
    "name:bul_x_preferred":[
        "\u0425\u0430\u0441\u0438\u0435\u043d\u0434\u0430"
    ],
    "name:cat_x_preferred":[
        "Hisenda"
    ],
    "name:ceb_x_preferred":[
        "Asyenda"
    ],
    "name:deu_x_preferred":[
        "Hazienda"
    ],
    "name:eus_x_preferred":[
        "Hacienda"
    ],
    "name:fra_x_preferred":[
        "Hacienda"
    ],
    "name:hun_x_preferred":[
        "Hacienda"
    ],
    "name:ind_x_preferred":[
        "Hacienda"
    ],
    "name:ita_x_preferred":[
        "Hacienda"
    ],
    "name:jpn_x_preferred":[
        "\u30a2\u30b7\u30a8\u30f3\u30c0\u5236"
    ],
    "name:kaz_x_preferred":[
        "\u0410\u0441\u044c\u0435\u043d\u0434\u0430"
    ],
    "name:kor_x_preferred":[
        "\uc544\uc2dc\uc5d4\ub2e4"
    ],
    "name:lit_x_preferred":[
        "Asjenda"
    ],
    "name:msa_x_preferred":[
        "Hasienda"
    ],
    "name:nld_x_preferred":[
        "Haci\u00ebnda"
    ],
    "name:nor_x_preferred":[
        "Hacienda"
    ],
    "name:pol_x_preferred":[
        "Hacjenda"
    ],
    "name:que_x_preferred":[
        "Qichuychakra"
    ],
    "name:ron_x_preferred":[
        "Haciend\u0103"
    ],
    "name:rus_x_preferred":[
        "\u0410\u0441\u044c\u0435\u043d\u0434\u0430"
    ],
    "name:spa_x_preferred":[
        "Hacienda"
    ],
    "name:swe_x_preferred":[
        "Hacienda"
    ],
    "name:tat_x_preferred":[
        "Asienda"
    ],
    "name:tgl_x_preferred":[
        "Asyenda"
    ],
    "name:ukr_x_preferred":[
        "\u0410\u0441\u044c\u0454\u043d\u0434\u0430"
    ],
    "wof:name":"Hacienda",
    "wof:placetype":"locality"
},
  "geometry": {"coordinates":[-75.88139,-12.90361],"type":"Point"}
}