{
  "type": "Feature",
  "properties": {
    "gn:admin1_code":"15",
    "gn:admin2_code":"1510.0",
    "gn:admin3_code":"151009.0",
    "gn:asciiname":"Hacienda",
    "gn:country_code":"PE",
    "gn:dem":2559,
    "gn:feature_class":"P",
    "gn:feature_code":"PPL",
    "gn:name":"Hacienda",
    "gn:population":0,
    "gn:timezone":"America/Lima",
    "iso:country":"PE",
    "wof:name":"Hacienda",
    "wof:placetype":"locality"
},
  "geometry": {"coordinates":[-75.88139,-12.90361],"type":"Point"}
}