{
  "type": "Feature",
  "properties": {
    "gn:admin1_code":"12.0",
    "gn:admin2_code":"1203.0",
    "gn:admin3_code":"120302.0",
    "gn:asciiname":"Pampa del Oso",
    "gn:country_code":"PE",
    "gn:dem":1553,
    "gn:feature_class":"P",
    "gn:feature_code":"PPL",
    "gn:name":"Pampa del Oso",
    "gn:population":0,
    "gn:timezone":"America/Lima",
    "iso:country":"PE",
    "wof:name":"Pampa del Oso",
    "wof:placetype":"locality"
},
  "geometry": {"coordinates":[-75.16741999999998,-11.00976],"type":"Point"}
}