{
  "type": "Feature",
  "properties": {
    "gn:admin1_code":"04",
    "gn:admin2_code":"403.0",
    "gn:admin3_code":"40306.0",
    "gn:asciiname":"Pirca",
    "gn:country_code":"PE",
    "gn:dem":3439,
    "gn:feature_class":"P",
    "gn:feature_code":"PPL",
    "gn:name":"Pirca",
    "gn:population":0,
    "gn:timezone":"America/Lima",
    "iso:country":"PE",
    "name:spa_x_preferred":[
        "Pirca"
    ],
    "wof:name":"Pirca",
    "wof:placetype":"locality"
},
  "geometry": {"coordinates":[-73.34735999999999,-15.41625],"type":"Point"}
}