{
  "type": "Feature",
  "properties": {
    "gn:admin1_code":"8",
    "gn:admin2_code":"806.0",
    "gn:admin3_code":"80601.0",
    "gn:asciiname":"Pallcachaca",
    "gn:country_code":"PE",
    "gn:dem":4346,
    "gn:feature_class":"P",
    "gn:feature_code":"PPL",
    "gn:name":"Pallcachaca",
    "gn:population":0,
    "gn:timezone":"America/Lima",
    "iso:country":"PE",
    "wof:name":"Pallcachaca",
    "wof:placetype":"locality"
},
  "geometry": {"coordinates":[-71.04691,-14.19384],"type":"Point"}
}