{
  "type": "Feature",
  "properties": {
    "gn:admin1_code":"3.0",
    "gn:admin2_code":"305.0",
    "gn:admin3_code":"30503.0",
    "gn:asciiname":"Pacharazo",
    "gn:country_code":"PE",
    "gn:dem":2347,
    "gn:feature_class":"P",
    "gn:feature_code":"PPL",
    "gn:name":"Pacharazo",
    "gn:population":0,
    "gn:timezone":"America/Lima",
    "iso:country":"PE",
    "wof:name":"Pacharazo",
    "wof:placetype":"locality"
},
  "geometry": {"coordinates":[-72.47166999999997,-13.83389],"type":"Point"}
}