{
  "type": "Feature",
  "properties": {
    "gn:admin1_code":"15",
    "gn:admin2_code":"1508.0",
    "gn:admin3_code":"150806.0",
    "gn:asciiname":"San Jose de Rontoy",
    "gn:cc2":"PE",
    "gn:country_code":"PE",
    "gn:dem":107,
    "gn:feature_class":"P",
    "gn:feature_code":"PPL",
    "gn:name":"San Jos\u00e9 de Rontoy",
    "gn:population":0,
    "gn:timezone":"America/Lima",
    "iso:country":"PE",
    "name:und_x_variant":[
        "Hacienda Rontoy",
        "Rontoy",
        "Rontoy Hacienda",
        "San Jos\u00e9 de Rontoy"
    ],
    "wof:name":"San Jose de Rontoy",
    "wof:placetype":"locality"
},
  "geometry": {"coordinates":[-77.56889,-11.045],"type":"Point"}
}