{
  "type": "Feature",
  "properties": {
    "gn:admin1_code":"12",
    "gn:admin2_code":"1208.0",
    "gn:admin3_code":"120810.0",
    "gn:asciiname":"San Cristobal",
    "gn:country_code":"PE",
    "gn:dem":4658,
    "gn:feature_class":"P",
    "gn:feature_code":"PPL",
    "gn:name":"San Crist\u00f3bal",
    "gn:population":0,
    "gn:timezone":"America/Lima",
    "iso:country":"PE",
    "wof:name":"San Cristobal",
    "wof:placetype":"locality"
},
  "geometry": {"coordinates":[-76.05778000000002,-11.74111],"type":"Point"}
}