{
  "type": "Feature",
  "properties": {
    "gn:admin1_code":"4",
    "gn:admin2_code":"401.0",
    "gn:admin3_code":"40125.0",
    "gn:asciiname":"San Javier Hacienda",
    "gn:country_code":"PE",
    "gn:dem":1117,
    "gn:feature_class":"P",
    "gn:feature_code":"PPL",
    "gn:name":"San Javier Hacienda",
    "gn:population":0,
    "gn:timezone":"America/Lima",
    "iso:country":"PE",
    "wof:name":"San Javier Hacienda",
    "wof:placetype":"locality"
},
  "geometry": {"coordinates":[-71.95097,-16.50395],"type":"Point"}
}