{
  "type": "Feature",
  "properties": {
    "gn:admin1_code":"9",
    "gn:admin2_code":"906.0",
    "gn:admin3_code":"90615.0",
    "gn:asciiname":"Ocustambo",
    "gn:country_code":"PE",
    "gn:dem":2267,
    "gn:feature_class":"P",
    "gn:feature_code":"PPL",
    "gn:name":"Ocustambo",
    "gn:population":0,
    "gn:timezone":"America/Lima",
    "iso:country":"PE",
    "wof:name":"Ocustambo",
    "wof:placetype":"locality"
},
  "geometry": {"coordinates":[-75.33972,-13.74667],"type":"Point"}
}