{
  "type": "Feature",
  "properties": {
    "gn:admin1_code":"12.0",
    "gn:admin2_code":"1203.0",
    "gn:admin3_code":"120305.0",
    "gn:asciiname":"San Pedro de Puntayacu",
    "gn:country_code":"PE",
    "gn:dem":1151,
    "gn:feature_class":"P",
    "gn:feature_code":"PPL",
    "gn:name":"San Pedro de Puntayacu",
    "gn:population":0,
    "gn:timezone":"America/Lima",
    "iso:country":"PE",
    "wof:name":"San Pedro de Puntayacu",
    "wof:placetype":"locality"
},
  "geometry": {"coordinates":[-75.42506999999998,-11.15901],"type":"Point"}
}