{
  "type": "Feature",
  "properties": {
    "gn:admin1_code":"21",
    "gn:admin2_code":"2102.0",
    "gn:admin3_code":"210214.0",
    "gn:asciiname":"Japune",
    "gn:country_code":"PE",
    "gn:dem":3859,
    "gn:feature_class":"P",
    "gn:feature_code":"PPL",
    "gn:name":"Japune",
    "gn:population":0,
    "gn:timezone":"America/Lima",
    "iso:country":"PE",
    "wof:name":"Japune",
    "wof:placetype":"locality"
},
  "geometry": {"coordinates":[-70.34772,-15.14765],"type":"Point"}
}