{
  "type": "Feature",
  "properties": {
    "gn:admin1_code":"15",
    "gn:admin2_code":"1510.0",
    "gn:admin3_code":"151033.0",
    "gn:asciiname":"Tunshucancha",
    "gn:country_code":"PE",
    "gn:dem":4467,
    "gn:feature_class":"P",
    "gn:feature_code":"PPL",
    "gn:name":"Tunshucancha",
    "gn:population":0,
    "gn:timezone":"America/Lima",
    "iso:country":"PE",
    "wof:name":"Tunshucancha",
    "wof:placetype":"locality"
},
  "geometry": {"coordinates":[-75.89556,-12.10417],"type":"Point"}
}