{
  "type": "Feature",
  "properties": {
    "gn:admin1_code":"09",
    "gn:admin2_code":"906.0",
    "gn:admin3_code":"90607.0",
    "gn:asciiname":"Taccancayo",
    "gn:country_code":"PE",
    "gn:dem":4397,
    "gn:feature_class":"P",
    "gn:feature_code":"PPL",
    "gn:name":"Taccancayo",
    "gn:population":0,
    "gn:timezone":"America/Lima",
    "iso:country":"PE",
    "wof:name":"Taccancayo",
    "wof:placetype":"locality"
},
  "geometry": {"coordinates":[-74.82871,-13.73229],"type":"Point"}
}