{
  "type": "Feature",
  "properties": {
    "gn:admin1_code":"24",
    "gn:admin2_code":"2401.0",
    "gn:admin3_code":"240105.0",
    "gn:asciiname":"Plateros",
    "gn:country_code":"PE",
    "gn:dem":25,
    "gn:feature_class":"P",
    "gn:feature_code":"PPL",
    "gn:name":"Plateros",
    "gn:population":0,
    "gn:timezone":"America/Lima",
    "iso:country":"PE",
    "name:ceb_x_preferred":[
        "Plateros"
    ],
    "name:swe_x_preferred":[
        "Plateros"
    ],
    "name:und_x_variant":[
        "Plateros Hacienda"
    ],
    "name:war_x_preferred":[
        "Plateros"
    ],
    "wof:name":"Plateros",
    "wof:placetype":"locality"
},
  "geometry": {"coordinates":[-80.4483,-3.65605],"type":"Point"}
}