{
  "type": "Feature",
  "properties": {
    "gn:admin1_code":"9.0",
    "gn:admin2_code":"907.0",
    "gn:admin3_code":"90717.0",
    "gn:asciiname":"Rumicruz",
    "gn:country_code":"PE",
    "gn:dem":3754,
    "gn:feature_class":"P",
    "gn:feature_code":"PPL",
    "gn:name":"Rumicruz",
    "gn:population":0,
    "gn:timezone":"America/Lima",
    "iso:country":"PE",
    "wof:name":"Rumicruz",
    "wof:placetype":"locality"
},
  "geometry": {"coordinates":[-74.63639999999999,-12.17291],"type":"Point"}
}