{
  "type": "Feature",
  "properties": {
    "gn:admin1_code":"12",
    "gn:admin2_code":"1206.0",
    "gn:admin3_code":"120601.0",
    "gn:asciiname":"Marankiari",
    "gn:cc2":"PE",
    "gn:country_code":"PE",
    "gn:dem":996,
    "gn:feature_class":"P",
    "gn:feature_code":"PPL",
    "gn:name":"Marankiari",
    "gn:population":0,
    "gn:timezone":"America/Lima",
    "iso:country":"PE",
    "name:und_x_variant":[
        "Moran Kiari",
        "Maranquiari",
        "Marankiari"
    ],
    "wof:name":"Marankiari",
    "wof:placetype":"locality"
},
  "geometry": {"coordinates":[-74.58333,-11.18333],"type":"Point"}
}