{
  "type": "Feature",
  "properties": {
    "gn:admin1_code":"5",
    "gn:admin2_code":"505.0",
    "gn:admin3_code":"50502.0",
    "gn:asciiname":"Anco",
    "gn:country_code":"PE",
    "gn:dem":3787,
    "gn:feature_class":"P",
    "gn:feature_code":"PPL",
    "gn:name":"Anco",
    "gn:population":0,
    "gn:timezone":"America/Lima",
    "iso:country":"PE",
    "wof:name":"Anco",
    "wof:placetype":"locality"
},
  "geometry": {"coordinates":[-73.68755,-13.11352],"type":"Point"}
}