{
  "type": "Feature",
  "properties": {
    "gn:admin1_code":"18",
    "gn:admin2_code":"1802.0",
    "gn:admin3_code":"180210.0",
    "gn:asciiname":"Pachamayo",
    "gn:country_code":"PE",
    "gn:dem":3858,
    "gn:feature_class":"P",
    "gn:feature_code":"PPL",
    "gn:name":"Pachamayo",
    "gn:population":0,
    "gn:timezone":"America/Lima",
    "iso:country":"PE",
    "wof:name":"Pachamayo",
    "wof:placetype":"locality"
},
  "geometry": {"coordinates":[-70.68482,-16.17047],"type":"Point"}
}