{
  "type": "Feature",
  "properties": {
    "gn:admin1_code":"08",
    "gn:admin2_code":"809.0",
    "gn:admin3_code":"80906.0",
    "gn:asciiname":"Mercedes",
    "gn:country_code":"PE",
    "gn:dem":1648,
    "gn:feature_class":"P",
    "gn:feature_code":"PPL",
    "gn:name":"Mercedes",
    "gn:population":0,
    "gn:timezone":"America/Lima",
    "iso:country":"PE",
    "name:bre_x_preferred":[
        "Mercedes"
    ],
    "name:cat_x_preferred":[
        "Mercedes"
    ],
    "name:ceb_x_preferred":[
        "Mercedes"
    ],
    "name:ces_x_preferred":[
        "Mercedes"
    ],
    "name:dan_x_preferred":[
        "Mercedes"
    ],
    "name:deu_x_preferred":[
        "Mercedes"
    ],
    "name:fas_x_preferred":[
        "\u0645\u0631\u0633\u062f\u0633"
    ],
    "name:fin_x_preferred":[
        "Mercedes"
    ],
    "name:fra_x_preferred":[
        "Mercedes"
    ],
    "name:heb_x_preferred":[
        "\u05de\u05e8\u05e6\u05d3\u05e1"
    ],
    "name:heb_x_variant":[
        "\u05de\u05e8\u05e1\u05d3\u05e1"
    ],
    "name:hin_x_preferred":[
        "\u092e\u0930\u094d\u0938\u0940\u0921\u0940\u091c\u093c"
    ],
    "name:hrv_x_preferred":[
        "Mercedes"
    ],
    "name:hun_x_preferred":[
        "Mercedes"
    ],
    "name:ilo_x_preferred":[
        "Mercedes"
    ],
    "name:ind_x_preferred":[
        "Mercedes"
    ],
    "name:ita_x_preferred":[
        "Mercedes"
    ],
    "name:jpn_x_preferred":[
        "\u30e1\u30eb\u30bb\u30c7\u30b9"
    ],
    "name:kor_x_preferred":[
        "\uba54\ub974\uc138\ub370\uc2a4"
    ],
    "name:lit_x_preferred":[
        "Mersedesas"
    ],
    "name:mlg_x_preferred":[
        "Mercedes"
    ],
    "name:nld_x_preferred":[
        "Mercedes"
    ],
    "name:nor_x_preferred":[
        "Mercedes"
    ],
    "name:pol_x_preferred":[
        "Mercedes"
    ],
    "name:por_x_preferred":[
        "Mercedes"
    ],
    "name:ron_x_preferred":[
        "Mercedes"
    ],
    "name:rus_x_preferred":[
        "\u041c\u0435\u0440\u0441\u0435\u0434\u0435\u0441"
    ],
    "name:sco_x_preferred":[
        "Mercedes"
    ],
    "name:slk_x_preferred":[
        "Mercedes"
    ],
    "name:spa_x_preferred":[
        "Mercedes"
    ],
    "name:srp_x_preferred":[
        "\u041c\u0435\u0440\u0441\u0435\u0434\u0435\u0441"
    ],
    "name:swe_x_preferred":[
        "Mercedes"
    ],
    "name:tur_x_preferred":[
        "Mercedes"
    ],
    "name:ukr_x_preferred":[
        "\u041c\u0435\u0440\u0441\u0435\u0434\u0435\u0441"
    ],
    "name:urd_x_preferred":[
        "\u0645\u0631\u0633\u06cc\u0688\u06cc\u0632"
    ],
    "name:vie_x_preferred":[
        "Mercedes"
    ],
    "name:vol_x_preferred":[
        "Mercedes"
    ],
    "name:war_x_preferred":[
        "Mercedes"
    ],
    "name:zho_x_preferred":[
        "\u6885\u8d5b\u5fb7\u65af"
    ],
    "wof:name":"Mercedes",
    "wof:placetype":"locality"
},
  "geometry": {"coordinates":[-72.65000000000001,-12.45],"type":"Point"}
}