{
  "type": "Feature",
  "properties": {
    "gn:admin1_code":"06",
    "gn:admin2_code":"603.0",
    "gn:admin3_code":"60304.0",
    "gn:asciiname":"Sendamal",
    "gn:country_code":"PE",
    "gn:dem":3381,
    "gn:feature_class":"P",
    "gn:feature_code":"PPL",
    "gn:name":"Sendamal",
    "gn:population":0,
    "gn:timezone":"America/Lima",
    "iso:country":"PE",
    "wof:name":"Sendamal",
    "wof:placetype":"locality"
},
  "geometry": {"coordinates":[-78.22365000000001,-6.97211],"type":"Point"}
}