{
  "type": "Feature",
  "properties": {
    "gn:admin1_code":"16",
    "gn:admin2_code":"1601.0",
    "gn:admin3_code":"160107.0",
    "gn:asciiname":"Isla Inayuga",
    "gn:country_code":"PE",
    "gn:dem":117,
    "gn:feature_class":"P",
    "gn:feature_code":"PPL",
    "gn:name":"Isla Inayuga",
    "gn:population":0,
    "gn:timezone":"America/Lima",
    "iso:country":"PE",
    "wof:name":"Isla Inayuga",
    "wof:placetype":"locality"
},
  "geometry": {"coordinates":[-73.60746999999998,-2.48218],"type":"Point"}
}