{
  "type": "Feature",
  "properties": {
    "gn:admin1_code":"5.0",
    "gn:admin2_code":"501.0",
    "gn:admin3_code":"50115.0",
    "gn:asciiname":"Gloriete",
    "gn:country_code":"PE",
    "gn:dem":2653,
    "gn:feature_class":"P",
    "gn:feature_code":"PPL",
    "gn:name":"Gloriete",
    "gn:population":0,
    "gn:timezone":"America/Lima",
    "iso:country":"PE",
    "wof:name":"Gloriete",
    "wof:placetype":"locality"
},
  "geometry": {"coordinates":[-74.19198,-13.13317],"type":"Point"}
}