{
  "type": "Feature",
  "properties": {
    "gn:admin1_code":"1",
    "gn:admin2_code":"105.0",
    "gn:admin3_code":"10502.0",
    "gn:asciiname":"Ocsho",
    "gn:country_code":"PE",
    "gn:dem":1651,
    "gn:feature_class":"P",
    "gn:feature_code":"PPL",
    "gn:name":"Ocsho",
    "gn:population":0,
    "gn:timezone":"America/Lima",
    "iso:country":"PE",
    "wof:name":"Ocsho",
    "wof:placetype":"locality"
},
  "geometry": {"coordinates":[-78.30332,-6.21138],"type":"Point"}
}