{
  "type": "Feature",
  "properties": {
    "gn:admin1_code":"3.0",
    "gn:admin2_code":"305.0",
    "gn:admin3_code":"30502.0",
    "gn:asciiname":"Llamarumioc",
    "gn:country_code":"PE",
    "gn:dem":4208,
    "gn:feature_class":"P",
    "gn:feature_code":"PPL",
    "gn:name":"Llamarumioc",
    "gn:population":0,
    "gn:timezone":"America/Lima",
    "iso:country":"PE",
    "wof:name":"Llamarumioc",
    "wof:placetype":"locality"
},
  "geometry": {"coordinates":[-72.26833000000001,-13.77694],"type":"Point"}
}