{
  "type": "Feature",
  "properties": {
    "gn:admin1_code":"10.0",
    "gn:admin2_code":"1010.0",
    "gn:admin3_code":"101001.0",
    "gn:asciiname":"Aparicuna",
    "gn:country_code":"PE",
    "gn:dem":3771,
    "gn:feature_class":"P",
    "gn:feature_code":"PPL",
    "gn:name":"Aparicuna",
    "gn:population":0,
    "gn:timezone":"America/Lima",
    "iso:country":"PE",
    "wof:name":"Aparicuna",
    "wof:placetype":"locality"
},
  "geometry": {"coordinates":[-76.76861,-10.22028],"type":"Point"}
}