{
  "type": "Feature",
  "properties": {
    "gn:admin1_code":"14",
    "gn:admin2_code":"1402.0",
    "gn:admin3_code":"140203.0",
    "gn:asciiname":"Tasajera",
    "gn:country_code":"PE",
    "gn:dem":3010,
    "gn:feature_class":"P",
    "gn:feature_code":"PPL",
    "gn:name":"Tasajera",
    "gn:population":0,
    "gn:timezone":"America/Lima",
    "iso:country":"PE",
    "wof:name":"Tasajera",
    "wof:placetype":"locality"
},
  "geometry": {"coordinates":[-79.33065000000001,-6.21561],"type":"Point"}
}