{
  "type": "Feature",
  "properties": {
    "gn:admin1_code":"04",
    "gn:admin2_code":"405.0",
    "gn:admin3_code":"40504.0",
    "gn:asciiname":"Pusahuina",
    "gn:country_code":"PE",
    "gn:dem":4235,
    "gn:feature_class":"P",
    "gn:feature_code":"PPL",
    "gn:name":"Pusahui\u00f1a",
    "gn:population":0,
    "gn:timezone":"America/Lima",
    "iso:country":"PE",
    "wof:name":"Pusahuina",
    "wof:placetype":"locality"
},
  "geometry": {"coordinates":[-71.39778000000003,-15.475],"type":"Point"}
}