{
  "type": "Feature",
  "properties": {
    "gn:admin1_code":"17.0",
    "gn:admin2_code":"1703.0",
    "gn:asciiname":"Tres Fronteras",
    "gn:country_code":"PE",
    "gn:dem":246,
    "gn:feature_class":"P",
    "gn:feature_code":"PPL",
    "gn:name":"Tres Fronteras",
    "gn:population":0,
    "gn:timezone":"America/Lima",
    "iso:country":"PE",
    "name:spa_x_preferred":[
        "Tres Fronteras"
    ],
    "wof:name":"Tres Fronteras",
    "wof:placetype":"locality"
},
  "geometry": {"coordinates":[-69.56518,-10.96919],"type":"Point"}
}