{
  "type": "Feature",
  "properties": {
    "gn:admin1_code":"01",
    "gn:admin2_code":"102.0",
    "gn:admin3_code":"10205.0",
    "gn:asciiname":"Tsamaren",
    "gn:country_code":"PE",
    "gn:dem":298,
    "gn:feature_class":"P",
    "gn:feature_code":"PPL",
    "gn:name":"Tsamar\u00e9n",
    "gn:population":0,
    "gn:timezone":"America/Lima",
    "iso:country":"PE",
    "wof:name":"Tsamaren",
    "wof:placetype":"locality"
},
  "geometry": {"coordinates":[-78.38249,-5.18028],"type":"Point"}
}