{
  "type": "Feature",
  "properties": {
    "gn:admin1_code":"21",
    "gn:admin2_code":"2104.0",
    "gn:admin3_code":"210407.0",
    "gn:asciiname":"Huatuhuatupampa",
    "gn:country_code":"PE",
    "gn:dem":3831,
    "gn:feature_class":"P",
    "gn:feature_code":"PPL",
    "gn:name":"Huatuhuatupampa",
    "gn:population":0,
    "gn:timezone":"America/Lima",
    "iso:country":"PE",
    "wof:name":"Huatuhuatupampa",
    "wof:placetype":"locality"
},
  "geometry": {"coordinates":[-69.09010000000001,-16.51711],"type":"Point"}
}