{
  "type": "Feature",
  "properties": {
    "gn:admin1_code":"16",
    "gn:admin2_code":"1602.0",
    "gn:admin3_code":"160202.0",
    "gn:asciiname":"Nueva Barranquita",
    "gn:country_code":"PE",
    "gn:dem":180,
    "gn:feature_class":"P",
    "gn:feature_code":"PPL",
    "gn:name":"Nueva Barranquita",
    "gn:population":0,
    "gn:timezone":"America/Lima",
    "iso:country":"PE",
    "name:spa_x_preferred":[
        "Nueva Barranquita"
    ],
    "wof:name":"Nueva Barranquita",
    "wof:placetype":"locality"
},
  "geometry": {"coordinates":[-76.53270999999999,-5.80354],"type":"Point"}
}