{
  "type": "Feature",
  "properties": {
    "gn:admin1_code":"24",
    "gn:admin2_code":"2401.0",
    "gn:admin3_code":"240102.0",
    "gn:asciiname":"La Teran",
    "gn:country_code":"PE",
    "gn:dem":7,
    "gn:feature_class":"P",
    "gn:feature_code":"PPL",
    "gn:name":"La Teran",
    "gn:population":0,
    "gn:timezone":"America/Lima",
    "iso:country":"PE",
    "wof:name":"La Teran",
    "wof:placetype":"locality"
},
  "geometry": {"coordinates":[-80.46935999999999,-3.56756],"type":"Point"}
}