{
  "type": "Feature",
  "properties": {
    "gn:admin1_code":"15",
    "gn:admin2_code":"1508.0",
    "gn:admin3_code":"150808.0",
    "gn:asciiname":"Colcapampa",
    "gn:country_code":"PE",
    "gn:dem":2440,
    "gn:feature_class":"P",
    "gn:feature_code":"PPL",
    "gn:name":"Colcapampa",
    "gn:population":0,
    "gn:timezone":"America/Lima",
    "iso:country":"PE",
    "wof:name":"Colcapampa",
    "wof:placetype":"locality"
},
  "geometry": {"coordinates":[-76.94815,-10.91921],"type":"Point"}
}