{
  "type": "Feature",
  "properties": {
    "gn:admin1_code":"8",
    "gn:admin2_code":"809.0",
    "gn:admin3_code":"80906.0",
    "gn:asciiname":"Chogoriari",
    "gn:country_code":"PE",
    "gn:dem":1189,
    "gn:feature_class":"P",
    "gn:feature_code":"PPL",
    "gn:name":"Chogoriari",
    "gn:population":0,
    "gn:timezone":"America/Lima",
    "iso:country":"PE",
    "wof:name":"Chogoriari",
    "wof:placetype":"locality"
},
  "geometry": {"coordinates":[-72.60030999999999,-12.56676],"type":"Point"}
}