{
  "type": "Feature",
  "properties": {
    "gn:admin1_code":"12",
    "gn:admin2_code":"1202.0",
    "gn:admin3_code":"120203.0",
    "gn:asciiname":"Punco",
    "gn:country_code":"PE",
    "gn:dem":3058,
    "gn:feature_class":"P",
    "gn:feature_code":"PPL",
    "gn:name":"Punco",
    "gn:population":0,
    "gn:timezone":"America/Lima",
    "iso:country":"PE",
    "wof:name":"Punco",
    "wof:placetype":"locality"
},
  "geometry": {"coordinates":[-74.82549,-11.64811],"type":"Point"}
}