{
  "type": "Feature",
  "properties": {
    "gn:admin1_code":"10.0",
    "gn:admin2_code":"1005.0",
    "gn:admin3_code":"100503.0",
    "gn:asciiname":"Quisijirca",
    "gn:country_code":"PE",
    "gn:dem":2893,
    "gn:feature_class":"P",
    "gn:feature_code":"PPL",
    "gn:name":"Quisijirca",
    "gn:population":0,
    "gn:timezone":"America/Lima",
    "iso:country":"PE",
    "wof:name":"Quisijirca",
    "wof:placetype":"locality"
},
  "geometry": {"coordinates":[-76.78654,-9.4543],"type":"Point"}
}