{
  "type": "Feature",
  "properties": {
    "gn:admin1_code":"13",
    "gn:admin2_code":"1309.0",
    "gn:admin3_code":"130906.0",
    "gn:asciiname":"Angasmarquilla",
    "gn:country_code":"PE",
    "gn:dem":2978,
    "gn:feature_class":"P",
    "gn:feature_code":"PPL",
    "gn:name":"Angasmarquilla",
    "gn:population":0,
    "gn:timezone":"America/Lima",
    "iso:country":"PE",
    "wof:name":"Angasmarquilla",
    "wof:placetype":"locality"
},
  "geometry": {"coordinates":[-78.1404,-7.71568],"type":"Point"}
}