{
  "type": "Feature",
  "properties": {
    "gn:admin1_code":"5",
    "gn:admin2_code":"509.0",
    "gn:admin3_code":"50901.0",
    "gn:asciiname":"Pucarpata",
    "gn:country_code":"PE",
    "gn:dem":3184,
    "gn:feature_class":"P",
    "gn:feature_code":"PPL",
    "gn:name":"Pucarpata",
    "gn:population":0,
    "gn:timezone":"America/Lima",
    "iso:country":"PE",
    "wof:name":"Pucarpata",
    "wof:placetype":"locality"
},
  "geometry": {"coordinates":[-73.87194000000002,-14.00639],"type":"Point"}
}