{
  "type": "Feature",
  "properties": {
    "gn:admin1_code":"05",
    "gn:admin2_code":"509.0",
    "gn:admin3_code":"50911.0",
    "gn:asciiname":"Soras",
    "gn:country_code":"PE",
    "gn:dem":3424,
    "gn:feature_class":"P",
    "gn:feature_code":"PPLA3",
    "gn:name":"Soras",
    "gn:population":0,
    "gn:timezone":"America/Lima",
    "iso:country":"PE",
    "wof:name":"Soras",
    "wof:placetype":"locality"
},
  "geometry": {"coordinates":[-73.60444,-14.115],"type":"Point"}
}