{
  "type": "Feature",
  "properties": {
    "gn:admin1_code":"1.0",
    "gn:admin2_code":"106.0",
    "gn:admin3_code":"10612.0",
    "gn:asciiname":"Galilea",
    "gn:country_code":"PE",
    "gn:dem":1127,
    "gn:feature_class":"P",
    "gn:feature_code":"PPL",
    "gn:name":"Galilea",
    "gn:population":0,
    "gn:timezone":"America/Lima",
    "iso:country":"PE",
    "wof:name":"Galilea",
    "wof:placetype":"locality"
},
  "geometry": {"coordinates":[-77.18971999999999,-6.24722],"type":"Point"}
}