{
  "type": "Feature",
  "properties": {
    "gn:admin1_code":"04",
    "gn:admin2_code":"403.0",
    "gn:admin3_code":"40309.0",
    "gn:asciiname":"Chaccuille",
    "gn:country_code":"PE",
    "gn:dem":1098,
    "gn:feature_class":"P",
    "gn:feature_code":"PPL",
    "gn:name":"Chaccuille",
    "gn:population":0,
    "gn:timezone":"America/Lima",
    "iso:country":"PE",
    "name:spa_x_preferred":[
        "Chaccuille"
    ],
    "name:und_x_variant":[
        "Chacchuille"
    ],
    "wof:name":"Chaccuille",
    "wof:placetype":"locality"
},
  "geometry": {"coordinates":[-74.07538000000002,-15.63471],"type":"Point"}
}