{
  "type": "Feature",
  "properties": {
    "gn:admin1_code":"9",
    "gn:admin2_code":"906.0",
    "gn:admin3_code":"90601.0",
    "gn:asciiname":"Jesque",
    "gn:country_code":"PE",
    "gn:dem":2448,
    "gn:feature_class":"P",
    "gn:feature_code":"PPL",
    "gn:name":"Jesque",
    "gn:population":0,
    "gn:timezone":"America/Lima",
    "iso:country":"PE",
    "wof:name":"Jesque",
    "wof:placetype":"locality"
},
  "geometry": {"coordinates":[-75.36750000000001,-13.59917],"type":"Point"}
}