{
  "type": "Feature",
  "properties": {
    "gn:admin1_code":"8",
    "gn:admin2_code":"812.0",
    "gn:admin3_code":"81209.0",
    "gn:asciiname":"Chaupichaca",
    "gn:country_code":"PE",
    "gn:dem":1724,
    "gn:feature_class":"P",
    "gn:feature_code":"PPL",
    "gn:name":"Chaupichaca",
    "gn:population":0,
    "gn:timezone":"America/Lima",
    "iso:country":"PE",
    "wof:name":"Chaupichaca",
    "wof:placetype":"locality"
},
  "geometry": {"coordinates":[-70.89721999999998,-13.4775],"type":"Point"}
}