{
  "type": "Feature",
  "properties": {
    "gn:admin1_code":"15",
    "gn:admin2_code":"1507.0",
    "gn:admin3_code":"150703.0",
    "gn:asciiname":"Chauca",
    "gn:country_code":"PE",
    "gn:dem":3407,
    "gn:feature_class":"P",
    "gn:feature_code":"PPL",
    "gn:name":"Chauca",
    "gn:population":0,
    "gn:timezone":"America/Lima",
    "iso:country":"PE",
    "name:spa_x_preferred":[
        "Chauca"
    ],
    "wof:name":"Chauca",
    "wof:placetype":"locality"
},
  "geometry": {"coordinates":[-76.55535999999999,-11.80787],"type":"Point"}
}