{
  "type": "Feature",
  "properties": {
    "gn:admin1_code":"10.0",
    "gn:admin2_code":"1003.0",
    "gn:admin3_code":"100301.0",
    "gn:asciiname":"Chagahuain",
    "gn:country_code":"PE",
    "gn:dem":4005,
    "gn:feature_class":"P",
    "gn:feature_code":"PPL",
    "gn:name":"Chagahuain",
    "gn:population":0,
    "gn:timezone":"America/Lima",
    "iso:country":"PE",
    "wof:name":"Chagahuain",
    "wof:placetype":"locality"
},
  "geometry": {"coordinates":[-76.76688,-9.94076],"type":"Point"}
}