{
  "type": "Feature",
  "properties": {
    "gn:admin1_code":"2.0",
    "gn:admin2_code":"212.0",
    "gn:admin3_code":"21207.0",
    "gn:asciiname":"Huashca",
    "gn:country_code":"PE",
    "gn:dem":2526,
    "gn:feature_class":"P",
    "gn:feature_code":"PPLL",
    "gn:name":"Huashca",
    "gn:population":0,
    "gn:timezone":"America/Lima",
    "iso:country":"PE",
    "wof:name":"Huashca",
    "wof:placetype":"locality"
},
  "geometry": {"coordinates":[-77.80221999999998,-9.11806],"type":"Point"}
}