{
  "type": "Feature",
  "properties": {
    "gn:admin1_code":"25",
    "gn:admin2_code":"2501.0",
    "gn:admin3_code":"250104.0",
    "gn:asciiname":"Panuco",
    "gn:country_code":"PE",
    "gn:dem":169,
    "gn:feature_class":"P",
    "gn:feature_code":"PPL",
    "gn:name":"Panuco",
    "gn:population":0,
    "gn:timezone":"America/Lima",
    "iso:country":"PE",
    "name:ceb_x_preferred":[
        "Panuco"
    ],
    "name:swe_x_preferred":[
        "Panuco"
    ],
    "name:und_x_variant":[
        "Panucu",
        "Panuco"
    ],
    "wof:name":"Panuco",
    "wof:placetype":"locality"
},
  "geometry": {"coordinates":[-74.20444000000001,-8.80102],"type":"Point"}
}