{
  "type": "Feature",
  "properties": {
    "gn:admin1_code":"9.0",
    "gn:admin2_code":"905.0",
    "gn:admin3_code":"90504.0",
    "gn:asciiname":"Pillcon",
    "gn:country_code":"PE",
    "gn:dem":2919,
    "gn:feature_class":"P",
    "gn:feature_code":"PPL",
    "gn:name":"Pillcon",
    "gn:population":0,
    "gn:timezone":"America/Lima",
    "iso:country":"PE",
    "wof:name":"Pillcon",
    "wof:placetype":"locality"
},
  "geometry": {"coordinates":[-74.50709999999999,-12.72254],"type":"Point"}
}