{
  "type": "Feature",
  "properties": {
    "gn:admin1_code":"02",
    "gn:admin2_code":"205.0",
    "gn:admin3_code":"20504.0",
    "gn:asciiname":"Jecanca",
    "gn:country_code":"PE",
    "gn:dem":3858,
    "gn:feature_class":"P",
    "gn:feature_code":"PPL",
    "gn:name":"Jecanca",
    "gn:population":0,
    "gn:timezone":"America/Lima",
    "iso:country":"PE",
    "wof:name":"Jecanca",
    "wof:placetype":"locality"
},
  "geometry": {"coordinates":[-77.11898000000002,-10.07507],"type":"Point"}
}