{
  "type": "Feature",
  "properties": {
    "gn:admin1_code":"16",
    "gn:admin2_code":"1604.0",
    "gn:admin3_code":"160404.0",
    "gn:asciiname":"Siete de Junio",
    "gn:country_code":"PE",
    "gn:dem":81,
    "gn:feature_class":"P",
    "gn:feature_code":"PPL",
    "gn:name":"Siete de Junio",
    "gn:population":0,
    "gn:timezone":"America/Lima",
    "iso:country":"PE",
    "wof:name":"Siete de Junio",
    "wof:placetype":"locality"
},
  "geometry": {"coordinates":[-71.15306,-3.95056],"type":"Point"}
}