{
  "type": "Feature",
  "properties": {
    "gn:admin1_code":"12",
    "gn:admin2_code":"1206.0",
    "gn:asciiname":"Quimpitirique",
    "gn:cc2":"PE",
    "gn:country_code":"PE",
    "gn:dem":918,
    "gn:feature_class":"P",
    "gn:feature_code":"PPL",
    "gn:name":"Quimpitirique",
    "gn:population":0,
    "gn:timezone":"America/Lima",
    "iso:country":"PE",
    "name:und_x_variant":[
        "Kimpitirique",
        "Quimpitirique"
    ],
    "wof:name":"Quimpitirique",
    "wof:placetype":"locality"
},
  "geometry": {"coordinates":[-73.86667,-12.25],"type":"Point"}
}