{
  "type": "Feature",
  "properties": {
    "gn:admin1_code":"05",
    "gn:admin2_code":"507.0",
    "gn:admin3_code":"50702.0",
    "gn:asciiname":"Matuyoc",
    "gn:country_code":"PE",
    "gn:dem":3710,
    "gn:feature_class":"P",
    "gn:feature_code":"PPL",
    "gn:name":"Matuyoc",
    "gn:population":0,
    "gn:timezone":"America/Lima",
    "iso:country":"PE",
    "name:spa_x_preferred":[
        "Matuyoc"
    ],
    "wof:name":"Matuyoc",
    "wof:placetype":"locality"
},
  "geometry": {"coordinates":[-73.70111,-15.07195],"type":"Point"}
}