{
  "type": "Feature",
  "properties": {
    "gn:admin1_code":"4",
    "gn:admin2_code":"405.0",
    "gn:admin3_code":"40504.0",
    "gn:asciiname":"Lacaitira",
    "gn:country_code":"PE",
    "gn:dem":4461,
    "gn:feature_class":"P",
    "gn:feature_code":"PPL",
    "gn:name":"Lacaitira",
    "gn:population":0,
    "gn:timezone":"America/Lima",
    "iso:country":"PE",
    "wof:name":"Lacaitira",
    "wof:placetype":"locality"
},
  "geometry": {"coordinates":[-71.17944,-15.52306],"type":"Point"}
}