{
  "type": "Feature",
  "properties": {
    "gn:admin1_code":"22.0",
    "gn:admin2_code":"2203.0",
    "gn:admin3_code":"220301.0",
    "gn:asciiname":"San Juan de Miraflores",
    "gn:country_code":"PE",
    "gn:dem":383,
    "gn:feature_class":"P",
    "gn:feature_code":"PPL",
    "gn:name":"San Juan de Miraflores",
    "gn:population":0,
    "gn:timezone":"America/Lima",
    "iso:country":"PE",
    "name:spa_x_preferred":[
        "San Juan de Miraflores"
    ],
    "wof:name":"San Juan de Miraflores",
    "wof:placetype":"locality"
},
  "geometry": {"coordinates":[-76.71236,-6.64067],"type":"Point"}
}