{
  "type": "Feature",
  "properties": {
    "gn:admin1_code":"12.0",
    "gn:admin2_code":"1204.0",
    "gn:admin3_code":"120425.0",
    "gn:asciiname":"Ullusca",
    "gn:country_code":"PE",
    "gn:dem":3417,
    "gn:feature_class":"P",
    "gn:feature_code":"PPL",
    "gn:name":"Ullusca",
    "gn:population":0,
    "gn:timezone":"America/Lima",
    "iso:country":"PE",
    "wof:name":"Ullusca",
    "wof:placetype":"locality"
},
  "geometry": {"coordinates":[-75.50878,-11.82018],"type":"Point"}
}