{
  "type": "Feature",
  "properties": {
    "gn:admin1_code":"9.0",
    "gn:admin2_code":"905.0",
    "gn:asciiname":"Antapahua",
    "gn:country_code":"PE",
    "gn:dem":2233,
    "gn:feature_class":"P",
    "gn:feature_code":"PPL",
    "gn:name":"Antapahua",
    "gn:population":0,
    "gn:timezone":"America/Lima",
    "iso:country":"PE",
    "wof:name":"Antapahua",
    "wof:placetype":"locality"
},
  "geometry": {"coordinates":[-74.40125999999999,-12.80616],"type":"Point"}
}