{
  "type": "Feature",
  "properties": {
    "gn:admin1_code":"13",
    "gn:admin2_code":"1310.0",
    "gn:admin3_code":"131001.0",
    "gn:asciiname":"Ishcap",
    "gn:country_code":"PE",
    "gn:dem":3882,
    "gn:feature_class":"P",
    "gn:feature_code":"PPL",
    "gn:name":"Ishcap",
    "gn:population":0,
    "gn:timezone":"America/Lima",
    "iso:country":"PE",
    "wof:name":"Ishcap",
    "wof:placetype":"locality"
},
  "geometry": {"coordinates":[-78.23188,-8.34727],"type":"Point"}
}