{
  "type": "Feature",
  "properties": {
    "gn:admin1_code":"21",
    "gn:admin2_code":"2107.0",
    "gn:admin3_code":"210701.0",
    "gn:asciiname":"Ojecunca",
    "gn:country_code":"PE",
    "gn:dem":3866,
    "gn:feature_class":"P",
    "gn:feature_code":"PPL",
    "gn:name":"Ojecunca",
    "gn:population":0,
    "gn:timezone":"America/Lima",
    "iso:country":"PE",
    "name:zho_x_preferred":[
        "\u70cf\u57fa\u6606\u5361\u5c71"
    ],
    "wof:name":"Ojecunca",
    "wof:placetype":"locality"
},
  "geometry": {"coordinates":[-70.31468000000001,-15.27477],"type":"Point"}
}