{
  "type": "Feature",
  "properties": {
    "gn:admin1_code":"04",
    "gn:admin2_code":"406.0",
    "gn:admin3_code":"40603.0",
    "gn:asciiname":"Quello Quello",
    "gn:country_code":"PE",
    "gn:dem":4517,
    "gn:feature_class":"P",
    "gn:feature_code":"PPL",
    "gn:name":"Quello Quello",
    "gn:population":0,
    "gn:timezone":"America/Lima",
    "iso:country":"PE",
    "wof:name":"Quello Quello",
    "wof:placetype":"locality"
},
  "geometry": {"coordinates":[-72.48555999999998,-15.27175],"type":"Point"}
}