{
  "type": "Feature",
  "properties": {
    "gn:admin1_code":"17.0",
    "gn:admin2_code":"1703.0",
    "gn:asciiname":"Naranjal",
    "gn:country_code":"PE",
    "gn:dem":266,
    "gn:feature_class":"P",
    "gn:feature_code":"PPL",
    "gn:name":"Naranjal",
    "gn:population":0,
    "gn:timezone":"America/Lima",
    "iso:country":"PE",
    "name:ceb_x_preferred":[
        "Naranjal"
    ],
    "name:deu_x_preferred":[
        "Naranjal"
    ],
    "name:pol_x_preferred":[
        "Naranjal"
    ],
    "name:spa_x_preferred":[
        "Naranjal"
    ],
    "name:swe_x_preferred":[
        "Naranjal"
    ],
    "wof:name":"Naranjal",
    "wof:placetype":"locality"
},
  "geometry": {"coordinates":[-69.48234000000001,-11.40962],"type":"Point"}
}