{
  "type": "Feature",
  "properties": {
    "gn:admin1_code":"13.0",
    "gn:admin2_code":"1308.0",
    "gn:admin3_code":"130804.0",
    "gn:asciiname":"Minas",
    "gn:country_code":"PE",
    "gn:dem":3524,
    "gn:feature_class":"P",
    "gn:feature_code":"PPL",
    "gn:name":"Minas",
    "gn:population":0,
    "gn:timezone":"America/Lima",
    "iso:country":"PE",
    "name:ceb_x_preferred":[
        "Minas"
    ],
    "name:deu_x_preferred":[
        "Minas"
    ],
    "name:fra_x_preferred":[
        "Minas"
    ],
    "name:hye_x_preferred":[
        "\u0544\u056b\u0576\u0561\u057d"
    ],
    "name:nld_x_preferred":[
        "Minas"
    ],
    "name:por_x_preferred":[
        "Minas"
    ],
    "name:rus_x_preferred":[
        "\u041c\u0438\u043d\u0430\u0441"
    ],
    "name:sco_x_preferred":[
        "Minas"
    ],
    "name:srp_x_preferred":[
        "\u041c\u0438\u043d\u0430\u0441"
    ],
    "name:swe_x_preferred":[
        "Minas"
    ],
    "name:ukr_x_preferred":[
        "\u041c\u0456\u043d\u0430\u0441"
    ],
    "wof:name":"Minas",
    "wof:placetype":"locality"
},
  "geometry": {"coordinates":[-77.26861,-8.41333],"type":"Point"}
}