{
  "type": "Feature",
  "properties": {
    "gn:admin1_code":"02",
    "gn:admin2_code":"201.0",
    "gn:admin3_code":"20107.0",
    "gn:asciiname":"Cajamarquilla",
    "gn:country_code":"PE",
    "gn:dem":3242,
    "gn:feature_class":"P",
    "gn:feature_code":"PPLA3",
    "gn:name":"Cajamarquilla",
    "gn:population":0,
    "gn:timezone":"America/Lima",
    "iso:country":"PE",
    "wof:name":"Cajamarquilla",
    "wof:placetype":"locality"
},
  "geometry": {"coordinates":[-77.75,-9.63333],"type":"Point"}
}