{
  "type": "Feature",
  "properties": {
    "gn:admin1_code":"02",
    "gn:admin2_code":"201.0",
    "gn:admin3_code":"20107.0",
    "gn:asciiname":"Cajamarquilla",
    "gn:country_code":"PE",
    "gn:dem":3242,
    "gn:feature_class":"P",
    "gn:feature_code":"PPLA3",
    "gn:name":"Cajamarquilla",
    "gn:population":0,
    "gn:timezone":"America/Lima",
    "iso:country":"PE",
    "name:kat_x_preferred":[
        "\u10d9\u10d0\u10ee\u10d0\u10db\u10d0\u10e0\u10d9\u10d8\u10da\u10d8\u10d0"
    ],
    "name:mkd_x_preferred":[
        "\u041a\u0430\u0445\u0430\u043c\u0430\u0440\u043a\u0438\u043b\u0430"
    ],
    "name:pol_x_preferred":[
        "Cajamarquilla"
    ],
    "name:que_x_preferred":[
        "Kashamarkilla"
    ],
    "name:spa_x_preferred":[
        "Cajamarquilla"
    ],
    "wof:name":"Cajamarquilla",
    "wof:placetype":"locality"
},
  "geometry": {"coordinates":[-77.75,-9.63333],"type":"Point"}
}