{
  "type": "Feature",
  "properties": {
    "gn:admin1_code":"15",
    "gn:admin2_code":"1507.0",
    "gn:admin3_code":"150701.0",
    "gn:asciiname":"Huilipa",
    "gn:country_code":"PE",
    "gn:dem":3291,
    "gn:feature_class":"P",
    "gn:feature_code":"PPL",
    "gn:name":"Huilipa",
    "gn:population":0,
    "gn:timezone":"America/Lima",
    "iso:country":"PE",
    "wof:name":"Huilipa",
    "wof:placetype":"locality"
},
  "geometry": {"coordinates":[-76.35611,-11.865],"type":"Point"}
}