{
  "type": "Feature",
  "properties": {
    "gn:admin1_code":"15",
    "gn:admin2_code":"1510.0",
    "gn:admin3_code":"151019.0",
    "gn:asciiname":"Huanacallpi",
    "gn:country_code":"PE",
    "gn:dem":4162,
    "gn:feature_class":"P",
    "gn:feature_code":"PPL",
    "gn:name":"Huanacallpi",
    "gn:population":0,
    "gn:timezone":"America/Lima",
    "iso:country":"PE",
    "wof:name":"Huanacallpi",
    "wof:placetype":"locality"
},
  "geometry": {"coordinates":[-75.65567,-12.82851],"type":"Point"}
}