{
  "type": "Feature",
  "properties": {
    "gn:admin1_code":"13",
    "gn:admin2_code":"1308.0",
    "gn:admin3_code":"130809.0",
    "gn:asciiname":"Macamia",
    "gn:country_code":"PE",
    "gn:dem":2829,
    "gn:feature_class":"P",
    "gn:feature_code":"PPL",
    "gn:name":"Macamia",
    "gn:population":0,
    "gn:timezone":"America/Lima",
    "iso:country":"PE",
    "wof:name":"Macamia",
    "wof:placetype":"locality"
},
  "geometry": {"coordinates":[-77.60583000000003,-7.65889],"type":"Point"}
}