{
  "type": "Feature",
  "properties": {
    "gn:admin1_code":"06",
    "gn:admin2_code":"606.0",
    "gn:admin3_code":"60603.0",
    "gn:asciiname":"Chiple",
    "gn:country_code":"PE",
    "gn:dem":867,
    "gn:feature_class":"P",
    "gn:feature_code":"PPL",
    "gn:name":"Chiple",
    "gn:population":0,
    "gn:timezone":"America/Lima",
    "iso:country":"PE",
    "wof:name":"Chiple",
    "wof:placetype":"locality"
},
  "geometry": {"coordinates":[-78.83333,-5.93333],"type":"Point"}
}