{
  "type": "Feature",
  "properties": {
    "gn:admin1_code":"20",
    "gn:admin2_code":"2006.0",
    "gn:admin3_code":"200604.0",
    "gn:asciiname":"Tamarindo",
    "gn:country_code":"PE",
    "gn:dem":154,
    "gn:feature_class":"P",
    "gn:feature_code":"PPL",
    "gn:name":"Tamarindo",
    "gn:population":0,
    "gn:timezone":"America/Lima",
    "iso:country":"PE",
    "name:spa_x_preferred":[
        "Tamarindo"
    ],
    "wof:name":"Tamarindo",
    "wof:placetype":"locality"
},
  "geometry": {"coordinates":[-80.52429000000002,-4.54879],"type":"Point"}
}