{
  "type": "Feature",
  "properties": {
    "gn:admin1_code":"10",
    "gn:admin2_code":"1002.0",
    "gn:admin3_code":"100202.0",
    "gn:asciiname":"Shocosh Pampa",
    "gn:country_code":"PE",
    "gn:dem":3063,
    "gn:feature_class":"P",
    "gn:feature_code":"PPL",
    "gn:name":"Shocosh Pampa",
    "gn:population":0,
    "gn:timezone":"America/Lima",
    "iso:country":"PE",
    "wof:name":"Shocosh Pampa",
    "wof:placetype":"locality"
},
  "geometry": {"coordinates":[-76.38656999999998,-10.27963],"type":"Point"}
}