{
  "type": "Feature",
  "properties": {
    "gn:admin1_code":"19",
    "gn:admin2_code":"1902.0",
    "gn:admin3_code":"190201.0",
    "gn:asciiname":"Hacienda Andacancha",
    "gn:country_code":"PE",
    "gn:dem":3877,
    "gn:feature_class":"P",
    "gn:feature_code":"PPL",
    "gn:name":"Hacienda Andacancha",
    "gn:population":0,
    "gn:timezone":"America/Lima",
    "iso:country":"PE",
    "wof:name":"Hacienda Andacancha",
    "wof:placetype":"locality"
},
  "geometry": {"coordinates":[-76.52124000000001,-10.63079],"type":"Point"}
}