{
  "type": "Feature",
  "properties": {
    "gn:admin1_code":"2.0",
    "gn:admin2_code":"208.0",
    "gn:admin3_code":"20802.0",
    "gn:asciiname":"Yanacaca Chico",
    "gn:country_code":"PE",
    "gn:dem":816,
    "gn:feature_class":"P",
    "gn:feature_code":"PPL",
    "gn:name":"Yanacaca Chico",
    "gn:population":0,
    "gn:timezone":"America/Lima",
    "iso:country":"PE",
    "wof:name":"Yanacaca Chico",
    "wof:placetype":"locality"
},
  "geometry": {"coordinates":[-78.09688,-9.33839],"type":"Point"}
}