{
  "type": "Feature",
  "properties": {
    "gn:admin1_code":"5",
    "gn:admin2_code":"506.0",
    "gn:admin3_code":"50606.0",
    "gn:asciiname":"Huirapampa",
    "gn:country_code":"PE",
    "gn:dem":3591,
    "gn:feature_class":"P",
    "gn:feature_code":"PPL",
    "gn:name":"Huirapampa",
    "gn:population":0,
    "gn:timezone":"America/Lima",
    "iso:country":"PE",
    "wof:name":"Huirapampa",
    "wof:placetype":"locality"
},
  "geometry": {"coordinates":[-73.84917,-14.39667],"type":"Point"}
}