{
  "type": "Feature",
  "properties": {
    "gn:admin1_code":"4",
    "gn:admin2_code":"406.0",
    "gn:admin3_code":"40604.0",
    "gn:asciiname":"Huiruro",
    "gn:country_code":"PE",
    "gn:dem":4426,
    "gn:feature_class":"P",
    "gn:feature_code":"PPL",
    "gn:name":"Huiruro",
    "gn:population":0,
    "gn:timezone":"America/Lima",
    "iso:country":"PE",
    "wof:name":"Huiruro",
    "wof:placetype":"locality"
},
  "geometry": {"coordinates":[-72.84528,-15.55472],"type":"Point"}
}