{
  "type": "Feature",
  "properties": {
    "gn:admin1_code":"9.0",
    "gn:admin2_code":"901.0",
    "gn:admin3_code":"90101.0",
    "gn:asciiname":"Huaylacucho",
    "gn:country_code":"PE",
    "gn:dem":3706,
    "gn:feature_class":"P",
    "gn:feature_code":"PPL",
    "gn:name":"Huaylacucho",
    "gn:population":0,
    "gn:timezone":"America/Lima",
    "iso:country":"PE",
    "wof:name":"Huaylacucho",
    "wof:placetype":"locality"
},
  "geometry": {"coordinates":[-74.94081,-12.79185],"type":"Point"}
}