{
  "type": "Feature",
  "properties": {
    "gn:admin1_code":"22.0",
    "gn:admin2_code":"2202.0",
    "gn:admin3_code":"220205.0",
    "gn:asciiname":"Huancayo",
    "gn:country_code":"PE",
    "gn:dem":328,
    "gn:feature_class":"P",
    "gn:feature_code":"PPL",
    "gn:name":"Huancayo",
    "gn:population":0,
    "gn:timezone":"America/Lima",
    "iso:country":"PE",
    "name:spa_x_preferred":[
        "Huancayo"
    ],
    "wof:name":"Huancayo",
    "wof:placetype":"locality"
},
  "geometry": {"coordinates":[-76.57257,-6.79456],"type":"Point"}
}