{
  "type": "Feature",
  "properties": {
    "gn:admin1_code":"18",
    "gn:admin2_code":"1801.0",
    "gn:admin3_code":"180106.0",
    "gn:asciiname":"Tijinani",
    "gn:country_code":"PE",
    "gn:dem":4010,
    "gn:feature_class":"P",
    "gn:feature_code":"PPL",
    "gn:name":"Tiji\u00f1ani",
    "gn:population":0,
    "gn:timezone":"America/Lima",
    "iso:country":"PE",
    "wof:name":"Tijinani",
    "wof:placetype":"locality"
},
  "geometry": {"coordinates":[-70.66303000000001,-17.03037999999999],"type":"Point"}
}