{
  "type": "Feature",
  "properties": {
    "gn:admin1_code":"10.0",
    "gn:admin2_code":"1005.0",
    "gn:admin3_code":"100505.0",
    "gn:asciiname":"Pirish",
    "gn:country_code":"PE",
    "gn:dem":3411,
    "gn:feature_class":"P",
    "gn:feature_code":"PPL",
    "gn:name":"Pirish",
    "gn:population":0,
    "gn:timezone":"America/Lima",
    "iso:country":"PE",
    "wof:name":"Pirish",
    "wof:placetype":"locality"
},
  "geometry": {"coordinates":[-76.71543,-9.28105],"type":"Point"}
}