{
  "type": "Feature",
  "properties": {
    "gn:admin1_code":"9.0",
    "gn:admin2_code":"902.0",
    "gn:admin3_code":"90203.0",
    "gn:asciiname":"Anccomarca",
    "gn:country_code":"PE",
    "gn:dem":3557,
    "gn:feature_class":"P",
    "gn:feature_code":"PPL",
    "gn:name":"Anccomarca",
    "gn:population":0,
    "gn:timezone":"America/Lima",
    "iso:country":"PE",
    "wof:name":"Anccomarca",
    "wof:placetype":"locality"
},
  "geometry": {"coordinates":[-74.64844000000002,-12.83372],"type":"Point"}
}