{
  "type": "Feature",
  "properties": {
    "gn:admin1_code":"04",
    "gn:admin2_code":"401.0",
    "gn:admin3_code":"40118.0",
    "gn:asciiname":"Cornejo",
    "gn:country_code":"PE",
    "gn:dem":1006,
    "gn:feature_class":"P",
    "gn:feature_code":"PPL",
    "gn:name":"Cornejo",
    "gn:population":0,
    "gn:timezone":"America/Lima",
    "iso:country":"PE",
    "wof:name":"Cornejo",
    "wof:placetype":"locality"
},
  "geometry": {"coordinates":[-72.19197,-16.46056],"type":"Point"}
}