{
  "type": "Feature",
  "properties": {
    "gn:admin1_code":"03",
    "gn:admin2_code":"302.0",
    "gn:admin3_code":"30203.0",
    "gn:asciiname":"Huillcaihua",
    "gn:country_code":"PE",
    "gn:dem":3393,
    "gn:feature_class":"P",
    "gn:feature_code":"PPL",
    "gn:name":"Huillcaihua",
    "gn:population":0,
    "gn:timezone":"America/Lima",
    "iso:country":"PE",
    "wof:name":"Huillcaihua",
    "wof:placetype":"locality"
},
  "geometry": {"coordinates":[-73.62929,-13.90375],"type":"Point"}
}