{
  "type": "Feature",
  "properties": {
    "gn:admin1_code":"21",
    "gn:admin2_code":"2112",
    "gn:asciiname":"Huanacuri",
    "gn:country_code":"PE",
    "gn:dem":1110,
    "gn:feature_class":"P",
    "gn:feature_code":"PPL",
    "gn:name":"Huanacuri",
    "gn:population":0,
    "gn:timezone":"America/Lima",
    "iso:country":"PE",
    "name:spa_x_preferred":[
        "Huanacuri"
    ],
    "wof:name":"Huanacuri",
    "wof:placetype":"locality"
},
  "geometry": {"coordinates":[-69.72895,-13.8337],"type":"Point"}
}