{
  "type": "Feature",
  "properties": {
    "gn:admin1_code":"15",
    "gn:admin2_code":"1507.0",
    "gn:admin3_code":"150719.0",
    "gn:asciiname":"San Juan de Iris",
    "gn:country_code":"PE",
    "gn:dem":3247,
    "gn:feature_class":"P",
    "gn:feature_code":"PPL",
    "gn:name":"San Juan de Iris",
    "gn:population":0,
    "gn:timezone":"America/Lima",
    "iso:country":"PE",
    "name:spa_x_preferred":[
        "San Juan de Iris"
    ],
    "wof:name":"San Juan de Iris",
    "wof:placetype":"locality"
},
  "geometry": {"coordinates":[-76.52306999999998,-11.68039],"type":"Point"}
}