{
  "type": "Feature",
  "properties": {
    "gn:admin1_code":"09",
    "gn:admin2_code":"901.0",
    "gn:admin3_code":"90102.0",
    "gn:asciiname":"Jenchomachay",
    "gn:country_code":"PE",
    "gn:dem":4573,
    "gn:feature_class":"P",
    "gn:feature_code":"PPL",
    "gn:name":"Jenchomachay",
    "gn:population":0,
    "gn:timezone":"America/Lima",
    "iso:country":"PE",
    "wof:name":"Jenchomachay",
    "wof:placetype":"locality"
},
  "geometry": {"coordinates":[-75.36521999999999,-12.79417],"type":"Point"}
}