{
  "type": "Feature",
  "properties": {
    "gn:admin1_code":"12.0",
    "gn:admin2_code":"1208.0",
    "gn:admin3_code":"120803.0",
    "gn:asciiname":"Tincocancha",
    "gn:country_code":"PE",
    "gn:dem":4316,
    "gn:feature_class":"P",
    "gn:feature_code":"PPL",
    "gn:name":"Tincocancha",
    "gn:population":0,
    "gn:timezone":"America/Lima",
    "iso:country":"PE",
    "wof:name":"Tincocancha",
    "wof:placetype":"locality"
},
  "geometry": {"coordinates":[-75.97875000000001,-11.6548],"type":"Point"}
}