{
  "type": "Feature",
  "properties": {
    "gn:admin1_code":"12.0",
    "gn:admin2_code":"1204.0",
    "gn:admin3_code":"120417.0",
    "gn:asciiname":"Lanlaspata",
    "gn:country_code":"PE",
    "gn:dem":3720,
    "gn:feature_class":"P",
    "gn:feature_code":"PPL",
    "gn:name":"Lanlaspata",
    "gn:population":0,
    "gn:timezone":"America/Lima",
    "iso:country":"PE",
    "wof:name":"Lanlaspata",
    "wof:placetype":"locality"
},
  "geometry": {"coordinates":[-75.38233000000002,-11.79337],"type":"Point"}
}