{
  "type": "Feature",
  "properties": {
    "gn:admin1_code":"15",
    "gn:admin2_code":"1506.0",
    "gn:admin3_code":"150610.0",
    "gn:asciiname":"Pucpuca",
    "gn:country_code":"PE",
    "gn:dem":4231,
    "gn:feature_class":"P",
    "gn:feature_code":"PPL",
    "gn:name":"Pucpuca",
    "gn:population":0,
    "gn:timezone":"America/Lima",
    "iso:country":"PE",
    "wof:name":"Pucpuca",
    "wof:placetype":"locality"
},
  "geometry": {"coordinates":[-76.58471999999998,-11.08139],"type":"Point"}
}