{
  "type": "Feature",
  "properties": {
    "gn:admin1_code":"21",
    "gn:admin2_code":"2112.0",
    "gn:admin3_code":"211205.0",
    "gn:asciiname":"Uchuy Cutine",
    "gn:country_code":"PE",
    "gn:dem":3615,
    "gn:feature_class":"P",
    "gn:feature_code":"PPL",
    "gn:name":"Uchuy Cutine",
    "gn:population":0,
    "gn:timezone":"America/Lima",
    "iso:country":"PE",
    "wof:name":"Uchuy Cutine",
    "wof:placetype":"locality"
},
  "geometry": {"coordinates":[-69.63674,-14.10495],"type":"Point"}
}