{
  "type": "Feature",
  "properties": {
    "gn:admin1_code":"03",
    "gn:admin2_code":"306.0",
    "gn:admin3_code":"30605.0",
    "gn:asciiname":"Chilcabamba",
    "gn:country_code":"PE",
    "gn:dem":3130,
    "gn:feature_class":"P",
    "gn:feature_code":"PPL",
    "gn:name":"Chilcabamba",
    "gn:population":0,
    "gn:timezone":"America/Lima",
    "iso:country":"PE",
    "wof:name":"Chilcabamba",
    "wof:placetype":"locality"
},
  "geometry": {"coordinates":[-73.55277,-13.47399],"type":"Point"}
}