{
  "type": "Feature",
  "properties": {
    "gn:admin1_code":"9.0",
    "gn:admin2_code":"901.0",
    "gn:admin3_code":"90119.0",
    "gn:asciiname":"Sonobamba",
    "gn:country_code":"PE",
    "gn:dem":2917,
    "gn:feature_class":"P",
    "gn:feature_code":"PPL",
    "gn:name":"Sonobamba",
    "gn:population":0,
    "gn:timezone":"America/Lima",
    "iso:country":"PE",
    "wof:name":"Sonobamba",
    "wof:placetype":"locality"
},
  "geometry": {"coordinates":[-74.96354000000002,-12.51559],"type":"Point"}
}