{
  "type": "Feature",
  "properties": {
    "gn:country":"PE",
    "gn:fcode":"PPLA3",
    "gn:pop":3978,
    "iso:country":"PE",
    "name:dut_x_preferred":[
        "Layo"
    ],
    "name:eng_x_preferred":[
        "Layo"
    ],
    "name:que_x_preferred":[
        "Layu llaqta"
    ],
    "name:spa_x_preferred":[
        "Layo"
    ],
    "qs:name":"Layo",
    "qs:photos_9r":0,
    "qs:photos_sr":0,
    "qs:pop_sr":"4",
    "wd:wordcount":26,
    "wof:name":"Layo",
    "wof:placetype":"locality",
    "wof:population":3978
},
  "geometry": {"coordinates":[-71.155,-14.49361],"type":"Point"}
}