{
  "type": "Feature",
  "properties": {
    "gn:admin1_code":"14",
    "gn:admin2_code":"1403.0",
    "gn:admin3_code":"140301.0",
    "gn:asciiname":"La Rosada",
    "gn:country_code":"PE",
    "gn:dem":26,
    "gn:feature_class":"P",
    "gn:feature_code":"PPL",
    "gn:name":"La Rosada",
    "gn:population":0,
    "gn:timezone":"America/Lima",
    "iso:country":"PE",
    "name:und_x_variant":[
        "Hacienda La Rosada",
        "Casa Rosada",
        "Casa Rosada Hacienda",
        "La Rosada"
    ],
    "wof:name":"La Rosada",
    "wof:placetype":"locality"
},
  "geometry": {"coordinates":[-79.87739000000001,-6.63213],"type":"Point"}
}