{
  "type": "Feature",
  "properties": {
    "gn:admin1_code":"10.0",
    "gn:admin2_code":"1006.0",
    "gn:admin3_code":"100605.0",
    "gn:asciiname":"Bolaina",
    "gn:country_code":"PE",
    "gn:dem":738,
    "gn:feature_class":"P",
    "gn:feature_code":"PPL",
    "gn:name":"Bolaina",
    "gn:population":0,
    "gn:timezone":"America/Lima",
    "iso:country":"PE",
    "wof:name":"Bolaina",
    "wof:placetype":"locality"
},
  "geometry": {"coordinates":[-75.95289,-9.23997],"type":"Point"}
}