{
  "type": "Feature",
  "properties": {
    "gn:admin1_code":"08",
    "gn:admin2_code":"805.0",
    "gn:admin3_code":"80501.0",
    "gn:asciiname":"Palcollo",
    "gn:country_code":"PE",
    "gn:dem":4225,
    "gn:feature_class":"P",
    "gn:feature_code":"PPL",
    "gn:name":"Palcollo",
    "gn:population":0,
    "gn:timezone":"America/Lima",
    "iso:country":"PE",
    "wof:name":"Palcollo",
    "wof:placetype":"locality"
},
  "geometry": {"coordinates":[-71.53333000000001,-14.28333],"type":"Point"}
}