{
  "type": "Feature",
  "properties": {
    "gn:admin1_code":"4",
    "gn:admin2_code":"404.0",
    "gn:admin3_code":"40411.0",
    "gn:asciiname":"Llachas",
    "gn:country_code":"PE",
    "gn:dem":2059,
    "gn:feature_class":"P",
    "gn:feature_code":"PPL",
    "gn:name":"Llachas",
    "gn:population":0,
    "gn:timezone":"America/Lima",
    "iso:country":"PE",
    "wof:name":"Llachas",
    "wof:placetype":"locality"
},
  "geometry": {"coordinates":[-72.50949,-15.73775],"type":"Point"}
}