{
  "type": "Feature",
  "properties": {
    "gn:admin1_code":"17.0",
    "gn:admin2_code":"1703.0",
    "gn:asciiname":"Rio Blanco",
    "gn:country_code":"PE",
    "gn:dem":266,
    "gn:feature_class":"P",
    "gn:feature_code":"PPL",
    "gn:name":"R\u00edo Blanco",
    "gn:population":0,
    "gn:timezone":"America/Lima",
    "iso:country":"PE",
    "name:spa_x_preferred":[
        "R\u00edo Blanco"
    ],
    "wof:name":"Rio Blanco",
    "wof:placetype":"locality"
},
  "geometry": {"coordinates":[-69.79564000000001,-10.93506],"type":"Point"}
}