{
  "type": "Feature",
  "properties": {
    "gn:admin1_code":"20",
    "gn:admin2_code":"2003.0",
    "gn:admin3_code":"200304.0",
    "gn:asciiname":"Gongona",
    "gn:cc2":"PE",
    "gn:country_code":"PE",
    "gn:dem":2097,
    "gn:feature_class":"P",
    "gn:feature_code":"PPL",
    "gn:name":"Gongo\u00f1a",
    "gn:population":0,
    "gn:timezone":"America/Lima",
    "iso:country":"PE",
    "name:und_x_variant":[
        "Congo\u00f1a",
        "Hacienda Gongo\u00f1a",
        "Gongo\u00f1a"
    ],
    "wof:name":"Gongona",
    "wof:placetype":"locality"
},
  "geometry": {"coordinates":[-79.55028,-5.67889],"type":"Point"}
}