{
  "type": "Feature",
  "properties": {
    "gn:admin1_code":"05",
    "gn:admin2_code":"505.0",
    "gn:admin3_code":"50506.0",
    "gn:asciiname":"Huachinga",
    "gn:country_code":"PE",
    "gn:dem":3125,
    "gn:feature_class":"P",
    "gn:feature_code":"PPL",
    "gn:name":"Huachinga",
    "gn:population":0,
    "gn:timezone":"America/Lima",
    "iso:country":"PE",
    "wof:name":"Huachinga",
    "wof:placetype":"locality"
},
  "geometry": {"coordinates":[-73.91273000000002,-13.20459],"type":"Point"}
}