{
  "type": "Feature",
  "properties": {
    "iso:country":"PE",
    "name:bul_x_preferred":[
        "\u041f\u0438\u0441\u0430\u043a"
    ],
    "name:deu_x_preferred":[
        "Pisac"
    ],
    "name:epo_x_preferred":[
        "Pisak"
    ],
    "name:fra_x_preferred":[
        "P\u00edsac"
    ],
    "name:hrv_x_preferred":[
        "P\u00edsac"
    ],
    "name:ita_x_preferred":[
        "P\u00edsac"
    ],
    "name:kat_x_preferred":[
        "\u10de\u10d8\u10e1\u10d0\u10d9\u10d8"
    ],
    "name:mkd_x_preferred":[
        "\u041f\u0438\u0441\u0430\u043a"
    ],
    "name:nld_x_preferred":[
        "P\u00edsac"
    ],
    "name:spa_x_preferred":[
        "P\u00edsac"
    ],
    "qs:gn_country":"PE",
    "qs:gn_fcode":"PPL",
    "qs:gn_pop":0,
    "qs:name":"Pisac",
    "qs:name_adm0":"Per\u00fa",
    "qs:name_adm1":"Cusco",
    "qs:photos":1680,
    "qs:photos_1k":340,
    "qs:photos_9k":7,
    "qs:photos_9r":8,
    "qs:photos_all":1680,
    "qs:photos_sr":14,
    "qs:placetype":"Town",
    "qs:pop_sr":"0",
    "qs:woe_adm0":23424919,
    "wd:elevation":2972.0,
    "wd:wordcount":629,
    "wof:name":"Pisac",
    "wof:placetype":"locality"
},
  "geometry": {"coordinates":[-72.45972,-13.82222],"type":"Point"}
}