{
  "type": "Feature",
  "properties": {
    "gn:admin1_code":"04",
    "gn:admin2_code":"405.0",
    "gn:admin3_code":"40515.0",
    "gn:asciiname":"Moyopampa",
    "gn:country_code":"PE",
    "gn:dem":4323,
    "gn:feature_class":"P",
    "gn:feature_code":"PPL",
    "gn:name":"Moyopampa",
    "gn:population":0,
    "gn:timezone":"America/Lima",
    "iso:country":"PE",
    "wof:name":"Moyopampa",
    "wof:placetype":"locality"
},
  "geometry": {"coordinates":[-71.48605000000001,-15.45483],"type":"Point"}
}