{
  "type": "Feature",
  "properties": {
    "gn:admin1_code":"20",
    "gn:admin2_code":"2003.0",
    "gn:admin3_code":"200301.0",
    "gn:asciiname":"Huancacarpa Alto",
    "gn:country_code":"PE",
    "gn:dem":3241,
    "gn:feature_class":"P",
    "gn:feature_code":"PPL",
    "gn:name":"Huancacarpa Alto",
    "gn:population":0,
    "gn:timezone":"America/Lima",
    "iso:country":"PE",
    "wof:name":"Huancacarpa Alto",
    "wof:placetype":"locality"
},
  "geometry": {"coordinates":[-79.53628,-5.13565],"type":"Point"}
}