{
  "type": "Feature",
  "properties": {
    "gn:admin1_code":"15",
    "gn:admin2_code":"1505.0",
    "gn:admin3_code":"150509.0",
    "gn:asciiname":"Salitre",
    "gn:cc2":"PE",
    "gn:country_code":"PE",
    "gn:dem":4,
    "gn:feature_class":"P",
    "gn:feature_code":"PPL",
    "gn:name":"Salitre",
    "gn:population":0,
    "gn:timezone":"America/Lima",
    "iso:country":"PE",
    "name:ceb_x_preferred":[
        "Salitre"
    ],
    "name:por_x_preferred":[
        "Salitre"
    ],
    "name:srp_x_preferred":[
        "\u0421\u0430\u043b\u0438\u0442\u0440\u0435"
    ],
    "name:swe_x_preferred":[
        "Salitre"
    ],
    "name:und_x_variant":[
        "Hacienda Salitre",
        "Salitre Hacienda"
    ],
    "wof:name":"Salitre",
    "wof:placetype":"locality"
},
  "geometry": {"coordinates":[-76.65000000000001,-12.68333],"type":"Point"}
}