{
  "type": "Feature",
  "properties": {
    "gn:admin1_code":"20",
    "gn:admin2_code":"2006.0",
    "gn:admin3_code":"200605.0",
    "gn:asciiname":"Tierra Blanca",
    "gn:country_code":"PE",
    "gn:dem":259,
    "gn:feature_class":"P",
    "gn:feature_code":"PPLL",
    "gn:name":"Tierra Blanca",
    "gn:population":0,
    "gn:timezone":"America/Lima",
    "iso:country":"PE",
    "name:ceb_x_preferred":[
        "Tierra Blanca"
    ],
    "name:deu_x_preferred":[
        "Tierra Blanca"
    ],
    "name:ita_x_preferred":[
        "Tierra Blanca"
    ],
    "name:pol_x_preferred":[
        "Tierra Blanca"
    ],
    "name:por_x_preferred":[
        "Tierra Blanca"
    ],
    "name:sco_x_preferred":[
        "Tierra Blanca"
    ],
    "name:spa_x_preferred":[
        "Tierra Blanca"
    ],
    "name:swe_x_preferred":[
        "Tierra Blanca"
    ],
    "wof:name":"Tierra Blanca",
    "wof:placetype":"locality"
},
  "geometry": {"coordinates":[-80.73889,-4.60017],"type":"Point"}
}