{
  "type": "Feature",
  "properties": {
    "gn:admin1_code":"12.0",
    "gn:admin2_code":"1202.0",
    "gn:admin3_code":"120209.0",
    "gn:asciiname":"Tuctuca",
    "gn:country_code":"PE",
    "gn:dem":2110,
    "gn:feature_class":"P",
    "gn:feature_code":"PPL",
    "gn:name":"Tuctuca",
    "gn:population":0,
    "gn:timezone":"America/Lima",
    "iso:country":"PE",
    "wof:name":"Tuctuca",
    "wof:placetype":"locality"
},
  "geometry": {"coordinates":[-75.13020999999998,-11.52839],"type":"Point"}
}