{
  "type": "Feature",
  "properties": {
    "gn:admin1_code":"9.0",
    "gn:admin2_code":"903.0",
    "gn:admin3_code":"90307.0",
    "gn:asciiname":"Yahuarcocha",
    "gn:country_code":"PE",
    "gn:dem":4054,
    "gn:feature_class":"P",
    "gn:feature_code":"PPL",
    "gn:name":"Yahuarcocha",
    "gn:population":0,
    "gn:timezone":"America/Lima",
    "iso:country":"PE",
    "wof:name":"Yahuarcocha",
    "wof:placetype":"locality"
},
  "geometry": {"coordinates":[-74.61667,-12.98194],"type":"Point"}
}