{
  "type": "Feature",
  "properties": {
    "gn:admin1_code":"10.0",
    "gn:admin2_code":"1003.0",
    "gn:admin3_code":"100313.0",
    "gn:asciiname":"Tejahuay",
    "gn:country_code":"PE",
    "gn:dem":3255,
    "gn:feature_class":"P",
    "gn:feature_code":"PPL",
    "gn:name":"Tejahuay",
    "gn:population":0,
    "gn:timezone":"America/Lima",
    "iso:country":"PE",
    "wof:name":"Tejahuay",
    "wof:placetype":"locality"
},
  "geometry": {"coordinates":[-76.7461,-9.6922],"type":"Point"}
}