{
  "type": "Feature",
  "properties": {
    "gn:admin1_code":"06",
    "gn:admin2_code":"608.0",
    "gn:admin3_code":"60801.0",
    "gn:asciiname":"Virginia",
    "gn:country_code":"PE",
    "gn:dem":1930,
    "gn:feature_class":"P",
    "gn:feature_code":"PPL",
    "gn:name":"Virginia",
    "gn:population":0,
    "gn:timezone":"America/Lima",
    "iso:country":"PE",
    "wof:name":"Virginia",
    "wof:placetype":"locality"
},
  "geometry": {"coordinates":[-78.90585,-5.73479],"type":"Point"}
}