{
  "type": "Feature",
  "properties": {
    "gn:admin1_code":"4",
    "gn:admin2_code":"403.0",
    "gn:admin3_code":"40308.0",
    "gn:asciiname":"Cali",
    "gn:country_code":"PE",
    "gn:dem":203,
    "gn:feature_class":"P",
    "gn:feature_code":"PPL",
    "gn:name":"Cali",
    "gn:population":0,
    "gn:timezone":"America/Lima",
    "iso:country":"PE",
    "name:spa_x_preferred":[
        "Cali"
    ],
    "wof:name":"Cali",
    "wof:placetype":"locality"
},
  "geometry": {"coordinates":[-74.1866,-15.86205],"type":"Point"}
}