{
  "type": "Feature",
  "properties": {
    "gn:admin1_code":"08",
    "gn:admin2_code":"807.0",
    "gn:admin3_code":"80701.0",
    "gn:asciiname":"Santo Tomas",
    "gn:country_code":"PE",
    "gn:dem":3663,
    "gn:feature_class":"P",
    "gn:feature_code":"PPL",
    "gn:name":"Santo Tom\u00e1s",
    "gn:population":0,
    "gn:timezone":"America/Lima",
    "iso:country":"PE",
    "name:aym_x_preferred":[
        "Santu Tumas"
    ],
    "name:deu_x_preferred":[
        "Santo Tom\u00e1s"
    ],
    "name:fra_x_preferred":[
        "Santo Tom\u00e1s"
    ],
    "name:pol_x_preferred":[
        "Santo Tom\u00e1s"
    ],
    "name:por_x_preferred":[
        "Santo Tom\u00e1s"
    ],
    "name:que_x_preferred":[
        "Santu Tumas"
    ],
    "name:rus_x_preferred":[
        "\u0421\u0430\u043d\u0442\u043e-\u0422\u043e\u043c\u0430\u0441"
    ],
    "name:spa_x_preferred":[
        "Santo Tom\u00e1s"
    ],
    "name:und_x_variant":[
        "Santo Tom\u00e1s"
    ],
    "name:war_x_preferred":[
        "Santo Tom\u00e1s"
    ],
    "name:zho_x_preferred":[
        "\u8056\u6258\u99ac\u65af"
    ],
    "wof:name":"Santo Tomas",
    "wof:placetype":"locality"
},
  "geometry": {"coordinates":[-72.08193,-14.45053],"type":"Point"}
}