{
  "type": "Feature",
  "properties": {
    "gn:admin1_code":"05",
    "gn:admin2_code":"508.0",
    "gn:admin3_code":"50805.0",
    "gn:asciiname":"Sequello",
    "gn:country_code":"PE",
    "gn:dem":2365,
    "gn:feature_class":"P",
    "gn:feature_code":"PPL",
    "gn:name":"Sequello",
    "gn:population":0,
    "gn:timezone":"America/Lima",
    "iso:country":"PE",
    "wof:name":"Sequello",
    "wof:placetype":"locality"
},
  "geometry": {"coordinates":[-73.33124000000002,-15.10291],"type":"Point"}
}