{
  "type": "Feature",
  "properties": {
    "gn:admin1_code":"10.0",
    "gn:admin2_code":"1010.0",
    "gn:admin3_code":"101004.0",
    "gn:asciiname":"Pucacocha",
    "gn:country_code":"PE",
    "gn:dem":4094,
    "gn:feature_class":"P",
    "gn:feature_code":"PPL",
    "gn:name":"Pucacocha",
    "gn:population":0,
    "gn:timezone":"America/Lima",
    "iso:country":"PE",
    "wof:name":"Pucacocha",
    "wof:placetype":"locality"
},
  "geometry": {"coordinates":[-76.85778000000001,-10.16111],"type":"Point"}
}