{
  "type": "Feature",
  "properties": {
    "gn:admin1_code":"21",
    "gn:admin2_code":"2105.0",
    "gn:admin3_code":"210503.0",
    "gn:asciiname":"Quispemaquera",
    "gn:country_code":"PE",
    "gn:dem":3822,
    "gn:feature_class":"P",
    "gn:feature_code":"PPL",
    "gn:name":"Quispemaquera",
    "gn:population":0,
    "gn:timezone":"America/Lima",
    "iso:country":"PE",
    "wof:name":"Quispemaquera",
    "wof:placetype":"locality"
},
  "geometry": {"coordinates":[-69.49566,-16.10682000000001],"type":"Point"}
}