{
  "type": "Feature",
  "properties": {
    "gn:admin1_code":"01",
    "gn:admin2_code":"107.0",
    "gn:admin3_code":"10703.0",
    "gn:asciiname":"Polocate",
    "gn:country_code":"PE",
    "gn:dem":1412,
    "gn:feature_class":"P",
    "gn:feature_code":"PPL",
    "gn:name":"Polocate",
    "gn:population":0,
    "gn:timezone":"America/Lima",
    "iso:country":"PE",
    "wof:name":"Polocate",
    "wof:placetype":"locality"
},
  "geometry": {"coordinates":[-78.59685999999998,-5.93369],"type":"Point"}
}