{
  "type": "Feature",
  "properties": {
    "gn:admin1_code":"04",
    "gn:admin2_code":"402.0",
    "gn:admin3_code":"40207.0",
    "gn:asciiname":"Pampa Blanca",
    "gn:country_code":"PE",
    "gn:dem":93,
    "gn:feature_class":"P",
    "gn:feature_code":"PPL",
    "gn:name":"Pampa Blanca",
    "gn:population":0,
    "gn:timezone":"America/Lima",
    "iso:country":"PE",
    "name:und_x_variant":[
        "Pampa Blanca Hacienda",
        "Pampa Blanca"
    ],
    "wof:name":"Pampa Blanca",
    "wof:placetype":"locality"
},
  "geometry": {"coordinates":[-72.34021,-16.61325],"type":"Point"}
}