{
  "type": "Feature",
  "properties": {
    "gn:admin1_code":"21.0",
    "gn:admin2_code":"2112.0",
    "gn:asciiname":"Ticatica",
    "gn:country_code":"PE",
    "gn:dem":3194,
    "gn:feature_class":"P",
    "gn:feature_code":"PPL",
    "gn:name":"Ticatica",
    "gn:population":0,
    "gn:timezone":"America/Lima",
    "iso:country":"PE",
    "name:spa_x_preferred":[
        "Ticatica"
    ],
    "wof:name":"Ticatica",
    "wof:placetype":"locality"
},
  "geometry": {"coordinates":[-69.34069000000001,-14.46049],"type":"Point"}
}