{
  "type": "Feature",
  "properties": {
    "gn:admin1_code":"4",
    "gn:admin2_code":"406.0",
    "gn:admin3_code":"40604.0",
    "gn:asciiname":"Chanchallay",
    "gn:country_code":"PE",
    "gn:dem":1737,
    "gn:feature_class":"P",
    "gn:feature_code":"PPL",
    "gn:name":"Chanchallay",
    "gn:population":0,
    "gn:timezone":"America/Lima",
    "iso:country":"PE",
    "wof:name":"Chanchallay",
    "wof:placetype":"locality"
},
  "geometry": {"coordinates":[-72.9712,-15.55954],"type":"Point"}
}