{
  "type": "Feature",
  "properties": {
    "gn:admin1_code":"15",
    "gn:admin2_code":"1510.0",
    "gn:admin3_code":"151015.0",
    "gn:asciiname":"Chocalla",
    "gn:country_code":"PE",
    "gn:dem":3174,
    "gn:feature_class":"P",
    "gn:feature_code":"PPL",
    "gn:name":"Chocalla",
    "gn:population":0,
    "gn:timezone":"America/Lima",
    "iso:country":"PE",
    "wof:name":"Chocalla",
    "wof:placetype":"locality"
},
  "geometry": {"coordinates":[-75.84141,-12.93529],"type":"Point"}
}