{
  "type": "Feature",
  "properties": {
    "gn:admin1_code":"13",
    "gn:admin2_code":"1304.0",
    "gn:admin3_code":"130403.0",
    "gn:asciiname":"Iglesia Vieja",
    "gn:country_code":"PE",
    "gn:dem":32,
    "gn:feature_class":"P",
    "gn:feature_code":"PPL",
    "gn:name":"Iglesia Vieja",
    "gn:population":0,
    "gn:timezone":"America/Lima",
    "iso:country":"PE",
    "wof:name":"Iglesia Vieja",
    "wof:placetype":"locality"
},
  "geometry": {"coordinates":[-79.59999999999999,-7.11667],"type":"Point"}
}