{
  "type": "Feature",
  "properties": {
    "gn:admin1_code":"14",
    "gn:admin2_code":"1402.0",
    "gn:admin3_code":"140204.0",
    "gn:asciiname":"Rompon",
    "gn:country_code":"PE",
    "gn:dem":60,
    "gn:feature_class":"P",
    "gn:feature_code":"PPL",
    "gn:name":"Romp\u00f3n",
    "gn:population":0,
    "gn:timezone":"America/Lima",
    "iso:country":"PE",
    "name:bug_x_preferred":[
        "Rompon"
    ],
    "name:cat_x_preferred":[
        "Rompon"
    ],
    "name:ceb_x_preferred":[
        "Rompon"
    ],
    "name:deu_x_preferred":[
        "Rompon"
    ],
    "name:eus_x_preferred":[
        "Rompon"
    ],
    "name:fra_x_preferred":[
        "Rompon"
    ],
    "name:hun_x_preferred":[
        "Rompon"
    ],
    "name:hye_x_preferred":[
        "\u054c\u0578\u0574\u057a\u0578\u0576"
    ],
    "name:ita_x_preferred":[
        "Rompon"
    ],
    "name:lat_x_preferred":[
        "Rompon"
    ],
    "name:lmo_x_preferred":[
        "Rompon"
    ],
    "name:mlg_x_preferred":[
        "Rompon"
    ],
    "name:msa_x_preferred":[
        "Rompon"
    ],
    "name:nld_x_preferred":[
        "Rompon"
    ],
    "name:oci_x_preferred":[
        "Rompon"
    ],
    "name:pms_x_preferred":[
        "Rompon"
    ],
    "name:pol_x_preferred":[
        "Rompon"
    ],
    "name:por_x_preferred":[
        "Rompon"
    ],
    "name:ron_x_preferred":[
        "Rompon"
    ],
    "name:rus_x_preferred":[
        "\u0420\u043e\u043c\u043f\u043e\u043d"
    ],
    "name:slk_x_preferred":[
        "Rompon"
    ],
    "name:spa_x_preferred":[
        "Rompon"
    ],
    "name:sqi_x_preferred":[
        "Rompon"
    ],
    "name:swe_x_preferred":[
        "Rompon"
    ],
    "name:ukr_x_preferred":[
        "\u0420\u043e\u043c\u043f\u043e\u043d"
    ],
    "name:uzb_x_preferred":[
        "Rompon"
    ],
    "name:vie_x_preferred":[
        "Rompon"
    ],
    "name:vol_x_preferred":[
        "Rompon"
    ],
    "name:war_x_preferred":[
        "Rompon"
    ],
    "name:zho_x_preferred":[
        "\u9f99\u84ec"
    ],
    "wof:name":"Rompon",
    "wof:placetype":"locality"
},
  "geometry": {"coordinates":[-79.75,-6.63333],"type":"Point"}
}