{
  "type": "Feature",
  "properties": {
    "gn:admin1_code":"14",
    "gn:admin2_code":"1402.0",
    "gn:admin3_code":"140204.0",
    "gn:asciiname":"Rompon",
    "gn:country_code":"PE",
    "gn:dem":60,
    "gn:feature_class":"P",
    "gn:feature_code":"PPL",
    "gn:name":"Romp\u00f3n",
    "gn:population":0,
    "gn:timezone":"America/Lima",
    "iso:country":"PE",
    "wof:name":"Rompon",
    "wof:placetype":"locality"
},
  "geometry": {"coordinates":[-79.75,-6.63333],"type":"Point"}
}