{
  "type": "Feature",
  "properties": {
    "gn:country":"PE",
    "gn:fcode":"PPLA3",
    "gn:population":5998,
    "iso:country":"PE",
    "name:ceb_x_preferred":[
        "Lluta"
    ],
    "name:eng_x_preferred":[
        "Lluta District"
    ],
    "name:kat_x_preferred":[
        "\u10da\u10e3\u10e2\u10d8\u10e1 \u10e0\u10d0\u10d8\u10dd\u10dc\u10d8"
    ],
    "name:nld_x_preferred":[
        "Lluta District"
    ],
    "name:por_x_preferred":[
        "Lluta"
    ],
    "name:que_x_preferred":[
        "Lluta distritu"
    ],
    "name:zho_x_preferred":[
        "\u5c24\u5854\u5340"
    ],
    "qs:name":"Lluta",
    "qs:photos_9r":0,
    "qs:photos_sr":0,
    "qs:pop_sr":"5",
    "wd:wordcount":28,
    "wof:name":"Lluta",
    "wof:placetype":"locality",
    "wof:population":5998
},
  "geometry": {"coordinates":[-72.01416999999999,-16.01472],"type":"Point"}
}