{
  "type": "Feature",
  "properties": {
    "gn:country":"PE",
    "gn:fcode":"PPLA3",
    "gn:pop":5998,
    "iso:country":"PE",
    "qs:name":"Lluta",
    "qs:photos_9r":0,
    "qs:photos_sr":0,
    "qs:pop_sr":"5",
    "wd:wordcount":28,
    "wof:name":"Lluta",
    "wof:placetype":"locality",
    "wof:population":5998
},
  "geometry": {"coordinates":[-72.01416999999999,-16.01472],"type":"Point"}
}