{
  "type": "Feature",
  "properties": {
    "gn:country":"PE",
    "gn:fcode":"PPL",
    "gn:population":5495,
    "iso:country":"PE",
    "name:arg_x_preferred":[
        "Ram\u00f3n Castilla"
    ],
    "name:ast_x_preferred":[
        "Ram\u00f3n Castilla"
    ],
    "name:aym_x_preferred":[
        "Ram\u00f3n Castilla"
    ],
    "name:cat_x_preferred":[
        "Ram\u00f3n Castilla"
    ],
    "name:ces_x_preferred":[
        "Ram\u00f3n Castilla"
    ],
    "name:dan_x_preferred":[
        "Ram\u00f3n Castilla"
    ],
    "name:deu_x_preferred":[
        "Ram\u00f3n Castilla"
    ],
    "name:eng_x_preferred":[
        "Ram\u00f3n Castilla"
    ],
    "name:fra_x_preferred":[
        "Ram\u00f3n Castilla"
    ],
    "name:hun_x_preferred":[
        "Ram\u00f3n Castilla"
    ],
    "name:ido_x_preferred":[
        "Ram\u00f3n Castilla"
    ],
    "name:ita_x_preferred":[
        "Ram\u00f3n Castilla"
    ],
    "name:jpn_x_preferred":[
        "\u30e9\u30e2\u30f3\u30fb\u30ab\u30b9\u30c6\u30a3\u30fc\u30ea\u30e3"
    ],
    "name:kat_x_preferred":[
        "\u10e0\u10d0\u10db\u10dd\u10dc \u10d9\u10d0\u10e1\u10e2\u10d8\u10da\u10d8\u10d0"
    ],
    "name:lat_x_preferred":[
        "Raimundus Castilla"
    ],
    "name:nah_x_preferred":[
        "Ram\u00f3n Castilla"
    ],
    "name:nld_x_preferred":[
        "Ram\u00f3n Castilla"
    ],
    "name:nob_x_preferred":[
        "Ram\u00f3n Castilla"
    ],
    "name:pol_x_preferred":[
        "Ram\u00f3n Castilla"
    ],
    "name:por_x_preferred":[
        "Ram\u00f3n Castilla"
    ],
    "name:que_x_preferred":[
        "Ram\u00f3n Castilla"
    ],
    "name:ron_x_preferred":[
        "Ram\u00f3n Castilla"
    ],
    "name:rus_x_preferred":[
        "\u0420\u0430\u043c\u043e\u043d \u041a\u0430\u0441\u0442\u0438\u043b\u044c\u044f"
    ],
    "name:slv_x_preferred":[
        "Ram\u00f3n Castilla"
    ],
    "name:spa_x_preferred":[
        "Ram\u00f3n Castilla"
    ],
    "name:swe_x_preferred":[
        "Ram\u00f3n Castilla"
    ],
    "name:yor_x_preferred":[
        "Ram\u00f3n Castilla"
    ],
    "qs:name":"Ram\u00f3n Castilla",
    "qs:photos_9r":0,
    "qs:photos_sr":0,
    "qs:pop_sr":"5",
    "wd:wordcount":1025,
    "wof:name":"Ram\u00f3n Castilla",
    "wof:placetype":"locality",
    "wof:population":5495
},
  "geometry": {"coordinates":[-69.95714,-4.26066],"type":"Point"}
}