{
  "type": "Feature",
  "properties": {
    "gn:country":"PE",
    "gn:fcode":"PPL",
    "gn:pop":5495,
    "iso:country":"PE",
    "qs:name":"Ram\u00f3n Castilla",
    "qs:photos_9r":0,
    "qs:photos_sr":0,
    "qs:pop_sr":"5",
    "wd:wordcount":1025,
    "wof:name":"Ram\u00f3n Castilla",
    "wof:placetype":"locality",
    "wof:population":5495
},
  "geometry": {"coordinates":[-69.95714,-4.26066],"type":"Point"}
}