{
  "type": "Feature",
  "properties": {
    "gn:admin1_code":"14",
    "gn:admin2_code":"1401.0",
    "gn:admin3_code":"140107.0",
    "gn:asciiname":"Hacienda Ucupe",
    "gn:country_code":"PE",
    "gn:dem":38,
    "gn:feature_class":"P",
    "gn:feature_code":"PPL",
    "gn:name":"Hacienda Ucupe",
    "gn:population":0,
    "gn:timezone":"America/Lima",
    "iso:country":"PE",
    "name:spa_x_preferred":[
        "Hacienda Ucupe"
    ],
    "name:spa_x_variant":[
        "Ucupe"
    ],
    "wof:name":"Hacienda Ucupe",
    "wof:placetype":"locality"
},
  "geometry": {"coordinates":[-79.62475000000001,-6.98111],"type":"Point"}
}