{
  "type": "Feature",
  "properties": {
    "gn:admin1_code":"15",
    "gn:admin2_code":"1504.0",
    "gn:admin3_code":"150407.0",
    "gn:asciiname":"Paypay",
    "gn:country_code":"PE",
    "gn:dem":907,
    "gn:feature_class":"P",
    "gn:feature_code":"PPL",
    "gn:name":"Paypay",
    "gn:population":0,
    "gn:timezone":"America/Lima",
    "iso:country":"PE",
    "name:spa_x_preferred":[
        "Paypay"
    ],
    "name:spa_x_variant":[
        "Pay Pay"
    ],
    "wof:name":"Paypay",
    "wof:placetype":"locality"
},
  "geometry": {"coordinates":[-76.8557,-11.69302],"type":"Point"}
}