{
  "type": "Feature",
  "properties": {
    "gn:admin1_code":"10",
    "gn:admin2_code":"1009.0",
    "gn:admin3_code":"100902.0",
    "gn:asciiname":"Codo del Pozuzo",
    "gn:country_code":"PE",
    "gn:dem":366,
    "gn:feature_class":"P",
    "gn:feature_code":"PPL",
    "gn:name":"Codo del Pozuzo",
    "gn:population":0,
    "gn:timezone":"America/Lima",
    "iso:country":"PE",
    "wof:name":"Codo del Pozuzo",
    "wof:placetype":"locality"
},
  "geometry": {"coordinates":[-75.45050000000001,-9.67478],"type":"Point"}
}