{
  "type": "Feature",
  "properties": {
    "gn:admin1_code":"23",
    "gn:admin2_code":"2304.0",
    "gn:admin3_code":"230401.0",
    "gn:asciiname":"Corocorane",
    "gn:country_code":"PE",
    "gn:dem":4375,
    "gn:feature_class":"P",
    "gn:feature_code":"PPL",
    "gn:name":"Corocorane",
    "gn:population":0,
    "gn:timezone":"America/Lima",
    "iso:country":"PE",
    "name:und_x_variant":[
        "Coracorane",
        "Corocorane"
    ],
    "wof:name":"Corocorane",
    "wof:placetype":"locality"
},
  "geometry": {"coordinates":[-69.74221999999999,-17.38013],"type":"Point"}
}