{
  "type": "Feature",
  "properties": {
    "gn:admin1_code":"02",
    "gn:admin2_code":"205.0",
    "gn:asciiname":"Nanis",
    "gn:country_code":"PE",
    "gn:dem":3239,
    "gn:feature_class":"P",
    "gn:feature_code":"PPL",
    "gn:name":"Nanis",
    "gn:population":0,
    "gn:timezone":"America/Lima",
    "iso:country":"PE",
    "wof:name":"Nanis",
    "wof:placetype":"locality"
},
  "geometry": {"coordinates":[-77.12976999999999,-10.37909],"type":"Point"}
}