{
  "type": "Feature",
  "properties": {
    "gn:admin1_code":"21",
    "gn:admin2_code":"2101.0",
    "gn:admin3_code":"210111.0",
    "gn:asciiname":"Cavala",
    "gn:cc2":"PE",
    "gn:country_code":"PE",
    "gn:dem":3944,
    "gn:feature_class":"P",
    "gn:feature_code":"PPL",
    "gn:name":"Cavala",
    "gn:population":0,
    "gn:timezone":"America/Lima",
    "iso:country":"PE",
    "name:und_x_variant":[
        "Hacienda Taipisipa",
        "Taypisipa",
        "Taipisipa Hacienda",
        "Cavala"
    ],
    "wof:name":"Cavala",
    "wof:placetype":"locality"
},
  "geometry": {"coordinates":[-70.01666999999999,-16.16667],"type":"Point"}
}