{
  "type": "Feature",
  "properties": {
    "gn:admin1_code":"04",
    "gn:admin2_code":"408.0",
    "gn:admin3_code":"40811.0",
    "gn:asciiname":"Pampa Cocha",
    "gn:country_code":"PE",
    "gn:dem":2647,
    "gn:feature_class":"P",
    "gn:feature_code":"PPL",
    "gn:name":"Pampa Cocha",
    "gn:population":0,
    "gn:timezone":"America/Lima",
    "iso:country":"PE",
    "wof:name":"Pampa Cocha",
    "wof:placetype":"locality"
},
  "geometry": {"coordinates":[-72.93779000000001,-15.25474],"type":"Point"}
}