{
  "type": "Feature",
  "properties": {
    "gn:admin1_code":"12",
    "gn:admin2_code":"1207.0",
    "gn:admin3_code":"120706.0",
    "gn:asciiname":"Nahuin",
    "gn:country_code":"PE",
    "gn:dem":3228,
    "gn:feature_class":"P",
    "gn:feature_code":"PPL",
    "gn:name":"\u00d1ahu\u00edn",
    "gn:population":0,
    "gn:timezone":"America/Lima",
    "iso:country":"PE",
    "wof:name":"Nahuin",
    "wof:placetype":"locality"
},
  "geometry": {"coordinates":[-75.52332,-11.28112],"type":"Point"}
}