{
  "type": "Feature",
  "properties": {
    "gn:admin1_code":"1.0",
    "gn:admin2_code":"101.0",
    "gn:admin3_code":"10117.0",
    "gn:asciiname":"Lanche",
    "gn:country_code":"PE",
    "gn:dem":3082,
    "gn:feature_class":"P",
    "gn:feature_code":"PPLL",
    "gn:name":"Lanche",
    "gn:population":0,
    "gn:timezone":"America/Lima",
    "iso:country":"PE",
    "wof:name":"Lanche",
    "wof:placetype":"locality"
},
  "geometry": {"coordinates":[-77.69143000000003,-6.06325],"type":"Point"}
}