{
  "type": "Feature",
  "properties": {
    "gn:admin1_code":"18",
    "gn:admin2_code":"1802.0",
    "gn:admin3_code":"180202.0",
    "gn:asciiname":"Potenhueco",
    "gn:country_code":"PE",
    "gn:dem":4267,
    "gn:feature_class":"P",
    "gn:feature_code":"PPL",
    "gn:name":"Potenhueco",
    "gn:population":0,
    "gn:timezone":"America/Lima",
    "iso:country":"PE",
    "wof:name":"Potenhueco",
    "wof:placetype":"locality"
},
  "geometry": {"coordinates":[-70.5102,-16.5408],"type":"Point"}
}