{
  "type": "Feature",
  "properties": {
    "gn:admin1_code":"13",
    "gn:admin2_code":"1306.0",
    "gn:admin3_code":"130601.0",
    "gn:asciiname":"Hacienda Llaugueda",
    "gn:country_code":"PE",
    "gn:dem":2222,
    "gn:feature_class":"P",
    "gn:feature_code":"PPL",
    "gn:name":"Hacienda Llaugueda",
    "gn:population":0,
    "gn:timezone":"America/Lima",
    "iso:country":"PE",
    "wof:name":"Hacienda Llaugueda",
    "wof:placetype":"locality"
},
  "geometry": {"coordinates":[-78.59477,-7.77318],"type":"Point"}
}