{
  "type": "Feature",
  "properties": {
    "gn:admin1_code":"20",
    "gn:admin2_code":"2004.0",
    "gn:admin3_code":"200401.0",
    "gn:asciiname":"Balcones de Talandracas",
    "gn:country_code":"PE",
    "gn:dem":149,
    "gn:feature_class":"P",
    "gn:feature_code":"PPL",
    "gn:name":"Balcones de Talandracas",
    "gn:population":0,
    "gn:timezone":"America/Lima",
    "iso:country":"PE",
    "name:und_x_variant":[
        "Balcones",
        "Balcones de Talandracas"
    ],
    "wof:name":"Balcones de Talandracas",
    "wof:placetype":"locality"
},
  "geometry": {"coordinates":[-80.07843000000003,-5.08484],"type":"Point"}
}