{
  "type": "Feature",
  "properties": {
    "gn:admin1_code":"03",
    "gn:admin2_code":"307.0",
    "gn:admin3_code":"30703.0",
    "gn:asciiname":"Sarconta",
    "gn:country_code":"PE",
    "gn:dem":3026,
    "gn:feature_class":"P",
    "gn:feature_code":"PPL",
    "gn:name":"Sarconta",
    "gn:population":0,
    "gn:timezone":"America/Lima",
    "iso:country":"PE",
    "wof:name":"Sarconta",
    "wof:placetype":"locality"
},
  "geometry": {"coordinates":[-72.56667,-13.81667],"type":"Point"}
}