{
  "type": "Feature",
  "properties": {
    "gn:admin1_code":"12.0",
    "gn:admin2_code":"1208.0",
    "gn:admin3_code":"120801.0",
    "gn:asciiname":"Yanapaccha",
    "gn:country_code":"PE",
    "gn:dem":4319,
    "gn:feature_class":"P",
    "gn:feature_code":"PPL",
    "gn:name":"Yanapaccha",
    "gn:population":0,
    "gn:timezone":"America/Lima",
    "iso:country":"PE",
    "name:cat_x_preferred":[
        "Yanapaccha"
    ],
    "name:ita_x_preferred":[
        "Yanapaccha"
    ],
    "name:lit_x_preferred":[
        "Janapak\u010dia"
    ],
    "name:nld_x_preferred":[
        "Yanaphaqcha"
    ],
    "name:que_x_preferred":[
        "Yanaphaqcha"
    ],
    "name:zho_x_preferred":[
        "\u4e9e\u7d0d\u5e15\u67e5\u5c71"
    ],
    "wof:name":"Yanapaccha",
    "wof:placetype":"locality"
},
  "geometry": {"coordinates":[-75.90037,-11.65836],"type":"Point"}
}