{
  "type": "Feature",
  "properties": {
    "gn:admin1_code":"9.0",
    "gn:admin2_code":"901.0",
    "gn:admin3_code":"90117.0",
    "gn:asciiname":"Taccasana",
    "gn:country_code":"PE",
    "gn:dem":3729,
    "gn:feature_class":"P",
    "gn:feature_code":"PPL",
    "gn:name":"Taccasana",
    "gn:population":0,
    "gn:timezone":"America/Lima",
    "iso:country":"PE",
    "wof:name":"Taccasana",
    "wof:placetype":"locality"
},
  "geometry": {"coordinates":[-74.83365999999999,-12.76427],"type":"Point"}
}