{
  "type": "Feature",
  "properties": {
    "gn:admin1_code":"21.0",
    "gn:admin2_code":"2112.0",
    "gn:asciiname":"Huanaraya",
    "gn:country_code":"PE",
    "gn:dem":2008,
    "gn:feature_class":"P",
    "gn:feature_code":"PPL",
    "gn:name":"Hua\u00f1araya",
    "gn:population":0,
    "gn:timezone":"America/Lima",
    "iso:country":"PE",
    "name:spa_x_preferred":[
        "Hua\u00f1araya"
    ],
    "wof:name":"Huanaraya",
    "wof:placetype":"locality"
},
  "geometry": {"coordinates":[-69.21106999999999,-14.26435],"type":"Point"}
}