{
  "type": "Feature",
  "properties": {
    "gn:admin1_code":"4",
    "gn:admin2_code":"404.0",
    "gn:admin3_code":"40412.0",
    "gn:asciiname":"Paccpaco",
    "gn:country_code":"PE",
    "gn:dem":1114,
    "gn:feature_class":"P",
    "gn:feature_code":"PPL",
    "gn:name":"Paccpaco",
    "gn:population":0,
    "gn:timezone":"America/Lima",
    "iso:country":"PE",
    "wof:name":"Paccpaco",
    "wof:placetype":"locality"
},
  "geometry": {"coordinates":[-72.46250000000001,-15.81833],"type":"Point"}
}