{
  "type": "Feature",
  "properties": {
    "gn:admin1_code":"2",
    "gn:admin2_code":"218.0",
    "gn:admin3_code":"21804.0",
    "gn:asciiname":"Ancon",
    "gn:country_code":"PE",
    "gn:dem":2122,
    "gn:feature_class":"P",
    "gn:feature_code":"PPL",
    "gn:name":"Anc\u00f3n",
    "gn:population":0,
    "gn:timezone":"America/Lima",
    "iso:country":"PE",
    "name:nld_x_preferred":[
        "Ancon"
    ],
    "wof:name":"Ancon",
    "wof:placetype":"locality"
},
  "geometry": {"coordinates":[-78.08389,-8.77944],"type":"Point"}
}