{
  "type": "Feature",
  "properties": {
    "gn:admin1_code":"06",
    "gn:admin2_code":"603.0",
    "gn:admin3_code":"60306.0",
    "gn:asciiname":"Santa Clara",
    "gn:country_code":"PE",
    "gn:dem":3264,
    "gn:feature_class":"P",
    "gn:feature_code":"PPL",
    "gn:name":"Santa Clara",
    "gn:population":0,
    "gn:timezone":"America/Lima",
    "iso:country":"PE",
    "wof:name":"Santa Clara",
    "wof:placetype":"locality"
},
  "geometry": {"coordinates":[-78.17260999999998,-6.94945],"type":"Point"}
}