{
  "type": "Feature",
  "properties": {
    "gn:admin1_code":"21",
    "gn:admin2_code":"2104.0",
    "gn:admin3_code":"210405.0",
    "gn:asciiname":"Tunquipa",
    "gn:country_code":"PE",
    "gn:dem":4093,
    "gn:feature_class":"P",
    "gn:feature_code":"PPL",
    "gn:name":"Tunquipa",
    "gn:population":0,
    "gn:timezone":"America/Lima",
    "iso:country":"PE",
    "wof:name":"Tunquipa",
    "wof:placetype":"locality"
},
  "geometry": {"coordinates":[-69.44873,-16.83446],"type":"Point"}
}