{
  "type": "Feature",
  "properties": {
    "gn:admin1_code":"11",
    "gn:admin2_code":"1101.0",
    "gn:admin3_code":"110104.0",
    "gn:asciiname":"Ocucaje",
    "gn:country_code":"PE",
    "gn:dem":323,
    "gn:feature_class":"P",
    "gn:feature_code":"PPLA3",
    "gn:name":"Ocucaje",
    "gn:population":0,
    "gn:timezone":"America/Lima",
    "iso:country":"PE",
    "name:und_x_variant":[
        "Hacienda Ocucaje",
        "Ocucaje Hacienda",
        "Ocucaje"
    ],
    "wof:name":"Ocucaje",
    "wof:placetype":"locality"
},
  "geometry": {"coordinates":[-75.66916999999999,-14.34861],"type":"Point"}
}