{
  "type": "Feature",
  "properties": {
    "gn:admin1_code":"5.0",
    "gn:admin2_code":"505.0",
    "gn:admin3_code":"50508.0",
    "gn:asciiname":"Acco",
    "gn:country_code":"PE",
    "gn:dem":3320,
    "gn:feature_class":"P",
    "gn:feature_code":"PPL",
    "gn:name":"Acco",
    "gn:population":0,
    "gn:timezone":"America/Lima",
    "iso:country":"PE",
    "wof:name":"Acco",
    "wof:placetype":"locality"
},
  "geometry": {"coordinates":[-74.03657,-12.91634],"type":"Point"}
}