{
  "type": "Feature",
  "properties": {
    "gn:admin1_code":"04",
    "gn:admin2_code":"404.0",
    "gn:admin3_code":"40404.0",
    "gn:asciiname":"Itushi",
    "gn:country_code":"PE",
    "gn:dem":4751,
    "gn:feature_class":"P",
    "gn:feature_code":"PPL",
    "gn:name":"Itushi",
    "gn:population":0,
    "gn:timezone":"America/Lima",
    "iso:country":"PE",
    "name:spa_x_preferred":[
        "Itushi"
    ],
    "wof:name":"Itushi",
    "wof:placetype":"locality"
},
  "geometry": {"coordinates":[-72.01685999999999,-15.00952],"type":"Point"}
}