{
  "type": "Feature",
  "properties": {
    "gn:admin1_code":"08",
    "gn:admin2_code":"806.0",
    "gn:admin3_code":"80605.0",
    "gn:asciiname":"Uchullucllo",
    "gn:country_code":"PE",
    "gn:dem":3981,
    "gn:feature_class":"P",
    "gn:feature_code":"PPL",
    "gn:name":"Uchullucllo",
    "gn:population":0,
    "gn:timezone":"America/Lima",
    "iso:country":"PE",
    "name:und_x_variant":[
        "Uchulujllo",
        "Uchullujllo",
        "Uchulluchlu",
        "Uchullucllo"
    ],
    "wof:name":"Uchullucllo",
    "wof:placetype":"locality"
},
  "geometry": {"coordinates":[-71.30743000000002,-13.97234],"type":"Point"}
}