{
  "type": "Feature",
  "properties": {
    "gn:admin1_code":"11",
    "gn:admin2_code":"1104.0",
    "gn:admin3_code":"110405.0",
    "gn:asciiname":"Fundo Palca Marcachico",
    "gn:country_code":"PE",
    "gn:dem":1517,
    "gn:feature_class":"P",
    "gn:feature_code":"PPL",
    "gn:name":"Fundo Palca Marcachico",
    "gn:population":0,
    "gn:timezone":"America/Lima",
    "iso:country":"PE",
    "wof:name":"Fundo Palca Marcachico",
    "wof:placetype":"locality"
},
  "geometry": {"coordinates":[-75.20668000000001,-14.24734],"type":"Point"}
}