{
  "type": "Feature",
  "properties": {
    "gn:admin1_code":"10.0",
    "gn:admin2_code":"1011.0",
    "gn:admin3_code":"101107.0",
    "gn:asciiname":"Contadera",
    "gn:country_code":"PE",
    "gn:dem":3980,
    "gn:feature_class":"P",
    "gn:feature_code":"PPL",
    "gn:name":"Contadera",
    "gn:population":0,
    "gn:timezone":"America/Lima",
    "iso:country":"PE",
    "wof:name":"Contadera",
    "wof:placetype":"locality"
},
  "geometry": {"coordinates":[-76.70974,-9.78386],"type":"Point"}
}