{
  "type": "Feature",
  "properties": {
    "gn:admin1_code":"9.0",
    "gn:admin2_code":"902.0",
    "gn:admin3_code":"90201.0",
    "gn:asciiname":"Rumihuasi",
    "gn:country_code":"PE",
    "gn:dem":3867,
    "gn:feature_class":"P",
    "gn:feature_code":"PPL",
    "gn:name":"Rumihuasi",
    "gn:population":0,
    "gn:timezone":"America/Lima",
    "iso:country":"PE",
    "wof:name":"Rumihuasi",
    "wof:placetype":"locality"
},
  "geometry": {"coordinates":[-74.57075999999998,-12.78904],"type":"Point"}
}