{
  "type": "Feature",
  "properties": {
    "gn:admin1_code":"20.0",
    "gn:admin2_code":"2002.0",
    "gn:admin3_code":"200202.0",
    "gn:asciiname":"Huamingas",
    "gn:country_code":"PE",
    "gn:dem":2114,
    "gn:feature_class":"P",
    "gn:feature_code":"PPL",
    "gn:name":"Huamingas",
    "gn:population":0,
    "gn:timezone":"America/Lima",
    "iso:country":"PE",
    "wof:name":"Huamingas",
    "wof:placetype":"locality"
},
  "geometry": {"coordinates":[-79.92749000000001,-4.94408],"type":"Point"}
}