{
  "type": "Feature",
  "properties": {
    "gn:admin1_code":"05",
    "gn:admin2_code":"502.0",
    "gn:admin3_code":"50203.0",
    "gn:asciiname":"Huayllabamba",
    "gn:country_code":"PE",
    "gn:dem":3699,
    "gn:feature_class":"P",
    "gn:feature_code":"PPL",
    "gn:name":"Huayllabamba",
    "gn:population":0,
    "gn:timezone":"America/Lima",
    "iso:country":"PE",
    "wof:name":"Huayllabamba",
    "wof:placetype":"locality"
},
  "geometry": {"coordinates":[-74.21829,-13.48792],"type":"Point"}
}