{
  "type": "Feature",
  "properties": {
    "iso:country":"PE",
    "name:ceb_x_preferred":[
        "Coya"
    ],
    "name:deu_x_preferred":[
        "Coya"
    ],
    "name:eng_x_preferred":[
        "Coya"
    ],
    "name:que_x_preferred":[
        "Quya llaqta"
    ],
    "name:spa_x_preferred":[
        "Coya"
    ],
    "qs:gn_country":"PE",
    "qs:gn_fcode":"PPL",
    "qs:gn_pop":0,
    "qs:name":"Coya",
    "qs:name_adm0":"Per\u00fa",
    "qs:name_adm1":"Cusco",
    "qs:photos":126,
    "qs:photos_1k":26,
    "qs:photos_9k":1,
    "qs:photos_9r":3,
    "qs:photos_all":126,
    "qs:photos_sr":3,
    "qs:placetype":"Town",
    "qs:pop_sr":"0",
    "qs:woe_adm0":23424919,
    "wd:wordcount":101,
    "wof:name":"Coya",
    "wof:placetype":"locality"
},
  "geometry": {"coordinates":[-72.08617,-13.99103],"type":"Point"}
}