{
  "type": "Feature",
  "properties": {
    "gn:admin1_code":"3",
    "gn:admin2_code":"301.0",
    "gn:admin3_code":"30102.0",
    "gn:asciiname":"Acco",
    "gn:country_code":"PE",
    "gn:dem":2738,
    "gn:feature_class":"P",
    "gn:feature_code":"PPL",
    "gn:name":"Acco",
    "gn:population":0,
    "gn:timezone":"America/Lima",
    "iso:country":"PE",
    "wof:name":"Acco",
    "wof:placetype":"locality"
},
  "geometry": {"coordinates":[-73.02761,-13.93818],"type":"Point"}
}