{
  "type": "Feature",
  "properties": {
    "gn:admin1_code":"13.0",
    "gn:admin2_code":"1308.0",
    "gn:admin3_code":"130802.0",
    "gn:asciiname":"Chicripata",
    "gn:country_code":"PE",
    "gn:dem":2961,
    "gn:feature_class":"P",
    "gn:feature_code":"PPL",
    "gn:name":"Chicripata",
    "gn:population":0,
    "gn:timezone":"America/Lima",
    "iso:country":"PE",
    "wof:name":"Chicripata",
    "wof:placetype":"locality"
},
  "geometry": {"coordinates":[-77.41806,-8.16778],"type":"Point"}
}