{
  "type": "Feature",
  "properties": {
    "gn:admin1_code":"05",
    "gn:admin2_code":"507.0",
    "gn:admin3_code":"50706.0",
    "gn:asciiname":"Pongo",
    "gn:country_code":"PE",
    "gn:dem":3290,
    "gn:feature_class":"P",
    "gn:feature_code":"PPL",
    "gn:name":"Pongo",
    "gn:population":0,
    "gn:timezone":"America/Lima",
    "iso:country":"PE",
    "name:ceb_x_preferred":[
        "Pongo"
    ],
    "name:deu_x_preferred":[
        "Pongo"
    ],
    "name:fra_x_preferred":[
        "Pongo"
    ],
    "name:ita_x_preferred":[
        "Pongo"
    ],
    "name:swe_x_preferred":[
        "Pongo"
    ],
    "wof:name":"Pongo",
    "wof:placetype":"locality"
},
  "geometry": {"coordinates":[-73.61667,-15.28333],"type":"Point"}
}