{
  "type": "Feature",
  "properties": {
    "gn:admin1_code":"15",
    "gn:admin2_code":"1507.0",
    "gn:admin3_code":"150702.0",
    "gn:asciiname":"Balconcillo de las Palmas",
    "gn:country_code":"PE",
    "gn:dem":939,
    "gn:feature_class":"P",
    "gn:feature_code":"PPL",
    "gn:name":"Balconcillo de las Palmas",
    "gn:population":0,
    "gn:timezone":"America/Lima",
    "iso:country":"PE",
    "name:spa_x_preferred":[
        "Balconcillo de las Palmas"
    ],
    "name:spa_x_variant":[
        "Balconcillo de la Palma"
    ],
    "wof:name":"Balconcillo de las Palmas",
    "wof:placetype":"locality"
},
  "geometry": {"coordinates":[-76.66152,-12.02448],"type":"Point"}
}