{
  "type": "Feature",
  "properties": {
    "gn:admin1_code":"2.0",
    "gn:admin2_code":"220.0",
    "gn:admin3_code":"22003.0",
    "gn:asciiname":"Huayapon",
    "gn:country_code":"PE",
    "gn:dem":3106,
    "gn:feature_class":"P",
    "gn:feature_code":"PPL",
    "gn:name":"Huayap\u00f3n",
    "gn:population":0,
    "gn:timezone":"America/Lima",
    "iso:country":"PE",
    "wof:name":"Huayapon",
    "wof:placetype":"locality"
},
  "geometry": {"coordinates":[-77.67749999999999,-9.19611],"type":"Point"}
}