{
  "type": "Feature",
  "properties": {
    "gn:admin1_code":"18",
    "gn:admin2_code":"1802.0",
    "gn:admin3_code":"180208.0",
    "gn:asciiname":"La Bodega",
    "gn:country_code":"PE",
    "gn:dem":2103,
    "gn:feature_class":"P",
    "gn:feature_code":"PPL",
    "gn:name":"La Bodega",
    "gn:population":0,
    "gn:timezone":"America/Lima",
    "iso:country":"PE",
    "wof:name":"La Bodega",
    "wof:placetype":"locality"
},
  "geometry": {"coordinates":[-71.125,-16.70833],"type":"Point"}
}