{
  "type": "Feature",
  "properties": {
    "gn:admin1_code":"20",
    "gn:admin2_code":"2002.0",
    "gn:admin3_code":"200208.0",
    "gn:asciiname":"Tazajeras",
    "gn:country_code":"PE",
    "gn:dem":1368,
    "gn:feature_class":"P",
    "gn:feature_code":"PPL",
    "gn:name":"Tazajeras",
    "gn:population":0,
    "gn:timezone":"America/Lima",
    "iso:country":"PE",
    "name:und_x_variant":[
        "Tazajera",
        "Tazajeras"
    ],
    "wof:name":"Tazajeras",
    "wof:placetype":"locality"
},
  "geometry": {"coordinates":[-79.99316,-4.74765],"type":"Point"}
}