{
  "type": "Feature",
  "properties": {
    "gn:admin1_code":"13",
    "gn:admin2_code":"1312.0",
    "gn:admin3_code":"131201.0",
    "gn:asciiname":"Huancaco",
    "gn:country_code":"PE",
    "gn:dem":55,
    "gn:feature_class":"P",
    "gn:feature_code":"PPL",
    "gn:name":"Huancaco",
    "gn:population":0,
    "gn:timezone":"America/Lima",
    "iso:country":"PE",
    "wof:name":"Huancaco",
    "wof:placetype":"locality"
},
  "geometry": {"coordinates":[-78.78333000000001,-8.43333],"type":"Point"}
}