{
  "type": "Feature",
  "properties": {
    "gn:admin1_code":"23",
    "gn:admin2_code":"2304.0",
    "gn:asciiname":"Ancohuyo",
    "gn:country_code":"PE",
    "gn:dem":4279,
    "gn:feature_class":"P",
    "gn:feature_code":"PPL",
    "gn:name":"Ancohuyo",
    "gn:population":0,
    "gn:timezone":"America/Lima",
    "iso:country":"PE",
    "name:und_x_variant":[
        "Anacallo",
        "Ancacollo",
        "Ancohuyo"
    ],
    "wof:name":"Ancohuyo",
    "wof:placetype":"locality"
},
  "geometry": {"coordinates":[-69.78882,-17.24342],"type":"Point"}
}