{
  "type": "Feature",
  "properties": {
    "gn:admin1_code":"10",
    "gn:admin2_code":"1005.0",
    "gn:admin3_code":"100509.0",
    "gn:asciiname":"Punos",
    "gn:country_code":"PE",
    "gn:dem":3664,
    "gn:feature_class":"P",
    "gn:feature_code":"PPLA3",
    "gn:name":"Pu\u00f1os",
    "gn:population":0,
    "gn:timezone":"America/Lima",
    "iso:country":"PE",
    "wof:name":"Punos",
    "wof:placetype":"locality"
},
  "geometry": {"coordinates":[-76.88469000000001,-9.49735],"type":"Point"}
}