{
  "type": "Feature",
  "properties": {
    "gn:admin1_code":"10.0",
    "gn:admin2_code":"1005.0",
    "gn:admin3_code":"100503.0",
    "gn:asciiname":"Agohuay",
    "gn:country_code":"PE",
    "gn:dem":3346,
    "gn:feature_class":"P",
    "gn:feature_code":"PPL",
    "gn:name":"Agohuay",
    "gn:population":0,
    "gn:timezone":"America/Lima",
    "iso:country":"PE",
    "wof:name":"Agohuay",
    "wof:placetype":"locality"
},
  "geometry": {"coordinates":[-76.76975,-9.39831],"type":"Point"}
}