{
  "type": "Feature",
  "properties": {
    "gn:admin1_code":"20",
    "gn:admin2_code":"2002.0",
    "gn:admin3_code":"200201.0",
    "gn:asciiname":"Chocan",
    "gn:country_code":"PE",
    "gn:dem":1890,
    "gn:feature_class":"P",
    "gn:feature_code":"PPL",
    "gn:name":"Choc\u00e1n",
    "gn:population":0,
    "gn:timezone":"America/Lima",
    "iso:country":"PE",
    "name:und_x_variant":[
        "Chocan Ciudad",
        "Choc\u00e1n"
    ],
    "wof:name":"Chocan",
    "wof:placetype":"locality"
},
  "geometry": {"coordinates":[-79.70917,-4.53759],"type":"Point"}
}