{
  "type": "Feature",
  "properties": {
    "gn:admin1_code":"15",
    "gn:admin2_code":"1507.0",
    "gn:admin3_code":"150718.0",
    "gn:asciiname":"Corpaayegua",
    "gn:country_code":"PE",
    "gn:dem":4083,
    "gn:feature_class":"P",
    "gn:feature_code":"PPL",
    "gn:name":"Corpaayegua",
    "gn:population":0,
    "gn:timezone":"America/Lima",
    "iso:country":"PE",
    "wof:name":"Corpaayegua",
    "wof:placetype":"locality"
},
  "geometry": {"coordinates":[-76.29167,-11.94889],"type":"Point"}
}