{
  "type": "Feature",
  "properties": {
    "gn:admin1_code":"03",
    "gn:admin2_code":"306.0",
    "gn:admin3_code":"30604.0",
    "gn:asciiname":"Uchuypata",
    "gn:country_code":"PE",
    "gn:dem":2594,
    "gn:feature_class":"P",
    "gn:feature_code":"PPL",
    "gn:name":"Uchuypata",
    "gn:population":0,
    "gn:timezone":"America/Lima",
    "iso:country":"PE",
    "wof:name":"Uchuypata",
    "wof:placetype":"locality"
},
  "geometry": {"coordinates":[-73.78860999999998,-13.29734],"type":"Point"}
}