{
  "type": "Feature",
  "properties": {
    "gn:admin1_code":"1.0",
    "gn:admin2_code":"105.0",
    "gn:admin3_code":"10504.0",
    "gn:asciiname":"Chuchan",
    "gn:country_code":"PE",
    "gn:dem":2413,
    "gn:feature_class":"P",
    "gn:feature_code":"PPL",
    "gn:name":"Chuch\u00e1n",
    "gn:population":0,
    "gn:timezone":"America/Lima",
    "iso:country":"PE",
    "wof:name":"Chuchan",
    "wof:placetype":"locality"
},
  "geometry": {"coordinates":[-77.97883,-6.30401],"type":"Point"}
}