{
  "type": "Feature",
  "properties": {
    "gn:admin1_code":"22.0",
    "gn:admin2_code":"2204.0",
    "gn:admin3_code":"220406.0",
    "gn:asciiname":"Tinguillo",
    "gn:country_code":"PE",
    "gn:dem":331,
    "gn:elevation":"493.0",
    "gn:feature_class":"P",
    "gn:feature_code":"PPL",
    "gn:name":"Tinguillo",
    "gn:population":0,
    "gn:timezone":"America/Lima",
    "iso:country":"PE",
    "name:spa_x_preferred":[
        "Tinguillo"
    ],
    "wof:name":"Tinguillo",
    "wof:placetype":"locality"
},
  "geometry": {"coordinates":[-76.66409,-7.06478],"type":"Point"}
}