{
  "type": "Feature",
  "properties": {
    "gn:admin1_code":"15",
    "gn:admin2_code":"1506.0",
    "gn:admin3_code":"150606.0",
    "gn:asciiname":"Huaylinco",
    "gn:country_code":"PE",
    "gn:dem":2361,
    "gn:feature_class":"P",
    "gn:feature_code":"PPL",
    "gn:name":"Huaylinco",
    "gn:population":0,
    "gn:timezone":"America/Lima",
    "iso:country":"PE",
    "wof:name":"Huaylinco",
    "wof:placetype":"locality"
},
  "geometry": {"coordinates":[-76.98194000000002,-11.15306],"type":"Point"}
}