{
  "type": "Feature",
  "properties": {
    "gn:admin1_code":"5",
    "gn:admin2_code":"509.0",
    "gn:admin3_code":"50905.0",
    "gn:asciiname":"Huanquine",
    "gn:country_code":"PE",
    "gn:dem":3647,
    "gn:feature_class":"P",
    "gn:feature_code":"PPL",
    "gn:name":"Huanquine",
    "gn:population":0,
    "gn:timezone":"America/Lima",
    "iso:country":"PE",
    "wof:name":"Huanquine",
    "wof:placetype":"locality"
},
  "geometry": {"coordinates":[-73.88611,-14.18611],"type":"Point"}
}