{
  "type": "Feature",
  "properties": {
    "gn:admin1_code":"5.0",
    "gn:admin2_code":"511.0",
    "gn:admin3_code":"51108.0",
    "gn:asciiname":"Pataccorral",
    "gn:country_code":"PE",
    "gn:dem":3715,
    "gn:feature_class":"P",
    "gn:feature_code":"PPL",
    "gn:name":"Pataccorral",
    "gn:population":0,
    "gn:timezone":"America/Lima",
    "iso:country":"PE",
    "wof:name":"Pataccorral",
    "wof:placetype":"locality"
},
  "geometry": {"coordinates":[-74.04405,-13.49243],"type":"Point"}
}