{
  "type": "Feature",
  "properties": {
    "gn:admin1_code":"04",
    "gn:admin2_code":"405.0",
    "gn:admin3_code":"40514.0",
    "gn:asciiname":"Hurasara",
    "gn:country_code":"PE",
    "gn:dem":4680,
    "gn:feature_class":"P",
    "gn:feature_code":"PPL",
    "gn:name":"Hurasara",
    "gn:population":0,
    "gn:timezone":"America/Lima",
    "iso:country":"PE",
    "wof:name":"Hurasara",
    "wof:placetype":"locality"
},
  "geometry": {"coordinates":[-71.15722,-15.72083],"type":"Point"}
}