{
  "type": "Feature",
  "properties": {
    "gn:admin1_code":"8",
    "gn:admin2_code":"805.0",
    "gn:admin3_code":"80503.0",
    "gn:asciiname":"Jantahuasi",
    "gn:country_code":"PE",
    "gn:dem":4110,
    "gn:feature_class":"P",
    "gn:feature_code":"PPL",
    "gn:name":"Jantahuasi",
    "gn:population":0,
    "gn:timezone":"America/Lima",
    "iso:country":"PE",
    "wof:name":"Jantahuasi",
    "wof:placetype":"locality"
},
  "geometry": {"coordinates":[-71.32886999999999,-14.47199],"type":"Point"}
}