{
  "type": "Feature",
  "properties": {
    "gn:admin1_code":"12",
    "gn:admin2_code":"1206.0",
    "gn:admin3_code":"120605.0",
    "gn:asciiname":"Villa Ancayo",
    "gn:country_code":"PE",
    "gn:dem":886,
    "gn:feature_class":"P",
    "gn:feature_code":"PPL",
    "gn:name":"Villa Ancayo",
    "gn:population":0,
    "gn:timezone":"America/Lima",
    "iso:country":"PE",
    "wof:name":"Villa Ancayo",
    "wof:placetype":"locality"
},
  "geometry": {"coordinates":[-74.72351,-11.33206],"type":"Point"}
}