{
  "type": "Feature",
  "properties": {
    "gn:admin1_code":"11",
    "gn:admin2_code":"1103.0",
    "gn:admin3_code":"110301.0",
    "gn:asciiname":"Hacienda Soisonguito",
    "gn:country_code":"PE",
    "gn:dem":453,
    "gn:feature_class":"P",
    "gn:feature_code":"PPL",
    "gn:name":"Hacienda Soisonguito",
    "gn:population":0,
    "gn:timezone":"America/Lima",
    "iso:country":"PE",
    "name:und_x_variant":[
        "Soisonguito Hacienda",
        "Soisonguito",
        "Hacienda Soisonguito"
    ],
    "wof:name":"Hacienda Soisonguito",
    "wof:placetype":"locality"
},
  "geometry": {"coordinates":[-75.02578000000003,-14.83508],"type":"Point"}
}