{
  "type": "Feature",
  "properties": {
    "gn:admin1_code":"8",
    "gn:admin2_code":"806.0",
    "gn:admin3_code":"80604.0",
    "gn:asciiname":"Chocahuaylla",
    "gn:country_code":"PE",
    "gn:dem":3777,
    "gn:feature_class":"P",
    "gn:feature_code":"PPL",
    "gn:name":"Chocahuaylla",
    "gn:population":0,
    "gn:timezone":"America/Lima",
    "iso:country":"PE",
    "wof:name":"Chocahuaylla",
    "wof:placetype":"locality"
},
  "geometry": {"coordinates":[-71.14806999999998,-14.36358],"type":"Point"}
}