{
  "type": "Feature",
  "properties": {
    "gn:admin1_code":"10.0",
    "gn:admin2_code":"1001.0",
    "gn:admin3_code":"100103.0",
    "gn:asciiname":"Shiracalla",
    "gn:country_code":"PE",
    "gn:dem":2173,
    "gn:feature_class":"P",
    "gn:feature_code":"PPL",
    "gn:name":"Shiracalla",
    "gn:population":0,
    "gn:timezone":"America/Lima",
    "iso:country":"PE",
    "wof:name":"Shiracalla",
    "wof:placetype":"locality"
},
  "geometry": {"coordinates":[-76.04538000000002,-9.8007],"type":"Point"}
}