{
  "type": "Feature",
  "properties": {
    "gn:admin1_code":"11",
    "gn:admin2_code":"1103.0",
    "gn:admin3_code":"110303.0",
    "gn:asciiname":"Hacienda Surcuna",
    "gn:country_code":"PE",
    "gn:dem":867,
    "gn:feature_class":"P",
    "gn:feature_code":"PPL",
    "gn:name":"Hacienda Surcu\u00f1a",
    "gn:population":0,
    "gn:timezone":"America/Lima",
    "iso:country":"PE",
    "name:spa_x_preferred":[
        "Hacienda Surcu\u00f1a"
    ],
    "name:spa_x_variant":[
        "Surcu\u00f1a"
    ],
    "wof:name":"Hacienda Surcuna",
    "wof:placetype":"locality"
},
  "geometry": {"coordinates":[-74.91314,-14.60182],"type":"Point"}
}