{
  "type": "Feature",
  "properties": {
    "gn:admin1_code":"12",
    "gn:admin2_code":"1205.0",
    "gn:admin3_code":"120501.0",
    "gn:asciiname":"Condorsenca",
    "gn:country_code":"PE",
    "gn:dem":4441,
    "gn:feature_class":"P",
    "gn:feature_code":"PPL",
    "gn:name":"C\u00f3ndorsenca",
    "gn:population":0,
    "gn:timezone":"America/Lima",
    "iso:country":"PE",
    "name:und_x_variant":[
        "C\u00f3ndorsenca",
        "C\u00f3ndorsencca"
    ],
    "wof:name":"Condorsenca",
    "wof:placetype":"locality"
},
  "geometry": {"coordinates":[-75.90222,-11.18972],"type":"Point"}
}