{
  "type": "Feature",
  "properties": {
    "gn:admin1_code":"11",
    "gn:admin2_code":"1101.0",
    "gn:admin3_code":"110101.0",
    "gn:asciiname":"Camino Grande",
    "gn:country_code":"PE",
    "gn:dem":395,
    "gn:feature_class":"P",
    "gn:feature_code":"PPLL",
    "gn:name":"Camino Grande",
    "gn:population":0,
    "gn:timezone":"America/Lima",
    "iso:country":"PE",
    "name:spa_x_preferred":[
        "Camino Grande"
    ],
    "wof:name":"Camino Grande",
    "wof:placetype":"locality"
},
  "geometry": {"coordinates":[-75.7146,-14.11093],"type":"Point"}
}