{
  "type": "Feature",
  "properties": {
    "gn:admin1_code":"11",
    "gn:admin2_code":"1101.0",
    "gn:admin3_code":"110111.0",
    "gn:asciiname":"Los Tronquitos",
    "gn:country_code":"PE",
    "gn:dem":369,
    "gn:feature_class":"P",
    "gn:feature_code":"PPL",
    "gn:name":"Los Tronquitos",
    "gn:population":0,
    "gn:timezone":"America/Lima",
    "iso:country":"PE",
    "name:und_x_variant":[
        "Tranquitos",
        "Los Tronquitos Hacienda",
        "Los Tronquitos"
    ],
    "wof:name":"Los Tronquitos",
    "wof:placetype":"locality"
},
  "geometry": {"coordinates":[-75.71642,-14.21472],"type":"Point"}
}