{
  "type": "Feature",
  "properties": {
    "gn:admin1_code":"11",
    "gn:admin2_code":"1102.0",
    "gn:asciiname":"Huirpina",
    "gn:country_code":"PE",
    "gn:dem":2976,
    "gn:feature_class":"P",
    "gn:feature_code":"PPL",
    "gn:name":"Huirpina",
    "gn:population":0,
    "gn:timezone":"America/Lima",
    "iso:country":"PE",
    "name:spa_x_preferred":[
        "Huirpina"
    ],
    "wof:name":"Huirpina",
    "wof:placetype":"locality"
},
  "geometry": {"coordinates":[-75.94098000000002,-13.01784],"type":"Point"}
}