{
  "type": "Feature",
  "properties": {
    "gn:admin1_code":"9",
    "gn:admin2_code":"906.0",
    "gn:admin3_code":"90606.0",
    "gn:asciiname":"Allccanja",
    "gn:country_code":"PE",
    "gn:dem":3340,
    "gn:feature_class":"P",
    "gn:feature_code":"PPL",
    "gn:name":"Allccanja",
    "gn:population":0,
    "gn:timezone":"America/Lima",
    "iso:country":"PE",
    "wof:name":"Allccanja",
    "wof:placetype":"locality"
},
  "geometry": {"coordinates":[-75.09697,-14.00936],"type":"Point"}
}