{
  "type": "Feature",
  "properties": {
    "gn:admin1_code":"10.0",
    "gn:admin2_code":"1003.0",
    "gn:admin3_code":"100316.0",
    "gn:asciiname":"San Miguel de Yanuma",
    "gn:country_code":"PE",
    "gn:dem":3707,
    "gn:feature_class":"P",
    "gn:feature_code":"PPL",
    "gn:name":"San Miguel de Yanuma",
    "gn:population":0,
    "gn:timezone":"America/Lima",
    "iso:country":"PE",
    "wof:name":"San Miguel de Yanuma",
    "wof:placetype":"locality"
},
  "geometry": {"coordinates":[-76.71174000000001,-9.58789],"type":"Point"}
}