{
  "type": "Feature",
  "properties": {
    "gn:admin1_code":"12.0",
    "gn:admin2_code":"1204.0",
    "gn:admin3_code":"120418.0",
    "gn:asciiname":"Cercamayos",
    "gn:country_code":"PE",
    "gn:dem":4429,
    "gn:feature_class":"P",
    "gn:feature_code":"PPL",
    "gn:name":"Cercamayos",
    "gn:population":0,
    "gn:timezone":"America/Lima",
    "iso:country":"PE",
    "wof:name":"Cercamayos",
    "wof:placetype":"locality"
},
  "geometry": {"coordinates":[-75.40731,-11.66123],"type":"Point"}
}