{
  "type": "Feature",
  "properties": {
    "gn:admin1_code":"3",
    "gn:admin2_code":"302.0",
    "gn:admin3_code":"30219.0",
    "gn:asciiname":"Collpapampa",
    "gn:country_code":"PE",
    "gn:dem":3327,
    "gn:feature_class":"P",
    "gn:feature_code":"PPL",
    "gn:name":"Collpapampa",
    "gn:population":0,
    "gn:timezone":"America/Lima",
    "iso:country":"PE",
    "wof:name":"Collpapampa",
    "wof:placetype":"locality"
},
  "geometry": {"coordinates":[-73.29209,-13.5415],"type":"Point"}
}