{
  "type": "Feature",
  "properties": {
    "gn:admin1_code":"12",
    "gn:admin2_code":"1201.0",
    "gn:admin3_code":"120135.0",
    "gn:asciiname":"Balcon",
    "gn:country_code":"PE",
    "gn:dem":2558,
    "gn:feature_class":"P",
    "gn:feature_code":"PPL",
    "gn:name":"Balc\u00f3n",
    "gn:population":0,
    "gn:timezone":"America/Lima",
    "iso:country":"PE",
    "name:und_x_variant":[
        "Balc\u00f3r",
        "Balc\u00f3n"
    ],
    "wof:name":"Balcon",
    "wof:placetype":"locality"
},
  "geometry": {"coordinates":[-74.66521999999998,-11.88393],"type":"Point"}
}