{
  "type": "Feature",
  "properties": {
    "gn:admin1_code":"2.0",
    "gn:admin2_code":"212.0",
    "gn:admin3_code":"21206.0",
    "gn:asciiname":"Yamahuilca",
    "gn:country_code":"PE",
    "gn:dem":3346,
    "gn:feature_class":"P",
    "gn:feature_code":"PPL",
    "gn:name":"Yamahuilca",
    "gn:population":0,
    "gn:timezone":"America/Lima",
    "iso:country":"PE",
    "wof:name":"Yamahuilca",
    "wof:placetype":"locality"
},
  "geometry": {"coordinates":[-77.95917,-9.06778],"type":"Point"}
}