{
  "type": "Feature",
  "properties": {
    "gn:admin1_code":"8",
    "gn:admin2_code":"808.0",
    "gn:asciiname":"Parpahuala",
    "gn:country_code":"PE",
    "gn:dem":4627,
    "gn:feature_class":"P",
    "gn:feature_code":"PPL",
    "gn:name":"Parpahuala",
    "gn:population":0,
    "gn:timezone":"America/Lima",
    "iso:country":"PE",
    "wof:name":"Parpahuala",
    "wof:placetype":"locality"
},
  "geometry": {"coordinates":[-71.10319,-15.40517],"type":"Point"}
}