{
  "type": "Feature",
  "properties": {
    "iso:country":"PE",
    "qs:gn_country":"PE",
    "qs:gn_fcode":"PPLX",
    "qs:gn_pop":0,
    "qs:name":"Pampa de Camarones",
    "qs:name_adm0":"Per\u00fa",
    "qs:name_adm1":"Arequipa",
    "qs:photos":1,
    "qs:photos_1k":1,
    "qs:photos_9k":1,
    "qs:photos_9r":1,
    "qs:photos_all":1,
    "qs:photos_sr":1,
    "qs:placetype":"Suburb",
    "qs:pop_sr":"0",
    "qs:woe_adm0":23424919,
    "wof:name":"Pampa de Camarones",
    "wof:placetype":"neighbourhood"
},
  "geometry": {"coordinates":[-71.56917,-16.40917],"type":"Point"}
}