{
  "type": "Feature",
  "properties": {
    "gn:admin1_code":"13",
    "gn:admin2_code":"1302.0",
    "gn:admin3_code":"130205.0",
    "gn:asciiname":"El Culto",
    "gn:country_code":"PE",
    "gn:dem":43,
    "gn:feature_class":"P",
    "gn:feature_code":"PPL",
    "gn:name":"El Culto",
    "gn:population":0,
    "gn:timezone":"America/Lima",
    "iso:country":"PE",
    "wof:name":"El Culto",
    "wof:placetype":"locality"
},
  "geometry": {"coordinates":[-79.34331,-7.70834],"type":"Point"}
}