{
  "type": "Feature",
  "properties": {
    "gn:admin1_code":"8",
    "gn:admin2_code":"809.0",
    "gn:admin3_code":"80906.0",
    "gn:asciiname":"Matoriato",
    "gn:country_code":"PE",
    "gn:dem":554,
    "gn:feature_class":"P",
    "gn:feature_code":"PPL",
    "gn:name":"Matoriato",
    "gn:population":0,
    "gn:timezone":"America/Lima",
    "iso:country":"PE",
    "wof:name":"Matoriato",
    "wof:placetype":"locality"
},
  "geometry": {"coordinates":[-72.76449000000002,-12.3881],"type":"Point"}
}