{
  "type": "Feature",
  "properties": {
    "gn:admin1_code":"09",
    "gn:admin2_code":"904.0",
    "gn:admin3_code":"90401.0",
    "gn:asciiname":"Paca Paca",
    "gn:country_code":"PE",
    "gn:dem":4790,
    "gn:feature_class":"P",
    "gn:feature_code":"PPL",
    "gn:name":"Paca Paca",
    "gn:population":0,
    "gn:timezone":"America/Lima",
    "iso:country":"PE",
    "wof:name":"Paca Paca",
    "wof:placetype":"locality"
},
  "geometry": {"coordinates":[-75.33589000000001,-13.02483],"type":"Point"}
}