{
  "type": "Feature",
  "properties": {
    "gn:admin1_code":"9.0",
    "gn:admin2_code":"907.0",
    "gn:admin3_code":"90709.0",
    "gn:asciiname":"Yanama",
    "gn:country_code":"PE",
    "gn:dem":3849,
    "gn:feature_class":"P",
    "gn:feature_code":"PPL",
    "gn:name":"Yanama",
    "gn:population":0,
    "gn:timezone":"America/Lima",
    "iso:country":"PE",
    "name:zho_x_preferred":[
        "\u4e9e\u7d0d\u99ac\u5c71"
    ],
    "wof:name":"Yanama",
    "wof:placetype":"locality"
},
  "geometry": {"coordinates":[-74.91361999999999,-12.16437],"type":"Point"}
}