{
  "type": "Feature",
  "properties": {
    "gn:admin1_code":"24",
    "gn:admin2_code":"2401.0",
    "gn:admin3_code":"240104.0",
    "gn:asciiname":"Chacritas",
    "gn:country_code":"PE",
    "gn:dem":68,
    "gn:feature_class":"P",
    "gn:feature_code":"PPL",
    "gn:name":"Chacritas",
    "gn:population":0,
    "gn:timezone":"America/Lima",
    "iso:country":"PE",
    "wof:name":"Chacritas",
    "wof:placetype":"locality"
},
  "geometry": {"coordinates":[-80.34631,-3.69588],"type":"Point"}
}