{
  "type": "Feature",
  "properties": {
    "gn:admin1_code":"21",
    "gn:admin2_code":"2101.0",
    "gn:admin3_code":"210102.0",
    "gn:asciiname":"Patarpi",
    "gn:country_code":"PE",
    "gn:dem":4205,
    "gn:feature_class":"P",
    "gn:feature_code":"PPL",
    "gn:name":"Patarpi",
    "gn:population":0,
    "gn:timezone":"America/Lima",
    "iso:country":"PE",
    "wof:name":"Patarpi",
    "wof:placetype":"locality"
},
  "geometry": {"coordinates":[-69.85339,-16.36649],"type":"Point"}
}