{
  "type": "Feature",
  "properties": {
    "gn:admin1_code":"14",
    "gn:admin2_code":"1401.0",
    "gn:admin3_code":"140118.0",
    "gn:asciiname":"Ventarron",
    "gn:country_code":"PE",
    "gn:dem":59,
    "gn:feature_class":"P",
    "gn:feature_code":"PPL",
    "gn:name":"Ventarr\u00f3n",
    "gn:population":0,
    "gn:timezone":"America/Lima",
    "iso:country":"PE",
    "name:ita_x_preferred":[
        "Ventarr\u00f3n"
    ],
    "name:jpn_x_preferred":[
        "\u30d9\u30f3\u30bf\u30ed\u30f3\u907a\u8de1"
    ],
    "name:spa_x_preferred":[
        "Ventarr\u00f3n"
    ],
    "name:swe_x_preferred":[
        "Ventarron"
    ],
    "name:und_x_variant":[
        "Ventarr\u00f3n"
    ],
    "wof:name":"Ventarron",
    "wof:placetype":"locality"
},
  "geometry": {"coordinates":[-79.75686999999998,-6.80125],"type":"Point"}
}