{
  "type": "Feature",
  "properties": {
    "gn:admin1_code":"04",
    "gn:admin2_code":"404.0",
    "gn:admin3_code":"40408.0",
    "gn:asciiname":"Malapampa",
    "gn:country_code":"PE",
    "gn:dem":3690,
    "gn:feature_class":"P",
    "gn:feature_code":"PPL",
    "gn:name":"Malapampa",
    "gn:population":0,
    "gn:timezone":"America/Lima",
    "iso:country":"PE",
    "wof:name":"Malapampa",
    "wof:placetype":"locality"
},
  "geometry": {"coordinates":[-72.46850000000001,-15.61179],"type":"Point"}
}