{
  "type": "Feature",
  "properties": {
    "gn:admin1_code":"01",
    "gn:admin2_code":"102.0",
    "gn:admin3_code":"10201.0",
    "gn:asciiname":"Brujo Pata",
    "gn:country_code":"PE",
    "gn:dem":810,
    "gn:feature_class":"P",
    "gn:feature_code":"PPL",
    "gn:name":"Brujo Pata",
    "gn:population":0,
    "gn:timezone":"America/Lima",
    "iso:country":"PE",
    "wof:name":"Brujo Pata",
    "wof:placetype":"locality"
},
  "geometry": {"coordinates":[-78.49694000000002,-5.63917],"type":"Point"}
}