{
  "type": "Feature",
  "properties": {
    "gn:admin1_code":"2",
    "gn:admin2_code":"218.0",
    "gn:admin3_code":"21802.0",
    "gn:asciiname":"Castillo",
    "gn:country_code":"PE",
    "gn:dem":3569,
    "gn:feature_class":"P",
    "gn:feature_code":"PPL",
    "gn:name":"Castillo",
    "gn:population":0,
    "gn:timezone":"America/Lima",
    "iso:country":"PE",
    "wof:name":"Castillo",
    "wof:placetype":"locality"
},
  "geometry": {"coordinates":[-78.09028000000001,-8.90306],"type":"Point"}
}