{
  "type": "Feature",
  "properties": {
    "gn:admin1_code":"3",
    "gn:admin2_code":"304.0",
    "gn:admin3_code":"30415.0",
    "gn:asciiname":"Huaillabamba",
    "gn:country_code":"PE",
    "gn:dem":2296,
    "gn:feature_class":"P",
    "gn:feature_code":"PPL",
    "gn:name":"Huaillabamba",
    "gn:population":0,
    "gn:timezone":"America/Lima",
    "iso:country":"PE",
    "wof:name":"Huaillabamba",
    "wof:placetype":"locality"
},
  "geometry": {"coordinates":[-73.15167,-13.96944],"type":"Point"}
}