{
  "type": "Feature",
  "properties": {
    "gn:admin1_code":"05",
    "gn:admin2_code":"507.0",
    "gn:admin3_code":"50705.0",
    "gn:asciiname":"Caseron",
    "gn:country_code":"PE",
    "gn:dem":3050,
    "gn:feature_class":"P",
    "gn:feature_code":"PPL",
    "gn:name":"Caseron",
    "gn:population":0,
    "gn:timezone":"America/Lima",
    "iso:country":"PE",
    "wof:name":"Caseron",
    "wof:placetype":"locality"
},
  "geometry": {"coordinates":[-74.01076,-15.35281],"type":"Point"}
}