{
  "type": "Feature",
  "properties": {
    "gn:admin1_code":"21",
    "gn:admin2_code":"2103",
    "gn:asciiname":"Mullacapaza",
    "gn:country_code":"PE",
    "gn:dem":4110,
    "gn:feature_class":"P",
    "gn:feature_code":"PPL",
    "gn:name":"Mullacapaza",
    "gn:population":0,
    "gn:timezone":"America/Lima",
    "iso:country":"PE",
    "name:spa_x_preferred":[
        "Mullacapaza"
    ],
    "wof:name":"Mullacapaza",
    "wof:placetype":"locality"
},
  "geometry": {"coordinates":[-69.97889000000001,-13.84899],"type":"Point"}
}