{
  "type": "Feature",
  "properties": {
    "gn:admin1_code":"22",
    "gn:admin2_code":"2202.0",
    "gn:admin3_code":"220206.0",
    "gn:asciiname":"Libertad",
    "gn:country_code":"PE",
    "gn:dem":239,
    "gn:feature_class":"P",
    "gn:feature_code":"PPL",
    "gn:name":"Libertad",
    "gn:population":0,
    "gn:timezone":"America/Lima",
    "iso:country":"PE",
    "wof:name":"Libertad",
    "wof:placetype":"locality"
},
  "geometry": {"coordinates":[-76.47381,-7.03667],"type":"Point"}
}