{
  "type": "Feature",
  "properties": {
    "gn:admin1_code":"09",
    "gn:admin2_code":"901.0",
    "gn:admin3_code":"90113.0",
    "gn:asciiname":"Tinyacllo",
    "gn:country_code":"PE",
    "gn:dem":4485,
    "gn:feature_class":"P",
    "gn:feature_code":"PPL",
    "gn:name":"Tinyacllo",
    "gn:population":0,
    "gn:timezone":"America/Lima",
    "iso:country":"PE",
    "wof:name":"Tinyacllo",
    "wof:placetype":"locality"
},
  "geometry": {"coordinates":[-75.09999999999999,-12.63333],"type":"Point"}
}