{
  "type": "Feature",
  "properties": {
    "gn:admin1_code":"22",
    "gn:admin2_code":"2210.0",
    "gn:admin3_code":"221004.0",
    "gn:asciiname":"Cueva Pintada",
    "gn:country_code":"PE",
    "gn:dem":1700,
    "gn:feature_class":"P",
    "gn:feature_code":"PPL",
    "gn:name":"Cueva Pintada",
    "gn:population":0,
    "gn:timezone":"America/Lima",
    "iso:country":"PE",
    "wof:name":"Cueva Pintada",
    "wof:placetype":"locality"
},
  "geometry": {"coordinates":[-76.76666999999998,-8.35],"type":"Point"}
}