{
  "type": "Feature",
  "properties": {
    "gn:admin1_code":"21.0",
    "gn:admin2_code":"2105.0",
    "gn:admin3_code":"210504.0",
    "gn:asciiname":"Vinto",
    "gn:country_code":"PE",
    "gn:dem":4540,
    "gn:feature_class":"P",
    "gn:feature_code":"PPL",
    "gn:name":"Vinto",
    "gn:population":0,
    "gn:timezone":"America/Lima",
    "iso:country":"PE",
    "wof:name":"Vinto",
    "wof:placetype":"locality"
},
  "geometry": {"coordinates":[-69.90486999999999,-17.06264],"type":"Point"}
}