{
  "type": "Feature",
  "properties": {
    "gn:admin1_code":"10.0",
    "gn:admin2_code":"1001.0",
    "gn:admin3_code":"100109.0",
    "gn:asciiname":"Ampatay",
    "gn:country_code":"PE",
    "gn:dem":2923,
    "gn:feature_class":"P",
    "gn:feature_code":"PPL",
    "gn:name":"Ampatay",
    "gn:population":0,
    "gn:timezone":"America/Lima",
    "iso:country":"PE",
    "wof:name":"Ampatay",
    "wof:placetype":"locality"
},
  "geometry": {"coordinates":[-76.27559000000002,-9.80056],"type":"Point"}
}