{
  "type": "Feature",
  "properties": {
    "gn:admin1_code":"22",
    "gn:admin2_code":"2202.0",
    "gn:admin3_code":"220203.0",
    "gn:asciiname":"El Sol",
    "gn:country_code":"PE",
    "gn:dem":240,
    "gn:feature_class":"P",
    "gn:feature_code":"PPL",
    "gn:name":"El Sol",
    "gn:population":0,
    "gn:timezone":"America/Lima",
    "iso:country":"PE",
    "wof:name":"El Sol",
    "wof:placetype":"locality"
},
  "geometry": {"coordinates":[-76.43119,-7.04876],"type":"Point"}
}