{
  "type": "Feature",
  "properties": {
    "gn:admin1_code":"22.0",
    "gn:admin2_code":"2203.0",
    "gn:admin3_code":"220301.0",
    "gn:asciiname":"Huascasapa",
    "gn:country_code":"PE",
    "gn:dem":403,
    "gn:feature_class":"P",
    "gn:feature_code":"PPL",
    "gn:name":"Huascasapa",
    "gn:population":0,
    "gn:timezone":"America/Lima",
    "iso:country":"PE",
    "name:spa_x_preferred":[
        "Huascasapa"
    ],
    "wof:name":"Huascasapa",
    "wof:placetype":"locality"
},
  "geometry": {"coordinates":[-76.73421,-6.65536],"type":"Point"}
}