{
  "type": "Feature",
  "properties": {
    "gn:admin1_code":"16.0",
    "gn:admin2_code":"1604.0",
    "gn:admin3_code":"160402.0",
    "gn:asciiname":"San Juan",
    "gn:country_code":"PE",
    "gn:dem":93,
    "gn:feature_class":"P",
    "gn:feature_code":"PPLL",
    "gn:name":"San Juan",
    "gn:population":0,
    "gn:timezone":"America/Lima",
    "iso:country":"PE",
    "wof:name":"San Juan",
    "wof:placetype":"locality"
},
  "geometry": {"coordinates":[-72.07304000000001,-3.50349],"type":"Point"}
}