{
  "type": "Feature",
  "properties": {
    "gn:admin1_code":"08",
    "gn:admin2_code":"807.0",
    "gn:admin3_code":"80704.0",
    "gn:asciiname":"Jaccara",
    "gn:cc2":"PE",
    "gn:country_code":"PE",
    "gn:dem":3652,
    "gn:feature_class":"P",
    "gn:feature_code":"PPL",
    "gn:name":"Jaccara",
    "gn:population":0,
    "gn:timezone":"America/Lima",
    "iso:country":"PE",
    "name:und_x_variant":[
        "Jaccara Hacienda",
        "Jaccara"
    ],
    "wof:name":"Jaccara",
    "wof:placetype":"locality"
},
  "geometry": {"coordinates":[-72.05,-14.21667],"type":"Point"}
}