{
  "type": "Feature",
  "properties": {
    "gn:admin1_code":"09",
    "gn:admin2_code":"907.0",
    "gn:admin3_code":"90711.0",
    "gn:asciiname":"Mullaca",
    "gn:country_code":"PE",
    "gn:dem":3899,
    "gn:feature_class":"P",
    "gn:feature_code":"PPL",
    "gn:name":"Mullaca",
    "gn:population":0,
    "gn:timezone":"America/Lima",
    "iso:country":"PE",
    "wof:name":"Mullaca",
    "wof:placetype":"locality"
},
  "geometry": {"coordinates":[-75.02752,-12.29845],"type":"Point"}
}