{
  "type": "Feature",
  "properties": {
    "gn:admin1_code":"05",
    "gn:admin2_code":"506.0",
    "gn:admin3_code":"50606.0",
    "gn:asciiname":"Negro Mayo",
    "gn:country_code":"PE",
    "gn:dem":4464,
    "gn:feature_class":"P",
    "gn:feature_code":"PPL",
    "gn:name":"Negro Mayo",
    "gn:population":0,
    "gn:timezone":"America/Lima",
    "iso:country":"PE",
    "wof:name":"Negro Mayo",
    "wof:placetype":"locality"
},
  "geometry": {"coordinates":[-73.75379000000002,-14.64127],"type":"Point"}
}