{
  "type": "Feature",
  "properties": {
    "gn:admin1_code":"19",
    "gn:admin2_code":"1903.0",
    "gn:admin3_code":"190304.0",
    "gn:asciiname":"San Francisco de Pichanaz",
    "gn:country_code":"PE",
    "gn:dem":439,
    "gn:feature_class":"P",
    "gn:feature_code":"PPL",
    "gn:name":"San Francisco de Pichanaz",
    "gn:population":0,
    "gn:timezone":"America/Lima",
    "iso:country":"PE",
    "wof:name":"San Francisco de Pichanaz",
    "wof:placetype":"locality"
},
  "geometry": {"coordinates":[-75.05528000000002,-10.44694],"type":"Point"}
}