{
  "type": "Feature",
  "properties": {
    "gn:admin1_code":"12.0",
    "gn:admin2_code":"1206.0",
    "gn:asciiname":"Quempiri",
    "gn:country_code":"PE",
    "gn:dem":424,
    "gn:feature_class":"P",
    "gn:feature_code":"PPL",
    "gn:name":"Quempiri",
    "gn:population":0,
    "gn:timezone":"America/Lima",
    "iso:country":"PE",
    "name:spa_x_preferred":[
        "Quempiri"
    ],
    "wof:name":"Quempiri",
    "wof:placetype":"locality"
},
  "geometry": {"coordinates":[-74.03544000000002,-12.04764],"type":"Point"}
}