{
  "type": "Feature",
  "properties": {
    "gn:admin1_code":"01",
    "gn:admin2_code":"105.0",
    "gn:admin3_code":"10503.0",
    "gn:asciiname":"Ashquita",
    "gn:country_code":"PE",
    "gn:dem":2430,
    "gn:feature_class":"P",
    "gn:feature_code":"PPL",
    "gn:name":"Ashquita",
    "gn:population":0,
    "gn:timezone":"America/Lima",
    "iso:country":"PE",
    "wof:name":"Ashquita",
    "wof:placetype":"locality"
},
  "geometry": {"coordinates":[-78.05,-6.61667],"type":"Point"}
}