{
  "type": "Feature",
  "properties": {
    "gn:admin1_code":"3",
    "gn:admin2_code":"304.0",
    "gn:admin3_code":"30415.0",
    "gn:asciiname":"Huayhuar Orcculla",
    "gn:country_code":"PE",
    "gn:dem":2564,
    "gn:feature_class":"P",
    "gn:feature_code":"PPL",
    "gn:name":"Huayhuar Orcculla",
    "gn:population":0,
    "gn:timezone":"America/Lima",
    "iso:country":"PE",
    "wof:name":"Huayhuar Orcculla",
    "wof:placetype":"locality"
},
  "geometry": {"coordinates":[-73.18861,-13.97306],"type":"Point"}
}