{
  "type": "Feature",
  "properties": {
    "gn:admin1_code":"23",
    "gn:admin2_code":"2304.0",
    "gn:admin3_code":"230401.0",
    "gn:asciiname":"Puralla",
    "gn:country_code":"PE",
    "gn:dem":4333,
    "gn:feature_class":"P",
    "gn:feature_code":"PPL",
    "gn:name":"Puralla",
    "gn:population":0,
    "gn:timezone":"America/Lima",
    "iso:country":"PE",
    "wof:name":"Puralla",
    "wof:placetype":"locality"
},
  "geometry": {"coordinates":[-69.66249999999999,-17.34444],"type":"Point"}
}