{
  "type": "Feature",
  "properties": {
    "gn:admin1_code":"11",
    "gn:admin2_code":"1104.0",
    "gn:asciiname":"Alto Laran",
    "gn:country_code":"PE",
    "gn:dem":604,
    "gn:feature_class":"P",
    "gn:feature_code":"PPL",
    "gn:name":"Alto Laran",
    "gn:population":0,
    "gn:timezone":"America/Lima",
    "iso:country":"PE",
    "wof:name":"Alto Laran",
    "wof:placetype":"locality"
},
  "geometry": {"coordinates":[-75.24247,-14.46401],"type":"Point"}
}