{
  "type": "Feature",
  "properties": {
    "gn:admin1_code":"21",
    "gn:admin2_code":"2110.0",
    "gn:admin3_code":"211001.0",
    "gn:asciiname":"Huayrapata",
    "gn:country_code":"PE",
    "gn:dem":4340,
    "gn:feature_class":"P",
    "gn:feature_code":"PPL",
    "gn:name":"Huayrapata",
    "gn:population":0,
    "gn:timezone":"America/Lima",
    "iso:country":"PE",
    "wof:name":"Huayrapata",
    "wof:placetype":"locality"
},
  "geometry": {"coordinates":[-69.94605,-14.49234],"type":"Point"}
}