{
  "type": "Feature",
  "properties": {
    "gn:admin1_code":"21",
    "gn:admin2_code":"2101.0",
    "gn:admin3_code":"210109.0",
    "gn:asciiname":"Chupapampa",
    "gn:country_code":"PE",
    "gn:dem":4294,
    "gn:feature_class":"P",
    "gn:feature_code":"PPL",
    "gn:name":"Chupapampa",
    "gn:population":0,
    "gn:timezone":"America/Lima",
    "iso:country":"PE",
    "wof:name":"Chupapampa",
    "wof:placetype":"locality"
},
  "geometry": {"coordinates":[-70.37006,-15.87081],"type":"Point"}
}