{
  "type": "Feature",
  "properties": {
    "gn:admin1_code":"3",
    "gn:admin2_code":"304.0",
    "gn:admin3_code":"30404.0",
    "gn:asciiname":"Ancobamba",
    "gn:country_code":"PE",
    "gn:dem":3596,
    "gn:feature_class":"P",
    "gn:feature_code":"PPL",
    "gn:name":"Ancobamba",
    "gn:population":0,
    "gn:timezone":"America/Lima",
    "iso:country":"PE",
    "wof:name":"Ancobamba",
    "wof:placetype":"locality"
},
  "geometry": {"coordinates":[-73.10081,-14.0354],"type":"Point"}
}