{
  "type": "Feature",
  "properties": {
    "gn:admin1_code":"15",
    "gn:admin2_code":"1510.0",
    "gn:admin3_code":"151029.0",
    "gn:asciiname":"Calipampa",
    "gn:country_code":"PE",
    "gn:dem":2818,
    "gn:feature_class":"P",
    "gn:feature_code":"PPL",
    "gn:name":"Calipampa",
    "gn:population":0,
    "gn:timezone":"America/Lima",
    "iso:country":"PE",
    "wof:name":"Calipampa",
    "wof:placetype":"locality"
},
  "geometry": {"coordinates":[-76.21269000000002,-12.61975],"type":"Point"}
}