{
  "type": "Feature",
  "properties": {
    "gn:admin1_code":"20",
    "gn:admin2_code":"2006.0",
    "gn:admin3_code":"200605.0",
    "gn:asciiname":"Algodonal",
    "gn:country_code":"PE",
    "gn:dem":397,
    "gn:feature_class":"P",
    "gn:feature_code":"PPL",
    "gn:name":"Algodonal",
    "gn:population":0,
    "gn:timezone":"America/Lima",
    "iso:country":"PE",
    "name:spa_x_preferred":[
        "Algodonal"
    ],
    "wof:name":"Algodonal",
    "wof:placetype":"locality"
},
  "geometry": {"coordinates":[-80.7814,-4.52491],"type":"Point"}
}