{
  "type": "Feature",
  "properties": {
    "gn:admin1_code":"08",
    "gn:admin2_code":"813.0",
    "gn:admin3_code":"81306.0",
    "gn:asciiname":"Tanca",
    "gn:country_code":"PE",
    "gn:dem":2782,
    "gn:feature_class":"P",
    "gn:feature_code":"PPL",
    "gn:name":"Tanca",
    "gn:population":0,
    "gn:timezone":"America/Lima",
    "iso:country":"PE",
    "name:por_x_preferred":[
        "Santa Tanca"
    ],
    "name:und_x_variant":[
        "Tanca Hacienda",
        "Tanca"
    ],
    "wof:name":"Tanca",
    "wof:placetype":"locality"
},
  "geometry": {"coordinates":[-72.3065,-13.22653],"type":"Point"}
}