{
  "type": "Feature",
  "properties": {
    "gn:admin1_code":"1.0",
    "gn:admin2_code":"101.0",
    "gn:admin3_code":"10101.0",
    "gn:asciiname":"Pucacruz",
    "gn:country_code":"PE",
    "gn:dem":2233,
    "gn:feature_class":"P",
    "gn:feature_code":"PPL",
    "gn:name":"Pucacruz",
    "gn:population":0,
    "gn:timezone":"America/Lima",
    "iso:country":"PE",
    "wof:name":"Pucacruz",
    "wof:placetype":"locality"
},
  "geometry": {"coordinates":[-77.87945000000001,-6.24623],"type":"Point"}
}