{
  "type": "Feature",
  "properties": {
    "gn:admin1_code":"20",
    "gn:admin2_code":"2006.0",
    "gn:admin3_code":"200605.0",
    "gn:asciiname":"Nariz del Diablo",
    "gn:country_code":"PE",
    "gn:dem":140,
    "gn:feature_class":"P",
    "gn:feature_code":"PPL",
    "gn:name":"Nariz del Diablo",
    "gn:population":0,
    "gn:timezone":"America/Lima",
    "iso:country":"PE",
    "wof:name":"Nariz del Diablo",
    "wof:placetype":"locality"
},
  "geometry": {"coordinates":[-80.86639,-4.19222],"type":"Point"}
}