{
  "type": "Feature",
  "properties": {
    "gn:admin1_code":"05",
    "gn:admin2_code":"507.0",
    "gn:admin3_code":"50701.0",
    "gn:asciiname":"Quinuane",
    "gn:country_code":"PE",
    "gn:dem":3555,
    "gn:feature_class":"P",
    "gn:feature_code":"PPL",
    "gn:name":"Qui\u00f1ua\u00f1e",
    "gn:population":0,
    "gn:timezone":"America/Lima",
    "iso:country":"PE",
    "name:spa_x_preferred":[
        "Qui\u00f1ua\u00f1e"
    ],
    "wof:name":"Quinuane",
    "wof:placetype":"locality"
},
  "geometry": {"coordinates":[-73.75124,-15.02485],"type":"Point"}
}