{
  "type": "Feature",
  "properties": {
    "gn:admin1_code":"23",
    "gn:admin2_code":"2302.0",
    "gn:admin3_code":"230201.0",
    "gn:asciiname":"Aranane",
    "gn:country_code":"PE",
    "gn:dem":4028,
    "gn:feature_class":"P",
    "gn:feature_code":"PPL",
    "gn:name":"Ara\u00f1ane",
    "gn:population":0,
    "gn:timezone":"America/Lima",
    "iso:country":"PE",
    "wof:name":"Aranane",
    "wof:placetype":"locality"
},
  "geometry": {"coordinates":[-70.28979,-17.1529],"type":"Point"}
}