{
  "type": "Feature",
  "properties": {
    "gn:admin1_code":"8",
    "gn:admin2_code":"806.0",
    "gn:admin3_code":"80607.0",
    "gn:asciiname":"Chaupi",
    "gn:country_code":"PE",
    "gn:dem":3689,
    "gn:feature_class":"P",
    "gn:feature_code":"PPL",
    "gn:name":"Chaupi",
    "gn:population":0,
    "gn:timezone":"America/Lima",
    "iso:country":"PE",
    "wof:name":"Chaupi",
    "wof:placetype":"locality"
},
  "geometry": {"coordinates":[-71.32724,-14.15906],"type":"Point"}
}