{
  "type": "Feature",
  "properties": {
    "gn:admin1_code":"16",
    "gn:admin2_code":"1605.0",
    "gn:admin3_code":"160511.0",
    "gn:asciiname":"Colonia Angamos",
    "gn:country_code":"PE",
    "gn:dem":105,
    "gn:feature_class":"P",
    "gn:feature_code":"PPL",
    "gn:name":"Colonia Angamos",
    "gn:population":0,
    "gn:timezone":"America/Lima",
    "iso:country":"PE",
    "wof:name":"Colonia Angamos",
    "wof:placetype":"locality"
},
  "geometry": {"coordinates":[-72.87524000000001,-5.14949],"type":"Point"}
}