{
  "type": "Feature",
  "properties": {
    "gn:admin1_code":"9.0",
    "gn:admin2_code":"905.0",
    "gn:admin3_code":"90502.0",
    "gn:asciiname":"Accoera",
    "gn:country_code":"PE",
    "gn:dem":3387,
    "gn:feature_class":"P",
    "gn:feature_code":"PPL",
    "gn:name":"Accoera",
    "gn:population":0,
    "gn:timezone":"America/Lima",
    "iso:country":"PE",
    "wof:name":"Accoera",
    "wof:placetype":"locality"
},
  "geometry": {"coordinates":[-74.64131999999999,-12.57977],"type":"Point"}
}