{
  "type": "Feature",
  "properties": {
    "gn:admin1_code":"11",
    "gn:admin2_code":"1103.0",
    "gn:admin3_code":"110302.0",
    "gn:asciiname":"Changuillo",
    "gn:cc2":"PE",
    "gn:country_code":"PE",
    "gn:dem":248,
    "gn:feature_class":"P",
    "gn:feature_code":"PPLA3",
    "gn:name":"Changuillo",
    "gn:population":0,
    "gn:timezone":"America/Lima",
    "iso:country":"PE",
    "name:und_x_variant":[
        "Chaguillo",
        "Shanguillo",
        "San Juan de Changuillo",
        "Changuillo"
    ],
    "wof:name":"Changuillo",
    "wof:placetype":"locality"
},
  "geometry": {"coordinates":[-75.22333,-14.66417],"type":"Point"}
}