{
  "type": "Feature",
  "properties": {
    "gn:admin1_code":"15",
    "gn:admin2_code":"1506.0",
    "gn:admin3_code":"150604.0",
    "gn:asciiname":"Banos Boza",
    "gn:country_code":"PE",
    "gn:dem":116,
    "gn:feature_class":"P",
    "gn:feature_code":"PPL",
    "gn:name":"Ba\u00f1os Boza",
    "gn:population":0,
    "gn:timezone":"America/Lima",
    "iso:country":"PE",
    "wof:name":"Banos Boza",
    "wof:placetype":"locality"
},
  "geometry": {"coordinates":[-77.17610999999999,-11.59056],"type":"Point"}
}