{
  "type": "Feature",
  "properties": {
    "gn:admin1_code":"12",
    "gn:admin2_code":"1206.0",
    "gn:admin3_code":"120607.0",
    "gn:asciiname":"Huahuari",
    "gn:country_code":"PE",
    "gn:dem":846,
    "gn:feature_class":"P",
    "gn:feature_code":"PPL",
    "gn:name":"Huahuari",
    "gn:population":0,
    "gn:timezone":"America/Lima",
    "iso:country":"PE",
    "wof:name":"Huahuari",
    "wof:placetype":"locality"
},
  "geometry": {"coordinates":[-74.8205,-11.13823],"type":"Point"}
}