{
  "type": "Feature",
  "properties": {
    "gn:admin1_code":"04",
    "gn:admin2_code":"407.0",
    "gn:admin3_code":"40702.0",
    "gn:asciiname":"El Canto",
    "gn:cc2":"PE",
    "gn:country_code":"PE",
    "gn:dem":62,
    "gn:feature_class":"P",
    "gn:feature_code":"PPL",
    "gn:name":"El Canto",
    "gn:population":0,
    "gn:timezone":"America/Lima",
    "iso:country":"PE",
    "name:und_x_variant":[
        "Canto Hacienda",
        "El Canto"
    ],
    "wof:name":"El Canto",
    "wof:placetype":"locality"
},
  "geometry": {"coordinates":[-71.77472,-17.09944],"type":"Point"}
}