{
  "type": "Feature",
  "properties": {
    "iso:country":"PE",
    "name:ceb_x_preferred":[
        "Desaguadero"
    ],
    "name:ces_x_preferred":[
        "Desaguadero"
    ],
    "name:deu_x_preferred":[
        "Desaguadero"
    ],
    "name:eng_x_preferred":[
        "Desaguadero"
    ],
    "name:fra_x_preferred":[
        "Desaguadero"
    ],
    "name:hrv_x_preferred":[
        "Desaguadero"
    ],
    "name:ita_x_preferred":[
        "Desaguadero"
    ],
    "name:lit_x_preferred":[
        "Desaguaderas"
    ],
    "name:nld_x_preferred":[
        "Desaguadero"
    ],
    "name:pol_x_preferred":[
        "Desaguadero"
    ],
    "name:por_x_preferred":[
        "Desaguadero"
    ],
    "name:rus_x_preferred":[
        "\u0414\u0435\u0441\u0430\u0433\u0443\u0430\u0434\u0435\u0440\u043e"
    ],
    "name:spa_x_preferred":[
        "Desaguadero"
    ],
    "name:swe_x_preferred":[
        "Desaguadero"
    ],
    "name:ukr_x_preferred":[
        "\u0414\u0435\u0441\u0430\u0491\u0443\u0430\u0434\u0435\u0440\u043e"
    ],
    "qs:gn_pop":0,
    "qs:name":"Desaguadero",
    "qs:name_adm0":"Per\u00fa",
    "qs:name_adm1":"Puno",
    "qs:photos":3,
    "qs:photos_1k":1,
    "qs:photos_9k":1,
    "qs:photos_9r":1,
    "qs:photos_all":3,
    "qs:photos_sr":1,
    "qs:placetype":"Town",
    "qs:pop_sr":"0",
    "qs:woe_adm0":23424919,
    "wd:wordcount":41,
    "wof:name":"Desaguadero",
    "wof:placetype":"locality"
},
  "geometry": {"coordinates":[-69.14604,-16.577659],"type":"Point"}
}