{
  "type": "Feature",
  "properties": {
    "gn:admin1_code":"5.0",
    "gn:admin2_code":"504.0",
    "gn:admin3_code":"50405.0",
    "gn:asciiname":"Pachapunya",
    "gn:country_code":"PE",
    "gn:dem":3721,
    "gn:feature_class":"P",
    "gn:feature_code":"PPL",
    "gn:name":"Pachapunya",
    "gn:population":0,
    "gn:timezone":"America/Lima",
    "iso:country":"PE",
    "wof:name":"Pachapunya",
    "wof:placetype":"locality"
},
  "geometry": {"coordinates":[-74.24743000000002,-12.87829],"type":"Point"}
}