{
  "type": "Feature",
  "properties": {
    "gn:admin1_code":"15",
    "gn:admin2_code":"1506.0",
    "gn:admin3_code":"150601.0",
    "gn:asciiname":"San Francisco",
    "gn:country_code":"PE",
    "gn:dem":139,
    "gn:feature_class":"P",
    "gn:feature_code":"PPL",
    "gn:name":"San Francisco",
    "gn:population":0,
    "gn:timezone":"America/Lima",
    "iso:country":"PE",
    "wof:name":"San Francisco",
    "wof:placetype":"locality"
},
  "geometry": {"coordinates":[-77.22778000000002,-11.52222],"type":"Point"}
}