{
  "type": "Feature",
  "properties": {
    "gn:admin1_code":"01",
    "gn:admin2_code":"107.0",
    "gn:admin3_code":"10702.0",
    "gn:asciiname":"Naranjos Alto",
    "gn:country_code":"PE",
    "gn:dem":640,
    "gn:feature_class":"P",
    "gn:feature_code":"PPL",
    "gn:name":"Naranjos Alto",
    "gn:population":0,
    "gn:timezone":"America/Lima",
    "iso:country":"PE",
    "wof:name":"Naranjos Alto",
    "wof:placetype":"locality"
},
  "geometry": {"coordinates":[-78.37272,-5.74278],"type":"Point"}
}