{
  "type": "Feature",
  "properties": {
    "gn:admin1_code":"1.0",
    "gn:admin2_code":"107.0",
    "gn:admin3_code":"10701.0",
    "gn:asciiname":"Playa Grande",
    "gn:country_code":"PE",
    "gn:dem":2399,
    "gn:feature_class":"P",
    "gn:feature_code":"PPL",
    "gn:name":"Playa Grande",
    "gn:population":0,
    "gn:timezone":"America/Lima",
    "iso:country":"PE",
    "name:ceb_x_preferred":[
        "Playa Grande"
    ],
    "name:fra_x_preferred":[
        "Playa Grande"
    ],
    "name:spa_x_preferred":[
        "Playa Grande"
    ],
    "name:swe_x_preferred":[
        "Playa Grande"
    ],
    "wof:name":"Playa Grande",
    "wof:placetype":"locality"
},
  "geometry": {"coordinates":[-78.35084000000001,-5.94203],"type":"Point"}
}