{
  "type": "Feature",
  "properties": {
    "gn:admin1_code":"11",
    "gn:admin2_code":"1105.0",
    "gn:admin3_code":"110502.0",
    "gn:asciiname":"Veladero Chico",
    "gn:country_code":"PE",
    "gn:dem":1082,
    "gn:feature_class":"P",
    "gn:feature_code":"PPL",
    "gn:name":"Veladero Chico",
    "gn:population":0,
    "gn:timezone":"America/Lima",
    "iso:country":"PE",
    "wof:name":"Veladero Chico",
    "wof:placetype":"locality"
},
  "geometry": {"coordinates":[-75.71666999999999,-13.61667],"type":"Point"}
}