{
  "type": "Feature",
  "properties": {
    "gn:admin1_code":"21",
    "gn:admin2_code":"2102.0",
    "gn:admin3_code":"210209.0",
    "gn:asciiname":"Totorojollo",
    "gn:country_code":"PE",
    "gn:dem":4306,
    "gn:feature_class":"P",
    "gn:feature_code":"PPL",
    "gn:name":"Totorojollo",
    "gn:population":0,
    "gn:timezone":"America/Lima",
    "iso:country":"PE",
    "wof:name":"Totorojollo",
    "wof:placetype":"locality"
},
  "geometry": {"coordinates":[-69.97105000000001,-14.46319],"type":"Point"}
}