{
  "type": "Feature",
  "properties": {
    "gn:admin1_code":"12.0",
    "gn:admin2_code":"1206.0",
    "gn:admin3_code":"120608.0",
    "gn:asciiname":"Anapati",
    "gn:country_code":"PE",
    "gn:dem":273,
    "gn:feature_class":"P",
    "gn:feature_code":"PPL",
    "gn:name":"Anapati",
    "gn:population":0,
    "gn:timezone":"America/Lima",
    "iso:country":"PE",
    "name:spa_x_preferred":[
        "Anapati"
    ],
    "wof:name":"Anapati",
    "wof:placetype":"locality"
},
  "geometry": {"coordinates":[-73.7786,-11.27949],"type":"Point"}
}