{
  "type": "Feature",
  "properties": {
    "gn:admin1_code":"4",
    "gn:admin2_code":"405.0",
    "gn:admin3_code":"40504.0",
    "gn:asciiname":"Taralla",
    "gn:country_code":"PE",
    "gn:dem":4521,
    "gn:feature_class":"P",
    "gn:feature_code":"PPL",
    "gn:name":"Taralla",
    "gn:population":0,
    "gn:timezone":"America/Lima",
    "iso:country":"PE",
    "wof:name":"Taralla",
    "wof:placetype":"locality"
},
  "geometry": {"coordinates":[-71.01948,-15.55202],"type":"Point"}
}