{
  "type": "Feature",
  "properties": {
    "gn:admin1_code":"20",
    "gn:admin2_code":"2001.0",
    "gn:admin3_code":"200104.0",
    "gn:asciiname":"Las Monteros",
    "gn:country_code":"PE",
    "gn:dem":30,
    "gn:feature_class":"P",
    "gn:feature_code":"PPL",
    "gn:name":"Las Monteros",
    "gn:population":0,
    "gn:timezone":"America/Lima",
    "iso:country":"PE",
    "wof:name":"Las Monteros",
    "wof:placetype":"locality"
},
  "geometry": {"coordinates":[-80.61667,-5.21667],"type":"Point"}
}