{
  "type": "Feature",
  "properties": {
    "gn:admin1_code":"15",
    "gn:admin2_code":"1505.0",
    "gn:asciiname":"Corralones",
    "gn:country_code":"PE",
    "gn:dem":794,
    "gn:feature_class":"P",
    "gn:feature_code":"PPL",
    "gn:name":"Corralones",
    "gn:population":0,
    "gn:timezone":"America/Lima",
    "iso:country":"PE",
    "wof:name":"Corralones",
    "wof:placetype":"locality"
},
  "geometry": {"coordinates":[-76.11131,-13.1601],"type":"Point"}
}