{
  "type": "Feature",
  "properties": {
    "gn:admin1_code":"20",
    "gn:admin2_code":"2001.0",
    "gn:admin3_code":"200101.0",
    "gn:asciiname":"Cieneguillo Central",
    "gn:country_code":"PE",
    "gn:dem":79,
    "gn:feature_class":"P",
    "gn:feature_code":"PPL",
    "gn:name":"Cieneguillo Central",
    "gn:population":0,
    "gn:timezone":"America/Lima",
    "iso:country":"PE",
    "wof:name":"Cieneguillo Central",
    "wof:placetype":"locality"
},
  "geometry": {"coordinates":[-80.63760000000001,-4.95149],"type":"Point"}
}