{
  "type": "Feature",
  "properties": {
    "gn:admin1_code":"14",
    "gn:admin2_code":"1403.0",
    "gn:admin3_code":"140302.0",
    "gn:asciiname":"Espinal",
    "gn:country_code":"PE",
    "gn:dem":324,
    "gn:feature_class":"P",
    "gn:feature_code":"PPL",
    "gn:name":"Espinal",
    "gn:population":0,
    "gn:timezone":"America/Lima",
    "iso:country":"PE",
    "name:ceb_x_preferred":[
        "Espinal"
    ],
    "name:deu_x_preferred":[
        "Espinal"
    ],
    "name:fra_x_preferred":[
        "Espinal"
    ],
    "name:mlg_x_preferred":[
        "Espinal"
    ],
    "name:rus_x_preferred":[
        "\u042d\u0441\u043f\u0438\u043d\u0430\u043b\u044c"
    ],
    "name:sco_x_preferred":[
        "Espinal"
    ],
    "name:spa_x_preferred":[
        "Espinal"
    ],
    "name:srp_x_preferred":[
        "\u0415\u0441\u043f\u0438\u043d\u0430\u043b"
    ],
    "name:swe_x_preferred":[
        "Espinal"
    ],
    "wof:name":"Espinal",
    "wof:placetype":"locality"
},
  "geometry": {"coordinates":[-79.60911999999998,-6.16047],"type":"Point"}
}