{
  "type": "Feature",
  "properties": {
    "gn:admin1_code":"4",
    "gn:admin2_code":"406.0",
    "gn:admin3_code":"40601.0",
    "gn:asciiname":"Acocra",
    "gn:country_code":"PE",
    "gn:dem":3007,
    "gn:feature_class":"P",
    "gn:feature_code":"PPL",
    "gn:name":"Acocra",
    "gn:population":0,
    "gn:timezone":"America/Lima",
    "iso:country":"PE",
    "wof:name":"Acocra",
    "wof:placetype":"locality"
},
  "geometry": {"coordinates":[-72.65753000000002,-15.82088],"type":"Point"}
}