{
  "type": "Feature",
  "properties": {
    "gn:admin1_code":"9.0",
    "gn:admin2_code":"903.0",
    "gn:admin3_code":"90304.0",
    "gn:asciiname":"Mimosa",
    "gn:country_code":"PE",
    "gn:dem":4280,
    "gn:feature_class":"P",
    "gn:feature_code":"PPL",
    "gn:name":"Mimosa",
    "gn:population":0,
    "gn:timezone":"America/Lima",
    "iso:country":"PE",
    "wof:name":"Mimosa",
    "wof:placetype":"locality"
},
  "geometry": {"coordinates":[-74.8077,-12.92094],"type":"Point"}
}