{
  "type": "Feature",
  "properties": {
    "gn:admin1_code":"12.0",
    "gn:admin2_code":"1204.0",
    "gn:admin3_code":"120406.0",
    "gn:asciiname":"Pique",
    "gn:country_code":"PE",
    "gn:dem":3468,
    "gn:feature_class":"P",
    "gn:feature_code":"PPL",
    "gn:name":"Pique",
    "gn:population":0,
    "gn:timezone":"America/Lima",
    "iso:country":"PE",
    "name:ceb_x_preferred":[
        "Pique"
    ],
    "name:fra_x_preferred":[
        "Pique"
    ],
    "name:spa_x_preferred":[
        "Pique"
    ],
    "name:swe_x_preferred":[
        "Pique"
    ],
    "name:ukr_x_preferred":[
        "\u041f\u0456\u043a\u0435"
    ],
    "wof:name":"Pique",
    "wof:placetype":"locality"
},
  "geometry": {"coordinates":[-75.6288,-11.8152],"type":"Point"}
}