{
  "type": "Feature",
  "properties": {
    "gn:admin1_code":"25",
    "gn:admin2_code":"2502.0",
    "gn:admin3_code":"250203.0",
    "gn:asciiname":"Puntijao",
    "gn:country_code":"PE",
    "gn:dem":186,
    "gn:feature_class":"P",
    "gn:feature_code":"PPL",
    "gn:name":"Puntijao",
    "gn:population":0,
    "gn:timezone":"America/Lima",
    "iso:country":"PE",
    "wof:name":"Puntijao",
    "wof:placetype":"locality"
},
  "geometry": {"coordinates":[-74.04444000000002,-10.30944],"type":"Point"}
}