{
  "type": "Feature",
  "properties": {
    "gn:admin1_code":"2.0",
    "gn:admin2_code":"214.0",
    "gn:admin3_code":"21403.0",
    "gn:asciiname":"Pampas",
    "gn:country_code":"PE",
    "gn:dem":3374,
    "gn:feature_class":"P",
    "gn:feature_code":"PPL",
    "gn:name":"Pampas",
    "gn:population":0,
    "gn:timezone":"America/Lima",
    "iso:country":"PE",
    "wof:name":"Pampas",
    "wof:placetype":"locality"
},
  "geometry": {"coordinates":[-77.19294000000002,-10.36102],"type":"Point"}
}