{
  "type": "Feature",
  "properties": {
    "gn:admin1_code":"04",
    "gn:admin2_code":"406.0",
    "gn:admin3_code":"40601.0",
    "gn:asciiname":"Sullunja",
    "gn:country_code":"PE",
    "gn:dem":3839,
    "gn:feature_class":"P",
    "gn:feature_code":"PPL",
    "gn:name":"Sullunja",
    "gn:population":0,
    "gn:timezone":"America/Lima",
    "iso:country":"PE",
    "wof:name":"Sullunja",
    "wof:placetype":"locality"
},
  "geometry": {"coordinates":[-72.67263,-15.73405],"type":"Point"}
}