{
  "type": "Feature",
  "properties": {
    "gn:admin1_code":"15.0",
    "gn:admin2_code":"1503.0",
    "gn:admin3_code":"150301.0",
    "gn:asciiname":"Huamanaca",
    "gn:country_code":"PE",
    "gn:dem":3560,
    "gn:feature_class":"P",
    "gn:feature_code":"PPL",
    "gn:name":"Huamanaca",
    "gn:population":0,
    "gn:timezone":"America/Lima",
    "iso:country":"PE",
    "wof:name":"Huamanaca",
    "wof:placetype":"locality"
},
  "geometry": {"coordinates":[-77.01555,-10.47704],"type":"Point"}
}