{
  "type": "Feature",
  "properties": {
    "gn:admin1_code":"01",
    "gn:admin2_code":"102.0",
    "gn:admin3_code":"10205.0",
    "gn:asciiname":"Puerto Pacuy",
    "gn:country_code":"PE",
    "gn:dem":304,
    "gn:feature_class":"P",
    "gn:feature_code":"PPL",
    "gn:name":"Puerto Pacuy",
    "gn:population":0,
    "gn:timezone":"America/Lima",
    "iso:country":"PE",
    "wof:name":"Puerto Pacuy",
    "wof:placetype":"locality"
},
  "geometry": {"coordinates":[-78.28827,-5.19949],"type":"Point"}
}