{
  "type": "Feature",
  "properties": {
    "gn:admin1_code":"05",
    "gn:admin2_code":"507.0",
    "gn:admin3_code":"50701.0",
    "gn:asciiname":"Tablacruz",
    "gn:country_code":"PE",
    "gn:dem":4297,
    "gn:feature_class":"P",
    "gn:feature_code":"PPL",
    "gn:name":"Tablacruz",
    "gn:population":0,
    "gn:timezone":"America/Lima",
    "iso:country":"PE",
    "wof:name":"Tablacruz",
    "wof:placetype":"locality"
},
  "geometry": {"coordinates":[-73.73333000000002,-14.88333],"type":"Point"}
}