{
  "type": "Feature",
  "properties": {
    "gn:admin1_code":"04",
    "gn:admin2_code":"402.0",
    "gn:admin3_code":"40207.0",
    "gn:asciiname":"Huata",
    "gn:country_code":"PE",
    "gn:dem":41,
    "gn:feature_class":"P",
    "gn:feature_code":"PPL",
    "gn:name":"Huata",
    "gn:population":0,
    "gn:timezone":"America/Lima",
    "iso:country":"PE",
    "wof:name":"Huata",
    "wof:placetype":"locality"
},
  "geometry": {"coordinates":[-72.28650999999998,-16.84232],"type":"Point"}
}