{
  "type": "Feature",
  "properties": {
    "gn:admin1_code":"9.0",
    "gn:admin2_code":"907.0",
    "gn:admin3_code":"90717.0",
    "gn:asciiname":"Novillo Pampa",
    "gn:country_code":"PE",
    "gn:dem":2595,
    "gn:feature_class":"P",
    "gn:feature_code":"PPL",
    "gn:name":"Novillo Pampa",
    "gn:population":0,
    "gn:timezone":"America/Lima",
    "iso:country":"PE",
    "wof:name":"Novillo Pampa",
    "wof:placetype":"locality"
},
  "geometry": {"coordinates":[-74.62940999999999,-12.08013],"type":"Point"}
}