{
  "type": "Feature",
  "properties": {
    "gn:admin1_code":"9.0",
    "gn:admin2_code":"907.0",
    "gn:admin3_code":"90707.0",
    "gn:asciiname":"Muyococha",
    "gn:country_code":"PE",
    "gn:dem":2349,
    "gn:feature_class":"P",
    "gn:feature_code":"PPL",
    "gn:name":"Muyococha",
    "gn:population":0,
    "gn:timezone":"America/Lima",
    "iso:country":"PE",
    "wof:name":"Muyococha",
    "wof:placetype":"locality"
},
  "geometry": {"coordinates":[-74.64288000000001,-12.05745],"type":"Point"}
}