{
  "type": "Feature",
  "properties": {
    "gn:admin1_code":"23",
    "gn:admin2_code":"2302.0",
    "gn:admin3_code":"230204.0",
    "gn:asciiname":"Paquina",
    "gn:country_code":"PE",
    "gn:dem":1912,
    "gn:feature_class":"P",
    "gn:feature_code":"PPL",
    "gn:name":"Paqui\u00f1a",
    "gn:population":0,
    "gn:timezone":"America/Lima",
    "iso:country":"PE",
    "wof:name":"Paquina",
    "wof:placetype":"locality"
},
  "geometry": {"coordinates":[-70.39225,-17.4112],"type":"Point"}
}