{
  "type": "Feature",
  "properties": {
    "gn:admin1_code":"15",
    "gn:admin2_code":"1510.0",
    "gn:admin3_code":"151008.0",
    "gn:asciiname":"Callanapaquisca",
    "gn:country_code":"PE",
    "gn:dem":1214,
    "gn:feature_class":"P",
    "gn:feature_code":"PPL",
    "gn:name":"Callanapaquisca",
    "gn:population":0,
    "gn:timezone":"America/Lima",
    "iso:country":"PE",
    "wof:name":"Callanapaquisca",
    "wof:placetype":"locality"
},
  "geometry": {"coordinates":[-75.89116,-12.80384],"type":"Point"}
}