{
  "type": "Feature",
  "properties": {
    "gn:admin1_code":"11.0",
    "gn:admin2_code":"1102.0",
    "gn:admin3_code":"110205.0",
    "gn:asciiname":"Salguero",
    "gn:country_code":"PE",
    "gn:dem":89,
    "gn:feature_class":"P",
    "gn:feature_code":"PPL",
    "gn:name":"Salguero",
    "gn:population":0,
    "gn:timezone":"America/Lima",
    "iso:country":"PE",
    "name:spa_x_preferred":[
        "Salguero"
    ],
    "wof:name":"Salguero",
    "wof:placetype":"locality"
},
  "geometry": {"coordinates":[-76.10146999999998,-13.50862],"type":"Point"}
}