{
  "type": "Feature",
  "properties": {
    "gn:admin1_code":"14",
    "gn:admin2_code":"1402.0",
    "gn:admin3_code":"140205.0",
    "gn:asciiname":"El Campamento",
    "gn:country_code":"PE",
    "gn:dem":399,
    "gn:feature_class":"P",
    "gn:feature_code":"PPL",
    "gn:name":"El Campamento",
    "gn:population":0,
    "gn:timezone":"America/Lima",
    "iso:country":"PE",
    "wof:name":"El Campamento",
    "wof:placetype":"locality"
},
  "geometry": {"coordinates":[-79.46337,-6.3733],"type":"Point"}
}