{
  "type": "Feature",
  "properties": {
    "gn:admin1_code":"13.0",
    "gn:admin2_code":"1308.0",
    "gn:admin3_code":"130805.0",
    "gn:asciiname":"El Viento",
    "gn:country_code":"PE",
    "gn:dem":2454,
    "gn:feature_class":"P",
    "gn:feature_code":"PPL",
    "gn:name":"El Viento",
    "gn:population":0,
    "gn:timezone":"America/Lima",
    "iso:country":"PE",
    "name:fra_x_preferred":[
        "El Viento"
    ],
    "name:nld_x_preferred":[
        "El Viento"
    ],
    "name:por_x_preferred":[
        "El Viento"
    ],
    "wof:name":"El Viento",
    "wof:placetype":"locality"
},
  "geometry": {"coordinates":[-77.33083000000001,-8.20306],"type":"Point"}
}