{
  "type": "Feature",
  "properties": {
    "gn:admin1_code":"04",
    "gn:admin2_code":"403.0",
    "gn:admin3_code":"40302.0",
    "gn:asciiname":"Sausal",
    "gn:country_code":"PE",
    "gn:dem":561,
    "gn:feature_class":"P",
    "gn:feature_code":"PPL",
    "gn:name":"Sausal",
    "gn:population":0,
    "gn:timezone":"America/Lima",
    "iso:country":"PE",
    "name:ceb_x_preferred":[
        "Sausal Gebirge"
    ],
    "name:swe_x_preferred":[
        "Sausal Gebirge"
    ],
    "wof:name":"Sausal",
    "wof:placetype":"locality"
},
  "geometry": {"coordinates":[-74.5106,-15.16804],"type":"Point"}
}