{
  "type": "Feature",
  "properties": {
    "gn:admin1_code":"12.0",
    "gn:admin2_code":"1206.0",
    "gn:admin3_code":"120604.0",
    "gn:asciiname":"Materiato",
    "gn:country_code":"PE",
    "gn:dem":597,
    "gn:feature_class":"P",
    "gn:feature_code":"PPL",
    "gn:name":"Materiato",
    "gn:population":0,
    "gn:timezone":"America/Lima",
    "iso:country":"PE",
    "wof:name":"Materiato",
    "wof:placetype":"locality"
},
  "geometry": {"coordinates":[-74.47841,-11.30535],"type":"Point"}
}