{
  "type": "Feature",
  "properties": {
    "gn:admin1_code":"15",
    "gn:admin2_code":"1505.0",
    "gn:admin3_code":"150501.0",
    "gn:asciiname":"Encanada",
    "gn:country_code":"PE",
    "gn:dem":27,
    "gn:feature_class":"P",
    "gn:feature_code":"PPL",
    "gn:name":"Enca\u00f1ada",
    "gn:population":0,
    "gn:timezone":"America/Lima",
    "iso:country":"PE",
    "name:und_x_variant":[
        "La Enca\u00f1ada Hacienda",
        "La Enca\u00f1ada",
        "Enca\u00f1ada"
    ],
    "wof:name":"Encanada",
    "wof:placetype":"locality"
},
  "geometry": {"coordinates":[-76.38653000000002,-13.10656],"type":"Point"}
}