{
  "type": "Feature",
  "properties": {
    "gn:admin1_code":"15",
    "gn:admin2_code":"1510.0",
    "gn:admin3_code":"151005.0",
    "gn:asciiname":"Torremacmay",
    "gn:country_code":"PE",
    "gn:dem":3995,
    "gn:feature_class":"P",
    "gn:feature_code":"PPL",
    "gn:name":"Torremacmay",
    "gn:population":0,
    "gn:timezone":"America/Lima",
    "iso:country":"PE",
    "name:spa_x_preferred":[
        "Torremacmay"
    ],
    "name:spa_x_variant":[
        "Torremachay"
    ],
    "wof:name":"Torremacmay",
    "wof:placetype":"locality"
},
  "geometry": {"coordinates":[-75.80498,-13.02487],"type":"Point"}
}