{
  "type": "Feature",
  "properties": {
    "gn:admin1_code":"4",
    "gn:admin2_code":"405.0",
    "gn:admin3_code":"40519.0",
    "gn:asciiname":"Palca",
    "gn:country_code":"PE",
    "gn:dem":4378,
    "gn:feature_class":"P",
    "gn:feature_code":"PPL",
    "gn:name":"Palca",
    "gn:population":0,
    "gn:timezone":"America/Lima",
    "iso:country":"PE",
    "wof:name":"Palca",
    "wof:placetype":"locality"
},
  "geometry": {"coordinates":[-71.30859,-15.66987],"type":"Point"}
}