{
  "type": "Feature",
  "properties": {
    "gn:admin1_code":"10",
    "gn:admin2_code":"1004.0",
    "gn:admin3_code":"100403.0",
    "gn:asciiname":"Manshito",
    "gn:country_code":"PE",
    "gn:dem":2158,
    "gn:feature_class":"P",
    "gn:feature_code":"PPL",
    "gn:name":"Manshito",
    "gn:population":0,
    "gn:timezone":"America/Lima",
    "iso:country":"PE",
    "wof:name":"Manshito",
    "wof:placetype":"locality"
},
  "geometry": {"coordinates":[-76.49167,-9.07889],"type":"Point"}
}