{
  "type": "Feature",
  "properties": {
    "gn:admin1_code":"12",
    "gn:admin2_code":"1203.0",
    "gn:admin3_code":"120305.0",
    "gn:asciiname":"Quimiri Sur",
    "gn:country_code":"PE",
    "gn:dem":1401,
    "gn:feature_class":"P",
    "gn:feature_code":"PPL",
    "gn:name":"Quimiri Sur",
    "gn:population":0,
    "gn:timezone":"America/Lima",
    "iso:country":"PE",
    "wof:name":"Quimiri Sur",
    "wof:placetype":"locality"
},
  "geometry": {"coordinates":[-75.29055,-11.08361],"type":"Point"}
}