{
  "type": "Feature",
  "properties": {
    "gn:admin1_code":"09",
    "gn:admin2_code":"901.0",
    "gn:admin3_code":"90118.0",
    "gn:asciiname":"Citahuas",
    "gn:country_code":"PE",
    "gn:dem":4643,
    "gn:feature_class":"P",
    "gn:feature_code":"PPL",
    "gn:name":"Citahuas",
    "gn:population":0,
    "gn:timezone":"America/Lima",
    "iso:country":"PE",
    "wof:name":"Citahuas",
    "wof:placetype":"locality"
},
  "geometry": {"coordinates":[-75.23881999999998,-12.83903],"type":"Point"}
}