{
  "type": "Feature",
  "properties": {
    "gn:country":"PE",
    "gn:fcode":"PPL",
    "gn:population":300,
    "iso:country":"PE",
    "qs:name":"C.P. Huanja",
    "qs:photos_9r":0,
    "qs:photos_sr":0,
    "qs:pop_sr":"2",
    "wof:name":"C.P. Huanja",
    "wof:placetype":"locality",
    "wof:population":300
},
  "geometry": {"coordinates":[-77.55976,-9.43786],"type":"Point"}
}