{
  "type": "Feature",
  "properties": {
    "gn:admin1_code":"05",
    "gn:admin2_code":"506.0",
    "gn:admin3_code":"50605.0",
    "gn:asciiname":"Uncalcocha",
    "gn:country_code":"PE",
    "gn:dem":3332,
    "gn:feature_class":"P",
    "gn:feature_code":"PPL",
    "gn:name":"Uncalcocha",
    "gn:population":0,
    "gn:timezone":"America/Lima",
    "iso:country":"PE",
    "wof:name":"Uncalcocha",
    "wof:placetype":"locality"
},
  "geometry": {"coordinates":[-73.84206999999998,-15.00013],"type":"Point"}
}