{
  "type": "Feature",
  "properties": {
    "gn:admin1_code":"12.0",
    "gn:admin2_code":"1201.0",
    "gn:asciiname":"Urumcuy",
    "gn:country_code":"PE",
    "gn:dem":2894,
    "gn:feature_class":"P",
    "gn:feature_code":"PPL",
    "gn:name":"Urumcuy",
    "gn:population":0,
    "gn:timezone":"America/Lima",
    "iso:country":"PE",
    "wof:name":"Urumcuy",
    "wof:placetype":"locality"
},
  "geometry": {"coordinates":[-74.76676999999999,-12.02593],"type":"Point"}
}