{
  "type": "Feature",
  "properties": {
    "gn:country":"PE",
    "gn:fcode":"PPL",
    "gn:pop":14210,
    "iso:country":"PE",
    "qs:name":"Salinera Col\u00e1n",
    "qs:photos_9r":0,
    "qs:photos_sr":0,
    "qs:pop_sr":"6",
    "wof:name":"Salinera Col\u00e1n",
    "wof:placetype":"locality",
    "wof:population":14210
},
  "geometry": {"coordinates":[-81.06667,-5.03333],"type":"Point"}
}