{
  "type": "Feature",
  "properties": {
    "gn:admin1_code":"17.0",
    "gn:admin2_code":"1703.0",
    "gn:asciiname":"Cespedes",
    "gn:country_code":"PE",
    "gn:dem":306,
    "gn:feature_class":"P",
    "gn:feature_code":"PPL",
    "gn:name":"Cespedes",
    "gn:population":0,
    "gn:timezone":"America/Lima",
    "iso:country":"PE",
    "name:spa_x_preferred":[
        "Cespedes"
    ],
    "wof:name":"Cespedes",
    "wof:placetype":"locality"
},
  "geometry": {"coordinates":[-69.04754,-11.82725],"type":"Point"}
}