{
  "type": "Feature",
  "properties": {
    "iso:country":"PE",
    "qs:gn_pop":0,
    "qs:name":"Sector Ii",
    "qs:name_adm0":"Per\u00fa",
    "qs:name_adm1":"Lima Metropolitan Area",
    "qs:photos":55,
    "qs:photos_1k":11,
    "qs:photos_9k":1,
    "qs:photos_9r":2,
    "qs:photos_all":55,
    "qs:photos_sr":2,
    "qs:placetype":"Town",
    "qs:pop_sr":"0",
    "qs:woe_adm0":23424919,
    "wof:name":"Sector Ii",
    "wof:placetype":"locality"
},
  "geometry": {"coordinates":[-76.956481,-12.208495],"type":"Point"}
}