{
  "type": "Feature",
  "properties": {
    "gn:admin1_code":"03",
    "gn:admin2_code":"304.0",
    "gn:admin3_code":"30406.0",
    "gn:asciiname":"Kello",
    "gn:country_code":"PE",
    "gn:dem":4054,
    "gn:feature_class":"P",
    "gn:feature_code":"PPL",
    "gn:name":"Kello",
    "gn:population":0,
    "gn:timezone":"America/Lima",
    "iso:country":"PE",
    "wof:name":"Kello",
    "wof:placetype":"locality"
},
  "geometry": {"coordinates":[-73.56395000000001,-14.70895],"type":"Point"}
}