{
  "type": "Feature",
  "properties": {
    "gn:admin1_code":"22",
    "gn:admin2_code":"2202.0",
    "gn:admin3_code":"220203.0",
    "gn:asciiname":"Pampa Hermosa",
    "gn:country_code":"PE",
    "gn:dem":258,
    "gn:feature_class":"P",
    "gn:feature_code":"PPL",
    "gn:name":"Pampa Hermosa",
    "gn:population":0,
    "gn:timezone":"America/Lima",
    "iso:country":"PE",
    "wof:name":"Pampa Hermosa",
    "wof:placetype":"locality"
},
  "geometry": {"coordinates":[-76.49528000000002,-7.17611],"type":"Point"}
}