{
  "type": "Feature",
  "properties": {
    "gn:admin1_code":"14",
    "gn:admin2_code":"1403.0",
    "gn:admin3_code":"140304.0",
    "gn:asciiname":"La Maravilla",
    "gn:country_code":"PE",
    "gn:dem":81,
    "gn:feature_class":"P",
    "gn:feature_code":"PPL",
    "gn:name":"La Maravilla",
    "gn:population":0,
    "gn:timezone":"America/Lima",
    "iso:country":"PE",
    "wof:name":"La Maravilla",
    "wof:placetype":"locality"
},
  "geometry": {"coordinates":[-79.92249,-6.15484],"type":"Point"}
}