{
  "type": "Feature",
  "properties": {
    "gn:admin1_code":"15.0",
    "gn:admin2_code":"1501.0",
    "gn:admin3_code":"150102.0",
    "gn:asciiname":"Peaje Pasamayo",
    "gn:country_code":"PE",
    "gn:dem":92,
    "gn:feature_class":"P",
    "gn:feature_code":"PPL",
    "gn:name":"Peaje Pasamayo",
    "gn:population":0,
    "gn:timezone":"America/Lima",
    "iso:country":"PE",
    "name:spa_x_preferred":[
        "Peaje Pasamayo"
    ],
    "wof:name":"Peaje Pasamayo",
    "wof:placetype":"locality"
},
  "geometry": {"coordinates":[-77.16207,-11.74022],"type":"Point"}
}