{
  "type": "Feature",
  "properties": {
    "gn:admin1_code":"11",
    "gn:admin2_code":"1105.0",
    "gn:admin3_code":"110505.0",
    "gn:asciiname":"Salinas de Otuma",
    "gn:country_code":"PE",
    "gn:dem":-9,
    "gn:feature_class":"P",
    "gn:feature_code":"PPL",
    "gn:name":"Salinas de Otuma",
    "gn:population":0,
    "gn:timezone":"America/Lima",
    "iso:country":"PE",
    "wof:name":"Salinas de Otuma",
    "wof:placetype":"locality"
},
  "geometry": {"coordinates":[-76.23863,-14.01016],"type":"Point"}
}