{
  "type": "Feature",
  "properties": {
    "gn:admin1_code":"21",
    "gn:admin2_code":"2106.0",
    "gn:admin3_code":"210605.0",
    "gn:asciiname":"Yapasmayo",
    "gn:country_code":"PE",
    "gn:dem":4039,
    "gn:feature_class":"P",
    "gn:feature_code":"PPL",
    "gn:name":"Yapasmayo",
    "gn:population":0,
    "gn:timezone":"America/Lima",
    "iso:country":"PE",
    "wof:name":"Yapasmayo",
    "wof:placetype":"locality"
},
  "geometry": {"coordinates":[-69.91667,-15.48333],"type":"Point"}
}