{
  "type": "Feature",
  "properties": {
    "gn:admin1_code":"9",
    "gn:admin2_code":"906.0",
    "gn:admin3_code":"90609.0",
    "gn:asciiname":"Pariuna",
    "gn:country_code":"PE",
    "gn:dem":3333,
    "gn:feature_class":"P",
    "gn:feature_code":"PPL",
    "gn:name":"Pariuna",
    "gn:population":0,
    "gn:timezone":"America/Lima",
    "iso:country":"PE",
    "wof:name":"Pariuna",
    "wof:placetype":"locality"
},
  "geometry": {"coordinates":[-75.32971999999999,-13.51611],"type":"Point"}
}