{
  "type": "Feature",
  "properties": {
    "gn:admin1_code":"20",
    "gn:admin2_code":"2006.0",
    "gn:admin3_code":"200604.0",
    "gn:asciiname":"Sitio Nuevo",
    "gn:country_code":"PE",
    "gn:dem":307,
    "gn:feature_class":"P",
    "gn:feature_code":"PPL",
    "gn:name":"Sitio Nuevo",
    "gn:population":0,
    "gn:timezone":"America/Lima",
    "iso:country":"PE",
    "name:spa_x_preferred":[
        "Sitio Nuevo"
    ],
    "wof:name":"Sitio Nuevo",
    "wof:placetype":"locality"
},
  "geometry": {"coordinates":[-80.63859000000002,-4.47687],"type":"Point"}
}