{
  "type": "Feature",
  "properties": {
    "gn:admin1_code":"21",
    "gn:admin2_code":"2103.0",
    "gn:admin3_code":"210310.0",
    "gn:asciiname":"Ccasanchaya",
    "gn:country_code":"PE",
    "gn:dem":3547,
    "gn:feature_class":"P",
    "gn:feature_code":"PPL",
    "gn:name":"Ccasanchaya",
    "gn:population":0,
    "gn:timezone":"America/Lima",
    "iso:country":"PE",
    "wof:name":"Ccasanchaya",
    "wof:placetype":"locality"
},
  "geometry": {"coordinates":[-69.88394,-14.12966],"type":"Point"}
}