{
  "type": "Feature",
  "properties": {
    "gn:admin1_code":"02",
    "gn:admin2_code":"205.0",
    "gn:admin3_code":"20515.0",
    "gn:asciiname":"Ticllos",
    "gn:country_code":"PE",
    "gn:dem":3644,
    "gn:feature_class":"P",
    "gn:feature_code":"PPLA3",
    "gn:name":"Ticllos",
    "gn:population":0,
    "gn:timezone":"America/Lima",
    "iso:country":"PE",
    "wof:name":"Ticllos",
    "wof:placetype":"locality"
},
  "geometry": {"coordinates":[-77.19088000000001,-10.25403],"type":"Point"}
}