{
  "type": "Feature",
  "properties": {
    "gn:admin1_code":"21",
    "gn:admin2_code":"2102.0",
    "gn:admin3_code":"210203.0",
    "gn:asciiname":"Yani Cuturi",
    "gn:country_code":"PE",
    "gn:dem":3875,
    "gn:feature_class":"P",
    "gn:feature_code":"PPL",
    "gn:name":"Yani Cuturi",
    "gn:population":0,
    "gn:timezone":"America/Lima",
    "iso:country":"PE",
    "wof:name":"Yani Cuturi",
    "wof:placetype":"locality"
},
  "geometry": {"coordinates":[-70.15652,-15.10539],"type":"Point"}
}