{
  "type": "Feature",
  "properties": {
    "gn:admin1_code":"3",
    "gn:admin2_code":"302.0",
    "gn:admin3_code":"30202.0",
    "gn:asciiname":"Andarapa",
    "gn:country_code":"PE",
    "gn:dem":2914,
    "gn:feature_class":"P",
    "gn:feature_code":"PPLA3",
    "gn:name":"Andarapa",
    "gn:population":0,
    "gn:timezone":"America/Lima",
    "iso:country":"PE",
    "wof:name":"Andarapa",
    "wof:placetype":"locality"
},
  "geometry": {"coordinates":[-73.36610999999998,-13.52611],"type":"Point"}
}