{
  "type": "Feature",
  "properties": {
    "gn:admin1_code":"12.0",
    "gn:admin2_code":"1203.0",
    "gn:admin3_code":"120301.0",
    "gn:asciiname":"Quimiri Norte",
    "gn:country_code":"PE",
    "gn:dem":1198,
    "gn:feature_class":"P",
    "gn:feature_code":"PPL",
    "gn:name":"Quimiri Norte",
    "gn:population":0,
    "gn:timezone":"America/Lima",
    "iso:country":"PE",
    "wof:name":"Quimiri Norte",
    "wof:placetype":"locality"
},
  "geometry": {"coordinates":[-75.30161,-11.02813],"type":"Point"}
}