{
  "type": "Feature",
  "properties": {
    "gn:admin1_code":"04",
    "gn:admin2_code":"405.0",
    "gn:admin3_code":"40517.0",
    "gn:asciiname":"Huiluma",
    "gn:country_code":"PE",
    "gn:dem":4724,
    "gn:feature_class":"P",
    "gn:feature_code":"PPL",
    "gn:name":"Huiluma",
    "gn:population":0,
    "gn:timezone":"America/Lima",
    "iso:country":"PE",
    "wof:name":"Huiluma",
    "wof:placetype":"locality"
},
  "geometry": {"coordinates":[-71.46375999999999,-15.05808],"type":"Point"}
}