{
  "type": "Feature",
  "properties": {
    "gn:admin1_code":"14",
    "gn:admin2_code":"1401.0",
    "gn:admin3_code":"140106.0",
    "gn:asciiname":"La Victoria",
    "gn:country_code":"PE",
    "gn:dem":29,
    "gn:feature_class":"P",
    "gn:feature_code":"PPLL",
    "gn:name":"La Victoria",
    "gn:population":0,
    "gn:timezone":"America/Lima",
    "iso:country":"PE",
    "name:spa_x_preferred":[
        "La Victoria"
    ],
    "wof:name":"La Victoria",
    "wof:placetype":"locality"
},
  "geometry": {"coordinates":[-79.82888,-6.79285],"type":"Point"}
}