{
  "type": "Feature",
  "properties": {
    "gn:admin1_code":"15",
    "gn:admin2_code":"1505.0",
    "gn:admin3_code":"150512.0",
    "gn:asciiname":"San Juan de Roldan",
    "gn:country_code":"PE",
    "gn:dem":121,
    "gn:feature_class":"P",
    "gn:feature_code":"PPL",
    "gn:name":"San Juan de Rold\u00e1n",
    "gn:population":0,
    "gn:timezone":"America/Lima",
    "iso:country":"PE",
    "wof:name":"San Juan de Roldan",
    "wof:placetype":"locality"
},
  "geometry": {"coordinates":[-76.41637,-12.96323],"type":"Point"}
}