{
  "type": "Feature",
  "properties": {
    "gn:admin1_code":"8.0",
    "gn:admin2_code":"809.0",
    "gn:asciiname":"Tarancayo",
    "gn:country_code":"PE",
    "gn:dem":1238,
    "gn:feature_class":"P",
    "gn:feature_code":"PPL",
    "gn:name":"Tarancayo",
    "gn:population":0,
    "gn:timezone":"America/Lima",
    "iso:country":"PE",
    "wof:name":"Tarancayo",
    "wof:placetype":"locality"
},
  "geometry": {"coordinates":[-73.77638,-12.52268],"type":"Point"}
}