{
  "type": "Feature",
  "properties": {
    "gn:admin1_code":"2.0",
    "gn:admin2_code":"205.0",
    "gn:asciiname":"Calannioc",
    "gn:country_code":"PE",
    "gn:dem":3830,
    "gn:feature_class":"P",
    "gn:feature_code":"PPL",
    "gn:name":"Calannioc",
    "gn:population":0,
    "gn:timezone":"America/Lima",
    "iso:country":"PE",
    "wof:name":"Calannioc",
    "wof:placetype":"locality"
},
  "geometry": {"coordinates":[-76.94699,-9.75468],"type":"Point"}
}