{
  "type": "Feature",
  "properties": {
    "gn:admin1_code":"10.0",
    "gn:admin2_code":"1003.0",
    "gn:admin3_code":"100323.0",
    "gn:asciiname":"Jachahuain",
    "gn:country_code":"PE",
    "gn:dem":3619,
    "gn:feature_class":"P",
    "gn:feature_code":"PPL",
    "gn:name":"Jachahuain",
    "gn:population":0,
    "gn:timezone":"America/Lima",
    "iso:country":"PE",
    "wof:name":"Jachahuain",
    "wof:placetype":"locality"
},
  "geometry": {"coordinates":[-76.72017,-9.72394],"type":"Point"}
}