{
  "type": "Feature",
  "properties": {
    "gn:admin1_code":"10",
    "gn:admin2_code":"1001.0",
    "gn:admin3_code":"100108.0",
    "gn:asciiname":"Puca Mochca",
    "gn:country_code":"PE",
    "gn:dem":3735,
    "gn:feature_class":"P",
    "gn:feature_code":"PPL",
    "gn:name":"Puca Mochca",
    "gn:population":0,
    "gn:timezone":"America/Lima",
    "iso:country":"PE",
    "wof:name":"Puca Mochca",
    "wof:placetype":"locality"
},
  "geometry": {"coordinates":[-76.47148,-10.09455],"type":"Point"}
}