{
  "type": "Feature",
  "properties": {
    "gn:admin1_code":"20",
    "gn:admin2_code":"2002.0",
    "gn:admin3_code":"200201.0",
    "gn:asciiname":"Vircales",
    "gn:country_code":"PE",
    "gn:dem":2391,
    "gn:feature_class":"P",
    "gn:feature_code":"PPL",
    "gn:name":"Vircales",
    "gn:population":0,
    "gn:timezone":"America/Lima",
    "iso:country":"PE",
    "name:und_x_variant":[
        "Hacienda Vircales",
        "Vircales Hacienda",
        "Vircales"
    ],
    "wof:name":"Vircales",
    "wof:placetype":"locality"
},
  "geometry": {"coordinates":[-79.52506,-4.80279],"type":"Point"}
}