{
  "type": "Feature",
  "properties": {
    "gn:admin1_code":"04",
    "gn:admin2_code":"405.0",
    "gn:admin3_code":"40517.0",
    "gn:asciiname":"Pisacani",
    "gn:country_code":"PE",
    "gn:dem":3950,
    "gn:feature_class":"P",
    "gn:feature_code":"PPL",
    "gn:name":"Pisacani",
    "gn:population":0,
    "gn:timezone":"America/Lima",
    "iso:country":"PE",
    "name:zho_x_preferred":[
        "\u76ae\u65af\u5361\u5c3c\u5c71"
    ],
    "wof:name":"Pisacani",
    "wof:placetype":"locality"
},
  "geometry": {"coordinates":[-71.46113000000003,-15.42037],"type":"Point"}
}