{
  "type": "Feature",
  "properties": {
    "gn:admin1_code":"12.0",
    "gn:admin2_code":"1205.0",
    "gn:asciiname":"Erapata",
    "gn:country_code":"PE",
    "gn:dem":2185,
    "gn:feature_class":"P",
    "gn:feature_code":"PPL",
    "gn:name":"Erapata",
    "gn:population":0,
    "gn:timezone":"America/Lima",
    "iso:country":"PE",
    "wof:name":"Erapata",
    "wof:placetype":"locality"
},
  "geometry": {"coordinates":[-74.85263,-12.03959],"type":"Point"}
}