{
  "type": "Feature",
  "properties": {
    "gn:admin1_code":"14.0",
    "gn:admin2_code":"1401.0",
    "gn:admin3_code":"140113.0",
    "gn:asciiname":"Ramon Changa",
    "gn:country_code":"PE",
    "gn:dem":31,
    "gn:feature_class":"P",
    "gn:feature_code":"PPL",
    "gn:name":"Ramon Changa",
    "gn:population":0,
    "gn:timezone":"America/Lima",
    "iso:country":"PE",
    "name:spa_x_preferred":[
        "Ramon Changa"
    ],
    "wof:name":"Ramon Changa",
    "wof:placetype":"locality"
},
  "geometry": {"coordinates":[-79.80436999999998,-6.85487],"type":"Point"}
}