{
  "type": "Feature",
  "properties": {
    "gn:admin1_code":"15.0",
    "gn:admin2_code":"1507.0",
    "gn:admin3_code":"150704.0",
    "gn:asciiname":"Yachacocha",
    "gn:country_code":"PE",
    "gn:dem":3379,
    "gn:feature_class":"P",
    "gn:feature_code":"PPL",
    "gn:name":"Yachacocha",
    "gn:population":0,
    "gn:timezone":"America/Lima",
    "iso:country":"PE",
    "name:spa_x_preferred":[
        "Yachacocha"
    ],
    "wof:name":"Yachacocha",
    "wof:placetype":"locality"
},
  "geometry": {"coordinates":[-76.51272,-11.65491],"type":"Point"}
}