{
  "type": "Feature",
  "properties": {
    "gn:admin1_code":"15.0",
    "gn:admin2_code":"1508.0",
    "gn:admin3_code":"150811.0",
    "gn:asciiname":"Huamboy Grande",
    "gn:country_code":"PE",
    "gn:dem":1068,
    "gn:feature_class":"P",
    "gn:feature_code":"PPL",
    "gn:name":"Huamboy Grande",
    "gn:population":0,
    "gn:timezone":"America/Lima",
    "iso:country":"PE",
    "wof:name":"Huamboy Grande",
    "wof:placetype":"locality"
},
  "geometry": {"coordinates":[-77.09583000000001,-11.03222],"type":"Point"}
}