{
  "type": "Feature",
  "properties": {
    "gn:admin1_code":"18",
    "gn:admin2_code":"1801.0",
    "gn:admin3_code":"180102.0",
    "gn:asciiname":"Estancia Huaraya",
    "gn:country_code":"PE",
    "gn:dem":4395,
    "gn:feature_class":"P",
    "gn:feature_code":"PPL",
    "gn:name":"Estancia Huaraya",
    "gn:population":0,
    "gn:timezone":"America/Lima",
    "iso:country":"PE",
    "wof:name":"Estancia Huaraya",
    "wof:placetype":"locality"
},
  "geometry": {"coordinates":[-70.32951,-16.68449],"type":"Point"}
}