{
  "type": "Feature",
  "properties": {
    "gn:admin1_code":"15.0",
    "gn:admin2_code":"1501.0",
    "gn:admin3_code":"150119.0",
    "gn:asciiname":"Julio C. Tello",
    "gn:country_code":"PE",
    "gn:dem":72,
    "gn:feature_class":"P",
    "gn:feature_code":"PPL",
    "gn:name":"Julio C. Tello",
    "gn:population":0,
    "gn:timezone":"America/Lima",
    "iso:country":"PE",
    "name:ara_x_preferred":[
        "\u062e\u0648\u0644\u064a\u0648 \u062a\u0644\u0644\u0648"
    ],
    "name:ast_x_preferred":[
        "Julio C\u00e9sar Tello"
    ],
    "name:aym_x_preferred":[
        "Julio C\u00e9sar Tello"
    ],
    "name:deu_x_preferred":[
        "Julio Tello"
    ],
    "name:fra_x_preferred":[
        "Julio Tello"
    ],
    "name:ita_x_preferred":[
        "Julio C\u00e9sar Tello"
    ],
    "name:lit_x_preferred":[
        "Julio C\u00e9sar Tello"
    ],
    "name:que_x_preferred":[
        "Julio C\u00e9sar Tello"
    ],
    "name:rus_x_preferred":[
        "\u0422\u0435\u043b\u044c\u043e"
    ],
    "name:spa_x_preferred":[
        "Julio C. Tello"
    ],
    "name:spa_x_variant":[
        "Julio C\u00e9sar Tello"
    ],
    "name:swe_x_preferred":[
        "Julio C. Tello"
    ],
    "wof:name":"Julio C. Tello",
    "wof:placetype":"locality"
},
  "geometry": {"coordinates":[-76.89474,-12.24547],"type":"Point"}
}