{
  "type": "Feature",
  "properties": {
    "gn:admin1_code":"22.0",
    "gn:admin2_code":"2207.0",
    "gn:admin3_code":"220701.0",
    "gn:asciiname":"Santa Rosillo",
    "gn:country_code":"PE",
    "gn:dem":349,
    "gn:feature_class":"P",
    "gn:feature_code":"PPL",
    "gn:name":"Santa Rosillo",
    "gn:population":0,
    "gn:timezone":"America/Lima",
    "iso:country":"PE",
    "name:spa_x_preferred":[
        "Santa Rosillo"
    ],
    "wof:name":"Santa Rosillo",
    "wof:placetype":"locality"
},
  "geometry": {"coordinates":[-76.36513000000002,-6.91761],"type":"Point"}
}