{
  "type": "Feature",
  "properties": {
    "gn:admin1_code":"22.0",
    "gn:admin2_code":"2210.0",
    "gn:admin3_code":"221002.0",
    "gn:asciiname":"Palma Semilla",
    "gn:country_code":"PE",
    "gn:dem":552,
    "gn:feature_class":"P",
    "gn:feature_code":"PPLL",
    "gn:name":"Palma Semilla",
    "gn:population":0,
    "gn:timezone":"America/Lima",
    "iso:country":"PE",
    "wof:name":"Palma Semilla",
    "wof:placetype":"locality"
},
  "geometry": {"coordinates":[-76.28222,-8.387],"type":"Point"}
}