{
  "type": "Feature",
  "properties": {
    "gn:admin1_code":"2.0",
    "gn:admin2_code":"201.0",
    "gn:admin3_code":"20106.0",
    "gn:asciiname":"Jagua",
    "gn:country_code":"PE",
    "gn:dem":3245,
    "gn:feature_class":"P",
    "gn:feature_code":"PPL",
    "gn:name":"Jagua",
    "gn:population":0,
    "gn:timezone":"America/Lima",
    "iso:country":"PE",
    "name:ceb_x_preferred":[
        "Jagua"
    ],
    "name:ita_x_preferred":[
        "Jagua"
    ],
    "name:swe_x_preferred":[
        "Jagua"
    ],
    "wof:name":"Jagua",
    "wof:placetype":"locality"
},
  "geometry": {"coordinates":[-77.5975,-9.40694],"type":"Point"}
}