{
  "type": "Feature",
  "properties": {
    "gn:admin1_code":"15",
    "gn:admin2_code":"1510.0",
    "gn:admin3_code":"151005.0",
    "gn:asciiname":"Pucarumi",
    "gn:country_code":"PE",
    "gn:dem":3652,
    "gn:feature_class":"P",
    "gn:feature_code":"PPL",
    "gn:name":"Pucarumi",
    "gn:population":0,
    "gn:timezone":"America/Lima",
    "iso:country":"PE",
    "wof:name":"Pucarumi",
    "wof:placetype":"locality"
},
  "geometry": {"coordinates":[-75.81026999999997,-12.99208],"type":"Point"}
}