{
  "type": "Feature",
  "properties": {
    "gn:admin1_code":"06",
    "gn:admin2_code":"608.0",
    "gn:admin3_code":"60810.0",
    "gn:asciiname":"San Felipe",
    "gn:country_code":"PE",
    "gn:dem":1943,
    "gn:feature_class":"P",
    "gn:feature_code":"PPLA3",
    "gn:name":"San Felipe",
    "gn:population":0,
    "gn:timezone":"America/Lima",
    "iso:country":"PE",
    "wof:name":"San Felipe",
    "wof:placetype":"locality"
},
  "geometry": {"coordinates":[-79.31166999999998,-5.76778],"type":"Point"}
}