{
  "type": "Feature",
  "properties": {
    "gn:admin1_code":"06",
    "gn:admin2_code":"608.0",
    "gn:admin3_code":"60810.0",
    "gn:asciiname":"San Felipe",
    "gn:country_code":"PE",
    "gn:dem":1943,
    "gn:feature_class":"P",
    "gn:feature_code":"PPLA3",
    "gn:name":"San Felipe",
    "gn:population":0,
    "gn:timezone":"America/Lima",
    "iso:country":"PE",
    "name:deu_x_preferred":[
        "San Felipe"
    ],
    "name:fas_x_preferred":[
        "\u0633\u0627\u0646 \u0641\u06cc\u0644\u06cc\u067e\u0647"
    ],
    "name:heb_x_preferred":[
        "\u05e1\u05df \u05e4\u05dc\u05d9\u05e4\u05d4"
    ],
    "name:hun_x_preferred":[
        "San Felipe"
    ],
    "wof:name":"San Felipe",
    "wof:placetype":"locality"
},
  "geometry": {"coordinates":[-79.31167000000001,-5.76778],"type":"Point"}
}