{
  "type": "Feature",
  "properties": {
    "gn:admin1_code":"01",
    "gn:admin2_code":"102.0",
    "gn:admin3_code":"10205.0",
    "gn:asciiname":"Mesones Muro",
    "gn:country_code":"PE",
    "gn:dem":275,
    "gn:feature_class":"P",
    "gn:feature_code":"PPL",
    "gn:name":"Mesones Muro",
    "gn:population":0,
    "gn:timezone":"America/Lima",
    "iso:country":"PE",
    "wof:name":"Mesones Muro",
    "wof:placetype":"locality"
},
  "geometry": {"coordinates":[-78.32884,-5.06803],"type":"Point"}
}