{
  "type": "Feature",
  "properties": {
    "gn:admin1_code":"2.0",
    "gn:admin2_code":"214.0",
    "gn:admin3_code":"21406.0",
    "gn:asciiname":"Parian",
    "gn:country_code":"PE",
    "gn:dem":2588,
    "gn:feature_class":"P",
    "gn:feature_code":"PPL",
    "gn:name":"Pari\u00e1n",
    "gn:population":0,
    "gn:timezone":"America/Lima",
    "iso:country":"PE",
    "name:ceb_x_preferred":[
        "Parian"
    ],
    "name:swe_x_preferred":[
        "Parian"
    ],
    "wof:name":"Parian",
    "wof:placetype":"locality"
},
  "geometry": {"coordinates":[-77.46204,-10.35046],"type":"Point"}
}