{
  "type": "Feature",
  "properties": {
    "gn:admin1_code":"11",
    "gn:admin2_code":"1105.0",
    "gn:admin3_code":"110503.0",
    "gn:asciiname":"Pantaico",
    "gn:country_code":"PE",
    "gn:dem":531,
    "gn:feature_class":"P",
    "gn:feature_code":"PPL",
    "gn:name":"Pantaico",
    "gn:population":0,
    "gn:timezone":"America/Lima",
    "iso:country":"PE",
    "wof:name":"Pantaico",
    "wof:placetype":"locality"
},
  "geometry": {"coordinates":[-75.83333,-13.71667],"type":"Point"}
}