{
  "type": "Feature",
  "properties": {
    "gn:admin1_code":"20",
    "gn:admin2_code":"2003.0",
    "gn:admin3_code":"200301.0",
    "gn:asciiname":"Hacienda Succhi",
    "gn:country_code":"PE",
    "gn:dem":3020,
    "gn:feature_class":"P",
    "gn:feature_code":"PPL",
    "gn:name":"Hacienda Succhi",
    "gn:population":0,
    "gn:timezone":"America/Lima",
    "iso:country":"PE",
    "name:und_x_variant":[
        "Suchil",
        "Hacienda Suchil",
        "Suchil Hacienda",
        "Succhil",
        "Hacienda Succhi"
    ],
    "wof:name":"Hacienda Succhi",
    "wof:placetype":"locality"
},
  "geometry": {"coordinates":[-79.54151999999998,-5.25668],"type":"Point"}
}