{
  "type": "Feature",
  "properties": {
    "gn:admin1_code":"5.0",
    "gn:admin2_code":"501.0",
    "gn:admin3_code":"50113.0",
    "gn:asciiname":"Saucecocha",
    "gn:country_code":"PE",
    "gn:dem":2963,
    "gn:feature_class":"P",
    "gn:feature_code":"PPL",
    "gn:name":"Saucecocha",
    "gn:population":0,
    "gn:timezone":"America/Lima",
    "iso:country":"PE",
    "name:und_x_variant":[
        "Hacienda Saucecocha"
    ],
    "wof:name":"Saucecocha",
    "wof:placetype":"locality"
},
  "geometry": {"coordinates":[-74.12406,-13.19514],"type":"Point"}
}