{
  "type": "Feature",
  "properties": {
    "gn:admin1_code":"15.0",
    "gn:admin2_code":"1505.0",
    "gn:admin3_code":"150501.0",
    "gn:asciiname":"Santa Margarita",
    "gn:country_code":"PE",
    "gn:dem":57,
    "gn:feature_class":"P",
    "gn:feature_code":"PPL",
    "gn:name":"Santa Margarita",
    "gn:population":0,
    "gn:timezone":"America/Lima",
    "iso:country":"PE",
    "wof:name":"Santa Margarita",
    "wof:placetype":"locality"
},
  "geometry": {"coordinates":[-76.35413,-13.12308],"type":"Point"}
}