{
  "type": "Feature",
  "properties": {
    "gn:admin1_code":"10",
    "gn:admin2_code":"1009.0",
    "gn:admin3_code":"100902.0",
    "gn:asciiname":"Tato",
    "gn:country_code":"PE",
    "gn:dem":411,
    "gn:feature_class":"P",
    "gn:feature_code":"PPL",
    "gn:name":"Tato",
    "gn:population":0,
    "gn:timezone":"America/Lima",
    "iso:country":"PE",
    "wof:name":"Tato",
    "wof:placetype":"locality"
},
  "geometry": {"coordinates":[-75.47672,-9.5841],"type":"Point"}
}