{
  "type": "Feature",
  "properties": {
    "gn:admin1_code":"10",
    "gn:admin2_code":"1009.0",
    "gn:admin3_code":"100902.0",
    "gn:asciiname":"Tato",
    "gn:country_code":"PE",
    "gn:dem":411,
    "gn:feature_class":"P",
    "gn:feature_code":"PPL",
    "gn:name":"Tato",
    "gn:population":0,
    "gn:timezone":"America/Lima",
    "iso:country":"PE",
    "name:ast_x_preferred":[
        "Tato"
    ],
    "name:bul_x_preferred":[
        "\u0422\u0430\u0442\u043e"
    ],
    "name:ces_x_preferred":[
        "Tato"
    ],
    "name:dan_x_preferred":[
        "Tato"
    ],
    "name:deu_x_preferred":[
        "Tato"
    ],
    "name:fra_x_preferred":[
        "Tatto"
    ],
    "name:glg_x_preferred":[
        "Tatto"
    ],
    "name:ind_x_preferred":[
        "Tatone"
    ],
    "name:ita_x_preferred":[
        "Tatone"
    ],
    "name:nld_x_preferred":[
        "Tato"
    ],
    "name:nor_x_preferred":[
        "Tato"
    ],
    "name:ron_x_preferred":[
        "Tato"
    ],
    "name:rus_x_preferred":[
        "\u0422\u0430\u0442\u043e"
    ],
    "name:srp_x_preferred":[
        "\u0422\u0430\u0442\u043e"
    ],
    "name:ukr_x_preferred":[
        "\u0422\u0430\u0442\u043e"
    ],
    "wof:name":"Tato",
    "wof:placetype":"locality"
},
  "geometry": {"coordinates":[-75.47672,-9.5841],"type":"Point"}
}