{
  "type": "Feature",
  "properties": {
    "gn:admin1_code":"19.0",
    "gn:admin2_code":"1901.0",
    "gn:admin3_code":"190104.0",
    "gn:asciiname":"Chacpatunac",
    "gn:country_code":"PE",
    "gn:dem":4584,
    "gn:feature_class":"P",
    "gn:feature_code":"PPL",
    "gn:name":"Chacpatunac",
    "gn:population":0,
    "gn:timezone":"America/Lima",
    "iso:country":"PE",
    "wof:name":"Chacpatunac",
    "wof:placetype":"locality"
},
  "geometry": {"coordinates":[-76.42896999999998,-11.03853],"type":"Point"}
}