{
  "type": "Feature",
  "properties": {
    "gn:admin1_code":"04",
    "gn:admin2_code":"403.0",
    "gn:admin3_code":"40308.0",
    "gn:asciiname":"Hacienda San Agustin",
    "gn:country_code":"PE",
    "gn:dem":537,
    "gn:feature_class":"P",
    "gn:feature_code":"PPL",
    "gn:name":"Hacienda San Agust\u00edn",
    "gn:population":0,
    "gn:timezone":"America/Lima",
    "iso:country":"PE",
    "name:und_x_variant":[
        "San August\u00edn",
        "Hacienda San Agust\u00edn"
    ],
    "wof:name":"Hacienda San Agustin",
    "wof:placetype":"locality"
},
  "geometry": {"coordinates":[-73.98224999999999,-15.80865],"type":"Point"}
}