{
  "type": "Feature",
  "properties": {
    "gn:admin1_code":"10.0",
    "gn:admin2_code":"1011.0",
    "gn:admin3_code":"101104.0",
    "gn:asciiname":"Yachas",
    "gn:country_code":"PE",
    "gn:dem":3783,
    "gn:feature_class":"P",
    "gn:feature_code":"PPL",
    "gn:name":"Yachas",
    "gn:population":0,
    "gn:timezone":"America/Lima",
    "iso:country":"PE",
    "wof:name":"Yachas",
    "wof:placetype":"locality"
},
  "geometry": {"coordinates":[-76.566,-9.71089],"type":"Point"}
}