{
  "type": "Feature",
  "properties": {
    "gn:admin1_code":"14",
    "gn:admin2_code":"1401.0",
    "gn:admin3_code":"140119.0",
    "gn:asciiname":"Huaca San Rosa",
    "gn:country_code":"PE",
    "gn:dem":79,
    "gn:feature_class":"P",
    "gn:feature_code":"PPL",
    "gn:name":"Huaca San Rosa",
    "gn:population":0,
    "gn:timezone":"America/Lima",
    "iso:country":"PE",
    "name:spa_x_preferred":[
        "Huaca San Rosa"
    ],
    "name:spa_x_variant":[
        "Santa Rosa"
    ],
    "wof:name":"Huaca San Rosa",
    "wof:placetype":"locality"
},
  "geometry": {"coordinates":[-79.62059000000001,-6.76922],"type":"Point"}
}