{
  "type": "Feature",
  "properties": {
    "gn:admin1_code":"9.0",
    "gn:admin2_code":"907.0",
    "gn:admin3_code":"90707.0",
    "gn:asciiname":"Tauribamba",
    "gn:country_code":"PE",
    "gn:dem":2956,
    "gn:feature_class":"P",
    "gn:feature_code":"PPL",
    "gn:name":"Tauribamba",
    "gn:population":0,
    "gn:timezone":"America/Lima",
    "iso:country":"PE",
    "wof:name":"Tauribamba",
    "wof:placetype":"locality"
},
  "geometry": {"coordinates":[-74.57984999999999,-12.03723],"type":"Point"}
}