{
  "type": "Feature",
  "properties": {
    "gn:admin1_code":"10.0",
    "gn:admin2_code":"1005.0",
    "gn:asciiname":"Dadococha",
    "gn:country_code":"PE",
    "gn:dem":4357,
    "gn:feature_class":"P",
    "gn:feature_code":"PPL",
    "gn:name":"Dadococha",
    "gn:population":0,
    "gn:timezone":"America/Lima",
    "iso:country":"PE",
    "wof:name":"Dadococha",
    "wof:placetype":"locality"
},
  "geometry": {"coordinates":[-76.96829,-9.58284],"type":"Point"}
}