{
  "type": "Feature",
  "properties": {
    "gn:admin1_code":"05",
    "gn:admin2_code":"506.0",
    "gn:admin3_code":"50612.0",
    "gn:asciiname":"Quesera",
    "gn:country_code":"PE",
    "gn:dem":3541,
    "gn:feature_class":"P",
    "gn:feature_code":"PPL",
    "gn:name":"Quesera",
    "gn:population":0,
    "gn:timezone":"America/Lima",
    "iso:country":"PE",
    "wof:name":"Quesera",
    "wof:placetype":"locality"
},
  "geometry": {"coordinates":[-74.70026999999997,-14.37969],"type":"Point"}
}