{
  "type": "Feature",
  "properties": {
    "gn:admin1_code":"01",
    "gn:admin2_code":"107.0",
    "gn:admin3_code":"10704.0",
    "gn:asciiname":"Papaya Baja",
    "gn:country_code":"PE",
    "gn:dem":370,
    "gn:feature_class":"P",
    "gn:feature_code":"PPL",
    "gn:name":"Papaya Baja",
    "gn:population":0,
    "gn:timezone":"America/Lima",
    "iso:country":"PE",
    "wof:name":"Papaya Baja",
    "wof:placetype":"locality"
},
  "geometry": {"coordinates":[-78.57919,-5.57285],"type":"Point"}
}