{
  "type": "Feature",
  "properties": {
    "gn:admin1_code":"2.0",
    "gn:admin2_code":"206.0",
    "gn:admin3_code":"20605.0",
    "gn:asciiname":"Saucipuquio",
    "gn:country_code":"PE",
    "gn:dem":3198,
    "gn:feature_class":"P",
    "gn:feature_code":"PPL",
    "gn:name":"Saucipuquio",
    "gn:population":0,
    "gn:timezone":"America/Lima",
    "iso:country":"PE",
    "wof:name":"Saucipuquio",
    "wof:placetype":"locality"
},
  "geometry": {"coordinates":[-77.70971999999998,-9.26972],"type":"Point"}
}