{
  "type": "Feature",
  "properties": {
    "gn:admin1_code":"20",
    "gn:admin2_code":"2006.0",
    "gn:admin3_code":"200608.0",
    "gn:asciiname":"Cabo Verde",
    "gn:country_code":"PE",
    "gn:dem":61,
    "gn:feature_class":"P",
    "gn:feature_code":"PPL",
    "gn:name":"Cabo Verde",
    "gn:population":0,
    "gn:timezone":"America/Lima",
    "iso:country":"PE",
    "wof:name":"Cabo Verde",
    "wof:placetype":"locality"
},
  "geometry": {"coordinates":[-80.68207,-4.83158],"type":"Point"}
}