{
  "type": "Feature",
  "properties": {
    "gn:admin1_code":"05",
    "gn:admin2_code":"501.0",
    "gn:admin3_code":"50106.0",
    "gn:asciiname":"Sunto Mojo",
    "gn:country_code":"PE",
    "gn:dem":3729,
    "gn:feature_class":"P",
    "gn:feature_code":"PPL",
    "gn:name":"Sunto Mojo",
    "gn:population":0,
    "gn:timezone":"America/Lima",
    "iso:country":"PE",
    "name:und_x_variant":[
        "Suntomocco",
        "Sunto Mojo"
    ],
    "wof:name":"Sunto Mojo",
    "wof:placetype":"locality"
},
  "geometry": {"coordinates":[-73.90328000000002,-13.33831],"type":"Point"}
}