{
  "type": "Feature",
  "properties": {
    "gn:admin1_code":"14",
    "gn:admin2_code":"1403.0",
    "gn:admin3_code":"140310.0",
    "gn:asciiname":"Corazon de Maria",
    "gn:country_code":"PE",
    "gn:dem":886,
    "gn:feature_class":"P",
    "gn:feature_code":"PPL",
    "gn:name":"Coraz\u00f3n de Mar\u00eda",
    "gn:population":0,
    "gn:timezone":"America/Lima",
    "iso:country":"PE",
    "name:und_x_variant":[
        "Carazon de Mar\u00eda",
        "Coraz\u00f3n de Mar\u00eda"
    ],
    "wof:name":"Corazon de Maria",
    "wof:placetype":"locality"
},
  "geometry": {"coordinates":[-79.53331999999997,-6.166],"type":"Point"}
}