{
  "type": "Feature",
  "properties": {
    "gn:admin1_code":"10.0",
    "gn:admin2_code":"1006.0",
    "gn:admin3_code":"100602.0",
    "gn:asciiname":"Topa",
    "gn:country_code":"PE",
    "gn:dem":760,
    "gn:feature_class":"P",
    "gn:feature_code":"PPL",
    "gn:name":"Topa",
    "gn:population":0,
    "gn:timezone":"America/Lima",
    "iso:country":"PE",
    "name:bih_x_preferred":[
        "\u0924\u094b\u092a\u093e"
    ],
    "name:bpy_x_preferred":[
        "\u09a4\u09cb\u09aa\u09be"
    ],
    "name:ind_x_preferred":[
        "Topa"
    ],
    "name:ita_x_preferred":[
        "Topa"
    ],
    "name:msa_x_preferred":[
        "Topa"
    ],
    "name:nld_x_preferred":[
        "Topa"
    ],
    "name:por_x_preferred":[
        "Topa"
    ],
    "name:spa_x_preferred":[
        "Topa"
    ],
    "name:vie_x_preferred":[
        "Topa"
    ],
    "wof:name":"Topa",
    "wof:placetype":"locality"
},
  "geometry": {"coordinates":[-75.84755,-9.27939],"type":"Point"}
}