{
  "type": "Feature",
  "properties": {
    "gn:admin1_code":"5",
    "gn:admin2_code":"510.0",
    "gn:admin3_code":"51001.0",
    "gn:asciiname":"Alcamenca",
    "gn:country_code":"PE",
    "gn:dem":2543,
    "gn:feature_class":"P",
    "gn:feature_code":"PPL",
    "gn:name":"Alcamenca",
    "gn:population":0,
    "gn:timezone":"America/Lima",
    "iso:country":"PE",
    "wof:name":"Alcamenca",
    "wof:placetype":"locality"
},
  "geometry": {"coordinates":[-74.10615,-13.66138],"type":"Point"}
}