{
  "type": "Feature",
  "properties": {
    "gn:admin1_code":"8",
    "gn:admin2_code":"806.0",
    "gn:admin3_code":"80603.0",
    "gn:asciiname":"Quispi Pata",
    "gn:country_code":"PE",
    "gn:dem":3484,
    "gn:feature_class":"P",
    "gn:feature_code":"PPL",
    "gn:name":"Quispi Pata",
    "gn:population":0,
    "gn:timezone":"America/Lima",
    "iso:country":"PE",
    "wof:name":"Quispi Pata",
    "wof:placetype":"locality"
},
  "geometry": {"coordinates":[-71.40389,-14.08583],"type":"Point"}
}