{
  "type": "Feature",
  "properties": {
    "gn:admin1_code":"22",
    "gn:admin2_code":"2207.0",
    "gn:admin3_code":"220702.0",
    "gn:asciiname":"Mariscal Castilla",
    "gn:country_code":"PE",
    "gn:dem":358,
    "gn:feature_class":"P",
    "gn:feature_code":"PPL",
    "gn:name":"Mariscal Castilla",
    "gn:population":0,
    "gn:timezone":"America/Lima",
    "iso:country":"PE",
    "name:spa_x_preferred":[
        "Mariscal Castilla"
    ],
    "wof:name":"Mariscal Castilla",
    "wof:placetype":"locality"
},
  "geometry": {"coordinates":[-76.39652,-6.72002],"type":"Point"}
}