{
  "type": "Feature",
  "properties": {
    "iso:country":"PE",
    "name:spa_x_preferred":[
        "En vivo: En la c\u00e1rcel de Santa Martha"
    ],
    "name:spa_x_variant":[
        "Santa Mar\u00eda"
    ],
    "qs:gn_country":"PE",
    "qs:gn_fcode":"PPL",
    "qs:gn_pop":14853,
    "qs:name":"Santa Martha",
    "qs:name_adm0":"Per\u00fa",
    "qs:name_adm1":"Lima Metropolitan Area",
    "qs:photos":0,
    "qs:photos_1k":0,
    "qs:photos_9k":0,
    "qs:photos_9r":0,
    "qs:photos_all":0,
    "qs:photos_sr":0,
    "qs:placetype":"Town",
    "qs:pop_sr":"6",
    "qs:woe_adm0":23424919,
    "wof:name":"Santa Martha",
    "wof:placetype":"locality",
    "wof:population":14853
},
  "geometry": {"coordinates":[-76.88892,-12.00883],"type":"Point"}
}