{
  "type": "Feature",
  "properties": {
    "gn:admin1_code":"22.0",
    "gn:admin2_code":"2206.0",
    "gn:admin3_code":"220603.0",
    "gn:asciiname":"La Morada",
    "gn:country_code":"PE",
    "gn:dem":2165,
    "gn:feature_class":"P",
    "gn:feature_code":"PPL",
    "gn:name":"La Morada",
    "gn:population":0,
    "gn:timezone":"America/Lima",
    "iso:country":"PE",
    "wof:name":"La Morada",
    "wof:placetype":"locality"
},
  "geometry": {"coordinates":[-77.51861,-6.95361],"type":"Point"}
}