{
  "type": "Feature",
  "properties": {
    "gn:admin1_code":"17.0",
    "gn:admin2_code":"1703.0",
    "gn:asciiname":"Collantes",
    "gn:country_code":"PE",
    "gn:dem":237,
    "gn:feature_class":"P",
    "gn:feature_code":"PPL",
    "gn:name":"Collantes",
    "gn:population":0,
    "gn:timezone":"America/Lima",
    "iso:country":"PE",
    "name:spa_x_preferred":[
        "Collantes"
    ],
    "wof:name":"Collantes",
    "wof:placetype":"locality"
},
  "geometry": {"coordinates":[-69.00464000000001,-11.91022],"type":"Point"}
}