{
  "type": "Feature",
  "properties": {
    "gn:admin1_code":"8.0",
    "gn:admin2_code":"801.0",
    "gn:admin3_code":"80102.0",
    "gn:asciiname":"Huancajrara",
    "gn:country_code":"PE",
    "gn:dem":3377,
    "gn:feature_class":"P",
    "gn:feature_code":"PPL",
    "gn:name":"Huancajrara",
    "gn:population":0,
    "gn:timezone":"America/Lima",
    "iso:country":"PE",
    "wof:name":"Huancajrara",
    "wof:placetype":"locality"
},
  "geometry": {"coordinates":[-72.04333000000003,-13.63222],"type":"Point"}
}