{
  "type": "Feature",
  "properties": {
    "gn:admin1_code":"3.0",
    "gn:admin2_code":"305.0",
    "gn:admin3_code":"30501.0",
    "gn:asciiname":"Canabamba",
    "gn:country_code":"PE",
    "gn:dem":3580,
    "gn:feature_class":"P",
    "gn:feature_code":"PPL",
    "gn:name":"Canabamba",
    "gn:population":0,
    "gn:timezone":"America/Lima",
    "iso:country":"PE",
    "wof:name":"Canabamba",
    "wof:placetype":"locality"
},
  "geometry": {"coordinates":[-72.19528000000003,-13.97556],"type":"Point"}
}