{
  "type": "Feature",
  "properties": {
    "gn:admin1_code":"12",
    "gn:admin2_code":"1209.0",
    "gn:admin3_code":"120909.0",
    "gn:asciiname":"Cashash",
    "gn:country_code":"PE",
    "gn:dem":4608,
    "gn:feature_class":"P",
    "gn:feature_code":"PPL",
    "gn:name":"Cashash",
    "gn:population":0,
    "gn:timezone":"America/Lima",
    "iso:country":"PE",
    "wof:name":"Cashash",
    "wof:placetype":"locality"
},
  "geometry": {"coordinates":[-75.60110999999998,-12.22639],"type":"Point"}
}