{
  "type": "Feature",
  "properties": {
    "gn:admin1_code":"11",
    "gn:admin2_code":"1101.0",
    "gn:admin3_code":"110102.0",
    "gn:asciiname":"Lopez",
    "gn:country_code":"PE",
    "gn:dem":423,
    "gn:feature_class":"P",
    "gn:feature_code":"PPL",
    "gn:name":"L\u00f3pez",
    "gn:population":0,
    "gn:timezone":"America/Lima",
    "iso:country":"PE",
    "name:und_x_variant":[
        "L\u00f3pez",
        "Hacienda L\u00f3pez"
    ],
    "wof:name":"Lopez",
    "wof:placetype":"locality"
},
  "geometry": {"coordinates":[-75.72078,-14.03533],"type":"Point"}
}