{
  "type": "Feature",
  "properties": {
    "gn:admin1_code":"18",
    "gn:admin2_code":"1802.0",
    "gn:admin3_code":"180205.0",
    "gn:asciiname":"Talahuaya",
    "gn:country_code":"PE",
    "gn:dem":2000,
    "gn:feature_class":"P",
    "gn:feature_code":"PPL",
    "gn:name":"Talahuaya",
    "gn:population":0,
    "gn:timezone":"America/Lima",
    "iso:country":"PE",
    "name:und_x_variant":[
        "Talahuay",
        "Talahuayo",
        "Talahuaya"
    ],
    "wof:name":"Talahuaya",
    "wof:placetype":"locality"
},
  "geometry": {"coordinates":[-71.1811,-16.73544],"type":"Point"}
}