{
  "type": "Feature",
  "properties": {
    "gn:admin1_code":"6.0",
    "gn:admin2_code":"608.0",
    "gn:admin3_code":"60801.0",
    "gn:asciiname":"Morro Solar",
    "gn:country_code":"PE",
    "gn:dem":703,
    "gn:feature_class":"P",
    "gn:feature_code":"PPL",
    "gn:name":"Morro Solar",
    "gn:population":0,
    "gn:timezone":"America/Lima",
    "iso:country":"PE",
    "wof:name":"Morro Solar",
    "wof:placetype":"locality"
},
  "geometry": {"coordinates":[-78.79666999999998,-5.71278],"type":"Point"}
}