{
  "type": "Feature",
  "properties": {
    "gn:admin1_code":"15",
    "gn:admin2_code":"1510.0",
    "gn:admin3_code":"151016.0",
    "gn:asciiname":"Parional",
    "gn:country_code":"PE",
    "gn:dem":4674,
    "gn:feature_class":"P",
    "gn:feature_code":"PPL",
    "gn:name":"Parional",
    "gn:population":0,
    "gn:timezone":"America/Lima",
    "iso:country":"PE",
    "wof:name":"Parional",
    "wof:placetype":"locality"
},
  "geometry": {"coordinates":[-75.67529999999999,-12.55982],"type":"Point"}
}