{
  "type": "Feature",
  "properties": {
    "gn:admin1_code":"21",
    "gn:admin2_code":"2105.0",
    "gn:admin3_code":"210502.0",
    "gn:asciiname":"Conchachiri",
    "gn:country_code":"PE",
    "gn:dem":4228,
    "gn:feature_class":"P",
    "gn:feature_code":"PPL",
    "gn:name":"Conchachiri",
    "gn:population":0,
    "gn:timezone":"America/Lima",
    "iso:country":"PE",
    "wof:name":"Conchachiri",
    "wof:placetype":"locality"
},
  "geometry": {"coordinates":[-69.71427,-17.28219],"type":"Point"}
}