{
  "type": "Feature",
  "properties": {
    "gn:admin1_code":"9.0",
    "gn:admin2_code":"906.0",
    "gn:admin3_code":"90607.0",
    "gn:asciiname":"Uchupuquio",
    "gn:country_code":"PE",
    "gn:dem":4699,
    "gn:feature_class":"P",
    "gn:feature_code":"PPL",
    "gn:name":"Uchupuquio",
    "gn:population":0,
    "gn:timezone":"America/Lima",
    "iso:country":"PE",
    "wof:name":"Uchupuquio",
    "wof:placetype":"locality"
},
  "geometry": {"coordinates":[-74.93517,-13.2051],"type":"Point"}
}