{
  "type": "Feature",
  "properties": {
    "gn:admin1_code":"9",
    "gn:admin2_code":"904.0",
    "gn:admin3_code":"90405.0",
    "gn:asciiname":"Conas",
    "gn:country_code":"PE",
    "gn:dem":3725,
    "gn:feature_class":"P",
    "gn:feature_code":"PPL",
    "gn:name":"Co\u00f1as",
    "gn:population":0,
    "gn:timezone":"America/Lima",
    "iso:country":"PE",
    "wof:name":"Conas",
    "wof:placetype":"locality"
},
  "geometry": {"coordinates":[-75.54722,-12.96944],"type":"Point"}
}