{
  "type": "Feature",
  "properties": {
    "gn:admin1_code":"10.0",
    "gn:admin2_code":"1008.0",
    "gn:admin3_code":"100803.0",
    "gn:asciiname":"Cuchapampa",
    "gn:country_code":"PE",
    "gn:dem":2421,
    "gn:feature_class":"P",
    "gn:feature_code":"PPL",
    "gn:name":"Cuchapampa",
    "gn:population":0,
    "gn:timezone":"America/Lima",
    "iso:country":"PE",
    "wof:name":"Cuchapampa",
    "wof:placetype":"locality"
},
  "geometry": {"coordinates":[-76.03059,-9.93757],"type":"Point"}
}