{
  "type": "Feature",
  "properties": {
    "gn:admin1_code":"12",
    "gn:admin2_code":"1201.0",
    "gn:admin3_code":"120124.0",
    "gn:asciiname":"Aychana",
    "gn:country_code":"PE",
    "gn:dem":3706,
    "gn:feature_class":"P",
    "gn:feature_code":"PPL",
    "gn:name":"Aychana",
    "gn:population":0,
    "gn:timezone":"America/Lima",
    "iso:country":"PE",
    "wof:name":"Aychana",
    "wof:placetype":"locality"
},
  "geometry": {"coordinates":[-74.97658,-11.87988],"type":"Point"}
}