{
  "type": "Feature",
  "properties": {
    "gn:admin1_code":"03",
    "gn:admin2_code":"301.0",
    "gn:admin3_code":"30104.0",
    "gn:asciiname":"Larata",
    "gn:country_code":"PE",
    "gn:dem":2891,
    "gn:feature_class":"P",
    "gn:feature_code":"PPL",
    "gn:name":"Larata",
    "gn:population":0,
    "gn:timezone":"America/Lima",
    "iso:country":"PE",
    "wof:name":"Larata",
    "wof:placetype":"locality"
},
  "geometry": {"coordinates":[-72.46666999999999,-13.68333],"type":"Point"}
}