{
  "type": "Feature",
  "properties": {
    "gn:admin1_code":"13.0",
    "gn:admin2_code":"1304.0",
    "gn:admin3_code":"130401.0",
    "gn:asciiname":"Manduma",
    "gn:country_code":"PE",
    "gn:dem":121,
    "gn:feature_class":"P",
    "gn:feature_code":"PPL",
    "gn:name":"Manduma",
    "gn:population":0,
    "gn:timezone":"America/Lima",
    "iso:country":"PE",
    "name:spa_x_preferred":[
        "Manduma"
    ],
    "wof:name":"Manduma",
    "wof:placetype":"locality"
},
  "geometry": {"coordinates":[-79.41923,-7.2343],"type":"Point"}
}