{
  "type": "Feature",
  "properties": {
    "gn:admin1_code":"8",
    "gn:admin2_code":"812.0",
    "gn:admin3_code":"81210.0",
    "gn:asciiname":"Mallma",
    "gn:country_code":"PE",
    "gn:dem":4171,
    "gn:feature_class":"P",
    "gn:feature_code":"PPL",
    "gn:name":"Mallma",
    "gn:population":0,
    "gn:timezone":"America/Lima",
    "iso:country":"PE",
    "wof:name":"Mallma",
    "wof:placetype":"locality"
},
  "geometry": {"coordinates":[-71.20525000000001,-13.60439],"type":"Point"}
}