{
  "type": "Feature",
  "properties": {
    "gn:admin1_code":"11.0",
    "gn:admin2_code":"1102.0",
    "gn:admin3_code":"110208.0",
    "gn:asciiname":"Chucchupunta",
    "gn:country_code":"PE",
    "gn:dem":3834,
    "gn:feature_class":"P",
    "gn:feature_code":"PPL",
    "gn:name":"Chucchupunta",
    "gn:population":0,
    "gn:timezone":"America/Lima",
    "iso:country":"PE",
    "name:spa_x_preferred":[
        "Chucchupunta"
    ],
    "wof:name":"Chucchupunta",
    "wof:placetype":"locality"
},
  "geometry": {"coordinates":[-75.83637,-13.11894],"type":"Point"}
}