{
  "type": "Feature",
  "properties": {
    "gn:admin1_code":"12.0",
    "gn:admin2_code":"1208.0",
    "gn:admin3_code":"120809.0",
    "gn:asciiname":"Suytuc",
    "gn:country_code":"PE",
    "gn:dem":4465,
    "gn:feature_class":"P",
    "gn:feature_code":"PPL",
    "gn:name":"Suytuc",
    "gn:population":0,
    "gn:timezone":"America/Lima",
    "iso:country":"PE",
    "wof:name":"Suytuc",
    "wof:placetype":"locality"
},
  "geometry": {"coordinates":[-75.97471999999998,-11.80395],"type":"Point"}
}