{
  "type": "Feature",
  "properties": {
    "gn:admin1_code":"04",
    "gn:admin2_code":"408.0",
    "gn:admin3_code":"40807.0",
    "gn:asciiname":"Hacienda Huana",
    "gn:country_code":"PE",
    "gn:dem":1641,
    "gn:feature_class":"P",
    "gn:feature_code":"PPL",
    "gn:name":"Hacienda Hua\u00f1a",
    "gn:population":0,
    "gn:timezone":"America/Lima",
    "iso:country":"PE",
    "name:spa_x_preferred":[
        "Hacienda Hua\u00f1a"
    ],
    "wof:name":"Hacienda Huana",
    "wof:placetype":"locality"
},
  "geometry": {"coordinates":[-73.05136,-15.30063],"type":"Point"}
}