{
  "type": "Feature",
  "properties": {
    "gn:admin1_code":"15",
    "gn:admin2_code":"1504.0",
    "gn:admin3_code":"150402.0",
    "gn:asciiname":"Arahuay",
    "gn:cc2":"PE",
    "gn:country_code":"PE",
    "gn:dem":2559,
    "gn:feature_class":"P",
    "gn:feature_code":"PPLA3",
    "gn:name":"Arahuay",
    "gn:population":0,
    "gn:timezone":"America/Lima",
    "iso:country":"PE",
    "name:spa_x_preferred":[
        "Arahuay"
    ],
    "name:und_x_variant":[
        "Araguay",
        "Arahuai",
        "Arahuay"
    ],
    "wof:name":"Arahuay",
    "wof:placetype":"locality"
},
  "geometry": {"coordinates":[-76.66944000000002,-11.62222],"type":"Point"}
}