{
  "type": "Feature",
  "properties": {
    "gn:admin1_code":"06",
    "gn:admin2_code":"609.0",
    "gn:asciiname":"Ternero Muerto",
    "gn:country_code":"PE",
    "gn:dem":1858,
    "gn:feature_class":"P",
    "gn:feature_code":"PPL",
    "gn:name":"Ternero Muerto",
    "gn:population":0,
    "gn:timezone":"America/Lima",
    "iso:country":"PE",
    "name:und_x_variant":[
        "Chimara",
        "Ternero Muerto"
    ],
    "wof:name":"Ternero Muerto",
    "wof:placetype":"locality"
},
  "geometry": {"coordinates":[-79.23639,-4.97528],"type":"Point"}
}