{
  "type": "Feature",
  "properties": {
    "gn:admin1_code":"05",
    "gn:admin2_code":"506.0",
    "gn:admin3_code":"50609.0",
    "gn:asciiname":"Tocahuasi",
    "gn:country_code":"PE",
    "gn:dem":2444,
    "gn:feature_class":"P",
    "gn:feature_code":"PPL",
    "gn:name":"Tocahuasi",
    "gn:population":0,
    "gn:timezone":"America/Lima",
    "iso:country":"PE",
    "name:und_x_variant":[
        "Tocahuasi Hacienda",
        "Tocahuasi"
    ],
    "wof:name":"Tocahuasi",
    "wof:placetype":"locality"
},
  "geometry": {"coordinates":[-74.80543,-14.67612],"type":"Point"}
}