{
  "type": "Feature",
  "properties": {
    "gn:admin1_code":"09",
    "gn:admin2_code":"903.0",
    "gn:admin3_code":"90305.0",
    "gn:asciiname":"Yanachoje",
    "gn:country_code":"PE",
    "gn:dem":3361,
    "gn:feature_class":"P",
    "gn:feature_code":"PPL",
    "gn:name":"Yanachoje",
    "gn:population":0,
    "gn:timezone":"America/Lima",
    "iso:country":"PE",
    "name:und_x_variant":[
        "Yanachoccue"
    ],
    "wof:name":"Yanachoje",
    "wof:placetype":"locality"
},
  "geometry": {"coordinates":[-74.41274,-12.97004],"type":"Point"}
}