{
  "type": "Feature",
  "properties": {
    "gn:admin1_code":"24",
    "gn:admin2_code":"2401.0",
    "gn:admin3_code":"240104.0",
    "gn:asciiname":"Yerbales",
    "gn:country_code":"PE",
    "gn:dem":637,
    "gn:feature_class":"P",
    "gn:feature_code":"PPL",
    "gn:name":"Yerbales",
    "gn:population":0,
    "gn:timezone":"America/Lima",
    "iso:country":"PE",
    "wof:name":"Yerbales",
    "wof:placetype":"locality"
},
  "geometry": {"coordinates":[-80.31667,-3.83333],"type":"Point"}
}