{
  "type": "Feature",
  "properties": {
    "gn:admin1_code":"04",
    "gn:admin2_code":"403.0",
    "gn:admin3_code":"40308.0",
    "gn:asciiname":"Hacienda Caramba",
    "gn:country_code":"PE",
    "gn:dem":751,
    "gn:feature_class":"P",
    "gn:feature_code":"PPL",
    "gn:name":"Hacienda Caramba",
    "gn:population":0,
    "gn:timezone":"America/Lima",
    "iso:country":"PE",
    "name:und_x_variant":[
        "Caramba",
        "Hacienda Caramba"
    ],
    "wof:name":"Hacienda Caramba",
    "wof:placetype":"locality"
},
  "geometry": {"coordinates":[-73.92779,-15.7743],"type":"Point"}
}