{
  "type": "Feature",
  "properties": {
    "gn:admin1_code":"18",
    "gn:admin2_code":"1801.0",
    "gn:admin3_code":"180105.0",
    "gn:asciiname":"Pumasolo",
    "gn:country_code":"PE",
    "gn:dem":4604,
    "gn:feature_class":"P",
    "gn:feature_code":"PPL",
    "gn:name":"Pumasolo",
    "gn:population":0,
    "gn:timezone":"America/Lima",
    "iso:country":"PE",
    "wof:name":"Pumasolo",
    "wof:placetype":"locality"
},
  "geometry": {"coordinates":[-70.57989999999999,-16.61768],"type":"Point"}
}