{
  "type": "Feature",
  "properties": {
    "gn:admin1_code":"21",
    "gn:admin2_code":"2107.0",
    "gn:admin3_code":"210704.0",
    "gn:asciiname":"Pichacane",
    "gn:country_code":"PE",
    "gn:dem":3881,
    "gn:feature_class":"P",
    "gn:feature_code":"PPL",
    "gn:name":"Pichacane",
    "gn:population":0,
    "gn:timezone":"America/Lima",
    "iso:country":"PE",
    "name:und_x_variant":[
        "Hacienda Pichacane",
        "Pichacane"
    ],
    "wof:name":"Pichacane",
    "wof:placetype":"locality"
},
  "geometry": {"coordinates":[-70.32203,-15.19766],"type":"Point"}
}