{
  "type": "Feature",
  "properties": {
    "gn:admin1_code":"15",
    "gn:admin2_code":"1510.0",
    "gn:admin3_code":"151033.0",
    "gn:asciiname":"Quispicancha",
    "gn:country_code":"PE",
    "gn:dem":4278,
    "gn:feature_class":"P",
    "gn:feature_code":"PPL",
    "gn:name":"Quispicancha",
    "gn:population":0,
    "gn:timezone":"America/Lima",
    "iso:country":"PE",
    "wof:name":"Quispicancha",
    "wof:placetype":"locality"
},
  "geometry": {"coordinates":[-75.82611,-12.18833],"type":"Point"}
}