{
  "type": "Feature",
  "properties": {
    "gn:admin1_code":"14",
    "gn:admin2_code":"1403.0",
    "gn:admin3_code":"140308.0",
    "gn:asciiname":"Querpon Viejo",
    "gn:cc2":"PE",
    "gn:country_code":"PE",
    "gn:dem":131,
    "gn:feature_class":"P",
    "gn:feature_code":"PPL",
    "gn:name":"Querp\u00f3n Viejo",
    "gn:population":0,
    "gn:timezone":"America/Lima",
    "iso:country":"PE",
    "name:und_x_variant":[
        "Querpon Ciudad",
        "Querp\u00f3n Viejo"
    ],
    "wof:name":"Querpon Viejo",
    "wof:placetype":"locality"
},
  "geometry": {"coordinates":[-79.88333,-5.68333],"type":"Point"}
}