{
  "type": "Feature",
  "properties": {
    "gn:admin1_code":"04",
    "gn:admin2_code":"401.0",
    "gn:admin3_code":"40128.0",
    "gn:asciiname":"Yura Viejo",
    "gn:country_code":"PE",
    "gn:dem":2625,
    "gn:feature_class":"P",
    "gn:feature_code":"PPL",
    "gn:name":"Yura Viejo",
    "gn:population":0,
    "gn:timezone":"America/Lima",
    "iso:country":"PE",
    "wof:name":"Yura Viejo",
    "wof:placetype":"locality"
},
  "geometry": {"coordinates":[-71.70278,-16.21778],"type":"Point"}
}