{
  "type": "Feature",
  "properties": {
    "gn:admin1_code":"23",
    "gn:admin2_code":"2304.0",
    "gn:admin3_code":"230408.0",
    "gn:asciiname":"Viluyo",
    "gn:country_code":"PE",
    "gn:dem":4530,
    "gn:feature_class":"P",
    "gn:feature_code":"PPL",
    "gn:name":"Viluyo",
    "gn:population":0,
    "gn:timezone":"America/Lima",
    "iso:country":"PE",
    "wof:name":"Viluyo",
    "wof:placetype":"locality"
},
  "geometry": {"coordinates":[-69.96666999999999,-17.33333],"type":"Point"}
}