{
  "type": "Feature",
  "properties": {
    "gn:admin1_code":"22.0",
    "gn:admin2_code":"2202.0",
    "gn:admin3_code":"220201.0",
    "gn:asciiname":"Valencia",
    "gn:country_code":"PE",
    "gn:dem":261,
    "gn:feature_class":"P",
    "gn:feature_code":"PPL",
    "gn:name":"Valencia",
    "gn:population":0,
    "gn:timezone":"America/Lima",
    "iso:country":"PE",
    "name:spa_x_preferred":[
        "Valencia"
    ],
    "wof:name":"Valencia",
    "wof:placetype":"locality"
},
  "geometry": {"coordinates":[-76.56748,-7.03775],"type":"Point"}
}