{
  "type": "Feature",
  "properties": {
    "gn:admin1_code":"10.0",
    "gn:admin2_code":"1001.0",
    "gn:admin3_code":"100109.0",
    "gn:asciiname":"Quera Pampa",
    "gn:country_code":"PE",
    "gn:dem":3529,
    "gn:feature_class":"P",
    "gn:feature_code":"PPL",
    "gn:name":"Quera Pampa",
    "gn:population":0,
    "gn:timezone":"America/Lima",
    "iso:country":"PE",
    "wof:name":"Quera Pampa",
    "wof:placetype":"locality"
},
  "geometry": {"coordinates":[-76.41011999999998,-9.7808],"type":"Point"}
}