{
  "type": "Feature",
  "properties": {
    "gn:admin1_code":"05",
    "gn:admin2_code":"506.0",
    "gn:admin3_code":"50605.0",
    "gn:asciiname":"Hualshua",
    "gn:country_code":"PE",
    "gn:dem":3346,
    "gn:feature_class":"P",
    "gn:feature_code":"PPL",
    "gn:name":"Hualshua",
    "gn:population":0,
    "gn:timezone":"America/Lima",
    "iso:country":"PE",
    "wof:name":"Hualshua",
    "wof:placetype":"locality"
},
  "geometry": {"coordinates":[-73.83333,-14.96667],"type":"Point"}
}