{
  "type": "Feature",
  "properties": {
    "gn:admin1_code":"12",
    "gn:admin2_code":"1207.0",
    "gn:admin3_code":"120701.0",
    "gn:asciiname":"Palcapacha",
    "gn:country_code":"PE",
    "gn:dem":3727,
    "gn:feature_class":"P",
    "gn:feature_code":"PPL",
    "gn:name":"Palcapacha",
    "gn:population":0,
    "gn:timezone":"America/Lima",
    "iso:country":"PE",
    "name:und_x_variant":[
        "Palcapaccha"
    ],
    "wof:name":"Palcapacha",
    "wof:placetype":"locality"
},
  "geometry": {"coordinates":[-75.80790999999998,-11.46559],"type":"Point"}
}