{
  "type": "Feature",
  "properties": {
    "gn:admin1_code":"05",
    "gn:admin2_code":"501.0",
    "gn:admin3_code":"50112.0",
    "gn:asciiname":"Yanayaco",
    "gn:country_code":"PE",
    "gn:dem":3188,
    "gn:feature_class":"P",
    "gn:feature_code":"PPL",
    "gn:name":"Yanayaco",
    "gn:population":0,
    "gn:timezone":"America/Lima",
    "iso:country":"PE",
    "name:und_x_variant":[
        "Hacienda Yanayaco"
    ],
    "wof:name":"Yanayaco",
    "wof:placetype":"locality"
},
  "geometry": {"coordinates":[-74.29115,-13.18807],"type":"Point"}
}