{
  "type": "Feature",
  "properties": {
    "gn:admin1_code":"15",
    "gn:admin2_code":"1509.0",
    "gn:admin3_code":"150903.0",
    "gn:asciiname":"Shampuy",
    "gn:country_code":"PE",
    "gn:dem":3776,
    "gn:feature_class":"P",
    "gn:feature_code":"PPL",
    "gn:name":"Shampuy",
    "gn:population":0,
    "gn:timezone":"America/Lima",
    "iso:country":"PE",
    "wof:name":"Shampuy",
    "wof:placetype":"locality"
},
  "geometry": {"coordinates":[-77.00111,-10.76556],"type":"Point"}
}