{
  "type": "Feature",
  "properties": {
    "gn:admin1_code":"16.0",
    "gn:admin2_code":"1601.0",
    "gn:admin3_code":"160105.0",
    "gn:asciiname":"Israel",
    "gn:country_code":"PE",
    "gn:dem":84,
    "gn:feature_class":"P",
    "gn:feature_code":"PPL",
    "gn:name":"Israel",
    "gn:population":0,
    "gn:timezone":"America/Lima",
    "iso:country":"PE",
    "wof:name":"Israel",
    "wof:placetype":"locality"
},
  "geometry": {"coordinates":[-72.33351999999999,-3.63998],"type":"Point"}
}