{
  "type": "Feature",
  "properties": {
    "gn:admin1_code":"11",
    "gn:admin2_code":"1104.0",
    "gn:admin3_code":"110401.0",
    "gn:asciiname":"Moyaque",
    "gn:country_code":"PE",
    "gn:dem":401,
    "gn:feature_class":"P",
    "gn:feature_code":"PPL",
    "gn:name":"Moyaque",
    "gn:population":0,
    "gn:timezone":"America/Lima",
    "iso:country":"PE",
    "name:und_x_variant":[
        "Moyaque Hacienda",
        "Moyaque"
    ],
    "wof:name":"Moyaque",
    "wof:placetype":"locality"
},
  "geometry": {"coordinates":[-75.16670000000001,-14.51672],"type":"Point"}
}