{
  "type": "Feature",
  "properties": {
    "gn:admin1_code":"05",
    "gn:admin2_code":"501.0",
    "gn:admin3_code":"50111.0",
    "gn:asciiname":"Pablopata",
    "gn:country_code":"PE",
    "gn:dem":2896,
    "gn:feature_class":"P",
    "gn:feature_code":"PPL",
    "gn:name":"Pablopata",
    "gn:population":0,
    "gn:timezone":"America/Lima",
    "iso:country":"PE",
    "wof:name":"Pablopata",
    "wof:placetype":"locality"
},
  "geometry": {"coordinates":[-74.37269000000001,-13.03957],"type":"Point"}
}