{
  "type": "Feature",
  "properties": {
    "gn:admin1_code":"21",
    "gn:admin2_code":"2112.0",
    "gn:admin3_code":"211204.0",
    "gn:asciiname":"Joneline",
    "gn:country_code":"PE",
    "gn:dem":3330,
    "gn:feature_class":"P",
    "gn:feature_code":"PPL",
    "gn:name":"Jo\u00f1eline",
    "gn:population":0,
    "gn:timezone":"America/Lima",
    "iso:country":"PE",
    "wof:name":"Joneline",
    "wof:placetype":"locality"
},
  "geometry": {"coordinates":[-69.60168,-14.35194],"type":"Point"}
}