{
  "type": "Feature",
  "properties": {
    "gn:admin1_code":"12",
    "gn:admin2_code":"1201.0",
    "gn:admin3_code":"120135.0",
    "gn:asciiname":"Putac",
    "gn:country_code":"PE",
    "gn:dem":3857,
    "gn:feature_class":"P",
    "gn:feature_code":"PPL",
    "gn:name":"Putac",
    "gn:population":0,
    "gn:timezone":"America/Lima",
    "iso:country":"PE",
    "wof:name":"Putac",
    "wof:placetype":"locality"
},
  "geometry": {"coordinates":[-74.76028000000002,-11.71194],"type":"Point"}
}