{
  "type": "Feature",
  "properties": {
    "gn:admin1_code":"04",
    "gn:admin2_code":"401.0",
    "gn:admin3_code":"40114.0",
    "gn:asciiname":"Chujomolle",
    "gn:country_code":"PE",
    "gn:dem":3730,
    "gn:feature_class":"P",
    "gn:feature_code":"PPL",
    "gn:name":"Chujomolle",
    "gn:population":0,
    "gn:timezone":"America/Lima",
    "iso:country":"PE",
    "wof:name":"Chujomolle",
    "wof:placetype":"locality"
},
  "geometry": {"coordinates":[-71.28333000000001,-16.53333],"type":"Point"}
}