{
  "type": "Feature",
  "properties": {
    "iso:country":"PE",
    "name:ceb_x_preferred":[
        "Ingenio"
    ],
    "name:ita_x_preferred":[
        "Ingenio"
    ],
    "name:nld_x_preferred":[
        "Ingenio"
    ],
    "name:por_x_preferred":[
        "Ingenio"
    ],
    "name:spa_x_preferred":[
        "Ingenio"
    ],
    "name:swe_x_preferred":[
        "Ingenio"
    ],
    "qs:gn_pop":0,
    "qs:name":"Ingenio",
    "qs:name_adm0":"Per\u00fa",
    "qs:name_adm1":"Ica",
    "qs:photos":11,
    "qs:photos_1k":2,
    "qs:photos_9k":1,
    "qs:photos_9r":1,
    "qs:photos_all":11,
    "qs:photos_sr":1,
    "qs:placetype":"Town",
    "qs:pop_sr":"0",
    "qs:woe_adm0":23424919,
    "wd:wordcount":68,
    "wof:name":"Ingenio",
    "wof:placetype":"locality"
},
  "geometry": {"coordinates":[-75.09979199999999,-14.74301],"type":"Point"}
}