{
  "type": "Feature",
  "properties": {
    "gn:admin1_code":"4",
    "gn:admin2_code":"403.0",
    "gn:admin3_code":"40305.0",
    "gn:asciiname":"Monasi",
    "gn:country_code":"PE",
    "gn:dem":46,
    "gn:feature_class":"P",
    "gn:feature_code":"PPL",
    "gn:name":"Monasi",
    "gn:population":0,
    "gn:timezone":"America/Lima",
    "iso:country":"PE",
    "wof:name":"Monasi",
    "wof:placetype":"locality"
},
  "geometry": {"coordinates":[-74.6392,-15.5863],"type":"Point"}
}