{
  "type": "Feature",
  "properties": {
    "gn:admin1_code":"15",
    "gn:admin2_code":"1505.0",
    "gn:admin3_code":"150501.0",
    "gn:asciiname":"Monte Jato",
    "gn:country_code":"PE",
    "gn:dem":69,
    "gn:feature_class":"P",
    "gn:feature_code":"PPL",
    "gn:name":"Monte Jato",
    "gn:population":0,
    "gn:timezone":"America/Lima",
    "iso:country":"PE",
    "name:und_x_variant":[
        "Montejato Hacienda",
        "Montejato",
        "Monte Jato"
    ],
    "wof:name":"Monte Jato",
    "wof:placetype":"locality"
},
  "geometry": {"coordinates":[-76.34658,-13.10732],"type":"Point"}
}