{
  "type": "Feature",
  "properties": {
    "gn:admin1_code":"1.0",
    "gn:admin2_code":"101.0",
    "gn:admin3_code":"10105.0",
    "gn:asciiname":"Yuramarca",
    "gn:country_code":"PE",
    "gn:dem":2676,
    "gn:feature_class":"P",
    "gn:feature_code":"PPL",
    "gn:name":"Yuramarca",
    "gn:population":0,
    "gn:timezone":"America/Lima",
    "iso:country":"PE",
    "wof:name":"Yuramarca",
    "wof:placetype":"locality"
},
  "geometry": {"coordinates":[-77.80032,-6.03096],"type":"Point"}
}