{
  "type": "Feature",
  "properties": {
    "gn:admin1_code":"13",
    "gn:admin2_code":"1301.0",
    "gn:admin3_code":"130106.0",
    "gn:asciiname":"Barraza",
    "gn:cc2":"PE",
    "gn:country_code":"PE",
    "gn:dem":40,
    "gn:feature_class":"P",
    "gn:feature_code":"PPL",
    "gn:name":"Barraza",
    "gn:population":0,
    "gn:timezone":"America/Lima",
    "iso:country":"PE",
    "name:und_x_variant":[
        "Barraza Hacienda",
        "Barraza"
    ],
    "wof:name":"Barraza",
    "wof:placetype":"locality"
},
  "geometry": {"coordinates":[-78.98333000000002,-8.11667],"type":"Point"}
}