{
  "type": "Feature",
  "properties": {
    "gn:admin1_code":"21.0",
    "gn:admin2_code":"2105.0",
    "gn:admin3_code":"210502.0",
    "gn:asciiname":"Chontacollo",
    "gn:country_code":"PE",
    "gn:dem":4280,
    "gn:feature_class":"P",
    "gn:feature_code":"PPL",
    "gn:name":"Chontacollo",
    "gn:population":0,
    "gn:timezone":"America/Lima",
    "iso:country":"PE",
    "wof:name":"Chontacollo",
    "wof:placetype":"locality"
},
  "geometry": {"coordinates":[-69.6126,-17.14894],"type":"Point"}
}