{
  "type": "Feature",
  "properties": {
    "gn:admin1_code":"2.0",
    "gn:admin2_code":"201.0",
    "gn:admin3_code":"20102.0",
    "gn:asciiname":"Pallac",
    "gn:country_code":"PE",
    "gn:dem":3024,
    "gn:feature_class":"P",
    "gn:feature_code":"PPL",
    "gn:name":"Pallac",
    "gn:population":0,
    "gn:timezone":"America/Lima",
    "iso:country":"PE",
    "wof:name":"Pallac",
    "wof:placetype":"locality"
},
  "geometry": {"coordinates":[-77.81610999999999,-9.46472],"type":"Point"}
}