{
  "type": "Feature",
  "properties": {
    "gn:admin1_code":"5.0",
    "gn:admin2_code":"504.0",
    "gn:admin3_code":"50402.0",
    "gn:asciiname":"Cayramayo",
    "gn:country_code":"PE",
    "gn:dem":4247,
    "gn:feature_class":"P",
    "gn:feature_code":"PPL",
    "gn:name":"Cayramayo",
    "gn:population":0,
    "gn:timezone":"America/Lima",
    "iso:country":"PE",
    "wof:name":"Cayramayo",
    "wof:placetype":"locality"
},
  "geometry": {"coordinates":[-74.24318000000002,-12.62933],"type":"Point"}
}