{
  "type": "Feature",
  "properties": {
    "gn:admin1_code":"12",
    "gn:admin2_code":"1207.0",
    "gn:admin3_code":"120707.0",
    "gn:asciiname":"Cucun",
    "gn:country_code":"PE",
    "gn:dem":3872,
    "gn:feature_class":"P",
    "gn:feature_code":"PPL",
    "gn:name":"Cucun",
    "gn:population":0,
    "gn:timezone":"America/Lima",
    "iso:country":"PE",
    "wof:name":"Cucun",
    "wof:placetype":"locality"
},
  "geometry": {"coordinates":[-75.74044000000001,-11.27289],"type":"Point"}
}