{
  "type": "Feature",
  "properties": {
    "gn:admin1_code":"11.0",
    "gn:admin2_code":"1101.0",
    "gn:admin3_code":"110101.0",
    "gn:asciiname":"Manrique",
    "gn:country_code":"PE",
    "gn:dem":402,
    "gn:feature_class":"P",
    "gn:feature_code":"PPLL",
    "gn:name":"Manrique",
    "gn:population":0,
    "gn:timezone":"America/Lima",
    "iso:country":"PE",
    "wof:name":"Manrique",
    "wof:placetype":"locality"
},
  "geometry": {"coordinates":[-75.73971999999998,-14.08528],"type":"Point"}
}