{
  "type": "Feature",
  "properties": {
    "gn:admin1_code":"11",
    "gn:admin2_code":"1103.0",
    "gn:admin3_code":"110301.0",
    "gn:asciiname":"Hacienda Tunga",
    "gn:country_code":"PE",
    "gn:dem":387,
    "gn:feature_class":"P",
    "gn:feature_code":"PPL",
    "gn:name":"Hacienda Tunga",
    "gn:population":0,
    "gn:timezone":"America/Lima",
    "iso:country":"PE",
    "name:und_x_variant":[
        "Tunga",
        "Tunga Hacienda",
        "Hacienda Tunga"
    ],
    "wof:name":"Hacienda Tunga",
    "wof:placetype":"locality"
},
  "geometry": {"coordinates":[-75.1156,-14.94374],"type":"Point"}
}