{
  "type": "Feature",
  "properties": {
    "gn:admin1_code":"12",
    "gn:admin2_code":"1202.0",
    "gn:admin3_code":"120214.0",
    "gn:asciiname":"San Juanpampa",
    "gn:country_code":"PE",
    "gn:dem":3643,
    "gn:feature_class":"P",
    "gn:feature_code":"PPL",
    "gn:name":"San Juanpampa",
    "gn:population":0,
    "gn:timezone":"America/Lima",
    "iso:country":"PE",
    "wof:name":"San Juanpampa",
    "wof:placetype":"locality"
},
  "geometry": {"coordinates":[-75.55781999999998,-12.02054],"type":"Point"}
}