{
  "type": "Feature",
  "properties": {
    "gn:admin1_code":"15",
    "gn:admin2_code":"1503.0",
    "gn:admin3_code":"150303.0",
    "gn:asciiname":"Esperanza",
    "gn:country_code":"PE",
    "gn:dem":4742,
    "gn:feature_class":"P",
    "gn:feature_code":"PPL",
    "gn:name":"Esperanza",
    "gn:population":0,
    "gn:timezone":"America/Lima",
    "iso:country":"PE",
    "wof:name":"Esperanza",
    "wof:placetype":"locality"
},
  "geometry": {"coordinates":[-76.96666999999999,-10.68333],"type":"Point"}
}