{
  "type": "Feature",
  "properties": {
    "gn:admin1_code":"04",
    "gn:admin2_code":"406.0",
    "gn:admin3_code":"40608.0",
    "gn:asciiname":"Choco",
    "gn:country_code":"PE",
    "gn:dem":586,
    "gn:feature_class":"P",
    "gn:feature_code":"PPL",
    "gn:name":"Choco",
    "gn:population":0,
    "gn:timezone":"America/Lima",
    "iso:country":"PE",
    "wof:name":"Choco",
    "wof:placetype":"locality"
},
  "geometry": {"coordinates":[-73.08278,-15.83444],"type":"Point"}
}