{
  "type": "Feature",
  "properties": {
    "gn:admin1_code":"8.0",
    "gn:admin2_code":"810.0",
    "gn:admin3_code":"81003.0",
    "gn:asciiname":"Racrapampa",
    "gn:country_code":"PE",
    "gn:dem":3312,
    "gn:feature_class":"P",
    "gn:feature_code":"PPL",
    "gn:name":"Racrapampa",
    "gn:population":0,
    "gn:timezone":"America/Lima",
    "iso:country":"PE",
    "wof:name":"Racrapampa",
    "wof:placetype":"locality"
},
  "geometry": {"coordinates":[-72.07833000000002,-13.87083],"type":"Point"}
}