{
  "type": "Feature",
  "properties": {
    "gn:admin1_code":"04",
    "gn:admin2_code":"405.0",
    "gn:admin3_code":"40504.0",
    "gn:asciiname":"Jayuni",
    "gn:country_code":"PE",
    "gn:dem":4485,
    "gn:feature_class":"P",
    "gn:feature_code":"PPL",
    "gn:name":"Jayuni",
    "gn:population":0,
    "gn:timezone":"America/Lima",
    "iso:country":"PE",
    "name:und_x_variant":[
        "Hacienda Jayune",
        "Jayuni"
    ],
    "name:zho_x_preferred":[
        "\u54c8\u5c24\u5c3c\u5c71"
    ],
    "wof:name":"Jayuni",
    "wof:placetype":"locality"
},
  "geometry": {"coordinates":[-71.02415000000001,-15.57127],"type":"Point"}
}