{
  "type": "Feature",
  "properties": {
    "gn:admin1_code":"21",
    "gn:admin2_code":"2104.0",
    "gn:admin3_code":"210403.0",
    "gn:asciiname":"Ingenio",
    "gn:country_code":"PE",
    "gn:dem":4020,
    "gn:feature_class":"P",
    "gn:feature_code":"PPL",
    "gn:name":"Ingenio",
    "gn:population":0,
    "gn:timezone":"America/Lima",
    "iso:country":"PE",
    "name:ceb_x_preferred":[
        "Ingenio"
    ],
    "name:ita_x_preferred":[
        "Ingenio"
    ],
    "name:nld_x_preferred":[
        "Ingenio"
    ],
    "name:por_x_preferred":[
        "Ingenio"
    ],
    "name:spa_x_preferred":[
        "Ingenio"
    ],
    "name:swe_x_preferred":[
        "Ingenio"
    ],
    "wof:name":"Ingenio",
    "wof:placetype":"locality"
},
  "geometry": {"coordinates":[-69.32214999999999,-16.64039],"type":"Point"}
}