{
  "type": "Feature",
  "properties": {
    "gn:admin1_code":"02",
    "gn:admin2_code":"218.0",
    "gn:admin3_code":"21805.0",
    "gn:asciiname":"Moro",
    "gn:country_code":"PE",
    "gn:dem":493,
    "gn:feature_class":"P",
    "gn:feature_code":"PPLA3",
    "gn:name":"Moro",
    "gn:population":0,
    "gn:timezone":"America/Lima",
    "iso:country":"PE",
    "wof:name":"Moro",
    "wof:placetype":"locality"
},
  "geometry": {"coordinates":[-78.18194,-9.13889],"type":"Point"}
}