{
  "type": "Feature",
  "properties": {
    "gn:admin1_code":"11",
    "gn:admin2_code":"1102.0",
    "gn:admin3_code":"110209.0",
    "gn:asciiname":"Liscay",
    "gn:country_code":"PE",
    "gn:dem":3682,
    "gn:feature_class":"P",
    "gn:feature_code":"PPL",
    "gn:name":"Liscay",
    "gn:population":0,
    "gn:timezone":"America/Lima",
    "iso:country":"PE",
    "wof:name":"Liscay",
    "wof:placetype":"locality"
},
  "geometry": {"coordinates":[-75.74603,-13.08773],"type":"Point"}
}