{
  "type": "Feature",
  "properties": {
    "gn:admin1_code":"20",
    "gn:admin2_code":"2003.0",
    "gn:admin3_code":"200306.0",
    "gn:asciiname":"Pampa Blanca",
    "gn:country_code":"PE",
    "gn:dem":1283,
    "gn:feature_class":"P",
    "gn:feature_code":"PPL",
    "gn:name":"Pampa Blanca",
    "gn:population":0,
    "gn:timezone":"America/Lima",
    "iso:country":"PE",
    "wof:name":"Pampa Blanca",
    "wof:placetype":"locality"
},
  "geometry": {"coordinates":[-79.60484,-5.39998],"type":"Point"}
}