{
  "type": "Feature",
  "properties": {
    "gn:admin1_code":"12",
    "gn:admin2_code":"1202.0",
    "gn:admin3_code":"120206.0",
    "gn:asciiname":"Mucllo",
    "gn:country_code":"PE",
    "gn:dem":4038,
    "gn:feature_class":"P",
    "gn:feature_code":"PPL",
    "gn:name":"Mucllo",
    "gn:population":0,
    "gn:timezone":"America/Lima",
    "iso:country":"PE",
    "wof:name":"Mucllo",
    "wof:placetype":"locality"
},
  "geometry": {"coordinates":[-75.03333000000001,-11.71667],"type":"Point"}
}