{
  "type": "Feature",
  "properties": {
    "gn:admin1_code":"15",
    "gn:admin2_code":"1503.0",
    "gn:admin3_code":"150301.0",
    "gn:asciiname":"Minas Chanca",
    "gn:country_code":"PE",
    "gn:dem":4581,
    "gn:feature_class":"P",
    "gn:feature_code":"PPL",
    "gn:name":"Minas Chanca",
    "gn:population":0,
    "gn:timezone":"America/Lima",
    "iso:country":"PE",
    "name:und_x_variant":[
        "Chanca",
        "Minas Chanca"
    ],
    "wof:name":"Minas Chanca",
    "wof:placetype":"locality"
},
  "geometry": {"coordinates":[-76.88053000000002,-10.55632],"type":"Point"}
}