{
  "type": "Feature",
  "properties": {
    "gn:admin1_code":"16",
    "gn:admin2_code":"1601.0",
    "gn:admin3_code":"160107.0",
    "gn:asciiname":"Nashino",
    "gn:country_code":"PE",
    "gn:dem":203,
    "gn:feature_class":"P",
    "gn:feature_code":"PPL",
    "gn:name":"Nashi\u00f1o",
    "gn:population":0,
    "gn:timezone":"America/Lima",
    "iso:country":"PE",
    "wof:name":"Nashino",
    "wof:placetype":"locality"
},
  "geometry": {"coordinates":[-75.43333,-1.18333],"type":"Point"}
}