{
  "type": "Feature",
  "properties": {
    "gn:admin1_code":"09",
    "gn:admin2_code":"901.0",
    "gn:admin3_code":"90106.0",
    "gn:asciiname":"Recuperada",
    "gn:country_code":"PE",
    "gn:dem":4542,
    "gn:feature_class":"P",
    "gn:feature_code":"PPL",
    "gn:name":"Recuperada",
    "gn:population":0,
    "gn:timezone":"America/Lima",
    "iso:country":"PE",
    "wof:name":"Recuperada",
    "wof:placetype":"locality"
},
  "geometry": {"coordinates":[-74.94485999999998,-13.11084],"type":"Point"}
}