{
  "type": "Feature",
  "properties": {
    "gn:admin1_code":"21",
    "gn:admin2_code":"2104.0",
    "gn:admin3_code":"210405.0",
    "gn:asciiname":"Cocatepina",
    "gn:country_code":"PE",
    "gn:dem":4045,
    "gn:feature_class":"P",
    "gn:feature_code":"PPL",
    "gn:name":"Cocatepi\u00f1a",
    "gn:population":0,
    "gn:timezone":"America/Lima",
    "iso:country":"PE",
    "wof:name":"Cocatepina",
    "wof:placetype":"locality"
},
  "geometry": {"coordinates":[-69.39936,-16.91893],"type":"Point"}
}