{
  "type": "Feature",
  "properties": {
    "gn:admin1_code":"20",
    "gn:admin2_code":"2003.0",
    "gn:admin3_code":"200307.0",
    "gn:asciiname":"Siclamache",
    "gn:cc2":"PE",
    "gn:country_code":"PE",
    "gn:dem":2023,
    "gn:feature_class":"P",
    "gn:feature_code":"PPL",
    "gn:name":"Siclamache",
    "gn:population":0,
    "gn:timezone":"America/Lima",
    "iso:country":"PE",
    "name:und_x_variant":[
        "Siclamache Hacienda",
        "Siclamache"
    ],
    "wof:name":"Siclamache",
    "wof:placetype":"locality"
},
  "geometry": {"coordinates":[-79.41667,-5.31667],"type":"Point"}
}