{
  "type": "Feature",
  "properties": {
    "gn:admin1_code":"11",
    "gn:admin2_code":"1101.0",
    "gn:admin3_code":"110114.0",
    "gn:asciiname":"Marcalla",
    "gn:country_code":"PE",
    "gn:dem":2653,
    "gn:feature_class":"P",
    "gn:feature_code":"PPL",
    "gn:name":"Marcalla",
    "gn:population":0,
    "gn:timezone":"America/Lima",
    "iso:country":"PE",
    "wof:name":"Marcalla",
    "wof:placetype":"locality"
},
  "geometry": {"coordinates":[-75.29536,-14.07524],"type":"Point"}
}