{
  "type": "Feature",
  "properties": {
    "gn:admin1_code":"17.0",
    "gn:admin2_code":"1701.0",
    "gn:asciiname":"Fundo Victoria",
    "gn:country_code":"PE",
    "gn:dem":220,
    "gn:feature_class":"P",
    "gn:feature_code":"PPL",
    "gn:name":"Fundo Victoria",
    "gn:population":0,
    "gn:timezone":"America/Lima",
    "iso:country":"PE",
    "name:spa_x_preferred":[
        "Fundo Victoria"
    ],
    "wof:name":"Fundo Victoria",
    "wof:placetype":"locality"
},
  "geometry": {"coordinates":[-69.44125,-12.59356],"type":"Point"}
}