{
  "type": "Feature",
  "properties": {
    "gn:admin1_code":"5.0",
    "gn:admin2_code":"504.0",
    "gn:admin3_code":"50401.0",
    "gn:asciiname":"Rumi Urmasja",
    "gn:country_code":"PE",
    "gn:dem":4092,
    "gn:feature_class":"P",
    "gn:feature_code":"PPL",
    "gn:name":"Rumi Urmasja",
    "gn:population":0,
    "gn:timezone":"America/Lima",
    "iso:country":"PE",
    "wof:name":"Rumi Urmasja",
    "wof:placetype":"locality"
},
  "geometry": {"coordinates":[-74.18486,-12.90845],"type":"Point"}
}