{
  "type": "Feature",
  "properties": {
    "gn:admin1_code":"04",
    "gn:admin2_code":"402.0",
    "gn:admin3_code":"40206.0",
    "gn:asciiname":"Vilque",
    "gn:country_code":"PE",
    "gn:dem":112,
    "gn:feature_class":"P",
    "gn:feature_code":"PPL",
    "gn:name":"Vilque",
    "gn:population":0,
    "gn:timezone":"America/Lima",
    "iso:country":"PE",
    "name:und_x_variant":[
        "Hacienda Vilque",
        "Vilque"
    ],
    "wof:name":"Vilque",
    "wof:placetype":"locality"
},
  "geometry": {"coordinates":[-73.14245,-16.31134],"type":"Point"}
}