{
  "type": "Feature",
  "properties": {
    "gn:admin1_code":"03",
    "gn:admin2_code":"302.0",
    "gn:admin3_code":"30214.0",
    "gn:asciiname":"Chaccrampa",
    "gn:country_code":"PE",
    "gn:dem":3657,
    "gn:feature_class":"P",
    "gn:feature_code":"PPLA3",
    "gn:name":"Chaccrampa",
    "gn:population":0,
    "gn:timezone":"America/Lima",
    "iso:country":"PE",
    "wof:name":"Chaccrampa",
    "wof:placetype":"locality"
},
  "geometry": {"coordinates":[-73.60916999999998,-13.95972],"type":"Point"}
}