{
  "type": "Feature",
  "properties": {
    "gn:admin1_code":"21.0",
    "gn:admin2_code":"2104.0",
    "gn:admin3_code":"210405.0",
    "gn:asciiname":"Vilquecahua",
    "gn:country_code":"PE",
    "gn:dem":4350,
    "gn:feature_class":"P",
    "gn:feature_code":"PPL",
    "gn:name":"Vilquecahua",
    "gn:population":0,
    "gn:timezone":"America/Lima",
    "iso:country":"PE",
    "wof:name":"Vilquecahua",
    "wof:placetype":"locality"
},
  "geometry": {"coordinates":[-69.49722,-17.02694],"type":"Point"}
}