{
  "type": "Feature",
  "properties": {
    "gn:admin1_code":"11",
    "gn:admin2_code":"1105.0",
    "gn:admin3_code":"110507.0",
    "gn:asciiname":"Monte Fertil",
    "gn:country_code":"PE",
    "gn:dem":138,
    "gn:feature_class":"P",
    "gn:feature_code":"PPL",
    "gn:name":"Monte F\u00e9rtil",
    "gn:population":0,
    "gn:timezone":"America/Lima",
    "iso:country":"PE",
    "name:und_x_variant":[
        "Monte F\u00e9rtil Hacienda",
        "Monte F\u00e9rtil"
    ],
    "wof:name":"Monte Fertil",
    "wof:placetype":"locality"
},
  "geometry": {"coordinates":[-76.08960999999999,-13.70092],"type":"Point"}
}