{
  "type": "Feature",
  "properties": {
    "gn:admin1_code":"02",
    "gn:admin2_code":"205.0",
    "gn:admin3_code":"20501.0",
    "gn:asciiname":"Carcas",
    "gn:country_code":"PE",
    "gn:dem":3133,
    "gn:feature_class":"P",
    "gn:feature_code":"PPL",
    "gn:name":"Carcas",
    "gn:population":0,
    "gn:timezone":"America/Lima",
    "iso:country":"PE",
    "wof:name":"Carcas",
    "wof:placetype":"locality"
},
  "geometry": {"coordinates":[-77.16372,-10.11331],"type":"Point"}
}