{
  "type": "Feature",
  "properties": {
    "gn:admin1_code":"12.0",
    "gn:admin2_code":"1208.0",
    "gn:admin3_code":"120809.0",
    "gn:asciiname":"Putucancha",
    "gn:country_code":"PE",
    "gn:dem":4426,
    "gn:feature_class":"P",
    "gn:feature_code":"PPL",
    "gn:name":"Putucancha",
    "gn:population":0,
    "gn:timezone":"America/Lima",
    "iso:country":"PE",
    "wof:name":"Putucancha",
    "wof:placetype":"locality"
},
  "geometry": {"coordinates":[-75.95809,-11.79642],"type":"Point"}
}