{
  "type": "Feature",
  "properties": {
    "gn:admin1_code":"24",
    "gn:admin2_code":"2402.0",
    "gn:admin3_code":"240202.0",
    "gn:asciiname":"Tacna Libre",
    "gn:country_code":"PE",
    "gn:dem":133,
    "gn:feature_class":"P",
    "gn:feature_code":"PPL",
    "gn:name":"Tacna Libre",
    "gn:population":0,
    "gn:timezone":"America/Lima",
    "iso:country":"PE",
    "wof:name":"Tacna Libre",
    "wof:placetype":"locality"
},
  "geometry": {"coordinates":[-80.65836999999998,-3.9533],"type":"Point"}
}