{
  "type": "Feature",
  "properties": {
    "gn:admin1_code":"21",
    "gn:admin2_code":"2105.0",
    "gn:admin3_code":"210504.0",
    "gn:asciiname":"Condoriquina",
    "gn:country_code":"PE",
    "gn:dem":4554,
    "gn:feature_class":"P",
    "gn:feature_code":"PPL",
    "gn:name":"Condoriqui\u00f1a",
    "gn:population":0,
    "gn:timezone":"America/Lima",
    "iso:country":"PE",
    "wof:name":"Condoriquina",
    "wof:placetype":"locality"
},
  "geometry": {"coordinates":[-70.01725999999999,-17.03472],"type":"Point"}
}