{
  "type": "Feature",
  "properties": {
    "iso:country":"PE",
    "name:ceb_x_preferred":[
        "La Uni\u00f3n"
    ],
    "name:deu_x_preferred":[
        "La Uni\u00f3n"
    ],
    "name:eng_x_preferred":[
        "La Uni\u00f3n"
    ],
    "name:fra_x_preferred":[
        "La Uni\u00f3n"
    ],
    "name:ita_x_preferred":[
        "La Uni\u00f3n"
    ],
    "name:jpn_x_preferred":[
        "\u30e9\u30fb\u30a6\u30cb\u30aa\u30f3"
    ],
    "name:nld_x_preferred":[
        "La Uni\u00f3n"
    ],
    "name:por_x_preferred":[
        "La Uni\u00f3n"
    ],
    "name:que_x_preferred":[
        "Tantasqa"
    ],
    "name:spa_x_preferred":[
        "La Uni\u00f3n"
    ],
    "name:war_x_preferred":[
        "La Uni\u00f3n"
    ],
    "name:zho_x_preferred":[
        "\u62c9\u70cf\u5c3c\u7fc1"
    ],
    "qs:gn_country":"PE",
    "qs:gn_fcode":"PPL",
    "qs:gn_pop":4788,
    "qs:name":"La Uni\u00f3n",
    "qs:name_adm0":"Per\u00fa",
    "qs:name_adm1":"Hu\u00e1nuco",
    "qs:photos":26,
    "qs:photos_1k":5,
    "qs:photos_9k":1,
    "qs:photos_9r":2,
    "qs:photos_all":26,
    "qs:photos_sr":2,
    "qs:placetype":"Town",
    "qs:pop_sr":"4",
    "qs:woe_adm0":23424919,
    "wd:elevation":3204.0,
    "wd:wordcount":985,
    "wof:name":"La Uni\u00f3n",
    "wof:placetype":"locality",
    "wof:population":4788
},
  "geometry": {"coordinates":[-76.80199,-9.82702],"type":"Point"}
}