{
  "type": "Feature",
  "properties": {
    "gn:admin1_code":"15",
    "gn:admin2_code":"1507.0",
    "gn:admin3_code":"150701.0",
    "gn:asciiname":"Pacotupe",
    "gn:country_code":"PE",
    "gn:dem":3397,
    "gn:feature_class":"P",
    "gn:feature_code":"PPL",
    "gn:name":"Pacotupe",
    "gn:population":0,
    "gn:timezone":"America/Lima",
    "iso:country":"PE",
    "wof:name":"Pacotupe",
    "wof:placetype":"locality"
},
  "geometry": {"coordinates":[-76.34917,-11.86444],"type":"Point"}
}