{
  "type": "Feature",
  "properties": {
    "gn:admin1_code":"17.0",
    "gn:admin2_code":"1703.0",
    "gn:asciiname":"Tabocal",
    "gn:country_code":"PE",
    "gn:dem":326,
    "gn:feature_class":"P",
    "gn:feature_code":"PPL",
    "gn:name":"Tabocal",
    "gn:population":0,
    "gn:timezone":"America/Lima",
    "iso:country":"PE",
    "name:spa_x_preferred":[
        "Tabocal"
    ],
    "wof:name":"Tabocal",
    "wof:placetype":"locality"
},
  "geometry": {"coordinates":[-69.58241,-11.20368],"type":"Point"}
}