{
  "type": "Feature",
  "properties": {
    "gn:admin1_code":"13",
    "gn:admin2_code":"1301.0",
    "gn:admin3_code":"130110.0",
    "gn:asciiname":"Simbal",
    "gn:country_code":"PE",
    "gn:dem":589,
    "gn:feature_class":"P",
    "gn:feature_code":"PPLA3",
    "gn:name":"Simbal",
    "gn:population":0,
    "gn:timezone":"America/Lima",
    "iso:country":"PE",
    "name:cat_x_preferred":[
        "Simbal"
    ],
    "name:spa_x_preferred":[
        "Simbal"
    ],
    "wof:name":"Simbal",
    "wof:placetype":"locality"
},
  "geometry": {"coordinates":[-78.81359999999999,-7.97639],"type":"Point"}
}