{
  "type": "Feature",
  "properties": {
    "gn:admin1_code":"3",
    "gn:admin2_code":"302.0",
    "gn:admin3_code":"30209.0",
    "gn:asciiname":"Parqueperla",
    "gn:country_code":"PE",
    "gn:dem":3266,
    "gn:feature_class":"P",
    "gn:feature_code":"PPL",
    "gn:name":"Parqueperla",
    "gn:population":0,
    "gn:timezone":"America/Lima",
    "iso:country":"PE",
    "wof:name":"Parqueperla",
    "wof:placetype":"locality"
},
  "geometry": {"coordinates":[-73.25098,-13.63088],"type":"Point"}
}