{
  "type": "Feature",
  "properties": {
    "gn:admin1_code":"09",
    "gn:admin2_code":"904.0",
    "gn:admin3_code":"90402.0",
    "gn:asciiname":"Jarua Pata",
    "gn:country_code":"PE",
    "gn:dem":3980,
    "gn:feature_class":"P",
    "gn:feature_code":"PPL",
    "gn:name":"Jarua Pata",
    "gn:population":0,
    "gn:timezone":"America/Lima",
    "iso:country":"PE",
    "wof:name":"Jarua Pata",
    "wof:placetype":"locality"
},
  "geometry": {"coordinates":[-75.56953,-13.09045],"type":"Point"}
}