{
  "type": "Feature",
  "properties": {
    "gn:admin1_code":"04",
    "gn:admin2_code":"403.0",
    "gn:admin3_code":"40302.0",
    "gn:asciiname":"Morro Canal",
    "gn:country_code":"PE",
    "gn:dem":112,
    "gn:feature_class":"P",
    "gn:feature_code":"PPL",
    "gn:name":"Morro Ca\u00f1al",
    "gn:population":0,
    "gn:timezone":"America/Lima",
    "iso:country":"PE",
    "name:und_x_variant":[
        "Morro Ca\u00f1al",
        "Ca\u00f1al"
    ],
    "wof:name":"Morro Canal",
    "wof:placetype":"locality"
},
  "geometry": {"coordinates":[-74.62138,-15.47989],"type":"Point"}
}