{
  "type": "Feature",
  "properties": {
    "gn:admin1_code":"3.0",
    "gn:admin2_code":"305.0",
    "gn:admin3_code":"30503.0",
    "gn:asciiname":"Quillirqui",
    "gn:country_code":"PE",
    "gn:dem":3207,
    "gn:feature_class":"P",
    "gn:feature_code":"PPL",
    "gn:name":"Quillirqui",
    "gn:population":0,
    "gn:timezone":"America/Lima",
    "iso:country":"PE",
    "wof:name":"Quillirqui",
    "wof:placetype":"locality"
},
  "geometry": {"coordinates":[-72.42778,-13.83694],"type":"Point"}
}