{
  "type": "Feature",
  "properties": {
    "gn:admin1_code":"8",
    "gn:admin2_code":"805.0",
    "gn:admin3_code":"80503.0",
    "gn:asciiname":"Jancayo",
    "gn:country_code":"PE",
    "gn:dem":4451,
    "gn:feature_class":"P",
    "gn:feature_code":"PPL",
    "gn:name":"Jancayo",
    "gn:population":0,
    "gn:timezone":"America/Lima",
    "iso:country":"PE",
    "wof:name":"Jancayo",
    "wof:placetype":"locality"
},
  "geometry": {"coordinates":[-71.32389000000001,-14.43056],"type":"Point"}
}