{
  "type": "Feature",
  "properties": {
    "gn:admin1_code":"12.0",
    "gn:admin2_code":"1203.0",
    "gn:admin3_code":"120302.0",
    "gn:asciiname":"Alto Kivinaki",
    "gn:country_code":"PE",
    "gn:dem":891,
    "gn:feature_class":"P",
    "gn:feature_code":"PPL",
    "gn:name":"Alto Kivinaki",
    "gn:population":0,
    "gn:timezone":"America/Lima",
    "iso:country":"PE",
    "name:spa_x_preferred":[
        "Alto Kivinaki"
    ],
    "wof:name":"Alto Kivinaki",
    "wof:placetype":"locality"
},
  "geometry": {"coordinates":[-75.00593000000001,-10.9077],"type":"Point"}
}