{
  "type": "Feature",
  "properties": {
    "gn:admin1_code":"04",
    "gn:admin2_code":"408.0",
    "gn:admin3_code":"40811.0",
    "gn:asciiname":"Llallihua",
    "gn:country_code":"PE",
    "gn:dem":2526,
    "gn:feature_class":"P",
    "gn:feature_code":"PPL",
    "gn:name":"Llallihua",
    "gn:population":0,
    "gn:timezone":"America/Lima",
    "iso:country":"PE",
    "name:spa_x_preferred":[
        "Llallihua"
    ],
    "wof:name":"Llallihua",
    "wof:placetype":"locality"
},
  "geometry": {"coordinates":[-73.03053,-15.32911],"type":"Point"}
}