{
  "type": "Feature",
  "properties": {
    "iso:country":"PE",
    "name:ast_x_preferred":[
        "San Ram\u00f3n"
    ],
    "name:ceb_x_preferred":[
        "San Ram\u00f3n"
    ],
    "name:deu_x_preferred":[
        "San Ram\u00f3n"
    ],
    "name:eng_x_preferred":[
        "San Ram\u00f3n"
    ],
    "name:jpn_x_preferred":[
        "\u30b5\u30f3\u30fb\u30e9\u30e2\u30f3"
    ],
    "name:nld_x_preferred":[
        "San Ram\u00f3n"
    ],
    "name:spa_x_preferred":[
        "San Ram\u00f3n"
    ],
    "ne:ADM0CAP":0.0,
    "ne:ADM0NAME":"Peru",
    "ne:ADM0_A3":"PER",
    "ne:ADM1NAME":"Jun\u00edn",
    "ne:ADMIN1_COD":12,
    "ne:CAPALT":0,
    "ne:CHANGED":0,
    "ne:CHECKME":0,
    "ne:COMPARE":0,
    "ne:DIFFASCII":0,
    "ne:ELEVATION":0.0,
    "ne:FEATURECLA":"Populated place",
    "ne:FEATURE_CL":"P",
    "ne:FEATURE_CO":"PPL",
    "ne:GEONAMEID":3929314,
    "ne:GEONAMESNO":"Geonames ascii name + lat.d + long.d matching.",
    "ne:GN_ASCII":"San Ramon",
    "ne:GN_POP":14708,
    "ne:GTOPO30":779.0,
    "ne:ISO_A2":"PE",
    "ne:LABELRANK":5,
    "ne:LATITUDE":-11.129619,
    "ne:LONGITUDE":-75.340011,
    "ne:LS_MATCH":1,
    "ne:LS_NAME":"San Ramon",
    "ne:MAX_AREAKM":5.0,
    "ne:MAX_AREAMI":2.0,
    "ne:MAX_BBXMAX":-75.333333,
    "ne:MAX_BBXMIN":-75.366667,
    "ne:MAX_BBYMAX":-11.116667,
    "ne:MAX_BBYMIN":-11.141667,
    "ne:MAX_NATSCA":20.0,
    "ne:MAX_PERKM":13.0,
    "ne:MAX_PERMI":8.0,
    "ne:MAX_POP10":6490,
    "ne:MAX_POP20":6490,
    "ne:MAX_POP300":0,
    "ne:MAX_POP310":0,
    "ne:MAX_POP50":0,
    "ne:MEAN_BBXC":-75.352778,
    "ne:MEAN_BBYC":-11.126389,
    "ne:MEGACITY":0,
    "ne:MIN_AREAKM":5.0,
    "ne:MIN_AREAMI":2.0,
    "ne:MIN_BBXMAX":-75.333333,
    "ne:MIN_BBXMIN":-75.366667,
    "ne:MIN_BBYMAX":-11.116667,
    "ne:MIN_BBYMIN":-11.141667,
    "ne:MIN_PERKM":13.0,
    "ne:MIN_PERMI":8.0,
    "ne:NAME":"San Ramon",
    "ne:NAMEASCII":"San Ramon",
    "ne:NAMEDIFF":0,
    "ne:NATSCALE":20,
    "ne:POP1950":0,
    "ne:POP1955":0,
    "ne:POP1960":0,
    "ne:POP1965":0,
    "ne:POP1970":0,
    "ne:POP1975":0,
    "ne:POP1980":0,
    "ne:POP1985":0,
    "ne:POP1990":0,
    "ne:POP1995":0,
    "ne:POP2000":0,
    "ne:POP2005":0,
    "ne:POP2010":0,
    "ne:POP2015":0,
    "ne:POP2020":0,
    "ne:POP2025":0,
    "ne:POP2050":0,
    "ne:POP_MAX":14708,
    "ne:POP_MIN":6490,
    "ne:POP_OTHER":0,
    "ne:RANK_MAX":6,
    "ne:RANK_MIN":5,
    "ne:SCALERANK":7,
    "ne:SOV0NAME":"Peru",
    "ne:SOV_A3":"PER",
    "ne:TIMEZONE":"America/Lima",
    "ne:UN_FID":0,
    "ne:UN_LAT":0.0,
    "ne:UN_LONG":0.0,
    "ne:WORLDCITY":0,
    "qs:gn_country":"PE",
    "qs:gn_fcode":"PPL",
    "qs:gn_pop":14708,
    "qs:name":"San Roman",
    "qs:name_adm0":"Per\u00fa",
    "qs:name_adm1":"Jun\u00edn",
    "qs:photos":158,
    "qs:photos_1k":32,
    "qs:photos_9k":1,
    "qs:photos_9r":4,
    "qs:photos_all":158,
    "qs:photos_sr":4,
    "qs:placetype":"Town",
    "qs:pop_sr":"6",
    "qs:woe_adm0":23424919,
    "wd:wordcount":117,
    "wof:name":"San Roman",
    "wof:placetype":"locality",
    "wof:population":14708
},
  "geometry": {"coordinates":[-75.35548,-11.12245],"type":"Point"}
}