{
  "type": "Feature",
  "properties": {
    "gn:admin1_code":"02",
    "gn:admin2_code":"211.0",
    "gn:admin3_code":"21103.0",
    "gn:asciiname":"Quita Sombrero",
    "gn:country_code":"PE",
    "gn:dem":27,
    "gn:feature_class":"P",
    "gn:feature_code":"PPL",
    "gn:name":"Quita Sombrero",
    "gn:population":0,
    "gn:timezone":"America/Lima",
    "iso:country":"PE",
    "wof:name":"Quita Sombrero",
    "wof:placetype":"locality"
},
  "geometry": {"coordinates":[-78.2009,-9.93677],"type":"Point"}
}