{
  "type": "Feature",
  "properties": {
    "gn:admin1_code":"12",
    "gn:admin2_code":"1207.0",
    "gn:admin3_code":"120701.0",
    "gn:asciiname":"Jachacancha",
    "gn:country_code":"PE",
    "gn:dem":3972,
    "gn:feature_class":"P",
    "gn:feature_code":"PPL",
    "gn:name":"Jachacancha",
    "gn:population":0,
    "gn:timezone":"America/Lima",
    "iso:country":"PE",
    "name:und_x_variant":[
        "Jachacanchha"
    ],
    "wof:name":"Jachacancha",
    "wof:placetype":"locality"
},
  "geometry": {"coordinates":[-75.73472,-11.4775],"type":"Point"}
}