{
  "type": "Feature",
  "properties": {
    "gn:admin1_code":"3",
    "gn:admin2_code":"302.0",
    "gn:admin3_code":"30209.0",
    "gn:asciiname":"Mazana Huayco",
    "gn:country_code":"PE",
    "gn:dem":3075,
    "gn:feature_class":"P",
    "gn:feature_code":"PPL",
    "gn:name":"Mazana Huayco",
    "gn:population":0,
    "gn:timezone":"America/Lima",
    "iso:country":"PE",
    "wof:name":"Mazana Huayco",
    "wof:placetype":"locality"
},
  "geometry": {"coordinates":[-73.36541,-13.58502],"type":"Point"}
}