{
  "type": "Feature",
  "properties": {
    "gn:admin1_code":"15",
    "gn:admin2_code":"1501.0",
    "gn:admin3_code":"150119.0",
    "gn:asciiname":"Los Almacigos",
    "gn:country_code":"PE",
    "gn:dem":140,
    "gn:feature_class":"P",
    "gn:feature_code":"PPL",
    "gn:name":"Los Almacigos",
    "gn:population":0,
    "gn:timezone":"America/Lima",
    "iso:country":"PE",
    "wof:name":"Los Almacigos",
    "wof:placetype":"locality"
},
  "geometry": {"coordinates":[-76.88333,-12.21667],"type":"Point"}
}