{
  "type": "Feature",
  "properties": {
    "gn:admin1_code":"14",
    "gn:admin2_code":"1401.0",
    "gn:admin3_code":"140119.0",
    "gn:asciiname":"Collique Alto",
    "gn:country_code":"PE",
    "gn:dem":130,
    "gn:feature_class":"P",
    "gn:feature_code":"PPL",
    "gn:name":"Collique Alto",
    "gn:population":0,
    "gn:timezone":"America/Lima",
    "iso:country":"PE",
    "wof:name":"Collique Alto",
    "wof:placetype":"locality"
},
  "geometry": {"coordinates":[-79.54637,-6.8054],"type":"Point"}
}