{
  "type": "Feature",
  "properties": {
    "iso:country":"PE",
    "name:ceb_x_preferred":[
        "Calca"
    ],
    "name:nld_x_preferred":[
        "Calca"
    ],
    "name:unk_x_variant":[
        "Palca Hacienda"
    ],
    "qs:gn_country":"PE",
    "qs:gn_fcode":"PPL",
    "qs:gn_pop":0,
    "qs:name":"Calca",
    "qs:name_adm0":"Per\u00fa",
    "qs:name_adm1":"Cusco",
    "qs:photos":1080,
    "qs:photos_1k":219,
    "qs:photos_9k":5,
    "qs:photos_9r":7,
    "qs:photos_all":1080,
    "qs:photos_sr":11,
    "qs:placetype":"Town",
    "qs:pop_sr":"0",
    "qs:woe_adm0":23424919,
    "wof:name":"Calca",
    "wof:placetype":"locality"
},
  "geometry": {"coordinates":[-72.45,-14.01667],"type":"Point"}
}