{
  "type": "Feature",
  "properties": {
    "gn:admin1_code":"2.0",
    "gn:admin2_code":"218.0",
    "gn:asciiname":"Cascajal Bajo",
    "gn:country_code":"PE",
    "gn:dem":132,
    "gn:feature_class":"P",
    "gn:feature_code":"PPL",
    "gn:name":"Cascajal Bajo",
    "gn:population":0,
    "gn:timezone":"America/Lima",
    "iso:country":"PE",
    "wof:name":"Cascajal Bajo",
    "wof:placetype":"locality"
},
  "geometry": {"coordinates":[-78.5275,-8.90833],"type":"Point"}
}