{
  "type": "Feature",
  "properties": {
    "gn:admin1_code":"17.0",
    "gn:admin2_code":"1703.0",
    "gn:asciiname":"Villa Rica",
    "gn:country_code":"PE",
    "gn:dem":281,
    "gn:feature_class":"P",
    "gn:feature_code":"PPL",
    "gn:name":"Villa Rica",
    "gn:population":0,
    "gn:timezone":"America/Lima",
    "iso:country":"PE",
    "name:spa_x_preferred":[
        "Villa Rica"
    ],
    "wof:name":"Villa Rica",
    "wof:placetype":"locality"
},
  "geometry": {"coordinates":[-69.23650000000001,-11.67191],"type":"Point"}
}