{
  "type": "Feature",
  "properties": {
    "gn:admin1_code":"15",
    "gn:admin2_code":"1502.0",
    "gn:admin3_code":"150201.0",
    "gn:asciiname":"Tambo Viejo",
    "gn:country_code":"PE",
    "gn:dem":58,
    "gn:feature_class":"P",
    "gn:feature_code":"PPL",
    "gn:name":"Tambo Viejo",
    "gn:population":0,
    "gn:timezone":"America/Lima",
    "iso:country":"PE",
    "wof:name":"Tambo Viejo",
    "wof:placetype":"locality"
},
  "geometry": {"coordinates":[-77.78333000000001,-10.73333],"type":"Point"}
}