{
  "type": "Feature",
  "properties": {
    "gn:admin1_code":"02",
    "gn:admin2_code":"218.0",
    "gn:admin3_code":"21801.0",
    "gn:asciiname":"Cruz Pampa",
    "gn:country_code":"PE",
    "gn:dem":920,
    "gn:feature_class":"P",
    "gn:feature_code":"PPL",
    "gn:name":"Cruz Pampa",
    "gn:population":0,
    "gn:timezone":"America/Lima",
    "iso:country":"PE",
    "name:spa_x_preferred":[
        "Cruz Pampa"
    ],
    "wof:name":"Cruz Pampa",
    "wof:placetype":"locality"
},
  "geometry": {"coordinates":[-78.27341,-8.88889],"type":"Point"}
}