{
  "type": "Feature",
  "properties": {
    "gn:admin1_code":"16",
    "gn:admin2_code":"1604.0",
    "gn:admin3_code":"160403.0",
    "gn:asciiname":"Yavara",
    "gn:country_code":"PE",
    "gn:dem":87,
    "gn:feature_class":"P",
    "gn:feature_code":"PPL",
    "gn:name":"Yavara",
    "gn:population":0,
    "gn:timezone":"America/Lima",
    "iso:country":"PE",
    "name:und_x_variant":[
        "Yaran\u00e1",
        "Yavara"
    ],
    "wof:name":"Yavara",
    "wof:placetype":"locality"
},
  "geometry": {"coordinates":[-70.63211,-4.11811],"type":"Point"}
}