{
  "type": "Feature",
  "properties": {
    "gn:admin1_code":"14",
    "gn:admin2_code":"1401.0",
    "gn:admin3_code":"140102.0",
    "gn:asciiname":"Zapotal",
    "gn:country_code":"PE",
    "gn:dem":234,
    "gn:feature_class":"P",
    "gn:feature_code":"PPL",
    "gn:name":"Zapotal",
    "gn:population":0,
    "gn:timezone":"America/Lima",
    "iso:country":"PE",
    "wof:name":"Zapotal",
    "wof:placetype":"locality"
},
  "geometry": {"coordinates":[-79.36813000000002,-6.66363],"type":"Point"}
}