{
  "type": "Feature",
  "properties": {
    "gn:admin1_code":"2",
    "gn:admin2_code":"218.0",
    "gn:admin3_code":"21802.0",
    "gn:asciiname":"Chilon",
    "gn:country_code":"PE",
    "gn:dem":3487,
    "gn:feature_class":"P",
    "gn:feature_code":"PPL",
    "gn:name":"Chilon",
    "gn:population":0,
    "gn:timezone":"America/Lima",
    "iso:country":"PE",
    "wof:name":"Chilon",
    "wof:placetype":"locality"
},
  "geometry": {"coordinates":[-78.05528000000002,-8.94111],"type":"Point"}
}