{
  "type": "Feature",
  "properties": {
    "gn:admin1_code":"10.0",
    "gn:admin2_code":"1003.0",
    "gn:admin3_code":"100322.0",
    "gn:asciiname":"Huichacsun",
    "gn:country_code":"PE",
    "gn:dem":3602,
    "gn:feature_class":"P",
    "gn:feature_code":"PPL",
    "gn:name":"Huichacsun",
    "gn:population":0,
    "gn:timezone":"America/Lima",
    "iso:country":"PE",
    "wof:name":"Huichacsun",
    "wof:placetype":"locality"
},
  "geometry": {"coordinates":[-76.77041,-9.77899],"type":"Point"}
}