{
  "type": "Feature",
  "properties": {
    "gn:admin1_code":"20",
    "gn:admin2_code":"2004.0",
    "gn:admin3_code":"200410.0",
    "gn:asciiname":"Cabuyal",
    "gn:country_code":"PE",
    "gn:dem":1075,
    "gn:feature_class":"P",
    "gn:feature_code":"PPL",
    "gn:name":"Cabuyal",
    "gn:population":0,
    "gn:timezone":"America/Lima",
    "iso:country":"PE",
    "name:und_x_variant":[
        "Cabuyal Hacienda",
        "Cabuyal"
    ],
    "wof:name":"Cabuyal",
    "wof:placetype":"locality"
},
  "geometry": {"coordinates":[-79.7266,-5.19074],"type":"Point"}
}