{
  "type": "Feature",
  "properties": {
    "gn:admin1_code":"15",
    "gn:admin2_code":"1506.0",
    "gn:admin3_code":"150607.0",
    "gn:asciiname":"Canchapilca",
    "gn:country_code":"PE",
    "gn:dem":1917,
    "gn:feature_class":"P",
    "gn:feature_code":"PPL",
    "gn:name":"Canchapilca",
    "gn:population":0,
    "gn:timezone":"America/Lima",
    "iso:country":"PE",
    "wof:name":"Canchapilca",
    "wof:placetype":"locality"
},
  "geometry": {"coordinates":[-76.81444,-11.24],"type":"Point"}
}