{
  "type": "Feature",
  "properties": {
    "gn:admin1_code":"13",
    "gn:admin2_code":"1302.0",
    "gn:admin3_code":"130203.0",
    "gn:asciiname":"Pueblo Libre",
    "gn:country_code":"PE",
    "gn:dem":73,
    "gn:feature_class":"P",
    "gn:feature_code":"PPLL",
    "gn:name":"Pueblo Libre",
    "gn:population":0,
    "gn:timezone":"America/Lima",
    "iso:country":"PE",
    "name:cat_x_preferred":[
        "Pueblo Libre"
    ],
    "name:que_x_preferred":[
        "Pueblo Libre distritu"
    ],
    "name:zho_x_preferred":[
        "\u81ea\u7531\u90e8\u843d\u5340"
    ],
    "wof:name":"Pueblo Libre",
    "wof:placetype":"locality"
},
  "geometry": {"coordinates":[-79.27574,-7.78632],"type":"Point"}
}