{
  "type": "Feature",
  "properties": {
    "gn:admin1_code":"8.0",
    "gn:admin2_code":"809.0",
    "gn:admin3_code":"80910.0",
    "gn:asciiname":"Quisto Valle",
    "gn:country_code":"PE",
    "gn:dem":551,
    "gn:feature_class":"P",
    "gn:feature_code":"PPL",
    "gn:name":"Quisto Valle",
    "gn:population":0,
    "gn:timezone":"America/Lima",
    "iso:country":"PE",
    "name:spa_x_preferred":[
        "Quisto Valle"
    ],
    "wof:name":"Quisto Valle",
    "wof:placetype":"locality"
},
  "geometry": {"coordinates":[-73.90476,-12.37195],"type":"Point"}
}