{
  "type": "Feature",
  "properties": {
    "gn:admin1_code":"04",
    "gn:admin2_code":"405.0",
    "gn:admin3_code":"40515.0",
    "gn:asciiname":"Nequehuiri",
    "gn:country_code":"PE",
    "gn:dem":4323,
    "gn:feature_class":"P",
    "gn:feature_code":"PPL",
    "gn:name":"\u00d1equehuiri",
    "gn:population":0,
    "gn:timezone":"America/Lima",
    "iso:country":"PE",
    "name:und_x_variant":[
        "Nequehuin",
        "\u00d1equehuiri"
    ],
    "wof:name":"Nequehuiri",
    "wof:placetype":"locality"
},
  "geometry": {"coordinates":[-71.60464,-15.24876],"type":"Point"}
}