{
  "type": "Feature",
  "properties": {
    "gn:admin1_code":"2.0",
    "gn:admin2_code":"217.0",
    "gn:admin3_code":"21702.0",
    "gn:asciiname":"Lajtu Cancha",
    "gn:country_code":"PE",
    "gn:dem":4078,
    "gn:feature_class":"P",
    "gn:feature_code":"PPL",
    "gn:name":"Lajtu Cancha",
    "gn:population":0,
    "gn:timezone":"America/Lima",
    "iso:country":"PE",
    "wof:name":"Lajtu Cancha",
    "wof:placetype":"locality"
},
  "geometry": {"coordinates":[-77.26286999999998,-10.07252],"type":"Point"}
}