{
  "type": "Feature",
  "properties": {
    "gn:admin1_code":"8",
    "gn:admin2_code":"809.0",
    "gn:admin3_code":"80902.0",
    "gn:asciiname":"Los Libertadores",
    "gn:country_code":"PE",
    "gn:dem":319,
    "gn:feature_class":"P",
    "gn:feature_code":"PPLL",
    "gn:name":"Los Libertadores",
    "gn:population":0,
    "gn:timezone":"America/Lima",
    "iso:country":"PE",
    "wof:name":"Los Libertadores",
    "wof:placetype":"locality"
},
  "geometry": {"coordinates":[-72.92333000000001,-11.32972],"type":"Point"}
}