{
  "type": "Feature",
  "properties": {
    "gn:admin1_code":"20",
    "gn:admin2_code":"2001.0",
    "gn:admin3_code":"200107.0",
    "gn:asciiname":"Chato",
    "gn:country_code":"PE",
    "gn:dem":25,
    "gn:feature_class":"P",
    "gn:feature_code":"PPL",
    "gn:name":"Chato",
    "gn:population":0,
    "gn:timezone":"America/Lima",
    "iso:country":"PE",
    "name:und_x_variant":[
        "Chato Chico",
        "Chato"
    ],
    "wof:name":"Chato",
    "wof:placetype":"locality"
},
  "geometry": {"coordinates":[-80.6649,-5.3677],"type":"Point"}
}