{
  "type": "Feature",
  "properties": {
    "gn:admin1_code":"9.0",
    "gn:admin2_code":"904.0",
    "gn:admin3_code":"90404.0",
    "gn:asciiname":"Songo Grande",
    "gn:country_code":"PE",
    "gn:dem":1890,
    "gn:feature_class":"P",
    "gn:feature_code":"PPL",
    "gn:name":"Songo Grande",
    "gn:population":0,
    "gn:timezone":"America/Lima",
    "iso:country":"PE",
    "name:spa_x_preferred":[
        "Songo Grande"
    ],
    "wof:name":"Songo Grande",
    "wof:placetype":"locality"
},
  "geometry": {"coordinates":[-75.61609,-13.25266],"type":"Point"}
}