{
  "type": "Feature",
  "properties": {
    "gn:admin1_code":"23",
    "gn:admin2_code":"2304.0",
    "gn:admin3_code":"230406.0",
    "gn:asciiname":"Huanacorasa",
    "gn:country_code":"PE",
    "gn:dem":4294,
    "gn:feature_class":"P",
    "gn:feature_code":"PPL",
    "gn:name":"Hua\u00f1acorasa",
    "gn:population":0,
    "gn:timezone":"America/Lima",
    "iso:country":"PE",
    "wof:name":"Huanacorasa",
    "wof:placetype":"locality"
},
  "geometry": {"coordinates":[-70.03304,-17.25519],"type":"Point"}
}