{
  "type": "Feature",
  "properties": {
    "gn:admin1_code":"13",
    "gn:admin2_code":"1307.0",
    "gn:admin3_code":"130702.0",
    "gn:asciiname":"Palan Alto",
    "gn:country_code":"PE",
    "gn:dem":22,
    "gn:feature_class":"P",
    "gn:feature_code":"PPL",
    "gn:name":"Pal\u00e1n Alto",
    "gn:population":0,
    "gn:timezone":"America/Lima",
    "iso:country":"PE",
    "wof:name":"Palan Alto",
    "wof:placetype":"locality"
},
  "geometry": {"coordinates":[-79.55736999999998,-7.32017],"type":"Point"}
}