{
  "type": "Feature",
  "properties": {
    "gn:admin1_code":"10",
    "gn:admin2_code":"1002.0",
    "gn:admin3_code":"100202.0",
    "gn:asciiname":"Puntahuasi",
    "gn:country_code":"PE",
    "gn:dem":4001,
    "gn:feature_class":"P",
    "gn:feature_code":"PPL",
    "gn:name":"Puntahuasi",
    "gn:population":0,
    "gn:timezone":"America/Lima",
    "iso:country":"PE",
    "wof:name":"Puntahuasi",
    "wof:placetype":"locality"
},
  "geometry": {"coordinates":[-76.35772,-10.18335],"type":"Point"}
}