{
  "type": "Feature",
  "properties": {
    "gn:admin1_code":"17.0",
    "gn:admin2_code":"1703.0",
    "gn:asciiname":"Chileno",
    "gn:country_code":"PE",
    "gn:dem":321,
    "gn:feature_class":"P",
    "gn:feature_code":"PPL",
    "gn:name":"Chileno",
    "gn:population":0,
    "gn:timezone":"America/Lima",
    "iso:country":"PE",
    "name:spa_x_preferred":[
        "Chileno"
    ],
    "wof:name":"Chileno",
    "wof:placetype":"locality"
},
  "geometry": {"coordinates":[-69.69410000000001,-11.28058],"type":"Point"}
}