{
  "type": "Feature",
  "properties": {
    "gn:admin1_code":"15",
    "gn:admin2_code":"1503.0",
    "gn:admin3_code":"150301.0",
    "gn:asciiname":"Uramaza",
    "gn:country_code":"PE",
    "gn:dem":3476,
    "gn:feature_class":"P",
    "gn:feature_code":"PPL",
    "gn:name":"Uramaza",
    "gn:population":0,
    "gn:timezone":"America/Lima",
    "iso:country":"PE",
    "wof:name":"Uramaza",
    "wof:placetype":"locality"
},
  "geometry": {"coordinates":[-77.01491999999998,-10.37923],"type":"Point"}
}