{
  "type": "Feature",
  "properties": {
    "gn:admin1_code":"18",
    "gn:admin2_code":"1802.0",
    "gn:admin3_code":"180204.0",
    "gn:asciiname":"Sicuani",
    "gn:country_code":"PE",
    "gn:dem":3842,
    "gn:feature_class":"P",
    "gn:feature_code":"PPL",
    "gn:name":"Sicuani",
    "gn:population":0,
    "gn:timezone":"America/Lima",
    "iso:country":"PE",
    "name:aym_x_preferred":[
        "Sikuwani"
    ],
    "name:ceb_x_preferred":[
        "Sicuani"
    ],
    "name:deu_x_preferred":[
        "Sicuani"
    ],
    "name:fra_x_preferred":[
        "Sicuani"
    ],
    "name:pol_x_preferred":[
        "Sicuani"
    ],
    "name:por_x_preferred":[
        "Sicuani"
    ],
    "name:que_x_preferred":[
        "Sikuwani"
    ],
    "name:rus_x_preferred":[
        "\u0421\u0438\u043a\u0443\u0430\u043d\u0438"
    ],
    "name:spa_x_preferred":[
        "Sicuani"
    ],
    "name:war_x_preferred":[
        "Sicuani"
    ],
    "name:zho_x_preferred":[
        "\u932b\u5938\u5c3c"
    ],
    "wof:name":"Sicuani",
    "wof:placetype":"locality"
},
  "geometry": {"coordinates":[-70.51336999999999,-16.1332],"type":"Point"}
}