{
  "type": "Feature",
  "properties": {
    "gn:admin1_code":"21",
    "gn:admin2_code":"2101.0",
    "gn:asciiname":"Calachaca",
    "gn:cc2":"PE",
    "gn:country_code":"PE",
    "gn:dem":3819,
    "gn:feature_class":"P",
    "gn:feature_code":"PPL",
    "gn:name":"Calachaca",
    "gn:population":0,
    "gn:timezone":"America/Lima",
    "iso:country":"PE",
    "name:und_x_variant":[
        "Callachaca",
        "Calachaca"
    ],
    "wof:name":"Calachaca",
    "wof:placetype":"locality"
},
  "geometry": {"coordinates":[-69.83333,-15.86667],"type":"Point"}
}