{
  "type": "Feature",
  "properties": {
    "gn:admin1_code":"9.0",
    "gn:admin2_code":"902.0",
    "gn:asciiname":"Pariza",
    "gn:country_code":"PE",
    "gn:dem":3054,
    "gn:feature_class":"P",
    "gn:feature_code":"PPL",
    "gn:name":"Pariza",
    "gn:population":0,
    "gn:timezone":"America/Lima",
    "iso:country":"PE",
    "wof:name":"Pariza",
    "wof:placetype":"locality"
},
  "geometry": {"coordinates":[-74.40955,-12.83455],"type":"Point"}
}