{
  "type": "Feature",
  "properties": {
    "gn:admin1_code":"1.0",
    "gn:admin2_code":"106.0",
    "gn:admin3_code":"10609.0",
    "gn:asciiname":"Jebil",
    "gn:country_code":"PE",
    "gn:dem":1333,
    "gn:feature_class":"P",
    "gn:feature_code":"PPL",
    "gn:name":"Jebil",
    "gn:population":0,
    "gn:timezone":"America/Lima",
    "iso:country":"PE",
    "wof:name":"Jebil",
    "wof:placetype":"locality"
},
  "geometry": {"coordinates":[-77.37721999999999,-6.47833],"type":"Point"}
}