{
  "type": "Feature",
  "properties": {
    "gn:admin1_code":"05",
    "gn:admin2_code":"506.0",
    "gn:admin3_code":"50601.0",
    "gn:asciiname":"Cceccaccasa",
    "gn:country_code":"PE",
    "gn:dem":4164,
    "gn:feature_class":"P",
    "gn:feature_code":"PPL",
    "gn:name":"Cceccaccasa",
    "gn:population":0,
    "gn:timezone":"America/Lima",
    "iso:country":"PE",
    "wof:name":"Cceccaccasa",
    "wof:placetype":"locality"
},
  "geometry": {"coordinates":[-73.92568,-14.77106],"type":"Point"}
}