{
  "type": "Feature",
  "properties": {
    "gn:admin1_code":"21",
    "gn:admin2_code":"2105.0",
    "gn:admin3_code":"210502.0",
    "gn:asciiname":"Chontacollo",
    "gn:country_code":"PE",
    "gn:dem":4402,
    "gn:feature_class":"P",
    "gn:feature_code":"PPL",
    "gn:name":"Chontacollo",
    "gn:population":0,
    "gn:timezone":"America/Lima",
    "iso:country":"PE",
    "name:que_x_preferred":[
        "Chuntaqullu"
    ],
    "name:zho_x_preferred":[
        "\u74ca\u5854\u79d1\u7565\u5c71"
    ],
    "wof:name":"Chontacollo",
    "wof:placetype":"locality"
},
  "geometry": {"coordinates":[-69.57344000000001,-17.02769],"type":"Point"}
}