{
  "type": "Feature",
  "properties": {
    "gn:admin1_code":"20",
    "gn:admin2_code":"2004.0",
    "gn:admin3_code":"200410.0",
    "gn:asciiname":"Huarpicha",
    "gn:country_code":"PE",
    "gn:dem":2705,
    "gn:feature_class":"P",
    "gn:feature_code":"PPL",
    "gn:name":"Huarpicha",
    "gn:population":0,
    "gn:timezone":"America/Lima",
    "iso:country":"PE",
    "wof:name":"Huarpicha",
    "wof:placetype":"locality"
},
  "geometry": {"coordinates":[-79.65859,-5.12811],"type":"Point"}
}