{
  "type": "Feature",
  "properties": {
    "gn:admin1_code":"08",
    "gn:admin2_code":"806.0",
    "gn:admin3_code":"80602.0",
    "gn:asciiname":"Finaya",
    "gn:country_code":"PE",
    "gn:dem":4697,
    "gn:feature_class":"P",
    "gn:feature_code":"PPL",
    "gn:name":"Finaya",
    "gn:population":0,
    "gn:timezone":"America/Lima",
    "iso:country":"PE",
    "wof:name":"Finaya",
    "wof:placetype":"locality"
},
  "geometry": {"coordinates":[-70.97374000000001,-13.89666],"type":"Point"}
}