{
  "type": "Feature",
  "properties": {
    "gn:admin1_code":"8",
    "gn:admin2_code":"809.0",
    "gn:admin3_code":"80902.0",
    "gn:asciiname":"Delicias",
    "gn:country_code":"PE",
    "gn:dem":1736,
    "gn:feature_class":"P",
    "gn:feature_code":"PPL",
    "gn:name":"Delicias",
    "gn:population":0,
    "gn:timezone":"America/Lima",
    "iso:country":"PE",
    "name:arg_x_preferred":[
        "Delicias"
    ],
    "name:cat_x_preferred":[
        "Delicias"
    ],
    "name:ceb_x_preferred":[
        "Delicias"
    ],
    "name:deu_x_preferred":[
        "Delicias"
    ],
    "name:fra_x_preferred":[
        "Delicias"
    ],
    "name:ita_x_preferred":[
        "Delicias"
    ],
    "name:mlg_x_preferred":[
        "Delicias"
    ],
    "name:nld_x_preferred":[
        "Delicias"
    ],
    "name:rus_x_preferred":[
        "\u0414\u0435\u043b\u0438\u0441\u044c\u044f\u0441"
    ],
    "name:spa_x_preferred":[
        "Las Delicias"
    ],
    "name:swe_x_preferred":[
        "Delicias"
    ],
    "wof:name":"Delicias",
    "wof:placetype":"locality"
},
  "geometry": {"coordinates":[-72.56399,-12.8231],"type":"Point"}
}