{
  "type": "Feature",
  "properties": {
    "gn:admin1_code":"4",
    "gn:admin2_code":"404.0",
    "gn:admin3_code":"40411.0",
    "gn:asciiname":"Ccallhuajoto",
    "gn:country_code":"PE",
    "gn:dem":2688,
    "gn:feature_class":"P",
    "gn:feature_code":"PPL",
    "gn:name":"Ccallhuajoto",
    "gn:population":0,
    "gn:timezone":"America/Lima",
    "iso:country":"PE",
    "wof:name":"Ccallhuajoto",
    "wof:placetype":"locality"
},
  "geometry": {"coordinates":[-72.50139,-15.6975],"type":"Point"}
}