{
  "type": "Feature",
  "properties": {
    "gn:admin1_code":"09",
    "gn:admin2_code":"903.0",
    "gn:admin3_code":"90312.0",
    "gn:asciiname":"Motuy",
    "gn:country_code":"PE",
    "gn:dem":3680,
    "gn:feature_class":"P",
    "gn:feature_code":"PPL",
    "gn:name":"Motuy",
    "gn:population":0,
    "gn:timezone":"America/Lima",
    "iso:country":"PE",
    "wof:name":"Motuy",
    "wof:placetype":"locality"
},
  "geometry": {"coordinates":[-74.46079,-13.0679],"type":"Point"}
}