{
  "type": "Feature",
  "properties": {
    "gn:admin1_code":"21",
    "gn:admin2_code":"2112.0",
    "gn:admin3_code":"211204.0",
    "gn:asciiname":"Jarahuana",
    "gn:country_code":"PE",
    "gn:dem":4030,
    "gn:feature_class":"P",
    "gn:feature_code":"PPL",
    "gn:name":"Jarahua\u00f1a",
    "gn:population":0,
    "gn:timezone":"America/Lima",
    "iso:country":"PE",
    "wof:name":"Jarahuana",
    "wof:placetype":"locality"
},
  "geometry": {"coordinates":[-69.60415999999999,-14.41734],"type":"Point"}
}