{
  "type": "Feature",
  "properties": {
    "gn:admin1_code":"3",
    "gn:admin2_code":"302.0",
    "gn:admin3_code":"30201.0",
    "gn:asciiname":"Campanayoc",
    "gn:country_code":"PE",
    "gn:dem":3190,
    "gn:feature_class":"P",
    "gn:feature_code":"PPL",
    "gn:name":"Campanayoc",
    "gn:population":0,
    "gn:timezone":"America/Lima",
    "iso:country":"PE",
    "wof:name":"Campanayoc",
    "wof:placetype":"locality"
},
  "geometry": {"coordinates":[-73.39659,-13.68235],"type":"Point"}
}