{
  "type": "Feature",
  "properties": {
    "gn:admin1_code":"04",
    "gn:admin2_code":"404.0",
    "gn:admin3_code":"40413.0",
    "gn:asciiname":"Hacienda Santa Elena",
    "gn:country_code":"PE",
    "gn:dem":472,
    "gn:feature_class":"P",
    "gn:feature_code":"PPL",
    "gn:name":"Hacienda Santa Elena",
    "gn:population":0,
    "gn:timezone":"America/Lima",
    "iso:country":"PE",
    "name:und_x_variant":[
        "Santa Elena Hacienda",
        "Santa Elena",
        "Hacienda Santa Elena"
    ],
    "wof:name":"Hacienda Santa Elena",
    "wof:placetype":"locality"
},
  "geometry": {"coordinates":[-72.47175,-16.19746],"type":"Point"}
}