{
  "type": "Feature",
  "properties": {
    "gn:admin1_code":"14",
    "gn:admin2_code":"1403.0",
    "gn:admin3_code":"140308.0",
    "gn:asciiname":"La Choza",
    "gn:country_code":"PE",
    "gn:dem":158,
    "gn:feature_class":"P",
    "gn:feature_code":"PPL",
    "gn:name":"La Choza",
    "gn:population":0,
    "gn:timezone":"America/Lima",
    "iso:country":"PE",
    "wof:name":"La Choza",
    "wof:placetype":"locality"
},
  "geometry": {"coordinates":[-79.76239,-5.95026],"type":"Point"}
}