{
  "type": "Feature",
  "properties": {
    "gn:admin1_code":"15",
    "gn:admin2_code":"1505.0",
    "gn:admin3_code":"150505.0",
    "gn:asciiname":"Los Icascos",
    "gn:country_code":"PE",
    "gn:dem":515,
    "gn:feature_class":"P",
    "gn:feature_code":"PPL",
    "gn:name":"Los Icascos",
    "gn:population":0,
    "gn:timezone":"America/Lima",
    "iso:country":"PE",
    "name:spa_x_preferred":[
        "Los Icascos"
    ],
    "name:spa_x_variant":[
        "Locicasos"
    ],
    "wof:name":"Los Icascos",
    "wof:placetype":"locality"
},
  "geometry": {"coordinates":[-76.6895,-12.37374],"type":"Point"}
}