{
  "type": "Feature",
  "properties": {
    "gn:admin1_code":"15",
    "gn:admin2_code":"1507.0",
    "gn:admin3_code":"150732.0",
    "gn:asciiname":"Chapo",
    "gn:country_code":"PE",
    "gn:dem":2665,
    "gn:feature_class":"P",
    "gn:feature_code":"PPL",
    "gn:name":"Chapo",
    "gn:population":0,
    "gn:timezone":"America/Lima",
    "iso:country":"PE",
    "wof:name":"Chapo",
    "wof:placetype":"locality"
},
  "geometry": {"coordinates":[-76.44694,-11.90111],"type":"Point"}
}