{
  "type": "Feature",
  "properties": {
    "gn:admin1_code":"04",
    "gn:admin2_code":"402.0",
    "gn:admin3_code":"40207.0",
    "gn:asciiname":"Las Higueritas",
    "gn:country_code":"PE",
    "gn:dem":32,
    "gn:feature_class":"P",
    "gn:feature_code":"PPL",
    "gn:name":"Las Higueritas",
    "gn:population":0,
    "gn:timezone":"America/Lima",
    "iso:country":"PE",
    "name:und_x_variant":[
        "Las Higueritas Hacienda",
        "Las Higueritas"
    ],
    "wof:name":"Las Higueritas",
    "wof:placetype":"locality"
},
  "geometry": {"coordinates":[-72.41439,-16.70713],"type":"Point"}
}