{
  "type": "Feature",
  "properties": {
    "gn:admin1_code":"06",
    "gn:admin2_code":"607.0",
    "gn:admin3_code":"60701.0",
    "gn:asciiname":"Puquipata",
    "gn:cc2":"PE",
    "gn:country_code":"PE",
    "gn:dem":2812,
    "gn:feature_class":"P",
    "gn:feature_code":"PPL",
    "gn:name":"Puquipata",
    "gn:population":0,
    "gn:timezone":"America/Lima",
    "iso:country":"PE",
    "name:und_x_variant":[
        "Puquipato",
        "Puquipata"
    ],
    "wof:name":"Puquipata",
    "wof:placetype":"locality"
},
  "geometry": {"coordinates":[-78.48333000000002,-6.76667],"type":"Point"}
}