{
  "type": "Feature",
  "properties": {
    "gn:admin1_code":"5",
    "gn:admin2_code":"505.0",
    "gn:admin3_code":"50501.0",
    "gn:asciiname":"Banico",
    "gn:country_code":"PE",
    "gn:dem":3692,
    "gn:feature_class":"P",
    "gn:feature_code":"PPL",
    "gn:name":"Ba\u00f1ico",
    "gn:population":0,
    "gn:timezone":"America/Lima",
    "iso:country":"PE",
    "wof:name":"Banico",
    "wof:placetype":"locality"
},
  "geometry": {"coordinates":[-73.87189000000002,-13.02646],"type":"Point"}
}