{
  "type": "Feature",
  "properties": {
    "gn:admin1_code":"9.0",
    "gn:admin2_code":"901.0",
    "gn:admin3_code":"90103.0",
    "gn:asciiname":"Maraycancha",
    "gn:country_code":"PE",
    "gn:dem":4047,
    "gn:feature_class":"P",
    "gn:feature_code":"PPL",
    "gn:name":"Maraycancha",
    "gn:population":0,
    "gn:timezone":"America/Lima",
    "iso:country":"PE",
    "wof:name":"Maraycancha",
    "wof:placetype":"locality"
},
  "geometry": {"coordinates":[-74.72511999999998,-12.53534],"type":"Point"}
}