{
  "type": "Feature",
  "properties": {
    "gn:admin1_code":"1",
    "gn:admin2_code":"101.0",
    "gn:admin3_code":"10110.0",
    "gn:asciiname":"San Roque",
    "gn:country_code":"PE",
    "gn:dem":3240,
    "gn:feature_class":"P",
    "gn:feature_code":"PPLL",
    "gn:name":"San Roque",
    "gn:population":0,
    "gn:timezone":"America/Lima",
    "iso:country":"PE",
    "wof:name":"San Roque",
    "wof:placetype":"locality"
},
  "geometry": {"coordinates":[-77.76878000000001,-6.77521],"type":"Point"}
}