{
  "type": "Feature",
  "properties": {
    "gn:admin1_code":"8",
    "gn:admin2_code":"808.0",
    "gn:admin3_code":"80803.0",
    "gn:asciiname":"Champacocha",
    "gn:country_code":"PE",
    "gn:dem":4653,
    "gn:feature_class":"P",
    "gn:feature_code":"PPL",
    "gn:name":"Champacocha",
    "gn:population":0,
    "gn:timezone":"America/Lima",
    "iso:country":"PE",
    "wof:name":"Champacocha",
    "wof:placetype":"locality"
},
  "geometry": {"coordinates":[-71.7281,-14.62718],"type":"Point"}
}