{
  "type": "Feature",
  "properties": {
    "gn:admin1_code":"16",
    "gn:admin2_code":"1601.0",
    "gn:admin3_code":"160108.0",
    "gn:asciiname":"Barrio Florido",
    "gn:country_code":"PE",
    "gn:dem":112,
    "gn:feature_class":"P",
    "gn:feature_code":"PPL",
    "gn:name":"Barrio Florido",
    "gn:population":0,
    "gn:timezone":"America/Lima",
    "iso:country":"PE",
    "name:und_x_variant":[
        "Barrio Florida",
        "Barrio Florido"
    ],
    "wof:name":"Barrio Florido",
    "wof:placetype":"locality"
},
  "geometry": {"coordinates":[-73.21573000000002,-3.63983],"type":"Point"}
}