{
  "type": "Feature",
  "properties": {
    "gn:admin1_code":"16",
    "gn:admin2_code":"1602.0",
    "gn:admin3_code":"160202.0",
    "gn:asciiname":"Canoa Puerto",
    "gn:country_code":"PE",
    "gn:dem":202,
    "gn:feature_class":"P",
    "gn:feature_code":"PPL",
    "gn:name":"Canoa Puerto",
    "gn:population":0,
    "gn:timezone":"America/Lima",
    "iso:country":"PE",
    "name:spa_x_preferred":[
        "Canoa Puerto"
    ],
    "wof:name":"Canoa Puerto",
    "wof:placetype":"locality"
},
  "geometry": {"coordinates":[-76.5701,-5.86432],"type":"Point"}
}