{
  "type": "Feature",
  "properties": {
    "gn:admin1_code":"09",
    "gn:admin2_code":"907.0",
    "gn:admin3_code":"90705.0",
    "gn:asciiname":"Huanchuy",
    "gn:cc2":"PE",
    "gn:country_code":"PE",
    "gn:dem":3533,
    "gn:feature_class":"P",
    "gn:feature_code":"PPL",
    "gn:name":"Huanchuy",
    "gn:population":0,
    "gn:timezone":"America/Lima",
    "iso:country":"PE",
    "name:und_x_variant":[
        "Huaychos",
        "Huanchuy"
    ],
    "wof:name":"Huanchuy",
    "wof:placetype":"locality"
},
  "geometry": {"coordinates":[-74.63333,-12.41667],"type":"Point"}
}