{
  "type": "Feature",
  "properties": {
    "gn:admin1_code":"11.0",
    "gn:admin2_code":"1102.0",
    "gn:admin3_code":"110203.0",
    "gn:asciiname":"Huarachaga",
    "gn:country_code":"PE",
    "gn:dem":4003,
    "gn:feature_class":"P",
    "gn:feature_code":"PPL",
    "gn:name":"Huarachaga",
    "gn:population":0,
    "gn:timezone":"America/Lima",
    "iso:country":"PE",
    "name:spa_x_preferred":[
        "Huarachaga"
    ],
    "wof:name":"Huarachaga",
    "wof:placetype":"locality"
},
  "geometry": {"coordinates":[-75.84853000000003,-13.04084],"type":"Point"}
}