{
  "type": "Feature",
  "properties": {
    "gn:admin1_code":"03",
    "gn:admin2_code":"302.0",
    "gn:admin3_code":"30217.0",
    "gn:asciiname":"Chichuacancha",
    "gn:country_code":"PE",
    "gn:dem":3927,
    "gn:feature_class":"P",
    "gn:feature_code":"PPL",
    "gn:name":"Chichuacancha",
    "gn:population":0,
    "gn:timezone":"America/Lima",
    "iso:country":"PE",
    "name:und_x_variant":[
        "Chinchuacancha",
        "Chichuacancha"
    ],
    "wof:name":"Chichuacancha",
    "wof:placetype":"locality"
},
  "geometry": {"coordinates":[-73.51399000000001,-13.89668],"type":"Point"}
}