{
  "type": "Feature",
  "properties": {
    "gn:admin1_code":"16",
    "gn:admin2_code":"1607.0",
    "gn:admin3_code":"160705.0",
    "gn:asciiname":"San Isidro",
    "gn:country_code":"PE",
    "gn:dem":133,
    "gn:feature_class":"P",
    "gn:feature_code":"PPL",
    "gn:name":"San Isidro",
    "gn:population":0,
    "gn:timezone":"America/Lima",
    "iso:country":"PE",
    "name:und_x_variant":[
        "San Isidor",
        "San Isidro"
    ],
    "wof:name":"San Isidro",
    "wof:placetype":"locality"
},
  "geometry": {"coordinates":[-76.25543,-4.91247],"type":"Point"}
}