{
  "type": "Feature",
  "properties": {
    "gn:admin1_code":"15",
    "gn:admin2_code":"1505.0",
    "gn:admin3_code":"150506.0",
    "gn:asciiname":"Corralon",
    "gn:country_code":"PE",
    "gn:dem":234,
    "gn:feature_class":"P",
    "gn:feature_code":"PPL",
    "gn:name":"Corral\u00f3n",
    "gn:population":0,
    "gn:timezone":"America/Lima",
    "iso:country":"PE",
    "wof:name":"Corralon",
    "wof:placetype":"locality"
},
  "geometry": {"coordinates":[-76.47306,-12.74014],"type":"Point"}
}