{
  "type": "Feature",
  "properties": {
    "gn:admin1_code":"6.0",
    "gn:admin2_code":"605.0",
    "gn:admin3_code":"60505.0",
    "gn:asciiname":"Las Tunitas",
    "gn:country_code":"PE",
    "gn:dem":2475,
    "gn:feature_class":"P",
    "gn:feature_code":"PPL",
    "gn:name":"Las Tunitas",
    "gn:population":0,
    "gn:timezone":"America/Lima",
    "iso:country":"PE",
    "name:spa_x_preferred":[
        "Las Tunitas"
    ],
    "wof:name":"Las Tunitas",
    "wof:placetype":"locality"
},
  "geometry": {"coordinates":[-79.03307,-7.4439],"type":"Point"}
}