{
  "type": "Feature",
  "properties": {
    "gn:admin1_code":"10.0",
    "gn:admin2_code":"1001.0",
    "gn:admin3_code":"100104.0",
    "gn:asciiname":"Matara",
    "gn:country_code":"PE",
    "gn:dem":2363,
    "gn:feature_class":"P",
    "gn:feature_code":"PPL",
    "gn:name":"Matara",
    "gn:population":0,
    "gn:timezone":"America/Lima",
    "iso:country":"PE",
    "wof:name":"Matara",
    "wof:placetype":"locality"
},
  "geometry": {"coordinates":[-76.09926,-9.84917],"type":"Point"}
}