{
  "type": "Feature",
  "properties": {
    "gn:admin1_code":"10",
    "gn:admin2_code":"1001.0",
    "gn:admin3_code":"100103.0",
    "gn:asciiname":"Acomayo",
    "gn:country_code":"PE",
    "gn:dem":2109,
    "gn:feature_class":"P",
    "gn:feature_code":"PPLA3",
    "gn:name":"Acomayo",
    "gn:population":0,
    "gn:timezone":"America/Lima",
    "iso:country":"PE",
    "wof:name":"Acomayo",
    "wof:placetype":"locality"
},
  "geometry": {"coordinates":[-76.07194,-9.80105],"type":"Point"}
}