{
  "type": "Feature",
  "properties": {
    "gn:admin1_code":"10",
    "gn:admin2_code":"1001.0",
    "gn:admin3_code":"100103.0",
    "gn:asciiname":"Acomayo",
    "gn:country_code":"PE",
    "gn:dem":2109,
    "gn:feature_class":"P",
    "gn:feature_code":"PPLA3",
    "gn:name":"Acomayo",
    "gn:population":0,
    "gn:timezone":"America/Lima",
    "iso:country":"PE",
    "name:aym_x_preferred":[
        "Aqumayu"
    ],
    "name:cat_x_preferred":[
        "Acomayo"
    ],
    "name:fas_x_preferred":[
        "\u0627\u06a9\u0648\u0645\u0627\u06cc\u0648"
    ],
    "name:ita_x_preferred":[
        "Acomayo"
    ],
    "name:mkd_x_preferred":[
        "\u0410\u043a\u043e\u043c\u0430\u0458\u043e"
    ],
    "name:nld_x_preferred":[
        "Acomayo"
    ],
    "name:pol_x_preferred":[
        "Acomayo"
    ],
    "name:por_x_preferred":[
        "Acomayo"
    ],
    "name:que_x_preferred":[
        "Aqumayu llaqta"
    ],
    "name:rus_x_preferred":[
        "\u0410\u043a\u043e\u043c\u0430\u0439\u043e"
    ],
    "name:spa_x_preferred":[
        "Acomayo"
    ],
    "name:war_x_preferred":[
        "Acomayo"
    ],
    "name:zho_x_preferred":[
        "\u963f\u79d1\u99ac\u7d04"
    ],
    "wof:name":"Acomayo",
    "wof:placetype":"locality"
},
  "geometry": {"coordinates":[-76.07194,-9.80105],"type":"Point"}
}