{
  "type": "Feature",
  "properties": {
    "gn:admin1_code":"18",
    "gn:admin2_code":"1802.0",
    "gn:admin3_code":"180206.0",
    "gn:asciiname":"Caparaqui",
    "gn:country_code":"PE",
    "gn:dem":4090,
    "gn:feature_class":"P",
    "gn:feature_code":"PPL",
    "gn:name":"Caparaqui",
    "gn:population":0,
    "gn:timezone":"America/Lima",
    "iso:country":"PE",
    "wof:name":"Caparaqui",
    "wof:placetype":"locality"
},
  "geometry": {"coordinates":[-70.71003,-16.31842],"type":"Point"}
}