{
  "type": "Feature",
  "properties": {
    "gn:admin1_code":"19.0",
    "gn:admin2_code":"1902.0",
    "gn:admin3_code":"190205.0",
    "gn:asciiname":"Chonta",
    "gn:country_code":"PE",
    "gn:dem":4256,
    "gn:feature_class":"P",
    "gn:feature_code":"PPL",
    "gn:name":"Chonta",
    "gn:population":0,
    "gn:timezone":"America/Lima",
    "iso:country":"PE",
    "wof:name":"Chonta",
    "wof:placetype":"locality"
},
  "geometry": {"coordinates":[-76.5425,-10.40472],"type":"Point"}
}