{
  "type": "Feature",
  "properties": {
    "gn:admin1_code":"05",
    "gn:admin2_code":"502.0",
    "gn:admin3_code":"50205.0",
    "gn:asciiname":"Chullcuhuaja",
    "gn:country_code":"PE",
    "gn:dem":3354,
    "gn:feature_class":"P",
    "gn:feature_code":"PPL",
    "gn:name":"Chullcuhuaja",
    "gn:population":0,
    "gn:timezone":"America/Lima",
    "iso:country":"PE",
    "name:und_x_variant":[
        "Cullcuhuaja",
        "Chullcuhuaja"
    ],
    "wof:name":"Chullcuhuaja",
    "wof:placetype":"locality"
},
  "geometry": {"coordinates":[-74.6058,-13.54355],"type":"Point"}
}