{
  "type": "Feature",
  "properties": {
    "gn:admin1_code":"21",
    "gn:admin2_code":"2106.0",
    "gn:admin3_code":"210607.0",
    "gn:asciiname":"Chulluhin",
    "gn:country_code":"PE",
    "gn:dem":3823,
    "gn:feature_class":"P",
    "gn:feature_code":"PPL",
    "gn:name":"Chulluhin",
    "gn:population":0,
    "gn:timezone":"America/Lima",
    "iso:country":"PE",
    "wof:name":"Chulluhin",
    "wof:placetype":"locality"
},
  "geometry": {"coordinates":[-69.97939000000001,-15.31162],"type":"Point"}
}