{
  "type": "Feature",
  "properties": {
    "gn:admin1_code":"08",
    "gn:admin2_code":"810.0",
    "gn:admin3_code":"81003.0",
    "gn:asciiname":"Miscca",
    "gn:country_code":"PE",
    "gn:dem":3412,
    "gn:feature_class":"P",
    "gn:feature_code":"PPL",
    "gn:name":"Miscca",
    "gn:population":0,
    "gn:timezone":"America/Lima",
    "iso:country":"PE",
    "name:und_x_variant":[
        "Mishca",
        "Miscca"
    ],
    "wof:name":"Miscca",
    "wof:placetype":"locality"
},
  "geometry": {"coordinates":[-72.07956999999998,-13.86632],"type":"Point"}
}