{
  "type": "Feature",
  "properties": {
    "gn:admin1_code":"22.0",
    "gn:admin2_code":"2210.0",
    "gn:admin3_code":"221001.0",
    "gn:asciiname":"Huayranga",
    "gn:country_code":"PE",
    "gn:dem":497,
    "gn:feature_class":"P",
    "gn:feature_code":"PPL",
    "gn:name":"Huayranga",
    "gn:population":0,
    "gn:timezone":"America/Lima",
    "iso:country":"PE",
    "wof:name":"Huayranga",
    "wof:placetype":"locality"
},
  "geometry": {"coordinates":[-76.47140999999998,-8.22235],"type":"Point"}
}