{
  "type": "Feature",
  "properties": {
    "gn:admin1_code":"05",
    "gn:admin2_code":"501.0",
    "gn:admin3_code":"50108.0",
    "gn:asciiname":"Chipingura",
    "gn:country_code":"PE",
    "gn:dem":3098,
    "gn:feature_class":"P",
    "gn:feature_code":"PPL",
    "gn:name":"Chipingura",
    "gn:population":0,
    "gn:timezone":"America/Lima",
    "iso:country":"PE",
    "wof:name":"Chipingura",
    "wof:placetype":"locality"
},
  "geometry": {"coordinates":[-74.15308,-13.05775],"type":"Point"}
}