{
  "type": "Feature",
  "properties": {
    "gn:admin1_code":"10",
    "gn:admin2_code":"1003.0",
    "gn:admin3_code":"100321.0",
    "gn:asciiname":"Shunqui",
    "gn:country_code":"PE",
    "gn:dem":3519,
    "gn:feature_class":"P",
    "gn:feature_code":"PPLA3",
    "gn:name":"Shunqui",
    "gn:population":0,
    "gn:timezone":"America/Lima",
    "iso:country":"PE",
    "wof:name":"Shunqui",
    "wof:placetype":"locality"
},
  "geometry": {"coordinates":[-76.78650999999998,-9.73384],"type":"Point"}
}