{
  "type": "Feature",
  "properties": {
    "gn:country":"PE",
    "gn:fcode":"PPLA3",
    "gn:population":9450,
    "iso:country":"PE",
    "name:ceb_x_preferred":[
        "Las Lomas"
    ],
    "name:deu_x_preferred":[
        "Las Lomas"
    ],
    "name:ita_x_preferred":[
        "Las Lomas"
    ],
    "name:nld_x_preferred":[
        "Las Lomas"
    ],
    "name:por_x_preferred":[
        "Las Lomas"
    ],
    "name:sco_x_preferred":[
        "Las Lomas"
    ],
    "name:spa_x_preferred":[
        "Las Lomas"
    ],
    "name:srp_x_preferred":[
        "\u041b\u0430\u0441 \u041b\u043e\u043c\u0430\u0441"
    ],
    "name:swe_x_preferred":[
        "Las Lomas"
    ],
    "name:vol_x_preferred":[
        "Las Lomas"
    ],
    "qs:name":"Las Lomas",
    "qs:photos_9r":0,
    "qs:photos_sr":0,
    "qs:pop_sr":"5",
    "wd:wordcount":54,
    "wof:name":"Las Lomas",
    "wof:placetype":"locality",
    "wof:population":9450
},
  "geometry": {"coordinates":[-80.24666999999999,-4.65333],"type":"Point"}
}