{
  "type": "Feature",
  "properties": {
    "gn:admin1_code":"23",
    "gn:admin2_code":"2304.0",
    "gn:admin3_code":"230401.0",
    "gn:asciiname":"Condorpica",
    "gn:cc2":"PE",
    "gn:country_code":"PE",
    "gn:dem":4362,
    "gn:feature_class":"P",
    "gn:feature_code":"PPL",
    "gn:name":"Condorpica",
    "gn:population":0,
    "gn:timezone":"America/Lima",
    "iso:country":"PE",
    "name:und_x_variant":[
        "Condorpico",
        "Condorpica"
    ],
    "wof:name":"Condorpica",
    "wof:placetype":"locality"
},
  "geometry": {"coordinates":[-69.73333000000001,-17.38332999999999],"type":"Point"}
}