{
  "type": "Feature",
  "properties": {
    "gn:admin1_code":"23",
    "gn:admin2_code":"2304.0",
    "gn:admin3_code":"230406.0",
    "gn:asciiname":"Colpapampa",
    "gn:country_code":"PE",
    "gn:dem":4036,
    "gn:feature_class":"P",
    "gn:feature_code":"PPL",
    "gn:name":"Colpapampa",
    "gn:population":0,
    "gn:timezone":"America/Lima",
    "iso:country":"PE",
    "wof:name":"Colpapampa",
    "wof:placetype":"locality"
},
  "geometry": {"coordinates":[-70.07942,-17.27504],"type":"Point"}
}