{
  "type": "Feature",
  "properties": {
    "gn:admin1_code":"23.0",
    "gn:admin2_code":"2303.0",
    "gn:admin3_code":"230303.0",
    "gn:asciiname":"Poza de Ite",
    "gn:country_code":"PE",
    "gn:dem":8,
    "gn:feature_class":"P",
    "gn:feature_code":"PPL",
    "gn:name":"Poza de Ite",
    "gn:population":0,
    "gn:timezone":"America/Lima",
    "iso:country":"PE",
    "wof:name":"Poza de Ite",
    "wof:placetype":"locality"
},
  "geometry": {"coordinates":[-70.93805999999999,-17.92278],"type":"Point"}
}