{
  "type": "Feature",
  "properties": {
    "gn:admin1_code":"3",
    "gn:admin2_code":"302.0",
    "gn:admin3_code":"30204.0",
    "gn:asciiname":"Arcahua",
    "gn:country_code":"PE",
    "gn:dem":3304,
    "gn:feature_class":"P",
    "gn:feature_code":"PPL",
    "gn:name":"Arcahua",
    "gn:population":0,
    "gn:timezone":"America/Lima",
    "iso:country":"PE",
    "wof:name":"Arcahua",
    "wof:placetype":"locality"
},
  "geometry": {"coordinates":[-73.05240999999999,-13.66851],"type":"Point"}
}