{
  "type": "Feature",
  "properties": {
    "gn:admin1_code":"15",
    "gn:admin2_code":"1510.0",
    "gn:admin3_code":"151020.0",
    "gn:asciiname":"Carhuacruz",
    "gn:country_code":"PE",
    "gn:dem":4481,
    "gn:feature_class":"P",
    "gn:feature_code":"PPL",
    "gn:name":"Carhuacruz",
    "gn:population":0,
    "gn:timezone":"America/Lima",
    "iso:country":"PE",
    "wof:name":"Carhuacruz",
    "wof:placetype":"locality"
},
  "geometry": {"coordinates":[-75.62786,-12.94276],"type":"Point"}
}