{
  "type": "Feature",
  "properties": {
    "gn:admin1_code":"2.0",
    "gn:admin2_code":"214.0",
    "gn:admin3_code":"21410.0",
    "gn:asciiname":"Tambo Blanco",
    "gn:country_code":"PE",
    "gn:dem":2739,
    "gn:feature_class":"P",
    "gn:feature_code":"PPL",
    "gn:name":"Tambo Blanco",
    "gn:population":0,
    "gn:timezone":"America/Lima",
    "iso:country":"PE",
    "wof:name":"Tambo Blanco",
    "wof:placetype":"locality"
},
  "geometry": {"coordinates":[-77.39039,-10.45406],"type":"Point"}
}