{
  "type": "Feature",
  "properties": {
    "gn:admin1_code":"10.0",
    "gn:admin2_code":"1009.0",
    "gn:admin3_code":"100905.0",
    "gn:asciiname":"Cuto",
    "gn:country_code":"PE",
    "gn:dem":210,
    "gn:feature_class":"P",
    "gn:feature_code":"PPL",
    "gn:name":"Cuto",
    "gn:population":0,
    "gn:timezone":"America/Lima",
    "iso:country":"PE",
    "wof:name":"Cuto",
    "wof:placetype":"locality"
},
  "geometry": {"coordinates":[-74.94483000000002,-9.58429],"type":"Point"}
}