{
  "type": "Feature",
  "properties": {
    "gn:admin1_code":"1.0",
    "gn:admin2_code":"105.0",
    "gn:admin3_code":"10509.0",
    "gn:asciiname":"Tincas",
    "gn:country_code":"PE",
    "gn:dem":2144,
    "gn:feature_class":"P",
    "gn:feature_code":"PPL",
    "gn:name":"Tincas",
    "gn:population":0,
    "gn:timezone":"America/Lima",
    "iso:country":"PE",
    "wof:name":"Tincas",
    "wof:placetype":"locality"
},
  "geometry": {"coordinates":[-77.92373000000001,-6.2009],"type":"Point"}
}