{
  "type": "Feature",
  "properties": {
    "gn:admin1_code":"20",
    "gn:admin2_code":"2004.0",
    "gn:admin3_code":"200405.0",
    "gn:asciiname":"Huaquilla",
    "gn:country_code":"PE",
    "gn:dem":124,
    "gn:feature_class":"P",
    "gn:feature_code":"PPL",
    "gn:name":"Huaquilla",
    "gn:population":0,
    "gn:timezone":"America/Lima",
    "iso:country":"PE",
    "name:und_x_variant":[
        "La Huaquilla",
        "Huaquilla"
    ],
    "wof:name":"Huaquilla",
    "wof:placetype":"locality"
},
  "geometry": {"coordinates":[-80.00960000000001,-5.20364],"type":"Point"}
}