{
  "type": "Feature",
  "properties": {
    "gn:admin1_code":"16",
    "gn:admin2_code":"1604.0",
    "gn:admin3_code":"160404.0",
    "gn:asciiname":"Alfaro",
    "gn:country_code":"PE",
    "gn:dem":77,
    "gn:feature_class":"P",
    "gn:feature_code":"PPL",
    "gn:name":"Alfaro",
    "gn:population":0,
    "gn:timezone":"America/Lima",
    "iso:country":"PE",
    "name:ceb_x_preferred":[
        "Alfaro"
    ],
    "name:deu_x_preferred":[
        "Alfaro"
    ],
    "name:fra_x_preferred":[
        "Alfaro"
    ],
    "name:glg_x_preferred":[
        "Alfaro"
    ],
    "name:ita_x_preferred":[
        "Alfaro"
    ],
    "name:jpn_x_preferred":[
        "\u30a2\u30eb\u30d5\u30a1\u30ed"
    ],
    "name:nld_x_preferred":[
        "Alfaro"
    ],
    "name:rus_x_preferred":[
        "\u0410\u043b\u044c\u0444\u0430\u0440\u043e"
    ],
    "name:spa_x_preferred":[
        "Alfaro"
    ],
    "name:swe_x_preferred":[
        "Alfaro"
    ],
    "name:ukr_x_preferred":[
        "\u0410\u043b\u044c\u0444\u0430\u0440\u043e"
    ],
    "name:zho_x_preferred":[
        "\u963f\u5c14\u6cd5\u7f57"
    ],
    "wof:name":"Alfaro",
    "wof:placetype":"locality"
},
  "geometry": {"coordinates":[-70.91126,-3.97152],"type":"Point"}
}