{
  "type": "Feature",
  "properties": {
    "gn:admin1_code":"10",
    "gn:admin2_code":"1006.0",
    "gn:admin3_code":"100604.0",
    "gn:asciiname":"Bajo Pacae",
    "gn:country_code":"PE",
    "gn:dem":657,
    "gn:feature_class":"P",
    "gn:feature_code":"PPL",
    "gn:name":"Bajo Pacae",
    "gn:population":0,
    "gn:timezone":"America/Lima",
    "iso:country":"PE",
    "wof:name":"Bajo Pacae",
    "wof:placetype":"locality"
},
  "geometry": {"coordinates":[-76.05056,-9.03028],"type":"Point"}
}