{
  "type": "Feature",
  "properties": {
    "gn:admin1_code":"13",
    "gn:admin2_code":"1309.0",
    "gn:admin3_code":"130904.0",
    "gn:asciiname":"Querobal",
    "gn:country_code":"PE",
    "gn:dem":3255,
    "gn:feature_class":"P",
    "gn:feature_code":"PPL",
    "gn:name":"Querobal",
    "gn:population":0,
    "gn:timezone":"America/Lima",
    "iso:country":"PE",
    "wof:name":"Querobal",
    "wof:placetype":"locality"
},
  "geometry": {"coordinates":[-77.93273000000001,-7.8221],"type":"Point"}
}