{
  "type": "Feature",
  "properties": {
    "gn:admin1_code":"17.0",
    "gn:admin2_code":"1703.0",
    "gn:asciiname":"Alto Peru",
    "gn:country_code":"PE",
    "gn:dem":259,
    "gn:feature_class":"P",
    "gn:feature_code":"PPL",
    "gn:name":"Alto Peru",
    "gn:population":0,
    "gn:timezone":"America/Lima",
    "iso:country":"PE",
    "name:spa_x_preferred":[
        "Alto Peru"
    ],
    "wof:name":"Alto Peru",
    "wof:placetype":"locality"
},
  "geometry": {"coordinates":[-69.25913,-11.45737],"type":"Point"}
}