{
  "type": "Feature",
  "properties": {
    "gn:admin1_code":"5.0",
    "gn:admin2_code":"504.0",
    "gn:admin3_code":"50405.0",
    "gn:asciiname":"Cucho Corral",
    "gn:country_code":"PE",
    "gn:dem":4084,
    "gn:feature_class":"P",
    "gn:feature_code":"PPL",
    "gn:name":"Cucho Corral",
    "gn:population":0,
    "gn:timezone":"America/Lima",
    "iso:country":"PE",
    "wof:name":"Cucho Corral",
    "wof:placetype":"locality"
},
  "geometry": {"coordinates":[-74.22672,-12.85152],"type":"Point"}
}