{
  "type": "Feature",
  "properties": {
    "gn:admin1_code":"10.0",
    "gn:admin2_code":"1010.0",
    "gn:admin3_code":"101007.0",
    "gn:asciiname":"Natipata",
    "gn:country_code":"PE",
    "gn:dem":3728,
    "gn:feature_class":"P",
    "gn:feature_code":"PPL",
    "gn:name":"Natipata",
    "gn:population":0,
    "gn:timezone":"America/Lima",
    "iso:country":"PE",
    "wof:name":"Natipata",
    "wof:placetype":"locality"
},
  "geometry": {"coordinates":[-76.61889000000002,-10.14778],"type":"Point"}
}