{
  "type": "Feature",
  "properties": {
    "gn:admin1_code":"05",
    "gn:admin2_code":"502.0",
    "gn:admin3_code":"50204.0",
    "gn:asciiname":"Mallocancha",
    "gn:country_code":"PE",
    "gn:dem":3763,
    "gn:feature_class":"P",
    "gn:feature_code":"PPL",
    "gn:name":"Mallocancha",
    "gn:population":0,
    "gn:timezone":"America/Lima",
    "iso:country":"PE",
    "wof:name":"Mallocancha",
    "wof:placetype":"locality"
},
  "geometry": {"coordinates":[-74.26666999999998,-13.53333],"type":"Point"}
}