{
  "type": "Feature",
  "properties": {
    "gn:admin1_code":"15.0",
    "gn:admin2_code":"1508.0",
    "gn:admin3_code":"150811.0",
    "gn:asciiname":"Callejon del Leon",
    "gn:country_code":"PE",
    "gn:dem":458,
    "gn:feature_class":"P",
    "gn:feature_code":"PPL",
    "gn:name":"Callejon del Leon",
    "gn:population":0,
    "gn:timezone":"America/Lima",
    "iso:country":"PE",
    "wof:name":"Callejon del Leon",
    "wof:placetype":"locality"
},
  "geometry": {"coordinates":[-77.31971999999998,-11.24306],"type":"Point"}
}