{
  "type": "Feature",
  "properties": {
    "gn:admin1_code":"8.0",
    "gn:admin2_code":"809.0",
    "gn:admin3_code":"80910.0",
    "gn:asciiname":"San Martin",
    "gn:country_code":"PE",
    "gn:dem":546,
    "gn:feature_class":"P",
    "gn:feature_code":"PPL",
    "gn:name":"San Mart\u00edn",
    "gn:population":0,
    "gn:timezone":"America/Lima",
    "iso:country":"PE",
    "name:spa_x_preferred":[
        "San Mart\u00edn"
    ],
    "wof:name":"San Martin",
    "wof:placetype":"locality"
},
  "geometry": {"coordinates":[-73.84339,-12.47919],"type":"Point"}
}