{
  "type": "Feature",
  "properties": {
    "gn:admin1_code":"21.0",
    "gn:admin2_code":"2112.0",
    "gn:asciiname":"Bajo Azata",
    "gn:country_code":"PE",
    "gn:dem":941,
    "gn:feature_class":"P",
    "gn:feature_code":"PPL",
    "gn:name":"Bajo Azata",
    "gn:population":0,
    "gn:timezone":"America/Lima",
    "iso:country":"PE",
    "name:spa_x_preferred":[
        "Bajo Azata"
    ],
    "wof:name":"Bajo Azata",
    "wof:placetype":"locality"
},
  "geometry": {"coordinates":[-69.01461,-13.98008],"type":"Point"}
}