{
  "type": "Feature",
  "properties": {
    "gn:admin1_code":"18",
    "gn:admin2_code":"1802.0",
    "gn:admin3_code":"180204.0",
    "gn:asciiname":"Mullipunco",
    "gn:country_code":"PE",
    "gn:dem":4025,
    "gn:feature_class":"P",
    "gn:feature_code":"PPL",
    "gn:name":"Mullipunco",
    "gn:population":0,
    "gn:timezone":"America/Lima",
    "iso:country":"PE",
    "wof:name":"Mullipunco",
    "wof:placetype":"locality"
},
  "geometry": {"coordinates":[-70.55759999999999,-16.12559],"type":"Point"}
}