{
  "type": "Feature",
  "properties": {
    "gn:admin1_code":"15",
    "gn:admin2_code":"1506.0",
    "gn:admin3_code":"150605.0",
    "gn:asciiname":"Chancayllo",
    "gn:country_code":"PE",
    "gn:dem":38,
    "gn:feature_class":"P",
    "gn:feature_code":"PPL",
    "gn:name":"Chancayllo",
    "gn:population":0,
    "gn:timezone":"America/Lima",
    "iso:country":"PE",
    "name:und_x_variant":[
        "Hacienda Chancayllo",
        "Chancayllo Hacienda",
        "Chancayllo"
    ],
    "wof:name":"Chancayllo",
    "wof:placetype":"locality"
},
  "geometry": {"coordinates":[-77.30889000000001,-11.48528],"type":"Point"}
}