{
  "type": "Feature",
  "properties": {
    "gn:admin1_code":"19",
    "gn:admin2_code":"1902.0",
    "gn:admin3_code":"190201.0",
    "gn:asciiname":"Huasca",
    "gn:country_code":"PE",
    "gn:dem":3891,
    "gn:feature_class":"P",
    "gn:feature_code":"PPL",
    "gn:name":"Huasca",
    "gn:population":0,
    "gn:timezone":"America/Lima",
    "iso:country":"PE",
    "wof:name":"Huasca",
    "wof:placetype":"locality"
},
  "geometry": {"coordinates":[-76.51935999999998,-10.52093],"type":"Point"}
}