{
  "type": "Feature",
  "properties": {
    "gn:country":"PE",
    "gn:fcode":"PPL",
    "gn:population":10926,
    "iso:country":"PE",
    "name:ara_x_preferred":[
        "\u0643\u0627\u0631\u0627\u0632\u060c \u0628\u064a\u0631\u0648"
    ],
    "name:ara_x_variant":[
        "\u0643\u0627\u0631\u0627\u0632"
    ],
    "name:aym_x_preferred":[
        "Qaras"
    ],
    "name:ceb_x_preferred":[
        "Car\u00e1s"
    ],
    "name:deu_x_preferred":[
        "Caraz"
    ],
    "name:eng_x_preferred":[
        "Caraz"
    ],
    "name:epo_x_preferred":[
        "Caraz"
    ],
    "name:fra_x_preferred":[
        "Caraz"
    ],
    "name:hin_x_preferred":[
        "\u0915\u0948\u0930\u091c\u093c"
    ],
    "name:hun_x_preferred":[
        "Caraz"
    ],
    "name:ita_x_preferred":[
        "Caraz"
    ],
    "name:jpn_x_preferred":[
        "\u30ab\u30e9\u30b9"
    ],
    "name:kat_x_preferred":[
        "\u10d9\u10d0\u10e0\u10d0\u10e1\u10d8"
    ],
    "name:kor_x_preferred":[
        "\uce74\ub77c\uc988"
    ],
    "name:lit_x_preferred":[
        "Karasas"
    ],
    "name:nld_x_preferred":[
        "Caraz"
    ],
    "name:por_x_preferred":[
        "Caraz"
    ],
    "name:que_x_preferred":[
        "Qaras"
    ],
    "name:ron_x_preferred":[
        "Caraz"
    ],
    "name:rus_x_preferred":[
        "\u041a\u0430\u0440\u0430\u0441"
    ],
    "name:spa_x_preferred":[
        "Caraz"
    ],
    "name:und_x_variant":[
        "Cav\u00e1s"
    ],
    "name:war_x_preferred":[
        "Caraz"
    ],
    "name:zho_x_preferred":[
        "\u5361\u62c9\u65af"
    ],
    "qs:name":"Car\u00e1s",
    "qs:photos_9r":0,
    "qs:photos_sr":0,
    "qs:pop_sr":"6",
    "wof:name":"Car\u00e1s",
    "wof:placetype":"locality",
    "wof:population":10926
},
  "geometry": {"coordinates":[-77.80901,-9.04692],"type":"Point"}
}