{
  "type": "Feature",
  "properties": {
    "gn:admin1_code":"11.0",
    "gn:admin2_code":"1101.0",
    "gn:admin3_code":"110111.0",
    "gn:asciiname":"Santa Julia",
    "gn:country_code":"PE",
    "gn:dem":398,
    "gn:feature_class":"P",
    "gn:feature_code":"PPLL",
    "gn:name":"Santa Julia",
    "gn:population":0,
    "gn:timezone":"America/Lima",
    "iso:country":"PE",
    "name:spa_x_preferred":[
        "Santa Julia"
    ],
    "wof:name":"Santa Julia",
    "wof:placetype":"locality"
},
  "geometry": {"coordinates":[-75.66246,-14.21467],"type":"Point"}
}