{
  "type": "Feature",
  "properties": {
    "gn:admin1_code":"08",
    "gn:admin2_code":"808.0",
    "gn:asciiname":"Negro Mayo",
    "gn:country_code":"PE",
    "gn:dem":4710,
    "gn:feature_class":"P",
    "gn:feature_code":"PPL",
    "gn:name":"Negro Mayo",
    "gn:population":0,
    "gn:timezone":"America/Lima",
    "iso:country":"PE",
    "wof:name":"Negro Mayo",
    "wof:placetype":"locality"
},
  "geometry": {"coordinates":[-71.15308,-15.23521],"type":"Point"}
}