{
  "type": "Feature",
  "properties": {
    "gn:admin1_code":"20",
    "gn:admin2_code":"2001.0",
    "gn:admin3_code":"200105.0",
    "gn:asciiname":"Narihuala",
    "gn:country_code":"PE",
    "gn:dem":23,
    "gn:feature_class":"P",
    "gn:feature_code":"PPL",
    "gn:name":"Narihual\u00e1",
    "gn:population":0,
    "gn:timezone":"America/Lima",
    "iso:country":"PE",
    "name:und_x_variant":[
        "Narhuala",
        "Narihual\u00e1"
    ],
    "wof:name":"Narihuala",
    "wof:placetype":"locality"
},
  "geometry": {"coordinates":[-80.68640000000001,-5.2912],"type":"Point"}
}