{
  "type": "Feature",
  "properties": {
    "gn:admin1_code":"10",
    "gn:admin2_code":"1009.0",
    "gn:asciiname":"El Dorado",
    "gn:country_code":"PE",
    "gn:dem":228,
    "gn:feature_class":"P",
    "gn:feature_code":"PPL",
    "gn:name":"El Dorado",
    "gn:population":0,
    "gn:timezone":"America/Lima",
    "iso:country":"PE",
    "wof:name":"El Dorado",
    "wof:placetype":"locality"
},
  "geometry": {"coordinates":[-75.0158,-9.81439],"type":"Point"}
}