{
  "type": "Feature",
  "properties": {
    "gn:admin1_code":"2",
    "gn:admin2_code":"218.0",
    "gn:admin3_code":"21802.0",
    "gn:asciiname":"Quipicsa Coto",
    "gn:country_code":"PE",
    "gn:dem":2112,
    "gn:feature_class":"P",
    "gn:feature_code":"PPL",
    "gn:name":"Quipicsa Coto",
    "gn:population":0,
    "gn:timezone":"America/Lima",
    "iso:country":"PE",
    "wof:name":"Quipicsa Coto",
    "wof:placetype":"locality"
},
  "geometry": {"coordinates":[-78.06111,-8.98417],"type":"Point"}
}