{
  "type": "Feature",
  "properties": {
    "gn:admin1_code":"05",
    "gn:admin2_code":"506.0",
    "gn:admin3_code":"50607.0",
    "gn:asciiname":"Huac Huas",
    "gn:country_code":"PE",
    "gn:dem":3172,
    "gn:feature_class":"P",
    "gn:feature_code":"PPL",
    "gn:name":"Huac Huas",
    "gn:population":0,
    "gn:timezone":"America/Lima",
    "iso:country":"PE",
    "wof:name":"Huac Huas",
    "wof:placetype":"locality"
},
  "geometry": {"coordinates":[-74.94221999999998,-14.13139],"type":"Point"}
}