{
  "type": "Feature",
  "properties": {
    "gn:admin1_code":"12.0",
    "gn:admin2_code":"1204.0",
    "gn:admin3_code":"120419.0",
    "gn:asciiname":"Cedruyoc",
    "gn:country_code":"PE",
    "gn:dem":1836,
    "gn:feature_class":"P",
    "gn:feature_code":"PPL",
    "gn:name":"Cedruyoc",
    "gn:population":0,
    "gn:timezone":"America/Lima",
    "iso:country":"PE",
    "wof:name":"Cedruyoc",
    "wof:placetype":"locality"
},
  "geometry": {"coordinates":[-75.30998000000002,-11.34859],"type":"Point"}
}