{
  "type": "Feature",
  "properties": {
    "gn:admin1_code":"16",
    "gn:admin2_code":"1604.0",
    "gn:admin3_code":"160404.0",
    "gn:asciiname":"Jesus de Praga",
    "gn:country_code":"PE",
    "gn:dem":78,
    "gn:feature_class":"P",
    "gn:feature_code":"PPL",
    "gn:name":"Jes\u00fas de Praga",
    "gn:population":0,
    "gn:timezone":"America/Lima",
    "iso:country":"PE",
    "wof:name":"Jesus de Praga",
    "wof:placetype":"locality"
},
  "geometry": {"coordinates":[-71.23028000000002,-3.94972],"type":"Point"}
}