{
  "type": "Feature",
  "properties": {
    "gn:admin1_code":"2.0",
    "gn:admin2_code":"206.0",
    "gn:admin3_code":"20601.0",
    "gn:asciiname":"Cajamarquilla",
    "gn:country_code":"PE",
    "gn:dem":2793,
    "gn:feature_class":"P",
    "gn:feature_code":"PPL",
    "gn:name":"Cajamarquilla",
    "gn:population":0,
    "gn:timezone":"America/Lima",
    "iso:country":"PE",
    "wof:name":"Cajamarquilla",
    "wof:placetype":"locality"
},
  "geometry": {"coordinates":[-77.63639000000001,-9.27472],"type":"Point"}
}