{
  "type": "Feature",
  "properties": {
    "gn:admin1_code":"16",
    "gn:admin2_code":"1601.0",
    "gn:admin3_code":"160108.0",
    "gn:asciiname":"Milagros",
    "gn:country_code":"PE",
    "gn:dem":100,
    "gn:feature_class":"P",
    "gn:feature_code":"PPL",
    "gn:name":"Milagros",
    "gn:population":0,
    "gn:timezone":"America/Lima",
    "iso:country":"PE",
    "name:ceb_x_preferred":[
        "Milagros"
    ],
    "name:deu_x_preferred":[
        "Milagros"
    ],
    "name:fra_x_preferred":[
        "Milagros"
    ],
    "name:ita_x_preferred":[
        "Milagros"
    ],
    "name:nld_x_preferred":[
        "Milagros"
    ],
    "name:swe_x_preferred":[
        "Milagros"
    ],
    "name:vie_x_preferred":[
        "Milagros"
    ],
    "name:war_x_preferred":[
        "Milagros"
    ],
    "wof:name":"Milagros",
    "wof:placetype":"locality"
},
  "geometry": {"coordinates":[-73.23997,-3.65639],"type":"Point"}
}