{
  "type": "Feature",
  "properties": {
    "gn:admin1_code":"10.0",
    "gn:admin2_code":"1003.0",
    "gn:admin3_code":"100313.0",
    "gn:asciiname":"Libertad",
    "gn:country_code":"PE",
    "gn:dem":4187,
    "gn:feature_class":"P",
    "gn:feature_code":"PPL",
    "gn:name":"Libertad",
    "gn:population":0,
    "gn:timezone":"America/Lima",
    "iso:country":"PE",
    "wof:name":"Libertad",
    "wof:placetype":"locality"
},
  "geometry": {"coordinates":[-76.87539,-9.70829],"type":"Point"}
}