{
  "type": "Feature",
  "properties": {
    "gn:admin1_code":"20",
    "gn:admin2_code":"2001.0",
    "gn:admin3_code":"200114.0",
    "gn:asciiname":"El Papayo",
    "gn:country_code":"PE",
    "gn:dem":140,
    "gn:feature_class":"P",
    "gn:feature_code":"PPL",
    "gn:name":"El Papayo",
    "gn:population":0,
    "gn:timezone":"America/Lima",
    "iso:country":"PE",
    "wof:name":"El Papayo",
    "wof:placetype":"locality"
},
  "geometry": {"coordinates":[-80.51208000000003,-4.85266],"type":"Point"}
}