{
  "type": "Feature",
  "properties": {
    "gn:admin1_code":"2.0",
    "gn:admin2_code":"203.0",
    "gn:admin3_code":"20304.0",
    "gn:asciiname":"Agupuquio",
    "gn:country_code":"PE",
    "gn:dem":2524,
    "gn:feature_class":"P",
    "gn:feature_code":"PPL",
    "gn:name":"Agupuquio",
    "gn:population":0,
    "gn:timezone":"America/Lima",
    "iso:country":"PE",
    "wof:name":"Agupuquio",
    "wof:placetype":"locality"
},
  "geometry": {"coordinates":[-76.9646,-9.11566],"type":"Point"}
}