{
  "type": "Feature",
  "properties": {
    "gn:admin1_code":"15.0",
    "gn:admin2_code":"1506.0",
    "gn:admin3_code":"150604.0",
    "gn:asciiname":"Cerro Locon",
    "gn:country_code":"PE",
    "gn:dem":861,
    "gn:feature_class":"P",
    "gn:feature_code":"PPL",
    "gn:name":"Cerro Locon",
    "gn:population":0,
    "gn:timezone":"America/Lima",
    "iso:country":"PE",
    "wof:name":"Cerro Locon",
    "wof:placetype":"locality"
},
  "geometry": {"coordinates":[-77.03166999999998,-11.38722],"type":"Point"}
}