{
  "type": "Feature",
  "properties": {
    "gn:admin1_code":"12.0",
    "gn:admin2_code":"1208.0",
    "gn:admin3_code":"120808.0",
    "gn:asciiname":"Chiuric",
    "gn:country_code":"PE",
    "gn:dem":4073,
    "gn:feature_class":"P",
    "gn:feature_code":"PPL",
    "gn:name":"Chiuric",
    "gn:population":0,
    "gn:timezone":"America/Lima",
    "iso:country":"PE",
    "wof:name":"Chiuric",
    "wof:placetype":"locality"
},
  "geometry": {"coordinates":[-75.98860999999999,-11.61185],"type":"Point"}
}