{
  "type": "Feature",
  "properties": {
    "gn:admin1_code":"14",
    "gn:admin2_code":"1403.0",
    "gn:admin3_code":"140308.0",
    "gn:asciiname":"La Juliana",
    "gn:country_code":"PE",
    "gn:dem":226,
    "gn:feature_class":"P",
    "gn:feature_code":"PPL",
    "gn:name":"La Juliana",
    "gn:population":0,
    "gn:timezone":"America/Lima",
    "iso:country":"PE",
    "wof:name":"La Juliana",
    "wof:placetype":"locality"
},
  "geometry": {"coordinates":[-79.70583000000001,-5.97509],"type":"Point"}
}