{
  "type": "Feature",
  "properties": {
    "gn:admin1_code":"9",
    "gn:admin2_code":"906.0",
    "gn:admin3_code":"90615.0",
    "gn:asciiname":"Santo Domingo de Capillas",
    "gn:country_code":"PE",
    "gn:dem":3456,
    "gn:feature_class":"P",
    "gn:feature_code":"PPL",
    "gn:name":"Santo Domingo de Capillas",
    "gn:population":0,
    "gn:timezone":"America/Lima",
    "iso:country":"PE",
    "name:und_x_variant":[
        "Capilla",
        "Capillas",
        "Santo Domingo de Capillas"
    ],
    "wof:name":"Santo Domingo de Capillas",
    "wof:placetype":"locality"
},
  "geometry": {"coordinates":[-75.24321999999999,-13.7373],"type":"Point"}
}