{
  "type": "Feature",
  "properties": {
    "gn:admin1_code":"17.0",
    "gn:admin2_code":"1703.0",
    "gn:asciiname":"Marcelino Cruz",
    "gn:country_code":"PE",
    "gn:dem":287,
    "gn:feature_class":"P",
    "gn:feature_code":"PPL",
    "gn:name":"Marcelino Cruz",
    "gn:population":0,
    "gn:timezone":"America/Lima",
    "iso:country":"PE",
    "name:spa_x_preferred":[
        "Marcelino Cruz"
    ],
    "wof:name":"Marcelino Cruz",
    "wof:placetype":"locality"
},
  "geometry": {"coordinates":[-69.05634999999999,-11.85901],"type":"Point"}
}