{
  "type": "Feature",
  "properties": {
    "gn:admin1_code":"9.0",
    "gn:admin2_code":"907.0",
    "gn:admin3_code":"90714.0",
    "gn:asciiname":"Tororumi",
    "gn:country_code":"PE",
    "gn:dem":4066,
    "gn:feature_class":"P",
    "gn:feature_code":"PPL",
    "gn:name":"Tororumi",
    "gn:population":0,
    "gn:timezone":"America/Lima",
    "iso:country":"PE",
    "wof:name":"Tororumi",
    "wof:placetype":"locality"
},
  "geometry": {"coordinates":[-74.80849000000001,-12.17699],"type":"Point"}
}