{
  "type": "Feature",
  "properties": {
    "gn:admin1_code":"11",
    "gn:admin2_code":"1105.0",
    "gn:admin3_code":"110503.0",
    "gn:asciiname":"Humay",
    "gn:cc2":"PE",
    "gn:country_code":"PE",
    "gn:dem":496,
    "gn:feature_class":"P",
    "gn:feature_code":"PPLA3",
    "gn:name":"Humay",
    "gn:population":0,
    "gn:timezone":"America/Lima",
    "iso:country":"PE",
    "name:und_x_variant":[
        "Huamai",
        "Humay"
    ],
    "wof:name":"Humay",
    "wof:placetype":"locality"
},
  "geometry": {"coordinates":[-75.90000000000001,-13.71667],"type":"Point"}
}