{
  "type": "Feature",
  "properties": {
    "gn:admin1_code":"2.0",
    "gn:admin2_code":"210.0",
    "gn:admin3_code":"21005.0",
    "gn:asciiname":"Colcabamba",
    "gn:country_code":"PE",
    "gn:dem":2685,
    "gn:feature_class":"P",
    "gn:feature_code":"PPL",
    "gn:name":"Colcabamba",
    "gn:population":0,
    "gn:timezone":"America/Lima",
    "iso:country":"PE",
    "wof:name":"Colcabamba",
    "wof:placetype":"locality"
},
  "geometry": {"coordinates":[-76.97648000000002,-9.2686],"type":"Point"}
}