{
  "type": "Feature",
  "properties": {
    "gn:admin1_code":"02",
    "gn:admin2_code":"211.0",
    "gn:admin3_code":"21103.0",
    "gn:asciiname":"Cochas",
    "gn:country_code":"PE",
    "gn:dem":415,
    "gn:feature_class":"P",
    "gn:feature_code":"PPL",
    "gn:name":"Cochas",
    "gn:population":0,
    "gn:timezone":"America/Lima",
    "iso:country":"PE",
    "name:und_x_variant":[
        "Coch\u00e1n",
        "Cochas"
    ],
    "wof:name":"Cochas",
    "wof:placetype":"locality"
},
  "geometry": {"coordinates":[-78.06610999999999,-9.85833],"type":"Point"}
}