{
  "type": "Feature",
  "properties": {
    "gn:admin1_code":"2",
    "gn:admin2_code":"211.0",
    "gn:admin3_code":"21101.0",
    "gn:asciiname":"Barbacay",
    "gn:country_code":"PE",
    "gn:dem":181,
    "gn:feature_class":"P",
    "gn:feature_code":"PPL",
    "gn:name":"Barbacay",
    "gn:population":0,
    "gn:timezone":"America/Lima",
    "iso:country":"PE",
    "name:und_x_variant":[
        "Hacienda Barbacay",
        "Barbacay"
    ],
    "wof:name":"Barbacay",
    "wof:placetype":"locality"
},
  "geometry": {"coordinates":[-77.9896,-10.00911],"type":"Point"}
}