{
  "type": "Feature",
  "properties": {
    "gn:admin1_code":"12.0",
    "gn:admin2_code":"1202.0",
    "gn:admin3_code":"120215.0",
    "gn:asciiname":"Manzanal",
    "gn:country_code":"PE",
    "gn:dem":3337,
    "gn:feature_class":"P",
    "gn:feature_code":"PPL",
    "gn:name":"Manzanal",
    "gn:population":0,
    "gn:timezone":"America/Lima",
    "iso:country":"PE",
    "wof:name":"Manzanal",
    "wof:placetype":"locality"
},
  "geometry": {"coordinates":[-75.31729,-11.87191],"type":"Point"}
}