{
  "type": "Feature",
  "properties": {
    "gn:admin1_code":"5.0",
    "gn:admin2_code":"505.0",
    "gn:admin3_code":"50504.0",
    "gn:asciiname":"Parabambi",
    "gn:country_code":"PE",
    "gn:dem":3425,
    "gn:feature_class":"P",
    "gn:feature_code":"PPL",
    "gn:name":"Parabambi",
    "gn:population":0,
    "gn:timezone":"America/Lima",
    "iso:country":"PE",
    "wof:name":"Parabambi",
    "wof:placetype":"locality"
},
  "geometry": {"coordinates":[-73.85805000000001,-13.19096],"type":"Point"}
}