{
  "type": "Feature",
  "properties": {
    "gn:admin1_code":"20",
    "gn:admin2_code":"2006.0",
    "gn:admin3_code":"200601.0",
    "gn:asciiname":"El Porton",
    "gn:country_code":"PE",
    "gn:dem":75,
    "gn:feature_class":"P",
    "gn:feature_code":"PPL",
    "gn:name":"El Port\u00f3n",
    "gn:population":0,
    "gn:timezone":"America/Lima",
    "iso:country":"PE",
    "wof:name":"El Porton",
    "wof:placetype":"locality"
},
  "geometry": {"coordinates":[-80.56286999999998,-4.78188],"type":"Point"}
}