{
  "type": "Feature",
  "properties": {
    "gn:admin1_code":"15",
    "gn:admin2_code":"1506.0",
    "gn:admin3_code":"150605.0",
    "gn:asciiname":"Pampa Libre",
    "gn:country_code":"PE",
    "gn:dem":127,
    "gn:feature_class":"P",
    "gn:feature_code":"PPL",
    "gn:name":"Pampa Libre",
    "gn:population":0,
    "gn:timezone":"America/Lima",
    "iso:country":"PE",
    "name:spa_x_preferred":[
        "Pampa Libre"
    ],
    "name:spa_x_variant":[
        "P.J. Pampa Libre"
    ],
    "wof:name":"Pampa Libre",
    "wof:placetype":"locality"
},
  "geometry": {"coordinates":[-77.28534999999999,-11.51295],"type":"Point"}
}