{
  "type": "Feature",
  "properties": {
    "gn:admin1_code":"16",
    "gn:admin2_code":"1601.0",
    "gn:admin3_code":"160110.0",
    "gn:asciiname":"Lobo",
    "gn:country_code":"PE",
    "gn:dem":225,
    "gn:feature_class":"P",
    "gn:feature_code":"PPL",
    "gn:name":"Lobo",
    "gn:population":0,
    "gn:timezone":"America/Lima",
    "iso:country":"PE",
    "wof:name":"Lobo",
    "wof:placetype":"locality"
},
  "geometry": {"coordinates":[-75.16667,-0.76667],"type":"Point"}
}