{
  "type": "Feature",
  "properties": {
    "gn:admin1_code":"10.0",
    "gn:admin2_code":"1006.0",
    "gn:admin3_code":"100604.0",
    "gn:asciiname":"Magdalena",
    "gn:country_code":"PE",
    "gn:dem":552,
    "gn:feature_class":"P",
    "gn:feature_code":"PPL",
    "gn:name":"Magdalena",
    "gn:population":0,
    "gn:timezone":"America/Lima",
    "iso:country":"PE",
    "name:ara_x_preferred":[
        "\u0645\u0627\u062c\u062f\u0627\u0644\u064a\u0646\u0627"
    ],
    "name:bre_x_preferred":[
        "Magdalena"
    ],
    "name:bul_x_preferred":[
        "\u041c\u0430\u0433\u0434\u0430\u043b\u0435\u043d\u0430"
    ],
    "name:cat_x_preferred":[
        "Magdalena"
    ],
    "name:ceb_x_preferred":[
        "Magdalena"
    ],
    "name:ces_x_preferred":[
        "Magdalena"
    ],
    "name:deu_x_preferred":[
        "Magdalena"
    ],
    "name:epo_x_preferred":[
        "Magdalena"
    ],
    "name:eus_x_preferred":[
        "Magdalena"
    ],
    "name:fas_x_preferred":[
        "\u0645\u0627\u06af\u062f\u0627\u0644\u0646\u0627"
    ],
    "name:fin_x_preferred":[
        "Magdalena"
    ],
    "name:fra_x_preferred":[
        "Magdalena"
    ],
    "name:heb_x_preferred":[
        "\u05de\u05d2\u05d3\u05dc\u05e0\u05d4"
    ],
    "name:ind_x_preferred":[
        "Magdalena"
    ],
    "name:ita_x_preferred":[
        "Magdalena"
    ],
    "name:jpn_x_preferred":[
        "\u30de\u30b0\u30c0\u30ec\u30ca"
    ],
    "name:kor_x_preferred":[
        "\ub9c9\ub2ec\ub808\ub098"
    ],
    "name:kor_x_variant":[
        "\ub9c8\uadf8\ub2ec\ub808\ub098"
    ],
    "name:lit_x_preferred":[
        "Magdalena"
    ],
    "name:nld_x_preferred":[
        "Magdalena"
    ],
    "name:nor_x_preferred":[
        "Magdalena"
    ],
    "name:pol_x_preferred":[
        "Magdalena"
    ],
    "name:por_x_preferred":[
        "Magdalena"
    ],
    "name:ron_x_preferred":[
        "Magdalena"
    ],
    "name:rus_x_preferred":[
        "\u041c\u0430\u0433\u0434\u0430\u043b\u0435\u043d\u0430"
    ],
    "name:sco_x_preferred":[
        "Magdalena"
    ],
    "name:spa_x_preferred":[
        "Magdalena"
    ],
    "name:srp_x_preferred":[
        "\u041c\u0430\u0433\u0434\u0430\u043b\u0435\u043d\u0430"
    ],
    "name:swe_x_preferred":[
        "Magdalena"
    ],
    "name:tgl_x_preferred":[
        "Magdalena"
    ],
    "name:tur_x_preferred":[
        "Magdalena"
    ],
    "name:ukr_x_preferred":[
        "\u041c\u0430\u0433\u0434\u0430\u043b\u0435\u043d\u0430"
    ],
    "name:urd_x_preferred":[
        "\u0645\u06cc\u06af\u0688\u0627\u0644\u06cc\u0646\u0627"
    ],
    "name:vie_x_preferred":[
        "Magdalena"
    ],
    "name:war_x_preferred":[
        "Magdalena"
    ],
    "wof:name":"Magdalena",
    "wof:placetype":"locality"
},
  "geometry": {"coordinates":[-76.19602,-8.81374],"type":"Point"}
}