{
  "type": "Feature",
  "properties": {
    "gn:admin1_code":"10.0",
    "gn:admin2_code":"1006.0",
    "gn:admin3_code":"100604.0",
    "gn:asciiname":"Magdalena",
    "gn:country_code":"PE",
    "gn:dem":552,
    "gn:feature_class":"P",
    "gn:feature_code":"PPL",
    "gn:name":"Magdalena",
    "gn:population":0,
    "gn:timezone":"America/Lima",
    "iso:country":"PE",
    "wof:name":"Magdalena",
    "wof:placetype":"locality"
},
  "geometry": {"coordinates":[-76.19601999999998,-8.81374],"type":"Point"}
}