{
  "type": "Feature",
  "properties": {
    "gn:admin1_code":"22.0",
    "gn:admin2_code":"2202.0",
    "gn:admin3_code":"220205.0",
    "gn:asciiname":"Centro Iberia",
    "gn:country_code":"PE",
    "gn:dem":278,
    "gn:feature_class":"P",
    "gn:feature_code":"PPL",
    "gn:name":"Centro Iberia",
    "gn:population":0,
    "gn:timezone":"America/Lima",
    "iso:country":"PE",
    "name:spa_x_preferred":[
        "Centro Iberia"
    ],
    "wof:name":"Centro Iberia",
    "wof:placetype":"locality"
},
  "geometry": {"coordinates":[-76.59607,-6.79485],"type":"Point"}
}