{
  "type": "Feature",
  "properties": {
    "gn:admin1_code":"12.0",
    "gn:admin2_code":"1206.0",
    "gn:admin3_code":"120606.0",
    "gn:asciiname":"Ticabeni",
    "gn:country_code":"PE",
    "gn:dem":508,
    "gn:feature_class":"P",
    "gn:feature_code":"PPL",
    "gn:name":"Ticabeni",
    "gn:population":0,
    "gn:timezone":"America/Lima",
    "iso:country":"PE",
    "wof:name":"Ticabeni",
    "wof:placetype":"locality"
},
  "geometry": {"coordinates":[-74.08358,-11.81851],"type":"Point"}
}