{
  "type": "Feature",
  "properties": {
    "gn:admin1_code":"12.0",
    "gn:admin2_code":"1204.0",
    "gn:admin3_code":"120419.0",
    "gn:asciiname":"San Jose de Ocoroyo",
    "gn:country_code":"PE",
    "gn:dem":1609,
    "gn:feature_class":"P",
    "gn:feature_code":"PPLL",
    "gn:name":"San Jos\u00e9 de Ocoroyo",
    "gn:population":0,
    "gn:timezone":"America/Lima",
    "iso:country":"PE",
    "wof:name":"San Jose de Ocoroyo",
    "wof:placetype":"locality"
},
  "geometry": {"coordinates":[-75.25516,-11.43064],"type":"Point"}
}