{
  "type": "Feature",
  "properties": {
    "gn:admin1_code":"15",
    "gn:admin2_code":"1510.0",
    "gn:admin3_code":"151020.0",
    "gn:asciiname":"Iscaycocha",
    "gn:country_code":"PE",
    "gn:dem":4319,
    "gn:feature_class":"P",
    "gn:feature_code":"PPL",
    "gn:name":"Iscaycocha",
    "gn:population":0,
    "gn:timezone":"America/Lima",
    "iso:country":"PE",
    "wof:name":"Iscaycocha",
    "wof:placetype":"locality"
},
  "geometry": {"coordinates":[-75.65394999999999,-12.90786],"type":"Point"}
}