{
  "type": "Feature",
  "properties": {
    "gn:admin1_code":"2.0",
    "gn:admin2_code":"210.0",
    "gn:admin3_code":"21010.0",
    "gn:asciiname":"Viscas",
    "gn:country_code":"PE",
    "gn:dem":3659,
    "gn:feature_class":"P",
    "gn:feature_code":"PPL",
    "gn:name":"Viscas",
    "gn:population":0,
    "gn:timezone":"America/Lima",
    "iso:country":"PE",
    "wof:name":"Viscas",
    "wof:placetype":"locality"
},
  "geometry": {"coordinates":[-76.84214,-9.14414],"type":"Point"}
}