{
  "type": "Feature",
  "properties": {
    "gn:admin1_code":"20",
    "gn:admin2_code":"2003.0",
    "gn:admin3_code":"200301.0",
    "gn:asciiname":"Juzgara",
    "gn:cc2":"PE",
    "gn:country_code":"PE",
    "gn:dem":2470,
    "gn:feature_class":"P",
    "gn:feature_code":"PPL",
    "gn:name":"Juzgara",
    "gn:population":0,
    "gn:timezone":"America/Lima",
    "iso:country":"PE",
    "name:und_x_variant":[
        "Juzgara Ciudad",
        "Juzgara"
    ],
    "wof:name":"Juzgara",
    "wof:placetype":"locality"
},
  "geometry": {"coordinates":[-79.46666999999999,-5.28333],"type":"Point"}
}