{
  "type": "Feature",
  "properties": {
    "gn:admin1_code":"9",
    "gn:admin2_code":"906.0",
    "gn:admin3_code":"90615.0",
    "gn:asciiname":"Alaseyhua",
    "gn:country_code":"PE",
    "gn:dem":4128,
    "gn:feature_class":"P",
    "gn:feature_code":"PPL",
    "gn:name":"Alaseyhua",
    "gn:population":0,
    "gn:timezone":"America/Lima",
    "iso:country":"PE",
    "wof:name":"Alaseyhua",
    "wof:placetype":"locality"
},
  "geometry": {"coordinates":[-75.20416999999998,-13.69],"type":"Point"}
}