{
  "type": "Feature",
  "properties": {
    "gn:admin1_code":"02",
    "gn:admin2_code":"211.0",
    "gn:admin3_code":"21101.0",
    "gn:asciiname":"Puerto Huarmey",
    "gn:country_code":"PE",
    "gn:dem":4,
    "gn:feature_class":"P",
    "gn:feature_code":"PPL",
    "gn:name":"Puerto Huarmey",
    "gn:population":0,
    "gn:timezone":"America/Lima",
    "iso:country":"PE",
    "name:und_x_variant":[
        "Huarmei",
        "Puerto Huarmey"
    ],
    "wof:name":"Puerto Huarmey",
    "wof:placetype":"locality"
},
  "geometry": {"coordinates":[-78.16549999999999,-10.09669],"type":"Point"}
}