{
  "type": "Feature",
  "properties": {
    "gn:admin1_code":"13",
    "gn:admin2_code":"1307.0",
    "gn:admin3_code":"130702.0",
    "gn:asciiname":"Faclo Chico",
    "gn:country_code":"PE",
    "gn:dem":72,
    "gn:feature_class":"P",
    "gn:feature_code":"PPL",
    "gn:name":"Faclo Chico",
    "gn:population":0,
    "gn:timezone":"America/Lima",
    "iso:country":"PE",
    "name:und_x_variant":[
        "Faclo Chico Hacienda",
        "Faclo Chico"
    ],
    "wof:name":"Faclo Chico",
    "wof:placetype":"locality"
},
  "geometry": {"coordinates":[-79.49101,-7.31209],"type":"Point"}
}