{
  "type": "Feature",
  "properties": {
    "gn:admin1_code":"4",
    "gn:admin2_code":"405.0",
    "gn:admin3_code":"40505.0",
    "gn:asciiname":"Anchaca",
    "gn:country_code":"PE",
    "gn:dem":4649,
    "gn:feature_class":"P",
    "gn:feature_code":"PPL",
    "gn:name":"Anchaca",
    "gn:population":0,
    "gn:timezone":"America/Lima",
    "iso:country":"PE",
    "wof:name":"Anchaca",
    "wof:placetype":"locality"
},
  "geometry": {"coordinates":[-71.88916999999999,-15.00417],"type":"Point"}
}