{
  "type": "Feature",
  "properties": {
    "gn:admin1_code":"8.0",
    "gn:admin2_code":"809.0",
    "gn:admin3_code":"80907.0",
    "gn:asciiname":"Los Angeles",
    "gn:country_code":"PE",
    "gn:dem":1172,
    "gn:feature_class":"P",
    "gn:feature_code":"PPL",
    "gn:name":"Los Angeles",
    "gn:population":0,
    "gn:timezone":"America/Lima",
    "iso:country":"PE",
    "wof:name":"Los Angeles",
    "wof:placetype":"locality"
},
  "geometry": {"coordinates":[-73.68439000000002,-12.66374],"type":"Point"}
}