{
  "type": "Feature",
  "properties": {
    "gn:admin1_code":"16",
    "gn:admin2_code":"1607.0",
    "gn:admin3_code":"160706.0",
    "gn:asciiname":"Puerto Pardo",
    "gn:country_code":"PE",
    "gn:dem":180,
    "gn:feature_class":"P",
    "gn:feature_code":"PPL",
    "gn:name":"Puerto Pardo",
    "gn:population":0,
    "gn:timezone":"America/Lima",
    "iso:country":"PE",
    "name:und_x_variant":[
        "Puerto Jos\u00e9 Pardo",
        "Puerto Pardo"
    ],
    "wof:name":"Puerto Pardo",
    "wof:placetype":"locality"
},
  "geometry": {"coordinates":[-76.41615,-3.70193],"type":"Point"}
}