{
  "type": "Feature",
  "properties": {
    "gn:admin1_code":"08",
    "gn:admin2_code":"808.0",
    "gn:admin3_code":"80805.0",
    "gn:asciiname":"Hector Tejada",
    "gn:country_code":"PE",
    "gn:dem":4002,
    "gn:feature_class":"P",
    "gn:feature_code":"PPL",
    "gn:name":"H\u00e9ctor Tejada",
    "gn:population":0,
    "gn:timezone":"America/Lima",
    "iso:country":"PE",
    "name:und_x_variant":[
        "Pallpata",
        "Palpata Hacienda",
        "Palpata",
        "H\u00e9ctor Tejada"
    ],
    "wof:name":"Hector Tejada",
    "wof:placetype":"locality"
},
  "geometry": {"coordinates":[-71.20961,-14.89088],"type":"Point"}
}