{
  "type": "Feature",
  "properties": {
    "gn:admin1_code":"15",
    "gn:admin2_code":"1509.0",
    "gn:admin3_code":"150901.0",
    "gn:asciiname":"Sanya",
    "gn:country_code":"PE",
    "gn:dem":3293,
    "gn:feature_class":"P",
    "gn:feature_code":"PPL",
    "gn:name":"Sanya",
    "gn:population":0,
    "gn:timezone":"America/Lima",
    "iso:country":"PE",
    "name:ara_x_preferred":[
        "\u0633\u0627\u0646\u064a\u0627"
    ],
    "name:bel_x_preferred":[
        "\u0421\u0430\u043d\u044c\u044f"
    ],
    "name:bod_x_preferred":[
        "\u0f66\u0f53\u0f0b\u0f61\u0f0b\u0f42\u0fb2\u0f7c\u0f44\u0f0b\u0f41\u0fb1\u0f7a\u0f62\u0f0d"
    ],
    "name:cdo_x_preferred":[
        "S\u0103ng-\u0101"
    ],
    "name:ceb_x_preferred":[
        "Sanya"
    ],
    "name:ces_x_preferred":[
        "San-ja"
    ],
    "name:cym_x_preferred":[
        "Sanya"
    ],
    "name:dan_x_preferred":[
        "Sanya"
    ],
    "name:deu_x_preferred":[
        "Sanya"
    ],
    "name:eus_x_preferred":[
        "Sanya"
    ],
    "name:fas_x_preferred":[
        "\u0633\u0627\u0646\u06cc\u0627"
    ],
    "name:fin_x_preferred":[
        "Sanya"
    ],
    "name:fra_x_preferred":[
        "Sanya"
    ],
    "name:ind_x_preferred":[
        "Sanya"
    ],
    "name:isl_x_preferred":[
        "Sanya"
    ],
    "name:ita_x_preferred":[
        "Sanya"
    ],
    "name:jpn_x_preferred":[
        "\u4e09\u4e9c\u5e02"
    ],
    "name:kik_x_preferred":[
        "Sanya"
    ],
    "name:kor_x_preferred":[
        "\uc2fc\uc57c\uc2dc"
    ],
    "name:mlg_x_preferred":[
        "Sanya"
    ],
    "name:nld_x_preferred":[
        "Sanya"
    ],
    "name:nor_x_preferred":[
        "Sanya"
    ],
    "name:pam_x_preferred":[
        "Sanya"
    ],
    "name:pol_x_preferred":[
        "Sanya"
    ],
    "name:por_x_preferred":[
        "Sanya"
    ],
    "name:ron_x_preferred":[
        "Sanya"
    ],
    "name:rus_x_preferred":[
        "\u0421\u0430\u043d\u044c\u044f"
    ],
    "name:sah_x_preferred":[
        "\u0421\u0430\u043d\u044c\u044f"
    ],
    "name:spa_x_preferred":[
        "Sanya"
    ],
    "name:swe_x_preferred":[
        "Sanya"
    ],
    "name:tgl_x_preferred":[
        "Sanya"
    ],
    "name:tha_x_preferred":[
        "\u0e0b\u0e32\u0e19\u0e22\u0e48\u0e32"
    ],
    "name:tur_x_preferred":[
        "Sanya"
    ],
    "name:uig_x_preferred":[
        "Senya shehiri"
    ],
    "name:ukr_x_preferred":[
        "\u0421\u0430\u043d\u044c\u044f"
    ],
    "name:urd_x_preferred":[
        "\u0633\u0627\u0646\u06cc\u0627"
    ],
    "name:vep_x_preferred":[
        "Sanj"
    ],
    "name:vie_x_preferred":[
        "Tam"
    ],
    "name:war_x_preferred":[
        "Sanya"
    ],
    "name:zho_x_preferred":[
        "\u4e09\u4e9a\u5e02"
    ],
    "wof:name":"Sanya",
    "wof:placetype":"locality"
},
  "geometry": {"coordinates":[-76.7898,-10.68705],"type":"Point"}
}