{
  "type": "Feature",
  "properties": {
    "gn:admin1_code":"12.0",
    "gn:admin2_code":"1208.0",
    "gn:admin3_code":"120801.0",
    "gn:asciiname":"Pataleoc",
    "gn:country_code":"PE",
    "gn:dem":3797,
    "gn:feature_class":"P",
    "gn:feature_code":"PPL",
    "gn:name":"Pataleoc",
    "gn:population":0,
    "gn:timezone":"America/Lima",
    "iso:country":"PE",
    "wof:name":"Pataleoc",
    "wof:placetype":"locality"
},
  "geometry": {"coordinates":[-75.84201999999998,-11.63277],"type":"Point"}
}