{
  "type": "Feature",
  "properties": {
    "gn:admin1_code":"12",
    "gn:admin2_code":"1202.0",
    "gn:admin3_code":"120214.0",
    "gn:asciiname":"Santa Rosa de Huarmita",
    "gn:country_code":"PE",
    "gn:dem":3780,
    "gn:feature_class":"P",
    "gn:feature_code":"PPL",
    "gn:name":"Santa Rosa de Huarmita",
    "gn:population":0,
    "gn:timezone":"America/Lima",
    "iso:country":"PE",
    "wof:name":"Santa Rosa de Huarmita",
    "wof:placetype":"locality"
},
  "geometry": {"coordinates":[-75.56222,-12.05833],"type":"Point"}
}