{
  "type": "Feature",
  "properties": {
    "gn:admin1_code":"01",
    "gn:admin2_code":"103.0",
    "gn:admin3_code":"10310.0",
    "gn:asciiname":"Tilango",
    "gn:country_code":"PE",
    "gn:dem":926,
    "gn:feature_class":"P",
    "gn:feature_code":"PPL",
    "gn:name":"Tilango",
    "gn:population":0,
    "gn:timezone":"America/Lima",
    "iso:country":"PE",
    "wof:name":"Tilango",
    "wof:placetype":"locality"
},
  "geometry": {"coordinates":[-78.07984,-5.91518],"type":"Point"}
}