{
  "type": "Feature",
  "properties": {
    "gn:admin1_code":"24",
    "gn:admin2_code":"2403.0",
    "gn:admin3_code":"240303.0",
    "gn:asciiname":"El Tutumo",
    "gn:country_code":"PE",
    "gn:dem":98,
    "gn:feature_class":"P",
    "gn:feature_code":"PPL",
    "gn:name":"El Tutumo",
    "gn:population":0,
    "gn:timezone":"America/Lima",
    "iso:country":"PE",
    "name:und_x_variant":[
        "Tutumo",
        "El Tutumo"
    ],
    "wof:name":"El Tutumo",
    "wof:placetype":"locality"
},
  "geometry": {"coordinates":[-80.25375,-3.69649],"type":"Point"}
}