{
  "type": "Feature",
  "properties": {
    "gn:admin1_code":"9.0",
    "gn:admin2_code":"905.0",
    "gn:admin3_code":"90502.0",
    "gn:asciiname":"Loma",
    "gn:country_code":"PE",
    "gn:dem":3612,
    "gn:feature_class":"P",
    "gn:feature_code":"PPL",
    "gn:name":"Loma",
    "gn:population":0,
    "gn:timezone":"America/Lima",
    "iso:country":"PE",
    "wof:name":"Loma",
    "wof:placetype":"locality"
},
  "geometry": {"coordinates":[-74.55949,-12.63519],"type":"Point"}
}