{
  "type": "Feature",
  "properties": {
    "gn:admin1_code":"9.0",
    "gn:admin2_code":"905.0",
    "gn:admin3_code":"90502.0",
    "gn:asciiname":"Loma",
    "gn:country_code":"PE",
    "gn:dem":3612,
    "gn:feature_class":"P",
    "gn:feature_code":"PPL",
    "gn:name":"Loma",
    "gn:population":0,
    "gn:timezone":"America/Lima",
    "iso:country":"PE",
    "name:ceb_x_preferred":[
        "Loma"
    ],
    "name:deu_x_preferred":[
        "Loma"
    ],
    "name:fra_x_preferred":[
        "Loma"
    ],
    "name:ita_x_preferred":[
        "Loma"
    ],
    "name:nld_x_preferred":[
        "Loma"
    ],
    "name:pol_x_preferred":[
        "Loma"
    ],
    "name:pus_x_preferred":[
        "\u0644\u0648\u0645\u0647"
    ],
    "name:spa_x_preferred":[
        "Loma"
    ],
    "name:srp_x_preferred":[
        "\u041b\u043e\u043c\u0430"
    ],
    "name:swe_x_preferred":[
        "Loma"
    ],
    "name:ukr_x_preferred":[
        "\u041b\u043e\u043c\u0430"
    ],
    "name:vol_x_preferred":[
        "Loma"
    ],
    "wof:name":"Loma",
    "wof:placetype":"locality"
},
  "geometry": {"coordinates":[-74.55949,-12.63519],"type":"Point"}
}