{
  "type": "Feature",
  "properties": {
    "gn:admin1_code":"14",
    "gn:admin2_code":"1401.0",
    "gn:admin3_code":"140116.0",
    "gn:asciiname":"Songoy",
    "gn:country_code":"PE",
    "gn:dem":122,
    "gn:feature_class":"P",
    "gn:feature_code":"PPL",
    "gn:name":"Songoy",
    "gn:population":0,
    "gn:timezone":"America/Lima",
    "iso:country":"PE",
    "name:spa_x_preferred":[
        "Songoy"
    ],
    "wof:name":"Songoy",
    "wof:placetype":"locality"
},
  "geometry": {"coordinates":[-79.47776999999998,-6.88891],"type":"Point"}
}