{
  "type": "Feature",
  "properties": {
    "gn:admin1_code":"15",
    "gn:admin2_code":"1505.0",
    "gn:admin3_code":"150505.0",
    "gn:asciiname":"Isla Verde",
    "gn:country_code":"PE",
    "gn:dem":17,
    "gn:feature_class":"P",
    "gn:feature_code":"PPL",
    "gn:name":"Isla Verde",
    "gn:population":0,
    "gn:timezone":"America/Lima",
    "iso:country":"PE",
    "name:ceb_x_preferred":[
        "Isla Verde"
    ],
    "name:spa_x_preferred":[
        "Isla Verde"
    ],
    "name:swe_x_preferred":[
        "Isla Verde"
    ],
    "wof:name":"Isla Verde",
    "wof:placetype":"locality"
},
  "geometry": {"coordinates":[-76.71666999999999,-12.53333],"type":"Point"}
}