{
  "type": "Feature",
  "properties": {
    "gn:admin1_code":"02",
    "gn:admin2_code":"218.0",
    "gn:admin3_code":"21805.0",
    "gn:asciiname":"Paderones",
    "gn:country_code":"PE",
    "gn:dem":416,
    "gn:feature_class":"P",
    "gn:feature_code":"PPL",
    "gn:name":"Paderones",
    "gn:population":0,
    "gn:timezone":"America/Lima",
    "iso:country":"PE",
    "wof:name":"Paderones",
    "wof:placetype":"locality"
},
  "geometry": {"coordinates":[-78.20043000000003,-9.15151],"type":"Point"}
}