{
  "type": "Feature",
  "properties": {
    "gn:admin1_code":"01",
    "gn:admin2_code":"104.0",
    "gn:asciiname":"Teniente Pinglo",
    "gn:country_code":"PE",
    "gn:dem":181,
    "gn:feature_class":"P",
    "gn:feature_code":"PPL",
    "gn:name":"Teniente Pinglo",
    "gn:population":0,
    "gn:timezone":"America/Lima",
    "iso:country":"PE",
    "name:und_x_variant":[
        "Pinglo",
        "Sub Teniente Pinglo",
        "Teniente Pinglo"
    ],
    "wof:name":"Teniente Pinglo",
    "wof:placetype":"locality"
},
  "geometry": {"coordinates":[-77.64055,-4.4296],"type":"Point"}
}