{
  "type": "Feature",
  "properties": {
    "gn:admin1_code":"2.0",
    "gn:admin2_code":"219.0",
    "gn:asciiname":"Pano Irca",
    "gn:country_code":"PE",
    "gn:dem":2522,
    "gn:feature_class":"P",
    "gn:feature_code":"PPL",
    "gn:name":"Pa\u00f1o Irca",
    "gn:population":0,
    "gn:timezone":"America/Lima",
    "iso:country":"PE",
    "wof:name":"Pano Irca",
    "wof:placetype":"locality"
},
  "geometry": {"coordinates":[-77.39917,-8.40722],"type":"Point"}
}