{
  "type": "Feature",
  "properties": {
    "gn:admin1_code":"14",
    "gn:admin2_code":"1402.0",
    "gn:admin3_code":"140202.0",
    "gn:asciiname":"Quinua",
    "gn:country_code":"PE",
    "gn:dem":2356,
    "gn:feature_class":"P",
    "gn:feature_code":"PPL",
    "gn:name":"Quinua",
    "gn:population":0,
    "gn:timezone":"America/Lima",
    "iso:country":"PE",
    "wof:name":"Quinua",
    "wof:placetype":"locality"
},
  "geometry": {"coordinates":[-79.19266,-6.0434],"type":"Point"}
}