{
  "type": "Feature",
  "properties": {
    "gn:admin1_code":"15.0",
    "gn:admin2_code":"1507.0",
    "gn:admin3_code":"150702.0",
    "gn:asciiname":"Palma Derecha",
    "gn:country_code":"PE",
    "gn:dem":1531,
    "gn:feature_class":"P",
    "gn:feature_code":"PPL",
    "gn:name":"Palma Derecha",
    "gn:population":0,
    "gn:timezone":"America/Lima",
    "iso:country":"PE",
    "name:spa_x_preferred":[
        "Palma Derecha"
    ],
    "wof:name":"Palma Derecha",
    "wof:placetype":"locality"
},
  "geometry": {"coordinates":[-76.56276,-12.04481],"type":"Point"}
}