{
  "type": "Feature",
  "properties": {
    "gn:admin1_code":"25",
    "gn:admin2_code":"2502.0",
    "gn:admin3_code":"250201.0",
    "gn:asciiname":"Mision Unine",
    "gn:country_code":"PE",
    "gn:dem":276,
    "gn:feature_class":"P",
    "gn:feature_code":"PPL",
    "gn:name":"Misi\u00f3n Unine",
    "gn:population":0,
    "gn:timezone":"America/Lima",
    "iso:country":"PE",
    "name:spa_x_preferred":[
        "Misi\u00f3n Unine"
    ],
    "wof:name":"Mision Unine",
    "wof:placetype":"locality"
},
  "geometry": {"coordinates":[-73.97176999999998,-10.63728],"type":"Point"}
}