{
  "type": "Feature",
  "properties": {
    "gn:admin1_code":"01",
    "gn:admin2_code":"104.0",
    "gn:admin3_code":"10403.0",
    "gn:asciiname":"Kucuaza",
    "gn:country_code":"PE",
    "gn:dem":213,
    "gn:feature_class":"P",
    "gn:feature_code":"PPL",
    "gn:name":"Kucuaza",
    "gn:population":0,
    "gn:timezone":"America/Lima",
    "iso:country":"PE",
    "wof:name":"Kucuaza",
    "wof:placetype":"locality"
},
  "geometry": {"coordinates":[-77.88167,-3.33833],"type":"Point"}
}