{
  "type": "Feature",
  "properties": {
    "gn:admin1_code":"20",
    "gn:admin2_code":"2005.0",
    "gn:admin3_code":"200506.0",
    "gn:asciiname":"Hacienda La Macarena",
    "gn:country_code":"PE",
    "gn:dem":26,
    "gn:feature_class":"P",
    "gn:feature_code":"PPL",
    "gn:name":"Hacienda La Macarena",
    "gn:population":0,
    "gn:timezone":"America/Lima",
    "iso:country":"PE",
    "name:spa_x_preferred":[
        "Hacienda La Macarena"
    ],
    "name:spa_x_variant":[
        "La Macarena"
    ],
    "wof:name":"Hacienda La Macarena",
    "wof:placetype":"locality"
},
  "geometry": {"coordinates":[-80.94422,-4.86875],"type":"Point"}
}