{
  "type": "Feature",
  "properties": {
    "gn:admin1_code":"23",
    "gn:admin2_code":"2301.0",
    "gn:admin3_code":"230106.0",
    "gn:asciiname":"Miculla",
    "gn:country_code":"PE",
    "gn:dem":1202,
    "gn:feature_class":"P",
    "gn:feature_code":"PPL",
    "gn:name":"Miculla",
    "gn:population":0,
    "gn:timezone":"America/Lima",
    "iso:country":"PE",
    "wof:name":"Miculla",
    "wof:placetype":"locality"
},
  "geometry": {"coordinates":[-70.13759,-17.88361],"type":"Point"}
}