{
  "type": "Feature",
  "properties": {
    "gn:admin1_code":"15",
    "gn:admin2_code":"1501.0",
    "gn:admin3_code":"150103.0",
    "gn:asciiname":"Bravo",
    "gn:cc2":"PE",
    "gn:country_code":"PE",
    "gn:dem":282,
    "gn:feature_class":"P",
    "gn:feature_code":"PPL",
    "gn:name":"Bravo",
    "gn:population":0,
    "gn:timezone":"America/Lima",
    "iso:country":"PE",
    "name:cat_x_preferred":[
        "Bravo"
    ],
    "name:ceb_x_preferred":[
        "Bravo"
    ],
    "name:ces_x_preferred":[
        "Bravo"
    ],
    "name:deu_x_preferred":[
        "Bravo"
    ],
    "name:est_x_preferred":[
        "Bravo"
    ],
    "name:fin_x_preferred":[
        "Bravo"
    ],
    "name:fra_x_preferred":[
        "Bravo"
    ],
    "name:heb_x_preferred":[
        "\u05d1\u05e8\u05d0\u05d1\u05d5"
    ],
    "name:ita_x_preferred":[
        "Bravo"
    ],
    "name:jpn_x_preferred":[
        "\u30d6\u30e9\u30dc\u30fc"
    ],
    "name:kat_x_preferred":[
        "\u10d1\u10e0\u10d0\u10d5\u10dd"
    ],
    "name:kor_x_preferred":[
        "\ube0c\ub77c\ubcf4"
    ],
    "name:lav_x_preferred":[
        "Bravo"
    ],
    "name:nld_x_preferred":[
        "Bravo"
    ],
    "name:nor_x_preferred":[
        "Bravo"
    ],
    "name:por_x_preferred":[
        "Bravo"
    ],
    "name:rus_x_preferred":[
        "Bravo"
    ],
    "name:sco_x_preferred":[
        "Bravo"
    ],
    "name:spa_x_preferred":[
        "Bravo"
    ],
    "name:srp_x_preferred":[
        "\u0411\u0440\u0430\u0432\u043e"
    ],
    "name:swe_x_preferred":[
        "Bravo"
    ],
    "name:ukr_x_preferred":[
        "\u0411\u0440\u0430\u0432\u043e"
    ],
    "name:und_x_variant":[
        "Bravo Grande",
        "Bravo"
    ],
    "wof:name":"Bravo",
    "wof:placetype":"locality"
},
  "geometry": {"coordinates":[-76.95,-12.05],"type":"Point"}
}