{
  "type": "Feature",
  "properties": {
    "gn:admin1_code":"01",
    "gn:admin2_code":"107.0",
    "gn:admin3_code":"10703.0",
    "gn:asciiname":"Octucho",
    "gn:country_code":"PE",
    "gn:dem":1200,
    "gn:feature_class":"P",
    "gn:feature_code":"PPL",
    "gn:name":"Octucho",
    "gn:population":0,
    "gn:timezone":"America/Lima",
    "iso:country":"PE",
    "wof:name":"Octucho",
    "wof:placetype":"locality"
},
  "geometry": {"coordinates":[-78.57044999999999,-5.99663],"type":"Point"}
}