{
  "type": "Feature",
  "properties": {
    "gn:admin1_code":"11",
    "gn:admin2_code":"1105.0",
    "gn:asciiname":"Chilca",
    "gn:country_code":"PE",
    "gn:dem":3077,
    "gn:feature_class":"P",
    "gn:feature_code":"PPL",
    "gn:name":"Chilca",
    "gn:population":0,
    "gn:timezone":"America/Lima",
    "iso:country":"PE",
    "name:spa_x_preferred":[
        "Chilca"
    ],
    "wof:name":"Chilca",
    "wof:placetype":"locality"
},
  "geometry": {"coordinates":[-75.55941999999997,-13.41593],"type":"Point"}
}