{
  "type": "Feature",
  "properties": {
    "gn:admin1_code":"11",
    "gn:admin2_code":"1105.0",
    "gn:asciiname":"Chilca",
    "gn:country_code":"PE",
    "gn:dem":3077,
    "gn:feature_class":"P",
    "gn:feature_code":"PPL",
    "gn:name":"Chilca",
    "gn:population":0,
    "gn:timezone":"America/Lima",
    "iso:country":"PE",
    "name:ara_x_preferred":[
        "\u0634\u064a\u0644\u0643\u0627"
    ],
    "name:ben_x_preferred":[
        "\u099a\u09bf\u09b2\u0995\u09be"
    ],
    "name:deu_x_preferred":[
        "Chilca"
    ],
    "name:ell_x_preferred":[
        "\u03a4\u03c3\u03af\u03bb\u03ba\u03b1"
    ],
    "name:fas_x_preferred":[
        "\u0686\u06cc\u0644\u06a9\u0627"
    ],
    "name:heb_x_preferred":[
        "\u05e6'\u05d9\u05dc\u05e7\u05d4"
    ],
    "name:hin_x_preferred":[
        "\u091a\u093f\u0932\u094d\u0915\u093e"
    ],
    "name:hun_x_preferred":[
        "Chilca"
    ],
    "name:ind_x_preferred":[
        "Chilca"
    ],
    "name:ita_x_preferred":[
        "Chilca"
    ],
    "name:jpn_x_preferred":[
        "\u30c1\u30eb\u30ab"
    ],
    "name:kor_x_preferred":[
        "\uce60\uce74"
    ],
    "name:pol_x_preferred":[
        "Chilca"
    ],
    "name:por_x_preferred":[
        "Chilca"
    ],
    "name:rus_x_preferred":[
        "\u0427\u0438\u043b\u044c\u043a\u0430"
    ],
    "name:spa_x_preferred":[
        "Chilca"
    ],
    "name:swe_x_preferred":[
        "Chilca"
    ],
    "name:tur_x_preferred":[
        "Chilca"
    ],
    "name:ukr_x_preferred":[
        "\u0427\u0456\u043b\u043a\u0430"
    ],
    "name:urd_x_preferred":[
        "\u0686\u0644\u06a9\u0627"
    ],
    "name:vie_x_preferred":[
        "Chilca"
    ],
    "name:zho_cn_x_preferred":[
        "\u5947\u5c14\u5361"
    ],
    "name:zho_tw_x_preferred":[
        "\u5947\u723e\u5361"
    ],
    "wof:name":"Chilca",
    "wof:placetype":"locality"
},
  "geometry": {"coordinates":[-75.55942,-13.41593],"type":"Point"}
}