{
  "type": "Feature",
  "properties": {
    "gn:admin1_code":"08",
    "gn:admin2_code":"809.0",
    "gn:admin3_code":"80902.0",
    "gn:asciiname":"Malaquiato",
    "gn:country_code":"PE",
    "gn:dem":692,
    "gn:feature_class":"P",
    "gn:feature_code":"PPL",
    "gn:name":"Malaquiato",
    "gn:population":0,
    "gn:timezone":"America/Lima",
    "iso:country":"PE",
    "wof:name":"Malaquiato",
    "wof:placetype":"locality"
},
  "geometry": {"coordinates":[-72.91667,-12.41667],"type":"Point"}
}