{
  "type": "Feature",
  "properties": {
    "gn:admin1_code":"05",
    "gn:admin2_code":"505.0",
    "gn:admin3_code":"50505.0",
    "gn:asciiname":"Collpata",
    "gn:country_code":"PE",
    "gn:dem":3059,
    "gn:feature_class":"P",
    "gn:feature_code":"PPL",
    "gn:name":"Collpata",
    "gn:population":0,
    "gn:timezone":"America/Lima",
    "iso:country":"PE",
    "name:und_x_variant":[
        "Collpapata",
        "Collpata"
    ],
    "wof:name":"Collpata",
    "wof:placetype":"locality"
},
  "geometry": {"coordinates":[-73.54340999999999,-13.32659],"type":"Point"}
}