{
  "type": "Feature",
  "properties": {
    "gn:admin1_code":"14",
    "gn:admin2_code":"1401.0",
    "gn:admin3_code":"140117.0",
    "gn:asciiname":"La Planta",
    "gn:country_code":"PE",
    "gn:dem":105,
    "gn:feature_class":"P",
    "gn:feature_code":"PPL",
    "gn:name":"La Planta",
    "gn:population":0,
    "gn:timezone":"America/Lima",
    "iso:country":"PE",
    "name:spa_x_preferred":[
        "La Planta"
    ],
    "wof:name":"La Planta",
    "wof:placetype":"locality"
},
  "geometry": {"coordinates":[-79.56704000000001,-6.7448],"type":"Point"}
}