{
  "type": "Feature",
  "properties": {
    "gn:admin1_code":"12.0",
    "gn:admin2_code":"1203.0",
    "gn:admin3_code":"120306.0",
    "gn:asciiname":"La Florencia",
    "gn:country_code":"PE",
    "gn:dem":1008,
    "gn:feature_class":"P",
    "gn:feature_code":"PPL",
    "gn:name":"La Florencia",
    "gn:population":0,
    "gn:timezone":"America/Lima",
    "iso:country":"PE",
    "wof:name":"La Florencia",
    "wof:placetype":"locality"
},
  "geometry": {"coordinates":[-75.32555000000001,-11.24184],"type":"Point"}
}