{
  "type": "Feature",
  "properties": {
    "gn:admin1_code":"14",
    "gn:admin2_code":"1403.0",
    "gn:admin3_code":"140310.0",
    "gn:asciiname":"Pilasca",
    "gn:country_code":"PE",
    "gn:dem":517,
    "gn:feature_class":"P",
    "gn:feature_code":"PPL",
    "gn:name":"Pilasca",
    "gn:population":0,
    "gn:timezone":"America/Lima",
    "iso:country":"PE",
    "wof:name":"Pilasca",
    "wof:placetype":"locality"
},
  "geometry": {"coordinates":[-79.58571999999999,-6.22617],"type":"Point"}
}