{
  "type": "Feature",
  "properties": {
    "gn:admin1_code":"15",
    "gn:admin2_code":"1507.0",
    "gn:admin3_code":"150704.0",
    "gn:asciiname":"Chaca",
    "gn:country_code":"PE",
    "gn:dem":3811,
    "gn:feature_class":"P",
    "gn:feature_code":"PPL",
    "gn:name":"Chaca",
    "gn:population":0,
    "gn:timezone":"America/Lima",
    "iso:country":"PE",
    "name:ceb_x_preferred":[
        "Chaca"
    ],
    "name:kor_x_preferred":[
        "\ucc28\uce74\uc18d"
    ],
    "name:swe_x_preferred":[
        "Chaca"
    ],
    "wof:name":"Chaca",
    "wof:placetype":"locality"
},
  "geometry": {"coordinates":[-76.44499999999999,-11.66722],"type":"Point"}
}