{
  "type": "Feature",
  "properties": {
    "gn:admin1_code":"5",
    "gn:admin2_code":"510.0",
    "gn:admin3_code":"51005.0",
    "gn:asciiname":"Huanca Pampa",
    "gn:country_code":"PE",
    "gn:dem":3047,
    "gn:feature_class":"P",
    "gn:feature_code":"PPL",
    "gn:name":"Huanca Pampa",
    "gn:population":0,
    "gn:timezone":"America/Lima",
    "iso:country":"PE",
    "wof:name":"Huanca Pampa",
    "wof:placetype":"locality"
},
  "geometry": {"coordinates":[-73.91767,-13.97005],"type":"Point"}
}