{
  "type": "Feature",
  "properties": {
    "gn:admin1_code":"18",
    "gn:admin2_code":"1802.0",
    "gn:admin3_code":"180205.0",
    "gn:asciiname":"Caiman",
    "gn:country_code":"PE",
    "gn:dem":2407,
    "gn:feature_class":"P",
    "gn:feature_code":"PPL",
    "gn:name":"Caim\u00e1n",
    "gn:population":0,
    "gn:timezone":"America/Lima",
    "iso:country":"PE",
    "name:ara_x_preferred":[
        "\u0643\u064a\u0627\u0645\u0646"
    ],
    "name:bre_x_preferred":[
        "Kaiman"
    ],
    "name:cat_x_preferred":[
        "Caimanins"
    ],
    "name:dan_x_preferred":[
        "Kaimaner"
    ],
    "name:deu_x_preferred":[
        "Kaimane"
    ],
    "name:ell_x_preferred":[
        "\u039a\u03b1\u03ca\u03bc\u03ac\u03bd"
    ],
    "name:eus_x_preferred":[
        "Kaiman"
    ],
    "name:fas_x_preferred":[
        "\u06a9\u06cc\u0645\u0646"
    ],
    "name:fin_x_preferred":[
        "Kaimaanit"
    ],
    "name:fra_x_preferred":[
        "Caimaninae"
    ],
    "name:glg_x_preferred":[
        "Caim\u00e1n"
    ],
    "name:hat_x_preferred":[
        "Kayiman"
    ],
    "name:heb_x_preferred":[
        "\u05e7\u05d9\u05d9\u05de\u05e0\u05d9\u05dd"
    ],
    "name:hun_x_preferred":[
        "Kajm\u00e1nform\u00e1k"
    ],
    "name:ind_x_preferred":[
        "Kaiman"
    ],
    "name:ita_x_preferred":[
        "Caimaninae"
    ],
    "name:jpn_x_preferred":[
        "\u30ab\u30a4\u30de\u30f3\u4e9c\u79d1"
    ],
    "name:kat_x_preferred":[
        "\u10d9\u10d0\u10d8\u10db\u10d0\u10dc\u10d4\u10d1\u10d8"
    ],
    "name:kir_x_preferred":[
        "\u041a\u0430\u0439\u043c\u0430\u043d\u0434\u0430\u0440"
    ],
    "name:kor_x_preferred":[
        "\uce74\uc774\ub9cc\uc544\uacfc"
    ],
    "name:mkd_x_preferred":[
        "\u041a\u0430\u0458\u043c\u0430\u043d\u0438"
    ],
    "name:nld_x_preferred":[
        "Kaaimannen"
    ],
    "name:nno_x_preferred":[
        "Kaimanar"
    ],
    "name:nor_x_preferred":[
        "Kaimaner"
    ],
    "name:pol_x_preferred":[
        "Kajmany"
    ],
    "name:rus_x_preferred":[
        "Caimaninae"
    ],
    "name:spa_x_preferred":[
        "Caimaninae"
    ],
    "name:tha_x_preferred":[
        "\u0e40\u0e04\u0e41\u0e21\u0e19"
    ],
    "name:ukr_x_preferred":[
        "\u041a\u0430\u0439\u043c\u0430\u043d\u043e\u0432\u0456"
    ],
    "name:vie_x_preferred":[
        "Caimaninae"
    ],
    "wof:name":"Caiman",
    "wof:placetype":"locality"
},
  "geometry": {"coordinates":[-71.16750999999999,-16.70697],"type":"Point"}
}