{
  "type": "Feature",
  "properties": {
    "gn:admin1_code":"10",
    "gn:admin2_code":"1005.0",
    "gn:admin3_code":"100507.0",
    "gn:asciiname":"Monzon",
    "gn:country_code":"PE",
    "gn:dem":977,
    "gn:feature_class":"P",
    "gn:feature_code":"PPL",
    "gn:name":"Monz\u00f3n",
    "gn:population":0,
    "gn:timezone":"America/Lima",
    "iso:country":"PE",
    "name:und_x_variant":[
        "Mons\u00f3n",
        "Monz\u00f3n"
    ],
    "wof:name":"Monzon",
    "wof:placetype":"locality"
},
  "geometry": {"coordinates":[-76.39404,-9.28073],"type":"Point"}
}