{
  "type": "Feature",
  "properties": {
    "gn:admin1_code":"10",
    "gn:admin2_code":"1005.0",
    "gn:admin3_code":"100507.0",
    "gn:asciiname":"Monzon",
    "gn:country_code":"PE",
    "gn:dem":977,
    "gn:feature_class":"P",
    "gn:feature_code":"PPL",
    "gn:name":"Monz\u00f3n",
    "gn:population":0,
    "gn:timezone":"America/Lima",
    "iso:country":"PE",
    "name:arg_x_preferred":[
        "Monz\u00f3n"
    ],
    "name:cat_x_preferred":[
        "Monz\u00f3n"
    ],
    "name:ceb_x_preferred":[
        "Monzon"
    ],
    "name:deu_x_preferred":[
        "Monz\u00f3n"
    ],
    "name:eus_x_preferred":[
        "Monz\u00f3n"
    ],
    "name:fra_x_preferred":[
        "Monz\u00f3n"
    ],
    "name:ita_x_preferred":[
        "Monz\u00f3n"
    ],
    "name:jpn_x_preferred":[
        "\u30e2\u30f3\u30bd\u30f3"
    ],
    "name:por_x_preferred":[
        "Monz\u00f3n"
    ],
    "name:spa_x_preferred":[
        "Monz\u00f3n"
    ],
    "name:swe_x_preferred":[
        "Monzon"
    ],
    "name:und_x_variant":[
        "Mons\u00f3n"
    ],
    "wof:name":"Monzon",
    "wof:placetype":"locality"
},
  "geometry": {"coordinates":[-76.39404,-9.28073],"type":"Point"}
}