{
  "type": "Feature",
  "properties": {
    "gn:admin1_code":"15",
    "gn:admin2_code":"1502.0",
    "gn:admin3_code":"150204.0",
    "gn:asciiname":"Tutumo",
    "gn:country_code":"PE",
    "gn:dem":66,
    "gn:feature_class":"P",
    "gn:feature_code":"PPL",
    "gn:name":"Tutumo",
    "gn:population":0,
    "gn:timezone":"America/Lima",
    "iso:country":"PE",
    "wof:name":"Tutumo",
    "wof:placetype":"locality"
},
  "geometry": {"coordinates":[-77.66681,-10.85019],"type":"Point"}
}