{
  "type": "Feature",
  "properties": {
    "gn:admin1_code":"10.0",
    "gn:admin2_code":"1001.0",
    "gn:admin3_code":"100106.0",
    "gn:asciiname":"Punchao Chico",
    "gn:country_code":"PE",
    "gn:dem":2838,
    "gn:feature_class":"P",
    "gn:feature_code":"PPL",
    "gn:name":"Punchao Chico",
    "gn:population":0,
    "gn:timezone":"America/Lima",
    "iso:country":"PE",
    "wof:name":"Punchao Chico",
    "wof:placetype":"locality"
},
  "geometry": {"coordinates":[-76.3981,-9.89754],"type":"Point"}
}