{
  "type": "Feature",
  "properties": {
    "gn:admin1_code":"16",
    "gn:admin2_code":"1604.0",
    "gn:admin3_code":"160403.0",
    "gn:asciiname":"San Vicente",
    "gn:country_code":"PE",
    "gn:dem":83,
    "gn:feature_class":"P",
    "gn:feature_code":"PPL",
    "gn:name":"San Vicente",
    "gn:population":0,
    "gn:timezone":"America/Lima",
    "iso:country":"PE",
    "wof:name":"San Vicente",
    "wof:placetype":"locality"
},
  "geometry": {"coordinates":[-71.15618000000001,-4.40685],"type":"Point"}
}