{
  "type": "Feature",
  "properties": {
    "gn:admin1_code":"12",
    "gn:admin2_code":"1201.0",
    "gn:admin3_code":"120108.0",
    "gn:asciiname":"Pampacancha",
    "gn:country_code":"PE",
    "gn:dem":4379,
    "gn:feature_class":"P",
    "gn:feature_code":"PPL",
    "gn:name":"Pampacancha",
    "gn:population":0,
    "gn:timezone":"America/Lima",
    "iso:country":"PE",
    "wof:name":"Pampacancha",
    "wof:placetype":"locality"
},
  "geometry": {"coordinates":[-75.41611,-12.42973],"type":"Point"}
}