{
  "type": "Feature",
  "properties": {
    "gn:admin1_code":"12.0",
    "gn:admin2_code":"1204.0",
    "gn:admin3_code":"120432.0",
    "gn:asciiname":"Yanasmayo",
    "gn:country_code":"PE",
    "gn:dem":3607,
    "gn:feature_class":"P",
    "gn:feature_code":"PPL",
    "gn:name":"Yanasmayo",
    "gn:population":0,
    "gn:timezone":"America/Lima",
    "iso:country":"PE",
    "wof:name":"Yanasmayo",
    "wof:placetype":"locality"
},
  "geometry": {"coordinates":[-75.58499999999999,-11.71839],"type":"Point"}
}