{
  "type": "Feature",
  "properties": {
    "gn:admin1_code":"4",
    "gn:admin2_code":"405.0",
    "gn:admin3_code":"40518.0",
    "gn:asciiname":"Chilluyoc",
    "gn:country_code":"PE",
    "gn:dem":4301,
    "gn:feature_class":"P",
    "gn:feature_code":"PPL",
    "gn:name":"Chilluyoc",
    "gn:population":0,
    "gn:timezone":"America/Lima",
    "iso:country":"PE",
    "wof:name":"Chilluyoc",
    "wof:placetype":"locality"
},
  "geometry": {"coordinates":[-71.56818,-15.48418],"type":"Point"}
}