{
  "type": "Feature",
  "properties": {
    "gn:admin1_code":"19",
    "gn:admin2_code":"1903.0",
    "gn:admin3_code":"190307.0",
    "gn:asciiname":"Cacazu",
    "gn:country_code":"PE",
    "gn:dem":1233,
    "gn:feature_class":"P",
    "gn:feature_code":"PPL",
    "gn:name":"Cacazu",
    "gn:population":0,
    "gn:timezone":"America/Lima",
    "iso:country":"PE",
    "wof:name":"Cacazu",
    "wof:placetype":"locality"
},
  "geometry": {"coordinates":[-75.11667,-10.56667],"type":"Point"}
}