{
  "type": "Feature",
  "properties": {
    "gn:admin1_code":"5.0",
    "gn:admin2_code":"505.0",
    "gn:asciiname":"Chontabamba",
    "gn:country_code":"PE",
    "gn:dem":1054,
    "gn:feature_class":"P",
    "gn:feature_code":"PPL",
    "gn:name":"Chontabamba",
    "gn:population":0,
    "gn:timezone":"America/Lima",
    "iso:country":"PE",
    "wof:name":"Chontabamba",
    "wof:placetype":"locality"
},
  "geometry": {"coordinates":[-73.70308,-12.73945],"type":"Point"}
}