{
  "type": "Feature",
  "properties": {
    "gn:admin1_code":"10.0",
    "gn:admin2_code":"1003.0",
    "gn:admin3_code":"100313.0",
    "gn:asciiname":"Pariagaga",
    "gn:country_code":"PE",
    "gn:dem":3888,
    "gn:feature_class":"P",
    "gn:feature_code":"PPL",
    "gn:name":"Pariagaga",
    "gn:population":0,
    "gn:timezone":"America/Lima",
    "iso:country":"PE",
    "wof:name":"Pariagaga",
    "wof:placetype":"locality"
},
  "geometry": {"coordinates":[-76.80136,-9.67565],"type":"Point"}
}