{
  "type": "Feature",
  "properties": {
    "gn:admin1_code":"16",
    "gn:admin2_code":"1601.0",
    "gn:admin3_code":"160107.0",
    "gn:asciiname":"Tambo Jimenez",
    "gn:country_code":"PE",
    "gn:dem":188,
    "gn:feature_class":"P",
    "gn:feature_code":"PPL",
    "gn:name":"Tambo Jim\u00e9nez",
    "gn:population":0,
    "gn:timezone":"America/Lima",
    "iso:country":"PE",
    "wof:name":"Tambo Jimenez",
    "wof:placetype":"locality"
},
  "geometry": {"coordinates":[-75.28333000000001,-1.46667],"type":"Point"}
}