{
  "type": "Feature",
  "properties": {
    "gn:admin1_code":"05",
    "gn:admin2_code":"503.0",
    "gn:admin3_code":"50301.0",
    "gn:asciiname":"Jasahuasi",
    "gn:country_code":"PE",
    "gn:dem":3952,
    "gn:feature_class":"P",
    "gn:feature_code":"PPL",
    "gn:name":"Jasahuasi",
    "gn:population":0,
    "gn:timezone":"America/Lima",
    "iso:country":"PE",
    "wof:name":"Jasahuasi",
    "wof:placetype":"locality"
},
  "geometry": {"coordinates":[-74.49946,-14.05039],"type":"Point"}
}