{
  "type": "Feature",
  "properties": {
    "gn:admin1_code":"1.0",
    "gn:admin2_code":"106.0",
    "gn:admin3_code":"10605.0",
    "gn:asciiname":"Challhuayacu",
    "gn:country_code":"PE",
    "gn:dem":1707,
    "gn:feature_class":"P",
    "gn:feature_code":"PPL",
    "gn:name":"Challhuayacu",
    "gn:population":0,
    "gn:timezone":"America/Lima",
    "iso:country":"PE",
    "wof:name":"Challhuayacu",
    "wof:placetype":"locality"
},
  "geometry": {"coordinates":[-77.57843000000003,-6.52561],"type":"Point"}
}