{
  "type": "Feature",
  "properties": {
    "gn:admin1_code":"21",
    "gn:admin2_code":"2105.0",
    "gn:admin3_code":"210504.0",
    "gn:asciiname":"Piltuta",
    "gn:country_code":"PE",
    "gn:dem":4576,
    "gn:feature_class":"P",
    "gn:feature_code":"PPL",
    "gn:name":"Piltuta",
    "gn:population":0,
    "gn:timezone":"America/Lima",
    "iso:country":"PE",
    "wof:name":"Piltuta",
    "wof:placetype":"locality"
},
  "geometry": {"coordinates":[-70.05,-16.81667],"type":"Point"}
}