{
  "type": "Feature",
  "properties": {
    "gn:admin1_code":"16",
    "gn:admin2_code":"1603.0",
    "gn:admin3_code":"160304.0",
    "gn:asciiname":"Valencia",
    "gn:country_code":"PE",
    "gn:dem":162,
    "gn:feature_class":"P",
    "gn:feature_code":"PPL",
    "gn:name":"Valencia",
    "gn:population":0,
    "gn:timezone":"America/Lima",
    "iso:country":"PE",
    "wof:name":"Valencia",
    "wof:placetype":"locality"
},
  "geometry": {"coordinates":[-75.66993000000002,-3.11249],"type":"Point"}
}