{
  "type": "Feature",
  "properties": {
    "gn:admin1_code":"12.0",
    "gn:admin2_code":"1202.0",
    "gn:admin3_code":"120205.0",
    "gn:asciiname":"Cangalayo",
    "gn:country_code":"PE",
    "gn:dem":3527,
    "gn:feature_class":"P",
    "gn:feature_code":"PPL",
    "gn:name":"Cangalayo",
    "gn:population":0,
    "gn:timezone":"America/Lima",
    "iso:country":"PE",
    "wof:name":"Cangalayo",
    "wof:placetype":"locality"
},
  "geometry": {"coordinates":[-75.1096,-11.63926],"type":"Point"}
}