{
  "type": "Feature",
  "properties": {
    "gn:admin1_code":"12.0",
    "gn:admin2_code":"1202.0",
    "gn:admin3_code":"120206.0",
    "gn:asciiname":"Uyacancha",
    "gn:country_code":"PE",
    "gn:dem":3625,
    "gn:feature_class":"P",
    "gn:feature_code":"PPL",
    "gn:name":"Uyacancha",
    "gn:population":0,
    "gn:timezone":"America/Lima",
    "iso:country":"PE",
    "wof:name":"Uyacancha",
    "wof:placetype":"locality"
},
  "geometry": {"coordinates":[-75.07419,-11.74858],"type":"Point"}
}