{
  "type": "Feature",
  "properties": {
    "gn:admin1_code":"09",
    "gn:admin2_code":"901.0",
    "gn:admin3_code":"90110.0",
    "gn:asciiname":"Cuchespata",
    "gn:country_code":"PE",
    "gn:dem":4274,
    "gn:feature_class":"P",
    "gn:feature_code":"PPL",
    "gn:name":"Cuchespata",
    "gn:population":0,
    "gn:timezone":"America/Lima",
    "iso:country":"PE",
    "wof:name":"Cuchespata",
    "wof:placetype":"locality"
},
  "geometry": {"coordinates":[-75.16181,-12.64309],"type":"Point"}
}