{
  "type": "Feature",
  "properties": {
    "gn:admin1_code":"13",
    "gn:admin2_code":"1301.0",
    "gn:admin3_code":"130106.0",
    "gn:asciiname":"Menocucho",
    "gn:cc2":"PE",
    "gn:country_code":"PE",
    "gn:dem":335,
    "gn:feature_class":"P",
    "gn:feature_code":"PPL",
    "gn:name":"Menocucho",
    "gn:population":0,
    "gn:timezone":"America/Lima",
    "iso:country":"PE",
    "name:und_x_variant":[
        "Menocucho Hacienda",
        "Menocucho"
    ],
    "wof:name":"Menocucho",
    "wof:placetype":"locality"
},
  "geometry": {"coordinates":[-78.83333,-8.01667],"type":"Point"}
}