{
  "type": "Feature",
  "properties": {
    "gn:admin1_code":"15",
    "gn:admin2_code":"1501.0",
    "gn:admin3_code":"150143.0",
    "gn:asciiname":"Nueva Esperanza",
    "gn:country_code":"PE",
    "gn:dem":324,
    "gn:feature_class":"P",
    "gn:feature_code":"PPL",
    "gn:name":"Nueva Esperanza",
    "gn:population":0,
    "gn:timezone":"America/Lima",
    "iso:country":"PE",
    "wof:name":"Nueva Esperanza",
    "wof:placetype":"locality"
},
  "geometry": {"coordinates":[-76.91667,-12.16667],"type":"Point"}
}