{
  "type": "Feature",
  "properties": {
    "gn:admin1_code":"12.0",
    "gn:admin2_code":"1202.0",
    "gn:admin3_code":"120206.0",
    "gn:asciiname":"Toro-Lumi",
    "gn:country_code":"PE",
    "gn:dem":3899,
    "gn:feature_class":"P",
    "gn:feature_code":"PPL",
    "gn:name":"Toro-Lumi",
    "gn:population":0,
    "gn:timezone":"America/Lima",
    "iso:country":"PE",
    "wof:name":"Toro-Lumi",
    "wof:placetype":"locality"
},
  "geometry": {"coordinates":[-75.05314,-11.6419],"type":"Point"}
}