{
  "type": "Feature",
  "properties": {
    "gn:admin1_code":"04",
    "gn:admin2_code":"403.0",
    "gn:admin3_code":"40301.0",
    "gn:asciiname":"Tres Cruces",
    "gn:cc2":"PE",
    "gn:country_code":"PE",
    "gn:dem":2598,
    "gn:feature_class":"P",
    "gn:feature_code":"PPL",
    "gn:name":"Tres Cruces",
    "gn:population":0,
    "gn:timezone":"America/Lima",
    "iso:country":"PE",
    "name:cat_x_preferred":[
        "Tres Cruces"
    ],
    "name:deu_x_preferred":[
        "Tres Cruces"
    ],
    "name:spa_x_preferred":[
        "Tres Cruces"
    ],
    "name:und_x_variant":[
        "Tres Cruce",
        "Tres Cruces"
    ],
    "wof:name":"Tres Cruces",
    "wof:placetype":"locality"
},
  "geometry": {"coordinates":[-73.33722,-15.73194],"type":"Point"}
}