{
  "type": "Feature",
  "properties": {
    "gn:admin1_code":"20",
    "gn:admin2_code":"2007.0",
    "gn:admin3_code":"200705.0",
    "gn:asciiname":"Cabo Blanco",
    "gn:country_code":"PE",
    "gn:dem":256,
    "gn:feature_class":"P",
    "gn:feature_code":"PPL",
    "gn:name":"Cabo Blanco",
    "gn:population":0,
    "gn:timezone":"America/Lima",
    "iso:country":"PE",
    "wof:name":"Cabo Blanco",
    "wof:placetype":"locality"
},
  "geometry": {"coordinates":[-81.06144999999999,-4.22689],"type":"Point"}
}