{
  "type": "Feature",
  "properties": {
    "gn:admin1_code":"21",
    "gn:admin2_code":"2110.0",
    "gn:admin3_code":"211003.0",
    "gn:asciiname":"Mayapunco",
    "gn:country_code":"PE",
    "gn:dem":3869,
    "gn:feature_class":"P",
    "gn:feature_code":"PPL",
    "gn:name":"Mayapunco",
    "gn:population":0,
    "gn:timezone":"America/Lima",
    "iso:country":"PE",
    "name:und_x_variant":[
        "Mayapunco Hacienda",
        "Mayapunco"
    ],
    "wof:name":"Mayapunco",
    "wof:placetype":"locality"
},
  "geometry": {"coordinates":[-69.91034999999999,-15.04917],"type":"Point"}
}