{
  "type": "Feature",
  "properties": {
    "gn:admin1_code":"15",
    "gn:admin2_code":"1507.0",
    "gn:admin3_code":"150705.0",
    "gn:asciiname":"Ayuyoc",
    "gn:country_code":"PE",
    "gn:dem":4357,
    "gn:feature_class":"P",
    "gn:feature_code":"PPL",
    "gn:name":"Ayuyoc",
    "gn:population":0,
    "gn:timezone":"America/Lima",
    "iso:country":"PE",
    "wof:name":"Ayuyoc",
    "wof:placetype":"locality"
},
  "geometry": {"coordinates":[-76.27583,-11.66417],"type":"Point"}
}