{
  "type": "Feature",
  "properties": {
    "gn:admin1_code":"2.0",
    "gn:admin2_code":"205.0",
    "gn:asciiname":"Shilipata",
    "gn:country_code":"PE",
    "gn:dem":4053,
    "gn:feature_class":"P",
    "gn:feature_code":"PPL",
    "gn:name":"Shilipata",
    "gn:population":0,
    "gn:timezone":"America/Lima",
    "iso:country":"PE",
    "wof:name":"Shilipata",
    "wof:placetype":"locality"
},
  "geometry": {"coordinates":[-76.92426999999998,-9.85612],"type":"Point"}
}