{
  "type": "Feature",
  "properties": {
    "gn:admin1_code":"23",
    "gn:admin2_code":"2302.0",
    "gn:admin3_code":"230201.0",
    "gn:asciiname":"Coline",
    "gn:country_code":"PE",
    "gn:dem":4259,
    "gn:feature_class":"P",
    "gn:feature_code":"PPL",
    "gn:name":"Coline",
    "gn:population":0,
    "gn:timezone":"America/Lima",
    "iso:country":"PE",
    "wof:name":"Coline",
    "wof:placetype":"locality"
},
  "geometry": {"coordinates":[-70.15846999999999,-17.16773],"type":"Point"}
}