{
  "type": "Feature",
  "properties": {
    "gn:admin1_code":"21",
    "gn:admin2_code":"2107.0",
    "gn:admin3_code":"210701.0",
    "gn:asciiname":"Titilesca",
    "gn:country_code":"PE",
    "gn:dem":3965,
    "gn:feature_class":"P",
    "gn:feature_code":"PPL",
    "gn:name":"Titilesca",
    "gn:population":0,
    "gn:timezone":"America/Lima",
    "iso:country":"PE",
    "wof:name":"Titilesca",
    "wof:placetype":"locality"
},
  "geometry": {"coordinates":[-70.40066,-15.3129],"type":"Point"}
}