{
  "type": "Feature",
  "properties": {
    "gn:admin1_code":"05",
    "gn:admin2_code":"508.0",
    "gn:admin3_code":"50806.0",
    "gn:asciiname":"Chunchuccasa",
    "gn:country_code":"PE",
    "gn:dem":4551,
    "gn:feature_class":"P",
    "gn:feature_code":"PPL",
    "gn:name":"Chunchuccasa",
    "gn:population":0,
    "gn:timezone":"America/Lima",
    "iso:country":"PE",
    "wof:name":"Chunchuccasa",
    "wof:placetype":"locality"
},
  "geometry": {"coordinates":[-73.13028,-15.08667],"type":"Point"}
}