{
  "type": "Feature",
  "properties": {
    "gn:admin1_code":"21",
    "gn:admin2_code":"2107.0",
    "gn:admin3_code":"210709.0",
    "gn:asciiname":"Chachacumani",
    "gn:country_code":"PE",
    "gn:dem":4704,
    "gn:feature_class":"P",
    "gn:feature_code":"PPL",
    "gn:name":"Chachacumani",
    "gn:population":0,
    "gn:timezone":"America/Lima",
    "iso:country":"PE",
    "wof:name":"Chachacumani",
    "wof:placetype":"locality"
},
  "geometry": {"coordinates":[-71.00359,-15.39835],"type":"Point"}
}