{
  "type": "Feature",
  "properties": {
    "gn:admin1_code":"21",
    "gn:admin2_code":"2104.0",
    "gn:admin3_code":"210401.0",
    "gn:asciiname":"Inca Apacheta",
    "gn:country_code":"PE",
    "gn:dem":4278,
    "gn:feature_class":"P",
    "gn:feature_code":"PPL",
    "gn:name":"Inca Apacheta",
    "gn:population":0,
    "gn:timezone":"America/Lima",
    "iso:country":"PE",
    "wof:name":"Inca Apacheta",
    "wof:placetype":"locality"
},
  "geometry": {"coordinates":[-69.42038000000001,-16.29356],"type":"Point"}
}