{
  "type": "Feature",
  "properties": {
    "gn:admin1_code":"2.0",
    "gn:admin2_code":"201.0",
    "gn:admin3_code":"20106.0",
    "gn:asciiname":"Huantallon",
    "gn:country_code":"PE",
    "gn:dem":2923,
    "gn:feature_class":"P",
    "gn:feature_code":"PPL",
    "gn:name":"Huantall\u00f3n",
    "gn:population":0,
    "gn:timezone":"America/Lima",
    "iso:country":"PE",
    "wof:name":"Huantallon",
    "wof:placetype":"locality"
},
  "geometry": {"coordinates":[-77.55110999999999,-9.43639],"type":"Point"}
}