{
  "type": "Feature",
  "properties": {
    "iso:country":"PE",
    "qs:gn_pop":0,
    "qs:name":"Ceya",
    "qs:name_adm0":"Per\u00fa",
    "qs:name_adm1":"Cusco",
    "qs:photos":120,
    "qs:photos_1k":24,
    "qs:photos_9k":1,
    "qs:photos_9r":3,
    "qs:photos_all":120,
    "qs:photos_sr":3,
    "qs:placetype":"Town",
    "qs:pop_sr":"0",
    "qs:woe_adm0":23424919,
    "wof:name":"Ceya",
    "wof:placetype":"locality"
},
  "geometry": {"coordinates":[-71.905689,-13.406902],"type":"Point"}
}