{
  "type": "Feature",
  "properties": {
    "gn:admin1_code":"24",
    "gn:admin2_code":"2401.0",
    "gn:asciiname":"Cucaracha",
    "gn:country_code":"PE",
    "gn:dem":-9999,
    "gn:feature_class":"P",
    "gn:feature_code":"PPL",
    "gn:name":"Cucaracha",
    "gn:population":0,
    "gn:timezone":"America/Lima",
    "iso:country":"PE",
    "wof:name":"Cucaracha",
    "wof:placetype":"locality"
},
  "geometry": {"coordinates":[-80.43333,-3.48333],"type":"Point"}
}