{
  "type": "Feature",
  "properties": {
    "gn:admin1_code":"12",
    "gn:admin2_code":"1207.0",
    "gn:admin3_code":"120707.0",
    "gn:asciiname":"Esquecha",
    "gn:country_code":"PE",
    "gn:dem":4168,
    "gn:feature_class":"P",
    "gn:feature_code":"PPL",
    "gn:name":"Esquecha",
    "gn:population":0,
    "gn:timezone":"America/Lima",
    "iso:country":"PE",
    "wof:name":"Esquecha",
    "wof:placetype":"locality"
},
  "geometry": {"coordinates":[-75.73918,-11.33939],"type":"Point"}
}