{
  "type": "Feature",
  "properties": {
    "gn:admin1_code":"08",
    "gn:admin2_code":"801.0",
    "gn:admin3_code":"80102.0",
    "gn:asciiname":"Chuspi",
    "gn:country_code":"PE",
    "gn:dem":3854,
    "gn:feature_class":"P",
    "gn:feature_code":"PPL",
    "gn:name":"Chuspi",
    "gn:population":0,
    "gn:timezone":"America/Lima",
    "iso:country":"PE",
    "name:und_x_variant":[
        "Chuspi Hacienda",
        "Chuspi"
    ],
    "wof:name":"Chuspi",
    "wof:placetype":"locality"
},
  "geometry": {"coordinates":[-72.00587,-13.56673],"type":"Point"}
}