{
  "type": "Feature",
  "properties": {
    "gn:admin1_code":"20",
    "gn:admin2_code":"2002.0",
    "gn:admin3_code":"200202.0",
    "gn:asciiname":"Arenales",
    "gn:country_code":"PE",
    "gn:dem":3093,
    "gn:feature_class":"P",
    "gn:feature_code":"PPL",
    "gn:name":"Arenales",
    "gn:population":0,
    "gn:timezone":"America/Lima",
    "iso:country":"PE",
    "name:und_x_variant":[
        "Hacienda Arenales",
        "Arenal Hacienda",
        "Arenales"
    ],
    "wof:name":"Arenales",
    "wof:placetype":"locality"
},
  "geometry": {"coordinates":[-79.84815999999999,-4.92304],"type":"Point"}
}