{
  "type": "Feature",
  "properties": {
    "gn:admin1_code":"8",
    "gn:admin2_code":"808.0",
    "gn:asciiname":"Chilanilla",
    "gn:country_code":"PE",
    "gn:dem":4644,
    "gn:feature_class":"P",
    "gn:feature_code":"PPL",
    "gn:name":"Chilanilla",
    "gn:population":0,
    "gn:timezone":"America/Lima",
    "iso:country":"PE",
    "wof:name":"Chilanilla",
    "wof:placetype":"locality"
},
  "geometry": {"coordinates":[-71.1283,-15.42157],"type":"Point"}
}