{
  "type": "Feature",
  "properties": {
    "gn:admin1_code":"11.0",
    "gn:admin2_code":"1105.0",
    "gn:admin3_code":"110503.0",
    "gn:asciiname":"Mayo Fundo",
    "gn:country_code":"PE",
    "gn:dem":424,
    "gn:feature_class":"P",
    "gn:feature_code":"PPL",
    "gn:name":"Mayo Fundo",
    "gn:population":0,
    "gn:timezone":"America/Lima",
    "iso:country":"PE",
    "name:spa_x_preferred":[
        "Mayo Fundo"
    ],
    "wof:name":"Mayo Fundo",
    "wof:placetype":"locality"
},
  "geometry": {"coordinates":[-75.87343,-13.72791],"type":"Point"}
}