{
  "type": "Feature",
  "properties": {
    "gn:admin1_code":"8.0",
    "gn:admin2_code":"801.0",
    "gn:admin3_code":"80106.0",
    "gn:asciiname":"Tancarcancha",
    "gn:country_code":"PE",
    "gn:dem":3877,
    "gn:feature_class":"P",
    "gn:feature_code":"PPL",
    "gn:name":"Tancarcancha",
    "gn:population":0,
    "gn:timezone":"America/Lima",
    "iso:country":"PE",
    "wof:name":"Tancarcancha",
    "wof:placetype":"locality"
},
  "geometry": {"coordinates":[-72.00889000000002,-13.56917],"type":"Point"}
}