{
  "type": "Feature",
  "properties": {
    "gn:admin1_code":"13.0",
    "gn:admin2_code":"1307.0",
    "gn:admin3_code":"130702.0",
    "gn:asciiname":"San Fernando",
    "gn:country_code":"PE",
    "gn:dem":87,
    "gn:feature_class":"P",
    "gn:feature_code":"PPL",
    "gn:name":"San Fernando",
    "gn:population":0,
    "gn:timezone":"America/Lima",
    "iso:country":"PE",
    "name:spa_x_preferred":[
        "San Fernando"
    ],
    "wof:name":"San Fernando",
    "wof:placetype":"locality"
},
  "geometry": {"coordinates":[-79.4847,-7.22678],"type":"Point"}
}