{
  "type": "Feature",
  "properties": {
    "gn:admin1_code":"04",
    "gn:admin2_code":"403.0",
    "gn:admin3_code":"40302.0",
    "gn:asciiname":"Umarote",
    "gn:country_code":"PE",
    "gn:dem":1715,
    "gn:feature_class":"P",
    "gn:feature_code":"PPL",
    "gn:name":"Umarote",
    "gn:population":0,
    "gn:timezone":"America/Lima",
    "iso:country":"PE",
    "wof:name":"Umarote",
    "wof:placetype":"locality"
},
  "geometry": {"coordinates":[-74.48333000000002,-15.25],"type":"Point"}
}