{
  "type": "Feature",
  "properties": {
    "gn:admin1_code":"16",
    "gn:admin2_code":"1607.0",
    "gn:admin3_code":"160705.0",
    "gn:asciiname":"Porvenir",
    "gn:country_code":"PE",
    "gn:dem":119,
    "gn:feature_class":"P",
    "gn:feature_code":"PPL",
    "gn:name":"Porvenir",
    "gn:population":0,
    "gn:timezone":"America/Lima",
    "iso:country":"PE",
    "wof:name":"Porvenir",
    "wof:placetype":"locality"
},
  "geometry": {"coordinates":[-75.87510999999998,-4.99748],"type":"Point"}
}