{
  "type": "Feature",
  "properties": {
    "gn:admin1_code":"23",
    "gn:admin2_code":"2304.0",
    "gn:admin3_code":"230406.0",
    "gn:asciiname":"Huaytuta",
    "gn:country_code":"PE",
    "gn:dem":4449,
    "gn:feature_class":"P",
    "gn:feature_code":"PPL",
    "gn:name":"Huaytuta",
    "gn:population":0,
    "gn:timezone":"America/Lima",
    "iso:country":"PE",
    "wof:name":"Huaytuta",
    "wof:placetype":"locality"
},
  "geometry": {"coordinates":[-70.05622,-17.12807],"type":"Point"}
}