{
  "type": "Feature",
  "properties": {
    "gn:admin1_code":"18",
    "gn:admin2_code":"1801.0",
    "gn:admin3_code":"180101.0",
    "gn:asciiname":"Corpantito",
    "gn:country_code":"PE",
    "gn:dem":1133,
    "gn:feature_class":"P",
    "gn:feature_code":"PPL",
    "gn:name":"Corpantito",
    "gn:population":0,
    "gn:timezone":"America/Lima",
    "iso:country":"PE",
    "name:und_x_variant":[
        "Corpanto Ghersi",
        "Corpantito"
    ],
    "wof:name":"Corpantito",
    "wof:placetype":"locality"
},
  "geometry": {"coordinates":[-70.98241999999998,-17.28101],"type":"Point"}
}