{
  "type": "Feature",
  "properties": {
    "gn:admin1_code":"11.0",
    "gn:admin2_code":"1101.0",
    "gn:admin3_code":"110107.0",
    "gn:asciiname":"La Rosada",
    "gn:country_code":"PE",
    "gn:dem":412,
    "gn:feature_class":"P",
    "gn:feature_code":"PPL",
    "gn:name":"La Rosada",
    "gn:population":0,
    "gn:timezone":"America/Lima",
    "iso:country":"PE",
    "name:spa_x_preferred":[
        "La Rosada"
    ],
    "wof:name":"La Rosada",
    "wof:placetype":"locality"
},
  "geometry": {"coordinates":[-75.69192,-14.11971],"type":"Point"}
}