{
  "type": "Feature",
  "properties": {
    "gn:admin1_code":"06",
    "gn:admin2_code":"608.0",
    "gn:asciiname":"Chilasque",
    "gn:country_code":"PE",
    "gn:dem":1302,
    "gn:feature_class":"P",
    "gn:feature_code":"PPL",
    "gn:name":"Chilasque",
    "gn:population":0,
    "gn:timezone":"America/Lima",
    "iso:country":"PE",
    "wof:name":"Chilasque",
    "wof:placetype":"locality"
},
  "geometry": {"coordinates":[-79.20389,-6.02528],"type":"Point"}
}