{
  "type": "Feature",
  "properties": {
    "gn:admin1_code":"9.0",
    "gn:admin2_code":"901.0",
    "gn:admin3_code":"90117.0",
    "gn:asciiname":"Totora",
    "gn:country_code":"PE",
    "gn:dem":3819,
    "gn:feature_class":"P",
    "gn:feature_code":"PPL",
    "gn:name":"Totora",
    "gn:population":0,
    "gn:timezone":"America/Lima",
    "iso:country":"PE",
    "wof:name":"Totora",
    "wof:placetype":"locality"
},
  "geometry": {"coordinates":[-74.83031,-12.72554],"type":"Point"}
}