{
  "type": "Feature",
  "properties": {
    "gn:admin1_code":"06",
    "gn:admin2_code":"610.0",
    "gn:admin3_code":"61001.0",
    "gn:asciiname":"San Marcos",
    "gn:country_code":"PE",
    "gn:dem":2294,
    "gn:feature_class":"P",
    "gn:feature_code":"PPLA3",
    "gn:name":"San Marcos",
    "gn:population":0,
    "gn:timezone":"America/Lima",
    "iso:country":"PE",
    "name:que_x_preferred":[
        "San Markus"
    ],
    "name:spa_x_preferred":[
        "San Marcos"
    ],
    "name:war_x_preferred":[
        "San Marcos"
    ],
    "name:zho_x_preferred":[
        "\u8056\u99ac\u79d1\u65af"
    ],
    "wof:name":"San Marcos",
    "wof:placetype":"locality"
},
  "geometry": {"coordinates":[-78.18333,-7.33333],"type":"Point"}
}