{
  "type": "Feature",
  "properties": {
    "gn:admin1_code":"9.0",
    "gn:admin2_code":"907.0",
    "gn:admin3_code":"90707.0",
    "gn:asciiname":"Cupis",
    "gn:country_code":"PE",
    "gn:dem":2872,
    "gn:feature_class":"P",
    "gn:feature_code":"PPL",
    "gn:name":"Cupis",
    "gn:population":0,
    "gn:timezone":"America/Lima",
    "iso:country":"PE",
    "wof:name":"Cupis",
    "wof:placetype":"locality"
},
  "geometry": {"coordinates":[-74.60961999999998,-12.03386],"type":"Point"}
}