{
  "type": "Feature",
  "properties": {
    "gn:admin1_code":"06",
    "gn:admin2_code":"608.0",
    "gn:admin3_code":"60801.0",
    "gn:asciiname":"Monte Grande",
    "gn:country_code":"PE",
    "gn:dem":736,
    "gn:feature_class":"P",
    "gn:feature_code":"PPL",
    "gn:name":"Monte Grande",
    "gn:population":0,
    "gn:timezone":"America/Lima",
    "iso:country":"PE",
    "wof:name":"Monte Grande",
    "wof:placetype":"locality"
},
  "geometry": {"coordinates":[-78.79557,-5.71661],"type":"Point"}
}