{
  "type": "Feature",
  "properties": {
    "gn:admin1_code":"8",
    "gn:admin2_code":"809.0",
    "gn:admin3_code":"80902.0",
    "gn:asciiname":"Villa Carmen",
    "gn:country_code":"PE",
    "gn:dem":791,
    "gn:feature_class":"P",
    "gn:feature_code":"PPL",
    "gn:name":"Villa Carmen",
    "gn:population":0,
    "gn:timezone":"America/Lima",
    "iso:country":"PE",
    "name:ita_x_preferred":[
        "Villa Carmen"
    ],
    "wof:name":"Villa Carmen",
    "wof:placetype":"locality"
},
  "geometry": {"coordinates":[-72.77069,-12.59519],"type":"Point"}
}