{
  "type": "Feature",
  "properties": {
    "gn:admin1_code":"3.0",
    "gn:admin2_code":"307.0",
    "gn:admin3_code":"30703.0",
    "gn:asciiname":"Collauro",
    "gn:country_code":"PE",
    "gn:dem":2545,
    "gn:feature_class":"P",
    "gn:feature_code":"PPL",
    "gn:name":"Collauro",
    "gn:population":0,
    "gn:timezone":"America/Lima",
    "iso:country":"PE",
    "wof:name":"Collauro",
    "wof:placetype":"locality"
},
  "geometry": {"coordinates":[-72.48860999999999,-13.8775],"type":"Point"}
}