{
  "type": "Feature",
  "properties": {
    "gn:admin1_code":"5.0",
    "gn:admin2_code":"501.0",
    "gn:admin3_code":"50102.0",
    "gn:asciiname":"Yanahuancu",
    "gn:country_code":"PE",
    "gn:dem":3583,
    "gn:feature_class":"P",
    "gn:feature_code":"PPL",
    "gn:name":"Yanahuancu",
    "gn:population":0,
    "gn:timezone":"America/Lima",
    "iso:country":"PE",
    "name:und_x_variant":[
        "Hacienda Yanahuancu"
    ],
    "wof:name":"Yanahuancu",
    "wof:placetype":"locality"
},
  "geometry": {"coordinates":[-74.00357,-13.3177],"type":"Point"}
}