{
  "type": "Feature",
  "properties": {
    "gn:admin1_code":"12",
    "gn:admin2_code":"1201.0",
    "gn:admin3_code":"120135.0",
    "gn:asciiname":"Huachicna",
    "gn:country_code":"PE",
    "gn:dem":2278,
    "gn:feature_class":"P",
    "gn:feature_code":"PPL",
    "gn:name":"Huachic\u00f1a",
    "gn:population":0,
    "gn:timezone":"America/Lima",
    "iso:country":"PE",
    "wof:name":"Huachicna",
    "wof:placetype":"locality"
},
  "geometry": {"coordinates":[-74.69329,-11.98197],"type":"Point"}
}