{
  "type": "Feature",
  "properties": {
    "gn:admin1_code":"21",
    "gn:admin2_code":"2104.0",
    "gn:admin3_code":"210402.0",
    "gn:asciiname":"Huilacalla",
    "gn:country_code":"PE",
    "gn:dem":3881,
    "gn:feature_class":"P",
    "gn:feature_code":"PPL",
    "gn:name":"Huilacalla",
    "gn:population":0,
    "gn:timezone":"America/Lima",
    "iso:country":"PE",
    "wof:name":"Huilacalla",
    "wof:placetype":"locality"
},
  "geometry": {"coordinates":[-69.11917,-16.60111],"type":"Point"}
}