{
  "type": "Feature",
  "properties": {
    "gn:admin1_code":"15",
    "gn:admin2_code":"1510.0",
    "gn:admin3_code":"151021.0",
    "gn:asciiname":"Uman",
    "gn:country_code":"PE",
    "gn:dem":4527,
    "gn:feature_class":"P",
    "gn:feature_code":"PPL",
    "gn:name":"Um\u00e1n",
    "gn:population":0,
    "gn:timezone":"America/Lima",
    "iso:country":"PE",
    "name:ben_x_preferred":[
        "\u0989\u09ae\u09be\u09a8"
    ],
    "name:hin_x_preferred":[
        "\u0909\u092e\u093e\u0928"
    ],
    "name:ind_x_preferred":[
        "Uman"
    ],
    "name:ukr_x_preferred":[
        "\u0423\u043c\u0430\u043d"
    ],
    "name:und_x_variant":[
        "Um\u00e1n"
    ],
    "name:urd_x_preferred":[
        "\u0639\u0645\u0627\u0646"
    ],
    "name:zho_x_preferred":[
        "\u70cf\u66fc\u5c71"
    ],
    "wof:name":"Uman",
    "wof:placetype":"locality"
},
  "geometry": {"coordinates":[-75.90639,-12.21722],"type":"Point"}
}