{
  "type": "Feature",
  "properties": {
    "gn:admin1_code":"15",
    "gn:admin2_code":"1510.0",
    "gn:admin3_code":"151021.0",
    "gn:asciiname":"Uman",
    "gn:country_code":"PE",
    "gn:dem":4527,
    "gn:feature_class":"P",
    "gn:feature_code":"PPL",
    "gn:name":"Um\u00e1n",
    "gn:population":0,
    "gn:timezone":"America/Lima",
    "iso:country":"PE",
    "name:und_x_variant":[
        "Um\u00e1n"
    ],
    "wof:name":"Uman",
    "wof:placetype":"locality"
},
  "geometry": {"coordinates":[-75.90639,-12.21722],"type":"Point"}
}