{
  "type": "Feature",
  "properties": {
    "gn:admin1_code":"5.0",
    "gn:admin2_code":"501.0",
    "gn:admin3_code":"50113.0",
    "gn:asciiname":"Tancayllo",
    "gn:country_code":"PE",
    "gn:dem":3043,
    "gn:feature_class":"P",
    "gn:feature_code":"PPL",
    "gn:name":"Tancayllo",
    "gn:population":0,
    "gn:timezone":"America/Lima",
    "iso:country":"PE",
    "name:und_x_variant":[
        "Hacienda Tancayllo"
    ],
    "wof:name":"Tancayllo",
    "wof:placetype":"locality"
},
  "geometry": {"coordinates":[-74.18503,-13.21606],"type":"Point"}
}