{
  "type": "Feature",
  "properties": {
    "gn:admin1_code":"04",
    "gn:admin2_code":"405.0",
    "gn:admin3_code":"40517.0",
    "gn:asciiname":"Laputana",
    "gn:country_code":"PE",
    "gn:dem":4529,
    "gn:feature_class":"P",
    "gn:feature_code":"PPL",
    "gn:name":"Laputa\u00f1a",
    "gn:population":0,
    "gn:timezone":"America/Lima",
    "iso:country":"PE",
    "wof:name":"Laputana",
    "wof:placetype":"locality"
},
  "geometry": {"coordinates":[-71.18937,-15.11328],"type":"Point"}
}