{
  "type": "Feature",
  "properties": {
    "gn:admin1_code":"20",
    "gn:admin2_code":"2006.0",
    "gn:admin3_code":"200608.0",
    "gn:asciiname":"Coco Bajo",
    "gn:country_code":"PE",
    "gn:dem":45,
    "gn:feature_class":"P",
    "gn:feature_code":"PPL",
    "gn:name":"Coco Bajo",
    "gn:population":0,
    "gn:timezone":"America/Lima",
    "iso:country":"PE",
    "wof:name":"Coco Bajo",
    "wof:placetype":"locality"
},
  "geometry": {"coordinates":[-80.69171999999998,-4.86675],"type":"Point"}
}