{
  "type": "Feature",
  "properties": {
    "gn:admin1_code":"04",
    "gn:admin2_code":"405.0",
    "gn:admin3_code":"40517.0",
    "gn:asciiname":"Pisaca",
    "gn:country_code":"PE",
    "gn:dem":4321,
    "gn:feature_class":"P",
    "gn:feature_code":"PPL",
    "gn:name":"Pisaca",
    "gn:population":0,
    "gn:timezone":"America/Lima",
    "iso:country":"PE",
    "wof:name":"Pisaca",
    "wof:placetype":"locality"
},
  "geometry": {"coordinates":[-71.43524000000002,-15.38989],"type":"Point"}
}