{
  "type": "Feature",
  "properties": {
    "gn:admin1_code":"13",
    "gn:admin2_code":"1306.0",
    "gn:admin3_code":"130602.0",
    "gn:asciiname":"Chota",
    "gn:country_code":"PE",
    "gn:dem":3104,
    "gn:feature_class":"P",
    "gn:feature_code":"PPL",
    "gn:name":"Chota",
    "gn:population":0,
    "gn:timezone":"America/Lima",
    "iso:country":"PE",
    "name:ara_x_preferred":[
        "\u062a\u0634\u0648\u062a\u0627"
    ],
    "name:ben_x_preferred":[
        "\u099a\u09cb\u09a4\u09be"
    ],
    "name:ceb_x_preferred":[
        "Chota"
    ],
    "name:deu_x_preferred":[
        "Chota"
    ],
    "name:ell_x_preferred":[
        "\u03a4\u03c3\u03cc\u03c4\u03c3\u03b1"
    ],
    "name:heb_x_preferred":[
        "\u05e6'\u05d5\u05d8\u05d4"
    ],
    "name:hin_x_preferred":[
        "\u091a\u094b\u091f\u093e"
    ],
    "name:hun_x_preferred":[
        "Chota"
    ],
    "name:ind_x_preferred":[
        "Chota"
    ],
    "name:ita_x_preferred":[
        "Chota"
    ],
    "name:jpn_x_preferred":[
        "\u30c1\u30e7\u30bf"
    ],
    "name:kor_x_preferred":[
        "\ucd08\ud0c0"
    ],
    "name:nld_x_preferred":[
        "Chota"
    ],
    "name:pol_x_preferred":[
        "Chota"
    ],
    "name:rus_x_preferred":[
        "\u0427\u043e\u0442\u0430"
    ],
    "name:spa_x_preferred":[
        "Chota"
    ],
    "name:swe_x_preferred":[
        "Chota"
    ],
    "name:tur_x_preferred":[
        "Chota"
    ],
    "name:ukr_x_preferred":[
        "\u0427\u043e\u0442\u0430"
    ],
    "name:und_x_variant":[
        "Chota Hacienda"
    ],
    "name:urd_x_preferred":[
        "\u0686\u0648\u0679\u0627"
    ],
    "name:vie_x_preferred":[
        "Chota"
    ],
    "wof:name":"Chota",
    "wof:placetype":"locality"
},
  "geometry": {"coordinates":[-78.4807,-7.93331],"type":"Point"}
}