{
  "type": "Feature",
  "properties": {
    "gn:admin1_code":"13",
    "gn:admin2_code":"1306.0",
    "gn:admin3_code":"130602.0",
    "gn:asciiname":"Chota",
    "gn:country_code":"PE",
    "gn:dem":3104,
    "gn:feature_class":"P",
    "gn:feature_code":"PPL",
    "gn:name":"Chota",
    "gn:population":0,
    "gn:timezone":"America/Lima",
    "iso:country":"PE",
    "name:und_x_variant":[
        "Chota Hacienda",
        "Chota"
    ],
    "wof:name":"Chota",
    "wof:placetype":"locality"
},
  "geometry": {"coordinates":[-78.4807,-7.93331],"type":"Point"}
}