{
  "type": "Feature",
  "properties": {
    "gn:admin1_code":"1",
    "gn:admin2_code":"101.0",
    "gn:admin3_code":"10109.0",
    "gn:asciiname":"Curpampa",
    "gn:country_code":"PE",
    "gn:dem":3011,
    "gn:feature_class":"P",
    "gn:feature_code":"PPL",
    "gn:name":"Curpampa",
    "gn:population":0,
    "gn:timezone":"America/Lima",
    "iso:country":"PE",
    "wof:name":"Curpampa",
    "wof:placetype":"locality"
},
  "geometry": {"coordinates":[-77.78301999999999,-6.52539],"type":"Point"}
}