{
  "type": "Feature",
  "properties": {
    "gn:admin1_code":"10.0",
    "gn:admin2_code":"1003.0",
    "gn:admin3_code":"100307.0",
    "gn:asciiname":"Jatunogo",
    "gn:country_code":"PE",
    "gn:dem":3618,
    "gn:feature_class":"P",
    "gn:feature_code":"PPL",
    "gn:name":"Jatunogo",
    "gn:population":0,
    "gn:timezone":"America/Lima",
    "iso:country":"PE",
    "wof:name":"Jatunogo",
    "wof:placetype":"locality"
},
  "geometry": {"coordinates":[-76.70187,-9.65593],"type":"Point"}
}