{
  "type": "Feature",
  "properties": {
    "gn:admin1_code":"12.0",
    "gn:admin2_code":"1201.0",
    "gn:admin3_code":"120128.0",
    "gn:asciiname":"Matacorral",
    "gn:country_code":"PE",
    "gn:dem":4562,
    "gn:feature_class":"P",
    "gn:feature_code":"PPL",
    "gn:name":"Matacorral",
    "gn:population":0,
    "gn:timezone":"America/Lima",
    "iso:country":"PE",
    "wof:name":"Matacorral",
    "wof:placetype":"locality"
},
  "geometry": {"coordinates":[-75.13741,-11.86424],"type":"Point"}
}