{
  "type": "Feature",
  "properties": {
    "gn:admin1_code":"01",
    "gn:admin2_code":"107.0",
    "gn:admin3_code":"10701.0",
    "gn:asciiname":"Jahuanga",
    "gn:country_code":"PE",
    "gn:dem":647,
    "gn:feature_class":"P",
    "gn:feature_code":"PPL",
    "gn:name":"Jahuanga",
    "gn:population":0,
    "gn:timezone":"America/Lima",
    "iso:country":"PE",
    "wof:name":"Jahuanga",
    "wof:placetype":"locality"
},
  "geometry": {"coordinates":[-78.56216999999999,-5.77592],"type":"Point"}
}