{
  "type": "Feature",
  "properties": {
    "gn:admin1_code":"15",
    "gn:admin2_code":"1508.0",
    "gn:admin3_code":"150806.0",
    "gn:asciiname":"Pinico",
    "gn:country_code":"PE",
    "gn:dem":565,
    "gn:feature_class":"P",
    "gn:feature_code":"PPL",
    "gn:name":"Pi\u00f1ico",
    "gn:population":0,
    "gn:timezone":"America/Lima",
    "iso:country":"PE",
    "name:und_x_variant":[
        "Hacienda Pi\u00f1ico",
        "Pe\u00f1ico",
        "Pe\u00f1ico Hacienda",
        "Pi\u00f1ico"
    ],
    "wof:name":"Pinico",
    "wof:placetype":"locality"
},
  "geometry": {"coordinates":[-77.43406,-10.92754],"type":"Point"}
}