{
  "type": "Feature",
  "properties": {
    "gn:admin1_code":"09",
    "gn:admin2_code":"906.0",
    "gn:admin3_code":"90603.0",
    "gn:asciiname":"Los Arenales",
    "gn:country_code":"PE",
    "gn:dem":3618,
    "gn:feature_class":"P",
    "gn:feature_code":"PPL",
    "gn:name":"Los Arenales",
    "gn:population":0,
    "gn:timezone":"America/Lima",
    "iso:country":"PE",
    "wof:name":"Los Arenales",
    "wof:placetype":"locality"
},
  "geometry": {"coordinates":[-75.17724,-14.01264],"type":"Point"}
}