{
  "type": "Feature",
  "properties": {
    "gn:admin1_code":"10.0",
    "gn:admin2_code":"1010.0",
    "gn:admin3_code":"101002.0",
    "gn:asciiname":"Shiripata",
    "gn:country_code":"PE",
    "gn:dem":3806,
    "gn:feature_class":"P",
    "gn:feature_code":"PPL",
    "gn:name":"Shiripata",
    "gn:population":0,
    "gn:timezone":"America/Lima",
    "iso:country":"PE",
    "wof:name":"Shiripata",
    "wof:placetype":"locality"
},
  "geometry": {"coordinates":[-76.74889,-10.17167],"type":"Point"}
}