{
  "type": "Feature",
  "properties": {
    "gn:admin1_code":"08",
    "gn:admin2_code":"807.0",
    "gn:asciiname":"Inapata",
    "gn:country_code":"PE",
    "gn:dem":4538,
    "gn:feature_class":"P",
    "gn:feature_code":"PPL",
    "gn:name":"I\u00f1apata",
    "gn:population":0,
    "gn:timezone":"America/Lima",
    "iso:country":"PE",
    "wof:name":"Inapata",
    "wof:placetype":"locality"
},
  "geometry": {"coordinates":[-72.09999999999999,-14.86667],"type":"Point"}
}