{
  "type": "Feature",
  "properties": {
    "gn:admin1_code":"13",
    "gn:admin2_code":"1306.0",
    "gn:admin3_code":"130614.0",
    "gn:asciiname":"Totora",
    "gn:country_code":"PE",
    "gn:dem":3086,
    "gn:feature_class":"P",
    "gn:feature_code":"PPL",
    "gn:name":"Totora",
    "gn:population":0,
    "gn:timezone":"America/Lima",
    "iso:country":"PE",
    "name:ceb_x_preferred":[
        "Totora"
    ],
    "name:deu_x_preferred":[
        "Totora"
    ],
    "name:epo_x_preferred":[
        "Totoro"
    ],
    "name:ita_x_preferred":[
        "Totora"
    ],
    "name:nld_x_preferred":[
        "Totora"
    ],
    "name:por_x_preferred":[
        "Totora"
    ],
    "name:que_x_preferred":[
        "Tutura"
    ],
    "name:sco_x_preferred":[
        "Totora"
    ],
    "name:spa_x_preferred":[
        "Totora"
    ],
    "name:swe_x_preferred":[
        "Totora"
    ],
    "wof:name":"Totora",
    "wof:placetype":"locality"
},
  "geometry": {"coordinates":[-78.38630000000001,-7.6995],"type":"Point"}
}