{
  "type": "Feature",
  "properties": {
    "gn:admin1_code":"05",
    "gn:admin2_code":"505.0",
    "gn:admin3_code":"50501.0",
    "gn:asciiname":"Putaja",
    "gn:country_code":"PE",
    "gn:dem":3840,
    "gn:feature_class":"P",
    "gn:feature_code":"PPL",
    "gn:name":"Putaja",
    "gn:population":0,
    "gn:timezone":"America/Lima",
    "iso:country":"PE",
    "wof:name":"Putaja",
    "wof:placetype":"locality"
},
  "geometry": {"coordinates":[-73.85760000000001,-13.01635],"type":"Point"}
}