{
  "type": "Feature",
  "properties": {
    "gn:admin1_code":"13",
    "gn:admin2_code":"1307.0",
    "gn:admin3_code":"130705.0",
    "gn:asciiname":"La Campanita",
    "gn:country_code":"PE",
    "gn:dem":101,
    "gn:feature_class":"P",
    "gn:feature_code":"PPL",
    "gn:name":"La Campanita",
    "gn:population":0,
    "gn:timezone":"America/Lima",
    "iso:country":"PE",
    "name:und_x_variant":[
        "La Campanita Hacienda",
        "La Campanita"
    ],
    "wof:name":"La Campanita",
    "wof:placetype":"locality"
},
  "geometry": {"coordinates":[-79.44242,-7.34779],"type":"Point"}
}