{
  "type": "Feature",
  "properties": {
    "gn:admin1_code":"13",
    "gn:admin2_code":"1309.0",
    "gn:admin3_code":"130901.0",
    "gn:asciiname":"Sausacocha",
    "gn:country_code":"PE",
    "gn:dem":3170,
    "gn:feature_class":"P",
    "gn:feature_code":"PPL",
    "gn:name":"Sausacocha",
    "gn:population":0,
    "gn:timezone":"America/Lima",
    "iso:country":"PE",
    "wof:name":"Sausacocha",
    "wof:placetype":"locality"
},
  "geometry": {"coordinates":[-77.98069,-7.80087],"type":"Point"}
}