{
  "type": "Feature",
  "properties": {
    "gn:admin1_code":"06",
    "gn:admin2_code":"613.0",
    "gn:admin3_code":"61303.0",
    "gn:asciiname":"El Chorro",
    "gn:country_code":"PE",
    "gn:dem":1364,
    "gn:feature_class":"P",
    "gn:feature_code":"PPL",
    "gn:name":"El Chorro",
    "gn:population":0,
    "gn:timezone":"America/Lima",
    "iso:country":"PE",
    "name:ceb_x_preferred":[
        "El Chorro"
    ],
    "name:dan_x_preferred":[
        "El Chorro"
    ],
    "name:epo_x_preferred":[
        "El Chorro"
    ],
    "name:eus_x_preferred":[
        "El Chorro"
    ],
    "name:fra_x_preferred":[
        "El Chorro"
    ],
    "name:glg_x_preferred":[
        "El Chorro"
    ],
    "name:hat_x_preferred":[
        "El Chorro"
    ],
    "name:nld_x_preferred":[
        "El Chorro"
    ],
    "name:pol_x_preferred":[
        "El Chorro"
    ],
    "name:spa_x_preferred":[
        "El Chorro"
    ],
    "name:swe_x_preferred":[
        "El Chorro"
    ],
    "wof:name":"El Chorro",
    "wof:placetype":"locality"
},
  "geometry": {"coordinates":[-79.10925,-6.85311],"type":"Point"}
}