{
  "type": "Feature",
  "properties": {
    "gn:admin1_code":"23",
    "gn:admin2_code":"2303.0",
    "gn:admin3_code":"230301.0",
    "gn:asciiname":"Cinto",
    "gn:country_code":"PE",
    "gn:dem":937,
    "gn:feature_class":"P",
    "gn:feature_code":"PPL",
    "gn:name":"Cinto",
    "gn:population":0,
    "gn:timezone":"America/Lima",
    "iso:country":"PE",
    "name:und_x_variant":[
        "Sinto",
        "Cinto Hacienda",
        "Cinto"
    ],
    "wof:name":"Cinto",
    "wof:placetype":"locality"
},
  "geometry": {"coordinates":[-70.71588,-17.5012],"type":"Point"}
}