{
  "type": "Feature",
  "properties": {
    "gn:admin1_code":"21",
    "gn:admin2_code":"2103.0",
    "gn:admin3_code":"210306.0",
    "gn:asciiname":"Llojarani Grande",
    "gn:country_code":"PE",
    "gn:dem":4485,
    "gn:feature_class":"P",
    "gn:feature_code":"PPL",
    "gn:name":"Llojarani Grande",
    "gn:population":0,
    "gn:timezone":"America/Lima",
    "iso:country":"PE",
    "wof:name":"Llojarani Grande",
    "wof:placetype":"locality"
},
  "geometry": {"coordinates":[-69.73948,-14.43834],"type":"Point"}
}