{
  "type": "Feature",
  "properties": {
    "gn:admin1_code":"14",
    "gn:admin2_code":"1403.0",
    "gn:admin3_code":"140307.0",
    "gn:asciiname":"Palo Blanco C",
    "gn:country_code":"PE",
    "gn:dem":152,
    "gn:feature_class":"P",
    "gn:feature_code":"PPLL",
    "gn:name":"Palo Blanco C",
    "gn:population":0,
    "gn:timezone":"America/Lima",
    "iso:country":"PE",
    "wof:name":"Palo Blanco C",
    "wof:placetype":"locality"
},
  "geometry": {"coordinates":[-79.69188,-6.13954],"type":"Point"}
}