{
  "type": "Feature",
  "properties": {
    "gn:admin1_code":"12",
    "gn:admin2_code":"1201.0",
    "gn:admin3_code":"120135.0",
    "gn:asciiname":"Santo Domingo de Acobamba",
    "gn:country_code":"PE",
    "gn:dem":2208,
    "gn:feature_class":"P",
    "gn:feature_code":"PPL",
    "gn:name":"Santo Domingo de Acobamba",
    "gn:population":0,
    "gn:timezone":"America/Lima",
    "iso:country":"PE",
    "name:und_x_variant":[
        "Acobamba",
        "Santo Domingo Acobamba",
        "Santo Domingo de Acobamba"
    ],
    "wof:name":"Santo Domingo de Acobamba",
    "wof:placetype":"locality"
},
  "geometry": {"coordinates":[-74.79528000000001,-11.76912],"type":"Point"}
}