{
  "type": "Feature",
  "properties": {
    "gn:admin1_code":"15",
    "gn:admin2_code":"1507.0",
    "gn:admin3_code":"150709.0",
    "gn:asciiname":"Jarjacha",
    "gn:country_code":"PE",
    "gn:dem":4173,
    "gn:feature_class":"P",
    "gn:feature_code":"PPL",
    "gn:name":"Jarjacha",
    "gn:population":0,
    "gn:timezone":"America/Lima",
    "iso:country":"PE",
    "wof:name":"Jarjacha",
    "wof:placetype":"locality"
},
  "geometry": {"coordinates":[-76.25,-12.01667],"type":"Point"}
}