{
  "type": "Feature",
  "properties": {
    "gn:admin1_code":"16",
    "gn:admin2_code":"1601.0",
    "gn:admin3_code":"160108.0",
    "gn:asciiname":"Santa Clara de Ojeal",
    "gn:country_code":"PE",
    "gn:dem":94,
    "gn:feature_class":"P",
    "gn:feature_code":"PPL",
    "gn:name":"Santa Clara de Ojeal",
    "gn:population":0,
    "gn:timezone":"America/Lima",
    "iso:country":"PE",
    "wof:name":"Santa Clara de Ojeal",
    "wof:placetype":"locality"
},
  "geometry": {"coordinates":[-73.20296,-3.63114],"type":"Point"}
}