{
  "type": "Feature",
  "properties": {
    "gn:admin1_code":"21",
    "gn:admin2_code":"2103.0",
    "gn:admin3_code":"210306.0",
    "gn:asciiname":"Jullmani",
    "gn:country_code":"PE",
    "gn:dem":4248,
    "gn:feature_class":"P",
    "gn:feature_code":"PPL",
    "gn:name":"Jullmani",
    "gn:population":0,
    "gn:timezone":"America/Lima",
    "iso:country":"PE",
    "wof:name":"Jullmani",
    "wof:placetype":"locality"
},
  "geometry": {"coordinates":[-69.97675,-14.34877],"type":"Point"}
}