{
  "type": "Feature",
  "properties": {
    "gn:admin1_code":"3",
    "gn:admin2_code":"302.0",
    "gn:admin3_code":"30217.0",
    "gn:asciiname":"Chirihuasi",
    "gn:country_code":"PE",
    "gn:dem":3811,
    "gn:feature_class":"P",
    "gn:feature_code":"PPL",
    "gn:name":"Chirihuasi",
    "gn:population":0,
    "gn:timezone":"America/Lima",
    "iso:country":"PE",
    "wof:name":"Chirihuasi",
    "wof:placetype":"locality"
},
  "geometry": {"coordinates":[-73.50360999999999,-14.07083],"type":"Point"}
}