{
  "type": "Feature",
  "properties": {
    "gn:admin1_code":"2.0",
    "gn:admin2_code":"203.0",
    "gn:admin3_code":"20304.0",
    "gn:asciiname":"Vilcabamba",
    "gn:country_code":"PE",
    "gn:dem":2665,
    "gn:feature_class":"P",
    "gn:feature_code":"PPL",
    "gn:name":"Vilcabamba",
    "gn:population":0,
    "gn:timezone":"America/Lima",
    "iso:country":"PE",
    "name:ceb_x_preferred":[
        "Vilcabamba"
    ],
    "name:deu_x_preferred":[
        "Vilcabamba"
    ],
    "name:fra_x_preferred":[
        "Vilcabamba"
    ],
    "name:ind_x_preferred":[
        "Vilcabamba"
    ],
    "name:ita_x_preferred":[
        "Vilcabamba"
    ],
    "name:kat_x_preferred":[
        "\u10d5\u10d8\u10da\u10d9\u10d0\u10d1\u10d0\u10db\u10d1\u10d0"
    ],
    "name:mkd_x_preferred":[
        "\u0412\u0438\u043b\u043a\u0430\u0431\u0430\u043c\u0431\u0430"
    ],
    "name:nld_x_preferred":[
        "Vilcabamba"
    ],
    "name:por_x_preferred":[
        "Vilcabamba"
    ],
    "name:que_x_preferred":[
        "Willkapampa"
    ],
    "name:spa_x_preferred":[
        "Vilcabamba"
    ],
    "name:tur_x_preferred":[
        "Vilcabamba"
    ],
    "wof:name":"Vilcabamba",
    "wof:placetype":"locality"
},
  "geometry": {"coordinates":[-76.97606,-9.12735],"type":"Point"}
}