{
  "type": "Feature",
  "properties": {
    "gn:admin1_code":"2.0",
    "gn:admin2_code":"203.0",
    "gn:admin3_code":"20304.0",
    "gn:asciiname":"Vilcabamba",
    "gn:country_code":"PE",
    "gn:dem":2665,
    "gn:feature_class":"P",
    "gn:feature_code":"PPL",
    "gn:name":"Vilcabamba",
    "gn:population":0,
    "gn:timezone":"America/Lima",
    "iso:country":"PE",
    "wof:name":"Vilcabamba",
    "wof:placetype":"locality"
},
  "geometry": {"coordinates":[-76.97606,-9.12735],"type":"Point"}
}