{
  "type": "Feature",
  "properties": {
    "gn:admin1_code":"15",
    "gn:admin2_code":"1510.0",
    "gn:admin3_code":"151006.0",
    "gn:asciiname":"Sicsihuasi",
    "gn:country_code":"PE",
    "gn:dem":4381,
    "gn:feature_class":"P",
    "gn:feature_code":"PPL",
    "gn:name":"Sicsihuasi",
    "gn:population":0,
    "gn:timezone":"America/Lima",
    "iso:country":"PE",
    "wof:name":"Sicsihuasi",
    "wof:placetype":"locality"
},
  "geometry": {"coordinates":[-75.64804000000002,-12.70432],"type":"Point"}
}