{
  "type": "Feature",
  "properties": {
    "gn:admin1_code":"21",
    "gn:admin2_code":"2113.0",
    "gn:admin3_code":"211303.0",
    "gn:asciiname":"Tacapisi",
    "gn:country_code":"PE",
    "gn:dem":3855,
    "gn:feature_class":"P",
    "gn:feature_code":"PPL",
    "gn:name":"Tacapisi",
    "gn:population":0,
    "gn:timezone":"America/Lima",
    "iso:country":"PE",
    "wof:name":"Tacapisi",
    "wof:placetype":"locality"
},
  "geometry": {"coordinates":[-69.036,-16.37628],"type":"Point"}
}