{
  "type": "Feature",
  "properties": {
    "gn:admin1_code":"06",
    "gn:admin2_code":"603.0",
    "gn:admin3_code":"60312.0",
    "gn:asciiname":"Sarsa Pampa",
    "gn:country_code":"PE",
    "gn:dem":2301,
    "gn:feature_class":"P",
    "gn:feature_code":"PPL",
    "gn:name":"Sarsa Pampa",
    "gn:population":0,
    "gn:timezone":"America/Lima",
    "iso:country":"PE",
    "wof:name":"Sarsa Pampa",
    "wof:placetype":"locality"
},
  "geometry": {"coordinates":[-78.26402,-6.78565],"type":"Point"}
}