{
  "type": "Feature",
  "properties": {
    "gn:admin1_code":"12.0",
    "gn:admin2_code":"1204.0",
    "gn:admin3_code":"120422.0",
    "gn:asciiname":"Pichjapuquio",
    "gn:country_code":"PE",
    "gn:dem":3718,
    "gn:feature_class":"P",
    "gn:feature_code":"PPL",
    "gn:name":"Pichjapuquio",
    "gn:population":0,
    "gn:timezone":"America/Lima",
    "iso:country":"PE",
    "wof:name":"Pichjapuquio",
    "wof:placetype":"locality"
},
  "geometry": {"coordinates":[-75.53312,-11.67885],"type":"Point"}
}