{
  "type": "Feature",
  "properties": {
    "gn:admin1_code":"15.0",
    "gn:admin2_code":"1504.0",
    "gn:admin3_code":"150402.0",
    "gn:asciiname":"Pirhuinco",
    "gn:country_code":"PE",
    "gn:dem":1806,
    "gn:feature_class":"P",
    "gn:feature_code":"PPL",
    "gn:name":"Pirhuinco",
    "gn:population":0,
    "gn:timezone":"America/Lima",
    "iso:country":"PE",
    "wof:name":"Pirhuinco",
    "wof:placetype":"locality"
},
  "geometry": {"coordinates":[-76.71966,-11.64727],"type":"Point"}
}