{
  "type": "Feature",
  "properties": {
    "gn:admin1_code":"05",
    "gn:admin2_code":"507.0",
    "gn:admin3_code":"50701.0",
    "gn:asciiname":"Huamanpampa",
    "gn:country_code":"PE",
    "gn:dem":2884,
    "gn:feature_class":"P",
    "gn:feature_code":"PPL",
    "gn:name":"Huamanpampa",
    "gn:population":0,
    "gn:timezone":"America/Lima",
    "iso:country":"PE",
    "name:spa_x_preferred":[
        "Huamanpampa"
    ],
    "wof:name":"Huamanpampa",
    "wof:placetype":"locality"
},
  "geometry": {"coordinates":[-73.80339000000002,-15.01708],"type":"Point"}
}