{
  "type": "Feature",
  "properties": {
    "gn:admin1_code":"21.0",
    "gn:admin2_code":"2112.0",
    "gn:asciiname":"Mancuari",
    "gn:country_code":"PE",
    "gn:dem":1410,
    "gn:feature_class":"P",
    "gn:feature_code":"PPL",
    "gn:name":"Mancuari",
    "gn:population":0,
    "gn:timezone":"America/Lima",
    "iso:country":"PE",
    "name:spa_x_preferred":[
        "Mancuari"
    ],
    "wof:name":"Mancuari",
    "wof:placetype":"locality"
},
  "geometry": {"coordinates":[-69.27271999999999,-14.12148],"type":"Point"}
}