{
  "type": "Feature",
  "properties": {
    "gn:admin1_code":"04",
    "gn:admin2_code":"404.0",
    "gn:admin3_code":"40409.0",
    "gn:asciiname":"Quinsapuquio",
    "gn:country_code":"PE",
    "gn:dem":3889,
    "gn:feature_class":"P",
    "gn:feature_code":"PPL",
    "gn:name":"Quinsapuquio",
    "gn:population":0,
    "gn:timezone":"America/Lima",
    "iso:country":"PE",
    "wof:name":"Quinsapuquio",
    "wof:placetype":"locality"
},
  "geometry": {"coordinates":[-72.35809999999999,-15.23477],"type":"Point"}
}