{
  "type": "Feature",
  "properties": {
    "gn:admin1_code":"02",
    "gn:admin2_code":"206.0",
    "gn:admin3_code":"20603.0",
    "gn:asciiname":"Amashca",
    "gn:country_code":"PE",
    "gn:dem":2873,
    "gn:feature_class":"P",
    "gn:feature_code":"PPLA3",
    "gn:name":"Amashca",
    "gn:population":0,
    "gn:timezone":"America/Lima",
    "iso:country":"PE",
    "wof:name":"Amashca",
    "wof:placetype":"locality"
},
  "geometry": {"coordinates":[-77.64639,-9.23917],"type":"Point"}
}