{
  "type": "Feature",
  "properties": {
    "gn:admin1_code":"12.0",
    "gn:admin2_code":"1207.0",
    "gn:admin3_code":"120708.0",
    "gn:asciiname":"Huaye",
    "gn:country_code":"PE",
    "gn:dem":3627,
    "gn:feature_class":"P",
    "gn:feature_code":"PPL",
    "gn:name":"Huaye",
    "gn:population":0,
    "gn:timezone":"America/Lima",
    "iso:country":"PE",
    "wof:name":"Huaye",
    "wof:placetype":"locality"
},
  "geometry": {"coordinates":[-75.64245,-11.03984],"type":"Point"}
}