{
  "type": "Feature",
  "properties": {
    "gn:admin1_code":"10.0",
    "gn:admin2_code":"1003.0",
    "gn:admin3_code":"100313.0",
    "gn:asciiname":"Rondobamba",
    "gn:country_code":"PE",
    "gn:dem":3994,
    "gn:feature_class":"P",
    "gn:feature_code":"PPL",
    "gn:name":"Rondobamba",
    "gn:population":0,
    "gn:timezone":"America/Lima",
    "iso:country":"PE",
    "wof:name":"Rondobamba",
    "wof:placetype":"locality"
},
  "geometry": {"coordinates":[-76.80485,-9.69134],"type":"Point"}
}