{
  "type": "Feature",
  "properties": {
    "gn:admin1_code":"05",
    "gn:admin2_code":"509.0",
    "gn:admin3_code":"50905.0",
    "gn:asciiname":"Soytojo",
    "gn:country_code":"PE",
    "gn:dem":3412,
    "gn:feature_class":"P",
    "gn:feature_code":"PPL",
    "gn:name":"Soytojo",
    "gn:population":0,
    "gn:timezone":"America/Lima",
    "iso:country":"PE",
    "wof:name":"Soytojo",
    "wof:placetype":"locality"
},
  "geometry": {"coordinates":[-73.93023000000002,-14.1947],"type":"Point"}
}