{
  "type": "Feature",
  "properties": {
    "gn:admin1_code":"11.0",
    "gn:admin2_code":"1101.0",
    "gn:admin3_code":"110106.0",
    "gn:asciiname":"Horno Viejo",
    "gn:country_code":"PE",
    "gn:dem":421,
    "gn:feature_class":"P",
    "gn:feature_code":"PPL",
    "gn:name":"Horno Viejo",
    "gn:population":0,
    "gn:timezone":"America/Lima",
    "iso:country":"PE",
    "name:spa_x_preferred":[
        "Horno Viejo"
    ],
    "wof:name":"Horno Viejo",
    "wof:placetype":"locality"
},
  "geometry": {"coordinates":[-75.71720000000001,-14.05631],"type":"Point"}
}