{
  "type": "Feature",
  "properties": {
    "gn:admin1_code":"2.0",
    "gn:admin2_code":"220.0",
    "gn:admin3_code":"22005.0",
    "gn:asciiname":"Luchaca",
    "gn:country_code":"PE",
    "gn:dem":3679,
    "gn:feature_class":"P",
    "gn:feature_code":"PPL",
    "gn:name":"Luchaca",
    "gn:population":0,
    "gn:timezone":"America/Lima",
    "iso:country":"PE",
    "wof:name":"Luchaca",
    "wof:placetype":"locality"
},
  "geometry": {"coordinates":[-77.89028,-9.30333],"type":"Point"}
}