{
  "type": "Feature",
  "properties": {
    "gn:admin1_code":"06",
    "gn:admin2_code":"604.0",
    "gn:admin3_code":"60411.0",
    "gn:asciiname":"Llama",
    "gn:country_code":"PE",
    "gn:dem":2096,
    "gn:feature_class":"P",
    "gn:feature_code":"PPLA3",
    "gn:name":"Llama",
    "gn:population":0,
    "gn:timezone":"America/Lima",
    "iso:country":"PE",
    "wof:name":"Llama",
    "wof:placetype":"locality"
},
  "geometry": {"coordinates":[-79.12028000000002,-6.51444],"type":"Point"}
}