{
  "type": "Feature",
  "properties": {
    "gn:admin1_code":"9.0",
    "gn:admin2_code":"907.0",
    "gn:admin3_code":"90703.0",
    "gn:asciiname":"Huasapuquio",
    "gn:country_code":"PE",
    "gn:dem":3289,
    "gn:feature_class":"P",
    "gn:feature_code":"PPL",
    "gn:name":"Huasapuquio",
    "gn:population":0,
    "gn:timezone":"America/Lima",
    "iso:country":"PE",
    "wof:name":"Huasapuquio",
    "wof:placetype":"locality"
},
  "geometry": {"coordinates":[-74.92307,-12.3939],"type":"Point"}
}