{
  "type": "Feature",
  "properties": {
    "gn:admin1_code":"15",
    "gn:admin2_code":"1507.0",
    "gn:admin3_code":"150721.0",
    "gn:asciiname":"Huanchac",
    "gn:country_code":"PE",
    "gn:dem":2146,
    "gn:feature_class":"P",
    "gn:feature_code":"PPL",
    "gn:name":"Huanchac",
    "gn:population":0,
    "gn:timezone":"America/Lima",
    "iso:country":"PE",
    "wof:name":"Huanchac",
    "wof:placetype":"locality"
},
  "geometry": {"coordinates":[-76.23333000000002,-12.21667],"type":"Point"}
}