{
  "type": "Feature",
  "properties": {
    "gn:admin1_code":"10.0",
    "gn:admin2_code":"1003.0",
    "gn:admin3_code":"100322.0",
    "gn:asciiname":"Culec Grande",
    "gn:country_code":"PE",
    "gn:dem":3985,
    "gn:feature_class":"P",
    "gn:feature_code":"PPL",
    "gn:name":"Culec Grande",
    "gn:population":0,
    "gn:timezone":"America/Lima",
    "iso:country":"PE",
    "wof:name":"Culec Grande",
    "wof:placetype":"locality"
},
  "geometry": {"coordinates":[-76.76430000000001,-9.83763],"type":"Point"}
}