{
  "type": "Feature",
  "properties": {
    "gn:admin1_code":"22.0",
    "gn:admin2_code":"2202.0",
    "gn:admin3_code":"220205.0",
    "gn:asciiname":"Porvenir",
    "gn:country_code":"PE",
    "gn:dem":306,
    "gn:feature_class":"P",
    "gn:feature_code":"PPL",
    "gn:name":"Porvenir",
    "gn:population":0,
    "gn:timezone":"America/Lima",
    "iso:country":"PE",
    "name:ceb_x_preferred":[
        "Porvenir"
    ],
    "name:deu_x_preferred":[
        "Porvenir"
    ],
    "name:hye_x_preferred":[
        "\u054a\u0578\u0580\u057e\u0565\u0576\u056b\u0580"
    ],
    "name:ita_x_preferred":[
        "Porvenir"
    ],
    "name:nld_x_preferred":[
        "Porvenir"
    ],
    "name:por_x_preferred":[
        "Porvenir"
    ],
    "name:rus_x_preferred":[
        "\u041f\u043e\u0440\u0432\u0435\u043d\u0438\u0440"
    ],
    "name:spa_x_preferred":[
        "Porvenir"
    ],
    "name:swe_x_preferred":[
        "Porvenir"
    ],
    "wof:name":"Porvenir",
    "wof:placetype":"locality"
},
  "geometry": {"coordinates":[-76.55750999999999,-6.79633],"type":"Point"}
}