{
  "type": "Feature",
  "properties": {
    "gn:admin1_code":"23.0",
    "gn:admin2_code":"2301.0",
    "gn:admin3_code":"230110.0",
    "gn:asciiname":"Alfonso Ugarte",
    "gn:country_code":"PE",
    "gn:dem":531,
    "gn:feature_class":"P",
    "gn:feature_code":"PPL",
    "gn:name":"Alf\u00f3nso Ugarte",
    "gn:population":0,
    "gn:timezone":"America/Lima",
    "iso:country":"PE",
    "name:ara_x_preferred":[
        "\u0623\u0644\u0641\u0648\u0646\u0633\u0648 \u0623\u0648\u062c\u0627\u0631\u062a"
    ],
    "name:aym_x_preferred":[
        "Alfonso Ugarte"
    ],
    "name:pol_x_preferred":[
        "Alfonso Ugarte y Vernal"
    ],
    "name:que_x_preferred":[
        "Alfonso Ugarte"
    ],
    "name:rus_x_preferred":[
        "\u0423\u0433\u0430\u0440\u0442\u0435"
    ],
    "name:spa_x_preferred":[
        "Alfonso Ugarte"
    ],
    "name:vie_x_preferred":[
        "Alfonso Ugarte"
    ],
    "wof:name":"Alfonso Ugarte",
    "wof:placetype":"locality"
},
  "geometry": {"coordinates":[-70.245,-18.0425],"type":"Point"}
}