{
  "type": "Feature",
  "properties": {
    "gn:admin1_code":"23.0",
    "gn:admin2_code":"2301.0",
    "gn:admin3_code":"230110.0",
    "gn:asciiname":"Alfonso Ugarte",
    "gn:country_code":"PE",
    "gn:dem":531,
    "gn:feature_class":"P",
    "gn:feature_code":"PPL",
    "gn:name":"Alf\u00f3nso Ugarte",
    "gn:population":0,
    "gn:timezone":"America/Lima",
    "iso:country":"PE",
    "wof:name":"Alfonso Ugarte",
    "wof:placetype":"locality"
},
  "geometry": {"coordinates":[-70.245,-18.0425],"type":"Point"}
}