{
  "type": "Feature",
  "properties": {
    "gn:admin1_code":"10.0",
    "gn:admin2_code":"1010.0",
    "gn:admin3_code":"101003.0",
    "gn:asciiname":"Salacancha",
    "gn:country_code":"PE",
    "gn:dem":3886,
    "gn:feature_class":"P",
    "gn:feature_code":"PPL",
    "gn:name":"Salacancha",
    "gn:population":0,
    "gn:timezone":"America/Lima",
    "iso:country":"PE",
    "wof:name":"Salacancha",
    "wof:placetype":"locality"
},
  "geometry": {"coordinates":[-76.61917,-10.02222],"type":"Point"}
}