{
  "type": "Feature",
  "properties": {
    "gn:admin1_code":"12.0",
    "gn:admin2_code":"1204.0",
    "gn:admin3_code":"120432.0",
    "gn:asciiname":"Pojuipuquio",
    "gn:country_code":"PE",
    "gn:dem":3778,
    "gn:feature_class":"P",
    "gn:feature_code":"PPL",
    "gn:name":"Pojuipuquio",
    "gn:population":0,
    "gn:timezone":"America/Lima",
    "iso:country":"PE",
    "wof:name":"Pojuipuquio",
    "wof:placetype":"locality"
},
  "geometry": {"coordinates":[-75.58906,-11.70225],"type":"Point"}
}