{
  "type": "Feature",
  "properties": {
    "gn:admin1_code":"22.0",
    "gn:admin2_code":"2203.0",
    "gn:admin3_code":"220301.0",
    "gn:asciiname":"Hidalgo",
    "gn:country_code":"PE",
    "gn:dem":437,
    "gn:feature_class":"P",
    "gn:feature_code":"PPL",
    "gn:name":"Hidalgo",
    "gn:population":0,
    "gn:timezone":"America/Lima",
    "iso:country":"PE",
    "name:spa_x_preferred":[
        "Hidalgo"
    ],
    "wof:name":"Hidalgo",
    "wof:placetype":"locality"
},
  "geometry": {"coordinates":[-76.73907,-6.63796],"type":"Point"}
}