{
  "type": "Feature",
  "properties": {
    "gn:admin1_code":"19",
    "gn:admin2_code":"1901.0",
    "gn:admin3_code":"190106.0",
    "gn:asciiname":"Umapancuy",
    "gn:country_code":"PE",
    "gn:dem":3818,
    "gn:feature_class":"P",
    "gn:feature_code":"PPL",
    "gn:name":"Umapancuy",
    "gn:population":0,
    "gn:timezone":"America/Lima",
    "iso:country":"PE",
    "wof:name":"Umapancuy",
    "wof:placetype":"locality"
},
  "geometry": {"coordinates":[-76.25079000000002,-10.43657],"type":"Point"}
}