{
  "type": "Feature",
  "properties": {
    "gn:admin1_code":"05",
    "gn:admin2_code":"506.0",
    "gn:admin3_code":"50609.0",
    "gn:asciiname":"Pirca",
    "gn:country_code":"PE",
    "gn:dem":1924,
    "gn:feature_class":"P",
    "gn:feature_code":"PPL",
    "gn:name":"Pirca",
    "gn:population":0,
    "gn:timezone":"America/Lima",
    "iso:country":"PE",
    "name:und_x_variant":[
        "Pirca Hacienda",
        "Pirca"
    ],
    "wof:name":"Pirca",
    "wof:placetype":"locality"
},
  "geometry": {"coordinates":[-74.76291999999999,-14.70186],"type":"Point"}
}