{
  "type": "Feature",
  "properties": {
    "gn:admin1_code":"14",
    "gn:admin2_code":"1403.0",
    "gn:admin3_code":"140310.0",
    "gn:asciiname":"Limon Pampa",
    "gn:country_code":"PE",
    "gn:dem":1019,
    "gn:feature_class":"P",
    "gn:feature_code":"PPL",
    "gn:name":"Lim\u00f3n Pampa",
    "gn:population":0,
    "gn:timezone":"America/Lima",
    "iso:country":"PE",
    "wof:name":"Limon Pampa",
    "wof:placetype":"locality"
},
  "geometry": {"coordinates":[-79.54174,-6.09384],"type":"Point"}
}