{
  "type": "Feature",
  "properties": {
    "gn:admin1_code":"12",
    "gn:admin2_code":"1205.0",
    "gn:admin3_code":"120501.0",
    "gn:asciiname":"Shacayan",
    "gn:country_code":"PE",
    "gn:dem":4169,
    "gn:feature_class":"P",
    "gn:feature_code":"PPL",
    "gn:name":"Shacay\u00e1n",
    "gn:population":0,
    "gn:timezone":"America/Lima",
    "iso:country":"PE",
    "wof:name":"Shacayan",
    "wof:placetype":"locality"
},
  "geometry": {"coordinates":[-75.99611,-11.02611],"type":"Point"}
}