{
  "type": "Feature",
  "properties": {
    "gn:admin1_code":"12",
    "gn:admin2_code":"1203.0",
    "gn:admin3_code":"120305.0",
    "gn:asciiname":"Mina Pichita",
    "gn:country_code":"PE",
    "gn:dem":2028,
    "gn:feature_class":"P",
    "gn:feature_code":"PPL",
    "gn:name":"Mina Pichita",
    "gn:population":0,
    "gn:timezone":"America/Lima",
    "iso:country":"PE",
    "wof:name":"Mina Pichita",
    "wof:placetype":"locality"
},
  "geometry": {"coordinates":[-75.41471999999997,-11.08611],"type":"Point"}
}