{
  "type": "Feature",
  "properties": {
    "gn:admin1_code":"12.0",
    "gn:admin2_code":"1201.0",
    "gn:admin3_code":"120128.0",
    "gn:asciiname":"Yuraccasha",
    "gn:country_code":"PE",
    "gn:dem":4435,
    "gn:feature_class":"P",
    "gn:feature_code":"PPL",
    "gn:name":"Yuraccasha",
    "gn:population":0,
    "gn:timezone":"America/Lima",
    "iso:country":"PE",
    "wof:name":"Yuraccasha",
    "wof:placetype":"locality"
},
  "geometry": {"coordinates":[-75.10951999999997,-11.90047],"type":"Point"}
}