{
  "type": "Feature",
  "properties": {
    "gn:admin1_code":"03",
    "gn:admin2_code":"304.0",
    "gn:admin3_code":"30404.0",
    "gn:asciiname":"Chapimarca",
    "gn:country_code":"PE",
    "gn:dem":3406,
    "gn:feature_class":"P",
    "gn:feature_code":"PPLA3",
    "gn:name":"Chapimarca",
    "gn:population":0,
    "gn:timezone":"America/Lima",
    "iso:country":"PE",
    "wof:name":"Chapimarca",
    "wof:placetype":"locality"
},
  "geometry": {"coordinates":[-73.065,-13.97528],"type":"Point"}
}