{
  "type": "Feature",
  "properties": {
    "gn:admin1_code":"17.0",
    "gn:admin2_code":"1703.0",
    "gn:asciiname":"Saccsayhuaman",
    "gn:country_code":"PE",
    "gn:dem":262,
    "gn:feature_class":"P",
    "gn:feature_code":"PPL",
    "gn:name":"Saccsayhuaman",
    "gn:population":0,
    "gn:timezone":"America/Lima",
    "iso:country":"PE",
    "wof:name":"Saccsayhuaman",
    "wof:placetype":"locality"
},
  "geometry": {"coordinates":[-69.15767,-11.90712],"type":"Point"}
}