{
  "type": "Feature",
  "properties": {
    "iso:country":"PE",
    "qs:gn_country":"PE",
    "qs:gn_fcode":"PPL",
    "qs:gn_pop":6757,
    "qs:name":"Huicungo",
    "qs:name_adm0":"Per\u00fa",
    "qs:name_adm1":"San Martin",
    "qs:photos":0,
    "qs:photos_1k":0,
    "qs:photos_9k":0,
    "qs:photos_9r":0,
    "qs:photos_all":0,
    "qs:photos_sr":0,
    "qs:placetype":"Town",
    "qs:pop_sr":"5",
    "qs:woe_adm0":23424919,
    "wof:name":"Huicungo",
    "wof:placetype":"locality",
    "wof:population":6757
},
  "geometry": {"coordinates":[-76.77556,-7.3186],"type":"Point"}
}