{
  "type": "Feature",
  "properties": {
    "gn:admin1_code":"2.0",
    "gn:admin2_code":"205.0",
    "gn:admin3_code":"20509.0",
    "gn:asciiname":"Quicash Pata",
    "gn:country_code":"PE",
    "gn:dem":3654,
    "gn:feature_class":"P",
    "gn:feature_code":"PPL",
    "gn:name":"Quicash Pata",
    "gn:population":0,
    "gn:timezone":"America/Lima",
    "iso:country":"PE",
    "wof:name":"Quicash Pata",
    "wof:placetype":"locality"
},
  "geometry": {"coordinates":[-77.02431,-10.14705],"type":"Point"}
}