{
  "type": "Feature",
  "properties": {
    "gn:admin1_code":"5",
    "gn:admin2_code":"511.0",
    "gn:admin3_code":"51107.0",
    "gn:asciiname":"Huallhua",
    "gn:country_code":"PE",
    "gn:dem":3429,
    "gn:feature_class":"P",
    "gn:feature_code":"PPL",
    "gn:name":"Huallhua",
    "gn:population":0,
    "gn:timezone":"America/Lima",
    "iso:country":"PE",
    "wof:name":"Huallhua",
    "wof:placetype":"locality"
},
  "geometry": {"coordinates":[-73.79522,-13.69464],"type":"Point"}
}