{
  "type": "Feature",
  "properties": {
    "gn:admin1_code":"10.0",
    "gn:admin2_code":"1009.0",
    "gn:admin3_code":"100903.0",
    "gn:asciiname":"Auagua Caliente",
    "gn:country_code":"PE",
    "gn:dem":202,
    "gn:feature_class":"P",
    "gn:feature_code":"PPL",
    "gn:name":"Auagua Caliente",
    "gn:population":0,
    "gn:timezone":"America/Lima",
    "iso:country":"PE",
    "wof:name":"Auagua Caliente",
    "wof:placetype":"locality"
},
  "geometry": {"coordinates":[-74.72291,-8.81239],"type":"Point"}
}