{
  "type": "Feature",
  "properties": {
    "gn:admin1_code":"03",
    "gn:admin2_code":"302.0",
    "gn:admin3_code":"30207.0",
    "gn:asciiname":"Kishuara",
    "gn:country_code":"PE",
    "gn:dem":3716,
    "gn:feature_class":"P",
    "gn:feature_code":"PPLA3",
    "gn:name":"Kishuara",
    "gn:population":0,
    "gn:timezone":"America/Lima",
    "iso:country":"PE",
    "name:und_x_variant":[
        "Quishuara",
        "Kishuara"
    ],
    "wof:name":"Kishuara",
    "wof:placetype":"locality"
},
  "geometry": {"coordinates":[-73.11639,-13.69444],"type":"Point"}
}