{
  "type": "Feature",
  "properties": {
    "gn:admin1_code":"12.0",
    "gn:admin2_code":"1201.0",
    "gn:admin3_code":"120128.0",
    "gn:asciiname":"Chuupata",
    "gn:country_code":"PE",
    "gn:dem":4277,
    "gn:feature_class":"P",
    "gn:feature_code":"PPL",
    "gn:name":"Chuupata",
    "gn:population":0,
    "gn:timezone":"America/Lima",
    "iso:country":"PE",
    "wof:name":"Chuupata",
    "wof:placetype":"locality"
},
  "geometry": {"coordinates":[-75.17416999999998,-11.89373],"type":"Point"}
}