{
  "type": "Feature",
  "properties": {
    "gn:admin1_code":"05",
    "gn:admin2_code":"509.0",
    "gn:admin3_code":"50908.0",
    "gn:asciiname":"Jihuane",
    "gn:country_code":"PE",
    "gn:dem":4167,
    "gn:feature_class":"P",
    "gn:feature_code":"PPL",
    "gn:name":"Jihuane",
    "gn:population":0,
    "gn:timezone":"America/Lima",
    "iso:country":"PE",
    "wof:name":"Jihuane",
    "wof:placetype":"locality"
},
  "geometry": {"coordinates":[-73.58806,-14.35611],"type":"Point"}
}