{
  "type": "Feature",
  "properties": {
    "gn:admin1_code":"2.0",
    "gn:admin2_code":"214.0",
    "gn:admin3_code":"21401.0",
    "gn:asciiname":"Anco",
    "gn:country_code":"PE",
    "gn:dem":3316,
    "gn:feature_class":"P",
    "gn:feature_code":"PPL",
    "gn:name":"Anco",
    "gn:population":0,
    "gn:timezone":"America/Lima",
    "iso:country":"PE",
    "name:ceb_x_preferred":[
        "Anco"
    ],
    "name:por_x_preferred":[
        "Anco"
    ],
    "wof:name":"Anco",
    "wof:placetype":"locality"
},
  "geometry": {"coordinates":[-77.40871,-10.40994],"type":"Point"}
}