{
  "type": "Feature",
  "properties": {
    "gn:admin1_code":"06",
    "gn:admin2_code":"607.0",
    "gn:admin3_code":"60701.0",
    "gn:asciiname":"Viscacha",
    "gn:country_code":"PE",
    "gn:dem":3428,
    "gn:feature_class":"P",
    "gn:feature_code":"PPL",
    "gn:name":"Viscacha",
    "gn:population":0,
    "gn:timezone":"America/Lima",
    "iso:country":"PE",
    "wof:name":"Viscacha",
    "wof:placetype":"locality"
},
  "geometry": {"coordinates":[-78.44181,-6.73784],"type":"Point"}
}