{
  "type": "Feature",
  "properties": {
    "gn:admin1_code":"06",
    "gn:admin2_code":"607.0",
    "gn:admin3_code":"60701.0",
    "gn:asciiname":"Viscacha",
    "gn:country_code":"PE",
    "gn:dem":3428,
    "gn:feature_class":"P",
    "gn:feature_code":"PPL",
    "gn:name":"Viscacha",
    "gn:population":0,
    "gn:timezone":"America/Lima",
    "iso:country":"PE",
    "name:aym_x_preferred":[
        "Wisk'achu"
    ],
    "name:bos_x_preferred":[
        "Viska\u010da"
    ],
    "name:bre_x_preferred":[
        "Viskacha"
    ],
    "name:fin_x_preferred":[
        "Viskatsat"
    ],
    "name:fra_x_preferred":[
        "Viscache"
    ],
    "name:ita_x_preferred":[
        "Viscaccia"
    ],
    "name:jpn_x_preferred":[
        "\u30d3\u30b9\u30ab\u30c3\u30c1\u30e3"
    ],
    "name:lit_x_preferred":[
        "Viska\u0161a"
    ],
    "name:por_x_preferred":[
        "Viscacha"
    ],
    "name:que_x_preferred":[
        "Wisk'acha"
    ],
    "name:spa_x_preferred":[
        "Vizcacha"
    ],
    "name:ukr_x_preferred":[
        "\u0412\u0456\u0441\u043a\u0430\u0448\u0456"
    ],
    "name:vie_x_preferred":[
        "Viscacha"
    ],
    "wof:name":"Viscacha",
    "wof:placetype":"locality"
},
  "geometry": {"coordinates":[-78.44181,-6.73784],"type":"Point"}
}