{
  "type": "Feature",
  "properties": {
    "gn:admin1_code":"02",
    "gn:admin2_code":"215.0",
    "gn:admin3_code":"21508.0",
    "gn:asciiname":"Canta Gallo",
    "gn:country_code":"PE",
    "gn:dem":2497,
    "gn:feature_class":"P",
    "gn:feature_code":"PPL",
    "gn:name":"Canta Gallo",
    "gn:population":0,
    "gn:timezone":"America/Lima",
    "iso:country":"PE",
    "wof:name":"Canta Gallo",
    "wof:placetype":"locality"
},
  "geometry": {"coordinates":[-78.00461999999997,-8.23354],"type":"Point"}
}