{
  "type": "Feature",
  "properties": {
    "gn:admin1_code":"06",
    "gn:admin2_code":"602.0",
    "gn:admin3_code":"60202.0",
    "gn:asciiname":"Tambillos",
    "gn:country_code":"PE",
    "gn:dem":3685,
    "gn:feature_class":"P",
    "gn:feature_code":"PPL",
    "gn:name":"Tambillos",
    "gn:population":0,
    "gn:timezone":"America/Lima",
    "iso:country":"PE",
    "wof:name":"Tambillos",
    "wof:placetype":"locality"
},
  "geometry": {"coordinates":[-78.32925999999998,-7.6685],"type":"Point"}
}