{
  "type": "Feature",
  "properties": {
    "gn:admin1_code":"08",
    "gn:admin2_code":"809.0",
    "gn:admin3_code":"80908.0",
    "gn:asciiname":"Churubamba",
    "gn:country_code":"PE",
    "gn:dem":4233,
    "gn:feature_class":"P",
    "gn:feature_code":"PPL",
    "gn:name":"Churubamba",
    "gn:population":0,
    "gn:timezone":"America/Lima",
    "iso:country":"PE",
    "wof:name":"Churubamba",
    "wof:placetype":"locality"
},
  "geometry": {"coordinates":[-72.68333,-13.23333],"type":"Point"}
}