{
  "type": "Feature",
  "properties": {
    "gn:admin1_code":"9.0",
    "gn:admin2_code":"907.0",
    "gn:admin3_code":"90709.0",
    "gn:asciiname":"Quillihuay",
    "gn:country_code":"PE",
    "gn:dem":3438,
    "gn:feature_class":"P",
    "gn:feature_code":"PPL",
    "gn:name":"Quillihuay",
    "gn:population":0,
    "gn:timezone":"America/Lima",
    "iso:country":"PE",
    "wof:name":"Quillihuay",
    "wof:placetype":"locality"
},
  "geometry": {"coordinates":[-74.98374,-12.27454],"type":"Point"}
}