{
  "type": "Feature",
  "properties": {
    "gn:admin1_code":"11",
    "gn:admin2_code":"1105.0",
    "gn:admin3_code":"110502.0",
    "gn:asciiname":"Huancacasa",
    "gn:country_code":"PE",
    "gn:dem":2859,
    "gn:feature_class":"P",
    "gn:feature_code":"PPL",
    "gn:name":"Huancacasa",
    "gn:population":0,
    "gn:timezone":"America/Lima",
    "iso:country":"PE",
    "wof:name":"Huancacasa",
    "wof:placetype":"locality"
},
  "geometry": {"coordinates":[-75.52807,-13.70547],"type":"Point"}
}