{
  "type": "Feature",
  "properties": {
    "gn:admin1_code":"13",
    "gn:admin2_code":"1309.0",
    "gn:admin3_code":"130904.0",
    "gn:asciiname":"Rayabal",
    "gn:country_code":"PE",
    "gn:dem":3387,
    "gn:feature_class":"P",
    "gn:feature_code":"PPL",
    "gn:name":"Rayabal",
    "gn:population":0,
    "gn:timezone":"America/Lima",
    "iso:country":"PE",
    "wof:name":"Rayabal",
    "wof:placetype":"locality"
},
  "geometry": {"coordinates":[-77.95589,-7.86171],"type":"Point"}
}