{
  "type": "Feature",
  "properties": {
    "gn:admin1_code":"24",
    "gn:admin2_code":"2401.0",
    "gn:admin3_code":"240105.0",
    "gn:asciiname":"Marcos",
    "gn:country_code":"PE",
    "gn:dem":164,
    "gn:feature_class":"P",
    "gn:feature_code":"PPLL",
    "gn:name":"Marcos",
    "gn:population":0,
    "gn:timezone":"America/Lima",
    "iso:country":"PE",
    "wof:name":"Marcos",
    "wof:placetype":"locality"
},
  "geometry": {"coordinates":[-80.54916999999998,-3.79806],"type":"Point"}
}