{
  "type": "Feature",
  "properties": {
    "gn:admin1_code":"11.0",
    "gn:admin2_code":"1101.0",
    "gn:admin3_code":"110101.0",
    "gn:asciiname":"La Palma Chica",
    "gn:country_code":"PE",
    "gn:dem":404,
    "gn:feature_class":"P",
    "gn:feature_code":"PPL",
    "gn:name":"La Palma Chica",
    "gn:population":0,
    "gn:timezone":"America/Lima",
    "iso:country":"PE",
    "name:spa_x_preferred":[
        "La Palma Chica"
    ],
    "wof:name":"La Palma Chica",
    "wof:placetype":"locality"
},
  "geometry": {"coordinates":[-75.73444000000001,-14.09201],"type":"Point"}
}