{
  "type": "Feature",
  "properties": {
    "gn:admin1_code":"15",
    "gn:admin2_code":"1508.0",
    "gn:admin3_code":"150806.0",
    "gn:asciiname":"Ingenio",
    "gn:country_code":"PE",
    "gn:dem":81,
    "gn:feature_class":"P",
    "gn:feature_code":"PPL",
    "gn:name":"Ingenio",
    "gn:population":0,
    "gn:timezone":"America/Lima",
    "iso:country":"PE",
    "name:und_x_variant":[
        "Ingenio Hacienda",
        "Ingenio"
    ],
    "wof:name":"Ingenio",
    "wof:placetype":"locality"
},
  "geometry": {"coordinates":[-77.59399000000001,-11.06434],"type":"Point"}
}