{
  "type": "Feature",
  "properties": {
    "gn:admin1_code":"2.0",
    "gn:admin2_code":"205.0",
    "gn:admin3_code":"20501.0",
    "gn:asciiname":"Cutacarcas",
    "gn:country_code":"PE",
    "gn:dem":3174,
    "gn:feature_class":"P",
    "gn:feature_code":"PPL",
    "gn:name":"Cutacarcas",
    "gn:population":0,
    "gn:timezone":"America/Lima",
    "iso:country":"PE",
    "wof:name":"Cutacarcas",
    "wof:placetype":"locality"
},
  "geometry": {"coordinates":[-77.16234,-10.10713],"type":"Point"}
}