{
  "type": "Feature",
  "properties": {
    "gn:admin1_code":"17.0",
    "gn:admin2_code":"1703.0",
    "gn:asciiname":"Fortaleza",
    "gn:country_code":"PE",
    "gn:dem":300,
    "gn:feature_class":"P",
    "gn:feature_code":"PPL",
    "gn:name":"Fortaleza",
    "gn:population":0,
    "gn:timezone":"America/Lima",
    "iso:country":"PE",
    "name:spa_x_preferred":[
        "Fortaleza"
    ],
    "wof:name":"Fortaleza",
    "wof:placetype":"locality"
},
  "geometry": {"coordinates":[-69.45489000000001,-11.16182],"type":"Point"}
}