{
  "type": "Feature",
  "properties": {
    "gn:admin1_code":"09",
    "gn:admin2_code":"907.0",
    "gn:admin3_code":"90711.0",
    "gn:asciiname":"Pazos",
    "gn:cc2":"PE",
    "gn:country_code":"PE",
    "gn:dem":3947,
    "gn:feature_class":"P",
    "gn:feature_code":"PPLA3",
    "gn:name":"Pazos",
    "gn:population":0,
    "gn:timezone":"America/Lima",
    "iso:country":"PE",
    "name:und_x_variant":[
        "Pasos",
        "Pazos"
    ],
    "wof:name":"Pazos",
    "wof:placetype":"locality"
},
  "geometry": {"coordinates":[-75.09999999999999,-12.26667],"type":"Point"}
}