{
  "type": "Feature",
  "properties": {
    "gn:admin1_code":"03",
    "gn:admin2_code":"306.0",
    "gn:admin3_code":"30605.0",
    "gn:asciiname":"Chojepuquio",
    "gn:country_code":"PE",
    "gn:dem":2799,
    "gn:feature_class":"P",
    "gn:feature_code":"PPL",
    "gn:name":"Chojepuquio",
    "gn:population":0,
    "gn:timezone":"America/Lima",
    "iso:country":"PE",
    "wof:name":"Chojepuquio",
    "wof:placetype":"locality"
},
  "geometry": {"coordinates":[-73.53144,-13.53613],"type":"Point"}
}