{
  "type": "Feature",
  "properties": {
    "gn:admin1_code":"11.0",
    "gn:admin2_code":"1101.0",
    "gn:admin3_code":"110102.0",
    "gn:asciiname":"Limoncillo",
    "gn:country_code":"PE",
    "gn:dem":420,
    "gn:feature_class":"P",
    "gn:feature_code":"PPL",
    "gn:name":"Limoncillo",
    "gn:population":0,
    "gn:timezone":"America/Lima",
    "iso:country":"PE",
    "name:spa_x_preferred":[
        "Limoncillo"
    ],
    "wof:name":"Limoncillo",
    "wof:placetype":"locality"
},
  "geometry": {"coordinates":[-75.72908000000002,-14.01393],"type":"Point"}
}