{
  "type": "Feature",
  "properties": {
    "gn:admin1_code":"8",
    "gn:admin2_code":"809.0",
    "gn:admin3_code":"80909.0",
    "gn:asciiname":"Lejiana",
    "gn:country_code":"PE",
    "gn:dem":2472,
    "gn:feature_class":"P",
    "gn:feature_code":"PPL",
    "gn:name":"Lejiana",
    "gn:population":0,
    "gn:timezone":"America/Lima",
    "iso:country":"PE",
    "wof:name":"Lejiana",
    "wof:placetype":"locality"
},
  "geometry": {"coordinates":[-73.19944,-13.29667],"type":"Point"}
}