{
  "type": "Feature",
  "properties": {
    "gn:admin1_code":"21",
    "gn:admin2_code":"2112.0",
    "gn:admin3_code":"211202.0",
    "gn:asciiname":"Ccalaccala",
    "gn:country_code":"PE",
    "gn:dem":4044,
    "gn:feature_class":"P",
    "gn:feature_code":"PPL",
    "gn:name":"Ccalaccala",
    "gn:population":0,
    "gn:timezone":"America/Lima",
    "iso:country":"PE",
    "wof:name":"Ccalaccala",
    "wof:placetype":"locality"
},
  "geometry": {"coordinates":[-69.60380000000001,-14.43813],"type":"Point"}
}