{
  "type": "Feature",
  "properties": {
    "gn:admin1_code":"18",
    "gn:admin2_code":"1802.0",
    "gn:admin3_code":"180204.0",
    "gn:asciiname":"Jucune",
    "gn:country_code":"PE",
    "gn:dem":3952,
    "gn:feature_class":"P",
    "gn:feature_code":"PPL",
    "gn:name":"Jucune",
    "gn:population":0,
    "gn:timezone":"America/Lima",
    "iso:country":"PE",
    "wof:name":"Jucune",
    "wof:placetype":"locality"
},
  "geometry": {"coordinates":[-70.62729,-16.01012],"type":"Point"}
}