{
  "type": "Feature",
  "properties": {
    "gn:admin1_code":"03",
    "gn:admin2_code":"301.0",
    "gn:admin3_code":"30108.0",
    "gn:asciiname":"Incahuasi",
    "gn:country_code":"PE",
    "gn:dem":3237,
    "gn:feature_class":"P",
    "gn:feature_code":"PPL",
    "gn:name":"Incahuasi",
    "gn:population":0,
    "gn:timezone":"America/Lima",
    "iso:country":"PE",
    "name:ast_x_preferred":[
        "Volc\u00e1n Incahuasi"
    ],
    "name:bre_x_preferred":[
        "Incahuasi"
    ],
    "name:cat_x_preferred":[
        "Incahuasi"
    ],
    "name:deu_x_preferred":[
        "Incahuasi"
    ],
    "name:epo_x_preferred":[
        "Incahuasi"
    ],
    "name:hye_x_preferred":[
        "\u053b\u0576\u056f\u0561\u0578\u0582\u0561\u057d\u056b"
    ],
    "name:jpn_x_preferred":[
        "\u30a4\u30f3\u30ab\u30ef\u30b7\u5c71"
    ],
    "name:kat_x_preferred":[
        "\u10d8\u10dc\u10d9\u10d0\u10e3\u10d0\u10e1\u10d8"
    ],
    "name:nld_x_preferred":[
        "Incahuasi"
    ],
    "name:oss_x_preferred":[
        "\u0418\u043d\u043a\u0430\u0443\u0430\u0441\u0438"
    ],
    "name:pol_x_preferred":[
        "Incahuasi"
    ],
    "name:por_x_preferred":[
        "Incahuasi"
    ],
    "name:rus_x_preferred":[
        "\u0418\u043d\u043a\u0430\u0443\u0430\u0441\u0438"
    ],
    "name:spa_x_preferred":[
        "Volc\u00e1n Incahuasi"
    ],
    "name:ukr_x_preferred":[
        "\u0406\u043d\u043a\u0430\u0443\u0430\u0441\u0456"
    ],
    "name:xmf_x_preferred":[
        "\u10d8\u10dc\u10d9\u10d0\u10e3\u10d0\u10e1\u10d8"
    ],
    "name:zho_x_preferred":[
        "\u5370\u52a0\u74e6\u897f\u5cf0"
    ],
    "wof:name":"Incahuasi",
    "wof:placetype":"locality"
},
  "geometry": {"coordinates":[-72.83333,-13.45],"type":"Point"}
}