{
  "type": "Feature",
  "properties": {
    "gn:admin1_code":"03",
    "gn:admin2_code":"301.0",
    "gn:admin3_code":"30108.0",
    "gn:asciiname":"Incahuasi",
    "gn:country_code":"PE",
    "gn:dem":3237,
    "gn:feature_class":"P",
    "gn:feature_code":"PPL",
    "gn:name":"Incahuasi",
    "gn:population":0,
    "gn:timezone":"America/Lima",
    "iso:country":"PE",
    "wof:name":"Incahuasi",
    "wof:placetype":"locality"
},
  "geometry": {"coordinates":[-72.83333,-13.45],"type":"Point"}
}