{
  "type": "Feature",
  "properties": {
    "gn:admin1_code":"10",
    "gn:admin2_code":"1001.0",
    "gn:admin3_code":"100108.0",
    "gn:asciiname":"Icuro",
    "gn:country_code":"PE",
    "gn:dem":4174,
    "gn:feature_class":"P",
    "gn:feature_code":"PPL",
    "gn:name":"Icuro",
    "gn:population":0,
    "gn:timezone":"America/Lima",
    "iso:country":"PE",
    "wof:name":"Icuro",
    "wof:placetype":"locality"
},
  "geometry": {"coordinates":[-76.44184,-10.12104],"type":"Point"}
}