{
  "type": "Feature",
  "properties": {
    "gn:admin1_code":"22.0",
    "gn:admin2_code":"2202.0",
    "gn:admin3_code":"220204.0",
    "gn:asciiname":"Angamos",
    "gn:country_code":"PE",
    "gn:dem":257,
    "gn:feature_class":"P",
    "gn:feature_code":"PPL",
    "gn:name":"Angamos",
    "gn:population":0,
    "gn:timezone":"America/Lima",
    "iso:country":"PE",
    "name:spa_x_preferred":[
        "Angamos"
    ],
    "wof:name":"Angamos",
    "wof:placetype":"locality"
},
  "geometry": {"coordinates":[-76.65000999999999,-7.10467],"type":"Point"}
}