{
  "type": "Feature",
  "properties": {
    "gn:admin1_code":"05",
    "gn:admin2_code":"501.0",
    "gn:admin3_code":"50107.0",
    "gn:asciiname":"Hilcaccasa",
    "gn:country_code":"PE",
    "gn:dem":3066,
    "gn:feature_class":"P",
    "gn:feature_code":"PPL",
    "gn:name":"Hilcaccasa",
    "gn:population":0,
    "gn:timezone":"America/Lima",
    "iso:country":"PE",
    "wof:name":"Hilcaccasa",
    "wof:placetype":"locality"
},
  "geometry": {"coordinates":[-74.1876,-13.02579],"type":"Point"}
}