{
  "type": "Feature",
  "properties": {
    "gn:admin1_code":"3",
    "gn:admin2_code":"302.0",
    "gn:admin3_code":"30202.0",
    "gn:asciiname":"Huallhuayoc",
    "gn:country_code":"PE",
    "gn:dem":3209,
    "gn:feature_class":"P",
    "gn:feature_code":"PPL",
    "gn:name":"Huallhuayoc",
    "gn:population":0,
    "gn:timezone":"America/Lima",
    "iso:country":"PE",
    "wof:name":"Huallhuayoc",
    "wof:placetype":"locality"
},
  "geometry": {"coordinates":[-73.3725,-13.54134],"type":"Point"}
}