{
  "type": "Feature",
  "properties": {
    "gn:admin1_code":"18",
    "gn:admin2_code":"1802.0",
    "gn:admin3_code":"180211.0",
    "gn:asciiname":"Sucanaya",
    "gn:country_code":"PE",
    "gn:dem":4550,
    "gn:feature_class":"P",
    "gn:feature_code":"PPL",
    "gn:name":"Sucanaya",
    "gn:population":0,
    "gn:timezone":"America/Lima",
    "iso:country":"PE",
    "wof:name":"Sucanaya",
    "wof:placetype":"locality"
},
  "geometry": {"coordinates":[-70.63535,-16.25792],"type":"Point"}
}