{
  "type": "Feature",
  "properties": {
    "gn:admin1_code":"02",
    "gn:admin2_code":"214.0",
    "gn:admin3_code":"21401.0",
    "gn:asciiname":"Lacchas",
    "gn:country_code":"PE",
    "gn:dem":2326,
    "gn:feature_class":"P",
    "gn:feature_code":"PPL",
    "gn:name":"Lacchas",
    "gn:population":0,
    "gn:timezone":"America/Lima",
    "iso:country":"PE",
    "wof:name":"Lacchas",
    "wof:placetype":"locality"
},
  "geometry": {"coordinates":[-77.43601,-10.46574],"type":"Point"}
}