{
  "type": "Feature",
  "properties": {
    "gn:admin1_code":"2.0",
    "gn:admin2_code":"220.0",
    "gn:admin3_code":"22002.0",
    "gn:asciiname":"Concepcion",
    "gn:country_code":"PE",
    "gn:dem":3524,
    "gn:feature_class":"P",
    "gn:feature_code":"PPL",
    "gn:name":"Concepci\u00f3n",
    "gn:population":0,
    "gn:timezone":"America/Lima",
    "iso:country":"PE",
    "wof:name":"Concepcion",
    "wof:placetype":"locality"
},
  "geometry": {"coordinates":[-77.88389000000002,-9.38694],"type":"Point"}
}