{
  "type": "Feature",
  "properties": {
    "gn:admin1_code":"21",
    "gn:admin2_code":"2106.0",
    "gn:admin3_code":"210607.0",
    "gn:asciiname":"Puquis",
    "gn:country_code":"PE",
    "gn:dem":3820,
    "gn:feature_class":"P",
    "gn:feature_code":"PPL",
    "gn:name":"Puqu\u00eds",
    "gn:population":0,
    "gn:timezone":"America/Lima",
    "iso:country":"PE",
    "wof:name":"Puquis",
    "wof:placetype":"locality"
},
  "geometry": {"coordinates":[-69.92650999999999,-15.27501],"type":"Point"}
}