{
  "type": "Feature",
  "properties": {
    "gn:admin1_code":"20",
    "gn:admin2_code":"2004.0",
    "gn:admin3_code":"200410.0",
    "gn:asciiname":"Confeccionario",
    "gn:country_code":"PE",
    "gn:dem":3088,
    "gn:feature_class":"P",
    "gn:feature_code":"PPL",
    "gn:name":"Confeccionario",
    "gn:population":0,
    "gn:timezone":"America/Lima",
    "iso:country":"PE",
    "wof:name":"Confeccionario",
    "wof:placetype":"locality"
},
  "geometry": {"coordinates":[-79.6853,-5.09144],"type":"Point"}
}