{
  "type": "Feature",
  "properties": {
    "gn:admin1_code":"09",
    "gn:admin2_code":"903.0",
    "gn:admin3_code":"90306.0",
    "gn:asciiname":"Eccana",
    "gn:country_code":"PE",
    "gn:dem":3420,
    "gn:feature_class":"P",
    "gn:feature_code":"PPL",
    "gn:name":"Eccana",
    "gn:population":0,
    "gn:timezone":"America/Lima",
    "iso:country":"PE",
    "wof:name":"Eccana",
    "wof:placetype":"locality"
},
  "geometry": {"coordinates":[-74.48873,-13.03672],"type":"Point"}
}