{
  "type": "Feature",
  "properties": {
    "gn:admin1_code":"08",
    "gn:admin2_code":"809.0",
    "gn:admin3_code":"80909.0",
    "gn:asciiname":"Espiritupampa",
    "gn:country_code":"PE",
    "gn:dem":989,
    "gn:feature_class":"P",
    "gn:feature_code":"PPL",
    "gn:name":"Espiritupampa",
    "gn:population":0,
    "gn:timezone":"America/Lima",
    "iso:country":"PE",
    "wof:name":"Espiritupampa",
    "wof:placetype":"locality"
},
  "geometry": {"coordinates":[-73.42833,-13.11444],"type":"Point"}
}