{
  "type": "Feature",
  "properties": {
    "gn:admin1_code":"04",
    "gn:admin2_code":"405.0",
    "gn:admin3_code":"40515.0",
    "gn:asciiname":"Chichihuiri",
    "gn:country_code":"PE",
    "gn:dem":4475,
    "gn:feature_class":"P",
    "gn:feature_code":"PPL",
    "gn:name":"Chichihuiri",
    "gn:population":0,
    "gn:timezone":"America/Lima",
    "iso:country":"PE",
    "wof:name":"Chichihuiri",
    "wof:placetype":"locality"
},
  "geometry": {"coordinates":[-71.51756999999998,-15.42918],"type":"Point"}
}