{
  "type": "Feature",
  "properties": {
    "gn:admin1_code":"4",
    "gn:admin2_code":"405.0",
    "gn:admin3_code":"40504.0",
    "gn:asciiname":"Veluyo",
    "gn:country_code":"PE",
    "gn:dem":4444,
    "gn:feature_class":"P",
    "gn:feature_code":"PPL",
    "gn:name":"Veluyo",
    "gn:population":0,
    "gn:timezone":"America/Lima",
    "iso:country":"PE",
    "wof:name":"Veluyo",
    "wof:placetype":"locality"
},
  "geometry": {"coordinates":[-71.04167,-15.60111],"type":"Point"}
}