{
  "type": "Feature",
  "properties": {
    "gn:admin1_code":"13",
    "gn:admin2_code":"1303.0",
    "gn:admin3_code":"130302.0",
    "gn:asciiname":"Calemar",
    "gn:country_code":"PE",
    "gn:dem":1150,
    "gn:feature_class":"P",
    "gn:feature_code":"PPL",
    "gn:name":"Calemar",
    "gn:population":0,
    "gn:timezone":"America/Lima",
    "iso:country":"PE",
    "wof:name":"Calemar",
    "wof:placetype":"locality"
},
  "geometry": {"coordinates":[-77.72556999999998,-7.51569],"type":"Point"}
}