{
  "type": "Feature",
  "properties": {
    "gn:admin1_code":"11",
    "gn:admin2_code":"1103.0",
    "gn:admin3_code":"110303.0",
    "gn:asciiname":"Hacienda Condonya",
    "gn:country_code":"PE",
    "gn:dem":845,
    "gn:feature_class":"P",
    "gn:feature_code":"PPL",
    "gn:name":"Hacienda Condonya",
    "gn:population":0,
    "gn:timezone":"America/Lima",
    "iso:country":"PE",
    "name:spa_x_preferred":[
        "Hacienda Condonya"
    ],
    "name:spa_x_variant":[
        "Condonya"
    ],
    "wof:name":"Hacienda Condonya",
    "wof:placetype":"locality"
},
  "geometry": {"coordinates":[-74.91804999999999,-14.60541],"type":"Point"}
}