{
  "type": "Feature",
  "properties": {
    "gn:admin1_code":"12.0",
    "gn:admin2_code":"1208.0",
    "gn:admin3_code":"120802.0",
    "gn:asciiname":"Chugupampa",
    "gn:country_code":"PE",
    "gn:dem":4466,
    "gn:feature_class":"P",
    "gn:feature_code":"PPL",
    "gn:name":"Chugupampa",
    "gn:population":0,
    "gn:timezone":"America/Lima",
    "iso:country":"PE",
    "wof:name":"Chugupampa",
    "wof:placetype":"locality"
},
  "geometry": {"coordinates":[-75.85763,-11.74622],"type":"Point"}
}