{
  "type": "Feature",
  "properties": {
    "gn:admin1_code":"14",
    "gn:admin2_code":"1401.0",
    "gn:admin3_code":"140110.0",
    "gn:asciiname":"Hacienda Gramadal",
    "gn:country_code":"PE",
    "gn:dem":205,
    "gn:feature_class":"P",
    "gn:feature_code":"PPL",
    "gn:name":"Hacienda Gramadal",
    "gn:population":0,
    "gn:timezone":"America/Lima",
    "iso:country":"PE",
    "name:spa_x_preferred":[
        "Hacienda Gramadal"
    ],
    "wof:name":"Hacienda Gramadal",
    "wof:placetype":"locality"
},
  "geometry": {"coordinates":[-79.30516999999998,-6.85143],"type":"Point"}
}