{
  "type": "Feature",
  "properties": {
    "gn:admin1_code":"18",
    "gn:admin2_code":"1801.0",
    "gn:admin3_code":"180106.0",
    "gn:asciiname":"Estupe",
    "gn:country_code":"PE",
    "gn:dem":3672,
    "gn:feature_class":"P",
    "gn:feature_code":"PPL",
    "gn:name":"Estupe",
    "gn:population":0,
    "gn:timezone":"America/Lima",
    "iso:country":"PE",
    "wof:name":"Estupe",
    "wof:placetype":"locality"
},
  "geometry": {"coordinates":[-70.80825,-16.88812],"type":"Point"}
}