{
  "type": "Feature",
  "properties": {
    "gn:admin1_code":"4.0",
    "gn:admin2_code":"401.0",
    "gn:admin3_code":"40117.0",
    "gn:asciiname":"Alata",
    "gn:country_code":"PE",
    "gn:dem":2212,
    "gn:feature_class":"P",
    "gn:feature_code":"PPL",
    "gn:name":"Alata",
    "gn:population":0,
    "gn:timezone":"America/Lima",
    "iso:country":"PE",
    "wof:name":"Alata",
    "wof:placetype":"locality"
},
  "geometry": {"coordinates":[-71.57585,-16.43803],"type":"Point"}
}