{
  "type": "Feature",
  "properties": {
    "gn:admin1_code":"06",
    "gn:admin2_code":"606.0",
    "gn:admin3_code":"60615.0",
    "gn:asciiname":"Panama",
    "gn:country_code":"PE",
    "gn:dem":1280,
    "gn:feature_class":"P",
    "gn:feature_code":"PPL",
    "gn:name":"Panam\u00e1",
    "gn:population":0,
    "gn:timezone":"America/Lima",
    "iso:country":"PE",
    "wof:name":"Panama",
    "wof:placetype":"locality"
},
  "geometry": {"coordinates":[-78.73486,-6.00583],"type":"Point"}
}