{
  "type": "Feature",
  "properties": {
    "gn:admin1_code":"17.0",
    "gn:admin2_code":"1703.0",
    "gn:asciiname":"Republica",
    "gn:country_code":"PE",
    "gn:dem":278,
    "gn:feature_class":"P",
    "gn:feature_code":"PPL",
    "gn:name":"Republica",
    "gn:population":0,
    "gn:timezone":"America/Lima",
    "iso:country":"PE",
    "name:ces_x_preferred":[
        "Republica"
    ],
    "name:dan_x_preferred":[
        "Republica"
    ],
    "name:deu_x_preferred":[
        "Republica"
    ],
    "name:fin_x_preferred":[
        "Republica"
    ],
    "name:fra_x_preferred":[
        "Republica"
    ],
    "name:ita_x_preferred":[
        "Republica"
    ],
    "name:nld_x_preferred":[
        "Republica"
    ],
    "name:pol_x_preferred":[
        "Republica"
    ],
    "name:rus_x_preferred":[
        "Republica"
    ],
    "name:slk_x_preferred":[
        "Republica"
    ],
    "name:spa_x_preferred":[
        "Republica"
    ],
    "name:swe_x_preferred":[
        "Republica"
    ],
    "wof:name":"Republica",
    "wof:placetype":"locality"
},
  "geometry": {"coordinates":[-69.46151999999999,-11.3182],"type":"Point"}
}