{
  "type": "Feature",
  "properties": {
    "gn:admin1_code":"02",
    "gn:admin2_code":"214.0",
    "gn:admin3_code":"21402.0",
    "gn:asciiname":"Tunas",
    "gn:country_code":"PE",
    "gn:dem":2028,
    "gn:feature_class":"P",
    "gn:feature_code":"PPL",
    "gn:name":"Tunas",
    "gn:population":0,
    "gn:timezone":"America/Lima",
    "iso:country":"PE",
    "wof:name":"Tunas",
    "wof:placetype":"locality"
},
  "geometry": {"coordinates":[-77.30209000000001,-10.48978],"type":"Point"}
}