{
  "type": "Feature",
  "properties": {
    "gn:admin1_code":"02",
    "gn:admin2_code":"215.0",
    "gn:admin3_code":"21510.0",
    "gn:asciiname":"Cocabal",
    "gn:country_code":"PE",
    "gn:dem":1451,
    "gn:feature_class":"P",
    "gn:feature_code":"PPL",
    "gn:name":"Cocabal",
    "gn:population":0,
    "gn:timezone":"America/Lima",
    "iso:country":"PE",
    "wof:name":"Cocabal",
    "wof:placetype":"locality"
},
  "geometry": {"coordinates":[-78.1301,-8.49827],"type":"Point"}
}