{
  "type": "Feature",
  "properties": {
    "gn:admin1_code":"8",
    "gn:admin2_code":"808.0",
    "gn:admin3_code":"80803.0",
    "gn:asciiname":"Itonuo",
    "gn:country_code":"PE",
    "gn:dem":3989,
    "gn:feature_class":"P",
    "gn:feature_code":"PPL",
    "gn:name":"Ito\u00f1uo",
    "gn:population":0,
    "gn:timezone":"America/Lima",
    "iso:country":"PE",
    "wof:name":"Itonuo",
    "wof:placetype":"locality"
},
  "geometry": {"coordinates":[-71.52450999999998,-14.91901],"type":"Point"}
}