{
  "type": "Feature",
  "properties": {
    "gn:admin1_code":"22.0",
    "gn:admin2_code":"2202.0",
    "gn:admin3_code":"220204.0",
    "gn:asciiname":"Ledoy",
    "gn:country_code":"PE",
    "gn:dem":262,
    "gn:feature_class":"P",
    "gn:feature_code":"PPLA3",
    "gn:name":"Ledoy",
    "gn:population":0,
    "gn:timezone":"America/Lima",
    "iso:country":"PE",
    "wof:name":"Ledoy",
    "wof:placetype":"locality"
},
  "geometry": {"coordinates":[-76.65018000000001,-7.12823],"type":"Point"}
}