{
  "type": "Feature",
  "properties": {
    "gn:admin1_code":"4",
    "gn:admin2_code":"406.0",
    "gn:admin3_code":"40602.0",
    "gn:asciiname":"Huajaja",
    "gn:country_code":"PE",
    "gn:dem":3020,
    "gn:feature_class":"P",
    "gn:feature_code":"PPL",
    "gn:name":"Huajaja",
    "gn:population":0,
    "gn:timezone":"America/Lima",
    "iso:country":"PE",
    "wof:name":"Huajaja",
    "wof:placetype":"locality"
},
  "geometry": {"coordinates":[-72.84724,-15.81879],"type":"Point"}
}