{
  "type": "Feature",
  "properties": {
    "gn:admin1_code":"21",
    "gn:admin2_code":"2104.0",
    "gn:admin3_code":"210406.0",
    "gn:asciiname":"Putu Huma",
    "gn:country_code":"PE",
    "gn:dem":3841,
    "gn:feature_class":"P",
    "gn:feature_code":"PPL",
    "gn:name":"Putu Huma",
    "gn:population":0,
    "gn:timezone":"America/Lima",
    "iso:country":"PE",
    "wof:name":"Putu Huma",
    "wof:placetype":"locality"
},
  "geometry": {"coordinates":[-69.28869,-16.33297],"type":"Point"}
}