{
  "type": "Feature",
  "properties": {
    "gn:admin1_code":"05",
    "gn:admin2_code":"507.0",
    "gn:admin3_code":"50706.0",
    "gn:asciiname":"Santa Catalina",
    "gn:country_code":"PE",
    "gn:dem":3299,
    "gn:feature_class":"P",
    "gn:feature_code":"PPL",
    "gn:name":"Santa Catalina",
    "gn:population":0,
    "gn:timezone":"America/Lima",
    "iso:country":"PE",
    "wof:name":"Santa Catalina",
    "wof:placetype":"locality"
},
  "geometry": {"coordinates":[-73.73333000000002,-15.23333],"type":"Point"}
}