{
  "type": "Feature",
  "properties": {
    "gn:admin1_code":"21",
    "gn:admin2_code":"2112",
    "gn:asciiname":"Calapampa",
    "gn:country_code":"PE",
    "gn:dem":1180,
    "gn:feature_class":"P",
    "gn:feature_code":"PPL",
    "gn:name":"Calapampa",
    "gn:population":0,
    "gn:timezone":"America/Lima",
    "iso:country":"PE",
    "name:spa_x_preferred":[
        "Calapampa"
    ],
    "wof:name":"Calapampa",
    "wof:placetype":"locality"
},
  "geometry": {"coordinates":[-69.53017,-13.9074],"type":"Point"}
}