{
  "type": "Feature",
  "properties": {
    "gn:admin1_code":"12",
    "gn:admin2_code":"1203.0",
    "gn:admin3_code":"120303.0",
    "gn:asciiname":"Pampa Julian",
    "gn:country_code":"PE",
    "gn:dem":746,
    "gn:feature_class":"P",
    "gn:feature_code":"PPL",
    "gn:name":"Pampa Juli\u00e1n",
    "gn:population":0,
    "gn:timezone":"America/Lima",
    "iso:country":"PE",
    "name:spa_x_preferred":[
        "Pampa Juli\u00e1n"
    ],
    "wof:name":"Pampa Julian",
    "wof:placetype":"locality"
},
  "geometry": {"coordinates":[-74.82169,-10.913],"type":"Point"}
}