{
  "type": "Feature",
  "properties": {
    "gn:admin1_code":"2.0",
    "gn:admin2_code":"214.0",
    "gn:admin3_code":"21401.0",
    "gn:asciiname":"Huancachacra",
    "gn:country_code":"PE",
    "gn:dem":3208,
    "gn:feature_class":"P",
    "gn:feature_code":"PPL",
    "gn:name":"Huancachacra",
    "gn:population":0,
    "gn:timezone":"America/Lima",
    "iso:country":"PE",
    "wof:name":"Huancachacra",
    "wof:placetype":"locality"
},
  "geometry": {"coordinates":[-77.41202,-10.40765],"type":"Point"}
}