{
  "type": "Feature",
  "properties": {
    "gn:admin1_code":"10.0",
    "gn:admin2_code":"1001.0",
    "gn:admin3_code":"100110.0",
    "gn:asciiname":"Pampamarca",
    "gn:country_code":"PE",
    "gn:dem":3364,
    "gn:feature_class":"P",
    "gn:feature_code":"PPL",
    "gn:name":"Pampamarca",
    "gn:population":0,
    "gn:timezone":"America/Lima",
    "iso:country":"PE",
    "wof:name":"Pampamarca",
    "wof:placetype":"locality"
},
  "geometry": {"coordinates":[-76.48115,-9.98483],"type":"Point"}
}