{
  "type": "Feature",
  "properties": {
    "gn:admin1_code":"09",
    "gn:admin2_code":"906.0",
    "gn:admin3_code":"90607.0",
    "gn:asciiname":"Puruchuco",
    "gn:country_code":"PE",
    "gn:dem":4296,
    "gn:feature_class":"P",
    "gn:feature_code":"PPL",
    "gn:name":"Puruchuco",
    "gn:population":0,
    "gn:timezone":"America/Lima",
    "iso:country":"PE",
    "name:fra_x_preferred":[
        "Puruchuco"
    ],
    "name:ita_x_preferred":[
        "Puruchuco"
    ],
    "name:kat_x_preferred":[
        "\u10de\u10e3\u10e0\u10e3\u10e9\u10e3\u10d9\u10dd"
    ],
    "name:que_x_preferred":[
        "Puruchuqu"
    ],
    "name:rus_x_preferred":[
        "\u041f\u0443\u0440\u0443\u0447\u0443\u043a\u043e"
    ],
    "name:spa_x_preferred":[
        "Puruchuco"
    ],
    "name:swe_x_preferred":[
        "Puruchuco"
    ],
    "wof:name":"Puruchuco",
    "wof:placetype":"locality"
},
  "geometry": {"coordinates":[-74.90944,-13.54137],"type":"Point"}
}