{
  "type": "Feature",
  "properties": {
    "gn:admin1_code":"9.0",
    "gn:admin2_code":"905.0",
    "gn:admin3_code":"90503.0",
    "gn:asciiname":"Pilata",
    "gn:country_code":"PE",
    "gn:dem":2813,
    "gn:feature_class":"P",
    "gn:feature_code":"PPL",
    "gn:name":"Pilata",
    "gn:population":0,
    "gn:timezone":"America/Lima",
    "iso:country":"PE",
    "wof:name":"Pilata",
    "wof:placetype":"locality"
},
  "geometry": {"coordinates":[-74.54621999999998,-12.50755],"type":"Point"}
}