{
  "type": "Feature",
  "properties": {
    "gn:admin1_code":"02",
    "gn:admin2_code":"211.0",
    "gn:admin3_code":"21101.0",
    "gn:asciiname":"Tuquillo",
    "gn:country_code":"PE",
    "gn:dem":11,
    "gn:feature_class":"P",
    "gn:feature_code":"PPL",
    "gn:name":"Tuquillo",
    "gn:population":0,
    "gn:timezone":"America/Lima",
    "iso:country":"PE",
    "name:und_x_variant":[
        "Tuquilla"
    ],
    "wof:name":"Tuquillo",
    "wof:placetype":"locality"
},
  "geometry": {"coordinates":[-78.1904,-10.015],"type":"Point"}
}