{
  "type": "Feature",
  "properties": {
    "gn:admin1_code":"15.0",
    "gn:admin2_code":"1507.0",
    "gn:admin3_code":"150716.0",
    "gn:asciiname":"Vado",
    "gn:country_code":"PE",
    "gn:dem":1888,
    "gn:feature_class":"P",
    "gn:feature_code":"PPL",
    "gn:name":"Vado",
    "gn:population":0,
    "gn:timezone":"America/Lima",
    "iso:country":"PE",
    "name:spa_x_preferred":[
        "Vado"
    ],
    "wof:name":"Vado",
    "wof:placetype":"locality"
},
  "geometry": {"coordinates":[-76.62146,-11.7806],"type":"Point"}
}