{
  "type": "Feature",
  "properties": {
    "gn:admin1_code":"3",
    "gn:admin2_code":"304.0",
    "gn:admin3_code":"30411.0",
    "gn:asciiname":"Huasquicha",
    "gn:country_code":"PE",
    "gn:dem":2668,
    "gn:feature_class":"P",
    "gn:feature_code":"PPL",
    "gn:name":"Huasquicha",
    "gn:population":0,
    "gn:timezone":"America/Lima",
    "iso:country":"PE",
    "wof:name":"Huasquicha",
    "wof:placetype":"locality"
},
  "geometry": {"coordinates":[-73.17194000000001,-13.93917],"type":"Point"}
}