{
  "type": "Feature",
  "properties": {
    "gn:admin1_code":"12",
    "gn:admin2_code":"1207.0",
    "gn:admin3_code":"120707.0",
    "gn:asciiname":"Shoclacancha",
    "gn:country_code":"PE",
    "gn:dem":4195,
    "gn:feature_class":"P",
    "gn:feature_code":"PPL",
    "gn:name":"Shoclacancha",
    "gn:population":0,
    "gn:timezone":"America/Lima",
    "iso:country":"PE",
    "wof:name":"Shoclacancha",
    "wof:placetype":"locality"
},
  "geometry": {"coordinates":[-75.84696,-11.3173],"type":"Point"}
}