{
  "type": "Feature",
  "properties": {
    "gn:admin1_code":"25",
    "gn:admin2_code":"2501.0",
    "gn:admin3_code":"250104.0",
    "gn:asciiname":"Vinoncuro",
    "gn:country_code":"PE",
    "gn:dem":164,
    "gn:feature_class":"P",
    "gn:feature_code":"PPL",
    "gn:name":"Vinoncuro",
    "gn:population":0,
    "gn:timezone":"America/Lima",
    "iso:country":"PE",
    "wof:name":"Vinoncuro",
    "wof:placetype":"locality"
},
  "geometry": {"coordinates":[-74.02611,-8.8575],"type":"Point"}
}