{
  "type": "Feature",
  "properties": {
    "gn:admin1_code":"19",
    "gn:admin2_code":"1902.0",
    "gn:admin3_code":"190206.0",
    "gn:asciiname":"Machin",
    "gn:country_code":"PE",
    "gn:dem":4209,
    "gn:feature_class":"P",
    "gn:feature_code":"PPL",
    "gn:name":"Mach\u00edn",
    "gn:population":0,
    "gn:timezone":"America/Lima",
    "iso:country":"PE",
    "name:deu_x_preferred":[
        "Machin"
    ],
    "name:fra_x_preferred":[
        "Machin"
    ],
    "name:pol_x_preferred":[
        "Machin"
    ],
    "name:rus_x_preferred":[
        "\u041c\u0430\u0448\u0435\u043d"
    ],
    "name:spa_x_preferred":[
        "Machin"
    ],
    "wof:name":"Machin",
    "wof:placetype":"locality"
},
  "geometry": {"coordinates":[-76.36521,-10.41441],"type":"Point"}
}