{
  "type": "Feature",
  "properties": {
    "gn:admin1_code":"06",
    "gn:admin2_code":"612.0",
    "gn:admin3_code":"61204.0",
    "gn:asciiname":"Granja Porcon",
    "gn:country_code":"PE",
    "gn:dem":3130,
    "gn:feature_class":"P",
    "gn:feature_code":"PPL",
    "gn:name":"Granja Porc\u00f3n",
    "gn:population":0,
    "gn:timezone":"America/Lima",
    "iso:country":"PE",
    "wof:name":"Granja Porcon",
    "wof:placetype":"locality"
},
  "geometry": {"coordinates":[-78.63379999999999,-7.0358],"type":"Point"}
}