{
  "type": "Feature",
  "properties": {
    "gn:admin1_code":"05",
    "gn:admin2_code":"501.0",
    "gn:admin3_code":"50111.0",
    "gn:asciiname":"Ocana",
    "gn:country_code":"PE",
    "gn:dem":3178,
    "gn:feature_class":"P",
    "gn:feature_code":"PPL",
    "gn:name":"Oca\u00f1a",
    "gn:population":0,
    "gn:timezone":"America/Lima",
    "iso:country":"PE",
    "wof:name":"Ocana",
    "wof:placetype":"locality"
},
  "geometry": {"coordinates":[-74.3784,-13.04506],"type":"Point"}
}