{
  "type": "Feature",
  "properties": {
    "gn:admin1_code":"9.0",
    "gn:admin2_code":"903.0",
    "gn:admin3_code":"90304.0",
    "gn:asciiname":"Jihuajasa",
    "gn:country_code":"PE",
    "gn:dem":4143,
    "gn:feature_class":"P",
    "gn:feature_code":"PPL",
    "gn:name":"Jihuajasa",
    "gn:population":0,
    "gn:timezone":"America/Lima",
    "iso:country":"PE",
    "wof:name":"Jihuajasa",
    "wof:placetype":"locality"
},
  "geometry": {"coordinates":[-74.7664,-12.88498],"type":"Point"}
}