{
  "type": "Feature",
  "properties": {
    "gn:admin1_code":"5.0",
    "gn:admin2_code":"504.0",
    "gn:admin3_code":"50405.0",
    "gn:asciiname":"Condor Senja",
    "gn:country_code":"PE",
    "gn:dem":3435,
    "gn:feature_class":"P",
    "gn:feature_code":"PPL",
    "gn:name":"Condor Senja",
    "gn:population":0,
    "gn:timezone":"America/Lima",
    "iso:country":"PE",
    "wof:name":"Condor Senja",
    "wof:placetype":"locality"
},
  "geometry": {"coordinates":[-74.27457,-12.81431],"type":"Point"}
}