{
  "type": "Feature",
  "properties": {
    "gn:admin1_code":"16.0",
    "gn:admin2_code":"1606.0",
    "gn:asciiname":"Shanaillo",
    "gn:country_code":"PE",
    "gn:dem":129,
    "gn:feature_class":"P",
    "gn:feature_code":"PPL",
    "gn:name":"Shanaillo",
    "gn:population":0,
    "gn:timezone":"America/Lima",
    "iso:country":"PE",
    "name:spa_x_preferred":[
        "Shanaillo"
    ],
    "wof:name":"Shanaillo",
    "wof:placetype":"locality"
},
  "geometry": {"coordinates":[-75.11731,-7.22548],"type":"Point"}
}