{
  "type": "Feature",
  "properties": {
    "gn:admin1_code":"14.0",
    "gn:admin2_code":"1401.0",
    "gn:admin3_code":"140117.0",
    "gn:asciiname":"La Concordia",
    "gn:country_code":"PE",
    "gn:dem":93,
    "gn:feature_class":"P",
    "gn:feature_code":"PPL",
    "gn:name":"La Concordia",
    "gn:population":0,
    "gn:timezone":"America/Lima",
    "iso:country":"PE",
    "name:ceb_x_preferred":[
        "La Concordia"
    ],
    "name:deu_x_preferred":[
        "La Concordia"
    ],
    "name:nld_x_preferred":[
        "La Concordia"
    ],
    "name:rus_x_preferred":[
        "\u041b\u0430-\u041a\u043e\u043d\u043a\u043e\u0440\u0434\u0438\u044f"
    ],
    "name:sco_x_preferred":[
        "La Concordia"
    ],
    "name:spa_x_preferred":[
        "La Concordia"
    ],
    "name:swe_x_preferred":[
        "La Concordia"
    ],
    "wof:name":"La Concordia",
    "wof:placetype":"locality"
},
  "geometry": {"coordinates":[-79.64295,-6.73431],"type":"Point"}
}