{
  "type": "Feature",
  "properties": {
    "gn:admin1_code":"2.0",
    "gn:admin2_code":"212.0",
    "gn:admin3_code":"21201.0",
    "gn:asciiname":"Nueva Victoria",
    "gn:country_code":"PE",
    "gn:dem":2209,
    "gn:feature_class":"P",
    "gn:feature_code":"PPL",
    "gn:name":"Nueva Vict\u00f3ria",
    "gn:population":0,
    "gn:timezone":"America/Lima",
    "iso:country":"PE",
    "wof:name":"Nueva Victoria",
    "wof:placetype":"locality"
},
  "geometry": {"coordinates":[-77.83194,-9.03278],"type":"Point"}
}