{
  "type": "Feature",
  "properties": {
    "gn:admin1_code":"8",
    "gn:admin2_code":"806.0",
    "gn:admin3_code":"80601.0",
    "gn:asciiname":"Malcurumi",
    "gn:country_code":"PE",
    "gn:dem":3635,
    "gn:feature_class":"P",
    "gn:feature_code":"PPL",
    "gn:name":"Malcurumi",
    "gn:population":0,
    "gn:timezone":"America/Lima",
    "iso:country":"PE",
    "wof:name":"Malcurumi",
    "wof:placetype":"locality"
},
  "geometry": {"coordinates":[-71.20708,-14.24364],"type":"Point"}
}