{
  "type": "Feature",
  "properties": {
    "gn:admin1_code":"9.0",
    "gn:admin2_code":"907.0",
    "gn:admin3_code":"90717.0",
    "gn:asciiname":"Mio Huacta",
    "gn:country_code":"PE",
    "gn:dem":2775,
    "gn:feature_class":"P",
    "gn:feature_code":"PPL",
    "gn:name":"Mio Huacta",
    "gn:population":0,
    "gn:timezone":"America/Lima",
    "iso:country":"PE",
    "wof:name":"Mio Huacta",
    "wof:placetype":"locality"
},
  "geometry": {"coordinates":[-74.65744000000002,-12.12221],"type":"Point"}
}