{
  "type": "Feature",
  "properties": {
    "gn:admin1_code":"13",
    "gn:admin2_code":"1311.0",
    "gn:admin3_code":"131103.0",
    "gn:asciiname":"Marmot",
    "gn:country_code":"PE",
    "gn:dem":2250,
    "gn:feature_class":"P",
    "gn:feature_code":"PPL",
    "gn:name":"Marmot",
    "gn:population":0,
    "gn:timezone":"America/Lima",
    "iso:country":"PE",
    "wof:name":"Marmot",
    "wof:placetype":"locality"
},
  "geometry": {"coordinates":[-78.62603,-7.71847],"type":"Point"}
}