{
  "type": "Feature",
  "properties": {
    "gn:admin1_code":"08",
    "gn:admin2_code":"811.0",
    "gn:admin3_code":"81106.0",
    "gn:asciiname":"Cruz Pampa",
    "gn:country_code":"PE",
    "gn:dem":1318,
    "gn:feature_class":"P",
    "gn:feature_code":"PPL",
    "gn:name":"Cruz Pampa",
    "gn:population":0,
    "gn:timezone":"America/Lima",
    "iso:country":"PE",
    "wof:name":"Cruz Pampa",
    "wof:placetype":"locality"
},
  "geometry": {"coordinates":[-71.28333000000001,-13.08333],"type":"Point"}
}