{
  "type": "Feature",
  "properties": {
    "gn:admin1_code":"10.0",
    "gn:admin2_code":"1006.0",
    "gn:asciiname":"Jorge Basadre",
    "gn:country_code":"PE",
    "gn:dem":587,
    "gn:feature_class":"P",
    "gn:feature_code":"PPL",
    "gn:name":"Jorge Basadre",
    "gn:population":0,
    "gn:timezone":"America/Lima",
    "iso:country":"PE",
    "wof:name":"Jorge Basadre",
    "wof:placetype":"locality"
},
  "geometry": {"coordinates":[-76.12134,-8.67785],"type":"Point"}
}