{
  "type": "Feature",
  "properties": {
    "gn:admin1_code":"10.0",
    "gn:admin2_code":"1006.0",
    "gn:asciiname":"Jorge Basadre",
    "gn:country_code":"PE",
    "gn:dem":587,
    "gn:feature_class":"P",
    "gn:feature_code":"PPL",
    "gn:name":"Jorge Basadre",
    "gn:population":0,
    "gn:timezone":"America/Lima",
    "iso:country":"PE",
    "name:ara_x_preferred":[
        "\u062e\u0648\u0631\u062e\u064a \u0628\u0627\u0633\u0627\u062f\u0631\u064a"
    ],
    "name:aym_x_preferred":[
        "Jorge Basadre"
    ],
    "name:deu_x_preferred":[
        "Jorge Basadre Grohmann"
    ],
    "name:est_x_preferred":[
        "Jorge Basadre"
    ],
    "name:fra_x_preferred":[
        "Jorge Basadre"
    ],
    "name:ita_x_preferred":[
        "Jorge Basadre"
    ],
    "name:nah_x_preferred":[
        "Jorge Basadre"
    ],
    "name:por_x_preferred":[
        "Jorge Basadre"
    ],
    "name:que_x_preferred":[
        "Jorge Basadre"
    ],
    "name:rus_x_preferred":[
        "\u0411\u0430\u0441\u0430\u0434\u0440\u0435 \u0413\u0440\u043e\u043c\u0430\u043d\u043d"
    ],
    "name:spa_x_preferred":[
        "Jorge Basadre"
    ],
    "wof:name":"Jorge Basadre",
    "wof:placetype":"locality"
},
  "geometry": {"coordinates":[-76.12134,-8.67785],"type":"Point"}
}