{
  "type": "Feature",
  "properties": {
    "gn:admin1_code":"14",
    "gn:admin2_code":"1403.0",
    "gn:asciiname":"Vega del Padre",
    "gn:country_code":"PE",
    "gn:dem":91,
    "gn:feature_class":"P",
    "gn:feature_code":"PPL",
    "gn:name":"Vega del Padre",
    "gn:population":0,
    "gn:timezone":"America/Lima",
    "iso:country":"PE",
    "wof:name":"Vega del Padre",
    "wof:placetype":"locality"
},
  "geometry": {"coordinates":[-80.05858000000001,-5.81492],"type":"Point"}
}