{
  "type": "Feature",
  "properties": {
    "gn:admin1_code":"19",
    "gn:admin2_code":"1903.0",
    "gn:admin3_code":"190304.0",
    "gn:asciiname":"Puerto Clemente",
    "gn:country_code":"PE",
    "gn:dem":285,
    "gn:feature_class":"P",
    "gn:feature_code":"PPL",
    "gn:name":"Puerto Clemente",
    "gn:population":0,
    "gn:timezone":"America/Lima",
    "iso:country":"PE",
    "name:und_x_variant":[
        "Puerto Clement",
        "Puerto Clemente"
    ],
    "wof:name":"Puerto Clemente",
    "wof:placetype":"locality"
},
  "geometry": {"coordinates":[-75.24556,-10.02472],"type":"Point"}
}