{
  "type": "Feature",
  "properties": {
    "gn:admin1_code":"1.0",
    "gn:admin2_code":"101.0",
    "gn:admin3_code":"10106.0",
    "gn:asciiname":"Cochabamba",
    "gn:country_code":"PE",
    "gn:dem":2751,
    "gn:feature_class":"P",
    "gn:feature_code":"PPL",
    "gn:name":"Cochabamba",
    "gn:population":0,
    "gn:timezone":"America/Lima",
    "iso:country":"PE",
    "wof:name":"Cochabamba",
    "wof:placetype":"locality"
},
  "geometry": {"coordinates":[-77.90076999999999,-6.92736],"type":"Point"}
}