{
  "type": "Feature",
  "properties": {
    "gn:admin1_code":"06",
    "gn:admin2_code":"611.0",
    "gn:admin3_code":"61110.0",
    "gn:asciiname":"Palo Blanco",
    "gn:country_code":"PE",
    "gn:dem":474,
    "gn:feature_class":"P",
    "gn:feature_code":"PPL",
    "gn:name":"Palo Blanco",
    "gn:population":0,
    "gn:timezone":"America/Lima",
    "iso:country":"PE",
    "name:ceb_x_preferred":[
        "Palo Blanco"
    ],
    "name:spa_x_preferred":[
        "Palo blanco"
    ],
    "name:swe_x_preferred":[
        "Palo Blanco"
    ],
    "wof:name":"Palo Blanco",
    "wof:placetype":"locality"
},
  "geometry": {"coordinates":[-79.18116999999999,-7.13054],"type":"Point"}
}