{
  "type": "Feature",
  "properties": {
    "gn:admin1_code":"04",
    "gn:admin2_code":"406.0",
    "gn:admin3_code":"40606.0",
    "gn:asciiname":"Santa Catalina",
    "gn:country_code":"PE",
    "gn:dem":989,
    "gn:feature_class":"P",
    "gn:feature_code":"PPL",
    "gn:name":"Santa Catalina",
    "gn:population":0,
    "gn:timezone":"America/Lima",
    "iso:country":"PE",
    "wof:name":"Santa Catalina",
    "wof:placetype":"locality"
},
  "geometry": {"coordinates":[-73.00715,-15.8704],"type":"Point"}
}