{
  "type": "Feature",
  "properties": {
    "gn:admin1_code":"12",
    "gn:admin2_code":"1205.0",
    "gn:admin3_code":"120501.0",
    "gn:asciiname":"Picuicancha",
    "gn:country_code":"PE",
    "gn:dem":4244,
    "gn:feature_class":"P",
    "gn:feature_code":"PPL",
    "gn:name":"Picuicancha",
    "gn:population":0,
    "gn:timezone":"America/Lima",
    "iso:country":"PE",
    "wof:name":"Picuicancha",
    "wof:placetype":"locality"
},
  "geometry": {"coordinates":[-75.95388,-11.03282],"type":"Point"}
}