{
  "type": "Feature",
  "properties": {
    "gn:admin1_code":"20",
    "gn:admin2_code":"2006.0",
    "gn:admin3_code":"200601.0",
    "gn:asciiname":"El Bendito",
    "gn:country_code":"PE",
    "gn:dem":94,
    "gn:feature_class":"P",
    "gn:feature_code":"PPL",
    "gn:name":"El Bendito",
    "gn:population":0,
    "gn:timezone":"America/Lima",
    "iso:country":"PE",
    "wof:name":"El Bendito",
    "wof:placetype":"locality"
},
  "geometry": {"coordinates":[-80.69736,-4.94287],"type":"Point"}
}