{
  "type": "Feature",
  "properties": {
    "gn:admin1_code":"09",
    "gn:admin2_code":"904.0",
    "gn:admin3_code":"90413.0",
    "gn:asciiname":"Huachac",
    "gn:country_code":"PE",
    "gn:dem":1903,
    "gn:feature_class":"P",
    "gn:feature_code":"PPL",
    "gn:name":"Huachac",
    "gn:population":0,
    "gn:timezone":"America/Lima",
    "iso:country":"PE",
    "wof:name":"Huachac",
    "wof:placetype":"locality"
},
  "geometry": {"coordinates":[-75.46259000000001,-13.43316],"type":"Point"}
}