{
  "type": "Feature",
  "properties": {
    "gn:admin1_code":"02",
    "gn:admin2_code":"219.0",
    "gn:admin3_code":"21909.0",
    "gn:asciiname":"Sicsibamba",
    "gn:country_code":"PE",
    "gn:dem":3093,
    "gn:feature_class":"P",
    "gn:feature_code":"PPL",
    "gn:name":"Sicsibamba",
    "gn:population":0,
    "gn:timezone":"America/Lima",
    "iso:country":"PE",
    "wof:name":"Sicsibamba",
    "wof:placetype":"locality"
},
  "geometry": {"coordinates":[-77.57519000000001,-8.62224],"type":"Point"}
}