{
  "type": "Feature",
  "properties": {
    "gn:admin1_code":"2.0",
    "gn:admin2_code":"208.0",
    "gn:admin3_code":"20804.0",
    "gn:asciiname":"Chantri",
    "gn:country_code":"PE",
    "gn:dem":1847,
    "gn:feature_class":"P",
    "gn:feature_code":"PPL",
    "gn:name":"Chantri",
    "gn:population":0,
    "gn:timezone":"America/Lima",
    "iso:country":"PE",
    "wof:name":"Chantri",
    "wof:placetype":"locality"
},
  "geometry": {"coordinates":[-77.94221999999998,-9.45361],"type":"Point"}
}