{
  "type": "Feature",
  "properties": {
    "gn:admin1_code":"23.0",
    "gn:admin2_code":"2301.0",
    "gn:admin3_code":"230101.0",
    "gn:asciiname":"Almara",
    "gn:country_code":"PE",
    "gn:dem":544,
    "gn:feature_class":"P",
    "gn:feature_code":"PPL",
    "gn:name":"Almara",
    "gn:population":0,
    "gn:timezone":"America/Lima",
    "iso:country":"PE",
    "wof:name":"Almara",
    "wof:placetype":"locality"
},
  "geometry": {"coordinates":[-70.26056,-18.01889],"type":"Point"}
}