{
  "type": "Feature",
  "properties": {
    "gn:admin1_code":"12",
    "gn:admin2_code":"1203.0",
    "gn:admin3_code":"120305.0",
    "gn:asciiname":"Putaca",
    "gn:country_code":"PE",
    "gn:dem":3684,
    "gn:feature_class":"P",
    "gn:feature_code":"PPL",
    "gn:name":"Putaca",
    "gn:population":0,
    "gn:timezone":"America/Lima",
    "iso:country":"PE",
    "name:und_x_variant":[
        "Putacca",
        "Putaca"
    ],
    "wof:name":"Putaca",
    "wof:placetype":"locality"
},
  "geometry": {"coordinates":[-75.55595,-11.20048],"type":"Point"}
}