{
  "type": "Feature",
  "properties": {
    "gn:admin1_code":"05",
    "gn:admin2_code":"501.0",
    "gn:admin3_code":"50108.0",
    "gn:asciiname":"Sancapata",
    "gn:country_code":"PE",
    "gn:dem":3094,
    "gn:feature_class":"P",
    "gn:feature_code":"PPL",
    "gn:name":"Sancapata",
    "gn:population":0,
    "gn:timezone":"America/Lima",
    "iso:country":"PE",
    "wof:name":"Sancapata",
    "wof:placetype":"locality"
},
  "geometry": {"coordinates":[-74.13876999999999,-13.06122],"type":"Point"}
}