{
  "type": "Feature",
  "properties": {
    "gn:admin1_code":"19.0",
    "gn:admin2_code":"1902.0",
    "gn:admin3_code":"190201.0",
    "gn:asciiname":"Lacshacocha",
    "gn:country_code":"PE",
    "gn:dem":4307,
    "gn:feature_class":"P",
    "gn:feature_code":"PPL",
    "gn:name":"Lacshacocha",
    "gn:population":0,
    "gn:timezone":"America/Lima",
    "iso:country":"PE",
    "wof:name":"Lacshacocha",
    "wof:placetype":"locality"
},
  "geometry": {"coordinates":[-76.58917,-10.44972],"type":"Point"}
}