{
  "type": "Feature",
  "properties": {
    "gn:admin1_code":"2.0",
    "gn:admin2_code":"220.0",
    "gn:admin3_code":"22001.0",
    "gn:asciiname":"Piquip",
    "gn:country_code":"PE",
    "gn:dem":2505,
    "gn:feature_class":"P",
    "gn:feature_code":"PPL",
    "gn:name":"Piquip",
    "gn:population":0,
    "gn:timezone":"America/Lima",
    "iso:country":"PE",
    "wof:name":"Piquip",
    "wof:placetype":"locality"
},
  "geometry": {"coordinates":[-77.74806,-9.14861],"type":"Point"}
}