{
  "type": "Feature",
  "properties": {
    "gn:admin1_code":"9",
    "gn:admin2_code":"904.0",
    "gn:admin3_code":"90403.0",
    "gn:asciiname":"Antacancha",
    "gn:country_code":"PE",
    "gn:dem":3933,
    "gn:feature_class":"P",
    "gn:feature_code":"PPL",
    "gn:name":"Antacancha",
    "gn:population":0,
    "gn:timezone":"America/Lima",
    "iso:country":"PE",
    "wof:name":"Antacancha",
    "wof:placetype":"locality"
},
  "geometry": {"coordinates":[-75.52118,-12.99097],"type":"Point"}
}