{
  "type": "Feature",
  "properties": {
    "gn:admin1_code":"06",
    "gn:admin2_code":"608.0",
    "gn:admin3_code":"60810.0",
    "gn:asciiname":"Tayapampa",
    "gn:country_code":"PE",
    "gn:dem":2160,
    "gn:feature_class":"P",
    "gn:feature_code":"PPL",
    "gn:name":"Tayapampa",
    "gn:population":0,
    "gn:timezone":"America/Lima",
    "iso:country":"PE",
    "wof:name":"Tayapampa",
    "wof:placetype":"locality"
},
  "geometry": {"coordinates":[-79.29343,-5.80016],"type":"Point"}
}