{
  "type": "Feature",
  "properties": {
    "gn:admin1_code":"05",
    "gn:admin2_code":"510.0",
    "gn:admin3_code":"51005.0",
    "gn:asciiname":"Huancani",
    "gn:country_code":"PE",
    "gn:dem":3674,
    "gn:feature_class":"P",
    "gn:feature_code":"PPL",
    "gn:name":"Huancani",
    "gn:population":0,
    "gn:timezone":"America/Lima",
    "iso:country":"PE",
    "wof:name":"Huancani",
    "wof:placetype":"locality"
},
  "geometry": {"coordinates":[-73.94360999999998,-13.93056],"type":"Point"}
}