{
  "type": "Feature",
  "properties": {
    "gn:admin1_code":"17.0",
    "gn:admin2_code":"1701.0",
    "gn:asciiname":"Fray Martin",
    "gn:country_code":"PE",
    "gn:dem":277,
    "gn:feature_class":"P",
    "gn:feature_code":"PPL",
    "gn:name":"Fray Martin",
    "gn:population":0,
    "gn:timezone":"America/Lima",
    "iso:country":"PE",
    "name:spa_x_preferred":[
        "Fray Martin"
    ],
    "wof:name":"Fray Martin",
    "wof:placetype":"locality"
},
  "geometry": {"coordinates":[-69.13316999999999,-12.03327],"type":"Point"}
}