{
  "type": "Feature",
  "properties": {
    "gn:admin1_code":"4",
    "gn:admin2_code":"404.0",
    "gn:admin3_code":"40408.0",
    "gn:asciiname":"Callchi",
    "gn:country_code":"PE",
    "gn:dem":2502,
    "gn:feature_class":"P",
    "gn:feature_code":"PPL",
    "gn:name":"Callchi",
    "gn:population":0,
    "gn:timezone":"America/Lima",
    "iso:country":"PE",
    "wof:name":"Callchi",
    "wof:placetype":"locality"
},
  "geometry": {"coordinates":[-72.49391999999997,-15.65975],"type":"Point"}
}