{
  "type": "Feature",
  "properties": {
    "gn:admin1_code":"12.0",
    "gn:admin2_code":"1203.0",
    "gn:admin3_code":"120302.0",
    "gn:asciiname":"Miguel Grau",
    "gn:country_code":"PE",
    "gn:dem":1445,
    "gn:feature_class":"P",
    "gn:feature_code":"PPL",
    "gn:name":"Miguel Grau",
    "gn:population":0,
    "gn:timezone":"America/Lima",
    "iso:country":"PE",
    "name:spa_x_preferred":[
        "Miguel Grau"
    ],
    "wof:name":"Miguel Grau",
    "wof:placetype":"locality"
},
  "geometry": {"coordinates":[-75.08071,-10.80869],"type":"Point"}
}