{
  "type": "Feature",
  "properties": {
    "gn:admin1_code":"12",
    "gn:admin2_code":"1208.0",
    "gn:admin3_code":"120810.0",
    "gn:asciiname":"Magdalena",
    "gn:country_code":"PE",
    "gn:dem":4503,
    "gn:feature_class":"P",
    "gn:feature_code":"PPL",
    "gn:name":"Magdalena",
    "gn:population":0,
    "gn:timezone":"America/Lima",
    "iso:country":"PE",
    "wof:name":"Magdalena",
    "wof:placetype":"locality"
},
  "geometry": {"coordinates":[-76.14278,-11.67611],"type":"Point"}
}