{
  "type": "Feature",
  "properties": {
    "gn:admin1_code":"17.0",
    "gn:admin2_code":"1703.0",
    "gn:asciiname":"Cumaru",
    "gn:country_code":"PE",
    "gn:dem":322,
    "gn:feature_class":"P",
    "gn:feature_code":"PPL",
    "gn:name":"Cumaru",
    "gn:population":0,
    "gn:timezone":"America/Lima",
    "iso:country":"PE",
    "name:spa_x_preferred":[
        "Cumaru"
    ],
    "wof:name":"Cumaru",
    "wof:placetype":"locality"
},
  "geometry": {"coordinates":[-69.52865,-11.17493],"type":"Point"}
}