{
  "type": "Feature",
  "properties": {
    "gn:admin1_code":"09",
    "gn:admin2_code":"901.0",
    "gn:admin3_code":"90102.0",
    "gn:asciiname":"Martinhuasi",
    "gn:country_code":"PE",
    "gn:dem":4476,
    "gn:feature_class":"P",
    "gn:feature_code":"PPL",
    "gn:name":"Martinhuasi",
    "gn:population":0,
    "gn:timezone":"America/Lima",
    "iso:country":"PE",
    "wof:name":"Martinhuasi",
    "wof:placetype":"locality"
},
  "geometry": {"coordinates":[-75.41883,-12.70466],"type":"Point"}
}