{
  "type": "Feature",
  "properties": {
    "gn:admin1_code":"3",
    "gn:admin2_code":"307.0",
    "gn:admin3_code":"30709.0",
    "gn:asciiname":"San Antonio",
    "gn:country_code":"PE",
    "gn:dem":3655,
    "gn:feature_class":"P",
    "gn:feature_code":"PPLA3",
    "gn:name":"San Antonio",
    "gn:population":0,
    "gn:timezone":"America/Lima",
    "iso:country":"PE",
    "wof:name":"San Antonio",
    "wof:placetype":"locality"
},
  "geometry": {"coordinates":[-72.62111,-14.16472],"type":"Point"}
}