{
  "type": "Feature",
  "properties": {
    "gn:admin1_code":"12",
    "gn:admin2_code":"1203.0",
    "gn:admin3_code":"120303.0",
    "gn:asciiname":"Puerto Huachiriki",
    "gn:country_code":"PE",
    "gn:dem":479,
    "gn:feature_class":"P",
    "gn:feature_code":"PPLL",
    "gn:name":"Puerto Huachiriki",
    "gn:population":0,
    "gn:timezone":"America/Lima",
    "iso:country":"PE",
    "name:spa_x_preferred":[
        "Puerto Huachiriki"
    ],
    "wof:name":"Puerto Huachiriki",
    "wof:placetype":"locality"
},
  "geometry": {"coordinates":[-74.81079,-10.95489],"type":"Point"}
}