{
  "type": "Feature",
  "properties": {
    "gn:admin1_code":"05",
    "gn:admin2_code":"503.0",
    "gn:asciiname":"Chanlacnioc",
    "gn:country_code":"PE",
    "gn:dem":4558,
    "gn:feature_class":"P",
    "gn:feature_code":"PPL",
    "gn:name":"Chanlacnioc",
    "gn:population":0,
    "gn:timezone":"America/Lima",
    "iso:country":"PE",
    "wof:name":"Chanlacnioc",
    "wof:placetype":"locality"
},
  "geometry": {"coordinates":[-74.71319,-13.78722],"type":"Point"}
}