{
  "type": "Feature",
  "properties": {
    "gn:admin1_code":"21",
    "gn:admin2_code":"2101.0",
    "gn:admin3_code":"210102.0",
    "gn:asciiname":"Quenco",
    "gn:country_code":"PE",
    "gn:dem":3879,
    "gn:feature_class":"P",
    "gn:feature_code":"PPL",
    "gn:name":"Quenco",
    "gn:population":0,
    "gn:timezone":"America/Lima",
    "iso:country":"PE",
    "wof:name":"Quenco",
    "wof:placetype":"locality"
},
  "geometry": {"coordinates":[-69.76078000000001,-16.03523],"type":"Point"}
}