{
  "type": "Feature",
  "properties": {
    "gn:admin1_code":"23",
    "gn:admin2_code":"2302.0",
    "gn:admin3_code":"230203.0",
    "gn:asciiname":"Japo",
    "gn:country_code":"PE",
    "gn:dem":4201,
    "gn:feature_class":"P",
    "gn:feature_code":"PPL",
    "gn:name":"Japo",
    "gn:population":0,
    "gn:timezone":"America/Lima",
    "iso:country":"PE",
    "wof:name":"Japo",
    "wof:placetype":"locality"
},
  "geometry": {"coordinates":[-70.42639,-17.17527999999999],"type":"Point"}
}