{
  "type": "Feature",
  "properties": {
    "gn:admin1_code":"5",
    "gn:admin2_code":"506.0",
    "gn:admin3_code":"50606.0",
    "gn:asciiname":"Sarco",
    "gn:country_code":"PE",
    "gn:dem":4229,
    "gn:feature_class":"P",
    "gn:feature_code":"PPL",
    "gn:name":"Sarco",
    "gn:population":0,
    "gn:timezone":"America/Lima",
    "iso:country":"PE",
    "wof:name":"Sarco",
    "wof:placetype":"locality"
},
  "geometry": {"coordinates":[-73.73111,-14.41472],"type":"Point"}
}