{
  "type": "Feature",
  "properties": {
    "gn:admin1_code":"20.0",
    "gn:admin2_code":"2002.0",
    "gn:admin3_code":"200201.0",
    "gn:asciiname":"Cerro Las Cruces",
    "gn:country_code":"PE",
    "gn:dem":2590,
    "gn:feature_class":"P",
    "gn:feature_code":"PPL",
    "gn:name":"Cerro Las Cruces",
    "gn:population":0,
    "gn:timezone":"America/Lima",
    "iso:country":"PE",
    "wof:name":"Cerro Las Cruces",
    "wof:placetype":"locality"
},
  "geometry": {"coordinates":[-79.75145000000001,-4.62397],"type":"Point"}
}