{
  "type": "Feature",
  "properties": {
    "gn:admin1_code":"09",
    "gn:admin2_code":"903.0",
    "gn:admin3_code":"90311.0",
    "gn:asciiname":"Chaquiccpampa",
    "gn:country_code":"PE",
    "gn:dem":3299,
    "gn:feature_class":"P",
    "gn:feature_code":"PPL",
    "gn:name":"Chaquiccpampa",
    "gn:population":0,
    "gn:timezone":"America/Lima",
    "iso:country":"PE",
    "wof:name":"Chaquiccpampa",
    "wof:placetype":"locality"
},
  "geometry": {"coordinates":[-74.39010999999998,-13.16668],"type":"Point"}
}