{
  "type": "Feature",
  "properties": {
    "gn:admin1_code":"09",
    "gn:admin2_code":"906.0",
    "gn:admin3_code":"90608.0",
    "gn:asciiname":"uunchayoc",
    "gn:country_code":"PE",
    "gn:dem":3907,
    "gn:feature_class":"P",
    "gn:feature_code":"PPL",
    "gn:name":"uunchayoc",
    "gn:population":0,
    "gn:timezone":"America/Lima",
    "iso:country":"PE",
    "name:und_x_variant":[
        "Nunun Chayoc",
        "\u00d1u\u00f1unchayoc"
    ],
    "wof:name":"uunchayoc",
    "wof:placetype":"locality"
},
  "geometry": {"coordinates":[-74.86270999999998,-13.7855],"type":"Point"}
}