{
  "type": "Feature",
  "properties": {
    "gn:admin1_code":"13",
    "gn:admin2_code":"1309.0",
    "gn:admin3_code":"130901.0",
    "gn:asciiname":"Chisday",
    "gn:country_code":"PE",
    "gn:dem":3076,
    "gn:feature_class":"P",
    "gn:feature_code":"PPL",
    "gn:name":"Chisday",
    "gn:population":0,
    "gn:timezone":"America/Lima",
    "iso:country":"PE",
    "wof:name":"Chisday",
    "wof:placetype":"locality"
},
  "geometry": {"coordinates":[-78.01014000000001,-7.74991],"type":"Point"}
}