{
  "type": "Feature",
  "properties": {
    "gn:admin1_code":"03",
    "gn:admin2_code":"306.0",
    "gn:admin3_code":"30603.0",
    "gn:asciiname":"Sulcabamba",
    "gn:country_code":"PE",
    "gn:dem":2058,
    "gn:feature_class":"P",
    "gn:feature_code":"PPL",
    "gn:name":"Sulcabamba",
    "gn:population":0,
    "gn:timezone":"America/Lima",
    "iso:country":"PE",
    "wof:name":"Sulcabamba",
    "wof:placetype":"locality"
},
  "geometry": {"coordinates":[-73.73333000000002,-13.66667],"type":"Point"}
}