{
  "type": "Feature",
  "properties": {
    "gn:admin1_code":"10.0",
    "gn:admin2_code":"1005.0",
    "gn:admin3_code":"100508.0",
    "gn:asciiname":"Santa",
    "gn:country_code":"PE",
    "gn:dem":3279,
    "gn:feature_class":"P",
    "gn:feature_code":"PPL",
    "gn:name":"Santa",
    "gn:population":0,
    "gn:timezone":"America/Lima",
    "iso:country":"PE",
    "wof:name":"Santa",
    "wof:placetype":"locality"
},
  "geometry": {"coordinates":[-76.81614999999999,-9.46895],"type":"Point"}
}