{
  "type": "Feature",
  "properties": {
    "gn:admin1_code":"13",
    "gn:admin2_code":"1311.0",
    "gn:asciiname":"Sacha Grande",
    "gn:country_code":"PE",
    "gn:dem":2610,
    "gn:feature_class":"P",
    "gn:feature_code":"PPL",
    "gn:name":"Sacha Grande",
    "gn:population":0,
    "gn:timezone":"America/Lima",
    "iso:country":"PE",
    "wof:name":"Sacha Grande",
    "wof:placetype":"locality"
},
  "geometry": {"coordinates":[-78.40777,-7.58473],"type":"Point"}
}