{
  "type": "Feature",
  "properties": {
    "gn:admin1_code":"12",
    "gn:admin2_code":"1206.0",
    "gn:admin3_code":"120601.0",
    "gn:asciiname":"San Francisco",
    "gn:country_code":"PE",
    "gn:dem":1557,
    "gn:feature_class":"P",
    "gn:feature_code":"PPL",
    "gn:name":"San Francisco",
    "gn:population":0,
    "gn:timezone":"America/Lima",
    "iso:country":"PE",
    "wof:name":"San Francisco",
    "wof:placetype":"locality"
},
  "geometry": {"coordinates":[-74.55726999999997,-11.21027],"type":"Point"}
}