{
  "type": "Feature",
  "properties": {
    "gn:admin1_code":"06",
    "gn:admin2_code":"610.0",
    "gn:admin3_code":"61001.0",
    "gn:asciiname":"Vizcachas",
    "gn:country_code":"PE",
    "gn:dem":3526,
    "gn:feature_class":"P",
    "gn:feature_code":"PPL",
    "gn:name":"Vizcachas",
    "gn:population":0,
    "gn:timezone":"America/Lima",
    "iso:country":"PE",
    "wof:name":"Vizcachas",
    "wof:placetype":"locality"
},
  "geometry": {"coordinates":[-78.08306999999998,-7.28518],"type":"Point"}
}