{
  "type": "Feature",
  "properties": {
    "gn:admin1_code":"06",
    "gn:admin2_code":"603.0",
    "gn:admin3_code":"60304.0",
    "gn:asciiname":"Congona",
    "gn:country_code":"PE",
    "gn:dem":2951,
    "gn:feature_class":"P",
    "gn:feature_code":"PPL",
    "gn:name":"Congona",
    "gn:population":0,
    "gn:timezone":"America/Lima",
    "iso:country":"PE",
    "wof:name":"Congona",
    "wof:placetype":"locality"
},
  "geometry": {"coordinates":[-78.22203,-6.83207],"type":"Point"}
}