{
  "type": "Feature",
  "properties": {
    "gn:admin1_code":"12.0",
    "gn:admin2_code":"1202.0",
    "gn:admin3_code":"120210.0",
    "gn:asciiname":"Huampon",
    "gn:country_code":"PE",
    "gn:dem":3276,
    "gn:feature_class":"P",
    "gn:feature_code":"PPL",
    "gn:name":"Huampon",
    "gn:population":0,
    "gn:timezone":"America/Lima",
    "iso:country":"PE",
    "wof:name":"Huampon",
    "wof:placetype":"locality"
},
  "geometry": {"coordinates":[-75.35845,-11.88991],"type":"Point"}
}