{
  "type": "Feature",
  "properties": {
    "gn:admin1_code":"20",
    "gn:admin2_code":"2007.0",
    "gn:admin3_code":"200703.0",
    "gn:asciiname":"Planta Verdun",
    "gn:country_code":"PE",
    "gn:dem":61,
    "gn:feature_class":"P",
    "gn:feature_code":"PPL",
    "gn:name":"Planta Verdun",
    "gn:population":0,
    "gn:timezone":"America/Lima",
    "iso:country":"PE",
    "wof:name":"Planta Verdun",
    "wof:placetype":"locality"
},
  "geometry": {"coordinates":[-81.23971999999998,-4.62583],"type":"Point"}
}