{
  "type": "Feature",
  "properties": {
    "gn:admin1_code":"8.0",
    "gn:admin2_code":"803.0",
    "gn:admin3_code":"80306.0",
    "gn:asciiname":"Huaracaro",
    "gn:country_code":"PE",
    "gn:dem":3086,
    "gn:feature_class":"P",
    "gn:feature_code":"PPL",
    "gn:name":"Huaracaro",
    "gn:population":0,
    "gn:timezone":"America/Lima",
    "iso:country":"PE",
    "wof:name":"Huaracaro",
    "wof:placetype":"locality"
},
  "geometry": {"coordinates":[-72.43639,-13.44806],"type":"Point"}
}