{
  "type": "Feature",
  "properties": {
    "gn:admin1_code":"5.0",
    "gn:admin2_code":"504.0",
    "gn:admin3_code":"50401.0",
    "gn:asciiname":"Balconcucho",
    "gn:country_code":"PE",
    "gn:dem":4079,
    "gn:feature_class":"P",
    "gn:feature_code":"PPL",
    "gn:name":"Balconcucho",
    "gn:population":0,
    "gn:timezone":"America/Lima",
    "iso:country":"PE",
    "wof:name":"Balconcucho",
    "wof:placetype":"locality"
},
  "geometry": {"coordinates":[-74.20513000000003,-12.85099],"type":"Point"}
}