{
  "type": "Feature",
  "properties": {
    "gn:admin1_code":"21",
    "gn:admin2_code":"2105.0",
    "gn:admin3_code":"210504.0",
    "gn:asciiname":"Chinchillane",
    "gn:country_code":"PE",
    "gn:dem":4513,
    "gn:feature_class":"P",
    "gn:feature_code":"PPL",
    "gn:name":"Chinchillane",
    "gn:population":0,
    "gn:timezone":"America/Lima",
    "iso:country":"PE",
    "wof:name":"Chinchillane",
    "wof:placetype":"locality"
},
  "geometry": {"coordinates":[-69.93893,-16.99938],"type":"Point"}
}