{
  "type": "Feature",
  "properties": {
    "gn:admin1_code":"15.0",
    "gn:admin2_code":"1508.0",
    "gn:admin3_code":"150810.0",
    "gn:asciiname":"Naranjo",
    "gn:country_code":"PE",
    "gn:dem":245,
    "gn:feature_class":"P",
    "gn:feature_code":"PPL",
    "gn:name":"Naranjo",
    "gn:population":0,
    "gn:timezone":"America/Lima",
    "iso:country":"PE",
    "wof:name":"Naranjo",
    "wof:placetype":"locality"
},
  "geometry": {"coordinates":[-77.47194,-11.09861],"type":"Point"}
}