{
  "type": "Feature",
  "properties": {
    "gn:admin1_code":"03",
    "gn:admin2_code":"305.0",
    "gn:admin3_code":"30506.0",
    "gn:asciiname":"Chila",
    "gn:country_code":"PE",
    "gn:dem":3813,
    "gn:feature_class":"P",
    "gn:feature_code":"PPL",
    "gn:name":"Chila",
    "gn:population":0,
    "gn:timezone":"America/Lima",
    "iso:country":"PE",
    "name:ceb_x_preferred":[
        "Chila"
    ],
    "name:deu_x_preferred":[
        "Chila"
    ],
    "name:spa_x_preferred":[
        "Chila"
    ],
    "name:swe_x_preferred":[
        "Chila"
    ],
    "name:vie_x_preferred":[
        "Chila"
    ],
    "wof:name":"Chila",
    "wof:placetype":"locality"
},
  "geometry": {"coordinates":[-72.23333000000002,-14.11667],"type":"Point"}
}