{
  "type": "Feature",
  "properties": {
    "gn:admin1_code":"06",
    "gn:admin2_code":"601.0",
    "gn:admin3_code":"60101.0",
    "gn:asciiname":"Huayllapampa",
    "gn:country_code":"PE",
    "gn:dem":3329,
    "gn:feature_class":"P",
    "gn:feature_code":"PPL",
    "gn:name":"Huayllapampa",
    "gn:population":0,
    "gn:timezone":"America/Lima",
    "iso:country":"PE",
    "wof:name":"Huayllapampa",
    "wof:placetype":"locality"
},
  "geometry": {"coordinates":[-78.52899000000002,-7.20953],"type":"Point"}
}