{
  "type": "Feature",
  "properties": {
    "gn:admin1_code":"20",
    "gn:admin2_code":"2002.0",
    "gn:admin3_code":"200206.0",
    "gn:asciiname":"El Manzano",
    "gn:country_code":"PE",
    "gn:dem":2955,
    "gn:feature_class":"P",
    "gn:feature_code":"PPL",
    "gn:name":"El Manzano",
    "gn:population":0,
    "gn:timezone":"America/Lima",
    "iso:country":"PE",
    "wof:name":"El Manzano",
    "wof:placetype":"locality"
},
  "geometry": {"coordinates":[-79.63197,-5.10134],"type":"Point"}
}