{
  "type": "Feature",
  "properties": {
    "gn:admin1_code":"2.0",
    "gn:admin2_code":"210.0",
    "gn:admin3_code":"21006.0",
    "gn:asciiname":"Punrunya",
    "gn:country_code":"PE",
    "gn:dem":3709,
    "gn:feature_class":"P",
    "gn:feature_code":"PPL",
    "gn:name":"Punrunya",
    "gn:population":0,
    "gn:timezone":"America/Lima",
    "iso:country":"PE",
    "wof:name":"Punrunya",
    "wof:placetype":"locality"
},
  "geometry": {"coordinates":[-76.80373,-9.21791],"type":"Point"}
}