{
  "type": "Feature",
  "properties": {
    "gn:admin1_code":"21",
    "gn:admin2_code":"2103.0",
    "gn:admin3_code":"210306.0",
    "gn:asciiname":"Huarajo Pampa",
    "gn:country_code":"PE",
    "gn:dem":4484,
    "gn:feature_class":"P",
    "gn:feature_code":"PPL",
    "gn:name":"Huarajo Pampa",
    "gn:population":0,
    "gn:timezone":"America/Lima",
    "iso:country":"PE",
    "wof:name":"Huarajo Pampa",
    "wof:placetype":"locality"
},
  "geometry": {"coordinates":[-69.77731,-14.40069],"type":"Point"}
}