{
  "type": "Feature",
  "properties": {
    "gn:admin1_code":"25",
    "gn:admin2_code":"2502.0",
    "gn:admin3_code":"250201.0",
    "gn:asciiname":"Termopilas",
    "gn:cc2":"PE",
    "gn:country_code":"PE",
    "gn:dem":287,
    "gn:feature_class":"P",
    "gn:feature_code":"PPL",
    "gn:name":"Term\u00f3pilas",
    "gn:population":0,
    "gn:timezone":"America/Lima",
    "iso:country":"PE",
    "name:und_x_variant":[
        "Mal Paso",
        "Term\u00f3pilas"
    ],
    "wof:name":"Termopilas",
    "wof:placetype":"locality"
},
  "geometry": {"coordinates":[-73.86667,-10.68333],"type":"Point"}
}