{
  "type": "Feature",
  "properties": {
    "gn:admin1_code":"3.0",
    "gn:admin2_code":"307.0",
    "gn:admin3_code":"30703.0",
    "gn:asciiname":"Pupurqui",
    "gn:country_code":"PE",
    "gn:dem":3131,
    "gn:feature_class":"P",
    "gn:feature_code":"PPL",
    "gn:name":"Pupurqui",
    "gn:population":0,
    "gn:timezone":"America/Lima",
    "iso:country":"PE",
    "wof:name":"Pupurqui",
    "wof:placetype":"locality"
},
  "geometry": {"coordinates":[-72.49221999999997,-13.85028],"type":"Point"}
}