{
  "type": "Feature",
  "properties": {
    "gn:admin1_code":"2.0",
    "gn:admin2_code":"211.0",
    "gn:admin3_code":"21101.0",
    "gn:asciiname":"Hacienda Cuzcuz",
    "gn:country_code":"PE",
    "gn:dem":32,
    "gn:feature_class":"P",
    "gn:feature_code":"PPL",
    "gn:name":"Hacienda Cuzcuz",
    "gn:population":0,
    "gn:timezone":"America/Lima",
    "iso:country":"PE",
    "name:spa_x_preferred":[
        "Hacienda Cuzcuz"
    ],
    "wof:name":"Hacienda Cuzcuz",
    "wof:placetype":"locality"
},
  "geometry": {"coordinates":[-78.10722,-10.06709],"type":"Point"}
}