{
  "type": "Feature",
  "properties": {
    "gn:admin1_code":"09",
    "gn:admin2_code":"906.0",
    "gn:admin3_code":"90607.0",
    "gn:asciiname":"Cenega",
    "gn:country_code":"PE",
    "gn:dem":3973,
    "gn:feature_class":"P",
    "gn:feature_code":"PPL",
    "gn:name":"Cenega",
    "gn:population":0,
    "gn:timezone":"America/Lima",
    "iso:country":"PE",
    "wof:name":"Cenega",
    "wof:placetype":"locality"
},
  "geometry": {"coordinates":[-74.88333,-13.58333],"type":"Point"}
}