{
  "type": "Feature",
  "properties": {
    "gn:admin1_code":"12.0",
    "gn:admin2_code":"1206.0",
    "gn:admin3_code":"120608.0",
    "gn:asciiname":"Camajeni",
    "gn:country_code":"PE",
    "gn:dem":393,
    "gn:feature_class":"P",
    "gn:feature_code":"PPLL",
    "gn:name":"Camajeni",
    "gn:population":0,
    "gn:timezone":"America/Lima",
    "iso:country":"PE",
    "name:spa_x_preferred":[
        "Camajeni"
    ],
    "wof:name":"Camajeni",
    "wof:placetype":"locality"
},
  "geometry": {"coordinates":[-73.861,-11.22849],"type":"Point"}
}