{
  "type": "Feature",
  "properties": {
    "gn:admin1_code":"10.0",
    "gn:admin2_code":"1010.0",
    "gn:admin3_code":"101005.0",
    "gn:asciiname":"Tamborajra",
    "gn:country_code":"PE",
    "gn:dem":3950,
    "gn:feature_class":"P",
    "gn:feature_code":"PPL",
    "gn:name":"Tamborajra",
    "gn:population":0,
    "gn:timezone":"America/Lima",
    "iso:country":"PE",
    "wof:name":"Tamborajra",
    "wof:placetype":"locality"
},
  "geometry": {"coordinates":[-76.75938000000002,-9.97628],"type":"Point"}
}