{
  "type": "Feature",
  "properties": {
    "gn:admin1_code":"06",
    "gn:admin2_code":"611.0",
    "gn:admin3_code":"61108.0",
    "gn:asciiname":"Nanchoc",
    "gn:cc2":"PE",
    "gn:country_code":"PE",
    "gn:dem":395,
    "gn:feature_class":"P",
    "gn:feature_code":"PPLA3",
    "gn:name":"Nanchoc",
    "gn:population":0,
    "gn:timezone":"America/Lima",
    "iso:country":"PE",
    "name:und_x_variant":[
        "Nancho",
        "Nanchoc"
    ],
    "wof:name":"Nanchoc",
    "wof:placetype":"locality"
},
  "geometry": {"coordinates":[-79.24221999999997,-6.95972],"type":"Point"}
}