{
  "type": "Feature",
  "properties": {
    "gn:admin1_code":"1.0",
    "gn:admin2_code":"103.0",
    "gn:admin3_code":"10301.0",
    "gn:asciiname":"Sengache",
    "gn:country_code":"PE",
    "gn:dem":2334,
    "gn:feature_class":"P",
    "gn:feature_code":"PPL",
    "gn:name":"Sengache",
    "gn:population":0,
    "gn:timezone":"America/Lima",
    "iso:country":"PE",
    "wof:name":"Sengache",
    "wof:placetype":"locality"
},
  "geometry": {"coordinates":[-77.80986999999998,-6.09686],"type":"Point"}
}