{
  "type": "Feature",
  "properties": {
    "gn:admin1_code":"11.0",
    "gn:admin2_code":"1102.0",
    "gn:admin3_code":"110202.0",
    "gn:asciiname":"Santa Enriqueta",
    "gn:country_code":"PE",
    "gn:dem":94,
    "gn:feature_class":"P",
    "gn:feature_code":"PPL",
    "gn:name":"Santa Enriqueta",
    "gn:population":0,
    "gn:timezone":"America/Lima",
    "iso:country":"PE",
    "wof:name":"Santa Enriqueta",
    "wof:placetype":"locality"
},
  "geometry": {"coordinates":[-76.10554999999999,-13.45363],"type":"Point"}
}