{
  "type": "Feature",
  "properties": {
    "gn:admin1_code":"19",
    "gn:admin2_code":"1902.0",
    "gn:admin3_code":"190206.0",
    "gn:asciiname":"Challhuan",
    "gn:country_code":"PE",
    "gn:dem":4250,
    "gn:feature_class":"P",
    "gn:feature_code":"PPL",
    "gn:name":"Challhu\u00e1n",
    "gn:population":0,
    "gn:timezone":"America/Lima",
    "iso:country":"PE",
    "wof:name":"Challhuan",
    "wof:placetype":"locality"
},
  "geometry": {"coordinates":[-76.31841,-10.48941],"type":"Point"}
}