{
  "type": "Feature",
  "properties": {
    "gn:admin1_code":"03",
    "gn:admin2_code":"306.0",
    "gn:admin3_code":"30604.0",
    "gn:asciiname":"Curampa",
    "gn:country_code":"PE",
    "gn:dem":3400,
    "gn:feature_class":"P",
    "gn:feature_code":"PPL",
    "gn:name":"Curampa",
    "gn:population":0,
    "gn:timezone":"America/Lima",
    "iso:country":"PE",
    "wof:name":"Curampa",
    "wof:placetype":"locality"
},
  "geometry": {"coordinates":[-73.71122,-13.38502],"type":"Point"}
}