{
  "type": "Feature",
  "properties": {
    "gn:admin1_code":"10",
    "gn:admin2_code":"1002.0",
    "gn:admin3_code":"100207.0",
    "gn:asciiname":"Mishacallo",
    "gn:country_code":"PE",
    "gn:dem":3960,
    "gn:feature_class":"P",
    "gn:feature_code":"PPL",
    "gn:name":"Mishacallo",
    "gn:population":0,
    "gn:timezone":"America/Lima",
    "iso:country":"PE",
    "wof:name":"Mishacallo",
    "wof:placetype":"locality"
},
  "geometry": {"coordinates":[-76.24101,-10.31072],"type":"Point"}
}