{
  "type": "Feature",
  "properties": {
    "gn:admin1_code":"5",
    "gn:admin2_code":"510.0",
    "gn:admin3_code":"51012.0",
    "gn:asciiname":"Uchpacocha",
    "gn:country_code":"PE",
    "gn:dem":4377,
    "gn:feature_class":"P",
    "gn:feature_code":"PPL",
    "gn:name":"Uchpacocha",
    "gn:population":0,
    "gn:timezone":"America/Lima",
    "iso:country":"PE",
    "wof:name":"Uchpacocha",
    "wof:placetype":"locality"
},
  "geometry": {"coordinates":[-74.62917,-13.72333],"type":"Point"}
}