{
  "type": "Feature",
  "properties": {
    "gn:admin1_code":"13",
    "gn:admin2_code":"1305.0",
    "gn:admin3_code":"130502.0",
    "gn:asciiname":"Barro Negro",
    "gn:country_code":"PE",
    "gn:dem":3640,
    "gn:feature_class":"P",
    "gn:feature_code":"PPL",
    "gn:name":"Barro Negro",
    "gn:population":0,
    "gn:timezone":"America/Lima",
    "iso:country":"PE",
    "wof:name":"Barro Negro",
    "wof:placetype":"locality"
},
  "geometry": {"coordinates":[-78.40293,-8.13517],"type":"Point"}
}