{
  "type": "Feature",
  "properties": {
    "gn:admin1_code":"10",
    "gn:admin2_code":"1011.0",
    "gn:admin3_code":"101101.0",
    "gn:asciiname":"Chavinillo",
    "gn:country_code":"PE",
    "gn:dem":3458,
    "gn:feature_class":"P",
    "gn:feature_code":"PPLA3",
    "gn:name":"Chavinillo",
    "gn:population":0,
    "gn:timezone":"America/Lima",
    "iso:country":"PE",
    "name:por_x_preferred":[
        "Chavinillo"
    ],
    "name:que_x_preferred":[
        "Chawinillu"
    ],
    "name:spa_x_preferred":[
        "Chavinillo"
    ],
    "name:und_x_variant":[
        "Chavanillo",
        "Chavinillo"
    ],
    "name:war_x_preferred":[
        "Chavinillo"
    ],
    "name:zho_x_preferred":[
        "\u67e5\u7dad\u5c3c\u7d04"
    ],
    "wof:name":"Chavinillo",
    "wof:placetype":"locality"
},
  "geometry": {"coordinates":[-76.60854999999999,-9.8585],"type":"Point"}
}