{
  "type": "Feature",
  "properties": {
    "gn:admin1_code":"9",
    "gn:admin2_code":"906.0",
    "gn:admin3_code":"90601.0",
    "gn:asciiname":"Pichante",
    "gn:country_code":"PE",
    "gn:dem":4401,
    "gn:feature_class":"P",
    "gn:feature_code":"PPL",
    "gn:name":"Pichante",
    "gn:population":0,
    "gn:timezone":"America/Lima",
    "iso:country":"PE",
    "wof:name":"Pichante",
    "wof:placetype":"locality"
},
  "geometry": {"coordinates":[-75.28471999999999,-13.63167],"type":"Point"}
}