{
  "type": "Feature",
  "properties": {
    "gn:admin1_code":"9.0",
    "gn:admin2_code":"901.0",
    "gn:admin3_code":"90119.0",
    "gn:asciiname":"Piucca",
    "gn:country_code":"PE",
    "gn:dem":3257,
    "gn:feature_class":"P",
    "gn:feature_code":"PPL",
    "gn:name":"Piucca",
    "gn:population":0,
    "gn:timezone":"America/Lima",
    "iso:country":"PE",
    "wof:name":"Piucca",
    "wof:placetype":"locality"
},
  "geometry": {"coordinates":[-74.9524,-12.54212],"type":"Point"}
}