{
  "type": "Feature",
  "properties": {
    "gn:admin1_code":"03",
    "gn:admin2_code":"301.0",
    "gn:admin3_code":"30105.0",
    "gn:asciiname":"San Ignacio",
    "gn:country_code":"PE",
    "gn:dem":1786,
    "gn:feature_class":"P",
    "gn:feature_code":"PPL",
    "gn:name":"San Ignacio",
    "gn:population":0,
    "gn:timezone":"America/Lima",
    "iso:country":"PE",
    "name:und_x_variant":[
        "San Ignacio Hacienda",
        "San Ignacio"
    ],
    "wof:name":"San Ignacio",
    "wof:placetype":"locality"
},
  "geometry": {"coordinates":[-72.88070999999999,-13.42133],"type":"Point"}
}