{
  "type": "Feature",
  "properties": {
    "gn:admin1_code":"10",
    "gn:admin2_code":"1001.0",
    "gn:admin3_code":"100105.0",
    "gn:asciiname":"Huacacancha",
    "gn:country_code":"PE",
    "gn:dem":3843,
    "gn:feature_class":"P",
    "gn:feature_code":"PPL",
    "gn:name":"Huacacancha",
    "gn:population":0,
    "gn:timezone":"America/Lima",
    "iso:country":"PE",
    "wof:name":"Huacacancha",
    "wof:placetype":"locality"
},
  "geometry": {"coordinates":[-76.55291,-10.00877],"type":"Point"}
}