{
  "type": "Feature",
  "properties": {
    "gn:admin1_code":"14",
    "gn:admin2_code":"1403.0",
    "gn:admin3_code":"140307.0",
    "gn:asciiname":"El Lindero",
    "gn:country_code":"PE",
    "gn:dem":85,
    "gn:feature_class":"P",
    "gn:feature_code":"PPL",
    "gn:name":"El Lindero",
    "gn:population":0,
    "gn:timezone":"America/Lima",
    "iso:country":"PE",
    "name:spa_x_preferred":[
        "El Lindero"
    ],
    "wof:name":"El Lindero",
    "wof:placetype":"locality"
},
  "geometry": {"coordinates":[-79.75493,-6.30069],"type":"Point"}
}