{
  "type": "Feature",
  "properties": {
    "gn:admin1_code":"12.0",
    "gn:admin2_code":"1202.0",
    "gn:admin3_code":"120209.0",
    "gn:asciiname":"Chalas",
    "gn:country_code":"PE",
    "gn:dem":3071,
    "gn:feature_class":"P",
    "gn:feature_code":"PPL",
    "gn:name":"Chalas",
    "gn:population":0,
    "gn:timezone":"America/Lima",
    "iso:country":"PE",
    "wof:name":"Chalas",
    "wof:placetype":"locality"
},
  "geometry": {"coordinates":[-75.08121,-11.60115],"type":"Point"}
}