{
  "type": "Feature",
  "properties": {
    "gn:admin1_code":"2.0",
    "gn:admin2_code":"210.0",
    "gn:asciiname":"Cachina Pampa",
    "gn:country_code":"PE",
    "gn:dem":3742,
    "gn:feature_class":"P",
    "gn:feature_code":"PPL",
    "gn:name":"Cachina Pampa",
    "gn:population":0,
    "gn:timezone":"America/Lima",
    "iso:country":"PE",
    "wof:name":"Cachina Pampa",
    "wof:placetype":"locality"
},
  "geometry": {"coordinates":[-76.7869,-9.25166],"type":"Point"}
}