{
  "type": "Feature",
  "properties": {
    "gn:admin1_code":"3",
    "gn:admin2_code":"307.0",
    "gn:admin3_code":"30706.0",
    "gn:asciiname":"Ayrihuanca",
    "gn:cc2":"PE",
    "gn:country_code":"PE",
    "gn:dem":3565,
    "gn:feature_class":"P",
    "gn:feature_code":"PPLA3",
    "gn:name":"Ayrihuanca",
    "gn:population":0,
    "gn:timezone":"America/Lima",
    "iso:country":"PE",
    "name:und_x_variant":[
        "Airihuanca",
        "Ayrihuanca"
    ],
    "wof:name":"Ayrihuanca",
    "wof:placetype":"locality"
},
  "geometry": {"coordinates":[-72.6125,-14.10472],"type":"Point"}
}