{
  "type": "Feature",
  "properties": {
    "gn:admin1_code":"11",
    "gn:admin2_code":"1102.0",
    "gn:admin3_code":"110203.0",
    "gn:asciiname":"Antalla",
    "gn:country_code":"PE",
    "gn:dem":2454,
    "gn:feature_class":"P",
    "gn:feature_code":"PPL",
    "gn:name":"Antalla",
    "gn:population":0,
    "gn:timezone":"America/Lima",
    "iso:country":"PE",
    "name:jpn_x_preferred":[
        "\u30a2\u30f3\u30bf\u30e9"
    ],
    "name:spa_x_preferred":[
        "Antalla"
    ],
    "wof:name":"Antalla",
    "wof:placetype":"locality"
},
  "geometry": {"coordinates":[-75.92180999999999,-13.16676],"type":"Point"}
}