{
  "type": "Feature",
  "properties": {
    "gn:admin1_code":"02",
    "gn:admin2_code":"218.0",
    "gn:admin3_code":"21805.0",
    "gn:asciiname":"Tomeque",
    "gn:country_code":"PE",
    "gn:dem":334,
    "gn:feature_class":"P",
    "gn:feature_code":"PPL",
    "gn:name":"Tomeque",
    "gn:population":0,
    "gn:timezone":"America/Lima",
    "iso:country":"PE",
    "wof:name":"Tomeque",
    "wof:placetype":"locality"
},
  "geometry": {"coordinates":[-78.23333000000002,-9.16667],"type":"Point"}
}