{
  "type": "Feature",
  "properties": {
    "gn:admin1_code":"16.0",
    "gn:admin2_code":"1606.0",
    "gn:asciiname":"Nuevo Tambomayo",
    "gn:country_code":"PE",
    "gn:dem":133,
    "gn:feature_class":"P",
    "gn:feature_code":"PPL",
    "gn:name":"Nuevo Tambomayo",
    "gn:population":0,
    "gn:timezone":"America/Lima",
    "iso:country":"PE",
    "name:spa_x_preferred":[
        "Nuevo Tambomayo"
    ],
    "wof:name":"Nuevo Tambomayo",
    "wof:placetype":"locality"
},
  "geometry": {"coordinates":[-75.21613000000001,-7.23073],"type":"Point"}
}