{
  "type": "Feature",
  "properties": {
    "gn:admin1_code":"10.0",
    "gn:admin2_code":"1005.0",
    "gn:asciiname":"Magan Patay",
    "gn:country_code":"PE",
    "gn:dem":2705,
    "gn:feature_class":"P",
    "gn:feature_code":"PPL",
    "gn:name":"Magan Patay",
    "gn:population":0,
    "gn:timezone":"America/Lima",
    "iso:country":"PE",
    "wof:name":"Magan Patay",
    "wof:placetype":"locality"
},
  "geometry": {"coordinates":[-76.75128000000002,-9.1808],"type":"Point"}
}