{
  "type": "Feature",
  "properties": {
    "gn:admin1_code":"19",
    "gn:admin2_code":"1902.0",
    "gn:admin3_code":"190201.0",
    "gn:asciiname":"Huarangayoc",
    "gn:country_code":"PE",
    "gn:dem":4043,
    "gn:feature_class":"P",
    "gn:feature_code":"PPL",
    "gn:name":"Huarangayoc",
    "gn:population":0,
    "gn:timezone":"America/Lima",
    "iso:country":"PE",
    "wof:name":"Huarangayoc",
    "wof:placetype":"locality"
},
  "geometry": {"coordinates":[-76.61638000000001,-10.46923],"type":"Point"}
}