{
  "type": "Feature",
  "properties": {
    "gn:admin1_code":"15.0",
    "gn:admin2_code":"1504.0",
    "gn:admin3_code":"150403.0",
    "gn:asciiname":"Arrachacra",
    "gn:country_code":"PE",
    "gn:dem":1702,
    "gn:feature_class":"P",
    "gn:feature_code":"PPL",
    "gn:name":"Arrachacra",
    "gn:population":0,
    "gn:timezone":"America/Lima",
    "iso:country":"PE",
    "wof:name":"Arrachacra",
    "wof:placetype":"locality"
},
  "geometry": {"coordinates":[-76.72884000000001,-11.56837],"type":"Point"}
}