{
  "type": "Feature",
  "properties": {
    "gn:admin1_code":"21",
    "gn:admin2_code":"2109.0",
    "gn:admin3_code":"210903.0",
    "gn:asciiname":"Chuyunjane",
    "gn:country_code":"PE",
    "gn:dem":4202,
    "gn:feature_class":"P",
    "gn:feature_code":"PPL",
    "gn:name":"Chuyunjane",
    "gn:population":0,
    "gn:timezone":"America/Lima",
    "iso:country":"PE",
    "name:spa_x_preferred":[
        "Chuyunjane"
    ],
    "wof:name":"Chuyunjane",
    "wof:placetype":"locality"
},
  "geometry": {"coordinates":[-69.26510999999999,-15.31019],"type":"Point"}
}