{
  "type": "Feature",
  "properties": {
    "gn:admin1_code":"15.0",
    "gn:admin2_code":"1503.0",
    "gn:admin3_code":"150301.0",
    "gn:asciiname":"Tuctucushman",
    "gn:country_code":"PE",
    "gn:dem":4229,
    "gn:feature_class":"P",
    "gn:feature_code":"PPL",
    "gn:name":"Tuctucushman",
    "gn:population":0,
    "gn:timezone":"America/Lima",
    "iso:country":"PE",
    "wof:name":"Tuctucushman",
    "wof:placetype":"locality"
},
  "geometry": {"coordinates":[-76.94499999999999,-10.49778],"type":"Point"}
}