{
  "type": "Feature",
  "properties": {
    "gn:admin1_code":"13",
    "gn:admin2_code":"1309.0",
    "gn:admin3_code":"130904.0",
    "gn:asciiname":"Choctamalca",
    "gn:country_code":"PE",
    "gn:dem":3430,
    "gn:feature_class":"P",
    "gn:feature_code":"PPL",
    "gn:name":"Choctamalca",
    "gn:population":0,
    "gn:timezone":"America/Lima",
    "iso:country":"PE",
    "wof:name":"Choctamalca",
    "wof:placetype":"locality"
},
  "geometry": {"coordinates":[-77.96341,-7.87761],"type":"Point"}
}