{
  "type": "Feature",
  "properties": {
    "gn:admin1_code":"21",
    "gn:admin2_code":"2112",
    "gn:asciiname":"Condor Senoca",
    "gn:country_code":"PE",
    "gn:dem":3348,
    "gn:feature_class":"P",
    "gn:feature_code":"PPL",
    "gn:name":"Condor Senoca",
    "gn:population":0,
    "gn:timezone":"America/Lima",
    "iso:country":"PE",
    "name:spa_x_preferred":[
        "Condor Senoca"
    ],
    "wof:name":"Condor Senoca",
    "wof:placetype":"locality"
},
  "geometry": {"coordinates":[-69.68299,-13.99799],"type":"Point"}
}