{
  "type": "Feature",
  "properties": {
    "gn:admin1_code":"11.0",
    "gn:admin2_code":"1105.0",
    "gn:asciiname":"Ichichuayrani",
    "gn:country_code":"PE",
    "gn:dem":2584,
    "gn:feature_class":"P",
    "gn:feature_code":"PPL",
    "gn:name":"Ichichuayrani",
    "gn:population":0,
    "gn:timezone":"America/Lima",
    "iso:country":"PE",
    "name:spa_x_preferred":[
        "Ichichuayrani"
    ],
    "wof:name":"Ichichuayrani",
    "wof:placetype":"locality"
},
  "geometry": {"coordinates":[-75.59654999999999,-13.47122],"type":"Point"}
}