{
  "type": "Feature",
  "properties": {
    "gn:admin1_code":"14.0",
    "gn:admin2_code":"1401.0",
    "gn:admin3_code":"140101.0",
    "gn:asciiname":"Nuevo Retiro",
    "gn:country_code":"PE",
    "gn:dem":29,
    "gn:feature_class":"P",
    "gn:feature_code":"PPL",
    "gn:name":"Nuevo Retiro",
    "gn:population":0,
    "gn:timezone":"America/Lima",
    "iso:country":"PE",
    "name:spa_x_preferred":[
        "Nuevo Retiro"
    ],
    "wof:name":"Nuevo Retiro",
    "wof:placetype":"locality"
},
  "geometry": {"coordinates":[-79.84653,-6.78646],"type":"Point"}
}