{
  "type": "Feature",
  "properties": {
    "gn:admin1_code":"11",
    "gn:admin2_code":"1101.0",
    "gn:admin3_code":"110113.0",
    "gn:asciiname":"Puno",
    "gn:country_code":"PE",
    "gn:dem":403,
    "gn:feature_class":"P",
    "gn:feature_code":"PPL",
    "gn:name":"Puno",
    "gn:population":0,
    "gn:timezone":"America/Lima",
    "iso:country":"PE",
    "name:spa_x_preferred":[
        "Puno"
    ],
    "wof:name":"Puno",
    "wof:placetype":"locality"
},
  "geometry": {"coordinates":[-75.70323,-14.13817],"type":"Point"}
}