{
  "type": "Feature",
  "properties": {
    "gn:admin1_code":"10.0",
    "gn:admin2_code":"1001.0",
    "gn:admin3_code":"100104.0",
    "gn:asciiname":"Rangra Huasi",
    "gn:country_code":"PE",
    "gn:dem":3954,
    "gn:feature_class":"P",
    "gn:feature_code":"PPL",
    "gn:name":"Rangra Huasi",
    "gn:population":0,
    "gn:timezone":"America/Lima",
    "iso:country":"PE",
    "wof:name":"Rangra Huasi",
    "wof:placetype":"locality"
},
  "geometry": {"coordinates":[-76.43916999999998,-9.66744],"type":"Point"}
}