{
  "type": "Feature",
  "properties": {
    "gn:admin1_code":"15",
    "gn:admin2_code":"1510.0",
    "gn:admin3_code":"151032.0",
    "gn:asciiname":"Totora",
    "gn:country_code":"PE",
    "gn:dem":3513,
    "gn:feature_class":"P",
    "gn:feature_code":"PPL",
    "gn:name":"Totora",
    "gn:population":0,
    "gn:timezone":"America/Lima",
    "iso:country":"PE",
    "name:und_x_variant":[
        "Totara",
        "Totora"
    ],
    "wof:name":"Totora",
    "wof:placetype":"locality"
},
  "geometry": {"coordinates":[-75.72837,-12.93287],"type":"Point"}
}