{
  "type": "Feature",
  "properties": {
    "gn:admin1_code":"12.0",
    "gn:admin2_code":"1206.0",
    "gn:admin3_code":"120608.0",
    "gn:asciiname":"Santaro",
    "gn:country_code":"PE",
    "gn:dem":324,
    "gn:feature_class":"P",
    "gn:feature_code":"PPLL",
    "gn:name":"Santaro",
    "gn:population":0,
    "gn:timezone":"America/Lima",
    "iso:country":"PE",
    "wof:name":"Santaro",
    "wof:placetype":"locality"
},
  "geometry": {"coordinates":[-74.18416999999999,-11.13856],"type":"Point"}
}