{
  "type": "Feature",
  "properties": {
    "gn:admin1_code":"02",
    "gn:admin2_code":"205.0",
    "gn:admin3_code":"20512.0",
    "gn:asciiname":"Gorgorillo",
    "gn:cc2":"PE",
    "gn:country_code":"PE",
    "gn:dem":2548,
    "gn:feature_class":"P",
    "gn:feature_code":"PPL",
    "gn:name":"Gorgorillo",
    "gn:population":0,
    "gn:timezone":"America/Lima",
    "iso:country":"PE",
    "wof:name":"Gorgorillo",
    "wof:placetype":"locality"
},
  "geometry": {"coordinates":[-77.13037,-10.33654],"type":"Point"}
}