{
  "type": "Feature",
  "properties": {
    "gn:admin1_code":"22",
    "gn:admin2_code":"2206.0",
    "gn:admin3_code":"220604.0",
    "gn:asciiname":"Puerto Billinghurst",
    "gn:country_code":"PE",
    "gn:dem":664,
    "gn:feature_class":"P",
    "gn:feature_code":"PPL",
    "gn:name":"Puerto Billinghurst",
    "gn:population":0,
    "gn:timezone":"America/Lima",
    "iso:country":"PE",
    "wof:name":"Puerto Billinghurst",
    "wof:placetype":"locality"
},
  "geometry": {"coordinates":[-77.16667,-7.03333],"type":"Point"}
}