{
  "type": "Feature",
  "properties": {
    "gn:admin1_code":"20",
    "gn:admin2_code":"2003.0",
    "gn:admin3_code":"200304.0",
    "gn:asciiname":"Chucuyuc",
    "gn:country_code":"PE",
    "gn:dem":2309,
    "gn:feature_class":"P",
    "gn:feature_code":"PPL",
    "gn:name":"Chucuyuc",
    "gn:population":0,
    "gn:timezone":"America/Lima",
    "iso:country":"PE",
    "wof:name":"Chucuyuc",
    "wof:placetype":"locality"
},
  "geometry": {"coordinates":[-79.61529,-5.72656],"type":"Point"}
}