{
  "type": "Feature",
  "properties": {
    "gn:admin1_code":"8",
    "gn:admin2_code":"806.0",
    "gn:admin3_code":"80604.0",
    "gn:asciiname":"Chosicani",
    "gn:country_code":"PE",
    "gn:dem":3729,
    "gn:feature_class":"P",
    "gn:feature_code":"PPL",
    "gn:name":"Chosicani",
    "gn:population":0,
    "gn:timezone":"America/Lima",
    "iso:country":"PE",
    "wof:name":"Chosicani",
    "wof:placetype":"locality"
},
  "geometry": {"coordinates":[-71.14943000000002,-14.37333],"type":"Point"}
}