{
  "type": "Feature",
  "properties": {
    "gn:admin1_code":"15",
    "gn:admin2_code":"1507.0",
    "gn:admin3_code":"150702.0",
    "gn:asciiname":"Pacashuayque",
    "gn:country_code":"PE",
    "gn:dem":1473,
    "gn:feature_class":"P",
    "gn:feature_code":"PPL",
    "gn:name":"Pacashuayque",
    "gn:population":0,
    "gn:timezone":"America/Lima",
    "iso:country":"PE",
    "name:und_x_variant":[
        "Pacashuaique"
    ],
    "wof:name":"Pacashuayque",
    "wof:placetype":"locality"
},
  "geometry": {"coordinates":[-76.54345000000001,-12.05223],"type":"Point"}
}