{
  "type": "Feature",
  "properties": {
    "gn:admin1_code":"21",
    "gn:admin2_code":"2104.0",
    "gn:admin3_code":"210403.0",
    "gn:asciiname":"Salviani",
    "gn:country_code":"PE",
    "gn:dem":4244,
    "gn:feature_class":"P",
    "gn:feature_code":"PPL",
    "gn:name":"Salviani",
    "gn:population":0,
    "gn:timezone":"America/Lima",
    "iso:country":"PE",
    "wof:name":"Salviani",
    "wof:placetype":"locality"
},
  "geometry": {"coordinates":[-69.40575,-16.71576],"type":"Point"}
}