{
  "type": "Feature",
  "properties": {
    "gn:admin1_code":"10",
    "gn:admin2_code":"1001.0",
    "gn:admin3_code":"100105.0",
    "gn:asciiname":"Cancania",
    "gn:country_code":"PE",
    "gn:dem":3933,
    "gn:feature_class":"P",
    "gn:feature_code":"PPL",
    "gn:name":"Cancania",
    "gn:population":0,
    "gn:timezone":"America/Lima",
    "iso:country":"PE",
    "wof:name":"Cancania",
    "wof:placetype":"locality"
},
  "geometry": {"coordinates":[-76.47192,-10.13233],"type":"Point"}
}