{
  "type": "Feature",
  "properties": {
    "iso:country":"PE",
    "name:spa_x_preferred":[
        "Jesus Maria"
    ],
    "name:unk_x_variant":[
        "Jesus Maria"
    ],
    "qs:gn_adm0_cc":"PE",
    "qs:gn_local":3936456,
    "qs:gn_nam_loc":"Lima",
    "qs:gn_namadm1":"15",
    "qs:local_max":11098,
    "qs:local_sum":45985,
    "qs:localhoods":37,
    "qs:name":"Jesus Maria",
    "qs:name_adm0":"Per\u00fa",
    "qs:name_adm1":"Lima Metropolitan Area",
    "qs:name_adm2":"Lima",
    "qs:name_local":"Lima",
    "qs:photo_max":1239,
    "qs:photo_sum":4709,
    "qs:placetype":"Suburb",
    "qs:quad_count":65,
    "qs:woe_adm0":23424919,
    "qs:woe_adm1":28358302,
    "qs:woe_adm2":26805880,
    "qs:woe_lau":0,
    "qs:woe_local":418440,
    "qs:woe_ver":"7.10.0",
    "wof:lang":[
        "spa"
    ],
    "wof:name":"Jesus Maria",
    "wof:placetype":"neighbourhood"
},
  "geometry": {"coordinates":[-77.05085099999999,-12.072973],"type":"Point"}
}