{
  "type": "Feature",
  "properties": {
    "gn:admin1_code":"21.0",
    "gn:admin2_code":"2112.0",
    "gn:asciiname":"Organico",
    "gn:country_code":"PE",
    "gn:dem":778,
    "gn:feature_class":"P",
    "gn:feature_code":"PPL",
    "gn:name":"Organico",
    "gn:population":0,
    "gn:timezone":"America/Lima",
    "iso:country":"PE",
    "name:spa_x_preferred":[
        "Organico"
    ],
    "wof:name":"Organico",
    "wof:placetype":"locality"
},
  "geometry": {"coordinates":[-68.98541999999999,-13.93274],"type":"Point"}
}