{
  "type": "Feature",
  "properties": {
    "gn:admin1_code":"3",
    "gn:admin2_code":"302.0",
    "gn:admin3_code":"30206.0",
    "gn:asciiname":"Pampahuasi",
    "gn:country_code":"PE",
    "gn:dem":3885,
    "gn:feature_class":"P",
    "gn:feature_code":"PPL",
    "gn:name":"Pampahuasi",
    "gn:population":0,
    "gn:timezone":"America/Lima",
    "iso:country":"PE",
    "wof:name":"Pampahuasi",
    "wof:placetype":"locality"
},
  "geometry": {"coordinates":[-73.52332,-13.95819],"type":"Point"}
}