{
  "type": "Feature",
  "properties": {
    "gn:admin1_code":"16",
    "gn:admin2_code":"1605.0",
    "gn:admin3_code":"160507.0",
    "gn:asciiname":"Tibeplaya Dos",
    "gn:country_code":"PE",
    "gn:dem":97,
    "gn:feature_class":"P",
    "gn:feature_code":"PPL",
    "gn:name":"Tibeplaya Dos",
    "gn:population":0,
    "gn:timezone":"America/Lima",
    "iso:country":"PE",
    "wof:name":"Tibeplaya Dos",
    "wof:placetype":"locality"
},
  "geometry": {"coordinates":[-73.55944000000002,-4.62833],"type":"Point"}
}