{
  "type": "Feature",
  "properties": {
    "gn:admin1_code":"16",
    "gn:admin2_code":"1602.0",
    "gn:admin3_code":"160206.0",
    "gn:asciiname":"Nuevo Santa Isabel",
    "gn:country_code":"PE",
    "gn:dem":116,
    "gn:feature_class":"P",
    "gn:feature_code":"PPL",
    "gn:name":"Nuevo Santa Isabel",
    "gn:population":0,
    "gn:timezone":"America/Lima",
    "iso:country":"PE",
    "wof:name":"Nuevo Santa Isabel",
    "wof:placetype":"locality"
},
  "geometry": {"coordinates":[-75.62018,-5.16703],"type":"Point"}
}