{
  "type": "Feature",
  "properties": {
    "gn:admin1_code":"5",
    "gn:admin2_code":"510.0",
    "gn:admin3_code":"51005.0",
    "gn:asciiname":"Millpo Pampa",
    "gn:country_code":"PE",
    "gn:dem":4307,
    "gn:feature_class":"P",
    "gn:feature_code":"PPL",
    "gn:name":"Millpo Pampa",
    "gn:population":0,
    "gn:timezone":"America/Lima",
    "iso:country":"PE",
    "wof:name":"Millpo Pampa",
    "wof:placetype":"locality"
},
  "geometry": {"coordinates":[-73.99221999999997,-13.96694],"type":"Point"}
}