{
  "type": "Feature",
  "properties": {
    "gn:admin1_code":"10.0",
    "gn:admin2_code":"1001.0",
    "gn:admin3_code":"100108.0",
    "gn:asciiname":"Sumaranpampa",
    "gn:country_code":"PE",
    "gn:dem":3193,
    "gn:feature_class":"P",
    "gn:feature_code":"PPL",
    "gn:name":"Sumaranpampa",
    "gn:population":0,
    "gn:timezone":"America/Lima",
    "iso:country":"PE",
    "wof:name":"Sumaranpampa",
    "wof:placetype":"locality"
},
  "geometry": {"coordinates":[-76.36725,-9.98092],"type":"Point"}
}