{
  "type": "Feature",
  "properties": {
    "gn:admin1_code":"10.0",
    "gn:admin2_code":"1010.0",
    "gn:admin3_code":"101007.0",
    "gn:asciiname":"Huarhuash",
    "gn:country_code":"PE",
    "gn:dem":4038,
    "gn:feature_class":"P",
    "gn:feature_code":"PPL",
    "gn:name":"Huarhuash",
    "gn:population":0,
    "gn:timezone":"America/Lima",
    "iso:country":"PE",
    "wof:name":"Huarhuash",
    "wof:placetype":"locality"
},
  "geometry": {"coordinates":[-76.59111,-10.16389],"type":"Point"}
}