{
  "type": "Feature",
  "properties": {
    "gn:admin1_code":"10.0",
    "gn:admin2_code":"1005.0",
    "gn:admin3_code":"100504.0",
    "gn:asciiname":"Ragacha",
    "gn:country_code":"PE",
    "gn:dem":4038,
    "gn:feature_class":"P",
    "gn:feature_code":"PPL",
    "gn:name":"Ragacha",
    "gn:population":0,
    "gn:timezone":"America/Lima",
    "iso:country":"PE",
    "wof:name":"Ragacha",
    "wof:placetype":"locality"
},
  "geometry": {"coordinates":[-76.64146,-9.50858],"type":"Point"}
}