{
  "type": "Feature",
  "properties": {
    "gn:admin1_code":"22.0",
    "gn:admin2_code":"2203.0",
    "gn:admin3_code":"220305.0",
    "gn:asciiname":"Chahuarpampa",
    "gn:country_code":"PE",
    "gn:dem":406,
    "gn:feature_class":"P",
    "gn:feature_code":"PPL",
    "gn:name":"Chahuarpampa",
    "gn:population":0,
    "gn:timezone":"America/Lima",
    "iso:country":"PE",
    "name:spa_x_preferred":[
        "Chahuarpampa"
    ],
    "wof:name":"Chahuarpampa",
    "wof:placetype":"locality"
},
  "geometry": {"coordinates":[-76.70815,-6.54698],"type":"Point"}
}