{
  "type": "Feature",
  "properties": {
    "gn:admin1_code":"8",
    "gn:admin2_code":"806.0",
    "gn:admin3_code":"80608.0",
    "gn:asciiname":"Chacata",
    "gn:country_code":"PE",
    "gn:dem":3558,
    "gn:feature_class":"P",
    "gn:feature_code":"PPL",
    "gn:name":"Chacata",
    "gn:population":0,
    "gn:timezone":"America/Lima",
    "iso:country":"PE",
    "wof:name":"Chacata",
    "wof:placetype":"locality"
},
  "geometry": {"coordinates":[-71.41452,-14.11389],"type":"Point"}
}