{
  "type": "Feature",
  "properties": {
    "gn:admin1_code":"09",
    "gn:admin2_code":"906.0",
    "gn:admin3_code":"90607.0",
    "gn:asciiname":"Rangrapata",
    "gn:country_code":"PE",
    "gn:dem":4509,
    "gn:feature_class":"P",
    "gn:feature_code":"PPL",
    "gn:name":"Rangrapata",
    "gn:population":0,
    "gn:timezone":"America/Lima",
    "iso:country":"PE",
    "name:und_x_variant":[
        "Rangrapampa"
    ],
    "wof:name":"Rangrapata",
    "wof:placetype":"locality"
},
  "geometry": {"coordinates":[-74.68689999999999,-13.3301],"type":"Point"}
}