{
  "type": "Feature",
  "properties": {
    "gn:admin1_code":"9.0",
    "gn:admin2_code":"902.0",
    "gn:admin3_code":"90203.0",
    "gn:asciiname":"Quisira",
    "gn:country_code":"PE",
    "gn:dem":3844,
    "gn:feature_class":"P",
    "gn:feature_code":"PPL",
    "gn:name":"Quisira",
    "gn:population":0,
    "gn:timezone":"America/Lima",
    "iso:country":"PE",
    "wof:name":"Quisira",
    "wof:placetype":"locality"
},
  "geometry": {"coordinates":[-74.64914,-12.8064],"type":"Point"}
}