{
  "type": "Feature",
  "properties": {
    "gn:admin1_code":"4.0",
    "gn:admin2_code":"404.0",
    "gn:admin3_code":"40409.0",
    "gn:asciiname":"Juntaya",
    "gn:country_code":"PE",
    "gn:dem":4685,
    "gn:feature_class":"P",
    "gn:feature_code":"PPL",
    "gn:name":"Juntaya",
    "gn:population":0,
    "gn:timezone":"America/Lima",
    "iso:country":"PE",
    "name:spa_x_preferred":[
        "Juntaya"
    ],
    "wof:name":"Juntaya",
    "wof:placetype":"locality"
},
  "geometry": {"coordinates":[-72.23736,-15.04306],"type":"Point"}
}