{
  "type": "Feature",
  "properties": {
    "gn:admin1_code":"11.0",
    "gn:admin2_code":"1102.0",
    "gn:admin3_code":"110210.0",
    "gn:asciiname":"Guayabo",
    "gn:country_code":"PE",
    "gn:dem":91,
    "gn:feature_class":"P",
    "gn:feature_code":"PPLL",
    "gn:name":"Guayabo",
    "gn:population":0,
    "gn:timezone":"America/Lima",
    "iso:country":"PE",
    "wof:name":"Guayabo",
    "wof:placetype":"locality"
},
  "geometry": {"coordinates":[-76.14348000000003,-13.41932],"type":"Point"}
}