{
  "type": "Feature",
  "properties": {
    "gn:admin1_code":"16",
    "gn:admin2_code":"1605.0",
    "gn:admin3_code":"160502.0",
    "gn:asciiname":"San Lucas",
    "gn:country_code":"PE",
    "gn:dem":165,
    "gn:feature_class":"P",
    "gn:feature_code":"PPL",
    "gn:name":"San Lucas",
    "gn:population":0,
    "gn:timezone":"America/Lima",
    "iso:country":"PE",
    "wof:name":"San Lucas",
    "wof:placetype":"locality"
},
  "geometry": {"coordinates":[-74.34232,-6.92539],"type":"Point"}
}