{
  "type": "Feature",
  "properties": {
    "gn:admin1_code":"03",
    "gn:admin2_code":"307.0",
    "gn:admin3_code":"30704.0",
    "gn:asciiname":"Pampahuite",
    "gn:country_code":"PE",
    "gn:dem":3964,
    "gn:feature_class":"P",
    "gn:feature_code":"PPL",
    "gn:name":"Pampahuite",
    "gn:population":0,
    "gn:timezone":"America/Lima",
    "iso:country":"PE",
    "wof:name":"Pampahuite",
    "wof:placetype":"locality"
},
  "geometry": {"coordinates":[-72.53333000000001,-13.98333],"type":"Point"}
}