{
  "type": "Feature",
  "properties": {
    "gn:admin1_code":"11",
    "gn:admin2_code":"1104.0",
    "gn:admin3_code":"110402.0",
    "gn:asciiname":"Chillo",
    "gn:country_code":"PE",
    "gn:dem":320,
    "gn:feature_class":"P",
    "gn:feature_code":"PPL",
    "gn:name":"Chillo",
    "gn:population":0,
    "gn:timezone":"America/Lima",
    "iso:country":"PE",
    "name:und_x_variant":[
        "Chillo Hacienda",
        "Chillo"
    ],
    "wof:name":"Chillo",
    "wof:placetype":"locality"
},
  "geometry": {"coordinates":[-75.22395999999998,-14.57723],"type":"Point"}
}