{
  "type": "Feature",
  "properties": {
    "gn:admin1_code":"4",
    "gn:admin2_code":"406.0",
    "gn:admin3_code":"40603.0",
    "gn:asciiname":"Cala Cala",
    "gn:country_code":"PE",
    "gn:dem":4466,
    "gn:feature_class":"P",
    "gn:feature_code":"PPL",
    "gn:name":"Cala Cala",
    "gn:population":0,
    "gn:timezone":"America/Lima",
    "iso:country":"PE",
    "name:deu_x_preferred":[
        "Cala Cala"
    ],
    "name:zho_x_preferred":[
        "\u5361\u62c9\u5361\u62c9"
    ],
    "wof:name":"Cala Cala",
    "wof:placetype":"locality"
},
  "geometry": {"coordinates":[-71.94398000000002,-14.7527],"type":"Point"}
}