{
  "type": "Feature",
  "properties": {
    "gn:admin1_code":"8",
    "gn:admin2_code":"808.0",
    "gn:admin3_code":"80804.0",
    "gn:asciiname":"Alcamarine Muto",
    "gn:country_code":"PE",
    "gn:dem":4330,
    "gn:feature_class":"P",
    "gn:feature_code":"PPL",
    "gn:name":"Alcamarine Muto",
    "gn:population":0,
    "gn:timezone":"America/Lima",
    "iso:country":"PE",
    "wof:name":"Alcamarine Muto",
    "wof:placetype":"locality"
},
  "geometry": {"coordinates":[-71.14863000000003,-15.08851],"type":"Point"}
}