{
  "type": "Feature",
  "properties": {
    "gn:admin1_code":"5.0",
    "gn:admin2_code":"505.0",
    "gn:admin3_code":"50508.0",
    "gn:asciiname":"Jejra",
    "gn:country_code":"PE",
    "gn:dem":3049,
    "gn:feature_class":"P",
    "gn:feature_code":"PPL",
    "gn:name":"Jejra",
    "gn:population":0,
    "gn:timezone":"America/Lima",
    "iso:country":"PE",
    "wof:name":"Jejra",
    "wof:placetype":"locality"
},
  "geometry": {"coordinates":[-74.00346,-12.94076],"type":"Point"}
}