{
  "type": "Feature",
  "properties": {
    "gn:admin1_code":"02",
    "gn:admin2_code":"218.0",
    "gn:admin3_code":"21804.0",
    "gn:asciiname":"Malley",
    "gn:country_code":"PE",
    "gn:dem":2182,
    "gn:feature_class":"P",
    "gn:feature_code":"PPL",
    "gn:name":"Malley",
    "gn:population":0,
    "gn:timezone":"America/Lima",
    "iso:country":"PE",
    "name:und_x_variant":[
        "Mallay",
        "Malley"
    ],
    "wof:name":"Malley",
    "wof:placetype":"locality"
},
  "geometry": {"coordinates":[-78.17598000000002,-8.88288],"type":"Point"}
}