{
  "type": "Feature",
  "properties": {
    "gn:admin1_code":"06",
    "gn:admin2_code":"602.0",
    "gn:admin3_code":"60202.0",
    "gn:asciiname":"Algamarca",
    "gn:country_code":"PE",
    "gn:dem":2975,
    "gn:feature_class":"P",
    "gn:feature_code":"PPL",
    "gn:name":"Algamarca",
    "gn:population":0,
    "gn:timezone":"America/Lima",
    "iso:country":"PE",
    "name:und_x_variant":[
        "Algamarca Hacienda",
        "Algamarce Hacienda",
        "Algamarca"
    ],
    "wof:name":"Algamarca",
    "wof:placetype":"locality"
},
  "geometry": {"coordinates":[-78.24661999999999,-7.60903],"type":"Point"}
}