{
  "type": "Feature",
  "properties": {
    "gn:admin1_code":"01",
    "gn:admin2_code":"105.0",
    "gn:admin3_code":"10502.0",
    "gn:asciiname":"Camporredondo",
    "gn:country_code":"PE",
    "gn:dem":1754,
    "gn:feature_class":"P",
    "gn:feature_code":"PPL",
    "gn:name":"Camporredondo",
    "gn:population":0,
    "gn:timezone":"America/Lima",
    "iso:country":"PE",
    "name:und_x_variant":[
        "Cocohillo",
        "Campo Redondo",
        "Cocochillo",
        "Camporredondo"
    ],
    "wof:name":"Camporredondo",
    "wof:placetype":"locality"
},
  "geometry": {"coordinates":[-78.31974,-6.21472],"type":"Point"}
}