{
  "type": "Feature",
  "properties": {
    "gn:admin1_code":"11.0",
    "gn:admin2_code":"1101.0",
    "gn:admin3_code":"110104.0",
    "gn:asciiname":"La Pena",
    "gn:country_code":"PE",
    "gn:dem":356,
    "gn:feature_class":"P",
    "gn:feature_code":"PPLL",
    "gn:name":"La Pe\u00f1a",
    "gn:population":0,
    "gn:timezone":"America/Lima",
    "iso:country":"PE",
    "wof:name":"La Pena",
    "wof:placetype":"locality"
},
  "geometry": {"coordinates":[-75.6825,-14.33889],"type":"Point"}
}