{
  "type": "Feature",
  "properties": {
    "gn:admin1_code":"13",
    "gn:admin2_code":"1308.0",
    "gn:admin3_code":"130803.0",
    "gn:asciiname":"Conchamarca",
    "gn:country_code":"PE",
    "gn:dem":3145,
    "gn:feature_class":"P",
    "gn:feature_code":"PPL",
    "gn:name":"Conchamarca",
    "gn:population":0,
    "gn:timezone":"America/Lima",
    "iso:country":"PE",
    "wof:name":"Conchamarca",
    "wof:placetype":"locality"
},
  "geometry": {"coordinates":[-77.49194,-8.22278],"type":"Point"}
}