{
  "type": "Feature",
  "properties": {
    "gn:admin1_code":"20",
    "gn:admin2_code":"2003.0",
    "gn:admin3_code":"200304.0",
    "gn:asciiname":"Llamalam",
    "gn:country_code":"PE",
    "gn:dem":2207,
    "gn:feature_class":"P",
    "gn:feature_code":"PPL",
    "gn:name":"Llamalam",
    "gn:population":0,
    "gn:timezone":"America/Lima",
    "iso:country":"PE",
    "wof:name":"Llamalam",
    "wof:placetype":"locality"
},
  "geometry": {"coordinates":[-79.51666999999998,-5.58333],"type":"Point"}
}