{
  "type": "Feature",
  "properties": {
    "gn:admin1_code":"14",
    "gn:admin2_code":"1401.0",
    "gn:admin3_code":"140108.0",
    "gn:asciiname":"El Destino",
    "gn:country_code":"PE",
    "gn:dem":22,
    "gn:feature_class":"P",
    "gn:feature_code":"PPL",
    "gn:name":"El Destino",
    "gn:population":0,
    "gn:timezone":"America/Lima",
    "iso:country":"PE",
    "name:spa_x_preferred":[
        "El Destino"
    ],
    "name:spa_x_variant":[
        "Destino"
    ],
    "name:srp_x_preferred":[
        "\u0415\u043b \u0414\u0435\u0441\u0442\u0438\u043d\u043e"
    ],
    "wof:name":"El Destino",
    "wof:placetype":"locality"
},
  "geometry": {"coordinates":[-79.83314,-6.83953],"type":"Point"}
}