{
  "type": "Feature",
  "properties": {
    "gn:admin1_code":"12.0",
    "gn:admin2_code":"1205.0",
    "gn:admin3_code":"120503.0",
    "gn:asciiname":"Pisha Puquio",
    "gn:country_code":"PE",
    "gn:dem":4273,
    "gn:feature_class":"P",
    "gn:feature_code":"PPL",
    "gn:name":"Pisha Puquio",
    "gn:population":0,
    "gn:timezone":"America/Lima",
    "iso:country":"PE",
    "wof:name":"Pisha Puquio",
    "wof:placetype":"locality"
},
  "geometry": {"coordinates":[-76.19534,-11.10202],"type":"Point"}
}