{
  "type": "Feature",
  "properties": {
    "gn:admin1_code":"21",
    "gn:admin2_code":"2104.0",
    "gn:admin3_code":"210405.0",
    "gn:asciiname":"Vila Vilani",
    "gn:country_code":"PE",
    "gn:dem":3969,
    "gn:feature_class":"P",
    "gn:feature_code":"PPL",
    "gn:name":"Vila Vilani",
    "gn:population":0,
    "gn:timezone":"America/Lima",
    "iso:country":"PE",
    "wof:name":"Vila Vilani",
    "wof:placetype":"locality"
},
  "geometry": {"coordinates":[-69.40208,-16.88732000000001],"type":"Point"}
}