{
  "type": "Feature",
  "properties": {
    "gn:admin1_code":"10.0",
    "gn:admin2_code":"1011.0",
    "gn:admin3_code":"101103.0",
    "gn:asciiname":"Shulluyacu",
    "gn:country_code":"PE",
    "gn:dem":3513,
    "gn:feature_class":"P",
    "gn:feature_code":"PPL",
    "gn:name":"Shulluyacu",
    "gn:population":0,
    "gn:timezone":"America/Lima",
    "iso:country":"PE",
    "wof:name":"Shulluyacu",
    "wof:placetype":"locality"
},
  "geometry": {"coordinates":[-76.62845,-9.91054],"type":"Point"}
}