{
  "type": "Feature",
  "properties": {
    "gn:admin1_code":"15",
    "gn:admin2_code":"1510.0",
    "gn:admin3_code":"151021.0",
    "gn:asciiname":"Pinos",
    "gn:country_code":"PE",
    "gn:dem":3519,
    "gn:feature_class":"P",
    "gn:feature_code":"PPL",
    "gn:name":"Pi\u00f1os",
    "gn:population":0,
    "gn:timezone":"America/Lima",
    "iso:country":"PE",
    "wof:name":"Pinos",
    "wof:placetype":"locality"
},
  "geometry": {"coordinates":[-75.82833000000002,-12.31278],"type":"Point"}
}