{
  "type": "Feature",
  "properties": {
    "gn:admin1_code":"12",
    "gn:admin2_code":"1209.0",
    "gn:admin3_code":"120909.0",
    "gn:asciiname":"Lurincocha",
    "gn:country_code":"PE",
    "gn:dem":4444,
    "gn:feature_class":"P",
    "gn:feature_code":"PPL",
    "gn:name":"Lurincocha",
    "gn:population":0,
    "gn:timezone":"America/Lima",
    "iso:country":"PE",
    "wof:name":"Lurincocha",
    "wof:placetype":"locality"
},
  "geometry": {"coordinates":[-75.57861,-12.30222],"type":"Point"}
}