{
  "type": "Feature",
  "properties": {
    "gn:admin1_code":"9.0",
    "gn:admin2_code":"901.0",
    "gn:admin3_code":"90101.0",
    "gn:asciiname":"Huacluto",
    "gn:country_code":"PE",
    "gn:dem":4490,
    "gn:feature_class":"P",
    "gn:feature_code":"PPL",
    "gn:name":"Huacluto",
    "gn:population":0,
    "gn:timezone":"America/Lima",
    "iso:country":"PE",
    "wof:name":"Huacluto",
    "wof:placetype":"locality"
},
  "geometry": {"coordinates":[-74.94821999999998,-12.87069],"type":"Point"}
}