{
  "type": "Feature",
  "properties": {
    "gn:admin1_code":"9.0",
    "gn:admin2_code":"905.0",
    "gn:asciiname":"Arallasja",
    "gn:country_code":"PE",
    "gn:dem":3057,
    "gn:feature_class":"P",
    "gn:feature_code":"PPL",
    "gn:name":"Arallasja",
    "gn:population":0,
    "gn:timezone":"America/Lima",
    "iso:country":"PE",
    "wof:name":"Arallasja",
    "wof:placetype":"locality"
},
  "geometry": {"coordinates":[-74.44617,-12.75749],"type":"Point"}
}