{
  "type": "Feature",
  "properties": {
    "gn:admin1_code":"9",
    "gn:admin2_code":"906.0",
    "gn:admin3_code":"90607.0",
    "gn:asciiname":"Iscutana",
    "gn:country_code":"PE",
    "gn:dem":4341,
    "gn:feature_class":"P",
    "gn:feature_code":"PPL",
    "gn:name":"Iscutana",
    "gn:population":0,
    "gn:timezone":"America/Lima",
    "iso:country":"PE",
    "wof:name":"Iscutana",
    "wof:placetype":"locality"
},
  "geometry": {"coordinates":[-75.05333,-13.58056],"type":"Point"}
}