{
  "type": "Feature",
  "properties": {
    "gn:admin1_code":"8.0",
    "gn:admin2_code":"803.0",
    "gn:admin3_code":"80304.0",
    "gn:asciiname":"Huantaro",
    "gn:country_code":"PE",
    "gn:dem":2442,
    "gn:feature_class":"P",
    "gn:feature_code":"PPL",
    "gn:name":"Huantaro",
    "gn:population":0,
    "gn:timezone":"America/Lima",
    "iso:country":"PE",
    "wof:name":"Huantaro",
    "wof:placetype":"locality"
},
  "geometry": {"coordinates":[-72.23756,-13.67527],"type":"Point"}
}