{
  "type": "Feature",
  "properties": {
    "gn:admin1_code":"12.0",
    "gn:admin2_code":"1202.0",
    "gn:admin3_code":"120206.0",
    "gn:asciiname":"Ayayoc",
    "gn:country_code":"PE",
    "gn:dem":4359,
    "gn:feature_class":"P",
    "gn:feature_code":"PPL",
    "gn:name":"Ayayoc",
    "gn:population":0,
    "gn:timezone":"America/Lima",
    "iso:country":"PE",
    "wof:name":"Ayayoc",
    "wof:placetype":"locality"
},
  "geometry": {"coordinates":[-75.05481999999998,-11.83587],"type":"Point"}
}