{
  "type": "Feature",
  "properties": {
    "gn:admin1_code":"09",
    "gn:admin2_code":"906.0",
    "gn:admin3_code":"90612.0",
    "gn:asciiname":"Chuchaucruz",
    "gn:country_code":"PE",
    "gn:dem":3687,
    "gn:feature_class":"P",
    "gn:feature_code":"PPL",
    "gn:name":"Chuchaucruz",
    "gn:population":0,
    "gn:timezone":"America/Lima",
    "iso:country":"PE",
    "name:und_x_variant":[
        "Chuchau Cruz",
        "Chuchaucruz"
    ],
    "wof:name":"Chuchaucruz",
    "wof:placetype":"locality"
},
  "geometry": {"coordinates":[-75.22499999999999,-13.96861],"type":"Point"}
}