{
  "type": "Feature",
  "properties": {
    "gn:admin1_code":"21.0",
    "gn:admin2_code":"2112.0",
    "gn:asciiname":"Kallapapata",
    "gn:country_code":"PE",
    "gn:dem":3870,
    "gn:feature_class":"P",
    "gn:feature_code":"PPL",
    "gn:name":"Kallapapata",
    "gn:population":0,
    "gn:timezone":"America/Lima",
    "iso:country":"PE",
    "name:spa_x_preferred":[
        "Kallapapata"
    ],
    "wof:name":"Kallapapata",
    "wof:placetype":"locality"
},
  "geometry": {"coordinates":[-69.46065,-14.4949],"type":"Point"}
}