{
  "type": "Feature",
  "properties": {
    "gn:admin1_code":"06",
    "gn:admin2_code":"608.0",
    "gn:admin3_code":"60810.0",
    "gn:asciiname":"Molle",
    "gn:country_code":"PE",
    "gn:dem":1993,
    "gn:feature_class":"P",
    "gn:feature_code":"PPL",
    "gn:name":"Molle",
    "gn:population":0,
    "gn:timezone":"America/Lima",
    "iso:country":"PE",
    "name:deu_x_preferred":[
        "Molle"
    ],
    "name:swe_x_preferred":[
        "Molle"
    ],
    "wof:name":"Molle",
    "wof:placetype":"locality"
},
  "geometry": {"coordinates":[-79.31953,-5.76113],"type":"Point"}
}