{
  "type": "Feature",
  "properties": {
    "gn:admin1_code":"15.0",
    "gn:admin2_code":"1501.0",
    "gn:admin3_code":"150129.0",
    "gn:asciiname":"Fundo Chimbomba",
    "gn:country_code":"PE",
    "gn:dem":395,
    "gn:feature_class":"P",
    "gn:feature_code":"PPL",
    "gn:name":"Fundo Chimbomba",
    "gn:population":0,
    "gn:timezone":"America/Lima",
    "iso:country":"PE",
    "name:spa_x_preferred":[
        "Fundo Chimbomba"
    ],
    "wof:name":"Fundo Chimbomba",
    "wof:placetype":"locality"
},
  "geometry": {"coordinates":[-76.70095000000001,-12.34501],"type":"Point"}
}