{
  "type": "Feature",
  "properties": {
    "gn:admin1_code":"12.0",
    "gn:admin2_code":"1201.0",
    "gn:asciiname":"Chilifruta",
    "gn:country_code":"PE",
    "gn:dem":3187,
    "gn:feature_class":"P",
    "gn:feature_code":"PPL",
    "gn:name":"Chilifruta",
    "gn:population":0,
    "gn:timezone":"America/Lima",
    "iso:country":"PE",
    "wof:name":"Chilifruta",
    "wof:placetype":"locality"
},
  "geometry": {"coordinates":[-74.89995999999999,-12.00643],"type":"Point"}
}