{
  "type": "Feature",
  "properties": {
    "gn:admin1_code":"16",
    "gn:admin2_code":"1603.0",
    "gn:admin3_code":"160303.0",
    "gn:asciiname":"Berlin",
    "gn:country_code":"PE",
    "gn:dem":126,
    "gn:feature_class":"P",
    "gn:feature_code":"PPL",
    "gn:name":"Berl\u00edn",
    "gn:population":0,
    "gn:timezone":"America/Lima",
    "iso:country":"PE",
    "wof:name":"Berlin",
    "wof:placetype":"locality"
},
  "geometry": {"coordinates":[-74.40000000000001,-3.83333],"type":"Point"}
}