{
  "type": "Feature",
  "properties": {
    "gn:admin1_code":"9.0",
    "gn:admin2_code":"903.0",
    "gn:admin3_code":"90301.0",
    "gn:asciiname":"Chegragra",
    "gn:country_code":"PE",
    "gn:dem":4345,
    "gn:feature_class":"P",
    "gn:feature_code":"PPL",
    "gn:name":"Chegragra",
    "gn:population":0,
    "gn:timezone":"America/Lima",
    "iso:country":"PE",
    "wof:name":"Chegragra",
    "wof:placetype":"locality"
},
  "geometry": {"coordinates":[-74.86058,-13.0944],"type":"Point"}
}