{
  "type": "Feature",
  "properties": {
    "gn:admin1_code":"6",
    "gn:admin2_code":"609.0",
    "gn:admin3_code":"60901.0",
    "gn:asciiname":"Calabozo",
    "gn:country_code":"PE",
    "gn:dem":1405,
    "gn:feature_class":"P",
    "gn:feature_code":"PPL",
    "gn:name":"Calabozo",
    "gn:population":0,
    "gn:timezone":"America/Lima",
    "iso:country":"PE",
    "wof:name":"Calabozo",
    "wof:placetype":"locality"
},
  "geometry": {"coordinates":[-79.01813,-5.17605],"type":"Point"}
}