{
  "type": "Feature",
  "properties": {
    "gn:admin1_code":"6",
    "gn:admin2_code":"609.0",
    "gn:admin3_code":"60901.0",
    "gn:asciiname":"Calabozo",
    "gn:country_code":"PE",
    "gn:dem":1405,
    "gn:feature_class":"P",
    "gn:feature_code":"PPL",
    "gn:name":"Calabozo",
    "gn:population":0,
    "gn:timezone":"America/Lima",
    "iso:country":"PE",
    "name:ceb_x_preferred":[
        "Calabozo"
    ],
    "name:deu_x_preferred":[
        "Calabozo"
    ],
    "name:epo_x_preferred":[
        "Calabozo"
    ],
    "name:fra_x_preferred":[
        "Calabozo"
    ],
    "name:ita_x_preferred":[
        "Calabozo"
    ],
    "name:jpn_x_preferred":[
        "\u30ab\u30e9\u30dc\u30bd"
    ],
    "name:kat_x_preferred":[
        "\u10d9\u10d0\u10da\u10d0\u10d1\u10dd\u10e1\u10dd"
    ],
    "name:lit_x_preferred":[
        "Kalabosas"
    ],
    "name:pol_x_preferred":[
        "Calabozo"
    ],
    "name:por_x_preferred":[
        "Calabozo"
    ],
    "name:spa_x_preferred":[
        "Calabozo"
    ],
    "name:tat_x_preferred":[
        "\u041a\u0430\u043b\u0430\u0431\u043e\u0441\u043e"
    ],
    "name:vol_x_preferred":[
        "Calabozo"
    ],
    "name:zho_x_preferred":[
        "\u5361\u62c9\u6c83\u7d22"
    ],
    "wof:name":"Calabozo",
    "wof:placetype":"locality"
},
  "geometry": {"coordinates":[-79.01813,-5.17605],"type":"Point"}
}