{
  "type": "Feature",
  "properties": {
    "gn:admin1_code":"03",
    "gn:admin2_code":"305.0",
    "gn:admin3_code":"30501.0",
    "gn:asciiname":"Casahuasa",
    "gn:country_code":"PE",
    "gn:dem":4364,
    "gn:feature_class":"P",
    "gn:feature_code":"PPL",
    "gn:name":"Casahuasa",
    "gn:population":0,
    "gn:timezone":"America/Lima",
    "iso:country":"PE",
    "wof:name":"Casahuasa",
    "wof:placetype":"locality"
},
  "geometry": {"coordinates":[-72.28333000000001,-13.96667],"type":"Point"}
}