{
  "type": "Feature",
  "properties": {
    "gn:admin1_code":"1",
    "gn:admin2_code":"105.0",
    "gn:admin3_code":"10515.0",
    "gn:asciiname":"La Playa",
    "gn:country_code":"PE",
    "gn:dem":987,
    "gn:feature_class":"P",
    "gn:feature_code":"PPL",
    "gn:name":"La Playa",
    "gn:population":0,
    "gn:timezone":"America/Lima",
    "iso:country":"PE",
    "wof:name":"La Playa",
    "wof:placetype":"locality"
},
  "geometry": {"coordinates":[-78.27774000000002,-6.26536],"type":"Point"}
}