{
  "type": "Feature",
  "properties": {
    "gn:admin1_code":"17.0",
    "gn:admin2_code":"1703.0",
    "gn:asciiname":"Miguel Silva",
    "gn:country_code":"PE",
    "gn:dem":300,
    "gn:feature_class":"P",
    "gn:feature_code":"PPL",
    "gn:name":"Miguel Silva",
    "gn:population":0,
    "gn:timezone":"America/Lima",
    "iso:country":"PE",
    "name:spa_x_preferred":[
        "Miguel Silva"
    ],
    "wof:name":"Miguel Silva",
    "wof:placetype":"locality"
},
  "geometry": {"coordinates":[-69.15581999999999,-11.80602],"type":"Point"}
}