{
  "type": "Feature",
  "properties": {
    "gn:admin1_code":"21",
    "gn:admin2_code":"2105.0",
    "gn:admin3_code":"210502.0",
    "gn:asciiname":"Pallquipina",
    "gn:country_code":"PE",
    "gn:dem":4463,
    "gn:feature_class":"P",
    "gn:feature_code":"PPL",
    "gn:name":"Pallquipi\u00f1a",
    "gn:population":0,
    "gn:timezone":"America/Lima",
    "iso:country":"PE",
    "wof:name":"Pallquipina",
    "wof:placetype":"locality"
},
  "geometry": {"coordinates":[-69.76855,-17.06971],"type":"Point"}
}