{
  "type": "Feature",
  "properties": {
    "gn:admin1_code":"15",
    "gn:admin2_code":"1510.0",
    "gn:admin3_code":"151032.0",
    "gn:asciiname":"Tambopata",
    "gn:country_code":"PE",
    "gn:dem":3776,
    "gn:feature_class":"P",
    "gn:feature_code":"PPL",
    "gn:name":"Tambopata",
    "gn:population":0,
    "gn:timezone":"America/Lima",
    "iso:country":"PE",
    "wof:name":"Tambopata",
    "wof:placetype":"locality"
},
  "geometry": {"coordinates":[-75.76104000000002,-12.9179],"type":"Point"}
}