{
  "type": "Feature",
  "properties": {
    "gn:country":"PE",
    "gn:fcode":"PPLA3",
    "gn:pop":10066,
    "iso:country":"PE",
    "name:deu_x_preferred":[
        "Salaverry"
    ],
    "name:eng_x_preferred":[
        "Salaverry"
    ],
    "name:fra_x_preferred":[
        "Salaverry"
    ],
    "name:nld_x_preferred":[
        "Salaverry"
    ],
    "name:por_x_preferred":[
        "Salaverry"
    ],
    "name:spa_x_preferred":[
        "Salaverry"
    ],
    "name:unk_x_variant":[
        "Puerto de Salaverry"
    ],
    "ne:ADM0CAP":0.0,
    "ne:ADM0NAME":"Peru",
    "ne:ADM0_A3":"PER",
    "ne:ADM1NAME":"La Libertad",
    "ne:ADMIN1_COD":13,
    "ne:CAPALT":0,
    "ne:CHANGED":1,
    "ne:CHECKME":0,
    "ne:COMPARE":0,
    "ne:DIFFASCII":0,
    "ne:DIFFNOTE":"Changed scale rank.",
    "ne:ELEVATION":0.0,
    "ne:FEATURECLA":"Populated place",
    "ne:FEATURE_CL":"P",
    "ne:FEATURE_CO":"PPL",
    "ne:GEONAMEID":3692747,
    "ne:GEONAMESNO":"Geonames ascii name + lat.d + long.d matching.",
    "ne:GN_ASCII":"Salaverry",
    "ne:GN_POP":10066,
    "ne:GTOPO30":70.0,
    "ne:ISO_A2":"PE",
    "ne:LABELRANK":5,
    "ne:LATITUDE":-8.220029,
    "ne:LONGITUDE":-78.989995,
    "ne:LS_MATCH":1,
    "ne:LS_NAME":"Salaverry",
    "ne:MAX_AREAKM":3.0,
    "ne:MAX_AREAMI":1.0,
    "ne:MAX_BBXMAX":-78.966667,
    "ne:MAX_BBXMIN":-78.983333,
    "ne:MAX_BBYMAX":-8.208333,
    "ne:MAX_BBYMIN":-8.233333,
    "ne:MAX_NATSCA":20.0,
    "ne:MAX_PERKM":9.0,
    "ne:MAX_PERMI":6.0,
    "ne:MAX_POP10":4390,
    "ne:MAX_POP20":4390,
    "ne:MAX_POP300":0,
    "ne:MAX_POP310":0,
    "ne:MAX_POP50":0,
    "ne:MEAN_BBXC":-78.977083,
    "ne:MEAN_BBYC":-8.220833,
    "ne:MEGACITY":0,
    "ne:MIN_AREAKM":3.0,
    "ne:MIN_AREAMI":1.0,
    "ne:MIN_BBXMAX":-78.966667,
    "ne:MIN_BBXMIN":-78.983333,
    "ne:MIN_BBYMAX":-8.208333,
    "ne:MIN_BBYMIN":-8.233333,
    "ne:MIN_PERKM":9.0,
    "ne:MIN_PERMI":6.0,
    "ne:NAME":"Salaverry",
    "ne:NAMEASCII":"Salaverry",
    "ne:NAMEDIFF":0,
    "ne:NATSCALE":30,
    "ne:POP1950":0,
    "ne:POP1955":0,
    "ne:POP1960":0,
    "ne:POP1965":0,
    "ne:POP1970":0,
    "ne:POP1975":0,
    "ne:POP1980":0,
    "ne:POP1985":0,
    "ne:POP1990":0,
    "ne:POP1995":0,
    "ne:POP2000":0,
    "ne:POP2005":0,
    "ne:POP2010":0,
    "ne:POP2015":0,
    "ne:POP2020":0,
    "ne:POP2025":0,
    "ne:POP2050":0,
    "ne:POP_MAX":10066,
    "ne:POP_MIN":4390,
    "ne:POP_OTHER":0,
    "ne:RANK_MAX":6,
    "ne:RANK_MIN":4,
    "ne:SCALERANK":6,
    "ne:SOV0NAME":"Peru",
    "ne:SOV_A3":"PER",
    "ne:TIMEZONE":"America/Lima",
    "ne:UN_FID":0,
    "ne:UN_LAT":0.0,
    "ne:UN_LONG":0.0,
    "ne:WORLDCITY":0,
    "qs:name":"Salaverry",
    "qs:photos_9r":0,
    "qs:photos_sr":0,
    "qs:pop_sr":"6",
    "wd:wordcount":103,
    "wof:name":"Salaverry",
    "wof:placetype":"locality",
    "wof:population":10066
},
  "geometry": {"coordinates":[-78.96666999999999,-8.23333],"type":"Point"}
}