{
  "type": "Feature",
  "properties": {
    "gn:admin1_code":"17.0",
    "gn:admin2_code":"1701.0",
    "gn:asciiname":"Alto Chorrillos",
    "gn:country_code":"PE",
    "gn:dem":193,
    "gn:feature_class":"P",
    "gn:feature_code":"PPL",
    "gn:name":"Alto Chorrillos",
    "gn:population":0,
    "gn:timezone":"America/Lima",
    "iso:country":"PE",
    "name:spa_x_preferred":[
        "Alto Chorrillos"
    ],
    "wof:name":"Alto Chorrillos",
    "wof:placetype":"locality"
},
  "geometry": {"coordinates":[-69.291,-12.58691],"type":"Point"}
}