{
  "type": "Feature",
  "properties": {
    "gn:admin1_code":"03",
    "gn:admin2_code":"303.0",
    "gn:admin3_code":"30305.0",
    "gn:asciiname":"Huancaray",
    "gn:country_code":"PE",
    "gn:dem":3398,
    "gn:feature_class":"P",
    "gn:feature_code":"PPL",
    "gn:name":"Huancaray",
    "gn:population":0,
    "gn:timezone":"America/Lima",
    "iso:country":"PE",
    "wof:name":"Huancaray",
    "wof:placetype":"locality"
},
  "geometry": {"coordinates":[-72.55,-14.28333],"type":"Point"}
}