{
  "type": "Feature",
  "properties": {
    "gn:admin1_code":"5",
    "gn:admin2_code":"508.0",
    "gn:admin3_code":"50808.0",
    "gn:asciiname":"San Javier de Alpabamba",
    "gn:country_code":"PE",
    "gn:dem":2911,
    "gn:feature_class":"P",
    "gn:feature_code":"PPL",
    "gn:name":"San Javier de Alpabamba",
    "gn:population":0,
    "gn:timezone":"America/Lima",
    "iso:country":"PE",
    "name:und_x_variant":[
        "San Javier",
        "Alpabamba",
        "Allpabamba",
        "San Javier de Alpabamba"
    ],
    "wof:name":"San Javier de Alpabamba",
    "wof:placetype":"locality"
},
  "geometry": {"coordinates":[-73.31416999999998,-15.06144],"type":"Point"}
}