{
  "type": "Feature",
  "properties": {
    "gn:admin1_code":"02",
    "gn:admin2_code":"218.0",
    "gn:admin3_code":"21804.0",
    "gn:asciiname":"Huanchay",
    "gn:country_code":"PE",
    "gn:dem":2365,
    "gn:feature_class":"P",
    "gn:feature_code":"PPL",
    "gn:name":"Huanchay",
    "gn:population":0,
    "gn:timezone":"America/Lima",
    "iso:country":"PE",
    "wof:name":"Huanchay",
    "wof:placetype":"locality"
},
  "geometry": {"coordinates":[-78.16667,-8.86667],"type":"Point"}
}