{
  "type": "Feature",
  "properties": {
    "gn:admin1_code":"24",
    "gn:admin2_code":"2401.0",
    "gn:admin3_code":"240103.0",
    "gn:asciiname":"Cruz de Pizarro",
    "gn:country_code":"PE",
    "gn:dem":27,
    "gn:feature_class":"P",
    "gn:feature_code":"PPL",
    "gn:name":"Cruz de Pizarro",
    "gn:population":0,
    "gn:timezone":"America/Lima",
    "iso:country":"PE",
    "wof:name":"Cruz de Pizarro",
    "wof:placetype":"locality"
},
  "geometry": {"coordinates":[-80.59999999999999,-3.65],"type":"Point"}
}