{
  "type": "Feature",
  "properties": {
    "gn:admin1_code":"21",
    "gn:admin2_code":"2112.0",
    "gn:admin3_code":"211210.0",
    "gn:asciiname":"Alto Pauji",
    "gn:country_code":"PE",
    "gn:dem":1055,
    "gn:feature_class":"P",
    "gn:feature_code":"PPL",
    "gn:name":"Alto Pauji",
    "gn:population":0,
    "gn:timezone":"America/Lima",
    "iso:country":"PE",
    "name:spa_x_preferred":[
        "Alto Pauji"
    ],
    "wof:name":"Alto Pauji",
    "wof:placetype":"locality"
},
  "geometry": {"coordinates":[-68.99316999999999,-13.98944],"type":"Point"}
}