{
  "type": "Feature",
  "properties": {
    "gn:admin1_code":"14",
    "gn:admin2_code":"1403.0",
    "gn:admin3_code":"140307.0",
    "gn:asciiname":"El Papayo",
    "gn:country_code":"PE",
    "gn:dem":136,
    "gn:feature_class":"P",
    "gn:feature_code":"PPL",
    "gn:name":"El Papayo",
    "gn:population":0,
    "gn:timezone":"America/Lima",
    "iso:country":"PE",
    "wof:name":"El Papayo",
    "wof:placetype":"locality"
},
  "geometry": {"coordinates":[-79.69234,-6.18],"type":"Point"}
}