{
  "type": "Feature",
  "properties": {
    "gn:admin1_code":"23",
    "gn:admin2_code":"2302.0",
    "gn:admin3_code":"230201.0",
    "gn:asciiname":"Suches",
    "gn:country_code":"PE",
    "gn:dem":4481,
    "gn:feature_class":"P",
    "gn:feature_code":"PPL",
    "gn:name":"Suches",
    "gn:population":0,
    "gn:timezone":"America/Lima",
    "iso:country":"PE",
    "wof:name":"Suches",
    "wof:placetype":"locality"
},
  "geometry": {"coordinates":[-70.38884,-16.94034],"type":"Point"}
}