{
  "type": "Feature",
  "properties": {
    "gn:admin1_code":"12.0",
    "gn:admin2_code":"1208.0",
    "gn:admin3_code":"120802.0",
    "gn:asciiname":"Allarac",
    "gn:country_code":"PE",
    "gn:dem":3829,
    "gn:feature_class":"P",
    "gn:feature_code":"PPL",
    "gn:name":"Allarac",
    "gn:population":0,
    "gn:timezone":"America/Lima",
    "iso:country":"PE",
    "wof:name":"Allarac",
    "wof:placetype":"locality"
},
  "geometry": {"coordinates":[-75.81158000000001,-11.68526],"type":"Point"}
}