{
  "type": "Feature",
  "properties": {
    "gn:admin1_code":"21",
    "gn:admin2_code":"2104.0",
    "gn:admin3_code":"210402.0",
    "gn:asciiname":"Quintuvincalla",
    "gn:country_code":"PE",
    "gn:dem":3829,
    "gn:feature_class":"P",
    "gn:feature_code":"PPL",
    "gn:name":"Quintuvincalla",
    "gn:population":0,
    "gn:timezone":"America/Lima",
    "iso:country":"PE",
    "wof:name":"Quintuvincalla",
    "wof:placetype":"locality"
},
  "geometry": {"coordinates":[-69.04030999999999,-16.59679],"type":"Point"}
}