{
  "type": "Feature",
  "properties": {
    "gn:admin1_code":"21",
    "gn:admin2_code":"2111.0",
    "gn:admin3_code":"211104.0",
    "gn:asciiname":"Hacienda Ayagache",
    "gn:country_code":"PE",
    "gn:dem":3848,
    "gn:feature_class":"P",
    "gn:feature_code":"PPL",
    "gn:name":"Hacienda Ayagache",
    "gn:population":0,
    "gn:timezone":"America/Lima",
    "iso:country":"PE",
    "wof:name":"Hacienda Ayagache",
    "wof:placetype":"locality"
},
  "geometry": {"coordinates":[-70.20952,-15.58457],"type":"Point"}
}