{
  "type": "Feature",
  "properties": {
    "gn:admin1_code":"12",
    "gn:admin2_code":"1201.0",
    "gn:admin3_code":"120108.0",
    "gn:asciiname":"Pititayo",
    "gn:country_code":"PE",
    "gn:dem":3674,
    "gn:feature_class":"P",
    "gn:feature_code":"PPL",
    "gn:name":"P\u00edtitayo",
    "gn:population":0,
    "gn:timezone":"America/Lima",
    "iso:country":"PE",
    "wof:name":"Pititayo",
    "wof:placetype":"locality"
},
  "geometry": {"coordinates":[-75.34125,-12.30878],"type":"Point"}
}