{
  "type": "Feature",
  "properties": {
    "gn:admin1_code":"14",
    "gn:admin2_code":"1403.0",
    "gn:admin3_code":"140310.0",
    "gn:asciiname":"Cueva la Yegua",
    "gn:country_code":"PE",
    "gn:dem":581,
    "gn:feature_class":"P",
    "gn:feature_code":"PPL",
    "gn:name":"Cueva la Yegua",
    "gn:population":0,
    "gn:timezone":"America/Lima",
    "iso:country":"PE",
    "wof:name":"Cueva la Yegua",
    "wof:placetype":"locality"
},
  "geometry": {"coordinates":[-79.55313000000002,-6.24846],"type":"Point"}
}