{
  "type": "Feature",
  "properties": {
    "gn:admin1_code":"11",
    "gn:admin2_code":"1105.0",
    "gn:admin3_code":"110502.0",
    "gn:asciiname":"Cocamasana",
    "gn:country_code":"PE",
    "gn:dem":892,
    "gn:feature_class":"P",
    "gn:feature_code":"PPL",
    "gn:name":"Cocamasana",
    "gn:population":0,
    "gn:timezone":"America/Lima",
    "iso:country":"PE",
    "wof:name":"Cocamasana",
    "wof:placetype":"locality"
},
  "geometry": {"coordinates":[-75.68675,-13.63301],"type":"Point"}
}