{
  "type": "Feature",
  "properties": {
    "gn:admin1_code":"13.0",
    "gn:admin2_code":"1308.0",
    "gn:admin3_code":"130812.0",
    "gn:asciiname":"Aliso Pampa",
    "gn:country_code":"PE",
    "gn:dem":3274,
    "gn:feature_class":"P",
    "gn:feature_code":"PPL",
    "gn:name":"Aliso Pampa",
    "gn:population":0,
    "gn:timezone":"America/Lima",
    "iso:country":"PE",
    "wof:name":"Aliso Pampa",
    "wof:placetype":"locality"
},
  "geometry": {"coordinates":[-77.42556,-8.2975],"type":"Point"}
}