{
  "type": "Feature",
  "properties": {
    "gn:admin1_code":"9",
    "gn:admin2_code":"906.0",
    "gn:admin3_code":"90609.0",
    "gn:asciiname":"Huaycura",
    "gn:country_code":"PE",
    "gn:dem":2715,
    "gn:feature_class":"P",
    "gn:feature_code":"PPL",
    "gn:name":"Huaycura",
    "gn:population":0,
    "gn:timezone":"America/Lima",
    "iso:country":"PE",
    "wof:name":"Huaycura",
    "wof:placetype":"locality"
},
  "geometry": {"coordinates":[-75.33083000000001,-13.54139],"type":"Point"}
}