{
  "type": "Feature",
  "properties": {
    "gn:admin1_code":"4",
    "gn:admin2_code":"405.0",
    "gn:admin3_code":"40504.0",
    "gn:asciiname":"Chita",
    "gn:country_code":"PE",
    "gn:dem":4567,
    "gn:feature_class":"P",
    "gn:feature_code":"PPL",
    "gn:name":"Chita",
    "gn:population":0,
    "gn:timezone":"America/Lima",
    "iso:country":"PE",
    "name:ceb_x_preferred":[
        "Chita"
    ],
    "name:deu_x_preferred":[
        "Chita"
    ],
    "name:fas_x_preferred":[
        "\u0686\u06cc\u062a\u0627"
    ],
    "name:glg_x_preferred":[
        "Chita"
    ],
    "name:heb_x_preferred":[
        "\u05e6'\u05d9\u05d8\u05d4"
    ],
    "name:ita_x_preferred":[
        "Chita"
    ],
    "name:kor_x_preferred":[
        "\uce58\ud0c0"
    ],
    "name:lat_x_preferred":[
        "Tschita"
    ],
    "name:nds_x_preferred":[
        "Chita"
    ],
    "name:nld_x_preferred":[
        "Chita"
    ],
    "name:por_x_preferred":[
        "Chita"
    ],
    "name:rus_x_preferred":[
        "\u0427\u0438\u0442\u0430"
    ],
    "name:sco_x_preferred":[
        "Chita"
    ],
    "name:spa_x_preferred":[
        "Chita"
    ],
    "name:swe_x_preferred":[
        "Chita"
    ],
    "wof:name":"Chita",
    "wof:placetype":"locality"
},
  "geometry": {"coordinates":[-71.35356,-15.46362],"type":"Point"}
}