{
  "type": "Feature",
  "properties": {
    "gn:admin1_code":"01",
    "gn:admin2_code":"104.0",
    "gn:admin3_code":"10402.0",
    "gn:asciiname":"Puesto de Vigilancia Tres Alfonso Ugarte",
    "gn:country_code":"PE",
    "gn:dem":1264,
    "gn:feature_class":"P",
    "gn:feature_code":"PPL",
    "gn:name":"Puesto de Vigilancia Tres Alfonso Ugarte",
    "gn:population":0,
    "gn:timezone":"America/Lima",
    "iso:country":"PE",
    "name:und_x_variant":[
        "Puesto de Vigilancia 3 Alfonso Ugarte",
        "Puesto de Vigilancia Tres Alfonso Ugarte"
    ],
    "wof:name":"Puesto de Vigilancia Tres Alfonso Ugarte",
    "wof:placetype":"locality"
},
  "geometry": {"coordinates":[-78.4233,-3.90657],"type":"Point"}
}