{
  "type": "Feature",
  "properties": {
    "gn:admin1_code":"5",
    "gn:admin2_code":"506.0",
    "gn:admin3_code":"50604.0",
    "gn:asciiname":"Ayaorjo",
    "gn:country_code":"PE",
    "gn:dem":3523,
    "gn:feature_class":"P",
    "gn:feature_code":"PPL",
    "gn:name":"Ayaorjo",
    "gn:population":0,
    "gn:timezone":"America/Lima",
    "iso:country":"PE",
    "wof:name":"Ayaorjo",
    "wof:placetype":"locality"
},
  "geometry": {"coordinates":[-73.96889,-14.39167],"type":"Point"}
}