{
  "type": "Feature",
  "properties": {
    "gn:admin1_code":"19.0",
    "gn:admin2_code":"1903.0",
    "gn:asciiname":"Comunidad Nativa Septimo Unidos",
    "gn:country_code":"PE",
    "gn:dem":371,
    "gn:feature_class":"P",
    "gn:feature_code":"PPL",
    "gn:name":"Comunidad Nativa Septimo Unidos",
    "gn:population":0,
    "gn:timezone":"America/Lima",
    "iso:country":"PE",
    "name:spa_x_preferred":[
        "Comunidad Nativa Septimo Unidos"
    ],
    "wof:name":"Comunidad Nativa Septimo Unidos",
    "wof:placetype":"locality"
},
  "geometry": {"coordinates":[-74.90633000000003,-10.51797],"type":"Point"}
}