{
  "type": "Feature",
  "properties": {
    "gn:admin1_code":"10.0",
    "gn:admin2_code":"1004.0",
    "gn:admin3_code":"100401.0",
    "gn:asciiname":"Rachamachay",
    "gn:country_code":"PE",
    "gn:dem":2971,
    "gn:feature_class":"P",
    "gn:feature_code":"PPL",
    "gn:name":"Rachamachay",
    "gn:population":0,
    "gn:timezone":"America/Lima",
    "iso:country":"PE",
    "wof:name":"Rachamachay",
    "wof:placetype":"locality"
},
  "geometry": {"coordinates":[-76.96134000000001,-9.02903],"type":"Point"}
}