{
  "type": "Feature",
  "properties": {
    "iso:country":"PE",
    "name:aym_x_preferred":[
        "Chukuwitu"
    ],
    "name:dan_x_preferred":[
        "Chucuito"
    ],
    "name:eng_x_preferred":[
        "Chucuito"
    ],
    "name:fra_x_preferred":[
        "Chucuito"
    ],
    "name:heb_x_preferred":[
        "\u05e6'\u05d5\u05e7\u05d9\u05d8\u05d5"
    ],
    "name:nld_x_preferred":[
        "Chucuito"
    ],
    "name:que_x_preferred":[
        "Chukuwitu"
    ],
    "name:spa_x_preferred":[
        "Chucuito"
    ],
    "name:zho_x_preferred":[
        "\u4e18\u594e\u5716"
    ],
    "qs:gn_country":"PE",
    "qs:gn_fcode":"PPL",
    "qs:gn_pop":0,
    "qs:name":"Chucuito",
    "qs:name_adm0":"Per\u00fa",
    "qs:name_adm1":"Puno",
    "qs:photos":818,
    "qs:photos_1k":166,
    "qs:photos_9k":4,
    "qs:photos_9r":6,
    "qs:photos_all":818,
    "qs:photos_sr":9,
    "qs:placetype":"Town",
    "qs:pop_sr":"0",
    "qs:woe_adm0":23424919,
    "wd:wordcount":90,
    "wof:name":"Chucuito",
    "wof:placetype":"locality"
},
  "geometry": {"coordinates":[-69.88436,-15.89127],"type":"Point"}
}