{
  "type": "Feature",
  "properties": {
    "gn:admin1_code":"13.0",
    "gn:admin2_code":"1308.0",
    "gn:admin3_code":"130808.0",
    "gn:asciiname":"Yurirca",
    "gn:country_code":"PE",
    "gn:dem":3662,
    "gn:feature_class":"P",
    "gn:feature_code":"PPLL",
    "gn:name":"Yurirca",
    "gn:population":0,
    "gn:timezone":"America/Lima",
    "iso:country":"PE",
    "wof:name":"Yurirca",
    "wof:placetype":"locality"
},
  "geometry": {"coordinates":[-77.44861,-8.04583],"type":"Point"}
}