{
  "type": "Feature",
  "properties": {
    "gn:admin1_code":"9.0",
    "gn:admin2_code":"905.0",
    "gn:asciiname":"Pucahuarajoy",
    "gn:country_code":"PE",
    "gn:dem":3856,
    "gn:feature_class":"P",
    "gn:feature_code":"PPL",
    "gn:name":"Pucahuarajoy",
    "gn:population":0,
    "gn:timezone":"America/Lima",
    "iso:country":"PE",
    "wof:name":"Pucahuarajoy",
    "wof:placetype":"locality"
},
  "geometry": {"coordinates":[-74.48647,-12.61159],"type":"Point"}
}