{
  "type": "Feature",
  "properties": {
    "gn:admin1_code":"21",
    "gn:admin2_code":"2102.0",
    "gn:admin3_code":"210210.0",
    "gn:asciiname":"Collpashuni",
    "gn:country_code":"PE",
    "gn:dem":3819,
    "gn:feature_class":"P",
    "gn:feature_code":"PPL",
    "gn:name":"Collpashuni",
    "gn:population":0,
    "gn:timezone":"America/Lima",
    "iso:country":"PE",
    "wof:name":"Collpashuni",
    "wof:placetype":"locality"
},
  "geometry": {"coordinates":[-69.96666999999999,-15.25],"type":"Point"}
}