{
  "type": "Feature",
  "properties": {
    "gn:admin1_code":"17.0",
    "gn:admin2_code":"1701.0",
    "gn:asciiname":"Sonene",
    "gn:country_code":"PE",
    "gn:dem":187,
    "gn:feature_class":"P",
    "gn:feature_code":"PPL",
    "gn:name":"Sonene",
    "gn:population":0,
    "gn:timezone":"America/La_Paz",
    "iso:country":"PE",
    "name:spa_x_preferred":[
        "Sonene"
    ],
    "wof:name":"Sonene",
    "wof:placetype":"locality"
},
  "geometry": {"coordinates":[-68.70152,-12.57114],"type":"Point"}
}