{
  "type": "Feature",
  "properties": {
    "gn:admin1_code":"21",
    "gn:admin2_code":"2102.0",
    "gn:admin3_code":"210203.0",
    "gn:asciiname":"Arapa",
    "gn:country_code":"PE",
    "gn:dem":3916,
    "gn:feature_class":"P",
    "gn:feature_code":"PPLA3",
    "gn:name":"Arapa",
    "gn:population":0,
    "gn:timezone":"America/Lima",
    "iso:country":"PE",
    "wof:name":"Arapa",
    "wof:placetype":"locality"
},
  "geometry": {"coordinates":[-70.11667,-15.13333],"type":"Point"}
}