{
  "type": "Feature",
  "properties": {
    "gn:admin1_code":"21",
    "gn:admin2_code":"2102.0",
    "gn:admin3_code":"210203.0",
    "gn:asciiname":"Arapa",
    "gn:country_code":"PE",
    "gn:dem":3916,
    "gn:feature_class":"P",
    "gn:feature_code":"PPLA3",
    "gn:name":"Arapa",
    "gn:population":0,
    "gn:timezone":"America/Lima",
    "iso:country":"PE",
    "name:kat_x_preferred":[
        "\u10d0\u10e0\u10d0\u10de\u10d8\u10e1 \u10e0\u10d0\u10d8\u10dd\u10dc\u10d8"
    ],
    "name:por_x_preferred":[
        "Arapa"
    ],
    "name:que_x_preferred":[
        "Arapa distritu"
    ],
    "name:zho_x_preferred":[
        "\u963f\u62c9\u5e15\u5340"
    ],
    "wof:name":"Arapa",
    "wof:placetype":"locality"
},
  "geometry": {"coordinates":[-70.11667,-15.13333],"type":"Point"}
}