{
  "type": "Feature",
  "properties": {
    "gn:admin1_code":"05",
    "gn:admin2_code":"505.0",
    "gn:admin3_code":"50505.0",
    "gn:asciiname":"Janchijasa",
    "gn:country_code":"PE",
    "gn:dem":2690,
    "gn:feature_class":"P",
    "gn:feature_code":"PPL",
    "gn:name":"Janchijasa",
    "gn:population":0,
    "gn:timezone":"America/Lima",
    "iso:country":"PE",
    "name:und_x_variant":[
        "Janchiccasa",
        "Janchijasa"
    ],
    "wof:name":"Janchijasa",
    "wof:placetype":"locality"
},
  "geometry": {"coordinates":[-73.66753,-13.25717],"type":"Point"}
}