{
  "type": "Feature",
  "properties": {
    "gn:admin1_code":"12",
    "gn:admin2_code":"1207.0",
    "gn:admin3_code":"120704.0",
    "gn:asciiname":"Rambrash",
    "gn:country_code":"PE",
    "gn:dem":3510,
    "gn:feature_class":"P",
    "gn:feature_code":"PPL",
    "gn:name":"Rambrash",
    "gn:population":0,
    "gn:timezone":"America/Lima",
    "iso:country":"PE",
    "wof:name":"Rambrash",
    "wof:placetype":"locality"
},
  "geometry": {"coordinates":[-75.59058,-11.00507],"type":"Point"}
}