{
  "type": "Feature",
  "properties": {
    "gn:admin1_code":"1.0",
    "gn:admin2_code":"101.0",
    "gn:admin3_code":"10104.0",
    "gn:asciiname":"Agua Blanca",
    "gn:country_code":"PE",
    "gn:dem":2320,
    "gn:feature_class":"P",
    "gn:feature_code":"PPL",
    "gn:name":"Agua Blanca",
    "gn:population":0,
    "gn:timezone":"America/Lima",
    "iso:country":"PE",
    "name:bre_x_preferred":[
        "Agua Blanca"
    ],
    "name:ceb_x_preferred":[
        "Agua Blanca"
    ],
    "name:deu_x_preferred":[
        "Agua Blanca"
    ],
    "name:fra_x_preferred":[
        "Agua Blanca"
    ],
    "name:nld_x_preferred":[
        "Agua Blanca"
    ],
    "name:por_x_preferred":[
        "Agua Blanca"
    ],
    "name:sco_x_preferred":[
        "Agua Blanca"
    ],
    "name:spa_x_preferred":[
        "Agua Blanca"
    ],
    "name:swe_x_preferred":[
        "Agua Blanca"
    ],
    "wof:name":"Agua Blanca",
    "wof:placetype":"locality"
},
  "geometry": {"coordinates":[-77.67119,-6.301],"type":"Point"}
}