{
  "type": "Feature",
  "properties": {
    "gn:admin1_code":"3",
    "gn:admin2_code":"302.0",
    "gn:admin3_code":"30208.0",
    "gn:asciiname":"Pumararcco",
    "gn:country_code":"PE",
    "gn:dem":3091,
    "gn:feature_class":"P",
    "gn:feature_code":"PPL",
    "gn:name":"Pumararcco",
    "gn:population":0,
    "gn:timezone":"America/Lima",
    "iso:country":"PE",
    "wof:name":"Pumararcco",
    "wof:placetype":"locality"
},
  "geometry": {"coordinates":[-73.11288,-13.62395],"type":"Point"}
}