{
  "type": "Feature",
  "properties": {
    "gn:admin1_code":"9.0",
    "gn:admin2_code":"906.0",
    "gn:admin3_code":"90607.0",
    "gn:asciiname":"Pescapampa",
    "gn:country_code":"PE",
    "gn:dem":4115,
    "gn:feature_class":"P",
    "gn:feature_code":"PPL",
    "gn:name":"Pescapampa",
    "gn:population":0,
    "gn:timezone":"America/Lima",
    "iso:country":"PE",
    "wof:name":"Pescapampa",
    "wof:placetype":"locality"
},
  "geometry": {"coordinates":[-74.95009,-13.31885],"type":"Point"}
}