{
  "type": "Feature",
  "properties": {
    "gn:admin1_code":"15",
    "gn:admin2_code":"1506.0",
    "gn:admin3_code":"150610.0",
    "gn:asciiname":"Santa Cruz de Andamarca",
    "gn:country_code":"PE",
    "gn:dem":3527,
    "gn:feature_class":"P",
    "gn:feature_code":"PPL",
    "gn:name":"Santa Cruz de Andamarca",
    "gn:population":0,
    "gn:timezone":"America/Lima",
    "iso:country":"PE",
    "wof:name":"Santa Cruz de Andamarca",
    "wof:placetype":"locality"
},
  "geometry": {"coordinates":[-76.63401999999998,-11.19498],"type":"Point"}
}