{
  "type": "Feature",
  "properties": {
    "gn:admin1_code":"13.0",
    "gn:admin2_code":"1301.0",
    "gn:admin3_code":"130101.0",
    "gn:asciiname":"Urb La Merced",
    "gn:country_code":"PE",
    "gn:dem":20,
    "gn:feature_class":"P",
    "gn:feature_code":"PPL",
    "gn:name":"Urb La Merced",
    "gn:population":0,
    "gn:timezone":"America/Lima",
    "iso:country":"PE",
    "name:spa_x_preferred":[
        "La Merced"
    ],
    "wof:name":"Urb La Merced",
    "wof:placetype":"locality"
},
  "geometry": {"coordinates":[-79.03856,-8.12691],"type":"Point"}
}