{
  "type": "Feature",
  "properties": {
    "gn:country":"PE",
    "gn:fcode":"PPL",
    "gn:pop":200,
    "iso:country":"PE",
    "qs:name":"Cruzconga",
    "qs:photos_9r":0,
    "qs:photos_sr":0,
    "qs:pop_sr":"1",
    "wof:name":"Cruzconga",
    "wof:placetype":"locality",
    "wof:population":200
},
  "geometry": {"coordinates":[-78.19766,-7.00493],"type":"Point"}
}