{
  "type": "Feature",
  "properties": {
    "gn:admin1_code":"23",
    "gn:admin2_code":"2303.0",
    "gn:admin3_code":"230301.0",
    "gn:asciiname":"Barrial",
    "gn:country_code":"PE",
    "gn:dem":794,
    "gn:feature_class":"P",
    "gn:feature_code":"PPL",
    "gn:name":"Barrial",
    "gn:population":0,
    "gn:timezone":"America/Lima",
    "iso:country":"PE",
    "wof:name":"Barrial",
    "wof:placetype":"locality"
},
  "geometry": {"coordinates":[-70.72775,-17.54815],"type":"Point"}
}