{
  "type": "Feature",
  "properties": {
    "gn:admin1_code":"10",
    "gn:admin2_code":"1002.0",
    "gn:admin3_code":"100201.0",
    "gn:asciiname":"Huaylla",
    "gn:country_code":"PE",
    "gn:dem":2754,
    "gn:feature_class":"P",
    "gn:feature_code":"PPL",
    "gn:name":"Huaylla",
    "gn:population":0,
    "gn:timezone":"America/Lima",
    "iso:country":"PE",
    "wof:name":"Huaylla",
    "wof:placetype":"locality"
},
  "geometry": {"coordinates":[-76.17239000000002,-10.15032],"type":"Point"}
}