{
  "type": "Feature",
  "properties": {
    "gn:admin1_code":"03",
    "gn:admin2_code":"302.0",
    "gn:admin3_code":"30214.0",
    "gn:asciiname":"Perualla",
    "gn:country_code":"PE",
    "gn:dem":3789,
    "gn:feature_class":"P",
    "gn:feature_code":"PPL",
    "gn:name":"Perualla",
    "gn:population":0,
    "gn:timezone":"America/Lima",
    "iso:country":"PE",
    "wof:name":"Perualla",
    "wof:placetype":"locality"
},
  "geometry": {"coordinates":[-73.58889000000001,-13.99472],"type":"Point"}
}