{
  "type": "Feature",
  "properties": {
    "gn:admin1_code":"14",
    "gn:admin2_code":"1401.0",
    "gn:admin3_code":"140108.0",
    "gn:asciiname":"Hacienda Mira Flores",
    "gn:country_code":"PE",
    "gn:dem":14,
    "gn:feature_class":"P",
    "gn:feature_code":"PPL",
    "gn:name":"Hacienda Mira Flores",
    "gn:population":0,
    "gn:timezone":"America/Lima",
    "iso:country":"PE",
    "name:spa_x_preferred":[
        "Hacienda Mira Flores"
    ],
    "name:und_x_variant":[
        "Miraflores Hacienda",
        "Miraflores"
    ],
    "wof:name":"Hacienda Mira Flores",
    "wof:placetype":"locality"
},
  "geometry": {"coordinates":[-79.83736,-6.87332],"type":"Point"}
}