{
  "type": "Feature",
  "properties": {
    "gn:admin1_code":"04",
    "gn:admin2_code":"404.0",
    "gn:admin3_code":"40410.0",
    "gn:asciiname":"Sihuarpo",
    "gn:country_code":"PE",
    "gn:dem":2385,
    "gn:feature_class":"P",
    "gn:feature_code":"PPL",
    "gn:name":"Sihuarpo",
    "gn:population":0,
    "gn:timezone":"America/Lima",
    "iso:country":"PE",
    "name:und_x_variant":[
        "Sihu\u00e1n",
        "Sihuarpo"
    ],
    "wof:name":"Sihuarpo",
    "wof:placetype":"locality"
},
  "geometry": {"coordinates":[-72.52984000000002,-15.75563],"type":"Point"}
}