{
  "type": "Feature",
  "properties": {
    "gn:admin1_code":"12.0",
    "gn:admin2_code":"1204.0",
    "gn:admin3_code":"120428.0",
    "gn:asciiname":"Chichipampa",
    "gn:country_code":"PE",
    "gn:dem":3305,
    "gn:feature_class":"P",
    "gn:feature_code":"PPL",
    "gn:name":"Chichipampa",
    "gn:population":0,
    "gn:timezone":"America/Lima",
    "iso:country":"PE",
    "wof:name":"Chichipampa",
    "wof:placetype":"locality"
},
  "geometry": {"coordinates":[-75.38405999999998,-11.85153],"type":"Point"}
}