{
  "type": "Feature",
  "properties": {
    "gn:admin1_code":"4",
    "gn:admin2_code":"405.0",
    "gn:admin3_code":"40501.0",
    "gn:asciiname":"Caytape",
    "gn:country_code":"PE",
    "gn:dem":3890,
    "gn:feature_class":"P",
    "gn:feature_code":"PPL",
    "gn:name":"Caytape",
    "gn:population":0,
    "gn:timezone":"America/Lima",
    "iso:country":"PE",
    "wof:name":"Caytape",
    "wof:placetype":"locality"
},
  "geometry": {"coordinates":[-71.49315,-15.53539],"type":"Point"}
}