{
  "type": "Feature",
  "properties": {
    "gn:admin1_code":"3",
    "gn:admin2_code":"304.0",
    "gn:admin3_code":"30409.0",
    "gn:asciiname":"Socco",
    "gn:country_code":"PE",
    "gn:dem":3150,
    "gn:feature_class":"P",
    "gn:feature_code":"PPL",
    "gn:name":"Socco",
    "gn:population":0,
    "gn:timezone":"America/Lima",
    "iso:country":"PE",
    "wof:name":"Socco",
    "wof:placetype":"locality"
},
  "geometry": {"coordinates":[-73.23728,-13.94714],"type":"Point"}
}