{
  "type": "Feature",
  "properties": {
    "gn:admin1_code":"21",
    "gn:admin2_code":"2111.0",
    "gn:admin3_code":"211104.0",
    "gn:asciiname":"Huasalara",
    "gn:country_code":"PE",
    "gn:dem":3841,
    "gn:feature_class":"P",
    "gn:feature_code":"PPL",
    "gn:name":"Huasalara",
    "gn:population":0,
    "gn:timezone":"America/Lima",
    "iso:country":"PE",
    "wof:name":"Huasalara",
    "wof:placetype":"locality"
},
  "geometry": {"coordinates":[-70.03487,-15.47975],"type":"Point"}
}