{
  "type": "Feature",
  "properties": {
    "gn:admin1_code":"5",
    "gn:admin2_code":"511.0",
    "gn:admin3_code":"51106.0",
    "gn:asciiname":"Paccha Huallhua",
    "gn:country_code":"PE",
    "gn:dem":3014,
    "gn:feature_class":"P",
    "gn:feature_code":"PPL",
    "gn:name":"Paccha Huallhua",
    "gn:population":0,
    "gn:timezone":"America/Lima",
    "iso:country":"PE",
    "wof:name":"Paccha Huallhua",
    "wof:placetype":"locality"
},
  "geometry": {"coordinates":[-73.88613000000002,-13.86373],"type":"Point"}
}