{
  "type": "Feature",
  "properties": {
    "gn:admin1_code":"21",
    "gn:admin2_code":"2107.0",
    "gn:admin3_code":"210701.0",
    "gn:asciiname":"Collpani",
    "gn:country_code":"PE",
    "gn:dem":4200,
    "gn:feature_class":"P",
    "gn:feature_code":"PPL",
    "gn:name":"Collpani",
    "gn:population":0,
    "gn:timezone":"America/Lima",
    "iso:country":"PE",
    "wof:name":"Collpani",
    "wof:placetype":"locality"
},
  "geometry": {"coordinates":[-70.47221,-15.41785],"type":"Point"}
}