{
  "type": "Feature",
  "properties": {
    "gn:admin1_code":"05",
    "gn:admin2_code":"507.0",
    "gn:admin3_code":"50705.0",
    "gn:asciiname":"Salvia",
    "gn:country_code":"PE",
    "gn:dem":2982,
    "gn:feature_class":"P",
    "gn:feature_code":"PPL",
    "gn:name":"Salvia",
    "gn:population":0,
    "gn:timezone":"America/Lima",
    "iso:country":"PE",
    "name:spa_x_preferred":[
        "Salvia"
    ],
    "wof:name":"Salvia",
    "wof:placetype":"locality"
},
  "geometry": {"coordinates":[-73.86806,-15.18911],"type":"Point"}
}