{
  "type": "Feature",
  "properties": {
    "gn:admin1_code":"14.0",
    "gn:admin2_code":"1403.0",
    "gn:admin3_code":"140306.0",
    "gn:asciiname":"Alto del Medano",
    "gn:country_code":"PE",
    "gn:dem":30,
    "gn:feature_class":"P",
    "gn:feature_code":"PPL",
    "gn:name":"Alto del Medano",
    "gn:population":0,
    "gn:timezone":"America/Lima",
    "iso:country":"PE",
    "name:spa_x_preferred":[
        "Alto del Medano"
    ],
    "wof:name":"Alto del Medano",
    "wof:placetype":"locality"
},
  "geometry": {"coordinates":[-79.95886,-6.501],"type":"Point"}
}