{
  "type": "Feature",
  "properties": {
    "gn:admin1_code":"9.0",
    "gn:admin2_code":"905.0",
    "gn:asciiname":"Mala",
    "gn:country_code":"PE",
    "gn:dem":2755,
    "gn:feature_class":"P",
    "gn:feature_code":"PPL",
    "gn:name":"Mala",
    "gn:population":0,
    "gn:timezone":"America/Lima",
    "iso:country":"PE",
    "name:bos_x_preferred":[
        "Mala"
    ],
    "name:ceb_x_preferred":[
        "Mala"
    ],
    "name:deu_x_preferred":[
        "Mala"
    ],
    "name:fra_x_preferred":[
        "Mala"
    ],
    "name:hun_x_preferred":[
        "Mala"
    ],
    "name:ita_x_preferred":[
        "Mala"
    ],
    "name:nld_x_preferred":[
        "Mala"
    ],
    "name:nor_x_preferred":[
        "Mala"
    ],
    "name:pol_x_preferred":[
        "Mala"
    ],
    "name:por_x_preferred":[
        "Mala"
    ],
    "name:spa_x_preferred":[
        "Mala"
    ],
    "name:srp_x_preferred":[
        "Mala"
    ],
    "name:swe_x_preferred":[
        "Mala"
    ],
    "name:uzb_x_preferred":[
        "Male"
    ],
    "wof:name":"Mala",
    "wof:placetype":"locality"
},
  "geometry": {"coordinates":[-74.34285,-12.79683],"type":"Point"}
}