{
  "type": "Feature",
  "properties": {
    "gn:admin1_code":"05",
    "gn:admin2_code":"506.0",
    "gn:admin3_code":"50612.0",
    "gn:asciiname":"Vacahuasi",
    "gn:country_code":"PE",
    "gn:dem":3491,
    "gn:feature_class":"P",
    "gn:feature_code":"PPL",
    "gn:name":"Vacahuasi",
    "gn:population":0,
    "gn:timezone":"America/Lima",
    "iso:country":"PE",
    "wof:name":"Vacahuasi",
    "wof:placetype":"locality"
},
  "geometry": {"coordinates":[-74.68549,-14.34554],"type":"Point"}
}