{
  "type": "Feature",
  "properties": {
    "gn:admin1_code":"20",
    "gn:admin2_code":"2002.0",
    "gn:admin3_code":"200202.0",
    "gn:asciiname":"Barranco Blanco",
    "gn:country_code":"PE",
    "gn:dem":667,
    "gn:feature_class":"P",
    "gn:feature_code":"PPL",
    "gn:name":"Barranco Blanco",
    "gn:population":0,
    "gn:timezone":"America/Lima",
    "iso:country":"PE",
    "wof:name":"Barranco Blanco",
    "wof:placetype":"locality"
},
  "geometry": {"coordinates":[-80.04165999999999,-4.95946],"type":"Point"}
}