{
  "type": "Feature",
  "properties": {
    "gn:admin1_code":"05",
    "gn:admin2_code":"511.0",
    "gn:admin3_code":"51102.0",
    "gn:asciiname":"Violinnioc",
    "gn:country_code":"PE",
    "gn:dem":3136,
    "gn:feature_class":"P",
    "gn:feature_code":"PPL",
    "gn:name":"Violinnioc",
    "gn:population":0,
    "gn:timezone":"America/Lima",
    "iso:country":"PE",
    "wof:name":"Violinnioc",
    "wof:placetype":"locality"
},
  "geometry": {"coordinates":[-73.82472,-13.83611],"type":"Point"}
}