{
  "type": "Feature",
  "properties": {
    "gn:admin1_code":"20",
    "gn:admin2_code":"2004.0",
    "gn:admin3_code":"200401.0",
    "gn:asciiname":"Vicus",
    "gn:country_code":"PE",
    "gn:dem":105,
    "gn:feature_class":"P",
    "gn:feature_code":"PPL",
    "gn:name":"Vicus",
    "gn:population":0,
    "gn:timezone":"America/Lima",
    "iso:country":"PE",
    "name:cat_x_preferred":[
        "Vicus"
    ],
    "name:cym_x_preferred":[
        "Vicus"
    ],
    "name:deu_x_preferred":[
        "Vicus"
    ],
    "name:ell_x_preferred":[
        "Vicus"
    ],
    "name:fra_x_preferred":[
        "Vicus"
    ],
    "name:glg_x_preferred":[
        "Vicus"
    ],
    "name:hun_x_preferred":[
        "Vicus"
    ],
    "name:ind_x_preferred":[
        "Vicus"
    ],
    "name:ita_x_preferred":[
        "Vicus"
    ],
    "name:jpn_x_preferred":[
        "\u30a6\u30a3\u30af\u30b9"
    ],
    "name:lat_x_preferred":[
        "Vicus"
    ],
    "name:nld_x_preferred":[
        "Vicus"
    ],
    "name:por_x_preferred":[
        "Vicus"
    ],
    "name:ron_x_preferred":[
        "Vicus"
    ],
    "name:rus_x_preferred":[
        "Vicus"
    ],
    "name:spa_x_preferred":[
        "Vicus"
    ],
    "name:und_x_variant":[
        "Vic\u00fas Hacienda"
    ],
    "wof:name":"Vicus",
    "wof:placetype":"locality"
},
  "geometry": {"coordinates":[-80.14267,-5.16382],"type":"Point"}
}