{
  "type": "Feature",
  "properties": {
    "gn:admin1_code":"20",
    "gn:admin2_code":"2004.0",
    "gn:admin3_code":"200401.0",
    "gn:asciiname":"Vicus",
    "gn:country_code":"PE",
    "gn:dem":105,
    "gn:feature_class":"P",
    "gn:feature_code":"PPL",
    "gn:name":"Vicus",
    "gn:population":0,
    "gn:timezone":"America/Lima",
    "iso:country":"PE",
    "name:und_x_variant":[
        "Vic\u00fas Hacienda",
        "Vicus"
    ],
    "wof:name":"Vicus",
    "wof:placetype":"locality"
},
  "geometry": {"coordinates":[-80.14267,-5.16382],"type":"Point"}
}