{
  "type": "Feature",
  "properties": {
    "gn:admin1_code":"14",
    "gn:admin2_code":"1401.0",
    "gn:admin3_code":"140117.0",
    "gn:asciiname":"Hacienda Patapo",
    "gn:country_code":"PE",
    "gn:dem":103,
    "gn:feature_class":"P",
    "gn:feature_code":"PPL",
    "gn:name":"Hacienda P\u00e1tapo",
    "gn:population":0,
    "gn:timezone":"America/Lima",
    "iso:country":"PE",
    "name:und_x_variant":[
        "Hacienda P\u00e1tapo",
        "Patapa",
        "Patape",
        "P\u00e1tapo"
    ],
    "wof:name":"Hacienda Patapo",
    "wof:placetype":"locality"
},
  "geometry": {"coordinates":[-79.63590000000001,-6.73315],"type":"Point"}
}