{
  "type": "Feature",
  "properties": {
    "gn:admin1_code":"16",
    "gn:admin2_code":"1604.0",
    "gn:admin3_code":"160402.0",
    "gn:asciiname":"Triunfador",
    "gn:country_code":"PE",
    "gn:dem":72,
    "gn:feature_class":"P",
    "gn:feature_code":"PPL",
    "gn:name":"Triunfador",
    "gn:population":0,
    "gn:timezone":"America/Lima",
    "iso:country":"PE",
    "wof:name":"Triunfador",
    "wof:placetype":"locality"
},
  "geometry": {"coordinates":[-71.78601999999999,-3.53449],"type":"Point"}
}