{
  "type": "Feature",
  "properties": {
    "gn:admin1_code":"8",
    "gn:admin2_code":"806.0",
    "gn:admin3_code":"80602.0",
    "gn:asciiname":"Choclla",
    "gn:country_code":"PE",
    "gn:dem":4695,
    "gn:feature_class":"P",
    "gn:feature_code":"PPL",
    "gn:name":"Choclla",
    "gn:population":0,
    "gn:timezone":"America/Lima",
    "iso:country":"PE",
    "wof:name":"Choclla",
    "wof:placetype":"locality"
},
  "geometry": {"coordinates":[-71.12860999999999,-14.00528],"type":"Point"}
}