{
  "type": "Feature",
  "properties": {
    "gn:admin1_code":"24",
    "gn:admin2_code":"2403.0",
    "gn:admin3_code":"240303.0",
    "gn:asciiname":"Puesto Figueroa",
    "gn:country_code":"PE",
    "gn:dem":485,
    "gn:feature_class":"P",
    "gn:feature_code":"PPL",
    "gn:name":"Puesto Figueroa",
    "gn:population":0,
    "gn:timezone":"America/Lima",
    "iso:country":"PE",
    "wof:name":"Puesto Figueroa",
    "wof:placetype":"locality"
},
  "geometry": {"coordinates":[-80.15782,-3.87197],"type":"Point"}
}