{
  "type": "Feature",
  "properties": {
    "gn:admin1_code":"15",
    "gn:admin2_code":"1503.0",
    "gn:admin3_code":"150301.0",
    "gn:asciiname":"Pucapampa",
    "gn:country_code":"PE",
    "gn:dem":4480,
    "gn:feature_class":"P",
    "gn:feature_code":"PPL",
    "gn:name":"Pucapampa",
    "gn:population":0,
    "gn:timezone":"America/Lima",
    "iso:country":"PE",
    "wof:name":"Pucapampa",
    "wof:placetype":"locality"
},
  "geometry": {"coordinates":[-76.89474,-10.55698],"type":"Point"}
}