{
  "type": "Feature",
  "properties": {
    "gn:admin1_code":"23",
    "gn:admin2_code":"2301.0",
    "gn:admin3_code":"230101.0",
    "gn:asciiname":"Las Lagunas",
    "gn:country_code":"PE",
    "gn:dem":51,
    "gn:feature_class":"P",
    "gn:feature_code":"PPL",
    "gn:name":"Las Lagunas",
    "gn:population":0,
    "gn:timezone":"America/Lima",
    "iso:country":"PE",
    "name:ceb_x_preferred":[
        "Las Lagunas"
    ],
    "name:spa_x_preferred":[
        "Las Lagunas"
    ],
    "name:srp_x_preferred":[
        "\u041b\u0430\u0441 \u041b\u0430\u0433\u0443\u043d\u0430\u0441"
    ],
    "name:swe_x_preferred":[
        "Las Lagunas"
    ],
    "name:und_x_variant":[
        "Las Lagunas Hacienda"
    ],
    "wof:name":"Las Lagunas",
    "wof:placetype":"locality"
},
  "geometry": {"coordinates":[-70.40463000000003,-18.27542],"type":"Point"}
}