{
  "type": "Feature",
  "properties": {
    "gn:admin1_code":"15",
    "gn:admin2_code":"1507.0",
    "gn:admin3_code":"150713.0",
    "gn:asciiname":"Mariatana",
    "gn:country_code":"PE",
    "gn:dem":3548,
    "gn:feature_class":"P",
    "gn:feature_code":"PPLA3",
    "gn:name":"Mariatana",
    "gn:population":0,
    "gn:timezone":"America/Lima",
    "iso:country":"PE",
    "wof:name":"Mariatana",
    "wof:placetype":"locality"
},
  "geometry": {"coordinates":[-76.33333,-12.25],"type":"Point"}
}