{
  "type": "Feature",
  "properties": {
    "gn:admin1_code":"21",
    "gn:admin2_code":"2104.0",
    "gn:admin3_code":"210407.0",
    "gn:asciiname":"Humejalsopatilla",
    "gn:country_code":"PE",
    "gn:dem":4023,
    "gn:feature_class":"P",
    "gn:feature_code":"PPL",
    "gn:name":"Humejalsopatilla",
    "gn:population":0,
    "gn:timezone":"America/Lima",
    "iso:country":"PE",
    "wof:name":"Humejalsopatilla",
    "wof:placetype":"locality"
},
  "geometry": {"coordinates":[-69.16046,-16.59792],"type":"Point"}
}