{
  "type": "Feature",
  "properties": {
    "gn:admin1_code":"14",
    "gn:admin2_code":"1401.0",
    "gn:admin3_code":"140102.0",
    "gn:asciiname":"Wadington",
    "gn:country_code":"PE",
    "gn:dem":154,
    "gn:feature_class":"P",
    "gn:feature_code":"PPL",
    "gn:name":"Wadington",
    "gn:population":0,
    "gn:timezone":"America/Lima",
    "iso:country":"PE",
    "wof:name":"Wadington",
    "wof:placetype":"locality"
},
  "geometry": {"coordinates":[-79.45199000000002,-6.69914],"type":"Point"}
}