{
  "type": "Feature",
  "properties": {
    "gn:admin1_code":"11.0",
    "gn:admin2_code":"1102.0",
    "gn:admin3_code":"110203.0",
    "gn:asciiname":"Chacma",
    "gn:country_code":"PE",
    "gn:dem":2874,
    "gn:feature_class":"P",
    "gn:feature_code":"PPL",
    "gn:name":"Chacma",
    "gn:population":0,
    "gn:timezone":"America/Lima",
    "iso:country":"PE",
    "name:spa_x_preferred":[
        "Chacma"
    ],
    "wof:name":"Chacma",
    "wof:placetype":"locality"
},
  "geometry": {"coordinates":[-75.89589000000002,-13.13876],"type":"Point"}
}