{
  "type": "Feature",
  "properties": {
    "gn:admin1_code":"18",
    "gn:admin2_code":"1802.0",
    "gn:admin3_code":"180201.0",
    "gn:asciiname":"Chichilin",
    "gn:country_code":"PE",
    "gn:dem":2464,
    "gn:feature_class":"P",
    "gn:feature_code":"PPL",
    "gn:name":"Chichilin",
    "gn:population":0,
    "gn:timezone":"America/Lima",
    "iso:country":"PE",
    "wof:name":"Chichilin",
    "wof:placetype":"locality"
},
  "geometry": {"coordinates":[-70.96909000000002,-16.65153],"type":"Point"}
}