{
  "type": "Feature",
  "properties": {
    "gn:admin1_code":"13",
    "gn:admin2_code":"1308.0",
    "gn:admin3_code":"130808.0",
    "gn:asciiname":"La Vaqueria de Anda",
    "gn:country_code":"PE",
    "gn:dem":2811,
    "gn:feature_class":"P",
    "gn:feature_code":"PPL",
    "gn:name":"La Vaquer\u00eda de Anda",
    "gn:population":0,
    "gn:timezone":"America/Lima",
    "iso:country":"PE",
    "wof:name":"La Vaqueria de Anda",
    "wof:placetype":"locality"
},
  "geometry": {"coordinates":[-77.5941,-7.95055],"type":"Point"}
}