{
  "type": "Feature",
  "properties": {
    "gn:admin1_code":"2.0",
    "gn:admin2_code":"218.0",
    "gn:asciiname":"Catorce Incas",
    "gn:country_code":"PE",
    "gn:dem":167,
    "gn:feature_class":"P",
    "gn:feature_code":"PPL",
    "gn:name":"Catorce Incas",
    "gn:population":0,
    "gn:timezone":"America/Lima",
    "iso:country":"PE",
    "wof:name":"Catorce Incas",
    "wof:placetype":"locality"
},
  "geometry": {"coordinates":[-78.51694000000001,-8.94694],"type":"Point"}
}