{
  "type": "Feature",
  "properties": {
    "gn:admin1_code":"16",
    "gn:admin2_code":"1604.0",
    "gn:admin3_code":"160403.0",
    "gn:asciiname":"Rondina",
    "gn:country_code":"PE",
    "gn:dem":66,
    "gn:feature_class":"P",
    "gn:feature_code":"PPL",
    "gn:name":"Rondi\u00f1a",
    "gn:population":0,
    "gn:timezone":"America/Lima",
    "iso:country":"PE",
    "wof:name":"Rondina",
    "wof:placetype":"locality"
},
  "geometry": {"coordinates":[-69.99583,-4.19111],"type":"Point"}
}