{
  "type": "Feature",
  "properties": {
    "gn:admin1_code":"12",
    "gn:admin2_code":"1206.0",
    "gn:admin3_code":"120607.0",
    "gn:asciiname":"Rio Cheni",
    "gn:country_code":"PE",
    "gn:dem":572,
    "gn:feature_class":"P",
    "gn:feature_code":"PPL",
    "gn:name":"R\u00edo Cheni",
    "gn:population":0,
    "gn:timezone":"America/Lima",
    "iso:country":"PE",
    "wof:name":"Rio Cheni",
    "wof:placetype":"locality"
},
  "geometry": {"coordinates":[-74.72761,-11.06005],"type":"Point"}
}