{
  "type": "Feature",
  "properties": {
    "gn:admin1_code":"05",
    "gn:admin2_code":"501.0",
    "gn:asciiname":"Cusis",
    "gn:country_code":"PE",
    "gn:dem":1968,
    "gn:feature_class":"P",
    "gn:feature_code":"PPL",
    "gn:name":"Cusis",
    "gn:population":0,
    "gn:timezone":"America/Lima",
    "iso:country":"PE",
    "wof:name":"Cusis",
    "wof:placetype":"locality"
},
  "geometry": {"coordinates":[-73.84033000000002,-13.41437],"type":"Point"}
}