{
  "type": "Feature",
  "properties": {
    "gn:admin1_code":"9",
    "gn:admin2_code":"906.0",
    "gn:admin3_code":"90603.0",
    "gn:asciiname":"Contejasa",
    "gn:country_code":"PE",
    "gn:dem":3137,
    "gn:feature_class":"P",
    "gn:feature_code":"PPL",
    "gn:name":"Contejasa",
    "gn:population":0,
    "gn:timezone":"America/Lima",
    "iso:country":"PE",
    "wof:name":"Contejasa",
    "wof:placetype":"locality"
},
  "geometry": {"coordinates":[-75.20350000000001,-14.05085],"type":"Point"}
}