{
  "type": "Feature",
  "properties": {
    "gn:admin1_code":"04",
    "gn:admin2_code":"401.0",
    "gn:admin3_code":"40102.0",
    "gn:asciiname":"Pacheco",
    "gn:country_code":"PE",
    "gn:dem":3206,
    "gn:feature_class":"P",
    "gn:feature_code":"PPL",
    "gn:name":"Pacheco",
    "gn:population":0,
    "gn:timezone":"America/Lima",
    "iso:country":"PE",
    "name:kor_x_preferred":[
        "\ud30c\uccb4\ucf54"
    ],
    "name:spa_x_preferred":[
        "Pacheco"
    ],
    "wof:name":"Pacheco",
    "wof:placetype":"locality"
},
  "geometry": {"coordinates":[-71.47711,-16.31113],"type":"Point"}
}