{
  "type": "Feature",
  "properties": {
    "gn:admin1_code":"5.0",
    "gn:admin2_code":"507.0",
    "gn:admin3_code":"50705.0",
    "gn:asciiname":"Chunuma",
    "gn:country_code":"PE",
    "gn:dem":3415,
    "gn:feature_class":"P",
    "gn:feature_code":"PPL",
    "gn:name":"Chu\u00f1uma",
    "gn:population":0,
    "gn:timezone":"America/Lima",
    "iso:country":"PE",
    "name:spa_x_preferred":[
        "Chu\u00f1uma"
    ],
    "wof:name":"Chunuma",
    "wof:placetype":"locality"
},
  "geometry": {"coordinates":[-73.74204,-15.32604],"type":"Point"}
}