{
  "type": "Feature",
  "properties": {
    "gn:admin1_code":"15",
    "gn:admin2_code":"1506.0",
    "gn:admin3_code":"150606.0",
    "gn:asciiname":"Cullpa",
    "gn:country_code":"PE",
    "gn:dem":2448,
    "gn:feature_class":"P",
    "gn:feature_code":"PPL",
    "gn:name":"Cullpa",
    "gn:population":0,
    "gn:timezone":"America/Lima",
    "iso:country":"PE",
    "wof:name":"Cullpa",
    "wof:placetype":"locality"
},
  "geometry": {"coordinates":[-76.97139,-11.18028],"type":"Point"}
}