{
  "type": "Feature",
  "properties": {
    "gn:admin1_code":"5.0",
    "gn:admin2_code":"501.0",
    "gn:admin3_code":"50103.0",
    "gn:asciiname":"Cruzpata",
    "gn:country_code":"PE",
    "gn:dem":3125,
    "gn:feature_class":"P",
    "gn:feature_code":"PPL",
    "gn:name":"Cruzpata",
    "gn:population":0,
    "gn:timezone":"America/Lima",
    "iso:country":"PE",
    "wof:name":"Cruzpata",
    "wof:placetype":"locality"
},
  "geometry": {"coordinates":[-74.08588,-13.11707],"type":"Point"}
}