{
  "type": "Feature",
  "properties": {
    "gn:admin1_code":"17.0",
    "gn:admin2_code":"1703.0",
    "gn:asciiname":"Aserradero",
    "gn:country_code":"PE",
    "gn:dem":241,
    "gn:feature_class":"P",
    "gn:feature_code":"PPL",
    "gn:name":"Aserradero",
    "gn:population":0,
    "gn:timezone":"America/Lima",
    "iso:country":"PE",
    "name:spa_x_preferred":[
        "Aserradero"
    ],
    "wof:name":"Aserradero",
    "wof:placetype":"locality"
},
  "geometry": {"coordinates":[-69.03435999999999,-11.91086],"type":"Point"}
}