{
  "type": "Feature",
  "properties": {
    "gn:admin1_code":"10.0",
    "gn:admin2_code":"1005.0",
    "gn:admin3_code":"100510.0",
    "gn:asciiname":"Casa Cruz",
    "gn:country_code":"PE",
    "gn:dem":3430,
    "gn:feature_class":"P",
    "gn:feature_code":"PPL",
    "gn:name":"Casa Cruz",
    "gn:population":0,
    "gn:timezone":"America/Lima",
    "iso:country":"PE",
    "wof:name":"Casa Cruz",
    "wof:placetype":"locality"
},
  "geometry": {"coordinates":[-76.79875,-9.41469],"type":"Point"}
}