{
  "type": "Feature",
  "properties": {
    "gn:admin1_code":"03",
    "gn:admin2_code":"306.0",
    "gn:admin3_code":"30606.0",
    "gn:asciiname":"Toruro",
    "gn:country_code":"PE",
    "gn:dem":3208,
    "gn:feature_class":"P",
    "gn:feature_code":"PPL",
    "gn:name":"Toruro",
    "gn:population":0,
    "gn:timezone":"America/Lima",
    "iso:country":"PE",
    "wof:name":"Toruro",
    "wof:placetype":"locality"
},
  "geometry": {"coordinates":[-73.65598,-13.37156],"type":"Point"}
}