{
  "type": "Feature",
  "properties": {
    "gn:admin1_code":"10.0",
    "gn:admin2_code":"1001.0",
    "gn:admin3_code":"100104.0",
    "gn:asciiname":"Jatunchullpa",
    "gn:country_code":"PE",
    "gn:dem":2032,
    "gn:feature_class":"P",
    "gn:feature_code":"PPL",
    "gn:name":"Jatunchullpa",
    "gn:population":0,
    "gn:timezone":"America/Lima",
    "iso:country":"PE",
    "wof:name":"Jatunchullpa",
    "wof:placetype":"locality"
},
  "geometry": {"coordinates":[-76.13769000000001,-9.81807],"type":"Point"}
}