{
  "type": "Feature",
  "properties": {
    "gn:admin1_code":"16",
    "gn:admin2_code":"1601.0",
    "gn:admin3_code":"160109.0",
    "gn:asciiname":"Huapapa",
    "gn:country_code":"PE",
    "gn:dem":78,
    "gn:feature_class":"P",
    "gn:feature_code":"PPL",
    "gn:name":"Huapapa",
    "gn:population":0,
    "gn:timezone":"America/Lima",
    "iso:country":"PE",
    "wof:name":"Huapapa",
    "wof:placetype":"locality"
},
  "geometry": {"coordinates":[-70.42601999999999,-2.53993],"type":"Point"}
}