{
  "type": "Feature",
  "properties": {
    "gn:admin1_code":"05",
    "gn:admin2_code":"506.0",
    "gn:admin3_code":"50619.0",
    "gn:asciiname":"Tantarpampa",
    "gn:country_code":"PE",
    "gn:dem":2857,
    "gn:feature_class":"P",
    "gn:feature_code":"PPL",
    "gn:name":"Tantarpampa",
    "gn:population":0,
    "gn:timezone":"America/Lima",
    "iso:country":"PE",
    "wof:name":"Tantarpampa",
    "wof:placetype":"locality"
},
  "geometry": {"coordinates":[-74.19786999999999,-15.11181],"type":"Point"}
}