{
  "type": "Feature",
  "properties": {
    "gn:admin1_code":"15.0",
    "gn:admin2_code":"1509.0",
    "gn:admin3_code":"150901.0",
    "gn:asciiname":"Garbanzo",
    "gn:country_code":"PE",
    "gn:dem":4488,
    "gn:feature_class":"P",
    "gn:feature_code":"PPL",
    "gn:name":"Garbanzo",
    "gn:population":0,
    "gn:timezone":"America/Lima",
    "iso:country":"PE",
    "wof:name":"Garbanzo",
    "wof:placetype":"locality"
},
  "geometry": {"coordinates":[-76.79139000000001,-10.48056],"type":"Point"}
}