{
  "type": "Feature",
  "properties": {
    "gn:admin1_code":"21",
    "gn:admin2_code":"2104.0",
    "gn:admin3_code":"210404.0",
    "gn:asciiname":"Nuno Mayane",
    "gn:country_code":"PE",
    "gn:dem":4021,
    "gn:feature_class":"P",
    "gn:feature_code":"PPL",
    "gn:name":"Nu\u00f1o Mayane",
    "gn:population":0,
    "gn:timezone":"America/Lima",
    "iso:country":"PE",
    "wof:name":"Nuno Mayane",
    "wof:placetype":"locality"
},
  "geometry": {"coordinates":[-69.3021,-16.72785],"type":"Point"}
}