{
  "type": "Feature",
  "properties": {
    "gn:admin1_code":"15",
    "gn:admin2_code":"1502.0",
    "gn:admin3_code":"150201.0",
    "gn:asciiname":"Las Huertas",
    "gn:country_code":"PE",
    "gn:dem":456,
    "gn:feature_class":"P",
    "gn:feature_code":"PPL",
    "gn:name":"Las Huertas",
    "gn:population":0,
    "gn:timezone":"America/Lima",
    "iso:country":"PE",
    "name:und_x_variant":[
        "Las Huertas Hacienda",
        "Las Huertas"
    ],
    "wof:name":"Las Huertas",
    "wof:placetype":"locality"
},
  "geometry": {"coordinates":[-77.60899000000001,-10.6961],"type":"Point"}
}