{
  "type": "Feature",
  "properties": {
    "gn:admin1_code":"2.0",
    "gn:admin2_code":"206.0",
    "gn:admin3_code":"20606.0",
    "gn:asciiname":"Huiyash",
    "gn:country_code":"PE",
    "gn:dem":3204,
    "gn:feature_class":"P",
    "gn:feature_code":"PPL",
    "gn:name":"Huiyash",
    "gn:population":0,
    "gn:timezone":"America/Lima",
    "iso:country":"PE",
    "wof:name":"Huiyash",
    "wof:placetype":"locality"
},
  "geometry": {"coordinates":[-77.53860999999998,-9.35056],"type":"Point"}
}