{
  "type": "Feature",
  "properties": {
    "gn:admin1_code":"20",
    "gn:admin2_code":"2001.0",
    "gn:admin3_code":"200109.0",
    "gn:asciiname":"Monte Grande",
    "gn:country_code":"PE",
    "gn:dem":23,
    "gn:feature_class":"P",
    "gn:feature_code":"PPL",
    "gn:name":"Monte Grande",
    "gn:population":0,
    "gn:timezone":"America/Lima",
    "iso:country":"PE",
    "name:ara_x_preferred":[
        "\u0645\u0648\u0646\u062a\u064a \u063a\u0631\u0627\u0646\u062f\u064a"
    ],
    "name:azb_x_preferred":[
        "\u0645\u0648\u0646\u062a\u0647 \u0642\u0631\u0627\u0646\u062f\u0647"
    ],
    "name:deu_x_preferred":[
        "Monte Grande"
    ],
    "name:epo_x_preferred":[
        "Monte Grande"
    ],
    "name:fas_x_preferred":[
        "\u0645\u0648\u0646\u062a\u0647 \u06af\u0631\u0627\u0646\u062f\u0647"
    ],
    "name:fra_x_preferred":[
        "Monte Grande"
    ],
    "name:ita_x_preferred":[
        "Monte Grande"
    ],
    "name:kat_x_preferred":[
        "\u10db\u10dd\u10dc\u10e2\u10d4-\u10d2\u10e0\u10d0\u10dc\u10d3\u10d4"
    ],
    "name:nld_x_preferred":[
        "Monte Grande"
    ],
    "name:pol_x_preferred":[
        "Monte Grande"
    ],
    "name:sco_x_preferred":[
        "Monte Grande"
    ],
    "name:spa_x_preferred":[
        "Monte Grande"
    ],
    "name:zho_x_preferred":[
        "\u8499\u7279\u683c\u862d\u5fb7"
    ],
    "wof:name":"Monte Grande",
    "wof:placetype":"locality"
},
  "geometry": {"coordinates":[-80.69443000000003,-5.37106],"type":"Point"}
}