{
  "type": "Feature",
  "properties": {
    "gn:admin1_code":"20",
    "gn:admin2_code":"2001.0",
    "gn:admin3_code":"200109.0",
    "gn:asciiname":"Monte Grande",
    "gn:country_code":"PE",
    "gn:dem":23,
    "gn:feature_class":"P",
    "gn:feature_code":"PPL",
    "gn:name":"Monte Grande",
    "gn:population":0,
    "gn:timezone":"America/Lima",
    "iso:country":"PE",
    "wof:name":"Monte Grande",
    "wof:placetype":"locality"
},
  "geometry": {"coordinates":[-80.69443000000003,-5.37106],"type":"Point"}
}