{
  "type": "Feature",
  "properties": {
    "gn:admin1_code":"1.0",
    "gn:admin2_code":"101.0",
    "gn:admin3_code":"10106.0",
    "gn:asciiname":"Jaja",
    "gn:country_code":"PE",
    "gn:dem":2746,
    "gn:feature_class":"P",
    "gn:feature_code":"PPL",
    "gn:name":"Jaja",
    "gn:population":0,
    "gn:timezone":"America/Lima",
    "iso:country":"PE",
    "name:ces_x_preferred":[
        "Jaja"
    ],
    "name:deu_x_preferred":[
        "Jaja"
    ],
    "name:fas_x_preferred":[
        "\u062c\u0627\u062c\u0627"
    ],
    "name:ita_x_preferred":[
        "Jaja"
    ],
    "name:jpn_x_preferred":[
        "\u30b8\u30e3\u30b8\u30e3"
    ],
    "name:nor_x_preferred":[
        "Jaja"
    ],
    "name:por_x_preferred":[
        "Jaj\u00e1"
    ],
    "name:swe_x_preferred":[
        "Jaja"
    ],
    "wof:name":"Jaja",
    "wof:placetype":"locality"
},
  "geometry": {"coordinates":[-77.93064,-6.93428],"type":"Point"}
}