{
  "type": "Feature",
  "properties": {
    "gn:admin1_code":"11.0",
    "gn:admin2_code":"1101.0",
    "gn:admin3_code":"110111.0",
    "gn:asciiname":"Las Mercedes",
    "gn:country_code":"PE",
    "gn:dem":344,
    "gn:feature_class":"P",
    "gn:feature_code":"PPLL",
    "gn:name":"Las Mercedes",
    "gn:population":0,
    "gn:timezone":"America/Lima",
    "iso:country":"PE",
    "wof:name":"Las Mercedes",
    "wof:placetype":"locality"
},
  "geometry": {"coordinates":[-75.68361,-14.27917],"type":"Point"}
}