{
  "type": "Feature",
  "properties": {
    "gn:admin1_code":"1.0",
    "gn:admin2_code":"101.0",
    "gn:admin3_code":"10114.0",
    "gn:asciiname":"Cupacha",
    "gn:country_code":"PE",
    "gn:dem":2415,
    "gn:feature_class":"P",
    "gn:feature_code":"PPLL",
    "gn:name":"Cupacha",
    "gn:population":0,
    "gn:timezone":"America/Lima",
    "iso:country":"PE",
    "wof:name":"Cupacha",
    "wof:placetype":"locality"
},
  "geometry": {"coordinates":[-77.7214,-6.17141],"type":"Point"}
}