{
  "type": "Feature",
  "properties": {
    "gn:admin1_code":"8.0",
    "gn:admin2_code":"803.0",
    "gn:admin3_code":"80306.0",
    "gn:asciiname":"Aychacata",
    "gn:country_code":"PE",
    "gn:dem":3657,
    "gn:feature_class":"P",
    "gn:feature_code":"PPL",
    "gn:name":"Aychacata",
    "gn:population":0,
    "gn:timezone":"America/Lima",
    "iso:country":"PE",
    "wof:name":"Aychacata",
    "wof:placetype":"locality"
},
  "geometry": {"coordinates":[-72.41028,-13.51472],"type":"Point"}
}