{
  "type": "Feature",
  "properties": {
    "gn:admin1_code":"6",
    "gn:admin2_code":"603.0",
    "gn:admin3_code":"60303.0",
    "gn:asciiname":"Calvario",
    "gn:country_code":"PE",
    "gn:dem":2390,
    "gn:feature_class":"P",
    "gn:feature_code":"PPL",
    "gn:name":"Calvario",
    "gn:population":0,
    "gn:timezone":"America/Lima",
    "iso:country":"PE",
    "wof:name":"Calvario",
    "wof:placetype":"locality"
},
  "geometry": {"coordinates":[-78.29371,-6.45573],"type":"Point"}
}