{
  "type": "Feature",
  "properties": {
    "gn:country":"PE",
    "gn:fcode":"PPLA3",
    "gn:pop":5998,
    "iso:country":"PE",
    "name:cat_x_preferred":[
        "San Agust\u00edn"
    ],
    "name:ceb_x_preferred":[
        "San Agust\u00edn"
    ],
    "name:deu_x_preferred":[
        "San Agust\u00edn"
    ],
    "name:heb_x_preferred":[
        "\u05e1\u05df \u05d0\u05d2\u05d5\u05e1\u05d8\u05d9\u05df"
    ],
    "name:ilo_x_preferred":[
        "San Agust\u00edn"
    ],
    "name:lit_x_preferred":[
        "San Agustinas"
    ],
    "name:pol_x_preferred":[
        "San Agust\u00edn"
    ],
    "name:por_x_preferred":[
        "San Agust\u00edn"
    ],
    "name:rus_x_preferred":[
        "\u0421\u0430\u043d-\u0410\u0433\u0443\u0441\u0442\u0438\u043d"
    ],
    "name:sco_x_preferred":[
        "San Agust\u00edn"
    ],
    "name:spa_x_preferred":[
        "San Agust\u00edn"
    ],
    "name:swe_x_preferred":[
        "San Agust\u00edn"
    ],
    "name:unk_x_variant":[
        "San Agust\u00edn de Cajas"
    ],
    "name:vie_x_preferred":[
        "San Agust\u00edn"
    ],
    "qs:name":"San Agustin",
    "qs:photos_9r":0,
    "qs:photos_sr":0,
    "qs:pop_sr":"5",
    "wd:wordcount":209,
    "wof:name":"San Agustin",
    "wof:placetype":"locality",
    "wof:population":5998
},
  "geometry": {"coordinates":[-75.24527999999999,-11.99219],"type":"Point"}
}