{
  "type": "Feature",
  "properties": {
    "gn:country":"PE",
    "gn:fcode":"PPLA3",
    "gn:pop":5998,
    "iso:country":"PE",
    "name:unk_x_variant":[
        "San Agust\u00edn de Cajas"
    ],
    "qs:name":"San Agustin",
    "qs:photos_9r":0,
    "qs:photos_sr":0,
    "qs:pop_sr":"5",
    "wd:wordcount":209,
    "wof:name":"San Agustin",
    "wof:placetype":"locality",
    "wof:population":5998
},
  "geometry": {"coordinates":[-75.24527999999999,-11.99219],"type":"Point"}
}