{
  "type": "Feature",
  "properties": {
    "gn:admin1_code":"8",
    "gn:admin2_code":"806.0",
    "gn:admin3_code":"80602.0",
    "gn:asciiname":"Ccanocota",
    "gn:country_code":"PE",
    "gn:dem":4270,
    "gn:feature_class":"P",
    "gn:feature_code":"PPL",
    "gn:name":"Ccanocota",
    "gn:population":0,
    "gn:timezone":"America/Lima",
    "iso:country":"PE",
    "wof:name":"Ccanocota",
    "wof:placetype":"locality"
},
  "geometry": {"coordinates":[-71.42228,-14.02283],"type":"Point"}
}