{
  "type": "Feature",
  "properties": {
    "gn:admin1_code":"2.0",
    "gn:admin2_code":"201.0",
    "gn:admin3_code":"20105.0",
    "gn:asciiname":"Orcon",
    "gn:country_code":"PE",
    "gn:dem":3351,
    "gn:feature_class":"P",
    "gn:feature_code":"PPL",
    "gn:name":"Orc\u00f3n",
    "gn:population":0,
    "gn:timezone":"America/Lima",
    "iso:country":"PE",
    "wof:name":"Orcon",
    "wof:placetype":"locality"
},
  "geometry": {"coordinates":[-77.53139,-9.44528],"type":"Point"}
}