{
  "type": "Feature",
  "properties": {
    "gn:admin1_code":"9.0",
    "gn:admin2_code":"903.0",
    "gn:admin3_code":"90301.0",
    "gn:asciiname":"Patara",
    "gn:country_code":"PE",
    "gn:dem":4091,
    "gn:feature_class":"P",
    "gn:feature_code":"PPL",
    "gn:name":"Patara",
    "gn:population":0,
    "gn:timezone":"America/Lima",
    "iso:country":"PE",
    "wof:name":"Patara",
    "wof:placetype":"locality"
},
  "geometry": {"coordinates":[-74.681,-12.99948],"type":"Point"}
}