{
  "type": "Feature",
  "properties": {
    "gn:admin1_code":"05",
    "gn:admin2_code":"509.0",
    "gn:admin3_code":"50903.0",
    "gn:asciiname":"Corral Pata",
    "gn:country_code":"PE",
    "gn:dem":3123,
    "gn:feature_class":"P",
    "gn:feature_code":"PPL",
    "gn:name":"Corral Pata",
    "gn:population":0,
    "gn:timezone":"America/Lima",
    "iso:country":"PE",
    "wof:name":"Corral Pata",
    "wof:placetype":"locality"
},
  "geometry": {"coordinates":[-73.74399,-13.83665],"type":"Point"}
}