{
  "type": "Feature",
  "properties": {
    "gn:admin1_code":"16.0",
    "gn:admin2_code":"1606.0",
    "gn:asciiname":"Charashamana",
    "gn:country_code":"PE",
    "gn:dem":165,
    "gn:feature_class":"P",
    "gn:feature_code":"PPL",
    "gn:name":"Charashamana",
    "gn:population":0,
    "gn:timezone":"America/Lima",
    "iso:country":"PE",
    "name:spa_x_preferred":[
        "Charashamana"
    ],
    "wof:name":"Charashamana",
    "wof:placetype":"locality"
},
  "geometry": {"coordinates":[-75.37005000000001,-7.84541],"type":"Point"}
}