{
  "type": "Feature",
  "properties": {
    "gn:admin1_code":"16.0",
    "gn:admin2_code":"1607.0",
    "gn:admin3_code":"160703.0",
    "gn:asciiname":"Saramiriza",
    "gn:country_code":"PE",
    "gn:dem":148,
    "gn:feature_class":"P",
    "gn:feature_code":"PPLA3",
    "gn:name":"Saramiriza",
    "gn:population":0,
    "gn:timezone":"America/Lima",
    "iso:country":"PE",
    "name:spa_x_preferred":[
        "Saramiriza"
    ],
    "wof:name":"Saramiriza",
    "wof:placetype":"locality"
},
  "geometry": {"coordinates":[-77.41583,-4.56556],"type":"Point"}
}