{
  "type": "Feature",
  "properties": {
    "gn:admin1_code":"21.0",
    "gn:admin2_code":"2105.0",
    "gn:admin3_code":"210502.0",
    "gn:asciiname":"San Jose de Ancomarca",
    "gn:country_code":"PE",
    "gn:dem":4215,
    "gn:feature_class":"P",
    "gn:feature_code":"PPL",
    "gn:name":"San Jos\u00e9 de Ancomarca",
    "gn:population":0,
    "gn:timezone":"America/Lima",
    "iso:country":"PE",
    "wof:name":"San Jose de Ancomarca",
    "wof:placetype":"locality"
},
  "geometry": {"coordinates":[-69.61166999999999,-17.20389],"type":"Point"}
}