{
  "type": "Feature",
  "properties": {
    "gn:admin1_code":"2.0",
    "gn:admin2_code":"217.0",
    "gn:admin3_code":"21706.0",
    "gn:asciiname":"Yurac Caca",
    "gn:country_code":"PE",
    "gn:dem":3418,
    "gn:feature_class":"P",
    "gn:feature_code":"PPL",
    "gn:name":"Yurac Caca",
    "gn:population":0,
    "gn:timezone":"America/Lima",
    "iso:country":"PE",
    "wof:name":"Yurac Caca",
    "wof:placetype":"locality"
},
  "geometry": {"coordinates":[-77.46486999999998,-10.05048],"type":"Point"}
}