{
  "type": "Feature",
  "properties": {
    "gn:admin1_code":"17.0",
    "gn:admin2_code":"1703.0",
    "gn:asciiname":"Prosperidad",
    "gn:country_code":"PE",
    "gn:dem":249,
    "gn:feature_class":"P",
    "gn:feature_code":"PPL",
    "gn:name":"Prosperidad",
    "gn:population":0,
    "gn:timezone":"America/Lima",
    "iso:country":"PE",
    "name:spa_x_preferred":[
        "Prosperidad"
    ],
    "wof:name":"Prosperidad",
    "wof:placetype":"locality"
},
  "geometry": {"coordinates":[-69.58394,-10.9812],"type":"Point"}
}