{
  "type": "Feature",
  "properties": {
    "gn:admin1_code":"17.0",
    "gn:admin2_code":"1703.0",
    "gn:asciiname":"Prosperidad",
    "gn:country_code":"PE",
    "gn:dem":249,
    "gn:feature_class":"P",
    "gn:feature_code":"PPL",
    "gn:name":"Prosperidad",
    "gn:population":0,
    "gn:timezone":"America/Lima",
    "iso:country":"PE",
    "name:ara_x_preferred":[
        "\u0628\u0631\u0648\u0633\u0628\u0631\u064a\u062f\u0627\u062f"
    ],
    "name:bcl_x_preferred":[
        "Prosperidad"
    ],
    "name:ceb_x_preferred":[
        "Prosperidad"
    ],
    "name:deu_x_preferred":[
        "Prosperidad"
    ],
    "name:fas_x_preferred":[
        "\u067e\u0631\u0648\u0633\u067e\u0631\u06cc\u062f\u0627\u062f"
    ],
    "name:fra_x_preferred":[
        "Prosperidad"
    ],
    "name:ilo_x_preferred":[
        "Prosperidad"
    ],
    "name:ind_x_preferred":[
        "Prosperidad"
    ],
    "name:ita_x_preferred":[
        "Prosperidad"
    ],
    "name:kor_x_preferred":[
        "\ud504\ub85c\uc2a4\ud398\ub9ac\ub2e4\ub4dc"
    ],
    "name:msa_x_preferred":[
        "Prosperidad"
    ],
    "name:nld_x_preferred":[
        "Prosperidad"
    ],
    "name:nor_x_preferred":[
        "Prosperidad"
    ],
    "name:pag_x_preferred":[
        "Prosperidad"
    ],
    "name:pam_x_preferred":[
        "Prosperidad"
    ],
    "name:pnb_x_preferred":[
        "\u067e\u0631\u0648\u0633\u067e\u06cc\u0631\u06cc\u0688\u0627\u0688"
    ],
    "name:pol_x_preferred":[
        "Prosperidad"
    ],
    "name:spa_x_preferred":[
        "Prosperidad"
    ],
    "name:swe_x_preferred":[
        "Prosperidad"
    ],
    "name:tgl_x_preferred":[
        "Prosperidad"
    ],
    "name:tha_x_preferred":[
        "\u0e42\u0e1b\u0e23\u0e2a\u0e40\u0e1b\u0e23\u0e35\u0e14\u0e31\u0e14"
    ],
    "name:urd_x_preferred":[
        "\u067e\u0631\u0648\u0633\u067e\u0631\u06cc\u062f\u0627\u062f"
    ],
    "name:war_x_preferred":[
        "Prosperidad"
    ],
    "wof:name":"Prosperidad",
    "wof:placetype":"locality"
},
  "geometry": {"coordinates":[-69.58394,-10.9812],"type":"Point"}
}