{
  "type": "Feature",
  "properties": {
    "gn:admin1_code":"13",
    "gn:admin2_code":"1309.0",
    "gn:admin3_code":"130908.0",
    "gn:asciiname":"Las Tayangas",
    "gn:country_code":"PE",
    "gn:dem":3044,
    "gn:feature_class":"P",
    "gn:feature_code":"PPL",
    "gn:name":"Las Tayangas",
    "gn:population":0,
    "gn:timezone":"America/Lima",
    "iso:country":"PE",
    "wof:name":"Las Tayangas",
    "wof:placetype":"locality"
},
  "geometry": {"coordinates":[-77.77339000000001,-7.58413],"type":"Point"}
}