{
  "type": "Feature",
  "properties": {
    "gn:admin1_code":"22.0",
    "gn:admin2_code":"2203.0",
    "gn:admin3_code":"220302.0",
    "gn:asciiname":"Gracias a Dios",
    "gn:country_code":"PE",
    "gn:dem":306,
    "gn:feature_class":"P",
    "gn:feature_code":"PPL",
    "gn:name":"Gracias a Dios",
    "gn:population":0,
    "gn:timezone":"America/Lima",
    "iso:country":"PE",
    "name:ceb_x_preferred":[
        "Gracias a Dios"
    ],
    "name:nld_x_preferred":[
        "Gracias a Dios"
    ],
    "name:pol_x_preferred":[
        "Gracias a Dios"
    ],
    "name:rus_x_preferred":[
        "\u0413\u0440\u0430\u0441\u044c\u044f\u0441-\u0430-\u0414\u044c\u043e\u0441"
    ],
    "name:spa_x_preferred":[
        "Gracias a Dios"
    ],
    "name:swe_x_preferred":[
        "Gracias a Dios"
    ],
    "wof:name":"Gracias a Dios",
    "wof:placetype":"locality"
},
  "geometry": {"coordinates":[-76.65100000000002,-6.73301],"type":"Point"}
}