{
  "type": "Feature",
  "properties": {
    "gn:admin1_code":"12.0",
    "gn:admin2_code":"1208.0",
    "gn:admin3_code":"120804.0",
    "gn:asciiname":"Cuevas",
    "gn:country_code":"PE",
    "gn:dem":4358,
    "gn:feature_class":"P",
    "gn:feature_code":"PPL",
    "gn:name":"Cuevas",
    "gn:population":0,
    "gn:timezone":"America/Lima",
    "iso:country":"PE",
    "name:ast_x_preferred":[
        "Cuevas"
    ],
    "name:cat_x_preferred":[
        "Cuevas"
    ],
    "name:ceb_x_preferred":[
        "Cuevas"
    ],
    "name:deu_x_preferred":[
        "Cuevas"
    ],
    "name:fra_x_preferred":[
        "Cuevas"
    ],
    "name:por_x_preferred":[
        "Cuevas"
    ],
    "name:rus_x_preferred":[
        "\u041a\u0443\u044d\u0432\u0430"
    ],
    "name:spa_x_preferred":[
        "Cuevas"
    ],
    "name:swe_x_preferred":[
        "Cuevas"
    ],
    "wof:name":"Cuevas",
    "wof:placetype":"locality"
},
  "geometry": {"coordinates":[-76.30099,-11.49543],"type":"Point"}
}