{
  "type": "Feature",
  "properties": {
    "gn:admin1_code":"20",
    "gn:admin2_code":"2006.0",
    "gn:admin3_code":"200604.0",
    "gn:asciiname":"Piedra Redonda",
    "gn:country_code":"PE",
    "gn:dem":295,
    "gn:feature_class":"P",
    "gn:feature_code":"PPL",
    "gn:name":"Piedra Redonda",
    "gn:population":0,
    "gn:timezone":"America/Lima",
    "iso:country":"PE",
    "wof:name":"Piedra Redonda",
    "wof:placetype":"locality"
},
  "geometry": {"coordinates":[-80.57361,-4.36],"type":"Point"}
}