{
  "type": "Feature",
  "properties": {
    "gn:admin1_code":"9.0",
    "gn:admin2_code":"902.0",
    "gn:admin3_code":"90203.0",
    "gn:asciiname":"Chucpapampa",
    "gn:country_code":"PE",
    "gn:dem":3646,
    "gn:feature_class":"P",
    "gn:feature_code":"PPL",
    "gn:name":"Chucpapampa",
    "gn:population":0,
    "gn:timezone":"America/Lima",
    "iso:country":"PE",
    "wof:name":"Chucpapampa",
    "wof:placetype":"locality"
},
  "geometry": {"coordinates":[-74.71303,-12.80344],"type":"Point"}
}