{
  "type": "Feature",
  "properties": {
    "gn:admin1_code":"13.0",
    "gn:admin2_code":"1304.0",
    "gn:admin3_code":"130402.0",
    "gn:asciiname":"Huaca Rajada",
    "gn:country_code":"PE",
    "gn:dem":86,
    "gn:feature_class":"P",
    "gn:feature_code":"PPL",
    "gn:name":"Huaca Rajada",
    "gn:population":0,
    "gn:timezone":"America/Lima",
    "iso:country":"PE",
    "name:spa_x_preferred":[
        "Huaca Rajada"
    ],
    "wof:name":"Huaca Rajada",
    "wof:placetype":"locality"
},
  "geometry": {"coordinates":[-79.49313000000002,-7.17312],"type":"Point"}
}