{
  "type": "Feature",
  "properties": {
    "gn:admin1_code":"13.0",
    "gn:admin2_code":"1304.0",
    "gn:admin3_code":"130402.0",
    "gn:asciiname":"Huaca Rajada",
    "gn:country_code":"PE",
    "gn:dem":86,
    "gn:feature_class":"P",
    "gn:feature_code":"PPL",
    "gn:name":"Huaca Rajada",
    "gn:population":0,
    "gn:timezone":"America/Lima",
    "iso:country":"PE",
    "name:fra_x_preferred":[
        "Sip\u00e1n"
    ],
    "name:ita_x_preferred":[
        "Sip\u00e1n"
    ],
    "name:jpn_x_preferred":[
        "\u30b7\u30d1\u30f3"
    ],
    "name:kat_x_preferred":[
        "\u10e1\u10d8\u10de\u10d0\u10dc\u10d8"
    ],
    "name:mkd_x_preferred":[
        "\u0421\u0438\u043f\u0430\u043d"
    ],
    "name:nld_x_preferred":[
        "Sip\u00e1n"
    ],
    "name:nno_x_preferred":[
        "Sip\u00e1n"
    ],
    "name:pol_x_preferred":[
        "Sip\u00e1n"
    ],
    "name:que_x_preferred":[
        "Sip\u00e1n"
    ],
    "name:spa_x_preferred":[
        "Huaca Rajada"
    ],
    "name:swe_x_preferred":[
        "Sip\u00e1n"
    ],
    "name:ukr_x_preferred":[
        "\u0421\u0456\u043f\u0430\u043d"
    ],
    "wof:name":"Huaca Rajada",
    "wof:placetype":"locality"
},
  "geometry": {"coordinates":[-79.49313000000002,-7.17312],"type":"Point"}
}