{
  "type": "Feature",
  "properties": {
    "gn:admin1_code":"9.0",
    "gn:admin2_code":"905.0",
    "gn:admin3_code":"90507.0",
    "gn:asciiname":"Uchuytucu",
    "gn:country_code":"PE",
    "gn:dem":3968,
    "gn:feature_class":"P",
    "gn:feature_code":"PPL",
    "gn:name":"Uchuytucu",
    "gn:population":0,
    "gn:timezone":"America/Lima",
    "iso:country":"PE",
    "wof:name":"Uchuytucu",
    "wof:placetype":"locality"
},
  "geometry": {"coordinates":[-74.54568,-12.57308],"type":"Point"}
}