{
  "type": "Feature",
  "properties": {
    "gn:admin1_code":"21",
    "gn:admin2_code":"2104.0",
    "gn:admin3_code":"210401.0",
    "gn:asciiname":"Pallalli Marca",
    "gn:country_code":"PE",
    "gn:dem":4011,
    "gn:feature_class":"P",
    "gn:feature_code":"PPL",
    "gn:name":"Pallalli Marca",
    "gn:population":0,
    "gn:timezone":"America/Lima",
    "iso:country":"PE",
    "wof:name":"Pallalli Marca",
    "wof:placetype":"locality"
},
  "geometry": {"coordinates":[-69.48438,-16.4175],"type":"Point"}
}