{
  "type": "Feature",
  "properties": {
    "gn:admin1_code":"20",
    "gn:admin2_code":"2004.0",
    "gn:admin3_code":"200410.0",
    "gn:asciiname":"Nangay",
    "gn:country_code":"PE",
    "gn:dem":1273,
    "gn:feature_class":"P",
    "gn:feature_code":"PPL",
    "gn:name":"Nangay",
    "gn:population":0,
    "gn:timezone":"America/Lima",
    "iso:country":"PE",
    "wof:name":"Nangay",
    "wof:placetype":"locality"
},
  "geometry": {"coordinates":[-79.74921999999999,-5.13661],"type":"Point"}
}