{
  "type": "Feature",
  "properties": {
    "gn:admin1_code":"5",
    "gn:admin2_code":"506.0",
    "gn:admin3_code":"50608.0",
    "gn:asciiname":"Ichurutuna",
    "gn:country_code":"PE",
    "gn:dem":2525,
    "gn:feature_class":"P",
    "gn:feature_code":"PPL",
    "gn:name":"Ichurutuna",
    "gn:population":0,
    "gn:timezone":"America/Lima",
    "iso:country":"PE",
    "wof:name":"Ichurutuna",
    "wof:placetype":"locality"
},
  "geometry": {"coordinates":[-75.00641,-14.35228],"type":"Point"}
}