{
  "type": "Feature",
  "properties": {
    "gn:admin1_code":"8",
    "gn:admin2_code":"805.0",
    "gn:admin3_code":"80501.0",
    "gn:asciiname":"Curancuran",
    "gn:country_code":"PE",
    "gn:dem":4025,
    "gn:feature_class":"P",
    "gn:feature_code":"PPL",
    "gn:name":"Curancuran",
    "gn:population":0,
    "gn:timezone":"America/Lima",
    "iso:country":"PE",
    "wof:name":"Curancuran",
    "wof:placetype":"locality"
},
  "geometry": {"coordinates":[-71.41064,-14.24413],"type":"Point"}
}