{
  "type": "Feature",
  "properties": {
    "gn:admin1_code":"2.0",
    "gn:admin2_code":"208.0",
    "gn:admin3_code":"20804.0",
    "gn:asciiname":"Hacienda Quiuchan",
    "gn:country_code":"PE",
    "gn:dem":464,
    "gn:feature_class":"P",
    "gn:feature_code":"PPL",
    "gn:name":"Hacienda Quiuchan",
    "gn:population":0,
    "gn:timezone":"America/Lima",
    "iso:country":"PE",
    "name:spa_x_preferred":[
        "Hacienda Quiuchan"
    ],
    "wof:name":"Hacienda Quiuchan",
    "wof:placetype":"locality"
},
  "geometry": {"coordinates":[-78.05965999999999,-9.53368],"type":"Point"}
}