{
  "type": "Feature",
  "properties": {
    "gn:admin1_code":"09",
    "gn:admin2_code":"901.0",
    "gn:admin3_code":"90117.0",
    "gn:asciiname":"Cunyac",
    "gn:country_code":"PE",
    "gn:dem":4490,
    "gn:feature_class":"P",
    "gn:feature_code":"PPL",
    "gn:name":"Cunyac",
    "gn:population":0,
    "gn:timezone":"America/Lima",
    "iso:country":"PE",
    "wof:name":"Cunyac",
    "wof:placetype":"locality"
},
  "geometry": {"coordinates":[-74.88333,-12.86667],"type":"Point"}
}