{
  "type": "Feature",
  "properties": {
    "gn:admin1_code":"06",
    "gn:admin2_code":"603.0",
    "gn:admin3_code":"60304.0",
    "gn:asciiname":"Pajonal",
    "gn:country_code":"PE",
    "gn:dem":3179,
    "gn:feature_class":"P",
    "gn:feature_code":"PPL",
    "gn:name":"Pajonal",
    "gn:population":0,
    "gn:timezone":"America/Lima",
    "iso:country":"PE",
    "name:ita_x_preferred":[
        "Pajonal"
    ],
    "name:spa_x_preferred":[
        "Pajonal"
    ],
    "name:zho_x_preferred":[
        "\u5e15\u970d\u7eb3\u5c14"
    ],
    "wof:name":"Pajonal",
    "wof:placetype":"locality"
},
  "geometry": {"coordinates":[-78.22919,-6.95223],"type":"Point"}
}