{
  "type": "Feature",
  "properties": {
    "gn:admin1_code":"3",
    "gn:admin2_code":"302.0",
    "gn:admin3_code":"30212.0",
    "gn:asciiname":"Cascabambilla",
    "gn:country_code":"PE",
    "gn:dem":3651,
    "gn:feature_class":"P",
    "gn:feature_code":"PPL",
    "gn:name":"Cascabambilla",
    "gn:population":0,
    "gn:timezone":"America/Lima",
    "iso:country":"PE",
    "wof:name":"Cascabambilla",
    "wof:placetype":"locality"
},
  "geometry": {"coordinates":[-73.69228000000003,-13.80608],"type":"Point"}
}