{
  "type": "Feature",
  "properties": {
    "iso:country":"PE",
    "qs:gn_country":"PE",
    "qs:gn_fcode":"PPL",
    "qs:gn_pop":0,
    "qs:name":"Jancas",
    "qs:name_adm0":"Per\u00fa",
    "qs:name_adm1":"Ancash",
    "qs:photos":95,
    "qs:photos_1k":19,
    "qs:photos_9k":1,
    "qs:photos_9r":3,
    "qs:photos_all":95,
    "qs:photos_sr":3,
    "qs:placetype":"Town",
    "qs:pop_sr":"0",
    "qs:woe_adm0":23424919,
    "wof:name":"Jancas",
    "wof:placetype":"locality"
},
  "geometry": {"coordinates":[-76.88806,-10.17611],"type":"Point"}
}