{
  "type": "Feature",
  "properties": {
    "gn:admin1_code":"15.0",
    "gn:admin2_code":"1505.0",
    "gn:admin3_code":"150501.0",
    "gn:asciiname":"La Cruz",
    "gn:country_code":"PE",
    "gn:dem":21,
    "gn:feature_class":"P",
    "gn:feature_code":"PPL",
    "gn:name":"La Cruz",
    "gn:population":0,
    "gn:timezone":"America/Lima",
    "iso:country":"PE",
    "wof:name":"La Cruz",
    "wof:placetype":"locality"
},
  "geometry": {"coordinates":[-76.39615999999999,-13.13283],"type":"Point"}
}