{
  "type": "Feature",
  "properties": {
    "gn:admin1_code":"15",
    "gn:admin2_code":"1510.0",
    "gn:admin3_code":"151021.0",
    "gn:asciiname":"Tincopata",
    "gn:country_code":"PE",
    "gn:dem":3905,
    "gn:feature_class":"P",
    "gn:feature_code":"PPL",
    "gn:name":"Tincopata",
    "gn:population":0,
    "gn:timezone":"America/Lima",
    "iso:country":"PE",
    "wof:name":"Tincopata",
    "wof:placetype":"locality"
},
  "geometry": {"coordinates":[-75.86721999999997,-12.27139],"type":"Point"}
}