{
  "type": "Feature",
  "properties": {
    "gn:admin1_code":"12.0",
    "gn:admin2_code":"1208.0",
    "gn:admin3_code":"120802.0",
    "gn:asciiname":"Colpa",
    "gn:country_code":"PE",
    "gn:dem":3914,
    "gn:feature_class":"P",
    "gn:feature_code":"PPL",
    "gn:name":"Colpa",
    "gn:population":0,
    "gn:timezone":"America/Lima",
    "iso:country":"PE",
    "wof:name":"Colpa",
    "wof:placetype":"locality"
},
  "geometry": {"coordinates":[-75.87288000000002,-11.70976],"type":"Point"}
}