{
  "type": "Feature",
  "properties": {
    "gn:admin1_code":"11",
    "gn:admin2_code":"1103.0",
    "gn:admin3_code":"110305.0",
    "gn:asciiname":"Llicuas",
    "gn:country_code":"PE",
    "gn:dem":800,
    "gn:feature_class":"P",
    "gn:feature_code":"PPL",
    "gn:name":"Llicuas",
    "gn:population":0,
    "gn:timezone":"America/Lima",
    "iso:country":"PE",
    "name:spa_x_preferred":[
        "Llicuas"
    ],
    "wof:name":"Llicuas",
    "wof:placetype":"locality"
},
  "geometry": {"coordinates":[-74.76697,-14.97054],"type":"Point"}
}