{
  "type": "Feature",
  "properties": {
    "gn:admin1_code":"04",
    "gn:admin2_code":"401.0",
    "gn:admin3_code":"40119.0",
    "gn:asciiname":"Ceneguillas",
    "gn:country_code":"PE",
    "gn:dem":4360,
    "gn:feature_class":"P",
    "gn:feature_code":"PPL",
    "gn:name":"Ceneguillas",
    "gn:population":0,
    "gn:timezone":"America/Lima",
    "iso:country":"PE",
    "wof:name":"Ceneguillas",
    "wof:placetype":"locality"
},
  "geometry": {"coordinates":[-71.16991999999998,-16.33641],"type":"Point"}
}