{
  "type": "Feature",
  "properties": {
    "gn:admin1_code":"08",
    "gn:admin2_code":"809.0",
    "gn:admin3_code":"80902.0",
    "gn:asciiname":"Piquepata",
    "gn:country_code":"PE",
    "gn:dem":2237,
    "gn:feature_class":"P",
    "gn:feature_code":"PPL",
    "gn:name":"Piquepata",
    "gn:population":0,
    "gn:timezone":"America/Lima",
    "iso:country":"PE",
    "wof:name":"Piquepata",
    "wof:placetype":"locality"
},
  "geometry": {"coordinates":[-72.73333000000002,-12.75],"type":"Point"}
}