{
  "type": "Feature",
  "properties": {
    "gn:admin1_code":"12.0",
    "gn:admin2_code":"1208.0",
    "gn:admin3_code":"120809.0",
    "gn:asciiname":"Pacllaesquina",
    "gn:country_code":"PE",
    "gn:dem":4420,
    "gn:feature_class":"P",
    "gn:feature_code":"PPL",
    "gn:name":"Pacllaesquina",
    "gn:population":0,
    "gn:timezone":"America/Lima",
    "iso:country":"PE",
    "wof:name":"Pacllaesquina",
    "wof:placetype":"locality"
},
  "geometry": {"coordinates":[-75.99163,-11.81622],"type":"Point"}
}