{
  "type": "Feature",
  "properties": {
    "gn:admin1_code":"20",
    "gn:admin2_code":"2004.0",
    "gn:admin3_code":"200402.0",
    "gn:asciiname":"Piedra Herrada",
    "gn:country_code":"PE",
    "gn:dem":140,
    "gn:feature_class":"P",
    "gn:feature_code":"PPL",
    "gn:name":"Piedra Herrada",
    "gn:population":0,
    "gn:timezone":"America/Lima",
    "iso:country":"PE",
    "wof:name":"Piedra Herrada",
    "wof:placetype":"locality"
},
  "geometry": {"coordinates":[-79.93829000000002,-5.23922],"type":"Point"}
}