{
  "type": "Feature",
  "properties": {
    "gn:admin1_code":"13.0",
    "gn:admin2_code":"1308.0",
    "gn:admin3_code":"130804.0",
    "gn:asciiname":"Tancaybamba",
    "gn:country_code":"PE",
    "gn:dem":1958,
    "gn:feature_class":"P",
    "gn:feature_code":"PPL",
    "gn:name":"Tancaybamba",
    "gn:population":0,
    "gn:timezone":"America/Lima",
    "iso:country":"PE",
    "wof:name":"Tancaybamba",
    "wof:placetype":"locality"
},
  "geometry": {"coordinates":[-77.38916999999999,-8.38639],"type":"Point"}
}