{
  "type": "Feature",
  "properties": {
    "gn:admin1_code":"22.0",
    "gn:admin2_code":"2208.0",
    "gn:admin3_code":"220804.0",
    "gn:asciiname":"Tupac Amaru",
    "gn:country_code":"PE",
    "gn:dem":954,
    "gn:feature_class":"P",
    "gn:feature_code":"PPL",
    "gn:name":"T\u00fapac Amaru",
    "gn:population":0,
    "gn:timezone":"America/Lima",
    "iso:country":"PE",
    "wof:name":"Tupac Amaru",
    "wof:placetype":"locality"
},
  "geometry": {"coordinates":[-77.42889,-5.83722],"type":"Point"}
}