{
  "type": "Feature",
  "properties": {
    "gn:admin1_code":"15",
    "gn:admin2_code":"1510.0",
    "gn:admin3_code":"151007.0",
    "gn:asciiname":"Condumia",
    "gn:country_code":"PE",
    "gn:dem":4267,
    "gn:feature_class":"P",
    "gn:feature_code":"PPL",
    "gn:name":"Condumia",
    "gn:population":0,
    "gn:timezone":"America/Lima",
    "iso:country":"PE",
    "wof:name":"Condumia",
    "wof:placetype":"locality"
},
  "geometry": {"coordinates":[-75.85666999999999,-12.33417],"type":"Point"}
}