{
  "type": "Feature",
  "properties": {
    "gn:admin1_code":"10.0",
    "gn:admin2_code":"1003.0",
    "gn:admin3_code":"100301.0",
    "gn:asciiname":"Jircahuain",
    "gn:country_code":"PE",
    "gn:dem":3800,
    "gn:feature_class":"P",
    "gn:feature_code":"PPL",
    "gn:name":"Jircahuain",
    "gn:population":0,
    "gn:timezone":"America/Lima",
    "iso:country":"PE",
    "wof:name":"Jircahuain",
    "wof:placetype":"locality"
},
  "geometry": {"coordinates":[-76.74231999999998,-9.89787],"type":"Point"}
}