{
  "type": "Feature",
  "properties": {
    "gn:admin1_code":"5.0",
    "gn:admin2_code":"504.0",
    "gn:asciiname":"Torre Rumi",
    "gn:country_code":"PE",
    "gn:dem":1000,
    "gn:feature_class":"P",
    "gn:feature_code":"PPL",
    "gn:name":"Torre Rumi",
    "gn:population":0,
    "gn:timezone":"America/Lima",
    "iso:country":"PE",
    "name:spa_x_preferred":[
        "Torre Rumi"
    ],
    "wof:name":"Torre Rumi",
    "wof:placetype":"locality"
},
  "geometry": {"coordinates":[-73.91231999999999,-12.48397],"type":"Point"}
}