{
  "type": "Feature",
  "properties": {
    "gn:admin1_code":"9.0",
    "gn:admin2_code":"907.0",
    "gn:admin3_code":"90709.0",
    "gn:asciiname":"Corazon de Jesus de Ranracancha",
    "gn:country_code":"PE",
    "gn:dem":4195,
    "gn:feature_class":"P",
    "gn:feature_code":"PPL",
    "gn:name":"Coraz\u00f3n de Jes\u00fas de Ranracancha",
    "gn:population":0,
    "gn:timezone":"America/Lima",
    "iso:country":"PE",
    "wof:name":"Corazon de Jesus de Ranracancha",
    "wof:placetype":"locality"
},
  "geometry": {"coordinates":[-74.96911,-12.12443],"type":"Point"}
}