{
  "type": "Feature",
  "properties": {
    "gn:admin1_code":"10",
    "gn:admin2_code":"1008.0",
    "gn:admin3_code":"100801.0",
    "gn:asciiname":"Milpo",
    "gn:country_code":"PE",
    "gn:dem":3444,
    "gn:feature_class":"P",
    "gn:feature_code":"PPL",
    "gn:name":"Milpo",
    "gn:population":0,
    "gn:timezone":"America/Lima",
    "iso:country":"PE",
    "name:ceb_x_preferred":[
        "Milpo"
    ],
    "name:swe_x_preferred":[
        "Milpo"
    ],
    "wof:name":"Milpo",
    "wof:placetype":"locality"
},
  "geometry": {"coordinates":[-75.90444000000002,-10.30111],"type":"Point"}
}