{
  "type": "Feature",
  "properties": {
    "gn:admin1_code":"22",
    "gn:admin2_code":"2202.0",
    "gn:admin3_code":"220202.0",
    "gn:asciiname":"Barranca",
    "gn:country_code":"PE",
    "gn:dem":270,
    "gn:feature_class":"P",
    "gn:feature_code":"PPL",
    "gn:name":"Barranca",
    "gn:population":0,
    "gn:timezone":"America/Lima",
    "iso:country":"PE",
    "wof:name":"Barranca",
    "wof:placetype":"locality"
},
  "geometry": {"coordinates":[-76.46834,-7.27471],"type":"Point"}
}