{
  "type": "Feature",
  "properties": {
    "gn:admin1_code":"6.0",
    "gn:admin2_code":"608.0",
    "gn:admin3_code":"60805.0",
    "gn:asciiname":"Huabal",
    "gn:country_code":"PE",
    "gn:dem":1473,
    "gn:feature_class":"P",
    "gn:feature_code":"PPLA3",
    "gn:name":"Huabal",
    "gn:population":0,
    "gn:timezone":"America/Lima",
    "iso:country":"PE",
    "wof:name":"Huabal",
    "wof:placetype":"locality"
},
  "geometry": {"coordinates":[-78.92333000000001,-5.61611],"type":"Point"}
}