{
  "type": "Feature",
  "properties": {
    "gn:admin1_code":"20",
    "gn:admin2_code":"2003.0",
    "gn:admin3_code":"200302.0",
    "gn:asciiname":"Huajambe",
    "gn:country_code":"PE",
    "gn:dem":1435,
    "gn:feature_class":"P",
    "gn:feature_code":"PPL",
    "gn:name":"Huajambe",
    "gn:population":0,
    "gn:timezone":"America/Lima",
    "iso:country":"PE",
    "name:und_x_variant":[
        "Huajambre",
        "Huajambre Ciudad",
        "Huajambe"
    ],
    "wof:name":"Huajambe",
    "wof:placetype":"locality"
},
  "geometry": {"coordinates":[-79.62329,-5.22548],"type":"Point"}
}