{
  "type": "Feature",
  "properties": {
    "gn:admin1_code":"12.0",
    "gn:admin2_code":"1202.0",
    "gn:admin3_code":"120206.0",
    "gn:asciiname":"Repichon",
    "gn:country_code":"PE",
    "gn:dem":3735,
    "gn:feature_class":"P",
    "gn:feature_code":"PPL",
    "gn:name":"Repich\u00f3n",
    "gn:population":0,
    "gn:timezone":"America/Lima",
    "iso:country":"PE",
    "wof:name":"Repichon",
    "wof:placetype":"locality"
},
  "geometry": {"coordinates":[-75.02481,-11.69476],"type":"Point"}
}