{
  "type": "Feature",
  "properties": {
    "gn:admin1_code":"12.0",
    "gn:admin2_code":"1204.0",
    "gn:admin3_code":"120425.0",
    "gn:asciiname":"Turumanya",
    "gn:country_code":"PE",
    "gn:dem":3419,
    "gn:feature_class":"P",
    "gn:feature_code":"PPL",
    "gn:name":"Turumanya",
    "gn:population":0,
    "gn:timezone":"America/Lima",
    "iso:country":"PE",
    "wof:name":"Turumanya",
    "wof:placetype":"locality"
},
  "geometry": {"coordinates":[-75.5604,-11.78293],"type":"Point"}
}