{
  "type": "Feature",
  "properties": {
    "gn:admin1_code":"06",
    "gn:admin2_code":"601.0",
    "gn:admin3_code":"60104.0",
    "gn:asciiname":"Hacienda Farrat",
    "gn:country_code":"PE",
    "gn:dem":1341,
    "gn:feature_class":"P",
    "gn:feature_code":"PPL",
    "gn:name":"Hacienda Farrat",
    "gn:population":0,
    "gn:timezone":"America/Lima",
    "iso:country":"PE",
    "wof:name":"Hacienda Farrat",
    "wof:placetype":"locality"
},
  "geometry": {"coordinates":[-78.52444,-7.55711],"type":"Point"}
}