{
  "type": "Feature",
  "properties": {
    "gn:admin1_code":"05",
    "gn:admin2_code":"507.0",
    "gn:admin3_code":"50702.0",
    "gn:asciiname":"Jolchuscha",
    "gn:country_code":"PE",
    "gn:dem":3497,
    "gn:feature_class":"P",
    "gn:feature_code":"PPL",
    "gn:name":"Jolchuscha",
    "gn:population":0,
    "gn:timezone":"America/Lima",
    "iso:country":"PE",
    "name:spa_x_preferred":[
        "Jolchuscha"
    ],
    "wof:name":"Jolchuscha",
    "wof:placetype":"locality"
},
  "geometry": {"coordinates":[-73.56107,-15.09154],"type":"Point"}
}