{
  "type": "Feature",
  "properties": {
    "gn:admin1_code":"22.0",
    "gn:admin2_code":"2205.0",
    "gn:admin3_code":"220505.0",
    "gn:asciiname":"Progreso",
    "gn:country_code":"PE",
    "gn:dem":406,
    "gn:feature_class":"P",
    "gn:feature_code":"PPL",
    "gn:name":"Progreso",
    "gn:population":0,
    "gn:timezone":"America/Lima",
    "iso:country":"PE",
    "name:spa_x_preferred":[
        "Progreso"
    ],
    "wof:name":"Progreso",
    "wof:placetype":"locality"
},
  "geometry": {"coordinates":[-76.43734000000001,-6.65617],"type":"Point"}
}