{
  "type": "Feature",
  "properties": {
    "gn:admin1_code":"20",
    "gn:admin2_code":"2005.0",
    "gn:admin3_code":"200505.0",
    "gn:asciiname":"Viviate",
    "gn:country_code":"PE",
    "gn:dem":29,
    "gn:feature_class":"P",
    "gn:feature_code":"PPL",
    "gn:name":"Viviate",
    "gn:population":0,
    "gn:timezone":"America/Lima",
    "iso:country":"PE",
    "name:spa_x_preferred":[
        "Viviare"
    ],
    "name:und_x_variant":[
        "Viviate Hacienda",
        "Viviace",
        "Viviate"
    ],
    "wof:name":"Viviate",
    "wof:placetype":"locality"
},
  "geometry": {"coordinates":[-80.91622,-4.91958],"type":"Point"}
}