{
  "type": "Feature",
  "properties": {
    "gn:admin1_code":"14",
    "gn:admin2_code":"1403.0",
    "gn:admin3_code":"140303.0",
    "gn:asciiname":"Huaca Culpon Alto",
    "gn:country_code":"PE",
    "gn:dem":55,
    "gn:feature_class":"P",
    "gn:feature_code":"PPL",
    "gn:name":"Huaca Culp\u00f3n Alto",
    "gn:population":0,
    "gn:timezone":"America/Lima",
    "iso:country":"PE",
    "wof:name":"Huaca Culpon Alto",
    "wof:placetype":"locality"
},
  "geometry": {"coordinates":[-79.83575,-6.4659],"type":"Point"}
}