{
  "type": "Feature",
  "properties": {
    "gn:admin1_code":"05",
    "gn:admin2_code":"503.0",
    "gn:admin3_code":"50303.0",
    "gn:asciiname":"Huachoajasa",
    "gn:country_code":"PE",
    "gn:dem":4378,
    "gn:feature_class":"P",
    "gn:feature_code":"PPL",
    "gn:name":"Huachoajasa",
    "gn:population":0,
    "gn:timezone":"America/Lima",
    "iso:country":"PE",
    "wof:name":"Huachoajasa",
    "wof:placetype":"locality"
},
  "geometry": {"coordinates":[-74.12900999999999,-14.02187],"type":"Point"}
}