{
  "type": "Feature",
  "properties": {
    "gn:admin1_code":"21",
    "gn:admin2_code":"2103.0",
    "gn:admin3_code":"210306.0",
    "gn:asciiname":"Chajominas",
    "gn:country_code":"PE",
    "gn:dem":4472,
    "gn:feature_class":"P",
    "gn:feature_code":"PPL",
    "gn:name":"Chajominas",
    "gn:population":0,
    "gn:timezone":"America/Lima",
    "iso:country":"PE",
    "wof:name":"Chajominas",
    "wof:placetype":"locality"
},
  "geometry": {"coordinates":[-69.73846999999999,-14.46832],"type":"Point"}
}