{
  "type": "Feature",
  "properties": {
    "gn:admin1_code":"14",
    "gn:admin2_code":"1401.0",
    "gn:admin3_code":"140110.0",
    "gn:asciiname":"Zorronto",
    "gn:country_code":"PE",
    "gn:dem":237,
    "gn:feature_class":"P",
    "gn:feature_code":"PPL",
    "gn:name":"Zorronto",
    "gn:population":0,
    "gn:timezone":"America/Lima",
    "iso:country":"PE",
    "name:und_x_variant":[
        "Sorronto",
        "Zorronto"
    ],
    "wof:name":"Zorronto",
    "wof:placetype":"locality"
},
  "geometry": {"coordinates":[-79.31859,-6.833],"type":"Point"}
}