{
  "type": "Feature",
  "properties": {
    "gn:admin1_code":"8",
    "gn:admin2_code":"811.0",
    "gn:admin3_code":"81104.0",
    "gn:asciiname":"Rio Pichihua",
    "gn:country_code":"PE",
    "gn:dem":3081,
    "gn:feature_class":"P",
    "gn:feature_code":"PPL",
    "gn:name":"R\u00edo Pichihua",
    "gn:population":0,
    "gn:timezone":"America/Lima",
    "iso:country":"PE",
    "wof:name":"Rio Pichihua",
    "wof:placetype":"locality"
},
  "geometry": {"coordinates":[-71.54528000000001,-13.41639],"type":"Point"}
}