{
  "type": "Feature",
  "properties": {
    "gn:admin1_code":"10",
    "gn:admin2_code":"1001.0",
    "gn:admin3_code":"100104.0",
    "gn:asciiname":"Umari",
    "gn:country_code":"PE",
    "gn:dem":1981,
    "gn:feature_class":"P",
    "gn:feature_code":"PPL",
    "gn:name":"Umari",
    "gn:population":0,
    "gn:timezone":"America/Lima",
    "iso:country":"PE",
    "name:ceb_x_preferred":[
        "Umari"
    ],
    "name:deu_x_preferred":[
        "Umari"
    ],
    "name:ita_x_preferred":[
        "Umari"
    ],
    "name:swe_x_preferred":[
        "Umari"
    ],
    "wof:name":"Umari",
    "wof:placetype":"locality"
},
  "geometry": {"coordinates":[-76.13271,-9.84542],"type":"Point"}
}