{
  "type": "Feature",
  "properties": {
    "gn:admin1_code":"03",
    "gn:admin2_code":"305.0",
    "gn:admin3_code":"30506.0",
    "gn:asciiname":"Choccollo",
    "gn:country_code":"PE",
    "gn:dem":4156,
    "gn:feature_class":"P",
    "gn:feature_code":"PPL",
    "gn:name":"Choccollo",
    "gn:population":0,
    "gn:timezone":"America/Lima",
    "iso:country":"PE",
    "wof:name":"Choccollo",
    "wof:placetype":"locality"
},
  "geometry": {"coordinates":[-72.36667,-14.21667],"type":"Point"}
}