{
  "type": "Feature",
  "properties": {
    "gn:admin1_code":"11.0",
    "gn:admin2_code":"1103.0",
    "gn:admin3_code":"110305.0",
    "gn:asciiname":"Trigal",
    "gn:country_code":"PE",
    "gn:dem":1687,
    "gn:feature_class":"P",
    "gn:feature_code":"PPL",
    "gn:name":"Trigal",
    "gn:population":0,
    "gn:timezone":"America/Lima",
    "iso:country":"PE",
    "name:spa_x_preferred":[
        "Trigal"
    ],
    "wof:name":"Trigal",
    "wof:placetype":"locality"
},
  "geometry": {"coordinates":[-74.76326999999998,-14.87069],"type":"Point"}
}