{
  "type": "Feature",
  "properties": {
    "gn:admin1_code":"20",
    "gn:admin2_code":"2003.0",
    "gn:admin3_code":"200307.0",
    "gn:asciiname":"Churupampa",
    "gn:country_code":"PE",
    "gn:dem":1935,
    "gn:feature_class":"P",
    "gn:feature_code":"PPL",
    "gn:name":"Churupampa",
    "gn:population":0,
    "gn:timezone":"America/Lima",
    "iso:country":"PE",
    "name:und_x_variant":[
        "Churupampa Ciudad",
        "Churupampa"
    ],
    "wof:name":"Churupampa",
    "wof:placetype":"locality"
},
  "geometry": {"coordinates":[-79.34076,-5.48977],"type":"Point"}
}