{
  "type": "Feature",
  "properties": {
    "gn:admin1_code":"21",
    "gn:admin2_code":"2101.0",
    "gn:admin3_code":"210114.0",
    "gn:asciiname":"Peruani",
    "gn:country_code":"PE",
    "gn:dem":4287,
    "gn:feature_class":"P",
    "gn:feature_code":"PPL",
    "gn:name":"Peruani",
    "gn:population":0,
    "gn:timezone":"America/Lima",
    "iso:country":"PE",
    "wof:name":"Peruani",
    "wof:placetype":"locality"
},
  "geometry": {"coordinates":[-70.24565,-15.96639],"type":"Point"}
}