{
  "type": "Feature",
  "properties": {
    "gn:admin1_code":"21",
    "gn:admin2_code":"2101.0",
    "gn:admin3_code":"210113.0",
    "gn:asciiname":"Asiento Conchopata",
    "gn:country_code":"PE",
    "gn:dem":4604,
    "gn:feature_class":"P",
    "gn:feature_code":"PPL",
    "gn:name":"Asiento Conchopata",
    "gn:population":0,
    "gn:timezone":"America/Lima",
    "iso:country":"PE",
    "wof:name":"Asiento Conchopata",
    "wof:placetype":"locality"
},
  "geometry": {"coordinates":[-70.28076,-16.1154],"type":"Point"}
}