{
  "type": "Feature",
  "properties": {
    "gn:admin1_code":"12.0",
    "gn:admin2_code":"1205.0",
    "gn:admin3_code":"120503.0",
    "gn:asciiname":"Mesa Pata",
    "gn:country_code":"PE",
    "gn:dem":4071,
    "gn:feature_class":"P",
    "gn:feature_code":"PPL",
    "gn:name":"Mesa Pata",
    "gn:population":0,
    "gn:timezone":"America/Lima",
    "iso:country":"PE",
    "wof:name":"Mesa Pata",
    "wof:placetype":"locality"
},
  "geometry": {"coordinates":[-76.25205,-11.02731],"type":"Point"}
}