{
  "type": "Feature",
  "properties": {
    "gn:admin1_code":"19",
    "gn:admin2_code":"1903.0",
    "gn:admin3_code":"190306.0",
    "gn:asciiname":"La Llobera",
    "gn:country_code":"PE",
    "gn:dem":250,
    "gn:feature_class":"P",
    "gn:feature_code":"PPL",
    "gn:name":"La Llobera",
    "gn:population":0,
    "gn:timezone":"America/Lima",
    "iso:country":"PE",
    "wof:name":"La Llobera",
    "wof:placetype":"locality"
},
  "geometry": {"coordinates":[-74.89236,-10.12021],"type":"Point"}
}