{
  "type": "Feature",
  "properties": {
    "gn:admin1_code":"12",
    "gn:admin2_code":"1205.0",
    "gn:admin3_code":"120501.0",
    "gn:asciiname":"Uncha",
    "gn:country_code":"PE",
    "gn:dem":4421,
    "gn:feature_class":"P",
    "gn:feature_code":"PPL",
    "gn:name":"Uncha",
    "gn:population":0,
    "gn:timezone":"America/Lima",
    "iso:country":"PE",
    "wof:name":"Uncha",
    "wof:placetype":"locality"
},
  "geometry": {"coordinates":[-75.91148000000003,-11.1546],"type":"Point"}
}