{
  "type": "Feature",
  "properties": {
    "gn:admin1_code":"02",
    "gn:admin2_code":"202.0",
    "gn:admin3_code":"20204.0",
    "gn:asciiname":"La Merced",
    "gn:country_code":"PE",
    "gn:dem":3289,
    "gn:feature_class":"P",
    "gn:feature_code":"PPLA3",
    "gn:name":"La Merced",
    "gn:population":0,
    "gn:timezone":"America/Lima",
    "iso:country":"PE",
    "name:ceb_x_preferred":[
        "La Merced"
    ],
    "name:deu_x_preferred":[
        "La Merced"
    ],
    "name:fra_x_preferred":[
        "La Merced"
    ],
    "name:ita_x_preferred":[
        "La Merced"
    ],
    "name:nld_x_preferred":[
        "La Merced"
    ],
    "name:pol_x_preferred":[
        "La Merced"
    ],
    "name:por_x_preferred":[
        "La Merced"
    ],
    "name:spa_x_preferred":[
        "La Merced"
    ],
    "name:swe_x_preferred":[
        "La Merced"
    ],
    "name:vie_x_preferred":[
        "La Merced"
    ],
    "wof:name":"La Merced",
    "wof:placetype":"locality"
},
  "geometry": {"coordinates":[-77.61686,-9.7352],"type":"Point"}
}