{
  "type": "Feature",
  "properties": {
    "gn:admin1_code":"15",
    "gn:admin2_code":"1506.0",
    "gn:admin3_code":"150608.0",
    "gn:asciiname":"Aguila",
    "gn:country_code":"PE",
    "gn:dem":4622,
    "gn:feature_class":"P",
    "gn:feature_code":"PPL",
    "gn:name":"Aguila",
    "gn:population":0,
    "gn:timezone":"America/Lima",
    "iso:country":"PE",
    "wof:name":"Aguila",
    "wof:placetype":"locality"
},
  "geometry": {"coordinates":[-76.69556,-11.06333],"type":"Point"}
}