{
  "type": "Feature",
  "properties": {
    "gn:admin1_code":"03",
    "gn:admin2_code":"305.0",
    "gn:admin3_code":"30503.0",
    "gn:asciiname":"Chiscahuaya",
    "gn:country_code":"PE",
    "gn:dem":3673,
    "gn:feature_class":"P",
    "gn:feature_code":"PPL",
    "gn:name":"Chiscahuaya",
    "gn:population":0,
    "gn:timezone":"America/Lima",
    "iso:country":"PE",
    "wof:name":"Chiscahuaya",
    "wof:placetype":"locality"
},
  "geometry": {"coordinates":[-72.43333,-13.81667],"type":"Point"}
}