{
  "type": "Feature",
  "properties": {
    "gn:admin1_code":"20",
    "gn:admin2_code":"2006.0",
    "gn:admin3_code":"200603.0",
    "gn:asciiname":"Hacienda Monte Senor",
    "gn:country_code":"PE",
    "gn:dem":25,
    "gn:feature_class":"P",
    "gn:feature_code":"PPL",
    "gn:name":"Hacienda Monte Se\u00f1or",
    "gn:population":0,
    "gn:timezone":"America/Lima",
    "iso:country":"PE",
    "name:spa_x_preferred":[
        "Hacienda Monte Se\u00f1or"
    ],
    "name:spa_x_variant":[
        "Monte Se\u00f1or"
    ],
    "name:und_x_variant":[
        "Hacienda Mente Se\u00f1or"
    ],
    "wof:name":"Hacienda Monte Senor",
    "wof:placetype":"locality"
},
  "geometry": {"coordinates":[-80.93693,-4.86185],"type":"Point"}
}