{
  "type": "Feature",
  "properties": {
    "gn:admin1_code":"20",
    "gn:admin2_code":"2004.0",
    "gn:admin3_code":"200409.0",
    "gn:asciiname":"Noma",
    "gn:country_code":"PE",
    "gn:dem":1684,
    "gn:feature_class":"P",
    "gn:feature_code":"PPL",
    "gn:name":"\u00d1oma",
    "gn:population":0,
    "gn:timezone":"America/Lima",
    "iso:country":"PE",
    "wof:name":"Noma",
    "wof:placetype":"locality"
},
  "geometry": {"coordinates":[-79.83445999999998,-5.03059],"type":"Point"}
}