{
  "type": "Feature",
  "properties": {
    "gn:admin1_code":"5",
    "gn:admin2_code":"511.0",
    "gn:admin3_code":"51105.0",
    "gn:asciiname":"Molino",
    "gn:country_code":"PE",
    "gn:dem":3566,
    "gn:feature_class":"P",
    "gn:feature_code":"PPL",
    "gn:name":"Molino",
    "gn:population":0,
    "gn:timezone":"America/Lima",
    "iso:country":"PE",
    "wof:name":"Molino",
    "wof:placetype":"locality"
},
  "geometry": {"coordinates":[-73.92139,-13.75278],"type":"Point"}
}