{
  "type": "Feature",
  "properties": {
    "gn:admin1_code":"19",
    "gn:admin2_code":"1901.0",
    "gn:admin3_code":"190108.0",
    "gn:asciiname":"Piquillhuanca",
    "gn:country_code":"PE",
    "gn:dem":3201,
    "gn:feature_class":"P",
    "gn:feature_code":"PPL",
    "gn:name":"Piquillhuanca",
    "gn:population":0,
    "gn:timezone":"America/Lima",
    "iso:country":"PE",
    "name:und_x_variant":[
        "Hacienda Piquillhuanca"
    ],
    "wof:name":"Piquillhuanca",
    "wof:placetype":"locality"
},
  "geometry": {"coordinates":[-76.18586999999999,-10.48368],"type":"Point"}
}