{
  "type": "Feature",
  "properties": {
    "gn:admin1_code":"1",
    "gn:admin2_code":"101.0",
    "gn:admin3_code":"10109.0",
    "gn:asciiname":"Quelucas",
    "gn:country_code":"PE",
    "gn:dem":2397,
    "gn:feature_class":"P",
    "gn:feature_code":"PPL",
    "gn:name":"Quelucas",
    "gn:population":0,
    "gn:timezone":"America/Lima",
    "iso:country":"PE",
    "wof:name":"Quelucas",
    "wof:placetype":"locality"
},
  "geometry": {"coordinates":[-77.82445,-6.5208],"type":"Point"}
}