{
  "type": "Feature",
  "properties": {
    "gn:admin1_code":"05",
    "gn:admin2_code":"511.0",
    "gn:admin3_code":"51108.0",
    "gn:asciiname":"Matamata",
    "gn:country_code":"PE",
    "gn:dem":3479,
    "gn:feature_class":"P",
    "gn:feature_code":"PPL",
    "gn:name":"Matamata",
    "gn:population":0,
    "gn:timezone":"America/Lima",
    "iso:country":"PE",
    "name:ara_x_preferred":[
        "\u0645\u0637\u0645\u0627\u0637\u0629"
    ],
    "name:arg_x_preferred":[
        "Matamata"
    ],
    "name:ceb_x_preferred":[
        "Matamata"
    ],
    "name:deu_x_preferred":[
        "Matamata"
    ],
    "name:est_x_preferred":[
        "Matamata"
    ],
    "name:fra_x_preferred":[
        "Matamata"
    ],
    "name:gla_x_preferred":[
        "Matamata"
    ],
    "name:ita_x_preferred":[
        "Matamata"
    ],
    "name:msa_x_preferred":[
        "Matamata"
    ],
    "name:nld_x_preferred":[
        "Matamata"
    ],
    "name:nno_x_preferred":[
        "Matamata"
    ],
    "name:nor_x_preferred":[
        "Matamata"
    ],
    "name:pol_x_preferred":[
        "Matamata"
    ],
    "name:rus_x_preferred":[
        "\u041c\u0430\u0442\u0430\u043c\u0430\u0442\u0430"
    ],
    "name:swe_x_preferred":[
        "Matamata"
    ],
    "wof:name":"Matamata",
    "wof:placetype":"locality"
},
  "geometry": {"coordinates":[-74.01666999999998,-13.55],"type":"Point"}
}