{
  "type": "Feature",
  "properties": {
    "gn:admin1_code":"5",
    "gn:admin2_code":"503.0",
    "gn:asciiname":"Pocomaca",
    "gn:country_code":"PE",
    "gn:dem":4365,
    "gn:feature_class":"P",
    "gn:feature_code":"PPL",
    "gn:name":"Pocomaca",
    "gn:population":0,
    "gn:timezone":"America/Lima",
    "iso:country":"PE",
    "wof:name":"Pocomaca",
    "wof:placetype":"locality"
},
  "geometry": {"coordinates":[-74.77221999999998,-13.93278],"type":"Point"}
}