{
  "type": "Feature",
  "properties": {
    "gn:admin1_code":"10",
    "gn:admin2_code":"1002.0",
    "gn:admin3_code":"100203.0",
    "gn:asciiname":"Chugchupampa",
    "gn:country_code":"PE",
    "gn:dem":3497,
    "gn:feature_class":"P",
    "gn:feature_code":"PPL",
    "gn:name":"Chugchupampa",
    "gn:population":0,
    "gn:timezone":"America/Lima",
    "iso:country":"PE",
    "wof:name":"Chugchupampa",
    "wof:placetype":"locality"
},
  "geometry": {"coordinates":[-76.46278000000002,-10.2089],"type":"Point"}
}