{
  "type": "Feature",
  "properties": {
    "gn:admin1_code":"09",
    "gn:admin2_code":"903.0",
    "gn:admin3_code":"90301.0",
    "gn:asciiname":"Majerhua",
    "gn:country_code":"PE",
    "gn:dem":4337,
    "gn:feature_class":"P",
    "gn:feature_code":"PPL",
    "gn:name":"Majerhua",
    "gn:population":0,
    "gn:timezone":"America/Lima",
    "iso:country":"PE",
    "wof:name":"Majerhua",
    "wof:placetype":"locality"
},
  "geometry": {"coordinates":[-74.70488,-13.13617],"type":"Point"}
}