{
  "type": "Feature",
  "properties": {
    "gn:admin1_code":"12.0",
    "gn:admin2_code":"1204.0",
    "gn:admin3_code":"120426.0",
    "gn:asciiname":"Huithuisca",
    "gn:country_code":"PE",
    "gn:dem":4308,
    "gn:feature_class":"P",
    "gn:feature_code":"PPL",
    "gn:name":"Huithuisca",
    "gn:population":0,
    "gn:timezone":"America/Lima",
    "iso:country":"PE",
    "wof:name":"Huithuisca",
    "wof:placetype":"locality"
},
  "geometry": {"coordinates":[-75.7406,-11.62967],"type":"Point"}
}