{
  "type": "Feature",
  "properties": {
    "gn:admin1_code":"4",
    "gn:admin2_code":"405.0",
    "gn:admin3_code":"40504.0",
    "gn:asciiname":"Laycuna",
    "gn:country_code":"PE",
    "gn:dem":4563,
    "gn:feature_class":"P",
    "gn:feature_code":"PPL",
    "gn:name":"Laycu\u00f1a",
    "gn:population":0,
    "gn:timezone":"America/Lima",
    "iso:country":"PE",
    "wof:name":"Laycuna",
    "wof:placetype":"locality"
},
  "geometry": {"coordinates":[-71.31487,-15.51835],"type":"Point"}
}