{
  "type": "Feature",
  "properties": {
    "gn:admin1_code":"15",
    "gn:admin2_code":"1509.0",
    "gn:admin3_code":"150901.0",
    "gn:asciiname":"Jaraco",
    "gn:country_code":"PE",
    "gn:dem":4154,
    "gn:feature_class":"P",
    "gn:feature_code":"PPL",
    "gn:name":"Jaraco",
    "gn:population":0,
    "gn:timezone":"America/Lima",
    "iso:country":"PE",
    "wof:name":"Jaraco",
    "wof:placetype":"locality"
},
  "geometry": {"coordinates":[-76.70555999999998,-10.65444],"type":"Point"}
}