{
  "type": "Feature",
  "properties": {
    "gn:admin1_code":"8",
    "gn:admin2_code":"806.0",
    "gn:admin3_code":"80604.0",
    "gn:asciiname":"Munapata",
    "gn:country_code":"PE",
    "gn:dem":3727,
    "gn:feature_class":"P",
    "gn:feature_code":"PPL",
    "gn:name":"Mu\u00f1apata",
    "gn:population":0,
    "gn:timezone":"America/Lima",
    "iso:country":"PE",
    "wof:name":"Munapata",
    "wof:placetype":"locality"
},
  "geometry": {"coordinates":[-71.15366,-14.36232],"type":"Point"}
}