{
  "type": "Feature",
  "properties": {
    "gn:admin1_code":"04",
    "gn:admin2_code":"401.0",
    "gn:admin3_code":"40119.0",
    "gn:asciiname":"Pucarillo",
    "gn:country_code":"PE",
    "gn:dem":4285,
    "gn:feature_class":"P",
    "gn:feature_code":"PPL",
    "gn:name":"Pucarillo",
    "gn:population":0,
    "gn:timezone":"America/Lima",
    "iso:country":"PE",
    "wof:name":"Pucarillo",
    "wof:placetype":"locality"
},
  "geometry": {"coordinates":[-71.07337,-16.23098],"type":"Point"}
}