{
  "type": "Feature",
  "properties": {
    "gn:admin1_code":"11.0",
    "gn:admin2_code":"1102.0",
    "gn:admin3_code":"110204.0",
    "gn:asciiname":"San Pablito",
    "gn:country_code":"PE",
    "gn:dem":50,
    "gn:feature_class":"P",
    "gn:feature_code":"PPL",
    "gn:name":"San Pablito",
    "gn:population":0,
    "gn:timezone":"America/Lima",
    "iso:country":"PE",
    "wof:name":"San Pablito",
    "wof:placetype":"locality"
},
  "geometry": {"coordinates":[-76.14424,-13.45776],"type":"Point"}
}