{
  "type": "Feature",
  "properties": {
    "gn:admin1_code":"22",
    "gn:admin2_code":"2207.0",
    "gn:admin3_code":"220704.0",
    "gn:asciiname":"Vacatoril",
    "gn:country_code":"PE",
    "gn:dem":219,
    "gn:feature_class":"P",
    "gn:feature_code":"PPL",
    "gn:name":"Vacatoril",
    "gn:population":0,
    "gn:timezone":"America/Lima",
    "iso:country":"PE",
    "name:und_x_variant":[
        "Lim\u00f3n"
    ],
    "wof:name":"Vacatoril",
    "wof:placetype":"locality"
},
  "geometry": {"coordinates":[-76.27393000000002,-6.70859],"type":"Point"}
}