{
  "type": "Feature",
  "properties": {
    "gn:admin1_code":"03",
    "gn:admin2_code":"305.0",
    "gn:admin3_code":"30506.0",
    "gn:asciiname":"Huarcoyo",
    "gn:country_code":"PE",
    "gn:dem":4166,
    "gn:feature_class":"P",
    "gn:feature_code":"PPL",
    "gn:name":"Huarcoyo",
    "gn:population":0,
    "gn:timezone":"America/Lima",
    "iso:country":"PE",
    "wof:name":"Huarcoyo",
    "wof:placetype":"locality"
},
  "geometry": {"coordinates":[-72.33333,-14.23333],"type":"Point"}
}