{
  "type": "Feature",
  "properties": {
    "gn:admin1_code":"04",
    "gn:admin2_code":"405.0",
    "gn:admin3_code":"40505.0",
    "gn:asciiname":"Cencuyo",
    "gn:country_code":"PE",
    "gn:dem":4205,
    "gn:feature_class":"P",
    "gn:feature_code":"PPL",
    "gn:name":"Cencuyo",
    "gn:population":0,
    "gn:timezone":"America/Lima",
    "iso:country":"PE",
    "wof:name":"Cencuyo",
    "wof:placetype":"locality"
},
  "geometry": {"coordinates":[-71.66705,-15.16423],"type":"Point"}
}