{
  "type": "Feature",
  "properties": {
    "gn:admin1_code":"21.0",
    "gn:admin2_code":"2112.0",
    "gn:asciiname":"Pacollani",
    "gn:country_code":"PE",
    "gn:dem":3933,
    "gn:feature_class":"P",
    "gn:feature_code":"PPL",
    "gn:name":"Pacollani",
    "gn:population":0,
    "gn:timezone":"America/Lima",
    "iso:country":"PE",
    "name:spa_x_preferred":[
        "Pacollani"
    ],
    "wof:name":"Pacollani",
    "wof:placetype":"locality"
},
  "geometry": {"coordinates":[-69.31218,-14.47223],"type":"Point"}
}