{
  "type": "Feature",
  "properties": {
    "gn:admin1_code":"2.0",
    "gn:admin2_code":"210.0",
    "gn:admin3_code":"21011.0",
    "gn:asciiname":"Chacapampa",
    "gn:country_code":"PE",
    "gn:dem":3843,
    "gn:feature_class":"P",
    "gn:feature_code":"PPL",
    "gn:name":"Chacapampa",
    "gn:population":0,
    "gn:timezone":"America/Lima",
    "iso:country":"PE",
    "wof:name":"Chacapampa",
    "wof:placetype":"locality"
},
  "geometry": {"coordinates":[-76.97331,-9.37627],"type":"Point"}
}