{
  "type": "Feature",
  "properties": {
    "gn:admin1_code":"05",
    "gn:admin2_code":"510.0",
    "gn:admin3_code":"51006.0",
    "gn:asciiname":"Cayara",
    "gn:country_code":"PE",
    "gn:dem":3191,
    "gn:feature_class":"P",
    "gn:feature_code":"PPLA3",
    "gn:name":"Cayara",
    "gn:population":0,
    "gn:timezone":"America/Lima",
    "iso:country":"PE",
    "wof:name":"Cayara",
    "wof:placetype":"locality"
},
  "geometry": {"coordinates":[-73.98889,-13.79472],"type":"Point"}
}