{
  "type": "Feature",
  "properties": {
    "gn:admin1_code":"9",
    "gn:admin2_code":"906.0",
    "gn:admin3_code":"90615.0",
    "gn:asciiname":"Aleluya",
    "gn:country_code":"PE",
    "gn:dem":4046,
    "gn:feature_class":"P",
    "gn:feature_code":"PPL",
    "gn:name":"Aleluya",
    "gn:population":0,
    "gn:timezone":"America/Lima",
    "iso:country":"PE",
    "wof:name":"Aleluya",
    "wof:placetype":"locality"
},
  "geometry": {"coordinates":[-75.13639000000001,-13.66694],"type":"Point"}
}