{
  "type": "Feature",
  "properties": {
    "gn:admin1_code":"18",
    "gn:admin2_code":"1802.0",
    "gn:admin3_code":"180209.0",
    "gn:asciiname":"Quinistaquillas",
    "gn:cc2":"PE",
    "gn:country_code":"PE",
    "gn:dem":1767,
    "gn:feature_class":"P",
    "gn:feature_code":"PPLA3",
    "gn:name":"Quinistaquillas",
    "gn:population":0,
    "gn:timezone":"America/Lima",
    "iso:country":"PE",
    "name:und_x_variant":[
        "Quinistaquilla",
        "Quinistaquillas"
    ],
    "wof:name":"Quinistaquillas",
    "wof:placetype":"locality"
},
  "geometry": {"coordinates":[-70.88333,-16.75],"type":"Point"}
}