{
  "type": "Feature",
  "properties": {
    "gn:admin1_code":"15",
    "gn:admin2_code":"1505.0",
    "gn:admin3_code":"150503.0",
    "gn:asciiname":"La Era",
    "gn:country_code":"PE",
    "gn:dem":363,
    "gn:feature_class":"P",
    "gn:feature_code":"PPL",
    "gn:name":"La Era",
    "gn:population":0,
    "gn:timezone":"America/Lima",
    "iso:country":"PE",
    "wof:name":"La Era",
    "wof:placetype":"locality"
},
  "geometry": {"coordinates":[-76.53100000000001,-12.52138],"type":"Point"}
}