{
  "type": "Feature",
  "properties": {
    "gn:admin1_code":"15",
    "gn:admin2_code":"1501.0",
    "gn:admin3_code":"150117.0",
    "gn:asciiname":"Aznapuquio",
    "gn:cc2":"PE",
    "gn:country_code":"PE",
    "gn:dem":63,
    "gn:feature_class":"P",
    "gn:feature_code":"PPL",
    "gn:name":"Aznapuquio",
    "gn:population":0,
    "gn:timezone":"America/Lima",
    "iso:country":"PE",
    "name:und_x_variant":[
        "Aznapuquio Hacienda",
        "Asnapuquio",
        "Aznapuquio"
    ],
    "wof:name":"Aznapuquio",
    "wof:placetype":"locality"
},
  "geometry": {"coordinates":[-77.06667,-11.98333],"type":"Point"}
}