{
  "type": "Feature",
  "properties": {
    "gn:admin1_code":"13",
    "gn:admin2_code":"1310.0",
    "gn:admin3_code":"131001.0",
    "gn:asciiname":"Chuca",
    "gn:country_code":"PE",
    "gn:dem":2957,
    "gn:feature_class":"P",
    "gn:feature_code":"PPL",
    "gn:name":"Chuca",
    "gn:population":0,
    "gn:timezone":"America/Lima",
    "iso:country":"PE",
    "name:und_x_variant":[
        "Santa Cruz de Chuca",
        "Chuca"
    ],
    "wof:name":"Chuca",
    "wof:placetype":"locality"
},
  "geometry": {"coordinates":[-78.14138,-8.11575],"type":"Point"}
}