{
  "type": "Feature",
  "properties": {
    "gn:admin1_code":"4",
    "gn:admin2_code":"405.0",
    "gn:admin3_code":"40519.0",
    "gn:asciiname":"Caque",
    "gn:country_code":"PE",
    "gn:dem":4401,
    "gn:feature_class":"P",
    "gn:feature_code":"PPL",
    "gn:name":"Caque",
    "gn:population":0,
    "gn:timezone":"America/Lima",
    "iso:country":"PE",
    "wof:name":"Caque",
    "wof:placetype":"locality"
},
  "geometry": {"coordinates":[-71.24639000000001,-15.75601],"type":"Point"}
}