{
  "type": "Feature",
  "properties": {
    "gn:admin1_code":"15",
    "gn:admin2_code":"1502.0",
    "gn:admin3_code":"150201.0",
    "gn:asciiname":"Araya Chica",
    "gn:country_code":"PE",
    "gn:dem":467,
    "gn:feature_class":"P",
    "gn:feature_code":"PPL",
    "gn:name":"Araya Chica",
    "gn:population":0,
    "gn:timezone":"America/Lima",
    "iso:country":"PE",
    "name:und_x_variant":[
        "Araya Chica Hacienda",
        "Araya Chica"
    ],
    "wof:name":"Araya Chica",
    "wof:placetype":"locality"
},
  "geometry": {"coordinates":[-77.56963,-10.67189],"type":"Point"}
}