{
  "type": "Feature",
  "properties": {
    "gn:admin1_code":"04",
    "gn:admin2_code":"401.0",
    "gn:admin3_code":"40114.0",
    "gn:asciiname":"La Apacheta de Talamolle",
    "gn:country_code":"PE",
    "gn:dem":3455,
    "gn:feature_class":"P",
    "gn:feature_code":"PPL",
    "gn:name":"La Apacheta de Talamolle",
    "gn:population":0,
    "gn:timezone":"America/Lima",
    "iso:country":"PE",
    "wof:name":"La Apacheta de Talamolle",
    "wof:placetype":"locality"
},
  "geometry": {"coordinates":[-71.25997,-16.58236],"type":"Point"}
}