{
  "type": "Feature",
  "properties": {
    "gn:admin1_code":"16",
    "gn:admin2_code":"1601.0",
    "gn:admin3_code":"160113.0",
    "gn:asciiname":"San Juan de Miraflores",
    "gn:cc2":"PE",
    "gn:country_code":"PE",
    "gn:dem":99,
    "gn:feature_class":"P",
    "gn:feature_code":"PPL",
    "gn:name":"San Juan de Miraflores",
    "gn:population":0,
    "gn:timezone":"America/Lima",
    "iso:country":"PE",
    "name:und_x_variant":[
        "San Juan",
        "San Juan de Miraflores"
    ],
    "wof:name":"San Juan de Miraflores",
    "wof:placetype":"locality"
},
  "geometry": {"coordinates":[-73.28139,-3.77611],"type":"Point"}
}