{
  "type": "Feature",
  "properties": {
    "gn:admin1_code":"18",
    "gn:admin2_code":"1801.0",
    "gn:admin3_code":"180102.0",
    "gn:asciiname":"Patipatine",
    "gn:country_code":"PE",
    "gn:dem":4755,
    "gn:feature_class":"P",
    "gn:feature_code":"PPL",
    "gn:name":"Patipatine",
    "gn:population":0,
    "gn:timezone":"America/Lima",
    "iso:country":"PE",
    "wof:name":"Patipatine",
    "wof:placetype":"locality"
},
  "geometry": {"coordinates":[-70.49939999999999,-16.62126],"type":"Point"}
}