{
  "type": "Feature",
  "properties": {
    "gn:admin1_code":"20",
    "gn:admin2_code":"2001.0",
    "gn:admin3_code":"200111.0",
    "gn:asciiname":"Pelingara",
    "gn:country_code":"PE",
    "gn:dem":192,
    "gn:feature_class":"P",
    "gn:feature_code":"PPL",
    "gn:name":"Pelingara",
    "gn:population":0,
    "gn:timezone":"America/Lima",
    "iso:country":"PE",
    "name:und_x_variant":[
        "Pelingara Hacienda",
        "Pelingara"
    ],
    "wof:name":"Pelingara",
    "wof:placetype":"locality"
},
  "geometry": {"coordinates":[-80.30874,-4.70481],"type":"Point"}
}