{
  "type": "Feature",
  "properties": {
    "gn:admin1_code":"6.0",
    "gn:admin2_code":"605.0",
    "gn:admin3_code":"60503.0",
    "gn:asciiname":"La Toma",
    "gn:country_code":"PE",
    "gn:dem":2278,
    "gn:feature_class":"P",
    "gn:feature_code":"PPL",
    "gn:name":"La Toma",
    "gn:population":0,
    "gn:timezone":"America/Lima",
    "iso:country":"PE",
    "name:spa_x_preferred":[
        "La Toma"
    ],
    "wof:name":"La Toma",
    "wof:placetype":"locality"
},
  "geometry": {"coordinates":[-79.02076,-7.3593],"type":"Point"}
}