{
  "type": "Feature",
  "properties": {
    "gn:admin1_code":"10.0",
    "gn:admin2_code":"1006.0",
    "gn:admin3_code":"100606.0",
    "gn:asciiname":"Chontaplaya San Jose",
    "gn:country_code":"PE",
    "gn:dem":776,
    "gn:feature_class":"P",
    "gn:feature_code":"PPL",
    "gn:name":"Chontaplaya San Jos\u00e9",
    "gn:population":0,
    "gn:timezone":"America/Lima",
    "iso:country":"PE",
    "wof:name":"Chontaplaya San Jose",
    "wof:placetype":"locality"
},
  "geometry": {"coordinates":[-75.95835,-9.38279],"type":"Point"}
}