{
  "type": "Feature",
  "properties": {
    "gn:admin1_code":"05",
    "gn:admin2_code":"505.0",
    "gn:admin3_code":"50505.0",
    "gn:asciiname":"Lamblas",
    "gn:country_code":"PE",
    "gn:dem":3543,
    "gn:feature_class":"P",
    "gn:feature_code":"PPL",
    "gn:name":"Lamblas",
    "gn:population":0,
    "gn:timezone":"America/Lima",
    "iso:country":"PE",
    "wof:name":"Lamblas",
    "wof:placetype":"locality"
},
  "geometry": {"coordinates":[-73.57908,-13.29217],"type":"Point"}
}