{
  "type": "Feature",
  "properties": {
    "gn:admin1_code":"9.0",
    "gn:admin2_code":"907.0",
    "gn:admin3_code":"90705.0",
    "gn:asciiname":"Vantaquero",
    "gn:country_code":"PE",
    "gn:dem":2710,
    "gn:feature_class":"P",
    "gn:feature_code":"PPL",
    "gn:name":"Vantaquero",
    "gn:population":0,
    "gn:timezone":"America/Lima",
    "iso:country":"PE",
    "wof:name":"Vantaquero",
    "wof:placetype":"locality"
},
  "geometry": {"coordinates":[-74.69373,-12.32443],"type":"Point"}
}