{
  "type": "Feature",
  "properties": {
    "gn:admin1_code":"10.0",
    "gn:admin2_code":"1005.0",
    "gn:admin3_code":"100501.0",
    "gn:asciiname":"Uyucuyoc",
    "gn:country_code":"PE",
    "gn:dem":3748,
    "gn:feature_class":"P",
    "gn:feature_code":"PPL",
    "gn:name":"Uyucuyoc",
    "gn:population":0,
    "gn:timezone":"America/Lima",
    "iso:country":"PE",
    "wof:name":"Uyucuyoc",
    "wof:placetype":"locality"
},
  "geometry": {"coordinates":[-76.88965999999998,-9.57425],"type":"Point"}
}