{
  "type": "Feature",
  "properties": {
    "gn:admin1_code":"10.0",
    "gn:admin2_code":"1005.0",
    "gn:admin3_code":"100511.0",
    "gn:asciiname":"Quichqui",
    "gn:country_code":"PE",
    "gn:dem":3593,
    "gn:feature_class":"P",
    "gn:feature_code":"PPL",
    "gn:name":"Quichqui",
    "gn:population":0,
    "gn:timezone":"America/Lima",
    "iso:country":"PE",
    "wof:name":"Quichqui",
    "wof:placetype":"locality"
},
  "geometry": {"coordinates":[-76.70548000000002,-9.40894],"type":"Point"}
}