{
  "type": "Feature",
  "properties": {
    "gn:admin1_code":"20",
    "gn:admin2_code":"2002.0",
    "gn:admin3_code":"200206.0",
    "gn:asciiname":"San Lazaro",
    "gn:country_code":"PE",
    "gn:dem":1677,
    "gn:feature_class":"P",
    "gn:feature_code":"PPL",
    "gn:name":"San L\u00e1zaro",
    "gn:population":0,
    "gn:timezone":"America/Lima",
    "iso:country":"PE",
    "name:und_x_variant":[
        "San Lazaro Hacienda",
        "San L\u00e1zaro"
    ],
    "wof:name":"San Lazaro",
    "wof:placetype":"locality"
},
  "geometry": {"coordinates":[-79.63388,-4.9341],"type":"Point"}
}