{
  "type": "Feature",
  "properties": {
    "gn:admin1_code":"21",
    "gn:admin2_code":"2104.0",
    "gn:admin3_code":"210405.0",
    "gn:asciiname":"Ipinuma",
    "gn:country_code":"PE",
    "gn:dem":4280,
    "gn:feature_class":"P",
    "gn:feature_code":"PPL",
    "gn:name":"Ipi\u00f1uma",
    "gn:population":0,
    "gn:timezone":"America/Lima",
    "iso:country":"PE",
    "wof:name":"Ipinuma",
    "wof:placetype":"locality"
},
  "geometry": {"coordinates":[-69.52834,-17.11545],"type":"Point"}
}