{
  "type": "Feature",
  "properties": {
    "gn:admin1_code":"6.0",
    "gn:admin2_code":"605.0",
    "gn:admin3_code":"60503.0",
    "gn:asciiname":"Espinita",
    "gn:country_code":"PE",
    "gn:dem":2146,
    "gn:feature_class":"P",
    "gn:feature_code":"PPL",
    "gn:name":"Espinita",
    "gn:population":0,
    "gn:timezone":"America/Lima",
    "iso:country":"PE",
    "name:spa_x_preferred":[
        "Espinita"
    ],
    "wof:name":"Espinita",
    "wof:placetype":"locality"
},
  "geometry": {"coordinates":[-79.0196,-7.35238],"type":"Point"}
}