{
  "type": "Feature",
  "properties": {
    "gn:admin1_code":"18",
    "gn:admin2_code":"1802.0",
    "gn:admin3_code":"180205.0",
    "gn:asciiname":"Seche",
    "gn:country_code":"PE",
    "gn:dem":2370,
    "gn:feature_class":"P",
    "gn:feature_code":"PPL",
    "gn:name":"Seche",
    "gn:population":0,
    "gn:timezone":"America/Lima",
    "iso:country":"PE",
    "name:und_x_variant":[
        "Secho",
        "Seche"
    ],
    "wof:name":"Seche",
    "wof:placetype":"locality"
},
  "geometry": {"coordinates":[-71.2163,-16.69673],"type":"Point"}
}