{
  "type": "Feature",
  "properties": {
    "gn:admin1_code":"21.0",
    "gn:admin2_code":"2112.0",
    "gn:asciiname":"Simbapata",
    "gn:country_code":"PE",
    "gn:dem":2512,
    "gn:feature_class":"P",
    "gn:feature_code":"PPL",
    "gn:name":"Simbapata",
    "gn:population":0,
    "gn:timezone":"America/Lima",
    "iso:country":"PE",
    "name:spa_x_preferred":[
        "Simbapata"
    ],
    "wof:name":"Simbapata",
    "wof:placetype":"locality"
},
  "geometry": {"coordinates":[-69.48546999999999,-14.364],"type":"Point"}
}