{
  "type": "Feature",
  "properties": {
    "gn:admin1_code":"20",
    "gn:admin2_code":"2006.0",
    "gn:admin3_code":"200605.0",
    "gn:asciiname":"Rompe",
    "gn:country_code":"PE",
    "gn:dem":424,
    "gn:feature_class":"P",
    "gn:feature_code":"PPL",
    "gn:name":"Rompe",
    "gn:population":0,
    "gn:timezone":"America/Lima",
    "iso:country":"PE",
    "name:spa_x_preferred":[
        "Rompe"
    ],
    "wof:name":"Rompe",
    "wof:placetype":"locality"
},
  "geometry": {"coordinates":[-80.85084000000001,-4.27516],"type":"Point"}
}