{
  "type": "Feature",
  "properties": {
    "gn:admin1_code":"05",
    "gn:admin2_code":"509.0",
    "gn:admin3_code":"50903.0",
    "gn:asciiname":"Ocroca",
    "gn:country_code":"PE",
    "gn:dem":3351,
    "gn:feature_class":"P",
    "gn:feature_code":"PPL",
    "gn:name":"Ocroca",
    "gn:population":0,
    "gn:timezone":"America/Lima",
    "iso:country":"PE",
    "name:und_x_variant":[
        "Ocrocra",
        "Ocroca"
    ],
    "wof:name":"Ocroca",
    "wof:placetype":"locality"
},
  "geometry": {"coordinates":[-73.76661999999997,-13.8696],"type":"Point"}
}