{
  "type": "Feature",
  "properties": {
    "gn:admin1_code":"15.0",
    "gn:admin2_code":"1507.0",
    "gn:admin3_code":"150724.0",
    "gn:asciiname":"Huayococha",
    "gn:country_code":"PE",
    "gn:dem":3079,
    "gn:feature_class":"P",
    "gn:feature_code":"PPL",
    "gn:name":"Huayococha",
    "gn:population":0,
    "gn:timezone":"America/Lima",
    "iso:country":"PE",
    "name:spa_x_preferred":[
        "Huayococha"
    ],
    "wof:name":"Huayococha",
    "wof:placetype":"locality"
},
  "geometry": {"coordinates":[-76.59914999999999,-11.78188],"type":"Point"}
}