{
  "type": "Feature",
  "properties": {
    "gn:admin1_code":"9.0",
    "gn:admin2_code":"902.0",
    "gn:admin3_code":"90203.0",
    "gn:asciiname":"Cauchupata",
    "gn:country_code":"PE",
    "gn:dem":3506,
    "gn:feature_class":"P",
    "gn:feature_code":"PPL",
    "gn:name":"Cauchupata",
    "gn:population":0,
    "gn:timezone":"America/Lima",
    "iso:country":"PE",
    "wof:name":"Cauchupata",
    "wof:placetype":"locality"
},
  "geometry": {"coordinates":[-74.68223,-12.80824],"type":"Point"}
}