{
  "type": "Feature",
  "properties": {
    "gn:admin1_code":"16",
    "gn:admin2_code":"1605.0",
    "gn:admin3_code":"160501.0",
    "gn:asciiname":"Blanquita",
    "gn:country_code":"PE",
    "gn:dem":139,
    "gn:feature_class":"P",
    "gn:feature_code":"PPL",
    "gn:name":"Blanquita",
    "gn:population":0,
    "gn:timezone":"America/Lima",
    "iso:country":"PE",
    "wof:name":"Blanquita",
    "wof:placetype":"locality"
},
  "geometry": {"coordinates":[-73.78333000000001,-5.43333],"type":"Point"}
}