{
  "type": "Feature",
  "properties": {
    "gn:admin1_code":"16",
    "gn:admin2_code":"1604.0",
    "gn:admin3_code":"160404.0",
    "gn:asciiname":"San Alberto",
    "gn:country_code":"PE",
    "gn:dem":80,
    "gn:feature_class":"P",
    "gn:feature_code":"PPL",
    "gn:name":"San Alberto",
    "gn:population":0,
    "gn:timezone":"America/Lima",
    "iso:country":"PE",
    "name:ceb_x_preferred":[
        "San Alberto"
    ],
    "name:deu_x_preferred":[
        "San Alberto"
    ],
    "name:nld_x_preferred":[
        "San Alberto"
    ],
    "name:por_x_preferred":[
        "San Alberto"
    ],
    "name:spa_x_preferred":[
        "San Alberto"
    ],
    "name:srp_x_preferred":[
        "\u0421\u0430\u043d \u0410\u043b\u0431\u0435\u0440\u0442\u043e"
    ],
    "name:swe_x_preferred":[
        "San Alberto"
    ],
    "name:und_x_variant":[
        "San Alberto de Morona"
    ],
    "name:vie_x_preferred":[
        "San Alberto"
    ],
    "wof:name":"San Alberto",
    "wof:placetype":"locality"
},
  "geometry": {"coordinates":[-71.06456,-4.0177],"type":"Point"}
}