{
  "type": "Feature",
  "properties": {
    "gn:admin1_code":"09",
    "gn:admin2_code":"903.0",
    "gn:admin3_code":"90301.0",
    "gn:asciiname":"Huisiorco",
    "gn:country_code":"PE",
    "gn:dem":3799,
    "gn:feature_class":"P",
    "gn:feature_code":"PPL",
    "gn:name":"Huisiorco",
    "gn:population":0,
    "gn:timezone":"America/Lima",
    "iso:country":"PE",
    "name:und_x_variant":[
        "Huisiorcco"
    ],
    "wof:name":"Huisiorco",
    "wof:placetype":"locality"
},
  "geometry": {"coordinates":[-74.73291,-13.04289],"type":"Point"}
}