{
  "type": "Feature",
  "properties": {
    "gn:admin1_code":"20",
    "gn:admin2_code":"2008.0",
    "gn:admin3_code":"200801.0",
    "gn:asciiname":"Salina",
    "gn:cc2":"PE",
    "gn:country_code":"PE",
    "gn:dem":-2,
    "gn:feature_class":"P",
    "gn:feature_code":"PPL",
    "gn:name":"Salina",
    "gn:population":0,
    "gn:timezone":"America/Lima",
    "iso:country":"PE",
    "name:und_x_variant":[
        "Salinas",
        "Salina"
    ],
    "wof:name":"Salina",
    "wof:placetype":"locality"
},
  "geometry": {"coordinates":[-80.63333,-5.66667],"type":"Point"}
}